{
	"type": "FeatureCollection",
	"features": [
		{
			"type": "Feature",
			"properties": {
				"confidence": 8,
				"authenticationResultCode": "ValidCredentials",
				"brandLogoUri": "http://dev.virtualearth.net/Branding/logo_powered_by.png",
				"copyright": "Copyright © 2017 Microsoft and its suppliers. All rights reserved. This API cannot be accessed and the content and any results may not be used, reproduced or transmitted in any manner without express written permission from Microsoft Corporation.",
				"entityType": "RoadBlock",
				"matchCodes": [
					"Ambiguous"
				],
				"name": "Fire Route N, Azilda, ON P0M 1B0, Canada",
				"statusCode": 200,
				"statusDescription": "OK",
				"traceId": "a2ac1d6f9b804123b2c9885b1ee86b73|BN20130530|7.7.0.0|",
				"addressLine": "Fire Route N",
				"adminDistrict": "ON",
				"adminDistrict2": "Greater Sudbury",
				"countryRegion": "Canada",
				"formattedAddress": "Fire Route N, Azilda, ON P0M 1B0, Canada",
				"locality": "Greater Sudbury",
				"neighborhood": "Azilda",
				"postalCode": "P0M 1B0"
			},
			"geometry": {
				"type": "Point",
				"coordinates": [
					-81.10399,
					46.53222
				]
			},
			"bbox": [
				-81.10459,
				46.53067,
				-81.0984299,
				46.53301
			]
		},
		{
			"type": "Feature",
			"properties": {
				"confidence": 7,
				"authenticationResultCode": "ValidCredentials",
				"brandLogoUri": "http://dev.virtualearth.net/Branding/logo_powered_by.png",
				"copyright": "Copyright © 2017 Microsoft and its suppliers. All rights reserved. This API cannot be accessed and the content and any results may not be used, reproduced or transmitted in any manner without express written permission from Microsoft Corporation.",
				"entityType": "RoadBlock",
				"matchCodes": [
					"Ambiguous"
				],
				"name": "Fire Route O, Azilda, ON P0M 1B0, Canada",
				"statusCode": 200,
				"statusDescription": "OK",
				"traceId": "a2ac1d6f9b804123b2c9885b1ee86b73|BN20130530|7.7.0.0|",
				"addressLine": "Fire Route O",
				"adminDistrict": "ON",
				"adminDistrict2": "Greater Sudbury",
				"countryRegion": "Canada",
				"formattedAddress": "Fire Route O, Azilda, ON P0M 1B0, Canada",
				"locality": "Greater Sudbury",
				"neighborhood": "Azilda",
				"postalCode": "P0M 1B0"
			},
			"geometry": {
				"type": "Point",
				"coordinates": [
					-81.11337,
					46.52653
				]
			},
			"bbox": [
				-81.11648,
				46.52553,
				-81.08994,
				46.53949
			]
		}
	]
}
