{
	"type": "FeatureCollection",
	"features": [
		{
			"type": "Feature",
			"properties": {
				"confidence": 9,
				"location_type": "RANGE_INTERPOLATED",
				"formatted_address": "19939 101 Ave, Langley, BC V1M 3G7, Canada",
				"place_id": "EioxOTkzOSAxMDEgQXZlLCBMYW5nbGV5LCBCQyBWMU0gM0c3LCBDYW5hZGE",
				"types": [
					"street_address"
				],
				"street_number": "19939",
				"route": "101 Avenue",
				"locality": "Langley",
				"administrative_area_level_3": "Langley",
				"administrative_area_level_2": "Greater Vancouver",
				"administrative_area_level_1": "British Columbia",
				"country": "Canada",
				"postal_code": "V1M 3G7"
			},
			"geometry": {
				"type": "Point",
				"coordinates": [
					-122.6689051,
					49.1857759
				]
			},
			"bbox": [
				-122.6702540302915,
				49.18443301970849,
				-122.6675560697085,
				49.18713098029149
			]
		}
	]
}
