{
	"type": "FeatureCollection",
	"features": [
		{
			"type": "Feature",
			"properties": {
				"confidence": 9,
				"authenticationResultCode": "ValidCredentials",
				"brandLogoUri": "http://dev.virtualearth.net/Branding/logo_powered_by.png",
				"copyright": "Copyright © 2017 Microsoft and its suppliers. All rights reserved. This API cannot be accessed and the content and any results may not be used, reproduced or transmitted in any manner without express written permission from Microsoft Corporation.",
				"entityType": "Address",
				"matchCodes": [
					"Good"
				],
				"name": "1 Carmel St, Maple, ON L6A 0W5, Canada",
				"statusCode": 200,
				"statusDescription": "OK",
				"traceId": "5052fdcfd39a4d9d9b0e4cbbae3e6cf4|BN20250135|7.7.0.0|",
				"addressLine": "1 Carmel St",
				"adminDistrict": "ON",
				"adminDistrict2": "York",
				"countryRegion": "Canada",
				"formattedAddress": "1 Carmel St, Maple, ON L6A 0W5, Canada",
				"locality": "Vaughan",
				"neighborhood": "Maple",
				"postalCode": "L6A 0W5"
			},
			"geometry": {
				"type": "Point",
				"coordinates": [
					-79.46501,
					43.85592
				]
			},
			"bbox": [
				-79.466569,
				43.8547958,
				-79.463451,
				43.8570442
			]
		}
	]
}
