{
	"type": "FeatureCollection",
	"features": [
		{
			"type": "Feature",
			"properties": {
				"confidence": 9,
				"authenticationResultCode": "ValidCredentials",
				"brandLogoUri": "http://dev.virtualearth.net/Branding/logo_powered_by.png",
				"copyright": "Copyright © 2017 Microsoft and its suppliers. All rights reserved. This API cannot be accessed and the content and any results may not be used, reproduced or transmitted in any manner without express written permission from Microsoft Corporation.",
				"entityType": "Address",
				"matchCodes": [
					"Good"
				],
				"name": "1 Fairview St, Lewisporte, NL A0G, Canada",
				"statusCode": 200,
				"statusDescription": "OK",
				"traceId": "63d41f964048427fb2208c0c72090fc6|BN20260223|7.7.0.0|",
				"addressLine": "1 Fairview St",
				"adminDistrict": "NL",
				"adminDistrict2": "Newfoundland and Labrador",
				"countryRegion": "Canada",
				"formattedAddress": "1 Fairview St, Lewisporte, NL A0G, Canada",
				"locality": "Lewisporte",
				"postalCode": "A0G 3A0"
			},
			"geometry": {
				"type": "Point",
				"coordinates": [
					-55.0618754,
					49.2395951
				]
			},
			"bbox": [
				-55.0635972,
				49.238471,
				-55.0601536,
				49.2407193
			]
		}
	]
}
