{
	"type": "FeatureCollection",
	"features": [
		{
			"type": "Feature",
			"properties": {
				"confidence": 9,
				"authenticationResultCode": "ValidCredentials",
				"brandLogoUri": "http://dev.virtualearth.net/Branding/logo_powered_by.png",
				"copyright": "Copyright © 2017 Microsoft and its suppliers. All rights reserved. This API cannot be accessed and the content and any results may not be used, reproduced or transmitted in any manner without express written permission from Microsoft Corporation.",
				"entityType": "Address",
				"matchCodes": [
					"Good"
				],
				"name": "1 Logan St, Truro, NS B2N, Canada",
				"statusCode": 200,
				"statusDescription": "OK",
				"traceId": "6e1b0b853f014e71bab842db5aa197dc|BN20130625|7.7.0.0|",
				"addressLine": "1 Logan St",
				"adminDistrict": "NS",
				"adminDistrict2": "Colchester",
				"countryRegion": "Canada",
				"formattedAddress": "1 Logan St, Truro, NS B2N, Canada",
				"locality": "Truro",
				"postalCode": "B2N 5C2"
			},
			"geometry": {
				"type": "Point",
				"coordinates": [
					-63.27682,
					45.36746
				]
			},
			"bbox": [
				-63.2784201,
				45.3663358,
				-63.2752199,
				45.3685842
			]
		}
	]
}
