{
	"type": "FeatureCollection",
	"features": [
		{
			"type": "Feature",
			"properties": {
				"confidence": 9,
				"authenticationResultCode": "ValidCredentials",
				"brandLogoUri": "http://dev.virtualearth.net/Branding/logo_powered_by.png",
				"copyright": "Copyright © 2017 Microsoft and its suppliers. All rights reserved. This API cannot be accessed and the content and any results may not be used, reproduced or transmitted in any manner without express written permission from Microsoft Corporation.",
				"entityType": "Address",
				"matchCodes": [
					"Good"
				],
				"name": "1 Marina Rd, Point Edward, ON N7V, Canada",
				"statusCode": 200,
				"statusDescription": "OK",
				"traceId": "0c9e9d5a11944b549dcf189f64795c8a|BN20300154|7.7.0.0|",
				"addressLine": "1 Marina Rd",
				"adminDistrict": "ON",
				"adminDistrict2": "Lambton",
				"countryRegion": "Canada",
				"formattedAddress": "1 Marina Rd, Point Edward, ON N7V, Canada",
				"locality": "Point Edward",
				"postalCode": "N7V"
			},
			"geometry": {
				"type": "Point",
				"coordinates": [
					-82.417707,
					42.9913292
				]
			},
			"bbox": [
				-82.4192439,
				42.9902051,
				-82.4161702,
				42.9924534
			]
		}
	]
}
