{
	"type": "FeatureCollection",
	"features": [
		{
			"type": "Feature",
			"properties": {
				"confidence": 9,
				"authenticationResultCode": "ValidCredentials",
				"brandLogoUri": "http://dev.virtualearth.net/Branding/logo_powered_by.png",
				"copyright": "Copyright © 2017 Microsoft and its suppliers. All rights reserved. This API cannot be accessed and the content and any results may not be used, reproduced or transmitted in any manner without express written permission from Microsoft Corporation.",
				"entityType": "Address",
				"matchCodes": [
					"Good"
				],
				"name": "1 Rices Rd, Annapolis, NS B0S, Canada",
				"statusCode": 200,
				"statusDescription": "OK",
				"traceId": "dae55a120a5d4cdbaeb47deb5828018f|BN20181720|7.7.0.0|",
				"addressLine": "1 Rices Rd",
				"adminDistrict": "NS",
				"adminDistrict2": "Annapolis",
				"countryRegion": "Canada",
				"formattedAddress": "1 Rices Rd, Annapolis, NS B0S, Canada",
				"locality": "Annapolis",
				"neighborhood": "Bridgetown",
				"postalCode": "B0S 1C0"
			},
			"geometry": {
				"type": "Point",
				"coordinates": [
					-65.2998733,
					44.8128673
				]
			},
			"bbox": [
				-65.3014579,
				44.8117431,
				-65.2982887,
				44.8139914
			]
		}
	]
}
