{
	"type": "FeatureCollection",
	"features": [
		{
			"type": "Feature",
			"properties": {
				"confidence": 9,
				"authenticationResultCode": "ValidCredentials",
				"brandLogoUri": "http://dev.virtualearth.net/Branding/logo_powered_by.png",
				"copyright": "Copyright © 2017 Microsoft and its suppliers. All rights reserved. This API cannot be accessed and the content and any results may not be used, reproduced or transmitted in any manner without express written permission from Microsoft Corporation.",
				"entityType": "Address",
				"matchCodes": [
					"Good"
				],
				"name": "1 Select Ave, Scarborough, ON M1V 5J3, Canada",
				"statusCode": 200,
				"statusDescription": "OK",
				"traceId": "450cc117551d445b9122b49464ef0ea5|BN20130423|7.7.0.0|",
				"addressLine": "1 Select Ave",
				"adminDistrict": "ON",
				"adminDistrict2": "Toronto",
				"countryRegion": "Canada",
				"formattedAddress": "1 Select Ave, Scarborough, ON M1V 5J3, Canada",
				"locality": "Toronto",
				"neighborhood": "Milliken",
				"postalCode": "M1V 5J3"
			},
			"geometry": {
				"type": "Point",
				"coordinates": [
					-79.26501,
					43.82917
				]
			},
			"bbox": [
				-79.2665683,
				43.8280458,
				-79.2634517,
				43.8302942
			]
		}
	]
}
