{
	"type": "FeatureCollection",
	"features": [
		{
			"type": "Feature",
			"properties": {
				"confidence": 9,
				"authenticationResultCode": "ValidCredentials",
				"brandLogoUri": "http://dev.virtualearth.net/Branding/logo_powered_by.png",
				"copyright": "Copyright © 2017 Microsoft and its suppliers. All rights reserved. This API cannot be accessed and the content and any results may not be used, reproduced or transmitted in any manner without express written permission from Microsoft Corporation.",
				"entityType": "Address",
				"matchCodes": [
					"Good"
				],
				"name": "1 Union St, Elmira, ON N3B 3J9, Canada",
				"statusCode": 200,
				"statusDescription": "OK",
				"traceId": "bc508a5de33a41d6a90f4c9f2ebf75e6|BN20130625|7.7.0.0|",
				"addressLine": "1 Union St",
				"adminDistrict": "ON",
				"adminDistrict2": "Waterloo",
				"countryRegion": "Canada",
				"formattedAddress": "1 Union St, Elmira, ON N3B 3J9, Canada",
				"locality": "Woolwich",
				"neighborhood": "Elmira",
				"postalCode": "N3B 3J9"
			},
			"geometry": {
				"type": "Point",
				"coordinates": [
					-80.55268,
					43.59533
				]
			},
			"bbox": [
				-80.5542322,
				43.5942058,
				-80.5511278,
				43.5964542
			]
		}
	]
}
