{
	"type": "FeatureCollection",
	"features": [
		{
			"type": "Feature",
			"properties": {
				"confidence": 9,
				"authenticationResultCode": "ValidCredentials",
				"brandLogoUri": "http://dev.virtualearth.net/Branding/logo_powered_by.png",
				"copyright": "Copyright © 2017 Microsoft and its suppliers. All rights reserved. This API cannot be accessed and the content and any results may not be used, reproduced or transmitted in any manner without express written permission from Microsoft Corporation.",
				"entityType": "Address",
				"matchCodes": [
					"Good"
				],
				"name": "1 Yankeetown Rd, Hammonds Plains, NS B3Z 1K7, Canada",
				"statusCode": 200,
				"statusDescription": "OK",
				"traceId": "95372105acac433db3b053d88b5c82f8|BN20130631|7.7.0.0|",
				"addressLine": "1 Yankeetown Rd",
				"adminDistrict": "NS",
				"adminDistrict2": "Halifax",
				"countryRegion": "Canada",
				"formattedAddress": "1 Yankeetown Rd, Hammonds Plains, NS B3Z 1K7, Canada",
				"locality": "Halifax",
				"neighborhood": "Hammonds Plains",
				"postalCode": "B3Z 1K7"
			},
			"geometry": {
				"type": "Point",
				"coordinates": [
					-63.80562,
					44.73351
				]
			},
			"bbox": [
				-63.8072024,
				44.7323858,
				-63.8040376,
				44.7346342
			]
		}
	]
}
