{
	"type": "FeatureCollection",
	"features": [
		{
			"type": "Feature",
			"properties": {
				"confidence": 9,
				"authenticationResultCode": "ValidCredentials",
				"brandLogoUri": "http://dev.virtualearth.net/Branding/logo_powered_by.png",
				"copyright": "Copyright © 2017 Microsoft and its suppliers. All rights reserved. This API cannot be accessed and the content and any results may not be used, reproduced or transmitted in any manner without express written permission from Microsoft Corporation.",
				"entityType": "Address",
				"matchCodes": [
					"Good"
				],
				"name": "10 Citadel Meadows Gdns NW, Calgary, AB T3G, Canada",
				"statusCode": 200,
				"statusDescription": "OK",
				"traceId": "6df5f7aaca074ebab653cf3910d27d66|BN20130621|7.7.0.0|",
				"addressLine": "10 Citadel Meadows Gdns NW",
				"adminDistrict": "AB",
				"adminDistrict2": "Alberta",
				"countryRegion": "Canada",
				"formattedAddress": "10 Citadel Meadows Gdns NW, Calgary, AB T3G, Canada",
				"locality": "Calgary",
				"neighborhood": "Citadel",
				"postalCode": "T3G 5N6"
			},
			"geometry": {
				"type": "Point",
				"coordinates": [
					-114.1862543,
					51.1483934
				]
			},
			"bbox": [
				-114.1880463,
				51.1472692,
				-114.1844623,
				51.1495175
			]
		}
	]
}
