{
	"type": "FeatureCollection",
	"features": [
		{
			"type": "Feature",
			"properties": {
				"confidence": 9,
				"authenticationResultCode": "ValidCredentials",
				"brandLogoUri": "http://dev.virtualearth.net/Branding/logo_powered_by.png",
				"copyright": "Copyright © 2017 Microsoft and its suppliers. All rights reserved. This API cannot be accessed and the content and any results may not be used, reproduced or transmitted in any manner without express written permission from Microsoft Corporation.",
				"entityType": "Address",
				"matchCodes": [
					"Good"
				],
				"name": "10 Ipswich Ter, Kanata, ON K2K 2R5, Canada",
				"statusCode": 200,
				"statusDescription": "OK",
				"traceId": "52d4523567ed4223bd56a3dd1b63f132|BN20160335|7.7.0.0|",
				"addressLine": "10 Ipswich Ter",
				"adminDistrict": "ON",
				"adminDistrict2": "Ottawa",
				"countryRegion": "Canada",
				"formattedAddress": "10 Ipswich Ter, Kanata, ON K2K 2R5, Canada",
				"locality": "Ottawa",
				"neighborhood": "Kanata",
				"postalCode": "K2K 2R5"
			},
			"geometry": {
				"type": "Point",
				"coordinates": [
					-75.93268,
					45.34629
				]
			},
			"bbox": [
				-75.9342795,
				45.3451658,
				-75.9310805,
				45.3474142
			]
		}
	]
}
