{
	"type": "FeatureCollection",
	"features": [
		{
			"type": "Feature",
			"properties": {
				"confidence": 9,
				"authenticationResultCode": "ValidCredentials",
				"brandLogoUri": "http://dev.virtualearth.net/Branding/logo_powered_by.png",
				"copyright": "Copyright © 2017 Microsoft and its suppliers. All rights reserved. This API cannot be accessed and the content and any results may not be used, reproduced or transmitted in any manner without express written permission from Microsoft Corporation.",
				"entityType": "Address",
				"matchCodes": [
					"Good"
				],
				"name": "10 Milner Business Ct, Scarborough, ON M1B 3C6, Canada",
				"statusCode": 200,
				"statusDescription": "OK",
				"traceId": "65af4fe1635d417cbb07c0b916f44cb5|BN20121763|7.7.0.0|",
				"addressLine": "10 Milner Business Ct",
				"adminDistrict": "ON",
				"adminDistrict2": "Toronto",
				"countryRegion": "Canada",
				"formattedAddress": "10 Milner Business Ct, Scarborough, ON M1B 3C6, Canada",
				"locality": "Toronto",
				"neighborhood": "Malvern",
				"postalCode": "M1B 3C6"
			},
			"geometry": {
				"type": "Point",
				"coordinates": [
					-79.23566,
					43.78873
				]
			},
			"bbox": [
				-79.2372172,
				43.7876058,
				-79.2341028,
				43.7898542
			]
		}
	]
}
