{
	"type": "FeatureCollection",
	"features": [
		{
			"type": "Feature",
			"properties": {
				"confidence": 9,
				"authenticationResultCode": "ValidCredentials",
				"brandLogoUri": "http://dev.virtualearth.net/Branding/logo_powered_by.png",
				"copyright": "Copyright © 2017 Microsoft and its suppliers. All rights reserved. This API cannot be accessed and the content and any results may not be used, reproduced or transmitted in any manner without express written permission from Microsoft Corporation.",
				"entityType": "Address",
				"matchCodes": [
					"Good"
				],
				"name": "10 Mt Alberta Vw SE, Calgary, AB T2Z 3G6, Canada",
				"statusCode": 200,
				"statusDescription": "OK",
				"traceId": "1c220076427c45229ec8ff6cc5f2f463|BN20280152|7.7.0.0|",
				"addressLine": "10 Mt Alberta Vw SE",
				"adminDistrict": "AB",
				"adminDistrict2": "Alberta",
				"countryRegion": "Canada",
				"formattedAddress": "10 Mt Alberta Vw SE, Calgary, AB T2Z 3G6, Canada",
				"locality": "Calgary",
				"neighborhood": "McKenzie Lake",
				"postalCode": "T2Z 3G6"
			},
			"geometry": {
				"type": "Point",
				"coordinates": [
					-113.98864,
					50.91681
				]
			},
			"bbox": [
				-113.9904231,
				50.9156858,
				-113.9868569,
				50.9179342
			]
		}
	]
}
