{
	"type": "FeatureCollection",
	"features": [
		{
			"type": "Feature",
			"properties": {
				"confidence": 9,
				"authenticationResultCode": "ValidCredentials",
				"brandLogoUri": "http://dev.virtualearth.net/Branding/logo_powered_by.png",
				"copyright": "Copyright © 2017 Microsoft and its suppliers. All rights reserved. This API cannot be accessed and the content and any results may not be used, reproduced or transmitted in any manner without express written permission from Microsoft Corporation.",
				"entityType": "Address",
				"matchCodes": [
					"Good"
				],
				"name": "10 Pennington Cres, Red Deer, AB T4P 1L3, Canada",
				"statusCode": 200,
				"statusDescription": "OK",
				"traceId": "ee4b6c937b374dd7b0dd8b681a43f3ab|BN20260231|7.7.0.0|",
				"addressLine": "10 Pennington Cres",
				"adminDistrict": "AB",
				"adminDistrict2": "Alberta",
				"countryRegion": "Canada",
				"formattedAddress": "10 Pennington Cres, Red Deer, AB T4P 1L3, Canada",
				"locality": "Red Deer",
				"postalCode": "T4P 1L3"
			},
			"geometry": {
				"type": "Point",
				"coordinates": [
					-113.8097,
					52.2898
				]
			},
			"bbox": [
				-113.8115378,
				52.2886758,
				-113.8078622,
				52.2909242
			]
		}
	]
}
