{
	"type": "FeatureCollection",
	"features": [
		{
			"type": "Feature",
			"properties": {
				"confidence": 9,
				"authenticationResultCode": "ValidCredentials",
				"brandLogoUri": "http://dev.virtualearth.net/Branding/logo_powered_by.png",
				"copyright": "Copyright © 2017 Microsoft and its suppliers. All rights reserved. This API cannot be accessed and the content and any results may not be used, reproduced or transmitted in any manner without express written permission from Microsoft Corporation.",
				"entityType": "Address",
				"matchCodes": [
					"Good"
				],
				"name": "100 Radisson Ave, Chelmsford, ON P0M 1L0, Canada",
				"statusCode": 200,
				"statusDescription": "OK",
				"traceId": "0764769afda845fb9f104d8fd3c52b9f|BN20280152|7.7.0.0|",
				"addressLine": "100 Radisson Ave",
				"adminDistrict": "ON",
				"adminDistrict2": "Greater Sudbury",
				"countryRegion": "Canada",
				"formattedAddress": "100 Radisson Ave, Chelmsford, ON P0M 1L0, Canada",
				"locality": "Greater Sudbury",
				"neighborhood": "Chelmsford",
				"postalCode": "P0M 1L0"
			},
			"geometry": {
				"type": "Point",
				"coordinates": [
					-81.1815554,
					46.5702427
				]
			},
			"bbox": [
				-81.1831906,
				46.5691186,
				-81.1799202,
				46.5713669
			]
		}
	]
}
