{
	"type": "FeatureCollection",
	"features": [
		{
			"type": "Feature",
			"properties": {
				"confidence": 7,
				"authenticationResultCode": "ValidCredentials",
				"brandLogoUri": "http://dev.virtualearth.net/Branding/logo_powered_by.png",
				"copyright": "Copyright © 2017 Microsoft and its suppliers. All rights reserved. This API cannot be accessed and the content and any results may not be used, reproduced or transmitted in any manner without express written permission from Microsoft Corporation.",
				"entityType": "Postcode1",
				"matchCodes": [
					"UpHierarchy"
				],
				"name": "Copper Cliff, P0M 1N0, Canada",
				"statusCode": 200,
				"statusDescription": "OK",
				"traceId": "6a9ceb08b5f24e7cb33fc508d288ded6|BN20240423|7.7.0.0|",
				"adminDistrict": "ON",
				"adminDistrict2": "Greater Sudbury",
				"countryRegion": "Canada",
				"formattedAddress": "Copper Cliff, P0M 1N0, Canada",
				"locality": "Copper Cliff",
				"postalCode": "P0M 1N0"
			},
			"geometry": {
				"type": "Point",
				"coordinates": [
					-81.0679321289063,
					46.4777565002441
				]
			},
			"bbox": [
				-81.0754105697097,
				46.4738937826735,
				-81.0604536881028,
				46.4816192178148
			]
		}
	]
}
