{
	"type": "FeatureCollection",
	"features": [
		{
			"type": "Feature",
			"properties": {
				"confidence": 9,
				"authenticationResultCode": "ValidCredentials",
				"brandLogoUri": "http://dev.virtualearth.net/Branding/logo_powered_by.png",
				"copyright": "Copyright © 2017 Microsoft and its suppliers. All rights reserved. This API cannot be accessed and the content and any results may not be used, reproduced or transmitted in any manner without express written permission from Microsoft Corporation.",
				"entityType": "Address",
				"matchCodes": [
					"Good"
				],
				"name": "100 Falcon St, London, ON N5W 4Z1, Canada",
				"statusCode": 200,
				"statusDescription": "OK",
				"traceId": "0ac5af56659344dab2319672d11ab784|BN20280152|7.7.0.0|",
				"addressLine": "100 Falcon St",
				"adminDistrict": "ON",
				"adminDistrict2": "Middlesex",
				"countryRegion": "Canada",
				"formattedAddress": "100 Falcon St, London, ON N5W 4Z1, Canada",
				"locality": "London",
				"neighborhood": "Argyle",
				"postalCode": "N5W 4Z1"
			},
			"geometry": {
				"type": "Point",
				"coordinates": [
					-81.1737,
					42.9875
				]
			},
			"bbox": [
				-81.1752368,
				42.9863758,
				-81.1721632,
				42.9886242
			]
		}
	]
}
