{
	"type": "FeatureCollection",
	"features": [
		{
			"type": "Feature",
			"properties": {
				"confidence": 9,
				"authenticationResultCode": "ValidCredentials",
				"brandLogoUri": "http://dev.virtualearth.net/Branding/logo_powered_by.png",
				"copyright": "Copyright © 2017 Microsoft and its suppliers. All rights reserved. This API cannot be accessed and the content and any results may not be used, reproduced or transmitted in any manner without express written permission from Microsoft Corporation.",
				"entityType": "Address",
				"matchCodes": [
					"Good"
				],
				"name": "100 Emmeloord Cres, Unionville, ON L3R 1P8, Canada",
				"statusCode": 200,
				"statusDescription": "OK",
				"traceId": "46c354f0024e4b8aafef7233ca395298|BN20130520|7.7.0.0|",
				"addressLine": "100 Emmeloord Cres",
				"adminDistrict": "ON",
				"adminDistrict2": "York",
				"countryRegion": "Canada",
				"formattedAddress": "100 Emmeloord Cres, Unionville, ON L3R 1P8, Canada",
				"locality": "Markham",
				"neighborhood": "Unionville",
				"postalCode": "L3R 1P8"
			},
			"geometry": {
				"type": "Point",
				"coordinates": [
					-79.31985,
					43.86182
				]
			},
			"bbox": [
				-79.3214091,
				43.8606958,
				-79.3182909,
				43.8629442
			]
		}
	]
}
