{
	"type": "FeatureCollection",
	"features": [
		{
			"type": "Feature",
			"properties": {
				"confidence": 9,
				"authenticationResultCode": "ValidCredentials",
				"brandLogoUri": "http://dev.virtualearth.net/Branding/logo_powered_by.png",
				"copyright": "Copyright © 2017 Microsoft and its suppliers. All rights reserved. This API cannot be accessed and the content and any results may not be used, reproduced or transmitted in any manner without express written permission from Microsoft Corporation.",
				"entityType": "Address",
				"matchCodes": [
					"Good"
				],
				"name": "10006 101 St NW, Edmonton, AB T5J 0S1, Canada",
				"statusCode": 200,
				"statusDescription": "OK",
				"traceId": "46558f4591a64c91a856b9aa898d2955|BN20200239|7.7.0.0|",
				"addressLine": "10006 101 St NW",
				"adminDistrict": "AB",
				"adminDistrict2": "Alberta",
				"countryRegion": "Canada",
				"formattedAddress": "10006 101 St NW, Edmonton, AB T5J 0S1, Canada",
				"locality": "Edmonton",
				"neighborhood": "Downtown",
				"postalCode": "T5J 0S1"
			},
			"geometry": {
				"type": "Point",
				"coordinates": [
					-113.49432,
					53.54005
				]
			},
			"bbox": [
				-113.4962117,
				53.5389258,
				-113.4924283,
				53.5411742
			]
		}
	]
}
