{
	"type": "FeatureCollection",
	"features": [
		{
			"type": "Feature",
			"properties": {
				"confidence": 9,
				"authenticationResultCode": "ValidCredentials",
				"brandLogoUri": "http://dev.virtualearth.net/Branding/logo_powered_by.png",
				"copyright": "Copyright © 2017 Microsoft and its suppliers. All rights reserved. This API cannot be accessed and the content and any results may not be used, reproduced or transmitted in any manner without express written permission from Microsoft Corporation.",
				"entityType": "Address",
				"matchCodes": [
					"Good"
				],
				"name": "10011 Thatcher Ave, North Battleford, SK S9A, Canada",
				"statusCode": 200,
				"statusDescription": "OK",
				"traceId": "2ac1ad0f2e22430ab6ae04e34dff18a5|BN20171457|7.7.0.0|",
				"addressLine": "10011 Thatcher Ave",
				"adminDistrict": "SK",
				"adminDistrict2": "Saskatchewan",
				"countryRegion": "Canada",
				"formattedAddress": "10011 Thatcher Ave, North Battleford, SK S9A, Canada",
				"locality": "North Battleford",
				"postalCode": "S9A 3W8"
			},
			"geometry": {
				"type": "Point",
				"coordinates": [
					-108.2588247,
					52.7495331
				]
			},
			"bbox": [
				-108.2606818,
				52.7484089,
				-108.2569675,
				52.7506572
			]
		}
	]
}
