{
	"type": "FeatureCollection",
	"features": [
		{
			"type": "Feature",
			"properties": {
				"confidence": 9,
				"authenticationResultCode": "ValidCredentials",
				"brandLogoUri": "http://dev.virtualearth.net/Branding/logo_powered_by.png",
				"copyright": "Copyright © 2017 Microsoft and its suppliers. All rights reserved. This API cannot be accessed and the content and any results may not be used, reproduced or transmitted in any manner without express written permission from Microsoft Corporation.",
				"entityType": "Address",
				"matchCodes": [
					"Good"
				],
				"name": "10031 103 Ave, Grande Prairie, AB T8V 1B9, Canada",
				"statusCode": 200,
				"statusDescription": "OK",
				"traceId": "4385cc9a45f042498fc7f65f67b5cef8|BN20290118|7.7.0.0|",
				"addressLine": "10031 103 Ave",
				"adminDistrict": "AB",
				"adminDistrict2": "Alberta",
				"countryRegion": "Canada",
				"formattedAddress": "10031 103 Ave, Grande Prairie, AB T8V 1B9, Canada",
				"locality": "Grande Prairie",
				"neighborhood": "Northgate",
				"postalCode": "T8V 1B9"
			},
			"geometry": {
				"type": "Point",
				"coordinates": [
					-118.79744,
					55.17324
				]
			},
			"bbox": [
				-118.7994084,
				55.1721158,
				-118.7954716,
				55.1743642
			]
		}
	]
}
