{
	"type": "FeatureCollection",
	"features": [
		{
			"type": "Feature",
			"properties": {
				"confidence": 8,
				"authenticationResultCode": "ValidCredentials",
				"brandLogoUri": "http://dev.virtualearth.net/Branding/logo_powered_by.png",
				"copyright": "Copyright © 2017 Microsoft and its suppliers. All rights reserved. This API cannot be accessed and the content and any results may not be used, reproduced or transmitted in any manner without express written permission from Microsoft Corporation.",
				"entityType": "RoadBlock",
				"matchCodes": [
					"UpHierarchy"
				],
				"name": "102nd Ave, Tisdale, SK S0E, Canada",
				"statusCode": 200,
				"statusDescription": "OK",
				"traceId": "92dceade75a6484aa11b82bc1088e7d1|BN20130625|7.7.0.0|",
				"addressLine": "102nd Ave",
				"adminDistrict": "SK",
				"adminDistrict2": "Saskatchewan",
				"countryRegion": "Canada",
				"formattedAddress": "102nd Ave, Tisdale, SK S0E, Canada",
				"locality": "Tisdale",
				"postalCode": "S0E 1T0"
			},
			"geometry": {
				"type": "Point",
				"coordinates": [
					-104.04691,
					52.84961
				]
			},
			"bbox": [
				-104.0514199,
				52.84898,
				-104.04236,
				52.85044
			]
		}
	]
}
