{
	"type": "FeatureCollection",
	"features": [
		{
			"type": "Feature",
			"properties": {
				"confidence": 9,
				"authenticationResultCode": "ValidCredentials",
				"brandLogoUri": "http://dev.virtualearth.net/Branding/logo_powered_by.png",
				"copyright": "Copyright © 2017 Microsoft and its suppliers. All rights reserved. This API cannot be accessed and the content and any results may not be used, reproduced or transmitted in any manner without express written permission from Microsoft Corporation.",
				"entityType": "Address",
				"matchCodes": [
					"Good"
				],
				"name": "10055 106 St NW, Edmonton, AB T5J 2Y2, Canada",
				"statusCode": 200,
				"statusDescription": "OK",
				"traceId": "fffc66485e80428b9174f26f0cc5325a|BN20121764|7.7.0.0|",
				"addressLine": "10055 106 St NW",
				"adminDistrict": "AB",
				"adminDistrict2": "Alberta",
				"countryRegion": "Canada",
				"formattedAddress": "10055 106 St NW, Edmonton, AB T5J 2Y2, Canada",
				"locality": "Edmonton",
				"neighborhood": "Downtown",
				"postalCode": "T5J 2Y2"
			},
			"geometry": {
				"type": "Point",
				"coordinates": [
					-113.50263,
					53.54051
				]
			},
			"bbox": [
				-113.5045217,
				53.5393858,
				-113.5007383,
				53.5416342
			]
		}
	]
}
