{
	"type": "FeatureCollection",
	"features": [
		{
			"type": "Feature",
			"properties": {
				"confidence": 9,
				"authenticationResultCode": "ValidCredentials",
				"brandLogoUri": "http://dev.virtualearth.net/Branding/logo_powered_by.png",
				"copyright": "Copyright © 2017 Microsoft and its suppliers. All rights reserved. This API cannot be accessed and the content and any results may not be used, reproduced or transmitted in any manner without express written permission from Microsoft Corporation.",
				"entityType": "Address",
				"matchCodes": [
					"Good"
				],
				"name": "1006 Airport Rd, Gravenhurst, ON P0C, Canada",
				"statusCode": 200,
				"statusDescription": "OK",
				"traceId": "796fdef4ebc44385b923e0bc3ff8e1cd|BN20171457|7.7.0.0|",
				"addressLine": "1006 Airport Rd",
				"adminDistrict": "ON",
				"adminDistrict2": "Muskoka",
				"countryRegion": "Canada",
				"formattedAddress": "1006 Airport Rd, Gravenhurst, ON P0C, Canada",
				"locality": "Gravenhurst",
				"postalCode": "P0C"
			},
			"geometry": {
				"type": "Point",
				"coordinates": [
					-79.30743,
					44.9675
				]
			},
			"bbox": [
				-79.3090189,
				44.9663758,
				-79.3058411,
				44.9686242
			]
		}
	]
}
