{
	"type": "FeatureCollection",
	"features": [
		{
			"type": "Feature",
			"properties": {
				"confidence": 9,
				"authenticationResultCode": "ValidCredentials",
				"brandLogoUri": "http://dev.virtualearth.net/Branding/logo_powered_by.png",
				"copyright": "Copyright © 2017 Microsoft and its suppliers. All rights reserved. This API cannot be accessed and the content and any results may not be used, reproduced or transmitted in any manner without express written permission from Microsoft Corporation.",
				"entityType": "Address",
				"matchCodes": [
					"Good"
				],
				"name": "10095 Whalley Blvd, Surrey, BC V3T 4G1, Canada",
				"statusCode": 200,
				"statusDescription": "OK",
				"traceId": "38501240c41e4d04acba25a395c6587f|BN20121764|7.7.0.0|",
				"addressLine": "10095 Whalley Blvd",
				"adminDistrict": "BC",
				"adminDistrict2": "Greater Vancouver",
				"countryRegion": "Canada",
				"formattedAddress": "10095 Whalley Blvd, Surrey, BC V3T 4G1, Canada",
				"locality": "Surrey",
				"neighborhood": "Whalley",
				"postalCode": "V3T 4G1"
			},
			"geometry": {
				"type": "Point",
				"coordinates": [
					-122.8433549,
					49.1858858
				]
			},
			"bbox": [
				-122.8450748,
				49.1847617,
				-122.841635,
				49.18701
			]
		}
	]
}
