{
	"type": "FeatureCollection",
	"features": [
		{
			"type": "Feature",
			"properties": {
				"confidence": 9,
				"authenticationResultCode": "ValidCredentials",
				"brandLogoUri": "http://dev.virtualearth.net/Branding/logo_powered_by.png",
				"copyright": "Copyright © 2017 Microsoft and its suppliers. All rights reserved. This API cannot be accessed and the content and any results may not be used, reproduced or transmitted in any manner without express written permission from Microsoft Corporation.",
				"entityType": "Address",
				"matchCodes": [
					"Good"
				],
				"name": "10110 81 Ave NW, Edmonton, AB T6E, Canada",
				"statusCode": 200,
				"statusDescription": "OK",
				"traceId": "05be0e7f23934d88911a999aa421503a|BN20200137|7.7.0.0|",
				"addressLine": "10110 81 Ave NW",
				"adminDistrict": "AB",
				"adminDistrict2": "Alberta",
				"countryRegion": "Canada",
				"formattedAddress": "10110 81 Ave NW, Edmonton, AB T6E, Canada",
				"locality": "Edmonton",
				"neighborhood": "Ritchie",
				"postalCode": "T6E 1Z4"
			},
			"geometry": {
				"type": "Point",
				"coordinates": [
					-113.49187,
					53.5173599
				]
			},
			"bbox": [
				-113.4937607,
				53.5162357,
				-113.4899793,
				53.5184841
			]
		}
	]
}
