{
	"type": "FeatureCollection",
	"features": [
		{
			"type": "Feature",
			"properties": {
				"confidence": 5,
				"authenticationResultCode": "ValidCredentials",
				"brandLogoUri": "http://dev.virtualearth.net/Branding/logo_powered_by.png",
				"copyright": "Copyright © 2017 Microsoft and its suppliers. All rights reserved. This API cannot be accessed and the content and any results may not be used, reproduced or transmitted in any manner without express written permission from Microsoft Corporation.",
				"entityType": "RoadBlock",
				"matchCodes": [
					"UpHierarchy"
				],
				"name": "HWY-27, Woodbridge, ON L4L 1A7, Canada",
				"statusCode": 200,
				"statusDescription": "OK",
				"traceId": "18fd6bc115ab4916a65a8e26380ffacd|BN20130442|7.7.0.0|",
				"addressLine": "HWY-27",
				"adminDistrict": "ON",
				"adminDistrict2": "York",
				"countryRegion": "Canada",
				"formattedAddress": "HWY-27, Woodbridge, ON L4L 1A7, Canada",
				"locality": "Vaughan",
				"neighborhood": "Woodbridge",
				"postalCode": "L4L 1A7"
			},
			"geometry": {
				"type": "Point",
				"coordinates": [
					-79.629145,
					43.8117
				]
			},
			"bbox": [
				-79.6313799,
				43.7596599,
				-79.61679,
				43.82947
			]
		}
	]
}
