{
	"type": "FeatureCollection",
	"features": [
		{
			"type": "Feature",
			"properties": {
				"confidence": 9,
				"authenticationResultCode": "ValidCredentials",
				"brandLogoUri": "http://dev.virtualearth.net/Branding/logo_powered_by.png",
				"copyright": "Copyright © 2017 Microsoft and its suppliers. All rights reserved. This API cannot be accessed and the content and any results may not be used, reproduced or transmitted in any manner without express written permission from Microsoft Corporation.",
				"entityType": "Address",
				"matchCodes": [
					"Good"
				],
				"name": "10160 108 St, Grande Prairie, AB T8V 7B1, Canada",
				"statusCode": 200,
				"statusDescription": "OK",
				"traceId": "47160faf828847ffb7348d1289898b90|BN20160335|7.7.0.0|",
				"addressLine": "10160 108 St",
				"adminDistrict": "AB",
				"adminDistrict2": "Alberta",
				"countryRegion": "Canada",
				"formattedAddress": "10160 108 St, Grande Prairie, AB T8V 7B1, Canada",
				"locality": "Grande Prairie",
				"neighborhood": "Gateway",
				"postalCode": "T8V 7B1"
			},
			"geometry": {
				"type": "Point",
				"coordinates": [
					-118.82146,
					55.17186
				]
			},
			"bbox": [
				-118.8234283,
				55.1707358,
				-118.8194917,
				55.1729842
			]
		}
	]
}
