{
	"type": "FeatureCollection",
	"features": [
		{
			"type": "Feature",
			"properties": {
				"confidence": 9,
				"authenticationResultCode": "ValidCredentials",
				"brandLogoUri": "http://dev.virtualearth.net/Branding/logo_powered_by.png",
				"copyright": "Copyright © 2017 Microsoft and its suppliers. All rights reserved. This API cannot be accessed and the content and any results may not be used, reproduced or transmitted in any manner without express written permission from Microsoft Corporation.",
				"entityType": "Address",
				"matchCodes": [
					"Good"
				],
				"name": "10210 111 St NW, Edmonton, AB T5K 1K9, Canada",
				"statusCode": 200,
				"statusDescription": "OK",
				"traceId": "d73aa5137e494a4faa41ef745031e4ff|BN20121764|7.7.0.0|",
				"addressLine": "10210 111 St NW",
				"adminDistrict": "AB",
				"adminDistrict2": "Alberta",
				"countryRegion": "Canada",
				"formattedAddress": "10210 111 St NW, Edmonton, AB T5K 1K9, Canada",
				"locality": "Edmonton",
				"neighborhood": "Oliver",
				"postalCode": "T5K 1K9"
			},
			"geometry": {
				"type": "Point",
				"coordinates": [
					-113.51237,
					53.5435299
				]
			},
			"bbox": [
				-113.5142618,
				53.5424057,
				-113.5104782,
				53.5446541
			]
		}
	]
}
