{
	"type": "FeatureCollection",
	"features": [
		{
			"type": "Feature",
			"properties": {
				"confidence": 9,
				"authenticationResultCode": "ValidCredentials",
				"brandLogoUri": "http://dev.virtualearth.net/Branding/logo_powered_by.png",
				"copyright": "Copyright © 2017 Microsoft and its suppliers. All rights reserved. This API cannot be accessed and the content and any results may not be used, reproduced or transmitted in any manner without express written permission from Microsoft Corporation.",
				"entityType": "Address",
				"matchCodes": [
					"Good"
				],
				"name": "10241 109 St NW, Edmonton, AB T5J 1N2, Canada",
				"statusCode": 200,
				"statusDescription": "OK",
				"traceId": "dfea8f05c77f454790db5e6e58de7222|BN20200137|7.7.0.0|",
				"addressLine": "10241 109 St NW",
				"adminDistrict": "AB",
				"adminDistrict2": "Alberta",
				"countryRegion": "Canada",
				"formattedAddress": "10241 109 St NW, Edmonton, AB T5J 1N2, Canada",
				"locality": "Edmonton",
				"neighborhood": "Downtown",
				"postalCode": "T5J 1N2"
			},
			"geometry": {
				"type": "Point",
				"coordinates": [
					-113.50793,
					53.54395
				]
			},
			"bbox": [
				-113.5098219,
				53.5428258,
				-113.5060381,
				53.5450742
			]
		}
	]
}
