{
	"type": "FeatureCollection",
	"features": [
		{
			"type": "Feature",
			"properties": {
				"confidence": 9,
				"authenticationResultCode": "ValidCredentials",
				"brandLogoUri": "http://dev.virtualearth.net/Branding/logo_powered_by.png",
				"copyright": "Copyright © 2017 Microsoft and its suppliers. All rights reserved. This API cannot be accessed and the content and any results may not be used, reproduced or transmitted in any manner without express written permission from Microsoft Corporation.",
				"entityType": "Address",
				"matchCodes": [
					"Good"
				],
				"name": "103 Sornberger Pl, Hinton, AB T7V 1H6, Canada",
				"statusCode": 200,
				"statusDescription": "OK",
				"traceId": "a3e8747769c74e1fa5f0668355d9adf1|BN20130447|7.7.0.0|",
				"addressLine": "103 Sornberger Pl",
				"adminDistrict": "AB",
				"adminDistrict2": "Alberta",
				"countryRegion": "Canada",
				"formattedAddress": "103 Sornberger Pl, Hinton, AB T7V 1H6, Canada",
				"locality": "Hinton",
				"postalCode": "T7V 1H6"
			},
			"geometry": {
				"type": "Point",
				"coordinates": [
					-117.555,
					53.40285
				]
			},
			"bbox": [
				-117.5568856,
				53.4017258,
				-117.5531144,
				53.4039742
			]
		}
	]
}
