{
	"type": "FeatureCollection",
	"features": [
		{
			"type": "Feature",
			"properties": {
				"confidence": 9,
				"authenticationResultCode": "ValidCredentials",
				"brandLogoUri": "http://dev.virtualearth.net/Branding/logo_powered_by.png",
				"copyright": "Copyright © 2017 Microsoft and its suppliers. All rights reserved. This API cannot be accessed and the content and any results may not be used, reproduced or transmitted in any manner without express written permission from Microsoft Corporation.",
				"entityType": "Address",
				"matchCodes": [
					"Good"
				],
				"name": "10331 176 St NW, Edmonton, AB T5S 2E4, Canada",
				"statusCode": 200,
				"statusDescription": "OK",
				"traceId": "74afd8f5cc71419688589995cbebc180|BN20130625|7.7.0.0|",
				"addressLine": "10331 176 St NW",
				"adminDistrict": "AB",
				"adminDistrict2": "Alberta",
				"countryRegion": "Canada",
				"formattedAddress": "10331 176 St NW, Edmonton, AB T5S 2E4, Canada",
				"locality": "Edmonton",
				"neighborhood": "Stone Industrial",
				"postalCode": "T5S 2E4"
			},
			"geometry": {
				"type": "Point",
				"coordinates": [
					-113.62274,
					53.5462
				]
			},
			"bbox": [
				-113.624632,
				53.5450758,
				-113.620848,
				53.5473242
			]
		}
	]
}
