{
	"type": "FeatureCollection",
	"features": [
		{
			"type": "Feature",
			"properties": {
				"confidence": 9,
				"authenticationResultCode": "ValidCredentials",
				"brandLogoUri": "http://dev.virtualearth.net/Branding/logo_powered_by.png",
				"copyright": "Copyright © 2017 Microsoft and its suppliers. All rights reserved. This API cannot be accessed and the content and any results may not be used, reproduced or transmitted in any manner without express written permission from Microsoft Corporation.",
				"entityType": "Address",
				"matchCodes": [
					"Good"
				],
				"name": "1038 Parkinson Rd, Woodstock, ON N4S 7W3, Canada",
				"statusCode": 200,
				"statusDescription": "OK",
				"traceId": "f958cbbec6654ea3b147dd3e41291874|BN20160335|7.7.0.0|",
				"addressLine": "1038 Parkinson Rd",
				"adminDistrict": "ON",
				"adminDistrict2": "Oxford",
				"countryRegion": "Canada",
				"formattedAddress": "1038 Parkinson Rd, Woodstock, ON N4S 7W3, Canada",
				"locality": "Woodstock",
				"postalCode": "N4S 7W3"
			},
			"geometry": {
				"type": "Point",
				"coordinates": [
					-80.7217593,
					43.1226043
				]
			},
			"bbox": [
				-80.7232995,
				43.1214801,
				-80.7202192,
				43.1237284
			]
		}
	]
}
