{
	"type": "FeatureCollection",
	"features": [
		{
			"type": "Feature",
			"properties": {
				"confidence": 9,
				"authenticationResultCode": "ValidCredentials",
				"brandLogoUri": "http://dev.virtualearth.net/Branding/logo_powered_by.png",
				"copyright": "Copyright © 2017 Microsoft and its suppliers. All rights reserved. This API cannot be accessed and the content and any results may not be used, reproduced or transmitted in any manner without express written permission from Microsoft Corporation.",
				"entityType": "Address",
				"matchCodes": [
					"Good"
				],
				"name": "1039 Ridgeway Rd, Woodstock, ON N4V 1E1, Canada",
				"statusCode": 200,
				"statusDescription": "OK",
				"traceId": "3b590298d7ca44969f5ef9d958580acc|BN20130631|7.7.0.0|",
				"addressLine": "1039 Ridgeway Rd",
				"adminDistrict": "ON",
				"adminDistrict2": "Oxford",
				"countryRegion": "Canada",
				"formattedAddress": "1039 Ridgeway Rd, Woodstock, ON N4V 1E1, Canada",
				"locality": "Woodstock",
				"postalCode": "N4V 1E1"
			},
			"geometry": {
				"type": "Point",
				"coordinates": [
					-80.72593,
					43.11148
				]
			},
			"bbox": [
				-80.7274699,
				43.1103558,
				-80.7243901,
				43.1126042
			]
		}
	]
}
