{
	"type": "FeatureCollection",
	"features": [
		{
			"type": "Feature",
			"properties": {
				"confidence": 9,
				"authenticationResultCode": "ValidCredentials",
				"brandLogoUri": "http://dev.virtualearth.net/Branding/logo_powered_by.png",
				"copyright": "Copyright © 2017 Microsoft and its suppliers. All rights reserved. This API cannot be accessed and the content and any results may not be used, reproduced or transmitted in any manner without express written permission from Microsoft Corporation.",
				"entityType": "Address",
				"matchCodes": [
					"Good"
				],
				"name": "104 King St E, Bowmanville, ON L1C 1N5, Canada",
				"statusCode": 200,
				"statusDescription": "OK",
				"traceId": "e71c800afa9e44db836da250bacecb81|BN20130719|7.7.0.0|",
				"addressLine": "104 King St E",
				"adminDistrict": "ON",
				"adminDistrict2": "Durham",
				"countryRegion": "Canada",
				"formattedAddress": "104 King St E, Bowmanville, ON L1C 1N5, Canada",
				"locality": "Clarington",
				"neighborhood": "Bowmanville",
				"postalCode": "L1C 1N5"
			},
			"geometry": {
				"type": "Point",
				"coordinates": [
					-78.6853299,
					43.91139
				]
			},
			"bbox": [
				-78.6868903,
				43.9102658,
				-78.6837695,
				43.9125142
			]
		}
	]
}
