{
	"type": "FeatureCollection",
	"features": [
		{
			"type": "Feature",
			"properties": {
				"confidence": 9,
				"authenticationResultCode": "ValidCredentials",
				"brandLogoUri": "http://dev.virtualearth.net/Branding/logo_powered_by.png",
				"copyright": "Copyright © 2017 Microsoft and its suppliers. All rights reserved. This API cannot be accessed and the content and any results may not be used, reproduced or transmitted in any manner without express written permission from Microsoft Corporation.",
				"entityType": "Address",
				"matchCodes": [
					"Good"
				],
				"name": "104 Cour Forestview, Fredericton, NB E3A 1H8, Canada",
				"statusCode": 200,
				"statusDescription": "OK",
				"traceId": "b37513e9b47a4437af1ae2c04e9a84f7|BN20130442|7.7.0.0|",
				"addressLine": "104 Cour Forestview",
				"adminDistrict": "NB",
				"adminDistrict2": "York",
				"countryRegion": "Canada",
				"formattedAddress": "104 Cour Forestview, Fredericton, NB E3A 1H8, Canada",
				"locality": "Fredericton",
				"postalCode": "E3A 1H8"
			},
			"geometry": {
				"type": "Point",
				"coordinates": [
					-66.6707,
					45.98293
				]
			},
			"bbox": [
				-66.6723178,
				45.9818058,
				-66.6690822,
				45.9840542
			]
		}
	]
}
