{
	"type": "FeatureCollection",
	"features": [
		{
			"type": "Feature",
			"properties": {
				"confidence": 9,
				"authenticationResultCode": "ValidCredentials",
				"brandLogoUri": "http://dev.virtualearth.net/Branding/logo_powered_by.png",
				"copyright": "Copyright © 2017 Microsoft and its suppliers. All rights reserved. This API cannot be accessed and the content and any results may not be used, reproduced or transmitted in any manner without express written permission from Microsoft Corporation.",
				"entityType": "Address",
				"matchCodes": [
					"Good"
				],
				"name": "1040 Somerset St W, Ottawa, ON K1Y 4L3, Canada",
				"statusCode": 200,
				"statusDescription": "OK",
				"traceId": "d41bb447f1f942b385094d16b07616e2|BN20130522|7.7.0.0|",
				"addressLine": "1040 Somerset St W",
				"adminDistrict": "ON",
				"adminDistrict2": "Ottawa",
				"countryRegion": "Canada",
				"formattedAddress": "1040 Somerset St W, Ottawa, ON K1Y 4L3, Canada",
				"locality": "Ottawa",
				"neighborhood": "Hintonburg-Mechanicsville",
				"postalCode": "K1Y 4L3"
			},
			"geometry": {
				"type": "Point",
				"coordinates": [
					-75.71881,
					45.4066199
				]
			},
			"bbox": [
				-75.7204112,
				45.4054957,
				-75.7172088,
				45.4077441
			]
		}
	]
}
