{
	"type": "FeatureCollection",
	"features": [
		{
			"type": "Feature",
			"properties": {
				"confidence": 9,
				"authenticationResultCode": "ValidCredentials",
				"brandLogoUri": "http://dev.virtualearth.net/Branding/logo_powered_by.png",
				"copyright": "Copyright © 2017 Microsoft and its suppliers. All rights reserved. This API cannot be accessed and the content and any results may not be used, reproduced or transmitted in any manner without express written permission from Microsoft Corporation.",
				"entityType": "Address",
				"matchCodes": [
					"Good"
				],
				"name": "1040 Wilton Grove Rd, London, ON N6N 1C7, Canada",
				"statusCode": 200,
				"statusDescription": "OK",
				"traceId": "c12e132ba4a546168ed12e732c033b2f|CO30275941|7.7.0.0|",
				"addressLine": "1040 Wilton Grove Rd",
				"adminDistrict": "ON",
				"adminDistrict2": "Middlesex",
				"countryRegion": "Canada",
				"formattedAddress": "1040 Wilton Grove Rd, London, ON N6N 1C7, Canada",
				"locality": "London",
				"neighborhood": "Westminster",
				"postalCode": "N6N 1C7"
			},
			"geometry": {
				"type": "Point",
				"coordinates": [
					-81.1937034,
					42.9281602
				]
			},
			"bbox": [
				-81.1952386,
				42.9270361,
				-81.1921681,
				42.9292844
			]
		}
	]
}
