{
	"type": "FeatureCollection",
	"features": [
		{
			"type": "Feature",
			"properties": {
				"confidence": 9,
				"authenticationResultCode": "ValidCredentials",
				"brandLogoUri": "http://dev.virtualearth.net/Branding/logo_powered_by.png",
				"copyright": "Copyright © 2017 Microsoft and its suppliers. All rights reserved. This API cannot be accessed and the content and any results may not be used, reproduced or transmitted in any manner without express written permission from Microsoft Corporation.",
				"entityType": "Address",
				"matchCodes": [
					"Good"
				],
				"name": "1041 Moss St, Victoria, BC V8V 4P2, Canada",
				"statusCode": 200,
				"statusDescription": "OK",
				"traceId": "082b41c2bcbd40698bb3f2667152a4e6|BN20130532|7.7.0.0|",
				"addressLine": "1041 Moss St",
				"adminDistrict": "BC",
				"adminDistrict2": "Capital",
				"countryRegion": "Canada",
				"formattedAddress": "1041 Moss St, Victoria, BC V8V 4P2, Canada",
				"locality": "Victoria",
				"neighborhood": "Rockland",
				"postalCode": "V8V 4P2"
			},
			"geometry": {
				"type": "Point",
				"coordinates": [
					-123.34678,
					48.42216
				]
			},
			"bbox": [
				-123.3484739,
				48.4210358,
				-123.3450861,
				48.4232842
			]
		}
	]
}
