{
	"type": "FeatureCollection",
	"features": [
		{
			"type": "Feature",
			"properties": {
				"confidence": 9,
				"authenticationResultCode": "ValidCredentials",
				"brandLogoUri": "http://dev.virtualearth.net/Branding/logo_powered_by.png",
				"copyright": "Copyright © 2017 Microsoft and its suppliers. All rights reserved. This API cannot be accessed and the content and any results may not be used, reproduced or transmitted in any manner without express written permission from Microsoft Corporation.",
				"entityType": "Address",
				"matchCodes": [
					"Good"
				],
				"name": "10456 Lakeshore Rd, Grand Bend, ON N0M 1T0, Canada",
				"statusCode": 200,
				"statusDescription": "OK",
				"traceId": "99566e1967c14fb6a6d212b4861e7d4e|BN20130530|7.7.0.0|",
				"addressLine": "10456 Lakeshore Rd",
				"adminDistrict": "ON",
				"adminDistrict2": "Lambton",
				"countryRegion": "Canada",
				"formattedAddress": "10456 Lakeshore Rd, Grand Bend, ON N0M 1T0, Canada",
				"locality": "Lambton Shores",
				"neighborhood": "Grand Bend",
				"postalCode": "N0M 1T0"
			},
			"geometry": {
				"type": "Point",
				"coordinates": [
					-81.77357,
					43.29224
				]
			},
			"bbox": [
				-81.7751144,
				43.2911158,
				-81.7720256,
				43.2933642
			]
		}
	]
}
