{
	"type": "FeatureCollection",
	"features": [
		{
			"type": "Feature",
			"properties": {
				"confidence": 9,
				"authenticationResultCode": "ValidCredentials",
				"brandLogoUri": "http://dev.virtualearth.net/Branding/logo_powered_by.png",
				"copyright": "Copyright © 2017 Microsoft and its suppliers. All rights reserved. This API cannot be accessed and the content and any results may not be used, reproduced or transmitted in any manner without express written permission from Microsoft Corporation.",
				"entityType": "Address",
				"matchCodes": [
					"Good"
				],
				"name": "105 Olive St, Grimsby, ON L3M 5A6, Canada",
				"statusCode": 200,
				"statusDescription": "OK",
				"traceId": "b8b433ae717d478c9b83da2e00872627|BN20130520|7.7.0.0|",
				"addressLine": "105 Olive St",
				"adminDistrict": "ON",
				"adminDistrict2": "Niagara",
				"countryRegion": "Canada",
				"formattedAddress": "105 Olive St, Grimsby, ON L3M 5A6, Canada",
				"locality": "Grimsby",
				"postalCode": "L3M 5A6"
			},
			"geometry": {
				"type": "Point",
				"coordinates": [
					-79.57354,
					43.20357
				]
			},
			"bbox": [
				-79.5750822,
				43.2024458,
				-79.5719978,
				43.2046942
			]
		}
	]
}
