{
	"type": "FeatureCollection",
	"features": [
		{
			"type": "Feature",
			"properties": {
				"confidence": 9,
				"authenticationResultCode": "ValidCredentials",
				"brandLogoUri": "http://dev.virtualearth.net/Branding/logo_powered_by.png",
				"copyright": "Copyright © 2017 Microsoft and its suppliers. All rights reserved. This API cannot be accessed and the content and any results may not be used, reproduced or transmitted in any manner without express written permission from Microsoft Corporation.",
				"entityType": "Address",
				"matchCodes": [
					"Good"
				],
				"name": "10610 Airport Dr, Grande Prairie, AB T8V 7Z5, Canada",
				"statusCode": 200,
				"statusDescription": "OK",
				"traceId": "c9bf5a37c6734dab933bf9458be637e0|BN20130530|7.7.0.0|",
				"addressLine": "10610 Airport Dr",
				"adminDistrict": "AB",
				"adminDistrict2": "Alberta",
				"countryRegion": "Canada",
				"formattedAddress": "10610 Airport Dr, Grande Prairie, AB T8V 7Z5, Canada",
				"locality": "Grande Prairie",
				"postalCode": "T8V 7Z5"
			},
			"geometry": {
				"type": "Point",
				"coordinates": [
					-118.87381,
					55.17727
				]
			},
			"bbox": [
				-118.8757786,
				55.1761458,
				-118.8718414,
				55.1783942
			]
		}
	]
}
