{
	"type": "FeatureCollection",
	"features": [
		{
			"type": "Feature",
			"properties": {
				"confidence": 9,
				"authenticationResultCode": "ValidCredentials",
				"brandLogoUri": "http://dev.virtualearth.net/Branding/logo_powered_by.png",
				"copyright": "Copyright © 2017 Microsoft and its suppliers. All rights reserved. This API cannot be accessed and the content and any results may not be used, reproduced or transmitted in any manner without express written permission from Microsoft Corporation.",
				"entityType": "Address",
				"matchCodes": [
					"Good"
				],
				"name": "1065 Cambie St, Vancouver, BC V6B 5L7, Canada",
				"statusCode": 200,
				"statusDescription": "OK",
				"traceId": "940a25cc88ad49c6a9847b312a96daa5|BN20130621|7.7.0.0|",
				"addressLine": "1065 Cambie St",
				"adminDistrict": "BC",
				"adminDistrict2": "Greater Vancouver",
				"countryRegion": "Canada",
				"formattedAddress": "1065 Cambie St, Vancouver, BC V6B 5L7, Canada",
				"locality": "Vancouver",
				"neighborhood": "Yaletown",
				"postalCode": "V6B 5L7"
			},
			"geometry": {
				"type": "Point",
				"coordinates": [
					-123.1190331,
					49.2754202
				]
			},
			"bbox": [
				-123.1207562,
				49.274296,
				-123.1173101,
				49.2765443
			]
		}
	]
}
