{
	"type": "FeatureCollection",
	"features": [
		{
			"type": "Feature",
			"properties": {
				"confidence": 9,
				"authenticationResultCode": "ValidCredentials",
				"brandLogoUri": "http://dev.virtualearth.net/Branding/logo_powered_by.png",
				"copyright": "Copyright © 2017 Microsoft and its suppliers. All rights reserved. This API cannot be accessed and the content and any results may not be used, reproduced or transmitted in any manner without express written permission from Microsoft Corporation.",
				"entityType": "Address",
				"matchCodes": [
					"Good"
				],
				"name": "1065 Henry Eng Pl, Langford, BC V9B 6B2, Canada",
				"statusCode": 200,
				"statusDescription": "OK",
				"traceId": "1bb5aebd52714d7d9caf5e3c079b1d3a|BN20130520|7.7.0.0|",
				"addressLine": "1065 Henry Eng Pl",
				"adminDistrict": "BC",
				"adminDistrict2": "Capital",
				"countryRegion": "Canada",
				"formattedAddress": "1065 Henry Eng Pl, Langford, BC V9B 6B2, Canada",
				"locality": "Langford",
				"postalCode": "V9B 6B2"
			},
			"geometry": {
				"type": "Point",
				"coordinates": [
					-123.52075,
					48.44423
				]
			},
			"bbox": [
				-123.5224447,
				48.4431058,
				-123.5190553,
				48.4453542
			]
		}
	]
}
