{
	"type": "FeatureCollection",
	"features": [
		{
			"type": "Feature",
			"properties": {
				"confidence": 9,
				"authenticationResultCode": "ValidCredentials",
				"brandLogoUri": "http://dev.virtualearth.net/Branding/logo_powered_by.png",
				"copyright": "Copyright © 2017 Microsoft and its suppliers. All rights reserved. This API cannot be accessed and the content and any results may not be used, reproduced or transmitted in any manner without express written permission from Microsoft Corporation.",
				"entityType": "Address",
				"matchCodes": [
					"Good"
				],
				"name": "1065 30 St SW, Medicine Hat, AB T1B 3N3, Canada",
				"statusCode": 200,
				"statusDescription": "OK",
				"traceId": "6d1d6826cb364f2da91c2052af71df87|BN20220145|7.7.0.0|",
				"addressLine": "1065 30 St SW",
				"adminDistrict": "AB",
				"adminDistrict2": "Alberta",
				"countryRegion": "Canada",
				"formattedAddress": "1065 30 St SW, Medicine Hat, AB T1B 3N3, Canada",
				"locality": "Medicine Hat",
				"postalCode": "T1B 3N3"
			},
			"geometry": {
				"type": "Point",
				"coordinates": [
					-110.7122,
					50.01151
				]
			},
			"bbox": [
				-110.7139493,
				50.0103858,
				-110.7104507,
				50.0126342
			]
		}
	]
}
