{
	"type": "FeatureCollection",
	"features": [
		{
			"type": "Feature",
			"properties": {
				"confidence": 9,
				"authenticationResultCode": "ValidCredentials",
				"brandLogoUri": "http://dev.virtualearth.net/Branding/logo_powered_by.png",
				"copyright": "Copyright © 2017 Microsoft and its suppliers. All rights reserved. This API cannot be accessed and the content and any results may not be used, reproduced or transmitted in any manner without express written permission from Microsoft Corporation.",
				"entityType": "Address",
				"matchCodes": [
					"Good"
				],
				"name": "10755 69 Ave NW, Edmonton, AB T6H 2C9, Canada",
				"statusCode": 200,
				"statusDescription": "OK",
				"traceId": "dd97ad69c48b420a97613acfc0cfe376|BN20200239|7.7.0.0|",
				"addressLine": "10755 69 Ave NW",
				"adminDistrict": "AB",
				"adminDistrict2": "Alberta",
				"countryRegion": "Canada",
				"formattedAddress": "10755 69 Ave NW, Edmonton, AB T6H 2C9, Canada",
				"locality": "Edmonton",
				"neighborhood": "Allendale",
				"postalCode": "T6H 2C9"
			},
			"geometry": {
				"type": "Point",
				"coordinates": [
					-113.50902,
					53.50544
				]
			},
			"bbox": [
				-113.5109101,
				53.5043158,
				-113.5071299,
				53.5065642
			]
		}
	]
}
