{
	"type": "FeatureCollection",
	"features": [
		{
			"type": "Feature",
			"properties": {
				"confidence": 9,
				"authenticationResultCode": "ValidCredentials",
				"brandLogoUri": "http://dev.virtualearth.net/Branding/logo_powered_by.png",
				"copyright": "Copyright © 2017 Microsoft and its suppliers. All rights reserved. This API cannot be accessed and the content and any results may not be used, reproduced or transmitted in any manner without express written permission from Microsoft Corporation.",
				"entityType": "Address",
				"matchCodes": [
					"Good"
				],
				"name": "1079 Autumnwood Dr, Winnipeg, MB R2J 1C6, Canada",
				"statusCode": 200,
				"statusDescription": "OK",
				"traceId": "80d4414cbb0f44adb766595773a27abd|BN20300154|7.7.0.0|",
				"addressLine": "1079 Autumnwood Dr",
				"adminDistrict": "MB",
				"adminDistrict2": "Manitoba",
				"countryRegion": "Canada",
				"formattedAddress": "1079 Autumnwood Dr, Winnipeg, MB R2J 1C6, Canada",
				"locality": "Winnipeg",
				"neighborhood": "Windsor Park",
				"postalCode": "R2J 1C6"
			},
			"geometry": {
				"type": "Point",
				"coordinates": [
					-97.07695,
					49.86183
				]
			},
			"bbox": [
				-97.0786939,
				49.8607058,
				-97.0752061,
				49.8629542
			]
		}
	]
}
