{
	"type": "FeatureCollection",
	"features": [
		{
			"type": "Feature",
			"properties": {
				"confidence": 9,
				"authenticationResultCode": "ValidCredentials",
				"brandLogoUri": "http://dev.virtualearth.net/Branding/logo_powered_by.png",
				"copyright": "Copyright © 2017 Microsoft and its suppliers. All rights reserved. This API cannot be accessed and the content and any results may not be used, reproduced or transmitted in any manner without express written permission from Microsoft Corporation.",
				"entityType": "Address",
				"matchCodes": [
					"Good"
				],
				"name": "108 Bruton St, Port Hope, ON L1A 1V3, Canada",
				"statusCode": 200,
				"statusDescription": "OK",
				"traceId": "3a9b465228304690944d697050f28eb6|BN20130521|7.7.0.0|",
				"addressLine": "108 Bruton St",
				"adminDistrict": "ON",
				"adminDistrict2": "Northumberland",
				"countryRegion": "Canada",
				"formattedAddress": "108 Bruton St, Port Hope, ON L1A 1V3, Canada",
				"locality": "Port Hope",
				"postalCode": "L1A 1V3"
			},
			"geometry": {
				"type": "Point",
				"coordinates": [
					-78.30515,
					43.95385
				]
			},
			"bbox": [
				-78.3067115,
				43.9527258,
				-78.3035885,
				43.9549742
			]
		}
	]
}
