{
	"type": "FeatureCollection",
	"features": [
		{
			"type": "Feature",
			"properties": {
				"confidence": 9,
				"authenticationResultCode": "ValidCredentials",
				"brandLogoUri": "http://dev.virtualearth.net/Branding/logo_powered_by.png",
				"copyright": "Copyright © 2017 Microsoft and its suppliers. All rights reserved. This API cannot be accessed and the content and any results may not be used, reproduced or transmitted in any manner without express written permission from Microsoft Corporation.",
				"entityType": "Address",
				"matchCodes": [
					"Good"
				],
				"name": "1088 Grover Ave, Coquitlam, BC V3J 3G1, Canada",
				"statusCode": 200,
				"statusDescription": "OK",
				"traceId": "b8462a15263a434d8603f75b083b140d|BN20121763|7.7.0.0|",
				"addressLine": "1088 Grover Ave",
				"adminDistrict": "BC",
				"adminDistrict2": "Greater Vancouver",
				"countryRegion": "Canada",
				"formattedAddress": "1088 Grover Ave, Coquitlam, BC V3J 3G1, Canada",
				"locality": "Coquitlam",
				"neighborhood": "Central Coquitlam",
				"postalCode": "V3J 3G1"
			},
			"geometry": {
				"type": "Point",
				"coordinates": [
					-122.86211,
					49.26235
				]
			},
			"bbox": [
				-122.8638326,
				49.2612258,
				-122.8603874,
				49.2634742
			]
		}
	]
}
