{
	"type": "FeatureCollection",
	"features": [
		{
			"type": "Feature",
			"properties": {
				"confidence": 9,
				"authenticationResultCode": "ValidCredentials",
				"brandLogoUri": "http://dev.virtualearth.net/Branding/logo_powered_by.png",
				"copyright": "Copyright © 2017 Microsoft and its suppliers. All rights reserved. This API cannot be accessed and the content and any results may not be used, reproduced or transmitted in any manner without express written permission from Microsoft Corporation.",
				"entityType": "Address",
				"matchCodes": [
					"Good"
				],
				"name": "10900 Rue Secant, Anjou, QC H1J 1S5, Canada",
				"statusCode": 200,
				"statusDescription": "OK",
				"traceId": "36dc27cb352c43538c54248852dd6251|BN20130721|7.7.0.0|",
				"addressLine": "10900 Rue Secant",
				"adminDistrict": "QC",
				"adminDistrict2": "Montreal",
				"countryRegion": "Canada",
				"formattedAddress": "10900 Rue Secant, Anjou, QC H1J 1S5, Canada",
				"locality": "Montreal",
				"neighborhood": "Anjou",
				"postalCode": "H1J 1S5"
			},
			"geometry": {
				"type": "Point",
				"coordinates": [
					-73.58193,
					45.61938
				]
			},
			"bbox": [
				-73.5835373,
				45.6182558,
				-73.5803227,
				45.6205042
			]
		}
	]
}
