{
	"type": "FeatureCollection",
	"features": [
		{
			"type": "Feature",
			"properties": {
				"confidence": 9,
				"authenticationResultCode": "ValidCredentials",
				"brandLogoUri": "http://dev.virtualearth.net/Branding/logo_powered_by.png",
				"copyright": "Copyright © 2017 Microsoft and its suppliers. All rights reserved. This API cannot be accessed and the content and any results may not be used, reproduced or transmitted in any manner without express written permission from Microsoft Corporation.",
				"entityType": "Address",
				"matchCodes": [
					"Good"
				],
				"name": "10960 Airport Rd, Brampton, ON L6R 0E1, Canada",
				"statusCode": 200,
				"statusDescription": "OK",
				"traceId": "37e2ebdf185b4d3793f27f21dca1303a|BN20130530|7.7.0.0|",
				"addressLine": "10960 Airport Rd",
				"adminDistrict": "ON",
				"adminDistrict2": "Peel",
				"countryRegion": "Canada",
				"formattedAddress": "10960 Airport Rd, Brampton, ON L6R 0E1, Canada",
				"locality": "Brampton",
				"neighborhood": "Springdale",
				"postalCode": "L6R 0E1"
			},
			"geometry": {
				"type": "Point",
				"coordinates": [
					-79.74845,
					43.78204
				]
			},
			"bbox": [
				-79.750007,
				43.7809158,
				-79.746893,
				43.7831642
			]
		}
	]
}
