{
	"type": "FeatureCollection",
	"features": [
		{
			"type": "Feature",
			"properties": {
				"confidence": 9,
				"authenticationResultCode": "ValidCredentials",
				"brandLogoUri": "http://dev.virtualearth.net/Branding/logo_powered_by.png",
				"copyright": "Copyright © 2017 Microsoft and its suppliers. All rights reserved. This API cannot be accessed and the content and any results may not be used, reproduced or transmitted in any manner without express written permission from Microsoft Corporation.",
				"entityType": "Address",
				"matchCodes": [
					"Good"
				],
				"name": "1097 Ambercrest St, Gloucester, ON K1J 1G3, Canada",
				"statusCode": 200,
				"statusDescription": "OK",
				"traceId": "ca00db98de9848adbea8d52d3367b7eb|BN20200137|7.7.0.0|",
				"addressLine": "1097 Ambercrest St",
				"adminDistrict": "ON",
				"adminDistrict2": "Ottawa",
				"countryRegion": "Canada",
				"formattedAddress": "1097 Ambercrest St, Gloucester, ON K1J 1G3, Canada",
				"locality": "Ottawa",
				"neighborhood": "Gloucester",
				"postalCode": "K1J 1G3"
			},
			"geometry": {
				"type": "Point",
				"coordinates": [
					-75.6313,
					45.43412
				]
			},
			"bbox": [
				-75.632902,
				45.4329958,
				-75.629698,
				45.4352442
			]
		}
	]
}
