{
	"type": "FeatureCollection",
	"features": [
		{
			"type": "Feature",
			"properties": {
				"confidence": 9,
				"authenticationResultCode": "ValidCredentials",
				"brandLogoUri": "http://dev.virtualearth.net/Branding/logo_powered_by.png",
				"copyright": "Copyright © 2017 Microsoft and its suppliers. All rights reserved. This API cannot be accessed and the content and any results may not be used, reproduced or transmitted in any manner without express written permission from Microsoft Corporation.",
				"entityType": "Address",
				"matchCodes": [
					"Good"
				],
				"name": "11 Bank Note Pvt, Ottawa, ON K1Z 1C6, Canada",
				"statusCode": 200,
				"statusDescription": "OK",
				"traceId": "201de26752d54063a527fba5b4f7b37e|BN20260231|7.7.0.0|",
				"addressLine": "11 Bank Note Pvt",
				"adminDistrict": "ON",
				"adminDistrict2": "Ottawa",
				"countryRegion": "Canada",
				"formattedAddress": "11 Bank Note Pvt, Ottawa, ON K1Z 1C6, Canada",
				"locality": "Ottawa",
				"neighborhood": "Westboro",
				"postalCode": "K1Z 1C6"
			},
			"geometry": {
				"type": "Point",
				"coordinates": [
					-75.74677,
					45.3975
				]
			},
			"bbox": [
				-75.7483709,
				45.3963758,
				-75.7451691,
				45.3986242
			]
		}
	]
}
