{
	"type": "FeatureCollection",
	"features": [
		{
			"type": "Feature",
			"properties": {
				"confidence": 7,
				"authenticationResultCode": "ValidCredentials",
				"brandLogoUri": "http://dev.virtualearth.net/Branding/logo_powered_by.png",
				"copyright": "Copyright © 2017 Microsoft and its suppliers. All rights reserved. This API cannot be accessed and the content and any results may not be used, reproduced or transmitted in any manner without express written permission from Microsoft Corporation.",
				"entityType": "Neighborhood",
				"matchCodes": [
					"UpHierarchy"
				],
				"name": "Ste Agathe, Ritchot, Manitoba, Canada",
				"statusCode": 200,
				"statusDescription": "OK",
				"traceId": "c65d4ca8a8734245af50f9627f1a3cb3|BN20130530|7.7.0.0|",
				"adminDistrict": "MB",
				"countryRegion": "Canada",
				"formattedAddress": "Ste Agathe, Ritchot, Manitoba, Canada",
				"locality": "Ritchot",
				"neighborhood": "Ste Agathe"
			},
			"geometry": {
				"type": "Point",
				"coordinates": [
					-97.1823806762695,
					49.5681610107422
				]
			},
			"bbox": [
				-97.1903213721927,
				49.5642982931715,
				-97.1744399803464,
				49.5720237283129
			]
		}
	]
}
