{
	"type": "FeatureCollection",
	"features": [
		{
			"type": "Feature",
			"properties": {
				"confidence": 9,
				"authenticationResultCode": "ValidCredentials",
				"brandLogoUri": "http://dev.virtualearth.net/Branding/logo_powered_by.png",
				"copyright": "Copyright © 2017 Microsoft and its suppliers. All rights reserved. This API cannot be accessed and the content and any results may not be used, reproduced or transmitted in any manner without express written permission from Microsoft Corporation.",
				"entityType": "Address",
				"matchCodes": [
					"Good"
				],
				"name": "110 Morton Ave E, Brantford, ON N3R 7J7, Canada",
				"statusCode": 200,
				"statusDescription": "OK",
				"traceId": "1ae1c24d7966401290d33a8dd77a5236|BN20130719|7.7.0.0|",
				"addressLine": "110 Morton Ave E",
				"adminDistrict": "ON",
				"adminDistrict2": "Brant",
				"countryRegion": "Canada",
				"formattedAddress": "110 Morton Ave E, Brantford, ON N3R 7J7, Canada",
				"locality": "Brantford",
				"postalCode": "N3R 7J7"
			},
			"geometry": {
				"type": "Point",
				"coordinates": [
					-80.2431299,
					43.16163
				]
			},
			"bbox": [
				-80.244671,
				43.1605058,
				-80.2415888,
				43.1627542
			]
		}
	]
}
