{
	"type": "FeatureCollection",
	"features": [
		{
			"type": "Feature",
			"properties": {
				"confidence": 7,
				"authenticationResultCode": "ValidCredentials",
				"brandLogoUri": "http://dev.virtualearth.net/Branding/logo_powered_by.png",
				"copyright": "Copyright © 2017 Microsoft and its suppliers. All rights reserved. This API cannot be accessed and the content and any results may not be used, reproduced or transmitted in any manner without express written permission from Microsoft Corporation.",
				"entityType": "Postcode1",
				"matchCodes": [
					"UpHierarchy"
				],
				"name": "Bala, P0C 1A0, Canada",
				"statusCode": 200,
				"statusDescription": "OK",
				"traceId": "a970b500e8694f09824cf28f28808376|BN20260223|7.7.0.0|",
				"adminDistrict": "ON",
				"adminDistrict2": "Muskoka",
				"countryRegion": "Canada",
				"formattedAddress": "Bala, P0C 1A0, Canada",
				"locality": "Bala",
				"postalCode": "P0C 1A0"
			},
			"geometry": {
				"type": "Point",
				"coordinates": [
					-79.6146011352539,
					45.0164413452148
				]
			},
			"bbox": [
				-79.6218863449288,
				45.0125786276442,
				-79.6073159255791,
				45.0203040627855
			]
		}
	]
}
