{
	"type": "FeatureCollection",
	"features": [
		{
			"type": "Feature",
			"properties": {
				"confidence": 9,
				"authenticationResultCode": "ValidCredentials",
				"brandLogoUri": "http://dev.virtualearth.net/Branding/logo_powered_by.png",
				"copyright": "Copyright © 2017 Microsoft and its suppliers. All rights reserved. This API cannot be accessed and the content and any results may not be used, reproduced or transmitted in any manner without express written permission from Microsoft Corporation.",
				"entityType": "Address",
				"matchCodes": [
					"Good"
				],
				"name": "1100 Shoppers Row, Campbell River, BC V9W 2C8, Canada",
				"statusCode": 200,
				"statusDescription": "OK",
				"traceId": "90a4c52f9f344a0287ca6ff73f6eea92|BN20130423|7.7.0.0|",
				"addressLine": "1100 Shoppers Row",
				"adminDistrict": "BC",
				"adminDistrict2": "Strathcona",
				"countryRegion": "Canada",
				"formattedAddress": "1100 Shoppers Row, Campbell River, BC V9W 2C8, Canada",
				"locality": "Campbell River",
				"postalCode": "V9W 2C8"
			},
			"geometry": {
				"type": "Point",
				"coordinates": [
					-125.24581,
					50.0264499
				]
			},
			"bbox": [
				-125.2475598,
				50.0253257,
				-125.2440602,
				50.0275741
			]
		}
	]
}
