{
	"type": "FeatureCollection",
	"features": [
		{
			"type": "Feature",
			"properties": {
				"confidence": 9,
				"authenticationResultCode": "ValidCredentials",
				"brandLogoUri": "http://dev.virtualearth.net/Branding/logo_powered_by.png",
				"copyright": "Copyright © 2017 Microsoft and its suppliers. All rights reserved. This API cannot be accessed and the content and any results may not be used, reproduced or transmitted in any manner without express written permission from Microsoft Corporation.",
				"entityType": "Address",
				"matchCodes": [
					"Good"
				],
				"name": "1105 Rue Bersimis, Chicoutimi, QC G7K 1A4, Canada",
				"statusCode": 200,
				"statusDescription": "OK",
				"traceId": "588027dc767f4b04827b242eb8fba342|BN20130422|7.7.0.0|",
				"addressLine": "1105 Rue Bersimis",
				"adminDistrict": "QC",
				"adminDistrict2": "Saguenay",
				"countryRegion": "Canada",
				"formattedAddress": "1105 Rue Bersimis, Chicoutimi, QC G7K 1A4, Canada",
				"locality": "Saguenay",
				"neighborhood": "Chicoutimi",
				"postalCode": "G7K 1A4"
			},
			"geometry": {
				"type": "Point",
				"coordinates": [
					-71.10839,
					48.3950699
				]
			},
			"bbox": [
				-71.110083,
				48.3939457,
				-71.106697,
				48.3961941
			]
		}
	]
}
