{
	"type": "FeatureCollection",
	"features": [
		{
			"type": "Feature",
			"properties": {
				"confidence": 9,
				"authenticationResultCode": "ValidCredentials",
				"brandLogoUri": "http://dev.virtualearth.net/Branding/logo_powered_by.png",
				"copyright": "Copyright © 2017 Microsoft and its suppliers. All rights reserved. This API cannot be accessed and the content and any results may not be used, reproduced or transmitted in any manner without express written permission from Microsoft Corporation.",
				"entityType": "Address",
				"matchCodes": [
					"Good"
				],
				"name": "1106 Orr Dr, Port Coquitlam, BC V3C 6H2, Canada",
				"statusCode": 200,
				"statusDescription": "OK",
				"traceId": "c6df2bb74fe84b3a86a7fb6fd21213a5|BN20130521|7.7.0.0|",
				"addressLine": "1106 Orr Dr",
				"adminDistrict": "BC",
				"adminDistrict2": "Greater Vancouver",
				"countryRegion": "Canada",
				"formattedAddress": "1106 Orr Dr, Port Coquitlam, BC V3C 6H2, Canada",
				"locality": "Port Coquitlam",
				"postalCode": "V3C 6H2"
			},
			"geometry": {
				"type": "Point",
				"coordinates": [
					-122.79268,
					49.23283
				]
			},
			"bbox": [
				-122.7944016,
				49.2317058,
				-122.7909584,
				49.2339542
			]
		}
	]
}
