{
	"type": "FeatureCollection",
	"features": [
		{
			"type": "Feature",
			"properties": {
				"confidence": 10,
				"authenticationResultCode": "ValidCredentials",
				"brandLogoUri": "http://dev.virtualearth.net/Branding/logo_powered_by.png",
				"copyright": "Copyright © 2017 Microsoft and its suppliers. All rights reserved. This API cannot be accessed and the content and any results may not be used, reproduced or transmitted in any manner without express written permission from Microsoft Corporation.",
				"entityType": "RoadBlock",
				"matchCodes": [
					"UpHierarchy"
				],
				"name": "Middle Bench Rd, Keremeos, BC V0X 1N2, Canada",
				"statusCode": 200,
				"statusDescription": "OK",
				"traceId": "1137cdaeb8064cc3a055f17546ef2a83|BN20121762|7.7.0.0|",
				"addressLine": "Middle Bench Rd",
				"adminDistrict": "BC",
				"adminDistrict2": "Okanagan-Similkameen",
				"countryRegion": "Canada",
				"formattedAddress": "Middle Bench Rd, Keremeos, BC V0X 1N2, Canada",
				"locality": "Keremeos",
				"postalCode": "V0X 1N2"
			},
			"geometry": {
				"type": "Point",
				"coordinates": [
					-119.81386,
					49.210475
				]
			},
			"bbox": [
				-119.8151,
				49.21047,
				-119.81262,
				49.2104799
			]
		}
	]
}
