{
	"type": "FeatureCollection",
	"features": [
		{
			"type": "Feature",
			"properties": {
				"confidence": 9,
				"authenticationResultCode": "ValidCredentials",
				"brandLogoUri": "http://dev.virtualearth.net/Branding/logo_powered_by.png",
				"copyright": "Copyright © 2017 Microsoft and its suppliers. All rights reserved. This API cannot be accessed and the content and any results may not be used, reproduced or transmitted in any manner without express written permission from Microsoft Corporation.",
				"entityType": "Address",
				"matchCodes": [
					"Good"
				],
				"name": "1110 Birchmount Rd, Scarborough, ON M1K 5G7, Canada",
				"statusCode": 200,
				"statusDescription": "OK",
				"traceId": "811328516dbf471987965bd3c6e20ce2|BN20320521|7.7.0.0|",
				"addressLine": "1110 Birchmount Rd",
				"adminDistrict": "ON",
				"adminDistrict2": "Toronto",
				"countryRegion": "Canada",
				"formattedAddress": "1110 Birchmount Rd, Scarborough, ON M1K 5G7, Canada",
				"locality": "Toronto",
				"neighborhood": "Wexford-Maryvale",
				"postalCode": "M1K 5G7"
			},
			"geometry": {
				"type": "Point",
				"coordinates": [
					-79.28063,
					43.7363799
				]
			},
			"bbox": [
				-79.2821859,
				43.7352557,
				-79.2790741,
				43.7375041
			]
		}
	]
}
