{
	"type": "FeatureCollection",
	"features": [
		{
			"type": "Feature",
			"properties": {
				"confidence": 9,
				"authenticationResultCode": "ValidCredentials",
				"brandLogoUri": "http://dev.virtualearth.net/Branding/logo_powered_by.png",
				"copyright": "Copyright © 2017 Microsoft and its suppliers. All rights reserved. This API cannot be accessed and the content and any results may not be used, reproduced or transmitted in any manner without express written permission from Microsoft Corporation.",
				"entityType": "Address",
				"matchCodes": [
					"Good"
				],
				"name": "1120 Ave E N, Saskatoon, SK S7L 1T1, Canada",
				"statusCode": 200,
				"statusDescription": "OK",
				"traceId": "f8c5c071ca164427a86260cb6149bfaf|BN20130431|7.7.0.0|",
				"addressLine": "1120 Ave E N",
				"adminDistrict": "SK",
				"adminDistrict2": "Saskatchewan",
				"countryRegion": "Canada",
				"formattedAddress": "1120 Ave E N, Saskatoon, SK S7L 1T1, Canada",
				"locality": "Saskatoon",
				"neighborhood": "Caswell Hill",
				"postalCode": "S7L 1T1"
			},
			"geometry": {
				"type": "Point",
				"coordinates": [
					-106.67627,
					52.14287
				]
			},
			"bbox": [
				-106.6781018,
				52.1417458,
				-106.6744382,
				52.1439942
			]
		}
	]
}
