{
	"type": "FeatureCollection",
	"features": [
		{
			"type": "Feature",
			"properties": {
				"confidence": 9,
				"authenticationResultCode": "ValidCredentials",
				"brandLogoUri": "http://dev.virtualearth.net/Branding/logo_powered_by.png",
				"copyright": "Copyright © 2017 Microsoft and its suppliers. All rights reserved. This API cannot be accessed and the content and any results may not be used, reproduced or transmitted in any manner without express written permission from Microsoft Corporation.",
				"entityType": "Address",
				"matchCodes": [
					"Good"
				],
				"name": "1120 68 Ave NE, Calgary, AB T2E 8S5, Canada",
				"statusCode": 200,
				"statusDescription": "OK",
				"traceId": "d2a55930e8024def834e5b0979f7f5c5|BN20130533|7.7.0.0|",
				"addressLine": "1120 68 Ave NE",
				"adminDistrict": "AB",
				"adminDistrict2": "Alberta",
				"countryRegion": "Canada",
				"formattedAddress": "1120 68 Ave NE, Calgary, AB T2E 8S5, Canada",
				"locality": "Calgary",
				"postalCode": "T2E 8S5"
			},
			"geometry": {
				"type": "Point",
				"coordinates": [
					-114.038,
					51.11593
				]
			},
			"bbox": [
				-114.0397908,
				51.1148058,
				-114.0362092,
				51.1170542
			]
		}
	]
}
