{
	"type": "FeatureCollection",
	"features": [
		{
			"type": "Feature",
			"properties": {
				"confidence": 9,
				"authenticationResultCode": "ValidCredentials",
				"brandLogoUri": "http://dev.virtualearth.net/Branding/logo_powered_by.png",
				"copyright": "Copyright © 2017 Microsoft and its suppliers. All rights reserved. This API cannot be accessed and the content and any results may not be used, reproduced or transmitted in any manner without express written permission from Microsoft Corporation.",
				"entityType": "Address",
				"matchCodes": [
					"Good"
				],
				"name": "11226 100 Ave, Grande Prairie, AB T8V 7L2, Canada",
				"statusCode": 200,
				"statusDescription": "OK",
				"traceId": "18121c04c6ed4d97a0e5c639f2a4934a|BN20130719|7.7.0.0|",
				"addressLine": "11226 100 Ave",
				"adminDistrict": "AB",
				"adminDistrict2": "Alberta",
				"countryRegion": "Canada",
				"formattedAddress": "11226 100 Ave, Grande Prairie, AB T8V 7L2, Canada",
				"locality": "Grande Prairie",
				"neighborhood": "Westgate",
				"postalCode": "T8V 7L2"
			},
			"geometry": {
				"type": "Point",
				"coordinates": [
					-118.83637,
					55.17079
				]
			},
			"bbox": [
				-118.8383383,
				55.1696658,
				-118.8344017,
				55.1719142
			]
		}
	]
}
