{
	"type": "FeatureCollection",
	"features": [
		{
			"type": "Feature",
			"properties": {
				"confidence": 9,
				"authenticationResultCode": "ValidCredentials",
				"brandLogoUri": "http://dev.virtualearth.net/Branding/logo_powered_by.png",
				"copyright": "Copyright © 2017 Microsoft and its suppliers. All rights reserved. This API cannot be accessed and the content and any results may not be used, reproduced or transmitted in any manner without express written permission from Microsoft Corporation.",
				"entityType": "Address",
				"matchCodes": [
					"Good"
				],
				"name": "1122 Wilson St W, Ancaster, ON L9G 3K9, Canada",
				"statusCode": 200,
				"statusDescription": "OK",
				"traceId": "6267ddfc6cfc43dbb4fd1dfb4b69b665|BN20210145|7.7.0.0|",
				"addressLine": "1122 Wilson St W",
				"adminDistrict": "ON",
				"adminDistrict2": "Hamilton",
				"countryRegion": "Canada",
				"formattedAddress": "1122 Wilson St W, Ancaster, ON L9G 3K9, Canada",
				"locality": "Hamilton",
				"neighborhood": "Ancaster",
				"postalCode": "L9G 3K9"
			},
			"geometry": {
				"type": "Point",
				"coordinates": [
					-80.01732,
					43.19848
				]
			},
			"bbox": [
				-80.0188621,
				43.1973558,
				-80.0157779,
				43.1996042
			]
		}
	]
}
