{
	"type": "FeatureCollection",
	"features": [
		{
			"type": "Feature",
			"properties": {
				"confidence": 9,
				"authenticationResultCode": "ValidCredentials",
				"brandLogoUri": "http://dev.virtualearth.net/Branding/logo_powered_by.png",
				"copyright": "Copyright © 2017 Microsoft and its suppliers. All rights reserved. This API cannot be accessed and the content and any results may not be used, reproduced or transmitted in any manner without express written permission from Microsoft Corporation.",
				"entityType": "Address",
				"matchCodes": [
					"Good"
				],
				"name": "1123 Wagon Rd, Cariboo, BC V0L, Canada",
				"statusCode": 200,
				"statusDescription": "OK",
				"traceId": "4b8423e1612f4683afe2b08d4f58082b|BN20260231|7.7.0.0|",
				"addressLine": "1123 Wagon Rd",
				"adminDistrict": "BC",
				"adminDistrict2": "Cariboo",
				"countryRegion": "Canada",
				"formattedAddress": "1123 Wagon Rd, Cariboo, BC V0L, Canada",
				"locality": "Cariboo",
				"neighborhood": "Alkali Lake",
				"postalCode": "V0L 1B0"
			},
			"geometry": {
				"type": "Point",
				"coordinates": [
					-122.2203215,
					51.7896096
				]
			},
			"bbox": [
				-122.2221389,
				51.7884854,
				-122.2185041,
				51.7907337
			]
		}
	]
}
