{
	"type": "FeatureCollection",
	"features": [
		{
			"type": "Feature",
			"properties": {
				"confidence": 9,
				"authenticationResultCode": "ValidCredentials",
				"brandLogoUri": "http://dev.virtualearth.net/Branding/logo_powered_by.png",
				"copyright": "Copyright © 2017 Microsoft and its suppliers. All rights reserved. This API cannot be accessed and the content and any results may not be used, reproduced or transmitted in any manner without express written permission from Microsoft Corporation.",
				"entityType": "Address",
				"matchCodes": [
					"Good"
				],
				"name": "1123 Bellevue Ave SE, Calgary, AB T2G 4L2, Canada",
				"statusCode": 200,
				"statusDescription": "OK",
				"traceId": "b9605c107d594d0dbc74e3a0294ea357|BN20130634|7.7.0.0|",
				"addressLine": "1123 Bellevue Ave SE",
				"adminDistrict": "AB",
				"adminDistrict2": "Alberta",
				"countryRegion": "Canada",
				"formattedAddress": "1123 Bellevue Ave SE, Calgary, AB T2G 4L2, Canada",
				"locality": "Calgary",
				"neighborhood": "Ramsay",
				"postalCode": "T2G 4L2"
			},
			"geometry": {
				"type": "Point",
				"coordinates": [
					-114.04421,
					51.03923
				]
			},
			"bbox": [
				-114.0459978,
				51.0381058,
				-114.0424222,
				51.0403542
			]
		}
	]
}
