{
	"type": "FeatureCollection",
	"features": [
		{
			"type": "Feature",
			"properties": {
				"confidence": 9,
				"authenticationResultCode": "ValidCredentials",
				"brandLogoUri": "http://dev.virtualearth.net/Branding/logo_powered_by.png",
				"copyright": "Copyright © 2017 Microsoft and its suppliers. All rights reserved. This API cannot be accessed and the content and any results may not be used, reproduced or transmitted in any manner without express written permission from Microsoft Corporation.",
				"entityType": "Address",
				"matchCodes": [
					"Good"
				],
				"name": "1125 Rue de Cherbourg, Sherbrooke, QC J1K 0A8, Canada",
				"statusCode": 200,
				"statusDescription": "OK",
				"traceId": "b9e207f79c9f4c9ebc779e12b15493d9|BN20130625|7.7.0.0|",
				"addressLine": "1125 Rue de Cherbourg",
				"adminDistrict": "QC",
				"adminDistrict2": "Sherbrooke",
				"countryRegion": "Canada",
				"formattedAddress": "1125 Rue de Cherbourg, Sherbrooke, QC J1K 0A8, Canada",
				"locality": "Sherbrooke",
				"postalCode": "J1K 0A8"
			},
			"geometry": {
				"type": "Point",
				"coordinates": [
					-71.92545,
					45.38901
				]
			},
			"bbox": [
				-71.9270507,
				45.3878858,
				-71.9238493,
				45.3901342
			]
		}
	]
}
