{
	"type": "FeatureCollection",
	"features": [
		{
			"type": "Feature",
			"properties": {
				"confidence": 9,
				"authenticationResultCode": "ValidCredentials",
				"brandLogoUri": "http://dev.virtualearth.net/Branding/logo_powered_by.png",
				"copyright": "Copyright © 2017 Microsoft and its suppliers. All rights reserved. This API cannot be accessed and the content and any results may not be used, reproduced or transmitted in any manner without express written permission from Microsoft Corporation.",
				"entityType": "Address",
				"matchCodes": [
					"Good"
				],
				"name": "11266 89 Ave, Grande Prairie, AB T8V 5V8, Canada",
				"statusCode": 200,
				"statusDescription": "OK",
				"traceId": "ddb53a1c2d2d47ffa24e48233b13cee9|BN20130625|7.7.0.0|",
				"addressLine": "11266 89 Ave",
				"adminDistrict": "AB",
				"adminDistrict2": "Alberta",
				"countryRegion": "Canada",
				"formattedAddress": "11266 89 Ave, Grande Prairie, AB T8V 5V8, Canada",
				"locality": "Grande Prairie",
				"neighborhood": "Richmond Industrial Park",
				"postalCode": "T8V 5V8"
			},
			"geometry": {
				"type": "Point",
				"coordinates": [
					-118.83759,
					55.16005
				]
			},
			"bbox": [
				-118.8395578,
				55.1589258,
				-118.8356222,
				55.1611742
			]
		}
	]
}
