{
	"type": "FeatureCollection",
	"features": [
		{
			"type": "Feature",
			"properties": {
				"confidence": 9,
				"authenticationResultCode": "ValidCredentials",
				"brandLogoUri": "http://dev.virtualearth.net/Branding/logo_powered_by.png",
				"copyright": "Copyright © 2017 Microsoft and its suppliers. All rights reserved. This API cannot be accessed and the content and any results may not be used, reproduced or transmitted in any manner without express written permission from Microsoft Corporation.",
				"entityType": "Address",
				"matchCodes": [
					"Good"
				],
				"name": "1126 Richter St, Kelowna, BC V1Y 2K7, Canada",
				"statusCode": 200,
				"statusDescription": "OK",
				"traceId": "1a54e60816b546258d4a814cdbcaa6d2|BN20171457|7.7.0.0|",
				"addressLine": "1126 Richter St",
				"adminDistrict": "BC",
				"adminDistrict2": "Central Okanagan",
				"countryRegion": "Canada",
				"formattedAddress": "1126 Richter St, Kelowna, BC V1Y 2K7, Canada",
				"locality": "Kelowna",
				"neighborhood": "North End",
				"postalCode": "V1Y 2K7"
			},
			"geometry": {
				"type": "Point",
				"coordinates": [
					-119.4889,
					49.89519
				]
			},
			"bbox": [
				-119.4906451,
				49.8940658,
				-119.4871549,
				49.8963142
			]
		}
	]
}
