{
	"type": "FeatureCollection",
	"features": [
		{
			"type": "Feature",
			"properties": {
				"confidence": 9,
				"authenticationResultCode": "ValidCredentials",
				"brandLogoUri": "http://dev.virtualearth.net/Branding/logo_powered_by.png",
				"copyright": "Copyright © 2017 Microsoft and its suppliers. All rights reserved. This API cannot be accessed and the content and any results may not be used, reproduced or transmitted in any manner without express written permission from Microsoft Corporation.",
				"entityType": "Address",
				"matchCodes": [
					"Good"
				],
				"name": "11301 HWY-62, Madoc, ON K0K 2K0, Canada",
				"statusCode": 200,
				"statusDescription": "OK",
				"traceId": "017be6d4003d48548f13cb10458b49eb|BN20121762|7.7.0.0|",
				"addressLine": "11301 HWY-62",
				"adminDistrict": "ON",
				"adminDistrict2": "Hastings",
				"countryRegion": "Canada",
				"formattedAddress": "11301 HWY-62, Madoc, ON K0K 2K0, Canada",
				"locality": "Centre Hastings",
				"neighborhood": "Madoc",
				"postalCode": "K0K 2K0"
			},
			"geometry": {
				"type": "Point",
				"coordinates": [
					-77.4720239,
					44.3920716
				]
			},
			"bbox": [
				-77.473597,
				44.3909475,
				-77.4704507,
				44.3931958
			]
		}
	]
}
