{
	"type": "FeatureCollection",
	"features": [
		{
			"type": "Feature",
			"properties": {
				"confidence": 9,
				"authenticationResultCode": "ValidCredentials",
				"brandLogoUri": "http://dev.virtualearth.net/Branding/logo_powered_by.png",
				"copyright": "Copyright © 2017 Microsoft and its suppliers. All rights reserved. This API cannot be accessed and the content and any results may not be used, reproduced or transmitted in any manner without express written permission from Microsoft Corporation.",
				"entityType": "Address",
				"matchCodes": [
					"Good"
				],
				"name": "1130 Wall St, Winnipeg, MB R3E 2R9, Canada",
				"statusCode": 200,
				"statusDescription": "OK",
				"traceId": "3f5aea023b564e4fab5b73c882934375|BN20130423|7.7.0.0|",
				"addressLine": "1130 Wall St",
				"adminDistrict": "MB",
				"adminDistrict2": "Manitoba",
				"countryRegion": "Canada",
				"formattedAddress": "1130 Wall St, Winnipeg, MB R3E 2R9, Canada",
				"locality": "Winnipeg",
				"neighborhood": "Sargent Park",
				"postalCode": "R3E 2R9"
			},
			"geometry": {
				"type": "Point",
				"coordinates": [
					-97.1822399,
					49.89941
				]
			},
			"bbox": [
				-97.1839851,
				49.8982858,
				-97.1804947,
				49.9005342
			]
		}
	]
}
