{
	"type": "FeatureCollection",
	"features": [
		{
			"type": "Feature",
			"properties": {
				"confidence": 7,
				"authenticationResultCode": "ValidCredentials",
				"brandLogoUri": "http://dev.virtualearth.net/Branding/logo_powered_by.png",
				"copyright": "Copyright © 2017 Microsoft and its suppliers. All rights reserved. This API cannot be accessed and the content and any results may not be used, reproduced or transmitted in any manner without express written permission from Microsoft Corporation.",
				"entityType": "Postcode1",
				"matchCodes": [
					"Ambiguous",
					"UpHierarchy"
				],
				"name": "Powell River, V8A 0N5, Canada",
				"statusCode": 200,
				"statusDescription": "OK",
				"traceId": "3146edec8b5f4b9c8a9d9030d06471d5|BN20171457|7.7.0.0|",
				"adminDistrict": "BC",
				"adminDistrict2": "Powell River",
				"countryRegion": "Canada",
				"formattedAddress": "Powell River, V8A 0N5, Canada",
				"locality": "Powell River",
				"postalCode": "V8A 0N5"
			},
			"geometry": {
				"type": "Point",
				"coordinates": [
					-124.57494354248,
					49.8931007385254
				]
			},
			"bbox": [
				-124.58293756941,
				49.8892380209547,
				-124.566949515551,
				49.8969634560961
			]
		}
	]
}
