{
	"type": "FeatureCollection",
	"features": [
		{
			"type": "Feature",
			"properties": {
				"confidence": 9,
				"authenticationResultCode": "ValidCredentials",
				"brandLogoUri": "http://dev.virtualearth.net/Branding/logo_powered_by.png",
				"copyright": "Copyright © 2017 Microsoft and its suppliers. All rights reserved. This API cannot be accessed and the content and any results may not be used, reproduced or transmitted in any manner without express written permission from Microsoft Corporation.",
				"entityType": "Address",
				"matchCodes": [
					"Good"
				],
				"name": "1136 Lorimar Dr, Mississauga, ON L5S 1R8, Canada",
				"statusCode": 200,
				"statusDescription": "OK",
				"traceId": "d3a0edaec0af406298bef3404afe9186|BN20190642|7.7.0.0|",
				"addressLine": "1136 Lorimar Dr",
				"adminDistrict": "ON",
				"adminDistrict2": "Peel",
				"countryRegion": "Canada",
				"formattedAddress": "1136 Lorimar Dr, Mississauga, ON L5S 1R8, Canada",
				"locality": "Mississauga",
				"postalCode": "L5S 1R8"
			},
			"geometry": {
				"type": "Point",
				"coordinates": [
					-79.68274,
					43.66926
				]
			},
			"bbox": [
				-79.6842941,
				43.6681358,
				-79.6811859,
				43.6703842
			]
		}
	]
}
