{
	"type": "FeatureCollection",
	"features": [
		{
			"type": "Feature",
			"properties": {
				"confidence": 9,
				"authenticationResultCode": "ValidCredentials",
				"brandLogoUri": "http://dev.virtualearth.net/Branding/logo_powered_by.png",
				"copyright": "Copyright © 2017 Microsoft and its suppliers. All rights reserved. This API cannot be accessed and the content and any results may not be used, reproduced or transmitted in any manner without express written permission from Microsoft Corporation.",
				"entityType": "Address",
				"matchCodes": [
					"Good"
				],
				"name": "1138 E 61st Ave, Vancouver, BC V5X 2C6, Canada",
				"statusCode": 200,
				"statusDescription": "OK",
				"traceId": "0fe327778cfe4f0e987d2b1245f4477c|BN20130721|7.7.0.0|",
				"addressLine": "1138 E 61st Ave",
				"adminDistrict": "BC",
				"adminDistrict2": "Greater Vancouver",
				"countryRegion": "Canada",
				"formattedAddress": "1138 E 61st Ave, Vancouver, BC V5X 2C6, Canada",
				"locality": "Vancouver",
				"neighborhood": "Sunset",
				"postalCode": "V5X 2C6"
			},
			"geometry": {
				"type": "Point",
				"coordinates": [
					-123.08241,
					49.21443
				]
			},
			"bbox": [
				-123.0841309,
				49.2133058,
				-123.0806891,
				49.2155542
			]
		}
	]
}
