{
	"type": "FeatureCollection",
	"features": [
		{
			"type": "Feature",
			"properties": {
				"confidence": 9,
				"authenticationResultCode": "ValidCredentials",
				"brandLogoUri": "http://dev.virtualearth.net/Branding/logo_powered_by.png",
				"copyright": "Copyright © 2017 Microsoft and its suppliers. All rights reserved. This API cannot be accessed and the content and any results may not be used, reproduced or transmitted in any manner without express written permission from Microsoft Corporation.",
				"entityType": "Address",
				"matchCodes": [
					"Good"
				],
				"name": "1139 Carp Rd, Stittsville, ON K2S 1B9, Canada",
				"statusCode": 200,
				"statusDescription": "OK",
				"traceId": "96448930093e4ef7bc4a8ac030dfd236|BN20300154|7.7.0.0|",
				"addressLine": "1139 Carp Rd",
				"adminDistrict": "ON",
				"adminDistrict2": "Ottawa",
				"countryRegion": "Canada",
				"formattedAddress": "1139 Carp Rd, Stittsville, ON K2S 1B9, Canada",
				"locality": "Ottawa",
				"neighborhood": "Stittsville",
				"postalCode": "K2S 1B9"
			},
			"geometry": {
				"type": "Point",
				"coordinates": [
					-75.93974,
					45.2688
				]
			},
			"bbox": [
				-75.9413373,
				45.2676758,
				-75.9381427,
				45.2699242
			]
		}
	]
}
