{
	"type": "FeatureCollection",
	"features": [
		{
			"type": "Feature",
			"properties": {
				"confidence": 9,
				"authenticationResultCode": "ValidCredentials",
				"brandLogoUri": "http://dev.virtualearth.net/Branding/logo_powered_by.png",
				"copyright": "Copyright © 2017 Microsoft and its suppliers. All rights reserved. This API cannot be accessed and the content and any results may not be used, reproduced or transmitted in any manner without express written permission from Microsoft Corporation.",
				"entityType": "Address",
				"matchCodes": [
					"Good"
				],
				"name": "11419 98 Ave, Grande Prairie, AB T8V 5S5, Canada",
				"statusCode": 200,
				"statusDescription": "OK",
				"traceId": "a1f05a45f7b24c5bb5d14fd429e119d5|BN20190642|7.7.0.0|",
				"addressLine": "11419 98 Ave",
				"adminDistrict": "AB",
				"adminDistrict2": "Alberta",
				"countryRegion": "Canada",
				"formattedAddress": "11419 98 Ave, Grande Prairie, AB T8V 5S5, Canada",
				"locality": "Grande Prairie",
				"neighborhood": "Richmond Industrial Park",
				"postalCode": "T8V 5S5"
			},
			"geometry": {
				"type": "Point",
				"coordinates": [
					-118.83878,
					55.16832
				]
			},
			"bbox": [
				-118.8407482,
				55.1671958,
				-118.8368118,
				55.1694442
			]
		}
	]
}
