{
	"type": "FeatureCollection",
	"features": [
		{
			"type": "Feature",
			"properties": {
				"confidence": 9,
				"authenticationResultCode": "ValidCredentials",
				"brandLogoUri": "http://dev.virtualearth.net/Branding/logo_powered_by.png",
				"copyright": "Copyright © 2017 Microsoft and its suppliers. All rights reserved. This API cannot be accessed and the content and any results may not be used, reproduced or transmitted in any manner without express written permission from Microsoft Corporation.",
				"entityType": "Address",
				"matchCodes": [
					"Good"
				],
				"name": "11437 Railway Ave E, North Battleford, SK S9A 3G8, Canada",
				"statusCode": 200,
				"statusDescription": "OK",
				"traceId": "5fcd7e96d6874437a2553e3140c287f3|BN20200239|7.7.0.0|",
				"addressLine": "11437 Railway Ave E",
				"adminDistrict": "SK",
				"adminDistrict2": "Saskatchewan",
				"countryRegion": "Canada",
				"formattedAddress": "11437 Railway Ave E, North Battleford, SK S9A 3G8, Canada",
				"locality": "North Battleford",
				"postalCode": "S9A 3G8"
			},
			"geometry": {
				"type": "Point",
				"coordinates": [
					-108.2767479,
					52.7605687
				]
			},
			"bbox": [
				-108.2786056,
				52.7594445,
				-108.2748903,
				52.7616928
			]
		}
	]
}
