{
	"type": "FeatureCollection",
	"features": [
		{
			"type": "Feature",
			"properties": {
				"confidence": 9,
				"authenticationResultCode": "ValidCredentials",
				"brandLogoUri": "http://dev.virtualearth.net/Branding/logo_powered_by.png",
				"copyright": "Copyright © 2017 Microsoft and its suppliers. All rights reserved. This API cannot be accessed and the content and any results may not be used, reproduced or transmitted in any manner without express written permission from Microsoft Corporation.",
				"entityType": "Address",
				"matchCodes": [
					"Good"
				],
				"name": "115 Metcalfe St, Elora, ON N0B 1S0, Canada",
				"statusCode": 200,
				"statusDescription": "OK",
				"traceId": "693aead923d742e4852931e841746f25|BN20130721|7.7.0.0|",
				"addressLine": "115 Metcalfe St",
				"adminDistrict": "ON",
				"adminDistrict2": "Wellington",
				"countryRegion": "Canada",
				"formattedAddress": "115 Metcalfe St, Elora, ON N0B 1S0, Canada",
				"locality": "Centre Wellington",
				"neighborhood": "Elora",
				"postalCode": "N0B 1S0"
			},
			"geometry": {
				"type": "Point",
				"coordinates": [
					-80.4299588,
					43.6825221
				]
			},
			"bbox": [
				-80.4315132,
				43.681398,
				-80.4284043,
				43.6836463
			]
		}
	]
}
