{
	"type": "FeatureCollection",
	"features": [
		{
			"type": "Feature",
			"properties": {
				"confidence": 9,
				"authenticationResultCode": "ValidCredentials",
				"brandLogoUri": "http://dev.virtualearth.net/Branding/logo_powered_by.png",
				"copyright": "Copyright © 2017 Microsoft and its suppliers. All rights reserved. This API cannot be accessed and the content and any results may not be used, reproduced or transmitted in any manner without express written permission from Microsoft Corporation.",
				"entityType": "Address",
				"matchCodes": [
					"Good"
				],
				"name": "115 Rivalda Rd, North York, ON M9M 2M6, Canada",
				"statusCode": 200,
				"statusDescription": "OK",
				"traceId": "c667dd089e7440d88a0b71fe4fe3899e|BN20130532|7.7.0.0|",
				"addressLine": "115 Rivalda Rd",
				"adminDistrict": "ON",
				"adminDistrict2": "Toronto",
				"countryRegion": "Canada",
				"formattedAddress": "115 Rivalda Rd, North York, ON M9M 2M6, Canada",
				"locality": "Toronto",
				"neighborhood": "Humbermede",
				"postalCode": "M9M 2M6"
			},
			"geometry": {
				"type": "Point",
				"coordinates": [
					-79.53504,
					43.7434
				]
			},
			"bbox": [
				-79.536596,
				43.7422758,
				-79.533484,
				43.7445242
			]
		}
	]
}
