{
	"type": "FeatureCollection",
	"features": [
		{
			"type": "Feature",
			"properties": {
				"confidence": 9,
				"authenticationResultCode": "ValidCredentials",
				"brandLogoUri": "http://dev.virtualearth.net/Branding/logo_powered_by.png",
				"copyright": "Copyright © 2017 Microsoft and its suppliers. All rights reserved. This API cannot be accessed and the content and any results may not be used, reproduced or transmitted in any manner without express written permission from Microsoft Corporation.",
				"entityType": "Address",
				"matchCodes": [
					"Good"
				],
				"name": "116 Rue Desjardins, Beloeil, QC J3G 5Z5, Canada",
				"statusCode": 200,
				"statusDescription": "OK",
				"traceId": "dc9499a2bdf948ab815feb5e6b35bd71|BN20300154|7.7.0.0|",
				"addressLine": "116 Rue Desjardins",
				"adminDistrict": "QC",
				"adminDistrict2": "La Vallée-du-Richelieu",
				"countryRegion": "Canada",
				"formattedAddress": "116 Rue Desjardins, Beloeil, QC J3G 5Z5, Canada",
				"locality": "Beloeil",
				"postalCode": "J3G 5Z5"
			},
			"geometry": {
				"type": "Point",
				"coordinates": [
					-73.19825,
					45.58007
				]
			},
			"bbox": [
				-73.1998561,
				45.5789458,
				-73.1966439,
				45.5811942
			]
		}
	]
}
