{
	"type": "FeatureCollection",
	"features": [
		{
			"type": "Feature",
			"properties": {
				"confidence": 9,
				"authenticationResultCode": "ValidCredentials",
				"brandLogoUri": "http://dev.virtualearth.net/Branding/logo_powered_by.png",
				"copyright": "Copyright © 2017 Microsoft and its suppliers. All rights reserved. This API cannot be accessed and the content and any results may not be used, reproduced or transmitted in any manner without express written permission from Microsoft Corporation.",
				"entityType": "Address",
				"matchCodes": [
					"Good"
				],
				"name": "1162 Bev McLachlin Dr, Pincher Creek, AB T0K, Canada",
				"statusCode": 200,
				"statusDescription": "OK",
				"traceId": "fe97a62d8c514ee8bd2e309add838986|BN20130621|7.7.0.0|",
				"addressLine": "1162 Bev McLachlin Dr",
				"adminDistrict": "AB",
				"adminDistrict2": "Alberta",
				"countryRegion": "Canada",
				"formattedAddress": "1162 Bev McLachlin Dr, Pincher Creek, AB T0K, Canada",
				"locality": "Pincher Creek",
				"postalCode": "T0K 1W0"
			},
			"geometry": {
				"type": "Point",
				"coordinates": [
					-113.94566,
					49.4901
				]
			},
			"bbox": [
				-113.9473906,
				49.4889758,
				-113.9439294,
				49.4912242
			]
		}
	]
}
