{
	"type": "FeatureCollection",
	"features": [
		{
			"type": "Feature",
			"properties": {
				"confidence": 9,
				"authenticationResultCode": "ValidCredentials",
				"brandLogoUri": "http://dev.virtualearth.net/Branding/logo_powered_by.png",
				"copyright": "Copyright © 2017 Microsoft and its suppliers. All rights reserved. This API cannot be accessed and the content and any results may not be used, reproduced or transmitted in any manner without express written permission from Microsoft Corporation.",
				"entityType": "Address",
				"matchCodes": [
					"Good"
				],
				"name": "1163 Magnus Ave, Winnipeg, MB R2X 0N7, Canada",
				"statusCode": 200,
				"statusDescription": "OK",
				"traceId": "cca3875f06684bf49bb4098582d18693|BN20130442|7.7.0.0|",
				"addressLine": "1163 Magnus Ave",
				"adminDistrict": "MB",
				"adminDistrict2": "Manitoba",
				"countryRegion": "Canada",
				"formattedAddress": "1163 Magnus Ave, Winnipeg, MB R2X 0N7, Canada",
				"locality": "Winnipeg",
				"neighborhood": "Shaughnessy Park",
				"postalCode": "R2X 0N7"
			},
			"geometry": {
				"type": "Point",
				"coordinates": [
					-97.1709599,
					49.92685
				]
			},
			"bbox": [
				-97.1727061,
				49.9257258,
				-97.1692137,
				49.9279742
			]
		}
	]
}
