{
	"type": "FeatureCollection",
	"features": [
		{
			"type": "Feature",
			"properties": {
				"confidence": 9,
				"authenticationResultCode": "ValidCredentials",
				"brandLogoUri": "http://dev.virtualearth.net/Branding/logo_powered_by.png",
				"copyright": "Copyright © 2017 Microsoft and its suppliers. All rights reserved. This API cannot be accessed and the content and any results may not be used, reproduced or transmitted in any manner without express written permission from Microsoft Corporation.",
				"entityType": "Address",
				"matchCodes": [
					"Good"
				],
				"name": "1165 Kenaston St, Gloucester, ON K1B 3N9, Canada",
				"statusCode": 200,
				"statusDescription": "OK",
				"traceId": "f9cae1cfadbd4a0ab1fd3e66067a4d3f|BN20130422|7.7.0.0|",
				"addressLine": "1165 Kenaston St",
				"adminDistrict": "ON",
				"adminDistrict2": "Ottawa",
				"countryRegion": "Canada",
				"formattedAddress": "1165 Kenaston St, Gloucester, ON K1B 3N9, Canada",
				"locality": "Ottawa",
				"neighborhood": "Gloucester",
				"postalCode": "K1B 3N9"
			},
			"geometry": {
				"type": "Point",
				"coordinates": [
					-75.6252,
					45.41897
				]
			},
			"bbox": [
				-75.6268015,
				45.4178458,
				-75.6235985,
				45.4200942
			]
		}
	]
}
