{
	"type": "FeatureCollection",
	"features": [
		{
			"type": "Feature",
			"properties": {
				"confidence": 9,
				"authenticationResultCode": "ValidCredentials",
				"brandLogoUri": "http://dev.virtualearth.net/Branding/logo_powered_by.png",
				"copyright": "Copyright © 2017 Microsoft and its suppliers. All rights reserved. This API cannot be accessed and the content and any results may not be used, reproduced or transmitted in any manner without express written permission from Microsoft Corporation.",
				"entityType": "Address",
				"matchCodes": [
					"Good"
				],
				"name": "117 3rd Ave W, Melville, SK S0A, Canada",
				"statusCode": 200,
				"statusDescription": "OK",
				"traceId": "e63a3d84ee8c4a22ad0e7b174a1c6c88|BN20130620|7.7.0.0|",
				"addressLine": "117 3rd Ave W",
				"adminDistrict": "SK",
				"adminDistrict2": "Saskatchewan",
				"countryRegion": "Canada",
				"formattedAddress": "117 3rd Ave W, Melville, SK S0A, Canada",
				"locality": "Melville",
				"postalCode": "S0A 2P0"
			},
			"geometry": {
				"type": "Point",
				"coordinates": [
					-102.8084044,
					50.928992
				]
			},
			"bbox": [
				-102.810188,
				50.9278679,
				-102.8066208,
				50.9301162
			]
		}
	]
}
