{
	"type": "FeatureCollection",
	"features": [
		{
			"type": "Feature",
			"properties": {
				"confidence": 9,
				"authenticationResultCode": "ValidCredentials",
				"brandLogoUri": "http://dev.virtualearth.net/Branding/logo_powered_by.png",
				"copyright": "Copyright © 2017 Microsoft and its suppliers. All rights reserved. This API cannot be accessed and the content and any results may not be used, reproduced or transmitted in any manner without express written permission from Microsoft Corporation.",
				"entityType": "Address",
				"matchCodes": [
					"Good"
				],
				"name": "1170 Winnipeg St, Regina, SK S4R 1J6, Canada",
				"statusCode": 200,
				"statusDescription": "OK",
				"traceId": "8c71fa0410c74260b1df601b49fa9927|BN20130620|7.7.0.0|",
				"addressLine": "1170 Winnipeg St",
				"adminDistrict": "SK",
				"adminDistrict2": "Saskatchewan",
				"countryRegion": "Canada",
				"formattedAddress": "1170 Winnipeg St, Regina, SK S4R 1J6, Canada",
				"locality": "Regina",
				"neighborhood": "Eastview",
				"postalCode": "S4R 1J6"
			},
			"geometry": {
				"type": "Point",
				"coordinates": [
					-104.596,
					50.46016
				]
			},
			"bbox": [
				-104.5977658,
				50.4590358,
				-104.5942342,
				50.4612842
			]
		}
	]
}
