{
	"type": "FeatureCollection",
	"features": [
		{
			"type": "Feature",
			"properties": {
				"confidence": 9,
				"authenticationResultCode": "ValidCredentials",
				"brandLogoUri": "http://dev.virtualearth.net/Branding/logo_powered_by.png",
				"copyright": "Copyright © 2017 Microsoft and its suppliers. All rights reserved. This API cannot be accessed and the content and any results may not be used, reproduced or transmitted in any manner without express written permission from Microsoft Corporation.",
				"entityType": "Address",
				"matchCodes": [
					"Good"
				],
				"name": "1170 Birchmount Rd, Scarborough, ON M1K 5M1, Canada",
				"statusCode": 200,
				"statusDescription": "OK",
				"traceId": "7748375ecc2c47029efcf16014ea2bda|BN20130431|7.7.0.0|",
				"addressLine": "1170 Birchmount Rd",
				"adminDistrict": "ON",
				"adminDistrict2": "Toronto",
				"countryRegion": "Canada",
				"formattedAddress": "1170 Birchmount Rd, Scarborough, ON M1K 5M1, Canada",
				"locality": "Toronto",
				"neighborhood": "Wexford-Maryvale",
				"postalCode": "M1K 5M1"
			},
			"geometry": {
				"type": "Point",
				"coordinates": [
					-79.28397,
					43.74186
				]
			},
			"bbox": [
				-79.285526,
				43.7407358,
				-79.282414,
				43.7429842
			]
		}
	]
}
