{
	"type": "FeatureCollection",
	"features": [
		{
			"type": "Feature",
			"properties": {
				"confidence": 9,
				"authenticationResultCode": "ValidCredentials",
				"brandLogoUri": "http://dev.virtualearth.net/Branding/logo_powered_by.png",
				"copyright": "Copyright © 2017 Microsoft and its suppliers. All rights reserved. This API cannot be accessed and the content and any results may not be used, reproduced or transmitted in any manner without express written permission from Microsoft Corporation.",
				"entityType": "Address",
				"matchCodes": [
					"Good"
				],
				"name": "1175 Nicholson Rd, Newmarket, ON L3Y 9C3, Canada",
				"statusCode": 200,
				"statusDescription": "OK",
				"traceId": "3c49207238fa455e8bf665ea96d222a8|BN20290118|7.7.0.0|",
				"addressLine": "1175 Nicholson Rd",
				"adminDistrict": "ON",
				"adminDistrict2": "York",
				"countryRegion": "Canada",
				"formattedAddress": "1175 Nicholson Rd, Newmarket, ON L3Y 9C3, Canada",
				"locality": "Newmarket",
				"postalCode": "L3Y 9C3"
			},
			"geometry": {
				"type": "Point",
				"coordinates": [
					-79.42479,
					44.05621
				]
			},
			"bbox": [
				-79.4263542,
				44.0550858,
				-79.4232258,
				44.0573342
			]
		}
	]
}
