{
	"type": "FeatureCollection",
	"features": [
		{
			"type": "Feature",
			"properties": {
				"confidence": 9,
				"authenticationResultCode": "ValidCredentials",
				"brandLogoUri": "http://dev.virtualearth.net/Branding/logo_powered_by.png",
				"copyright": "Copyright © 2017 Microsoft and its suppliers. All rights reserved. This API cannot be accessed and the content and any results may not be used, reproduced or transmitted in any manner without express written permission from Microsoft Corporation.",
				"entityType": "Address",
				"matchCodes": [
					"Good"
				],
				"name": "118 King Ave W, Newcastle, ON L1B 1H7, Canada",
				"statusCode": 200,
				"statusDescription": "OK",
				"traceId": "e57597f727f84deca0ea062ee3a2a43c|BN20130521|7.7.0.0|",
				"addressLine": "118 King Ave W",
				"adminDistrict": "ON",
				"adminDistrict2": "Durham",
				"countryRegion": "Canada",
				"formattedAddress": "118 King Ave W, Newcastle, ON L1B 1H7, Canada",
				"locality": "Clarington",
				"neighborhood": "Newcastle",
				"postalCode": "L1B 1H7"
			},
			"geometry": {
				"type": "Point",
				"coordinates": [
					-78.5913,
					43.91714
				]
			},
			"bbox": [
				-78.5928606,
				43.9160158,
				-78.5897394,
				43.9182642
			]
		}
	]
}
