{
	"type": "FeatureCollection",
	"features": [
		{
			"type": "Feature",
			"properties": {
				"confidence": 9,
				"authenticationResultCode": "ValidCredentials",
				"brandLogoUri": "http://dev.virtualearth.net/Branding/logo_powered_by.png",
				"copyright": "Copyright © 2017 Microsoft and its suppliers. All rights reserved. This API cannot be accessed and the content and any results may not be used, reproduced or transmitted in any manner without express written permission from Microsoft Corporation.",
				"entityType": "Address",
				"matchCodes": [
					"Good"
				],
				"name": "118 Patton Rd, Upper Sackville, NS B4E 3B9, Canada",
				"statusCode": 200,
				"statusDescription": "OK",
				"traceId": "e5c83afb0a7a46819407b3e90c622007|BN20130442|7.7.0.0|",
				"addressLine": "118 Patton Rd",
				"adminDistrict": "NS",
				"adminDistrict2": "Halifax",
				"countryRegion": "Canada",
				"formattedAddress": "118 Patton Rd, Upper Sackville, NS B4E 3B9, Canada",
				"locality": "Halifax",
				"neighborhood": "Upper Sackville",
				"postalCode": "B4E 3B9"
			},
			"geometry": {
				"type": "Point",
				"coordinates": [
					-63.75554,
					44.80963
				]
			},
			"bbox": [
				-63.7571245,
				44.8085058,
				-63.7539555,
				44.8107542
			]
		}
	]
}
