{
	"type": "FeatureCollection",
	"features": [
		{
			"type": "Feature",
			"properties": {
				"confidence": 4,
				"authenticationResultCode": "ValidCredentials",
				"brandLogoUri": "http://dev.virtualearth.net/Branding/logo_powered_by.png",
				"copyright": "Copyright © 2017 Microsoft and its suppliers. All rights reserved. This API cannot be accessed and the content and any results may not be used, reproduced or transmitted in any manner without express written permission from Microsoft Corporation.",
				"entityType": "PopulatedPlace",
				"matchCodes": [
					"UpHierarchy"
				],
				"name": "Telegraph Creek, British Columbia, Canada",
				"statusCode": 200,
				"statusDescription": "OK",
				"traceId": "2002e5f0af374e90b0efe245de2c6c09|BN20320521|7.7.0.0|",
				"adminDistrict": "BC",
				"countryRegion": "Canada",
				"formattedAddress": "Telegraph Creek, British Columbia, Canada",
				"locality": "Telegraph Creek"
			},
			"geometry": {
				"type": "Point",
				"coordinates": [
					-131.151229858398,
					57.9096183776855
				]
			},
			"bbox": [
				-131.223880412789,
				57.880647994693,
				-131.078579304008,
				57.9385887606781
			]
		}
	]
}
