{
	"type": "FeatureCollection",
	"features": [
		{
			"type": "Feature",
			"properties": {
				"confidence": 9,
				"authenticationResultCode": "ValidCredentials",
				"brandLogoUri": "http://dev.virtualearth.net/Branding/logo_powered_by.png",
				"copyright": "Copyright © 2017 Microsoft and its suppliers. All rights reserved. This API cannot be accessed and the content and any results may not be used, reproduced or transmitted in any manner without express written permission from Microsoft Corporation.",
				"entityType": "Address",
				"matchCodes": [
					"Good"
				],
				"name": "11919 44 St SE, Calgary, AB T2Z 4G9, Canada",
				"statusCode": 200,
				"statusDescription": "OK",
				"traceId": "f94fe70bcd92414a80121225363faab1|BN20260223|7.7.0.0|",
				"addressLine": "11919 44 St SE",
				"adminDistrict": "AB",
				"adminDistrict2": "Alberta",
				"countryRegion": "Canada",
				"formattedAddress": "11919 44 St SE, Calgary, AB T2Z 4G9, Canada",
				"locality": "Calgary",
				"postalCode": "T2Z 4G9"
			},
			"geometry": {
				"type": "Point",
				"coordinates": [
					-113.9721,
					50.94433
				]
			},
			"bbox": [
				-113.9738842,
				50.9432058,
				-113.9703158,
				50.9454542
			]
		}
	]
}
