{
	"type": "FeatureCollection",
	"features": [
		{
			"type": "Feature",
			"properties": {
				"confidence": 9,
				"authenticationResultCode": "ValidCredentials",
				"brandLogoUri": "http://dev.virtualearth.net/Branding/logo_powered_by.png",
				"copyright": "Copyright © 2017 Microsoft and its suppliers. All rights reserved. This API cannot be accessed and the content and any results may not be used, reproduced or transmitted in any manner without express written permission from Microsoft Corporation.",
				"entityType": "Address",
				"matchCodes": [
					"Good"
				],
				"name": "12 Amber Rd, Cambridge, ON N1R 5K1, Canada",
				"statusCode": 200,
				"statusDescription": "OK",
				"traceId": "6c914bb292194ee19f81c699181eda86|BN20240253|7.7.0.0|",
				"addressLine": "12 Amber Rd",
				"adminDistrict": "ON",
				"adminDistrict2": "Waterloo",
				"countryRegion": "Canada",
				"formattedAddress": "12 Amber Rd, Cambridge, ON N1R 5K1, Canada",
				"locality": "Cambridge",
				"neighborhood": "East Galt",
				"postalCode": "N1R 5K1"
			},
			"geometry": {
				"type": "Point",
				"coordinates": [
					-80.29591,
					43.35762
				]
			},
			"bbox": [
				-80.2974561,
				43.3564958,
				-80.2943639,
				43.3587442
			]
		}
	]
}
