{
	"type": "FeatureCollection",
	"features": [
		{
			"type": "Feature",
			"properties": {
				"confidence": 9,
				"authenticationResultCode": "ValidCredentials",
				"brandLogoUri": "http://dev.virtualearth.net/Branding/logo_powered_by.png",
				"copyright": "Copyright © 2017 Microsoft and its suppliers. All rights reserved. This API cannot be accessed and the content and any results may not be used, reproduced or transmitted in any manner without express written permission from Microsoft Corporation.",
				"entityType": "Address",
				"matchCodes": [
					"Good"
				],
				"name": "12 Petersburg Cir, Port Colborne, ON L3K, Canada",
				"statusCode": 200,
				"statusDescription": "OK",
				"traceId": "e0b33eae8bfa49f29b84fbb56e24fa47|BN20121763|7.7.0.0|",
				"addressLine": "12 Petersburg Cir",
				"adminDistrict": "ON",
				"adminDistrict2": "Niagara",
				"countryRegion": "Canada",
				"formattedAddress": "12 Petersburg Cir, Port Colborne, ON L3K, Canada",
				"locality": "Port Colborne",
				"postalCode": "L3K 5V5"
			},
			"geometry": {
				"type": "Point",
				"coordinates": [
					-79.2594,
					42.91917
				]
			},
			"bbox": [
				-79.2609351,
				42.9180458,
				-79.2578649,
				42.9202942
			]
		}
	]
}
