{
	"type": "FeatureCollection",
	"features": [
		{
			"type": "Feature",
			"properties": {
				"confidence": 9,
				"authenticationResultCode": "ValidCredentials",
				"brandLogoUri": "http://dev.virtualearth.net/Branding/logo_powered_by.png",
				"copyright": "Copyright © 2017 Microsoft and its suppliers. All rights reserved. This API cannot be accessed and the content and any results may not be used, reproduced or transmitted in any manner without express written permission from Microsoft Corporation.",
				"entityType": "Address",
				"matchCodes": [
					"Good"
				],
				"name": "12 W Andison Clos, Cochrane, AB T4C 1J5, Canada",
				"statusCode": 200,
				"statusDescription": "OK",
				"traceId": "cc3afd10405b4b768739e25d2017ff04|BN20190642|7.7.0.0|",
				"addressLine": "12 W Andison Clos",
				"adminDistrict": "AB",
				"adminDistrict2": "Alberta",
				"countryRegion": "Canada",
				"formattedAddress": "12 W Andison Clos, Cochrane, AB T4C 1J5, Canada",
				"locality": "Cochrane",
				"postalCode": "T4C 1J5"
			},
			"geometry": {
				"type": "Point",
				"coordinates": [
					-114.49344,
					51.19264
				]
			},
			"bbox": [
				-114.4952338,
				51.1915158,
				-114.4916462,
				51.1937642
			]
		}
	]
}
