{
	"type": "FeatureCollection",
	"features": [
		{
			"type": "Feature",
			"properties": {
				"confidence": 9,
				"authenticationResultCode": "ValidCredentials",
				"brandLogoUri": "http://dev.virtualearth.net/Branding/logo_powered_by.png",
				"copyright": "Copyright © 2017 Microsoft and its suppliers. All rights reserved. This API cannot be accessed and the content and any results may not be used, reproduced or transmitted in any manner without express written permission from Microsoft Corporation.",
				"entityType": "Address",
				"matchCodes": [
					"Good"
				],
				"name": "120 General Manson Way, Miramichi, NB E1N 6K8, Canada",
				"statusCode": 200,
				"statusDescription": "OK",
				"traceId": "387344938d2b40d1b96f37cae9d6e720|BN20130423|7.7.0.0|",
				"addressLine": "120 General Manson Way",
				"adminDistrict": "NB",
				"adminDistrict2": "Northumberland",
				"countryRegion": "Canada",
				"formattedAddress": "120 General Manson Way, Miramichi, NB E1N 6K8, Canada",
				"locality": "Miramichi",
				"postalCode": "E1N 6K8"
			},
			"geometry": {
				"type": "Point",
				"coordinates": [
					-65.4453,
					47.01459
				]
			},
			"bbox": [
				-65.4469488,
				47.0134658,
				-65.4436512,
				47.0157142
			]
		}
	]
}
