{
	"type": "FeatureCollection",
	"features": [
		{
			"type": "Feature",
			"properties": {
				"confidence": 9,
				"authenticationResultCode": "ValidCredentials",
				"brandLogoUri": "http://dev.virtualearth.net/Branding/logo_powered_by.png",
				"copyright": "Copyright © 2017 Microsoft and its suppliers. All rights reserved. This API cannot be accessed and the content and any results may not be used, reproduced or transmitted in any manner without express written permission from Microsoft Corporation.",
				"entityType": "Address",
				"matchCodes": [
					"Good"
				],
				"name": "120 Troop Ave, Dartmouth, NS B3B 1Z1, Canada",
				"statusCode": 200,
				"statusDescription": "OK",
				"traceId": "62c34292b91f4e7a8535b94fc06a9356|BN20130632|7.7.0.0|",
				"addressLine": "120 Troop Ave",
				"adminDistrict": "NS",
				"adminDistrict2": "Halifax",
				"countryRegion": "Canada",
				"formattedAddress": "120 Troop Ave, Dartmouth, NS B3B 1Z1, Canada",
				"locality": "Halifax",
				"neighborhood": "Dartmouth",
				"postalCode": "B3B 1Z1"
			},
			"geometry": {
				"type": "Point",
				"coordinates": [
					-63.58473,
					44.70885
				]
			},
			"bbox": [
				-63.5863118,
				44.7077258,
				-63.5831482,
				44.7099742
			]
		}
	]
}
