{
	"type": "FeatureCollection",
	"features": [
		{
			"type": "Feature",
			"properties": {
				"confidence": 9,
				"authenticationResultCode": "ValidCredentials",
				"brandLogoUri": "http://dev.virtualearth.net/Branding/logo_powered_by.png",
				"copyright": "Copyright © 2017 Microsoft and its suppliers. All rights reserved. This API cannot be accessed and the content and any results may not be used, reproduced or transmitted in any manner without express written permission from Microsoft Corporation.",
				"entityType": "Address",
				"matchCodes": [
					"Good"
				],
				"name": "120 Hume St, Collingwood, ON L9Y 1V5, Canada",
				"statusCode": 200,
				"statusDescription": "OK",
				"traceId": "de171cf0f24c44689011d3f1bd215c76|BN20121763|7.7.0.0|",
				"addressLine": "120 Hume St",
				"adminDistrict": "ON",
				"adminDistrict2": "Simcoe",
				"countryRegion": "Canada",
				"formattedAddress": "120 Hume St, Collingwood, ON L9Y 1V5, Canada",
				"locality": "Collingwood",
				"postalCode": "L9Y 1V5"
			},
			"geometry": {
				"type": "Point",
				"coordinates": [
					-80.2122736,
					44.4960064
				]
			},
			"bbox": [
				-80.2138496,
				44.4948823,
				-80.2106976,
				44.4971306
			]
		}
	]
}
