{
	"type": "FeatureCollection",
	"features": [
		{
			"type": "Feature",
			"properties": {
				"confidence": 9,
				"authenticationResultCode": "ValidCredentials",
				"brandLogoUri": "http://dev.virtualearth.net/Branding/logo_powered_by.png",
				"copyright": "Copyright © 2017 Microsoft and its suppliers. All rights reserved. This API cannot be accessed and the content and any results may not be used, reproduced or transmitted in any manner without express written permission from Microsoft Corporation.",
				"entityType": "Address",
				"matchCodes": [
					"Good"
				],
				"name": "1200 26 Ave SE, Calgary, AB T2G 5S2, Canada",
				"statusCode": 200,
				"statusDescription": "OK",
				"traceId": "a1039f15e5b04c33ab1cc487f970f6b8|BN20130631|7.7.0.0|",
				"addressLine": "1200 26 Ave SE",
				"adminDistrict": "AB",
				"adminDistrict2": "Alberta",
				"countryRegion": "Canada",
				"formattedAddress": "1200 26 Ave SE, Calgary, AB T2G 5S2, Canada",
				"locality": "Calgary",
				"neighborhood": "Alyth-Bonnybrook-Manchester",
				"postalCode": "T2G 5S2"
			},
			"geometry": {
				"type": "Point",
				"coordinates": [
					-114.0365041,
					51.0307249
				]
			},
			"bbox": [
				-114.0382916,
				51.0296007,
				-114.0347167,
				51.031849
			]
		}
	]
}
