{
	"type": "FeatureCollection",
	"features": [
		{
			"type": "Feature",
			"properties": {
				"confidence": 9,
				"authenticationResultCode": "ValidCredentials",
				"brandLogoUri": "http://dev.virtualearth.net/Branding/logo_powered_by.png",
				"copyright": "Copyright © 2017 Microsoft and its suppliers. All rights reserved. This API cannot be accessed and the content and any results may not be used, reproduced or transmitted in any manner without express written permission from Microsoft Corporation.",
				"entityType": "Address",
				"matchCodes": [
					"Good"
				],
				"name": "1200 Brookdale Ave, Cornwall, ON K6J 4P4, Canada",
				"statusCode": 200,
				"statusDescription": "OK",
				"traceId": "78da60639b0c4a3faada8598e0402e2a|BN20130532|7.7.0.0|",
				"addressLine": "1200 Brookdale Ave",
				"adminDistrict": "ON",
				"adminDistrict2": "Stormont, Dundas and Glengarry",
				"countryRegion": "Canada",
				"formattedAddress": "1200 Brookdale Ave, Cornwall, ON K6J 4P4, Canada",
				"locality": "Cornwall",
				"postalCode": "K6J 4P4"
			},
			"geometry": {
				"type": "Point",
				"coordinates": [
					-74.75227,
					45.02715
				]
			},
			"bbox": [
				-74.7538605,
				45.0260258,
				-74.7506795,
				45.0282742
			]
		}
	]
}
