{
	"type": "FeatureCollection",
	"features": [
		{
			"type": "Feature",
			"properties": {
				"confidence": 9,
				"authenticationResultCode": "ValidCredentials",
				"brandLogoUri": "http://dev.virtualearth.net/Branding/logo_powered_by.png",
				"copyright": "Copyright © 2017 Microsoft and its suppliers. All rights reserved. This API cannot be accessed and the content and any results may not be used, reproduced or transmitted in any manner without express written permission from Microsoft Corporation.",
				"entityType": "Address",
				"matchCodes": [
					"Good"
				],
				"name": "1200 Place Nobel, Boucherville, QC J4B 5L2, Canada",
				"statusCode": 200,
				"statusDescription": "OK",
				"traceId": "d26160eeef7747dba59fc61db9838968|BN20130634|7.7.0.0|",
				"addressLine": "1200 Place Nobel",
				"adminDistrict": "QC",
				"adminDistrict2": "Longueuil",
				"countryRegion": "Canada",
				"formattedAddress": "1200 Place Nobel, Boucherville, QC J4B 5L2, Canada",
				"locality": "Boucherville",
				"postalCode": "J4B 5L2"
			},
			"geometry": {
				"type": "Point",
				"coordinates": [
					-73.44478,
					45.57049
				]
			},
			"bbox": [
				-73.4463859,
				45.5693658,
				-73.4431741,
				45.5716142
			]
		}
	]
}
