{
	"type": "FeatureCollection",
	"features": [
		{
			"type": "Feature",
			"properties": {
				"confidence": 9,
				"authenticationResultCode": "ValidCredentials",
				"brandLogoUri": "http://dev.virtualearth.net/Branding/logo_powered_by.png",
				"copyright": "Copyright © 2017 Microsoft and its suppliers. All rights reserved. This API cannot be accessed and the content and any results may not be used, reproduced or transmitted in any manner without express written permission from Microsoft Corporation.",
				"entityType": "Address",
				"matchCodes": [
					"Good"
				],
				"name": "1201 4 St, Nisku, AB T9E 7L3, Canada",
				"statusCode": 200,
				"statusDescription": "OK",
				"traceId": "daaa58aaf2d140daa889c91771589288|BN20130532|7.7.0.0|",
				"addressLine": "1201 4 St",
				"adminDistrict": "AB",
				"adminDistrict2": "Alberta",
				"countryRegion": "Canada",
				"formattedAddress": "1201 4 St, Nisku, AB T9E 7L3, Canada",
				"locality": "Leduc County",
				"neighborhood": "Nisku",
				"postalCode": "T9E 7L3"
			},
			"geometry": {
				"type": "Point",
				"coordinates": [
					-113.53598,
					53.31299
				]
			},
			"bbox": [
				-113.5378616,
				53.3118658,
				-113.5340984,
				53.3141142
			]
		}
	]
}
