{
	"type": "FeatureCollection",
	"features": [
		{
			"type": "Feature",
			"properties": {
				"confidence": 9,
				"authenticationResultCode": "ValidCredentials",
				"brandLogoUri": "http://dev.virtualearth.net/Branding/logo_powered_by.png",
				"copyright": "Copyright © 2017 Microsoft and its suppliers. All rights reserved. This API cannot be accessed and the content and any results may not be used, reproduced or transmitted in any manner without express written permission from Microsoft Corporation.",
				"entityType": "Address",
				"matchCodes": [
					"Good"
				],
				"name": "1209 Pinetree Way, Coquitlam, BC V3B 7Y3, Canada",
				"statusCode": 200,
				"statusDescription": "OK",
				"traceId": "07fb08317d854c188b2b5527fa22be39|BN20200239|7.7.0.0|",
				"addressLine": "1209 Pinetree Way",
				"adminDistrict": "BC",
				"adminDistrict2": "Greater Vancouver",
				"countryRegion": "Canada",
				"formattedAddress": "1209 Pinetree Way, Coquitlam, BC V3B 7Y3, Canada",
				"locality": "Coquitlam",
				"neighborhood": "Town Centre",
				"postalCode": "V3B 7Y3"
			},
			"geometry": {
				"type": "Point",
				"coordinates": [
					-122.7906,
					49.28569
				]
			},
			"bbox": [
				-122.7923234,
				49.2845658,
				-122.7888766,
				49.2868142
			]
		}
	]
}
