{
	"type": "FeatureCollection",
	"features": [
		{
			"type": "Feature",
			"properties": {
				"confidence": 9,
				"authenticationResultCode": "ValidCredentials",
				"brandLogoUri": "http://dev.virtualearth.net/Branding/logo_powered_by.png",
				"copyright": "Copyright © 2017 Microsoft and its suppliers. All rights reserved. This API cannot be accessed and the content and any results may not be used, reproduced or transmitted in any manner without express written permission from Microsoft Corporation.",
				"entityType": "Address",
				"matchCodes": [
					"Good"
				],
				"name": "121 Railside Rd, North York, ON M3A 1B2, Canada",
				"statusCode": 200,
				"statusDescription": "OK",
				"traceId": "3ce48b74a6ff4d9e9117e119d07a34e4|BN20130632|7.7.0.0|",
				"addressLine": "121 Railside Rd",
				"adminDistrict": "ON",
				"adminDistrict2": "Toronto",
				"countryRegion": "Canada",
				"formattedAddress": "121 Railside Rd, North York, ON M3A 1B2, Canada",
				"locality": "Toronto",
				"neighborhood": "Victoria Village",
				"postalCode": "M3A 1B2"
			},
			"geometry": {
				"type": "Point",
				"coordinates": [
					-79.32725,
					43.73548
				]
			},
			"bbox": [
				-79.3288058,
				43.7343558,
				-79.3256942,
				43.7366042
			]
		}
	]
}
