{
	"type": "FeatureCollection",
	"features": [
		{
			"type": "Feature",
			"properties": {
				"confidence": 9,
				"authenticationResultCode": "ValidCredentials",
				"brandLogoUri": "http://dev.virtualearth.net/Branding/logo_powered_by.png",
				"copyright": "Copyright © 2017 Microsoft and its suppliers. All rights reserved. This API cannot be accessed and the content and any results may not be used, reproduced or transmitted in any manner without express written permission from Microsoft Corporation.",
				"entityType": "Address",
				"matchCodes": [
					"Good"
				],
				"name": "121 Paddys Hill Dr, Saint John, NB E2M 0A9, Canada",
				"statusCode": 200,
				"statusDescription": "OK",
				"traceId": "31a639e40514424ea2074d68c79dcc10|BN20121764|7.7.0.0|",
				"addressLine": "121 Paddys Hill Dr",
				"adminDistrict": "NB",
				"adminDistrict2": "Saint John",
				"countryRegion": "Canada",
				"formattedAddress": "121 Paddys Hill Dr, Saint John, NB E2M 0A9, Canada",
				"locality": "Saint John",
				"postalCode": "E2M 0A9"
			},
			"geometry": {
				"type": "Point",
				"coordinates": [
					-66.1816599,
					45.20306
				]
			},
			"bbox": [
				-66.1832554,
				45.2019358,
				-66.1800644,
				45.2041842
			]
		}
	]
}
