{
	"type": "FeatureCollection",
	"features": [
		{
			"type": "Feature",
			"properties": {
				"confidence": 9,
				"authenticationResultCode": "ValidCredentials",
				"brandLogoUri": "http://dev.virtualearth.net/Branding/logo_powered_by.png",
				"copyright": "Copyright © 2017 Microsoft and its suppliers. All rights reserved. This API cannot be accessed and the content and any results may not be used, reproduced or transmitted in any manner without express written permission from Microsoft Corporation.",
				"entityType": "Address",
				"matchCodes": [
					"Good"
				],
				"name": "121 York St, Ottawa, ON K1N 5T4, Canada",
				"statusCode": 200,
				"statusDescription": "OK",
				"traceId": "8960cf6aba054f83b82793bd3530c22f|BN20190653|7.7.0.0|",
				"addressLine": "121 York St",
				"adminDistrict": "ON",
				"adminDistrict2": "Ottawa",
				"countryRegion": "Canada",
				"formattedAddress": "121 York St, Ottawa, ON K1N 5T4, Canada",
				"locality": "Ottawa",
				"neighborhood": "Byward Market-Parliament Hill",
				"postalCode": "K1N 5T4"
			},
			"geometry": {
				"type": "Point",
				"coordinates": [
					-75.6906,
					45.42951
				]
			},
			"bbox": [
				-75.6922018,
				45.4283858,
				-75.6889982,
				45.4306342
			]
		}
	]
}
