{
	"type": "FeatureCollection",
	"features": [
		{
			"type": "Feature",
			"properties": {
				"confidence": 9,
				"authenticationResultCode": "ValidCredentials",
				"brandLogoUri": "http://dev.virtualearth.net/Branding/logo_powered_by.png",
				"copyright": "Copyright © 2017 Microsoft and its suppliers. All rights reserved. This API cannot be accessed and the content and any results may not be used, reproduced or transmitted in any manner without express written permission from Microsoft Corporation.",
				"entityType": "Address",
				"matchCodes": [
					"Good"
				],
				"name": "1213 Hallecks Rd S, Brockville, ON K6V 5T3, Canada",
				"statusCode": 200,
				"statusDescription": "OK",
				"traceId": "258d57138e1741d4a9026ce82caf966f|BN20130532|7.7.0.0|",
				"addressLine": "1213 Hallecks Rd S",
				"adminDistrict": "ON",
				"adminDistrict2": "Leeds and Grenville",
				"countryRegion": "Canada",
				"formattedAddress": "1213 Hallecks Rd S, Brockville, ON K6V 5T3, Canada",
				"locality": "Elizabethtown-Kitley",
				"neighborhood": "Brockville",
				"postalCode": "K6V 5T3"
			},
			"geometry": {
				"type": "Point",
				"coordinates": [
					-75.75409,
					44.5465
				]
			},
			"bbox": [
				-75.7556674,
				44.5453758,
				-75.7525126,
				44.5476242
			]
		}
	]
}
