{
	"type": "FeatureCollection",
	"features": [
		{
			"type": "Feature",
			"properties": {
				"confidence": 9,
				"authenticationResultCode": "ValidCredentials",
				"brandLogoUri": "http://dev.virtualearth.net/Branding/logo_powered_by.png",
				"copyright": "Copyright © 2017 Microsoft and its suppliers. All rights reserved. This API cannot be accessed and the content and any results may not be used, reproduced or transmitted in any manner without express written permission from Microsoft Corporation.",
				"entityType": "Address",
				"matchCodes": [
					"Good"
				],
				"name": "12155 154 St NW, Edmonton, AB T5V 1J3, Canada",
				"statusCode": 200,
				"statusDescription": "OK",
				"traceId": "8b9068cd6d13419dad4506bf6c076364|BN20130625|7.7.0.0|",
				"addressLine": "12155 154 St NW",
				"adminDistrict": "AB",
				"adminDistrict2": "Alberta",
				"countryRegion": "Canada",
				"formattedAddress": "12155 154 St NW, Edmonton, AB T5V 1J3, Canada",
				"locality": "Edmonton",
				"neighborhood": "Mitchell Industrial",
				"postalCode": "T5V 1J3"
			},
			"geometry": {
				"type": "Point",
				"coordinates": [
					-113.5870051,
					53.5741935
				]
			},
			"bbox": [
				-113.5888983,
				53.5730693,
				-113.5851119,
				53.5753176
			]
		}
	]
}
