{
	"type": "FeatureCollection",
	"features": [
		{
			"type": "Feature",
			"properties": {
				"confidence": 9,
				"authenticationResultCode": "ValidCredentials",
				"brandLogoUri": "http://dev.virtualearth.net/Branding/logo_powered_by.png",
				"copyright": "Copyright © 2017 Microsoft and its suppliers. All rights reserved. This API cannot be accessed and the content and any results may not be used, reproduced or transmitted in any manner without express written permission from Microsoft Corporation.",
				"entityType": "Address",
				"matchCodes": [
					"Good"
				],
				"name": "1216 Rue du Pont, Marieville, QC J3M 1H1, Canada",
				"statusCode": 200,
				"statusDescription": "OK",
				"traceId": "ea373ee8e50a423ca104831dddd671e0|BN20190642|7.7.0.0|",
				"addressLine": "1216 Rue du Pont",
				"adminDistrict": "QC",
				"adminDistrict2": "Rouville",
				"countryRegion": "Canada",
				"formattedAddress": "1216 Rue du Pont, Marieville, QC J3M 1H1, Canada",
				"locality": "Marieville",
				"postalCode": "J3M 1H1"
			},
			"geometry": {
				"type": "Point",
				"coordinates": [
					-73.1628646,
					45.4318793
				]
			},
			"bbox": [
				-73.1644665,
				45.4307552,
				-73.1612627,
				45.4330035
			]
		}
	]
}
