{
	"type": "FeatureCollection",
	"features": [
		{
			"type": "Feature",
			"properties": {
				"confidence": 9,
				"authenticationResultCode": "ValidCredentials",
				"brandLogoUri": "http://dev.virtualearth.net/Branding/logo_powered_by.png",
				"copyright": "Copyright © 2017 Microsoft and its suppliers. All rights reserved. This API cannot be accessed and the content and any results may not be used, reproduced or transmitted in any manner without express written permission from Microsoft Corporation.",
				"entityType": "Address",
				"matchCodes": [
					"Good"
				],
				"name": "1216 4th St, Estevan, SK S4A 0W9, Canada",
				"statusCode": 200,
				"statusDescription": "OK",
				"traceId": "229336ec449c4a45a1911bfe817a39eb|BN20130423|7.7.0.0|",
				"addressLine": "1216 4th St",
				"adminDistrict": "SK",
				"adminDistrict2": "Saskatchewan",
				"countryRegion": "Canada",
				"formattedAddress": "1216 4th St, Estevan, SK S4A 0W9, Canada",
				"locality": "Estevan",
				"postalCode": "S4A 0W9"
			},
			"geometry": {
				"type": "Point",
				"coordinates": [
					-102.995242,
					49.1403542
				]
			},
			"bbox": [
				-102.9969603,
				49.1392301,
				-102.9935236,
				49.1414784
			]
		}
	]
}
