{
	"type": "FeatureCollection",
	"features": [
		{
			"type": "Feature",
			"properties": {
				"confidence": 9,
				"authenticationResultCode": "ValidCredentials",
				"brandLogoUri": "http://dev.virtualearth.net/Branding/logo_powered_by.png",
				"copyright": "Copyright © 2017 Microsoft and its suppliers. All rights reserved. This API cannot be accessed and the content and any results may not be used, reproduced or transmitted in any manner without express written permission from Microsoft Corporation.",
				"entityType": "Address",
				"matchCodes": [
					"Good"
				],
				"name": "12203 40 St SE, Calgary, AB T2Z 4E6, Canada",
				"statusCode": 200,
				"statusDescription": "OK",
				"traceId": "b6ba479ed4b94efe830a7d49010cc39a|BN20200239|7.7.0.0|",
				"addressLine": "12203 40 St SE",
				"adminDistrict": "AB",
				"adminDistrict2": "Alberta",
				"countryRegion": "Canada",
				"formattedAddress": "12203 40 St SE, Calgary, AB T2Z 4E6, Canada",
				"locality": "Calgary",
				"postalCode": "T2Z 4E6"
			},
			"geometry": {
				"type": "Point",
				"coordinates": [
					-113.97415,
					50.94033
				]
			},
			"bbox": [
				-113.975934,
				50.9392058,
				-113.972366,
				50.9414542
			]
		}
	]
}
