{
	"type": "FeatureCollection",
	"features": [
		{
			"type": "Feature",
			"properties": {
				"confidence": 9,
				"authenticationResultCode": "ValidCredentials",
				"brandLogoUri": "http://dev.virtualearth.net/Branding/logo_powered_by.png",
				"copyright": "Copyright © 2017 Microsoft and its suppliers. All rights reserved. This API cannot be accessed and the content and any results may not be used, reproduced or transmitted in any manner without express written permission from Microsoft Corporation.",
				"entityType": "Address",
				"matchCodes": [
					"Good"
				],
				"name": "1221 Weber St E, Kitchener, ON N2A 1C2, Canada",
				"statusCode": 200,
				"statusDescription": "OK",
				"traceId": "b1ca8632cc49498ea6d5b0856554b76a|BN20130632|7.7.0.0|",
				"addressLine": "1221 Weber St E",
				"adminDistrict": "ON",
				"adminDistrict2": "Waterloo",
				"countryRegion": "Canada",
				"formattedAddress": "1221 Weber St E, Kitchener, ON N2A 1C2, Canada",
				"locality": "Kitchener",
				"neighborhood": "Stanley Park",
				"postalCode": "N2A 1C2"
			},
			"geometry": {
				"type": "Point",
				"coordinates": [
					-80.44581,
					43.4332
				]
			},
			"bbox": [
				-80.447358,
				43.4320758,
				-80.444262,
				43.4343242
			]
		}
	]
}
