{
	"type": "FeatureCollection",
	"features": [
		{
			"type": "Feature",
			"properties": {
				"confidence": 9,
				"authenticationResultCode": "ValidCredentials",
				"brandLogoUri": "http://dev.virtualearth.net/Branding/logo_powered_by.png",
				"copyright": "Copyright © 2017 Microsoft and its suppliers. All rights reserved. This API cannot be accessed and the content and any results may not be used, reproduced or transmitted in any manner without express written permission from Microsoft Corporation.",
				"entityType": "Address",
				"matchCodes": [
					"Good"
				],
				"name": "1222 58 Ave SE, Calgary, AB T2H 2E9, Canada",
				"statusCode": 200,
				"statusDescription": "OK",
				"traceId": "7da2ef3e02cb45e4b37f0ba57df68bb3|BN20160335|7.7.0.0|",
				"addressLine": "1222 58 Ave SE",
				"adminDistrict": "AB",
				"adminDistrict2": "Alberta",
				"countryRegion": "Canada",
				"formattedAddress": "1222 58 Ave SE, Calgary, AB T2H 2E9, Canada",
				"locality": "Calgary",
				"neighborhood": "Alyth-Bonnybrook-Manchester",
				"postalCode": "T2H 2E9"
			},
			"geometry": {
				"type": "Point",
				"coordinates": [
					-114.0386104,
					51.0018749
				]
			},
			"bbox": [
				-114.0403968,
				51.0007507,
				-114.0368241,
				51.0029991
			]
		}
	]
}
