{
	"type": "FeatureCollection",
	"features": [
		{
			"type": "Feature",
			"properties": {
				"confidence": 9,
				"authenticationResultCode": "ValidCredentials",
				"brandLogoUri": "http://dev.virtualearth.net/Branding/logo_powered_by.png",
				"copyright": "Copyright © 2017 Microsoft and its suppliers. All rights reserved. This API cannot be accessed and the content and any results may not be used, reproduced or transmitted in any manner without express written permission from Microsoft Corporation.",
				"entityType": "Address",
				"matchCodes": [
					"Good"
				],
				"name": "1225 Franklin Blvd, Cambridge, ON N1R 7E5, Canada",
				"statusCode": 200,
				"statusDescription": "OK",
				"traceId": "9e8f1339c98c4c0dad3f9536ea48e6ff|BN20130721|7.7.0.0|",
				"addressLine": "1225 Franklin Blvd",
				"adminDistrict": "ON",
				"adminDistrict2": "Waterloo",
				"countryRegion": "Canada",
				"formattedAddress": "1225 Franklin Blvd, Cambridge, ON N1R 7E5, Canada",
				"locality": "Cambridge",
				"neighborhood": "Fiddlesticks",
				"postalCode": "N1R 7E5"
			},
			"geometry": {
				"type": "Point",
				"coordinates": [
					-80.3062,
					43.40777
				]
			},
			"bbox": [
				-80.3077474,
				43.4066458,
				-80.3046526,
				43.4088942
			]
		}
	]
}
