{
	"type": "FeatureCollection",
	"features": [
		{
			"type": "Feature",
			"properties": {
				"confidence": 9,
				"authenticationResultCode": "ValidCredentials",
				"brandLogoUri": "http://dev.virtualearth.net/Branding/logo_powered_by.png",
				"copyright": "Copyright © 2017 Microsoft and its suppliers. All rights reserved. This API cannot be accessed and the content and any results may not be used, reproduced or transmitted in any manner without express written permission from Microsoft Corporation.",
				"entityType": "Address",
				"matchCodes": [
					"Good"
				],
				"name": "123 Rogers St, Vancouver, BC V6A 3N2, Canada",
				"statusCode": 200,
				"statusDescription": "OK",
				"traceId": "699d9aa29a3b4475ad7a2cc89bb8989c|BN20121762|7.7.0.0|",
				"addressLine": "123 Rogers St",
				"adminDistrict": "BC",
				"adminDistrict2": "Greater Vancouver",
				"countryRegion": "Canada",
				"formattedAddress": "123 Rogers St, Vancouver, BC V6A 3N2, Canada",
				"locality": "Vancouver",
				"neighborhood": "Downtown Eastside",
				"postalCode": "V6A 3N2"
			},
			"geometry": {
				"type": "Point",
				"coordinates": [
					-123.08169,
					49.28357
				]
			},
			"bbox": [
				-123.0834133,
				49.2824458,
				-123.0799667,
				49.2846942
			]
		}
	]
}
