{
	"type": "FeatureCollection",
	"features": [
		{
			"type": "Feature",
			"properties": {
				"confidence": 9,
				"authenticationResultCode": "ValidCredentials",
				"brandLogoUri": "http://dev.virtualearth.net/Branding/logo_powered_by.png",
				"copyright": "Copyright © 2017 Microsoft and its suppliers. All rights reserved. This API cannot be accessed and the content and any results may not be used, reproduced or transmitted in any manner without express written permission from Microsoft Corporation.",
				"entityType": "Address",
				"matchCodes": [
					"Good"
				],
				"name": "12307 Woodbine Ave, Whitchurch-Stouffville, ON L0H, Canada",
				"statusCode": 200,
				"statusDescription": "OK",
				"traceId": "06ecc6d76e624758bbb8538faf4afa9e|BN20250135|7.7.0.0|",
				"addressLine": "12307 Woodbine Ave",
				"adminDistrict": "ON",
				"adminDistrict2": "York",
				"countryRegion": "Canada",
				"formattedAddress": "12307 Woodbine Ave, Whitchurch-Stouffville, ON L0H, Canada",
				"locality": "Whitchurch-Stouffville",
				"neighborhood": "Gormley",
				"postalCode": "L0H 1G0"
			},
			"geometry": {
				"type": "Point",
				"coordinates": [
					-79.37788,
					43.9435
				]
			},
			"bbox": [
				-79.3794413,
				43.9423758,
				-79.3763187,
				43.9446242
			]
		}
	]
}
