{
	"type": "FeatureCollection",
	"features": [
		{
			"type": "Feature",
			"properties": {
				"confidence": 9,
				"authenticationResultCode": "ValidCredentials",
				"brandLogoUri": "http://dev.virtualearth.net/Branding/logo_powered_by.png",
				"copyright": "Copyright © 2017 Microsoft and its suppliers. All rights reserved. This API cannot be accessed and the content and any results may not be used, reproduced or transmitted in any manner without express written permission from Microsoft Corporation.",
				"entityType": "Address",
				"matchCodes": [
					"Good"
				],
				"name": "1230 Rue de la Manic, Chicoutimi, QC G7K 1A2, Canada",
				"statusCode": 200,
				"statusDescription": "OK",
				"traceId": "b7691f73f7c74adb899bdab68e0b6d91|BN20130422|7.7.0.0|",
				"addressLine": "1230 Rue de la Manic",
				"adminDistrict": "QC",
				"adminDistrict2": "Saguenay",
				"countryRegion": "Canada",
				"formattedAddress": "1230 Rue de la Manic, Chicoutimi, QC G7K 1A2, Canada",
				"locality": "Saguenay",
				"neighborhood": "Chicoutimi",
				"postalCode": "G7K 1A2"
			},
			"geometry": {
				"type": "Point",
				"coordinates": [
					-71.11179,
					48.3976
				]
			},
			"bbox": [
				-71.1134831,
				48.3964758,
				-71.1100969,
				48.3987242
			]
		}
	]
}
