{
	"type": "FeatureCollection",
	"features": [
		{
			"type": "Feature",
			"properties": {
				"confidence": 9,
				"authenticationResultCode": "ValidCredentials",
				"brandLogoUri": "http://dev.virtualearth.net/Branding/logo_powered_by.png",
				"copyright": "Copyright © 2017 Microsoft and its suppliers. All rights reserved. This API cannot be accessed and the content and any results may not be used, reproduced or transmitted in any manner without express written permission from Microsoft Corporation.",
				"entityType": "Address",
				"matchCodes": [
					"Good"
				],
				"name": "1234 Barclay St, Vancouver, BC V6E 1H4, Canada",
				"statusCode": 200,
				"statusDescription": "OK",
				"traceId": "71523e640fd948898282a651bfebf6f6|BN20130431|7.7.0.0|",
				"addressLine": "1234 Barclay St",
				"adminDistrict": "BC",
				"adminDistrict2": "Greater Vancouver",
				"countryRegion": "Canada",
				"formattedAddress": "1234 Barclay St, Vancouver, BC V6E 1H4, Canada",
				"locality": "Vancouver",
				"neighborhood": "West End",
				"postalCode": "V6E 1H4"
			},
			"geometry": {
				"type": "Point",
				"coordinates": [
					-123.13019,
					49.2849
				]
			},
			"bbox": [
				-123.1319134,
				49.2837758,
				-123.1284666,
				49.2860242
			]
		}
	]
}
