{
	"type": "FeatureCollection",
	"features": [
		{
			"type": "Feature",
			"properties": {
				"confidence": 9,
				"authenticationResultCode": "ValidCredentials",
				"brandLogoUri": "http://dev.virtualearth.net/Branding/logo_powered_by.png",
				"copyright": "Copyright © 2017 Microsoft and its suppliers. All rights reserved. This API cannot be accessed and the content and any results may not be used, reproduced or transmitted in any manner without express written permission from Microsoft Corporation.",
				"entityType": "Address",
				"matchCodes": [
					"Good"
				],
				"name": "1235 Bay St, Toronto, ON M5R 3K4, Canada",
				"statusCode": 200,
				"statusDescription": "OK",
				"traceId": "8992575eba8c4c80b323e195a31783db|BN20210145|7.7.0.0|",
				"addressLine": "1235 Bay St",
				"adminDistrict": "ON",
				"adminDistrict2": "Toronto",
				"countryRegion": "Canada",
				"formattedAddress": "1235 Bay St, Toronto, ON M5R 3K4, Canada",
				"locality": "Toronto",
				"neighborhood": "Annex",
				"postalCode": "M5R 3K4"
			},
			"geometry": {
				"type": "Point",
				"coordinates": [
					-79.3896,
					43.6708799
				]
			},
			"bbox": [
				-79.3911542,
				43.6697557,
				-79.3880458,
				43.6720041
			]
		}
	]
}
