{
	"type": "FeatureCollection",
	"features": [
		{
			"type": "Feature",
			"properties": {
				"confidence": 9,
				"authenticationResultCode": "ValidCredentials",
				"brandLogoUri": "http://dev.virtualearth.net/Branding/logo_powered_by.png",
				"copyright": "Copyright © 2017 Microsoft and its suppliers. All rights reserved. This API cannot be accessed and the content and any results may not be used, reproduced or transmitted in any manner without express written permission from Microsoft Corporation.",
				"entityType": "Address",
				"matchCodes": [
					"Good"
				],
				"name": "1249 Carman Rd, Brighton, ON K0K 1H0, Canada",
				"statusCode": 200,
				"statusDescription": "OK",
				"traceId": "9f55ae06c5f64a6287b2e5c019f2bc78|BN20130530|7.7.0.0|",
				"addressLine": "1249 Carman Rd",
				"adminDistrict": "ON",
				"adminDistrict2": "Northumberland",
				"countryRegion": "Canada",
				"formattedAddress": "1249 Carman Rd, Brighton, ON K0K 1H0, Canada",
				"locality": "Brighton",
				"postalCode": "K0K 1H0"
			},
			"geometry": {
				"type": "Point",
				"coordinates": [
					-77.70011,
					44.11715
				]
			},
			"bbox": [
				-77.7016759,
				44.1160258,
				-77.6985441,
				44.1182742
			]
		}
	]
}
