{
	"type": "FeatureCollection",
	"features": [
		{
			"type": "Feature",
			"properties": {
				"confidence": 9,
				"authenticationResultCode": "ValidCredentials",
				"brandLogoUri": "http://dev.virtualearth.net/Branding/logo_powered_by.png",
				"copyright": "Copyright © 2017 Microsoft and its suppliers. All rights reserved. This API cannot be accessed and the content and any results may not be used, reproduced or transmitted in any manner without express written permission from Microsoft Corporation.",
				"entityType": "Address",
				"matchCodes": [
					"Good"
				],
				"name": "12509 124 St NW, Edmonton, AB T5L 0N6, Canada",
				"statusCode": 200,
				"statusDescription": "OK",
				"traceId": "b4ad2815cb7247c28b30eb82ca0a4e81|BN20260223|7.7.0.0|",
				"addressLine": "12509 124 St NW",
				"adminDistrict": "AB",
				"adminDistrict2": "Alberta",
				"countryRegion": "Canada",
				"formattedAddress": "12509 124 St NW, Edmonton, AB T5L 0N6, Canada",
				"locality": "Edmonton",
				"neighborhood": "Hagmann Estate Industrial",
				"postalCode": "T5L 0N6"
			},
			"geometry": {
				"type": "Point",
				"coordinates": [
					-113.5355,
					53.5812
				]
			},
			"bbox": [
				-113.5373935,
				53.5800758,
				-113.5336065,
				53.5823242
			]
		}
	]
}
