{
	"type": "FeatureCollection",
	"features": [
		{
			"type": "Feature",
			"properties": {
				"confidence": 9,
				"authenticationResultCode": "ValidCredentials",
				"brandLogoUri": "http://dev.virtualearth.net/Branding/logo_powered_by.png",
				"copyright": "Copyright © 2017 Microsoft and its suppliers. All rights reserved. This API cannot be accessed and the content and any results may not be used, reproduced or transmitted in any manner without express written permission from Microsoft Corporation.",
				"entityType": "Address",
				"matchCodes": [
					"Good"
				],
				"name": "1250 Thornton Rd S, Oshawa, ON L1J 7E2, Canada",
				"statusCode": 200,
				"statusDescription": "OK",
				"traceId": "aff2a06f80334128977bc8011a9c67c7|BN20130634|7.7.0.0|",
				"addressLine": "1250 Thornton Rd S",
				"adminDistrict": "ON",
				"adminDistrict2": "Durham",
				"countryRegion": "Canada",
				"formattedAddress": "1250 Thornton Rd S, Oshawa, ON L1J 7E2, Canada",
				"locality": "Oshawa",
				"neighborhood": "Stevenson",
				"postalCode": "L1J 7E2"
			},
			"geometry": {
				"type": "Point",
				"coordinates": [
					-78.8786717,
					43.8575724
				]
			},
			"bbox": [
				-78.8802307,
				43.8564482,
				-78.8771126,
				43.8586966
			]
		}
	]
}
