{
	"type": "FeatureCollection",
	"features": [
		{
			"type": "Feature",
			"properties": {
				"confidence": 9,
				"authenticationResultCode": "ValidCredentials",
				"brandLogoUri": "http://dev.virtualearth.net/Branding/logo_powered_by.png",
				"copyright": "Copyright © 2017 Microsoft and its suppliers. All rights reserved. This API cannot be accessed and the content and any results may not be used, reproduced or transmitted in any manner without express written permission from Microsoft Corporation.",
				"entityType": "Address",
				"matchCodes": [
					"Good"
				],
				"name": "1254 Rue Labadie, Longueuil, QC J4N 1C7, Canada",
				"statusCode": 200,
				"statusDescription": "OK",
				"traceId": "821465f95e834f10b6f04329920ce61b|BN20130620|7.7.0.0|",
				"addressLine": "1254 Rue Labadie",
				"adminDistrict": "QC",
				"adminDistrict2": "Longueuil",
				"countryRegion": "Canada",
				"formattedAddress": "1254 Rue Labadie, Longueuil, QC J4N 1C7, Canada",
				"locality": "Longueuil",
				"postalCode": "J4N 1C7"
			},
			"geometry": {
				"type": "Point",
				"coordinates": [
					-73.45379,
					45.56341
				]
			},
			"bbox": [
				-73.4553957,
				45.5622858,
				-73.4521843,
				45.5645342
			]
		}
	]
}
