{
	"type": "FeatureCollection",
	"features": [
		{
			"type": "Feature",
			"properties": {
				"confidence": 9,
				"authenticationResultCode": "ValidCredentials",
				"brandLogoUri": "http://dev.virtualearth.net/Branding/logo_powered_by.png",
				"copyright": "Copyright © 2017 Microsoft and its suppliers. All rights reserved. This API cannot be accessed and the content and any results may not be used, reproduced or transmitted in any manner without express written permission from Microsoft Corporation.",
				"entityType": "Address",
				"matchCodes": [
					"Good"
				],
				"name": "1255 Reid St, Richmond Hill, ON L4B, Canada",
				"statusCode": 200,
				"statusDescription": "OK",
				"traceId": "89bb4c57db6a49698301c512d5ae4b8b|BN20320521|7.7.0.0|",
				"addressLine": "1255 Reid St",
				"adminDistrict": "ON",
				"adminDistrict2": "York",
				"countryRegion": "Canada",
				"formattedAddress": "1255 Reid St, Richmond Hill, ON L4B, Canada",
				"locality": "Richmond Hill",
				"postalCode": "L4B 1E9"
			},
			"geometry": {
				"type": "Point",
				"coordinates": [
					-79.38563,
					43.85005
				]
			},
			"bbox": [
				-79.3871888,
				43.8489258,
				-79.3840712,
				43.8511742
			]
		}
	]
}
