{
	"type": "FeatureCollection",
	"features": [
		{
			"type": "Feature",
			"properties": {
				"confidence": 9,
				"authenticationResultCode": "ValidCredentials",
				"brandLogoUri": "http://dev.virtualearth.net/Branding/logo_powered_by.png",
				"copyright": "Copyright © 2017 Microsoft and its suppliers. All rights reserved. This API cannot be accessed and the content and any results may not be used, reproduced or transmitted in any manner without express written permission from Microsoft Corporation.",
				"entityType": "Address",
				"matchCodes": [
					"Good"
				],
				"name": "1255 Fewster Dr, Mississauga, ON L4W 1A2, Canada",
				"statusCode": 200,
				"statusDescription": "OK",
				"traceId": "e9a7b67507f04013b69cb34d62892928|BN20130620|7.7.0.0|",
				"addressLine": "1255 Fewster Dr",
				"adminDistrict": "ON",
				"adminDistrict2": "Peel",
				"countryRegion": "Canada",
				"formattedAddress": "1255 Fewster Dr, Mississauga, ON L4W 1A2, Canada",
				"locality": "Mississauga",
				"neighborhood": "Dixie",
				"postalCode": "L4W 1A2"
			},
			"geometry": {
				"type": "Point",
				"coordinates": [
					-79.61938,
					43.6298699
				]
			},
			"bbox": [
				-79.6209331,
				43.6287457,
				-79.6178269,
				43.6309941
			]
		}
	]
}
