{
	"type": "FeatureCollection",
	"features": [
		{
			"type": "Feature",
			"properties": {
				"confidence": 9,
				"authenticationResultCode": "ValidCredentials",
				"brandLogoUri": "http://dev.virtualearth.net/Branding/logo_powered_by.png",
				"copyright": "Copyright © 2017 Microsoft and its suppliers. All rights reserved. This API cannot be accessed and the content and any results may not be used, reproduced or transmitted in any manner without express written permission from Microsoft Corporation.",
				"entityType": "Address",
				"matchCodes": [
					"Good"
				],
				"name": "1260 McDonald St, Regina, SK S4N 4X6, Canada",
				"statusCode": 200,
				"statusDescription": "OK",
				"traceId": "a41d31cff5824146b7cb1cf8aba36997|BN20130447|7.7.0.0|",
				"addressLine": "1260 McDonald St",
				"adminDistrict": "SK",
				"adminDistrict2": "Saskatchewan",
				"countryRegion": "Canada",
				"formattedAddress": "1260 McDonald St, Regina, SK S4N 4X6, Canada",
				"locality": "Regina",
				"neighborhood": "Eastview",
				"postalCode": "S4N 4X6"
			},
			"geometry": {
				"type": "Point",
				"coordinates": [
					-104.5840599,
					50.45866
				]
			},
			"bbox": [
				-104.5858257,
				50.4575358,
				-104.5822941,
				50.4597842
			]
		}
	]
}
