{
	"type": "FeatureCollection",
	"features": [
		{
			"type": "Feature",
			"properties": {
				"confidence": 9,
				"authenticationResultCode": "ValidCredentials",
				"brandLogoUri": "http://dev.virtualearth.net/Branding/logo_powered_by.png",
				"copyright": "Copyright © 2017 Microsoft and its suppliers. All rights reserved. This API cannot be accessed and the content and any results may not be used, reproduced or transmitted in any manner without express written permission from Microsoft Corporation.",
				"entityType": "Address",
				"matchCodes": [
					"Good"
				],
				"name": "1260 Clarence Ave, Winnipeg, MB R3T 1T2, Canada",
				"statusCode": 200,
				"statusDescription": "OK",
				"traceId": "8f901d20d5304662bed371c0613ce39c|BN20181720|7.7.0.0|",
				"addressLine": "1260 Clarence Ave",
				"adminDistrict": "MB",
				"adminDistrict2": "Manitoba",
				"countryRegion": "Canada",
				"formattedAddress": "1260 Clarence Ave, Winnipeg, MB R3T 1T2, Canada",
				"locality": "Winnipeg",
				"neighborhood": "Chevrier",
				"postalCode": "R3T 1T2"
			},
			"geometry": {
				"type": "Point",
				"coordinates": [
					-97.1629094,
					49.8323149
				]
			},
			"bbox": [
				-97.1646522,
				49.8311908,
				-97.1611666,
				49.8334391
			]
		}
	]
}
