{
	"type": "FeatureCollection",
	"features": [
		{
			"type": "Feature",
			"properties": {
				"confidence": 9,
				"authenticationResultCode": "ValidCredentials",
				"brandLogoUri": "http://dev.virtualearth.net/Branding/logo_powered_by.png",
				"copyright": "Copyright © 2017 Microsoft and its suppliers. All rights reserved. This API cannot be accessed and the content and any results may not be used, reproduced or transmitted in any manner without express written permission from Microsoft Corporation.",
				"entityType": "Address",
				"matchCodes": [
					"Good"
				],
				"name": "127 Woodington Ave, East York, ON M4C 3K5, Canada",
				"statusCode": 200,
				"statusDescription": "OK",
				"traceId": "436882cda663481fbb83dfaa5f1b169d|BN20130625|7.7.0.0|",
				"addressLine": "127 Woodington Ave",
				"adminDistrict": "ON",
				"adminDistrict2": "Toronto",
				"countryRegion": "Canada",
				"formattedAddress": "127 Woodington Ave, East York, ON M4C 3K5, Canada",
				"locality": "Toronto",
				"neighborhood": "Danforth Village-East York",
				"postalCode": "M4C 3K5"
			},
			"geometry": {
				"type": "Point",
				"coordinates": [
					-79.32239,
					43.68821
				]
			},
			"bbox": [
				-79.3239446,
				43.6870858,
				-79.3208354,
				43.6893342
			]
		}
	]
}
