{
	"type": "FeatureCollection",
	"features": [
		{
			"type": "Feature",
			"properties": {
				"confidence": 9,
				"authenticationResultCode": "ValidCredentials",
				"brandLogoUri": "http://dev.virtualearth.net/Branding/logo_powered_by.png",
				"copyright": "Copyright © 2017 Microsoft and its suppliers. All rights reserved. This API cannot be accessed and the content and any results may not be used, reproduced or transmitted in any manner without express written permission from Microsoft Corporation.",
				"entityType": "Address",
				"matchCodes": [
					"Good"
				],
				"name": "1270 Aberdeen St, Hawkesbury, ON K6A 1K7, Canada",
				"statusCode": 200,
				"statusDescription": "OK",
				"traceId": "e5e50ee7d4be4e659922b5dc98a3ffac|BN20240423|7.7.0.0|",
				"addressLine": "1270 Aberdeen St",
				"adminDistrict": "ON",
				"adminDistrict2": "Prescott and Russell",
				"countryRegion": "Canada",
				"formattedAddress": "1270 Aberdeen St, Hawkesbury, ON K6A 1K7, Canada",
				"locality": "Hawkesbury",
				"postalCode": "K6A 1K7"
			},
			"geometry": {
				"type": "Point",
				"coordinates": [
					-74.5910797,
					45.6039368
				]
			},
			"bbox": [
				-74.5926866,
				45.6028126,
				-74.5894729,
				45.6050609
			]
		}
	]
}
