{
	"type": "FeatureCollection",
	"features": [
		{
			"type": "Feature",
			"properties": {
				"confidence": 9,
				"authenticationResultCode": "ValidCredentials",
				"brandLogoUri": "http://dev.virtualearth.net/Branding/logo_powered_by.png",
				"copyright": "Copyright © 2017 Microsoft and its suppliers. All rights reserved. This API cannot be accessed and the content and any results may not be used, reproduced or transmitted in any manner without express written permission from Microsoft Corporation.",
				"entityType": "Address",
				"matchCodes": [
					"Good"
				],
				"name": "1271 6 Ave NE, Salmon Arm, BC V1E 2S5, Canada",
				"statusCode": 200,
				"statusDescription": "OK",
				"traceId": "fb26711c06ac4653bd350aacaef808ff|BN20130530|7.7.0.0|",
				"addressLine": "1271 6 Ave NE",
				"adminDistrict": "BC",
				"adminDistrict2": "Columbia-Shuswap",
				"countryRegion": "Canada",
				"formattedAddress": "1271 6 Ave NE, Salmon Arm, BC V1E 2S5, Canada",
				"locality": "Salmon Arm",
				"postalCode": "V1E 2S5"
			},
			"geometry": {
				"type": "Point",
				"coordinates": [
					-119.2700398,
					50.7043049
				]
			},
			"bbox": [
				-119.2718148,
				50.7031807,
				-119.2682648,
				50.7054291
			]
		}
	]
}
