{
	"type": "FeatureCollection",
	"features": [
		{
			"type": "Feature",
			"properties": {
				"confidence": 9,
				"authenticationResultCode": "ValidCredentials",
				"brandLogoUri": "http://dev.virtualearth.net/Branding/logo_powered_by.png",
				"copyright": "Copyright © 2017 Microsoft and its suppliers. All rights reserved. This API cannot be accessed and the content and any results may not be used, reproduced or transmitted in any manner without express written permission from Microsoft Corporation.",
				"entityType": "Address",
				"matchCodes": [
					"Good"
				],
				"name": "1277 York Mills Rd, North York, ON M3A 1Z5, Canada",
				"statusCode": 200,
				"statusDescription": "OK",
				"traceId": "405074b0ccaa4ae39b6db2d852dde408|BN20121763|7.7.0.0|",
				"addressLine": "1277 York Mills Rd",
				"adminDistrict": "ON",
				"adminDistrict2": "Toronto",
				"countryRegion": "Canada",
				"formattedAddress": "1277 York Mills Rd, North York, ON M3A 1Z5, Canada",
				"locality": "Toronto",
				"neighborhood": "Parkwoods-Donalda",
				"postalCode": "M3A 1Z5"
			},
			"geometry": {
				"type": "Point",
				"coordinates": [
					-79.32517,
					43.76054
				]
			},
			"bbox": [
				-79.3267265,
				43.7594158,
				-79.3236135,
				43.7616642
			]
		}
	]
}
