{
	"type": "FeatureCollection",
	"features": [
		{
			"type": "Feature",
			"properties": {
				"confidence": 9,
				"authenticationResultCode": "ValidCredentials",
				"brandLogoUri": "http://dev.virtualearth.net/Branding/logo_powered_by.png",
				"copyright": "Copyright © 2017 Microsoft and its suppliers. All rights reserved. This API cannot be accessed and the content and any results may not be used, reproduced or transmitted in any manner without express written permission from Microsoft Corporation.",
				"entityType": "Address",
				"matchCodes": [
					"Good"
				],
				"name": "128 Walgreen Rd, Carp, ON K0A 1L0, Canada",
				"statusCode": 200,
				"statusDescription": "OK",
				"traceId": "764579d95f3c47d38b31e70893b578aa|BN20290118|7.7.0.0|",
				"addressLine": "128 Walgreen Rd",
				"adminDistrict": "ON",
				"adminDistrict2": "Ottawa",
				"countryRegion": "Canada",
				"formattedAddress": "128 Walgreen Rd, Carp, ON K0A 1L0, Canada",
				"locality": "Ottawa",
				"neighborhood": "Carp",
				"postalCode": "K0A 1L0"
			},
			"geometry": {
				"type": "Point",
				"coordinates": [
					-75.95732,
					45.27235
				]
			},
			"bbox": [
				-75.9589174,
				45.2712258,
				-75.9557226,
				45.2734742
			]
		}
	]
}
