{
	"type": "FeatureCollection",
	"features": [
		{
			"type": "Feature",
			"properties": {
				"confidence": 9,
				"authenticationResultCode": "ValidCredentials",
				"brandLogoUri": "http://dev.virtualearth.net/Branding/logo_powered_by.png",
				"copyright": "Copyright © 2017 Microsoft and its suppliers. All rights reserved. This API cannot be accessed and the content and any results may not be used, reproduced or transmitted in any manner without express written permission from Microsoft Corporation.",
				"entityType": "Address",
				"matchCodes": [
					"Good"
				],
				"name": "12805 Rue du Parc, Mirabel, QC J7J 0W5, Canada",
				"statusCode": 200,
				"statusDescription": "OK",
				"traceId": "f07b4a246a694f38b6934bcde246fb10|BN20220145|7.7.0.0|",
				"addressLine": "12805 Rue du Parc",
				"adminDistrict": "QC",
				"adminDistrict2": "Mirabel",
				"countryRegion": "Canada",
				"formattedAddress": "12805 Rue du Parc, Mirabel, QC J7J 0W5, Canada",
				"locality": "Mirabel",
				"postalCode": "J7J 0W5"
			},
			"geometry": {
				"type": "Point",
				"coordinates": [
					-73.92945,
					45.69301
				]
			},
			"bbox": [
				-73.9310594,
				45.6918858,
				-73.9278406,
				45.6941342
			]
		}
	]
}
