{
	"type": "FeatureCollection",
	"features": [
		{
			"type": "Feature",
			"properties": {
				"confidence": 9,
				"authenticationResultCode": "ValidCredentials",
				"brandLogoUri": "http://dev.virtualearth.net/Branding/logo_powered_by.png",
				"copyright": "Copyright © 2017 Microsoft and its suppliers. All rights reserved. This API cannot be accessed and the content and any results may not be used, reproduced or transmitted in any manner without express written permission from Microsoft Corporation.",
				"entityType": "Address",
				"matchCodes": [
					"Good"
				],
				"name": "129 Upper Rd, Londonderry, NS B0M 1M0, Canada",
				"statusCode": 200,
				"statusDescription": "OK",
				"traceId": "b7904391d01a4e36bf601243c89e3604|BN20130530|7.7.0.0|",
				"addressLine": "129 Upper Rd",
				"adminDistrict": "NS",
				"adminDistrict2": "Colchester",
				"countryRegion": "Canada",
				"formattedAddress": "129 Upper Rd, Londonderry, NS B0M 1M0, Canada",
				"locality": "Colchester",
				"neighborhood": "Londonderry",
				"postalCode": "B0M 1M0"
			},
			"geometry": {
				"type": "Point",
				"coordinates": [
					-63.62751,
					45.4764
				]
			},
			"bbox": [
				-63.6291132,
				45.4752758,
				-63.6259068,
				45.4775242
			]
		}
	]
}
