{
	"type": "FeatureCollection",
	"features": [
		{
			"type": "Feature",
			"properties": {
				"confidence": 9,
				"authenticationResultCode": "ValidCredentials",
				"brandLogoUri": "http://dev.virtualearth.net/Branding/logo_powered_by.png",
				"copyright": "Copyright © 2017 Microsoft and its suppliers. All rights reserved. This API cannot be accessed and the content and any results may not be used, reproduced or transmitted in any manner without express written permission from Microsoft Corporation.",
				"entityType": "Address",
				"matchCodes": [
					"Good"
				],
				"name": "13 Chemin Lattion, Gatineau, QC J9H 5C9, Canada",
				"statusCode": 200,
				"statusDescription": "OK",
				"traceId": "7c3c9fd8ffe849f79246549f409a15cb|BN20280152|7.7.0.0|",
				"addressLine": "13 Chemin Lattion",
				"adminDistrict": "QC",
				"adminDistrict2": "Gatineau",
				"countryRegion": "Canada",
				"formattedAddress": "13 Chemin Lattion, Gatineau, QC J9H 5C9, Canada",
				"locality": "Gatineau",
				"neighborhood": "Aylmer",
				"postalCode": "J9H 5C9"
			},
			"geometry": {
				"type": "Point",
				"coordinates": [
					-75.86959,
					45.40851
				]
			},
			"bbox": [
				-75.8711912,
				45.4073858,
				-75.8679888,
				45.4096342
			]
		}
	]
}
