{
	"type": "FeatureCollection",
	"features": [
		{
			"type": "Feature",
			"properties": {
				"confidence": 9,
				"authenticationResultCode": "ValidCredentials",
				"brandLogoUri": "http://dev.virtualearth.net/Branding/logo_powered_by.png",
				"copyright": "Copyright © 2017 Microsoft and its suppliers. All rights reserved. This API cannot be accessed and the content and any results may not be used, reproduced or transmitted in any manner without express written permission from Microsoft Corporation.",
				"entityType": "Address",
				"matchCodes": [
					"Good"
				],
				"name": "1300 Homewood Rd, Campbell River, BC V9W 3N7, Canada",
				"statusCode": 200,
				"statusDescription": "OK",
				"traceId": "6acdd34ea2684854ac8ed1d4d871dd42|BN20130530|7.7.0.0|",
				"addressLine": "1300 Homewood Rd",
				"adminDistrict": "BC",
				"adminDistrict2": "Strathcona",
				"countryRegion": "Canada",
				"formattedAddress": "1300 Homewood Rd, Campbell River, BC V9W 3N7, Canada",
				"locality": "Campbell River",
				"postalCode": "V9W 3N7"
			},
			"geometry": {
				"type": "Point",
				"coordinates": [
					-125.263631,
					50.0271206
				]
			},
			"bbox": [
				-125.2653809,
				50.0259964,
				-125.2618811,
				50.0282447
			]
		}
	]
}
