{
	"type": "FeatureCollection",
	"features": [
		{
			"type": "Feature",
			"properties": {
				"confidence": 9,
				"authenticationResultCode": "ValidCredentials",
				"brandLogoUri": "http://dev.virtualearth.net/Branding/logo_powered_by.png",
				"copyright": "Copyright © 2017 Microsoft and its suppliers. All rights reserved. This API cannot be accessed and the content and any results may not be used, reproduced or transmitted in any manner without express written permission from Microsoft Corporation.",
				"entityType": "Address",
				"matchCodes": [
					"Good"
				],
				"name": "1305 Woodgrove Pl, Oakville, ON L6M 1V5, Canada",
				"statusCode": 200,
				"statusDescription": "OK",
				"traceId": "4923cfc2f399432cabc8c4d79adc94d7|BN20220145|7.7.0.0|",
				"addressLine": "1305 Woodgrove Pl",
				"adminDistrict": "ON",
				"adminDistrict2": "Halton",
				"countryRegion": "Canada",
				"formattedAddress": "1305 Woodgrove Pl, Oakville, ON L6M 1V5, Canada",
				"locality": "Oakville",
				"neighborhood": "Glen Abbey",
				"postalCode": "L6M 1V5"
			},
			"geometry": {
				"type": "Point",
				"coordinates": [
					-79.72734,
					43.43786
				]
			},
			"bbox": [
				-79.7288882,
				43.4367358,
				-79.7257918,
				43.4389842
			]
		}
	]
}
