{
	"type": "FeatureCollection",
	"features": [
		{
			"type": "Feature",
			"properties": {
				"confidence": 9,
				"authenticationResultCode": "ValidCredentials",
				"brandLogoUri": "http://dev.virtualearth.net/Branding/logo_powered_by.png",
				"copyright": "Copyright © 2017 Microsoft and its suppliers. All rights reserved. This API cannot be accessed and the content and any results may not be used, reproduced or transmitted in any manner without express written permission from Microsoft Corporation.",
				"entityType": "Address",
				"matchCodes": [
					"Good"
				],
				"name": "131 Ilsley Ave, Dartmouth, NS B3B 1T1, Canada",
				"statusCode": 200,
				"statusDescription": "OK",
				"traceId": "ea144b2ae1314221b0dc1c13599715e6|BN20130521|7.7.0.0|",
				"addressLine": "131 Ilsley Ave",
				"adminDistrict": "NS",
				"adminDistrict2": "Halifax",
				"countryRegion": "Canada",
				"formattedAddress": "131 Ilsley Ave, Dartmouth, NS B3B 1T1, Canada",
				"locality": "Halifax",
				"neighborhood": "Dartmouth",
				"postalCode": "B3B 1T1"
			},
			"geometry": {
				"type": "Point",
				"coordinates": [
					-63.58323,
					44.69615
				]
			},
			"bbox": [
				-63.5848114,
				44.6950258,
				-63.5816486,
				44.6972742
			]
		}
	]
}
