{
	"type": "FeatureCollection",
	"features": [
		{
			"type": "Feature",
			"properties": {
				"confidence": 9,
				"authenticationResultCode": "ValidCredentials",
				"brandLogoUri": "http://dev.virtualearth.net/Branding/logo_powered_by.png",
				"copyright": "Copyright © 2017 Microsoft and its suppliers. All rights reserved. This API cannot be accessed and the content and any results may not be used, reproduced or transmitted in any manner without express written permission from Microsoft Corporation.",
				"entityType": "Address",
				"matchCodes": [
					"Good"
				],
				"name": "131 Rue Principale, Fassett, QC J0V 1H0, Canada",
				"statusCode": 200,
				"statusDescription": "OK",
				"traceId": "45ca9862185b469c94c904cb7c944c0e|BN20130533|7.7.0.0|",
				"addressLine": "131 Rue Principale",
				"adminDistrict": "QC",
				"adminDistrict2": "Papineau",
				"countryRegion": "Canada",
				"formattedAddress": "131 Rue Principale, Fassett, QC J0V 1H0, Canada",
				"locality": "Fassett",
				"postalCode": "J0V 1H0"
			},
			"geometry": {
				"type": "Point",
				"coordinates": [
					-74.8617675,
					45.6435992
				]
			},
			"bbox": [
				-74.8633754,
				45.642475,
				-74.8601595,
				45.6447233
			]
		}
	]
}
