{
	"type": "FeatureCollection",
	"features": [
		{
			"type": "Feature",
			"properties": {
				"confidence": 9,
				"authenticationResultCode": "ValidCredentials",
				"brandLogoUri": "http://dev.virtualearth.net/Branding/logo_powered_by.png",
				"copyright": "Copyright © 2017 Microsoft and its suppliers. All rights reserved. This API cannot be accessed and the content and any results may not be used, reproduced or transmitted in any manner without express written permission from Microsoft Corporation.",
				"entityType": "Address",
				"matchCodes": [
					"Good"
				],
				"name": "131 Lowther Ave, Toronto, ON M5R 1E4, Canada",
				"statusCode": 200,
				"statusDescription": "OK",
				"traceId": "259f9594e2cc48b2a564d392c4297eec|BN20130719|7.7.0.0|",
				"addressLine": "131 Lowther Ave",
				"adminDistrict": "ON",
				"adminDistrict2": "Toronto",
				"countryRegion": "Canada",
				"formattedAddress": "131 Lowther Ave, Toronto, ON M5R 1E4, Canada",
				"locality": "Toronto",
				"neighborhood": "Annex",
				"postalCode": "M5R 1E4"
			},
			"geometry": {
				"type": "Point",
				"coordinates": [
					-79.40255,
					43.66923
				]
			},
			"bbox": [
				-79.4041041,
				43.6681058,
				-79.4009959,
				43.6703542
			]
		}
	]
}
