{
	"type": "FeatureCollection",
	"features": [
		{
			"type": "Feature",
			"properties": {
				"confidence": 9,
				"authenticationResultCode": "ValidCredentials",
				"brandLogoUri": "http://dev.virtualearth.net/Branding/logo_powered_by.png",
				"copyright": "Copyright © 2017 Microsoft and its suppliers. All rights reserved. This API cannot be accessed and the content and any results may not be used, reproduced or transmitted in any manner without express written permission from Microsoft Corporation.",
				"entityType": "Address",
				"matchCodes": [
					"Good"
				],
				"name": "131 Planchet Rd, Concord, ON L4K 2C6, Canada",
				"statusCode": 200,
				"statusDescription": "OK",
				"traceId": "ed9456a4fd8546c0a1c05f7f2daa42a1|BN20200137|7.7.0.0|",
				"addressLine": "131 Planchet Rd",
				"adminDistrict": "ON",
				"adminDistrict2": "York",
				"countryRegion": "Canada",
				"formattedAddress": "131 Planchet Rd, Concord, ON L4K 2C6, Canada",
				"locality": "Vaughan",
				"neighborhood": "Concord",
				"postalCode": "L4K 2C6"
			},
			"geometry": {
				"type": "Point",
				"coordinates": [
					-79.49948,
					43.82339
				]
			},
			"bbox": [
				-79.5010381,
				43.8222658,
				-79.4979219,
				43.8245142
			]
		}
	]
}
