{
	"type": "FeatureCollection",
	"features": [
		{
			"type": "Feature",
			"properties": {
				"confidence": 9,
				"authenticationResultCode": "ValidCredentials",
				"brandLogoUri": "http://dev.virtualearth.net/Branding/logo_powered_by.png",
				"copyright": "Copyright © 2017 Microsoft and its suppliers. All rights reserved. This API cannot be accessed and the content and any results may not be used, reproduced or transmitted in any manner without express written permission from Microsoft Corporation.",
				"entityType": "Address",
				"matchCodes": [
					"Good"
				],
				"name": "131 Regalcrest Ct, Woodbridge, ON L4L 8P3, Canada",
				"statusCode": 200,
				"statusDescription": "OK",
				"traceId": "f214629a2f9b4afdb76779d48eeb350c|BN20131519|7.7.0.0|",
				"addressLine": "131 Regalcrest Ct",
				"adminDistrict": "ON",
				"adminDistrict2": "York",
				"countryRegion": "Canada",
				"formattedAddress": "131 Regalcrest Ct, Woodbridge, ON L4L 8P3, Canada",
				"locality": "Vaughan",
				"neighborhood": "Woodbridge",
				"postalCode": "L4L 8P3"
			},
			"geometry": {
				"type": "Point",
				"coordinates": [
					-79.61805,
					43.77194
				]
			},
			"bbox": [
				-79.6196068,
				43.7708158,
				-79.6164932,
				43.7730642
			]
		}
	]
}
