{
	"type": "FeatureCollection",
	"features": [
		{
			"type": "Feature",
			"properties": {
				"confidence": 9,
				"authenticationResultCode": "ValidCredentials",
				"brandLogoUri": "http://dev.virtualearth.net/Branding/logo_powered_by.png",
				"copyright": "Copyright © 2017 Microsoft and its suppliers. All rights reserved. This API cannot be accessed and the content and any results may not be used, reproduced or transmitted in any manner without express written permission from Microsoft Corporation.",
				"entityType": "Address",
				"matchCodes": [
					"Good"
				],
				"name": "131 Doyle Dr, Guelph, ON N1G 5B4, Canada",
				"statusCode": 200,
				"statusDescription": "OK",
				"traceId": "f412f8c0c0624973a14f92141b33bb83|BN20300154|7.7.0.0|",
				"addressLine": "131 Doyle Dr",
				"adminDistrict": "ON",
				"adminDistrict2": "Wellington",
				"countryRegion": "Canada",
				"formattedAddress": "131 Doyle Dr, Guelph, ON N1G 5B4, Canada",
				"locality": "Guelph",
				"neighborhood": "Clairfields/Hanlon Business Park",
				"postalCode": "N1G 5B4"
			},
			"geometry": {
				"type": "Point",
				"coordinates": [
					-80.19619,
					43.49591
				]
			},
			"bbox": [
				-80.1977396,
				43.4947858,
				-80.1946404,
				43.4970342
			]
		}
	]
}
