{
	"type": "FeatureCollection",
	"features": [
		{
			"type": "Feature",
			"properties": {
				"confidence": 9,
				"authenticationResultCode": "ValidCredentials",
				"brandLogoUri": "http://dev.virtualearth.net/Branding/logo_powered_by.png",
				"copyright": "Copyright © 2017 Microsoft and its suppliers. All rights reserved. This API cannot be accessed and the content and any results may not be used, reproduced or transmitted in any manner without express written permission from Microsoft Corporation.",
				"entityType": "Address",
				"matchCodes": [
					"Good"
				],
				"name": "1312 Maple St, Vancouver, BC V6J 3R9, Canada",
				"statusCode": 200,
				"statusDescription": "OK",
				"traceId": "b10a4523ed9c428cb6c16c14ea0122d3|BN20320521|7.7.0.0|",
				"addressLine": "1312 Maple St",
				"adminDistrict": "BC",
				"adminDistrict2": "Greater Vancouver",
				"countryRegion": "Canada",
				"formattedAddress": "1312 Maple St, Vancouver, BC V6J 3R9, Canada",
				"locality": "Vancouver",
				"neighborhood": "Kitsilano",
				"postalCode": "V6J 3R9"
			},
			"geometry": {
				"type": "Point",
				"coordinates": [
					-123.1499268,
					49.2742191
				]
			},
			"bbox": [
				-123.1516498,
				49.273095,
				-123.1482038,
				49.2753433
			]
		}
	]
}
