{
	"type": "FeatureCollection",
	"features": [
		{
			"type": "Feature",
			"properties": {
				"confidence": 9,
				"authenticationResultCode": "ValidCredentials",
				"brandLogoUri": "http://dev.virtualearth.net/Branding/logo_powered_by.png",
				"copyright": "Copyright © 2017 Microsoft and its suppliers. All rights reserved. This API cannot be accessed and the content and any results may not be used, reproduced or transmitted in any manner without express written permission from Microsoft Corporation.",
				"entityType": "Address",
				"matchCodes": [
					"Good"
				],
				"name": "132 RTE-132 O, Nouvelle, QC G0C 2E0, Canada",
				"statusCode": 200,
				"statusDescription": "OK",
				"traceId": "785dde73730a41e2857eaeb4e934c473|BN20121762|7.7.0.0|",
				"addressLine": "132 RTE-132 O",
				"adminDistrict": "QC",
				"adminDistrict2": "Avignon",
				"countryRegion": "Canada",
				"formattedAddress": "132 RTE-132 O, Nouvelle, QC G0C 2E0, Canada",
				"locality": "Nouvelle",
				"postalCode": "G0C 2E0"
			},
			"geometry": {
				"type": "Point",
				"coordinates": [
					-66.3241475,
					48.1507972
				]
			},
			"bbox": [
				-66.3258324,
				48.149673,
				-66.3224625,
				48.1519213
			]
		}
	]
}
