{
	"type": "FeatureCollection",
	"features": [
		{
			"type": "Feature",
			"properties": {
				"confidence": 9,
				"authenticationResultCode": "ValidCredentials",
				"brandLogoUri": "http://dev.virtualearth.net/Branding/logo_powered_by.png",
				"copyright": "Copyright © 2017 Microsoft and its suppliers. All rights reserved. This API cannot be accessed and the content and any results may not be used, reproduced or transmitted in any manner without express written permission from Microsoft Corporation.",
				"entityType": "Address",
				"matchCodes": [
					"Good"
				],
				"name": "132 Rue Industrielle, Albanel, QC G8M 3H9, Canada",
				"statusCode": 200,
				"statusDescription": "OK",
				"traceId": "26d742e9afbf416eabab648b85721250|BN20260223|7.7.0.0|",
				"addressLine": "132 Rue Industrielle",
				"adminDistrict": "QC",
				"adminDistrict2": "Maria-Chapdelaine",
				"countryRegion": "Canada",
				"formattedAddress": "132 Rue Industrielle, Albanel, QC G8M 3H9, Canada",
				"locality": "Albanel",
				"postalCode": "G8M 3H9"
			},
			"geometry": {
				"type": "Point",
				"coordinates": [
					-72.44376,
					48.88662
				]
			},
			"bbox": [
				-72.4454696,
				48.8854958,
				-72.4420504,
				48.8877442
			]
		}
	]
}
