{
	"type": "FeatureCollection",
	"features": [
		{
			"type": "Feature",
			"properties": {
				"confidence": 9,
				"authenticationResultCode": "ValidCredentials",
				"brandLogoUri": "http://dev.virtualearth.net/Branding/logo_powered_by.png",
				"copyright": "Copyright © 2017 Microsoft and its suppliers. All rights reserved. This API cannot be accessed and the content and any results may not be used, reproduced or transmitted in any manner without express written permission from Microsoft Corporation.",
				"entityType": "Address",
				"matchCodes": [
					"Good"
				],
				"name": "1320 E 3rd Ave, Vancouver, BC V5N 5R8, Canada",
				"statusCode": 200,
				"statusDescription": "OK",
				"traceId": "835f1bb4e32c4445b1910f55366a4791|BN20121762|7.7.0.0|",
				"addressLine": "1320 E 3rd Ave",
				"adminDistrict": "BC",
				"adminDistrict2": "Greater Vancouver",
				"countryRegion": "Canada",
				"formattedAddress": "1320 E 3rd Ave, Vancouver, BC V5N 5R8, Canada",
				"locality": "Vancouver",
				"neighborhood": "Grandview-Woodland",
				"postalCode": "V5N 5R8"
			},
			"geometry": {
				"type": "Point",
				"coordinates": [
					-123.07703,
					49.26741
				]
			},
			"bbox": [
				-123.0787528,
				49.2662858,
				-123.0753072,
				49.2685342
			]
		}
	]
}
