{
	"type": "FeatureCollection",
	"features": [
		{
			"type": "Feature",
			"properties": {
				"confidence": 9,
				"authenticationResultCode": "ValidCredentials",
				"brandLogoUri": "http://dev.virtualearth.net/Branding/logo_powered_by.png",
				"copyright": "Copyright © 2017 Microsoft and its suppliers. All rights reserved. This API cannot be accessed and the content and any results may not be used, reproduced or transmitted in any manner without express written permission from Microsoft Corporation.",
				"entityType": "Address",
				"matchCodes": [
					"Good"
				],
				"name": "1321 Ketch Ct, Coquitlam, BC V3K 6X7, Canada",
				"statusCode": 200,
				"statusDescription": "OK",
				"traceId": "7114dbb9d3b644ac8f7e5cd7aab90808|BN20121763|7.7.0.0|",
				"addressLine": "1321 Ketch Ct",
				"adminDistrict": "BC",
				"adminDistrict2": "Greater Vancouver",
				"countryRegion": "Canada",
				"formattedAddress": "1321 Ketch Ct, Coquitlam, BC V3K 6X7, Canada",
				"locality": "Coquitlam",
				"neighborhood": "Mayfair/Pacific Reach",
				"postalCode": "V3K 6X7"
			},
			"geometry": {
				"type": "Point",
				"coordinates": [
					-122.85397,
					49.22802
				]
			},
			"bbox": [
				-122.8556914,
				49.2268958,
				-122.8522486,
				49.2291442
			]
		}
	]
}
