{
	"type": "FeatureCollection",
	"features": [
		{
			"type": "Feature",
			"properties": {
				"confidence": 9,
				"authenticationResultCode": "ValidCredentials",
				"brandLogoUri": "http://dev.virtualearth.net/Branding/logo_powered_by.png",
				"copyright": "Copyright © 2017 Microsoft and its suppliers. All rights reserved. This API cannot be accessed and the content and any results may not be used, reproduced or transmitted in any manner without express written permission from Microsoft Corporation.",
				"entityType": "Address",
				"matchCodes": [
					"Good"
				],
				"name": "1322 W Broadway, Vancouver, BC V6H 1H2, Canada",
				"statusCode": 200,
				"statusDescription": "OK",
				"traceId": "1a270d74648e48989a3539361b58a535|BN20130521|7.7.0.0|",
				"addressLine": "1322 W Broadway",
				"adminDistrict": "BC",
				"adminDistrict2": "Greater Vancouver",
				"countryRegion": "Canada",
				"formattedAddress": "1322 W Broadway, Vancouver, BC V6H 1H2, Canada",
				"locality": "Vancouver",
				"neighborhood": "Fairview",
				"postalCode": "V6H 1H2"
			},
			"geometry": {
				"type": "Point",
				"coordinates": [
					-123.1340819,
					49.2633701
				]
			},
			"bbox": [
				-123.1358045,
				49.262246,
				-123.1323593,
				49.2644943
			]
		}
	]
}
