{
	"type": "FeatureCollection",
	"features": [
		{
			"type": "Feature",
			"properties": {
				"confidence": 9,
				"authenticationResultCode": "ValidCredentials",
				"brandLogoUri": "http://dev.virtualearth.net/Branding/logo_powered_by.png",
				"copyright": "Copyright © 2017 Microsoft and its suppliers. All rights reserved. This API cannot be accessed and the content and any results may not be used, reproduced or transmitted in any manner without express written permission from Microsoft Corporation.",
				"entityType": "Address",
				"matchCodes": [
					"Good"
				],
				"name": "1329 Bay St, Toronto, ON M5R 2C4, Canada",
				"statusCode": 200,
				"statusDescription": "OK",
				"traceId": "4cbfbfebb4824651affa20343cbae81d|BN20290118|7.7.0.0|",
				"addressLine": "1329 Bay St",
				"adminDistrict": "ON",
				"adminDistrict2": "Toronto",
				"countryRegion": "Canada",
				"formattedAddress": "1329 Bay St, Toronto, ON M5R 2C4, Canada",
				"locality": "Toronto",
				"neighborhood": "Annex",
				"postalCode": "M5R 2C4"
			},
			"geometry": {
				"type": "Point",
				"coordinates": [
					-79.39039,
					43.67279
				]
			},
			"bbox": [
				-79.3919442,
				43.6716658,
				-79.3888358,
				43.6739142
			]
		}
	]
}
