{
	"type": "FeatureCollection",
	"features": [
		{
			"type": "Feature",
			"properties": {
				"confidence": 9,
				"authenticationResultCode": "ValidCredentials",
				"brandLogoUri": "http://dev.virtualearth.net/Branding/logo_powered_by.png",
				"copyright": "Copyright © 2017 Microsoft and its suppliers. All rights reserved. This API cannot be accessed and the content and any results may not be used, reproduced or transmitted in any manner without express written permission from Microsoft Corporation.",
				"entityType": "Address",
				"matchCodes": [
					"Good"
				],
				"name": "133 Lahave St, Bridgewater, NS B4V 2T6, Canada",
				"statusCode": 200,
				"statusDescription": "OK",
				"traceId": "f0c7e9100d1f4b3bb85e25f078f90d01|BN20200239|7.7.0.0|",
				"addressLine": "133 Lahave St",
				"adminDistrict": "NS",
				"adminDistrict2": "Lunenburg",
				"countryRegion": "Canada",
				"formattedAddress": "133 Lahave St, Bridgewater, NS B4V 2T6, Canada",
				"locality": "Bridgewater",
				"postalCode": "B4V 2T6"
			},
			"geometry": {
				"type": "Point",
				"coordinates": [
					-64.50427,
					44.37219
				]
			},
			"bbox": [
				-64.5058427,
				44.3710658,
				-64.5026973,
				44.3733142
			]
		}
	]
}
