{
	"type": "FeatureCollection",
	"features": [
		{
			"type": "Feature",
			"properties": {
				"confidence": 9,
				"authenticationResultCode": "ValidCredentials",
				"brandLogoUri": "http://dev.virtualearth.net/Branding/logo_powered_by.png",
				"copyright": "Copyright © 2017 Microsoft and its suppliers. All rights reserved. This API cannot be accessed and the content and any results may not be used, reproduced or transmitted in any manner without express written permission from Microsoft Corporation.",
				"entityType": "Address",
				"matchCodes": [
					"Good"
				],
				"name": "1330 Courtneypark Dr E, Mississauga, ON L5T 1K5, Canada",
				"statusCode": 200,
				"statusDescription": "OK",
				"traceId": "d70ba26084be4282a61c8ebb90cb3bc4|BN20130422|7.7.0.0|",
				"addressLine": "1330 Courtneypark Dr E",
				"adminDistrict": "ON",
				"adminDistrict2": "Peel",
				"countryRegion": "Canada",
				"formattedAddress": "1330 Courtneypark Dr E, Mississauga, ON L5T 1K5, Canada",
				"locality": "Mississauga",
				"postalCode": "L5T 1K5"
			},
			"geometry": {
				"type": "Point",
				"coordinates": [
					-79.65978,
					43.6606
				]
			},
			"bbox": [
				-79.6613339,
				43.6594758,
				-79.6582261,
				43.6617242
			]
		}
	]
}
