{
	"type": "FeatureCollection",
	"features": [
		{
			"type": "Feature",
			"properties": {
				"confidence": 9,
				"authenticationResultCode": "ValidCredentials",
				"brandLogoUri": "http://dev.virtualearth.net/Branding/logo_powered_by.png",
				"copyright": "Copyright © 2017 Microsoft and its suppliers. All rights reserved. This API cannot be accessed and the content and any results may not be used, reproduced or transmitted in any manner without express written permission from Microsoft Corporation.",
				"entityType": "Address",
				"matchCodes": [
					"Good"
				],
				"name": "13340 St Albert Trl NW, Edmonton, AB T5L 4P6, Canada",
				"statusCode": 200,
				"statusDescription": "OK",
				"traceId": "3a12febf9bf84eb49605a44d8e29ce9e|BN20290118|7.7.0.0|",
				"addressLine": "13340 St Albert Trl NW",
				"adminDistrict": "AB",
				"adminDistrict2": "Alberta",
				"countryRegion": "Canada",
				"formattedAddress": "13340 St Albert Trl NW, Edmonton, AB T5L 4P6, Canada",
				"locality": "Edmonton",
				"neighborhood": "Bonaventure Industrial",
				"postalCode": "T5L 4P6"
			},
			"geometry": {
				"type": "Point",
				"coordinates": [
					-113.57101,
					53.59401
				]
			},
			"bbox": [
				-113.5729041,
				53.5928858,
				-113.5691159,
				53.5951342
			]
		}
	]
}
