{
	"type": "FeatureCollection",
	"features": [
		{
			"type": "Feature",
			"properties": {
				"confidence": 9,
				"authenticationResultCode": "ValidCredentials",
				"brandLogoUri": "http://dev.virtualearth.net/Branding/logo_powered_by.png",
				"copyright": "Copyright © 2017 Microsoft and its suppliers. All rights reserved. This API cannot be accessed and the content and any results may not be used, reproduced or transmitted in any manner without express written permission from Microsoft Corporation.",
				"entityType": "Address",
				"matchCodes": [
					"Good"
				],
				"name": "134 Hubman Lndg, Canmore, AB T1W 3L3, Canada",
				"statusCode": 200,
				"statusDescription": "OK",
				"traceId": "579660632be14826b9e672be552d3bdf|BN20130431|7.7.0.0|",
				"addressLine": "134 Hubman Lndg",
				"adminDistrict": "AB",
				"adminDistrict2": "Alberta",
				"countryRegion": "Canada",
				"formattedAddress": "134 Hubman Lndg, Canmore, AB T1W 3L3, Canada",
				"locality": "Canmore",
				"postalCode": "T1W 3L3"
			},
			"geometry": {
				"type": "Point",
				"coordinates": [
					-115.3269201,
					51.0533537
				]
			},
			"bbox": [
				-115.3287084,
				51.0522296,
				-115.3251317,
				51.0544779
			]
		}
	]
}
