{
	"type": "FeatureCollection",
	"features": [
		{
			"type": "Feature",
			"properties": {
				"confidence": 9,
				"authenticationResultCode": "ValidCredentials",
				"brandLogoUri": "http://dev.virtualearth.net/Branding/logo_powered_by.png",
				"copyright": "Copyright © 2017 Microsoft and its suppliers. All rights reserved. This API cannot be accessed and the content and any results may not be used, reproduced or transmitted in any manner without express written permission from Microsoft Corporation.",
				"entityType": "Address",
				"matchCodes": [
					"Good"
				],
				"name": "134 Albert St, Kingston, ON K7L 3V2, Canada",
				"statusCode": 200,
				"statusDescription": "OK",
				"traceId": "2e3916be469f4afc9a248689680c7a1f|BN20250135|7.7.0.0|",
				"addressLine": "134 Albert St",
				"adminDistrict": "ON",
				"adminDistrict2": "Frontenac",
				"countryRegion": "Canada",
				"formattedAddress": "134 Albert St, Kingston, ON K7L 3V2, Canada",
				"locality": "Kingston",
				"neighborhood": "Alwington",
				"postalCode": "K7L 3V2"
			},
			"geometry": {
				"type": "Point",
				"coordinates": [
					-76.50005,
					44.22576
				]
			},
			"bbox": [
				-76.5016187,
				44.2246358,
				-76.4984813,
				44.2268842
			]
		}
	]
}
