{
	"type": "FeatureCollection",
	"features": [
		{
			"type": "Feature",
			"properties": {
				"confidence": 9,
				"authenticationResultCode": "ValidCredentials",
				"brandLogoUri": "http://dev.virtualearth.net/Branding/logo_powered_by.png",
				"copyright": "Copyright © 2017 Microsoft and its suppliers. All rights reserved. This API cannot be accessed and the content and any results may not be used, reproduced or transmitted in any manner without express written permission from Microsoft Corporation.",
				"entityType": "Address",
				"matchCodes": [
					"Good"
				],
				"name": "1341 Henderson Hwy, Winnipeg, MB R2G 1M5, Canada",
				"statusCode": 200,
				"statusDescription": "OK",
				"traceId": "556eb77ee1ec4b7fa2aa13b184a92f9d|BN20121762|7.7.0.0|",
				"addressLine": "1341 Henderson Hwy",
				"adminDistrict": "MB",
				"adminDistrict2": "Manitoba",
				"countryRegion": "Canada",
				"formattedAddress": "1341 Henderson Hwy, Winnipeg, MB R2G 1M5, Canada",
				"locality": "Winnipeg",
				"neighborhood": "Rossmere-A",
				"postalCode": "R2G 1M5"
			},
			"geometry": {
				"type": "Point",
				"coordinates": [
					-97.0877877,
					49.9433012
				]
			},
			"bbox": [
				-97.0895345,
				49.942177,
				-97.0860409,
				49.9444253
			]
		}
	]
}
