{
	"type": "FeatureCollection",
	"features": [
		{
			"type": "Feature",
			"properties": {
				"confidence": 9,
				"authenticationResultCode": "ValidCredentials",
				"brandLogoUri": "http://dev.virtualearth.net/Branding/logo_powered_by.png",
				"copyright": "Copyright © 2017 Microsoft and its suppliers. All rights reserved. This API cannot be accessed and the content and any results may not be used, reproduced or transmitted in any manner without express written permission from Microsoft Corporation.",
				"entityType": "Address",
				"matchCodes": [
					"Good"
				],
				"name": "1345 Cliveden Ave, Delta, BC V3M 6C7, Canada",
				"statusCode": 200,
				"statusDescription": "OK",
				"traceId": "94e432d259d9491e99469d6f024e0db3|BN20210145|7.7.0.0|",
				"addressLine": "1345 Cliveden Ave",
				"adminDistrict": "BC",
				"adminDistrict2": "Greater Vancouver",
				"countryRegion": "Canada",
				"formattedAddress": "1345 Cliveden Ave, Delta, BC V3M 6C7, Canada",
				"locality": "Delta",
				"postalCode": "V3M 6C7"
			},
			"geometry": {
				"type": "Point",
				"coordinates": [
					-122.95762,
					49.16931
				]
			},
			"bbox": [
				-122.9593393,
				49.1681858,
				-122.9559007,
				49.1704342
			]
		}
	]
}
