{
	"type": "FeatureCollection",
	"features": [
		{
			"type": "Feature",
			"properties": {
				"confidence": 9,
				"authenticationResultCode": "ValidCredentials",
				"brandLogoUri": "http://dev.virtualearth.net/Branding/logo_powered_by.png",
				"copyright": "Copyright © 2017 Microsoft and its suppliers. All rights reserved. This API cannot be accessed and the content and any results may not be used, reproduced or transmitted in any manner without express written permission from Microsoft Corporation.",
				"entityType": "Address",
				"matchCodes": [
					"Good"
				],
				"name": "135 Bothwell St, Chatham-Kent, ON N7M, Canada",
				"statusCode": 200,
				"statusDescription": "OK",
				"traceId": "1a7c36e720ca45d0b7c34438b9c1bc41|BN20200137|7.7.0.0|",
				"addressLine": "135 Bothwell St",
				"adminDistrict": "ON",
				"adminDistrict2": "Chatham-Kent",
				"countryRegion": "Canada",
				"formattedAddress": "135 Bothwell St, Chatham-Kent, ON N7M, Canada",
				"locality": "Chatham-Kent",
				"neighborhood": "Chatham",
				"postalCode": "N7M 5K5"
			},
			"geometry": {
				"type": "Point",
				"coordinates": [
					-82.2017,
					42.38476
				]
			},
			"bbox": [
				-82.2032219,
				42.3836358,
				-82.2001781,
				42.3858842
			]
		}
	]
}
