{
	"type": "FeatureCollection",
	"features": [
		{
			"type": "Feature",
			"properties": {
				"confidence": 9,
				"authenticationResultCode": "ValidCredentials",
				"brandLogoUri": "http://dev.virtualearth.net/Branding/logo_powered_by.png",
				"copyright": "Copyright © 2017 Microsoft and its suppliers. All rights reserved. This API cannot be accessed and the content and any results may not be used, reproduced or transmitted in any manner without express written permission from Microsoft Corporation.",
				"entityType": "Address",
				"matchCodes": [
					"Good"
				],
				"name": "1350 Mt Pleasant Rd, Toronto, ON M4N 2T3, Canada",
				"statusCode": 200,
				"statusDescription": "OK",
				"traceId": "6f427da99de344dea1f20f59421b0588|BN20130719|7.7.0.0|",
				"addressLine": "1350 Mt Pleasant Rd",
				"adminDistrict": "ON",
				"adminDistrict2": "Toronto",
				"countryRegion": "Canada",
				"formattedAddress": "1350 Mt Pleasant Rd, Toronto, ON M4N 2T3, Canada",
				"locality": "Toronto",
				"neighborhood": "Lawrence Park South",
				"postalCode": "M4N 2T3"
			},
			"geometry": {
				"type": "Point",
				"coordinates": [
					-79.39619,
					43.72281
				]
			},
			"bbox": [
				-79.3977455,
				43.7216858,
				-79.3946345,
				43.7239342
			]
		}
	]
}
