{
	"type": "FeatureCollection",
	"features": [
		{
			"type": "Feature",
			"properties": {
				"confidence": 9,
				"authenticationResultCode": "ValidCredentials",
				"brandLogoUri": "http://dev.virtualearth.net/Branding/logo_powered_by.png",
				"copyright": "Copyright © 2017 Microsoft and its suppliers. All rights reserved. This API cannot be accessed and the content and any results may not be used, reproduced or transmitted in any manner without express written permission from Microsoft Corporation.",
				"entityType": "Address",
				"matchCodes": [
					"Good"
				],
				"name": "13540 97 St NW, Edmonton, AB T5E 4E2, Canada",
				"statusCode": 200,
				"statusDescription": "OK",
				"traceId": "99ff78df154b4b78bf3e6f472ca7cf6a|BN20250135|7.7.0.0|",
				"addressLine": "13540 97 St NW",
				"adminDistrict": "AB",
				"adminDistrict2": "Alberta",
				"countryRegion": "Canada",
				"formattedAddress": "13540 97 St NW, Edmonton, AB T5E 4E2, Canada",
				"locality": "Edmonton",
				"neighborhood": "Rosslyn",
				"postalCode": "T5E 4E2"
			},
			"geometry": {
				"type": "Point",
				"coordinates": [
					-113.49302,
					53.5976
				]
			},
			"bbox": [
				-113.4949143,
				53.5964758,
				-113.4911257,
				53.5987242
			]
		}
	]
}
