{
	"type": "FeatureCollection",
	"features": [
		{
			"type": "Feature",
			"properties": {
				"confidence": 9,
				"authenticationResultCode": "ValidCredentials",
				"brandLogoUri": "http://dev.virtualearth.net/Branding/logo_powered_by.png",
				"copyright": "Copyright © 2017 Microsoft and its suppliers. All rights reserved. This API cannot be accessed and the content and any results may not be used, reproduced or transmitted in any manner without express written permission from Microsoft Corporation.",
				"entityType": "Address",
				"matchCodes": [
					"Good"
				],
				"name": "136 Hodgson Rd, Fredericton, NB E3C 2G4, Canada",
				"statusCode": 200,
				"statusDescription": "OK",
				"traceId": "a62dcdd665864284b6bdae2e4211365b|BN20160335|7.7.0.0|",
				"addressLine": "136 Hodgson Rd",
				"adminDistrict": "NB",
				"adminDistrict2": "York",
				"countryRegion": "Canada",
				"formattedAddress": "136 Hodgson Rd, Fredericton, NB E3C 2G4, Canada",
				"locality": "Fredericton",
				"postalCode": "E3C 2G4"
			},
			"geometry": {
				"type": "Point",
				"coordinates": [
					-66.62161,
					45.91367
				]
			},
			"bbox": [
				-66.6232258,
				45.9125458,
				-66.6199942,
				45.9147942
			]
		}
	]
}
