{
	"type": "FeatureCollection",
	"features": [
		{
			"type": "Feature",
			"properties": {
				"confidence": 9,
				"authenticationResultCode": "ValidCredentials",
				"brandLogoUri": "http://dev.virtualearth.net/Branding/logo_powered_by.png",
				"copyright": "Copyright © 2017 Microsoft and its suppliers. All rights reserved. This API cannot be accessed and the content and any results may not be used, reproduced or transmitted in any manner without express written permission from Microsoft Corporation.",
				"entityType": "Address",
				"matchCodes": [
					"Good"
				],
				"name": "136 Oriole Ave, Kanata, ON K2L 2G2, Canada",
				"statusCode": 200,
				"statusDescription": "OK",
				"traceId": "442bae91435745639c7e425bd477f225|BN20280152|7.7.0.0|",
				"addressLine": "136 Oriole Ave",
				"adminDistrict": "ON",
				"adminDistrict2": "Ottawa",
				"countryRegion": "Canada",
				"formattedAddress": "136 Oriole Ave, Kanata, ON K2L 2G2, Canada",
				"locality": "Ottawa",
				"neighborhood": "Kanata",
				"postalCode": "K2L 2G2"
			},
			"geometry": {
				"type": "Point",
				"coordinates": [
					-75.88226,
					45.29462
				]
			},
			"bbox": [
				-75.883858,
				45.2934958,
				-75.880662,
				45.2957442
			]
		}
	]
}
