{
	"type": "FeatureCollection",
	"features": [
		{
			"type": "Feature",
			"properties": {
				"confidence": 9,
				"authenticationResultCode": "ValidCredentials",
				"brandLogoUri": "http://dev.virtualearth.net/Branding/logo_powered_by.png",
				"copyright": "Copyright © 2017 Microsoft and its suppliers. All rights reserved. This API cannot be accessed and the content and any results may not be used, reproduced or transmitted in any manner without express written permission from Microsoft Corporation.",
				"entityType": "Address",
				"matchCodes": [
					"Good"
				],
				"name": "13700 International Pl, Richmond, BC V6V 2X8, Canada",
				"statusCode": 200,
				"statusDescription": "OK",
				"traceId": "bb398a292e8c4d44a6748e8958940ae9|BN20260223|7.7.0.0|",
				"addressLine": "13700 International Pl",
				"adminDistrict": "BC",
				"adminDistrict2": "Greater Vancouver",
				"countryRegion": "Canada",
				"formattedAddress": "13700 International Pl, Richmond, BC V6V 2X8, Canada",
				"locality": "Richmond",
				"neighborhood": "East Cambie",
				"postalCode": "V6V 2X8"
			},
			"geometry": {
				"type": "Point",
				"coordinates": [
					-123.07046,
					49.17328
				]
			},
			"bbox": [
				-123.0721795,
				49.1721558,
				-123.0687405,
				49.1744042
			]
		}
	]
}
