{
	"type": "FeatureCollection",
	"features": [
		{
			"type": "Feature",
			"properties": {
				"confidence": 9,
				"authenticationResultCode": "ValidCredentials",
				"brandLogoUri": "http://dev.virtualearth.net/Branding/logo_powered_by.png",
				"copyright": "Copyright © 2017 Microsoft and its suppliers. All rights reserved. This API cannot be accessed and the content and any results may not be used, reproduced or transmitted in any manner without express written permission from Microsoft Corporation.",
				"entityType": "Address",
				"matchCodes": [
					"Good"
				],
				"name": "1140 Burnhamthorpe Rd W, Mississauga, ON L5C 0A3, Canada",
				"statusCode": 200,
				"statusDescription": "OK",
				"traceId": "90343ea391874f6fb947f11b169b10ef|BN20190642|7.7.0.0|",
				"addressLine": "1140 Burnhamthorpe Rd W",
				"adminDistrict": "ON",
				"adminDistrict2": "Peel",
				"countryRegion": "Canada",
				"formattedAddress": "1140 Burnhamthorpe Rd W, Mississauga, ON L5C 0A3, Canada",
				"locality": "Mississauga",
				"neighborhood": "Erindale",
				"postalCode": "L5C 0A3"
			},
			"geometry": {
				"type": "Point",
				"coordinates": [
					-79.66216,
					43.56895
				]
			},
			"bbox": [
				-79.6637115,
				43.5678258,
				-79.6606085,
				43.5700742
			]
		}
	]
}
