{
	"type": "FeatureCollection",
	"features": [
		{
			"type": "Feature",
			"properties": {
				"confidence": 9,
				"authenticationResultCode": "ValidCredentials",
				"brandLogoUri": "http://dev.virtualearth.net/Branding/logo_powered_by.png",
				"copyright": "Copyright © 2017 Microsoft and its suppliers. All rights reserved. This API cannot be accessed and the content and any results may not be used, reproduced or transmitted in any manner without express written permission from Microsoft Corporation.",
				"entityType": "Address",
				"matchCodes": [
					"Good"
				],
				"name": "1372 Chemin Oka, Oka, QC J0N, Canada",
				"statusCode": 200,
				"statusDescription": "OK",
				"traceId": "9b57149e000b4b6f9bf27f2464f8b034|BN20190653|7.7.0.0|",
				"addressLine": "1372 Chemin Oka",
				"adminDistrict": "QC",
				"adminDistrict2": "Deux-Montagnes",
				"countryRegion": "Canada",
				"formattedAddress": "1372 Chemin Oka, Oka, QC J0N, Canada",
				"locality": "Oka",
				"neighborhood": "Le Coq-Rond",
				"postalCode": "J0N 1E0"
			},
			"geometry": {
				"type": "Point",
				"coordinates": [
					-74.02427,
					45.4978399
				]
			},
			"bbox": [
				-74.0258738,
				45.4967157,
				-74.0226662,
				45.4989641
			]
		}
	]
}
