{
	"type": "FeatureCollection",
	"features": [
		{
			"type": "Feature",
			"properties": {
				"confidence": 9,
				"authenticationResultCode": "ValidCredentials",
				"brandLogoUri": "http://dev.virtualearth.net/Branding/logo_powered_by.png",
				"copyright": "Copyright © 2017 Microsoft and its suppliers. All rights reserved. This API cannot be accessed and the content and any results may not be used, reproduced or transmitted in any manner without express written permission from Microsoft Corporation.",
				"entityType": "Address",
				"matchCodes": [
					"Good"
				],
				"name": "1373 Confederation St, Sarnia, ON N7S 5P1, Canada",
				"statusCode": 200,
				"statusDescription": "OK",
				"traceId": "71799c24cf344d6c8713ac50019c6392|BN20320521|7.7.0.0|",
				"addressLine": "1373 Confederation St",
				"adminDistrict": "ON",
				"adminDistrict2": "Lambton",
				"countryRegion": "Canada",
				"formattedAddress": "1373 Confederation St, Sarnia, ON N7S 5P1, Canada",
				"locality": "Sarnia",
				"postalCode": "N7S 5P1"
			},
			"geometry": {
				"type": "Point",
				"coordinates": [
					-82.3556027,
					42.9600086
				]
			},
			"bbox": [
				-82.3571388,
				42.9588844,
				-82.3540666,
				42.9611327
			]
		}
	]
}
