{
	"type": "FeatureCollection",
	"features": [
		{
			"type": "Feature",
			"properties": {
				"confidence": 9,
				"authenticationResultCode": "ValidCredentials",
				"brandLogoUri": "http://dev.virtualearth.net/Branding/logo_powered_by.png",
				"copyright": "Copyright © 2017 Microsoft and its suppliers. All rights reserved. This API cannot be accessed and the content and any results may not be used, reproduced or transmitted in any manner without express written permission from Microsoft Corporation.",
				"entityType": "Address",
				"matchCodes": [
					"Good"
				],
				"name": "1375 Southdown Rd, Mississauga, ON L5J 2Z1, Canada",
				"statusCode": 200,
				"statusDescription": "OK",
				"traceId": "8d2387416a664ae987a0152d5b749c75|BN20190653|7.7.0.0|",
				"addressLine": "1375 Southdown Rd",
				"adminDistrict": "ON",
				"adminDistrict2": "Peel",
				"countryRegion": "Canada",
				"formattedAddress": "1375 Southdown Rd, Mississauga, ON L5J 2Z1, Canada",
				"locality": "Mississauga",
				"neighborhood": "Lorne Park",
				"postalCode": "L5J 2Z1"
			},
			"geometry": {
				"type": "Point",
				"coordinates": [
					-79.63968,
					43.5186599
				]
			},
			"bbox": [
				-79.6412302,
				43.5175357,
				-79.6381298,
				43.5197841
			]
		}
	]
}
