{
	"type": "FeatureCollection",
	"features": [
		{
			"type": "Feature",
			"properties": {
				"confidence": 9,
				"authenticationResultCode": "ValidCredentials",
				"brandLogoUri": "http://dev.virtualearth.net/Branding/logo_powered_by.png",
				"copyright": "Copyright © 2017 Microsoft and its suppliers. All rights reserved. This API cannot be accessed and the content and any results may not be used, reproduced or transmitted in any manner without express written permission from Microsoft Corporation.",
				"entityType": "Address",
				"matchCodes": [
					"Good"
				],
				"name": "1376 Bank St, Ottawa, ON K1H 7Y3, Canada",
				"statusCode": 200,
				"statusDescription": "OK",
				"traceId": "aa1194bd1b5d43b3ab19855b4befdcf2|BN20280152|7.7.0.0|",
				"addressLine": "1376 Bank St",
				"adminDistrict": "ON",
				"adminDistrict2": "Ottawa",
				"countryRegion": "Canada",
				"formattedAddress": "1376 Bank St, Ottawa, ON K1H 7Y3, Canada",
				"locality": "Ottawa",
				"neighborhood": "Billings Bridge-Alta Vista",
				"postalCode": "K1H 7Y3"
			},
			"geometry": {
				"type": "Point",
				"coordinates": [
					-75.673,
					45.3846599
				]
			},
			"bbox": [
				-75.6746006,
				45.3835357,
				-75.6713994,
				45.3857841
			]
		}
	]
}
