{
	"type": "FeatureCollection",
	"features": [
		{
			"type": "Feature",
			"properties": {
				"confidence": 9,
				"authenticationResultCode": "ValidCredentials",
				"brandLogoUri": "http://dev.virtualearth.net/Branding/logo_powered_by.png",
				"copyright": "Copyright © 2017 Microsoft and its suppliers. All rights reserved. This API cannot be accessed and the content and any results may not be used, reproduced or transmitted in any manner without express written permission from Microsoft Corporation.",
				"entityType": "Address",
				"matchCodes": [
					"Good"
				],
				"name": "138 Sixteen Mile Dr, Oakville, ON L6M 0T7, Canada",
				"statusCode": 200,
				"statusDescription": "OK",
				"traceId": "2edae7708a144205a35eba651ae2bd51|BN20130422|7.7.0.0|",
				"addressLine": "138 Sixteen Mile Dr",
				"adminDistrict": "ON",
				"adminDistrict2": "Halton",
				"countryRegion": "Canada",
				"formattedAddress": "138 Sixteen Mile Dr, Oakville, ON L6M 0T7, Canada",
				"locality": "Oakville",
				"postalCode": "L6M 0T7"
			},
			"geometry": {
				"type": "Point",
				"coordinates": [
					-79.73596,
					43.47788
				]
			},
			"bbox": [
				-79.7375092,
				43.4767558,
				-79.7344108,
				43.4790042
			]
		}
	]
}
