{
	"type": "FeatureCollection",
	"features": [
		{
			"type": "Feature",
			"properties": {
				"confidence": 9,
				"authenticationResultCode": "ValidCredentials",
				"brandLogoUri": "http://dev.virtualearth.net/Branding/logo_powered_by.png",
				"copyright": "Copyright © 2017 Microsoft and its suppliers. All rights reserved. This API cannot be accessed and the content and any results may not be used, reproduced or transmitted in any manner without express written permission from Microsoft Corporation.",
				"entityType": "Address",
				"matchCodes": [
					"Good"
				],
				"name": "14 Drummond St, Etobicoke, ON M8V 1Y8, Canada",
				"statusCode": 200,
				"statusDescription": "OK",
				"traceId": "0e5d2212679a4e6e9304c75de9b5d3d1|BN20220145|7.7.0.0|",
				"addressLine": "14 Drummond St",
				"adminDistrict": "ON",
				"adminDistrict2": "Toronto",
				"countryRegion": "Canada",
				"formattedAddress": "14 Drummond St, Etobicoke, ON M8V 1Y8, Canada",
				"locality": "Toronto",
				"neighborhood": "Mimico",
				"postalCode": "M8V 1Y8"
			},
			"geometry": {
				"type": "Point",
				"coordinates": [
					-79.49862,
					43.61312
				]
			},
			"bbox": [
				-79.5001727,
				43.6119958,
				-79.4970673,
				43.6142442
			]
		}
	]
}
