{
	"type": "FeatureCollection",
	"features": [
		{
			"type": "Feature",
			"properties": {
				"confidence": 9,
				"authenticationResultCode": "ValidCredentials",
				"brandLogoUri": "http://dev.virtualearth.net/Branding/logo_powered_by.png",
				"copyright": "Copyright © 2017 Microsoft and its suppliers. All rights reserved. This API cannot be accessed and the content and any results may not be used, reproduced or transmitted in any manner without express written permission from Microsoft Corporation.",
				"entityType": "Address",
				"matchCodes": [
					"Good"
				],
				"name": "14 Rue de Montgolfier, Boucherville, QC J4B 7Y4, Canada",
				"statusCode": 200,
				"statusDescription": "OK",
				"traceId": "83e3dd065ee34fa58e555c721a2d0385|BN20200239|7.7.0.0|",
				"addressLine": "14 Rue de Montgolfier",
				"adminDistrict": "QC",
				"adminDistrict2": "Longueuil",
				"countryRegion": "Canada",
				"formattedAddress": "14 Rue de Montgolfier, Boucherville, QC J4B 7Y4, Canada",
				"locality": "Boucherville",
				"postalCode": "J4B 7Y4"
			},
			"geometry": {
				"type": "Point",
				"coordinates": [
					-73.4282,
					45.55463
				]
			},
			"bbox": [
				-73.4298054,
				45.5535058,
				-73.4265946,
				45.5557542
			]
		}
	]
}
