{
	"type": "FeatureCollection",
	"features": [
		{
			"type": "Feature",
			"properties": {
				"confidence": 7,
				"authenticationResultCode": "ValidCredentials",
				"brandLogoUri": "http://dev.virtualearth.net/Branding/logo_powered_by.png",
				"copyright": "Copyright © 2017 Microsoft and its suppliers. All rights reserved. This API cannot be accessed and the content and any results may not be used, reproduced or transmitted in any manner without express written permission from Microsoft Corporation.",
				"entityType": "RoadBlock",
				"matchCodes": [
					"UpHierarchy"
				],
				"name": "2nd Ave W, Owen Sound, ON N4K, Canada",
				"statusCode": 200,
				"statusDescription": "OK",
				"traceId": "94273b0b3d0a493a9a776caab4cf9431|BN20121763|7.7.0.0|",
				"addressLine": "2nd Ave W",
				"adminDistrict": "ON",
				"adminDistrict2": "Grey",
				"countryRegion": "Canada",
				"formattedAddress": "2nd Ave W, Owen Sound, ON N4K, Canada",
				"locality": "Owen Sound",
				"postalCode": "N4K 6T6"
			},
			"geometry": {
				"type": "Point",
				"coordinates": [
					-80.94598,
					44.56679
				]
			},
			"bbox": [
				-80.94744,
				44.55069,
				-80.94273,
				44.5903
			]
		}
	]
}
