{
	"type": "FeatureCollection",
	"features": [
		{
			"type": "Feature",
			"properties": {
				"confidence": 9,
				"authenticationResultCode": "ValidCredentials",
				"brandLogoUri": "http://dev.virtualearth.net/Branding/logo_powered_by.png",
				"copyright": "Copyright © 2017 Microsoft and its suppliers. All rights reserved. This API cannot be accessed and the content and any results may not be used, reproduced or transmitted in any manner without express written permission from Microsoft Corporation.",
				"entityType": "Address",
				"matchCodes": [
					"Good"
				],
				"name": "1405 31 St N, Lethbridge, AB T1H 5G8, Canada",
				"statusCode": 200,
				"statusDescription": "OK",
				"traceId": "9e2445b902794b95b9d32d756081b975|BN20220145|7.7.0.0|",
				"addressLine": "1405 31 St N",
				"adminDistrict": "AB",
				"adminDistrict2": "Alberta",
				"countryRegion": "Canada",
				"formattedAddress": "1405 31 St N, Lethbridge, AB T1H 5G8, Canada",
				"locality": "Lethbridge",
				"postalCode": "T1H 5G8"
			},
			"geometry": {
				"type": "Point",
				"coordinates": [
					-112.79368,
					49.71789
				]
			},
			"bbox": [
				-112.7954187,
				49.7167658,
				-112.7919413,
				49.7190142
			]
		}
	]
}
