{
	"type": "FeatureCollection",
	"features": [
		{
			"type": "Feature",
			"properties": {
				"confidence": 7,
				"authenticationResultCode": "ValidCredentials",
				"brandLogoUri": "http://dev.virtualearth.net/Branding/logo_powered_by.png",
				"copyright": "Copyright © 2017 Microsoft and its suppliers. All rights reserved. This API cannot be accessed and the content and any results may not be used, reproduced or transmitted in any manner without express written permission from Microsoft Corporation.",
				"entityType": "Postcode1",
				"matchCodes": [
					"UpHierarchy"
				],
				"name": "Churchill, R0B 0E0, Canada",
				"statusCode": 200,
				"statusDescription": "OK",
				"traceId": "e67613f6dfb24a03810d394809c6f2a8|BN20130442|7.7.0.0|",
				"adminDistrict": "MB",
				"countryRegion": "Canada",
				"formattedAddress": "Churchill, R0B 0E0, Canada",
				"locality": "Churchill",
				"postalCode": "R0B 0E0"
			},
			"geometry": {
				"type": "Point",
				"coordinates": [
					-94.1691589355469,
					58.7677383422852
				]
			},
			"bbox": [
				-94.1790907245309,
				58.7638756247145,
				-94.1592271465629,
				58.7716010598558
			]
		}
	]
}
