{
	"type": "FeatureCollection",
	"features": [
		{
			"type": "Feature",
			"properties": {
				"confidence": 9,
				"authenticationResultCode": "ValidCredentials",
				"brandLogoUri": "http://dev.virtualearth.net/Branding/logo_powered_by.png",
				"copyright": "Copyright © 2017 Microsoft and its suppliers. All rights reserved. This API cannot be accessed and the content and any results may not be used, reproduced or transmitted in any manner without express written permission from Microsoft Corporation.",
				"entityType": "Address",
				"matchCodes": [
					"Good"
				],
				"name": "1424 Ellice Ave, Winnipeg, MB R3G 0G4, Canada",
				"statusCode": 200,
				"statusDescription": "OK",
				"traceId": "162dfd42ffed405d84c380180943101c|BN20240253|7.7.0.0|",
				"addressLine": "1424 Ellice Ave",
				"adminDistrict": "MB",
				"adminDistrict2": "Manitoba",
				"countryRegion": "Canada",
				"formattedAddress": "1424 Ellice Ave, Winnipeg, MB R3G 0G4, Canada",
				"locality": "Winnipeg",
				"neighborhood": "Polo Park",
				"postalCode": "R3G 0G4"
			},
			"geometry": {
				"type": "Point",
				"coordinates": [
					-97.1995175,
					49.8940551
				]
			},
			"bbox": [
				-97.2012626,
				49.892931,
				-97.1977725,
				49.8951793
			]
		}
	]
}
