{
	"type": "FeatureCollection",
	"features": [
		{
			"type": "Feature",
			"properties": {
				"confidence": 9,
				"authenticationResultCode": "ValidCredentials",
				"brandLogoUri": "http://dev.virtualearth.net/Branding/logo_powered_by.png",
				"copyright": "Copyright © 2017 Microsoft and its suppliers. All rights reserved. This API cannot be accessed and the content and any results may not be used, reproduced or transmitted in any manner without express written permission from Microsoft Corporation.",
				"entityType": "Address",
				"matchCodes": [
					"Good"
				],
				"name": "1435 Rue de Kingston, Sherbrooke, QC J1H 3S9, Canada",
				"statusCode": 200,
				"statusDescription": "OK",
				"traceId": "04e209e60e954b2387a5d748d563a189|BN20130621|7.7.0.0|",
				"addressLine": "1435 Rue de Kingston",
				"adminDistrict": "QC",
				"adminDistrict2": "Sherbrooke",
				"countryRegion": "Canada",
				"formattedAddress": "1435 Rue de Kingston, Sherbrooke, QC J1H 3S9, Canada",
				"locality": "Sherbrooke",
				"postalCode": "J1H 3S9"
			},
			"geometry": {
				"type": "Point",
				"coordinates": [
					-71.90167,
					45.38492
				]
			},
			"bbox": [
				-71.9032706,
				45.3837958,
				-71.9000694,
				45.3860442
			]
		}
	]
}
