{
	"type": "FeatureCollection",
	"features": [
		{
			"type": "Feature",
			"properties": {
				"confidence": 9,
				"authenticationResultCode": "ValidCredentials",
				"brandLogoUri": "http://dev.virtualearth.net/Branding/logo_powered_by.png",
				"copyright": "Copyright © 2017 Microsoft and its suppliers. All rights reserved. This API cannot be accessed and the content and any results may not be used, reproduced or transmitted in any manner without express written permission from Microsoft Corporation.",
				"entityType": "Address",
				"matchCodes": [
					"Good"
				],
				"name": "14390 Rue Shaw, Pierrefonds, QC H9H 1J8, Canada",
				"statusCode": 200,
				"statusDescription": "OK",
				"traceId": "f49627e6fd58498cbb133f1d433760e8|BN20130423|7.7.0.0|",
				"addressLine": "14390 Rue Shaw",
				"adminDistrict": "QC",
				"adminDistrict2": "Montreal",
				"countryRegion": "Canada",
				"formattedAddress": "14390 Rue Shaw, Pierrefonds, QC H9H 1J8, Canada",
				"locality": "Montreal",
				"neighborhood": "Pierrefonds",
				"postalCode": "H9H 1J8"
			},
			"geometry": {
				"type": "Point",
				"coordinates": [
					-73.85175,
					45.48457
				]
			},
			"bbox": [
				-73.8533534,
				45.4834458,
				-73.8501466,
				45.4856942
			]
		}
	]
}
