{
	"type": "FeatureCollection",
	"features": [
		{
			"type": "Feature",
			"properties": {
				"confidence": 9,
				"authenticationResultCode": "ValidCredentials",
				"brandLogoUri": "http://dev.virtualearth.net/Branding/logo_powered_by.png",
				"copyright": "Copyright © 2017 Microsoft and its suppliers. All rights reserved. This API cannot be accessed and the content and any results may not be used, reproduced or transmitted in any manner without express written permission from Microsoft Corporation.",
				"entityType": "Address",
				"matchCodes": [
					"Good"
				],
				"name": "14403 Rue Mayo, Pierrefonds, QC H9H 1L8, Canada",
				"statusCode": 200,
				"statusDescription": "OK",
				"traceId": "385e2e255a67451a848f816e29a3204d|BN20130631|7.7.0.0|",
				"addressLine": "14403 Rue Mayo",
				"adminDistrict": "QC",
				"adminDistrict2": "Montreal",
				"countryRegion": "Canada",
				"formattedAddress": "14403 Rue Mayo, Pierrefonds, QC H9H 1L8, Canada",
				"locality": "Montreal",
				"neighborhood": "Pierrefonds",
				"postalCode": "H9H 1L8"
			},
			"geometry": {
				"type": "Point",
				"coordinates": [
					-73.85272,
					45.4819699
				]
			},
			"bbox": [
				-73.8543233,
				45.4808457,
				-73.8511167,
				45.4830941
			]
		}
	]
}
