{
	"type": "FeatureCollection",
	"features": [
		{
			"type": "Feature",
			"properties": {
				"confidence": 9,
				"authenticationResultCode": "ValidCredentials",
				"brandLogoUri": "http://dev.virtualearth.net/Branding/logo_powered_by.png",
				"copyright": "Copyright © 2017 Microsoft and its suppliers. All rights reserved. This API cannot be accessed and the content and any results may not be used, reproduced or transmitted in any manner without express written permission from Microsoft Corporation.",
				"entityType": "Address",
				"matchCodes": [
					"Good"
				],
				"name": "1440 Island Hwy, Campbell River, BC V9W 8C9, Canada",
				"statusCode": 200,
				"statusDescription": "OK",
				"traceId": "823760d7a8a747c1bf3a3207de6c10df|BN20130721|7.7.0.0|",
				"addressLine": "1440 Island Hwy",
				"adminDistrict": "BC",
				"adminDistrict2": "Strathcona",
				"countryRegion": "Canada",
				"formattedAddress": "1440 Island Hwy, Campbell River, BC V9W 8C9, Canada",
				"locality": "Campbell River",
				"postalCode": "V9W 8C9"
			},
			"geometry": {
				"type": "Point",
				"coordinates": [
					-125.251483,
					50.0343444
				]
			},
			"bbox": [
				-125.2532331,
				50.0332202,
				-125.2497328,
				50.0354685
			]
		}
	]
}
