{
	"type": "FeatureCollection",
	"features": [
		{
			"type": "Feature",
			"properties": {
				"confidence": 9,
				"authenticationResultCode": "ValidCredentials",
				"brandLogoUri": "http://dev.virtualearth.net/Branding/logo_powered_by.png",
				"copyright": "Copyright © 2017 Microsoft and its suppliers. All rights reserved. This API cannot be accessed and the content and any results may not be used, reproduced or transmitted in any manner without express written permission from Microsoft Corporation.",
				"entityType": "Address",
				"matchCodes": [
					"Good"
				],
				"name": "1447 Royal York Rd, Etobicoke, ON M9P 3V8, Canada",
				"statusCode": 200,
				"statusDescription": "OK",
				"traceId": "f1922e271a134cf087f605e618763d99|BN20320521|7.7.0.0|",
				"addressLine": "1447 Royal York Rd",
				"adminDistrict": "ON",
				"adminDistrict2": "Toronto",
				"countryRegion": "Canada",
				"formattedAddress": "1447 Royal York Rd, Etobicoke, ON M9P 3V8, Canada",
				"locality": "Toronto",
				"neighborhood": "Humber Heights-Westmount",
				"postalCode": "M9P 3V8"
			},
			"geometry": {
				"type": "Point",
				"coordinates": [
					-79.52761,
					43.68652
				]
			},
			"bbox": [
				-79.5291646,
				43.6853958,
				-79.5260554,
				43.6876442
			]
		}
	]
}
