{
	"type": "FeatureCollection",
	"features": [
		{
			"type": "Feature",
			"properties": {
				"confidence": 9,
				"authenticationResultCode": "ValidCredentials",
				"brandLogoUri": "http://dev.virtualearth.net/Branding/logo_powered_by.png",
				"copyright": "Copyright © 2017 Microsoft and its suppliers. All rights reserved. This API cannot be accessed and the content and any results may not be used, reproduced or transmitted in any manner without express written permission from Microsoft Corporation.",
				"entityType": "Address",
				"matchCodes": [
					"Good"
				],
				"name": "145 Prestwick Ave SE, Calgary, AB T2Z 3S6, Canada",
				"statusCode": 200,
				"statusDescription": "OK",
				"traceId": "0ec1fd46a0564fc58da643ee51e8072c|BN20130625|7.7.0.0|",
				"addressLine": "145 Prestwick Ave SE",
				"adminDistrict": "AB",
				"adminDistrict2": "Alberta",
				"countryRegion": "Canada",
				"formattedAddress": "145 Prestwick Ave SE, Calgary, AB T2Z 3S6, Canada",
				"locality": "Calgary",
				"neighborhood": "McKenzie Towne",
				"postalCode": "T2Z 3S6"
			},
			"geometry": {
				"type": "Point",
				"coordinates": [
					-113.96095,
					50.92206
				]
			},
			"bbox": [
				-113.9627333,
				50.9209358,
				-113.9591667,
				50.9231842
			]
		}
	]
}
