{
	"type": "FeatureCollection",
	"features": [
		{
			"type": "Feature",
			"properties": {
				"confidence": 9,
				"authenticationResultCode": "ValidCredentials",
				"brandLogoUri": "http://dev.virtualearth.net/Branding/logo_powered_by.png",
				"copyright": "Copyright © 2017 Microsoft and its suppliers. All rights reserved. This API cannot be accessed and the content and any results may not be used, reproduced or transmitted in any manner without express written permission from Microsoft Corporation.",
				"entityType": "Address",
				"matchCodes": [
					"Good"
				],
				"name": "14624 Niagara Pkwy, Niagara-on-the-Lake, ON L0S, Canada",
				"statusCode": 200,
				"statusDescription": "OK",
				"traceId": "ec2c30cb46a64f4b997628f3cc80302e|BN20181720|7.7.0.0|",
				"addressLine": "14624 Niagara Pkwy",
				"adminDistrict": "ON",
				"adminDistrict2": "Niagara",
				"countryRegion": "Canada",
				"formattedAddress": "14624 Niagara Pkwy, Niagara-on-the-Lake, ON L0S, Canada",
				"locality": "Niagara-on-the-Lake",
				"neighborhood": "Queenston",
				"postalCode": "L0S 1L0"
			},
			"geometry": {
				"type": "Point",
				"coordinates": [
					-79.05847,
					43.17104
				]
			},
			"bbox": [
				-79.0600114,
				43.1699158,
				-79.0569286,
				43.1721642
			]
		}
	]
}
