{
	"type": "FeatureCollection",
	"features": [
		{
			"type": "Feature",
			"properties": {
				"confidence": 9,
				"authenticationResultCode": "ValidCredentials",
				"brandLogoUri": "http://dev.virtualearth.net/Branding/logo_powered_by.png",
				"copyright": "Copyright © 2017 Microsoft and its suppliers. All rights reserved. This API cannot be accessed and the content and any results may not be used, reproduced or transmitted in any manner without express written permission from Microsoft Corporation.",
				"entityType": "Address",
				"matchCodes": [
					"Good"
				],
				"name": "1469 Princess St, Kingston, ON K7M 3E9, Canada",
				"statusCode": 200,
				"statusDescription": "OK",
				"traceId": "a500ce5686aa4fd58e0249a575ef6832|BN20130442|7.7.0.0|",
				"addressLine": "1469 Princess St",
				"adminDistrict": "ON",
				"adminDistrict2": "Frontenac",
				"countryRegion": "Canada",
				"formattedAddress": "1469 Princess St, Kingston, ON K7M 3E9, Canada",
				"locality": "Kingston",
				"neighborhood": "Strathcona Park",
				"postalCode": "K7M 3E9"
			},
			"geometry": {
				"type": "Point",
				"coordinates": [
					-76.53358,
					44.25216
				]
			},
			"bbox": [
				-76.5351494,
				44.2510358,
				-76.5320106,
				44.2532842
			]
		}
	]
}
