{
	"type": "FeatureCollection",
	"features": [
		{
			"type": "Feature",
			"properties": {
				"confidence": 9,
				"authenticationResultCode": "ValidCredentials",
				"brandLogoUri": "http://dev.virtualearth.net/Branding/logo_powered_by.png",
				"copyright": "Copyright © 2017 Microsoft and its suppliers. All rights reserved. This API cannot be accessed and the content and any results may not be used, reproduced or transmitted in any manner without express written permission from Microsoft Corporation.",
				"entityType": "Address",
				"matchCodes": [
					"Good"
				],
				"name": "14721 123 Ave NW, Edmonton, AB T5L 2Y6, Canada",
				"statusCode": 200,
				"statusDescription": "OK",
				"traceId": "e6fc7f1624fe40ceb914754097c20a32|BN20130620|7.7.0.0|",
				"addressLine": "14721 123 Ave NW",
				"adminDistrict": "AB",
				"adminDistrict2": "Alberta",
				"countryRegion": "Canada",
				"formattedAddress": "14721 123 Ave NW, Edmonton, AB T5L 2Y6, Canada",
				"locality": "Edmonton",
				"neighborhood": "Dominion Industrial",
				"postalCode": "T5L 2Y6"
			},
			"geometry": {
				"type": "Point",
				"coordinates": [
					-113.57443,
					53.57655
				]
			},
			"bbox": [
				-113.5763233,
				53.5754258,
				-113.5725367,
				53.5776742
			]
		}
	]
}
