{
	"type": "FeatureCollection",
	"features": [
		{
			"type": "Feature",
			"properties": {
				"confidence": 9,
				"authenticationResultCode": "ValidCredentials",
				"brandLogoUri": "http://dev.virtualearth.net/Branding/logo_powered_by.png",
				"copyright": "Copyright © 2017 Microsoft and its suppliers. All rights reserved. This API cannot be accessed and the content and any results may not be used, reproduced or transmitted in any manner without express written permission from Microsoft Corporation.",
				"entityType": "Address",
				"matchCodes": [
					"Good"
				],
				"name": "1477 Derwent Way, Delta, BC V3M 6N3, Canada",
				"statusCode": 200,
				"statusDescription": "OK",
				"traceId": "686ac29393ba49f998be40070700739b|BN20290118|7.7.0.0|",
				"addressLine": "1477 Derwent Way",
				"adminDistrict": "BC",
				"adminDistrict2": "Greater Vancouver",
				"countryRegion": "Canada",
				"formattedAddress": "1477 Derwent Way, Delta, BC V3M 6N3, Canada",
				"locality": "Delta",
				"postalCode": "V3M 6N3"
			},
			"geometry": {
				"type": "Point",
				"coordinates": [
					-122.95907,
					49.16285
				]
			},
			"bbox": [
				-122.9607891,
				49.1617258,
				-122.9573509,
				49.1639742
			]
		}
	]
}
