{
	"type": "FeatureCollection",
	"features": [
		{
			"type": "Feature",
			"properties": {
				"confidence": 9,
				"authenticationResultCode": "ValidCredentials",
				"brandLogoUri": "http://dev.virtualearth.net/Branding/logo_powered_by.png",
				"copyright": "Copyright © 2017 Microsoft and its suppliers. All rights reserved. This API cannot be accessed and the content and any results may not be used, reproduced or transmitted in any manner without express written permission from Microsoft Corporation.",
				"entityType": "Address",
				"matchCodes": [
					"Good"
				],
				"name": "1489 Hurontario St, Mississauga, ON L5G 3H7, Canada",
				"statusCode": 200,
				"statusDescription": "OK",
				"traceId": "3a5142bad06d485694c71cef98f77010|BN20121763|7.7.0.0|",
				"addressLine": "1489 Hurontario St",
				"adminDistrict": "ON",
				"adminDistrict2": "Peel",
				"countryRegion": "Canada",
				"formattedAddress": "1489 Hurontario St, Mississauga, ON L5G 3H7, Canada",
				"locality": "Mississauga",
				"neighborhood": "Mineola",
				"postalCode": "L5G 3H7"
			},
			"geometry": {
				"type": "Point",
				"coordinates": [
					-79.59443,
					43.5650199
				]
			},
			"bbox": [
				-79.5959814,
				43.5638957,
				-79.5928786,
				43.5661441
			]
		}
	]
}
