{
	"type": "FeatureCollection",
	"features": [
		{
			"type": "Feature",
			"properties": {
				"confidence": 9,
				"authenticationResultCode": "ValidCredentials",
				"brandLogoUri": "http://dev.virtualearth.net/Branding/logo_powered_by.png",
				"copyright": "Copyright © 2017 Microsoft and its suppliers. All rights reserved. This API cannot be accessed and the content and any results may not be used, reproduced or transmitted in any manner without express written permission from Microsoft Corporation.",
				"entityType": "Address",
				"matchCodes": [
					"Good"
				],
				"name": "1491 Elizabeth Ave, Kings, NS B0P, Canada",
				"statusCode": 200,
				"statusDescription": "OK",
				"traceId": "e3af80a9f7574c958528bbe84d509bdf|BN20121763|7.7.0.0|",
				"addressLine": "1491 Elizabeth Ave",
				"adminDistrict": "NS",
				"adminDistrict2": "Kings",
				"countryRegion": "Canada",
				"formattedAddress": "1491 Elizabeth Ave, Kings, NS B0P, Canada",
				"locality": "Kings",
				"neighborhood": "Kingston",
				"postalCode": "B0P 1R0"
			},
			"geometry": {
				"type": "Point",
				"coordinates": [
					-64.95406,
					44.9885499
				]
			},
			"bbox": [
				-64.9556495,
				44.9874257,
				-64.9524705,
				44.9896741
			]
		}
	]
}
