{
	"type": "FeatureCollection",
	"features": [
		{
			"type": "Feature",
			"properties": {
				"confidence": 9,
				"authenticationResultCode": "ValidCredentials",
				"brandLogoUri": "http://dev.virtualearth.net/Branding/logo_powered_by.png",
				"copyright": "Copyright © 2017 Microsoft and its suppliers. All rights reserved. This API cannot be accessed and the content and any results may not be used, reproduced or transmitted in any manner without express written permission from Microsoft Corporation.",
				"entityType": "Address",
				"matchCodes": [
					"Good"
				],
				"name": "1491 Rue Ouiatchouan, Le Domaine-du-Roy, QC G0W 2H0, Canada",
				"statusCode": 200,
				"statusDescription": "OK",
				"traceId": "f08f9309b30a42a7ab1154a839de33f5|BN20130634|7.7.0.0|",
				"addressLine": "1491 Rue Ouiatchouan",
				"adminDistrict": "QC",
				"adminDistrict2": "Le Domaine-du-Roy",
				"countryRegion": "Canada",
				"formattedAddress": "1491 Rue Ouiatchouan, Le Domaine-du-Roy, QC G0W 2H0, Canada",
				"locality": "Le Domaine-du-Roy",
				"neighborhood": "Le Domaine-du-Roy",
				"postalCode": "G0W 2H0"
			},
			"geometry": {
				"type": "Point",
				"coordinates": [
					-72.23048,
					48.56749
				]
			},
			"bbox": [
				-72.2321788,
				48.5663658,
				-72.2287812,
				48.5686142
			]
		}
	]
}
