{
	"type": "FeatureCollection",
	"features": [
		{
			"type": "Feature",
			"properties": {
				"confidence": 9,
				"authenticationResultCode": "ValidCredentials",
				"brandLogoUri": "http://dev.virtualearth.net/Branding/logo_powered_by.png",
				"copyright": "Copyright © 2017 Microsoft and its suppliers. All rights reserved. This API cannot be accessed and the content and any results may not be used, reproduced or transmitted in any manner without express written permission from Microsoft Corporation.",
				"entityType": "Address",
				"matchCodes": [
					"Good"
				],
				"name": "1491 Hollywell Ave, Mississauga, ON L5N 4P2, Canada",
				"statusCode": 200,
				"statusDescription": "OK",
				"traceId": "af7cd27963134f3980465090eef25792|BN20130431|7.7.0.0|",
				"addressLine": "1491 Hollywell Ave",
				"adminDistrict": "ON",
				"adminDistrict2": "Peel",
				"countryRegion": "Canada",
				"formattedAddress": "1491 Hollywell Ave, Mississauga, ON L5N 4P2, Canada",
				"locality": "Mississauga",
				"neighborhood": "Meadowvale",
				"postalCode": "L5N 4P2"
			},
			"geometry": {
				"type": "Point",
				"coordinates": [
					-79.71598,
					43.60004
				]
			},
			"bbox": [
				-79.7175323,
				43.5989158,
				-79.7144277,
				43.6011642
			]
		}
	]
}
