{
	"type": "FeatureCollection",
	"features": [
		{
			"type": "Feature",
			"properties": {
				"confidence": 9,
				"authenticationResultCode": "ValidCredentials",
				"brandLogoUri": "http://dev.virtualearth.net/Branding/logo_powered_by.png",
				"copyright": "Copyright © 2017 Microsoft and its suppliers. All rights reserved. This API cannot be accessed and the content and any results may not be used, reproduced or transmitted in any manner without express written permission from Microsoft Corporation.",
				"entityType": "Address",
				"matchCodes": [
					"Good"
				],
				"name": "1492 Venetian Blvd, Point Edward, ON N7T 7W6, Canada",
				"statusCode": 200,
				"statusDescription": "OK",
				"traceId": "f1913b4f07114b1b92f9e0b1af4adbc8|BN20130632|7.7.0.0|",
				"addressLine": "1492 Venetian Blvd",
				"adminDistrict": "ON",
				"adminDistrict2": "Lambton",
				"countryRegion": "Canada",
				"formattedAddress": "1492 Venetian Blvd, Point Edward, ON N7T 7W6, Canada",
				"locality": "Point Edward",
				"postalCode": "N7T 7W6"
			},
			"geometry": {
				"type": "Point",
				"coordinates": [
					-82.40853,
					42.98904
				]
			},
			"bbox": [
				-82.4100668,
				42.9879158,
				-82.4069932,
				42.9901642
			]
		}
	]
}
