{
	"type": "FeatureCollection",
	"features": [
		{
			"type": "Feature",
			"properties": {
				"confidence": 9,
				"authenticationResultCode": "ValidCredentials",
				"brandLogoUri": "http://dev.virtualearth.net/Branding/logo_powered_by.png",
				"copyright": "Copyright © 2017 Microsoft and its suppliers. All rights reserved. This API cannot be accessed and the content and any results may not be used, reproduced or transmitted in any manner without express written permission from Microsoft Corporation.",
				"entityType": "Address",
				"matchCodes": [
					"Good"
				],
				"name": "1495 Hobson Ave, Courtenay, BC V9N 6P2, Canada",
				"statusCode": 200,
				"statusDescription": "OK",
				"traceId": "dfa6c87197124371aa6a89900cd3d18a|BN20121764|7.7.0.0|",
				"addressLine": "1495 Hobson Ave",
				"adminDistrict": "BC",
				"adminDistrict2": "Comox Valley",
				"countryRegion": "Canada",
				"formattedAddress": "1495 Hobson Ave, Courtenay, BC V9N 6P2, Canada",
				"locality": "Courtenay",
				"postalCode": "V9N 6P2"
			},
			"geometry": {
				"type": "Point",
				"coordinates": [
					-124.96892,
					49.69851
				]
			},
			"bbox": [
				-124.970658,
				49.6973858,
				-124.967182,
				49.6996342
			]
		}
	]
}
