{
	"type": "FeatureCollection",
	"features": [
		{
			"type": "Feature",
			"properties": {
				"confidence": 9,
				"authenticationResultCode": "ValidCredentials",
				"brandLogoUri": "http://dev.virtualearth.net/Branding/logo_powered_by.png",
				"copyright": "Copyright © 2017 Microsoft and its suppliers. All rights reserved. This API cannot be accessed and the content and any results may not be used, reproduced or transmitted in any manner without express written permission from Microsoft Corporation.",
				"entityType": "Address",
				"matchCodes": [
					"Good"
				],
				"name": "15 Allstate Pkwy, Markham, ON L3R 5B4, Canada",
				"statusCode": 200,
				"statusDescription": "OK",
				"traceId": "e92ceb2eded04a35a3ec1d49b038a3ce|BN20130447|7.7.0.0|",
				"addressLine": "15 Allstate Pkwy",
				"adminDistrict": "ON",
				"adminDistrict2": "York",
				"countryRegion": "Canada",
				"formattedAddress": "15 Allstate Pkwy, Markham, ON L3R 5B4, Canada",
				"locality": "Markham",
				"neighborhood": "Buttonville",
				"postalCode": "L3R 5B4"
			},
			"geometry": {
				"type": "Point",
				"coordinates": [
					-79.36338,
					43.8502
				]
			},
			"bbox": [
				-79.3649388,
				43.8490758,
				-79.3618212,
				43.8513242
			]
		}
	]
}
