{
	"type": "FeatureCollection",
	"features": [
		{
			"type": "Feature",
			"properties": {
				"confidence": 9,
				"authenticationResultCode": "ValidCredentials",
				"brandLogoUri": "http://dev.virtualearth.net/Branding/logo_powered_by.png",
				"copyright": "Copyright © 2017 Microsoft and its suppliers. All rights reserved. This API cannot be accessed and the content and any results may not be used, reproduced or transmitted in any manner without express written permission from Microsoft Corporation.",
				"entityType": "Address",
				"matchCodes": [
					"Good"
				],
				"name": "15 Corvus Ct, Nepean, ON K2E 7Z4, Canada",
				"statusCode": 200,
				"statusDescription": "OK",
				"traceId": "b8dff006f30f480b8404efca19d11ec0|BN20171457|7.7.0.0|",
				"addressLine": "15 Corvus Ct",
				"adminDistrict": "ON",
				"adminDistrict2": "Ottawa",
				"countryRegion": "Canada",
				"formattedAddress": "15 Corvus Ct, Nepean, ON K2E 7Z4, Canada",
				"locality": "Ottawa",
				"neighborhood": "Nepean",
				"postalCode": "K2E 7Z4"
			},
			"geometry": {
				"type": "Point",
				"coordinates": [
					-75.71287,
					45.32696
				]
			},
			"bbox": [
				-75.7144689,
				45.3258358,
				-75.7112711,
				45.3280842
			]
		}
	]
}
