{
	"type": "FeatureCollection",
	"features": [
		{
			"type": "Feature",
			"properties": {
				"confidence": 7,
				"authenticationResultCode": "ValidCredentials",
				"brandLogoUri": "http://dev.virtualearth.net/Branding/logo_powered_by.png",
				"copyright": "Copyright © 2017 Microsoft and its suppliers. All rights reserved. This API cannot be accessed and the content and any results may not be used, reproduced or transmitted in any manner without express written permission from Microsoft Corporation.",
				"entityType": "Postcode1",
				"matchCodes": [
					"UpHierarchy"
				],
				"name": "Edmundston, E3V 3K5, Canada",
				"statusCode": 200,
				"statusDescription": "OK",
				"traceId": "f66eba8ae0dd4bb49451bcc7626d47d5|BN20130422|7.7.0.0|",
				"adminDistrict": "NB",
				"adminDistrict2": "Madawaska",
				"countryRegion": "Canada",
				"formattedAddress": "Edmundston, E3V 3K5, Canada",
				"locality": "Edmundston",
				"postalCode": "E3V 3K5"
			},
			"geometry": {
				"type": "Point",
				"coordinates": [
					-68.3529510498047,
					47.3970718383789
				]
			},
			"bbox": [
				-68.3605589818653,
				47.3932091208082,
				-68.3453431177441,
				47.4009345559496
			]
		}
	]
}
