{
	"type": "FeatureCollection",
	"features": [
		{
			"type": "Feature",
			"properties": {
				"confidence": 9,
				"authenticationResultCode": "ValidCredentials",
				"brandLogoUri": "http://dev.virtualearth.net/Branding/logo_powered_by.png",
				"copyright": "Copyright © 2017 Microsoft and its suppliers. All rights reserved. This API cannot be accessed and the content and any results may not be used, reproduced or transmitted in any manner without express written permission from Microsoft Corporation.",
				"entityType": "Address",
				"matchCodes": [
					"Good"
				],
				"name": "15 Mary St W, Lindsay, ON K9V 2N5, Canada",
				"statusCode": 200,
				"statusDescription": "OK",
				"traceId": "6149a4fdf3d3445a94f3c443a9cafaaa|BN20130631|7.7.0.0|",
				"addressLine": "15 Mary St W",
				"adminDistrict": "ON",
				"adminDistrict2": "Kawartha Lakes",
				"countryRegion": "Canada",
				"formattedAddress": "15 Mary St W, Lindsay, ON K9V 2N5, Canada",
				"locality": "Kawartha Lakes",
				"neighborhood": "Lindsay",
				"postalCode": "K9V 2N5"
			},
			"geometry": {
				"type": "Point",
				"coordinates": [
					-78.7319856,
					44.3465935
				]
			},
			"bbox": [
				-78.7335576,
				44.3454693,
				-78.7304136,
				44.3477177
			]
		}
	]
}
