{
	"type": "FeatureCollection",
	"features": [
		{
			"type": "Feature",
			"properties": {
				"confidence": 9,
				"authenticationResultCode": "ValidCredentials",
				"brandLogoUri": "http://dev.virtualearth.net/Branding/logo_powered_by.png",
				"copyright": "Copyright © 2017 Microsoft and its suppliers. All rights reserved. This API cannot be accessed and the content and any results may not be used, reproduced or transmitted in any manner without express written permission from Microsoft Corporation.",
				"entityType": "Address",
				"matchCodes": [
					"Good"
				],
				"name": "15 Richmond St E, Toronto, ON M5C 1N2, Canada",
				"statusCode": 200,
				"statusDescription": "OK",
				"traceId": "75ee403a4ca545d886280af5795c50e4|BN20160335|7.7.0.0|",
				"addressLine": "15 Richmond St E",
				"adminDistrict": "ON",
				"adminDistrict2": "Toronto",
				"countryRegion": "Canada",
				"formattedAddress": "15 Richmond St E, Toronto, ON M5C 1N2, Canada",
				"locality": "Toronto",
				"neighborhood": "Church-Yonge Corridor",
				"postalCode": "M5C 1N2"
			},
			"geometry": {
				"type": "Point",
				"coordinates": [
					-79.37809,
					43.65168
				]
			},
			"bbox": [
				-79.3796437,
				43.6505558,
				-79.3765363,
				43.6528042
			]
		}
	]
}
