{
	"type": "FeatureCollection",
	"features": [
		{
			"type": "Feature",
			"properties": {
				"confidence": 9,
				"authenticationResultCode": "ValidCredentials",
				"brandLogoUri": "http://dev.virtualearth.net/Branding/logo_powered_by.png",
				"copyright": "Copyright © 2017 Microsoft and its suppliers. All rights reserved. This API cannot be accessed and the content and any results may not be used, reproduced or transmitted in any manner without express written permission from Microsoft Corporation.",
				"entityType": "Address",
				"matchCodes": [
					"Good"
				],
				"name": "15 Slessor Ln, Brampton, ON L6P 1L8, Canada",
				"statusCode": 200,
				"statusDescription": "OK",
				"traceId": "771c12903dcd40de9d6e604cf0c0b657|BN20250135|7.7.0.0|",
				"addressLine": "15 Slessor Ln",
				"adminDistrict": "ON",
				"adminDistrict2": "Peel",
				"countryRegion": "Canada",
				"formattedAddress": "15 Slessor Ln, Brampton, ON L6P 1L8, Canada",
				"locality": "Brampton",
				"neighborhood": "Castlemore",
				"postalCode": "L6P 1L8"
			},
			"geometry": {
				"type": "Point",
				"coordinates": [
					-79.67224,
					43.7753
				]
			},
			"bbox": [
				-79.6737969,
				43.7741758,
				-79.6706831,
				43.7764242
			]
		}
	]
}
