{
	"type": "FeatureCollection",
	"features": [
		{
			"type": "Feature",
			"properties": {
				"confidence": 7,
				"authenticationResultCode": "ValidCredentials",
				"brandLogoUri": "http://dev.virtualearth.net/Branding/logo_powered_by.png",
				"copyright": "Copyright © 2017 Microsoft and its suppliers. All rights reserved. This API cannot be accessed and the content and any results may not be used, reproduced or transmitted in any manner without express written permission from Microsoft Corporation.",
				"entityType": "Postcode1",
				"matchCodes": [
					"UpHierarchy"
				],
				"name": "Boucherville, J4B 2X3, Canada",
				"statusCode": 200,
				"statusDescription": "OK",
				"traceId": "6ef941b7d9ad468ea7dd394ecc897639|BN20280152|7.7.0.0|",
				"adminDistrict": "QC",
				"adminDistrict2": "Urban agglomeration of Longueuil",
				"countryRegion": "Canada",
				"formattedAddress": "Boucherville, J4B 2X3, Canada",
				"locality": "Boucherville",
				"postalCode": "J4B 2X3"
			},
			"geometry": {
				"type": "Point",
				"coordinates": [
					-73.4574966430664,
					45.5833396911621
				]
			},
			"bbox": [
				-73.4648550495636,
				45.5794769735914,
				-73.4501382365692,
				45.5872024087328
			]
		}
	]
}
