{
	"type": "FeatureCollection",
	"features": [
		{
			"type": "Feature",
			"properties": {
				"confidence": 9,
				"authenticationResultCode": "ValidCredentials",
				"brandLogoUri": "http://dev.virtualearth.net/Branding/logo_powered_by.png",
				"copyright": "Copyright © 2017 Microsoft and its suppliers. All rights reserved. This API cannot be accessed and the content and any results may not be used, reproduced or transmitted in any manner without express written permission from Microsoft Corporation.",
				"entityType": "Address",
				"matchCodes": [
					"Good"
				],
				"name": "150 Sykes St N, Meaford, ON N4L 1P3, Canada",
				"statusCode": 200,
				"statusDescription": "OK",
				"traceId": "72a5426b3e24405da35d065c88da6bf2|BN20130423|7.7.0.0|",
				"addressLine": "150 Sykes St N",
				"adminDistrict": "ON",
				"adminDistrict2": "Grey",
				"countryRegion": "Canada",
				"formattedAddress": "150 Sykes St N, Meaford, ON N4L 1P3, Canada",
				"locality": "Meaford",
				"postalCode": "N4L 1P3"
			},
			"geometry": {
				"type": "Point",
				"coordinates": [
					-80.59339,
					44.61022
				]
			},
			"bbox": [
				-80.5949691,
				44.6090958,
				-80.5918109,
				44.6113442
			]
		}
	]
}
