{
	"type": "FeatureCollection",
	"features": [
		{
			"type": "Feature",
			"properties": {
				"confidence": 9,
				"authenticationResultCode": "ValidCredentials",
				"brandLogoUri": "http://dev.virtualearth.net/Branding/logo_powered_by.png",
				"copyright": "Copyright © 2017 Microsoft and its suppliers. All rights reserved. This API cannot be accessed and the content and any results may not be used, reproduced or transmitted in any manner without express written permission from Microsoft Corporation.",
				"entityType": "Address",
				"matchCodes": [
					"Good"
				],
				"name": "150 Boulevard de Lucerne, Gatineau, QC J9A 3V7, Canada",
				"statusCode": 200,
				"statusDescription": "OK",
				"traceId": "b8a64870922c47e3824fca8cb40a439f|BN20280152|7.7.0.0|",
				"addressLine": "150 Boulevard de Lucerne",
				"adminDistrict": "QC",
				"adminDistrict2": "Gatineau",
				"countryRegion": "Canada",
				"formattedAddress": "150 Boulevard de Lucerne, Gatineau, QC J9A 3V7, Canada",
				"locality": "Gatineau",
				"neighborhood": "Hull",
				"postalCode": "J9A 3V7"
			},
			"geometry": {
				"type": "Point",
				"coordinates": [
					-75.76074,
					45.41642
				]
			},
			"bbox": [
				-75.7623415,
				45.4152958,
				-75.7591385,
				45.4175442
			]
		}
	]
}
