{
	"type": "FeatureCollection",
	"features": [
		{
			"type": "Feature",
			"properties": {
				"confidence": 9,
				"authenticationResultCode": "ValidCredentials",
				"brandLogoUri": "http://dev.virtualearth.net/Branding/logo_powered_by.png",
				"copyright": "Copyright © 2017 Microsoft and its suppliers. All rights reserved. This API cannot be accessed and the content and any results may not be used, reproduced or transmitted in any manner without express written permission from Microsoft Corporation.",
				"entityType": "Address",
				"matchCodes": [
					"Good"
				],
				"name": "1505 Birch St, Whitehorse, YT Y1A 3X1, Canada",
				"statusCode": 200,
				"statusDescription": "OK",
				"traceId": "ca78a7a7a9c943c5861440ff3468aadf|BN20130423|7.7.0.0|",
				"addressLine": "1505 Birch St",
				"adminDistrict": "YT",
				"adminDistrict2": "Yukon",
				"countryRegion": "Canada",
				"formattedAddress": "1505 Birch St, Whitehorse, YT Y1A 3X1, Canada",
				"locality": "Whitehorse",
				"postalCode": "Y1A 3X1"
			},
			"geometry": {
				"type": "Point",
				"coordinates": [
					-135.1478,
					60.76735
				]
			},
			"bbox": [
				-135.1501019,
				60.7662258,
				-135.1454981,
				60.7684742
			]
		}
	]
}
