{
	"type": "FeatureCollection",
	"features": [
		{
			"type": "Feature",
			"properties": {
				"confidence": 9,
				"authenticationResultCode": "ValidCredentials",
				"brandLogoUri": "http://dev.virtualearth.net/Branding/logo_powered_by.png",
				"copyright": "Copyright © 2017 Microsoft and its suppliers. All rights reserved. This API cannot be accessed and the content and any results may not be used, reproduced or transmitted in any manner without express written permission from Microsoft Corporation.",
				"entityType": "Address",
				"matchCodes": [
					"Good"
				],
				"name": "15108 76A Ave, Surrey, BC V3S 5P1, Canada",
				"statusCode": 200,
				"statusDescription": "OK",
				"traceId": "a561dbb604ed48f2a1691ef3938d87b6|BN20181720|7.7.0.0|",
				"addressLine": "15108 76A Ave",
				"adminDistrict": "BC",
				"adminDistrict2": "Greater Vancouver",
				"countryRegion": "Canada",
				"formattedAddress": "15108 76A Ave, Surrey, BC V3S 5P1, Canada",
				"locality": "Surrey",
				"neighborhood": "Newton",
				"postalCode": "V3S 5P1"
			},
			"geometry": {
				"type": "Point",
				"coordinates": [
					-122.8035099,
					49.1418451
				]
			},
			"bbox": [
				-122.8052283,
				49.140721,
				-122.8017915,
				49.1429693
			]
		}
	]
}
