{
	"type": "FeatureCollection",
	"features": [
		{
			"type": "Feature",
			"properties": {
				"confidence": 9,
				"authenticationResultCode": "ValidCredentials",
				"brandLogoUri": "http://dev.virtualearth.net/Branding/logo_powered_by.png",
				"copyright": "Copyright © 2017 Microsoft and its suppliers. All rights reserved. This API cannot be accessed and the content and any results may not be used, reproduced or transmitted in any manner without express written permission from Microsoft Corporation.",
				"entityType": "Address",
				"matchCodes": [
					"Good"
				],
				"name": "1510 Tower St, Abbotsford, BC V2T 6H5, Canada",
				"statusCode": 200,
				"statusDescription": "OK",
				"traceId": "3c83a81a85cf43b9abd5658a225d1d1a|BN20130447|7.7.0.0|",
				"addressLine": "1510 Tower St",
				"adminDistrict": "BC",
				"adminDistrict2": "Fraser Valley",
				"countryRegion": "Canada",
				"formattedAddress": "1510 Tower St, Abbotsford, BC V2T 6H5, Canada",
				"locality": "Abbotsford",
				"neighborhood": "South Poplar",
				"postalCode": "V2T 6H5"
			},
			"geometry": {
				"type": "Point",
				"coordinates": [
					-122.37473,
					49.02978
				]
			},
			"bbox": [
				-122.3764445,
				49.0286558,
				-122.3730155,
				49.0309042
			]
		}
	]
}
