{
	"type": "FeatureCollection",
	"features": [
		{
			"type": "Feature",
			"properties": {
				"confidence": 9,
				"authenticationResultCode": "ValidCredentials",
				"brandLogoUri": "http://dev.virtualearth.net/Branding/logo_powered_by.png",
				"copyright": "Copyright © 2017 Microsoft and its suppliers. All rights reserved. This API cannot be accessed and the content and any results may not be used, reproduced or transmitted in any manner without express written permission from Microsoft Corporation.",
				"entityType": "Address",
				"matchCodes": [
					"Good"
				],
				"name": "1512 113 Ave, Dawson Creek, BC V1G 2Z5, Canada",
				"statusCode": 200,
				"statusDescription": "OK",
				"traceId": "44752560b650426f95cefd9e2960fac1|BN20280152|7.7.0.0|",
				"addressLine": "1512 113 Ave",
				"adminDistrict": "BC",
				"adminDistrict2": "Peace River",
				"countryRegion": "Canada",
				"formattedAddress": "1512 113 Ave, Dawson Creek, BC V1G 2Z5, Canada",
				"locality": "Dawson Creek",
				"postalCode": "V1G 2Z5"
			},
			"geometry": {
				"type": "Point",
				"coordinates": [
					-120.24567,
					55.74828
				]
			},
			"bbox": [
				-120.2476673,
				55.7471558,
				-120.2436727,
				55.7494042
			]
		}
	]
}
