{
	"type": "FeatureCollection",
	"features": [
		{
			"type": "Feature",
			"properties": {
				"confidence": 9,
				"authenticationResultCode": "ValidCredentials",
				"brandLogoUri": "http://dev.virtualearth.net/Branding/logo_powered_by.png",
				"copyright": "Copyright © 2017 Microsoft and its suppliers. All rights reserved. This API cannot be accessed and the content and any results may not be used, reproduced or transmitted in any manner without express written permission from Microsoft Corporation.",
				"entityType": "Address",
				"matchCodes": [
					"Good"
				],
				"name": "152 Brandt St, Steinbach, MB R5G 0R2, Canada",
				"statusCode": 200,
				"statusDescription": "OK",
				"traceId": "37f4f383bc2d4ed79d6dcac1c8480312|BN20190642|7.7.0.0|",
				"addressLine": "152 Brandt St",
				"adminDistrict": "MB",
				"adminDistrict2": "Manitoba",
				"countryRegion": "Canada",
				"formattedAddress": "152 Brandt St, Steinbach, MB R5G 0R2, Canada",
				"locality": "Steinbach",
				"postalCode": "R5G 0R2"
			},
			"geometry": {
				"type": "Point",
				"coordinates": [
					-96.6915949,
					49.5191847
				]
			},
			"bbox": [
				-96.6933265,
				49.5180606,
				-96.6898633,
				49.5203089
			]
		}
	]
}
