{
	"type": "FeatureCollection",
	"features": [
		{
			"type": "Feature",
			"properties": {
				"confidence": 9,
				"authenticationResultCode": "ValidCredentials",
				"brandLogoUri": "http://dev.virtualearth.net/Branding/logo_powered_by.png",
				"copyright": "Copyright © 2017 Microsoft and its suppliers. All rights reserved. This API cannot be accessed and the content and any results may not be used, reproduced or transmitted in any manner without express written permission from Microsoft Corporation.",
				"entityType": "Address",
				"matchCodes": [
					"Good"
				],
				"name": "1523 Bell Mill Sdrd, Tillsonburg, ON N4G, Canada",
				"statusCode": 200,
				"statusDescription": "OK",
				"traceId": "2050feb6927045a3b37429ddc8d6b8f6|BN20130532|7.7.0.0|",
				"addressLine": "1523 Bell Mill Sdrd",
				"adminDistrict": "ON",
				"adminDistrict2": "Oxford",
				"countryRegion": "Canada",
				"formattedAddress": "1523 Bell Mill Sdrd, Tillsonburg, ON N4G, Canada",
				"locality": "Tillsonburg",
				"postalCode": "N4G 0C9"
			},
			"geometry": {
				"type": "Point",
				"coordinates": [
					-80.70782,
					42.85336
				]
			},
			"bbox": [
				-80.7093534,
				42.8522358,
				-80.7062866,
				42.8544842
			]
		}
	]
}
