{
	"type": "FeatureCollection",
	"features": [
		{
			"type": "Feature",
			"properties": {
				"confidence": 9,
				"authenticationResultCode": "ValidCredentials",
				"brandLogoUri": "http://dev.virtualearth.net/Branding/logo_powered_by.png",
				"copyright": "Copyright © 2017 Microsoft and its suppliers. All rights reserved. This API cannot be accessed and the content and any results may not be used, reproduced or transmitted in any manner without express written permission from Microsoft Corporation.",
				"entityType": "Address",
				"matchCodes": [
					"Good"
				],
				"name": "1530 9 Ave SE, Calgary, AB T2G 0T7, Canada",
				"statusCode": 200,
				"statusDescription": "OK",
				"traceId": "daa8be3994684ca7b9e3712d969e4169|BN20290118|7.7.0.0|",
				"addressLine": "1530 9 Ave SE",
				"adminDistrict": "AB",
				"adminDistrict2": "Alberta",
				"countryRegion": "Canada",
				"formattedAddress": "1530 9 Ave SE, Calgary, AB T2G 0T7, Canada",
				"locality": "Calgary",
				"neighborhood": "Inglewood",
				"postalCode": "T2G 0T7"
			},
			"geometry": {
				"type": "Point",
				"coordinates": [
					-114.026743,
					51.038453
				]
			},
			"bbox": [
				-114.0285308,
				51.0373288,
				-114.0249552,
				51.0395771
			]
		}
	]
}
