{
	"type": "FeatureCollection",
	"features": [
		{
			"type": "Feature",
			"properties": {
				"confidence": 9,
				"authenticationResultCode": "ValidCredentials",
				"brandLogoUri": "http://dev.virtualearth.net/Branding/logo_powered_by.png",
				"copyright": "Copyright © 2017 Microsoft and its suppliers. All rights reserved. This API cannot be accessed and the content and any results may not be used, reproduced or transmitted in any manner without express written permission from Microsoft Corporation.",
				"entityType": "Address",
				"matchCodes": [
					"Good"
				],
				"name": "1534 Rue Principale, Granby, QC J2J 0S6, Canada",
				"statusCode": 200,
				"statusDescription": "OK",
				"traceId": "65037625cc0e4432ad6e0a7abb5a8bf9|BN20190642|7.7.0.0|",
				"addressLine": "1534 Rue Principale",
				"adminDistrict": "QC",
				"adminDistrict2": "La Haute-Yamaska",
				"countryRegion": "Canada",
				"formattedAddress": "1534 Rue Principale, Granby, QC J2J 0S6, Canada",
				"locality": "Granby",
				"postalCode": "J2J 0S6"
			},
			"geometry": {
				"type": "Point",
				"coordinates": [
					-72.80592,
					45.42461
				]
			},
			"bbox": [
				-72.8075217,
				45.4234858,
				-72.8043183,
				45.4257342
			]
		}
	]
}
