{
	"type": "FeatureCollection",
	"features": [
		{
			"type": "Feature",
			"properties": {
				"confidence": 9,
				"authenticationResultCode": "ValidCredentials",
				"brandLogoUri": "http://dev.virtualearth.net/Branding/logo_powered_by.png",
				"copyright": "Copyright © 2017 Microsoft and its suppliers. All rights reserved. This API cannot be accessed and the content and any results may not be used, reproduced or transmitted in any manner without express written permission from Microsoft Corporation.",
				"entityType": "Address",
				"matchCodes": [
					"Good"
				],
				"name": "1534 Shore Rd, Halifax, NS B3G, Canada",
				"statusCode": 200,
				"statusDescription": "OK",
				"traceId": "16b6102ea5ce4520b2e6faac31dc600d|BN20121764|7.7.0.0|",
				"addressLine": "1534 Shore Rd",
				"adminDistrict": "NS",
				"adminDistrict2": "Halifax",
				"countryRegion": "Canada",
				"formattedAddress": "1534 Shore Rd, Halifax, NS B3G, Canada",
				"locality": "Halifax",
				"neighborhood": "Eastern Passage",
				"postalCode": "B3G 1M5"
			},
			"geometry": {
				"type": "Point",
				"coordinates": [
					-63.49301,
					44.61104
				]
			},
			"bbox": [
				-63.4945891,
				44.6099158,
				-63.4914309,
				44.6121642
			]
		}
	]
}
