{
	"type": "FeatureCollection",
	"features": [
		{
			"type": "Feature",
			"properties": {
				"confidence": 9,
				"authenticationResultCode": "ValidCredentials",
				"brandLogoUri": "http://dev.virtualearth.net/Branding/logo_powered_by.png",
				"copyright": "Copyright © 2017 Microsoft and its suppliers. All rights reserved. This API cannot be accessed and the content and any results may not be used, reproduced or transmitted in any manner without express written permission from Microsoft Corporation.",
				"entityType": "Address",
				"matchCodes": [
					"Good"
				],
				"name": "154 Bentinck St, Sydney, NS B1P 1G6, Canada",
				"statusCode": 200,
				"statusDescription": "OK",
				"traceId": "f03413775fd7492a868f434c75f9ee4c|BN20200137|7.7.0.0|",
				"addressLine": "154 Bentinck St",
				"adminDistrict": "NS",
				"adminDistrict2": "Cape Breton",
				"countryRegion": "Canada",
				"formattedAddress": "154 Bentinck St, Sydney, NS B1P 1G6, Canada",
				"locality": "Cape Breton",
				"neighborhood": "Sydney",
				"postalCode": "B1P 1G6"
			},
			"geometry": {
				"type": "Point",
				"coordinates": [
					-60.19323,
					46.13624
				]
			},
			"bbox": [
				-60.1948523,
				46.1351158,
				-60.1916077,
				46.1373642
			]
		}
	]
}
