{
	"type": "FeatureCollection",
	"features": [
		{
			"type": "Feature",
			"properties": {
				"confidence": 9,
				"authenticationResultCode": "ValidCredentials",
				"brandLogoUri": "http://dev.virtualearth.net/Branding/logo_powered_by.png",
				"copyright": "Copyright © 2017 Microsoft and its suppliers. All rights reserved. This API cannot be accessed and the content and any results may not be used, reproduced or transmitted in any manner without express written permission from Microsoft Corporation.",
				"entityType": "Address",
				"matchCodes": [
					"Good"
				],
				"name": "1543 Westall Ave, Victoria, BC V8T 2G6, Canada",
				"statusCode": 200,
				"statusDescription": "OK",
				"traceId": "a50642467e524d0987ad1afcedb4d4b2|BN20130634|7.7.0.0|",
				"addressLine": "1543 Westall Ave",
				"adminDistrict": "BC",
				"adminDistrict2": "Capital",
				"countryRegion": "Canada",
				"formattedAddress": "1543 Westall Ave, Victoria, BC V8T 2G6, Canada",
				"locality": "Victoria",
				"neighborhood": "Oaklands",
				"postalCode": "V8T 2G6"
			},
			"geometry": {
				"type": "Point",
				"coordinates": [
					-123.34033,
					48.44372
				]
			},
			"bbox": [
				-123.3420246,
				48.4425958,
				-123.3386354,
				48.4448442
			]
		}
	]
}
