{
	"type": "FeatureCollection",
	"features": [
		{
			"type": "Feature",
			"properties": {
				"confidence": 9,
				"authenticationResultCode": "ValidCredentials",
				"brandLogoUri": "http://dev.virtualearth.net/Branding/logo_powered_by.png",
				"copyright": "Copyright © 2017 Microsoft and its suppliers. All rights reserved. This API cannot be accessed and the content and any results may not be used, reproduced or transmitted in any manner without express written permission from Microsoft Corporation.",
				"entityType": "Address",
				"matchCodes": [
					"Good"
				],
				"name": "1545 Maley Dr, Sudbury, ON P3A 4R7, Canada",
				"statusCode": 200,
				"statusDescription": "OK",
				"traceId": "aa39b34efb67448fba16be4a5a5092b5|BN20130442|7.7.0.0|",
				"addressLine": "1545 Maley Dr",
				"adminDistrict": "ON",
				"adminDistrict2": "Greater Sudbury",
				"countryRegion": "Canada",
				"formattedAddress": "1545 Maley Dr, Sudbury, ON P3A 4R7, Canada",
				"locality": "Greater Sudbury",
				"neighborhood": "Sudbury",
				"postalCode": "P3A 4R7"
			},
			"geometry": {
				"type": "Point",
				"coordinates": [
					-80.9428025,
					46.5370951
				]
			},
			"bbox": [
				-80.9444367,
				46.5359709,
				-80.9411683,
				46.5382193
			]
		}
	]
}
