{
	"type": "FeatureCollection",
	"features": [
		{
			"type": "Feature",
			"properties": {
				"confidence": 9,
				"authenticationResultCode": "ValidCredentials",
				"brandLogoUri": "http://dev.virtualearth.net/Branding/logo_powered_by.png",
				"copyright": "Copyright © 2017 Microsoft and its suppliers. All rights reserved. This API cannot be accessed and the content and any results may not be used, reproduced or transmitted in any manner without express written permission from Microsoft Corporation.",
				"entityType": "Address",
				"matchCodes": [
					"Good"
				],
				"name": "1545 Chatelain Ave, Ottawa, ON K1Z 8B6, Canada",
				"statusCode": 200,
				"statusDescription": "OK",
				"traceId": "aaa7d99343af4ec0964f106b0bde5fab|BN20130431|7.7.0.0|",
				"addressLine": "1545 Chatelain Ave",
				"adminDistrict": "ON",
				"adminDistrict2": "Ottawa",
				"countryRegion": "Canada",
				"formattedAddress": "1545 Chatelain Ave, Ottawa, ON K1Z 8B6, Canada",
				"locality": "Ottawa",
				"neighborhood": "Carlington",
				"postalCode": "K1Z 8B6"
			},
			"geometry": {
				"type": "Point",
				"coordinates": [
					-75.74199,
					45.37486
				]
			},
			"bbox": [
				-75.7435903,
				45.3737358,
				-75.7403897,
				45.3759842
			]
		}
	]
}
