{
	"type": "FeatureCollection",
	"features": [
		{
			"type": "Feature",
			"properties": {
				"confidence": 9,
				"authenticationResultCode": "ValidCredentials",
				"brandLogoUri": "http://dev.virtualearth.net/Branding/logo_powered_by.png",
				"copyright": "Copyright © 2017 Microsoft and its suppliers. All rights reserved. This API cannot be accessed and the content and any results may not be used, reproduced or transmitted in any manner without express written permission from Microsoft Corporation.",
				"entityType": "Address",
				"matchCodes": [
					"Good"
				],
				"name": "1550 Stone Church Rd E, Hamilton, ON L8W 3P9, Canada",
				"statusCode": 200,
				"statusDescription": "OK",
				"traceId": "b6d63436979d4b0fa2db9fb58cc265b3|BN20130442|7.7.0.0|",
				"addressLine": "1550 Stone Church Rd E",
				"adminDistrict": "ON",
				"adminDistrict2": "Hamilton",
				"countryRegion": "Canada",
				"formattedAddress": "1550 Stone Church Rd E, Hamilton, ON L8W 3P9, Canada",
				"locality": "Hamilton",
				"neighborhood": "Hannon North",
				"postalCode": "L8W 3P9"
			},
			"geometry": {
				"type": "Point",
				"coordinates": [
					-79.82171,
					43.19444
				]
			},
			"bbox": [
				-79.823252,
				43.1933158,
				-79.820168,
				43.1955642
			]
		}
	]
}
