{
	"type": "FeatureCollection",
	"features": [
		{
			"type": "Feature",
			"properties": {
				"confidence": 9,
				"authenticationResultCode": "ValidCredentials",
				"brandLogoUri": "http://dev.virtualearth.net/Branding/logo_powered_by.png",
				"copyright": "Copyright © 2017 Microsoft and its suppliers. All rights reserved. This API cannot be accessed and the content and any results may not be used, reproduced or transmitted in any manner without express written permission from Microsoft Corporation.",
				"entityType": "Address",
				"matchCodes": [
					"Good"
				],
				"name": "15540 Columbia Ave, White Rock, BC V4B 1K4, Canada",
				"statusCode": 200,
				"statusDescription": "OK",
				"traceId": "ec97ccd77fe24584be72f4a79003e003|BN20130620|7.7.0.0|",
				"addressLine": "15540 Columbia Ave",
				"adminDistrict": "BC",
				"adminDistrict2": "Greater Vancouver",
				"countryRegion": "Canada",
				"formattedAddress": "15540 Columbia Ave, White Rock, BC V4B 1K4, Canada",
				"locality": "White Rock",
				"postalCode": "V4B 1K4"
			},
			"geometry": {
				"type": "Point",
				"coordinates": [
					-122.79201,
					49.01867
				]
			},
			"bbox": [
				-122.7937241,
				49.0175458,
				-122.7902959,
				49.0197942
			]
		}
	]
}
