{
	"type": "FeatureCollection",
	"features": [
		{
			"type": "Feature",
			"properties": {
				"confidence": 9,
				"authenticationResultCode": "ValidCredentials",
				"brandLogoUri": "http://dev.virtualearth.net/Branding/logo_powered_by.png",
				"copyright": "Copyright © 2017 Microsoft and its suppliers. All rights reserved. This API cannot be accessed and the content and any results may not be used, reproduced or transmitted in any manner without express written permission from Microsoft Corporation.",
				"entityType": "Address",
				"matchCodes": [
					"Good"
				],
				"name": "1561 Federal Rd, Iqaluit, NU X0A, Canada",
				"statusCode": 200,
				"statusDescription": "OK",
				"traceId": "f9bc23eb4175429c801b30c26151401e|BN20121764|7.7.0.0|",
				"addressLine": "1561 Federal Rd",
				"adminDistrict": "NU",
				"adminDistrict2": "Nunavut",
				"countryRegion": "Canada",
				"formattedAddress": "1561 Federal Rd, Iqaluit, NU X0A, Canada",
				"locality": "Iqaluit",
				"postalCode": "X0A 0H0"
			},
			"geometry": {
				"type": "Point",
				"coordinates": [
					-68.5436943,
					63.7613416
				]
			},
			"bbox": [
				-68.546237,
				63.7602175,
				-68.5411516,
				63.7624658
			]
		}
	]
}
