{
	"type": "FeatureCollection",
	"features": [
		{
			"type": "Feature",
			"properties": {
				"confidence": 9,
				"authenticationResultCode": "ValidCredentials",
				"brandLogoUri": "http://dev.virtualearth.net/Branding/logo_powered_by.png",
				"copyright": "Copyright © 2017 Microsoft and its suppliers. All rights reserved. This API cannot be accessed and the content and any results may not be used, reproduced or transmitted in any manner without express written permission from Microsoft Corporation.",
				"entityType": "Address",
				"matchCodes": [
					"Good"
				],
				"name": "1561 Upper Wellington St, Hamilton, ON L9B 2H4, Canada",
				"statusCode": 200,
				"statusDescription": "OK",
				"traceId": "925af469af514d78bf0842cb51e2f400|BN20200239|7.7.0.0|",
				"addressLine": "1561 Upper Wellington St",
				"adminDistrict": "ON",
				"adminDistrict2": "Hamilton",
				"countryRegion": "Canada",
				"formattedAddress": "1561 Upper Wellington St, Hamilton, ON L9B 2H4, Canada",
				"locality": "Hamilton",
				"neighborhood": "Barnstown",
				"postalCode": "L9B 2H4"
			},
			"geometry": {
				"type": "Point",
				"coordinates": [
					-79.88064,
					43.20487
				]
			},
			"bbox": [
				-79.8821822,
				43.2037458,
				-79.8790978,
				43.2059942
			]
		}
	]
}
