{
	"type": "FeatureCollection",
	"features": [
		{
			"type": "Feature",
			"properties": {
				"confidence": 9,
				"authenticationResultCode": "ValidCredentials",
				"brandLogoUri": "http://dev.virtualearth.net/Branding/logo_powered_by.png",
				"copyright": "Copyright © 2017 Microsoft and its suppliers. All rights reserved. This API cannot be accessed and the content and any results may not be used, reproduced or transmitted in any manner without express written permission from Microsoft Corporation.",
				"entityType": "Address",
				"matchCodes": [
					"Good"
				],
				"name": "1563 Chemong Rd, Selwyn, ON K9J 6X2, Canada",
				"statusCode": 200,
				"statusDescription": "OK",
				"traceId": "424f1886a46c46faab71b0ac8b0b101b|BN20290118|7.7.0.0|",
				"addressLine": "1563 Chemong Rd",
				"adminDistrict": "ON",
				"adminDistrict2": "Peterborough",
				"countryRegion": "Canada",
				"formattedAddress": "1563 Chemong Rd, Selwyn, ON K9J 6X2, Canada",
				"locality": "Selwyn",
				"postalCode": "K9J 6X2"
			},
			"geometry": {
				"type": "Point",
				"coordinates": [
					-78.3524039,
					44.3397745
				]
			},
			"bbox": [
				-78.3539757,
				44.3386503,
				-78.3508321,
				44.3408986
			]
		}
	]
}
