{
	"type": "FeatureCollection",
	"features": [
		{
			"type": "Feature",
			"properties": {
				"confidence": 9,
				"authenticationResultCode": "ValidCredentials",
				"brandLogoUri": "http://dev.virtualearth.net/Branding/logo_powered_by.png",
				"copyright": "Copyright © 2017 Microsoft and its suppliers. All rights reserved. This API cannot be accessed and the content and any results may not be used, reproduced or transmitted in any manner without express written permission from Microsoft Corporation.",
				"entityType": "Address",
				"matchCodes": [
					"Good"
				],
				"name": "158 Herriott St, Carleton Place, ON K7C 2A9, Canada",
				"statusCode": 200,
				"statusDescription": "OK",
				"traceId": "1b66695d97194af98fba5b3c5da77074|BN20131519|7.7.0.0|",
				"addressLine": "158 Herriott St",
				"adminDistrict": "ON",
				"adminDistrict2": "Lanark",
				"countryRegion": "Canada",
				"formattedAddress": "158 Herriott St, Carleton Place, ON K7C 2A9, Canada",
				"locality": "Carleton Place",
				"postalCode": "K7C 2A9"
			},
			"geometry": {
				"type": "Point",
				"coordinates": [
					-76.1541,
					45.13971
				]
			},
			"bbox": [
				-76.1556937,
				45.1385858,
				-76.1525063,
				45.1408342
			]
		}
	]
}
