{
	"type": "FeatureCollection",
	"features": [
		{
			"type": "Feature",
			"properties": {
				"confidence": 9,
				"authenticationResultCode": "ValidCredentials",
				"brandLogoUri": "http://dev.virtualearth.net/Branding/logo_powered_by.png",
				"copyright": "Copyright © 2017 Microsoft and its suppliers. All rights reserved. This API cannot be accessed and the content and any results may not be used, reproduced or transmitted in any manner without express written permission from Microsoft Corporation.",
				"entityType": "Address",
				"matchCodes": [
					"Good"
				],
				"name": "1581 Bank St, Ottawa, ON K1H 7Z3, Canada",
				"statusCode": 200,
				"statusDescription": "OK",
				"traceId": "db9b41d5df444e05a1c4788fb273e3ff|BN20130632|7.7.0.0|",
				"addressLine": "1581 Bank St",
				"adminDistrict": "ON",
				"adminDistrict2": "Ottawa",
				"countryRegion": "Canada",
				"formattedAddress": "1581 Bank St, Ottawa, ON K1H 7Z3, Canada",
				"locality": "Ottawa",
				"neighborhood": "Billings Bridge-Alta Vista",
				"postalCode": "K1H 7Z3"
			},
			"geometry": {
				"type": "Point",
				"coordinates": [
					-75.66742,
					45.37937
				]
			},
			"bbox": [
				-75.6690204,
				45.3782458,
				-75.6658196,
				45.3804942
			]
		}
	]
}
