{
	"type": "FeatureCollection",
	"features": [
		{
			"type": "Feature",
			"properties": {
				"confidence": 9,
				"authenticationResultCode": "ValidCredentials",
				"brandLogoUri": "http://dev.virtualearth.net/Branding/logo_powered_by.png",
				"copyright": "Copyright © 2017 Microsoft and its suppliers. All rights reserved. This API cannot be accessed and the content and any results may not be used, reproduced or transmitted in any manner without express written permission from Microsoft Corporation.",
				"entityType": "Address",
				"matchCodes": [
					"Good"
				],
				"name": "1588 Rand Ave, Vancouver, BC V6P 3G2, Canada",
				"statusCode": 200,
				"statusDescription": "OK",
				"traceId": "e800ff325fe14ef5bde5164507fe6841|BN20130423|7.7.0.0|",
				"addressLine": "1588 Rand Ave",
				"adminDistrict": "BC",
				"adminDistrict2": "Greater Vancouver",
				"countryRegion": "Canada",
				"formattedAddress": "1588 Rand Ave, Vancouver, BC V6P 3G2, Canada",
				"locality": "Vancouver",
				"neighborhood": "Marpole",
				"postalCode": "V6P 3G2"
			},
			"geometry": {
				"type": "Point",
				"coordinates": [
					-123.1426145,
					49.2053644
				]
			},
			"bbox": [
				-123.1443351,
				49.2042402,
				-123.1408939,
				49.2064885
			]
		}
	]
}
