{
	"type": "FeatureCollection",
	"features": [
		{
			"type": "Feature",
			"properties": {
				"confidence": 9,
				"authenticationResultCode": "ValidCredentials",
				"brandLogoUri": "http://dev.virtualearth.net/Branding/logo_powered_by.png",
				"copyright": "Copyright © 2017 Microsoft and its suppliers. All rights reserved. This API cannot be accessed and the content and any results may not be used, reproduced or transmitted in any manner without express written permission from Microsoft Corporation.",
				"entityType": "Address",
				"matchCodes": [
					"Good"
				],
				"name": "1594 RTE-201, Ormstown, QC J0S 1K0, Canada",
				"statusCode": 200,
				"statusDescription": "OK",
				"traceId": "a454458528024bd2995a2cafdb3e20ac|BN20130632|7.7.0.0|",
				"addressLine": "1594 RTE-201",
				"adminDistrict": "QC",
				"adminDistrict2": "Le Haut-St-Laurent",
				"countryRegion": "Canada",
				"formattedAddress": "1594 RTE-201, Ormstown, QC J0S 1K0, Canada",
				"locality": "Ormstown",
				"postalCode": "J0S 1K0"
			},
			"geometry": {
				"type": "Point",
				"coordinates": [
					-73.9801257,
					45.1131059
				]
			},
			"bbox": [
				-73.9817186,
				45.1119818,
				-73.9785328,
				45.1142301
			]
		}
	]
}
