{
	"type": "FeatureCollection",
	"features": [
		{
			"type": "Feature",
			"properties": {
				"confidence": 9,
				"authenticationResultCode": "ValidCredentials",
				"brandLogoUri": "http://dev.virtualearth.net/Branding/logo_powered_by.png",
				"copyright": "Copyright © 2017 Microsoft and its suppliers. All rights reserved. This API cannot be accessed and the content and any results may not be used, reproduced or transmitted in any manner without express written permission from Microsoft Corporation.",
				"entityType": "Address",
				"matchCodes": [
					"Good"
				],
				"name": "16 Elston Bay SE, Airdrie, AB T4B 2G3, Canada",
				"statusCode": 200,
				"statusDescription": "OK",
				"traceId": "e0b622c3952947bf80aa36c93c4fc3e0|BN20121763|7.7.0.0|",
				"addressLine": "16 Elston Bay SE",
				"adminDistrict": "AB",
				"adminDistrict2": "Alberta",
				"countryRegion": "Canada",
				"formattedAddress": "16 Elston Bay SE, Airdrie, AB T4B 2G3, Canada",
				"locality": "Airdrie",
				"postalCode": "T4B 2G3"
			},
			"geometry": {
				"type": "Point",
				"coordinates": [
					-114.00815,
					51.2845299
				]
			},
			"bbox": [
				-114.0099473,
				51.2834057,
				-114.0063527,
				51.2856541
			]
		}
	]
}
