{
	"type": "FeatureCollection",
	"features": [
		{
			"type": "Feature",
			"properties": {
				"confidence": 9,
				"authenticationResultCode": "ValidCredentials",
				"brandLogoUri": "http://dev.virtualearth.net/Branding/logo_powered_by.png",
				"copyright": "Copyright © 2017 Microsoft and its suppliers. All rights reserved. This API cannot be accessed and the content and any results may not be used, reproduced or transmitted in any manner without express written permission from Microsoft Corporation.",
				"entityType": "Address",
				"matchCodes": [
					"Good"
				],
				"name": "16 Leyland Grv, Dartmouth, NS B2W 6P6, Canada",
				"statusCode": 200,
				"statusDescription": "OK",
				"traceId": "23aa027d68d1403dac7858032b05e861|BN20130520|7.7.0.0|",
				"addressLine": "16 Leyland Grv",
				"adminDistrict": "NS",
				"adminDistrict2": "Halifax",
				"countryRegion": "Canada",
				"formattedAddress": "16 Leyland Grv, Dartmouth, NS B2W 6P6, Canada",
				"locality": "Halifax",
				"neighborhood": "Dartmouth",
				"postalCode": "B2W 6P6"
			},
			"geometry": {
				"type": "Point",
				"coordinates": [
					-63.50875,
					44.66838
				]
			},
			"bbox": [
				-63.5103307,
				44.6672558,
				-63.5071693,
				44.6695042
			]
		}
	]
}
