{
	"type": "FeatureCollection",
	"features": [
		{
			"type": "Feature",
			"properties": {
				"confidence": 9,
				"authenticationResultCode": "ValidCredentials",
				"brandLogoUri": "http://dev.virtualearth.net/Branding/logo_powered_by.png",
				"copyright": "Copyright © 2017 Microsoft and its suppliers. All rights reserved. This API cannot be accessed and the content and any results may not be used, reproduced or transmitted in any manner without express written permission from Microsoft Corporation.",
				"entityType": "Address",
				"matchCodes": [
					"Good"
				],
				"name": "16 Rue du Pacifique E, Bromont, QC J2L 1J5, Canada",
				"statusCode": 200,
				"statusDescription": "OK",
				"traceId": "e191c400df9a42a0ae8e23eebefe8b54|BN20130721|7.7.0.0|",
				"addressLine": "16 Rue du Pacifique E",
				"adminDistrict": "QC",
				"adminDistrict2": "Brome-Missisquoi",
				"countryRegion": "Canada",
				"formattedAddress": "16 Rue du Pacifique E, Bromont, QC J2L 1J5, Canada",
				"locality": "Bromont",
				"postalCode": "J2L 1J5"
			},
			"geometry": {
				"type": "Point",
				"coordinates": [
					-72.6686,
					45.30809
				]
			},
			"bbox": [
				-72.6701984,
				45.3069658,
				-72.6670016,
				45.3092142
			]
		}
	]
}
