{
	"type": "FeatureCollection",
	"features": [
		{
			"type": "Feature",
			"properties": {
				"confidence": 9,
				"authenticationResultCode": "ValidCredentials",
				"brandLogoUri": "http://dev.virtualearth.net/Branding/logo_powered_by.png",
				"copyright": "Copyright © 2017 Microsoft and its suppliers. All rights reserved. This API cannot be accessed and the content and any results may not be used, reproduced or transmitted in any manner without express written permission from Microsoft Corporation.",
				"entityType": "Address",
				"matchCodes": [
					"Good"
				],
				"name": "160 Adelaide St S, London, ON N5Z 3L1, Canada",
				"statusCode": 200,
				"statusDescription": "OK",
				"traceId": "b1fb7de347884fbea1747b5c1e9fb70a|CO30305304|7.7.0.0|",
				"addressLine": "160 Adelaide St S",
				"adminDistrict": "ON",
				"adminDistrict2": "Middlesex",
				"countryRegion": "Canada",
				"formattedAddress": "160 Adelaide St S, London, ON N5Z 3L1, Canada",
				"locality": "London",
				"neighborhood": "Glen Cairn",
				"postalCode": "N5Z 3L1"
			},
			"geometry": {
				"type": "Point",
				"coordinates": [
					-81.2209,
					42.9659
				]
			},
			"bbox": [
				-81.2224362,
				42.9647758,
				-81.2193638,
				42.9670242
			]
		}
	]
}
