{
	"type": "FeatureCollection",
	"features": [
		{
			"type": "Feature",
			"properties": {
				"confidence": 9,
				"authenticationResultCode": "ValidCredentials",
				"brandLogoUri": "http://dev.virtualearth.net/Branding/logo_powered_by.png",
				"copyright": "Copyright © 2017 Microsoft and its suppliers. All rights reserved. This API cannot be accessed and the content and any results may not be used, reproduced or transmitted in any manner without express written permission from Microsoft Corporation.",
				"entityType": "Address",
				"matchCodes": [
					"Good"
				],
				"name": "16099 Fraser Hwy, Surrey, BC V4N 0G2, Canada",
				"statusCode": 200,
				"statusDescription": "OK",
				"traceId": "5243ea5be9064b128a769dbc62336fae|BN20130625|7.7.0.0|",
				"addressLine": "16099 Fraser Hwy",
				"adminDistrict": "BC",
				"adminDistrict2": "Greater Vancouver",
				"countryRegion": "Canada",
				"formattedAddress": "16099 Fraser Hwy, Surrey, BC V4N 0G2, Canada",
				"locality": "Surrey",
				"neighborhood": "Fleetwood",
				"postalCode": "V4N 0G2"
			},
			"geometry": {
				"type": "Point",
				"coordinates": [
					-122.77665,
					49.15679
				]
			},
			"bbox": [
				-122.7783689,
				49.1556658,
				-122.7749311,
				49.1579142
			]
		}
	]
}
