{
	"type": "FeatureCollection",
	"features": [
		{
			"type": "Feature",
			"properties": {
				"confidence": 9,
				"authenticationResultCode": "ValidCredentials",
				"brandLogoUri": "http://dev.virtualearth.net/Branding/logo_powered_by.png",
				"copyright": "Copyright © 2017 Microsoft and its suppliers. All rights reserved. This API cannot be accessed and the content and any results may not be used, reproduced or transmitted in any manner without express written permission from Microsoft Corporation.",
				"entityType": "Address",
				"matchCodes": [
					"Good"
				],
				"name": "1609 14 St SW, Calgary, AB T3C 1E3, Canada",
				"statusCode": 200,
				"statusDescription": "OK",
				"traceId": "9e649891a8014462a2cea0efc7d1674f|BN20130625|7.7.0.0|",
				"addressLine": "1609 14 St SW",
				"adminDistrict": "AB",
				"adminDistrict2": "Alberta",
				"countryRegion": "Canada",
				"formattedAddress": "1609 14 St SW, Calgary, AB T3C 1E3, Canada",
				"locality": "Calgary",
				"neighborhood": "Sunalta",
				"postalCode": "T3C 1E3"
			},
			"geometry": {
				"type": "Point",
				"coordinates": [
					-114.09504,
					51.03817
				]
			},
			"bbox": [
				-114.0968278,
				51.0370458,
				-114.0932522,
				51.0392942
			]
		}
	]
}
