{
	"type": "FeatureCollection",
	"features": [
		{
			"type": "Feature",
			"properties": {
				"confidence": 9,
				"authenticationResultCode": "ValidCredentials",
				"brandLogoUri": "http://dev.virtualearth.net/Branding/logo_powered_by.png",
				"copyright": "Copyright © 2017 Microsoft and its suppliers. All rights reserved. This API cannot be accessed and the content and any results may not be used, reproduced or transmitted in any manner without express written permission from Microsoft Corporation.",
				"entityType": "Address",
				"matchCodes": [
					"Good"
				],
				"name": "163 Lawndale Ave, Winnipeg, MB R2H 1T2, Canada",
				"statusCode": 200,
				"statusDescription": "OK",
				"traceId": "4a178eeebb934f4e8fd0831c4b0e6173|BN20240253|7.7.0.0|",
				"addressLine": "163 Lawndale Ave",
				"adminDistrict": "MB",
				"adminDistrict2": "Manitoba",
				"countryRegion": "Canada",
				"formattedAddress": "163 Lawndale Ave, Winnipeg, MB R2H 1T2, Canada",
				"locality": "Winnipeg",
				"neighborhood": "Norwood West",
				"postalCode": "R2H 1T2"
			},
			"geometry": {
				"type": "Point",
				"coordinates": [
					-97.12895,
					49.87699
				]
			},
			"bbox": [
				-97.1306944,
				49.8758658,
				-97.1272056,
				49.8781142
			]
		}
	]
}
