{
	"type": "FeatureCollection",
	"features": [
		{
			"type": "Feature",
			"properties": {
				"confidence": 9,
				"authenticationResultCode": "ValidCredentials",
				"brandLogoUri": "http://dev.virtualearth.net/Branding/logo_powered_by.png",
				"copyright": "Copyright © 2017 Microsoft and its suppliers. All rights reserved. This API cannot be accessed and the content and any results may not be used, reproduced or transmitted in any manner without express written permission from Microsoft Corporation.",
				"entityType": "Address",
				"matchCodes": [
					"Good"
				],
				"name": "1635 RTE-133, Ste-Anne-de-Sabrevois, QC J0J 2G0, Canada",
				"statusCode": 200,
				"statusDescription": "OK",
				"traceId": "74935f8cf22d4fc2a3928ae2240d702d|BN20250135|7.7.0.0|",
				"addressLine": "1635 RTE-133",
				"adminDistrict": "QC",
				"adminDistrict2": "Le Haut-Richelieu",
				"countryRegion": "Canada",
				"formattedAddress": "1635 RTE-133, Ste-Anne-de-Sabrevois, QC J0J 2G0, Canada",
				"locality": "Ste-Anne-de-Sabrevois",
				"postalCode": "J0J 2G0"
			},
			"geometry": {
				"type": "Point",
				"coordinates": [
					-73.2111555,
					45.1905701
				]
			},
			"bbox": [
				-73.2127506,
				45.1894459,
				-73.2095604,
				45.1916942
			]
		}
	]
}
