{
	"type": "FeatureCollection",
	"features": [
		{
			"type": "Feature",
			"properties": {
				"confidence": 9,
				"authenticationResultCode": "ValidCredentials",
				"brandLogoUri": "http://dev.virtualearth.net/Branding/logo_powered_by.png",
				"copyright": "Copyright © 2017 Microsoft and its suppliers. All rights reserved. This API cannot be accessed and the content and any results may not be used, reproduced or transmitted in any manner without express written permission from Microsoft Corporation.",
				"entityType": "Address",
				"matchCodes": [
					"Good"
				],
				"name": "164 Wellington St, Bracebridge, ON P1L, Canada",
				"statusCode": 200,
				"statusDescription": "OK",
				"traceId": "ff0bb7c0800148048e65eca6088d3a67|BN20260223|7.7.0.0|",
				"addressLine": "164 Wellington St",
				"adminDistrict": "ON",
				"adminDistrict2": "Muskoka",
				"countryRegion": "Canada",
				"formattedAddress": "164 Wellington St, Bracebridge, ON P1L, Canada",
				"locality": "Bracebridge",
				"postalCode": "P1L 1C4"
			},
			"geometry": {
				"type": "Point",
				"coordinates": [
					-79.3194199,
					45.03829
				]
			},
			"bbox": [
				-79.3210108,
				45.0371658,
				-79.317829,
				45.0394142
			]
		}
	]
}
