{
	"type": "FeatureCollection",
	"features": [
		{
			"type": "Feature",
			"properties": {
				"confidence": 9,
				"authenticationResultCode": "ValidCredentials",
				"brandLogoUri": "http://dev.virtualearth.net/Branding/logo_powered_by.png",
				"copyright": "Copyright © 2017 Microsoft and its suppliers. All rights reserved. This API cannot be accessed and the content and any results may not be used, reproduced or transmitted in any manner without express written permission from Microsoft Corporation.",
				"entityType": "Address",
				"matchCodes": [
					"Good"
				],
				"name": "1640 Saskatchewan Ave, Saskatoon, SK S7K 1P6, Canada",
				"statusCode": 200,
				"statusDescription": "OK",
				"traceId": "b920af56f6be42078f6896d0342333cd|BN20130625|7.7.0.0|",
				"addressLine": "1640 Saskatchewan Ave",
				"adminDistrict": "SK",
				"adminDistrict2": "Saskatchewan",
				"countryRegion": "Canada",
				"formattedAddress": "1640 Saskatchewan Ave, Saskatoon, SK S7K 1P6, Canada",
				"locality": "Saskatoon",
				"neighborhood": "Kelsey Woodlawn",
				"postalCode": "S7K 1P6"
			},
			"geometry": {
				"type": "Point",
				"coordinates": [
					-106.6687551,
					52.1513763
				]
			},
			"bbox": [
				-106.6705872,
				52.1502521,
				-106.666923,
				52.1525004
			]
		}
	]
}
