{
	"type": "FeatureCollection",
	"features": [
		{
			"type": "Feature",
			"properties": {
				"confidence": 9,
				"authenticationResultCode": "ValidCredentials",
				"brandLogoUri": "http://dev.virtualearth.net/Branding/logo_powered_by.png",
				"copyright": "Copyright © 2017 Microsoft and its suppliers. All rights reserved. This API cannot be accessed and the content and any results may not be used, reproduced or transmitted in any manner without express written permission from Microsoft Corporation.",
				"entityType": "Address",
				"matchCodes": [
					"Good"
				],
				"name": "1640 California Ave, Brockville, ON K6V, Canada",
				"statusCode": 200,
				"statusDescription": "OK",
				"traceId": "60c7717d7f41472a9cd6d2ff17b21a00|BN20121764|7.7.0.0|",
				"addressLine": "1640 California Ave",
				"adminDistrict": "ON",
				"adminDistrict2": "Leeds and Grenville",
				"countryRegion": "Canada",
				"formattedAddress": "1640 California Ave, Brockville, ON K6V, Canada",
				"locality": "Brockville",
				"postalCode": "K6V 5V5"
			},
			"geometry": {
				"type": "Point",
				"coordinates": [
					-75.70014,
					44.6259299
				]
			},
			"bbox": [
				-75.7017195,
				44.6248057,
				-75.6985605,
				44.6270541
			]
		}
	]
}
