{
	"type": "FeatureCollection",
	"features": [
		{
			"type": "Feature",
			"properties": {
				"confidence": 9,
				"authenticationResultCode": "ValidCredentials",
				"brandLogoUri": "http://dev.virtualearth.net/Branding/logo_powered_by.png",
				"copyright": "Copyright © 2017 Microsoft and its suppliers. All rights reserved. This API cannot be accessed and the content and any results may not be used, reproduced or transmitted in any manner without express written permission from Microsoft Corporation.",
				"entityType": "Address",
				"matchCodes": [
					"Good"
				],
				"name": "1641 17th Ave, Campbell River, BC V9W 4L5, Canada",
				"statusCode": 200,
				"statusDescription": "OK",
				"traceId": "72eb46f15f5a4623af88e164be78fd8f|BN20220145|7.7.0.0|",
				"addressLine": "1641 17th Ave",
				"adminDistrict": "BC",
				"adminDistrict2": "Strathcona",
				"countryRegion": "Canada",
				"formattedAddress": "1641 17th Ave, Campbell River, BC V9W 4L5, Canada",
				"locality": "Campbell River",
				"postalCode": "V9W 4L5"
			},
			"geometry": {
				"type": "Point",
				"coordinates": [
					-125.26585,
					50.03112
				]
			},
			"bbox": [
				-125.2676,
				50.0299958,
				-125.2641,
				50.0322442
			]
		}
	]
}
