{
	"type": "FeatureCollection",
	"features": [
		{
			"type": "Feature",
			"properties": {
				"confidence": 9,
				"authenticationResultCode": "ValidCredentials",
				"brandLogoUri": "http://dev.virtualearth.net/Branding/logo_powered_by.png",
				"copyright": "Copyright © 2017 Microsoft and its suppliers. All rights reserved. This API cannot be accessed and the content and any results may not be used, reproduced or transmitted in any manner without express written permission from Microsoft Corporation.",
				"entityType": "Address",
				"matchCodes": [
					"Good"
				],
				"name": "1645 Finfar Ct, Mississauga, ON L5J 4K1, Canada",
				"statusCode": 200,
				"statusDescription": "OK",
				"traceId": "16290f5c9e8047b59ae6b4020e139cae|BN20130532|7.7.0.0|",
				"addressLine": "1645 Finfar Ct",
				"adminDistrict": "ON",
				"adminDistrict2": "Peel",
				"countryRegion": "Canada",
				"formattedAddress": "1645 Finfar Ct, Mississauga, ON L5J 4K1, Canada",
				"locality": "Mississauga",
				"postalCode": "L5J 4K1"
			},
			"geometry": {
				"type": "Point",
				"coordinates": [
					-79.65196,
					43.51756
				]
			},
			"bbox": [
				-79.6535102,
				43.5164358,
				-79.6504098,
				43.5186842
			]
		}
	]
}
