{
	"type": "FeatureCollection",
	"features": [
		{
			"type": "Feature",
			"properties": {
				"confidence": 9,
				"authenticationResultCode": "ValidCredentials",
				"brandLogoUri": "http://dev.virtualearth.net/Branding/logo_powered_by.png",
				"copyright": "Copyright © 2017 Microsoft and its suppliers. All rights reserved. This API cannot be accessed and the content and any results may not be used, reproduced or transmitted in any manner without express written permission from Microsoft Corporation.",
				"entityType": "Address",
				"matchCodes": [
					"Good"
				],
				"name": "1649 Wedmore Way, Mississauga, ON L5J 2J7, Canada",
				"statusCode": 200,
				"statusDescription": "OK",
				"traceId": "21bca5bec1254968ab2ddf547f4a33cd|BN20130447|7.7.0.0|",
				"addressLine": "1649 Wedmore Way",
				"adminDistrict": "ON",
				"adminDistrict2": "Peel",
				"countryRegion": "Canada",
				"formattedAddress": "1649 Wedmore Way, Mississauga, ON L5J 2J7, Canada",
				"locality": "Mississauga",
				"neighborhood": "Lorne Park",
				"postalCode": "L5J 2J7"
			},
			"geometry": {
				"type": "Point",
				"coordinates": [
					-79.63567,
					43.53028
				]
			},
			"bbox": [
				-79.6372205,
				43.5291558,
				-79.6341195,
				43.5314042
			]
		}
	]
}
