{
	"type": "FeatureCollection",
	"features": [
		{
			"type": "Feature",
			"properties": {
				"confidence": 9,
				"authenticationResultCode": "ValidCredentials",
				"brandLogoUri": "http://dev.virtualearth.net/Branding/logo_powered_by.png",
				"copyright": "Copyright © 2017 Microsoft and its suppliers. All rights reserved. This API cannot be accessed and the content and any results may not be used, reproduced or transmitted in any manner without express written permission from Microsoft Corporation.",
				"entityType": "Address",
				"matchCodes": [
					"Good"
				],
				"name": "1655 W 4th Ave, Vancouver, BC V6J 1L8, Canada",
				"statusCode": 200,
				"statusDescription": "OK",
				"traceId": "661f55dc6a1141f29d4ff5f85deabf09|BN20121763|7.7.0.0|",
				"addressLine": "1655 W 4th Ave",
				"adminDistrict": "BC",
				"adminDistrict2": "Greater Vancouver",
				"countryRegion": "Canada",
				"formattedAddress": "1655 W 4th Ave, Vancouver, BC V6J 1L8, Canada",
				"locality": "Vancouver",
				"neighborhood": "Fairview",
				"postalCode": "V6J 1L8"
			},
			"geometry": {
				"type": "Point",
				"coordinates": [
					-123.142263,
					49.2681091
				]
			},
			"bbox": [
				-123.1439857,
				49.266985,
				-123.1405402,
				49.2692333
			]
		}
	]
}
