{
	"type": "FeatureCollection",
	"features": [
		{
			"type": "Feature",
			"properties": {
				"confidence": 9,
				"authenticationResultCode": "ValidCredentials",
				"brandLogoUri": "http://dev.virtualearth.net/Branding/logo_powered_by.png",
				"copyright": "Copyright © 2017 Microsoft and its suppliers. All rights reserved. This API cannot be accessed and the content and any results may not be used, reproduced or transmitted in any manner without express written permission from Microsoft Corporation.",
				"entityType": "Address",
				"matchCodes": [
					"Good"
				],
				"name": "166 Commercial St, Middleton, NS B0S 1P0, Canada",
				"statusCode": 200,
				"statusDescription": "OK",
				"traceId": "23ea15991ae9466da635aaeaa350c4fd|BN20130522|7.7.0.0|",
				"addressLine": "166 Commercial St",
				"adminDistrict": "NS",
				"adminDistrict2": "Annapolis",
				"countryRegion": "Canada",
				"formattedAddress": "166 Commercial St, Middleton, NS B0S 1P0, Canada",
				"locality": "Middleton",
				"postalCode": "B0S 1P0"
			},
			"geometry": {
				"type": "Point",
				"coordinates": [
					-65.0709425,
					44.9472555
				]
			},
			"bbox": [
				-65.0725308,
				44.9461313,
				-65.0693542,
				44.9483796
			]
		}
	]
}
