{
	"type": "FeatureCollection",
	"features": [
		{
			"type": "Feature",
			"properties": {
				"confidence": 9,
				"authenticationResultCode": "ValidCredentials",
				"brandLogoUri": "http://dev.virtualearth.net/Branding/logo_powered_by.png",
				"copyright": "Copyright © 2017 Microsoft and its suppliers. All rights reserved. This API cannot be accessed and the content and any results may not be used, reproduced or transmitted in any manner without express written permission from Microsoft Corporation.",
				"entityType": "Address",
				"matchCodes": [
					"Good"
				],
				"name": "1660 Broadway Ave S, Williams Lake, BC V2G 2W4, Canada",
				"statusCode": 200,
				"statusDescription": "OK",
				"traceId": "20d239bde6d9435894bd183f0de1316c|BN20130422|7.7.0.0|",
				"addressLine": "1660 Broadway Ave S",
				"adminDistrict": "BC",
				"adminDistrict2": "Cariboo",
				"countryRegion": "Canada",
				"formattedAddress": "1660 Broadway Ave S, Williams Lake, BC V2G 2W4, Canada",
				"locality": "Williams Lake",
				"postalCode": "V2G 2W4"
			},
			"geometry": {
				"type": "Point",
				"coordinates": [
					-122.0985885,
					52.1226398
				]
			},
			"bbox": [
				-122.1004195,
				52.1215156,
				-122.0967576,
				52.1237639
			]
		}
	]
}
