{
	"type": "FeatureCollection",
	"features": [
		{
			"type": "Feature",
			"properties": {
				"confidence": 9,
				"authenticationResultCode": "ValidCredentials",
				"brandLogoUri": "http://dev.virtualearth.net/Branding/logo_powered_by.png",
				"copyright": "Copyright © 2017 Microsoft and its suppliers. All rights reserved. This API cannot be accessed and the content and any results may not be used, reproduced or transmitted in any manner without express written permission from Microsoft Corporation.",
				"entityType": "Address",
				"matchCodes": [
					"Good"
				],
				"name": "1665 Highland Rd W, Kitchener, ON N2N 3K5, Canada",
				"statusCode": 200,
				"statusDescription": "OK",
				"traceId": "a0a0f5745e2744aeaa28532627897405|BN20130621|7.7.0.0|",
				"addressLine": "1665 Highland Rd W",
				"adminDistrict": "ON",
				"adminDistrict2": "Waterloo",
				"countryRegion": "Canada",
				"formattedAddress": "1665 Highland Rd W, Kitchener, ON N2N 3K5, Canada",
				"locality": "Kitchener",
				"neighborhood": "Forest Heights",
				"postalCode": "N2N 3K5"
			},
			"geometry": {
				"type": "Point",
				"coordinates": [
					-80.55902,
					43.42028
				]
			},
			"bbox": [
				-80.5605677,
				43.4191558,
				-80.5574723,
				43.4214042
			]
		}
	]
}
