{
	"type": "FeatureCollection",
	"features": [
		{
			"type": "Feature",
			"properties": {
				"confidence": 9,
				"authenticationResultCode": "ValidCredentials",
				"brandLogoUri": "http://dev.virtualearth.net/Branding/logo_powered_by.png",
				"copyright": "Copyright © 2017 Microsoft and its suppliers. All rights reserved. This API cannot be accessed and the content and any results may not be used, reproduced or transmitted in any manner without express written permission from Microsoft Corporation.",
				"entityType": "Address",
				"matchCodes": [
					"Good"
				],
				"name": "1668 Chiefswood Rd, Brant, ON N0A, Canada",
				"statusCode": 200,
				"statusDescription": "OK",
				"traceId": "0cd02b6e1ba84622b1104140aa5fb45e|BN20130442|7.7.0.0|",
				"addressLine": "1668 Chiefswood Rd",
				"adminDistrict": "ON",
				"adminDistrict2": "Brant",
				"countryRegion": "Canada",
				"formattedAddress": "1668 Chiefswood Rd, Brant, ON N0A, Canada",
				"locality": "Brant",
				"neighborhood": "Ohsweken",
				"postalCode": "N0A 1M0"
			},
			"geometry": {
				"type": "Point",
				"coordinates": [
					-80.1176638,
					43.0689638
				]
			},
			"bbox": [
				-80.1192026,
				43.0678396,
				-80.116125,
				43.0700879
			]
		}
	]
}
