{
	"type": "FeatureCollection",
	"features": [
		{
			"type": "Feature",
			"properties": {
				"confidence": 9,
				"authenticationResultCode": "ValidCredentials",
				"brandLogoUri": "http://dev.virtualearth.net/Branding/logo_powered_by.png",
				"copyright": "Copyright © 2017 Microsoft and its suppliers. All rights reserved. This API cannot be accessed and the content and any results may not be used, reproduced or transmitted in any manner without express written permission from Microsoft Corporation.",
				"entityType": "Address",
				"matchCodes": [
					"Good"
				],
				"name": "1668 Boulevard des Laurentides, Laval, QC H7M 2P4, Canada",
				"statusCode": 200,
				"statusDescription": "OK",
				"traceId": "ff7712e911eb4ef683922dadd7679229|BN20130422|7.7.0.0|",
				"addressLine": "1668 Boulevard des Laurentides",
				"adminDistrict": "QC",
				"adminDistrict2": "Laval",
				"countryRegion": "Canada",
				"formattedAddress": "1668 Boulevard des Laurentides, Laval, QC H7M 2P4, Canada",
				"locality": "Laval",
				"neighborhood": "Vimont",
				"postalCode": "H7M 2P4"
			},
			"geometry": {
				"type": "Point",
				"coordinates": [
					-73.72092,
					45.59554
				]
			},
			"bbox": [
				-73.7225266,
				45.5944158,
				-73.7193134,
				45.5966642
			]
		}
	]
}
