{
	"type": "FeatureCollection",
	"features": [
		{
			"type": "Feature",
			"properties": {
				"confidence": 9,
				"authenticationResultCode": "ValidCredentials",
				"brandLogoUri": "http://dev.virtualearth.net/Branding/logo_powered_by.png",
				"copyright": "Copyright © 2017 Microsoft and its suppliers. All rights reserved. This API cannot be accessed and the content and any results may not be used, reproduced or transmitted in any manner without express written permission from Microsoft Corporation.",
				"entityType": "Address",
				"matchCodes": [
					"Good"
				],
				"name": "167 Shore Club Rd, Hubbards, NS B0J 1T0, Canada",
				"statusCode": 200,
				"statusDescription": "OK",
				"traceId": "506d876df1a84bbd9965d7cd01fec929|BN20130532|7.7.0.0|",
				"addressLine": "167 Shore Club Rd",
				"adminDistrict": "NS",
				"adminDistrict2": "Halifax",
				"countryRegion": "Canada",
				"formattedAddress": "167 Shore Club Rd, Hubbards, NS B0J 1T0, Canada",
				"locality": "Halifax",
				"neighborhood": "Hubbards",
				"postalCode": "B0J 1T0"
			},
			"geometry": {
				"type": "Point",
				"coordinates": [
					-64.05616,
					44.6366
				]
			},
			"bbox": [
				-64.0577398,
				44.6354758,
				-64.0545802,
				44.6377242
			]
		}
	]
}
