{
	"type": "FeatureCollection",
	"features": [
		{
			"type": "Feature",
			"properties": {
				"confidence": 9,
				"authenticationResultCode": "ValidCredentials",
				"brandLogoUri": "http://dev.virtualearth.net/Branding/logo_powered_by.png",
				"copyright": "Copyright © 2017 Microsoft and its suppliers. All rights reserved. This API cannot be accessed and the content and any results may not be used, reproduced or transmitted in any manner without express written permission from Microsoft Corporation.",
				"entityType": "Address",
				"matchCodes": [
					"Good"
				],
				"name": "16715 Yonge St, Newmarket, ON L3X 1X4, Canada",
				"statusCode": 200,
				"statusDescription": "OK",
				"traceId": "b61271d9dad7423f86c6f32a5b938e6a|BN20130532|7.7.0.0|",
				"addressLine": "16715 Yonge St",
				"adminDistrict": "ON",
				"adminDistrict2": "York",
				"countryRegion": "Canada",
				"formattedAddress": "16715 Yonge St, Newmarket, ON L3X 1X4, Canada",
				"locality": "Newmarket",
				"postalCode": "L3X 1X4"
			},
			"geometry": {
				"type": "Point",
				"coordinates": [
					-79.47416,
					44.03601
				]
			},
			"bbox": [
				-79.4757237,
				44.0348858,
				-79.4725963,
				44.0371342
			]
		}
	]
}
