{
	"type": "FeatureCollection",
	"features": [
		{
			"type": "Feature",
			"properties": {
				"confidence": 9,
				"authenticationResultCode": "ValidCredentials",
				"brandLogoUri": "http://dev.virtualearth.net/Branding/logo_powered_by.png",
				"copyright": "Copyright © 2017 Microsoft and its suppliers. All rights reserved. This API cannot be accessed and the content and any results may not be used, reproduced or transmitted in any manner without express written permission from Microsoft Corporation.",
				"entityType": "Address",
				"matchCodes": [
					"Good"
				],
				"name": "1695 Boulevard de Montarville, Boucherville, QC J4B 7W4, Canada",
				"statusCode": 200,
				"statusDescription": "OK",
				"traceId": "18d8faec298544d9a65f383c57dbe05e|BN20131519|7.7.0.0|",
				"addressLine": "1695 Boulevard de Montarville",
				"adminDistrict": "QC",
				"adminDistrict2": "Longueuil",
				"countryRegion": "Canada",
				"formattedAddress": "1695 Boulevard de Montarville, Boucherville, QC J4B 7W4, Canada",
				"locality": "Boucherville",
				"postalCode": "J4B 7W4"
			},
			"geometry": {
				"type": "Point",
				"coordinates": [
					-73.4018786,
					45.5639045
				]
			},
			"bbox": [
				-73.4034843,
				45.5627804,
				-73.400273,
				45.5650287
			]
		}
	]
}
