{
	"type": "FeatureCollection",
	"features": [
		{
			"type": "Feature",
			"properties": {
				"confidence": 9,
				"authenticationResultCode": "ValidCredentials",
				"brandLogoUri": "http://dev.virtualearth.net/Branding/logo_powered_by.png",
				"copyright": "Copyright © 2017 Microsoft and its suppliers. All rights reserved. This API cannot be accessed and the content and any results may not be used, reproduced or transmitted in any manner without express written permission from Microsoft Corporation.",
				"entityType": "Address",
				"matchCodes": [
					"Good"
				],
				"name": "170 Princess St, Hamilton, ON L8L 3L3, Canada",
				"statusCode": 200,
				"statusDescription": "OK",
				"traceId": "c1939da007aa47a69ac7a8f12d898260|BN20280152|7.7.0.0|",
				"addressLine": "170 Princess St",
				"adminDistrict": "ON",
				"adminDistrict2": "Hamilton",
				"countryRegion": "Canada",
				"formattedAddress": "170 Princess St, Hamilton, ON L8L 3L3, Canada",
				"locality": "Hamilton",
				"neighborhood": "Stipley",
				"postalCode": "L8L 3L3"
			},
			"geometry": {
				"type": "Point",
				"coordinates": [
					-79.8328499,
					43.2580699
				]
			},
			"bbox": [
				-79.8343935,
				43.2569457,
				-79.8313063,
				43.2591941
			]
		}
	]
}
