{
	"type": "FeatureCollection",
	"features": [
		{
			"type": "Feature",
			"properties": {
				"confidence": 9,
				"authenticationResultCode": "ValidCredentials",
				"brandLogoUri": "http://dev.virtualearth.net/Branding/logo_powered_by.png",
				"copyright": "Copyright © 2017 Microsoft and its suppliers. All rights reserved. This API cannot be accessed and the content and any results may not be used, reproduced or transmitted in any manner without express written permission from Microsoft Corporation.",
				"entityType": "Address",
				"matchCodes": [
					"Good"
				],
				"name": "170 Commercial Ave, Ajax, ON L1S 2H5, Canada",
				"statusCode": 200,
				"statusDescription": "OK",
				"traceId": "05f29078912d41fe8b39dfb9a485a2cc|BN20130620|7.7.0.0|",
				"addressLine": "170 Commercial Ave",
				"adminDistrict": "ON",
				"adminDistrict2": "Durham",
				"countryRegion": "Canada",
				"formattedAddress": "170 Commercial Ave, Ajax, ON L1S 2H5, Canada",
				"locality": "Ajax",
				"postalCode": "L1S 2H5"
			},
			"geometry": {
				"type": "Point",
				"coordinates": [
					-79.02287,
					43.84763
				]
			},
			"bbox": [
				-79.0244288,
				43.8465058,
				-79.0213112,
				43.8487542
			]
		}
	]
}
