{
	"type": "FeatureCollection",
	"features": [
		{
			"type": "Feature",
			"properties": {
				"confidence": 9,
				"authenticationResultCode": "ValidCredentials",
				"brandLogoUri": "http://dev.virtualearth.net/Branding/logo_powered_by.png",
				"copyright": "Copyright © 2017 Microsoft and its suppliers. All rights reserved. This API cannot be accessed and the content and any results may not be used, reproduced or transmitted in any manner without express written permission from Microsoft Corporation.",
				"entityType": "Address",
				"matchCodes": [
					"Good"
				],
				"name": "1703 67 St SW, Edmonton, AB T6X 0G9, Canada",
				"statusCode": 200,
				"statusDescription": "OK",
				"traceId": "e4a43990aa084458b1ad2272de0010e3|BN20200137|7.7.0.0|",
				"addressLine": "1703 67 St SW",
				"adminDistrict": "AB",
				"adminDistrict2": "Alberta",
				"countryRegion": "Canada",
				"formattedAddress": "1703 67 St SW, Edmonton, AB T6X 0G9, Canada",
				"locality": "Edmonton",
				"neighborhood": "Summerside",
				"postalCode": "T6X 0G9"
			},
			"geometry": {
				"type": "Point",
				"coordinates": [
					-113.44313,
					53.41889
				]
			},
			"bbox": [
				-113.4450163,
				53.4177658,
				-113.4412437,
				53.4200142
			]
		}
	]
}
