{
	"type": "FeatureCollection",
	"features": [
		{
			"type": "Feature",
			"properties": {
				"confidence": 9,
				"authenticationResultCode": "ValidCredentials",
				"brandLogoUri": "http://dev.virtualearth.net/Branding/logo_powered_by.png",
				"copyright": "Copyright © 2017 Microsoft and its suppliers. All rights reserved. This API cannot be accessed and the content and any results may not be used, reproduced or transmitted in any manner without express written permission from Microsoft Corporation.",
				"entityType": "Address",
				"matchCodes": [
					"Good"
				],
				"name": "171 Erskine Ave, Toronto, ON M4P 1Y8, Canada",
				"statusCode": 200,
				"statusDescription": "OK",
				"traceId": "cfd8d1ff57664fcfbe7c35a83677872f|BN20131519|7.7.0.0|",
				"addressLine": "171 Erskine Ave",
				"adminDistrict": "ON",
				"adminDistrict2": "Toronto",
				"countryRegion": "Canada",
				"formattedAddress": "171 Erskine Ave, Toronto, ON M4P 1Y8, Canada",
				"locality": "Toronto",
				"neighborhood": "Mt Pleasant West",
				"postalCode": "M4P 1Y8"
			},
			"geometry": {
				"type": "Point",
				"coordinates": [
					-79.39225,
					43.71231
				]
			},
			"bbox": [
				-79.3938052,
				43.7111858,
				-79.3906948,
				43.7134342
			]
		}
	]
}
