{
	"type": "FeatureCollection",
	"features": [
		{
			"type": "Feature",
			"properties": {
				"confidence": 9,
				"authenticationResultCode": "ValidCredentials",
				"brandLogoUri": "http://dev.virtualearth.net/Branding/logo_powered_by.png",
				"copyright": "Copyright © 2017 Microsoft and its suppliers. All rights reserved. This API cannot be accessed and the content and any results may not be used, reproduced or transmitted in any manner without express written permission from Microsoft Corporation.",
				"entityType": "Address",
				"matchCodes": [
					"Good"
				],
				"name": "1713 Mellors Pl, Kamloops, BC V2E 2E4, Canada",
				"statusCode": 200,
				"statusDescription": "OK",
				"traceId": "f462948851e34abc9d6aa8e8206f7c50|BN20250135|7.7.0.0|",
				"addressLine": "1713 Mellors Pl",
				"adminDistrict": "BC",
				"adminDistrict2": "Thompson-Nicola",
				"countryRegion": "Canada",
				"formattedAddress": "1713 Mellors Pl, Kamloops, BC V2E 2E4, Canada",
				"locality": "Kamloops",
				"neighborhood": "Mt Dufferin",
				"postalCode": "V2E 2E4"
			},
			"geometry": {
				"type": "Point",
				"coordinates": [
					-120.37831,
					50.65683
				]
			},
			"bbox": [
				-120.3800832,
				50.6557058,
				-120.3765368,
				50.6579542
			]
		}
	]
}
