{
	"type": "FeatureCollection",
	"features": [
		{
			"type": "Feature",
			"properties": {
				"confidence": 9,
				"authenticationResultCode": "ValidCredentials",
				"brandLogoUri": "http://dev.virtualearth.net/Branding/logo_powered_by.png",
				"copyright": "Copyright © 2017 Microsoft and its suppliers. All rights reserved. This API cannot be accessed and the content and any results may not be used, reproduced or transmitted in any manner without express written permission from Microsoft Corporation.",
				"entityType": "Address",
				"matchCodes": [
					"Good"
				],
				"name": "1719 Champlain St, Dieppe, NB E1A 7P5, Canada",
				"statusCode": 200,
				"statusDescription": "OK",
				"traceId": "5dff98db852b4a7fae12ba46aeffce66|BN20240423|7.7.0.0|",
				"addressLine": "1719 Champlain St",
				"adminDistrict": "NB",
				"adminDistrict2": "Westmorland",
				"countryRegion": "Canada",
				"formattedAddress": "1719 Champlain St, Dieppe, NB E1A 7P5, Canada",
				"locality": "Dieppe",
				"postalCode": "E1A 7P5"
			},
			"geometry": {
				"type": "Point",
				"coordinates": [
					-64.6747873,
					46.1039646
				]
			},
			"bbox": [
				-64.6764086,
				46.1028404,
				-64.673166,
				46.1050887
			]
		}
	]
}
