{
	"type": "FeatureCollection",
	"features": [
		{
			"type": "Feature",
			"properties": {
				"confidence": 9,
				"authenticationResultCode": "ValidCredentials",
				"brandLogoUri": "http://dev.virtualearth.net/Branding/logo_powered_by.png",
				"copyright": "Copyright © 2017 Microsoft and its suppliers. All rights reserved. This API cannot be accessed and the content and any results may not be used, reproduced or transmitted in any manner without express written permission from Microsoft Corporation.",
				"entityType": "Address",
				"matchCodes": [
					"Good"
				],
				"name": "1727 Eglington Ave, Nanaimo District, BC V9X 1T8, Canada",
				"statusCode": 200,
				"statusDescription": "OK",
				"traceId": "ea1bd3c6d1574ae2a183b9499643ed2c|BN20130442|7.7.0.0|",
				"addressLine": "1727 Eglington Ave",
				"adminDistrict": "BC",
				"adminDistrict2": "Nanaimo",
				"countryRegion": "Canada",
				"formattedAddress": "1727 Eglington Ave, Nanaimo District, BC V9X 1T8, Canada",
				"locality": "Nanaimo District",
				"neighborhood": "Cedar",
				"postalCode": "V9X 1T8"
			},
			"geometry": {
				"type": "Point",
				"coordinates": [
					-123.8806096,
					49.0917351
				]
			},
			"bbox": [
				-123.8823263,
				49.090611,
				-123.8788929,
				49.0928593
			]
		}
	]
}
