{
	"type": "FeatureCollection",
	"features": [
		{
			"type": "Feature",
			"properties": {
				"confidence": 9,
				"authenticationResultCode": "ValidCredentials",
				"brandLogoUri": "http://dev.virtualearth.net/Branding/logo_powered_by.png",
				"copyright": "Copyright © 2017 Microsoft and its suppliers. All rights reserved. This API cannot be accessed and the content and any results may not be used, reproduced or transmitted in any manner without express written permission from Microsoft Corporation.",
				"entityType": "Address",
				"matchCodes": [
					"Good"
				],
				"name": "1730 Winhara Rd, Bracebridge, ON P0B, Canada",
				"statusCode": 200,
				"statusDescription": "OK",
				"traceId": "484f136676214afdb2cc8e25719a3394|BN20250135|7.7.0.0|",
				"addressLine": "1730 Winhara Rd",
				"adminDistrict": "ON",
				"adminDistrict2": "Muskoka",
				"countryRegion": "Canada",
				"formattedAddress": "1730 Winhara Rd, Bracebridge, ON P0B, Canada",
				"locality": "Bracebridge",
				"postalCode": "P0B"
			},
			"geometry": {
				"type": "Point",
				"coordinates": [
					-79.3092099,
					44.99472
				]
			},
			"bbox": [
				-79.3107995,
				44.9935958,
				-79.3076203,
				44.9958442
			]
		}
	]
}
