{
	"type": "FeatureCollection",
	"features": [
		{
			"type": "Feature",
			"properties": {
				"confidence": 9,
				"authenticationResultCode": "ValidCredentials",
				"brandLogoUri": "http://dev.virtualearth.net/Branding/logo_powered_by.png",
				"copyright": "Copyright © 2017 Microsoft and its suppliers. All rights reserved. This API cannot be accessed and the content and any results may not be used, reproduced or transmitted in any manner without express written permission from Microsoft Corporation.",
				"entityType": "Address",
				"matchCodes": [
					"Good"
				],
				"name": "1730 Dundas St E, Toronto, ON M4L 1L8, Canada",
				"statusCode": 200,
				"statusDescription": "OK",
				"traceId": "34724bf9b8bc43f0bb563446df98511f|BN20130422|7.7.0.0|",
				"addressLine": "1730 Dundas St E",
				"adminDistrict": "ON",
				"adminDistrict2": "Toronto",
				"countryRegion": "Canada",
				"formattedAddress": "1730 Dundas St E, Toronto, ON M4L 1L8, Canada",
				"locality": "Toronto",
				"neighborhood": "Greenwood-Coxwell",
				"postalCode": "M4L 1L8"
			},
			"geometry": {
				"type": "Point",
				"coordinates": [
					-79.3242099,
					43.66786
				]
			},
			"bbox": [
				-79.325764,
				43.6667358,
				-79.3226558,
				43.6689842
			]
		}
	]
}
