{
	"type": "FeatureCollection",
	"features": [
		{
			"type": "Feature",
			"properties": {
				"confidence": 9,
				"authenticationResultCode": "ValidCredentials",
				"brandLogoUri": "http://dev.virtualearth.net/Branding/logo_powered_by.png",
				"copyright": "Copyright © 2017 Microsoft and its suppliers. All rights reserved. This API cannot be accessed and the content and any results may not be used, reproduced or transmitted in any manner without express written permission from Microsoft Corporation.",
				"entityType": "Address",
				"matchCodes": [
					"Good"
				],
				"name": "175 Kincora Vw NW, Calgary, AB T3R 1M3, Canada",
				"statusCode": 200,
				"statusDescription": "OK",
				"traceId": "c34fe0254ab14b0b85afba5f8fb4a974|BN20130530|7.7.0.0|",
				"addressLine": "175 Kincora Vw NW",
				"adminDistrict": "AB",
				"adminDistrict2": "Alberta",
				"countryRegion": "Canada",
				"formattedAddress": "175 Kincora Vw NW, Calgary, AB T3R 1M3, Canada",
				"locality": "Calgary",
				"neighborhood": "Kincora",
				"postalCode": "T3R 1M3"
			},
			"geometry": {
				"type": "Point",
				"coordinates": [
					-114.13297,
					51.16048
				]
			},
			"bbox": [
				-114.1347625,
				51.1593558,
				-114.1311775,
				51.1616042
			]
		}
	]
}
