{
	"type": "FeatureCollection",
	"features": [
		{
			"type": "Feature",
			"properties": {
				"confidence": 9,
				"authenticationResultCode": "ValidCredentials",
				"brandLogoUri": "http://dev.virtualearth.net/Branding/logo_powered_by.png",
				"copyright": "Copyright © 2017 Microsoft and its suppliers. All rights reserved. This API cannot be accessed and the content and any results may not be used, reproduced or transmitted in any manner without express written permission from Microsoft Corporation.",
				"entityType": "Address",
				"matchCodes": [
					"Good"
				],
				"name": "175 3rd Ave, Halifax, NS B4C, Canada",
				"statusCode": 200,
				"statusDescription": "OK",
				"traceId": "aa9342b266154a2a8b432674306f49d0|BN20250135|7.7.0.0|",
				"addressLine": "175 3rd Ave",
				"adminDistrict": "NS",
				"adminDistrict2": "Halifax",
				"countryRegion": "Canada",
				"formattedAddress": "175 3rd Ave, Halifax, NS B4C, Canada",
				"locality": "Halifax",
				"neighborhood": "Lakeview",
				"postalCode": "B4C 4C9"
			},
			"geometry": {
				"type": "Point",
				"coordinates": [
					-63.6327,
					44.76165
				]
			},
			"bbox": [
				-63.6342832,
				44.7605258,
				-63.6311168,
				44.7627742
			]
		}
	]
}
