{
	"type": "FeatureCollection",
	"features": [
		{
			"type": "Feature",
			"properties": {
				"confidence": 9,
				"authenticationResultCode": "ValidCredentials",
				"brandLogoUri": "http://dev.virtualearth.net/Branding/logo_powered_by.png",
				"copyright": "Copyright © 2017 Microsoft and its suppliers. All rights reserved. This API cannot be accessed and the content and any results may not be used, reproduced or transmitted in any manner without express written permission from Microsoft Corporation.",
				"entityType": "Address",
				"matchCodes": [
					"Good"
				],
				"name": "17559 Innis Lake Rd, Caledon East, ON L7K 2L1, Canada",
				"statusCode": 200,
				"statusDescription": "OK",
				"traceId": "24ba08595580485b8719a625d92ceec5|BN20260223|7.7.0.0|",
				"addressLine": "17559 Innis Lake Rd",
				"adminDistrict": "ON",
				"adminDistrict2": "Peel",
				"countryRegion": "Canada",
				"formattedAddress": "17559 Innis Lake Rd, Caledon East, ON L7K 2L1, Canada",
				"locality": "Caledon",
				"neighborhood": "Caledon East",
				"postalCode": "L7K 2L1"
			},
			"geometry": {
				"type": "Point",
				"coordinates": [
					-79.89582,
					43.91087
				]
			},
			"bbox": [
				-79.8973804,
				43.9097458,
				-79.8942596,
				43.9119942
			]
		}
	]
}
