{
	"type": "FeatureCollection",
	"features": [
		{
			"type": "Feature",
			"properties": {
				"confidence": 9,
				"authenticationResultCode": "ValidCredentials",
				"brandLogoUri": "http://dev.virtualearth.net/Branding/logo_powered_by.png",
				"copyright": "Copyright © 2017 Microsoft and its suppliers. All rights reserved. This API cannot be accessed and the content and any results may not be used, reproduced or transmitted in any manner without express written permission from Microsoft Corporation.",
				"entityType": "Address",
				"matchCodes": [
					"Good"
				],
				"name": "176 Shaw St, Hamilton, ON L8L 3P7, Canada",
				"statusCode": 200,
				"statusDescription": "OK",
				"traceId": "e1120ef991504464a7c07f7c803f0ac9|BN20290118|7.7.0.0|",
				"addressLine": "176 Shaw St",
				"adminDistrict": "ON",
				"adminDistrict2": "Hamilton",
				"countryRegion": "Canada",
				"formattedAddress": "176 Shaw St, Hamilton, ON L8L 3P7, Canada",
				"locality": "Hamilton",
				"neighborhood": "Industrial Sector A and Keith",
				"postalCode": "L8L 3P7"
			},
			"geometry": {
				"type": "Point",
				"coordinates": [
					-79.8456999,
					43.26236
				]
			},
			"bbox": [
				-79.8472436,
				43.2612358,
				-79.8441562,
				43.2634842
			]
		}
	]
}
