{
	"type": "FeatureCollection",
	"features": [
		{
			"type": "Feature",
			"properties": {
				"confidence": 9,
				"authenticationResultCode": "ValidCredentials",
				"brandLogoUri": "http://dev.virtualearth.net/Branding/logo_powered_by.png",
				"copyright": "Copyright © 2017 Microsoft and its suppliers. All rights reserved. This API cannot be accessed and the content and any results may not be used, reproduced or transmitted in any manner without express written permission from Microsoft Corporation.",
				"entityType": "Address",
				"matchCodes": [
					"Good"
				],
				"name": "1770 Starling Rd, Nanaimo District, BC V9X 1H8, Canada",
				"statusCode": 200,
				"statusDescription": "OK",
				"traceId": "54f0200eb22c4737a583ccb35994d487|BN20130533|7.7.0.0|",
				"addressLine": "1770 Starling Rd",
				"adminDistrict": "BC",
				"adminDistrict2": "Nanaimo",
				"countryRegion": "Canada",
				"formattedAddress": "1770 Starling Rd, Nanaimo District, BC V9X 1H8, Canada",
				"locality": "Nanaimo District",
				"neighborhood": "Cedar",
				"postalCode": "V9X 1H8"
			},
			"geometry": {
				"type": "Point",
				"coordinates": [
					-123.8533285,
					49.1087801
				]
			},
			"bbox": [
				-123.8550458,
				49.1076559,
				-123.8516113,
				49.1099042
			]
		}
	]
}
