{
	"type": "FeatureCollection",
	"features": [
		{
			"type": "Feature",
			"properties": {
				"confidence": 9,
				"authenticationResultCode": "ValidCredentials",
				"brandLogoUri": "http://dev.virtualearth.net/Branding/logo_powered_by.png",
				"copyright": "Copyright © 2017 Microsoft and its suppliers. All rights reserved. This API cannot be accessed and the content and any results may not be used, reproduced or transmitted in any manner without express written permission from Microsoft Corporation.",
				"entityType": "Address",
				"matchCodes": [
					"Good"
				],
				"name": "179 Wicksteed Ave, East York, ON M4G 2B9, Canada",
				"statusCode": 200,
				"statusDescription": "OK",
				"traceId": "b5df13c13bf94aedb1554249ba44fd9b|BN20130442|7.7.0.0|",
				"addressLine": "179 Wicksteed Ave",
				"adminDistrict": "ON",
				"adminDistrict2": "Toronto",
				"countryRegion": "Canada",
				"formattedAddress": "179 Wicksteed Ave, East York, ON M4G 2B9, Canada",
				"locality": "Toronto",
				"neighborhood": "Thorncliffe Park",
				"postalCode": "M4G 2B9"
			},
			"geometry": {
				"type": "Point",
				"coordinates": [
					-79.35468,
					43.71177
				]
			},
			"bbox": [
				-79.3562352,
				43.7106458,
				-79.3531248,
				43.7128942
			]
		}
	]
}
