{
	"type": "FeatureCollection",
	"features": [
		{
			"type": "Feature",
			"properties": {
				"confidence": 9,
				"authenticationResultCode": "ValidCredentials",
				"brandLogoUri": "http://dev.virtualearth.net/Branding/logo_powered_by.png",
				"copyright": "Copyright © 2017 Microsoft and its suppliers. All rights reserved. This API cannot be accessed and the content and any results may not be used, reproduced or transmitted in any manner without express written permission from Microsoft Corporation.",
				"entityType": "Address",
				"matchCodes": [
					"Good"
				],
				"name": "179 Woodridge Pl SW, Calgary, AB T2W 3R4, Canada",
				"statusCode": 200,
				"statusDescription": "OK",
				"traceId": "01b6a0b846c74389b1a75b1a1f95cd84|BN20300154|7.7.0.0|",
				"addressLine": "179 Woodridge Pl SW",
				"adminDistrict": "AB",
				"adminDistrict2": "Alberta",
				"countryRegion": "Canada",
				"formattedAddress": "179 Woodridge Pl SW, Calgary, AB T2W 3R4, Canada",
				"locality": "Calgary",
				"neighborhood": "Woodlands",
				"postalCode": "T2W 3R4"
			},
			"geometry": {
				"type": "Point",
				"coordinates": [
					-114.11546,
					50.93506
				]
			},
			"bbox": [
				-114.1172438,
				50.9339358,
				-114.1136762,
				50.9361842
			]
		}
	]
}
