{
	"type": "FeatureCollection",
	"features": [
		{
			"type": "Feature",
			"properties": {
				"confidence": 9,
				"authenticationResultCode": "ValidCredentials",
				"brandLogoUri": "http://dev.virtualearth.net/Branding/logo_powered_by.png",
				"copyright": "Copyright © 2017 Microsoft and its suppliers. All rights reserved. This API cannot be accessed and the content and any results may not be used, reproduced or transmitted in any manner without express written permission from Microsoft Corporation.",
				"entityType": "Address",
				"matchCodes": [
					"Good"
				],
				"name": "18 Rue du Maroc, Candiac, QC J5R 5W9, Canada",
				"statusCode": 200,
				"statusDescription": "OK",
				"traceId": "d5826cacdca644f9a5b12dc821bf11c4|BN20121764|7.7.0.0|",
				"addressLine": "18 Rue du Maroc",
				"adminDistrict": "QC",
				"adminDistrict2": "Roussillon",
				"countryRegion": "Canada",
				"formattedAddress": "18 Rue du Maroc, Candiac, QC J5R 5W9, Canada",
				"locality": "Candiac",
				"postalCode": "J5R 5W9"
			},
			"geometry": {
				"type": "Point",
				"coordinates": [
					-73.53478,
					45.39387
				]
			},
			"bbox": [
				-73.5363808,
				45.3927458,
				-73.5331792,
				45.3949942
			]
		}
	]
}
