{
	"type": "FeatureCollection",
	"features": [
		{
			"type": "Feature",
			"properties": {
				"confidence": 9,
				"authenticationResultCode": "ValidCredentials",
				"brandLogoUri": "http://dev.virtualearth.net/Branding/logo_powered_by.png",
				"copyright": "Copyright © 2017 Microsoft and its suppliers. All rights reserved. This API cannot be accessed and the content and any results may not be used, reproduced or transmitted in any manner without express written permission from Microsoft Corporation.",
				"entityType": "Address",
				"matchCodes": [
					"Good"
				],
				"name": "18 Ontario St, Grimsby, ON L3M 3H1, Canada",
				"statusCode": 200,
				"statusDescription": "OK",
				"traceId": "f55c44cfa9234a45b8403bc95186f02d|BN20130520|7.7.0.0|",
				"addressLine": "18 Ontario St",
				"adminDistrict": "ON",
				"adminDistrict2": "Niagara",
				"countryRegion": "Canada",
				"formattedAddress": "18 Ontario St, Grimsby, ON L3M 3H1, Canada",
				"locality": "Grimsby",
				"postalCode": "L3M 3H1"
			},
			"geometry": {
				"type": "Point",
				"coordinates": [
					-79.55947,
					43.1939
				]
			},
			"bbox": [
				-79.561012,
				43.1927758,
				-79.557928,
				43.1950242
			]
		}
	]
}
