{
	"type": "FeatureCollection",
	"features": [
		{
			"type": "Feature",
			"properties": {
				"confidence": 9,
				"authenticationResultCode": "ValidCredentials",
				"brandLogoUri": "http://dev.virtualearth.net/Branding/logo_powered_by.png",
				"copyright": "Copyright © 2017 Microsoft and its suppliers. All rights reserved. This API cannot be accessed and the content and any results may not be used, reproduced or transmitted in any manner without express written permission from Microsoft Corporation.",
				"entityType": "Address",
				"matchCodes": [
					"Good"
				],
				"name": "18 Orchard Park Blvd, Winnipeg, MB R3R 2K3, Canada",
				"statusCode": 200,
				"statusDescription": "OK",
				"traceId": "20e8673f3c9a43a0843abc7c38c6a0e5|BN20220145|7.7.0.0|",
				"addressLine": "18 Orchard Park Blvd",
				"adminDistrict": "MB",
				"adminDistrict2": "Manitoba",
				"countryRegion": "Canada",
				"formattedAddress": "18 Orchard Park Blvd, Winnipeg, MB R3R 2K3, Canada",
				"locality": "Winnipeg",
				"neighborhood": "Southboine",
				"postalCode": "R3R 2K3"
			},
			"geometry": {
				"type": "Point",
				"coordinates": [
					-97.30515,
					49.86359
				]
			},
			"bbox": [
				-97.3068939,
				49.8624658,
				-97.3034061,
				49.8647142
			]
		}
	]
}
