{
	"type": "FeatureCollection",
	"features": [
		{
			"type": "Feature",
			"properties": {
				"confidence": 9,
				"authenticationResultCode": "ValidCredentials",
				"brandLogoUri": "http://dev.virtualearth.net/Branding/logo_powered_by.png",
				"copyright": "Copyright © 2017 Microsoft and its suppliers. All rights reserved. This API cannot be accessed and the content and any results may not be used, reproduced or transmitted in any manner without express written permission from Microsoft Corporation.",
				"entityType": "Address",
				"matchCodes": [
					"Good"
				],
				"name": "18 Sonesto Ct, Hamilton, ON L9C 7H3, Canada",
				"statusCode": 200,
				"statusDescription": "OK",
				"traceId": "28a28ee5385e462aa14e005359cf7a8f|BN20130532|7.7.0.0|",
				"addressLine": "18 Sonesto Ct",
				"adminDistrict": "ON",
				"adminDistrict2": "Hamilton",
				"countryRegion": "Canada",
				"formattedAddress": "18 Sonesto Ct, Hamilton, ON L9C 7H3, Canada",
				"locality": "Hamilton",
				"neighborhood": "Gurnett",
				"postalCode": "L9C 7H3"
			},
			"geometry": {
				"type": "Point",
				"coordinates": [
					-79.91745,
					43.2232
				]
			},
			"bbox": [
				-79.9189927,
				43.2220758,
				-79.9159073,
				43.2243242
			]
		}
	]
}
