{
	"type": "FeatureCollection",
	"features": [
		{
			"type": "Feature",
			"properties": {
				"confidence": 9,
				"authenticationResultCode": "ValidCredentials",
				"brandLogoUri": "http://dev.virtualearth.net/Branding/logo_powered_by.png",
				"copyright": "Copyright © 2017 Microsoft and its suppliers. All rights reserved. This API cannot be accessed and the content and any results may not be used, reproduced or transmitted in any manner without express written permission from Microsoft Corporation.",
				"entityType": "Address",
				"matchCodes": [
					"Good"
				],
				"name": "180 Rue Dominion, Waterville, QC J0B 3H0, Canada",
				"statusCode": 200,
				"statusDescription": "OK",
				"traceId": "5fe70d65025247be9a547dd6f5a79ce7|BN20200137|7.7.0.0|",
				"addressLine": "180 Rue Dominion",
				"adminDistrict": "QC",
				"adminDistrict2": "Coaticook",
				"countryRegion": "Canada",
				"formattedAddress": "180 Rue Dominion, Waterville, QC J0B 3H0, Canada",
				"locality": "Waterville",
				"postalCode": "J0B 3H0"
			},
			"geometry": {
				"type": "Point",
				"coordinates": [
					-71.89333,
					45.28036
				]
			},
			"bbox": [
				-71.8949276,
				45.2792358,
				-71.8917324,
				45.2814842
			]
		}
	]
}
