{
	"type": "FeatureCollection",
	"features": [
		{
			"type": "Feature",
			"properties": {
				"confidence": 9,
				"authenticationResultCode": "ValidCredentials",
				"brandLogoUri": "http://dev.virtualearth.net/Branding/logo_powered_by.png",
				"copyright": "Copyright © 2017 Microsoft and its suppliers. All rights reserved. This API cannot be accessed and the content and any results may not be used, reproduced or transmitted in any manner without express written permission from Microsoft Corporation.",
				"entityType": "Address",
				"matchCodes": [
					"Good"
				],
				"name": "180 Amber Trl, Winnipeg, MB R2P 2S4, Canada",
				"statusCode": 200,
				"statusDescription": "OK",
				"traceId": "b1ffe6470a8f40078543b18fe0c9fc3f|BN20190642|7.7.0.0|",
				"addressLine": "180 Amber Trl",
				"adminDistrict": "MB",
				"adminDistrict2": "Manitoba",
				"countryRegion": "Canada",
				"formattedAddress": "180 Amber Trl, Winnipeg, MB R2P 2S4, Canada",
				"locality": "Winnipeg",
				"neighborhood": "Amber Trails",
				"postalCode": "R2P 2S4"
			},
			"geometry": {
				"type": "Point",
				"coordinates": [
					-97.16549,
					49.96116
				]
			},
			"bbox": [
				-97.1672375,
				49.9600358,
				-97.1637425,
				49.9622842
			]
		}
	]
}
