{
	"type": "FeatureCollection",
	"features": [
		{
			"type": "Feature",
			"properties": {
				"confidence": 9,
				"authenticationResultCode": "ValidCredentials",
				"brandLogoUri": "http://dev.virtualearth.net/Branding/logo_powered_by.png",
				"copyright": "Copyright © 2017 Microsoft and its suppliers. All rights reserved. This API cannot be accessed and the content and any results may not be used, reproduced or transmitted in any manner without express written permission from Microsoft Corporation.",
				"entityType": "Address",
				"matchCodes": [
					"Good"
				],
				"name": "181 Nawishaskin Ln, Merritt, BC V1K 0A7, Canada",
				"statusCode": 200,
				"statusDescription": "OK",
				"traceId": "7122a604bb224334a1eaeaf51fec304a|BN20121762|7.7.0.0|",
				"addressLine": "181 Nawishaskin Ln",
				"adminDistrict": "BC",
				"adminDistrict2": "Thompson-Nicola",
				"countryRegion": "Canada",
				"formattedAddress": "181 Nawishaskin Ln, Merritt, BC V1K 0A7, Canada",
				"locality": "Thompson-Nicola",
				"neighborhood": "Merritt",
				"postalCode": "V1K 0A7"
			},
			"geometry": {
				"type": "Point",
				"coordinates": [
					-120.8619836,
					50.1382452
				]
			},
			"bbox": [
				-120.8637375,
				50.1371211,
				-120.8602297,
				50.1393694
			]
		}
	]
}
