{
	"type": "FeatureCollection",
	"features": [
		{
			"type": "Feature",
			"properties": {
				"confidence": 9,
				"authenticationResultCode": "ValidCredentials",
				"brandLogoUri": "http://dev.virtualearth.net/Branding/logo_powered_by.png",
				"copyright": "Copyright © 2017 Microsoft and its suppliers. All rights reserved. This API cannot be accessed and the content and any results may not be used, reproduced or transmitted in any manner without express written permission from Microsoft Corporation.",
				"entityType": "Address",
				"matchCodes": [
					"Good"
				],
				"name": "1835 Western Dr, Port Coquitlam, BC V3C 2X4, Canada",
				"statusCode": 200,
				"statusDescription": "OK",
				"traceId": "29c11f01f572475ba4b1f7a0be085749|BN20121762|7.7.0.0|",
				"addressLine": "1835 Western Dr",
				"adminDistrict": "BC",
				"adminDistrict2": "Greater Vancouver",
				"countryRegion": "Canada",
				"formattedAddress": "1835 Western Dr, Port Coquitlam, BC V3C 2X4, Canada",
				"locality": "Port Coquitlam",
				"postalCode": "V3C 2X4"
			},
			"geometry": {
				"type": "Point",
				"coordinates": [
					-122.77944,
					49.25049
				]
			},
			"bbox": [
				-122.7811622,
				49.2493658,
				-122.7777178,
				49.2516142
			]
		}
	]
}
