{
	"type": "FeatureCollection",
	"features": [
		{
			"type": "Feature",
			"properties": {
				"confidence": 9,
				"authenticationResultCode": "ValidCredentials",
				"brandLogoUri": "http://dev.virtualearth.net/Branding/logo_powered_by.png",
				"copyright": "Copyright © 2017 Microsoft and its suppliers. All rights reserved. This API cannot be accessed and the content and any results may not be used, reproduced or transmitted in any manner without express written permission from Microsoft Corporation.",
				"entityType": "Address",
				"matchCodes": [
					"Good"
				],
				"name": "184 Mohawk St, Brantford, ON N3S 2X2, Canada",
				"statusCode": 200,
				"statusDescription": "OK",
				"traceId": "c36f6a2717f9429b816be93bea576cb2|BN20240423|7.7.0.0|",
				"addressLine": "184 Mohawk St",
				"adminDistrict": "ON",
				"adminDistrict2": "Brant",
				"countryRegion": "Canada",
				"formattedAddress": "184 Mohawk St, Brantford, ON N3S 2X2, Canada",
				"locality": "Brantford",
				"postalCode": "N3S 2X2"
			},
			"geometry": {
				"type": "Point",
				"coordinates": [
					-80.2415541,
					43.1259543
				]
			},
			"bbox": [
				-80.2430944,
				43.1248302,
				-80.2400139,
				43.1270785
			]
		}
	]
}
