{
	"type": "FeatureCollection",
	"features": [
		{
			"type": "Feature",
			"properties": {
				"confidence": 9,
				"authenticationResultCode": "ValidCredentials",
				"brandLogoUri": "http://dev.virtualearth.net/Branding/logo_powered_by.png",
				"copyright": "Copyright © 2017 Microsoft and its suppliers. All rights reserved. This API cannot be accessed and the content and any results may not be used, reproduced or transmitted in any manner without express written permission from Microsoft Corporation.",
				"entityType": "Address",
				"matchCodes": [
					"Good"
				],
				"name": "185 Romfield Cirt, Thornhill, ON L3T 3H7, Canada",
				"statusCode": 200,
				"statusDescription": "OK",
				"traceId": "39ea21260368400ba4805649079f6b5c|BN20190642|7.7.0.0|",
				"addressLine": "185 Romfield Cirt",
				"adminDistrict": "ON",
				"adminDistrict2": "York",
				"countryRegion": "Canada",
				"formattedAddress": "185 Romfield Cirt, Thornhill, ON L3T 3H7, Canada",
				"locality": "Markham",
				"neighborhood": "Thornhill",
				"postalCode": "L3T 3H7"
			},
			"geometry": {
				"type": "Point",
				"coordinates": [
					-79.4124,
					43.83221
				]
			},
			"bbox": [
				-79.4139584,
				43.8310858,
				-79.4108416,
				43.8333342
			]
		}
	]
}
