{
	"type": "FeatureCollection",
	"features": [
		{
			"type": "Feature",
			"properties": {
				"confidence": 9,
				"authenticationResultCode": "ValidCredentials",
				"brandLogoUri": "http://dev.virtualearth.net/Branding/logo_powered_by.png",
				"copyright": "Copyright © 2017 Microsoft and its suppliers. All rights reserved. This API cannot be accessed and the content and any results may not be used, reproduced or transmitted in any manner without express written permission from Microsoft Corporation.",
				"entityType": "Address",
				"matchCodes": [
					"Good"
				],
				"name": "185 Courtneypark Dr E, Mississauga, ON L5T 2T6, Canada",
				"statusCode": 200,
				"statusDescription": "OK",
				"traceId": "86fac83e29f44bd6b4ed87eadca0594d|BN20130631|7.7.0.0|",
				"addressLine": "185 Courtneypark Dr E",
				"adminDistrict": "ON",
				"adminDistrict2": "Peel",
				"countryRegion": "Canada",
				"formattedAddress": "185 Courtneypark Dr E, Mississauga, ON L5T 2T6, Canada",
				"locality": "Mississauga",
				"postalCode": "L5T 2T6"
			},
			"geometry": {
				"type": "Point",
				"coordinates": [
					-79.69165,
					43.64078
				]
			},
			"bbox": [
				-79.6932034,
				43.6396558,
				-79.6900966,
				43.6419042
			]
		}
	]
}
