{
	"type": "FeatureCollection",
	"features": [
		{
			"type": "Feature",
			"properties": {
				"confidence": 9,
				"authenticationResultCode": "ValidCredentials",
				"brandLogoUri": "http://dev.virtualearth.net/Branding/logo_powered_by.png",
				"copyright": "Copyright © 2017 Microsoft and its suppliers. All rights reserved. This API cannot be accessed and the content and any results may not be used, reproduced or transmitted in any manner without express written permission from Microsoft Corporation.",
				"entityType": "Address",
				"matchCodes": [
					"Good"
				],
				"name": "1853 Waterwheel Pl, London, ON N5X 4K4, Canada",
				"statusCode": 200,
				"statusDescription": "OK",
				"traceId": "65043da2752745589c52e757d1ec4689|BN20220145|7.7.0.0|",
				"addressLine": "1853 Waterwheel Pl",
				"adminDistrict": "ON",
				"adminDistrict2": "Middlesex",
				"countryRegion": "Canada",
				"formattedAddress": "1853 Waterwheel Pl, London, ON N5X 4K4, Canada",
				"locality": "London",
				"neighborhood": "Stoney Creek",
				"postalCode": "N5X 4K4"
			},
			"geometry": {
				"type": "Point",
				"coordinates": [
					-81.2507,
					43.0516
				]
			},
			"bbox": [
				-81.2522384,
				43.0504758,
				-81.2491616,
				43.0527242
			]
		}
	]
}
