{
	"type": "FeatureCollection",
	"features": [
		{
			"type": "Feature",
			"properties": {
				"confidence": 9,
				"authenticationResultCode": "ValidCredentials",
				"brandLogoUri": "http://dev.virtualearth.net/Branding/logo_powered_by.png",
				"copyright": "Copyright © 2017 Microsoft and its suppliers. All rights reserved. This API cannot be accessed and the content and any results may not be used, reproduced or transmitted in any manner without express written permission from Microsoft Corporation.",
				"entityType": "Address",
				"matchCodes": [
					"Good"
				],
				"name": "1862 Angus St, Regina, SK S4T 1Z4, Canada",
				"statusCode": 200,
				"statusDescription": "OK",
				"traceId": "a5b46d89f81a49b29acfc192047e6ec6|BN20240253|7.7.0.0|",
				"addressLine": "1862 Angus St",
				"adminDistrict": "SK",
				"adminDistrict2": "Saskatchewan",
				"countryRegion": "Canada",
				"formattedAddress": "1862 Angus St, Regina, SK S4T 1Z4, Canada",
				"locality": "Regina",
				"neighborhood": "Cathedral",
				"postalCode": "S4T 1Z4"
			},
			"geometry": {
				"type": "Point",
				"coordinates": [
					-104.62002,
					50.44957
				]
			},
			"bbox": [
				-104.6217854,
				50.4484458,
				-104.6182546,
				50.4506942
			]
		}
	]
}
