{
	"type": "FeatureCollection",
	"features": [
		{
			"type": "Feature",
			"properties": {
				"confidence": 9,
				"authenticationResultCode": "ValidCredentials",
				"brandLogoUri": "http://dev.virtualearth.net/Branding/logo_powered_by.png",
				"copyright": "Copyright © 2017 Microsoft and its suppliers. All rights reserved. This API cannot be accessed and the content and any results may not be used, reproduced or transmitted in any manner without express written permission from Microsoft Corporation.",
				"entityType": "Address",
				"matchCodes": [
					"Good"
				],
				"name": "1870 Gage Ct, Mississauga, ON L5S 1S1, Canada",
				"statusCode": 200,
				"statusDescription": "OK",
				"traceId": "e9e1b1c5c1cd4b0fa461c1423945ab23|BN20280152|7.7.0.0|",
				"addressLine": "1870 Gage Ct",
				"adminDistrict": "ON",
				"adminDistrict2": "Peel",
				"countryRegion": "Canada",
				"formattedAddress": "1870 Gage Ct, Mississauga, ON L5S 1S1, Canada",
				"locality": "Mississauga",
				"postalCode": "L5S 1S1"
			},
			"geometry": {
				"type": "Point",
				"coordinates": [
					-79.67019,
					43.68475
				]
			},
			"bbox": [
				-79.6717445,
				43.6836258,
				-79.6686355,
				43.6858742
			]
		}
	]
}
