{
	"type": "FeatureCollection",
	"features": [
		{
			"type": "Feature",
			"properties": {
				"confidence": 9,
				"authenticationResultCode": "ValidCredentials",
				"brandLogoUri": "http://dev.virtualearth.net/Branding/logo_powered_by.png",
				"copyright": "Copyright © 2017 Microsoft and its suppliers. All rights reserved. This API cannot be accessed and the content and any results may not be used, reproduced or transmitted in any manner without express written permission from Microsoft Corporation.",
				"entityType": "Address",
				"matchCodes": [
					"Good"
				],
				"name": "1875 Avenue Panama, Brossard, QC J4W, Canada",
				"statusCode": 200,
				"statusDescription": "OK",
				"traceId": "f1cf2a4ad7234590b0e11b9e7d6d8f73|BN20130719|7.7.0.0|",
				"addressLine": "1875 Avenue Panama",
				"adminDistrict": "QC",
				"adminDistrict2": "Longueuil",
				"countryRegion": "Canada",
				"formattedAddress": "1875 Avenue Panama, Brossard, QC J4W, Canada",
				"locality": "Brossard",
				"postalCode": "J4W 2S8"
			},
			"geometry": {
				"type": "Point",
				"coordinates": [
					-73.47024,
					45.46774
				]
			},
			"bbox": [
				-73.4718429,
				45.4666158,
				-73.4686371,
				45.4688642
			]
		}
	]
}
