{
	"type": "FeatureCollection",
	"features": [
		{
			"type": "Feature",
			"properties": {
				"confidence": 9,
				"authenticationResultCode": "ValidCredentials",
				"brandLogoUri": "http://dev.virtualearth.net/Branding/logo_powered_by.png",
				"copyright": "Copyright © 2017 Microsoft and its suppliers. All rights reserved. This API cannot be accessed and the content and any results may not be used, reproduced or transmitted in any manner without express written permission from Microsoft Corporation.",
				"entityType": "Address",
				"matchCodes": [
					"Good"
				],
				"name": "1879 Rue de Lunebourg, Laval, QC H7M 2A3, Canada",
				"statusCode": 200,
				"statusDescription": "OK",
				"traceId": "06767ed2892f43e4a995901c910f3d0e|BN20130422|7.7.0.0|",
				"addressLine": "1879 Rue de Lunebourg",
				"adminDistrict": "QC",
				"adminDistrict2": "Laval",
				"countryRegion": "Canada",
				"formattedAddress": "1879 Rue de Lunebourg, Laval, QC H7M 2A3, Canada",
				"locality": "Laval",
				"postalCode": "H7M 2A3"
			},
			"geometry": {
				"type": "Point",
				"coordinates": [
					-73.71923,
					45.60723
				]
			},
			"bbox": [
				-73.7208369,
				45.6061058,
				-73.7176231,
				45.6083542
			]
		}
	]
}
