{
	"type": "FeatureCollection",
	"features": [
		{
			"type": "Feature",
			"properties": {
				"confidence": 9,
				"authenticationResultCode": "ValidCredentials",
				"brandLogoUri": "http://dev.virtualearth.net/Branding/logo_powered_by.png",
				"copyright": "Copyright © 2017 Microsoft and its suppliers. All rights reserved. This API cannot be accessed and the content and any results may not be used, reproduced or transmitted in any manner without express written permission from Microsoft Corporation.",
				"entityType": "Address",
				"matchCodes": [
					"Good"
				],
				"name": "188 RTE-132 E, New Richmond, QC G0C 2B0, Canada",
				"statusCode": 200,
				"statusDescription": "OK",
				"traceId": "2a7dfdfe22674988bcdc4242eea8a028|BN20280152|7.7.0.0|",
				"addressLine": "188 RTE-132 E",
				"adminDistrict": "QC",
				"adminDistrict2": "Bonaventure",
				"countryRegion": "Canada",
				"formattedAddress": "188 RTE-132 E, New Richmond, QC G0C 2B0, Canada",
				"locality": "New Richmond",
				"neighborhood": "Black Cape",
				"postalCode": "G0C 2B0"
			},
			"geometry": {
				"type": "Point",
				"coordinates": [
					-65.8284605,
					48.1624836
				]
			},
			"bbox": [
				-65.8301458,
				48.1613595,
				-65.8267752,
				48.1636078
			]
		}
	]
}
