{
	"type": "FeatureCollection",
	"features": [
		{
			"type": "Feature",
			"properties": {
				"confidence": 9,
				"authenticationResultCode": "ValidCredentials",
				"brandLogoUri": "http://dev.virtualearth.net/Branding/logo_powered_by.png",
				"copyright": "Copyright © 2017 Microsoft and its suppliers. All rights reserved. This API cannot be accessed and the content and any results may not be used, reproduced or transmitted in any manner without express written permission from Microsoft Corporation.",
				"entityType": "Address",
				"matchCodes": [
					"Good"
				],
				"name": "1891 Wharncliffe Rd S, London, ON N6L 1K2, Canada",
				"statusCode": 200,
				"statusDescription": "OK",
				"traceId": "e51272ba3aa34f24a738adad5c4dac1d|BN20200137|7.7.0.0|",
				"addressLine": "1891 Wharncliffe Rd S",
				"adminDistrict": "ON",
				"adminDistrict2": "Middlesex",
				"countryRegion": "Canada",
				"formattedAddress": "1891 Wharncliffe Rd S, London, ON N6L 1K2, Canada",
				"locality": "London",
				"neighborhood": "Lambeth",
				"postalCode": "N6L 1K2"
			},
			"geometry": {
				"type": "Point",
				"coordinates": [
					-81.2814032,
					42.9203924
				]
			},
			"bbox": [
				-81.2829383,
				42.9192683,
				-81.2798681,
				42.9215166
			]
		}
	]
}
