{
	"type": "FeatureCollection",
	"features": [
		{
			"type": "Feature",
			"properties": {
				"confidence": 9,
				"authenticationResultCode": "ValidCredentials",
				"brandLogoUri": "http://dev.virtualearth.net/Branding/logo_powered_by.png",
				"copyright": "Copyright © 2017 Microsoft and its suppliers. All rights reserved. This API cannot be accessed and the content and any results may not be used, reproduced or transmitted in any manner without express written permission from Microsoft Corporation.",
				"entityType": "Address",
				"matchCodes": [
					"Good"
				],
				"name": "19 Clyde Ave, Mt Pearl, NL A1N 4R8, Canada",
				"statusCode": 200,
				"statusDescription": "OK",
				"traceId": "17ca902756ed49f49fd7ad77aebda6b7|BN20190653|7.7.0.0|",
				"addressLine": "19 Clyde Ave",
				"adminDistrict": "NL",
				"adminDistrict2": "Newfoundland and Labrador",
				"countryRegion": "Canada",
				"formattedAddress": "19 Clyde Ave, Mt Pearl, NL A1N 4R8, Canada",
				"locality": "Mt Pearl",
				"postalCode": "A1N 4R8"
			},
			"geometry": {
				"type": "Point",
				"coordinates": [
					-52.8323838,
					47.5248413
				]
			},
			"bbox": [
				-52.8340485,
				47.5237171,
				-52.830719,
				47.5259654
			]
		}
	]
}
