{
	"type": "FeatureCollection",
	"features": [
		{
			"type": "Feature",
			"properties": {
				"confidence": 9,
				"authenticationResultCode": "ValidCredentials",
				"brandLogoUri": "http://dev.virtualearth.net/Branding/logo_powered_by.png",
				"copyright": "Copyright © 2017 Microsoft and its suppliers. All rights reserved. This API cannot be accessed and the content and any results may not be used, reproduced or transmitted in any manner without express written permission from Microsoft Corporation.",
				"entityType": "Address",
				"matchCodes": [
					"Good"
				],
				"name": "19 Coronet Ave, Nepean, ON K2G 6R8, Canada",
				"statusCode": 200,
				"statusDescription": "OK",
				"traceId": "ded24029a48749d8bf3f1ff6ba0a23e5|BN20210145|7.7.0.0|",
				"addressLine": "19 Coronet Ave",
				"adminDistrict": "ON",
				"adminDistrict2": "Ottawa",
				"countryRegion": "Canada",
				"formattedAddress": "19 Coronet Ave, Nepean, ON K2G 6R8, Canada",
				"locality": "Ottawa",
				"neighborhood": "Nepean",
				"postalCode": "K2G 6R8"
			},
			"geometry": {
				"type": "Point",
				"coordinates": [
					-75.70862,
					45.28839
				]
			},
			"bbox": [
				-75.7102179,
				45.2872658,
				-75.7070221,
				45.2895142
			]
		}
	]
}
