{
	"type": "FeatureCollection",
	"features": [
		{
			"type": "Feature",
			"properties": {
				"confidence": 9,
				"authenticationResultCode": "ValidCredentials",
				"brandLogoUri": "http://dev.virtualearth.net/Branding/logo_powered_by.png",
				"copyright": "Copyright © 2017 Microsoft and its suppliers. All rights reserved. This API cannot be accessed and the content and any results may not be used, reproduced or transmitted in any manner without express written permission from Microsoft Corporation.",
				"entityType": "Address",
				"matchCodes": [
					"Good"
				],
				"name": "19 MacRae Ave, Sydney River, NS B1S 1M1, Canada",
				"statusCode": 200,
				"statusDescription": "OK",
				"traceId": "1540dae3fc4742a2bc5e55bcfc506275|BN20130625|7.7.0.0|",
				"addressLine": "19 MacRae Ave",
				"adminDistrict": "NS",
				"adminDistrict2": "Cape Breton",
				"countryRegion": "Canada",
				"formattedAddress": "19 MacRae Ave, Sydney River, NS B1S 1M1, Canada",
				"locality": "Cape Breton",
				"neighborhood": "Sydney River",
				"postalCode": "B1S 1M1"
			},
			"geometry": {
				"type": "Point",
				"coordinates": [
					-60.22661,
					46.10407
				]
			},
			"bbox": [
				-60.2282313,
				46.1029458,
				-60.2249887,
				46.1051942
			]
		}
	]
}
