{
	"type": "FeatureCollection",
	"features": [
		{
			"type": "Feature",
			"properties": {
				"confidence": 9,
				"authenticationResultCode": "ValidCredentials",
				"brandLogoUri": "http://dev.virtualearth.net/Branding/logo_powered_by.png",
				"copyright": "Copyright © 2017 Microsoft and its suppliers. All rights reserved. This API cannot be accessed and the content and any results may not be used, reproduced or transmitted in any manner without express written permission from Microsoft Corporation.",
				"entityType": "Address",
				"matchCodes": [
					"Good"
				],
				"name": "19 Tamblyn Rd, Orono, ON L0B 1M0, Canada",
				"statusCode": 200,
				"statusDescription": "OK",
				"traceId": "b4323606d5bb4ed4a6a71223713dad9e|BN20320521|7.7.0.0|",
				"addressLine": "19 Tamblyn Rd",
				"adminDistrict": "ON",
				"adminDistrict2": "Durham",
				"countryRegion": "Canada",
				"formattedAddress": "19 Tamblyn Rd, Orono, ON L0B 1M0, Canada",
				"locality": "Clarington",
				"neighborhood": "Orono",
				"postalCode": "L0B 1M0"
			},
			"geometry": {
				"type": "Point",
				"coordinates": [
					-78.6135889,
					43.9872545
				]
			},
			"bbox": [
				-78.6151513,
				43.9861304,
				-78.6120264,
				43.9883787
			]
		}
	]
}
