{
	"type": "FeatureCollection",
	"features": [
		{
			"type": "Feature",
			"properties": {
				"confidence": 9,
				"authenticationResultCode": "ValidCredentials",
				"brandLogoUri": "http://dev.virtualearth.net/Branding/logo_powered_by.png",
				"copyright": "Copyright © 2017 Microsoft and its suppliers. All rights reserved. This API cannot be accessed and the content and any results may not be used, reproduced or transmitted in any manner without express written permission from Microsoft Corporation.",
				"entityType": "Address",
				"matchCodes": [
					"Good"
				],
				"name": "190 Hodsman Rd, Regina, SK S4N 5X4, Canada",
				"statusCode": 200,
				"statusDescription": "OK",
				"traceId": "ed8cf08c305540e4a925817ac978e6a9|BN20131519|7.7.0.0|",
				"addressLine": "190 Hodsman Rd",
				"adminDistrict": "SK",
				"adminDistrict2": "Saskatchewan",
				"countryRegion": "Canada",
				"formattedAddress": "190 Hodsman Rd, Regina, SK S4N 5X4, Canada",
				"locality": "Regina",
				"postalCode": "S4N 5X4"
			},
			"geometry": {
				"type": "Point",
				"coordinates": [
					-104.58311,
					50.47916
				]
			},
			"bbox": [
				-104.5848765,
				50.4780358,
				-104.5813435,
				50.4802842
			]
		}
	]
}
