{
	"type": "FeatureCollection",
	"features": [
		{
			"type": "Feature",
			"properties": {
				"confidence": 9,
				"authenticationResultCode": "ValidCredentials",
				"brandLogoUri": "http://dev.virtualearth.net/Branding/logo_powered_by.png",
				"copyright": "Copyright © 2017 Microsoft and its suppliers. All rights reserved. This API cannot be accessed and the content and any results may not be used, reproduced or transmitted in any manner without express written permission from Microsoft Corporation.",
				"entityType": "Address",
				"matchCodes": [
					"Good"
				],
				"name": "190 Washburn Dr, Kitchener, ON N2R 1S2, Canada",
				"statusCode": 200,
				"statusDescription": "OK",
				"traceId": "4b149ba7ea7a42158af66f3ae406f82a|BN20200137|7.7.0.0|",
				"addressLine": "190 Washburn Dr",
				"adminDistrict": "ON",
				"adminDistrict2": "Waterloo",
				"countryRegion": "Canada",
				"formattedAddress": "190 Washburn Dr, Kitchener, ON N2R 1S2, Canada",
				"locality": "Kitchener",
				"neighborhood": "Huron Park",
				"postalCode": "N2R 1S2"
			},
			"geometry": {
				"type": "Point",
				"coordinates": [
					-80.49167,
					43.40229
				]
			},
			"bbox": [
				-80.4932173,
				43.4011658,
				-80.4901227,
				43.4034142
			]
		}
	]
}
