{
	"type": "FeatureCollection",
	"features": [
		{
			"type": "Feature",
			"properties": {
				"confidence": 9,
				"authenticationResultCode": "ValidCredentials",
				"brandLogoUri": "http://dev.virtualearth.net/Branding/logo_powered_by.png",
				"copyright": "Copyright © 2017 Microsoft and its suppliers. All rights reserved. This API cannot be accessed and the content and any results may not be used, reproduced or transmitted in any manner without express written permission from Microsoft Corporation.",
				"entityType": "Address",
				"matchCodes": [
					"Good"
				],
				"name": "190 Nugget Ave, Scarborough, ON M1S 3A7, Canada",
				"statusCode": 200,
				"statusDescription": "OK",
				"traceId": "c9a18718dd7f4294b077d67b220e4f05|BN20130621|7.7.0.0|",
				"addressLine": "190 Nugget Ave",
				"adminDistrict": "ON",
				"adminDistrict2": "Toronto",
				"countryRegion": "Canada",
				"formattedAddress": "190 Nugget Ave, Scarborough, ON M1S 3A7, Canada",
				"locality": "Toronto",
				"neighborhood": "Agincourt South-Malvern West",
				"postalCode": "M1S 3A7"
			},
			"geometry": {
				"type": "Point",
				"coordinates": [
					-79.25317,
					43.79578
				]
			},
			"bbox": [
				-79.2547274,
				43.7946558,
				-79.2516126,
				43.7969042
			]
		}
	]
}
