{
	"type": "FeatureCollection",
	"features": [
		{
			"type": "Feature",
			"properties": {
				"confidence": 9,
				"authenticationResultCode": "ValidCredentials",
				"brandLogoUri": "http://dev.virtualearth.net/Branding/logo_powered_by.png",
				"copyright": "Copyright © 2017 Microsoft and its suppliers. All rights reserved. This API cannot be accessed and the content and any results may not be used, reproduced or transmitted in any manner without express written permission from Microsoft Corporation.",
				"entityType": "Address",
				"matchCodes": [
					"Good"
				],
				"name": "191 Birch Hill Pvt, Ottawa, ON K1K 3Y5, Canada",
				"statusCode": 200,
				"statusDescription": "OK",
				"traceId": "250eb721e5244a8bbacf1bb1bae20e40|BN20200239|7.7.0.0|",
				"addressLine": "191 Birch Hill Pvt",
				"adminDistrict": "ON",
				"adminDistrict2": "Ottawa",
				"countryRegion": "Canada",
				"formattedAddress": "191 Birch Hill Pvt, Ottawa, ON K1K 3Y5, Canada",
				"locality": "Ottawa",
				"neighborhood": "Carson Grove-Carson Meadows",
				"postalCode": "K1K 3Y5"
			},
			"geometry": {
				"type": "Point",
				"coordinates": [
					-75.62511,
					45.44433
				]
			},
			"bbox": [
				-75.6267123,
				45.4432058,
				-75.6235077,
				45.4454542
			]
		}
	]
}
