{
	"type": "FeatureCollection",
	"features": [
		{
			"type": "Feature",
			"properties": {
				"confidence": 9,
				"authenticationResultCode": "ValidCredentials",
				"brandLogoUri": "http://dev.virtualearth.net/Branding/logo_powered_by.png",
				"copyright": "Copyright © 2017 Microsoft and its suppliers. All rights reserved. This API cannot be accessed and the content and any results may not be used, reproduced or transmitted in any manner without express written permission from Microsoft Corporation.",
				"entityType": "Address",
				"matchCodes": [
					"Good"
				],
				"name": "1917 Logan Ave, Winnipeg, MB R2R 0H6, Canada",
				"statusCode": 200,
				"statusDescription": "OK",
				"traceId": "3c866b9bd86841959c7687ca86f4fe3d|BN20130533|7.7.0.0|",
				"addressLine": "1917 Logan Ave",
				"adminDistrict": "MB",
				"adminDistrict2": "Manitoba",
				"countryRegion": "Canada",
				"formattedAddress": "1917 Logan Ave, Winnipeg, MB R2R 0H6, Canada",
				"locality": "Winnipeg",
				"neighborhood": "Brooklands",
				"postalCode": "R2R 0H6"
			},
			"geometry": {
				"type": "Point",
				"coordinates": [
					-97.20028,
					49.92378
				]
			},
			"bbox": [
				-97.2020261,
				49.9226558,
				-97.1985339,
				49.9249042
			]
		}
	]
}
