{
	"type": "FeatureCollection",
	"features": [
		{
			"type": "Feature",
			"properties": {
				"confidence": 9,
				"authenticationResultCode": "ValidCredentials",
				"brandLogoUri": "http://dev.virtualearth.net/Branding/logo_powered_by.png",
				"copyright": "Copyright © 2017 Microsoft and its suppliers. All rights reserved. This API cannot be accessed and the content and any results may not be used, reproduced or transmitted in any manner without express written permission from Microsoft Corporation.",
				"entityType": "Address",
				"matchCodes": [
					"Good"
				],
				"name": "1925 Dundas St, London, ON N5V 1P7, Canada",
				"statusCode": 200,
				"statusDescription": "OK",
				"traceId": "c241a91de66242579810d7af5d6f4444|BN20160335|7.7.0.0|",
				"addressLine": "1925 Dundas St",
				"adminDistrict": "ON",
				"adminDistrict2": "Middlesex",
				"countryRegion": "Canada",
				"formattedAddress": "1925 Dundas St, London, ON N5V 1P7, Canada",
				"locality": "London",
				"neighborhood": "Argyle",
				"postalCode": "N5V 1P7"
			},
			"geometry": {
				"type": "Point",
				"coordinates": [
					-81.1744206,
					43.0050291
				]
			},
			"bbox": [
				-81.1759578,
				43.0039049,
				-81.1728834,
				43.0061532
			]
		}
	]
}
