{
	"type": "FeatureCollection",
	"features": [
		{
			"type": "Feature",
			"properties": {
				"confidence": 9,
				"authenticationResultCode": "ValidCredentials",
				"brandLogoUri": "http://dev.virtualearth.net/Branding/logo_powered_by.png",
				"copyright": "Copyright © 2017 Microsoft and its suppliers. All rights reserved. This API cannot be accessed and the content and any results may not be used, reproduced or transmitted in any manner without express written permission from Microsoft Corporation.",
				"entityType": "Address",
				"matchCodes": [
					"Good"
				],
				"name": "19360 CR-43, North Glengarry, ON K0C, Canada",
				"statusCode": 200,
				"statusDescription": "OK",
				"traceId": "59abe6017ebc483fae7e422e5d1a97b2|BN20130532|7.7.0.0|",
				"addressLine": "19360 CR-43",
				"adminDistrict": "ON",
				"adminDistrict2": "Stormont, Dundas and Glengarry",
				"countryRegion": "Canada",
				"formattedAddress": "19360 CR-43, North Glengarry, ON K0C, Canada",
				"locality": "North Glengarry",
				"postalCode": "K0C 1A0"
			},
			"geometry": {
				"type": "Point",
				"coordinates": [
					-74.7185557,
					45.2729094
				]
			},
			"bbox": [
				-74.7201531,
				45.2717853,
				-74.7169582,
				45.2740336
			]
		}
	]
}
