{
	"type": "FeatureCollection",
	"features": [
		{
			"type": "Feature",
			"properties": {
				"confidence": 9,
				"authenticationResultCode": "ValidCredentials",
				"brandLogoUri": "http://dev.virtualearth.net/Branding/logo_powered_by.png",
				"copyright": "Copyright © 2017 Microsoft and its suppliers. All rights reserved. This API cannot be accessed and the content and any results may not be used, reproduced or transmitted in any manner without express written permission from Microsoft Corporation.",
				"entityType": "Address",
				"matchCodes": [
					"Good"
				],
				"name": "1940 Rue Pigeon, Mascouche, QC J7L 2C8, Canada",
				"statusCode": 200,
				"statusDescription": "OK",
				"traceId": "3ed10c9c3d204a5fa2c4dda6f8453146|BN20240423|7.7.0.0|",
				"addressLine": "1940 Rue Pigeon",
				"adminDistrict": "QC",
				"adminDistrict2": "Les Moulins",
				"countryRegion": "Canada",
				"formattedAddress": "1940 Rue Pigeon, Mascouche, QC J7L 2C8, Canada",
				"locality": "Mascouche",
				"postalCode": "J7L 2C8"
			},
			"geometry": {
				"type": "Point",
				"coordinates": [
					-73.64456,
					45.72694
				]
			},
			"bbox": [
				-73.6461704,
				45.7258158,
				-73.6429496,
				45.7280642
			]
		}
	]
}
