{
	"type": "FeatureCollection",
	"features": [
		{
			"type": "Feature",
			"properties": {
				"confidence": 9,
				"authenticationResultCode": "ValidCredentials",
				"brandLogoUri": "http://dev.virtualearth.net/Branding/logo_powered_by.png",
				"copyright": "Copyright © 2017 Microsoft and its suppliers. All rights reserved. This API cannot be accessed and the content and any results may not be used, reproduced or transmitted in any manner without express written permission from Microsoft Corporation.",
				"entityType": "Address",
				"matchCodes": [
					"Good"
				],
				"name": "1941 Mallard Rd, London, ON N6H 5M1, Canada",
				"statusCode": 200,
				"statusDescription": "OK",
				"traceId": "11c45b1834e04385b9ae92b152d8b44b|CO30275938|7.7.0.0|",
				"addressLine": "1941 Mallard Rd",
				"adminDistrict": "ON",
				"adminDistrict2": "Middlesex",
				"countryRegion": "Canada",
				"formattedAddress": "1941 Mallard Rd, London, ON N6H 5M1, Canada",
				"locality": "London",
				"neighborhood": "Hyde Park",
				"postalCode": "N6H 5M1"
			},
			"geometry": {
				"type": "Point",
				"coordinates": [
					-81.3406,
					43.0067
				]
			},
			"bbox": [
				-81.3421373,
				43.0055758,
				-81.3390627,
				43.0078242
			]
		}
	]
}
