{
	"type": "FeatureCollection",
	"features": [
		{
			"type": "Feature",
			"properties": {
				"confidence": 9,
				"authenticationResultCode": "ValidCredentials",
				"brandLogoUri": "http://dev.virtualearth.net/Branding/logo_powered_by.png",
				"copyright": "Copyright © 2017 Microsoft and its suppliers. All rights reserved. This API cannot be accessed and the content and any results may not be used, reproduced or transmitted in any manner without express written permission from Microsoft Corporation.",
				"entityType": "Address",
				"matchCodes": [
					"Good"
				],
				"name": "195 Magill St, Lively, ON P3Y 1K6, Canada",
				"statusCode": 200,
				"statusDescription": "OK",
				"traceId": "69648b04b19543f2b157d756dfbdbb1c|BN20131519|7.7.0.0|",
				"addressLine": "195 Magill St",
				"adminDistrict": "ON",
				"adminDistrict2": "Greater Sudbury",
				"countryRegion": "Canada",
				"formattedAddress": "195 Magill St, Lively, ON P3Y 1K6, Canada",
				"locality": "Greater Sudbury",
				"neighborhood": "Lively",
				"postalCode": "P3Y 1K6"
			},
			"geometry": {
				"type": "Point",
				"coordinates": [
					-81.12244,
					46.43568
				]
			},
			"bbox": [
				-81.1240712,
				46.4345558,
				-81.1208088,
				46.4368042
			]
		}
	]
}
