{
	"type": "FeatureCollection",
	"features": [
		{
			"type": "Feature",
			"properties": {
				"confidence": 9,
				"authenticationResultCode": "ValidCredentials",
				"brandLogoUri": "http://dev.virtualearth.net/Branding/logo_powered_by.png",
				"copyright": "Copyright © 2017 Microsoft and its suppliers. All rights reserved. This API cannot be accessed and the content and any results may not be used, reproduced or transmitted in any manner without express written permission from Microsoft Corporation.",
				"entityType": "Address",
				"matchCodes": [
					"Good"
				],
				"name": "19501 96 Ave, Surrey, BC V4N 4C5, Canada",
				"statusCode": 200,
				"statusDescription": "OK",
				"traceId": "bdba447164294e909f3fb6106e0f9562|BN20130533|7.7.0.0|",
				"addressLine": "19501 96 Ave",
				"adminDistrict": "BC",
				"adminDistrict2": "Greater Vancouver",
				"countryRegion": "Canada",
				"formattedAddress": "19501 96 Ave, Surrey, BC V4N 4C5, Canada",
				"locality": "Surrey",
				"neighborhood": "Guildford",
				"postalCode": "V4N 4C5"
			},
			"geometry": {
				"type": "Point",
				"coordinates": [
					-122.68199,
					49.1771699
				]
			},
			"bbox": [
				-122.6837096,
				49.1760457,
				-122.6802704,
				49.1782941
			]
		}
	]
}
