{
	"type": "FeatureCollection",
	"features": [
		{
			"type": "Feature",
			"properties": {
				"confidence": 9,
				"authenticationResultCode": "ValidCredentials",
				"brandLogoUri": "http://dev.virtualearth.net/Branding/logo_powered_by.png",
				"copyright": "Copyright © 2017 Microsoft and its suppliers. All rights reserved. This API cannot be accessed and the content and any results may not be used, reproduced or transmitted in any manner without express written permission from Microsoft Corporation.",
				"entityType": "Address",
				"matchCodes": [
					"Good"
				],
				"name": "1954 10 Ave NW, Medicine Hat, AB T1C 1T5, Canada",
				"statusCode": 200,
				"statusDescription": "OK",
				"traceId": "1cd2b8e8944d4d2586fe9c60ef26cfa1|BN20121763|7.7.0.0|",
				"addressLine": "1954 10 Ave NW",
				"adminDistrict": "AB",
				"adminDistrict2": "Alberta",
				"countryRegion": "Canada",
				"formattedAddress": "1954 10 Ave NW, Medicine Hat, AB T1C 1T5, Canada",
				"locality": "Medicine Hat",
				"postalCode": "T1C 1T5"
			},
			"geometry": {
				"type": "Point",
				"coordinates": [
					-110.70983,
					50.06051
				]
			},
			"bbox": [
				-110.7115811,
				50.0593858,
				-110.7080789,
				50.0616342
			]
		}
	]
}
