{
	"type": "FeatureCollection",
	"features": [
		{
			"type": "Feature",
			"properties": {
				"confidence": 9,
				"authenticationResultCode": "ValidCredentials",
				"brandLogoUri": "http://dev.virtualearth.net/Branding/logo_powered_by.png",
				"copyright": "Copyright © 2017 Microsoft and its suppliers. All rights reserved. This API cannot be accessed and the content and any results may not be used, reproduced or transmitted in any manner without express written permission from Microsoft Corporation.",
				"entityType": "Address",
				"matchCodes": [
					"Good"
				],
				"name": "197 Dean Burton Ln, Newmarket, ON L3X 3C4, Canada",
				"statusCode": 200,
				"statusDescription": "OK",
				"traceId": "8af32049085b4891a3fc7d4e8eabfce8|BN20240423|7.7.0.0|",
				"addressLine": "197 Dean Burton Ln",
				"adminDistrict": "ON",
				"adminDistrict2": "York",
				"countryRegion": "Canada",
				"formattedAddress": "197 Dean Burton Ln, Newmarket, ON L3X 3C4, Canada",
				"locality": "Newmarket",
				"postalCode": "L3X 3C4"
			},
			"geometry": {
				"type": "Point",
				"coordinates": [
					-79.48679,
					44.06025
				]
			},
			"bbox": [
				-79.4883543,
				44.0591258,
				-79.4852257,
				44.0613742
			]
		}
	]
}
