{
	"type": "FeatureCollection",
	"features": [
		{
			"type": "Feature",
			"properties": {
				"confidence": 9,
				"authenticationResultCode": "ValidCredentials",
				"brandLogoUri": "http://dev.virtualearth.net/Branding/logo_powered_by.png",
				"copyright": "Copyright © 2017 Microsoft and its suppliers. All rights reserved. This API cannot be accessed and the content and any results may not be used, reproduced or transmitted in any manner without express written permission from Microsoft Corporation.",
				"entityType": "Address",
				"matchCodes": [
					"Good"
				],
				"name": "19855 98 Ave, Langley, BC V1M 2X5, Canada",
				"statusCode": 200,
				"statusDescription": "OK",
				"traceId": "1dce9a6ba6d740369358bafc54f56ee0|BN20260231|7.7.0.0|",
				"addressLine": "19855 98 Ave",
				"adminDistrict": "BC",
				"adminDistrict2": "Greater Vancouver",
				"countryRegion": "Canada",
				"formattedAddress": "19855 98 Ave, Langley, BC V1M 2X5, Canada",
				"locality": "Langley",
				"postalCode": "V1M 2X5"
			},
			"geometry": {
				"type": "Point",
				"coordinates": [
					-122.6736,
					49.18061
				]
			},
			"bbox": [
				-122.6753197,
				49.1794858,
				-122.6718803,
				49.1817342
			]
		}
	]
}
