{
	"type": "FeatureCollection",
	"features": [
		{
			"type": "Feature",
			"properties": {
				"confidence": 9,
				"authenticationResultCode": "ValidCredentials",
				"brandLogoUri": "http://dev.virtualearth.net/Branding/logo_powered_by.png",
				"copyright": "Copyright © 2017 Microsoft and its suppliers. All rights reserved. This API cannot be accessed and the content and any results may not be used, reproduced or transmitted in any manner without express written permission from Microsoft Corporation.",
				"entityType": "Address",
				"matchCodes": [
					"Good"
				],
				"name": "1 Stull St, Capreol, ON P0M 1H0, Canada",
				"statusCode": 200,
				"statusDescription": "OK",
				"traceId": "179bccb24fe0468ba09848f377b74775|BN20240253|7.7.0.0|",
				"addressLine": "1 Stull St",
				"adminDistrict": "ON",
				"adminDistrict2": "Greater Sudbury",
				"countryRegion": "Canada",
				"formattedAddress": "1 Stull St, Capreol, ON P0M 1H0, Canada",
				"locality": "Greater Sudbury",
				"neighborhood": "Capreol",
				"postalCode": "P0M 1H0"
			},
			"geometry": {
				"type": "Point",
				"coordinates": [
					-80.92731,
					46.71524
				]
			},
			"bbox": [
				-80.9289496,
				46.7141158,
				-80.9256704,
				46.7163642
			]
		}
	]
}
