{
	"type": "FeatureCollection",
	"features": [
		{
			"type": "Feature",
			"properties": {
				"confidence": 9,
				"authenticationResultCode": "ValidCredentials",
				"brandLogoUri": "http://dev.virtualearth.net/Branding/logo_powered_by.png",
				"copyright": "Copyright © 2017 Microsoft and its suppliers. All rights reserved. This API cannot be accessed and the content and any results may not be used, reproduced or transmitted in any manner without express written permission from Microsoft Corporation.",
				"entityType": "Address",
				"matchCodes": [
					"Good"
				],
				"name": "2 Brisbane Rd, North York, ON M3J 2J8, Canada",
				"statusCode": 200,
				"statusDescription": "OK",
				"traceId": "ff521a21a4994e76b1ae61d297afe16c|BN20130423|7.7.0.0|",
				"addressLine": "2 Brisbane Rd",
				"adminDistrict": "ON",
				"adminDistrict2": "Toronto",
				"countryRegion": "Canada",
				"formattedAddress": "2 Brisbane Rd, North York, ON M3J 2J8, Canada",
				"locality": "Toronto",
				"neighborhood": "York University Heights",
				"postalCode": "M3J 2J8"
			},
			"geometry": {
				"type": "Point",
				"coordinates": [
					-79.47112,
					43.77389
				]
			},
			"bbox": [
				-79.4726768,
				43.7727658,
				-79.4695632,
				43.7750142
			]
		}
	]
}
