{
	"type": "FeatureCollection",
	"features": [
		{
			"type": "Feature",
			"properties": {
				"confidence": 9,
				"authenticationResultCode": "ValidCredentials",
				"brandLogoUri": "http://dev.virtualearth.net/Branding/logo_powered_by.png",
				"copyright": "Copyright © 2017 Microsoft and its suppliers. All rights reserved. This API cannot be accessed and the content and any results may not be used, reproduced or transmitted in any manner without express written permission from Microsoft Corporation.",
				"entityType": "Address",
				"matchCodes": [
					"Good"
				],
				"name": "2 St Clair Ave E, Toronto, ON M4T 2T5, Canada",
				"statusCode": 200,
				"statusDescription": "OK",
				"traceId": "8ee2a80171ff4c34845f2b491880a2e2|BN20130530|7.7.0.0|",
				"addressLine": "2 St Clair Ave E",
				"adminDistrict": "ON",
				"adminDistrict2": "Toronto",
				"countryRegion": "Canada",
				"formattedAddress": "2 St Clair Ave E, Toronto, ON M4T 2T5, Canada",
				"locality": "Toronto",
				"neighborhood": "Rosedale-Moore Park",
				"postalCode": "M4T 2T5"
			},
			"geometry": {
				"type": "Point",
				"coordinates": [
					-79.39377,
					43.68848
				]
			},
			"bbox": [
				-79.3953246,
				43.6873558,
				-79.3922154,
				43.6896042
			]
		}
	]
}
