{
	"type": "FeatureCollection",
	"features": [
		{
			"type": "Feature",
			"properties": {
				"confidence": 9,
				"authenticationResultCode": "ValidCredentials",
				"brandLogoUri": "http://dev.virtualearth.net/Branding/logo_powered_by.png",
				"copyright": "Copyright © 2017 Microsoft and its suppliers. All rights reserved. This API cannot be accessed and the content and any results may not be used, reproduced or transmitted in any manner without express written permission from Microsoft Corporation.",
				"entityType": "Address",
				"matchCodes": [
					"Good"
				],
				"name": "20 Berkeley Ct, Unionville, ON L3R 6M3, Canada",
				"statusCode": 200,
				"statusDescription": "OK",
				"traceId": "25d6cc7ba6e94a63a9a12467dd77d903|BN20181720|7.7.0.0|",
				"addressLine": "20 Berkeley Ct",
				"adminDistrict": "ON",
				"adminDistrict2": "York",
				"countryRegion": "Canada",
				"formattedAddress": "20 Berkeley Ct, Unionville, ON L3R 6M3, Canada",
				"locality": "Markham",
				"neighborhood": "Unionville",
				"postalCode": "L3R 6M3"
			},
			"geometry": {
				"type": "Point",
				"coordinates": [
					-79.30586,
					43.86877
				]
			},
			"bbox": [
				-79.3074193,
				43.8676458,
				-79.3043007,
				43.8698942
			]
		}
	]
}
