{
	"type": "FeatureCollection",
	"features": [
		{
			"type": "Feature",
			"properties": {
				"confidence": 9,
				"authenticationResultCode": "ValidCredentials",
				"brandLogoUri": "http://dev.virtualearth.net/Branding/logo_powered_by.png",
				"copyright": "Copyright © 2017 Microsoft and its suppliers. All rights reserved. This API cannot be accessed and the content and any results may not be used, reproduced or transmitted in any manner without express written permission from Microsoft Corporation.",
				"entityType": "Address",
				"matchCodes": [
					"Good"
				],
				"name": "20 Camden St, Toronto, ON M5V 1V1, Canada",
				"statusCode": 200,
				"statusDescription": "OK",
				"traceId": "2dd19fa970e24ca8930af53ba777c3a9|BN20130522|7.7.0.0|",
				"addressLine": "20 Camden St",
				"adminDistrict": "ON",
				"adminDistrict2": "Toronto",
				"countryRegion": "Canada",
				"formattedAddress": "20 Camden St, Toronto, ON M5V 1V1, Canada",
				"locality": "Toronto",
				"neighborhood": "Waterfront Communities-the Island",
				"postalCode": "M5V 1V1"
			},
			"geometry": {
				"type": "Point",
				"coordinates": [
					-79.39696,
					43.64736
				]
			},
			"bbox": [
				-79.3985136,
				43.6462358,
				-79.3954064,
				43.6484842
			]
		}
	]
}
