{
	"type": "FeatureCollection",
	"features": [
		{
			"type": "Feature",
			"properties": {
				"confidence": 9,
				"authenticationResultCode": "ValidCredentials",
				"brandLogoUri": "http://dev.virtualearth.net/Branding/logo_powered_by.png",
				"copyright": "Copyright © 2017 Microsoft and its suppliers. All rights reserved. This API cannot be accessed and the content and any results may not be used, reproduced or transmitted in any manner without express written permission from Microsoft Corporation.",
				"entityType": "Address",
				"matchCodes": [
					"Good"
				],
				"name": "20 Rue de la Plage, Lavaltrie, QC J5T 1E8, Canada",
				"statusCode": 200,
				"statusDescription": "OK",
				"traceId": "e5d6a853e6e94ba7a1ab88ed04509040|BN20280152|7.7.0.0|",
				"addressLine": "20 Rue de la Plage",
				"adminDistrict": "QC",
				"adminDistrict2": "D'Autray",
				"countryRegion": "Canada",
				"formattedAddress": "20 Rue de la Plage, Lavaltrie, QC J5T 1E8, Canada",
				"locality": "Lavaltrie",
				"postalCode": "J5T 1E8"
			},
			"geometry": {
				"type": "Point",
				"coordinates": [
					-73.28582,
					45.87604
				]
			},
			"bbox": [
				-73.2874347,
				45.8749158,
				-73.2842053,
				45.8771642
			]
		}
	]
}
