{
	"type": "FeatureCollection",
	"features": [
		{
			"type": "Feature",
			"properties": {
				"confidence": 9,
				"authenticationResultCode": "ValidCredentials",
				"brandLogoUri": "http://dev.virtualearth.net/Branding/logo_powered_by.png",
				"copyright": "Copyright © 2017 Microsoft and its suppliers. All rights reserved. This API cannot be accessed and the content and any results may not be used, reproduced or transmitted in any manner without express written permission from Microsoft Corporation.",
				"entityType": "Address",
				"matchCodes": [
					"Good"
				],
				"name": "20 Tagish Rd, Whitehorse, YT Y1A 3P5, Canada",
				"statusCode": 200,
				"statusDescription": "OK",
				"traceId": "c59783343b6a4abf96e0627e73ccdb8a|BN20160335|7.7.0.0|",
				"addressLine": "20 Tagish Rd",
				"adminDistrict": "YT",
				"adminDistrict2": "Yukon",
				"countryRegion": "Canada",
				"formattedAddress": "20 Tagish Rd, Whitehorse, YT Y1A 3P5, Canada",
				"locality": "Whitehorse",
				"postalCode": "Y1A 3P5"
			},
			"geometry": {
				"type": "Point",
				"coordinates": [
					-135.0299,
					60.70842
				]
			},
			"bbox": [
				-135.0321977,
				60.7072958,
				-135.0276023,
				60.7095442
			]
		}
	]
}
