{
	"type": "FeatureCollection",
	"features": [
		{
			"type": "Feature",
			"properties": {
				"confidence": 9,
				"authenticationResultCode": "ValidCredentials",
				"brandLogoUri": "http://dev.virtualearth.net/Branding/logo_powered_by.png",
				"copyright": "Copyright © 2017 Microsoft and its suppliers. All rights reserved. This API cannot be accessed and the content and any results may not be used, reproduced or transmitted in any manner without express written permission from Microsoft Corporation.",
				"entityType": "Address",
				"matchCodes": [
					"Good"
				],
				"name": "20 Route Villeneuve, Tremblay, QC G7H 5A8, Canada",
				"statusCode": 200,
				"statusDescription": "OK",
				"traceId": "8f5a6a1ce39f406ea56e252d903168fc|BN20131519|7.7.0.0|",
				"addressLine": "20 Route Villeneuve",
				"adminDistrict": "QC",
				"adminDistrict2": "Saguenay",
				"countryRegion": "Canada",
				"formattedAddress": "20 Route Villeneuve, Tremblay, QC G7H 5A8, Canada",
				"locality": "Saguenay",
				"neighborhood": "Tremblay",
				"postalCode": "G7H 5A8"
			},
			"geometry": {
				"type": "Point",
				"coordinates": [
					-70.99738,
					48.46256
				]
			},
			"bbox": [
				-70.9990753,
				48.4614358,
				-70.9956847,
				48.4636842
			]
		}
	]
}
