{
	"type": "FeatureCollection",
	"features": [
		{
			"type": "Feature",
			"properties": {
				"confidence": 9,
				"authenticationResultCode": "ValidCredentials",
				"brandLogoUri": "http://dev.virtualearth.net/Branding/logo_powered_by.png",
				"copyright": "Copyright © 2017 Microsoft and its suppliers. All rights reserved. This API cannot be accessed and the content and any results may not be used, reproduced or transmitted in any manner without express written permission from Microsoft Corporation.",
				"entityType": "Address",
				"matchCodes": [
					"Good"
				],
				"name": "200 Rue Bank, Sherbrooke, QC J1H 4K3, Canada",
				"statusCode": 200,
				"statusDescription": "OK",
				"traceId": "1c33437484ea4fed947b47e61a23bfc7|BN20260231|7.7.0.0|",
				"addressLine": "200 Rue Bank",
				"adminDistrict": "QC",
				"adminDistrict2": "Sherbrooke",
				"countryRegion": "Canada",
				"formattedAddress": "200 Rue Bank, Sherbrooke, QC J1H 4K3, Canada",
				"locality": "Sherbrooke",
				"postalCode": "J1H 4K3"
			},
			"geometry": {
				"type": "Point",
				"coordinates": [
					-71.89575,
					45.40443
				]
			},
			"bbox": [
				-71.8973511,
				45.4033058,
				-71.8941489,
				45.4055542
			]
		}
	]
}
