{
	"type": "FeatureCollection",
	"features": [
		{
			"type": "Feature",
			"properties": {
				"confidence": 7,
				"authenticationResultCode": "ValidCredentials",
				"brandLogoUri": "http://dev.virtualearth.net/Branding/logo_powered_by.png",
				"copyright": "Copyright © 2017 Microsoft and its suppliers. All rights reserved. This API cannot be accessed and the content and any results may not be used, reproduced or transmitted in any manner without express written permission from Microsoft Corporation.",
				"entityType": "RoadBlock",
				"matchCodes": [
					"UpHierarchy"
				],
				"name": "James St S, Thunder Bay, ON P7E, Canada",
				"statusCode": 200,
				"statusDescription": "OK",
				"traceId": "55d6c1ba9e0244abb05e22e633bd6b8a|BN20130533|7.7.0.0|",
				"addressLine": "James St S",
				"adminDistrict": "ON",
				"adminDistrict2": "Thunder Bay",
				"countryRegion": "Canada",
				"formattedAddress": "James St S, Thunder Bay, ON P7E, Canada",
				"locality": "Thunder Bay",
				"postalCode": "P7E"
			},
			"geometry": {
				"type": "Point",
				"coordinates": [
					-89.28962,
					48.37261
				]
			},
			"bbox": [
				-89.29064,
				48.35495,
				-89.28498,
				48.38413
			]
		}
	]
}
