{
	"type": "FeatureCollection",
	"features": [
		{
			"type": "Feature",
			"properties": {
				"confidence": 9,
				"authenticationResultCode": "ValidCredentials",
				"brandLogoUri": "http://dev.virtualearth.net/Branding/logo_powered_by.png",
				"copyright": "Copyright © 2017 Microsoft and its suppliers. All rights reserved. This API cannot be accessed and the content and any results may not be used, reproduced or transmitted in any manner without express written permission from Microsoft Corporation.",
				"entityType": "Address",
				"matchCodes": [
					"Good"
				],
				"name": "201 Robertson St, Thunder Bay, ON P7C 2N7, Canada",
				"statusCode": 200,
				"statusDescription": "OK",
				"traceId": "f22409281d6448b58a9b984414ec9fb4|BN20280152|7.7.0.0|",
				"addressLine": "201 Robertson St",
				"adminDistrict": "ON",
				"adminDistrict2": "Thunder Bay",
				"countryRegion": "Canada",
				"formattedAddress": "201 Robertson St, Thunder Bay, ON P7C 2N7, Canada",
				"locality": "Thunder Bay",
				"postalCode": "P7C 2N7"
			},
			"geometry": {
				"type": "Point",
				"coordinates": [
					-89.23794,
					48.39347
				]
			},
			"bbox": [
				-89.239633,
				48.3923458,
				-89.236247,
				48.3945942
			]
		}
	]
}
