{
	"type": "FeatureCollection",
	"features": [
		{
			"type": "Feature",
			"properties": {
				"confidence": 9,
				"authenticationResultCode": "ValidCredentials",
				"brandLogoUri": "http://dev.virtualearth.net/Branding/logo_powered_by.png",
				"copyright": "Copyright © 2017 Microsoft and its suppliers. All rights reserved. This API cannot be accessed and the content and any results may not be used, reproduced or transmitted in any manner without express written permission from Microsoft Corporation.",
				"entityType": "Address",
				"matchCodes": [
					"Good"
				],
				"name": "20204 110 Ave NW, Edmonton, AB T5S 1X8, Canada",
				"statusCode": 200,
				"statusDescription": "OK",
				"traceId": "c9b806618dcd48f9abd99e3a8c1cbae2|BN20130719|7.7.0.0|",
				"addressLine": "20204 110 Ave NW",
				"adminDistrict": "AB",
				"adminDistrict2": "Alberta",
				"countryRegion": "Canada",
				"formattedAddress": "20204 110 Ave NW, Edmonton, AB T5S 1X8, Canada",
				"locality": "Edmonton",
				"neighborhood": "Winterburn Industrial Area East",
				"postalCode": "T5S 1X8"
			},
			"geometry": {
				"type": "Point",
				"coordinates": [
					-113.66946,
					53.55719
				]
			},
			"bbox": [
				-113.6713524,
				53.5560658,
				-113.6675676,
				53.5583142
			]
		}
	]
}
