{
	"type": "FeatureCollection",
	"features": [
		{
			"type": "Feature",
			"properties": {
				"confidence": 9,
				"authenticationResultCode": "ValidCredentials",
				"brandLogoUri": "http://dev.virtualearth.net/Branding/logo_powered_by.png",
				"copyright": "Copyright © 2017 Microsoft and its suppliers. All rights reserved. This API cannot be accessed and the content and any results may not be used, reproduced or transmitted in any manner without express written permission from Microsoft Corporation.",
				"entityType": "Address",
				"matchCodes": [
					"Good"
				],
				"name": "20214 116B Ave, Maple Ridge, BC V2X 0E4, Canada",
				"statusCode": 200,
				"statusDescription": "OK",
				"traceId": "7619dc7a9237437f8560289576726317|BN20130634|7.7.0.0|",
				"addressLine": "20214 116B Ave",
				"adminDistrict": "BC",
				"adminDistrict2": "Greater Vancouver",
				"countryRegion": "Canada",
				"formattedAddress": "20214 116B Ave, Maple Ridge, BC V2X 0E4, Canada",
				"locality": "Maple Ridge",
				"postalCode": "V2X 0E4"
			},
			"geometry": {
				"type": "Point",
				"coordinates": [
					-122.6614046,
					49.2151722
				]
			},
			"bbox": [
				-122.6631255,
				49.214048,
				-122.6596836,
				49.2162963
			]
		}
	]
}
