{
	"type": "FeatureCollection",
	"features": [
		{
			"type": "Feature",
			"properties": {
				"confidence": 6,
				"authenticationResultCode": "ValidCredentials",
				"brandLogoUri": "http://dev.virtualearth.net/Branding/logo_powered_by.png",
				"copyright": "Copyright © 2017 Microsoft and its suppliers. All rights reserved. This API cannot be accessed and the content and any results may not be used, reproduced or transmitted in any manner without express written permission from Microsoft Corporation.",
				"entityType": "RoadBlock",
				"matchCodes": [
					"UpHierarchy"
				],
				"name": "Baseline Rd, Clarington, ON L1C, Canada",
				"statusCode": 200,
				"statusDescription": "OK",
				"traceId": "0221ee6e88454f85963637259d2d6271|BN20130634|7.7.0.0|",
				"addressLine": "Baseline Rd",
				"adminDistrict": "ON",
				"adminDistrict2": "Durham",
				"countryRegion": "Canada",
				"formattedAddress": "Baseline Rd, Clarington, ON L1C, Canada",
				"locality": "Clarington",
				"neighborhood": "Bowmanville",
				"postalCode": "L1C 3K3"
			},
			"geometry": {
				"type": "Point",
				"coordinates": [
					-78.71042,
					43.89328
				]
			},
			"bbox": [
				-78.7252199,
				43.88997,
				-78.65638,
				43.90557
			]
		}
	]
}
