{
	"type": "FeatureCollection",
	"features": [
		{
			"type": "Feature",
			"properties": {
				"confidence": 9,
				"authenticationResultCode": "ValidCredentials",
				"brandLogoUri": "http://dev.virtualearth.net/Branding/logo_powered_by.png",
				"copyright": "Copyright © 2017 Microsoft and its suppliers. All rights reserved. This API cannot be accessed and the content and any results may not be used, reproduced or transmitted in any manner without express written permission from Microsoft Corporation.",
				"entityType": "Address",
				"matchCodes": [
					"Good"
				],
				"name": "2023 Kingsway Ave, Port Coquitlam, BC V3C 1S9, Canada",
				"statusCode": 200,
				"statusDescription": "OK",
				"traceId": "46e1e1c6bf3f42b793144ab761b2c57a|BN20130423|7.7.0.0|",
				"addressLine": "2023 Kingsway Ave",
				"adminDistrict": "BC",
				"adminDistrict2": "Greater Vancouver",
				"countryRegion": "Canada",
				"formattedAddress": "2023 Kingsway Ave, Port Coquitlam, BC V3C 1S9, Canada",
				"locality": "Port Coquitlam",
				"postalCode": "V3C 1S9"
			},
			"geometry": {
				"type": "Point",
				"coordinates": [
					-122.7734807,
					49.2576398
				]
			},
			"bbox": [
				-122.7752031,
				49.2565156,
				-122.7717583,
				49.2587639
			]
		}
	]
}
