{
	"type": "FeatureCollection",
	"features": [
		{
			"type": "Feature",
			"properties": {
				"confidence": 7,
				"authenticationResultCode": "ValidCredentials",
				"brandLogoUri": "http://dev.virtualearth.net/Branding/logo_powered_by.png",
				"copyright": "Copyright © 2017 Microsoft and its suppliers. All rights reserved. This API cannot be accessed and the content and any results may not be used, reproduced or transmitted in any manner without express written permission from Microsoft Corporation.",
				"entityType": "Postcode1",
				"matchCodes": [
					"UpHierarchy"
				],
				"name": "North Vancouver, V7L 1A1, Canada",
				"statusCode": 200,
				"statusDescription": "OK",
				"traceId": "07c54f6d0bbe4997bf4f56da763bd708|BN20130442|7.7.0.0|",
				"adminDistrict": "BC",
				"adminDistrict2": "Greater Vancouver",
				"countryRegion": "Canada",
				"formattedAddress": "North Vancouver, V7L 1A1, Canada",
				"locality": "North Vancouver",
				"postalCode": "V7L 1A1"
			},
			"geometry": {
				"type": "Point",
				"coordinates": [
					-123.076034545898,
					49.3095436096191
				]
			},
			"bbox": [
				-123.083933482407,
				49.3056808920485,
				-123.06813560939,
				49.3134063271898
			]
		}
	]
}
