{
	"type": "FeatureCollection",
	"features": [
		{
			"type": "Feature",
			"properties": {
				"confidence": 9,
				"authenticationResultCode": "ValidCredentials",
				"brandLogoUri": "http://dev.virtualearth.net/Branding/logo_powered_by.png",
				"copyright": "Copyright © 2017 Microsoft and its suppliers. All rights reserved. This API cannot be accessed and the content and any results may not be used, reproduced or transmitted in any manner without express written permission from Microsoft Corporation.",
				"entityType": "Address",
				"matchCodes": [
					"Good"
				],
				"name": "2040 Cliffe Ave, Courtenay, BC V9N 2L3, Canada",
				"statusCode": 200,
				"statusDescription": "OK",
				"traceId": "fbb7c4bb94504176be14a4f7c5fe3b56|BN20130447|7.7.0.0|",
				"addressLine": "2040 Cliffe Ave",
				"adminDistrict": "BC",
				"adminDistrict2": "Comox Valley",
				"countryRegion": "Canada",
				"formattedAddress": "2040 Cliffe Ave, Courtenay, BC V9N 2L3, Canada",
				"locality": "Courtenay",
				"postalCode": "V9N 2L3"
			},
			"geometry": {
				"type": "Point",
				"coordinates": [
					-124.98479,
					49.68133
				]
			},
			"bbox": [
				-124.9865274,
				49.6802058,
				-124.9830526,
				49.6824542
			]
		}
	]
}
