{
	"type": "FeatureCollection",
	"features": [
		{
			"type": "Feature",
			"properties": {
				"confidence": 9,
				"authenticationResultCode": "ValidCredentials",
				"brandLogoUri": "http://dev.virtualearth.net/Branding/logo_powered_by.png",
				"copyright": "Copyright © 2017 Microsoft and its suppliers. All rights reserved. This API cannot be accessed and the content and any results may not be used, reproduced or transmitted in any manner without express written permission from Microsoft Corporation.",
				"entityType": "Address",
				"matchCodes": [
					"Good"
				],
				"name": "20403 Kwik Mix Rd, Wainfleet, ON L0S, Canada",
				"statusCode": 200,
				"statusDescription": "OK",
				"traceId": "c2cfa80549354b9a9858b948ef322edb|BN20130532|7.7.0.0|",
				"addressLine": "20403 Kwik Mix Rd",
				"adminDistrict": "ON",
				"adminDistrict2": "Niagara",
				"countryRegion": "Canada",
				"formattedAddress": "20403 Kwik Mix Rd, Wainfleet, ON L0S, Canada",
				"locality": "Wainfleet",
				"postalCode": "L0S 1V0"
			},
			"geometry": {
				"type": "Point",
				"coordinates": [
					-79.29401,
					42.89206
				]
			},
			"bbox": [
				-79.2955444,
				42.8909358,
				-79.2924756,
				42.8931842
			]
		}
	]
}
