{
	"type": "FeatureCollection",
	"features": [
		{
			"type": "Feature",
			"properties": {
				"confidence": 9,
				"authenticationResultCode": "ValidCredentials",
				"brandLogoUri": "http://dev.virtualearth.net/Branding/logo_powered_by.png",
				"copyright": "Copyright © 2017 Microsoft and its suppliers. All rights reserved. This API cannot be accessed and the content and any results may not be used, reproduced or transmitted in any manner without express written permission from Microsoft Corporation.",
				"entityType": "Address",
				"matchCodes": [
					"Good"
				],
				"name": "2065 Triumph St, Vancouver, BC V5L 1K7, Canada",
				"statusCode": 200,
				"statusDescription": "OK",
				"traceId": "aa20115e6f06488cb1abbc4aa498207a|BN20130625|7.7.0.0|",
				"addressLine": "2065 Triumph St",
				"adminDistrict": "BC",
				"adminDistrict2": "Greater Vancouver",
				"countryRegion": "Canada",
				"formattedAddress": "2065 Triumph St, Vancouver, BC V5L 1K7, Canada",
				"locality": "Vancouver",
				"neighborhood": "Hastings-Sunrise",
				"postalCode": "V5L 1K7"
			},
			"geometry": {
				"type": "Point",
				"coordinates": [
					-123.0619,
					49.2841499
				]
			},
			"bbox": [
				-123.0636233,
				49.2830257,
				-123.0601767,
				49.2852741
			]
		}
	]
}
