{
	"type": "FeatureCollection",
	"features": [
		{
			"type": "Feature",
			"properties": {
				"confidence": 9,
				"authenticationResultCode": "ValidCredentials",
				"brandLogoUri": "http://dev.virtualearth.net/Branding/logo_powered_by.png",
				"copyright": "Copyright © 2017 Microsoft and its suppliers. All rights reserved. This API cannot be accessed and the content and any results may not be used, reproduced or transmitted in any manner without express written permission from Microsoft Corporation.",
				"entityType": "Address",
				"matchCodes": [
					"Good"
				],
				"name": "2067 Sea Mount Pl, Central Saanich, BC V8M 1M5, Canada",
				"statusCode": 200,
				"statusDescription": "OK",
				"traceId": "f372ff56aff8401fad7faadb4420bd2a|BN20130442|7.7.0.0|",
				"addressLine": "2067 Sea Mount Pl",
				"adminDistrict": "BC",
				"adminDistrict2": "Capital",
				"countryRegion": "Canada",
				"formattedAddress": "2067 Sea Mount Pl, Central Saanich, BC V8M 1M5, Canada",
				"locality": "Central Saanich",
				"postalCode": "V8M 1M5"
			},
			"geometry": {
				"type": "Point",
				"coordinates": [
					-123.4148669,
					48.5778012
				]
			},
			"bbox": [
				-123.4165661,
				48.576677,
				-123.4131678,
				48.5789253
			]
		}
	]
}
