{
	"type": "FeatureCollection",
	"features": [
		{
			"type": "Feature",
			"properties": {
				"confidence": 9,
				"authenticationResultCode": "ValidCredentials",
				"brandLogoUri": "http://dev.virtualearth.net/Branding/logo_powered_by.png",
				"copyright": "Copyright © 2017 Microsoft and its suppliers. All rights reserved. This API cannot be accessed and the content and any results may not be used, reproduced or transmitted in any manner without express written permission from Microsoft Corporation.",
				"entityType": "Address",
				"matchCodes": [
					"Good"
				],
				"name": "207 Shawinigan Way SW, Calgary, AB T2Y 2W3, Canada",
				"statusCode": 200,
				"statusDescription": "OK",
				"traceId": "0c49bdf050b6441d8295f29c858eab8a|BN20181720|7.7.0.0|",
				"addressLine": "207 Shawinigan Way SW",
				"adminDistrict": "AB",
				"adminDistrict2": "Alberta",
				"countryRegion": "Canada",
				"formattedAddress": "207 Shawinigan Way SW, Calgary, AB T2Y 2W3, Canada",
				"locality": "Calgary",
				"neighborhood": "Shawnessy",
				"postalCode": "T2Y 2W3"
			},
			"geometry": {
				"type": "Point",
				"coordinates": [
					-114.08463,
					50.90585
				]
			},
			"bbox": [
				-114.0864127,
				50.9047258,
				-114.0828473,
				50.9069742
			]
		}
	]
}
