{
	"type": "FeatureCollection",
	"features": [
		{
			"type": "Feature",
			"properties": {
				"confidence": 9,
				"authenticationResultCode": "ValidCredentials",
				"brandLogoUri": "http://dev.virtualearth.net/Branding/logo_powered_by.png",
				"copyright": "Copyright © 2017 Microsoft and its suppliers. All rights reserved. This API cannot be accessed and the content and any results may not be used, reproduced or transmitted in any manner without express written permission from Microsoft Corporation.",
				"entityType": "Address",
				"matchCodes": [
					"Good"
				],
				"name": "20731 46A Ave, Langley, BC V3A 3K1, Canada",
				"statusCode": 200,
				"statusDescription": "OK",
				"traceId": "8051961ef178498f8dadbff157ab76f4|BN20130621|7.7.0.0|",
				"addressLine": "20731 46A Ave",
				"adminDistrict": "BC",
				"adminDistrict2": "Greater Vancouver",
				"countryRegion": "Canada",
				"formattedAddress": "20731 46A Ave, Langley, BC V3A 3K1, Canada",
				"locality": "Langley",
				"neighborhood": "Uplands",
				"postalCode": "V3A 3K1"
			},
			"geometry": {
				"type": "Point",
				"coordinates": [
					-122.6491245,
					49.0866569
				]
			},
			"bbox": [
				-122.650841,
				49.0855328,
				-122.647408,
				49.0877811
			]
		}
	]
}
