{
	"type": "FeatureCollection",
	"features": [
		{
			"type": "Feature",
			"properties": {
				"confidence": 9,
				"authenticationResultCode": "ValidCredentials",
				"brandLogoUri": "http://dev.virtualearth.net/Branding/logo_powered_by.png",
				"copyright": "Copyright © 2017 Microsoft and its suppliers. All rights reserved. This API cannot be accessed and the content and any results may not be used, reproduced or transmitted in any manner without express written permission from Microsoft Corporation.",
				"entityType": "Address",
				"matchCodes": [
					"Good"
				],
				"name": "2077 Lawrence Ave E, Scarborough, ON M1R 2Z4, Canada",
				"statusCode": 200,
				"statusDescription": "OK",
				"traceId": "190ac6433eb04b4cb38388fac2b8ccce|BN20190653|7.7.0.0|",
				"addressLine": "2077 Lawrence Ave E",
				"adminDistrict": "ON",
				"adminDistrict2": "Toronto",
				"countryRegion": "Canada",
				"formattedAddress": "2077 Lawrence Ave E, Scarborough, ON M1R 2Z4, Canada",
				"locality": "Toronto",
				"neighborhood": "Wexford-Maryvale",
				"postalCode": "M1R 2Z4"
			},
			"geometry": {
				"type": "Point",
				"coordinates": [
					-79.2933192,
					43.7455677
				]
			},
			"bbox": [
				-79.2948753,
				43.7444435,
				-79.2917631,
				43.7466918
			]
		}
	]
}
