{
	"type": "FeatureCollection",
	"features": [
		{
			"type": "Feature",
			"properties": {
				"confidence": 9,
				"authenticationResultCode": "ValidCredentials",
				"brandLogoUri": "http://dev.virtualearth.net/Branding/logo_powered_by.png",
				"copyright": "Copyright © 2017 Microsoft and its suppliers. All rights reserved. This API cannot be accessed and the content and any results may not be used, reproduced or transmitted in any manner without express written permission from Microsoft Corporation.",
				"entityType": "Address",
				"matchCodes": [
					"Good"
				],
				"name": "2080 55e Avenue, Dorval, QC H9P 1H1, Canada",
				"statusCode": 200,
				"statusDescription": "OK",
				"traceId": "06cb391048c74623af5d0c828bbca30b|BN20121763|7.7.0.0|",
				"addressLine": "2080 55e Avenue",
				"adminDistrict": "QC",
				"adminDistrict2": "Montreal",
				"countryRegion": "Canada",
				"formattedAddress": "2080 55e Avenue, Dorval, QC H9P 1H1, Canada",
				"locality": "Dorval",
				"postalCode": "H9P 1H1"
			},
			"geometry": {
				"type": "Point",
				"coordinates": [
					-73.72724,
					45.46329
				]
			},
			"bbox": [
				-73.7288428,
				45.4621658,
				-73.7256372,
				45.4644142
			]
		}
	]
}
