{
	"type": "FeatureCollection",
	"features": [
		{
			"type": "Feature",
			"properties": {
				"confidence": 9,
				"authenticationResultCode": "ValidCredentials",
				"brandLogoUri": "http://dev.virtualearth.net/Branding/logo_powered_by.png",
				"copyright": "Copyright © 2017 Microsoft and its suppliers. All rights reserved. This API cannot be accessed and the content and any results may not be used, reproduced or transmitted in any manner without express written permission from Microsoft Corporation.",
				"entityType": "Address",
				"matchCodes": [
					"Good"
				],
				"name": "2087 Gottingen St, Halifax, NS B3K 3B2, Canada",
				"statusCode": 200,
				"statusDescription": "OK",
				"traceId": "44c3ba99cf9a4205ad7dea2efca9fa7e|BN20290118|7.7.0.0|",
				"addressLine": "2087 Gottingen St",
				"adminDistrict": "NS",
				"adminDistrict2": "Halifax",
				"countryRegion": "Canada",
				"formattedAddress": "2087 Gottingen St, Halifax, NS B3K 3B2, Canada",
				"locality": "Halifax",
				"neighborhood": "North End",
				"postalCode": "B3K 3B2"
			},
			"geometry": {
				"type": "Point",
				"coordinates": [
					-63.58265,
					44.65168
				]
			},
			"bbox": [
				-63.5842302,
				44.6505558,
				-63.5810698,
				44.6528042
			]
		}
	]
}
