{
	"type": "FeatureCollection",
	"features": [
		{
			"type": "Feature",
			"properties": {
				"confidence": 9,
				"authenticationResultCode": "ValidCredentials",
				"brandLogoUri": "http://dev.virtualearth.net/Branding/logo_powered_by.png",
				"copyright": "Copyright © 2017 Microsoft and its suppliers. All rights reserved. This API cannot be accessed and the content and any results may not be used, reproduced or transmitted in any manner without express written permission from Microsoft Corporation.",
				"entityType": "Address",
				"matchCodes": [
					"Good"
				],
				"name": "21 Albert St, Trenton, ON K8V 4S4, Canada",
				"statusCode": 200,
				"statusDescription": "OK",
				"traceId": "9bab173ad965402c82c7a42a17a3e4c7|BN20190653|7.7.0.0|",
				"addressLine": "21 Albert St",
				"adminDistrict": "ON",
				"adminDistrict2": "Hastings",
				"countryRegion": "Canada",
				"formattedAddress": "21 Albert St, Trenton, ON K8V 4S4, Canada",
				"locality": "Quinte West",
				"neighborhood": "Trenton",
				"postalCode": "K8V 4S4"
			},
			"geometry": {
				"type": "Point",
				"coordinates": [
					-77.57396,
					44.10026
				]
			},
			"bbox": [
				-77.5755254,
				44.0991358,
				-77.5723946,
				44.1013842
			]
		}
	]
}
