{
	"type": "FeatureCollection",
	"features": [
		{
			"type": "Feature",
			"properties": {
				"confidence": 9,
				"authenticationResultCode": "ValidCredentials",
				"brandLogoUri": "http://dev.virtualearth.net/Branding/logo_powered_by.png",
				"copyright": "Copyright © 2017 Microsoft and its suppliers. All rights reserved. This API cannot be accessed and the content and any results may not be used, reproduced or transmitted in any manner without express written permission from Microsoft Corporation.",
				"entityType": "Address",
				"matchCodes": [
					"Good"
				],
				"name": "21 Randolph Ave, Toronto, ON M6P 4G4, Canada",
				"statusCode": 200,
				"statusDescription": "OK",
				"traceId": "f42d06e622d0418783d691ab5d132e86|BN20240253|7.7.0.0|",
				"addressLine": "21 Randolph Ave",
				"adminDistrict": "ON",
				"adminDistrict2": "Toronto",
				"countryRegion": "Canada",
				"formattedAddress": "21 Randolph Ave, Toronto, ON M6P 4G4, Canada",
				"locality": "Toronto",
				"neighborhood": "Dovercourt-Wallace Emerson-Junction",
				"postalCode": "M6P 4G4"
			},
			"geometry": {
				"type": "Point",
				"coordinates": [
					-79.4507,
					43.65828
				]
			},
			"bbox": [
				-79.4522538,
				43.6571558,
				-79.4491462,
				43.6594042
			]
		}
	]
}
