{
	"type": "FeatureCollection",
	"features": [
		{
			"type": "Feature",
			"properties": {
				"confidence": 9,
				"authenticationResultCode": "ValidCredentials",
				"brandLogoUri": "http://dev.virtualearth.net/Branding/logo_powered_by.png",
				"copyright": "Copyright © 2017 Microsoft and its suppliers. All rights reserved. This API cannot be accessed and the content and any results may not be used, reproduced or transmitted in any manner without express written permission from Microsoft Corporation.",
				"entityType": "Address",
				"matchCodes": [
					"Good"
				],
				"name": "210 Wolfe St, Peterborough, ON K9J 2K9, Canada",
				"statusCode": 200,
				"statusDescription": "OK",
				"traceId": "11552863e26a45dbacdfbf8eb5ec894f|BN20260223|7.7.0.0|",
				"addressLine": "210 Wolfe St",
				"adminDistrict": "ON",
				"adminDistrict2": "Peterborough",
				"countryRegion": "Canada",
				"formattedAddress": "210 Wolfe St, Peterborough, ON K9J 2K9, Canada",
				"locality": "Peterborough",
				"postalCode": "K9J 2K9"
			},
			"geometry": {
				"type": "Point",
				"coordinates": [
					-78.32196,
					44.29838
				]
			},
			"bbox": [
				-78.3235307,
				44.2972558,
				-78.3203893,
				44.2995042
			]
		}
	]
}
