{
	"type": "FeatureCollection",
	"features": [
		{
			"type": "Feature",
			"properties": {
				"confidence": 9,
				"authenticationResultCode": "ValidCredentials",
				"brandLogoUri": "http://dev.virtualearth.net/Branding/logo_powered_by.png",
				"copyright": "Copyright © 2017 Microsoft and its suppliers. All rights reserved. This API cannot be accessed and the content and any results may not be used, reproduced or transmitted in any manner without express written permission from Microsoft Corporation.",
				"entityType": "Address",
				"matchCodes": [
					"Good"
				],
				"name": "2103 6 St, Nisku, AB T9E 7X8, Canada",
				"statusCode": 200,
				"statusDescription": "OK",
				"traceId": "ed93c0f29abe4e3481f7013a8b353c09|BN20240423|7.7.0.0|",
				"addressLine": "2103 6 St",
				"adminDistrict": "AB",
				"adminDistrict2": "Alberta",
				"countryRegion": "Canada",
				"formattedAddress": "2103 6 St, Nisku, AB T9E 7X8, Canada",
				"locality": "Leduc County",
				"neighborhood": "Nisku",
				"postalCode": "T9E 7X8"
			},
			"geometry": {
				"type": "Point",
				"coordinates": [
					-113.52599,
					53.34021
				]
			},
			"bbox": [
				-113.5278728,
				53.3390858,
				-113.5241072,
				53.3413342
			]
		}
	]
}
