{
	"type": "FeatureCollection",
	"features": [
		{
			"type": "Feature",
			"properties": {
				"confidence": 9,
				"authenticationResultCode": "ValidCredentials",
				"brandLogoUri": "http://dev.virtualearth.net/Branding/logo_powered_by.png",
				"copyright": "Copyright © 2017 Microsoft and its suppliers. All rights reserved. This API cannot be accessed and the content and any results may not be used, reproduced or transmitted in any manner without express written permission from Microsoft Corporation.",
				"entityType": "Address",
				"matchCodes": [
					"Good"
				],
				"name": "2127 1st Ave N, Saskatoon, SK S7K 2A3, Canada",
				"statusCode": 200,
				"statusDescription": "OK",
				"traceId": "2bf234bd613b4721ab9cab2eeaf0427f|BN20130422|7.7.0.0|",
				"addressLine": "2127 1st Ave N",
				"adminDistrict": "SK",
				"adminDistrict2": "Saskatchewan",
				"countryRegion": "Canada",
				"formattedAddress": "2127 1st Ave N, Saskatoon, SK S7K 2A3, Canada",
				"locality": "Saskatoon",
				"neighborhood": "North Industrial",
				"postalCode": "S7K 2A3"
			},
			"geometry": {
				"type": "Point",
				"coordinates": [
					-106.66105,
					52.15885
				]
			},
			"bbox": [
				-106.6628824,
				52.1577258,
				-106.6592176,
				52.1599742
			]
		}
	]
}
