{
	"type": "FeatureCollection",
	"features": [
		{
			"type": "Feature",
			"properties": {
				"confidence": 9,
				"authenticationResultCode": "ValidCredentials",
				"brandLogoUri": "http://dev.virtualearth.net/Branding/logo_powered_by.png",
				"copyright": "Copyright © 2017 Microsoft and its suppliers. All rights reserved. This API cannot be accessed and the content and any results may not be used, reproduced or transmitted in any manner without express written permission from Microsoft Corporation.",
				"entityType": "Address",
				"matchCodes": [
					"Good"
				],
				"name": "213 2 Ave NW, Slave Lake, AB T0G 2A1, Canada",
				"statusCode": 200,
				"statusDescription": "OK",
				"traceId": "8eb6c0e686534d2686e05a230940921e|BN20160335|7.7.0.0|",
				"addressLine": "213 2 Ave NW",
				"adminDistrict": "AB",
				"adminDistrict2": "Alberta",
				"countryRegion": "Canada",
				"formattedAddress": "213 2 Ave NW, Slave Lake, AB T0G 2A1, Canada",
				"locality": "Slave Lake",
				"postalCode": "T0G 2A1"
			},
			"geometry": {
				"type": "Point",
				"coordinates": [
					-114.77366,
					55.2826852
				]
			},
			"bbox": [
				-114.7756338,
				55.281561,
				-114.7716862,
				55.2838093
			]
		}
	]
}
