{
	"type": "FeatureCollection",
	"features": [
		{
			"type": "Feature",
			"properties": {
				"confidence": 9,
				"authenticationResultCode": "ValidCredentials",
				"brandLogoUri": "http://dev.virtualearth.net/Branding/logo_powered_by.png",
				"copyright": "Copyright © 2017 Microsoft and its suppliers. All rights reserved. This API cannot be accessed and the content and any results may not be used, reproduced or transmitted in any manner without express written permission from Microsoft Corporation.",
				"entityType": "Address",
				"matchCodes": [
					"Good"
				],
				"name": "2139 Wyecroft Rd, Oakville, ON L6L 5L7, Canada",
				"statusCode": 200,
				"statusDescription": "OK",
				"traceId": "58e4c8a8738e4e20819d483953e77c62|BN20190653|7.7.0.0|",
				"addressLine": "2139 Wyecroft Rd",
				"adminDistrict": "ON",
				"adminDistrict2": "Halton",
				"countryRegion": "Canada",
				"formattedAddress": "2139 Wyecroft Rd, Oakville, ON L6L 5L7, Canada",
				"locality": "Oakville",
				"postalCode": "L6L 5L7"
			},
			"geometry": {
				"type": "Point",
				"coordinates": [
					-79.72635,
					43.41784
				]
			},
			"bbox": [
				-79.7278976,
				43.4167158,
				-79.7248024,
				43.4189642
			]
		}
	]
}
