{
	"type": "FeatureCollection",
	"features": [
		{
			"type": "Feature",
			"properties": {
				"confidence": 9,
				"authenticationResultCode": "ValidCredentials",
				"brandLogoUri": "http://dev.virtualearth.net/Branding/logo_powered_by.png",
				"copyright": "Copyright © 2017 Microsoft and its suppliers. All rights reserved. This API cannot be accessed and the content and any results may not be used, reproduced or transmitted in any manner without express written permission from Microsoft Corporation.",
				"entityType": "Address",
				"matchCodes": [
					"Good"
				],
				"name": "214 Center Ave, Blumenort, MB R0A 0C1, Canada",
				"statusCode": 200,
				"statusDescription": "OK",
				"traceId": "3d6eb21cc02748a295cfa47d81bfe860|BN20131519|7.7.0.0|",
				"addressLine": "214 Center Ave",
				"adminDistrict": "MB",
				"adminDistrict2": "Manitoba",
				"countryRegion": "Canada",
				"formattedAddress": "214 Center Ave, Blumenort, MB R0A 0C1, Canada",
				"locality": "Hanover",
				"neighborhood": "Blumenort",
				"postalCode": "R0A 0C1"
			},
			"geometry": {
				"type": "Point",
				"coordinates": [
					-96.69546,
					49.60412
				]
			},
			"bbox": [
				-96.6971946,
				49.6029958,
				-96.6937254,
				49.6052442
			]
		}
	]
}
