{
	"type": "FeatureCollection",
	"features": [
		{
			"type": "Feature",
			"properties": {
				"confidence": 9,
				"authenticationResultCode": "ValidCredentials",
				"brandLogoUri": "http://dev.virtualearth.net/Branding/logo_powered_by.png",
				"copyright": "Copyright © 2017 Microsoft and its suppliers. All rights reserved. This API cannot be accessed and the content and any results may not be used, reproduced or transmitted in any manner without express written permission from Microsoft Corporation.",
				"entityType": "Address",
				"matchCodes": [
					"Good"
				],
				"name": "2140 Rue de la Province, Longueuil, QC J4G 1R7, Canada",
				"statusCode": 200,
				"statusDescription": "OK",
				"traceId": "04c598aaacb64d4d8ab414afe96d5cb4|BN20290118|7.7.0.0|",
				"addressLine": "2140 Rue de la Province",
				"adminDistrict": "QC",
				"adminDistrict2": "Longueuil",
				"countryRegion": "Canada",
				"formattedAddress": "2140 Rue de la Province, Longueuil, QC J4G 1R7, Canada",
				"locality": "Longueuil",
				"postalCode": "J4G 1R7"
			},
			"geometry": {
				"type": "Point",
				"coordinates": [
					-73.47142,
					45.56436
				]
			},
			"bbox": [
				-73.4730257,
				45.5632358,
				-73.4698143,
				45.5654842
			]
		}
	]
}
