{
	"type": "FeatureCollection",
	"features": [
		{
			"type": "Feature",
			"properties": {
				"confidence": 9,
				"authenticationResultCode": "ValidCredentials",
				"brandLogoUri": "http://dev.virtualearth.net/Branding/logo_powered_by.png",
				"copyright": "Copyright © 2017 Microsoft and its suppliers. All rights reserved. This API cannot be accessed and the content and any results may not be used, reproduced or transmitted in any manner without express written permission from Microsoft Corporation.",
				"entityType": "Address",
				"matchCodes": [
					"Good"
				],
				"name": "215 Queen St E, Brampton, ON L6W 0A9, Canada",
				"statusCode": 200,
				"statusDescription": "OK",
				"traceId": "a65cdf3673d849138613ea30945ad4bb|BN20320521|7.7.0.0|",
				"addressLine": "215 Queen St E",
				"adminDistrict": "ON",
				"adminDistrict2": "Peel",
				"countryRegion": "Canada",
				"formattedAddress": "215 Queen St E, Brampton, ON L6W 0A9, Canada",
				"locality": "Brampton",
				"neighborhood": "Downtown Brampton",
				"postalCode": "L6W 0A9"
			},
			"geometry": {
				"type": "Point",
				"coordinates": [
					-79.74954,
					43.69544
				]
			},
			"bbox": [
				-79.7510948,
				43.6943158,
				-79.7479852,
				43.6965642
			]
		}
	]
}
