{
	"type": "FeatureCollection",
	"features": [
		{
			"type": "Feature",
			"properties": {
				"confidence": 9,
				"authenticationResultCode": "ValidCredentials",
				"brandLogoUri": "http://dev.virtualearth.net/Branding/logo_powered_by.png",
				"copyright": "Copyright © 2017 Microsoft and its suppliers. All rights reserved. This API cannot be accessed and the content and any results may not be used, reproduced or transmitted in any manner without express written permission from Microsoft Corporation.",
				"entityType": "Address",
				"matchCodes": [
					"Good"
				],
				"name": "215 Herbert St, Gananoque, ON K7G 2Y7, Canada",
				"statusCode": 200,
				"statusDescription": "OK",
				"traceId": "9f2a7572c31f462790e37a5e622edb36|BN20190653|7.7.0.0|",
				"addressLine": "215 Herbert St",
				"adminDistrict": "ON",
				"adminDistrict2": "Leeds and Grenville",
				"countryRegion": "Canada",
				"formattedAddress": "215 Herbert St, Gananoque, ON K7G 2Y7, Canada",
				"locality": "Gananoque",
				"postalCode": "K7G 2Y7"
			},
			"geometry": {
				"type": "Point",
				"coordinates": [
					-76.1567129,
					44.3360263
				]
			},
			"bbox": [
				-76.1582846,
				44.3349022,
				-76.1551412,
				44.3371505
			]
		}
	]
}
