{
	"type": "FeatureCollection",
	"features": [
		{
			"type": "Feature",
			"properties": {
				"confidence": 9,
				"authenticationResultCode": "ValidCredentials",
				"brandLogoUri": "http://dev.virtualearth.net/Branding/logo_powered_by.png",
				"copyright": "Copyright © 2017 Microsoft and its suppliers. All rights reserved. This API cannot be accessed and the content and any results may not be used, reproduced or transmitted in any manner without express written permission from Microsoft Corporation.",
				"entityType": "Address",
				"matchCodes": [
					"Good"
				],
				"name": "2157 23 St NE, Calgary, AB T2E 8J8, Canada",
				"statusCode": 200,
				"statusDescription": "OK",
				"traceId": "6ead575671f64af78b12185fe8a510b7|BN20190642|7.7.0.0|",
				"addressLine": "2157 23 St NE",
				"adminDistrict": "AB",
				"adminDistrict2": "Alberta",
				"countryRegion": "Canada",
				"formattedAddress": "2157 23 St NE, Calgary, AB T2E 8J8, Canada",
				"locality": "Calgary",
				"neighborhood": "Vista Heights",
				"postalCode": "T2E 8J8"
			},
			"geometry": {
				"type": "Point",
				"coordinates": [
					-114.0043624,
					51.0710188
				]
			},
			"bbox": [
				-114.0061515,
				51.0698946,
				-114.0025734,
				51.0721429
			]
		}
	]
}
