{
	"type": "FeatureCollection",
	"features": [
		{
			"type": "Feature",
			"properties": {
				"confidence": 9,
				"authenticationResultCode": "ValidCredentials",
				"brandLogoUri": "http://dev.virtualearth.net/Branding/logo_powered_by.png",
				"copyright": "Copyright © 2017 Microsoft and its suppliers. All rights reserved. This API cannot be accessed and the content and any results may not be used, reproduced or transmitted in any manner without express written permission from Microsoft Corporation.",
				"entityType": "Address",
				"matchCodes": [
					"Good"
				],
				"name": "2176 Government St, Penticton, BC V2A 8B5, Canada",
				"statusCode": 200,
				"statusDescription": "OK",
				"traceId": "490324d40b86486fbdc021896ed239b7|BN20130532|7.7.0.0|",
				"addressLine": "2176 Government St",
				"adminDistrict": "BC",
				"adminDistrict2": "Okanagan-Similkameen",
				"countryRegion": "Canada",
				"formattedAddress": "2176 Government St, Penticton, BC V2A 8B5, Canada",
				"locality": "Penticton",
				"postalCode": "V2A 8B5"
			},
			"geometry": {
				"type": "Point",
				"coordinates": [
					-119.57368,
					49.47514
				]
			},
			"bbox": [
				-119.5754101,
				49.4740158,
				-119.5719499,
				49.4762642
			]
		}
	]
}
