{
	"type": "FeatureCollection",
	"features": [
		{
			"type": "Feature",
			"properties": {
				"confidence": 9,
				"authenticationResultCode": "ValidCredentials",
				"brandLogoUri": "http://dev.virtualearth.net/Branding/logo_powered_by.png",
				"copyright": "Copyright © 2017 Microsoft and its suppliers. All rights reserved. This API cannot be accessed and the content and any results may not be used, reproduced or transmitted in any manner without express written permission from Microsoft Corporation.",
				"entityType": "Address",
				"matchCodes": [
					"Good"
				],
				"name": "2176 Torquay Mews, Mississauga, ON L5N 2M6, Canada",
				"statusCode": 200,
				"statusDescription": "OK",
				"traceId": "05b249606e6d4019bf0c941b426ac6c3|BN20131519|7.7.0.0|",
				"addressLine": "2176 Torquay Mews",
				"adminDistrict": "ON",
				"adminDistrict2": "Peel",
				"countryRegion": "Canada",
				"formattedAddress": "2176 Torquay Mews, Mississauga, ON L5N 2M6, Canada",
				"locality": "Mississauga",
				"neighborhood": "Meadowvale",
				"postalCode": "L5N 2M6"
			},
			"geometry": {
				"type": "Point",
				"coordinates": [
					-79.74303,
					43.59594
				]
			},
			"bbox": [
				-79.7445822,
				43.5948158,
				-79.7414778,
				43.5970642
			]
		}
	]
}
