{
	"type": "FeatureCollection",
	"features": [
		{
			"type": "Feature",
			"properties": {
				"confidence": 9,
				"authenticationResultCode": "ValidCredentials",
				"brandLogoUri": "http://dev.virtualearth.net/Branding/logo_powered_by.png",
				"copyright": "Copyright © 2017 Microsoft and its suppliers. All rights reserved. This API cannot be accessed and the content and any results may not be used, reproduced or transmitted in any manner without express written permission from Microsoft Corporation.",
				"entityType": "Address",
				"matchCodes": [
					"Good"
				],
				"name": "218 Queen St W, Mississauga, ON L5H 1L6, Canada",
				"statusCode": 200,
				"statusDescription": "OK",
				"traceId": "9c863f1d2a834df391b0cb938bfb8398|BN20130423|7.7.0.0|",
				"addressLine": "218 Queen St W",
				"adminDistrict": "ON",
				"adminDistrict2": "Peel",
				"countryRegion": "Canada",
				"formattedAddress": "218 Queen St W, Mississauga, ON L5H 1L6, Canada",
				"locality": "Mississauga",
				"neighborhood": "Port Credit",
				"postalCode": "L5H 1L6"
			},
			"geometry": {
				"type": "Point",
				"coordinates": [
					-79.60063,
					43.54291
				]
			},
			"bbox": [
				-79.6021809,
				43.5417858,
				-79.5990791,
				43.5440342
			]
		}
	]
}
