{
	"type": "FeatureCollection",
	"features": [
		{
			"type": "Feature",
			"properties": {
				"confidence": 9,
				"authenticationResultCode": "ValidCredentials",
				"brandLogoUri": "http://dev.virtualearth.net/Branding/logo_powered_by.png",
				"copyright": "Copyright © 2017 Microsoft and its suppliers. All rights reserved. This API cannot be accessed and the content and any results may not be used, reproduced or transmitted in any manner without express written permission from Microsoft Corporation.",
				"entityType": "Address",
				"matchCodes": [
					"Good"
				],
				"name": "219 Front St E, Toronto, ON M5A 1E8, Canada",
				"statusCode": 200,
				"statusDescription": "OK",
				"traceId": "92f3b630177749ff83995e423e62de7b|BN20130719|7.7.0.0|",
				"addressLine": "219 Front St E",
				"adminDistrict": "ON",
				"adminDistrict2": "Toronto",
				"countryRegion": "Canada",
				"formattedAddress": "219 Front St E, Toronto, ON M5A 1E8, Canada",
				"locality": "Toronto",
				"neighborhood": "Waterfront Communities-the Island",
				"postalCode": "M5A 1E8"
			},
			"geometry": {
				"type": "Point",
				"coordinates": [
					-79.36564,
					43.65066
				]
			},
			"bbox": [
				-79.3671936,
				43.6495358,
				-79.3640864,
				43.6517842
			]
		}
	]
}
