{
	"type": "FeatureCollection",
	"features": [
		{
			"type": "Feature",
			"properties": {
				"confidence": 9,
				"authenticationResultCode": "ValidCredentials",
				"brandLogoUri": "http://dev.virtualearth.net/Branding/logo_powered_by.png",
				"copyright": "Copyright © 2017 Microsoft and its suppliers. All rights reserved. This API cannot be accessed and the content and any results may not be used, reproduced or transmitted in any manner without express written permission from Microsoft Corporation.",
				"entityType": "Address",
				"matchCodes": [
					"Good"
				],
				"name": "22 Nichols Ave, Kentville, NS B4N 2H1, Canada",
				"statusCode": 200,
				"statusDescription": "OK",
				"traceId": "d70b0c56d65d4836a0df18a6872e56d1|BN20130521|7.7.0.0|",
				"addressLine": "22 Nichols Ave",
				"adminDistrict": "NS",
				"adminDistrict2": "Kings",
				"countryRegion": "Canada",
				"formattedAddress": "22 Nichols Ave, Kentville, NS B4N 2H1, Canada",
				"locality": "Kentville",
				"postalCode": "B4N 2H1"
			},
			"geometry": {
				"type": "Point",
				"coordinates": [
					-64.49619,
					45.0882
				]
			},
			"bbox": [
				-64.4977822,
				45.0870758,
				-64.4945978,
				45.0893242
			]
		}
	]
}
