{
	"type": "FeatureCollection",
	"features": [
		{
			"type": "Feature",
			"properties": {
				"confidence": 9,
				"authenticationResultCode": "ValidCredentials",
				"brandLogoUri": "http://dev.virtualearth.net/Branding/logo_powered_by.png",
				"copyright": "Copyright © 2017 Microsoft and its suppliers. All rights reserved. This API cannot be accessed and the content and any results may not be used, reproduced or transmitted in any manner without express written permission from Microsoft Corporation.",
				"entityType": "Address",
				"matchCodes": [
					"Good"
				],
				"name": "220 Gage Ave N, Hamilton, ON L8L 7A5, Canada",
				"statusCode": 200,
				"statusDescription": "OK",
				"traceId": "7144eddb236844c387d8b42313b2a27f|BN20130625|7.7.0.0|",
				"addressLine": "220 Gage Ave N",
				"adminDistrict": "ON",
				"adminDistrict2": "Hamilton",
				"countryRegion": "Canada",
				"formattedAddress": "220 Gage Ave N, Hamilton, ON L8L 7A5, Canada",
				"locality": "Hamilton",
				"neighborhood": "Crown Point West",
				"postalCode": "L8L 7A5"
			},
			"geometry": {
				"type": "Point",
				"coordinates": [
					-79.82534,
					43.2549599
				]
			},
			"bbox": [
				-79.8268835,
				43.2538357,
				-79.8237965,
				43.2560841
			]
		}
	]
}
