{
	"type": "FeatureCollection",
	"features": [
		{
			"type": "Feature",
			"properties": {
				"confidence": 9,
				"authenticationResultCode": "ValidCredentials",
				"brandLogoUri": "http://dev.virtualearth.net/Branding/logo_powered_by.png",
				"copyright": "Copyright © 2017 Microsoft and its suppliers. All rights reserved. This API cannot be accessed and the content and any results may not be used, reproduced or transmitted in any manner without express written permission from Microsoft Corporation.",
				"entityType": "Address",
				"matchCodes": [
					"Good"
				],
				"name": "2211 Rue du Pont, Marieville, QC J3M 1K8, Canada",
				"statusCode": 200,
				"statusDescription": "OK",
				"traceId": "52cb10d4a675451887f6cc6760e13e43|BN20181720|7.7.0.0|",
				"addressLine": "2211 Rue du Pont",
				"adminDistrict": "QC",
				"adminDistrict2": "Rouville",
				"countryRegion": "Canada",
				"formattedAddress": "2211 Rue du Pont, Marieville, QC J3M 1K8, Canada",
				"locality": "Marieville",
				"postalCode": "J3M 1K8"
			},
			"geometry": {
				"type": "Point",
				"coordinates": [
					-73.15199,
					45.43359
				]
			},
			"bbox": [
				-73.153592,
				45.4324658,
				-73.150388,
				45.4347142
			]
		}
	]
}
