{
	"type": "FeatureCollection",
	"features": [
		{
			"type": "Feature",
			"properties": {
				"confidence": 9,
				"authenticationResultCode": "ValidCredentials",
				"brandLogoUri": "http://dev.virtualearth.net/Branding/logo_powered_by.png",
				"copyright": "Copyright © 2017 Microsoft and its suppliers. All rights reserved. This API cannot be accessed and the content and any results may not be used, reproduced or transmitted in any manner without express written permission from Microsoft Corporation.",
				"entityType": "Address",
				"matchCodes": [
					"Good"
				],
				"name": "223 Queen St E, Toronto, ON M5A 1S2, Canada",
				"statusCode": 200,
				"statusDescription": "OK",
				"traceId": "9f75f107b5e44e148197aaf8c9c5ecfc|BN20200239|7.7.0.0|",
				"addressLine": "223 Queen St E",
				"adminDistrict": "ON",
				"adminDistrict2": "Toronto",
				"countryRegion": "Canada",
				"formattedAddress": "223 Queen St E, Toronto, ON M5A 1S2, Canada",
				"locality": "Toronto",
				"neighborhood": "Moss Park",
				"postalCode": "M5A 1S2"
			},
			"geometry": {
				"type": "Point",
				"coordinates": [
					-79.36997,
					43.65424
				]
			},
			"bbox": [
				-79.3715237,
				43.6531158,
				-79.3684163,
				43.6553642
			]
		}
	]
}
