{
	"type": "FeatureCollection",
	"features": [
		{
			"type": "Feature",
			"properties": {
				"confidence": 9,
				"authenticationResultCode": "ValidCredentials",
				"brandLogoUri": "http://dev.virtualearth.net/Branding/logo_powered_by.png",
				"copyright": "Copyright © 2017 Microsoft and its suppliers. All rights reserved. This API cannot be accessed and the content and any results may not be used, reproduced or transmitted in any manner without express written permission from Microsoft Corporation.",
				"entityType": "Address",
				"matchCodes": [
					"Good"
				],
				"name": "2231 Banff Trl NW, Calgary, AB T2M 4L2, Canada",
				"statusCode": 200,
				"statusDescription": "OK",
				"traceId": "0dc6b744c7364eec96e7728339556f56|BN20130625|7.7.0.0|",
				"addressLine": "2231 Banff Trl NW",
				"adminDistrict": "AB",
				"adminDistrict2": "Alberta",
				"countryRegion": "Canada",
				"formattedAddress": "2231 Banff Trl NW, Calgary, AB T2M 4L2, Canada",
				"locality": "Calgary",
				"neighborhood": "Banff Trail",
				"postalCode": "T2M 4L2"
			},
			"geometry": {
				"type": "Point",
				"coordinates": [
					-114.11414,
					51.0686
				]
			},
			"bbox": [
				-114.1159289,
				51.0674758,
				-114.1123511,
				51.0697242
			]
		}
	]
}
