{
	"type": "FeatureCollection",
	"features": [
		{
			"type": "Feature",
			"properties": {
				"confidence": 9,
				"authenticationResultCode": "ValidCredentials",
				"brandLogoUri": "http://dev.virtualearth.net/Branding/logo_powered_by.png",
				"copyright": "Copyright © 2017 Microsoft and its suppliers. All rights reserved. This API cannot be accessed and the content and any results may not be used, reproduced or transmitted in any manner without express written permission from Microsoft Corporation.",
				"entityType": "Address",
				"matchCodes": [
					"Good"
				],
				"name": "224 4th Ave S, Saskatoon, SK S7K 5M5, Canada",
				"statusCode": 200,
				"statusDescription": "OK",
				"traceId": "f5947087cd3b4d73aa66208e8a81768c|BN20130625|7.7.0.0|",
				"addressLine": "224 4th Ave S",
				"adminDistrict": "SK",
				"adminDistrict2": "Saskatchewan",
				"countryRegion": "Canada",
				"formattedAddress": "224 4th Ave S, Saskatoon, SK S7K 5M5, Canada",
				"locality": "Saskatoon",
				"neighborhood": "Central Business District",
				"postalCode": "S7K 5M5"
			},
			"geometry": {
				"type": "Point",
				"coordinates": [
					-106.66145,
					52.12567
				]
			},
			"bbox": [
				-106.6632811,
				52.1245458,
				-106.6596189,
				52.1267942
			]
		}
	]
}
