{
	"type": "FeatureCollection",
	"features": [
		{
			"type": "Feature",
			"properties": {
				"confidence": 9,
				"authenticationResultCode": "ValidCredentials",
				"brandLogoUri": "http://dev.virtualearth.net/Branding/logo_powered_by.png",
				"copyright": "Copyright © 2017 Microsoft and its suppliers. All rights reserved. This API cannot be accessed and the content and any results may not be used, reproduced or transmitted in any manner without express written permission from Microsoft Corporation.",
				"entityType": "Address",
				"matchCodes": [
					"Good"
				],
				"name": "225 Dundas St E, Mississauga, ON L5A 1W8, Canada",
				"statusCode": 200,
				"statusDescription": "OK",
				"traceId": "9c8f8aba40a24b7294d9363c06da2a33|BN20130625|7.7.0.0|",
				"addressLine": "225 Dundas St E",
				"adminDistrict": "ON",
				"adminDistrict2": "Peel",
				"countryRegion": "Canada",
				"formattedAddress": "225 Dundas St E, Mississauga, ON L5A 1W8, Canada",
				"locality": "Mississauga",
				"neighborhood": "Cooksville",
				"postalCode": "L5A 1W8"
			},
			"geometry": {
				"type": "Point",
				"coordinates": [
					-79.61187,
					43.58513
				]
			},
			"bbox": [
				-79.6134219,
				43.5840058,
				-79.6103181,
				43.5862542
			]
		}
	]
}
