{
	"type": "FeatureCollection",
	"features": [
		{
			"type": "Feature",
			"properties": {
				"confidence": 9,
				"authenticationResultCode": "ValidCredentials",
				"brandLogoUri": "http://dev.virtualearth.net/Branding/logo_powered_by.png",
				"copyright": "Copyright © 2017 Microsoft and its suppliers. All rights reserved. This API cannot be accessed and the content and any results may not be used, reproduced or transmitted in any manner without express written permission from Microsoft Corporation.",
				"entityType": "Address",
				"matchCodes": [
					"Good"
				],
				"name": "2255 Kirkton Ave, Armstrong, BC V0E, Canada",
				"statusCode": 200,
				"statusDescription": "OK",
				"traceId": "f14f0b97a5e846489eb64464951f7009|BN20130634|7.7.0.0|",
				"addressLine": "2255 Kirkton Ave",
				"adminDistrict": "BC",
				"adminDistrict2": "North Okanagan",
				"countryRegion": "Canada",
				"formattedAddress": "2255 Kirkton Ave, Armstrong, BC V0E, Canada",
				"locality": "Armstrong",
				"postalCode": "V0E 1B0"
			},
			"geometry": {
				"type": "Point",
				"coordinates": [
					-119.18788,
					50.44987
				]
			},
			"bbox": [
				-119.1896454,
				50.4487458,
				-119.1861146,
				50.4509942
			]
		}
	]
}
