{
	"type": "FeatureCollection",
	"features": [
		{
			"type": "Feature",
			"properties": {
				"confidence": 9,
				"authenticationResultCode": "ValidCredentials",
				"brandLogoUri": "http://dev.virtualearth.net/Branding/logo_powered_by.png",
				"copyright": "Copyright © 2017 Microsoft and its suppliers. All rights reserved. This API cannot be accessed and the content and any results may not be used, reproduced or transmitted in any manner without express written permission from Microsoft Corporation.",
				"entityType": "Address",
				"matchCodes": [
					"Good"
				],
				"name": "2256 Shannon Hills Pl, West Kelowna, BC V4T 2V2, Canada",
				"statusCode": 200,
				"statusDescription": "OK",
				"traceId": "625dafb03504439e8c5a3e7aa3f3d168|BN20130422|7.7.0.0|",
				"addressLine": "2256 Shannon Hills Pl",
				"adminDistrict": "BC",
				"adminDistrict2": "Central Okanagan",
				"countryRegion": "Canada",
				"formattedAddress": "2256 Shannon Hills Pl, West Kelowna, BC V4T 2V2, Canada",
				"locality": "West Kelowna",
				"neighborhood": "Westbank",
				"postalCode": "V4T 2V2"
			},
			"geometry": {
				"type": "Point",
				"coordinates": [
					-119.60985,
					49.87225
				]
			},
			"bbox": [
				-119.6115942,
				49.8711258,
				-119.6081058,
				49.8733742
			]
		}
	]
}
