{
	"type": "FeatureCollection",
	"features": [
		{
			"type": "Feature",
			"properties": {
				"confidence": 9,
				"authenticationResultCode": "ValidCredentials",
				"brandLogoUri": "http://dev.virtualearth.net/Branding/logo_powered_by.png",
				"copyright": "Copyright © 2017 Microsoft and its suppliers. All rights reserved. This API cannot be accessed and the content and any results may not be used, reproduced or transmitted in any manner without express written permission from Microsoft Corporation.",
				"entityType": "Address",
				"matchCodes": [
					"Good"
				],
				"name": "227 Bunting Rd, St Catharines, ON L2M 3Y2, Canada",
				"statusCode": 200,
				"statusDescription": "OK",
				"traceId": "c74a63f4277c4d75a631fcb3ddd09b12|BN20130530|7.7.0.0|",
				"addressLine": "227 Bunting Rd",
				"adminDistrict": "ON",
				"adminDistrict2": "Niagara",
				"countryRegion": "Canada",
				"formattedAddress": "227 Bunting Rd, St Catharines, ON L2M 3Y2, Canada",
				"locality": "St Catharines",
				"neighborhood": "Queenston",
				"postalCode": "L2M 3Y2"
			},
			"geometry": {
				"type": "Point",
				"coordinates": [
					-79.2108,
					43.17385
				]
			},
			"bbox": [
				-79.2123415,
				43.1727258,
				-79.2092585,
				43.1749742
			]
		}
	]
}
