{
	"type": "FeatureCollection",
	"features": [
		{
			"type": "Feature",
			"properties": {
				"confidence": 9,
				"authenticationResultCode": "ValidCredentials",
				"brandLogoUri": "http://dev.virtualearth.net/Branding/logo_powered_by.png",
				"copyright": "Copyright © 2017 Microsoft and its suppliers. All rights reserved. This API cannot be accessed and the content and any results may not be used, reproduced or transmitted in any manner without express written permission from Microsoft Corporation.",
				"entityType": "Address",
				"matchCodes": [
					"Good"
				],
				"name": "2273 Blue Oak Cir, Oakville, ON L6M 5J4, Canada",
				"statusCode": 200,
				"statusDescription": "OK",
				"traceId": "829eded73eeb4c6a821e8bf3b6f45323|BN20130520|7.7.0.0|",
				"addressLine": "2273 Blue Oak Cir",
				"adminDistrict": "ON",
				"adminDistrict2": "Halton",
				"countryRegion": "Canada",
				"formattedAddress": "2273 Blue Oak Cir, Oakville, ON L6M 5J4, Canada",
				"locality": "Oakville",
				"neighborhood": "Westmount",
				"postalCode": "L6M 5J4"
			},
			"geometry": {
				"type": "Point",
				"coordinates": [
					-79.76775,
					43.4403999
				]
			},
			"bbox": [
				-79.7692982,
				43.4392757,
				-79.7662018,
				43.4415241
			]
		}
	]
}
