{
	"type": "FeatureCollection",
	"features": [
		{
			"type": "Feature",
			"properties": {
				"confidence": 7,
				"authenticationResultCode": "ValidCredentials",
				"brandLogoUri": "http://dev.virtualearth.net/Branding/logo_powered_by.png",
				"copyright": "Copyright © 2017 Microsoft and its suppliers. All rights reserved. This API cannot be accessed and the content and any results may not be used, reproduced or transmitted in any manner without express written permission from Microsoft Corporation.",
				"entityType": "Postcode1",
				"matchCodes": [
					"UpHierarchy"
				],
				"name": "Crescent Valley, V0G 1H0, Canada",
				"statusCode": 200,
				"statusDescription": "OK",
				"traceId": "ec2b7613bff44490a145f4741a918602|BN20130621|7.7.0.0|",
				"adminDistrict": "BC",
				"adminDistrict2": "Central Kootenay",
				"countryRegion": "Canada",
				"formattedAddress": "Crescent Valley, V0G 1H0, Canada",
				"locality": "Crescent Valley",
				"postalCode": "V0G 1H0"
			},
			"geometry": {
				"type": "Point",
				"coordinates": [
					-117.560752868652,
					49.4511909484863
				]
			},
			"bbox": [
				-117.568674602656,
				49.4473282309157,
				-117.552831134648,
				49.455053666057
			]
		}
	]
}
