{
	"type": "FeatureCollection",
	"features": [
		{
			"type": "Feature",
			"properties": {
				"confidence": 9,
				"authenticationResultCode": "ValidCredentials",
				"brandLogoUri": "http://dev.virtualearth.net/Branding/logo_powered_by.png",
				"copyright": "Copyright © 2017 Microsoft and its suppliers. All rights reserved. This API cannot be accessed and the content and any results may not be used, reproduced or transmitted in any manner without express written permission from Microsoft Corporation.",
				"entityType": "Address",
				"matchCodes": [
					"Good"
				],
				"name": "23 Alexander Ln, Carlow/Mayo, ON K0L, Canada",
				"statusCode": 200,
				"statusDescription": "OK",
				"traceId": "e380de4a47be4bcfa332cbf8ca480135|BN20130431|7.7.0.0|",
				"addressLine": "23 Alexander Ln",
				"adminDistrict": "ON",
				"adminDistrict2": "Hastings",
				"countryRegion": "Canada",
				"formattedAddress": "23 Alexander Ln, Carlow/Mayo, ON K0L, Canada",
				"locality": "Carlow/Mayo",
				"postalCode": "K0L 1G0"
			},
			"geometry": {
				"type": "Point",
				"coordinates": [
					-77.65496,
					45.19696
				]
			},
			"bbox": [
				-77.6565553,
				45.1958358,
				-77.6533647,
				45.1980842
			]
		}
	]
}
