{
	"type": "FeatureCollection",
	"features": [
		{
			"type": "Feature",
			"properties": {
				"confidence": 9,
				"authenticationResultCode": "ValidCredentials",
				"brandLogoUri": "http://dev.virtualearth.net/Branding/logo_powered_by.png",
				"copyright": "Copyright © 2017 Microsoft and its suppliers. All rights reserved. This API cannot be accessed and the content and any results may not be used, reproduced or transmitted in any manner without express written permission from Microsoft Corporation.",
				"entityType": "Address",
				"matchCodes": [
					"Good"
				],
				"name": "230 Lucasville Rd, Halifax, NS B4B 1S1, Canada",
				"statusCode": 200,
				"statusDescription": "OK",
				"traceId": "27627bf848e44ab793c8cd3562320fbb|BN20131519|7.7.0.0|",
				"addressLine": "230 Lucasville Rd",
				"adminDistrict": "NS",
				"adminDistrict2": "Halifax",
				"countryRegion": "Canada",
				"formattedAddress": "230 Lucasville Rd, Halifax, NS B4B 1S1, Canada",
				"locality": "Halifax",
				"neighborhood": "Lucasville",
				"postalCode": "B4B 1S1"
			},
			"geometry": {
				"type": "Point",
				"coordinates": [
					-63.71351,
					44.77502
				]
			},
			"bbox": [
				-63.7150936,
				44.7738958,
				-63.7119264,
				44.7761442
			]
		}
	]
}
