{
	"type": "FeatureCollection",
	"features": [
		{
			"type": "Feature",
			"properties": {
				"confidence": 9,
				"authenticationResultCode": "ValidCredentials",
				"brandLogoUri": "http://dev.virtualearth.net/Branding/logo_powered_by.png",
				"copyright": "Copyright © 2017 Microsoft and its suppliers. All rights reserved. This API cannot be accessed and the content and any results may not be used, reproduced or transmitted in any manner without express written permission from Microsoft Corporation.",
				"entityType": "Address",
				"matchCodes": [
					"Good"
				],
				"name": "2300 Ryan Rd, Courtenay, BC V9N 8N6, Canada",
				"statusCode": 200,
				"statusDescription": "OK",
				"traceId": "8555d86ba1334a708676b02f92d0db3d|BN20320521|7.7.0.0|",
				"addressLine": "2300 Ryan Rd",
				"adminDistrict": "BC",
				"adminDistrict2": "Comox Valley",
				"countryRegion": "Canada",
				"formattedAddress": "2300 Ryan Rd, Courtenay, BC V9N 8N6, Canada",
				"locality": "Courtenay",
				"postalCode": "V9N 8N6"
			},
			"geometry": {
				"type": "Point",
				"coordinates": [
					-124.97098,
					49.7084
				]
			},
			"bbox": [
				-124.9727183,
				49.7072758,
				-124.9692417,
				49.7095242
			]
		}
	]
}
