{
	"type": "FeatureCollection",
	"features": [
		{
			"type": "Feature",
			"properties": {
				"confidence": 9,
				"authenticationResultCode": "ValidCredentials",
				"brandLogoUri": "http://dev.virtualearth.net/Branding/logo_powered_by.png",
				"copyright": "Copyright © 2017 Microsoft and its suppliers. All rights reserved. This API cannot be accessed and the content and any results may not be used, reproduced or transmitted in any manner without express written permission from Microsoft Corporation.",
				"entityType": "Address",
				"matchCodes": [
					"Good"
				],
				"name": "231 HWY-148, St Marys, NB E3A, Canada",
				"statusCode": 200,
				"statusDescription": "OK",
				"traceId": "312c32e5cd1c40af9c5efe0797cef4f1|BN20280152|7.7.0.0|",
				"addressLine": "231 HWY-148",
				"adminDistrict": "NB",
				"adminDistrict2": "York",
				"countryRegion": "Canada",
				"formattedAddress": "231 HWY-148, St Marys, NB E3A, Canada",
				"locality": "St Marys",
				"neighborhood": "Killarney Road",
				"postalCode": "E3A"
			},
			"geometry": {
				"type": "Point",
				"coordinates": [
					-66.6245465,
					46.0392286
				]
			},
			"bbox": [
				-66.626166,
				46.0381045,
				-66.6229271,
				46.0403528
			]
		}
	]
}
