{
	"type": "FeatureCollection",
	"features": [
		{
			"type": "Feature",
			"properties": {
				"confidence": 9,
				"authenticationResultCode": "ValidCredentials",
				"brandLogoUri": "http://dev.virtualearth.net/Branding/logo_powered_by.png",
				"copyright": "Copyright © 2017 Microsoft and its suppliers. All rights reserved. This API cannot be accessed and the content and any results may not be used, reproduced or transmitted in any manner without express written permission from Microsoft Corporation.",
				"entityType": "Address",
				"matchCodes": [
					"Good"
				],
				"name": "2327 Brouseville Rd, Edwardsburgh/Cardinal, ON K0E 1X0, Canada",
				"statusCode": 200,
				"statusDescription": "OK",
				"traceId": "c567d3541fd840fa8c710dceac621abe|BN20240423|7.7.0.0|",
				"addressLine": "2327 Brouseville Rd",
				"adminDistrict": "ON",
				"adminDistrict2": "Leeds and Grenville",
				"countryRegion": "Canada",
				"formattedAddress": "2327 Brouseville Rd, Edwardsburgh/Cardinal, ON K0E 1X0, Canada",
				"locality": "Edwardsburgh/Cardinal",
				"postalCode": "K0E 1X0"
			},
			"geometry": {
				"type": "Point",
				"coordinates": [
					-75.48678,
					44.7909999
				]
			},
			"bbox": [
				-75.488364,
				44.7898757,
				-75.485196,
				44.7921241
			]
		}
	]
}
