{
	"type": "FeatureCollection",
	"features": [
		{
			"type": "Feature",
			"properties": {
				"confidence": 9,
				"authenticationResultCode": "ValidCredentials",
				"brandLogoUri": "http://dev.virtualearth.net/Branding/logo_powered_by.png",
				"copyright": "Copyright © 2017 Microsoft and its suppliers. All rights reserved. This API cannot be accessed and the content and any results may not be used, reproduced or transmitted in any manner without express written permission from Microsoft Corporation.",
				"entityType": "Address",
				"matchCodes": [
					"Good"
				],
				"name": "2327 Meriadoc Dr, Pickering, ON L1X 2T1, Canada",
				"statusCode": 200,
				"statusDescription": "OK",
				"traceId": "0de2e65133a84f08a0ea295e9f3903de|BN20260223|7.7.0.0|",
				"addressLine": "2327 Meriadoc Dr",
				"adminDistrict": "ON",
				"adminDistrict2": "Durham",
				"countryRegion": "Canada",
				"formattedAddress": "2327 Meriadoc Dr, Pickering, ON L1X 2T1, Canada",
				"locality": "Pickering",
				"postalCode": "L1X 2T1"
			},
			"geometry": {
				"type": "Point",
				"coordinates": [
					-79.08525,
					43.86257
				]
			},
			"bbox": [
				-79.0868091,
				43.8614458,
				-79.0836909,
				43.8636942
			]
		}
	]
}
