{
	"type": "FeatureCollection",
	"features": [
		{
			"type": "Feature",
			"properties": {
				"confidence": 9,
				"authenticationResultCode": "ValidCredentials",
				"brandLogoUri": "http://dev.virtualearth.net/Branding/logo_powered_by.png",
				"copyright": "Copyright © 2017 Microsoft and its suppliers. All rights reserved. This API cannot be accessed and the content and any results may not be used, reproduced or transmitted in any manner without express written permission from Microsoft Corporation.",
				"entityType": "Address",
				"matchCodes": [
					"Good"
				],
				"name": "2335 Pegasus Rd NE, Calgary, AB T2E 8C3, Canada",
				"statusCode": 200,
				"statusDescription": "OK",
				"traceId": "3c51c17244344da78213ef5b68bdf80f|BN20121763|7.7.0.0|",
				"addressLine": "2335 Pegasus Rd NE",
				"adminDistrict": "AB",
				"adminDistrict2": "Alberta",
				"countryRegion": "Canada",
				"formattedAddress": "2335 Pegasus Rd NE, Calgary, AB T2E 8C3, Canada",
				"locality": "Calgary",
				"postalCode": "T2E 8C3"
			},
			"geometry": {
				"type": "Point",
				"coordinates": [
					-114.00513,
					51.09411
				]
			},
			"bbox": [
				-114.0069199,
				51.0929858,
				-114.0033401,
				51.0952342
			]
		}
	]
}
