{
	"type": "FeatureCollection",
	"features": [
		{
			"type": "Feature",
			"properties": {
				"confidence": 9,
				"authenticationResultCode": "ValidCredentials",
				"brandLogoUri": "http://dev.virtualearth.net/Branding/logo_powered_by.png",
				"copyright": "Copyright © 2017 Microsoft and its suppliers. All rights reserved. This API cannot be accessed and the content and any results may not be used, reproduced or transmitted in any manner without express written permission from Microsoft Corporation.",
				"entityType": "Address",
				"matchCodes": [
					"Good"
				],
				"name": "235 Queen St, Ottawa, ON K1A 0H5, Canada",
				"statusCode": 200,
				"statusDescription": "OK",
				"traceId": "9eb2510baff0423ab25b19de92058c82|BN20130721|7.7.0.0|",
				"addressLine": "235 Queen St",
				"adminDistrict": "ON",
				"adminDistrict2": "Ottawa",
				"countryRegion": "Canada",
				"formattedAddress": "235 Queen St, Ottawa, ON K1A 0H5, Canada",
				"locality": "Ottawa",
				"neighborhood": "Byward Market-Parliament Hill",
				"postalCode": "K1A 0H5"
			},
			"geometry": {
				"type": "Point",
				"coordinates": [
					-75.701524,
					45.4203977
				]
			},
			"bbox": [
				-75.7031256,
				45.4192735,
				-75.6999224,
				45.4215218
			]
		}
	]
}
