{
	"type": "FeatureCollection",
	"features": [
		{
			"type": "Feature",
			"properties": {
				"confidence": 9,
				"authenticationResultCode": "ValidCredentials",
				"brandLogoUri": "http://dev.virtualearth.net/Branding/logo_powered_by.png",
				"copyright": "Copyright © 2017 Microsoft and its suppliers. All rights reserved. This API cannot be accessed and the content and any results may not be used, reproduced or transmitted in any manner without express written permission from Microsoft Corporation.",
				"entityType": "Address",
				"matchCodes": [
					"Good"
				],
				"name": "235 Ave D N, Saskatoon, SK S7L 1M7, Canada",
				"statusCode": 200,
				"statusDescription": "OK",
				"traceId": "69edddbae5634e099268c6a95b70b9a3|BN20250135|7.7.0.0|",
				"addressLine": "235 Ave D N",
				"adminDistrict": "SK",
				"adminDistrict2": "Saskatchewan",
				"countryRegion": "Canada",
				"formattedAddress": "235 Ave D N, Saskatoon, SK S7L 1M7, Canada",
				"locality": "Saskatoon",
				"neighborhood": "Caswell Hill",
				"postalCode": "S7L 1M7"
			},
			"geometry": {
				"type": "Point",
				"coordinates": [
					-106.67554,
					52.13208
				]
			},
			"bbox": [
				-106.6773713,
				52.1309558,
				-106.6737087,
				52.1332042
			]
		}
	]
}
