{
	"type": "FeatureCollection",
	"features": [
		{
			"type": "Feature",
			"properties": {
				"confidence": 9,
				"authenticationResultCode": "ValidCredentials",
				"brandLogoUri": "http://dev.virtualearth.net/Branding/logo_powered_by.png",
				"copyright": "Copyright © 2017 Microsoft and its suppliers. All rights reserved. This API cannot be accessed and the content and any results may not be used, reproduced or transmitted in any manner without express written permission from Microsoft Corporation.",
				"entityType": "Address",
				"matchCodes": [
					"Good"
				],
				"name": "2358 Rascal Ln, Nanoose Bay, BC V9P 9L6, Canada",
				"statusCode": 200,
				"statusDescription": "OK",
				"traceId": "8b5f6b75b7b44851bff11fababd452a5|BN20200137|7.7.0.0|",
				"addressLine": "2358 Rascal Ln",
				"adminDistrict": "BC",
				"adminDistrict2": "Nanaimo",
				"countryRegion": "Canada",
				"formattedAddress": "2358 Rascal Ln, Nanoose Bay, BC V9P 9L6, Canada",
				"locality": "Nanaimo District",
				"neighborhood": "Nanoose Bay",
				"postalCode": "V9P 9L6"
			},
			"geometry": {
				"type": "Point",
				"coordinates": [
					-124.2710752,
					49.2781536
				]
			},
			"bbox": [
				-124.2727983,
				49.2770294,
				-124.2693521,
				49.2792777
			]
		}
	]
}
