{
	"type": "FeatureCollection",
	"features": [
		{
			"type": "Feature",
			"properties": {
				"confidence": 9,
				"authenticationResultCode": "ValidCredentials",
				"brandLogoUri": "http://dev.virtualearth.net/Branding/logo_powered_by.png",
				"copyright": "Copyright © 2017 Microsoft and its suppliers. All rights reserved. This API cannot be accessed and the content and any results may not be used, reproduced or transmitted in any manner without express written permission from Microsoft Corporation.",
				"entityType": "Address",
				"matchCodes": [
					"Good"
				],
				"name": "2382 HWY-774, Wilsons Beach, NB E5E 1L5, Canada",
				"statusCode": 200,
				"statusDescription": "OK",
				"traceId": "b1f24463040243d39384e474b4075325|BN20130620|7.7.0.0|",
				"addressLine": "2382 HWY-774",
				"adminDistrict": "NB",
				"adminDistrict2": "Charlotte",
				"countryRegion": "Canada",
				"formattedAddress": "2382 HWY-774, Wilsons Beach, NB E5E 1L5, Canada",
				"locality": "Campobello Island",
				"neighborhood": "Wilsons Beach",
				"postalCode": "E5E 1L5"
			},
			"geometry": {
				"type": "Point",
				"coordinates": [
					-66.9373253,
					44.9313179
				]
			},
			"bbox": [
				-66.9389132,
				44.9301937,
				-66.9357374,
				44.932442
			]
		}
	]
}
