{
	"type": "FeatureCollection",
	"features": [
		{
			"type": "Feature",
			"properties": {
				"confidence": 9,
				"authenticationResultCode": "ValidCredentials",
				"brandLogoUri": "http://dev.virtualearth.net/Branding/logo_powered_by.png",
				"copyright": "Copyright © 2017 Microsoft and its suppliers. All rights reserved. This API cannot be accessed and the content and any results may not be used, reproduced or transmitted in any manner without express written permission from Microsoft Corporation.",
				"entityType": "Address",
				"matchCodes": [
					"Good"
				],
				"name": "2393 Monroe Ave, Ottawa, ON K2C 1L3, Canada",
				"statusCode": 200,
				"statusDescription": "OK",
				"traceId": "db04954cbfe941949ba80737ee57ff17|BN20200239|7.7.0.0|",
				"addressLine": "2393 Monroe Ave",
				"adminDistrict": "ON",
				"adminDistrict2": "Ottawa",
				"countryRegion": "Canada",
				"formattedAddress": "2393 Monroe Ave, Ottawa, ON K2C 1L3, Canada",
				"locality": "Ottawa",
				"neighborhood": "Iris",
				"postalCode": "K2C 1L3"
			},
			"geometry": {
				"type": "Point",
				"coordinates": [
					-75.78166,
					45.34813
				]
			},
			"bbox": [
				-75.7832595,
				45.3470058,
				-75.7800605,
				45.3492542
			]
		}
	]
}
