{
	"type": "FeatureCollection",
	"features": [
		{
			"type": "Feature",
			"properties": {
				"confidence": 9,
				"authenticationResultCode": "ValidCredentials",
				"brandLogoUri": "http://dev.virtualearth.net/Branding/logo_powered_by.png",
				"copyright": "Copyright © 2017 Microsoft and its suppliers. All rights reserved. This API cannot be accessed and the content and any results may not be used, reproduced or transmitted in any manner without express written permission from Microsoft Corporation.",
				"entityType": "Address",
				"matchCodes": [
					"Good"
				],
				"name": "2394 HWY-11, Gravenhurst, ON P0C, Canada",
				"statusCode": 200,
				"statusDescription": "OK",
				"traceId": "128a7e66f13f4868921f72f4be42d142|BN20130631|7.7.0.0|",
				"addressLine": "2394 HWY-11",
				"adminDistrict": "ON",
				"adminDistrict2": "Muskoka",
				"countryRegion": "Canada",
				"formattedAddress": "2394 HWY-11, Gravenhurst, ON P0C, Canada",
				"locality": "Gravenhurst",
				"postalCode": "P0C"
			},
			"geometry": {
				"type": "Point",
				"coordinates": [
					-79.3584507,
					44.8936299
				]
			},
			"bbox": [
				-79.3600375,
				44.8925057,
				-79.3568638,
				44.894754
			]
		}
	]
}
