{
	"type": "FeatureCollection",
	"features": [
		{
			"type": "Feature",
			"properties": {
				"confidence": 9,
				"authenticationResultCode": "ValidCredentials",
				"brandLogoUri": "http://dev.virtualearth.net/Branding/logo_powered_by.png",
				"copyright": "Copyright © 2017 Microsoft and its suppliers. All rights reserved. This API cannot be accessed and the content and any results may not be used, reproduced or transmitted in any manner without express written permission from Microsoft Corporation.",
				"entityType": "Address",
				"matchCodes": [
					"Good"
				],
				"name": "2395 Meadowpine Blvd, Mississauga, ON L5N 7W6, Canada",
				"statusCode": 200,
				"statusDescription": "OK",
				"traceId": "ca468d6aa8784534a44a6831b22566b6|BN20130422|7.7.0.0|",
				"addressLine": "2395 Meadowpine Blvd",
				"adminDistrict": "ON",
				"adminDistrict2": "Peel",
				"countryRegion": "Canada",
				"formattedAddress": "2395 Meadowpine Blvd, Mississauga, ON L5N 7W6, Canada",
				"locality": "Mississauga",
				"postalCode": "L5N 7W6"
			},
			"geometry": {
				"type": "Point",
				"coordinates": [
					-79.77186,
					43.60284
				]
			},
			"bbox": [
				-79.7734124,
				43.6017158,
				-79.7703076,
				43.6039642
			]
		}
	]
}
