{
	"type": "FeatureCollection",
	"features": [
		{
			"type": "Feature",
			"properties": {
				"confidence": 9,
				"authenticationResultCode": "ValidCredentials",
				"brandLogoUri": "http://dev.virtualearth.net/Branding/logo_powered_by.png",
				"copyright": "Copyright © 2017 Microsoft and its suppliers. All rights reserved. This API cannot be accessed and the content and any results may not be used, reproduced or transmitted in any manner without express written permission from Microsoft Corporation.",
				"entityType": "Address",
				"matchCodes": [
					"Good"
				],
				"name": "2396 Rue de la Province, Longueuil, QC J4G 1G1, Canada",
				"statusCode": 200,
				"statusDescription": "OK",
				"traceId": "2d3a46748bfc4390af2f2195cb3b736f|BN20171457|7.7.0.0|",
				"addressLine": "2396 Rue de la Province",
				"adminDistrict": "QC",
				"adminDistrict2": "Longueuil",
				"countryRegion": "Canada",
				"formattedAddress": "2396 Rue de la Province, Longueuil, QC J4G 1G1, Canada",
				"locality": "Longueuil",
				"postalCode": "J4G 1G1"
			},
			"geometry": {
				"type": "Point",
				"coordinates": [
					-73.4626,
					45.57212
				]
			},
			"bbox": [
				-73.4642059,
				45.5709958,
				-73.4609941,
				45.5732442
			]
		}
	]
}
