{
	"type": "FeatureCollection",
	"features": [
		{
			"type": "Feature",
			"properties": {
				"confidence": 9,
				"authenticationResultCode": "ValidCredentials",
				"brandLogoUri": "http://dev.virtualearth.net/Branding/logo_powered_by.png",
				"copyright": "Copyright © 2017 Microsoft and its suppliers. All rights reserved. This API cannot be accessed and the content and any results may not be used, reproduced or transmitted in any manner without express written permission from Microsoft Corporation.",
				"entityType": "Address",
				"matchCodes": [
					"Good"
				],
				"name": "24 Malibou Rd SW, Calgary, AB T2V 1W6, Canada",
				"statusCode": 200,
				"statusDescription": "OK",
				"traceId": "3e62f37c640c49fba977a18c41a12619|BN20130632|7.7.0.0|",
				"addressLine": "24 Malibou Rd SW",
				"adminDistrict": "AB",
				"adminDistrict2": "Alberta",
				"countryRegion": "Canada",
				"formattedAddress": "24 Malibou Rd SW, Calgary, AB T2V 1W6, Canada",
				"locality": "Calgary",
				"neighborhood": "Meadowlark Park",
				"postalCode": "T2V 1W6"
			},
			"geometry": {
				"type": "Point",
				"coordinates": [
					-114.08,
					51.00013
				]
			},
			"bbox": [
				-114.0817863,
				50.9990058,
				-114.0782137,
				51.0012542
			]
		}
	]
}
