{
	"type": "FeatureCollection",
	"features": [
		{
			"type": "Feature",
			"properties": {
				"confidence": 9,
				"authenticationResultCode": "ValidCredentials",
				"brandLogoUri": "http://dev.virtualearth.net/Branding/logo_powered_by.png",
				"copyright": "Copyright © 2017 Microsoft and its suppliers. All rights reserved. This API cannot be accessed and the content and any results may not be used, reproduced or transmitted in any manner without express written permission from Microsoft Corporation.",
				"entityType": "Address",
				"matchCodes": [
					"Good"
				],
				"name": "24 Sisley Ct, Vaughan, ON L4J, Canada",
				"statusCode": 200,
				"statusDescription": "OK",
				"traceId": "209fa23e66bb414498e89283e8c2920d|BN20130634|7.7.0.0|",
				"addressLine": "24 Sisley Ct",
				"adminDistrict": "ON",
				"adminDistrict2": "York",
				"countryRegion": "Canada",
				"formattedAddress": "24 Sisley Ct, Vaughan, ON L4J, Canada",
				"locality": "Vaughan",
				"neighborhood": "Thornhill",
				"postalCode": "L4J 9J1"
			},
			"geometry": {
				"type": "Point",
				"coordinates": [
					-79.47629,
					43.82908
				]
			},
			"bbox": [
				-79.4778483,
				43.8279558,
				-79.4747317,
				43.8302042
			]
		}
	]
}
