{
	"type": "FeatureCollection",
	"features": [
		{
			"type": "Feature",
			"properties": {
				"confidence": 9,
				"authenticationResultCode": "ValidCredentials",
				"brandLogoUri": "http://dev.virtualearth.net/Branding/logo_powered_by.png",
				"copyright": "Copyright © 2017 Microsoft and its suppliers. All rights reserved. This API cannot be accessed and the content and any results may not be used, reproduced or transmitted in any manner without express written permission from Microsoft Corporation.",
				"entityType": "Address",
				"matchCodes": [
					"Good"
				],
				"name": "2400 Dollarton Hwy, North Vancouver, BC V7H 0B3, Canada",
				"statusCode": 200,
				"statusDescription": "OK",
				"traceId": "afe171c4a4ad4c0db13a678306764b97|BN20130632|7.7.0.0|",
				"addressLine": "2400 Dollarton Hwy",
				"adminDistrict": "BC",
				"adminDistrict2": "Greater Vancouver",
				"countryRegion": "Canada",
				"formattedAddress": "2400 Dollarton Hwy, North Vancouver, BC V7H 0B3, Canada",
				"locality": "North Vancouver District",
				"neighborhood": "Maplewood",
				"postalCode": "V7H 0B3"
			},
			"geometry": {
				"type": "Point",
				"coordinates": [
					-123.0075715,
					49.3077017
				]
			},
			"bbox": [
				-123.0092956,
				49.3065775,
				-123.0058473,
				49.3088259
			]
		}
	]
}
