{
	"type": "FeatureCollection",
	"features": [
		{
			"type": "Feature",
			"properties": {
				"confidence": 9,
				"authenticationResultCode": "ValidCredentials",
				"brandLogoUri": "http://dev.virtualearth.net/Branding/logo_powered_by.png",
				"copyright": "Copyright © 2017 Microsoft and its suppliers. All rights reserved. This API cannot be accessed and the content and any results may not be used, reproduced or transmitted in any manner without express written permission from Microsoft Corporation.",
				"entityType": "Address",
				"matchCodes": [
					"Good"
				],
				"name": "2405 Collingwood Rd, West Kelowna, BC V1Z 2C3, Canada",
				"statusCode": 200,
				"statusDescription": "OK",
				"traceId": "0ef732f6bb964f2bb9901f8dadc48fe6|BN20220145|7.7.0.0|",
				"addressLine": "2405 Collingwood Rd",
				"adminDistrict": "BC",
				"adminDistrict2": "Central Okanagan",
				"countryRegion": "Canada",
				"formattedAddress": "2405 Collingwood Rd, West Kelowna, BC V1Z 2C3, Canada",
				"locality": "West Kelowna",
				"postalCode": "V1Z 2C3"
			},
			"geometry": {
				"type": "Point",
				"coordinates": [
					-119.55139,
					49.86807
				]
			},
			"bbox": [
				-119.5531341,
				49.8669458,
				-119.5496459,
				49.8691942
			]
		}
	]
}
