{
	"type": "FeatureCollection",
	"features": [
		{
			"type": "Feature",
			"properties": {
				"confidence": 9,
				"authenticationResultCode": "ValidCredentials",
				"brandLogoUri": "http://dev.virtualearth.net/Branding/logo_powered_by.png",
				"copyright": "Copyright © 2017 Microsoft and its suppliers. All rights reserved. This API cannot be accessed and the content and any results may not be used, reproduced or transmitted in any manner without express written permission from Microsoft Corporation.",
				"entityType": "Address",
				"matchCodes": [
					"Good"
				],
				"name": "241 King Ave, Bathurst, NB E2A 1N9, Canada",
				"statusCode": 200,
				"statusDescription": "OK",
				"traceId": "402ba8dffdd94ab4bb07fb1e72c579fd|BN20121762|7.7.0.0|",
				"addressLine": "241 King Ave",
				"adminDistrict": "NB",
				"adminDistrict2": "Gloucester",
				"countryRegion": "Canada",
				"formattedAddress": "241 King Ave, Bathurst, NB E2A 1N9, Canada",
				"locality": "Bathurst",
				"postalCode": "E2A 1N9"
			},
			"geometry": {
				"type": "Point",
				"coordinates": [
					-65.6533253,
					47.6202081
				]
			},
			"bbox": [
				-65.6549931,
				47.619084,
				-65.6516575,
				47.6213323
			]
		}
	]
}
