{
	"type": "FeatureCollection",
	"features": [
		{
			"type": "Feature",
			"properties": {
				"confidence": 9,
				"authenticationResultCode": "ValidCredentials",
				"brandLogoUri": "http://dev.virtualearth.net/Branding/logo_powered_by.png",
				"copyright": "Copyright © 2017 Microsoft and its suppliers. All rights reserved. This API cannot be accessed and the content and any results may not be used, reproduced or transmitted in any manner without express written permission from Microsoft Corporation.",
				"entityType": "Address",
				"matchCodes": [
					"Good"
				],
				"name": "2410 2 Ave SE, Calgary, AB T2E 6J9, Canada",
				"statusCode": 200,
				"statusDescription": "OK",
				"traceId": "46d5c5be1c53444cb18c37d03f5a851b|BN20200239|7.7.0.0|",
				"addressLine": "2410 2 Ave SE",
				"adminDistrict": "AB",
				"adminDistrict2": "Alberta",
				"countryRegion": "Canada",
				"formattedAddress": "2410 2 Ave SE, Calgary, AB T2E 6J9, Canada",
				"locality": "Calgary",
				"neighborhood": "Mayland Heights",
				"postalCode": "T2E 6J9"
			},
			"geometry": {
				"type": "Point",
				"coordinates": [
					-114.0026393,
					51.0509552
				]
			},
			"bbox": [
				-114.0044275,
				51.0498311,
				-114.000851,
				51.0520794
			]
		}
	]
}
