{
	"type": "FeatureCollection",
	"features": [
		{
			"type": "Feature",
			"properties": {
				"confidence": 9,
				"authenticationResultCode": "ValidCredentials",
				"brandLogoUri": "http://dev.virtualearth.net/Branding/logo_powered_by.png",
				"copyright": "Copyright © 2017 Microsoft and its suppliers. All rights reserved. This API cannot be accessed and the content and any results may not be used, reproduced or transmitted in any manner without express written permission from Microsoft Corporation.",
				"entityType": "Address",
				"matchCodes": [
					"Good"
				],
				"name": "243 Queen St N, Hamilton, ON L8R 3N6, Canada",
				"statusCode": 200,
				"statusDescription": "OK",
				"traceId": "5d0353db29b241b996dff27964400402|BN20130631|7.7.0.0|",
				"addressLine": "243 Queen St N",
				"adminDistrict": "ON",
				"adminDistrict2": "Hamilton",
				"countryRegion": "Canada",
				"formattedAddress": "243 Queen St N, Hamilton, ON L8R 3N6, Canada",
				"locality": "Hamilton",
				"neighborhood": "Strathcona",
				"postalCode": "L8R 3N6"
			},
			"geometry": {
				"type": "Point",
				"coordinates": [
					-79.8758212,
					43.266703
				]
			},
			"bbox": [
				-79.877365,
				43.2655788,
				-79.8742774,
				43.2678271
			]
		}
	]
}
