{
	"type": "FeatureCollection",
	"features": [
		{
			"type": "Feature",
			"properties": {
				"confidence": 9,
				"authenticationResultCode": "ValidCredentials",
				"brandLogoUri": "http://dev.virtualearth.net/Branding/logo_powered_by.png",
				"copyright": "Copyright © 2017 Microsoft and its suppliers. All rights reserved. This API cannot be accessed and the content and any results may not be used, reproduced or transmitted in any manner without express written permission from Microsoft Corporation.",
				"entityType": "Address",
				"matchCodes": [
					"Good"
				],
				"name": "2431 Dominion Rd, West Kelowna, BC V1Z 2Y4, Canada",
				"statusCode": 200,
				"statusDescription": "OK",
				"traceId": "42cee9f6002243c8a47dd7309f883c94|BN20130532|7.7.0.0|",
				"addressLine": "2431 Dominion Rd",
				"adminDistrict": "BC",
				"adminDistrict2": "Central Okanagan",
				"countryRegion": "Canada",
				"formattedAddress": "2431 Dominion Rd, West Kelowna, BC V1Z 2Y4, Canada",
				"locality": "West Kelowna",
				"postalCode": "V1Z 2Y4"
			},
			"geometry": {
				"type": "Point",
				"coordinates": [
					-119.58009,
					49.86744
				]
			},
			"bbox": [
				-119.5818341,
				49.8663158,
				-119.5783459,
				49.8685642
			]
		}
	]
}
