{
	"type": "FeatureCollection",
	"features": [
		{
			"type": "Feature",
			"properties": {
				"confidence": 9,
				"authenticationResultCode": "ValidCredentials",
				"brandLogoUri": "http://dev.virtualearth.net/Branding/logo_powered_by.png",
				"copyright": "Copyright © 2017 Microsoft and its suppliers. All rights reserved. This API cannot be accessed and the content and any results may not be used, reproduced or transmitted in any manner without express written permission from Microsoft Corporation.",
				"entityType": "Address",
				"matchCodes": [
					"Good"
				],
				"name": "2438 Dudley St, Saskatoon, SK S7M 5S9, Canada",
				"statusCode": 200,
				"statusDescription": "OK",
				"traceId": "c8e98e8b1eb14c60be3ebb93d1292fca|BN20181720|7.7.0.0|",
				"addressLine": "2438 Dudley St",
				"adminDistrict": "SK",
				"adminDistrict2": "Saskatchewan",
				"countryRegion": "Canada",
				"formattedAddress": "2438 Dudley St, Saskatoon, SK S7M 5S9, Canada",
				"locality": "Saskatoon",
				"neighborhood": "South West Industrial",
				"postalCode": "S7M 5S9"
			},
			"geometry": {
				"type": "Point",
				"coordinates": [
					-106.71087,
					52.11263
				]
			},
			"bbox": [
				-106.7127005,
				52.1115058,
				-106.7090395,
				52.1137542
			]
		}
	]
}
