{
	"type": "FeatureCollection",
	"features": [
		{
			"type": "Feature",
			"properties": {
				"confidence": 9,
				"authenticationResultCode": "ValidCredentials",
				"brandLogoUri": "http://dev.virtualearth.net/Branding/logo_powered_by.png",
				"copyright": "Copyright © 2017 Microsoft and its suppliers. All rights reserved. This API cannot be accessed and the content and any results may not be used, reproduced or transmitted in any manner without express written permission from Microsoft Corporation.",
				"entityType": "Address",
				"matchCodes": [
					"Good"
				],
				"name": "2441 Agricola St, Halifax, NS B3K 4C1, Canada",
				"statusCode": 200,
				"statusDescription": "OK",
				"traceId": "c4af79bc9acc428780b050c138bf2b2d|BN20130442|7.7.0.0|",
				"addressLine": "2441 Agricola St",
				"adminDistrict": "NS",
				"adminDistrict2": "Halifax",
				"countryRegion": "Canada",
				"formattedAddress": "2441 Agricola St, Halifax, NS B3K 4C1, Canada",
				"locality": "Halifax",
				"neighborhood": "North End",
				"postalCode": "B3K 4C1"
			},
			"geometry": {
				"type": "Point",
				"coordinates": [
					-63.59073,
					44.65353
				]
			},
			"bbox": [
				-63.5923103,
				44.6524058,
				-63.5891497,
				44.6546542
			]
		}
	]
}
