{
	"type": "FeatureCollection",
	"features": [
		{
			"type": "Feature",
			"properties": {
				"confidence": 7,
				"authenticationResultCode": "ValidCredentials",
				"brandLogoUri": "http://dev.virtualearth.net/Branding/logo_powered_by.png",
				"copyright": "Copyright © 2017 Microsoft and its suppliers. All rights reserved. This API cannot be accessed and the content and any results may not be used, reproduced or transmitted in any manner without express written permission from Microsoft Corporation.",
				"entityType": "RoadBlock",
				"matchCodes": [
					"UpHierarchy"
				],
				"name": "Arsenault Rd, Dieppe, NB E1H, Canada",
				"statusCode": 200,
				"statusDescription": "OK",
				"traceId": "d4a38d4cc02e450d9f3f06a056d8108c|BN20130631|7.7.0.0|",
				"addressLine": "Arsenault Rd",
				"adminDistrict": "NB",
				"adminDistrict2": "Westmorland",
				"countryRegion": "Canada",
				"formattedAddress": "Arsenault Rd, Dieppe, NB E1H, Canada",
				"locality": "Dieppe",
				"postalCode": "E1H"
			},
			"geometry": {
				"type": "Point",
				"coordinates": [
					-64.63804,
					46.11341
				]
			},
			"bbox": [
				-64.6413199,
				46.10544,
				-64.63741,
				46.12362
			]
		}
	]
}
