{
	"type": "FeatureCollection",
	"features": [
		{
			"type": "Feature",
			"properties": {
				"confidence": 9,
				"authenticationResultCode": "ValidCredentials",
				"brandLogoUri": "http://dev.virtualearth.net/Branding/logo_powered_by.png",
				"copyright": "Copyright © 2017 Microsoft and its suppliers. All rights reserved. This API cannot be accessed and the content and any results may not be used, reproduced or transmitted in any manner without express written permission from Microsoft Corporation.",
				"entityType": "Address",
				"matchCodes": [
					"Good"
				],
				"name": "248 Water St, Selwyn, ON K0L, Canada",
				"statusCode": 200,
				"statusDescription": "OK",
				"traceId": "5aec7f62ce0e479086b5016f63c675ec|BN20190642|7.7.0.0|",
				"addressLine": "248 Water St",
				"adminDistrict": "ON",
				"adminDistrict2": "Peterborough",
				"countryRegion": "Canada",
				"formattedAddress": "248 Water St, Selwyn, ON K0L, Canada",
				"locality": "Selwyn",
				"neighborhood": "Lakefield",
				"postalCode": "K0L 2H0"
			},
			"geometry": {
				"type": "Point",
				"coordinates": [
					-78.2657217,
					44.4175634
				]
			},
			"bbox": [
				-78.2672956,
				44.4164392,
				-78.2641478,
				44.4186876
			]
		}
	]
}
