{
	"type": "FeatureCollection",
	"features": [
		{
			"type": "Feature",
			"properties": {
				"confidence": 9,
				"authenticationResultCode": "ValidCredentials",
				"brandLogoUri": "http://dev.virtualearth.net/Branding/logo_powered_by.png",
				"copyright": "Copyright © 2017 Microsoft and its suppliers. All rights reserved. This API cannot be accessed and the content and any results may not be used, reproduced or transmitted in any manner without express written permission from Microsoft Corporation.",
				"entityType": "Address",
				"matchCodes": [
					"Good"
				],
				"name": "2480 Lancaster Rd, Ottawa, ON K1B 4S5, Canada",
				"statusCode": 200,
				"statusDescription": "OK",
				"traceId": "d031c3663eca4b2d88c8aeeba60b9ff0|BN20121763|7.7.0.0|",
				"addressLine": "2480 Lancaster Rd",
				"adminDistrict": "ON",
				"adminDistrict2": "Ottawa",
				"countryRegion": "Canada",
				"formattedAddress": "2480 Lancaster Rd, Ottawa, ON K1B 4S5, Canada",
				"locality": "Ottawa",
				"neighborhood": "Hawthorne Meadows-Sheffield Glen",
				"postalCode": "K1B 4S5"
			},
			"geometry": {
				"type": "Point",
				"coordinates": [
					-75.61681,
					45.40179
				]
			},
			"bbox": [
				-75.6184111,
				45.4006658,
				-75.6152089,
				45.4029142
			]
		}
	]
}
