{
	"type": "FeatureCollection",
	"features": [
		{
			"type": "Feature",
			"properties": {
				"confidence": 9,
				"authenticationResultCode": "ValidCredentials",
				"brandLogoUri": "http://dev.virtualearth.net/Branding/logo_powered_by.png",
				"copyright": "Copyright © 2017 Microsoft and its suppliers. All rights reserved. This API cannot be accessed and the content and any results may not be used, reproduced or transmitted in any manner without express written permission from Microsoft Corporation.",
				"entityType": "Address",
				"matchCodes": [
					"Good"
				],
				"name": "2497 Cousins Ave, Courtenay, BC V9N 3N6, Canada",
				"statusCode": 200,
				"statusDescription": "OK",
				"traceId": "1006567a47f6443684379b81295bbc53|CO30324010|7.7.0.0|",
				"addressLine": "2497 Cousins Ave",
				"adminDistrict": "BC",
				"adminDistrict2": "Comox Valley",
				"countryRegion": "Canada",
				"formattedAddress": "2497 Cousins Ave, Courtenay, BC V9N 3N6, Canada",
				"locality": "Courtenay",
				"postalCode": "V9N 3N6"
			},
			"geometry": {
				"type": "Point",
				"coordinates": [
					-124.99555,
					49.66939
				]
			},
			"bbox": [
				-124.997287,
				49.6682658,
				-124.993813,
				49.6705142
			]
		}
	]
}
