{
	"type": "FeatureCollection",
	"features": [
		{
			"type": "Feature",
			"properties": {
				"confidence": 9,
				"authenticationResultCode": "ValidCredentials",
				"brandLogoUri": "http://dev.virtualearth.net/Branding/logo_powered_by.png",
				"copyright": "Copyright © 2017 Microsoft and its suppliers. All rights reserved. This API cannot be accessed and the content and any results may not be used, reproduced or transmitted in any manner without express written permission from Microsoft Corporation.",
				"entityType": "Address",
				"matchCodes": [
					"Good"
				],
				"name": "2499 HWY-3, Lower East Pubnico, NS B0W 2A0, Canada",
				"statusCode": 200,
				"statusDescription": "OK",
				"traceId": "1703a5345752441da4456271d68fcbf5|BN20260223|7.7.0.0|",
				"addressLine": "2499 HWY-3",
				"adminDistrict": "NS",
				"adminDistrict2": "Yarmouth",
				"countryRegion": "Canada",
				"formattedAddress": "2499 HWY-3, Lower East Pubnico, NS B0W 2A0, Canada",
				"locality": "Argyle",
				"neighborhood": "Lower East Pubnico",
				"postalCode": "B0W 2A0"
			},
			"geometry": {
				"type": "Point",
				"coordinates": [
					-65.7742669,
					43.7041195
				]
			},
			"bbox": [
				-65.7758219,
				43.7029953,
				-65.7727119,
				43.7052436
			]
		}
	]
}
