{
	"type": "FeatureCollection",
	"features": [
		{
			"type": "Feature",
			"properties": {
				"confidence": 7,
				"authenticationResultCode": "ValidCredentials",
				"brandLogoUri": "http://dev.virtualearth.net/Branding/logo_powered_by.png",
				"copyright": "Copyright © 2017 Microsoft and its suppliers. All rights reserved. This API cannot be accessed and the content and any results may not be used, reproduced or transmitted in any manner without express written permission from Microsoft Corporation.",
				"entityType": "Postcode1",
				"matchCodes": [
					"UpHierarchy"
				],
				"name": "North Bay, P1B 8G5, Canada",
				"statusCode": 200,
				"statusDescription": "OK",
				"traceId": "c8b38036449f4320bbd832d3f1f8fa66|BN20130521|7.7.0.0|",
				"adminDistrict": "ON",
				"adminDistrict2": "Nipissing",
				"countryRegion": "Canada",
				"formattedAddress": "North Bay, P1B 8G5, Canada",
				"locality": "North Bay",
				"postalCode": "P1B 8G5"
			},
			"geometry": {
				"type": "Point",
				"coordinates": [
					-79.4925231933594,
					46.3258857727051
				]
			},
			"bbox": [
				-79.4999808486903,
				46.3220230551344,
				-79.4850655380284,
				46.3297484902758
			]
		}
	]
}
