{
	"type": "FeatureCollection",
	"features": [
		{
			"type": "Feature",
			"properties": {
				"confidence": 9,
				"authenticationResultCode": "ValidCredentials",
				"brandLogoUri": "http://dev.virtualearth.net/Branding/logo_powered_by.png",
				"copyright": "Copyright © 2017 Microsoft and its suppliers. All rights reserved. This API cannot be accessed and the content and any results may not be used, reproduced or transmitted in any manner without express written permission from Microsoft Corporation.",
				"entityType": "Address",
				"matchCodes": [
					"Good"
				],
				"name": "25 Bongard Ave, Nepean, ON K2E 6V2, Canada",
				"statusCode": 200,
				"statusDescription": "OK",
				"traceId": "b493ad46ad154318ac3a1c588e1dd3ec|BN20240423|7.7.0.0|",
				"addressLine": "25 Bongard Ave",
				"adminDistrict": "ON",
				"adminDistrict2": "Ottawa",
				"countryRegion": "Canada",
				"formattedAddress": "25 Bongard Ave, Nepean, ON K2E 6V2, Canada",
				"locality": "Ottawa",
				"neighborhood": "Nepean",
				"postalCode": "K2E 6V2"
			},
			"geometry": {
				"type": "Point",
				"coordinates": [
					-75.71812,
					45.3312
				]
			},
			"bbox": [
				-75.7197191,
				45.3300758,
				-75.7165209,
				45.3323242
			]
		}
	]
}
