{
	"type": "FeatureCollection",
	"features": [
		{
			"type": "Feature",
			"properties": {
				"confidence": 9,
				"authenticationResultCode": "ValidCredentials",
				"brandLogoUri": "http://dev.virtualearth.net/Branding/logo_powered_by.png",
				"copyright": "Copyright © 2017 Microsoft and its suppliers. All rights reserved. This API cannot be accessed and the content and any results may not be used, reproduced or transmitted in any manner without express written permission from Microsoft Corporation.",
				"entityType": "Address",
				"matchCodes": [
					"Good"
				],
				"name": "25 Erb St, Elmira, ON N3B, Canada",
				"statusCode": 200,
				"statusDescription": "OK",
				"traceId": "925512bd2c854586a3e9e0927a3de076|BN20210145|7.7.0.0|",
				"addressLine": "25 Erb St",
				"adminDistrict": "ON",
				"adminDistrict2": "Waterloo",
				"countryRegion": "Canada",
				"formattedAddress": "25 Erb St, Elmira, ON N3B, Canada",
				"locality": "Woolwich",
				"neighborhood": "Elmira",
				"postalCode": "N3B 3A3"
			},
			"geometry": {
				"type": "Point",
				"coordinates": [
					-80.552726,
					43.5966451
				]
			},
			"bbox": [
				-80.5542782,
				43.5955209,
				-80.5511738,
				43.5977693
			]
		}
	]
}
