{
	"type": "FeatureCollection",
	"features": [
		{
			"type": "Feature",
			"properties": {
				"confidence": 9,
				"authenticationResultCode": "ValidCredentials",
				"brandLogoUri": "http://dev.virtualearth.net/Branding/logo_powered_by.png",
				"copyright": "Copyright © 2017 Microsoft and its suppliers. All rights reserved. This API cannot be accessed and the content and any results may not be used, reproduced or transmitted in any manner without express written permission from Microsoft Corporation.",
				"entityType": "Address",
				"matchCodes": [
					"Good"
				],
				"name": "25 Promenade Youghall, Bathurst, NB E2A 4X5, Canada",
				"statusCode": 200,
				"statusDescription": "OK",
				"traceId": "cbd7bfc42fbb4d0a98f6f4bacf050d18|BN20260231|7.7.0.0|",
				"addressLine": "25 Promenade Youghall",
				"adminDistrict": "NB",
				"adminDistrict2": "Gloucester",
				"countryRegion": "Canada",
				"formattedAddress": "25 Promenade Youghall, Bathurst, NB E2A 4X5, Canada",
				"locality": "Bathurst",
				"postalCode": "E2A 4X5"
			},
			"geometry": {
				"type": "Point",
				"coordinates": [
					-65.6771105,
					47.6504076
				]
			},
			"bbox": [
				-65.6787792,
				47.6492835,
				-65.6754418,
				47.6515318
			]
		}
	]
}
