{
	"type": "FeatureCollection",
	"features": [
		{
			"type": "Feature",
			"properties": {
				"confidence": 9,
				"authenticationResultCode": "ValidCredentials",
				"brandLogoUri": "http://dev.virtualearth.net/Branding/logo_powered_by.png",
				"copyright": "Copyright © 2017 Microsoft and its suppliers. All rights reserved. This API cannot be accessed and the content and any results may not be used, reproduced or transmitted in any manner without express written permission from Microsoft Corporation.",
				"entityType": "Address",
				"matchCodes": [
					"Good"
				],
				"name": "25 Rue Angers, Victoriaville, QC G6T 0B1, Canada",
				"statusCode": 200,
				"statusDescription": "OK",
				"traceId": "35f5c5240bdf4e778c2e7b521bad50d5|BN20160335|7.7.0.0|",
				"addressLine": "25 Rue Angers",
				"adminDistrict": "QC",
				"adminDistrict2": "Arthabaska County",
				"countryRegion": "Canada",
				"formattedAddress": "25 Rue Angers, Victoriaville, QC G6T 0B1, Canada",
				"locality": "Victoriaville",
				"postalCode": "G6T 0B1"
			},
			"geometry": {
				"type": "Point",
				"coordinates": [
					-71.9808,
					46.08969
				]
			},
			"bbox": [
				-71.9824209,
				46.0885658,
				-71.9791791,
				46.0908142
			]
		}
	]
}
