{
	"type": "FeatureCollection",
	"features": [
		{
			"type": "Feature",
			"properties": {
				"confidence": 9,
				"authenticationResultCode": "ValidCredentials",
				"brandLogoUri": "http://dev.virtualearth.net/Branding/logo_powered_by.png",
				"copyright": "Copyright © 2017 Microsoft and its suppliers. All rights reserved. This API cannot be accessed and the content and any results may not be used, reproduced or transmitted in any manner without express written permission from Microsoft Corporation.",
				"entityType": "Address",
				"matchCodes": [
					"Good"
				],
				"name": "250 Main St, Antigonish, NS B2G 2C2, Canada",
				"statusCode": 200,
				"statusDescription": "OK",
				"traceId": "8f62ada1173b4a07a0022e09556bb26c|BN20130422|7.7.0.0|",
				"addressLine": "250 Main St",
				"adminDistrict": "NS",
				"adminDistrict2": "Antigonish",
				"countryRegion": "Canada",
				"formattedAddress": "250 Main St, Antigonish, NS B2G 2C2, Canada",
				"locality": "Antigonish",
				"postalCode": "B2G 2C2"
			},
			"geometry": {
				"type": "Point",
				"coordinates": [
					-61.99069,
					45.62266
				]
			},
			"bbox": [
				-61.9922974,
				45.6215358,
				-61.9890826,
				45.6237842
			]
		}
	]
}
