{
	"type": "FeatureCollection",
	"features": [
		{
			"type": "Feature",
			"properties": {
				"confidence": 9,
				"authenticationResultCode": "ValidCredentials",
				"brandLogoUri": "http://dev.virtualearth.net/Branding/logo_powered_by.png",
				"copyright": "Copyright © 2017 Microsoft and its suppliers. All rights reserved. This API cannot be accessed and the content and any results may not be used, reproduced or transmitted in any manner without express written permission from Microsoft Corporation.",
				"entityType": "Address",
				"matchCodes": [
					"Good"
				],
				"name": "250 City Centre Ave, Ottawa, ON K1R 6K7, Canada",
				"statusCode": 200,
				"statusDescription": "OK",
				"traceId": "309ebb246ba247bf9520975f2930556d|BN20210145|7.7.0.0|",
				"addressLine": "250 City Centre Ave",
				"adminDistrict": "ON",
				"adminDistrict2": "Ottawa",
				"countryRegion": "Canada",
				"formattedAddress": "250 City Centre Ave, Ottawa, ON K1R 6K7, Canada",
				"locality": "Ottawa",
				"neighborhood": "West Centre Town-Little Italy-Civic",
				"postalCode": "K1R 6K7"
			},
			"geometry": {
				"type": "Point",
				"coordinates": [
					-75.71847,
					45.40853
				]
			},
			"bbox": [
				-75.7200712,
				45.4074058,
				-75.7168688,
				45.4096542
			]
		}
	]
}
