{
	"type": "FeatureCollection",
	"features": [
		{
			"type": "Feature",
			"properties": {
				"confidence": 9,
				"authenticationResultCode": "ValidCredentials",
				"brandLogoUri": "http://dev.virtualearth.net/Branding/logo_powered_by.png",
				"copyright": "Copyright © 2017 Microsoft and its suppliers. All rights reserved. This API cannot be accessed and the content and any results may not be used, reproduced or transmitted in any manner without express written permission from Microsoft Corporation.",
				"entityType": "Address",
				"matchCodes": [
					"Good"
				],
				"name": "251 Racco Pkwy, Thornhill, ON L4J 8X9, Canada",
				"statusCode": 200,
				"statusDescription": "OK",
				"traceId": "c3b6095d49be4c6982f690e313bf1754|BN20130632|7.7.0.0|",
				"addressLine": "251 Racco Pkwy",
				"adminDistrict": "ON",
				"adminDistrict2": "York",
				"countryRegion": "Canada",
				"formattedAddress": "251 Racco Pkwy, Thornhill, ON L4J 8X9, Canada",
				"locality": "Vaughan",
				"neighborhood": "Thornhill",
				"postalCode": "L4J 8X9"
			},
			"geometry": {
				"type": "Point",
				"coordinates": [
					-79.4706099,
					43.81824
				]
			},
			"bbox": [
				-79.4721679,
				43.8171158,
				-79.4690519,
				43.8193642
			]
		}
	]
}
