{
	"type": "FeatureCollection",
	"features": [
		{
			"type": "Feature",
			"properties": {
				"confidence": 9,
				"authenticationResultCode": "ValidCredentials",
				"brandLogoUri": "http://dev.virtualearth.net/Branding/logo_powered_by.png",
				"copyright": "Copyright © 2017 Microsoft and its suppliers. All rights reserved. This API cannot be accessed and the content and any results may not be used, reproduced or transmitted in any manner without express written permission from Microsoft Corporation.",
				"entityType": "Address",
				"matchCodes": [
					"Good"
				],
				"name": "2521 Juliann Rd, West Kelowna, BC V1Z 2M3, Canada",
				"statusCode": 200,
				"statusDescription": "OK",
				"traceId": "557f0675b82c4a9592f4e01d24d77e44|BN20130521|7.7.0.0|",
				"addressLine": "2521 Juliann Rd",
				"adminDistrict": "BC",
				"adminDistrict2": "Central Okanagan",
				"countryRegion": "Canada",
				"formattedAddress": "2521 Juliann Rd, West Kelowna, BC V1Z 2M3, Canada",
				"locality": "West Kelowna",
				"postalCode": "V1Z 2M3"
			},
			"geometry": {
				"type": "Point",
				"coordinates": [
					-119.57868,
					49.86511
				]
			},
			"bbox": [
				-119.580424,
				49.8639858,
				-119.576936,
				49.8662342
			]
		}
	]
}
