{
	"type": "FeatureCollection",
	"features": [
		{
			"type": "Feature",
			"properties": {
				"confidence": 9,
				"authenticationResultCode": "ValidCredentials",
				"brandLogoUri": "http://dev.virtualearth.net/Branding/logo_powered_by.png",
				"copyright": "Copyright © 2017 Microsoft and its suppliers. All rights reserved. This API cannot be accessed and the content and any results may not be used, reproduced or transmitted in any manner without express written permission from Microsoft Corporation.",
				"entityType": "Address",
				"matchCodes": [
					"Good"
				],
				"name": "2540 5 Ave NW, Calgary, AB T2N 0T5, Canada",
				"statusCode": 200,
				"statusDescription": "OK",
				"traceId": "4a149a1a0019492992d1436d544baa86|BN20130422|7.7.0.0|",
				"addressLine": "2540 5 Ave NW",
				"adminDistrict": "AB",
				"adminDistrict2": "Alberta",
				"countryRegion": "Canada",
				"formattedAddress": "2540 5 Ave NW, Calgary, AB T2N 0T5, Canada",
				"locality": "Calgary",
				"neighborhood": "West Hillhurst",
				"postalCode": "T2N 0T5"
			},
			"geometry": {
				"type": "Point",
				"coordinates": [
					-114.11981,
					51.05712
				]
			},
			"bbox": [
				-114.1215985,
				51.0559958,
				-114.1180215,
				51.0582442
			]
		}
	]
}
