{
	"type": "FeatureCollection",
	"features": [
		{
			"type": "Feature",
			"properties": {
				"confidence": 9,
				"authenticationResultCode": "ValidCredentials",
				"brandLogoUri": "http://dev.virtualearth.net/Branding/logo_powered_by.png",
				"copyright": "Copyright © 2017 Microsoft and its suppliers. All rights reserved. This API cannot be accessed and the content and any results may not be used, reproduced or transmitted in any manner without express written permission from Microsoft Corporation.",
				"entityType": "Address",
				"matchCodes": [
					"Good"
				],
				"name": "2552 Bristol Cir, Oakville, ON L6H 5S1, Canada",
				"statusCode": 200,
				"statusDescription": "OK",
				"traceId": "021642bc39b642efbcfcd0b563e89b9d|BN20130625|7.7.0.0|",
				"addressLine": "2552 Bristol Cir",
				"adminDistrict": "ON",
				"adminDistrict2": "Halton",
				"countryRegion": "Canada",
				"formattedAddress": "2552 Bristol Cir, Oakville, ON L6H 5S1, Canada",
				"locality": "Oakville",
				"postalCode": "L6H 5S1"
			},
			"geometry": {
				"type": "Point",
				"coordinates": [
					-79.68331,
					43.51766
				]
			},
			"bbox": [
				-79.6848602,
				43.5165358,
				-79.6817598,
				43.5187842
			]
		}
	]
}
