{
	"type": "FeatureCollection",
	"features": [
		{
			"type": "Feature",
			"properties": {
				"confidence": 9,
				"authenticationResultCode": "ValidCredentials",
				"brandLogoUri": "http://dev.virtualearth.net/Branding/logo_powered_by.png",
				"copyright": "Copyright © 2017 Microsoft and its suppliers. All rights reserved. This API cannot be accessed and the content and any results may not be used, reproduced or transmitted in any manner without express written permission from Microsoft Corporation.",
				"entityType": "Address",
				"matchCodes": [
					"Good"
				],
				"name": "2568 Bristol Cir, Oakville, ON L6H 5S1, Canada",
				"statusCode": 200,
				"statusDescription": "OK",
				"traceId": "e46972bd40e947dea3898cf53dc8a0bd|BN20130442|7.7.0.0|",
				"addressLine": "2568 Bristol Cir",
				"adminDistrict": "ON",
				"adminDistrict2": "Halton",
				"countryRegion": "Canada",
				"formattedAddress": "2568 Bristol Cir, Oakville, ON L6H 5S1, Canada",
				"locality": "Oakville",
				"postalCode": "L6H 5S1"
			},
			"geometry": {
				"type": "Point",
				"coordinates": [
					-79.68375,
					43.51726
				]
			},
			"bbox": [
				-79.6853002,
				43.5161358,
				-79.6821998,
				43.5183842
			]
		}
	]
}
