{
	"type": "FeatureCollection",
	"features": [
		{
			"type": "Feature",
			"properties": {
				"confidence": 7,
				"authenticationResultCode": "ValidCredentials",
				"brandLogoUri": "http://dev.virtualearth.net/Branding/logo_powered_by.png",
				"copyright": "Copyright © 2017 Microsoft and its suppliers. All rights reserved. This API cannot be accessed and the content and any results may not be used, reproduced or transmitted in any manner without express written permission from Microsoft Corporation.",
				"entityType": "Postcode1",
				"matchCodes": [
					"UpHierarchy"
				],
				"name": "New Glasgow, B2H 2S9, Canada",
				"statusCode": 200,
				"statusDescription": "OK",
				"traceId": "e70667c7bf834909a8628945e8f4a710|BN20300154|7.7.0.0|",
				"adminDistrict": "NS",
				"adminDistrict2": "Pictou",
				"countryRegion": "Canada",
				"formattedAddress": "New Glasgow, B2H 2S9, Canada",
				"locality": "New Glasgow",
				"postalCode": "B2H 2S9"
			},
			"geometry": {
				"type": "Point",
				"coordinates": [
					-62.641242980957,
					45.5937728881836
				]
			},
			"bbox": [
				-62.6486027551305,
				45.5899101706129,
				-62.6338832067835,
				45.5976356057543
			]
		}
	]
}
