{
	"type": "FeatureCollection",
	"features": [
		{
			"type": "Feature",
			"properties": {
				"confidence": 9,
				"authenticationResultCode": "ValidCredentials",
				"brandLogoUri": "http://dev.virtualearth.net/Branding/logo_powered_by.png",
				"copyright": "Copyright © 2017 Microsoft and its suppliers. All rights reserved. This API cannot be accessed and the content and any results may not be used, reproduced or transmitted in any manner without express written permission from Microsoft Corporation.",
				"entityType": "Address",
				"matchCodes": [
					"Good"
				],
				"name": "2580 Robinson Rd, Lake Country, BC V4V 1G4, Canada",
				"statusCode": 200,
				"statusDescription": "OK",
				"traceId": "a4679f0470314e0893e3eedc1f551282|BN20130634|7.7.0.0|",
				"addressLine": "2580 Robinson Rd",
				"adminDistrict": "BC",
				"adminDistrict2": "Central Okanagan",
				"countryRegion": "Canada",
				"formattedAddress": "2580 Robinson Rd, Lake Country, BC V4V 1G4, Canada",
				"locality": "Lake Country",
				"postalCode": "V4V 1G4"
			},
			"geometry": {
				"type": "Point",
				"coordinates": [
					-119.4178708,
					50.0496749
				]
			},
			"bbox": [
				-119.4196215,
				50.0485507,
				-119.4161201,
				50.050799
			]
		}
	]
}
