{
	"type": "FeatureCollection",
	"features": [
		{
			"type": "Feature",
			"properties": {
				"confidence": 9,
				"authenticationResultCode": "ValidCredentials",
				"brandLogoUri": "http://dev.virtualearth.net/Branding/logo_powered_by.png",
				"copyright": "Copyright © 2017 Microsoft and its suppliers. All rights reserved. This API cannot be accessed and the content and any results may not be used, reproduced or transmitted in any manner without express written permission from Microsoft Corporation.",
				"entityType": "Address",
				"matchCodes": [
					"Good"
				],
				"name": "2585 Meadowpine Blvd, Mississauga, ON L5N 8H9, Canada",
				"statusCode": 200,
				"statusDescription": "OK",
				"traceId": "d013a7c6c5f94446b4c3839bf08749f5|BN20130621|7.7.0.0|",
				"addressLine": "2585 Meadowpine Blvd",
				"adminDistrict": "ON",
				"adminDistrict2": "Peel",
				"countryRegion": "Canada",
				"formattedAddress": "2585 Meadowpine Blvd, Mississauga, ON L5N 8H9, Canada",
				"locality": "Mississauga",
				"postalCode": "L5N 8H9"
			},
			"geometry": {
				"type": "Point",
				"coordinates": [
					-79.77934,
					43.60229
				]
			},
			"bbox": [
				-79.7808924,
				43.6011658,
				-79.7777876,
				43.6034142
			]
		}
	]
}
