{
	"type": "FeatureCollection",
	"features": [
		{
			"type": "Feature",
			"properties": {
				"confidence": 9,
				"authenticationResultCode": "ValidCredentials",
				"brandLogoUri": "http://dev.virtualearth.net/Branding/logo_powered_by.png",
				"copyright": "Copyright © 2017 Microsoft and its suppliers. All rights reserved. This API cannot be accessed and the content and any results may not be used, reproduced or transmitted in any manner without express written permission from Microsoft Corporation.",
				"entityType": "Address",
				"matchCodes": [
					"Good"
				],
				"name": "2595 N Island Hwy, Campbell River, BC V9W 2H2, Canada",
				"statusCode": 200,
				"statusDescription": "OK",
				"traceId": "5fbdde97532b4a9eb7ec73b63e6e8096|BN20130520|7.7.0.0|",
				"addressLine": "2595 N Island Hwy",
				"adminDistrict": "BC",
				"adminDistrict2": "Strathcona",
				"countryRegion": "Canada",
				"formattedAddress": "2595 N Island Hwy, Campbell River, BC V9W 2H2, Canada",
				"locality": "Campbell River",
				"postalCode": "V9W 2H2"
			},
			"geometry": {
				"type": "Point",
				"coordinates": [
					-125.26873,
					50.04167
				]
			},
			"bbox": [
				-125.2704804,
				50.0405458,
				-125.2669796,
				50.0427942
			]
		}
	]
}
