{
	"type": "FeatureCollection",
	"features": [
		{
			"type": "Feature",
			"properties": {
				"confidence": 9,
				"authenticationResultCode": "ValidCredentials",
				"brandLogoUri": "http://dev.virtualearth.net/Branding/logo_powered_by.png",
				"copyright": "Copyright © 2017 Microsoft and its suppliers. All rights reserved. This API cannot be accessed and the content and any results may not be used, reproduced or transmitted in any manner without express written permission from Microsoft Corporation.",
				"entityType": "Address",
				"matchCodes": [
					"Good"
				],
				"name": "26 Drysdale St, Kanata, ON K2K 3L3, Canada",
				"statusCode": 200,
				"statusDescription": "OK",
				"traceId": "0d1a4e76c72b4d399483eb2bb5ef5da6|BN20130625|7.7.0.0|",
				"addressLine": "26 Drysdale St",
				"adminDistrict": "ON",
				"adminDistrict2": "Ottawa",
				"countryRegion": "Canada",
				"formattedAddress": "26 Drysdale St, Kanata, ON K2K 3L3, Canada",
				"locality": "Ottawa",
				"neighborhood": "Kanata",
				"postalCode": "K2K 3L3"
			},
			"geometry": {
				"type": "Point",
				"coordinates": [
					-75.89693,
					45.3167199
				]
			},
			"bbox": [
				-75.8985287,
				45.3155957,
				-75.8953313,
				45.3178441
			]
		}
	]
}
