{
	"type": "FeatureCollection",
	"features": [
		{
			"type": "Feature",
			"properties": {
				"confidence": 9,
				"authenticationResultCode": "ValidCredentials",
				"brandLogoUri": "http://dev.virtualearth.net/Branding/logo_powered_by.png",
				"copyright": "Copyright © 2017 Microsoft and its suppliers. All rights reserved. This API cannot be accessed and the content and any results may not be used, reproduced or transmitted in any manner without express written permission from Microsoft Corporation.",
				"entityType": "Address",
				"matchCodes": [
					"Good"
				],
				"name": "26 Prince Andrew Pl, North York, ON M3C 2H4, Canada",
				"statusCode": 200,
				"statusDescription": "OK",
				"traceId": "53b713e379ac45e1b077a3aaa9862b7c|BN20130522|7.7.0.0|",
				"addressLine": "26 Prince Andrew Pl",
				"adminDistrict": "ON",
				"adminDistrict2": "Toronto",
				"countryRegion": "Canada",
				"formattedAddress": "26 Prince Andrew Pl, North York, ON M3C 2H4, Canada",
				"locality": "Toronto",
				"neighborhood": "Banbury-Don Mills",
				"postalCode": "M3C 2H4"
			},
			"geometry": {
				"type": "Point",
				"coordinates": [
					-79.34563,
					43.72511
				]
			},
			"bbox": [
				-79.3471856,
				43.7239858,
				-79.3440744,
				43.7262342
			]
		}
	]
}
