{
	"type": "FeatureCollection",
	"features": [
		{
			"type": "Feature",
			"properties": {
				"confidence": 9,
				"authenticationResultCode": "ValidCredentials",
				"brandLogoUri": "http://dev.virtualearth.net/Branding/logo_powered_by.png",
				"copyright": "Copyright © 2017 Microsoft and its suppliers. All rights reserved. This API cannot be accessed and the content and any results may not be used, reproduced or transmitted in any manner without express written permission from Microsoft Corporation.",
				"entityType": "Address",
				"matchCodes": [
					"Good"
				],
				"name": "261051 Bearspaw Rd, Rocky View County, AB T3R 1H6, Canada",
				"statusCode": 200,
				"statusDescription": "OK",
				"traceId": "c23002ce95034b55bc8d4f3caac92b74|BN20130447|7.7.0.0|",
				"addressLine": "261051 Bearspaw Rd",
				"adminDistrict": "AB",
				"adminDistrict2": "Alberta",
				"countryRegion": "Canada",
				"formattedAddress": "261051 Bearspaw Rd, Rocky View County, AB T3R 1H6, Canada",
				"locality": "Rocky View County",
				"postalCode": "T3R 1H6"
			},
			"geometry": {
				"type": "Point",
				"coordinates": [
					-114.2808349,
					51.2102066
				]
			},
			"bbox": [
				-114.2826293,
				51.2090825,
				-114.2790405,
				51.2113308
			]
		}
	]
}
