{
	"type": "FeatureCollection",
	"features": [
		{
			"type": "Feature",
			"properties": {
				"confidence": 9,
				"authenticationResultCode": "ValidCredentials",
				"brandLogoUri": "http://dev.virtualearth.net/Branding/logo_powered_by.png",
				"copyright": "Copyright © 2017 Microsoft and its suppliers. All rights reserved. This API cannot be accessed and the content and any results may not be used, reproduced or transmitted in any manner without express written permission from Microsoft Corporation.",
				"entityType": "Address",
				"matchCodes": [
					"Good"
				],
				"name": "26322 Township Road 514, Spruce Grove, AB T7Y 1C8, Canada",
				"statusCode": 200,
				"statusDescription": "OK",
				"traceId": "5db8fca20ade46d38b88a2b310f53620|BN20130621|7.7.0.0|",
				"addressLine": "26322 Township Road 514",
				"adminDistrict": "AB",
				"adminDistrict2": "Alberta",
				"countryRegion": "Canada",
				"formattedAddress": "26322 Township Road 514, Spruce Grove, AB T7Y 1C8, Canada",
				"locality": "Parkland County",
				"neighborhood": "Spruce Grove",
				"postalCode": "T7Y 1C8"
			},
			"geometry": {
				"type": "Point",
				"coordinates": [
					-113.7803963,
					53.4253002
				]
			},
			"bbox": [
				-113.7822829,
				53.424176,
				-113.7785098,
				53.4264243
			]
		}
	]
}
