{
	"type": "FeatureCollection",
	"features": [
		{
			"type": "Feature",
			"properties": {
				"confidence": 9,
				"authenticationResultCode": "ValidCredentials",
				"brandLogoUri": "http://dev.virtualearth.net/Branding/logo_powered_by.png",
				"copyright": "Copyright © 2017 Microsoft and its suppliers. All rights reserved. This API cannot be accessed and the content and any results may not be used, reproduced or transmitted in any manner without express written permission from Microsoft Corporation.",
				"entityType": "Address",
				"matchCodes": [
					"Good"
				],
				"name": "2648 Burrard Ave, Vanderhoof, BC V0J, Canada",
				"statusCode": 200,
				"statusDescription": "OK",
				"traceId": "06feee15533f4448928877d70c311f43|BN20210145|7.7.0.0|",
				"addressLine": "2648 Burrard Ave",
				"adminDistrict": "BC",
				"adminDistrict2": "Bulkley-Nechako",
				"countryRegion": "Canada",
				"formattedAddress": "2648 Burrard Ave, Vanderhoof, BC V0J, Canada",
				"locality": "Vanderhoof",
				"postalCode": "V0J 3A0"
			},
			"geometry": {
				"type": "Point",
				"coordinates": [
					-124.0089851,
					54.018267
				]
			},
			"bbox": [
				-124.0108985,
				54.0171429,
				-124.0070717,
				54.0193912
			]
		}
	]
}
