{
	"type": "FeatureCollection",
	"features": [
		{
			"type": "Feature",
			"properties": {
				"confidence": 9,
				"authenticationResultCode": "ValidCredentials",
				"brandLogoUri": "http://dev.virtualearth.net/Branding/logo_powered_by.png",
				"copyright": "Copyright © 2017 Microsoft and its suppliers. All rights reserved. This API cannot be accessed and the content and any results may not be used, reproduced or transmitted in any manner without express written permission from Microsoft Corporation.",
				"entityType": "Address",
				"matchCodes": [
					"Good"
				],
				"name": "265 Conception Bay Hwy, Bay Roberts, NL A0A 3S0, Canada",
				"statusCode": 200,
				"statusDescription": "OK",
				"traceId": "7fac3b2487424003aa3d3176cc591a0f|BN20171457|7.7.0.0|",
				"addressLine": "265 Conception Bay Hwy",
				"adminDistrict": "NL",
				"adminDistrict2": "Newfoundland and Labrador",
				"countryRegion": "Canada",
				"formattedAddress": "265 Conception Bay Hwy, Bay Roberts, NL A0A 3S0, Canada",
				"locality": "Bay Roberts",
				"postalCode": "A0A 3S0"
			},
			"geometry": {
				"type": "Point",
				"coordinates": [
					-53.2866657,
					47.5717349
				]
			},
			"bbox": [
				-53.2883319,
				47.5706107,
				-53.2849995,
				47.572859
			]
		}
	]
}
