{
	"type": "FeatureCollection",
	"features": [
		{
			"type": "Feature",
			"properties": {
				"confidence": 9,
				"authenticationResultCode": "ValidCredentials",
				"brandLogoUri": "http://dev.virtualearth.net/Branding/logo_powered_by.png",
				"copyright": "Copyright © 2017 Microsoft and its suppliers. All rights reserved. This API cannot be accessed and the content and any results may not be used, reproduced or transmitted in any manner without express written permission from Microsoft Corporation.",
				"entityType": "Address",
				"matchCodes": [
					"Good"
				],
				"name": "2665 Renfrew St, Vancouver, BC V5M 0A7, Canada",
				"statusCode": 200,
				"statusDescription": "OK",
				"traceId": "5525acb49d6f47148d2a334318797849|BN20200137|7.7.0.0|",
				"addressLine": "2665 Renfrew St",
				"adminDistrict": "BC",
				"adminDistrict2": "Greater Vancouver",
				"countryRegion": "Canada",
				"formattedAddress": "2665 Renfrew St, Vancouver, BC V5M 0A7, Canada",
				"locality": "Vancouver",
				"neighborhood": "Renfrew-Collingwood",
				"postalCode": "V5M 0A7"
			},
			"geometry": {
				"type": "Point",
				"coordinates": [
					-123.0444249,
					49.2601906
				]
			},
			"bbox": [
				-123.0461474,
				49.2590665,
				-123.0427024,
				49.2613148
			]
		}
	]
}
