{
	"type": "FeatureCollection",
	"features": [
		{
			"type": "Feature",
			"properties": {
				"confidence": 9,
				"authenticationResultCode": "ValidCredentials",
				"brandLogoUri": "http://dev.virtualearth.net/Branding/logo_powered_by.png",
				"copyright": "Copyright © 2017 Microsoft and its suppliers. All rights reserved. This API cannot be accessed and the content and any results may not be used, reproduced or transmitted in any manner without express written permission from Microsoft Corporation.",
				"entityType": "Address",
				"matchCodes": [
					"Good"
				],
				"name": "27 E 7th Ave, Vancouver, BC V5T 1M4, Canada",
				"statusCode": 200,
				"statusDescription": "OK",
				"traceId": "4d155468a604423492c853306ce09118|BN20200137|7.7.0.0|",
				"addressLine": "27 E 7th Ave",
				"adminDistrict": "BC",
				"adminDistrict2": "Greater Vancouver",
				"countryRegion": "Canada",
				"formattedAddress": "27 E 7th Ave, Vancouver, BC V5T 1M4, Canada",
				"locality": "Vancouver",
				"neighborhood": "Mt Pleasant",
				"postalCode": "V5T 1M4"
			},
			"geometry": {
				"type": "Point",
				"coordinates": [
					-123.10421,
					49.2649
				]
			},
			"bbox": [
				-123.1059327,
				49.2637758,
				-123.1024873,
				49.2660242
			]
		}
	]
}
