{
	"type": "FeatureCollection",
	"features": [
		{
			"type": "Feature",
			"properties": {
				"confidence": 9,
				"authenticationResultCode": "ValidCredentials",
				"brandLogoUri": "http://dev.virtualearth.net/Branding/logo_powered_by.png",
				"copyright": "Copyright © 2017 Microsoft and its suppliers. All rights reserved. This API cannot be accessed and the content and any results may not be used, reproduced or transmitted in any manner without express written permission from Microsoft Corporation.",
				"entityType": "Address",
				"matchCodes": [
					"Ambiguous"
				],
				"name": "27 Perivale Rd E, Central Manitoulin, ON P0P, Canada",
				"statusCode": 200,
				"statusDescription": "OK",
				"traceId": "d0d9a2e123b143e1ae3c197b80daba7b|BN20240423|7.7.0.0|",
				"addressLine": "27 Perivale Rd E",
				"adminDistrict": "ON",
				"adminDistrict2": "Manitoulin",
				"countryRegion": "Canada",
				"formattedAddress": "27 Perivale Rd E, Central Manitoulin, ON P0P, Canada",
				"locality": "Central Manitoulin",
				"postalCode": "P0P 2B0"
			},
			"geometry": {
				"type": "Point",
				"coordinates": [
					-82.32429,
					45.73318
				]
			},
			"bbox": [
				-82.3259005,
				45.7320558,
				-82.3226795,
				45.7343042
			]
		},
		{
			"type": "Feature",
			"properties": {
				"confidence": 9,
				"authenticationResultCode": "ValidCredentials",
				"brandLogoUri": "http://dev.virtualearth.net/Branding/logo_powered_by.png",
				"copyright": "Copyright © 2017 Microsoft and its suppliers. All rights reserved. This API cannot be accessed and the content and any results may not be used, reproduced or transmitted in any manner without express written permission from Microsoft Corporation.",
				"entityType": "Address",
				"matchCodes": [
					"Ambiguous"
				],
				"name": "27 Perivale Rd W, Central Manitoulin, ON P0P 2B0, Canada",
				"statusCode": 200,
				"statusDescription": "OK",
				"traceId": "d0d9a2e123b143e1ae3c197b80daba7b|BN20240423|7.7.0.0|",
				"addressLine": "27 Perivale Rd W",
				"adminDistrict": "ON",
				"adminDistrict2": "Manitoulin",
				"countryRegion": "Canada",
				"formattedAddress": "27 Perivale Rd W, Central Manitoulin, ON P0P 2B0, Canada",
				"locality": "Central Manitoulin",
				"postalCode": "P0P 2B0"
			},
			"geometry": {
				"type": "Point",
				"coordinates": [
					-82.3091203,
					45.7740326
				]
			},
			"bbox": [
				-82.3107321,
				45.7729084,
				-82.3075086,
				45.7751567
			]
		}
	]
}
