{
	"type": "FeatureCollection",
	"features": [
		{
			"type": "Feature",
			"properties": {
				"confidence": 9,
				"authenticationResultCode": "ValidCredentials",
				"brandLogoUri": "http://dev.virtualearth.net/Branding/logo_powered_by.png",
				"copyright": "Copyright © 2017 Microsoft and its suppliers. All rights reserved. This API cannot be accessed and the content and any results may not be used, reproduced or transmitted in any manner without express written permission from Microsoft Corporation.",
				"entityType": "Address",
				"matchCodes": [
					"Good"
				],
				"name": "2715 61 Ave SE, Calgary, AB T2C 4X3, Canada",
				"statusCode": 200,
				"statusDescription": "OK",
				"traceId": "5983f8b65033404ab9d4e624319ef9bf|BN20130431|7.7.0.0|",
				"addressLine": "2715 61 Ave SE",
				"adminDistrict": "AB",
				"adminDistrict2": "Alberta",
				"countryRegion": "Canada",
				"formattedAddress": "2715 61 Ave SE, Calgary, AB T2C 4X3, Canada",
				"locality": "Calgary",
				"postalCode": "T2C 4X3"
			},
			"geometry": {
				"type": "Point",
				"coordinates": [
					-113.9976209,
					50.9986756
				]
			},
			"bbox": [
				-113.9994071,
				50.9975514,
				-113.9958346,
				50.9997998
			]
		}
	]
}
