{
	"type": "FeatureCollection",
	"features": [
		{
			"type": "Feature",
			"properties": {
				"confidence": 7,
				"authenticationResultCode": "ValidCredentials",
				"brandLogoUri": "http://dev.virtualearth.net/Branding/logo_powered_by.png",
				"copyright": "Copyright © 2017 Microsoft and its suppliers. All rights reserved. This API cannot be accessed and the content and any results may not be used, reproduced or transmitted in any manner without express written permission from Microsoft Corporation.",
				"entityType": "RoadBlock",
				"matchCodes": [
					"UpHierarchy"
				],
				"name": "Township Road 391, Red Deer County, AB T4S, Canada",
				"statusCode": 200,
				"statusDescription": "OK",
				"traceId": "1d5cdc598b61461381a792dc9a12643c|BN20130631|7.7.0.0|",
				"addressLine": "Township Road 391",
				"adminDistrict": "AB",
				"adminDistrict2": "Alberta",
				"countryRegion": "Canada",
				"formattedAddress": "Township Road 391, Red Deer County, AB T4S, Canada",
				"locality": "Red Deer County",
				"postalCode": "T4S 2A1"
			},
			"geometry": {
				"type": "Point",
				"coordinates": [
					-114.03542,
					52.33409
				]
			},
			"bbox": [
				-114.07241,
				52.33319,
				-114.0018,
				52.33418
			]
		}
	]
}
