{
	"type": "FeatureCollection",
	"features": [
		{
			"type": "Feature",
			"properties": {
				"confidence": 9,
				"authenticationResultCode": "ValidCredentials",
				"brandLogoUri": "http://dev.virtualearth.net/Branding/logo_powered_by.png",
				"copyright": "Copyright © 2017 Microsoft and its suppliers. All rights reserved. This API cannot be accessed and the content and any results may not be used, reproduced or transmitted in any manner without express written permission from Microsoft Corporation.",
				"entityType": "Address",
				"matchCodes": [
					"Good"
				],
				"name": "2745 W 4th Ave, Vancouver, BC V6K 1P9, Canada",
				"statusCode": 200,
				"statusDescription": "OK",
				"traceId": "e4232515d05c4b6dbb4f4d16d1f1a540|BN20240423|7.7.0.0|",
				"addressLine": "2745 W 4th Ave",
				"adminDistrict": "BC",
				"adminDistrict2": "Greater Vancouver",
				"countryRegion": "Canada",
				"formattedAddress": "2745 W 4th Ave, Vancouver, BC V6K 1P9, Canada",
				"locality": "Vancouver",
				"neighborhood": "Kitsilano",
				"postalCode": "V6K 1P9"
			},
			"geometry": {
				"type": "Point",
				"coordinates": [
					-123.1673186,
					49.2684849
				]
			},
			"bbox": [
				-123.1690414,
				49.2673607,
				-123.1655958,
				49.269609
			]
		}
	]
}
