{
	"type": "FeatureCollection",
	"features": [
		{
			"type": "Feature",
			"properties": {
				"confidence": 9,
				"authenticationResultCode": "ValidCredentials",
				"brandLogoUri": "http://dev.virtualearth.net/Branding/logo_powered_by.png",
				"copyright": "Copyright © 2017 Microsoft and its suppliers. All rights reserved. This API cannot be accessed and the content and any results may not be used, reproduced or transmitted in any manner without express written permission from Microsoft Corporation.",
				"entityType": "Address",
				"matchCodes": [
					"Good"
				],
				"name": "275 Slater St, Ottawa, ON K1P 5H9, Canada",
				"statusCode": 200,
				"statusDescription": "OK",
				"traceId": "78cfd882a94c4622a8d1fcce581400e7|BN20260223|7.7.0.0|",
				"addressLine": "275 Slater St",
				"adminDistrict": "ON",
				"adminDistrict2": "Ottawa",
				"countryRegion": "Canada",
				"formattedAddress": "275 Slater St, Ottawa, ON K1P 5H9, Canada",
				"locality": "Ottawa",
				"neighborhood": "Byward Market-Parliament Hill",
				"postalCode": "K1P 5H9"
			},
			"geometry": {
				"type": "Point",
				"coordinates": [
					-75.70139,
					45.4189
				]
			},
			"bbox": [
				-75.7029915,
				45.4177758,
				-75.6997885,
				45.4200242
			]
		}
	]
}
