{
	"type": "FeatureCollection",
	"features": [
		{
			"type": "Feature",
			"properties": {
				"confidence": 9,
				"authenticationResultCode": "ValidCredentials",
				"brandLogoUri": "http://dev.virtualearth.net/Branding/logo_powered_by.png",
				"copyright": "Copyright © 2017 Microsoft and its suppliers. All rights reserved. This API cannot be accessed and the content and any results may not be used, reproduced or transmitted in any manner without express written permission from Microsoft Corporation.",
				"entityType": "Address",
				"matchCodes": [
					"Good"
				],
				"name": "275 Leclair Ave, Timmins, ON P4R 0C1, Canada",
				"statusCode": 200,
				"statusDescription": "OK",
				"traceId": "4cf8d6c69f154645aedae05f6a98453f|BN20130632|7.7.0.0|",
				"addressLine": "275 Leclair Ave",
				"adminDistrict": "ON",
				"adminDistrict2": "Cochrane",
				"countryRegion": "Canada",
				"formattedAddress": "275 Leclair Ave, Timmins, ON P4R 0C1, Canada",
				"locality": "Timmins",
				"neighborhood": "Kamiskotia",
				"postalCode": "P4R 0C1"
			},
			"geometry": {
				"type": "Point",
				"coordinates": [
					-81.63461,
					48.5825466
				]
			},
			"bbox": [
				-81.6363093,
				48.5814225,
				-81.6329107,
				48.5836708
			]
		}
	]
}
