{
	"type": "FeatureCollection",
	"features": [
		{
			"type": "Feature",
			"properties": {
				"confidence": 9,
				"authenticationResultCode": "ValidCredentials",
				"brandLogoUri": "http://dev.virtualearth.net/Branding/logo_powered_by.png",
				"copyright": "Copyright © 2017 Microsoft and its suppliers. All rights reserved. This API cannot be accessed and the content and any results may not be used, reproduced or transmitted in any manner without express written permission from Microsoft Corporation.",
				"entityType": "Address",
				"matchCodes": [
					"Good"
				],
				"name": "275 Rue Quinlan, La Salle, QC H8R 3W4, Canada",
				"statusCode": 200,
				"statusDescription": "OK",
				"traceId": "c9dbe2d2f4ba4a5fab113226716b0c16|BN20290118|7.7.0.0|",
				"addressLine": "275 Rue Quinlan",
				"adminDistrict": "QC",
				"adminDistrict2": "Montreal",
				"countryRegion": "Canada",
				"formattedAddress": "275 Rue Quinlan, La Salle, QC H8R 3W4, Canada",
				"locality": "Montreal",
				"neighborhood": "La Salle",
				"postalCode": "H8R 3W4"
			},
			"geometry": {
				"type": "Point",
				"coordinates": [
					-73.64583,
					45.42893
				]
			},
			"bbox": [
				-73.6474318,
				45.4278058,
				-73.6442282,
				45.4300542
			]
		}
	]
}
