{
	"type": "FeatureCollection",
	"features": [
		{
			"type": "Feature",
			"properties": {
				"confidence": 9,
				"authenticationResultCode": "ValidCredentials",
				"brandLogoUri": "http://dev.virtualearth.net/Branding/logo_powered_by.png",
				"copyright": "Copyright © 2017 Microsoft and its suppliers. All rights reserved. This API cannot be accessed and the content and any results may not be used, reproduced or transmitted in any manner without express written permission from Microsoft Corporation.",
				"entityType": "Address",
				"matchCodes": [
					"Good"
				],
				"name": "2777 Alder St S, Campbell River, BC V9H 1S1, Canada",
				"statusCode": 200,
				"statusDescription": "OK",
				"traceId": "2ea70a5e5840499c97521b6444a88143|BN20131519|7.7.0.0|",
				"addressLine": "2777 Alder St S",
				"adminDistrict": "BC",
				"adminDistrict2": "Strathcona",
				"countryRegion": "Canada",
				"formattedAddress": "2777 Alder St S, Campbell River, BC V9H 1S1, Canada",
				"locality": "Campbell River",
				"postalCode": "V9H 1S1"
			},
			"geometry": {
				"type": "Point",
				"coordinates": [
					-125.23213,
					49.96307
				]
			},
			"bbox": [
				-125.2338775,
				49.9619458,
				-125.2303825,
				49.9641942
			]
		}
	]
}
