{
	"type": "FeatureCollection",
	"features": [
		{
			"type": "Feature",
			"properties": {
				"confidence": 9,
				"authenticationResultCode": "ValidCredentials",
				"brandLogoUri": "http://dev.virtualearth.net/Branding/logo_powered_by.png",
				"copyright": "Copyright © 2017 Microsoft and its suppliers. All rights reserved. This API cannot be accessed and the content and any results may not be used, reproduced or transmitted in any manner without express written permission from Microsoft Corporation.",
				"entityType": "Address",
				"matchCodes": [
					"Good"
				],
				"name": "2782 Dufferin St, North York, ON M6B 3R7, Canada",
				"statusCode": 200,
				"statusDescription": "OK",
				"traceId": "5cc7066043574db1848dbb9281a166f7|BN20130533|7.7.0.0|",
				"addressLine": "2782 Dufferin St",
				"adminDistrict": "ON",
				"adminDistrict2": "Toronto",
				"countryRegion": "Canada",
				"formattedAddress": "2782 Dufferin St, North York, ON M6B 3R7, Canada",
				"locality": "Toronto",
				"neighborhood": "Yorkdale-Glen Park",
				"postalCode": "M6B 3R7"
			},
			"geometry": {
				"type": "Point",
				"coordinates": [
					-79.45289,
					43.70438
				]
			},
			"bbox": [
				-79.454445,
				43.7032558,
				-79.451335,
				43.7055042
			]
		}
	]
}
