{
	"type": "FeatureCollection",
	"features": [
		{
			"type": "Feature",
			"properties": {
				"confidence": 9,
				"authenticationResultCode": "ValidCredentials",
				"brandLogoUri": "http://dev.virtualearth.net/Branding/logo_powered_by.png",
				"copyright": "Copyright © 2017 Microsoft and its suppliers. All rights reserved. This API cannot be accessed and the content and any results may not be used, reproduced or transmitted in any manner without express written permission from Microsoft Corporation.",
				"entityType": "Address",
				"matchCodes": [
					"Good"
				],
				"name": "2783 Fenton Rd, Gloucester, ON K1T 3T8, Canada",
				"statusCode": 200,
				"statusDescription": "OK",
				"traceId": "98f8cdc3a7d0468fa8fd7e25d69419e7|BN20250135|7.7.0.0|",
				"addressLine": "2783 Fenton Rd",
				"adminDistrict": "ON",
				"adminDistrict2": "Ottawa",
				"countryRegion": "Canada",
				"formattedAddress": "2783 Fenton Rd, Gloucester, ON K1T 3T8, Canada",
				"locality": "Ottawa",
				"neighborhood": "Gloucester",
				"postalCode": "K1T 3T8"
			},
			"geometry": {
				"type": "Point",
				"coordinates": [
					-75.61919,
					45.32055
				]
			},
			"bbox": [
				-75.6207888,
				45.3194258,
				-75.6175912,
				45.3216742
			]
		}
	]
}
