{
	"type": "FeatureCollection",
	"features": [
		{
			"type": "Feature",
			"properties": {
				"confidence": 9,
				"authenticationResultCode": "ValidCredentials",
				"brandLogoUri": "http://dev.virtualearth.net/Branding/logo_powered_by.png",
				"copyright": "Copyright © 2017 Microsoft and its suppliers. All rights reserved. This API cannot be accessed and the content and any results may not be used, reproduced or transmitted in any manner without express written permission from Microsoft Corporation.",
				"entityType": "Address",
				"matchCodes": [
					"Good"
				],
				"name": "2785 HWY-15, Rideau Lakes, ON K0G 1E0, Canada",
				"statusCode": 200,
				"statusDescription": "OK",
				"traceId": "4e4926cf6f4d4d67bdf300efee113886|BN20130442|7.7.0.0|",
				"addressLine": "2785 HWY-15",
				"adminDistrict": "ON",
				"adminDistrict2": "Leeds and Grenville",
				"countryRegion": "Canada",
				"formattedAddress": "2785 HWY-15, Rideau Lakes, ON K0G 1E0, Canada",
				"locality": "Rideau Lakes",
				"neighborhood": "Portland",
				"postalCode": "K0G 1E0"
			},
			"geometry": {
				"type": "Point",
				"coordinates": [
					-76.1864197,
					44.699862
				]
			},
			"bbox": [
				-76.1880012,
				44.6987378,
				-76.1848381,
				44.7009861
			]
		}
	]
}
