{
	"type": "FeatureCollection",
	"features": [
		{
			"type": "Feature",
			"properties": {
				"confidence": 9,
				"authenticationResultCode": "ValidCredentials",
				"brandLogoUri": "http://dev.virtualearth.net/Branding/logo_powered_by.png",
				"copyright": "Copyright © 2017 Microsoft and its suppliers. All rights reserved. This API cannot be accessed and the content and any results may not be used, reproduced or transmitted in any manner without express written permission from Microsoft Corporation.",
				"entityType": "Address",
				"matchCodes": [
					"Good"
				],
				"name": "279 Yonge St, Barrie, ON L4N 7T9, Canada",
				"statusCode": 200,
				"statusDescription": "OK",
				"traceId": "7110132474834db3a3266572dc3665bb|BN20181720|7.7.0.0|",
				"addressLine": "279 Yonge St",
				"adminDistrict": "ON",
				"adminDistrict2": "Simcoe",
				"countryRegion": "Canada",
				"formattedAddress": "279 Yonge St, Barrie, ON L4N 7T9, Canada",
				"locality": "Barrie",
				"neighborhood": "South Shore",
				"postalCode": "L4N 7T9"
			},
			"geometry": {
				"type": "Point",
				"coordinates": [
					-79.67359,
					44.3713
				]
			},
			"bbox": [
				-79.6751626,
				44.3701758,
				-79.6720174,
				44.3724242
			]
		}
	]
}
