{
	"type": "FeatureCollection",
	"features": [
		{
			"type": "Feature",
			"properties": {
				"confidence": 9,
				"authenticationResultCode": "ValidCredentials",
				"brandLogoUri": "http://dev.virtualearth.net/Branding/logo_powered_by.png",
				"copyright": "Copyright © 2017 Microsoft and its suppliers. All rights reserved. This API cannot be accessed and the content and any results may not be used, reproduced or transmitted in any manner without express written permission from Microsoft Corporation.",
				"entityType": "Address",
				"matchCodes": [
					"Good"
				],
				"name": "2790 Aviation Way, Kamloops, BC V2B 7W1, Canada",
				"statusCode": 200,
				"statusDescription": "OK",
				"traceId": "b80f11791d974433a7fdbdc1089d7cef|BN20130532|7.7.0.0|",
				"addressLine": "2790 Aviation Way",
				"adminDistrict": "BC",
				"adminDistrict2": "Thompson-Nicola",
				"countryRegion": "Canada",
				"formattedAddress": "2790 Aviation Way, Kamloops, BC V2B 7W1, Canada",
				"locality": "Kamloops",
				"neighborhood": "Brocklehurst",
				"postalCode": "V2B 7W1"
			},
			"geometry": {
				"type": "Point",
				"coordinates": [
					-120.4279152,
					50.6997478
				]
			},
			"bbox": [
				-120.42969,
				50.6986237,
				-120.4261403,
				50.700872
			]
		}
	]
}
