{
	"type": "FeatureCollection",
	"features": [
		{
			"type": "Feature",
			"properties": {
				"confidence": 9,
				"authenticationResultCode": "ValidCredentials",
				"brandLogoUri": "http://dev.virtualearth.net/Branding/logo_powered_by.png",
				"copyright": "Copyright © 2017 Microsoft and its suppliers. All rights reserved. This API cannot be accessed and the content and any results may not be used, reproduced or transmitted in any manner without express written permission from Microsoft Corporation.",
				"entityType": "Address",
				"matchCodes": [
					"Good"
				],
				"name": "28 Couvent Rd, Bouctouche, NB E4S 3B9, Canada",
				"statusCode": 200,
				"statusDescription": "OK",
				"traceId": "6c6bcbb85907487cab5df6e3dbac2c98|BN20290118|7.7.0.0|",
				"addressLine": "28 Couvent Rd",
				"adminDistrict": "NB",
				"adminDistrict2": "Kent",
				"countryRegion": "Canada",
				"formattedAddress": "28 Couvent Rd, Bouctouche, NB E4S 3B9, Canada",
				"locality": "Bouctouche",
				"postalCode": "E4S 3B9"
			},
			"geometry": {
				"type": "Point",
				"coordinates": [
					-64.7141828,
					46.4770071
				]
			},
			"bbox": [
				-64.7158152,
				46.4758829,
				-64.7125504,
				46.4781312
			]
		}
	]
}
