{
	"type": "FeatureCollection",
	"features": [
		{
			"type": "Feature",
			"properties": {
				"confidence": 9,
				"authenticationResultCode": "ValidCredentials",
				"brandLogoUri": "http://dev.virtualearth.net/Branding/logo_powered_by.png",
				"copyright": "Copyright © 2017 Microsoft and its suppliers. All rights reserved. This API cannot be accessed and the content and any results may not be used, reproduced or transmitted in any manner without express written permission from Microsoft Corporation.",
				"entityType": "Address",
				"matchCodes": [
					"Good"
				],
				"name": "28 Prestwick Row SE, Calgary, AB T2Z 3L7, Canada",
				"statusCode": 200,
				"statusDescription": "OK",
				"traceId": "a737a129ba7c4d84bd17bbf531d05454|BN20130521|7.7.0.0|",
				"addressLine": "28 Prestwick Row SE",
				"adminDistrict": "AB",
				"adminDistrict2": "Alberta",
				"countryRegion": "Canada",
				"formattedAddress": "28 Prestwick Row SE, Calgary, AB T2Z 3L7, Canada",
				"locality": "Calgary",
				"neighborhood": "McKenzie Towne",
				"postalCode": "T2Z 3L7"
			},
			"geometry": {
				"type": "Point",
				"coordinates": [
					-113.96274,
					50.91898
				]
			},
			"bbox": [
				-113.9645232,
				50.9178558,
				-113.9609568,
				50.9201042
			]
		}
	]
}
