{
	"type": "FeatureCollection",
	"features": [
		{
			"type": "Feature",
			"properties": {
				"confidence": 9,
				"authenticationResultCode": "ValidCredentials",
				"brandLogoUri": "http://dev.virtualearth.net/Branding/logo_powered_by.png",
				"copyright": "Copyright © 2017 Microsoft and its suppliers. All rights reserved. This API cannot be accessed and the content and any results may not be used, reproduced or transmitted in any manner without express written permission from Microsoft Corporation.",
				"entityType": "Address",
				"matchCodes": [
					"Good"
				],
				"name": "280 Dovercourt Ave, Ottawa, ON K1Z 7H5, Canada",
				"statusCode": 200,
				"statusDescription": "OK",
				"traceId": "a7d89abc24d84c35aefeabb6330a8973|BN20260223|7.7.0.0|",
				"addressLine": "280 Dovercourt Ave",
				"adminDistrict": "ON",
				"adminDistrict2": "Ottawa",
				"countryRegion": "Canada",
				"formattedAddress": "280 Dovercourt Ave, Ottawa, ON K1Z 7H5, Canada",
				"locality": "Ottawa",
				"neighborhood": "Westboro",
				"postalCode": "K1Z 7H5"
			},
			"geometry": {
				"type": "Point",
				"coordinates": [
					-75.74642,
					45.38494
				]
			},
			"bbox": [
				-75.7480206,
				45.3838158,
				-75.7448194,
				45.3860642
			]
		}
	]
}
