{
	"type": "FeatureCollection",
	"features": [
		{
			"type": "Feature",
			"properties": {
				"confidence": 9,
				"authenticationResultCode": "ValidCredentials",
				"brandLogoUri": "http://dev.virtualearth.net/Branding/logo_powered_by.png",
				"copyright": "Copyright © 2017 Microsoft and its suppliers. All rights reserved. This API cannot be accessed and the content and any results may not be used, reproduced or transmitted in any manner without express written permission from Microsoft Corporation.",
				"entityType": "Address",
				"matchCodes": [
					"Good"
				],
				"name": "2812 Calgary Trl NW, Edmonton, AB T6J 6V7, Canada",
				"statusCode": 200,
				"statusDescription": "OK",
				"traceId": "b99b86b9fdcc47f4a22071428d53069a|BN20130721|7.7.0.0|",
				"addressLine": "2812 Calgary Trl NW",
				"adminDistrict": "AB",
				"adminDistrict2": "Alberta",
				"countryRegion": "Canada",
				"formattedAddress": "2812 Calgary Trl NW, Edmonton, AB T6J 6V7, Canada",
				"locality": "Edmonton",
				"neighborhood": "Ermineskin",
				"postalCode": "T6J 6V7"
			},
			"geometry": {
				"type": "Point",
				"coordinates": [
					-113.49441,
					53.45779
				]
			},
			"bbox": [
				-113.496298,
				53.4566658,
				-113.492522,
				53.4589142
			]
		}
	]
}
