{
	"type": "FeatureCollection",
	"features": [
		{
			"type": "Feature",
			"properties": {
				"confidence": 9,
				"authenticationResultCode": "ValidCredentials",
				"brandLogoUri": "http://dev.virtualearth.net/Branding/logo_powered_by.png",
				"copyright": "Copyright © 2017 Microsoft and its suppliers. All rights reserved. This API cannot be accessed and the content and any results may not be used, reproduced or transmitted in any manner without express written permission from Microsoft Corporation.",
				"entityType": "Address",
				"matchCodes": [
					"Good"
				],
				"name": "2815 12 St NE, Calgary, AB T2E 7J2, Canada",
				"statusCode": 200,
				"statusDescription": "OK",
				"traceId": "6dc12df8ab7748b8851e39b5b555f2d8|BN20160335|7.7.0.0|",
				"addressLine": "2815 12 St NE",
				"adminDistrict": "AB",
				"adminDistrict2": "Alberta",
				"countryRegion": "Canada",
				"formattedAddress": "2815 12 St NE, Calgary, AB T2E 7J2, Canada",
				"locality": "Calgary",
				"neighborhood": "Vista Heights",
				"postalCode": "T2E 7J2"
			},
			"geometry": {
				"type": "Point",
				"coordinates": [
					-114.02602,
					51.07779
				]
			},
			"bbox": [
				-114.0278093,
				51.0766658,
				-114.0242307,
				51.0789142
			]
		}
	]
}
