{
	"type": "FeatureCollection",
	"features": [
		{
			"type": "Feature",
			"properties": {
				"confidence": 9,
				"authenticationResultCode": "ValidCredentials",
				"brandLogoUri": "http://dev.virtualearth.net/Branding/logo_powered_by.png",
				"copyright": "Copyright © 2017 Microsoft and its suppliers. All rights reserved. This API cannot be accessed and the content and any results may not be used, reproduced or transmitted in any manner without express written permission from Microsoft Corporation.",
				"entityType": "Address",
				"matchCodes": [
					"Good"
				],
				"name": "2860 Rue du Pic, Laval, QC H7E 1J8, Canada",
				"statusCode": 200,
				"statusDescription": "OK",
				"traceId": "50d10036e635429c823d0ed7d72d528c|BN20130719|7.7.0.0|",
				"addressLine": "2860 Rue du Pic",
				"adminDistrict": "QC",
				"adminDistrict2": "Laval",
				"countryRegion": "Canada",
				"formattedAddress": "2860 Rue du Pic, Laval, QC H7E 1J8, Canada",
				"locality": "Laval",
				"postalCode": "H7E 1J8"
			},
			"geometry": {
				"type": "Point",
				"coordinates": [
					-73.67729,
					45.5966
				]
			},
			"bbox": [
				-73.6788966,
				45.5954758,
				-73.6756834,
				45.5977242
			]
		}
	]
}
