{
	"type": "FeatureCollection",
	"features": [
		{
			"type": "Feature",
			"properties": {
				"confidence": 9,
				"authenticationResultCode": "ValidCredentials",
				"brandLogoUri": "http://dev.virtualearth.net/Branding/logo_powered_by.png",
				"copyright": "Copyright © 2017 Microsoft and its suppliers. All rights reserved. This API cannot be accessed and the content and any results may not be used, reproduced or transmitted in any manner without express written permission from Microsoft Corporation.",
				"entityType": "Address",
				"matchCodes": [
					"Good"
				],
				"name": "2864 Norland Ave, Burnaby, BC V5B 3A6, Canada",
				"statusCode": 200,
				"statusDescription": "OK",
				"traceId": "946cdf0876e2402781bdd187de3db00c|BN20260231|7.7.0.0|",
				"addressLine": "2864 Norland Ave",
				"adminDistrict": "BC",
				"adminDistrict2": "Greater Vancouver",
				"countryRegion": "Canada",
				"formattedAddress": "2864 Norland Ave, Burnaby, BC V5B 3A6, Canada",
				"locality": "Burnaby",
				"neighborhood": "Ardingley-Sprott",
				"postalCode": "V5B 3A6"
			},
			"geometry": {
				"type": "Point",
				"coordinates": [
					-122.9782115,
					49.2583322
				]
			},
			"bbox": [
				-122.9799339,
				49.257208,
				-122.976489,
				49.2594563
			]
		}
	]
}
