{
	"type": "FeatureCollection",
	"features": [
		{
			"type": "Feature",
			"properties": {
				"confidence": 9,
				"authenticationResultCode": "ValidCredentials",
				"brandLogoUri": "http://dev.virtualearth.net/Branding/logo_powered_by.png",
				"copyright": "Copyright © 2017 Microsoft and its suppliers. All rights reserved. This API cannot be accessed and the content and any results may not be used, reproduced or transmitted in any manner without express written permission from Microsoft Corporation.",
				"entityType": "Address",
				"matchCodes": [
					"Good"
				],
				"name": "286 Campion St, Kelowna, BC V1X 7S8, Canada",
				"statusCode": 200,
				"statusDescription": "OK",
				"traceId": "f2c7e64de3354c9c8018cea6e94340ee|BN20130625|7.7.0.0|",
				"addressLine": "286 Campion St",
				"adminDistrict": "BC",
				"adminDistrict2": "Central Okanagan",
				"countryRegion": "Canada",
				"formattedAddress": "286 Campion St, Kelowna, BC V1X 7S8, Canada",
				"locality": "Kelowna",
				"postalCode": "V1X 7S8"
			},
			"geometry": {
				"type": "Point",
				"coordinates": [
					-119.4028858,
					49.9154235
				]
			},
			"bbox": [
				-119.4046316,
				49.9142994,
				-119.40114,
				49.9165477
			]
		}
	]
}
