{
	"type": "FeatureCollection",
	"features": [
		{
			"type": "Feature",
			"properties": {
				"confidence": 9,
				"authenticationResultCode": "ValidCredentials",
				"brandLogoUri": "http://dev.virtualearth.net/Branding/logo_powered_by.png",
				"copyright": "Copyright © 2017 Microsoft and its suppliers. All rights reserved. This API cannot be accessed and the content and any results may not be used, reproduced or transmitted in any manner without express written permission from Microsoft Corporation.",
				"entityType": "RoadBlock",
				"matchCodes": [
					"Good"
				],
				"name": "Des Arcs Rd, Bighorn No 8, AB T1W, Canada",
				"statusCode": 200,
				"statusDescription": "OK",
				"traceId": "2a671a643bee467c84742917ace05c07|BN20130620|7.7.0.0|",
				"addressLine": "Des Arcs Rd",
				"adminDistrict": "AB",
				"adminDistrict2": "Alberta",
				"countryRegion": "Canada",
				"formattedAddress": "Des Arcs Rd, Bighorn No 8, AB T1W, Canada",
				"locality": "Bighorn No 8",
				"neighborhood": "Lac des Arcs",
				"postalCode": "T1W 2W3"
			},
			"geometry": {
				"type": "Point",
				"coordinates": [
					-115.16263,
					51.05434
				]
			},
			"bbox": [
				-115.16312,
				51.05335,
				-115.16066,
				51.05512
			]
		}
	]
}
