{
	"type": "FeatureCollection",
	"features": [
		{
			"type": "Feature",
			"properties": {
				"confidence": 9,
				"authenticationResultCode": "ValidCredentials",
				"brandLogoUri": "http://dev.virtualearth.net/Branding/logo_powered_by.png",
				"copyright": "Copyright © 2017 Microsoft and its suppliers. All rights reserved. This API cannot be accessed and the content and any results may not be used, reproduced or transmitted in any manner without express written permission from Microsoft Corporation.",
				"entityType": "Address",
				"matchCodes": [
					"Good"
				],
				"name": "29 Youngestar Trl, Brampton, ON L6P 1P5, Canada",
				"statusCode": 200,
				"statusDescription": "OK",
				"traceId": "e5a47dec7a7e47f980b6ee02196797b6|BN20260231|7.7.0.0|",
				"addressLine": "29 Youngestar Trl",
				"adminDistrict": "ON",
				"adminDistrict2": "Peel",
				"countryRegion": "Canada",
				"formattedAddress": "29 Youngestar Trl, Brampton, ON L6P 1P5, Canada",
				"locality": "Brampton",
				"neighborhood": "Castlemore",
				"postalCode": "L6P 1P5"
			},
			"geometry": {
				"type": "Point",
				"coordinates": [
					-79.66055,
					43.78308
				]
			},
			"bbox": [
				-79.6621071,
				43.7819558,
				-79.6589929,
				43.7842042
			]
		}
	]
}
