{
	"type": "FeatureCollection",
	"features": [
		{
			"type": "Feature",
			"properties": {
				"confidence": 9,
				"authenticationResultCode": "ValidCredentials",
				"brandLogoUri": "http://dev.virtualearth.net/Branding/logo_powered_by.png",
				"copyright": "Copyright © 2017 Microsoft and its suppliers. All rights reserved. This API cannot be accessed and the content and any results may not be used, reproduced or transmitted in any manner without express written permission from Microsoft Corporation.",
				"entityType": "Address",
				"matchCodes": [
					"Good"
				],
				"name": "2907 Parsons Rd NW, Edmonton, AB T6N 1A3, Canada",
				"statusCode": 200,
				"statusDescription": "OK",
				"traceId": "c7feffde479d4ef29a9b42253869efbd|BN20190653|7.7.0.0|",
				"addressLine": "2907 Parsons Rd NW",
				"adminDistrict": "AB",
				"adminDistrict2": "Alberta",
				"countryRegion": "Canada",
				"formattedAddress": "2907 Parsons Rd NW, Edmonton, AB T6N 1A3, Canada",
				"locality": "Edmonton",
				"neighborhood": "Parsons Industrial",
				"postalCode": "T6N 1A3"
			},
			"geometry": {
				"type": "Point",
				"coordinates": [
					-113.48222,
					53.45897
				]
			},
			"bbox": [
				-113.4841081,
				53.4578458,
				-113.4803319,
				53.4600942
			]
		}
	]
}
