{
	"type": "FeatureCollection",
	"features": [
		{
			"type": "Feature",
			"properties": {
				"confidence": 9,
				"authenticationResultCode": "ValidCredentials",
				"brandLogoUri": "http://dev.virtualearth.net/Branding/logo_powered_by.png",
				"copyright": "Copyright © 2017 Microsoft and its suppliers. All rights reserved. This API cannot be accessed and the content and any results may not be used, reproduced or transmitted in any manner without express written permission from Microsoft Corporation.",
				"entityType": "Address",
				"matchCodes": [
					"Good"
				],
				"name": "291 Williamstown Clos NW, Airdrie, AB T4B 0X8, Canada",
				"statusCode": 200,
				"statusDescription": "OK",
				"traceId": "9436f4f675b44324a8854acaccf3c858|BN20260223|7.7.0.0|",
				"addressLine": "291 Williamstown Clos NW",
				"adminDistrict": "AB",
				"adminDistrict2": "Alberta",
				"countryRegion": "Canada",
				"formattedAddress": "291 Williamstown Clos NW, Airdrie, AB T4B 0X8, Canada",
				"locality": "Airdrie",
				"postalCode": "T4B 0X8"
			},
			"geometry": {
				"type": "Point",
				"coordinates": [
					-114.03497,
					51.3015
				]
			},
			"bbox": [
				-114.036768,
				51.3003758,
				-114.033172,
				51.3026242
			]
		}
	]
}
