{
	"type": "FeatureCollection",
	"features": [
		{
			"type": "Feature",
			"properties": {
				"confidence": 9,
				"authenticationResultCode": "ValidCredentials",
				"brandLogoUri": "http://dev.virtualearth.net/Branding/logo_powered_by.png",
				"copyright": "Copyright © 2017 Microsoft and its suppliers. All rights reserved. This API cannot be accessed and the content and any results may not be used, reproduced or transmitted in any manner without express written permission from Microsoft Corporation.",
				"entityType": "Address",
				"matchCodes": [
					"Good"
				],
				"name": "292 Rue Principale, Girardville, QC G0W 1R0, Canada",
				"statusCode": 200,
				"statusDescription": "OK",
				"traceId": "0e547aeca303473087463187184ad659|BN20240253|7.7.0.0|",
				"addressLine": "292 Rue Principale",
				"adminDistrict": "QC",
				"adminDistrict2": "Maria-Chapdelaine",
				"countryRegion": "Canada",
				"formattedAddress": "292 Rue Principale, Girardville, QC G0W 1R0, Canada",
				"locality": "Girardville",
				"postalCode": "G0W 1R0"
			},
			"geometry": {
				"type": "Point",
				"coordinates": [
					-72.53689,
					48.99385
				]
			},
			"bbox": [
				-72.5386033,
				48.9927258,
				-72.5351767,
				48.9949742
			]
		}
	]
}
