{
	"type": "FeatureCollection",
	"features": [
		{
			"type": "Feature",
			"properties": {
				"confidence": 9,
				"authenticationResultCode": "ValidCredentials",
				"brandLogoUri": "http://dev.virtualearth.net/Branding/logo_powered_by.png",
				"copyright": "Copyright © 2017 Microsoft and its suppliers. All rights reserved. This API cannot be accessed and the content and any results may not be used, reproduced or transmitted in any manner without express written permission from Microsoft Corporation.",
				"entityType": "Address",
				"matchCodes": [
					"Good"
				],
				"name": "2933 Murray St, Port Moody, BC V3H 1X3, Canada",
				"statusCode": 200,
				"statusDescription": "OK",
				"traceId": "07864f4e4be34d1bb3040e527d6c556c|BN20121764|7.7.0.0|",
				"addressLine": "2933 Murray St",
				"adminDistrict": "BC",
				"adminDistrict2": "Greater Vancouver",
				"countryRegion": "Canada",
				"formattedAddress": "2933 Murray St, Port Moody, BC V3H 1X3, Canada",
				"locality": "Port Moody",
				"postalCode": "V3H 1X3"
			},
			"geometry": {
				"type": "Point",
				"coordinates": [
					-122.84552,
					49.27857
				]
			},
			"bbox": [
				-122.8472432,
				49.2774458,
				-122.8437968,
				49.2796942
			]
		}
	]
}
