{
	"type": "FeatureCollection",
	"features": [
		{
			"type": "Feature",
			"properties": {
				"confidence": 9,
				"authenticationResultCode": "ValidCredentials",
				"brandLogoUri": "http://dev.virtualearth.net/Branding/logo_powered_by.png",
				"copyright": "Copyright © 2017 Microsoft and its suppliers. All rights reserved. This API cannot be accessed and the content and any results may not be used, reproduced or transmitted in any manner without express written permission from Microsoft Corporation.",
				"entityType": "Address",
				"matchCodes": [
					"Good"
				],
				"name": "2940 Elegante Pl, Langford, BC V9B 5W8, Canada",
				"statusCode": 200,
				"statusDescription": "OK",
				"traceId": "6264bf3b6f90461283c8b1d90d828684|BN20320521|7.7.0.0|",
				"addressLine": "2940 Elegante Pl",
				"adminDistrict": "BC",
				"adminDistrict2": "Capital",
				"countryRegion": "Canada",
				"formattedAddress": "2940 Elegante Pl, Langford, BC V9B 5W8, Canada",
				"locality": "Langford",
				"postalCode": "V9B 5W8"
			},
			"geometry": {
				"type": "Point",
				"coordinates": [
					-123.55516,
					48.4564499
				]
			},
			"bbox": [
				-123.5568551,
				48.4553257,
				-123.5534649,
				48.4575741
			]
		}
	]
}
