{
	"type": "FeatureCollection",
	"features": [
		{
			"type": "Feature",
			"properties": {
				"confidence": 9,
				"authenticationResultCode": "ValidCredentials",
				"brandLogoUri": "http://dev.virtualearth.net/Branding/logo_powered_by.png",
				"copyright": "Copyright © 2017 Microsoft and its suppliers. All rights reserved. This API cannot be accessed and the content and any results may not be used, reproduced or transmitted in any manner without express written permission from Microsoft Corporation.",
				"entityType": "Address",
				"matchCodes": [
					"Good"
				],
				"name": "295 Hunter Rd, Grimsby, ON L3M, Canada",
				"statusCode": 200,
				"statusDescription": "OK",
				"traceId": "0db63400610c4ffb90287268b75a8b62|BN20130447|7.7.0.0|",
				"addressLine": "295 Hunter Rd",
				"adminDistrict": "ON",
				"adminDistrict2": "Niagara",
				"countryRegion": "Canada",
				"formattedAddress": "295 Hunter Rd, Grimsby, ON L3M, Canada",
				"locality": "Grimsby",
				"postalCode": "L3M 4H5"
			},
			"geometry": {
				"type": "Point",
				"coordinates": [
					-79.60341,
					43.208179
				]
			},
			"bbox": [
				-79.6049523,
				43.2070549,
				-79.6018676,
				43.2093032
			]
		}
	]
}
