{
	"type": "FeatureCollection",
	"features": [
		{
			"type": "Feature",
			"properties": {
				"confidence": 9,
				"authenticationResultCode": "ValidCredentials",
				"brandLogoUri": "http://dev.virtualearth.net/Branding/logo_powered_by.png",
				"copyright": "Copyright © 2017 Microsoft and its suppliers. All rights reserved. This API cannot be accessed and the content and any results may not be used, reproduced or transmitted in any manner without express written permission from Microsoft Corporation.",
				"entityType": "Address",
				"matchCodes": [
					"Good"
				],
				"name": "295 Rue Dufferin, Sherbrooke, QC J1H 4M5, Canada",
				"statusCode": 200,
				"statusDescription": "OK",
				"traceId": "dc2e1a102e5842b8ad3e90773565ee7f|BN20210145|7.7.0.0|",
				"addressLine": "295 Rue Dufferin",
				"adminDistrict": "QC",
				"adminDistrict2": "Sherbrooke",
				"countryRegion": "Canada",
				"formattedAddress": "295 Rue Dufferin, Sherbrooke, QC J1H 4M5, Canada",
				"locality": "Sherbrooke",
				"postalCode": "J1H 4M5"
			},
			"geometry": {
				"type": "Point",
				"coordinates": [
					-71.8952,
					45.4056799
				]
			},
			"bbox": [
				-71.8968012,
				45.4045557,
				-71.8935988,
				45.4068041
			]
		}
	]
}
