{
	"type": "FeatureCollection",
	"features": [
		{
			"type": "Feature",
			"properties": {
				"confidence": 9,
				"authenticationResultCode": "ValidCredentials",
				"brandLogoUri": "http://dev.virtualearth.net/Branding/logo_powered_by.png",
				"copyright": "Copyright © 2017 Microsoft and its suppliers. All rights reserved. This API cannot be accessed and the content and any results may not be used, reproduced or transmitted in any manner without express written permission from Microsoft Corporation.",
				"entityType": "Address",
				"matchCodes": [
					"Good"
				],
				"name": "295159 8th Line, Amaranth, ON L9V, Canada",
				"statusCode": 200,
				"statusDescription": "OK",
				"traceId": "99077dfeec794506b0335d6903552495|BN20130532|7.7.0.0|",
				"addressLine": "295159 8th Line",
				"adminDistrict": "ON",
				"adminDistrict2": "Dufferin",
				"countryRegion": "Canada",
				"formattedAddress": "295159 8th Line, Amaranth, ON L9V, Canada",
				"locality": "Amaranth",
				"postalCode": "L9V"
			},
			"geometry": {
				"type": "Point",
				"coordinates": [
					-80.2757913,
					44.0111719
				]
			},
			"bbox": [
				-80.2773544,
				44.0100478,
				-80.2742283,
				44.0122961
			]
		}
	]
}
