{
	"type": "FeatureCollection",
	"features": [
		{
			"type": "Feature",
			"properties": {
				"confidence": 9,
				"authenticationResultCode": "ValidCredentials",
				"brandLogoUri": "http://dev.virtualearth.net/Branding/logo_powered_by.png",
				"copyright": "Copyright © 2017 Microsoft and its suppliers. All rights reserved. This API cannot be accessed and the content and any results may not be used, reproduced or transmitted in any manner without express written permission from Microsoft Corporation.",
				"entityType": "Address",
				"matchCodes": [
					"Good"
				],
				"name": "297 Shoreline Ave, South Bruce Peninsula, ON N0H 2T0, Canada",
				"statusCode": 200,
				"statusDescription": "OK",
				"traceId": "d567b189beb848a3b79f596784bf6885|BN20190642|7.7.0.0|",
				"addressLine": "297 Shoreline Ave",
				"adminDistrict": "ON",
				"adminDistrict2": "Bruce",
				"countryRegion": "Canada",
				"formattedAddress": "297 Shoreline Ave, South Bruce Peninsula, ON N0H 2T0, Canada",
				"locality": "South Bruce Peninsula",
				"postalCode": "N0H 2T0"
			},
			"geometry": {
				"type": "Point",
				"coordinates": [
					-81.27921,
					44.74648
				]
			},
			"bbox": [
				-81.2807928,
				44.7453558,
				-81.2776272,
				44.7476042
			]
		}
	]
}
