{
	"type": "FeatureCollection",
	"features": [
		{
			"type": "Feature",
			"properties": {
				"confidence": 9,
				"authenticationResultCode": "ValidCredentials",
				"brandLogoUri": "http://dev.virtualearth.net/Branding/logo_powered_by.png",
				"copyright": "Copyright © 2017 Microsoft and its suppliers. All rights reserved. This API cannot be accessed and the content and any results may not be used, reproduced or transmitted in any manner without express written permission from Microsoft Corporation.",
				"entityType": "Address",
				"matchCodes": [
					"Good"
				],
				"name": "3 Boorman Ct, Barrie, ON L4N 8J4, Canada",
				"statusCode": 200,
				"statusDescription": "OK",
				"traceId": "568b445952bc48b28e5b674c98a5c97b|BN20160335|7.7.0.0|",
				"addressLine": "3 Boorman Ct",
				"adminDistrict": "ON",
				"adminDistrict2": "Simcoe",
				"countryRegion": "Canada",
				"formattedAddress": "3 Boorman Ct, Barrie, ON L4N 8J4, Canada",
				"locality": "Barrie",
				"neighborhood": "Holly",
				"postalCode": "L4N 8J4"
			},
			"geometry": {
				"type": "Point",
				"coordinates": [
					-79.7145,
					44.3344499
				]
			},
			"bbox": [
				-79.7160716,
				44.3333257,
				-79.7129284,
				44.3355741
			]
		}
	]
}
