{
	"type": "FeatureCollection",
	"features": [
		{
			"type": "Feature",
			"properties": {
				"confidence": 9,
				"authenticationResultCode": "ValidCredentials",
				"brandLogoUri": "http://dev.virtualearth.net/Branding/logo_powered_by.png",
				"copyright": "Copyright © 2017 Microsoft and its suppliers. All rights reserved. This API cannot be accessed and the content and any results may not be used, reproduced or transmitted in any manner without express written permission from Microsoft Corporation.",
				"entityType": "Address",
				"matchCodes": [
					"Good"
				],
				"name": "3 Boulevard du Casino, Gatineau, QC J8Y 6X4, Canada",
				"statusCode": 200,
				"statusDescription": "OK",
				"traceId": "00d503ea21bc4cb3869e4ffe877f1635|BN20130442|7.7.0.0|",
				"addressLine": "3 Boulevard du Casino",
				"adminDistrict": "QC",
				"adminDistrict2": "Gatineau",
				"countryRegion": "Canada",
				"formattedAddress": "3 Boulevard du Casino, Gatineau, QC J8Y 6X4, Canada",
				"locality": "Gatineau",
				"neighborhood": "Hull",
				"postalCode": "J8Y 6X4"
			},
			"geometry": {
				"type": "Point",
				"coordinates": [
					-75.72847,
					45.44874
				]
			},
			"bbox": [
				-75.7300724,
				45.4476158,
				-75.7268676,
				45.4498642
			]
		}
	]
}
