{
	"type": "FeatureCollection",
	"features": [
		{
			"type": "Feature",
			"properties": {
				"confidence": 9,
				"authenticationResultCode": "ValidCredentials",
				"brandLogoUri": "http://dev.virtualearth.net/Branding/logo_powered_by.png",
				"copyright": "Copyright © 2017 Microsoft and its suppliers. All rights reserved. This API cannot be accessed and the content and any results may not be used, reproduced or transmitted in any manner without express written permission from Microsoft Corporation.",
				"entityType": "Address",
				"matchCodes": [
					"Good"
				],
				"name": "30 Nashville Ave, York, ON M6M 1J1, Canada",
				"statusCode": 200,
				"statusDescription": "OK",
				"traceId": "6facf762fedc4001b7eac37e4f787f94|BN20121763|7.7.0.0|",
				"addressLine": "30 Nashville Ave",
				"adminDistrict": "ON",
				"adminDistrict2": "Toronto",
				"countryRegion": "Canada",
				"formattedAddress": "30 Nashville Ave, York, ON M6M 1J1, Canada",
				"locality": "Toronto",
				"neighborhood": "Keelesdale-Eglinton West",
				"postalCode": "M6M 1J1"
			},
			"geometry": {
				"type": "Point",
				"coordinates": [
					-79.47704,
					43.68291
				]
			},
			"bbox": [
				-79.4785945,
				43.6817858,
				-79.4754855,
				43.6840342
			]
		}
	]
}
