{
	"type": "FeatureCollection",
	"features": [
		{
			"type": "Feature",
			"properties": {
				"confidence": 9,
				"authenticationResultCode": "ValidCredentials",
				"brandLogoUri": "http://dev.virtualearth.net/Branding/logo_powered_by.png",
				"copyright": "Copyright © 2017 Microsoft and its suppliers. All rights reserved. This API cannot be accessed and the content and any results may not be used, reproduced or transmitted in any manner without express written permission from Microsoft Corporation.",
				"entityType": "Address",
				"matchCodes": [
					"Good"
				],
				"name": "30 Rue Racine E, Chicoutimi, QC G7H 1P5, Canada",
				"statusCode": 200,
				"statusDescription": "OK",
				"traceId": "bef7a3d17d384dc29b68d3161f52834c|BN20250135|7.7.0.0|",
				"addressLine": "30 Rue Racine E",
				"adminDistrict": "QC",
				"adminDistrict2": "Saguenay",
				"countryRegion": "Canada",
				"formattedAddress": "30 Rue Racine E, Chicoutimi, QC G7H 1P5, Canada",
				"locality": "Saguenay",
				"neighborhood": "Chicoutimi",
				"postalCode": "G7H 1P5"
			},
			"geometry": {
				"type": "Point",
				"coordinates": [
					-71.06747,
					48.4277
				]
			},
			"bbox": [
				-71.0691641,
				48.4265758,
				-71.0657759,
				48.4288242
			]
		}
	]
}
