{
	"type": "FeatureCollection",
	"features": [
		{
			"type": "Feature",
			"properties": {
				"confidence": 9,
				"authenticationResultCode": "ValidCredentials",
				"brandLogoUri": "http://dev.virtualearth.net/Branding/logo_powered_by.png",
				"copyright": "Copyright © 2017 Microsoft and its suppliers. All rights reserved. This API cannot be accessed and the content and any results may not be used, reproduced or transmitted in any manner without express written permission from Microsoft Corporation.",
				"entityType": "Address",
				"matchCodes": [
					"Good"
				],
				"name": "300 Rossland Rd E, Ajax, ON L1Z 0M1, Canada",
				"statusCode": 200,
				"statusDescription": "OK",
				"traceId": "545d25717c6c49349f76f0af9894ce07|BN20130632|7.7.0.0|",
				"addressLine": "300 Rossland Rd E",
				"adminDistrict": "ON",
				"adminDistrict2": "Durham",
				"countryRegion": "Canada",
				"formattedAddress": "300 Rossland Rd E, Ajax, ON L1Z 0M1, Canada",
				"locality": "Ajax",
				"postalCode": "L1Z 0M1"
			},
			"geometry": {
				"type": "Point",
				"coordinates": [
					-79.0184699,
					43.88244
				]
			},
			"bbox": [
				-79.0200296,
				43.8813158,
				-79.0169102,
				43.8835642
			]
		}
	]
}
