{
	"type": "FeatureCollection",
	"features": [
		{
			"type": "Feature",
			"properties": {
				"confidence": 9,
				"authenticationResultCode": "ValidCredentials",
				"brandLogoUri": "http://dev.virtualearth.net/Branding/logo_powered_by.png",
				"copyright": "Copyright © 2017 Microsoft and its suppliers. All rights reserved. This API cannot be accessed and the content and any results may not be used, reproduced or transmitted in any manner without express written permission from Microsoft Corporation.",
				"entityType": "Address",
				"matchCodes": [
					"Good"
				],
				"name": "30075 Downes Rd, Abbotsford, BC V4X 1Z8, Canada",
				"statusCode": 200,
				"statusDescription": "OK",
				"traceId": "6ddc51da2c944afbbd6da7451f56b6d2|BN20240253|7.7.0.0|",
				"addressLine": "30075 Downes Rd",
				"adminDistrict": "BC",
				"adminDistrict2": "Fraser Valley",
				"countryRegion": "Canada",
				"formattedAddress": "30075 Downes Rd, Abbotsford, BC V4X 1Z8, Canada",
				"locality": "Abbotsford",
				"neighborhood": "Bradner-Mt Lehman",
				"postalCode": "V4X 1Z8"
			},
			"geometry": {
				"type": "Point",
				"coordinates": [
					-122.3900549,
					49.0751468
				]
			},
			"bbox": [
				-122.391771,
				49.0740226,
				-122.3883388,
				49.0762709
			]
		}
	]
}
