{
	"type": "FeatureCollection",
	"features": [
		{
			"type": "Feature",
			"properties": {
				"confidence": 9,
				"authenticationResultCode": "ValidCredentials",
				"brandLogoUri": "http://dev.virtualearth.net/Branding/logo_powered_by.png",
				"copyright": "Copyright © 2017 Microsoft and its suppliers. All rights reserved. This API cannot be accessed and the content and any results may not be used, reproduced or transmitted in any manner without express written permission from Microsoft Corporation.",
				"entityType": "Address",
				"matchCodes": [
					"Good"
				],
				"name": "3015 57 Ave SE, Calgary, AB T2C 0B2, Canada",
				"statusCode": 200,
				"statusDescription": "OK",
				"traceId": "5d7f76eb63634580a631d7748d5fa744|BN20171457|7.7.0.0|",
				"addressLine": "3015 57 Ave SE",
				"adminDistrict": "AB",
				"adminDistrict2": "Alberta",
				"countryRegion": "Canada",
				"formattedAddress": "3015 57 Ave SE, Calgary, AB T2C 0B2, Canada",
				"locality": "Calgary",
				"neighborhood": "Foothills",
				"postalCode": "T2C 0B2"
			},
			"geometry": {
				"type": "Point",
				"coordinates": [
					-113.99278,
					51.00326
				]
			},
			"bbox": [
				-113.9945664,
				51.0021358,
				-113.9909936,
				51.0043842
			]
		}
	]
}
