{
	"type": "FeatureCollection",
	"features": [
		{
			"type": "Feature",
			"properties": {
				"confidence": 9,
				"authenticationResultCode": "ValidCredentials",
				"brandLogoUri": "http://dev.virtualearth.net/Branding/logo_powered_by.png",
				"copyright": "Copyright © 2017 Microsoft and its suppliers. All rights reserved. This API cannot be accessed and the content and any results may not be used, reproduced or transmitted in any manner without express written permission from Microsoft Corporation.",
				"entityType": "Address",
				"matchCodes": [
					"Good"
				],
				"name": "3015 Boulevard Tessier, Laval, QC H7S 2M1, Canada",
				"statusCode": 200,
				"statusDescription": "OK",
				"traceId": "33631d3e624f4f2c98646c7e6d678982|BN20121763|7.7.0.0|",
				"addressLine": "3015 Boulevard Tessier",
				"adminDistrict": "QC",
				"adminDistrict2": "Laval",
				"countryRegion": "Canada",
				"formattedAddress": "3015 Boulevard Tessier, Laval, QC H7S 2M1, Canada",
				"locality": "Laval",
				"postalCode": "H7S 2M1"
			},
			"geometry": {
				"type": "Point",
				"coordinates": [
					-73.74059,
					45.5700999
				]
			},
			"bbox": [
				-73.7421958,
				45.5689757,
				-73.7389842,
				45.5712241
			]
		}
	]
}
