{
	"type": "FeatureCollection",
	"features": [
		{
			"type": "Feature",
			"properties": {
				"confidence": 7,
				"authenticationResultCode": "ValidCredentials",
				"brandLogoUri": "http://dev.virtualearth.net/Branding/logo_powered_by.png",
				"copyright": "Copyright © 2017 Microsoft and its suppliers. All rights reserved. This API cannot be accessed and the content and any results may not be used, reproduced or transmitted in any manner without express written permission from Microsoft Corporation.",
				"entityType": "Postcode1",
				"matchCodes": [
					"UpHierarchy"
				],
				"name": "Chauvin, T0B 0V0, Canada",
				"statusCode": 200,
				"statusDescription": "OK",
				"traceId": "63f986349510469aa3aa38aa3e083ad5|BN20300154|7.7.0.0|",
				"adminDistrict": "AB",
				"countryRegion": "Canada",
				"formattedAddress": "Chauvin, T0B 0V0, Canada",
				"locality": "Chauvin",
				"postalCode": "T0B 0V0"
			},
			"geometry": {
				"type": "Point",
				"coordinates": [
					-110.142112731934,
					52.697639465332
				]
			},
			"bbox": [
				-110.150610511623,
				52.6937767477614,
				-110.133614952244,
				52.7015021829027
			]
		}
	]
}
