{
	"type": "FeatureCollection",
	"features": [
		{
			"type": "Feature",
			"properties": {
				"confidence": 9,
				"authenticationResultCode": "ValidCredentials",
				"brandLogoUri": "http://dev.virtualearth.net/Branding/logo_powered_by.png",
				"copyright": "Copyright © 2017 Microsoft and its suppliers. All rights reserved. This API cannot be accessed and the content and any results may not be used, reproduced or transmitted in any manner without express written permission from Microsoft Corporation.",
				"entityType": "Address",
				"matchCodes": [
					"Good"
				],
				"name": "303 Nantucket Blvd, Scarborough, ON M1P 2P2, Canada",
				"statusCode": 200,
				"statusDescription": "OK",
				"traceId": "4005e650a3b547f597785bebe9e98055|BN20130431|7.7.0.0|",
				"addressLine": "303 Nantucket Blvd",
				"adminDistrict": "ON",
				"adminDistrict2": "Toronto",
				"countryRegion": "Canada",
				"formattedAddress": "303 Nantucket Blvd, Scarborough, ON M1P 2P2, Canada",
				"locality": "Toronto",
				"neighborhood": "Dorset Park",
				"postalCode": "M1P 2P2"
			},
			"geometry": {
				"type": "Point",
				"coordinates": [
					-79.27576,
					43.76176
				]
			},
			"bbox": [
				-79.2773165,
				43.7606358,
				-79.2742035,
				43.7628842
			]
		}
	]
}
