{
	"type": "FeatureCollection",
	"features": [
		{
			"type": "Feature",
			"properties": {
				"confidence": 9,
				"authenticationResultCode": "ValidCredentials",
				"brandLogoUri": "http://dev.virtualearth.net/Branding/logo_powered_by.png",
				"copyright": "Copyright © 2017 Microsoft and its suppliers. All rights reserved. This API cannot be accessed and the content and any results may not be used, reproduced or transmitted in any manner without express written permission from Microsoft Corporation.",
				"entityType": "Address",
				"matchCodes": [
					"Good"
				],
				"name": "3035 Ross Rd, Nanaimo, BC V9T 5S8, Canada",
				"statusCode": 200,
				"statusDescription": "OK",
				"traceId": "ae13f03b78ec400ca256dc28a9fd9b6e|BN20130423|7.7.0.0|",
				"addressLine": "3035 Ross Rd",
				"adminDistrict": "BC",
				"adminDistrict2": "Nanaimo",
				"countryRegion": "Canada",
				"formattedAddress": "3035 Ross Rd, Nanaimo, BC V9T 5S8, Canada",
				"locality": "Nanaimo",
				"postalCode": "V9T 5S8"
			},
			"geometry": {
				"type": "Point",
				"coordinates": [
					-124.00665,
					49.20776
				]
			},
			"bbox": [
				-124.0083707,
				49.2066358,
				-124.0049293,
				49.2088842
			]
		}
	]
}
