{
	"type": "FeatureCollection",
	"features": [
		{
			"type": "Feature",
			"properties": {
				"confidence": 9,
				"authenticationResultCode": "ValidCredentials",
				"brandLogoUri": "http://dev.virtualearth.net/Branding/logo_powered_by.png",
				"copyright": "Copyright © 2017 Microsoft and its suppliers. All rights reserved. This API cannot be accessed and the content and any results may not be used, reproduced or transmitted in any manner without express written permission from Microsoft Corporation.",
				"entityType": "Address",
				"matchCodes": [
					"Good"
				],
				"name": "304 78 Ave NE, Calgary, AB T2K 0R6, Canada",
				"statusCode": 200,
				"statusDescription": "OK",
				"traceId": "12ab051e29454d6cac07ff6a80286686|BN20280152|7.7.0.0|",
				"addressLine": "304 78 Ave NE",
				"adminDistrict": "AB",
				"adminDistrict2": "Alberta",
				"countryRegion": "Canada",
				"formattedAddress": "304 78 Ave NE, Calgary, AB T2K 0R6, Canada",
				"locality": "Calgary",
				"neighborhood": "Huntington Hills",
				"postalCode": "T2K 0R6"
			},
			"geometry": {
				"type": "Point",
				"coordinates": [
					-114.06485,
					51.1215199
				]
			},
			"bbox": [
				-114.066641,
				51.1203957,
				-114.063059,
				51.1226441
			]
		}
	]
}
