{
	"type": "FeatureCollection",
	"features": [
		{
			"type": "Feature",
			"properties": {
				"confidence": 9,
				"authenticationResultCode": "ValidCredentials",
				"brandLogoUri": "http://dev.virtualearth.net/Branding/logo_powered_by.png",
				"copyright": "Copyright © 2017 Microsoft and its suppliers. All rights reserved. This API cannot be accessed and the content and any results may not be used, reproduced or transmitted in any manner without express written permission from Microsoft Corporation.",
				"entityType": "Address",
				"matchCodes": [
					"Good"
				],
				"name": "305 Rue Papineau, Joliette, QC J6E 2K8, Canada",
				"statusCode": 200,
				"statusDescription": "OK",
				"traceId": "a97284b108964de19e2bd7e15423cccd|BN20260231|7.7.0.0|",
				"addressLine": "305 Rue Papineau",
				"adminDistrict": "QC",
				"adminDistrict2": "Joliette",
				"countryRegion": "Canada",
				"formattedAddress": "305 Rue Papineau, Joliette, QC J6E 2K8, Canada",
				"locality": "Joliette",
				"postalCode": "J6E 2K8"
			},
			"geometry": {
				"type": "Point",
				"coordinates": [
					-73.44651,
					46.0327399
				]
			},
			"bbox": [
				-73.4481292,
				46.0316157,
				-73.4448908,
				46.0338641
			]
		}
	]
}
