{
	"type": "FeatureCollection",
	"features": [
		{
			"type": "Feature",
			"properties": {
				"confidence": 9,
				"authenticationResultCode": "ValidCredentials",
				"brandLogoUri": "http://dev.virtualearth.net/Branding/logo_powered_by.png",
				"copyright": "Copyright © 2017 Microsoft and its suppliers. All rights reserved. This API cannot be accessed and the content and any results may not be used, reproduced or transmitted in any manner without express written permission from Microsoft Corporation.",
				"entityType": "Address",
				"matchCodes": [
					"Good"
				],
				"name": "30552 Progressive Way, Abbotsford, BC V2T 6W3, Canada",
				"statusCode": 200,
				"statusDescription": "OK",
				"traceId": "cd8b54a683a246768e36147769701787|BN20290118|7.7.0.0|",
				"addressLine": "30552 Progressive Way",
				"adminDistrict": "BC",
				"adminDistrict2": "Fraser Valley",
				"countryRegion": "Canada",
				"formattedAddress": "30552 Progressive Way, Abbotsford, BC V2T 6W3, Canada",
				"locality": "Abbotsford",
				"neighborhood": "South Poplar",
				"postalCode": "V2T 6W3"
			},
			"geometry": {
				"type": "Point",
				"coordinates": [
					-122.37713,
					49.04815
				]
			},
			"bbox": [
				-122.3788452,
				49.0470258,
				-122.3754148,
				49.0492742
			]
		}
	]
}
