{
	"type": "FeatureCollection",
	"features": [
		{
			"type": "Feature",
			"properties": {
				"confidence": 9,
				"authenticationResultCode": "ValidCredentials",
				"brandLogoUri": "http://dev.virtualearth.net/Branding/logo_powered_by.png",
				"copyright": "Copyright © 2017 Microsoft and its suppliers. All rights reserved. This API cannot be accessed and the content and any results may not be used, reproduced or transmitted in any manner without express written permission from Microsoft Corporation.",
				"entityType": "Address",
				"matchCodes": [
					"Good"
				],
				"name": "307 Cundles Rd E, Barrie, ON L4M 0G9, Canada",
				"statusCode": 200,
				"statusDescription": "OK",
				"traceId": "42d2f986375c4e39a50a0de75e2e3337|BN20130719|7.7.0.0|",
				"addressLine": "307 Cundles Rd E",
				"adminDistrict": "ON",
				"adminDistrict2": "Simcoe",
				"countryRegion": "Canada",
				"formattedAddress": "307 Cundles Rd E, Barrie, ON L4M 0G9, Canada",
				"locality": "Barrie",
				"neighborhood": "Alliance",
				"postalCode": "L4M 0G9"
			},
			"geometry": {
				"type": "Point",
				"coordinates": [
					-79.6809271,
					44.4148887
				]
			},
			"bbox": [
				-79.6825009,
				44.4137646,
				-79.6793533,
				44.4160129
			]
		}
	]
}
