{
	"type": "FeatureCollection",
	"features": [
		{
			"type": "Feature",
			"properties": {
				"confidence": 9,
				"authenticationResultCode": "ValidCredentials",
				"brandLogoUri": "http://dev.virtualearth.net/Branding/logo_powered_by.png",
				"copyright": "Copyright © 2017 Microsoft and its suppliers. All rights reserved. This API cannot be accessed and the content and any results may not be used, reproduced or transmitted in any manner without express written permission from Microsoft Corporation.",
				"entityType": "Address",
				"matchCodes": [
					"Good"
				],
				"name": "308 Springborough Way SW, Calgary, AB T3H 5M7, Canada",
				"statusCode": 200,
				"statusDescription": "OK",
				"traceId": "8cb58ced6e9947218b205b5ff4318991|BN20130631|7.7.0.0|",
				"addressLine": "308 Springborough Way SW",
				"adminDistrict": "AB",
				"adminDistrict2": "Alberta",
				"countryRegion": "Canada",
				"formattedAddress": "308 Springborough Way SW, Calgary, AB T3H 5M7, Canada",
				"locality": "Calgary",
				"neighborhood": "Springbank Hill",
				"postalCode": "T3H 5M7"
			},
			"geometry": {
				"type": "Point",
				"coordinates": [
					-114.19063,
					51.03319
				]
			},
			"bbox": [
				-114.1924176,
				51.0320658,
				-114.1888424,
				51.0343142
			]
		}
	]
}
