{
	"type": "FeatureCollection",
	"features": [
		{
			"type": "Feature",
			"properties": {
				"confidence": 9,
				"authenticationResultCode": "ValidCredentials",
				"brandLogoUri": "http://dev.virtualearth.net/Branding/logo_powered_by.png",
				"copyright": "Copyright © 2017 Microsoft and its suppliers. All rights reserved. This API cannot be accessed and the content and any results may not be used, reproduced or transmitted in any manner without express written permission from Microsoft Corporation.",
				"entityType": "Address",
				"matchCodes": [
					"Good"
				],
				"name": "309 1st St, Irricana, AB T0M, Canada",
				"statusCode": 200,
				"statusDescription": "OK",
				"traceId": "12d1625c7c4c4388ab59e031680ffcbf|BN20220145|7.7.0.0|",
				"addressLine": "309 1st St",
				"adminDistrict": "AB",
				"adminDistrict2": "Alberta",
				"countryRegion": "Canada",
				"formattedAddress": "309 1st St, Irricana, AB T0M, Canada",
				"locality": "Irricana",
				"postalCode": "T0M 1B0"
			},
			"geometry": {
				"type": "Point",
				"coordinates": [
					-113.60533,
					51.32262
				]
			},
			"bbox": [
				-113.6071288,
				51.3214958,
				-113.6035312,
				51.3237442
			]
		}
	]
}
