{
	"type": "FeatureCollection",
	"features": [
		{
			"type": "Feature",
			"properties": {
				"confidence": 9,
				"authenticationResultCode": "ValidCredentials",
				"brandLogoUri": "http://dev.virtualearth.net/Branding/logo_powered_by.png",
				"copyright": "Copyright © 2017 Microsoft and its suppliers. All rights reserved. This API cannot be accessed and the content and any results may not be used, reproduced or transmitted in any manner without express written permission from Microsoft Corporation.",
				"entityType": "Address",
				"matchCodes": [
					"Good"
				],
				"name": "31 Carmody Ln, Uxbridge, ON L9P 1A5, Canada",
				"statusCode": 200,
				"statusDescription": "OK",
				"traceId": "dbaa5f110b3444389f54fe322bfa1d43|BN20300154|7.7.0.0|",
				"addressLine": "31 Carmody Ln",
				"adminDistrict": "ON",
				"adminDistrict2": "Durham",
				"countryRegion": "Canada",
				"formattedAddress": "31 Carmody Ln, Uxbridge, ON L9P 1A5, Canada",
				"locality": "Uxbridge",
				"postalCode": "L9P 1A5"
			},
			"geometry": {
				"type": "Point",
				"coordinates": [
					-79.13546,
					44.11084
				]
			},
			"bbox": [
				-79.1370257,
				44.1097158,
				-79.1338943,
				44.1119642
			]
		}
	]
}
