{
	"type": "FeatureCollection",
	"features": [
		{
			"type": "Feature",
			"properties": {
				"confidence": 9,
				"authenticationResultCode": "ValidCredentials",
				"brandLogoUri": "http://dev.virtualearth.net/Branding/logo_powered_by.png",
				"copyright": "Copyright © 2017 Microsoft and its suppliers. All rights reserved. This API cannot be accessed and the content and any results may not be used, reproduced or transmitted in any manner without express written permission from Microsoft Corporation.",
				"entityType": "Address",
				"matchCodes": [
					"Good"
				],
				"name": "31 Macey Ave, Scarborough, ON M1L 2T6, Canada",
				"statusCode": 200,
				"statusDescription": "OK",
				"traceId": "d8364408fe1a439c81482bc272f33a9c|BN20121763|7.7.0.0|",
				"addressLine": "31 Macey Ave",
				"adminDistrict": "ON",
				"adminDistrict2": "Toronto",
				"countryRegion": "Canada",
				"formattedAddress": "31 Macey Ave, Scarborough, ON M1L 2T6, Canada",
				"locality": "Toronto",
				"neighborhood": "Oakridge",
				"postalCode": "M1L 2T6"
			},
			"geometry": {
				"type": "Point",
				"coordinates": [
					-79.28693,
					43.69321
				]
			},
			"bbox": [
				-79.2884847,
				43.6920858,
				-79.2853753,
				43.6943342
			]
		}
	]
}
