{
	"type": "FeatureCollection",
	"features": [
		{
			"type": "Feature",
			"properties": {
				"confidence": 9,
				"authenticationResultCode": "ValidCredentials",
				"brandLogoUri": "http://dev.virtualearth.net/Branding/logo_powered_by.png",
				"copyright": "Copyright © 2017 Microsoft and its suppliers. All rights reserved. This API cannot be accessed and the content and any results may not be used, reproduced or transmitted in any manner without express written permission from Microsoft Corporation.",
				"entityType": "Address",
				"matchCodes": [
					"Good"
				],
				"name": "31 Rue Nove-Mesto, Cantley, QC J8V 3B2, Canada",
				"statusCode": 200,
				"statusDescription": "OK",
				"traceId": "cba1f6f037504d539b40721cc90b7e8d|BN20290118|7.7.0.0|",
				"addressLine": "31 Rue Nove-Mesto",
				"adminDistrict": "QC",
				"adminDistrict2": "Les Collines-de-l'Outaouais",
				"countryRegion": "Canada",
				"formattedAddress": "31 Rue Nove-Mesto, Cantley, QC J8V 3B2, Canada",
				"locality": "Cantley",
				"postalCode": "J8V 3B2"
			},
			"geometry": {
				"type": "Point",
				"coordinates": [
					-75.84698,
					45.60797
				]
			},
			"bbox": [
				-75.8485869,
				45.6068458,
				-75.8453731,
				45.6090942
			]
		}
	]
}
