{
	"type": "FeatureCollection",
	"features": [
		{
			"type": "Feature",
			"properties": {
				"confidence": 9,
				"authenticationResultCode": "ValidCredentials",
				"brandLogoUri": "http://dev.virtualearth.net/Branding/logo_powered_by.png",
				"copyright": "Copyright © 2017 Microsoft and its suppliers. All rights reserved. This API cannot be accessed and the content and any results may not be used, reproduced or transmitted in any manner without express written permission from Microsoft Corporation.",
				"entityType": "Address",
				"matchCodes": [
					"Good"
				],
				"name": "31 Pennsylvania Ave, Concord, ON L4K 5V5, Canada",
				"statusCode": 200,
				"statusDescription": "OK",
				"traceId": "6f240f99e2ad4888884d1983155828b7|BN20290118|7.7.0.0|",
				"addressLine": "31 Pennsylvania Ave",
				"adminDistrict": "ON",
				"adminDistrict2": "York",
				"countryRegion": "Canada",
				"formattedAddress": "31 Pennsylvania Ave, Concord, ON L4K 5V5, Canada",
				"locality": "Vaughan",
				"neighborhood": "Concord",
				"postalCode": "L4K 5V5"
			},
			"geometry": {
				"type": "Point",
				"coordinates": [
					-79.52743,
					43.80228
				]
			},
			"bbox": [
				-79.5289876,
				43.8011558,
				-79.5258724,
				43.8034042
			]
		}
	]
}
