{
	"type": "FeatureCollection",
	"features": [
		{
			"type": "Feature",
			"properties": {
				"confidence": 9,
				"authenticationResultCode": "ValidCredentials",
				"brandLogoUri": "http://dev.virtualearth.net/Branding/logo_powered_by.png",
				"copyright": "Copyright © 2017 Microsoft and its suppliers. All rights reserved. This API cannot be accessed and the content and any results may not be used, reproduced or transmitted in any manner without express written permission from Microsoft Corporation.",
				"entityType": "Address",
				"matchCodes": [
					"Good"
				],
				"name": "310 Hunt Club Rd, Ottawa, ON K1V 1C1, Canada",
				"statusCode": 200,
				"statusDescription": "OK",
				"traceId": "1335fdf0612041a98453a4041f93f118|BN20121764|7.7.0.0|",
				"addressLine": "310 Hunt Club Rd",
				"adminDistrict": "ON",
				"adminDistrict2": "Ottawa",
				"countryRegion": "Canada",
				"formattedAddress": "310 Hunt Club Rd, Ottawa, ON K1V 1C1, Canada",
				"locality": "Ottawa",
				"neighborhood": "Hunt Club-Ottawa Airport",
				"postalCode": "K1V 1C1"
			},
			"geometry": {
				"type": "Point",
				"coordinates": [
					-75.68526,
					45.33759
				]
			},
			"bbox": [
				-75.6868592,
				45.3364658,
				-75.6836608,
				45.3387142
			]
		}
	]
}
