{
	"type": "FeatureCollection",
	"features": [
		{
			"type": "Feature",
			"properties": {
				"confidence": 9,
				"authenticationResultCode": "ValidCredentials",
				"brandLogoUri": "http://dev.virtualearth.net/Branding/logo_powered_by.png",
				"copyright": "Copyright © 2017 Microsoft and its suppliers. All rights reserved. This API cannot be accessed and the content and any results may not be used, reproduced or transmitted in any manner without express written permission from Microsoft Corporation.",
				"entityType": "Address",
				"matchCodes": [
					"Good"
				],
				"name": "3100 Boulevard Mascouche, Mascouche, QC J7K, Canada",
				"statusCode": 200,
				"statusDescription": "OK",
				"traceId": "eeb45b555ea04782a596c63c9f9b2c86|BN20130625|7.7.0.0|",
				"addressLine": "3100 Boulevard Mascouche",
				"adminDistrict": "QC",
				"adminDistrict2": "Les Moulins",
				"countryRegion": "Canada",
				"formattedAddress": "3100 Boulevard Mascouche, Mascouche, QC J7K, Canada",
				"locality": "Mascouche",
				"postalCode": "J7K 1Y4"
			},
			"geometry": {
				"type": "Point",
				"coordinates": [
					-73.59947,
					45.74204
				]
			},
			"bbox": [
				-73.6010808,
				45.7409158,
				-73.5978592,
				45.7431642
			]
		}
	]
}
