{
	"type": "FeatureCollection",
	"features": [
		{
			"type": "Feature",
			"properties": {
				"confidence": 9,
				"authenticationResultCode": "ValidCredentials",
				"brandLogoUri": "http://dev.virtualearth.net/Branding/logo_powered_by.png",
				"copyright": "Copyright © 2017 Microsoft and its suppliers. All rights reserved. This API cannot be accessed and the content and any results may not be used, reproduced or transmitted in any manner without express written permission from Microsoft Corporation.",
				"entityType": "Address",
				"matchCodes": [
					"Good"
				],
				"name": "3100 Pasqua St, Regina, SK S4S, Canada",
				"statusCode": 200,
				"statusDescription": "OK",
				"traceId": "db61ef5c7ffb44418f74577f87c94720|BN20130631|7.7.0.0|",
				"addressLine": "3100 Pasqua St",
				"adminDistrict": "SK",
				"adminDistrict2": "Saskatchewan",
				"countryRegion": "Canada",
				"formattedAddress": "3100 Pasqua St, Regina, SK S4S, Canada",
				"locality": "Regina",
				"neighborhood": "Lakeview",
				"postalCode": "S4S"
			},
			"geometry": {
				"type": "Point",
				"coordinates": [
					-104.63882,
					50.42822
				]
			},
			"bbox": [
				-104.6405846,
				50.4270958,
				-104.6370554,
				50.4293442
			]
		}
	]
}
