{
	"type": "FeatureCollection",
	"features": [
		{
			"type": "Feature",
			"properties": {
				"confidence": 9,
				"authenticationResultCode": "ValidCredentials",
				"brandLogoUri": "http://dev.virtualearth.net/Branding/logo_powered_by.png",
				"copyright": "Copyright © 2017 Microsoft and its suppliers. All rights reserved. This API cannot be accessed and the content and any results may not be used, reproduced or transmitted in any manner without express written permission from Microsoft Corporation.",
				"entityType": "Address",
				"matchCodes": [
					"Good"
				],
				"name": "31192 S Fraser Way, Abbotsford, BC V2T 6L5, Canada",
				"statusCode": 200,
				"statusDescription": "OK",
				"traceId": "4edb86363afa49a79a7c8cca53eee676|BN20130442|7.7.0.0|",
				"addressLine": "31192 S Fraser Way",
				"adminDistrict": "BC",
				"adminDistrict2": "Fraser Valley",
				"countryRegion": "Canada",
				"formattedAddress": "31192 S Fraser Way, Abbotsford, BC V2T 6L5, Canada",
				"locality": "Abbotsford",
				"neighborhood": "South Poplar",
				"postalCode": "V2T 6L5"
			},
			"geometry": {
				"type": "Point",
				"coordinates": [
					-122.3605334,
					49.048113
				]
			},
			"bbox": [
				-122.3622486,
				49.0469888,
				-122.3588183,
				49.0492371
			]
		}
	]
}
