{
	"type": "FeatureCollection",
	"features": [
		{
			"type": "Feature",
			"properties": {
				"confidence": 9,
				"authenticationResultCode": "ValidCredentials",
				"brandLogoUri": "http://dev.virtualearth.net/Branding/logo_powered_by.png",
				"copyright": "Copyright © 2017 Microsoft and its suppliers. All rights reserved. This API cannot be accessed and the content and any results may not be used, reproduced or transmitted in any manner without express written permission from Microsoft Corporation.",
				"entityType": "Address",
				"matchCodes": [
					"Good"
				],
				"name": "3121 Channel Blvd, Chemainus, BC V0R 1K2, Canada",
				"statusCode": 200,
				"statusDescription": "OK",
				"traceId": "345cad615e0a4f7398beafc9ef4221c9|BN20260231|7.7.0.0|",
				"addressLine": "3121 Channel Blvd",
				"adminDistrict": "BC",
				"adminDistrict2": "Cowichan Valley",
				"countryRegion": "Canada",
				"formattedAddress": "3121 Channel Blvd, Chemainus, BC V0R 1K2, Canada",
				"locality": "North Cowichan",
				"neighborhood": "Chemainus",
				"postalCode": "V0R 1K2"
			},
			"geometry": {
				"type": "Point",
				"coordinates": [
					-123.73189,
					48.92649
				]
			},
			"bbox": [
				-123.733601,
				48.9253658,
				-123.730179,
				48.9276142
			]
		}
	]
}
