{
	"type": "FeatureCollection",
	"features": [
		{
			"type": "Feature",
			"properties": {
				"confidence": 9,
				"authenticationResultCode": "ValidCredentials",
				"brandLogoUri": "http://dev.virtualearth.net/Branding/logo_powered_by.png",
				"copyright": "Copyright © 2017 Microsoft and its suppliers. All rights reserved. This API cannot be accessed and the content and any results may not be used, reproduced or transmitted in any manner without express written permission from Microsoft Corporation.",
				"entityType": "Address",
				"matchCodes": [
					"Good"
				],
				"name": "317 Noorduyn Pk, Rocky View County, AB T3Z, Canada",
				"statusCode": 200,
				"statusDescription": "OK",
				"traceId": "dc9a56ade8c547c09c9bb6c7ee405fd2|BN20190642|7.7.0.0|",
				"addressLine": "317 Noorduyn Pk",
				"adminDistrict": "AB",
				"adminDistrict2": "Alberta",
				"countryRegion": "Canada",
				"formattedAddress": "317 Noorduyn Pk, Rocky View County, AB T3Z, Canada",
				"locality": "Rocky View County",
				"neighborhood": "Calgary",
				"postalCode": "T3Z 3S7"
			},
			"geometry": {
				"type": "Point",
				"coordinates": [
					-114.3706549,
					51.09771
				]
			},
			"bbox": [
				-114.372445,
				51.0965859,
				-114.3688648,
				51.0988342
			]
		}
	]
}
