{
	"type": "FeatureCollection",
	"features": [
		{
			"type": "Feature",
			"properties": {
				"confidence": 9,
				"authenticationResultCode": "ValidCredentials",
				"brandLogoUri": "http://dev.virtualearth.net/Branding/logo_powered_by.png",
				"copyright": "Copyright © 2017 Microsoft and its suppliers. All rights reserved. This API cannot be accessed and the content and any results may not be used, reproduced or transmitted in any manner without express written permission from Microsoft Corporation.",
				"entityType": "Address",
				"matchCodes": [
					"Good"
				],
				"name": "318 Red Head Dr, Kings, PE C0A, Canada",
				"statusCode": 200,
				"statusDescription": "OK",
				"traceId": "efb31b4dff124adfa2d81f4c2738bf65|BN20320521|7.7.0.0|",
				"addressLine": "318 Red Head Dr",
				"adminDistrict": "PE",
				"adminDistrict2": "Kings",
				"countryRegion": "Canada",
				"formattedAddress": "318 Red Head Dr, Kings, PE C0A, Canada",
				"locality": "Kings",
				"neighborhood": "Morell",
				"postalCode": "C0A 1S0"
			},
			"geometry": {
				"type": "Point",
				"coordinates": [
					-62.71181,
					46.42948
				]
			},
			"bbox": [
				-62.713441,
				46.4283558,
				-62.710179,
				46.4306042
			]
		}
	]
}
