{
	"type": "FeatureCollection",
	"features": [
		{
			"type": "Feature",
			"properties": {
				"confidence": 9,
				"authenticationResultCode": "ValidCredentials",
				"brandLogoUri": "http://dev.virtualearth.net/Branding/logo_powered_by.png",
				"copyright": "Copyright © 2017 Microsoft and its suppliers. All rights reserved. This API cannot be accessed and the content and any results may not be used, reproduced or transmitted in any manner without express written permission from Microsoft Corporation.",
				"entityType": "Address",
				"matchCodes": [
					"Good"
				],
				"name": "319 Wood Valley Bay SW, Calgary, AB T2W 5Y5, Canada",
				"statusCode": 200,
				"statusDescription": "OK",
				"traceId": "22cbe8aaf91b498c9c2f50a851795711|BN20121762|7.7.0.0|",
				"addressLine": "319 Wood Valley Bay SW",
				"adminDistrict": "AB",
				"adminDistrict2": "Alberta",
				"countryRegion": "Canada",
				"formattedAddress": "319 Wood Valley Bay SW, Calgary, AB T2W 5Y5, Canada",
				"locality": "Calgary",
				"neighborhood": "Woodbine",
				"postalCode": "T2W 5Y5"
			},
			"geometry": {
				"type": "Point",
				"coordinates": [
					-114.13886,
					50.93817
				]
			},
			"bbox": [
				-114.1406439,
				50.9370458,
				-114.1370761,
				50.9392942
			]
		}
	]
}
