{
	"type": "FeatureCollection",
	"features": [
		{
			"type": "Feature",
			"properties": {
				"confidence": 9,
				"authenticationResultCode": "ValidCredentials",
				"brandLogoUri": "http://dev.virtualearth.net/Branding/logo_powered_by.png",
				"copyright": "Copyright © 2017 Microsoft and its suppliers. All rights reserved. This API cannot be accessed and the content and any results may not be used, reproduced or transmitted in any manner without express written permission from Microsoft Corporation.",
				"entityType": "Address",
				"matchCodes": [
					"Good"
				],
				"name": "3199 Boulevard Talbot, Chicoutimi, QC G7H 5B1, Canada",
				"statusCode": 200,
				"statusDescription": "OK",
				"traceId": "8251ecf2255f408c947490d8999a6d40|BN20130521|7.7.0.0|",
				"addressLine": "3199 Boulevard Talbot",
				"adminDistrict": "QC",
				"adminDistrict2": "Saguenay",
				"countryRegion": "Canada",
				"formattedAddress": "3199 Boulevard Talbot, Chicoutimi, QC G7H 5B1, Canada",
				"locality": "Saguenay",
				"neighborhood": "Chicoutimi",
				"postalCode": "G7H 5B1"
			},
			"geometry": {
				"type": "Point",
				"coordinates": [
					-71.09625,
					48.3690799
				]
			},
			"bbox": [
				-71.0979422,
				48.3679557,
				-71.0945578,
				48.3702041
			]
		}
	]
}
