{
	"type": "FeatureCollection",
	"features": [
		{
			"type": "Feature",
			"properties": {
				"confidence": 9,
				"authenticationResultCode": "ValidCredentials",
				"brandLogoUri": "http://dev.virtualearth.net/Branding/logo_powered_by.png",
				"copyright": "Copyright © 2017 Microsoft and its suppliers. All rights reserved. This API cannot be accessed and the content and any results may not be used, reproduced or transmitted in any manner without express written permission from Microsoft Corporation.",
				"entityType": "Address",
				"matchCodes": [
					"Good"
				],
				"name": "3206 Orlando Dr, Mississauga, ON L4V 1R5, Canada",
				"statusCode": 200,
				"statusDescription": "OK",
				"traceId": "d58739b7f4aa49128952adab8ff9866f|BN20130719|7.7.0.0|",
				"addressLine": "3206 Orlando Dr",
				"adminDistrict": "ON",
				"adminDistrict2": "Peel",
				"countryRegion": "Canada",
				"formattedAddress": "3206 Orlando Dr, Mississauga, ON L4V 1R5, Canada",
				"locality": "Mississauga",
				"neighborhood": "Malton",
				"postalCode": "L4V 1R5"
			},
			"geometry": {
				"type": "Point",
				"coordinates": [
					-79.62526,
					43.69893
				]
			},
			"bbox": [
				-79.6268149,
				43.6978058,
				-79.6237051,
				43.7000542
			]
		}
	]
}
