{
	"type": "FeatureCollection",
	"features": [
		{
			"type": "Feature",
			"properties": {
				"confidence": 9,
				"authenticationResultCode": "ValidCredentials",
				"brandLogoUri": "http://dev.virtualearth.net/Branding/logo_powered_by.png",
				"copyright": "Copyright © 2017 Microsoft and its suppliers. All rights reserved. This API cannot be accessed and the content and any results may not be used, reproduced or transmitted in any manner without express written permission from Microsoft Corporation.",
				"entityType": "Address",
				"matchCodes": [
					"Good"
				],
				"name": "321 Consortium Ct, London, ON N6E 2S8, Canada",
				"statusCode": 200,
				"statusDescription": "OK",
				"traceId": "1ae105870d1d4bec9c88ec3a084512dd|CO30275938|7.7.0.0|",
				"addressLine": "321 Consortium Ct",
				"adminDistrict": "ON",
				"adminDistrict2": "Middlesex",
				"countryRegion": "Canada",
				"formattedAddress": "321 Consortium Ct, London, ON N6E 2S8, Canada",
				"locality": "London",
				"neighborhood": "Westminster",
				"postalCode": "N6E 2S8"
			},
			"geometry": {
				"type": "Point",
				"coordinates": [
					-81.2047,
					42.9322
				]
			},
			"bbox": [
				-81.2062354,
				42.9310758,
				-81.2031646,
				42.9333242
			]
		}
	]
}
