{
	"type": "FeatureCollection",
	"features": [
		{
			"type": "Feature",
			"properties": {
				"confidence": 9,
				"authenticationResultCode": "ValidCredentials",
				"brandLogoUri": "http://dev.virtualearth.net/Branding/logo_powered_by.png",
				"copyright": "Copyright © 2017 Microsoft and its suppliers. All rights reserved. This API cannot be accessed and the content and any results may not be used, reproduced or transmitted in any manner without express written permission from Microsoft Corporation.",
				"entityType": "Address",
				"matchCodes": [
					"Good"
				],
				"name": "325 HWY-105, Maugerville, NB E3A 8P1, Canada",
				"statusCode": 200,
				"statusDescription": "OK",
				"traceId": "59cba1f73159414098f0fe418933655c|BN20130625|7.7.0.0|",
				"addressLine": "325 HWY-105",
				"adminDistrict": "NB",
				"adminDistrict2": "Sunbury",
				"countryRegion": "Canada",
				"formattedAddress": "325 HWY-105, Maugerville, NB E3A 8P1, Canada",
				"locality": "Maugerville",
				"postalCode": "E3A 8P1"
			},
			"geometry": {
				"type": "Point",
				"coordinates": [
					-66.5581134,
					45.9105904
				]
			},
			"bbox": [
				-66.559729,
				45.9094663,
				-66.5564977,
				45.9117146
			]
		}
	]
}
