{
	"type": "FeatureCollection",
	"features": [
		{
			"type": "Feature",
			"properties": {
				"confidence": 9,
				"authenticationResultCode": "ValidCredentials",
				"brandLogoUri": "http://dev.virtualearth.net/Branding/logo_powered_by.png",
				"copyright": "Copyright © 2017 Microsoft and its suppliers. All rights reserved. This API cannot be accessed and the content and any results may not be used, reproduced or transmitted in any manner without express written permission from Microsoft Corporation.",
				"entityType": "Address",
				"matchCodes": [
					"Good"
				],
				"name": "32585 S Fraser Way, Abbotsford, BC V2T 1X8, Canada",
				"statusCode": 200,
				"statusDescription": "OK",
				"traceId": "3182e2507c2d4725b1c321b9639fd5fe|BN20260223|7.7.0.0|",
				"addressLine": "32585 S Fraser Way",
				"adminDistrict": "BC",
				"adminDistrict2": "Fraser Valley",
				"countryRegion": "Canada",
				"formattedAddress": "32585 S Fraser Way, Abbotsford, BC V2T 1X8, Canada",
				"locality": "Abbotsford",
				"neighborhood": "Clearbrook",
				"postalCode": "V2T 1X8"
			},
			"geometry": {
				"type": "Point",
				"coordinates": [
					-122.32115,
					49.05155
				]
			},
			"bbox": [
				-122.3228653,
				49.0504258,
				-122.3194347,
				49.0526742
			]
		}
	]
}
