{
	"type": "FeatureCollection",
	"features": [
		{
			"type": "Feature",
			"properties": {
				"confidence": 9,
				"authenticationResultCode": "ValidCredentials",
				"brandLogoUri": "http://dev.virtualearth.net/Branding/logo_powered_by.png",
				"copyright": "Copyright © 2017 Microsoft and its suppliers. All rights reserved. This API cannot be accessed and the content and any results may not be used, reproduced or transmitted in any manner without express written permission from Microsoft Corporation.",
				"entityType": "Address",
				"matchCodes": [
					"Good"
				],
				"name": "3264 Mainway, Burlington, ON L7M 1A7, Canada",
				"statusCode": 200,
				"statusDescription": "OK",
				"traceId": "2e397132e1be4d85a50f29a5971364be|BN20130532|7.7.0.0|",
				"addressLine": "3264 Mainway",
				"adminDistrict": "ON",
				"adminDistrict2": "Halton",
				"countryRegion": "Canada",
				"formattedAddress": "3264 Mainway, Burlington, ON L7M 1A7, Canada",
				"locality": "Burlington",
				"neighborhood": "Palmer",
				"postalCode": "L7M 1A7"
			},
			"geometry": {
				"type": "Point",
				"coordinates": [
					-79.8024499,
					43.36433
				]
			},
			"bbox": [
				-79.8039962,
				43.3632058,
				-79.8009036,
				43.3654542
			]
		}
	]
}
