{
	"type": "FeatureCollection",
	"features": [
		{
			"type": "Feature",
			"properties": {
				"confidence": 9,
				"authenticationResultCode": "ValidCredentials",
				"brandLogoUri": "http://dev.virtualearth.net/Branding/logo_powered_by.png",
				"copyright": "Copyright © 2017 Microsoft and its suppliers. All rights reserved. This API cannot be accessed and the content and any results may not be used, reproduced or transmitted in any manner without express written permission from Microsoft Corporation.",
				"entityType": "Address",
				"matchCodes": [
					"Good"
				],
				"name": "3287 Cook St, Chemainus, BC V0R 1K2, Canada",
				"statusCode": 200,
				"statusDescription": "OK",
				"traceId": "38a14ab5d2dd4973961beb93579087f1|BN20210145|7.7.0.0|",
				"addressLine": "3287 Cook St",
				"adminDistrict": "BC",
				"adminDistrict2": "Cowichan Valley",
				"countryRegion": "Canada",
				"formattedAddress": "3287 Cook St, Chemainus, BC V0R 1K2, Canada",
				"locality": "North Cowichan",
				"neighborhood": "Chemainus",
				"postalCode": "V0R 1K2"
			},
			"geometry": {
				"type": "Point",
				"coordinates": [
					-123.7389938,
					48.9311932
				]
			},
			"bbox": [
				-123.7407049,
				48.930069,
				-123.7372827,
				48.9323174
			]
		}
	]
}
