{
	"type": "FeatureCollection",
	"features": [
		{
			"type": "Feature",
			"properties": {
				"confidence": 9,
				"authenticationResultCode": "ValidCredentials",
				"brandLogoUri": "http://dev.virtualearth.net/Branding/logo_powered_by.png",
				"copyright": "Copyright © 2017 Microsoft and its suppliers. All rights reserved. This API cannot be accessed and the content and any results may not be used, reproduced or transmitted in any manner without express written permission from Microsoft Corporation.",
				"entityType": "Address",
				"matchCodes": [
					"Good"
				],
				"name": "33 Billingham Rd, Etobicoke, ON M9B 3X2, Canada",
				"statusCode": 200,
				"statusDescription": "OK",
				"traceId": "5dc416949cfc4404b32d2ea2ca4d41a0|BN20130530|7.7.0.0|",
				"addressLine": "33 Billingham Rd",
				"adminDistrict": "ON",
				"adminDistrict2": "Toronto",
				"countryRegion": "Canada",
				"formattedAddress": "33 Billingham Rd, Etobicoke, ON M9B 3X2, Canada",
				"locality": "Toronto",
				"neighborhood": "Islington-City Centre West",
				"postalCode": "M9B 3X2"
			},
			"geometry": {
				"type": "Point",
				"coordinates": [
					-79.54991,
					43.63304
				]
			},
			"bbox": [
				-79.5514632,
				43.6319158,
				-79.5483568,
				43.6341642
			]
		}
	]
}
