{
	"type": "FeatureCollection",
	"features": [
		{
			"type": "Feature",
			"properties": {
				"confidence": 9,
				"authenticationResultCode": "ValidCredentials",
				"brandLogoUri": "http://dev.virtualearth.net/Branding/logo_powered_by.png",
				"copyright": "Copyright © 2017 Microsoft and its suppliers. All rights reserved. This API cannot be accessed and the content and any results may not be used, reproduced or transmitted in any manner without express written permission from Microsoft Corporation.",
				"entityType": "Address",
				"matchCodes": [
					"Good"
				],
				"name": "33 York St W, Elora, ON N0B 1S0, Canada",
				"statusCode": 200,
				"statusDescription": "OK",
				"traceId": "76d0eae706af44adbed3dfc88753a1f6|BN20240423|7.7.0.0|",
				"addressLine": "33 York St W",
				"adminDistrict": "ON",
				"adminDistrict2": "Wellington",
				"countryRegion": "Canada",
				"formattedAddress": "33 York St W, Elora, ON N0B 1S0, Canada",
				"locality": "Centre Wellington",
				"neighborhood": "Elora",
				"postalCode": "N0B 1S0"
			},
			"geometry": {
				"type": "Point",
				"coordinates": [
					-80.4259639,
					43.6771253
				]
			},
			"bbox": [
				-80.4275182,
				43.6760012,
				-80.4244096,
				43.6782495
			]
		}
	]
}
