{
	"type": "FeatureCollection",
	"features": [
		{
			"type": "Feature",
			"properties": {
				"confidence": 9,
				"authenticationResultCode": "ValidCredentials",
				"brandLogoUri": "http://dev.virtualearth.net/Branding/logo_powered_by.png",
				"copyright": "Copyright © 2017 Microsoft and its suppliers. All rights reserved. This API cannot be accessed and the content and any results may not be used, reproduced or transmitted in any manner without express written permission from Microsoft Corporation.",
				"entityType": "Address",
				"matchCodes": [
					"Good"
				],
				"name": "3310 Mainway, Burlington, ON L7M 1A7, Canada",
				"statusCode": 200,
				"statusDescription": "OK",
				"traceId": "aa5b345aa7874fd2a2227bd591cbc7da|BN20300154|7.7.0.0|",
				"addressLine": "3310 Mainway",
				"adminDistrict": "ON",
				"adminDistrict2": "Halton",
				"countryRegion": "Canada",
				"formattedAddress": "3310 Mainway, Burlington, ON L7M 1A7, Canada",
				"locality": "Burlington",
				"neighborhood": "Palmer",
				"postalCode": "L7M 1A7"
			},
			"geometry": {
				"type": "Point",
				"coordinates": [
					-79.80108,
					43.36569
				]
			},
			"bbox": [
				-79.8026263,
				43.3645658,
				-79.7995337,
				43.3668142
			]
		}
	]
}
