{
	"type": "FeatureCollection",
	"features": [
		{
			"type": "Feature",
			"properties": {
				"confidence": 9,
				"authenticationResultCode": "ValidCredentials",
				"brandLogoUri": "http://dev.virtualearth.net/Branding/logo_powered_by.png",
				"copyright": "Copyright © 2017 Microsoft and its suppliers. All rights reserved. This API cannot be accessed and the content and any results may not be used, reproduced or transmitted in any manner without express written permission from Microsoft Corporation.",
				"entityType": "Address",
				"matchCodes": [
					"Good"
				],
				"name": "332 Industrial Ave, Truro, NS B2N 6V7, Canada",
				"statusCode": 200,
				"statusDescription": "OK",
				"traceId": "bb0f615c8fe6426594c2114ba0382d48|BN20290118|7.7.0.0|",
				"addressLine": "332 Industrial Ave",
				"adminDistrict": "NS",
				"adminDistrict2": "Colchester",
				"countryRegion": "Canada",
				"formattedAddress": "332 Industrial Ave, Truro, NS B2N 6V7, Canada",
				"locality": "Truro",
				"postalCode": "B2N 6V7"
			},
			"geometry": {
				"type": "Point",
				"coordinates": [
					-63.28734,
					45.34299
				]
			},
			"bbox": [
				-63.2889394,
				45.3418658,
				-63.2857406,
				45.3441142
			]
		}
	]
}
