{
	"type": "FeatureCollection",
	"features": [
		{
			"type": "Feature",
			"properties": {
				"confidence": 9,
				"authenticationResultCode": "ValidCredentials",
				"brandLogoUri": "http://dev.virtualearth.net/Branding/logo_powered_by.png",
				"copyright": "Copyright © 2017 Microsoft and its suppliers. All rights reserved. This API cannot be accessed and the content and any results may not be used, reproduced or transmitted in any manner without express written permission from Microsoft Corporation.",
				"entityType": "Address",
				"matchCodes": [
					"Good"
				],
				"name": "332 Sovereign Rd, London, ON N6M 1A8, Canada",
				"statusCode": 200,
				"statusDescription": "OK",
				"traceId": "087cb45697664444b957d06f223b23c8|CO30305304|7.7.0.0|",
				"addressLine": "332 Sovereign Rd",
				"adminDistrict": "ON",
				"adminDistrict2": "Middlesex",
				"countryRegion": "Canada",
				"formattedAddress": "332 Sovereign Rd, London, ON N6M 1A8, Canada",
				"locality": "London",
				"neighborhood": "Crumlin",
				"postalCode": "N6M 1A8"
			},
			"geometry": {
				"type": "Point",
				"coordinates": [
					-81.1393,
					42.9903
				]
			},
			"bbox": [
				-81.1408368,
				42.9891758,
				-81.1377632,
				42.9914242
			]
		}
	]
}
