{
	"type": "FeatureCollection",
	"features": [
		{
			"type": "Feature",
			"properties": {
				"confidence": 9,
				"authenticationResultCode": "ValidCredentials",
				"brandLogoUri": "http://dev.virtualearth.net/Branding/logo_powered_by.png",
				"copyright": "Copyright © 2017 Microsoft and its suppliers. All rights reserved. This API cannot be accessed and the content and any results may not be used, reproduced or transmitted in any manner without express written permission from Microsoft Corporation.",
				"entityType": "Address",
				"matchCodes": [
					"Good"
				],
				"name": "333 King St W, Oshawa, ON L1J 2J8, Canada",
				"statusCode": 200,
				"statusDescription": "OK",
				"traceId": "8202f5cbb8fb4bf89d8d55ea84aeaca4|BN20130431|7.7.0.0|",
				"addressLine": "333 King St W",
				"adminDistrict": "ON",
				"adminDistrict2": "Durham",
				"countryRegion": "Canada",
				"formattedAddress": "333 King St W, Oshawa, ON L1J 2J8, Canada",
				"locality": "Oshawa",
				"neighborhood": "Vanier",
				"postalCode": "L1J 2J8"
			},
			"geometry": {
				"type": "Point",
				"coordinates": [
					-78.87564,
					43.89431
				]
			},
			"bbox": [
				-78.8772,
				43.8931858,
				-78.87408,
				43.8954342
			]
		}
	]
}
