{
	"type": "FeatureCollection",
	"features": [
		{
			"type": "Feature",
			"properties": {
				"confidence": 9,
				"authenticationResultCode": "ValidCredentials",
				"brandLogoUri": "http://dev.virtualearth.net/Branding/logo_powered_by.png",
				"copyright": "Copyright © 2017 Microsoft and its suppliers. All rights reserved. This API cannot be accessed and the content and any results may not be used, reproduced or transmitted in any manner without express written permission from Microsoft Corporation.",
				"entityType": "Address",
				"matchCodes": [
					"Good"
				],
				"name": "33496 S Fraser Way, Abbotsford, BC V2S 2B5, Canada",
				"statusCode": 200,
				"statusDescription": "OK",
				"traceId": "26238f040e594f5891594640cc946b2d|BN20130522|7.7.0.0|",
				"addressLine": "33496 S Fraser Way",
				"adminDistrict": "BC",
				"adminDistrict2": "Fraser Valley",
				"countryRegion": "Canada",
				"formattedAddress": "33496 S Fraser Way, Abbotsford, BC V2S 2B5, Canada",
				"locality": "Abbotsford",
				"neighborhood": "Mill Lake",
				"postalCode": "V2S 2B5"
			},
			"geometry": {
				"type": "Point",
				"coordinates": [
					-122.29622,
					49.04916
				]
			},
			"bbox": [
				-122.2979352,
				49.0480358,
				-122.2945048,
				49.0502842
			]
		}
	]
}
