{
	"type": "FeatureCollection",
	"features": [
		{
			"type": "Feature",
			"properties": {
				"confidence": 9,
				"authenticationResultCode": "ValidCredentials",
				"brandLogoUri": "http://dev.virtualearth.net/Branding/logo_powered_by.png",
				"copyright": "Copyright © 2017 Microsoft and its suppliers. All rights reserved. This API cannot be accessed and the content and any results may not be used, reproduced or transmitted in any manner without express written permission from Microsoft Corporation.",
				"entityType": "Address",
				"matchCodes": [
					"Good"
				],
				"name": "335 Connie Cres, Concord, ON L4K 5R2, Canada",
				"statusCode": 200,
				"statusDescription": "OK",
				"traceId": "0c67e79e9b1d46ca9af91d2a4c96eda0|BN20130521|7.7.0.0|",
				"addressLine": "335 Connie Cres",
				"adminDistrict": "ON",
				"adminDistrict2": "York",
				"countryRegion": "Canada",
				"formattedAddress": "335 Connie Cres, Concord, ON L4K 5R2, Canada",
				"locality": "Vaughan",
				"neighborhood": "Concord",
				"postalCode": "L4K 5R2"
			},
			"geometry": {
				"type": "Point",
				"coordinates": [
					-79.4799,
					43.82024
				]
			},
			"bbox": [
				-79.481458,
				43.8191158,
				-79.478342,
				43.8213642
			]
		}
	]
}
