{
	"type": "FeatureCollection",
	"features": [
		{
			"type": "Feature",
			"properties": {
				"confidence": 9,
				"authenticationResultCode": "ValidCredentials",
				"brandLogoUri": "http://dev.virtualearth.net/Branding/logo_powered_by.png",
				"copyright": "Copyright © 2017 Microsoft and its suppliers. All rights reserved. This API cannot be accessed and the content and any results may not be used, reproduced or transmitted in any manner without express written permission from Microsoft Corporation.",
				"entityType": "Address",
				"matchCodes": [
					"Good"
				],
				"name": "336 Frost Ave, Ottawa, ON K1H 5J2, Canada",
				"statusCode": 200,
				"statusDescription": "OK",
				"traceId": "892f4d887ac945a094fc084de1960643|BN20130520|7.7.0.0|",
				"addressLine": "336 Frost Ave",
				"adminDistrict": "ON",
				"adminDistrict2": "Ottawa",
				"countryRegion": "Canada",
				"formattedAddress": "336 Frost Ave, Ottawa, ON K1H 5J2, Canada",
				"locality": "Ottawa",
				"neighborhood": "Billings Bridge-Alta Vista",
				"postalCode": "K1H 5J2"
			},
			"geometry": {
				"type": "Point",
				"coordinates": [
					-75.65783,
					45.39523
				]
			},
			"bbox": [
				-75.6594309,
				45.3941058,
				-75.6562291,
				45.3963542
			]
		}
	]
}
