{
	"type": "FeatureCollection",
	"features": [
		{
			"type": "Feature",
			"properties": {
				"confidence": 9,
				"authenticationResultCode": "ValidCredentials",
				"brandLogoUri": "http://dev.virtualearth.net/Branding/logo_powered_by.png",
				"copyright": "Copyright © 2017 Microsoft and its suppliers. All rights reserved. This API cannot be accessed and the content and any results may not be used, reproduced or transmitted in any manner without express written permission from Microsoft Corporation.",
				"entityType": "Address",
				"matchCodes": [
					"Good"
				],
				"name": "3371 Richmond St, Richmond, BC V7E 2V9, Canada",
				"statusCode": 200,
				"statusDescription": "OK",
				"traceId": "a3d2acc98c2e420eafa22876a55c0795|BN20290118|7.7.0.0|",
				"addressLine": "3371 Richmond St",
				"adminDistrict": "BC",
				"adminDistrict2": "Greater Vancouver",
				"countryRegion": "Canada",
				"formattedAddress": "3371 Richmond St, Richmond, BC V7E 2V9, Canada",
				"locality": "Richmond",
				"neighborhood": "Steveston",
				"postalCode": "V7E 2V9"
			},
			"geometry": {
				"type": "Point",
				"coordinates": [
					-123.18815,
					49.12863
				]
			},
			"bbox": [
				-123.1898679,
				49.1275058,
				-123.1864321,
				49.1297542
			]
		}
	]
}
