{
	"type": "FeatureCollection",
	"features": [
		{
			"type": "Feature",
			"properties": {
				"confidence": 7,
				"authenticationResultCode": "ValidCredentials",
				"brandLogoUri": "http://dev.virtualearth.net/Branding/logo_powered_by.png",
				"copyright": "Copyright © 2017 Microsoft and its suppliers. All rights reserved. This API cannot be accessed and the content and any results may not be used, reproduced or transmitted in any manner without express written permission from Microsoft Corporation.",
				"entityType": "Postcode1",
				"matchCodes": [
					"UpHierarchy"
				],
				"name": "Regina, S4P 3R9, Canada",
				"statusCode": 200,
				"statusDescription": "OK",
				"traceId": "f047987863344306a3c0382fc21c1946|BN20130521|7.7.0.0|",
				"adminDistrict": "SK",
				"countryRegion": "Canada",
				"formattedAddress": "Regina, S4P 3R9, Canada",
				"locality": "Regina",
				"postalCode": "S4P 3R9"
			},
			"geometry": {
				"type": "Point",
				"coordinates": [
					-104.595169067383,
					50.4482498168945
				]
			},
			"bbox": [
				-104.603256493118,
				50.4443870993239,
				-104.587081641647,
				50.4521125344652
			]
		}
	]
}
