{
	"type": "FeatureCollection",
	"features": [
		{
			"type": "Feature",
			"properties": {
				"confidence": 9,
				"authenticationResultCode": "ValidCredentials",
				"brandLogoUri": "http://dev.virtualearth.net/Branding/logo_powered_by.png",
				"copyright": "Copyright © 2017 Microsoft and its suppliers. All rights reserved. This API cannot be accessed and the content and any results may not be used, reproduced or transmitted in any manner without express written permission from Microsoft Corporation.",
				"entityType": "Address",
				"matchCodes": [
					"Good"
				],
				"name": "3392 Concession Road 8, Orono, ON L0B 1M0, Canada",
				"statusCode": 200,
				"statusDescription": "OK",
				"traceId": "0eb4b32b5d6545d88caa2fed07bec559|BN20121762|7.7.0.0|",
				"addressLine": "3392 Concession Road 8",
				"adminDistrict": "ON",
				"adminDistrict2": "Durham",
				"countryRegion": "Canada",
				"formattedAddress": "3392 Concession Road 8, Orono, ON L0B 1M0, Canada",
				"locality": "Clarington",
				"neighborhood": "Orono",
				"postalCode": "L0B 1M0"
			},
			"geometry": {
				"type": "Point",
				"coordinates": [
					-78.6482438,
					44.0235498
				]
			},
			"bbox": [
				-78.6498072,
				44.0224256,
				-78.6466804,
				44.0246739
			]
		}
	]
}
