{
	"type": "FeatureCollection",
	"features": [
		{
			"type": "Feature",
			"properties": {
				"confidence": 1,
				"authenticationResultCode": "ValidCredentials",
				"brandLogoUri": "http://dev.virtualearth.net/Branding/logo_powered_by.png",
				"copyright": "Copyright © 2017 Microsoft and its suppliers. All rights reserved. This API cannot be accessed and the content and any results may not be used, reproduced or transmitted in any manner without express written permission from Microsoft Corporation.",
				"entityType": "Postcode2",
				"matchCodes": [
					"Ambiguous",
					"UpHierarchy"
				],
				"name": "Guelph, N1H, Canada",
				"statusCode": 200,
				"statusDescription": "OK",
				"traceId": "08a27dc329024a018c1dd45d7b75423f|BN20240253|7.7.0.0|",
				"adminDistrict": "ON",
				"adminDistrict2": "Wellington",
				"countryRegion": "Canada",
				"formattedAddress": "Guelph, N1H, Canada",
				"locality": "Guelph",
				"postalCode": "N1H"
			},
			"geometry": {
				"type": "Point",
				"coordinates": [
					-80.1813507080078,
					43.5710334777832
				]
			},
			"bbox": [
				-80.3740615844727,
				43.4471893310547,
				-80.1005020141602,
				43.7055397033691
			]
		},
		{
			"type": "Feature",
			"properties": {
				"confidence": 7,
				"authenticationResultCode": "ValidCredentials",
				"brandLogoUri": "http://dev.virtualearth.net/Branding/logo_powered_by.png",
				"copyright": "Copyright © 2017 Microsoft and its suppliers. All rights reserved. This API cannot be accessed and the content and any results may not be used, reproduced or transmitted in any manner without express written permission from Microsoft Corporation.",
				"entityType": "Postcode1",
				"matchCodes": [
					"UpHierarchy"
				],
				"name": "Puslinch, N1H 6H9, Canada",
				"statusCode": 200,
				"statusDescription": "OK",
				"traceId": "08a27dc329024a018c1dd45d7b75423f|BN20240253|7.7.0.0|",
				"adminDistrict": "ON",
				"adminDistrict2": "Wellington",
				"countryRegion": "Canada",
				"formattedAddress": "Puslinch, N1H 6H9, Canada",
				"locality": "Puslinch",
				"postalCode": "N1H 6H9"
			},
			"geometry": {
				"type": "Point",
				"coordinates": [
					-80.1403121948242,
					43.4815292358398
				]
			},
			"bbox": [
				-80.1474097520508,
				43.4776665182692,
				-80.1332146375976,
				43.4853919534105
			]
		},
		{
			"type": "Feature",
			"properties": {
				"confidence": 7,
				"authenticationResultCode": "ValidCredentials",
				"brandLogoUri": "http://dev.virtualearth.net/Branding/logo_powered_by.png",
				"copyright": "Copyright © 2017 Microsoft and its suppliers. All rights reserved. This API cannot be accessed and the content and any results may not be used, reproduced or transmitted in any manner without express written permission from Microsoft Corporation.",
				"entityType": "Neighborhood",
				"matchCodes": [
					"Ambiguous",
					"UpHierarchy"
				],
				"name": "Guelph, Puslinch, Ontario, Canada",
				"statusCode": 200,
				"statusDescription": "OK",
				"traceId": "08a27dc329024a018c1dd45d7b75423f|BN20240253|7.7.0.0|",
				"adminDistrict": "ON",
				"adminDistrict2": "Wellington",
				"countryRegion": "Canada",
				"formattedAddress": "Guelph, Puslinch, Ontario, Canada",
				"locality": "Puslinch",
				"neighborhood": "Guelph"
			},
			"geometry": {
				"type": "Point",
				"coordinates": [
					-80.1419982910156,
					43.4816017150879
				]
			},
			"bbox": [
				-80.1490958567558,
				43.4777389975172,
				-80.1349007252754,
				43.4854644326586
			]
		},
		{
			"type": "Feature",
			"properties": {
				"confidence": 7,
				"authenticationResultCode": "ValidCredentials",
				"brandLogoUri": "http://dev.virtualearth.net/Branding/logo_powered_by.png",
				"copyright": "Copyright © 2017 Microsoft and its suppliers. All rights reserved. This API cannot be accessed and the content and any results may not be used, reproduced or transmitted in any manner without express written permission from Microsoft Corporation.",
				"entityType": "Neighborhood",
				"matchCodes": [
					"Ambiguous",
					"UpHierarchy"
				],
				"name": "Guelph, Guelph, Ontario, Canada",
				"statusCode": 200,
				"statusDescription": "OK",
				"traceId": "08a27dc329024a018c1dd45d7b75423f|BN20240253|7.7.0.0|",
				"adminDistrict": "ON",
				"adminDistrict2": "Wellington",
				"countryRegion": "Canada",
				"formattedAddress": "Guelph, Guelph, Ontario, Canada",
				"locality": "Guelph",
				"neighborhood": "Guelph"
			},
			"geometry": {
				"type": "Point",
				"coordinates": [
					-80.3090972900391,
					43.5929985046387
				]
			},
			"bbox": [
				-80.3162079783366,
				43.589135787068,
				-80.3019866017415,
				43.5968612222093
			]
		}
	]
}
