{
	"type": "FeatureCollection",
	"features": [
		{
			"type": "Feature",
			"properties": {
				"confidence": 9,
				"authenticationResultCode": "ValidCredentials",
				"brandLogoUri": "http://dev.virtualearth.net/Branding/logo_powered_by.png",
				"copyright": "Copyright © 2017 Microsoft and its suppliers. All rights reserved. This API cannot be accessed and the content and any results may not be used, reproduced or transmitted in any manner without express written permission from Microsoft Corporation.",
				"entityType": "Address",
				"matchCodes": [
					"Good"
				],
				"name": "34 Main St, Carberry, MB R0K, Canada",
				"statusCode": 200,
				"statusDescription": "OK",
				"traceId": "15ffef74a35e4154977b82abb4a0884e|BN20260223|7.7.0.0|",
				"addressLine": "34 Main St",
				"adminDistrict": "MB",
				"adminDistrict2": "Manitoba",
				"countryRegion": "Canada",
				"formattedAddress": "34 Main St, Carberry, MB R0K, Canada",
				"locality": "Carberry",
				"postalCode": "R0K 0H0"
			},
			"geometry": {
				"type": "Point",
				"coordinates": [
					-99.3592306,
					49.8665106
				]
			},
			"bbox": [
				-99.3609747,
				49.8653864,
				-99.3574866,
				49.8676347
			]
		}
	]
}
