{
	"type": "FeatureCollection",
	"features": [
		{
			"type": "Feature",
			"properties": {
				"confidence": 9,
				"authenticationResultCode": "ValidCredentials",
				"brandLogoUri": "http://dev.virtualearth.net/Branding/logo_powered_by.png",
				"copyright": "Copyright © 2017 Microsoft and its suppliers. All rights reserved. This API cannot be accessed and the content and any results may not be used, reproduced or transmitted in any manner without express written permission from Microsoft Corporation.",
				"entityType": "Address",
				"matchCodes": [
					"Good"
				],
				"name": "3400 HWY-132, Scoudouc, NB E4P 3S8, Canada",
				"statusCode": 200,
				"statusDescription": "OK",
				"traceId": "38753c7d4169411a9584576480135a36|BN20130719|7.7.0.0|",
				"addressLine": "3400 HWY-132",
				"adminDistrict": "NB",
				"adminDistrict2": "Westmorland",
				"countryRegion": "Canada",
				"formattedAddress": "3400 HWY-132, Scoudouc, NB E4P 3S8, Canada",
				"locality": "Shediac Parish",
				"neighborhood": "Scoudouc",
				"postalCode": "E4P 3S8"
			},
			"geometry": {
				"type": "Point",
				"coordinates": [
					-64.5618461,
					46.1654371
				]
			},
			"bbox": [
				-64.5634693,
				46.164313,
				-64.560223,
				46.1665613
			]
		}
	]
}
