{
	"type": "FeatureCollection",
	"features": [
		{
			"type": "Feature",
			"properties": {
				"confidence": 9,
				"authenticationResultCode": "ValidCredentials",
				"brandLogoUri": "http://dev.virtualearth.net/Branding/logo_powered_by.png",
				"copyright": "Copyright © 2017 Microsoft and its suppliers. All rights reserved. This API cannot be accessed and the content and any results may not be used, reproduced or transmitted in any manner without express written permission from Microsoft Corporation.",
				"entityType": "Address",
				"matchCodes": [
					"Good"
				],
				"name": "341 9e Rue S, Thetford Mines, QC G6G 6R5, Canada",
				"statusCode": 200,
				"statusDescription": "OK",
				"traceId": "0bacf09c10014be4b683e98520605965|BN20260223|7.7.0.0|",
				"addressLine": "341 9e Rue S",
				"adminDistrict": "QC",
				"adminDistrict2": "Les Appalaches",
				"countryRegion": "Canada",
				"formattedAddress": "341 9e Rue S, Thetford Mines, QC G6G 6R5, Canada",
				"locality": "Thetford Mines",
				"postalCode": "G6G 6R5"
			},
			"geometry": {
				"type": "Point",
				"coordinates": [
					-71.27668,
					46.10152
				]
			},
			"bbox": [
				-71.2783013,
				46.1003958,
				-71.2750587,
				46.1026442
			]
		}
	]
}
