{
	"type": "FeatureCollection",
	"features": [
		{
			"type": "Feature",
			"properties": {
				"confidence": 9,
				"authenticationResultCode": "ValidCredentials",
				"brandLogoUri": "http://dev.virtualearth.net/Branding/logo_powered_by.png",
				"copyright": "Copyright © 2017 Microsoft and its suppliers. All rights reserved. This API cannot be accessed and the content and any results may not be used, reproduced or transmitted in any manner without express written permission from Microsoft Corporation.",
				"entityType": "Address",
				"matchCodes": [
					"Good"
				],
				"name": "3435 Landmark Rd, Burlington, ON L7M 1T4, Canada",
				"statusCode": 200,
				"statusDescription": "OK",
				"traceId": "6067719e473c480d8f1f50ac68ed33cd|BN20220145|7.7.0.0|",
				"addressLine": "3435 Landmark Rd",
				"adminDistrict": "ON",
				"adminDistrict2": "Halton",
				"countryRegion": "Canada",
				"formattedAddress": "3435 Landmark Rd, Burlington, ON L7M 1T4, Canada",
				"locality": "Burlington",
				"neighborhood": "Palmer",
				"postalCode": "L7M 1T4"
			},
			"geometry": {
				"type": "Point",
				"coordinates": [
					-79.79758,
					43.36759
				]
			},
			"bbox": [
				-79.7991264,
				43.3664658,
				-79.7960336,
				43.3687142
			]
		}
	]
}
