{
	"type": "FeatureCollection",
	"features": [
		{
			"type": "Feature",
			"properties": {
				"confidence": 9,
				"authenticationResultCode": "ValidCredentials",
				"brandLogoUri": "http://dev.virtualearth.net/Branding/logo_powered_by.png",
				"copyright": "Copyright © 2017 Microsoft and its suppliers. All rights reserved. This API cannot be accessed and the content and any results may not be used, reproduced or transmitted in any manner without express written permission from Microsoft Corporation.",
				"entityType": "Address",
				"matchCodes": [
					"Good"
				],
				"name": "346 Yonge St, Toronto, ON M5B 1R8, Canada",
				"statusCode": 200,
				"statusDescription": "OK",
				"traceId": "84bef44125af4565bc41aa6979bf33e9|BN20130533|7.7.0.0|",
				"addressLine": "346 Yonge St",
				"adminDistrict": "ON",
				"adminDistrict2": "Toronto",
				"countryRegion": "Canada",
				"formattedAddress": "346 Yonge St, Toronto, ON M5B 1R8, Canada",
				"locality": "Toronto",
				"neighborhood": "Bay Street Corridor",
				"postalCode": "M5B 1R8"
			},
			"geometry": {
				"type": "Point",
				"coordinates": [
					-79.38167,
					43.65776
				]
			},
			"bbox": [
				-79.3832238,
				43.6566358,
				-79.3801162,
				43.6588842
			]
		}
	]
}
