{
	"type": "FeatureCollection",
	"features": [
		{
			"type": "Feature",
			"properties": {
				"confidence": 9,
				"authenticationResultCode": "ValidCredentials",
				"brandLogoUri": "http://dev.virtualearth.net/Branding/logo_powered_by.png",
				"copyright": "Copyright © 2017 Microsoft and its suppliers. All rights reserved. This API cannot be accessed and the content and any results may not be used, reproduced or transmitted in any manner without express written permission from Microsoft Corporation.",
				"entityType": "Address",
				"matchCodes": [
					"Good"
				],
				"name": "3480 Rue du Renard, Sherbrooke, QC J1E, Canada",
				"statusCode": 200,
				"statusDescription": "OK",
				"traceId": "f19ec7425feb4dc2b535e40e81d93c1e|BN20130631|7.7.0.0|",
				"addressLine": "3480 Rue du Renard",
				"adminDistrict": "QC",
				"adminDistrict2": "Sherbrooke",
				"countryRegion": "Canada",
				"formattedAddress": "3480 Rue du Renard, Sherbrooke, QC J1E, Canada",
				"locality": "Sherbrooke",
				"neighborhood": "Fleurimont",
				"postalCode": "J1E"
			},
			"geometry": {
				"type": "Point",
				"coordinates": [
					-71.84109,
					45.45038
				]
			},
			"bbox": [
				-71.8426924,
				45.4492558,
				-71.8394876,
				45.4515042
			]
		}
	]
}
