{
	"type": "FeatureCollection",
	"features": [
		{
			"type": "Feature",
			"properties": {
				"confidence": 9,
				"authenticationResultCode": "ValidCredentials",
				"brandLogoUri": "http://dev.virtualearth.net/Branding/logo_powered_by.png",
				"copyright": "Copyright © 2017 Microsoft and its suppliers. All rights reserved. This API cannot be accessed and the content and any results may not be used, reproduced or transmitted in any manner without express written permission from Microsoft Corporation.",
				"entityType": "Address",
				"matchCodes": [
					"Good"
				],
				"name": "349 Mooney Ave, Thunder Bay, ON P7B 5L5, Canada",
				"statusCode": 200,
				"statusDescription": "OK",
				"traceId": "f3dd4bedb6b94782986c367945ce725e|BN20200137|7.7.0.0|",
				"addressLine": "349 Mooney Ave",
				"adminDistrict": "ON",
				"adminDistrict2": "Thunder Bay",
				"countryRegion": "Canada",
				"formattedAddress": "349 Mooney Ave, Thunder Bay, ON P7B 5L5, Canada",
				"locality": "Thunder Bay",
				"postalCode": "P7B 5L5"
			},
			"geometry": {
				"type": "Point",
				"coordinates": [
					-89.23596,
					48.40776
				]
			},
			"bbox": [
				-89.2376534,
				48.4066358,
				-89.2342666,
				48.4088842
			]
		}
	]
}
