{
	"type": "FeatureCollection",
	"features": [
		{
			"type": "Feature",
			"properties": {
				"confidence": 9,
				"authenticationResultCode": "ValidCredentials",
				"brandLogoUri": "http://dev.virtualearth.net/Branding/logo_powered_by.png",
				"copyright": "Copyright © 2017 Microsoft and its suppliers. All rights reserved. This API cannot be accessed and the content and any results may not be used, reproduced or transmitted in any manner without express written permission from Microsoft Corporation.",
				"entityType": "Address",
				"matchCodes": [
					"Good"
				],
				"name": "35 Church St, Stoney Creek, ON L8E 2X7, Canada",
				"statusCode": 200,
				"statusDescription": "OK",
				"traceId": "972ce48f13474ac480fbc99fcd6a3252|BN20190653|7.7.0.0|",
				"addressLine": "35 Church St",
				"adminDistrict": "ON",
				"adminDistrict2": "Hamilton",
				"countryRegion": "Canada",
				"formattedAddress": "35 Church St, Stoney Creek, ON L8E 2X7, Canada",
				"locality": "Hamilton",
				"neighborhood": "Stoney Creek",
				"postalCode": "L8E 2X7"
			},
			"geometry": {
				"type": "Point",
				"coordinates": [
					-79.7262499,
					43.2432
				]
			},
			"bbox": [
				-79.7277931,
				43.2420758,
				-79.7247067,
				43.2443242
			]
		}
	]
}
