{
	"type": "FeatureCollection",
	"features": [
		{
			"type": "Feature",
			"properties": {
				"confidence": 9,
				"authenticationResultCode": "ValidCredentials",
				"brandLogoUri": "http://dev.virtualearth.net/Branding/logo_powered_by.png",
				"copyright": "Copyright © 2017 Microsoft and its suppliers. All rights reserved. This API cannot be accessed and the content and any results may not be used, reproduced or transmitted in any manner without express written permission from Microsoft Corporation.",
				"entityType": "Address",
				"matchCodes": [
					"Good"
				],
				"name": "35 Shangarry Dr, Scarborough, ON M1R 1A5, Canada",
				"statusCode": 200,
				"statusDescription": "OK",
				"traceId": "409c60c761df442d957d9c1c4f0d2f8d|BN20320521|7.7.0.0|",
				"addressLine": "35 Shangarry Dr",
				"adminDistrict": "ON",
				"adminDistrict2": "Toronto",
				"countryRegion": "Canada",
				"formattedAddress": "35 Shangarry Dr, Scarborough, ON M1R 1A5, Canada",
				"locality": "Toronto",
				"neighborhood": "Wexford-Maryvale",
				"postalCode": "M1R 1A5"
			},
			"geometry": {
				"type": "Point",
				"coordinates": [
					-79.30388,
					43.73195
				]
			},
			"bbox": [
				-79.3054357,
				43.7308258,
				-79.3023243,
				43.7330742
			]
		}
	]
}
