{
	"type": "FeatureCollection",
	"features": [
		{
			"type": "Feature",
			"properties": {
				"confidence": 9,
				"authenticationResultCode": "ValidCredentials",
				"brandLogoUri": "http://dev.virtualearth.net/Branding/logo_powered_by.png",
				"copyright": "Copyright © 2017 Microsoft and its suppliers. All rights reserved. This API cannot be accessed and the content and any results may not be used, reproduced or transmitted in any manner without express written permission from Microsoft Corporation.",
				"entityType": "Address",
				"matchCodes": [
					"Good"
				],
				"name": "350 Rue des Entrepreneurs, Montmagny, QC G5V 4T1, Canada",
				"statusCode": 200,
				"statusDescription": "OK",
				"traceId": "d2622c9f8f0149a7813eef2a3e399a4c|BN20200239|7.7.0.0|",
				"addressLine": "350 Rue des Entrepreneurs",
				"adminDistrict": "QC",
				"adminDistrict2": "Montmagny",
				"countryRegion": "Canada",
				"formattedAddress": "350 Rue des Entrepreneurs, Montmagny, QC G5V 4T1, Canada",
				"locality": "Montmagny",
				"postalCode": "G5V 4T1"
			},
			"geometry": {
				"type": "Point",
				"coordinates": [
					-70.58524,
					46.96819
				]
			},
			"bbox": [
				-70.5868873,
				46.9670658,
				-70.5835927,
				46.9693142
			]
		}
	]
}
