{
	"type": "FeatureCollection",
	"features": [
		{
			"type": "Feature",
			"properties": {
				"confidence": 9,
				"authenticationResultCode": "ValidCredentials",
				"brandLogoUri": "http://dev.virtualearth.net/Branding/logo_powered_by.png",
				"copyright": "Copyright © 2017 Microsoft and its suppliers. All rights reserved. This API cannot be accessed and the content and any results may not be used, reproduced or transmitted in any manner without express written permission from Microsoft Corporation.",
				"entityType": "Address",
				"matchCodes": [
					"Good"
				],
				"name": "351 Chaparral Ravine Vw SE, Calgary, AB T2X 0A3, Canada",
				"statusCode": 200,
				"statusDescription": "OK",
				"traceId": "54c5ee4934f5468f9f99f5664b0f86eb|BN20130719|7.7.0.0|",
				"addressLine": "351 Chaparral Ravine Vw SE",
				"adminDistrict": "AB",
				"adminDistrict2": "Alberta",
				"countryRegion": "Canada",
				"formattedAddress": "351 Chaparral Ravine Vw SE, Calgary, AB T2X 0A3, Canada",
				"locality": "Calgary",
				"neighborhood": "Chaparral",
				"postalCode": "T2X 0A3"
			},
			"geometry": {
				"type": "Point",
				"coordinates": [
					-114.0242,
					50.88177
				]
			},
			"bbox": [
				-114.0259818,
				50.8806458,
				-114.0224182,
				50.8828942
			]
		}
	]
}
