{
	"type": "FeatureCollection",
	"features": [
		{
			"type": "Feature",
			"properties": {
				"confidence": 9,
				"authenticationResultCode": "ValidCredentials",
				"brandLogoUri": "http://dev.virtualearth.net/Branding/logo_powered_by.png",
				"copyright": "Copyright © 2017 Microsoft and its suppliers. All rights reserved. This API cannot be accessed and the content and any results may not be used, reproduced or transmitted in any manner without express written permission from Microsoft Corporation.",
				"entityType": "Address",
				"matchCodes": [
					"Good"
				],
				"name": "352 Bayly St W, Ajax, ON L1S 1P1, Canada",
				"statusCode": 200,
				"statusDescription": "OK",
				"traceId": "c3bf8f7cb611450986b8d3f15f516752|BN20160335|7.7.0.0|",
				"addressLine": "352 Bayly St W",
				"adminDistrict": "ON",
				"adminDistrict2": "Durham",
				"countryRegion": "Canada",
				"formattedAddress": "352 Bayly St W, Ajax, ON L1S 1P1, Canada",
				"locality": "Ajax",
				"postalCode": "L1S 1P1"
			},
			"geometry": {
				"type": "Point",
				"coordinates": [
					-79.0319761,
					43.8411127
				]
			},
			"bbox": [
				-79.0335347,
				43.8399886,
				-79.0304175,
				43.8422369
			]
		}
	]
}
