{
	"type": "FeatureCollection",
	"features": [
		{
			"type": "Feature",
			"properties": {
				"confidence": 9,
				"authenticationResultCode": "ValidCredentials",
				"brandLogoUri": "http://dev.virtualearth.net/Branding/logo_powered_by.png",
				"copyright": "Copyright © 2017 Microsoft and its suppliers. All rights reserved. This API cannot be accessed and the content and any results may not be used, reproduced or transmitted in any manner without express written permission from Microsoft Corporation.",
				"entityType": "Address",
				"matchCodes": [
					"Good"
				],
				"name": "3526 Lake Shore Blvd W, Etobicoke, ON M8W 1N6, Canada",
				"statusCode": 200,
				"statusDescription": "OK",
				"traceId": "fccdced5f78e4e3494024dfe19d3da93|BN20130521|7.7.0.0|",
				"addressLine": "3526 Lake Shore Blvd W",
				"adminDistrict": "ON",
				"adminDistrict2": "Toronto",
				"countryRegion": "Canada",
				"formattedAddress": "3526 Lake Shore Blvd W, Etobicoke, ON M8W 1N6, Canada",
				"locality": "Toronto",
				"neighborhood": "Long Branch",
				"postalCode": "M8W 1N6"
			},
			"geometry": {
				"type": "Point",
				"coordinates": [
					-79.53253,
					43.59569
				]
			},
			"bbox": [
				-79.5340822,
				43.5945658,
				-79.5309778,
				43.5968142
			]
		}
	]
}
