{
	"type": "FeatureCollection",
	"features": [
		{
			"type": "Feature",
			"properties": {
				"confidence": 9,
				"authenticationResultCode": "ValidCredentials",
				"brandLogoUri": "http://dev.virtualearth.net/Branding/logo_powered_by.png",
				"copyright": "Copyright © 2017 Microsoft and its suppliers. All rights reserved. This API cannot be accessed and the content and any results may not be used, reproduced or transmitted in any manner without express written permission from Microsoft Corporation.",
				"entityType": "Address",
				"matchCodes": [
					"Good"
				],
				"name": "3538 Wyman Cres, Gloucester, ON K1V 0Z1, Canada",
				"statusCode": 200,
				"statusDescription": "OK",
				"traceId": "17607266f9114a1598424cde74086562|BN20130422|7.7.0.0|",
				"addressLine": "3538 Wyman Cres",
				"adminDistrict": "ON",
				"adminDistrict2": "Ottawa",
				"countryRegion": "Canada",
				"formattedAddress": "3538 Wyman Cres, Gloucester, ON K1V 0Z1, Canada",
				"locality": "Ottawa",
				"neighborhood": "Gloucester",
				"postalCode": "K1V 0Z1"
			},
			"geometry": {
				"type": "Point",
				"coordinates": [
					-75.65786,
					45.34476
				]
			},
			"bbox": [
				-75.6594594,
				45.3436358,
				-75.6562606,
				45.3458842
			]
		}
	]
}
