{
	"type": "FeatureCollection",
	"features": [
		{
			"type": "Feature",
			"properties": {
				"confidence": 9,
				"authenticationResultCode": "ValidCredentials",
				"brandLogoUri": "http://dev.virtualearth.net/Branding/logo_powered_by.png",
				"copyright": "Copyright © 2017 Microsoft and its suppliers. All rights reserved. This API cannot be accessed and the content and any results may not be used, reproduced or transmitted in any manner without express written permission from Microsoft Corporation.",
				"entityType": "Address",
				"matchCodes": [
					"Good"
				],
				"name": "355 Michener Rd, Guelph, ON N1K 1E8, Canada",
				"statusCode": 200,
				"statusDescription": "OK",
				"traceId": "407812df2e7c47c090be28d412afc1ca|BN20160335|7.7.0.0|",
				"addressLine": "355 Michener Rd",
				"adminDistrict": "ON",
				"adminDistrict2": "Wellington",
				"countryRegion": "Canada",
				"formattedAddress": "355 Michener Rd, Guelph, ON N1K 1E8, Canada",
				"locality": "Guelph",
				"neighborhood": "Willow West/Sugarbush",
				"postalCode": "N1K 1E8"
			},
			"geometry": {
				"type": "Point",
				"coordinates": [
					-80.31582,
					43.53215
				]
			},
			"bbox": [
				-80.3173706,
				43.5310258,
				-80.3142694,
				43.5332742
			]
		}
	]
}
