{
	"type": "FeatureCollection",
	"features": [
		{
			"type": "Feature",
			"properties": {
				"confidence": 9,
				"authenticationResultCode": "ValidCredentials",
				"brandLogoUri": "http://dev.virtualearth.net/Branding/logo_powered_by.png",
				"copyright": "Copyright © 2017 Microsoft and its suppliers. All rights reserved. This API cannot be accessed and the content and any results may not be used, reproduced or transmitted in any manner without express written permission from Microsoft Corporation.",
				"entityType": "Address",
				"matchCodes": [
					"Good"
				],
				"name": "355 Rue des Merles, Boucherville, QC J4B 5Y5, Canada",
				"statusCode": 200,
				"statusDescription": "OK",
				"traceId": "35ed8af32fe841f583e0fca6c4c5dbf6|BN20260231|7.7.0.0|",
				"addressLine": "355 Rue des Merles",
				"adminDistrict": "QC",
				"adminDistrict2": "Longueuil",
				"countryRegion": "Canada",
				"formattedAddress": "355 Rue des Merles, Boucherville, QC J4B 5Y5, Canada",
				"locality": "Boucherville",
				"neighborhood": "La Broquerie",
				"postalCode": "J4B 5Y5"
			},
			"geometry": {
				"type": "Point",
				"coordinates": [
					-73.43291,
					45.58442
				]
			},
			"bbox": [
				-73.4345163,
				45.5832958,
				-73.4313037,
				45.5855442
			]
		}
	]
}
