{
	"type": "FeatureCollection",
	"features": [
		{
			"type": "Feature",
			"properties": {
				"confidence": 9,
				"authenticationResultCode": "ValidCredentials",
				"brandLogoUri": "http://dev.virtualearth.net/Branding/logo_powered_by.png",
				"copyright": "Copyright © 2017 Microsoft and its suppliers. All rights reserved. This API cannot be accessed and the content and any results may not be used, reproduced or transmitted in any manner without express written permission from Microsoft Corporation.",
				"entityType": "Address",
				"matchCodes": [
					"Good"
				],
				"name": "3553 31 St NW, Calgary, AB T2L 2K7, Canada",
				"statusCode": 200,
				"statusDescription": "OK",
				"traceId": "222e7570591544958c0fea924b4be0a4|BN20130533|7.7.0.0|",
				"addressLine": "3553 31 St NW",
				"adminDistrict": "AB",
				"adminDistrict2": "Alberta",
				"countryRegion": "Canada",
				"formattedAddress": "3553 31 St NW, Calgary, AB T2L 2K7, Canada",
				"locality": "Calgary",
				"neighborhood": "Varsity",
				"postalCode": "T2L 2K7"
			},
			"geometry": {
				"type": "Point",
				"coordinates": [
					-114.12971,
					51.08479
				]
			},
			"bbox": [
				-114.1314996,
				51.0836658,
				-114.1279204,
				51.0859142
			]
		}
	]
}
