{
	"type": "FeatureCollection",
	"features": [
		{
			"type": "Feature",
			"properties": {
				"confidence": 9,
				"authenticationResultCode": "ValidCredentials",
				"brandLogoUri": "http://dev.virtualearth.net/Branding/logo_powered_by.png",
				"copyright": "Copyright © 2017 Microsoft and its suppliers. All rights reserved. This API cannot be accessed and the content and any results may not be used, reproduced or transmitted in any manner without express written permission from Microsoft Corporation.",
				"entityType": "Address",
				"matchCodes": [
					"Good"
				],
				"name": "356 Hillsboro Pvt, Kanata, ON K2M 3B1, Canada",
				"statusCode": 200,
				"statusDescription": "OK",
				"traceId": "36278693d00b44ab8e43e9ef1e319e1c|BN20290118|7.7.0.0|",
				"addressLine": "356 Hillsboro Pvt",
				"adminDistrict": "ON",
				"adminDistrict2": "Ottawa",
				"countryRegion": "Canada",
				"formattedAddress": "356 Hillsboro Pvt, Kanata, ON K2M 3B1, Canada",
				"locality": "Ottawa",
				"neighborhood": "Kanata",
				"postalCode": "K2M 3B1"
			},
			"geometry": {
				"type": "Point",
				"coordinates": [
					-75.8497534,
					45.2721323
				]
			},
			"bbox": [
				-75.8513508,
				45.2710082,
				-75.848156,
				45.2732565
			]
		}
	]
}
