{
	"type": "FeatureCollection",
	"features": [
		{
			"type": "Feature",
			"properties": {
				"confidence": 9,
				"authenticationResultCode": "ValidCredentials",
				"brandLogoUri": "http://dev.virtualearth.net/Branding/logo_powered_by.png",
				"copyright": "Copyright © 2017 Microsoft and its suppliers. All rights reserved. This API cannot be accessed and the content and any results may not be used, reproduced or transmitted in any manner without express written permission from Microsoft Corporation.",
				"entityType": "Address",
				"matchCodes": [
					"Good"
				],
				"name": "36 Queen Elizabeth Blvd, Etobicoke, ON M8Z 1L8, Canada",
				"statusCode": 200,
				"statusDescription": "OK",
				"traceId": "67d88436138d4c3d89a001ca1e0fbf55|BN20240423|7.7.0.0|",
				"addressLine": "36 Queen Elizabeth Blvd",
				"adminDistrict": "ON",
				"adminDistrict2": "Toronto",
				"countryRegion": "Canada",
				"formattedAddress": "36 Queen Elizabeth Blvd, Etobicoke, ON M8Z 1L8, Canada",
				"locality": "Toronto",
				"neighborhood": "Stonegate-Queensway",
				"postalCode": "M8Z 1L8"
			},
			"geometry": {
				"type": "Point",
				"coordinates": [
					-79.50585,
					43.62254
				]
			},
			"bbox": [
				-79.5074029,
				43.6214158,
				-79.5042971,
				43.6236642
			]
		}
	]
}
