{
	"type": "FeatureCollection",
	"features": [
		{
			"type": "Feature",
			"properties": {
				"confidence": 9,
				"authenticationResultCode": "ValidCredentials",
				"brandLogoUri": "http://dev.virtualearth.net/Branding/logo_powered_by.png",
				"copyright": "Copyright © 2017 Microsoft and its suppliers. All rights reserved. This API cannot be accessed and the content and any results may not be used, reproduced or transmitted in any manner without express written permission from Microsoft Corporation.",
				"entityType": "Address",
				"matchCodes": [
					"Good"
				],
				"name": "3612 Burnsland Rd SE, Calgary, AB T2G 3Z2, Canada",
				"statusCode": 200,
				"statusDescription": "OK",
				"traceId": "6fc3cc2956a549c9968831cba5ec3568|BN20190642|7.7.0.0|",
				"addressLine": "3612 Burnsland Rd SE",
				"adminDistrict": "AB",
				"adminDistrict2": "Alberta",
				"countryRegion": "Canada",
				"formattedAddress": "3612 Burnsland Rd SE, Calgary, AB T2G 3Z2, Canada",
				"locality": "Calgary",
				"neighborhood": "Alyth-Bonnybrook-Manchester",
				"postalCode": "T2G 3Z2"
			},
			"geometry": {
				"type": "Point",
				"coordinates": [
					-114.05775,
					51.02273
				]
			},
			"bbox": [
				-114.0595372,
				51.0216058,
				-114.0559628,
				51.0238542
			]
		}
	]
}
