{
	"type": "FeatureCollection",
	"features": [
		{
			"type": "Feature",
			"properties": {
				"confidence": 9,
				"authenticationResultCode": "ValidCredentials",
				"brandLogoUri": "http://dev.virtualearth.net/Branding/logo_powered_by.png",
				"copyright": "Copyright © 2017 Microsoft and its suppliers. All rights reserved. This API cannot be accessed and the content and any results may not be used, reproduced or transmitted in any manner without express written permission from Microsoft Corporation.",
				"entityType": "Address",
				"matchCodes": [
					"Good"
				],
				"name": "362 Davenport Rd, Toronto, ON M5R 1K6, Canada",
				"statusCode": 200,
				"statusDescription": "OK",
				"traceId": "9625282412b04225a829f36dd982318b|BN20121762|7.7.0.0|",
				"addressLine": "362 Davenport Rd",
				"adminDistrict": "ON",
				"adminDistrict2": "Toronto",
				"countryRegion": "Canada",
				"formattedAddress": "362 Davenport Rd, Toronto, ON M5R 1K6, Canada",
				"locality": "Toronto",
				"neighborhood": "Annex",
				"postalCode": "M5R 1K6"
			},
			"geometry": {
				"type": "Point",
				"coordinates": [
					-79.40186,
					43.67563
				]
			},
			"bbox": [
				-79.4034143,
				43.6745058,
				-79.4003057,
				43.6767542
			]
		}
	]
}
