{
	"type": "FeatureCollection",
	"features": [
		{
			"type": "Feature",
			"properties": {
				"confidence": 9,
				"authenticationResultCode": "ValidCredentials",
				"brandLogoUri": "http://dev.virtualearth.net/Branding/logo_powered_by.png",
				"copyright": "Copyright © 2017 Microsoft and its suppliers. All rights reserved. This API cannot be accessed and the content and any results may not be used, reproduced or transmitted in any manner without express written permission from Microsoft Corporation.",
				"entityType": "Address",
				"matchCodes": [
					"Good"
				],
				"name": "3674 Douglas Woods Hts SE, Calgary, AB T2Z 2G4, Canada",
				"statusCode": 200,
				"statusDescription": "OK",
				"traceId": "c6c5e223469c4df3b91cfa8a90488b86|BN20130423|7.7.0.0|",
				"addressLine": "3674 Douglas Woods Hts SE",
				"adminDistrict": "AB",
				"adminDistrict2": "Alberta",
				"countryRegion": "Canada",
				"formattedAddress": "3674 Douglas Woods Hts SE, Calgary, AB T2Z 2G4, Canada",
				"locality": "Calgary",
				"neighborhood": "Douglasdale",
				"postalCode": "T2Z 2G4"
			},
			"geometry": {
				"type": "Point",
				"coordinates": [
					-113.9848,
					50.94442
				]
			},
			"bbox": [
				-113.9865842,
				50.9432958,
				-113.9830158,
				50.9455442
			]
		}
	]
}
