{
	"type": "FeatureCollection",
	"features": [
		{
			"type": "Feature",
			"properties": {
				"confidence": 9,
				"authenticationResultCode": "ValidCredentials",
				"brandLogoUri": "http://dev.virtualearth.net/Branding/logo_powered_by.png",
				"copyright": "Copyright © 2017 Microsoft and its suppliers. All rights reserved. This API cannot be accessed and the content and any results may not be used, reproduced or transmitted in any manner without express written permission from Microsoft Corporation.",
				"entityType": "Address",
				"matchCodes": [
					"Good"
				],
				"name": "37 Myrtle Ave, Yorkton, SK S3N 1P6, Canada",
				"statusCode": 200,
				"statusDescription": "OK",
				"traceId": "1a9818287d184664b38118ed2a49c83f|BN20200239|7.7.0.0|",
				"addressLine": "37 Myrtle Ave",
				"adminDistrict": "SK",
				"adminDistrict2": "Saskatchewan",
				"countryRegion": "Canada",
				"formattedAddress": "37 Myrtle Ave, Yorkton, SK S3N 1P6, Canada",
				"locality": "Yorkton",
				"postalCode": "S3N 1P6"
			},
			"geometry": {
				"type": "Point",
				"coordinates": [
					-102.46529,
					51.21157
				]
			},
			"bbox": [
				-102.4670845,
				51.2104458,
				-102.4634955,
				51.2126942
			]
		}
	]
}
