{
	"type": "FeatureCollection",
	"features": [
		{
			"type": "Feature",
			"properties": {
				"confidence": 9,
				"authenticationResultCode": "ValidCredentials",
				"brandLogoUri": "http://dev.virtualearth.net/Branding/logo_powered_by.png",
				"copyright": "Copyright © 2017 Microsoft and its suppliers. All rights reserved. This API cannot be accessed and the content and any results may not be used, reproduced or transmitted in any manner without express written permission from Microsoft Corporation.",
				"entityType": "Address",
				"matchCodes": [
					"Good"
				],
				"name": "370 Stone Rd W, Guelph, ON N1G 4V9, Canada",
				"statusCode": 200,
				"statusDescription": "OK",
				"traceId": "03b88535e44b4b77859e43276ee297f5|BN20210145|7.7.0.0|",
				"addressLine": "370 Stone Rd W",
				"adminDistrict": "ON",
				"adminDistrict2": "Wellington",
				"countryRegion": "Canada",
				"formattedAddress": "370 Stone Rd W, Guelph, ON N1G 4V9, Canada",
				"locality": "Guelph",
				"neighborhood": "Kortright West",
				"postalCode": "N1G 4V9"
			},
			"geometry": {
				"type": "Point",
				"coordinates": [
					-80.23541,
					43.5171
				]
			},
			"bbox": [
				-80.2369602,
				43.5159758,
				-80.2338598,
				43.5182242
			]
		}
	]
}
