{
	"type": "FeatureCollection",
	"features": [
		{
			"type": "Feature",
			"properties": {
				"confidence": 9,
				"authenticationResultCode": "ValidCredentials",
				"brandLogoUri": "http://dev.virtualearth.net/Branding/logo_powered_by.png",
				"copyright": "Copyright © 2017 Microsoft and its suppliers. All rights reserved. This API cannot be accessed and the content and any results may not be used, reproduced or transmitted in any manner without express written permission from Microsoft Corporation.",
				"entityType": "Address",
				"matchCodes": [
					"Good"
				],
				"name": "3702 Kinnear Pl, Saskatoon, SK S7K, Canada",
				"statusCode": 200,
				"statusDescription": "OK",
				"traceId": "2244af356891452eaafe5d690f3a2ee9|BN20130533|7.7.0.0|",
				"addressLine": "3702 Kinnear Pl",
				"adminDistrict": "SK",
				"adminDistrict2": "Saskatchewan",
				"countryRegion": "Canada",
				"formattedAddress": "3702 Kinnear Pl, Saskatoon, SK S7K, Canada",
				"locality": "Saskatoon",
				"neighborhood": "Marquis Industrial",
				"postalCode": "S7K"
			},
			"geometry": {
				"type": "Point",
				"coordinates": [
					-106.62169,
					52.1921899
				]
			},
			"bbox": [
				-106.6235238,
				52.1910657,
				-106.6198562,
				52.1933141
			]
		}
	]
}
