{
	"type": "FeatureCollection",
	"features": [
		{
			"type": "Feature",
			"properties": {
				"confidence": 9,
				"authenticationResultCode": "ValidCredentials",
				"brandLogoUri": "http://dev.virtualearth.net/Branding/logo_powered_by.png",
				"copyright": "Copyright © 2017 Microsoft and its suppliers. All rights reserved. This API cannot be accessed and the content and any results may not be used, reproduced or transmitted in any manner without express written permission from Microsoft Corporation.",
				"entityType": "Address",
				"matchCodes": [
					"Good"
				],
				"name": "3716 Dougall Ave, Windsor, ON N9E 1T7, Canada",
				"statusCode": 200,
				"statusDescription": "OK",
				"traceId": "bbfd4ff580dc40f89120c4a1db83068a|BN20130719|7.7.0.0|",
				"addressLine": "3716 Dougall Ave",
				"adminDistrict": "ON",
				"adminDistrict2": "Essex",
				"countryRegion": "Canada",
				"formattedAddress": "3716 Dougall Ave, Windsor, ON N9E 1T7, Canada",
				"locality": "Windsor",
				"neighborhood": "South Windsor",
				"postalCode": "N9E 1T7"
			},
			"geometry": {
				"type": "Point",
				"coordinates": [
					-83.00483,
					42.25947
				]
			},
			"bbox": [
				-83.0063489,
				42.2583458,
				-83.0033111,
				42.2605942
			]
		}
	]
}
