{
	"type": "FeatureCollection",
	"features": [
		{
			"type": "Feature",
			"properties": {
				"confidence": 9,
				"authenticationResultCode": "ValidCredentials",
				"brandLogoUri": "http://dev.virtualearth.net/Branding/logo_powered_by.png",
				"copyright": "Copyright © 2017 Microsoft and its suppliers. All rights reserved. This API cannot be accessed and the content and any results may not be used, reproduced or transmitted in any manner without express written permission from Microsoft Corporation.",
				"entityType": "Address",
				"matchCodes": [
					"Good"
				],
				"name": "3726 13 St NW, Edmonton, AB T6T 0G3, Canada",
				"statusCode": 200,
				"statusDescription": "OK",
				"traceId": "f6958169006c487c8dfeb0258f76d5a3|BN20130634|7.7.0.0|",
				"addressLine": "3726 13 St NW",
				"adminDistrict": "AB",
				"adminDistrict2": "Alberta",
				"countryRegion": "Canada",
				"formattedAddress": "3726 13 St NW, Edmonton, AB T6T 0G3, Canada",
				"locality": "Edmonton",
				"neighborhood": "Tamarack",
				"postalCode": "T6T 0G3"
			},
			"geometry": {
				"type": "Point",
				"coordinates": [
					-113.36191,
					53.47341
				]
			},
			"bbox": [
				-113.3637987,
				53.4722858,
				-113.3600213,
				53.4745342
			]
		}
	]
}
