{
	"type": "FeatureCollection",
	"features": [
		{
			"type": "Feature",
			"properties": {
				"confidence": 9,
				"authenticationResultCode": "ValidCredentials",
				"brandLogoUri": "http://dev.virtualearth.net/Branding/logo_powered_by.png",
				"copyright": "Copyright © 2017 Microsoft and its suppliers. All rights reserved. This API cannot be accessed and the content and any results may not be used, reproduced or transmitted in any manner without express written permission from Microsoft Corporation.",
				"entityType": "Address",
				"matchCodes": [
					"Good"
				],
				"name": "3790 Davidson Rd, Inverary, ON K0H 1X0, Canada",
				"statusCode": 200,
				"statusDescription": "OK",
				"traceId": "4ec7af473aa8445faad3014fb4a382a2|BN20131519|7.7.0.0|",
				"addressLine": "3790 Davidson Rd",
				"adminDistrict": "ON",
				"adminDistrict2": "Frontenac",
				"countryRegion": "Canada",
				"formattedAddress": "3790 Davidson Rd, Inverary, ON K0H 1X0, Canada",
				"locality": "South Frontenac",
				"neighborhood": "Inverary",
				"postalCode": "K0H 1X0"
			},
			"geometry": {
				"type": "Point",
				"coordinates": [
					-76.4755152,
					44.3759654
				]
			},
			"bbox": [
				-76.477088,
				44.3748412,
				-76.4739425,
				44.3770895
			]
		}
	]
}
