{
	"type": "FeatureCollection",
	"features": [
		{
			"type": "Feature",
			"properties": {
				"confidence": 9,
				"authenticationResultCode": "ValidCredentials",
				"brandLogoUri": "http://dev.virtualearth.net/Branding/logo_powered_by.png",
				"copyright": "Copyright © 2017 Microsoft and its suppliers. All rights reserved. This API cannot be accessed and the content and any results may not be used, reproduced or transmitted in any manner without express written permission from Microsoft Corporation.",
				"entityType": "Address",
				"matchCodes": [
					"Good"
				],
				"name": "3791 HWY-97B, Salmon Arm, BC V1E, Canada",
				"statusCode": 200,
				"statusDescription": "OK",
				"traceId": "d2c366f83f4d492f9596e88050f757a8|BN20130721|7.7.0.0|",
				"addressLine": "3791 HWY-97B",
				"adminDistrict": "BC",
				"adminDistrict2": "Columbia-Shuswap",
				"countryRegion": "Canada",
				"formattedAddress": "3791 HWY-97B, Salmon Arm, BC V1E, Canada",
				"locality": "Salmon Arm",
				"postalCode": "V1E 1W9"
			},
			"geometry": {
				"type": "Point",
				"coordinates": [
					-119.2161749,
					50.6719496
				]
			},
			"bbox": [
				-119.2179487,
				50.6708254,
				-119.2144011,
				50.6730737
			]
		}
	]
}
