{
	"type": "FeatureCollection",
	"features": [
		{
			"type": "Feature",
			"properties": {
				"confidence": 8,
				"authenticationResultCode": "ValidCredentials",
				"brandLogoUri": "http://dev.virtualearth.net/Branding/logo_powered_by.png",
				"copyright": "Copyright © 2017 Microsoft and its suppliers. All rights reserved. This API cannot be accessed and the content and any results may not be used, reproduced or transmitted in any manner without express written permission from Microsoft Corporation.",
				"entityType": "RoadBlock",
				"matchCodes": [
					"Good"
				],
				"name": "Spruce Ave, Glenwood, NL A0G, Canada",
				"statusCode": 200,
				"statusDescription": "OK",
				"traceId": "36b16df319494de2a13fde16313222a6|BN20130532|7.7.0.0|",
				"addressLine": "Spruce Ave",
				"adminDistrict": "NL",
				"adminDistrict2": "Newfoundland and Labrador",
				"countryRegion": "Canada",
				"formattedAddress": "Spruce Ave, Glenwood, NL A0G, Canada",
				"locality": "Glenwood",
				"postalCode": "A0G 2K0"
			},
			"geometry": {
				"type": "Point",
				"coordinates": [
					-54.87835,
					48.99295
				]
			},
			"bbox": [
				-54.87895,
				48.99132,
				-54.87481,
				48.99725
			]
		}
	]
}
