{
	"type": "FeatureCollection",
	"features": [
		{
			"type": "Feature",
			"properties": {
				"confidence": 9,
				"authenticationResultCode": "ValidCredentials",
				"brandLogoUri": "http://dev.virtualearth.net/Branding/logo_powered_by.png",
				"copyright": "Copyright © 2017 Microsoft and its suppliers. All rights reserved. This API cannot be accessed and the content and any results may not be used, reproduced or transmitted in any manner without express written permission from Microsoft Corporation.",
				"entityType": "Address",
				"matchCodes": [
					"Good"
				],
				"name": "380 Mooney Ave, Thunder Bay, ON P7B 5R4, Canada",
				"statusCode": 200,
				"statusDescription": "OK",
				"traceId": "4184387fd7444a2daa0cdd866f44af84|BN20130422|7.7.0.0|",
				"addressLine": "380 Mooney Ave",
				"adminDistrict": "ON",
				"adminDistrict2": "Thunder Bay",
				"countryRegion": "Canada",
				"formattedAddress": "380 Mooney Ave, Thunder Bay, ON P7B 5R4, Canada",
				"locality": "Thunder Bay",
				"postalCode": "P7B 5R4"
			},
			"geometry": {
				"type": "Point",
				"coordinates": [
					-89.23768,
					48.40878
				]
			},
			"bbox": [
				-89.2393735,
				48.4076558,
				-89.2359865,
				48.4099042
			]
		}
	]
}
