{
	"type": "FeatureCollection",
	"features": [
		{
			"type": "Feature",
			"properties": {
				"confidence": 9,
				"authenticationResultCode": "ValidCredentials",
				"brandLogoUri": "http://dev.virtualearth.net/Branding/logo_powered_by.png",
				"copyright": "Copyright © 2017 Microsoft and its suppliers. All rights reserved. This API cannot be accessed and the content and any results may not be used, reproduced or transmitted in any manner without express written permission from Microsoft Corporation.",
				"entityType": "Address",
				"matchCodes": [
					"Good"
				],
				"name": "380 Montrose St, Winnipeg, MB R3M 3M8, Canada",
				"statusCode": 200,
				"statusDescription": "OK",
				"traceId": "9789652543964e059e52567b56623b2c|BN20190642|7.7.0.0|",
				"addressLine": "380 Montrose St",
				"adminDistrict": "MB",
				"adminDistrict2": "Manitoba",
				"countryRegion": "Canada",
				"formattedAddress": "380 Montrose St, Winnipeg, MB R3M 3M8, Canada",
				"locality": "Winnipeg",
				"neighborhood": "North River Heights",
				"postalCode": "R3M 3M8"
			},
			"geometry": {
				"type": "Point",
				"coordinates": [
					-97.17844,
					49.86707
				]
			},
			"bbox": [
				-97.1801841,
				49.8659458,
				-97.1766959,
				49.8681942
			]
		}
	]
}
