{
	"type": "FeatureCollection",
	"features": [
		{
			"type": "Feature",
			"properties": {
				"confidence": 9,
				"authenticationResultCode": "ValidCredentials",
				"brandLogoUri": "http://dev.virtualearth.net/Branding/logo_powered_by.png",
				"copyright": "Copyright © 2017 Microsoft and its suppliers. All rights reserved. This API cannot be accessed and the content and any results may not be used, reproduced or transmitted in any manner without express written permission from Microsoft Corporation.",
				"entityType": "Address",
				"matchCodes": [
					"Good"
				],
				"name": "111 Ontario St, Stratford, ON N5A 3H1, Canada",
				"statusCode": 200,
				"statusDescription": "OK",
				"traceId": "79315cdf09a64c7fbbbb6b677cfe94e2|BN20130442|7.7.0.0|",
				"addressLine": "111 Ontario St",
				"adminDistrict": "ON",
				"adminDistrict2": "Perth",
				"countryRegion": "Canada",
				"formattedAddress": "111 Ontario St, Stratford, ON N5A 3H1, Canada",
				"locality": "Stratford",
				"postalCode": "N5A 3H1"
			},
			"geometry": {
				"type": "Point",
				"coordinates": [
					-80.98116,
					43.37116
				]
			},
			"bbox": [
				-80.9827065,
				43.3700358,
				-80.9796135,
				43.3722842
			]
		}
	]
}
