{
	"type": "FeatureCollection",
	"features": [
		{
			"type": "Feature",
			"properties": {
				"confidence": 9,
				"authenticationResultCode": "ValidCredentials",
				"brandLogoUri": "http://dev.virtualearth.net/Branding/logo_powered_by.png",
				"copyright": "Copyright © 2017 Microsoft and its suppliers. All rights reserved. This API cannot be accessed and the content and any results may not be used, reproduced or transmitted in any manner without express written permission from Microsoft Corporation.",
				"entityType": "Address",
				"matchCodes": [
					"Good"
				],
				"name": "3850 Place de Java, Brossard, QC J4Y 0C4, Canada",
				"statusCode": 200,
				"statusDescription": "OK",
				"traceId": "ce55b2eee60543e09ff2d891b508cf72|BN20280152|7.7.0.0|",
				"addressLine": "3850 Place de Java",
				"adminDistrict": "QC",
				"adminDistrict2": "Longueuil",
				"countryRegion": "Canada",
				"formattedAddress": "3850 Place de Java, Brossard, QC J4Y 0C4, Canada",
				"locality": "Brossard",
				"postalCode": "J4Y 0C4"
			},
			"geometry": {
				"type": "Point",
				"coordinates": [
					-73.45865,
					45.43291
				]
			},
			"bbox": [
				-73.4602519,
				45.4317858,
				-73.4570481,
				45.4340342
			]
		}
	]
}
