{
	"type": "FeatureCollection",
	"features": [
		{
			"type": "Feature",
			"properties": {
				"confidence": 9,
				"authenticationResultCode": "ValidCredentials",
				"brandLogoUri": "http://dev.virtualearth.net/Branding/logo_powered_by.png",
				"copyright": "Copyright © 2017 Microsoft and its suppliers. All rights reserved. This API cannot be accessed and the content and any results may not be used, reproduced or transmitted in any manner without express written permission from Microsoft Corporation.",
				"entityType": "Address",
				"matchCodes": [
					"Good"
				],
				"name": "3885 Boulevard Industriel, Laval, QC H7L 4S3, Canada",
				"statusCode": 200,
				"statusDescription": "OK",
				"traceId": "a267b60cf10a454c88f2569499ef4d05|BN20130621|7.7.0.0|",
				"addressLine": "3885 Boulevard Industriel",
				"adminDistrict": "QC",
				"adminDistrict2": "Laval",
				"countryRegion": "Canada",
				"formattedAddress": "3885 Boulevard Industriel, Laval, QC H7L 4S3, Canada",
				"locality": "Laval",
				"postalCode": "H7L 4S3"
			},
			"geometry": {
				"type": "Point",
				"coordinates": [
					-73.74699,
					45.59557
				]
			},
			"bbox": [
				-73.7485966,
				45.5944458,
				-73.7453834,
				45.5966942
			]
		}
	]
}
