{
	"type": "FeatureCollection",
	"features": [
		{
			"type": "Feature",
			"properties": {
				"confidence": 9,
				"authenticationResultCode": "ValidCredentials",
				"brandLogoUri": "http://dev.virtualearth.net/Branding/logo_powered_by.png",
				"copyright": "Copyright © 2017 Microsoft and its suppliers. All rights reserved. This API cannot be accessed and the content and any results may not be used, reproduced or transmitted in any manner without express written permission from Microsoft Corporation.",
				"entityType": "Address",
				"matchCodes": [
					"Good"
				],
				"name": "3908 69 Ave NW, Edmonton, AB T6B 2V2, Canada",
				"statusCode": 200,
				"statusDescription": "OK",
				"traceId": "0be01e1ef98b4fa59aefe1e0cf91c2a2|BN20130533|7.7.0.0|",
				"addressLine": "3908 69 Ave NW",
				"adminDistrict": "AB",
				"adminDistrict2": "Alberta",
				"countryRegion": "Canada",
				"formattedAddress": "3908 69 Ave NW, Edmonton, AB T6B 2V2, Canada",
				"locality": "Edmonton",
				"neighborhood": "Pylypow Industrial",
				"postalCode": "T6B 2V2"
			},
			"geometry": {
				"type": "Point",
				"coordinates": [
					-113.40189,
					53.50651
				]
			},
			"bbox": [
				-113.4037802,
				53.5053858,
				-113.3999998,
				53.5076342
			]
		}
	]
}
