{
	"type": "FeatureCollection",
	"features": [
		{
			"type": "Feature",
			"properties": {
				"confidence": 9,
				"authenticationResultCode": "ValidCredentials",
				"brandLogoUri": "http://dev.virtualearth.net/Branding/logo_powered_by.png",
				"copyright": "Copyright © 2017 Microsoft and its suppliers. All rights reserved. This API cannot be accessed and the content and any results may not be used, reproduced or transmitted in any manner without express written permission from Microsoft Corporation.",
				"entityType": "Address",
				"matchCodes": [
					"Good"
				],
				"name": "3953 Gulfview Dr, Nanaimo, BC V9T 6B5, Canada",
				"statusCode": 200,
				"statusDescription": "OK",
				"traceId": "42a27a3309e84fb5b6731dd6915bef59|BN20171457|7.7.0.0|",
				"addressLine": "3953 Gulfview Dr",
				"adminDistrict": "BC",
				"adminDistrict2": "Nanaimo",
				"countryRegion": "Canada",
				"formattedAddress": "3953 Gulfview Dr, Nanaimo, BC V9T 6B5, Canada",
				"locality": "Nanaimo",
				"postalCode": "V9T 6B5"
			},
			"geometry": {
				"type": "Point",
				"coordinates": [
					-123.96509,
					49.22745
				]
			},
			"bbox": [
				-123.9668114,
				49.2263258,
				-123.9633686,
				49.2285742
			]
		}
	]
}
