{
	"type": "FeatureCollection",
	"features": [
		{
			"type": "Feature",
			"properties": {
				"confidence": 9,
				"authenticationResultCode": "ValidCredentials",
				"brandLogoUri": "http://dev.virtualearth.net/Branding/logo_powered_by.png",
				"copyright": "Copyright © 2017 Microsoft and its suppliers. All rights reserved. This API cannot be accessed and the content and any results may not be used, reproduced or transmitted in any manner without express written permission from Microsoft Corporation.",
				"entityType": "Address",
				"matchCodes": [
					"Good"
				],
				"name": "3963 15th Ave, Prince George, BC V2M, Canada",
				"statusCode": 200,
				"statusDescription": "OK",
				"traceId": "17d7f12d63a34583bea3f9f39c77793f|BN20130631|7.7.0.0|",
				"addressLine": "3963 15th Ave",
				"adminDistrict": "BC",
				"adminDistrict2": "Fraser-Fort George",
				"countryRegion": "Canada",
				"formattedAddress": "3963 15th Ave, Prince George, BC V2M, Canada",
				"locality": "Prince George",
				"postalCode": "V2M"
			},
			"geometry": {
				"type": "Point",
				"coordinates": [
					-122.7939307,
					53.9101251
				]
			},
			"bbox": [
				-122.7958391,
				53.909001,
				-122.7920223,
				53.9112493
			]
		}
	]
}
