{
	"type": "FeatureCollection",
	"features": [
		{
			"type": "Feature",
			"properties": {
				"confidence": 9,
				"authenticationResultCode": "ValidCredentials",
				"brandLogoUri": "http://dev.virtualearth.net/Branding/logo_powered_by.png",
				"copyright": "Copyright © 2017 Microsoft and its suppliers. All rights reserved. This API cannot be accessed and the content and any results may not be used, reproduced or transmitted in any manner without express written permission from Microsoft Corporation.",
				"entityType": "Address",
				"matchCodes": [
					"Good"
				],
				"name": "3976 Hastings St, Burnaby, BC V5C 6C1, Canada",
				"statusCode": 200,
				"statusDescription": "OK",
				"traceId": "11c86d306198437d8943afaa3fae5c9e|BN20190653|7.7.0.0|",
				"addressLine": "3976 Hastings St",
				"adminDistrict": "BC",
				"adminDistrict2": "Greater Vancouver",
				"countryRegion": "Canada",
				"formattedAddress": "3976 Hastings St, Burnaby, BC V5C 6C1, Canada",
				"locality": "Burnaby",
				"neighborhood": "Willingdon Heights",
				"postalCode": "V5C 6C1"
			},
			"geometry": {
				"type": "Point",
				"coordinates": [
					-123.0169175,
					49.2809396
				]
			},
			"bbox": [
				-123.0186407,
				49.2798155,
				-123.0151943,
				49.2820638
			]
		}
	]
}
