{
	"type": "FeatureCollection",
	"features": [
		{
			"type": "Feature",
			"properties": {
				"confidence": 9,
				"authenticationResultCode": "ValidCredentials",
				"brandLogoUri": "http://dev.virtualearth.net/Branding/logo_powered_by.png",
				"copyright": "Copyright © 2017 Microsoft and its suppliers. All rights reserved. This API cannot be accessed and the content and any results may not be used, reproduced or transmitted in any manner without express written permission from Microsoft Corporation.",
				"entityType": "Address",
				"matchCodes": [
					"Good"
				],
				"name": "3995 Ponderosa Pl, Peachland, BC V0H 1X5, Canada",
				"statusCode": 200,
				"statusDescription": "OK",
				"traceId": "73c8cefc81da405c96df346d3a8cac97|BN20240423|7.7.0.0|",
				"addressLine": "3995 Ponderosa Pl",
				"adminDistrict": "BC",
				"adminDistrict2": "Central Okanagan",
				"countryRegion": "Canada",
				"formattedAddress": "3995 Ponderosa Pl, Peachland, BC V0H 1X5, Canada",
				"locality": "Peachland",
				"postalCode": "V0H 1X5"
			},
			"geometry": {
				"type": "Point",
				"coordinates": [
					-119.72823,
					49.7872
				]
			},
			"bbox": [
				-119.7299712,
				49.7860758,
				-119.7264888,
				49.7883242
			]
		}
	]
}
