{
	"type": "FeatureCollection",
	"features": [
		{
			"type": "Feature",
			"properties": {
				"confidence": 9,
				"authenticationResultCode": "ValidCredentials",
				"brandLogoUri": "http://dev.virtualearth.net/Branding/logo_powered_by.png",
				"copyright": "Copyright © 2017 Microsoft and its suppliers. All rights reserved. This API cannot be accessed and the content and any results may not be used, reproduced or transmitted in any manner without express written permission from Microsoft Corporation.",
				"entityType": "Address",
				"matchCodes": [
					"Good"
				],
				"name": "4 Edgemont Ct, Richmond Hill, ON L4S 2H8, Canada",
				"statusCode": 200,
				"statusDescription": "OK",
				"traceId": "0f7e9c1cbf8541c3b411e6df3dfc3658|BN20210145|7.7.0.0|",
				"addressLine": "4 Edgemont Ct",
				"adminDistrict": "ON",
				"adminDistrict2": "York",
				"countryRegion": "Canada",
				"formattedAddress": "4 Edgemont Ct, Richmond Hill, ON L4S 2H8, Canada",
				"locality": "Richmond Hill",
				"postalCode": "L4S 2H8"
			},
			"geometry": {
				"type": "Point",
				"coordinates": [
					-79.46362,
					43.90185
				]
			},
			"bbox": [
				-79.4651802,
				43.9007258,
				-79.4620598,
				43.9029742
			]
		}
	]
}
