{
	"type": "FeatureCollection",
	"features": [
		{
			"type": "Feature",
			"properties": {
				"confidence": 9,
				"authenticationResultCode": "ValidCredentials",
				"brandLogoUri": "http://dev.virtualearth.net/Branding/logo_powered_by.png",
				"copyright": "Copyright © 2017 Microsoft and its suppliers. All rights reserved. This API cannot be accessed and the content and any results may not be used, reproduced or transmitted in any manner without express written permission from Microsoft Corporation.",
				"entityType": "Address",
				"matchCodes": [
					"Good"
				],
				"name": "4 Flanders Ct, Moncton, NB E1C 0K6, Canada",
				"statusCode": 200,
				"statusDescription": "OK",
				"traceId": "52b381ffd92b414ca0f750f09651912f|BN20130631|7.7.0.0|",
				"addressLine": "4 Flanders Ct",
				"adminDistrict": "NB",
				"adminDistrict2": "Westmorland",
				"countryRegion": "Canada",
				"formattedAddress": "4 Flanders Ct, Moncton, NB E1C 0K6, Canada",
				"locality": "Moncton",
				"postalCode": "E1C 0K6"
			},
			"geometry": {
				"type": "Point",
				"coordinates": [
					-64.8000924,
					46.094159
				]
			},
			"bbox": [
				-64.8017134,
				46.0930348,
				-64.7984713,
				46.0952831
			]
		}
	]
}
