{
	"type": "FeatureCollection",
	"features": [
		{
			"type": "Feature",
			"properties": {
				"confidence": 9,
				"authenticationResultCode": "ValidCredentials",
				"brandLogoUri": "http://dev.virtualearth.net/Branding/logo_powered_by.png",
				"copyright": "Copyright © 2017 Microsoft and its suppliers. All rights reserved. This API cannot be accessed and the content and any results may not be used, reproduced or transmitted in any manner without express written permission from Microsoft Corporation.",
				"entityType": "Address",
				"matchCodes": [
					"Good"
				],
				"name": "40 Kress St, Regina, SK S4N 5Y3, Canada",
				"statusCode": 200,
				"statusDescription": "OK",
				"traceId": "c7259198f21e456195a4c37eb336501d|BN20130634|7.7.0.0|",
				"addressLine": "40 Kress St",
				"adminDistrict": "SK",
				"adminDistrict2": "Saskatchewan",
				"countryRegion": "Canada",
				"formattedAddress": "40 Kress St, Regina, SK S4N 5Y3, Canada",
				"locality": "Regina",
				"postalCode": "S4N 5Y3"
			},
			"geometry": {
				"type": "Point",
				"coordinates": [
					-104.56465,
					50.48086
				]
			},
			"bbox": [
				-104.5664166,
				50.4797358,
				-104.5628834,
				50.4819842
			]
		}
	]
}
