{
	"type": "FeatureCollection",
	"features": [
		{
			"type": "Feature",
			"properties": {
				"confidence": 9,
				"authenticationResultCode": "ValidCredentials",
				"brandLogoUri": "http://dev.virtualearth.net/Branding/logo_powered_by.png",
				"copyright": "Copyright © 2017 Microsoft and its suppliers. All rights reserved. This API cannot be accessed and the content and any results may not be used, reproduced or transmitted in any manner without express written permission from Microsoft Corporation.",
				"entityType": "Address",
				"matchCodes": [
					"Good"
				],
				"name": "40 Melair Dr, Ayr, ON N0B 1E0, Canada",
				"statusCode": 200,
				"statusDescription": "OK",
				"traceId": "8523c36e6f804ad4b2e33a6a1bf2eb8b|BN20190642|7.7.0.0|",
				"addressLine": "40 Melair Dr",
				"adminDistrict": "ON",
				"adminDistrict2": "Waterloo",
				"countryRegion": "Canada",
				"formattedAddress": "40 Melair Dr, Ayr, ON N0B 1E0, Canada",
				"locality": "North Dumfries",
				"neighborhood": "Ayr",
				"postalCode": "N0B 1E0"
			},
			"geometry": {
				"type": "Point",
				"coordinates": [
					-80.45774,
					43.29898
				]
			},
			"bbox": [
				-80.4592846,
				43.2978558,
				-80.4561954,
				43.3001042
			]
		}
	]
}
