{
	"type": "FeatureCollection",
	"features": [
		{
			"type": "Feature",
			"properties": {
				"confidence": 9,
				"authenticationResultCode": "ValidCredentials",
				"brandLogoUri": "http://dev.virtualearth.net/Branding/logo_powered_by.png",
				"copyright": "Copyright © 2017 Microsoft and its suppliers. All rights reserved. This API cannot be accessed and the content and any results may not be used, reproduced or transmitted in any manner without express written permission from Microsoft Corporation.",
				"entityType": "Address",
				"matchCodes": [
					"Good"
				],
				"name": "400 Rowntree Dairy Rd, Woodbridge, ON L4L 8H2, Canada",
				"statusCode": 200,
				"statusDescription": "OK",
				"traceId": "a3c693057f5f4874acc3b3acb29b9159|BN20181720|7.7.0.0|",
				"addressLine": "400 Rowntree Dairy Rd",
				"adminDistrict": "ON",
				"adminDistrict2": "York",
				"countryRegion": "Canada",
				"formattedAddress": "400 Rowntree Dairy Rd, Woodbridge, ON L4L 8H2, Canada",
				"locality": "Vaughan",
				"neighborhood": "Woodbridge",
				"postalCode": "L4L 8H2"
			},
			"geometry": {
				"type": "Point",
				"coordinates": [
					-79.55702,
					43.78029
				]
			},
			"bbox": [
				-79.558577,
				43.7791658,
				-79.555463,
				43.7814142
			]
		}
	]
}
