{
	"type": "FeatureCollection",
	"features": [
		{
			"type": "Feature",
			"properties": {
				"confidence": 9,
				"authenticationResultCode": "ValidCredentials",
				"brandLogoUri": "http://dev.virtualearth.net/Branding/logo_powered_by.png",
				"copyright": "Copyright © 2017 Microsoft and its suppliers. All rights reserved. This API cannot be accessed and the content and any results may not be used, reproduced or transmitted in any manner without express written permission from Microsoft Corporation.",
				"entityType": "Address",
				"matchCodes": [
					"Good"
				],
				"name": "403 Rue de Dieppe, Quebec, QC G1N 3N2, Canada",
				"statusCode": 200,
				"statusDescription": "OK",
				"traceId": "a0a0a63bce404ea591546cd5a156fdd3|BN20130634|7.7.0.0|",
				"addressLine": "403 Rue de Dieppe",
				"adminDistrict": "QC",
				"adminDistrict2": "Quebec",
				"countryRegion": "Canada",
				"formattedAddress": "403 Rue de Dieppe, Quebec, QC G1N 3N2, Canada",
				"locality": "Quebec",
				"neighborhood": "St-Sauveur",
				"postalCode": "G1N 3N2"
			},
			"geometry": {
				"type": "Point",
				"coordinates": [
					-71.24484,
					46.8046
				]
			},
			"bbox": [
				-71.2464823,
				46.8034758,
				-71.2431977,
				46.8057242
			]
		}
	]
}
