{
	"type": "FeatureCollection",
	"features": [
		{
			"type": "Feature",
			"properties": {
				"confidence": 9,
				"authenticationResultCode": "ValidCredentials",
				"brandLogoUri": "http://dev.virtualearth.net/Branding/logo_powered_by.png",
				"copyright": "Copyright © 2017 Microsoft and its suppliers. All rights reserved. This API cannot be accessed and the content and any results may not be used, reproduced or transmitted in any manner without express written permission from Microsoft Corporation.",
				"entityType": "Address",
				"matchCodes": [
					"Good"
				],
				"name": "405 Rue Masson, Chicoutimi, QC G7G 2B8, Canada",
				"statusCode": 200,
				"statusDescription": "OK",
				"traceId": "e149c55621e94bdda61166ec0144b792|BN20130621|7.7.0.0|",
				"addressLine": "405 Rue Masson",
				"adminDistrict": "QC",
				"adminDistrict2": "Saguenay",
				"countryRegion": "Canada",
				"formattedAddress": "405 Rue Masson, Chicoutimi, QC G7G 2B8, Canada",
				"locality": "Saguenay",
				"neighborhood": "Chicoutimi",
				"postalCode": "G7G 2B8"
			},
			"geometry": {
				"type": "Point",
				"coordinates": [
					-71.07362,
					48.43965
				]
			},
			"bbox": [
				-71.0753145,
				48.4385258,
				-71.0719255,
				48.4407742
			]
		}
	]
}
