{
	"type": "FeatureCollection",
	"features": [
		{
			"type": "Feature",
			"properties": {
				"confidence": 9,
				"authenticationResultCode": "ValidCredentials",
				"brandLogoUri": "http://dev.virtualearth.net/Branding/logo_powered_by.png",
				"copyright": "Copyright © 2017 Microsoft and its suppliers. All rights reserved. This API cannot be accessed and the content and any results may not be used, reproduced or transmitted in any manner without express written permission from Microsoft Corporation.",
				"entityType": "Address",
				"matchCodes": [
					"Good"
				],
				"name": "4050 Boulevard Industriel, Laval, QC H7L 6C3, Canada",
				"statusCode": 200,
				"statusDescription": "OK",
				"traceId": "e045b11ec8a84b3d9e77581bfd3072bc|BN20121762|7.7.0.0|",
				"addressLine": "4050 Boulevard Industriel",
				"adminDistrict": "QC",
				"adminDistrict2": "Laval",
				"countryRegion": "Canada",
				"formattedAddress": "4050 Boulevard Industriel, Laval, QC H7L 6C3, Canada",
				"locality": "Laval",
				"postalCode": "H7L 6C3"
			},
			"geometry": {
				"type": "Point",
				"coordinates": [
					-73.75304,
					45.59888
				]
			},
			"bbox": [
				-73.7546467,
				45.5977558,
				-73.7514333,
				45.6000042
			]
		}
	]
}
