{
	"type": "FeatureCollection",
	"features": [
		{
			"type": "Feature",
			"properties": {
				"confidence": 9,
				"authenticationResultCode": "ValidCredentials",
				"brandLogoUri": "http://dev.virtualearth.net/Branding/logo_powered_by.png",
				"copyright": "Copyright © 2017 Microsoft and its suppliers. All rights reserved. This API cannot be accessed and the content and any results may not be used, reproduced or transmitted in any manner without express written permission from Microsoft Corporation.",
				"entityType": "Address",
				"matchCodes": [
					"Good"
				],
				"name": "406 Durie St, Toronto, ON M6S 3G4, Canada",
				"statusCode": 200,
				"statusDescription": "OK",
				"traceId": "ec86b427fa12413792ce72f36d85a6b3|BN20130447|7.7.0.0|",
				"addressLine": "406 Durie St",
				"adminDistrict": "ON",
				"adminDistrict2": "Toronto",
				"countryRegion": "Canada",
				"formattedAddress": "406 Durie St, Toronto, ON M6S 3G4, Canada",
				"locality": "Toronto",
				"neighborhood": "Runnymede-Bloor West Village",
				"postalCode": "M6S 3G4"
			},
			"geometry": {
				"type": "Point",
				"coordinates": [
					-79.48145,
					43.65579
				]
			},
			"bbox": [
				-79.4830038,
				43.6546658,
				-79.4798962,
				43.6569142
			]
		}
	]
}
