{
	"type": "FeatureCollection",
	"features": [
		{
			"type": "Feature",
			"properties": {
				"confidence": 9,
				"authenticationResultCode": "ValidCredentials",
				"brandLogoUri": "http://dev.virtualearth.net/Branding/logo_powered_by.png",
				"copyright": "Copyright © 2017 Microsoft and its suppliers. All rights reserved. This API cannot be accessed and the content and any results may not be used, reproduced or transmitted in any manner without express written permission from Microsoft Corporation.",
				"entityType": "Address",
				"matchCodes": [
					"Good"
				],
				"name": "408 Churchill Ave N, Ottawa, ON K1Z 5C6, Canada",
				"statusCode": 200,
				"statusDescription": "OK",
				"traceId": "7b5fffc0a5b34c31b82e93ca3740d300|BN20130533|7.7.0.0|",
				"addressLine": "408 Churchill Ave N",
				"adminDistrict": "ON",
				"adminDistrict2": "Ottawa",
				"countryRegion": "Canada",
				"formattedAddress": "408 Churchill Ave N, Ottawa, ON K1Z 5C6, Canada",
				"locality": "Ottawa",
				"neighborhood": "Carlingwood-McKellar Pk-Laurentien",
				"postalCode": "K1Z 5C6"
			},
			"geometry": {
				"type": "Point",
				"coordinates": [
					-75.75406,
					45.39165
				]
			},
			"bbox": [
				-75.7556608,
				45.3905258,
				-75.7524592,
				45.3927742
			]
		}
	]
}
