{
	"type": "FeatureCollection",
	"features": [
		{
			"type": "Feature",
			"properties": {
				"confidence": 9,
				"authenticationResultCode": "ValidCredentials",
				"brandLogoUri": "http://dev.virtualearth.net/Branding/logo_powered_by.png",
				"copyright": "Copyright © 2017 Microsoft and its suppliers. All rights reserved. This API cannot be accessed and the content and any results may not be used, reproduced or transmitted in any manner without express written permission from Microsoft Corporation.",
				"entityType": "Address",
				"matchCodes": [
					"Good"
				],
				"name": "408 Mersea Road 3, Leamington, ON N8H 3V5, Canada",
				"statusCode": 200,
				"statusDescription": "OK",
				"traceId": "1e10ae6a0a4e462192c28fab36e98e3d|BN20200239|7.7.0.0|",
				"addressLine": "408 Mersea Road 3",
				"adminDistrict": "ON",
				"adminDistrict2": "Essex",
				"countryRegion": "Canada",
				"formattedAddress": "408 Mersea Road 3, Leamington, ON N8H 3V5, Canada",
				"locality": "Leamington",
				"postalCode": "N8H 3V5"
			},
			"geometry": {
				"type": "Point",
				"coordinates": [
					-82.6194861,
					42.0598952
				]
			},
			"bbox": [
				-82.6210002,
				42.058771,
				-82.617972,
				42.0610193
			]
		}
	]
}
