{
	"type": "FeatureCollection",
	"features": [
		{
			"type": "Feature",
			"properties": {
				"confidence": 9,
				"authenticationResultCode": "ValidCredentials",
				"brandLogoUri": "http://dev.virtualearth.net/Branding/logo_powered_by.png",
				"copyright": "Copyright © 2017 Microsoft and its suppliers. All rights reserved. This API cannot be accessed and the content and any results may not be used, reproduced or transmitted in any manner without express written permission from Microsoft Corporation.",
				"entityType": "Address",
				"matchCodes": [
					"Good"
				],
				"name": "4085 Sladeview Cres, Mississauga, ON L5L 5X3, Canada",
				"statusCode": 200,
				"statusDescription": "OK",
				"traceId": "3114cef3e62e48f5ad9fea02388e0f86|BN20300154|7.7.0.0|",
				"addressLine": "4085 Sladeview Cres",
				"adminDistrict": "ON",
				"adminDistrict2": "Peel",
				"countryRegion": "Canada",
				"formattedAddress": "4085 Sladeview Cres, Mississauga, ON L5L 5X3, Canada",
				"locality": "Mississauga",
				"neighborhood": "Erin Mills",
				"postalCode": "L5L 5X3"
			},
			"geometry": {
				"type": "Point",
				"coordinates": [
					-79.71796,
					43.5278599
				]
			},
			"bbox": [
				-79.7195105,
				43.5267357,
				-79.7164095,
				43.5289841
			]
		}
	]
}
