{
	"type": "FeatureCollection",
	"features": [
		{
			"type": "Feature",
			"properties": {
				"confidence": 9,
				"authenticationResultCode": "ValidCredentials",
				"brandLogoUri": "http://dev.virtualearth.net/Branding/logo_powered_by.png",
				"copyright": "Copyright © 2017 Microsoft and its suppliers. All rights reserved. This API cannot be accessed and the content and any results may not be used, reproduced or transmitted in any manner without express written permission from Microsoft Corporation.",
				"entityType": "Address",
				"matchCodes": [
					"Good"
				],
				"name": "4090 HWY-63, North Bay, ON P1B 8G4, Canada",
				"statusCode": 200,
				"statusDescription": "OK",
				"traceId": "b24b44b6dfbc4032bfe831fe511f81d8|BN20130719|7.7.0.0|",
				"addressLine": "4090 HWY-63",
				"adminDistrict": "ON",
				"adminDistrict2": "Nipissing",
				"countryRegion": "Canada",
				"formattedAddress": "4090 HWY-63, North Bay, ON P1B 8G4, Canada",
				"locality": "North Bay",
				"postalCode": "P1B 8G4"
			},
			"geometry": {
				"type": "Point",
				"coordinates": [
					-79.3778253,
					46.3302083
				]
			},
			"bbox": [
				-79.3794533,
				46.3290841,
				-79.3761972,
				46.3313324
			]
		}
	]
}
