{
	"type": "FeatureCollection",
	"features": [
		{
			"type": "Feature",
			"properties": {
				"confidence": 9,
				"authenticationResultCode": "ValidCredentials",
				"brandLogoUri": "http://dev.virtualearth.net/Branding/logo_powered_by.png",
				"copyright": "Copyright © 2017 Microsoft and its suppliers. All rights reserved. This API cannot be accessed and the content and any results may not be used, reproduced or transmitted in any manner without express written permission from Microsoft Corporation.",
				"entityType": "Address",
				"matchCodes": [
					"Good"
				],
				"name": "4094 Kerry Ct, Vineland, ON L0R 2C0, Canada",
				"statusCode": 200,
				"statusDescription": "OK",
				"traceId": "d9be97783d744eb8b8310ae1e89a43a9|BN20130447|7.7.0.0|",
				"addressLine": "4094 Kerry Ct",
				"adminDistrict": "ON",
				"adminDistrict2": "Niagara",
				"countryRegion": "Canada",
				"formattedAddress": "4094 Kerry Ct, Vineland, ON L0R 2C0, Canada",
				"locality": "Lincoln",
				"neighborhood": "Vineland",
				"postalCode": "L0R 2C0"
			},
			"geometry": {
				"type": "Point",
				"coordinates": [
					-79.39804,
					43.15847
				]
			},
			"bbox": [
				-79.3995811,
				43.1573458,
				-79.3964989,
				43.1595942
			]
		}
	]
}
