{
	"type": "FeatureCollection",
	"features": [
		{
			"type": "Feature",
			"properties": {
				"confidence": 9,
				"authenticationResultCode": "ValidCredentials",
				"brandLogoUri": "http://dev.virtualearth.net/Branding/logo_powered_by.png",
				"copyright": "Copyright © 2017 Microsoft and its suppliers. All rights reserved. This API cannot be accessed and the content and any results may not be used, reproduced or transmitted in any manner without express written permission from Microsoft Corporation.",
				"entityType": "Address",
				"matchCodes": [
					"Good"
				],
				"name": "41 Earnhardt Rd, Sussex Corner, NB E4E 6A1, Canada",
				"statusCode": 200,
				"statusDescription": "OK",
				"traceId": "5cd6f7b58a6445cd94cc34fb0ac71e4b|BN20300154|7.7.0.0|",
				"addressLine": "41 Earnhardt Rd",
				"adminDistrict": "NB",
				"adminDistrict2": "Kings",
				"countryRegion": "Canada",
				"formattedAddress": "41 Earnhardt Rd, Sussex Corner, NB E4E 6A1, Canada",
				"locality": "Sussex Corner",
				"postalCode": "E4E 6A1"
			},
			"geometry": {
				"type": "Point",
				"coordinates": [
					-65.470711,
					45.7298448
				]
			},
			"bbox": [
				-65.4723214,
				45.7287207,
				-65.4691006,
				45.730969
			]
		}
	]
}
