{
	"type": "FeatureCollection",
	"features": [
		{
			"type": "Feature",
			"properties": {
				"confidence": 9,
				"authenticationResultCode": "ValidCredentials",
				"brandLogoUri": "http://dev.virtualearth.net/Branding/logo_powered_by.png",
				"copyright": "Copyright © 2017 Microsoft and its suppliers. All rights reserved. This API cannot be accessed and the content and any results may not be used, reproduced or transmitted in any manner without express written permission from Microsoft Corporation.",
				"entityType": "Address",
				"matchCodes": [
					"Good"
				],
				"name": "41 Ilsley Ave, Dartmouth, NS B3B 1K9, Canada",
				"statusCode": 200,
				"statusDescription": "OK",
				"traceId": "d4ed5d2d90ab45ff9072641f6235af2a|BN20210145|7.7.0.0|",
				"addressLine": "41 Ilsley Ave",
				"adminDistrict": "NS",
				"adminDistrict2": "Halifax",
				"countryRegion": "Canada",
				"formattedAddress": "41 Ilsley Ave, Dartmouth, NS B3B 1K9, Canada",
				"locality": "Halifax",
				"neighborhood": "Dartmouth",
				"postalCode": "B3B 1K9"
			},
			"geometry": {
				"type": "Point",
				"coordinates": [
					-63.59152,
					44.70285
				]
			},
			"bbox": [
				-63.5931016,
				44.7017258,
				-63.5899384,
				44.7039742
			]
		}
	]
}
