{
	"type": "FeatureCollection",
	"features": [
		{
			"type": "Feature",
			"properties": {
				"confidence": 9,
				"authenticationResultCode": "ValidCredentials",
				"brandLogoUri": "http://dev.virtualearth.net/Branding/logo_powered_by.png",
				"copyright": "Copyright © 2017 Microsoft and its suppliers. All rights reserved. This API cannot be accessed and the content and any results may not be used, reproduced or transmitted in any manner without express written permission from Microsoft Corporation.",
				"entityType": "Address",
				"matchCodes": [
					"Good"
				],
				"name": "410 2nd Ave N, Saskatoon, SK S7K 2C3, Canada",
				"statusCode": 200,
				"statusDescription": "OK",
				"traceId": "f57a4e8086954c23bd4be409ff21da0e|BN20130422|7.7.0.0|",
				"addressLine": "410 2nd Ave N",
				"adminDistrict": "SK",
				"adminDistrict2": "Saskatchewan",
				"countryRegion": "Canada",
				"formattedAddress": "410 2nd Ave N, Saskatoon, SK S7K 2C3, Canada",
				"locality": "Saskatoon",
				"neighborhood": "City Park",
				"postalCode": "S7K 2C3"
			},
			"geometry": {
				"type": "Point",
				"coordinates": [
					-106.66079,
					52.13388
				]
			},
			"bbox": [
				-106.6626214,
				52.1327558,
				-106.6589586,
				52.1350042
			]
		}
	]
}
