{
	"type": "FeatureCollection",
	"features": [
		{
			"type": "Feature",
			"properties": {
				"confidence": 9,
				"authenticationResultCode": "ValidCredentials",
				"brandLogoUri": "http://dev.virtualearth.net/Branding/logo_powered_by.png",
				"copyright": "Copyright © 2017 Microsoft and its suppliers. All rights reserved. This API cannot be accessed and the content and any results may not be used, reproduced or transmitted in any manner without express written permission from Microsoft Corporation.",
				"entityType": "Address",
				"matchCodes": [
					"Good"
				],
				"name": "4115 Shore Rd, Cape Breton, NS B1W, Canada",
				"statusCode": 200,
				"statusDescription": "OK",
				"traceId": "3568e60f5a87469ba31f27534a6ebe78|BN20240423|7.7.0.0|",
				"addressLine": "4115 Shore Rd",
				"adminDistrict": "NS",
				"adminDistrict2": "Cape Breton",
				"countryRegion": "Canada",
				"formattedAddress": "4115 Shore Rd, Cape Breton, NS B1W, Canada",
				"locality": "Cape Breton",
				"neighborhood": "Eskasoni",
				"postalCode": "B1W 1C2"
			},
			"geometry": {
				"type": "Point",
				"coordinates": [
					-60.5854261,
					45.9559486
				]
			},
			"bbox": [
				-60.5870431,
				45.9548245,
				-60.5838091,
				45.9570728
			]
		}
	]
}
