{
	"type": "FeatureCollection",
	"features": [
		{
			"type": "Feature",
			"properties": {
				"confidence": 9,
				"authenticationResultCode": "ValidCredentials",
				"brandLogoUri": "http://dev.virtualearth.net/Branding/logo_powered_by.png",
				"copyright": "Copyright © 2017 Microsoft and its suppliers. All rights reserved. This API cannot be accessed and the content and any results may not be used, reproduced or transmitted in any manner without express written permission from Microsoft Corporation.",
				"entityType": "Address",
				"matchCodes": [
					"Good"
				],
				"name": "4120 Finch Ave E, Scarborough, ON M1S 3T9, Canada",
				"statusCode": 200,
				"statusDescription": "OK",
				"traceId": "1d6cd8eba3824bafbee48424bf09b0e0|BN20130447|7.7.0.0|",
				"addressLine": "4120 Finch Ave E",
				"adminDistrict": "ON",
				"adminDistrict2": "Toronto",
				"countryRegion": "Canada",
				"formattedAddress": "4120 Finch Ave E, Scarborough, ON M1S 3T9, Canada",
				"locality": "Toronto",
				"neighborhood": "Milliken",
				"postalCode": "M1S 3T9"
			},
			"geometry": {
				"type": "Point",
				"coordinates": [
					-79.29113,
					43.80342
				]
			},
			"bbox": [
				-79.2926876,
				43.8022958,
				-79.2895724,
				43.8045442
			]
		}
	]
}
