{
	"type": "FeatureCollection",
	"features": [
		{
			"type": "Feature",
			"properties": {
				"confidence": 9,
				"authenticationResultCode": "ValidCredentials",
				"brandLogoUri": "http://dev.virtualearth.net/Branding/logo_powered_by.png",
				"copyright": "Copyright © 2017 Microsoft and its suppliers. All rights reserved. This API cannot be accessed and the content and any results may not be used, reproduced or transmitted in any manner without express written permission from Microsoft Corporation.",
				"entityType": "Address",
				"matchCodes": [
					"Good"
				],
				"name": "4136 Varden Ct, Mississauga, ON L5L 4A7, Canada",
				"statusCode": 200,
				"statusDescription": "OK",
				"traceId": "4490932e0e8a4c53bf3c154f6033d581|BN20200239|7.7.0.0|",
				"addressLine": "4136 Varden Ct",
				"adminDistrict": "ON",
				"adminDistrict2": "Peel",
				"countryRegion": "Canada",
				"formattedAddress": "4136 Varden Ct, Mississauga, ON L5L 4A7, Canada",
				"locality": "Mississauga",
				"neighborhood": "Erin Mills",
				"postalCode": "L5L 4A7"
			},
			"geometry": {
				"type": "Point",
				"coordinates": [
					-79.70987,
					43.53357
				]
			},
			"bbox": [
				-79.7114206,
				43.5324458,
				-79.7083194,
				43.5346942
			]
		}
	]
}
