{
	"type": "FeatureCollection",
	"features": [
		{
			"type": "Feature",
			"properties": {
				"confidence": 9,
				"authenticationResultCode": "ValidCredentials",
				"brandLogoUri": "http://dev.virtualearth.net/Branding/logo_powered_by.png",
				"copyright": "Copyright © 2017 Microsoft and its suppliers. All rights reserved. This API cannot be accessed and the content and any results may not be used, reproduced or transmitted in any manner without express written permission from Microsoft Corporation.",
				"entityType": "Address",
				"matchCodes": [
					"Good"
				],
				"name": "42 Florence St, Toronto, ON M6K 1P5, Canada",
				"statusCode": 200,
				"statusDescription": "OK",
				"traceId": "168370ed9bed4adf81928475968c0f65|BN20130721|7.7.0.0|",
				"addressLine": "42 Florence St",
				"adminDistrict": "ON",
				"adminDistrict2": "Toronto",
				"countryRegion": "Canada",
				"formattedAddress": "42 Florence St, Toronto, ON M6K 1P5, Canada",
				"locality": "Toronto",
				"neighborhood": "Little Portugal",
				"postalCode": "M6K 1P5"
			},
			"geometry": {
				"type": "Point",
				"coordinates": [
					-79.43243,
					43.64565
				]
			},
			"bbox": [
				-79.4339835,
				43.6445258,
				-79.4308765,
				43.6467742
			]
		}
	]
}
