{
	"type": "FeatureCollection",
	"features": [
		{
			"type": "Feature",
			"properties": {
				"confidence": 9,
				"authenticationResultCode": "ValidCredentials",
				"brandLogoUri": "http://dev.virtualearth.net/Branding/logo_powered_by.png",
				"copyright": "Copyright © 2017 Microsoft and its suppliers. All rights reserved. This API cannot be accessed and the content and any results may not be used, reproduced or transmitted in any manner without express written permission from Microsoft Corporation.",
				"entityType": "Address",
				"matchCodes": [
					"Good"
				],
				"name": "42 Saddlebrook St, Nepean, ON K2G 5N4, Canada",
				"statusCode": 200,
				"statusDescription": "OK",
				"traceId": "43dc682c805847fe995b018c2a2ed52c|BN20210145|7.7.0.0|",
				"addressLine": "42 Saddlebrook St",
				"adminDistrict": "ON",
				"adminDistrict2": "Ottawa",
				"countryRegion": "Canada",
				"formattedAddress": "42 Saddlebrook St, Nepean, ON K2G 5N4, Canada",
				"locality": "Ottawa",
				"neighborhood": "Nepean",
				"postalCode": "K2G 5N4"
			},
			"geometry": {
				"type": "Point",
				"coordinates": [
					-75.77316,
					45.33659
				]
			},
			"bbox": [
				-75.7747592,
				45.3354658,
				-75.7715608,
				45.3377142
			]
		}
	]
}
