{
	"type": "FeatureCollection",
	"features": [
		{
			"type": "Feature",
			"properties": {
				"confidence": 9,
				"authenticationResultCode": "ValidCredentials",
				"brandLogoUri": "http://dev.virtualearth.net/Branding/logo_powered_by.png",
				"copyright": "Copyright © 2017 Microsoft and its suppliers. All rights reserved. This API cannot be accessed and the content and any results may not be used, reproduced or transmitted in any manner without express written permission from Microsoft Corporation.",
				"entityType": "Address",
				"matchCodes": [
					"Good"
				],
				"name": "420 Wilsey Rd, Fredericton, NB E3B 6E9, Canada",
				"statusCode": 200,
				"statusDescription": "OK",
				"traceId": "5d875a2608b94e978fefcc0439760249|BN20210145|7.7.0.0|",
				"addressLine": "420 Wilsey Rd",
				"adminDistrict": "NB",
				"adminDistrict2": "York",
				"countryRegion": "Canada",
				"formattedAddress": "420 Wilsey Rd, Fredericton, NB E3B 6E9, Canada",
				"locality": "Fredericton",
				"postalCode": "E3B 6E9"
			},
			"geometry": {
				"type": "Point",
				"coordinates": [
					-66.6182,
					45.91834
				]
			},
			"bbox": [
				-66.6198159,
				45.9172158,
				-66.6165841,
				45.9194642
			]
		}
	]
}
