{
	"type": "FeatureCollection",
	"features": [
		{
			"type": "Feature",
			"properties": {
				"confidence": 9,
				"authenticationResultCode": "ValidCredentials",
				"brandLogoUri": "http://dev.virtualearth.net/Branding/logo_powered_by.png",
				"copyright": "Copyright © 2017 Microsoft and its suppliers. All rights reserved. This API cannot be accessed and the content and any results may not be used, reproduced or transmitted in any manner without express written permission from Microsoft Corporation.",
				"entityType": "Address",
				"matchCodes": [
					"Good"
				],
				"name": "4200 Fairview St, Burlington, ON L7L 4Y8, Canada",
				"statusCode": 200,
				"statusDescription": "OK",
				"traceId": "3b478a03f6e248059deeef54ed7e9c95|BN20121762|7.7.0.0|",
				"addressLine": "4200 Fairview St",
				"adminDistrict": "ON",
				"adminDistrict2": "Halton",
				"countryRegion": "Canada",
				"formattedAddress": "4200 Fairview St, Burlington, ON L7L 4Y8, Canada",
				"locality": "Burlington",
				"neighborhood": "Longmoor",
				"postalCode": "L7L 4Y8"
			},
			"geometry": {
				"type": "Point",
				"coordinates": [
					-79.77276,
					43.36496
				]
			},
			"bbox": [
				-79.7743063,
				43.3638358,
				-79.7712137,
				43.3660842
			]
		}
	]
}
