{
	"type": "FeatureCollection",
	"features": [
		{
			"type": "Feature",
			"properties": {
				"confidence": 9,
				"authenticationResultCode": "ValidCredentials",
				"brandLogoUri": "http://dev.virtualearth.net/Branding/logo_powered_by.png",
				"copyright": "Copyright © 2017 Microsoft and its suppliers. All rights reserved. This API cannot be accessed and the content and any results may not be used, reproduced or transmitted in any manner without express written permission from Microsoft Corporation.",
				"entityType": "Address",
				"matchCodes": [
					"Good"
				],
				"name": "421 Lahave St, Bridgewater, NS B4V 3A2, Canada",
				"statusCode": 200,
				"statusDescription": "OK",
				"traceId": "c2f71090103044cda76960f000610185|BN20130632|7.7.0.0|",
				"addressLine": "421 Lahave St",
				"adminDistrict": "NS",
				"adminDistrict2": "Lunenburg",
				"countryRegion": "Canada",
				"formattedAddress": "421 Lahave St, Bridgewater, NS B4V 3A2, Canada",
				"locality": "Bridgewater",
				"postalCode": "B4V 3A2"
			},
			"geometry": {
				"type": "Point",
				"coordinates": [
					-64.51561,
					44.37723
				]
			},
			"bbox": [
				-64.5171828,
				44.3761058,
				-64.5140372,
				44.3783542
			]
		}
	]
}
