{
	"type": "FeatureCollection",
	"features": [
		{
			"type": "Feature",
			"properties": {
				"confidence": 9,
				"authenticationResultCode": "ValidCredentials",
				"brandLogoUri": "http://dev.virtualearth.net/Branding/logo_powered_by.png",
				"copyright": "Copyright © 2017 Microsoft and its suppliers. All rights reserved. This API cannot be accessed and the content and any results may not be used, reproduced or transmitted in any manner without express written permission from Microsoft Corporation.",
				"entityType": "Address",
				"matchCodes": [
					"Good"
				],
				"name": "4212 Fieldstone Ave, Niagara Falls, ON L2H 2V4, Canada",
				"statusCode": 200,
				"statusDescription": "OK",
				"traceId": "a1c46d6db7584ef9a05f2f4ba56c440d|BN20130632|7.7.0.0|",
				"addressLine": "4212 Fieldstone Ave",
				"adminDistrict": "ON",
				"adminDistrict2": "Niagara",
				"countryRegion": "Canada",
				"formattedAddress": "4212 Fieldstone Ave, Niagara Falls, ON L2H 2V4, Canada",
				"locality": "Niagara Falls",
				"postalCode": "L2H 2V4"
			},
			"geometry": {
				"type": "Point",
				"coordinates": [
					-79.12996,
					43.11153
				]
			},
			"bbox": [
				-79.1314999,
				43.1104058,
				-79.1284201,
				43.1126542
			]
		}
	]
}
