{
	"type": "FeatureCollection",
	"features": [
		{
			"type": "Feature",
			"properties": {
				"confidence": 9,
				"authenticationResultCode": "ValidCredentials",
				"brandLogoUri": "http://dev.virtualearth.net/Branding/logo_powered_by.png",
				"copyright": "Copyright © 2017 Microsoft and its suppliers. All rights reserved. This API cannot be accessed and the content and any results may not be used, reproduced or transmitted in any manner without express written permission from Microsoft Corporation.",
				"entityType": "Address",
				"matchCodes": [
					"Good"
				],
				"name": "422 Richards St, Vancouver, BC V6B 2Z3, Canada",
				"statusCode": 200,
				"statusDescription": "OK",
				"traceId": "3ab0ff085c734888baba2a5715be1e8e|BN20300154|7.7.0.0|",
				"addressLine": "422 Richards St",
				"adminDistrict": "BC",
				"adminDistrict2": "Greater Vancouver",
				"countryRegion": "Canada",
				"formattedAddress": "422 Richards St, Vancouver, BC V6B 2Z3, Canada",
				"locality": "Vancouver",
				"neighborhood": "Downtown",
				"postalCode": "V6B 2Z3"
			},
			"geometry": {
				"type": "Point",
				"coordinates": [
					-123.11206,
					49.28375
				]
			},
			"bbox": [
				-123.1137833,
				49.2826258,
				-123.1103367,
				49.2848742
			]
		}
	]
}
