{
	"type": "FeatureCollection",
	"features": [
		{
			"type": "Feature",
			"properties": {
				"confidence": 9,
				"authenticationResultCode": "ValidCredentials",
				"brandLogoUri": "http://dev.virtualearth.net/Branding/logo_powered_by.png",
				"copyright": "Copyright © 2017 Microsoft and its suppliers. All rights reserved. This API cannot be accessed and the content and any results may not be used, reproduced or transmitted in any manner without express written permission from Microsoft Corporation.",
				"entityType": "Address",
				"matchCodes": [
					"Good"
				],
				"name": "423 Dakota Rd, Colchester, NS B0M, Canada",
				"statusCode": 200,
				"statusDescription": "OK",
				"traceId": "c9fdde1f64c1456b9c132c4a336420a3|BN20130442|7.7.0.0|",
				"addressLine": "423 Dakota Rd",
				"adminDistrict": "NS",
				"adminDistrict2": "Colchester",
				"countryRegion": "Canada",
				"formattedAddress": "423 Dakota Rd, Colchester, NS B0M, Canada",
				"locality": "Colchester",
				"neighborhood": "Debert",
				"postalCode": "B0M 1G0"
			},
			"geometry": {
				"type": "Point",
				"coordinates": [
					-63.4511065,
					45.4464584
				]
			},
			"bbox": [
				-63.4527088,
				45.4453343,
				-63.4495042,
				45.4475826
			]
		}
	]
}
