{
	"type": "FeatureCollection",
	"features": [
		{
			"type": "Feature",
			"properties": {
				"confidence": 9,
				"authenticationResultCode": "ValidCredentials",
				"brandLogoUri": "http://dev.virtualearth.net/Branding/logo_powered_by.png",
				"copyright": "Copyright © 2017 Microsoft and its suppliers. All rights reserved. This API cannot be accessed and the content and any results may not be used, reproduced or transmitted in any manner without express written permission from Microsoft Corporation.",
				"entityType": "Address",
				"matchCodes": [
					"Good"
				],
				"name": "425 3e Rue, Chibougamau, QC G8P 1N6, Canada",
				"statusCode": 200,
				"statusDescription": "OK",
				"traceId": "9c1d4be39fa0442b8115b4fd9e529e2d|BN20130621|7.7.0.0|",
				"addressLine": "425 3e Rue",
				"adminDistrict": "QC",
				"adminDistrict2": "Baie-James",
				"countryRegion": "Canada",
				"formattedAddress": "425 3e Rue, Chibougamau, QC G8P 1N6, Canada",
				"locality": "Chibougamau",
				"postalCode": "G8P 1N6"
			},
			"geometry": {
				"type": "Point",
				"coordinates": [
					-74.36072,
					49.91393
				]
			},
			"bbox": [
				-74.3624657,
				49.9128058,
				-74.3589743,
				49.9150542
			]
		}
	]
}
