{
	"type": "FeatureCollection",
	"features": [
		{
			"type": "Feature",
			"properties": {
				"confidence": 9,
				"authenticationResultCode": "ValidCredentials",
				"brandLogoUri": "http://dev.virtualearth.net/Branding/logo_powered_by.png",
				"copyright": "Copyright © 2017 Microsoft and its suppliers. All rights reserved. This API cannot be accessed and the content and any results may not be used, reproduced or transmitted in any manner without express written permission from Microsoft Corporation.",
				"entityType": "Address",
				"matchCodes": [
					"Good"
				],
				"name": "4254 Chesswood Dr, North York, ON M3J 2B9, Canada",
				"statusCode": 200,
				"statusDescription": "OK",
				"traceId": "e160b913534742c291b2428b39ea12d9|BN20121762|7.7.0.0|",
				"addressLine": "4254 Chesswood Dr",
				"adminDistrict": "ON",
				"adminDistrict2": "Toronto",
				"countryRegion": "Canada",
				"formattedAddress": "4254 Chesswood Dr, North York, ON M3J 2B9, Canada",
				"locality": "Toronto",
				"neighborhood": "York University Heights",
				"postalCode": "M3J 2B9"
			},
			"geometry": {
				"type": "Point",
				"coordinates": [
					-79.47874,
					43.7602199
				]
			},
			"bbox": [
				-79.4802965,
				43.7590957,
				-79.4771835,
				43.7613441
			]
		}
	]
}
