{
	"type": "FeatureCollection",
	"features": [
		{
			"type": "Feature",
			"properties": {
				"confidence": 9,
				"authenticationResultCode": "ValidCredentials",
				"brandLogoUri": "http://dev.virtualearth.net/Branding/logo_powered_by.png",
				"copyright": "Copyright © 2017 Microsoft and its suppliers. All rights reserved. This API cannot be accessed and the content and any results may not be used, reproduced or transmitted in any manner without express written permission from Microsoft Corporation.",
				"entityType": "Address",
				"matchCodes": [
					"Good"
				],
				"name": "43 Pine Glen Rd, Riverview, NB E1B 1V3, Canada",
				"statusCode": 200,
				"statusDescription": "OK",
				"traceId": "e22237f6203f49d08c4f66aa8b155833|BN20130719|7.7.0.0|",
				"addressLine": "43 Pine Glen Rd",
				"adminDistrict": "NB",
				"adminDistrict2": "Albert",
				"countryRegion": "Canada",
				"formattedAddress": "43 Pine Glen Rd, Riverview, NB E1B 1V3, Canada",
				"locality": "Riverview",
				"postalCode": "E1B 1V3"
			},
			"geometry": {
				"type": "Point",
				"coordinates": [
					-64.79401,
					46.06653
				]
			},
			"bbox": [
				-64.7956302,
				46.0654058,
				-64.7923898,
				46.0676542
			]
		}
	]
}
