{
	"type": "FeatureCollection",
	"features": [
		{
			"type": "Feature",
			"properties": {
				"confidence": 9,
				"authenticationResultCode": "ValidCredentials",
				"brandLogoUri": "http://dev.virtualearth.net/Branding/logo_powered_by.png",
				"copyright": "Copyright © 2017 Microsoft and its suppliers. All rights reserved. This API cannot be accessed and the content and any results may not be used, reproduced or transmitted in any manner without express written permission from Microsoft Corporation.",
				"entityType": "Address",
				"matchCodes": [
					"Good"
				],
				"name": "43 Rue Forget, Repentigny, QC J6A 4M4, Canada",
				"statusCode": 200,
				"statusDescription": "OK",
				"traceId": "df4956b4316f4bc48c50bd5071892bb2|BN20190653|7.7.0.0|",
				"addressLine": "43 Rue Forget",
				"adminDistrict": "QC",
				"adminDistrict2": "L'Assomption",
				"countryRegion": "Canada",
				"formattedAddress": "43 Rue Forget, Repentigny, QC J6A 4M4, Canada",
				"locality": "Repentigny",
				"postalCode": "J6A 4M4"
			},
			"geometry": {
				"type": "Point",
				"coordinates": [
					-73.45191,
					45.73852
				]
			},
			"bbox": [
				-73.4535207,
				45.7373958,
				-73.4502993,
				45.7396442
			]
		}
	]
}
