{
	"type": "FeatureCollection",
	"features": [
		{
			"type": "Feature",
			"properties": {
				"confidence": 9,
				"authenticationResultCode": "ValidCredentials",
				"brandLogoUri": "http://dev.virtualearth.net/Branding/logo_powered_by.png",
				"copyright": "Copyright © 2017 Microsoft and its suppliers. All rights reserved. This API cannot be accessed and the content and any results may not be used, reproduced or transmitted in any manner without express written permission from Microsoft Corporation.",
				"entityType": "Address",
				"matchCodes": [
					"Good"
				],
				"name": "430 Steelcase Rd E, Markham, ON L3R 1G2, Canada",
				"statusCode": 200,
				"statusDescription": "OK",
				"traceId": "e621f0cd3f24480294f6fe7bcda6a27a|BN20130522|7.7.0.0|",
				"addressLine": "430 Steelcase Rd E",
				"adminDistrict": "ON",
				"adminDistrict2": "York",
				"countryRegion": "Canada",
				"formattedAddress": "430 Steelcase Rd E, Markham, ON L3R 1G2, Canada",
				"locality": "Markham",
				"postalCode": "L3R 1G2"
			},
			"geometry": {
				"type": "Point",
				"coordinates": [
					-79.33822,
					43.82318
				]
			},
			"bbox": [
				-79.3397781,
				43.8220558,
				-79.3366619,
				43.8243042
			]
		}
	]
}
