{
	"type": "FeatureCollection",
	"features": [
		{
			"type": "Feature",
			"properties": {
				"confidence": 9,
				"authenticationResultCode": "ValidCredentials",
				"brandLogoUri": "http://dev.virtualearth.net/Branding/logo_powered_by.png",
				"copyright": "Copyright © 2017 Microsoft and its suppliers. All rights reserved. This API cannot be accessed and the content and any results may not be used, reproduced or transmitted in any manner without express written permission from Microsoft Corporation.",
				"entityType": "Address",
				"matchCodes": [
					"Good"
				],
				"name": "431114 19th Line, East Garafraxa, ON L9W 7E4, Canada",
				"statusCode": 200,
				"statusDescription": "OK",
				"traceId": "5e9d841b12c048e88ef816aaa541b2a2|BN20290118|7.7.0.0|",
				"addressLine": "431114 19th Line",
				"adminDistrict": "ON",
				"adminDistrict2": "Dufferin",
				"countryRegion": "Canada",
				"formattedAddress": "431114 19th Line, East Garafraxa, ON L9W 7E4, Canada",
				"locality": "East Garafraxa",
				"postalCode": "L9W 7E4"
			},
			"geometry": {
				"type": "Point",
				"coordinates": [
					-80.1480933,
					43.8764618
				]
			},
			"bbox": [
				-80.1496528,
				43.8753377,
				-80.1465338,
				43.877586
			]
		}
	]
}
