{
	"type": "FeatureCollection",
	"features": [
		{
			"type": "Feature",
			"properties": {
				"confidence": 9,
				"authenticationResultCode": "ValidCredentials",
				"brandLogoUri": "http://dev.virtualearth.net/Branding/logo_powered_by.png",
				"copyright": "Copyright © 2017 Microsoft and its suppliers. All rights reserved. This API cannot be accessed and the content and any results may not be used, reproduced or transmitted in any manner without express written permission from Microsoft Corporation.",
				"entityType": "Address",
				"matchCodes": [
					"Good"
				],
				"name": "4324 Roy Ave, Hanmer, ON P3P 1M5, Canada",
				"statusCode": 200,
				"statusDescription": "OK",
				"traceId": "029f19b612484fc1879d32e0cbec466d|BN20280152|7.7.0.0|",
				"addressLine": "4324 Roy Ave",
				"adminDistrict": "ON",
				"adminDistrict2": "Greater Sudbury",
				"countryRegion": "Canada",
				"formattedAddress": "4324 Roy Ave, Hanmer, ON P3P 1M5, Canada",
				"locality": "Greater Sudbury",
				"neighborhood": "Hanmer",
				"postalCode": "P3P 1M5"
			},
			"geometry": {
				"type": "Point",
				"coordinates": [
					-80.9353299,
					46.64635
				]
			},
			"bbox": [
				-80.9369674,
				46.6452258,
				-80.9336924,
				46.6474742
			]
		}
	]
}
