{
	"type": "FeatureCollection",
	"features": [
		{
			"type": "Feature",
			"properties": {
				"confidence": 9,
				"authenticationResultCode": "ValidCredentials",
				"brandLogoUri": "http://dev.virtualearth.net/Branding/logo_powered_by.png",
				"copyright": "Copyright © 2017 Microsoft and its suppliers. All rights reserved. This API cannot be accessed and the content and any results may not be used, reproduced or transmitted in any manner without express written permission from Microsoft Corporation.",
				"entityType": "Address",
				"matchCodes": [
					"Good"
				],
				"name": "4369 Poplar Ridge Rd, Central Kootenay, BC V0G 1H1, Canada",
				"statusCode": 200,
				"statusDescription": "OK",
				"traceId": "7a0f360dd4534e358f0b5fd82bfa10ed|BN20200137|7.7.0.0|",
				"addressLine": "4369 Poplar Ridge Rd",
				"adminDistrict": "BC",
				"adminDistrict2": "Central Kootenay",
				"countryRegion": "Canada",
				"formattedAddress": "4369 Poplar Ridge Rd, Central Kootenay, BC V0G 1H1, Canada",
				"locality": "Central Kootenay",
				"neighborhood": "Central Kootenay",
				"postalCode": "V0G 1H1"
			},
			"geometry": {
				"type": "Point",
				"coordinates": [
					-117.57874,
					49.4683599
				]
			},
			"bbox": [
				-117.5804698,
				49.4672357,
				-117.5770102,
				49.4694841
			]
		}
	]
}
