{
	"type": "FeatureCollection",
	"features": [
		{
			"type": "Feature",
			"properties": {
				"confidence": 9,
				"authenticationResultCode": "ValidCredentials",
				"brandLogoUri": "http://dev.virtualearth.net/Branding/logo_powered_by.png",
				"copyright": "Copyright © 2017 Microsoft and its suppliers. All rights reserved. This API cannot be accessed and the content and any results may not be used, reproduced or transmitted in any manner without express written permission from Microsoft Corporation.",
				"entityType": "Address",
				"matchCodes": [
					"Good"
				],
				"name": "442 Avenue Willow, Shawinigan, QC G9N 1X2, Canada",
				"statusCode": 200,
				"statusDescription": "OK",
				"traceId": "a3387aa3fc184c36a907fe9d4e2dc368|BN20200137|7.7.0.0|",
				"addressLine": "442 Avenue Willow",
				"adminDistrict": "QC",
				"adminDistrict2": "Shawinigan",
				"countryRegion": "Canada",
				"formattedAddress": "442 Avenue Willow, Shawinigan, QC G9N 1X2, Canada",
				"locality": "Shawinigan",
				"postalCode": "G9N 1X2"
			},
			"geometry": {
				"type": "Point",
				"coordinates": [
					-72.75316,
					46.5404
				]
			},
			"bbox": [
				-72.7547943,
				46.5392758,
				-72.7515257,
				46.5415242
			]
		}
	]
}
