{
	"type": "FeatureCollection",
	"features": [
		{
			"type": "Feature",
			"properties": {
				"confidence": 9,
				"authenticationResultCode": "ValidCredentials",
				"brandLogoUri": "http://dev.virtualearth.net/Branding/logo_powered_by.png",
				"copyright": "Copyright © 2017 Microsoft and its suppliers. All rights reserved. This API cannot be accessed and the content and any results may not be used, reproduced or transmitted in any manner without express written permission from Microsoft Corporation.",
				"entityType": "Address",
				"matchCodes": [
					"Good"
				],
				"name": "4428 CR-121, Minden Hills, ON K0M, Canada",
				"statusCode": 200,
				"statusDescription": "OK",
				"traceId": "f38ea058a3a94f5e907337655a67ed47|BN20190653|7.7.0.0|",
				"addressLine": "4428 CR-121",
				"adminDistrict": "ON",
				"adminDistrict2": "Haliburton",
				"countryRegion": "Canada",
				"formattedAddress": "4428 CR-121, Minden Hills, ON K0M, Canada",
				"locality": "Minden Hills",
				"postalCode": "K0M 2A0"
			},
			"geometry": {
				"type": "Point",
				"coordinates": [
					-78.6588777,
					44.8007236
				]
			},
			"bbox": [
				-78.660462,
				44.7995995,
				-78.6572934,
				44.8018478
			]
		}
	]
}
