{
	"type": "FeatureCollection",
	"features": [
		{
			"type": "Feature",
			"properties": {
				"confidence": 9,
				"authenticationResultCode": "ValidCredentials",
				"brandLogoUri": "http://dev.virtualearth.net/Branding/logo_powered_by.png",
				"copyright": "Copyright © 2017 Microsoft and its suppliers. All rights reserved. This API cannot be accessed and the content and any results may not be used, reproduced or transmitted in any manner without express written permission from Microsoft Corporation.",
				"entityType": "Address",
				"matchCodes": [
					"Good"
				],
				"name": "444 Hollandview Trl, Aurora, ON L4G 7Z9, Canada",
				"statusCode": 200,
				"statusDescription": "OK",
				"traceId": "1d82858723b24f6cbb44e1ebdbbd9564|BN20260223|7.7.0.0|",
				"addressLine": "444 Hollandview Trl",
				"adminDistrict": "ON",
				"adminDistrict2": "York",
				"countryRegion": "Canada",
				"formattedAddress": "444 Hollandview Trl, Aurora, ON L4G 7Z9, Canada",
				"locality": "Aurora",
				"postalCode": "L4G 7Z9"
			},
			"geometry": {
				"type": "Point",
				"coordinates": [
					-79.4484,
					44.01561
				]
			},
			"bbox": [
				-79.4499632,
				44.0144858,
				-79.4468368,
				44.0167342
			]
		}
	]
}
