{
	"type": "FeatureCollection",
	"features": [
		{
			"type": "Feature",
			"properties": {
				"confidence": 9,
				"authenticationResultCode": "ValidCredentials",
				"brandLogoUri": "http://dev.virtualearth.net/Branding/logo_powered_by.png",
				"copyright": "Copyright © 2017 Microsoft and its suppliers. All rights reserved. This API cannot be accessed and the content and any results may not be used, reproduced or transmitted in any manner without express written permission from Microsoft Corporation.",
				"entityType": "Address",
				"matchCodes": [
					"Good"
				],
				"name": "4451 54 Ave SE, Calgary, AB T2C 2A2, Canada",
				"statusCode": 200,
				"statusDescription": "OK",
				"traceId": "5f77771591414b72be4094270e885a3a|BN20121764|7.7.0.0|",
				"addressLine": "4451 54 Ave SE",
				"adminDistrict": "AB",
				"adminDistrict2": "Alberta",
				"countryRegion": "Canada",
				"formattedAddress": "4451 54 Ave SE, Calgary, AB T2C 2A2, Canada",
				"locality": "Calgary",
				"neighborhood": "Foothills",
				"postalCode": "T2C 2A2"
			},
			"geometry": {
				"type": "Point",
				"coordinates": [
					-113.97105,
					51.00354
				]
			},
			"bbox": [
				-113.9728364,
				51.0024158,
				-113.9692636,
				51.0046642
			]
		}
	]
}
