{
	"type": "FeatureCollection",
	"features": [
		{
			"type": "Feature",
			"properties": {
				"confidence": 9,
				"authenticationResultCode": "ValidCredentials",
				"brandLogoUri": "http://dev.virtualearth.net/Branding/logo_powered_by.png",
				"copyright": "Copyright © 2017 Microsoft and its suppliers. All rights reserved. This API cannot be accessed and the content and any results may not be used, reproduced or transmitted in any manner without express written permission from Microsoft Corporation.",
				"entityType": "Address",
				"matchCodes": [
					"Good"
				],
				"name": "4481 Concord Pl, Burlington, ON L7L 1J5, Canada",
				"statusCode": 200,
				"statusDescription": "OK",
				"traceId": "d3ec8b5e3ecb494782904fceee5ff56a|BN20280152|7.7.0.0|",
				"addressLine": "4481 Concord Pl",
				"adminDistrict": "ON",
				"adminDistrict2": "Halton",
				"countryRegion": "Canada",
				"formattedAddress": "4481 Concord Pl, Burlington, ON L7L 1J5, Canada",
				"locality": "Burlington",
				"neighborhood": "Shoreacres",
				"postalCode": "L7L 1J5"
			},
			"geometry": {
				"type": "Point",
				"coordinates": [
					-79.74912,
					43.36147
				]
			},
			"bbox": [
				-79.7506662,
				43.3603458,
				-79.7475738,
				43.3625942
			]
		}
	]
}
