{
	"type": "FeatureCollection",
	"features": [
		{
			"type": "Feature",
			"properties": {
				"confidence": 9,
				"authenticationResultCode": "ValidCredentials",
				"brandLogoUri": "http://dev.virtualearth.net/Branding/logo_powered_by.png",
				"copyright": "Copyright © 2017 Microsoft and its suppliers. All rights reserved. This API cannot be accessed and the content and any results may not be used, reproduced or transmitted in any manner without express written permission from Microsoft Corporation.",
				"entityType": "Address",
				"matchCodes": [
					"Good"
				],
				"name": "449 Martin Ave, New Glasgow, NS B2H 1R8, Canada",
				"statusCode": 200,
				"statusDescription": "OK",
				"traceId": "c7f2dc3d5e7344789011cd128aba2a3b|BN20200137|7.7.0.0|",
				"addressLine": "449 Martin Ave",
				"adminDistrict": "NS",
				"adminDistrict2": "Pictou",
				"countryRegion": "Canada",
				"formattedAddress": "449 Martin Ave, New Glasgow, NS B2H 1R8, Canada",
				"locality": "New Glasgow",
				"postalCode": "B2H 1R8"
			},
			"geometry": {
				"type": "Point",
				"coordinates": [
					-62.6588685,
					45.5999526
				]
			},
			"bbox": [
				-62.6604752,
				45.5988284,
				-62.6572618,
				45.6010767
			]
		}
	]
}
