{
	"type": "FeatureCollection",
	"features": [
		{
			"type": "Feature",
			"properties": {
				"confidence": 9,
				"authenticationResultCode": "ValidCredentials",
				"brandLogoUri": "http://dev.virtualearth.net/Branding/logo_powered_by.png",
				"copyright": "Copyright © 2017 Microsoft and its suppliers. All rights reserved. This API cannot be accessed and the content and any results may not be used, reproduced or transmitted in any manner without express written permission from Microsoft Corporation.",
				"entityType": "Address",
				"matchCodes": [
					"Good"
				],
				"name": "45 Red Maple Rd, Richmond Hill, ON L4B 4M6, Canada",
				"statusCode": 200,
				"statusDescription": "OK",
				"traceId": "2976e59b17fd4e068cf2306b48cb42ce|BN20121763|7.7.0.0|",
				"addressLine": "45 Red Maple Rd",
				"adminDistrict": "ON",
				"adminDistrict2": "York",
				"countryRegion": "Canada",
				"formattedAddress": "45 Red Maple Rd, Richmond Hill, ON L4B 4M6, Canada",
				"locality": "Richmond Hill",
				"postalCode": "L4B 4M6"
			},
			"geometry": {
				"type": "Point",
				"coordinates": [
					-79.42242,
					43.84124
				]
			},
			"bbox": [
				-79.4239786,
				43.8401158,
				-79.4208614,
				43.8423642
			]
		}
	]
}
