{
	"type": "FeatureCollection",
	"features": [
		{
			"type": "Feature",
			"properties": {
				"confidence": 9,
				"authenticationResultCode": "ValidCredentials",
				"brandLogoUri": "http://dev.virtualearth.net/Branding/logo_powered_by.png",
				"copyright": "Copyright © 2017 Microsoft and its suppliers. All rights reserved. This API cannot be accessed and the content and any results may not be used, reproduced or transmitted in any manner without express written permission from Microsoft Corporation.",
				"entityType": "Address",
				"matchCodes": [
					"Good"
				],
				"name": "4505 101 St NW, Edmonton, AB T6E 5C6, Canada",
				"statusCode": 200,
				"statusDescription": "OK",
				"traceId": "97e250d57a944018b41b34c809005448|BN20181720|7.7.0.0|",
				"addressLine": "4505 101 St NW",
				"adminDistrict": "AB",
				"adminDistrict2": "Alberta",
				"countryRegion": "Canada",
				"formattedAddress": "4505 101 St NW, Edmonton, AB T6E 5C6, Canada",
				"locality": "Edmonton",
				"neighborhood": "Papaschase Industrial",
				"postalCode": "T6E 5C6"
			},
			"geometry": {
				"type": "Point",
				"coordinates": [
					-113.48893,
					53.48334
				]
			},
			"bbox": [
				-113.4908192,
				53.4822158,
				-113.4870408,
				53.4844642
			]
		}
	]
}
