{
	"type": "FeatureCollection",
	"features": [
		{
			"type": "Feature",
			"properties": {
				"confidence": 7,
				"authenticationResultCode": "ValidCredentials",
				"brandLogoUri": "http://dev.virtualearth.net/Branding/logo_powered_by.png",
				"copyright": "Copyright © 2017 Microsoft and its suppliers. All rights reserved. This API cannot be accessed and the content and any results may not be used, reproduced or transmitted in any manner without express written permission from Microsoft Corporation.",
				"entityType": "Postcode1",
				"matchCodes": [
					"UpHierarchy"
				],
				"name": "Marchand, R0A 0Z0, Canada",
				"statusCode": 200,
				"statusDescription": "OK",
				"traceId": "dc9691b69ba44c67ad91b4c1f609a1e7|BN20130442|7.7.0.0|",
				"adminDistrict": "MB",
				"countryRegion": "Canada",
				"formattedAddress": "Marchand, R0A 0Z0, Canada",
				"locality": "Marchand",
				"postalCode": "R0A 0Z0"
			},
			"geometry": {
				"type": "Point",
				"coordinates": [
					-96.4034118652344,
					49.4439811706543
				]
			},
			"bbox": [
				-96.411332434509,
				49.4401184530836,
				-96.3954912959597,
				49.447843888225
			]
		}
	]
}
