{
	"type": "FeatureCollection",
	"features": [
		{
			"type": "Feature",
			"properties": {
				"confidence": 9,
				"authenticationResultCode": "ValidCredentials",
				"brandLogoUri": "http://dev.virtualearth.net/Branding/logo_powered_by.png",
				"copyright": "Copyright © 2017 Microsoft and its suppliers. All rights reserved. This API cannot be accessed and the content and any results may not be used, reproduced or transmitted in any manner without express written permission from Microsoft Corporation.",
				"entityType": "Address",
				"matchCodes": [
					"Good"
				],
				"name": "452 Oakwood Pl SW, Calgary, AB T2V 1R6, Canada",
				"statusCode": 200,
				"statusDescription": "OK",
				"traceId": "ca2635875b4c43fabc088439d4a78c28|BN20121762|7.7.0.0|",
				"addressLine": "452 Oakwood Pl SW",
				"adminDistrict": "AB",
				"adminDistrict2": "Alberta",
				"countryRegion": "Canada",
				"formattedAddress": "452 Oakwood Pl SW, Calgary, AB T2V 1R6, Canada",
				"locality": "Calgary",
				"neighborhood": "Oakridge",
				"postalCode": "T2V 1R6"
			},
			"geometry": {
				"type": "Point",
				"coordinates": [
					-114.13458,
					50.96562
				]
			},
			"bbox": [
				-114.136365,
				50.9644958,
				-114.132795,
				50.9667442
			]
		}
	]
}
