{
	"type": "FeatureCollection",
	"features": [
		{
			"type": "Feature",
			"properties": {
				"confidence": 7,
				"authenticationResultCode": "ValidCredentials",
				"brandLogoUri": "http://dev.virtualearth.net/Branding/logo_powered_by.png",
				"copyright": "Copyright © 2017 Microsoft and its suppliers. All rights reserved. This API cannot be accessed and the content and any results may not be used, reproduced or transmitted in any manner without express written permission from Microsoft Corporation.",
				"entityType": "RoadBlock",
				"matchCodes": [
					"Good"
				],
				"name": "10th Ave, New Hazelton, BC V0J, Canada",
				"statusCode": 200,
				"statusDescription": "OK",
				"traceId": "a929ff2076e84fdd907896083597e49a|BN20200239|7.7.0.0|",
				"addressLine": "10th Ave",
				"adminDistrict": "BC",
				"adminDistrict2": "Kitimat-Stikine",
				"countryRegion": "Canada",
				"formattedAddress": "10th Ave, New Hazelton, BC V0J, Canada",
				"locality": "New Hazelton",
				"postalCode": "V0J 2J0"
			},
			"geometry": {
				"type": "Point",
				"coordinates": [
					-127.57741,
					55.24674
				]
			},
			"bbox": [
				-127.60604,
				55.2466,
				-127.56633,
				55.24677
			]
		}
	]
}
