{
	"type": "FeatureCollection",
	"features": [
		{
			"type": "Feature",
			"properties": {
				"confidence": 9,
				"authenticationResultCode": "ValidCredentials",
				"brandLogoUri": "http://dev.virtualearth.net/Branding/logo_powered_by.png",
				"copyright": "Copyright © 2017 Microsoft and its suppliers. All rights reserved. This API cannot be accessed and the content and any results may not be used, reproduced or transmitted in any manner without express written permission from Microsoft Corporation.",
				"entityType": "Address",
				"matchCodes": [
					"Good"
				],
				"name": "4555 Hillbank Rd, Duncan, BC V9L 6M2, Canada",
				"statusCode": 200,
				"statusDescription": "OK",
				"traceId": "d1457e74b25d48c289aea80386c39f44|BN20210145|7.7.0.0|",
				"addressLine": "4555 Hillbank Rd",
				"adminDistrict": "BC",
				"adminDistrict2": "Cowichan Valley",
				"countryRegion": "Canada",
				"formattedAddress": "4555 Hillbank Rd, Duncan, BC V9L 6M2, Canada",
				"locality": "Cowichan Valley",
				"neighborhood": "Duncan",
				"postalCode": "V9L 6M2"
			},
			"geometry": {
				"type": "Point",
				"coordinates": [
					-123.6435383,
					48.7328077
				]
			},
			"bbox": [
				-123.6452426,
				48.7316835,
				-123.6418339,
				48.7339318
			]
		}
	]
}
