{
	"type": "FeatureCollection",
	"features": [
		{
			"type": "Feature",
			"properties": {
				"confidence": 9,
				"authenticationResultCode": "ValidCredentials",
				"brandLogoUri": "http://dev.virtualearth.net/Branding/logo_powered_by.png",
				"copyright": "Copyright © 2017 Microsoft and its suppliers. All rights reserved. This API cannot be accessed and the content and any results may not be used, reproduced or transmitted in any manner without express written permission from Microsoft Corporation.",
				"entityType": "Address",
				"matchCodes": [
					"Good"
				],
				"name": "457 King St, London, ON N6B 1S8, Canada",
				"statusCode": 200,
				"statusDescription": "OK",
				"traceId": "6c97071152484e7eae6db9409ac52eec|BN20200137|7.7.0.0|",
				"addressLine": "457 King St",
				"adminDistrict": "ON",
				"adminDistrict2": "Middlesex",
				"countryRegion": "Canada",
				"formattedAddress": "457 King St, London, ON N6B 1S8, Canada",
				"locality": "London",
				"neighborhood": "Central London",
				"postalCode": "N6B 1S8"
			},
			"geometry": {
				"type": "Point",
				"coordinates": [
					-81.2367,
					42.9856
				]
			},
			"bbox": [
				-81.2382367,
				42.9844758,
				-81.2351633,
				42.9867242
			]
		}
	]
}
