{
	"type": "FeatureCollection",
	"features": [
		{
			"type": "Feature",
			"properties": {
				"confidence": 9,
				"authenticationResultCode": "ValidCredentials",
				"brandLogoUri": "http://dev.virtualearth.net/Branding/logo_powered_by.png",
				"copyright": "Copyright © 2017 Microsoft and its suppliers. All rights reserved. This API cannot be accessed and the content and any results may not be used, reproduced or transmitted in any manner without express written permission from Microsoft Corporation.",
				"entityType": "Address",
				"matchCodes": [
					"Good"
				],
				"name": "457 Tissot St, Winnipeg, MB R2J 0C6, Canada",
				"statusCode": 200,
				"statusDescription": "OK",
				"traceId": "8e685f510851421b8a7fdb1cef23c0eb|BN20130634|7.7.0.0|",
				"addressLine": "457 Tissot St",
				"adminDistrict": "MB",
				"adminDistrict2": "Manitoba",
				"countryRegion": "Canada",
				"formattedAddress": "457 Tissot St, Winnipeg, MB R2J 0C6, Canada",
				"locality": "Winnipeg",
				"neighborhood": "Tissot",
				"postalCode": "R2J 0C6"
			},
			"geometry": {
				"type": "Point",
				"coordinates": [
					-97.1082,
					49.89495
				]
			},
			"bbox": [
				-97.1099451,
				49.8938258,
				-97.1064549,
				49.8960742
			]
		}
	]
}
