{
	"type": "FeatureCollection",
	"features": [
		{
			"type": "Feature",
			"properties": {
				"confidence": 4,
				"authenticationResultCode": "ValidCredentials",
				"brandLogoUri": "http://dev.virtualearth.net/Branding/logo_powered_by.png",
				"copyright": "Copyright © 2017 Microsoft and its suppliers. All rights reserved. This API cannot be accessed and the content and any results may not be used, reproduced or transmitted in any manner without express written permission from Microsoft Corporation.",
				"entityType": "Postcode2",
				"matchCodes": [
					"UpHierarchy"
				],
				"name": "Winnipeg, R2C, Canada",
				"statusCode": 200,
				"statusDescription": "OK",
				"traceId": "4cb660cdc1854348a741503309deb36e|BN20130620|7.7.0.0|",
				"adminDistrict": "MB",
				"countryRegion": "Canada",
				"formattedAddress": "Winnipeg, R2C, Canada",
				"locality": "Winnipeg",
				"postalCode": "R2C"
			},
			"geometry": {
				"type": "Point",
				"coordinates": [
					-97.0131759643555,
					49.8937492370605
				]
			},
			"bbox": [
				-97.0776062011719,
				49.859748840332,
				-96.9554824829102,
				49.9277496337891
			]
		},
		{
			"type": "Feature",
			"properties": {
				"confidence": 7,
				"authenticationResultCode": "ValidCredentials",
				"brandLogoUri": "http://dev.virtualearth.net/Branding/logo_powered_by.png",
				"copyright": "Copyright © 2017 Microsoft and its suppliers. All rights reserved. This API cannot be accessed and the content and any results may not be used, reproduced or transmitted in any manner without express written permission from Microsoft Corporation.",
				"entityType": "Postcode1",
				"matchCodes": [
					"UpHierarchy"
				],
				"name": "Springfield, R2C 2Z2, Canada",
				"statusCode": 200,
				"statusDescription": "OK",
				"traceId": "4cb660cdc1854348a741503309deb36e|BN20130620|7.7.0.0|",
				"adminDistrict": "MB",
				"countryRegion": "Canada",
				"formattedAddress": "Springfield, R2C 2Z2, Canada",
				"locality": "Springfield",
				"postalCode": "R2C 2Z2"
			},
			"geometry": {
				"type": "Point",
				"coordinates": [
					-96.9794006347656,
					49.919807434082
				]
			},
			"bbox": [
				-96.987399088301,
				49.9159447165114,
				-96.9714021812302,
				49.9236701516527
			]
		}
	]
}
