{
	"type": "FeatureCollection",
	"features": [
		{
			"type": "Feature",
			"properties": {
				"confidence": 9,
				"authenticationResultCode": "ValidCredentials",
				"brandLogoUri": "http://dev.virtualearth.net/Branding/logo_powered_by.png",
				"copyright": "Copyright © 2017 Microsoft and its suppliers. All rights reserved. This API cannot be accessed and the content and any results may not be used, reproduced or transmitted in any manner without express written permission from Microsoft Corporation.",
				"entityType": "Address",
				"matchCodes": [
					"Good"
				],
				"name": "46 Rue Railroad, Stanstead, QC J0B 3E2, Canada",
				"statusCode": 200,
				"statusDescription": "OK",
				"traceId": "ccfdbb2807ca482698daba4dd3e78ccc|BN20290118|7.7.0.0|",
				"addressLine": "46 Rue Railroad",
				"adminDistrict": "QC",
				"adminDistrict2": "Memphrémagog",
				"countryRegion": "Canada",
				"formattedAddress": "46 Rue Railroad, Stanstead, QC J0B 3E2, Canada",
				"locality": "Stanstead",
				"neighborhood": "Rock Island",
				"postalCode": "J0B 3E2"
			},
			"geometry": {
				"type": "Point",
				"coordinates": [
					-72.10159,
					45.00663
				]
			},
			"bbox": [
				-72.10318,
				45.0055058,
				-72.1,
				45.0077542
			]
		}
	]
}
