{
	"type": "FeatureCollection",
	"features": [
		{
			"type": "Feature",
			"properties": {
				"confidence": 9,
				"authenticationResultCode": "ValidCredentials",
				"brandLogoUri": "http://dev.virtualearth.net/Branding/logo_powered_by.png",
				"copyright": "Copyright © 2017 Microsoft and its suppliers. All rights reserved. This API cannot be accessed and the content and any results may not be used, reproduced or transmitted in any manner without express written permission from Microsoft Corporation.",
				"entityType": "Address",
				"matchCodes": [
					"Good"
				],
				"name": "460 Main St W, Hamilton, ON L8P 1K7, Canada",
				"statusCode": 200,
				"statusDescription": "OK",
				"traceId": "eb8f6a992c6c465ba0405a84fd0bffa1|BN20130442|7.7.0.0|",
				"addressLine": "460 Main St W",
				"adminDistrict": "ON",
				"adminDistrict2": "Hamilton",
				"countryRegion": "Canada",
				"formattedAddress": "460 Main St W, Hamilton, ON L8P 1K7, Canada",
				"locality": "Hamilton",
				"neighborhood": "Strathcona",
				"postalCode": "L8P 1K7"
			},
			"geometry": {
				"type": "Point",
				"coordinates": [
					-79.88846,
					43.25994
				]
			},
			"bbox": [
				-79.8900036,
				43.2588158,
				-79.8869164,
				43.2610642
			]
		}
	]
}
