{
	"type": "FeatureCollection",
	"features": [
		{
			"type": "Feature",
			"properties": {
				"confidence": 9,
				"authenticationResultCode": "ValidCredentials",
				"brandLogoUri": "http://dev.virtualearth.net/Branding/logo_powered_by.png",
				"copyright": "Copyright © 2017 Microsoft and its suppliers. All rights reserved. This API cannot be accessed and the content and any results may not be used, reproduced or transmitted in any manner without express written permission from Microsoft Corporation.",
				"entityType": "Address",
				"matchCodes": [
					"Good"
				],
				"name": "460 Barton St E, Hamilton, ON L8L 2Y6, Canada",
				"statusCode": 200,
				"statusDescription": "OK",
				"traceId": "3b39e2d0771a44da83be839f20976620|BN20250135|7.7.0.0|",
				"addressLine": "460 Barton St E",
				"adminDistrict": "ON",
				"adminDistrict2": "Hamilton",
				"countryRegion": "Canada",
				"formattedAddress": "460 Barton St E, Hamilton, ON L8L 2Y6, Canada",
				"locality": "Hamilton",
				"neighborhood": "Landsdale",
				"postalCode": "L8L 2Y6"
			},
			"geometry": {
				"type": "Point",
				"coordinates": [
					-79.84635,
					43.25882
				]
			},
			"bbox": [
				-79.8478936,
				43.2576958,
				-79.8448064,
				43.2599442
			]
		}
	]
}
