{
	"type": "FeatureCollection",
	"features": [
		{
			"type": "Feature",
			"properties": {
				"confidence": 9,
				"authenticationResultCode": "ValidCredentials",
				"brandLogoUri": "http://dev.virtualearth.net/Branding/logo_powered_by.png",
				"copyright": "Copyright © 2017 Microsoft and its suppliers. All rights reserved. This API cannot be accessed and the content and any results may not be used, reproduced or transmitted in any manner without express written permission from Microsoft Corporation.",
				"entityType": "Address",
				"matchCodes": [
					"Good"
				],
				"name": "4607 61 Ave, Leduc, AB T9E 7A4, Canada",
				"statusCode": 200,
				"statusDescription": "OK",
				"traceId": "80e63a42a97748488d07471de06f91de|BN20130522|7.7.0.0|",
				"addressLine": "4607 61 Ave",
				"adminDistrict": "AB",
				"adminDistrict2": "Alberta",
				"countryRegion": "Canada",
				"formattedAddress": "4607 61 Ave, Leduc, AB T9E 7A4, Canada",
				"locality": "Leduc",
				"postalCode": "T9E 7A4"
			},
			"geometry": {
				"type": "Point",
				"coordinates": [
					-113.5476834,
					53.2743166
				]
			},
			"bbox": [
				-113.5495633,
				53.2731925,
				-113.5458035,
				53.2754408
			]
		}
	]
}
