{
	"type": "FeatureCollection",
	"features": [
		{
			"type": "Feature",
			"properties": {
				"confidence": 9,
				"authenticationResultCode": "ValidCredentials",
				"brandLogoUri": "http://dev.virtualearth.net/Branding/logo_powered_by.png",
				"copyright": "Copyright © 2017 Microsoft and its suppliers. All rights reserved. This API cannot be accessed and the content and any results may not be used, reproduced or transmitted in any manner without express written permission from Microsoft Corporation.",
				"entityType": "Address",
				"matchCodes": [
					"Good"
				],
				"name": "464 McNicoll Ave, North York, ON M2H 2E1, Canada",
				"statusCode": 200,
				"statusDescription": "OK",
				"traceId": "80a38342099d4914b057e1ac0b0c7f34|BN20130533|7.7.0.0|",
				"addressLine": "464 McNicoll Ave",
				"adminDistrict": "ON",
				"adminDistrict2": "Toronto",
				"countryRegion": "Canada",
				"formattedAddress": "464 McNicoll Ave, North York, ON M2H 2E1, Canada",
				"locality": "Toronto",
				"neighborhood": "Hillcrest Village",
				"postalCode": "M2H 2E1"
			},
			"geometry": {
				"type": "Point",
				"coordinates": [
					-79.3418,
					43.80457
				]
			},
			"bbox": [
				-79.3433576,
				43.8034458,
				-79.3402424,
				43.8056942
			]
		}
	]
}
