{
	"type": "FeatureCollection",
	"features": [
		{
			"type": "Feature",
			"properties": {
				"confidence": 9,
				"authenticationResultCode": "ValidCredentials",
				"brandLogoUri": "http://dev.virtualearth.net/Branding/logo_powered_by.png",
				"copyright": "Copyright © 2017 Microsoft and its suppliers. All rights reserved. This API cannot be accessed and the content and any results may not be used, reproduced or transmitted in any manner without express written permission from Microsoft Corporation.",
				"entityType": "Address",
				"matchCodes": [
					"Good"
				],
				"name": "4658 Ontario St, Beamsville, ON L0R 1B4, Canada",
				"statusCode": 200,
				"statusDescription": "OK",
				"traceId": "1146326f4bb44c4083613eeb0a51b93a|BN20190642|7.7.0.0|",
				"addressLine": "4658 Ontario St",
				"adminDistrict": "ON",
				"adminDistrict2": "Niagara",
				"countryRegion": "Canada",
				"formattedAddress": "4658 Ontario St, Beamsville, ON L0R 1B4, Canada",
				"locality": "Lincoln",
				"neighborhood": "Beamsville",
				"postalCode": "L0R 1B4"
			},
			"geometry": {
				"type": "Point",
				"coordinates": [
					-79.47779,
					43.18377
				]
			},
			"bbox": [
				-79.4793317,
				43.1826458,
				-79.4762483,
				43.1848942
			]
		}
	]
}
