{
	"type": "FeatureCollection",
	"features": [
		{
			"type": "Feature",
			"properties": {
				"confidence": 9,
				"authenticationResultCode": "ValidCredentials",
				"brandLogoUri": "http://dev.virtualearth.net/Branding/logo_powered_by.png",
				"copyright": "Copyright © 2017 Microsoft and its suppliers. All rights reserved. This API cannot be accessed and the content and any results may not be used, reproduced or transmitted in any manner without express written permission from Microsoft Corporation.",
				"entityType": "Address",
				"matchCodes": [
					"Good"
				],
				"name": "4668 25 St SE, Calgary, AB T2B 3M2, Canada",
				"statusCode": 200,
				"statusDescription": "OK",
				"traceId": "8bd54cf1013f4cc1bc622ef308513ed6|BN20240423|7.7.0.0|",
				"addressLine": "4668 25 St SE",
				"adminDistrict": "AB",
				"adminDistrict2": "Alberta",
				"countryRegion": "Canada",
				"formattedAddress": "4668 25 St SE, Calgary, AB T2B 3M2, Canada",
				"locality": "Calgary",
				"postalCode": "T2B 3M2"
			},
			"geometry": {
				"type": "Point",
				"coordinates": [
					-113.99902,
					51.01242
				]
			},
			"bbox": [
				-114.0008068,
				51.0112958,
				-113.9972332,
				51.0135442
			]
		}
	]
}
