{
	"type": "FeatureCollection",
	"features": [
		{
			"type": "Feature",
			"properties": {
				"confidence": 9,
				"authenticationResultCode": "ValidCredentials",
				"brandLogoUri": "http://dev.virtualearth.net/Branding/logo_powered_by.png",
				"copyright": "Copyright © 2017 Microsoft and its suppliers. All rights reserved. This API cannot be accessed and the content and any results may not be used, reproduced or transmitted in any manner without express written permission from Microsoft Corporation.",
				"entityType": "Address",
				"matchCodes": [
					"Good"
				],
				"name": "469 McNicoll Ave, North York, ON M2H 2C9, Canada",
				"statusCode": 200,
				"statusDescription": "OK",
				"traceId": "df7563ce5ac3410fb39908f07fd3290e|BN20300154|7.7.0.0|",
				"addressLine": "469 McNicoll Ave",
				"adminDistrict": "ON",
				"adminDistrict2": "Toronto",
				"countryRegion": "Canada",
				"formattedAddress": "469 McNicoll Ave, North York, ON M2H 2C9, Canada",
				"locality": "Toronto",
				"neighborhood": "Hillcrest Village",
				"postalCode": "M2H 2C9"
			},
			"geometry": {
				"type": "Point",
				"coordinates": [
					-79.34112,
					43.80271
				]
			},
			"bbox": [
				-79.3426776,
				43.8015858,
				-79.3395624,
				43.8038342
			]
		}
	]
}
