{
	"type": "FeatureCollection",
	"features": [
		{
			"type": "Feature",
			"properties": {
				"confidence": 9,
				"authenticationResultCode": "ValidCredentials",
				"brandLogoUri": "http://dev.virtualearth.net/Branding/logo_powered_by.png",
				"copyright": "Copyright © 2017 Microsoft and its suppliers. All rights reserved. This API cannot be accessed and the content and any results may not be used, reproduced or transmitted in any manner without express written permission from Microsoft Corporation.",
				"entityType": "Address",
				"matchCodes": [
					"Good"
				],
				"name": "47 Laurier Ave, Timmins, ON P4N 4G7, Canada",
				"statusCode": 200,
				"statusDescription": "OK",
				"traceId": "bfa84dd9325244f7acf0a0731da9ed10|BN20130532|7.7.0.0|",
				"addressLine": "47 Laurier Ave",
				"adminDistrict": "ON",
				"adminDistrict2": "Cochrane",
				"countryRegion": "Canada",
				"formattedAddress": "47 Laurier Ave, Timmins, ON P4N 4G7, Canada",
				"locality": "Timmins",
				"postalCode": "P4N 4G7"
			},
			"geometry": {
				"type": "Point",
				"coordinates": [
					-81.3387862,
					48.4791876
				]
			},
			"bbox": [
				-81.3404821,
				48.4780635,
				-81.3370904,
				48.4803118
			]
		}
	]
}
