{
	"type": "FeatureCollection",
	"features": [
		{
			"type": "Feature",
			"properties": {
				"confidence": 9,
				"authenticationResultCode": "ValidCredentials",
				"brandLogoUri": "http://dev.virtualearth.net/Branding/logo_powered_by.png",
				"copyright": "Copyright © 2017 Microsoft and its suppliers. All rights reserved. This API cannot be accessed and the content and any results may not be used, reproduced or transmitted in any manner without express written permission from Microsoft Corporation.",
				"entityType": "Address",
				"matchCodes": [
					"Good"
				],
				"name": "47 Ortona Ct, Concord, ON L4K 3M2, Canada",
				"statusCode": 200,
				"statusDescription": "OK",
				"traceId": "a21cf981703749bdbb10deda8dcdaf5b|BN20130521|7.7.0.0|",
				"addressLine": "47 Ortona Ct",
				"adminDistrict": "ON",
				"adminDistrict2": "York",
				"countryRegion": "Canada",
				"formattedAddress": "47 Ortona Ct, Concord, ON L4K 3M2, Canada",
				"locality": "Vaughan",
				"neighborhood": "Concord",
				"postalCode": "L4K 3M2"
			},
			"geometry": {
				"type": "Point",
				"coordinates": [
					-79.4873099,
					43.80991
				]
			},
			"bbox": [
				-79.4888677,
				43.8087858,
				-79.4857521,
				43.8110342
			]
		}
	]
}
