{
	"type": "FeatureCollection",
	"features": [
		{
			"type": "Feature",
			"properties": {
				"confidence": 9,
				"authenticationResultCode": "ValidCredentials",
				"brandLogoUri": "http://dev.virtualearth.net/Branding/logo_powered_by.png",
				"copyright": "Copyright © 2017 Microsoft and its suppliers. All rights reserved. This API cannot be accessed and the content and any results may not be used, reproduced or transmitted in any manner without express written permission from Microsoft Corporation.",
				"entityType": "Address",
				"matchCodes": [
					"Good"
				],
				"name": "47 Rue Champlain, Bromont, QC J2L 3A2, Canada",
				"statusCode": 200,
				"statusDescription": "OK",
				"traceId": "135e8396fc9444fb80bea10dac7be549|BN20250135|7.7.0.0|",
				"addressLine": "47 Rue Champlain",
				"adminDistrict": "QC",
				"adminDistrict2": "Brome-Missisquoi",
				"countryRegion": "Canada",
				"formattedAddress": "47 Rue Champlain, Bromont, QC J2L 3A2, Canada",
				"locality": "Bromont",
				"postalCode": "J2L 3A2"
			},
			"geometry": {
				"type": "Point",
				"coordinates": [
					-72.64922,
					45.30896
				]
			},
			"bbox": [
				-72.6508184,
				45.3078358,
				-72.6476216,
				45.3100842
			]
		}
	]
}
