{
	"type": "FeatureCollection",
	"features": [
		{
			"type": "Feature",
			"properties": {
				"confidence": 9,
				"authenticationResultCode": "ValidCredentials",
				"brandLogoUri": "http://dev.virtualearth.net/Branding/logo_powered_by.png",
				"copyright": "Copyright © 2017 Microsoft and its suppliers. All rights reserved. This API cannot be accessed and the content and any results may not be used, reproduced or transmitted in any manner without express written permission from Microsoft Corporation.",
				"entityType": "Address",
				"matchCodes": [
					"Good"
				],
				"name": "4715 HWY-101 E, Timmins, ON P0N 1H0, Canada",
				"statusCode": 200,
				"statusDescription": "OK",
				"traceId": "dccf90cb33744f73a49326afc86a197e|BN20121763|7.7.0.0|",
				"addressLine": "4715 HWY-101 E",
				"adminDistrict": "ON",
				"adminDistrict2": "Cochrane",
				"countryRegion": "Canada",
				"formattedAddress": "4715 HWY-101 E, Timmins, ON P0N 1H0, Canada",
				"locality": "Timmins",
				"neighborhood": "South Porcupine",
				"postalCode": "P0N 1H0"
			},
			"geometry": {
				"type": "Point",
				"coordinates": [
					-81.2000697,
					48.4886777
				]
			},
			"bbox": [
				-81.2017658,
				48.4875535,
				-81.1983735,
				48.4898018
			]
		}
	]
}
