{
	"type": "FeatureCollection",
	"features": [
		{
			"type": "Feature",
			"properties": {
				"confidence": 9,
				"authenticationResultCode": "ValidCredentials",
				"brandLogoUri": "http://dev.virtualearth.net/Branding/logo_powered_by.png",
				"copyright": "Copyright © 2017 Microsoft and its suppliers. All rights reserved. This API cannot be accessed and the content and any results may not be used, reproduced or transmitted in any manner without express written permission from Microsoft Corporation.",
				"entityType": "Address",
				"matchCodes": [
					"Good"
				],
				"name": "473 Hensall Cir, Mississauga, ON L5A 1X9, Canada",
				"statusCode": 200,
				"statusDescription": "OK",
				"traceId": "a6351d27930f403789f25945cc67db83|BN20130423|7.7.0.0|",
				"addressLine": "473 Hensall Cir",
				"adminDistrict": "ON",
				"adminDistrict2": "Peel",
				"countryRegion": "Canada",
				"formattedAddress": "473 Hensall Cir, Mississauga, ON L5A 1X9, Canada",
				"locality": "Mississauga",
				"neighborhood": "Cooksville",
				"postalCode": "L5A 1X9"
			},
			"geometry": {
				"type": "Point",
				"coordinates": [
					-79.60509,
					43.59098
				]
			},
			"bbox": [
				-79.6066421,
				43.5898558,
				-79.6035379,
				43.5921042
			]
		}
	]
}
