{
	"type": "FeatureCollection",
	"features": [
		{
			"type": "Feature",
			"properties": {
				"confidence": 9,
				"authenticationResultCode": "ValidCredentials",
				"brandLogoUri": "http://dev.virtualearth.net/Branding/logo_powered_by.png",
				"copyright": "Copyright © 2017 Microsoft and its suppliers. All rights reserved. This API cannot be accessed and the content and any results may not be used, reproduced or transmitted in any manner without express written permission from Microsoft Corporation.",
				"entityType": "Address",
				"matchCodes": [
					"Good"
				],
				"name": "4736 Teskey Rd, Chilliwack, BC V2R 0C7, Canada",
				"statusCode": 200,
				"statusDescription": "OK",
				"traceId": "9d9c3434471a4d048c1dd9355aac36bd|BN20260223|7.7.0.0|",
				"addressLine": "4736 Teskey Rd",
				"adminDistrict": "BC",
				"adminDistrict2": "Fraser Valley",
				"countryRegion": "Canada",
				"formattedAddress": "4736 Teskey Rd, Chilliwack, BC V2R 0C7, Canada",
				"locality": "Chilliwack",
				"neighborhood": "Promontory",
				"postalCode": "V2R 0C7"
			},
			"geometry": {
				"type": "Point",
				"coordinates": [
					-121.9455864,
					49.1034158
				]
			},
			"bbox": [
				-121.9473035,
				49.1022917,
				-121.9438694,
				49.10454
			]
		}
	]
}
