{
	"type": "FeatureCollection",
	"features": [
		{
			"type": "Feature",
			"properties": {
				"confidence": 9,
				"authenticationResultCode": "ValidCredentials",
				"brandLogoUri": "http://dev.virtualearth.net/Branding/logo_powered_by.png",
				"copyright": "Copyright © 2017 Microsoft and its suppliers. All rights reserved. This API cannot be accessed and the content and any results may not be used, reproduced or transmitted in any manner without express written permission from Microsoft Corporation.",
				"entityType": "Address",
				"matchCodes": [
					"Good"
				],
				"name": "4794 94 Ave NW, Edmonton, AB T6B 2T3, Canada",
				"statusCode": 200,
				"statusDescription": "OK",
				"traceId": "13a19a97c3834fff906b303048b618f7|BN20210145|7.7.0.0|",
				"addressLine": "4794 94 Ave NW",
				"adminDistrict": "AB",
				"adminDistrict2": "Alberta",
				"countryRegion": "Canada",
				"formattedAddress": "4794 94 Ave NW, Edmonton, AB T6B 2T3, Canada",
				"locality": "Edmonton",
				"neighborhood": "Eastgate Business Park",
				"postalCode": "T6B 2T3"
			},
			"geometry": {
				"type": "Point",
				"coordinates": [
					-113.41026,
					53.53296
				]
			},
			"bbox": [
				-113.4121514,
				53.5318358,
				-113.4083686,
				53.5340842
			]
		}
	]
}
