{
	"type": "FeatureCollection",
	"features": [
		{
			"type": "Feature",
			"properties": {
				"confidence": 9,
				"authenticationResultCode": "ValidCredentials",
				"brandLogoUri": "http://dev.virtualearth.net/Branding/logo_powered_by.png",
				"copyright": "Copyright © 2017 Microsoft and its suppliers. All rights reserved. This API cannot be accessed and the content and any results may not be used, reproduced or transmitted in any manner without express written permission from Microsoft Corporation.",
				"entityType": "Address",
				"matchCodes": [
					"Good"
				],
				"name": "48 Friars Way, London, ON N6G 2B2, Canada",
				"statusCode": 200,
				"statusDescription": "OK",
				"traceId": "e36c8e695ae84a31a2afdff2dfce1e5f|BN20130431|7.7.0.0|",
				"addressLine": "48 Friars Way",
				"adminDistrict": "ON",
				"adminDistrict2": "Middlesex",
				"countryRegion": "Canada",
				"formattedAddress": "48 Friars Way, London, ON N6G 2B2, Canada",
				"locality": "London",
				"neighborhood": "Medway",
				"postalCode": "N6G 2B2"
			},
			"geometry": {
				"type": "Point",
				"coordinates": [
					-81.3009,
					43.0065
				]
			},
			"bbox": [
				-81.3024372,
				43.0053758,
				-81.2993628,
				43.0076242
			]
		}
	]
}
