{
	"type": "FeatureCollection",
	"features": [
		{
			"type": "Feature",
			"properties": {
				"confidence": 9,
				"authenticationResultCode": "ValidCredentials",
				"brandLogoUri": "http://dev.virtualearth.net/Branding/logo_powered_by.png",
				"copyright": "Copyright © 2017 Microsoft and its suppliers. All rights reserved. This API cannot be accessed and the content and any results may not be used, reproduced or transmitted in any manner without express written permission from Microsoft Corporation.",
				"entityType": "Address",
				"matchCodes": [
					"Good"
				],
				"name": "481 Rue Bourbonnais, La Salle, QC H8R 2Z2, Canada",
				"statusCode": 200,
				"statusDescription": "OK",
				"traceId": "c4b01981419545318fc4c1ee3c444114|BN20190653|7.7.0.0|",
				"addressLine": "481 Rue Bourbonnais",
				"adminDistrict": "QC",
				"adminDistrict2": "Montreal",
				"countryRegion": "Canada",
				"formattedAddress": "481 Rue Bourbonnais, La Salle, QC H8R 2Z2, Canada",
				"locality": "Montreal",
				"neighborhood": "La Salle",
				"postalCode": "H8R 2Z2"
			},
			"geometry": {
				"type": "Point",
				"coordinates": [
					-73.63703,
					45.43165
				]
			},
			"bbox": [
				-73.6386319,
				45.4305258,
				-73.6354281,
				45.4327742
			]
		}
	]
}
