{
	"type": "FeatureCollection",
	"features": [
		{
			"type": "Feature",
			"properties": {
				"confidence": 9,
				"authenticationResultCode": "ValidCredentials",
				"brandLogoUri": "http://dev.virtualearth.net/Branding/logo_powered_by.png",
				"copyright": "Copyright © 2017 Microsoft and its suppliers. All rights reserved. This API cannot be accessed and the content and any results may not be used, reproduced or transmitted in any manner without express written permission from Microsoft Corporation.",
				"entityType": "Address",
				"matchCodes": [
					"Good"
				],
				"name": "485 McCormick Blvd, London, ON N5W 5N1, Canada",
				"statusCode": 200,
				"statusDescription": "OK",
				"traceId": "b09bdb39fc394ec49eb452d2d04214cc|CO30276241|7.7.0.0|",
				"addressLine": "485 McCormick Blvd",
				"adminDistrict": "ON",
				"adminDistrict2": "Middlesex",
				"countryRegion": "Canada",
				"formattedAddress": "485 McCormick Blvd, London, ON N5W 5N1, Canada",
				"locality": "London",
				"neighborhood": "East London",
				"postalCode": "N5W 5N1"
			},
			"geometry": {
				"type": "Point",
				"coordinates": [
					-81.2127,
					42.9977
				]
			},
			"bbox": [
				-81.214237,
				42.9965758,
				-81.211163,
				42.9988242
			]
		}
	]
}
