{
	"type": "FeatureCollection",
	"features": [
		{
			"type": "Feature",
			"properties": {
				"confidence": 9,
				"authenticationResultCode": "ValidCredentials",
				"brandLogoUri": "http://dev.virtualearth.net/Branding/logo_powered_by.png",
				"copyright": "Copyright © 2017 Microsoft and its suppliers. All rights reserved. This API cannot be accessed and the content and any results may not be used, reproduced or transmitted in any manner without express written permission from Microsoft Corporation.",
				"entityType": "Address",
				"matchCodes": [
					"Good"
				],
				"name": "485 Head St, Victoria, BC V9A 5S1, Canada",
				"statusCode": 200,
				"statusDescription": "OK",
				"traceId": "b9c08269913e49d0ada19b98ca2c22c9|BN20130634|7.7.0.0|",
				"addressLine": "485 Head St",
				"adminDistrict": "BC",
				"adminDistrict2": "Capital",
				"countryRegion": "Canada",
				"formattedAddress": "485 Head St, Victoria, BC V9A 5S1, Canada",
				"locality": "Esquimalt",
				"neighborhood": "Victoria",
				"postalCode": "V9A 5S1"
			},
			"geometry": {
				"type": "Point",
				"coordinates": [
					-123.39887,
					48.4271
				]
			},
			"bbox": [
				-123.4005641,
				48.4259758,
				-123.3971759,
				48.4282242
			]
		}
	]
}
