{
	"type": "FeatureCollection",
	"features": [
		{
			"type": "Feature",
			"properties": {
				"confidence": 9,
				"authenticationResultCode": "ValidCredentials",
				"brandLogoUri": "http://dev.virtualearth.net/Branding/logo_powered_by.png",
				"copyright": "Copyright © 2017 Microsoft and its suppliers. All rights reserved. This API cannot be accessed and the content and any results may not be used, reproduced or transmitted in any manner without express written permission from Microsoft Corporation.",
				"entityType": "Address",
				"matchCodes": [
					"Good"
				],
				"name": "489 Mt Pleasant Ave, Westmount, QC H3Y 3H4, Canada",
				"statusCode": 200,
				"statusDescription": "OK",
				"traceId": "65067a4404414b5bbb0d2f1f8f38f6fd|BN20130634|7.7.0.0|",
				"addressLine": "489 Mt Pleasant Ave",
				"adminDistrict": "QC",
				"adminDistrict2": "Montreal",
				"countryRegion": "Canada",
				"formattedAddress": "489 Mt Pleasant Ave, Westmount, QC H3Y 3H4, Canada",
				"locality": "Westmount",
				"postalCode": "H3Y 3H4"
			},
			"geometry": {
				"type": "Point",
				"coordinates": [
					-73.59512,
					45.49088
				]
			},
			"bbox": [
				-73.5967236,
				45.4897558,
				-73.5935164,
				45.4920042
			]
		}
	]
}
