{
	"type": "FeatureCollection",
	"features": [
		{
			"type": "Feature",
			"properties": {
				"confidence": 9,
				"authenticationResultCode": "ValidCredentials",
				"brandLogoUri": "http://dev.virtualearth.net/Branding/logo_powered_by.png",
				"copyright": "Copyright © 2017 Microsoft and its suppliers. All rights reserved. This API cannot be accessed and the content and any results may not be used, reproduced or transmitted in any manner without express written permission from Microsoft Corporation.",
				"entityType": "Address",
				"matchCodes": [
					"Good"
				],
				"name": "49 Rutherford Rd S, Brampton, ON L6W 3J3, Canada",
				"statusCode": 200,
				"statusDescription": "OK",
				"traceId": "c8ed996fad9b4f18b70ba05b1e34b91d|BN20130632|7.7.0.0|",
				"addressLine": "49 Rutherford Rd S",
				"adminDistrict": "ON",
				"adminDistrict2": "Peel",
				"countryRegion": "Canada",
				"formattedAddress": "49 Rutherford Rd S, Brampton, ON L6W 3J3, Canada",
				"locality": "Brampton",
				"postalCode": "L6W 3J3"
			},
			"geometry": {
				"type": "Point",
				"coordinates": [
					-79.7370399,
					43.69691
				]
			},
			"bbox": [
				-79.7385947,
				43.6957858,
				-79.7354851,
				43.6980342
			]
		}
	]
}
