{
	"type": "FeatureCollection",
	"features": [
		{
			"type": "Feature",
			"properties": {
				"confidence": 9,
				"authenticationResultCode": "ValidCredentials",
				"brandLogoUri": "http://dev.virtualearth.net/Branding/logo_powered_by.png",
				"copyright": "Copyright © 2017 Microsoft and its suppliers. All rights reserved. This API cannot be accessed and the content and any results may not be used, reproduced or transmitted in any manner without express written permission from Microsoft Corporation.",
				"entityType": "Address",
				"matchCodes": [
					"Good"
				],
				"name": "49 Southworth St N, Welland, ON L3B 1Y3, Canada",
				"statusCode": 200,
				"statusDescription": "OK",
				"traceId": "6ea9f45a14e84e0c95911bf773c957ae|BN20220145|7.7.0.0|",
				"addressLine": "49 Southworth St N",
				"adminDistrict": "ON",
				"adminDistrict2": "Niagara",
				"countryRegion": "Canada",
				"formattedAddress": "49 Southworth St N, Welland, ON L3B 1Y3, Canada",
				"locality": "Welland",
				"postalCode": "L3B 1Y3"
			},
			"geometry": {
				"type": "Point",
				"coordinates": [
					-79.2359151,
					42.98187
				]
			},
			"bbox": [
				-79.2374517,
				42.9807459,
				-79.2343785,
				42.9829942
			]
		}
	]
}
