{
	"type": "FeatureCollection",
	"features": [
		{
			"type": "Feature",
			"properties": {
				"confidence": 9,
				"authenticationResultCode": "ValidCredentials",
				"brandLogoUri": "http://dev.virtualearth.net/Branding/logo_powered_by.png",
				"copyright": "Copyright © 2017 Microsoft and its suppliers. All rights reserved. This API cannot be accessed and the content and any results may not be used, reproduced or transmitted in any manner without express written permission from Microsoft Corporation.",
				"entityType": "Address",
				"matchCodes": [
					"Good"
				],
				"name": "490 York Rd, Guelph, ON N1E 6V1, Canada",
				"statusCode": 200,
				"statusDescription": "OK",
				"traceId": "a217e97bbd734f8aa1351a072b5cea9f|BN20130522|7.7.0.0|",
				"addressLine": "490 York Rd",
				"adminDistrict": "ON",
				"adminDistrict2": "Wellington",
				"countryRegion": "Canada",
				"formattedAddress": "490 York Rd, Guelph, ON N1E 6V1, Canada",
				"locality": "Guelph",
				"neighborhood": "St Georges/St Patricks",
				"postalCode": "N1E 6V1"
			},
			"geometry": {
				"type": "Point",
				"coordinates": [
					-80.2249293,
					43.5513357
				]
			},
			"bbox": [
				-80.2264804,
				43.5502115,
				-80.2233783,
				43.5524598
			]
		}
	]
}
