{
	"type": "FeatureCollection",
	"features": [
		{
			"type": "Feature",
			"properties": {
				"confidence": 9,
				"authenticationResultCode": "ValidCredentials",
				"brandLogoUri": "http://dev.virtualearth.net/Branding/logo_powered_by.png",
				"copyright": "Copyright © 2017 Microsoft and its suppliers. All rights reserved. This API cannot be accessed and the content and any results may not be used, reproduced or transmitted in any manner without express written permission from Microsoft Corporation.",
				"entityType": "Address",
				"matchCodes": [
					"Good"
				],
				"name": "4910 Anthony Way, Regina, SK S4X 0H4, Canada",
				"statusCode": 200,
				"statusDescription": "OK",
				"traceId": "ca6f2a28c1124df4b205e785287ca1f3|BN20130521|7.7.0.0|",
				"addressLine": "4910 Anthony Way",
				"adminDistrict": "SK",
				"adminDistrict2": "Saskatchewan",
				"countryRegion": "Canada",
				"formattedAddress": "4910 Anthony Way, Regina, SK S4X 0H4, Canada",
				"locality": "Regina",
				"postalCode": "S4X 0H4"
			},
			"geometry": {
				"type": "Point",
				"coordinates": [
					-104.6515731,
					50.5076101
				]
			},
			"bbox": [
				-104.6533407,
				50.5064859,
				-104.6498055,
				50.5087342
			]
		}
	]
}
