{
	"type": "FeatureCollection",
	"features": [
		{
			"type": "Feature",
			"properties": {
				"confidence": 9,
				"authenticationResultCode": "ValidCredentials",
				"brandLogoUri": "http://dev.virtualearth.net/Branding/logo_powered_by.png",
				"copyright": "Copyright © 2017 Microsoft and its suppliers. All rights reserved. This API cannot be accessed and the content and any results may not be used, reproduced or transmitted in any manner without express written permission from Microsoft Corporation.",
				"entityType": "Address",
				"matchCodes": [
					"Good"
				],
				"name": "4916 Batchelor Cres NW, Calgary, AB T2L 1S9, Canada",
				"statusCode": 200,
				"statusDescription": "OK",
				"traceId": "fcc1c41acad24e7ca68c88330e4e7b28|BN20130620|7.7.0.0|",
				"addressLine": "4916 Batchelor Cres NW",
				"adminDistrict": "AB",
				"adminDistrict2": "Alberta",
				"countryRegion": "Canada",
				"formattedAddress": "4916 Batchelor Cres NW, Calgary, AB T2L 1S9, Canada",
				"locality": "Calgary",
				"neighborhood": "Brentwood",
				"postalCode": "T2L 1S9"
			},
			"geometry": {
				"type": "Point",
				"coordinates": [
					-114.13417,
					51.09651
				]
			},
			"bbox": [
				-114.13596,
				51.0953858,
				-114.13238,
				51.0976342
			]
		}
	]
}
