{
	"type": "FeatureCollection",
	"features": [
		{
			"type": "Feature",
			"properties": {
				"confidence": 9,
				"authenticationResultCode": "ValidCredentials",
				"brandLogoUri": "http://dev.virtualearth.net/Branding/logo_powered_by.png",
				"copyright": "Copyright © 2017 Microsoft and its suppliers. All rights reserved. This API cannot be accessed and the content and any results may not be used, reproduced or transmitted in any manner without express written permission from Microsoft Corporation.",
				"entityType": "Address",
				"matchCodes": [
					"Good"
				],
				"name": "4920 51 Ave, Rocky Mountain House, AB T4T, Canada",
				"statusCode": 200,
				"statusDescription": "OK",
				"traceId": "c3c2651915a74dca864e40ab768e45b6|BN20121764|7.7.0.0|",
				"addressLine": "4920 51 Ave",
				"adminDistrict": "AB",
				"adminDistrict2": "Alberta",
				"countryRegion": "Canada",
				"formattedAddress": "4920 51 Ave, Rocky Mountain House, AB T4T, Canada",
				"locality": "Rocky Mountain House",
				"postalCode": "T4T 1J6"
			},
			"geometry": {
				"type": "Point",
				"coordinates": [
					-114.91882,
					52.37609
				]
			},
			"bbox": [
				-114.9206614,
				52.3749658,
				-114.9169786,
				52.3772142
			]
		}
	]
}
