{
	"type": "FeatureCollection",
	"features": [
		{
			"type": "Feature",
			"properties": {
				"confidence": 9,
				"authenticationResultCode": "ValidCredentials",
				"brandLogoUri": "http://dev.virtualearth.net/Branding/logo_powered_by.png",
				"copyright": "Copyright © 2017 Microsoft and its suppliers. All rights reserved. This API cannot be accessed and the content and any results may not be used, reproduced or transmitted in any manner without express written permission from Microsoft Corporation.",
				"entityType": "Address",
				"matchCodes": [
					"Good"
				],
				"name": "4950 Keith Rd, West Vancouver, BC V7W 2N1, Canada",
				"statusCode": 200,
				"statusDescription": "OK",
				"traceId": "1417ce875d71442ebdd88a3aa19e6c14|BN20130422|7.7.0.0|",
				"addressLine": "4950 Keith Rd",
				"adminDistrict": "BC",
				"adminDistrict2": "Greater Vancouver",
				"countryRegion": "Canada",
				"formattedAddress": "4950 Keith Rd, West Vancouver, BC V7W 2N1, Canada",
				"locality": "West Vancouver",
				"neighborhood": "Caulfeild",
				"postalCode": "V7W 2N1"
			},
			"geometry": {
				"type": "Point",
				"coordinates": [
					-123.26125,
					49.34172
				]
			},
			"bbox": [
				-123.2629754,
				49.3405958,
				-123.2595246,
				49.3428442
			]
		}
	]
}
