{
	"type": "FeatureCollection",
	"features": [
		{
			"type": "Feature",
			"properties": {
				"confidence": 9,
				"authenticationResultCode": "ValidCredentials",
				"brandLogoUri": "http://dev.virtualearth.net/Branding/logo_powered_by.png",
				"copyright": "Copyright © 2017 Microsoft and its suppliers. All rights reserved. This API cannot be accessed and the content and any results may not be used, reproduced or transmitted in any manner without express written permission from Microsoft Corporation.",
				"entityType": "Address",
				"matchCodes": [
					"Good"
				],
				"name": "5 Abacus Rd, Brampton, ON L6T 5B7, Canada",
				"statusCode": 200,
				"statusDescription": "OK",
				"traceId": "568118c1adbe4acfb91569b6183ffd5b|BN20240253|7.7.0.0|",
				"addressLine": "5 Abacus Rd",
				"adminDistrict": "ON",
				"adminDistrict2": "Peel",
				"countryRegion": "Canada",
				"formattedAddress": "5 Abacus Rd, Brampton, ON L6T 5B7, Canada",
				"locality": "Brampton",
				"neighborhood": "Castlemore",
				"postalCode": "L6T 5B7"
			},
			"geometry": {
				"type": "Point",
				"coordinates": [
					-79.6606,
					43.7632199
				]
			},
			"bbox": [
				-79.6621566,
				43.7620957,
				-79.6590434,
				43.7643441
			]
		}
	]
}
