{
	"type": "FeatureCollection",
	"features": [
		{
			"type": "Feature",
			"properties": {
				"confidence": 9,
				"authenticationResultCode": "ValidCredentials",
				"brandLogoUri": "http://dev.virtualearth.net/Branding/logo_powered_by.png",
				"copyright": "Copyright © 2017 Microsoft and its suppliers. All rights reserved. This API cannot be accessed and the content and any results may not be used, reproduced or transmitted in any manner without express written permission from Microsoft Corporation.",
				"entityType": "Address",
				"matchCodes": [
					"Good"
				],
				"name": "50 Bruchanski Rd, Lac du Bonnet RM, MB R0E, Canada",
				"statusCode": 200,
				"statusDescription": "OK",
				"traceId": "1cfc5f7520934b8d8c6b2c7fc04842bf|BN20160335|7.7.0.0|",
				"addressLine": "50 Bruchanski Rd",
				"adminDistrict": "MB",
				"adminDistrict2": "Manitoba",
				"countryRegion": "Canada",
				"formattedAddress": "50 Bruchanski Rd, Lac du Bonnet RM, MB R0E, Canada",
				"locality": "Lac du Bonnet RM",
				"postalCode": "R0E 1A0"
			},
			"geometry": {
				"type": "Point",
				"coordinates": [
					-96.0706614,
					50.1480387
				]
			},
			"bbox": [
				-96.0724157,
				50.1469146,
				-96.0689071,
				50.1491629
			]
		}
	]
}
