{
	"type": "FeatureCollection",
	"features": [
		{
			"type": "Feature",
			"properties": {
				"confidence": 9,
				"authenticationResultCode": "ValidCredentials",
				"brandLogoUri": "http://dev.virtualearth.net/Branding/logo_powered_by.png",
				"copyright": "Copyright © 2017 Microsoft and its suppliers. All rights reserved. This API cannot be accessed and the content and any results may not be used, reproduced or transmitted in any manner without express written permission from Microsoft Corporation.",
				"entityType": "Address",
				"matchCodes": [
					"Good"
				],
				"name": "50 Raglin Rd, Cambridge, ON N1T 1Z5, Canada",
				"statusCode": 200,
				"statusDescription": "OK",
				"traceId": "afffa36e6e0c4461bdf24fada581072d|BN20130631|7.7.0.0|",
				"addressLine": "50 Raglin Rd",
				"adminDistrict": "ON",
				"adminDistrict2": "Waterloo",
				"countryRegion": "Canada",
				"formattedAddress": "50 Raglin Rd, Cambridge, ON N1T 1Z5, Canada",
				"locality": "Cambridge",
				"neighborhood": "Fiddlesticks",
				"postalCode": "N1T 1Z5"
			},
			"geometry": {
				"type": "Point",
				"coordinates": [
					-80.30326,
					43.40208
				]
			},
			"bbox": [
				-80.3048072,
				43.4009558,
				-80.3017128,
				43.4032042
			]
		}
	]
}
