{
	"type": "FeatureCollection",
	"features": [
		{
			"type": "Feature",
			"properties": {
				"confidence": 9,
				"authenticationResultCode": "ValidCredentials",
				"brandLogoUri": "http://dev.virtualearth.net/Branding/logo_powered_by.png",
				"copyright": "Copyright © 2017 Microsoft and its suppliers. All rights reserved. This API cannot be accessed and the content and any results may not be used, reproduced or transmitted in any manner without express written permission from Microsoft Corporation.",
				"entityType": "Address",
				"matchCodes": [
					"Good"
				],
				"name": "50 Terminal St, North Bay, ON P1B 8G2, Canada",
				"statusCode": 200,
				"statusDescription": "OK",
				"traceId": "1e3bfe01ae2c4faaafd8c57c87b8f9b9|BN20131519|7.7.0.0|",
				"addressLine": "50 Terminal St",
				"adminDistrict": "ON",
				"adminDistrict2": "Nipissing",
				"countryRegion": "Canada",
				"formattedAddress": "50 Terminal St, North Bay, ON P1B 8G2, Canada",
				"locality": "North Bay",
				"postalCode": "P1B 8G2"
			},
			"geometry": {
				"type": "Point",
				"coordinates": [
					-79.4282371,
					46.3567724
				]
			},
			"bbox": [
				-79.4298659,
				46.3556482,
				-79.4266083,
				46.3578965
			]
		}
	]
}
