{
	"type": "FeatureCollection",
	"features": [
		{
			"type": "Feature",
			"properties": {
				"confidence": 9,
				"authenticationResultCode": "ValidCredentials",
				"brandLogoUri": "http://dev.virtualearth.net/Branding/logo_powered_by.png",
				"copyright": "Copyright © 2017 Microsoft and its suppliers. All rights reserved. This API cannot be accessed and the content and any results may not be used, reproduced or transmitted in any manner without express written permission from Microsoft Corporation.",
				"entityType": "Address",
				"matchCodes": [
					"Good"
				],
				"name": "502 Cour Steiner, Boisbriand, QC J7E 4H4, Canada",
				"statusCode": 200,
				"statusDescription": "OK",
				"traceId": "4d08102642d94294937da4fa62162d08|BN20220145|7.7.0.0|",
				"addressLine": "502 Cour Steiner",
				"adminDistrict": "QC",
				"adminDistrict2": "Thérèse-de-Blainville",
				"countryRegion": "Canada",
				"formattedAddress": "502 Cour Steiner, Boisbriand, QC J7E 4H4, Canada",
				"locality": "Boisbriand",
				"postalCode": "J7E 4H4"
			},
			"geometry": {
				"type": "Point",
				"coordinates": [
					-73.86809,
					45.6107299
				]
			},
			"bbox": [
				-73.869697,
				45.6096057,
				-73.866483,
				45.6118541
			]
		}
	]
}
