{
	"type": "FeatureCollection",
	"features": [
		{
			"type": "Feature",
			"properties": {
				"confidence": 9,
				"authenticationResultCode": "ValidCredentials",
				"brandLogoUri": "http://dev.virtualearth.net/Branding/logo_powered_by.png",
				"copyright": "Copyright © 2017 Microsoft and its suppliers. All rights reserved. This API cannot be accessed and the content and any results may not be used, reproduced or transmitted in any manner without express written permission from Microsoft Corporation.",
				"entityType": "Address",
				"matchCodes": [
					"Good"
				],
				"name": "503 Centennial Rd N, Scarborough, ON M1C 2A5, Canada",
				"statusCode": 200,
				"statusDescription": "OK",
				"traceId": "b4aab772a505458cb4a22d89c8a35908|BN20260231|7.7.0.0|",
				"addressLine": "503 Centennial Rd N",
				"adminDistrict": "ON",
				"adminDistrict2": "Toronto",
				"countryRegion": "Canada",
				"formattedAddress": "503 Centennial Rd N, Scarborough, ON M1C 2A5, Canada",
				"locality": "Toronto",
				"neighborhood": "Centennial Scarborough",
				"postalCode": "M1C 2A5"
			},
			"geometry": {
				"type": "Point",
				"coordinates": [
					-79.1524699,
					43.79315
				]
			},
			"bbox": [
				-79.1540272,
				43.7920258,
				-79.1509126,
				43.7942742
			]
		}
	]
}
