{
	"type": "FeatureCollection",
	"features": [
		{
			"type": "Feature",
			"properties": {
				"confidence": 9,
				"authenticationResultCode": "ValidCredentials",
				"brandLogoUri": "http://dev.virtualearth.net/Branding/logo_powered_by.png",
				"copyright": "Copyright © 2017 Microsoft and its suppliers. All rights reserved. This API cannot be accessed and the content and any results may not be used, reproduced or transmitted in any manner without express written permission from Microsoft Corporation.",
				"entityType": "Address",
				"matchCodes": [
					"Good"
				],
				"name": "5036 Banning Ct, Nanaimo, BC V9V 0A2, Canada",
				"statusCode": 200,
				"statusDescription": "OK",
				"traceId": "da02fffdc5d4420d9301be3e505ee827|BN20210145|7.7.0.0|",
				"addressLine": "5036 Banning Ct",
				"adminDistrict": "BC",
				"adminDistrict2": "Nanaimo",
				"countryRegion": "Canada",
				"formattedAddress": "5036 Banning Ct, Nanaimo, BC V9V 0A2, Canada",
				"locality": "Nanaimo",
				"postalCode": "V9V 0A2"
			},
			"geometry": {
				"type": "Point",
				"coordinates": [
					-123.98116,
					49.23708
				]
			},
			"bbox": [
				-123.9828817,
				49.2359558,
				-123.9794383,
				49.2382042
			]
		}
	]
}
