{
	"type": "FeatureCollection",
	"features": [
		{
			"type": "Feature",
			"properties": {
				"confidence": 9,
				"authenticationResultCode": "ValidCredentials",
				"brandLogoUri": "http://dev.virtualearth.net/Branding/logo_powered_by.png",
				"copyright": "Copyright © 2017 Microsoft and its suppliers. All rights reserved. This API cannot be accessed and the content and any results may not be used, reproduced or transmitted in any manner without express written permission from Microsoft Corporation.",
				"entityType": "Address",
				"matchCodes": [
					"Good"
				],
				"name": "5041 1st Ave, Edson, AB T7E, Canada",
				"statusCode": 200,
				"statusDescription": "OK",
				"traceId": "b62701c060954ffc925f1831dbb010f5|BN20250135|7.7.0.0|",
				"addressLine": "5041 1st Ave",
				"adminDistrict": "AB",
				"adminDistrict2": "Alberta",
				"countryRegion": "Canada",
				"formattedAddress": "5041 1st Ave, Edson, AB T7E, Canada",
				"locality": "Edson",
				"postalCode": "T7E 1T3"
			},
			"geometry": {
				"type": "Point",
				"coordinates": [
					-116.4308643,
					53.5800947
				]
			},
			"bbox": [
				-116.4327577,
				53.5789706,
				-116.4289708,
				53.5812189
			]
		}
	]
}
