{
	"type": "FeatureCollection",
	"features": [
		{
			"type": "Feature",
			"properties": {
				"confidence": 9,
				"authenticationResultCode": "ValidCredentials",
				"brandLogoUri": "http://dev.virtualearth.net/Branding/logo_powered_by.png",
				"copyright": "Copyright © 2017 Microsoft and its suppliers. All rights reserved. This API cannot be accessed and the content and any results may not be used, reproduced or transmitted in any manner without express written permission from Microsoft Corporation.",
				"entityType": "Address",
				"matchCodes": [
					"Good"
				],
				"name": "15183 Russell Ave, White Rock, BC V4B 2P4, Canada",
				"statusCode": 200,
				"statusDescription": "OK",
				"traceId": "470954bd8b7a41c1963ebc9e0b30b6aa|BN20130532|7.7.0.0|",
				"addressLine": "15183 Russell Ave",
				"adminDistrict": "BC",
				"adminDistrict2": "Greater Vancouver",
				"countryRegion": "Canada",
				"formattedAddress": "15183 Russell Ave, White Rock, BC V4B 2P4, Canada",
				"locality": "White Rock",
				"postalCode": "V4B 2P4"
			},
			"geometry": {
				"type": "Point",
				"coordinates": [
					-122.8017131,
					49.0294749
				]
			},
			"bbox": [
				-122.8034276,
				49.0283507,
				-122.7999986,
				49.030599
			]
		}
	]
}
