{
	"type": "FeatureCollection",
	"features": [
		{
			"type": "Feature",
			"properties": {
				"confidence": 9,
				"authenticationResultCode": "ValidCredentials",
				"brandLogoUri": "http://dev.virtualearth.net/Branding/logo_powered_by.png",
				"copyright": "Copyright © 2017 Microsoft and its suppliers. All rights reserved. This API cannot be accessed and the content and any results may not be used, reproduced or transmitted in any manner without express written permission from Microsoft Corporation.",
				"entityType": "Address",
				"matchCodes": [
					"Good"
				],
				"name": "507 12 Ave, Nisku, AB T9E 7N8, Canada",
				"statusCode": 200,
				"statusDescription": "OK",
				"traceId": "b7cd04b9059048b3be0511b45b445c10|BN20130447|7.7.0.0|",
				"addressLine": "507 12 Ave",
				"adminDistrict": "AB",
				"adminDistrict2": "Alberta",
				"countryRegion": "Canada",
				"formattedAddress": "507 12 Ave, Nisku, AB T9E 7N8, Canada",
				"locality": "Leduc County",
				"neighborhood": "Nisku",
				"postalCode": "T9E 7N8"
			},
			"geometry": {
				"type": "Point",
				"coordinates": [
					-113.5288,
					53.31182
				]
			},
			"bbox": [
				-113.5306816,
				53.3106958,
				-113.5269184,
				53.3129442
			]
		}
	]
}
