{
	"type": "FeatureCollection",
	"features": [
		{
			"type": "Feature",
			"properties": {
				"confidence": 9,
				"authenticationResultCode": "ValidCredentials",
				"brandLogoUri": "http://dev.virtualearth.net/Branding/logo_powered_by.png",
				"copyright": "Copyright © 2017 Microsoft and its suppliers. All rights reserved. This API cannot be accessed and the content and any results may not be used, reproduced or transmitted in any manner without express written permission from Microsoft Corporation.",
				"entityType": "Address",
				"matchCodes": [
					"Good"
				],
				"name": "507468 HWY-89, Mono, ON L9V 1J4, Canada",
				"statusCode": 200,
				"statusDescription": "OK",
				"traceId": "28887b1709184cdc96b8d00bca177214|BN20130442|7.7.0.0|",
				"addressLine": "507468 HWY-89",
				"adminDistrict": "ON",
				"adminDistrict2": "Dufferin",
				"countryRegion": "Canada",
				"formattedAddress": "507468 HWY-89, Mono, ON L9V 1J4, Canada",
				"locality": "Mono",
				"postalCode": "L9V 1J4"
			},
			"geometry": {
				"type": "Point",
				"coordinates": [
					-80.0697875,
					44.1052905
				]
			},
			"bbox": [
				-80.071353,
				44.1041663,
				-80.0682219,
				44.1064146
			]
		}
	]
}
