{
	"type": "FeatureCollection",
	"features": [
		{
			"type": "Feature",
			"properties": {
				"confidence": 9,
				"authenticationResultCode": "ValidCredentials",
				"brandLogoUri": "http://dev.virtualearth.net/Branding/logo_powered_by.png",
				"copyright": "Copyright © 2017 Microsoft and its suppliers. All rights reserved. This API cannot be accessed and the content and any results may not be used, reproduced or transmitted in any manner without express written permission from Microsoft Corporation.",
				"entityType": "Address",
				"matchCodes": [
					"Good"
				],
				"name": "508 Hurdville Rd, McKellar, ON P2A 0B5, Canada",
				"statusCode": 200,
				"statusDescription": "OK",
				"traceId": "63064b5a883e4f59951980c77fc9c4be|BN20130431|7.7.0.0|",
				"addressLine": "508 Hurdville Rd",
				"adminDistrict": "ON",
				"adminDistrict2": "Parry Sound",
				"countryRegion": "Canada",
				"formattedAddress": "508 Hurdville Rd, McKellar, ON P2A 0B5, Canada",
				"locality": "McKellar",
				"postalCode": "P2A 0B5"
			},
			"geometry": {
				"type": "Point",
				"coordinates": [
					-79.92029,
					45.43784
				]
			},
			"bbox": [
				-79.9218921,
				45.4367158,
				-79.9186879,
				45.4389642
			]
		}
	]
}
