{
	"type": "FeatureCollection",
	"features": [
		{
			"type": "Feature",
			"properties": {
				"confidence": 9,
				"authenticationResultCode": "ValidCredentials",
				"brandLogoUri": "http://dev.virtualearth.net/Branding/logo_powered_by.png",
				"copyright": "Copyright © 2017 Microsoft and its suppliers. All rights reserved. This API cannot be accessed and the content and any results may not be used, reproduced or transmitted in any manner without express written permission from Microsoft Corporation.",
				"entityType": "Address",
				"matchCodes": [
					"Good"
				],
				"name": "51 Burmac Rd, Winnipeg, MB R2J 4J3, Canada",
				"statusCode": 200,
				"statusDescription": "OK",
				"traceId": "24e312b658d84706be80d065769a16e3|BN20240253|7.7.0.0|",
				"addressLine": "51 Burmac Rd",
				"adminDistrict": "MB",
				"adminDistrict2": "Manitoba",
				"countryRegion": "Canada",
				"formattedAddress": "51 Burmac Rd, Winnipeg, MB R2J 4J3, Canada",
				"locality": "Winnipeg",
				"neighborhood": "The Mint",
				"postalCode": "R2J 4J3"
			},
			"geometry": {
				"type": "Point",
				"coordinates": [
					-97.0529797,
					49.8481849
				]
			},
			"bbox": [
				-97.054723,
				49.8470607,
				-97.0512363,
				49.8493091
			]
		}
	]
}
