{
	"type": "FeatureCollection",
	"features": [
		{
			"type": "Feature",
			"properties": {
				"confidence": 9,
				"authenticationResultCode": "ValidCredentials",
				"brandLogoUri": "http://dev.virtualearth.net/Branding/logo_powered_by.png",
				"copyright": "Copyright © 2017 Microsoft and its suppliers. All rights reserved. This API cannot be accessed and the content and any results may not be used, reproduced or transmitted in any manner without express written permission from Microsoft Corporation.",
				"entityType": "Address",
				"matchCodes": [
					"Good"
				],
				"name": "510 Clothier St E, North Grenville, ON K0G, Canada",
				"statusCode": 200,
				"statusDescription": "OK",
				"traceId": "f3a63131e55a439882d39e56ff73e118|BN20280152|7.7.0.0|",
				"addressLine": "510 Clothier St E",
				"adminDistrict": "ON",
				"adminDistrict2": "Leeds and Grenville",
				"countryRegion": "Canada",
				"formattedAddress": "510 Clothier St E, North Grenville, ON K0G, Canada",
				"locality": "North Grenville",
				"neighborhood": "Kemptville",
				"postalCode": "K0G 1J0"
			},
			"geometry": {
				"type": "Point",
				"coordinates": [
					-75.64182,
					45.02153
				]
			},
			"bbox": [
				-75.6434104,
				45.0204058,
				-75.6402296,
				45.0226542
			]
		}
	]
}
