{
	"type": "FeatureCollection",
	"features": [
		{
			"type": "Feature",
			"properties": {
				"confidence": 9,
				"authenticationResultCode": "ValidCredentials",
				"brandLogoUri": "http://dev.virtualearth.net/Branding/logo_powered_by.png",
				"copyright": "Copyright © 2017 Microsoft and its suppliers. All rights reserved. This API cannot be accessed and the content and any results may not be used, reproduced or transmitted in any manner without express written permission from Microsoft Corporation.",
				"entityType": "Address",
				"matchCodes": [
					"Good"
				],
				"name": "5119 49 Ave, Barrhead, AB T7N 1G3, Canada",
				"statusCode": 200,
				"statusDescription": "OK",
				"traceId": "573f44cddffa4a5493c781b932bb3185|BN20130422|7.7.0.0|",
				"addressLine": "5119 49 Ave",
				"adminDistrict": "AB",
				"adminDistrict2": "Alberta",
				"countryRegion": "Canada",
				"formattedAddress": "5119 49 Ave, Barrhead, AB T7N 1G3, Canada",
				"locality": "Barrhead",
				"postalCode": "T7N 1G3"
			},
			"geometry": {
				"type": "Point",
				"coordinates": [
					-114.40899,
					54.11821
				]
			},
			"bbox": [
				-114.410908,
				54.1170858,
				-114.407072,
				54.1193342
			]
		}
	]
}
