{
	"type": "FeatureCollection",
	"features": [
		{
			"type": "Feature",
			"properties": {
				"confidence": 9,
				"authenticationResultCode": "ValidCredentials",
				"brandLogoUri": "http://dev.virtualearth.net/Branding/logo_powered_by.png",
				"copyright": "Copyright © 2017 Microsoft and its suppliers. All rights reserved. This API cannot be accessed and the content and any results may not be used, reproduced or transmitted in any manner without express written permission from Microsoft Corporation.",
				"entityType": "Address",
				"matchCodes": [
					"Good"
				],
				"name": "512 Waterloo St, London, ON N6B 2P7, Canada",
				"statusCode": 200,
				"statusDescription": "OK",
				"traceId": "d1a340bedf9b4cf5aaa9972419779295|BN20200239|7.7.0.0|",
				"addressLine": "512 Waterloo St",
				"adminDistrict": "ON",
				"adminDistrict2": "Middlesex",
				"countryRegion": "Canada",
				"formattedAddress": "512 Waterloo St, London, ON N6B 2P7, Canada",
				"locality": "London",
				"neighborhood": "Central London",
				"postalCode": "N6B 2P7"
			},
			"geometry": {
				"type": "Point",
				"coordinates": [
					-81.2437999,
					42.9891999
				]
			},
			"bbox": [
				-81.2453367,
				42.9880757,
				-81.2422631,
				42.9903241
			]
		}
	]
}
