{
	"type": "FeatureCollection",
	"features": [
		{
			"type": "Feature",
			"properties": {
				"confidence": 9,
				"authenticationResultCode": "ValidCredentials",
				"brandLogoUri": "http://dev.virtualearth.net/Branding/logo_powered_by.png",
				"copyright": "Copyright © 2017 Microsoft and its suppliers. All rights reserved. This API cannot be accessed and the content and any results may not be used, reproduced or transmitted in any manner without express written permission from Microsoft Corporation.",
				"entityType": "Address",
				"matchCodes": [
					"Good"
				],
				"name": "514 1st St, London, ON N5V, Canada",
				"statusCode": 200,
				"statusDescription": "OK",
				"traceId": "11d83132810e4c8baaef9347bf986811|BN20190653|7.7.0.0|",
				"addressLine": "514 1st St",
				"adminDistrict": "ON",
				"adminDistrict2": "Middlesex",
				"countryRegion": "Canada",
				"formattedAddress": "514 1st St, London, ON N5V, Canada",
				"locality": "London",
				"neighborhood": "Argyle",
				"postalCode": "N5V 1Z3"
			},
			"geometry": {
				"type": "Point",
				"coordinates": [
					-81.196017,
					43.0031854
				]
			},
			"bbox": [
				-81.1975541,
				43.0020613,
				-81.1944798,
				43.0043096
			]
		}
	]
}
