{
	"type": "FeatureCollection",
	"features": [
		{
			"type": "Feature",
			"properties": {
				"confidence": 9,
				"authenticationResultCode": "ValidCredentials",
				"brandLogoUri": "http://dev.virtualearth.net/Branding/logo_powered_by.png",
				"copyright": "Copyright © 2017 Microsoft and its suppliers. All rights reserved. This API cannot be accessed and the content and any results may not be used, reproduced or transmitted in any manner without express written permission from Microsoft Corporation.",
				"entityType": "Address",
				"matchCodes": [
					"Good"
				],
				"name": "5150 72 Ave NW, Edmonton, AB T6B 3H4, Canada",
				"statusCode": 200,
				"statusDescription": "OK",
				"traceId": "670a7f46aba14195a9a3b5e9c064cbd9|BN20260231|7.7.0.0|",
				"addressLine": "5150 72 Ave NW",
				"adminDistrict": "AB",
				"adminDistrict2": "Alberta",
				"countryRegion": "Canada",
				"formattedAddress": "5150 72 Ave NW, Edmonton, AB T6B 3H4, Canada",
				"locality": "Edmonton",
				"neighborhood": "Davies Industrial East",
				"postalCode": "T6B 3H4"
			},
			"geometry": {
				"type": "Point",
				"coordinates": [
					-113.41966,
					53.50842
				]
			},
			"bbox": [
				-113.4215503,
				53.5072958,
				-113.4177697,
				53.5095442
			]
		}
	]
}
