{
	"type": "FeatureCollection",
	"features": [
		{
			"type": "Feature",
			"properties": {
				"confidence": 9,
				"authenticationResultCode": "ValidCredentials",
				"brandLogoUri": "http://dev.virtualearth.net/Branding/logo_powered_by.png",
				"copyright": "Copyright © 2017 Microsoft and its suppliers. All rights reserved. This API cannot be accessed and the content and any results may not be used, reproduced or transmitted in any manner without express written permission from Microsoft Corporation.",
				"entityType": "Address",
				"matchCodes": [
					"Good"
				],
				"name": "518 Moberly Rd, Vancouver, BC V5Z 4G3, Canada",
				"statusCode": 200,
				"statusDescription": "OK",
				"traceId": "04c075b8cdbd423eb1f88676af74cd2a|BN20190642|7.7.0.0|",
				"addressLine": "518 Moberly Rd",
				"adminDistrict": "BC",
				"adminDistrict2": "Greater Vancouver",
				"countryRegion": "Canada",
				"formattedAddress": "518 Moberly Rd, Vancouver, BC V5Z 4G3, Canada",
				"locality": "Vancouver",
				"neighborhood": "Fairview",
				"postalCode": "V5Z 4G3"
			},
			"geometry": {
				"type": "Point",
				"coordinates": [
					-123.1173276,
					49.2676126
				]
			},
			"bbox": [
				-123.1190503,
				49.2664885,
				-123.1156048,
				49.2687368
			]
		}
	]
}
