{
	"type": "FeatureCollection",
	"features": [
		{
			"type": "Feature",
			"properties": {
				"confidence": 9,
				"authenticationResultCode": "ValidCredentials",
				"brandLogoUri": "http://dev.virtualearth.net/Branding/logo_powered_by.png",
				"copyright": "Copyright © 2017 Microsoft and its suppliers. All rights reserved. This API cannot be accessed and the content and any results may not be used, reproduced or transmitted in any manner without express written permission from Microsoft Corporation.",
				"entityType": "Address",
				"matchCodes": [
					"Good"
				],
				"name": "520 Millway Ave, Concord, ON L4K 3V5, Canada",
				"statusCode": 200,
				"statusDescription": "OK",
				"traceId": "f3673a5f8f174dee99a5fd34d02d21e7|BN20130631|7.7.0.0|",
				"addressLine": "520 Millway Ave",
				"adminDistrict": "ON",
				"adminDistrict2": "York",
				"countryRegion": "Canada",
				"formattedAddress": "520 Millway Ave, Concord, ON L4K 3V5, Canada",
				"locality": "Vaughan",
				"neighborhood": "Concord",
				"postalCode": "L4K 3V5"
			},
			"geometry": {
				"type": "Point",
				"coordinates": [
					-79.53095,
					43.80729
				]
			},
			"bbox": [
				-79.5325077,
				43.8061658,
				-79.5293923,
				43.8084142
			]
		}
	]
}
