{
	"type": "FeatureCollection",
	"features": [
		{
			"type": "Feature",
			"properties": {
				"confidence": 9,
				"authenticationResultCode": "ValidCredentials",
				"brandLogoUri": "http://dev.virtualearth.net/Branding/logo_powered_by.png",
				"copyright": "Copyright © 2017 Microsoft and its suppliers. All rights reserved. This API cannot be accessed and the content and any results may not be used, reproduced or transmitted in any manner without express written permission from Microsoft Corporation.",
				"entityType": "Address",
				"matchCodes": [
					"Good"
				],
				"name": "520 King St, Fredericton, NB E3B 6G3, Canada",
				"statusCode": 200,
				"statusDescription": "OK",
				"traceId": "9c39ea951e9942d485381297fc64542a|BN20260223|7.7.0.0|",
				"addressLine": "520 King St",
				"adminDistrict": "NB",
				"adminDistrict2": "York",
				"countryRegion": "Canada",
				"formattedAddress": "520 King St, Fredericton, NB E3B 6G3, Canada",
				"locality": "Fredericton",
				"postalCode": "E3B 6G3"
			},
			"geometry": {
				"type": "Point",
				"coordinates": [
					-66.64119,
					45.96074
				]
			},
			"bbox": [
				-66.6428071,
				45.9596158,
				-66.6395729,
				45.9618642
			]
		}
	]
}
