{
	"type": "FeatureCollection",
	"features": [
		{
			"type": "Feature",
			"properties": {
				"confidence": 9,
				"authenticationResultCode": "ValidCredentials",
				"brandLogoUri": "http://dev.virtualearth.net/Branding/logo_powered_by.png",
				"copyright": "Copyright © 2017 Microsoft and its suppliers. All rights reserved. This API cannot be accessed and the content and any results may not be used, reproduced or transmitted in any manner without express written permission from Microsoft Corporation.",
				"entityType": "Address",
				"matchCodes": [
					"Good"
				],
				"name": "5201 64 Ave SE, Calgary, AB T2C 4Z9, Canada",
				"statusCode": 200,
				"statusDescription": "OK",
				"traceId": "49e1b0b6cff642018076cb7ae0fe8c3f|BN20130423|7.7.0.0|",
				"addressLine": "5201 64 Ave SE",
				"adminDistrict": "AB",
				"adminDistrict2": "Alberta",
				"countryRegion": "Canada",
				"formattedAddress": "5201 64 Ave SE, Calgary, AB T2C 4Z9, Canada",
				"locality": "Calgary",
				"neighborhood": "Foothills",
				"postalCode": "T2C 4Z9"
			},
			"geometry": {
				"type": "Point",
				"coordinates": [
					-113.9604562,
					50.9967076
				]
			},
			"bbox": [
				-113.9622424,
				50.9955834,
				-113.95867,
				50.9978317
			]
		}
	]
}
