{
	"type": "FeatureCollection",
	"features": [
		{
			"type": "Feature",
			"properties": {
				"confidence": 9,
				"authenticationResultCode": "ValidCredentials",
				"brandLogoUri": "http://dev.virtualearth.net/Branding/logo_powered_by.png",
				"copyright": "Copyright © 2017 Microsoft and its suppliers. All rights reserved. This API cannot be accessed and the content and any results may not be used, reproduced or transmitted in any manner without express written permission from Microsoft Corporation.",
				"entityType": "Address",
				"matchCodes": [
					"Good"
				],
				"name": "521 Bayfield St, Barrie, ON L4M 4Z9, Canada",
				"statusCode": 200,
				"statusDescription": "OK",
				"traceId": "a8d370d088204043b52b776237b39884|BN20130521|7.7.0.0|",
				"addressLine": "521 Bayfield St",
				"adminDistrict": "ON",
				"adminDistrict2": "Simcoe",
				"countryRegion": "Canada",
				"formattedAddress": "521 Bayfield St, Barrie, ON L4M 4Z9, Canada",
				"locality": "Barrie",
				"neighborhood": "Bayfield",
				"postalCode": "L4M 4Z9"
			},
			"geometry": {
				"type": "Point",
				"coordinates": [
					-79.71122,
					44.41407
				]
			},
			"bbox": [
				-79.7127938,
				44.4129458,
				-79.7096462,
				44.4151942
			]
		}
	]
}
