{
	"type": "FeatureCollection",
	"features": [
		{
			"type": "Feature",
			"properties": {
				"confidence": 9,
				"authenticationResultCode": "ValidCredentials",
				"brandLogoUri": "http://dev.virtualearth.net/Branding/logo_powered_by.png",
				"copyright": "Copyright © 2017 Microsoft and its suppliers. All rights reserved. This API cannot be accessed and the content and any results may not be used, reproduced or transmitted in any manner without express written permission from Microsoft Corporation.",
				"entityType": "Address",
				"matchCodes": [
					"Good"
				],
				"name": "522 James St N, Hamilton, ON L8L 1J4, Canada",
				"statusCode": 200,
				"statusDescription": "OK",
				"traceId": "3469056ad2f94230beab980fbea74863|BN20130625|7.7.0.0|",
				"addressLine": "522 James St N",
				"adminDistrict": "ON",
				"adminDistrict2": "Hamilton",
				"countryRegion": "Canada",
				"formattedAddress": "522 James St N, Hamilton, ON L8L 1J4, Canada",
				"locality": "Hamilton",
				"neighborhood": "North End East",
				"postalCode": "L8L 1J4"
			},
			"geometry": {
				"type": "Point",
				"coordinates": [
					-79.86277,
					43.27049
				]
			},
			"bbox": [
				-79.8643139,
				43.2693658,
				-79.8612261,
				43.2716142
			]
		}
	]
}
