{
	"type": "FeatureCollection",
	"features": [
		{
			"type": "Feature",
			"properties": {
				"confidence": 9,
				"authenticationResultCode": "ValidCredentials",
				"brandLogoUri": "http://dev.virtualearth.net/Branding/logo_powered_by.png",
				"copyright": "Copyright © 2017 Microsoft and its suppliers. All rights reserved. This API cannot be accessed and the content and any results may not be used, reproduced or transmitted in any manner without express written permission from Microsoft Corporation.",
				"entityType": "Address",
				"matchCodes": [
					"Good"
				],
				"name": "5225 Rue Debours, Pierrefonds, QC H8Z 3L8, Canada",
				"statusCode": 200,
				"statusDescription": "OK",
				"traceId": "a2ab8a2644404434b00b1b1537f939da|BN20121763|7.7.0.0|",
				"addressLine": "5225 Rue Debours",
				"adminDistrict": "QC",
				"adminDistrict2": "Montreal",
				"countryRegion": "Canada",
				"formattedAddress": "5225 Rue Debours, Pierrefonds, QC H8Z 3L8, Canada",
				"locality": "Montreal",
				"neighborhood": "Pierrefonds",
				"postalCode": "H8Z 3L8"
			},
			"geometry": {
				"type": "Point",
				"coordinates": [
					-73.82451,
					45.51395
				]
			},
			"bbox": [
				-73.8261142,
				45.5128258,
				-73.8229058,
				45.5150742
			]
		}
	]
}
