{
	"type": "FeatureCollection",
	"features": [
		{
			"type": "Feature",
			"properties": {
				"confidence": 9,
				"authenticationResultCode": "ValidCredentials",
				"brandLogoUri": "http://dev.virtualearth.net/Branding/logo_powered_by.png",
				"copyright": "Copyright © 2017 Microsoft and its suppliers. All rights reserved. This API cannot be accessed and the content and any results may not be used, reproduced or transmitted in any manner without express written permission from Microsoft Corporation.",
				"entityType": "Address",
				"matchCodes": [
					"Good"
				],
				"name": "5260 River Forest Ct, Mississauga, ON L5V 2C6, Canada",
				"statusCode": 200,
				"statusDescription": "OK",
				"traceId": "1f9ec59205ba493fa949998ca578ed91|BN20130634|7.7.0.0|",
				"addressLine": "5260 River Forest Ct",
				"adminDistrict": "ON",
				"adminDistrict2": "Peel",
				"countryRegion": "Canada",
				"formattedAddress": "5260 River Forest Ct, Mississauga, ON L5V 2C6, Canada",
				"locality": "Mississauga",
				"postalCode": "L5V 2C6"
			},
			"geometry": {
				"type": "Point",
				"coordinates": [
					-79.68665,
					43.5868899
				]
			},
			"bbox": [
				-79.688202,
				43.5857657,
				-79.685098,
				43.5880141
			]
		}
	]
}
