{
	"type": "FeatureCollection",
	"features": [
		{
			"type": "Feature",
			"properties": {
				"confidence": 9,
				"authenticationResultCode": "ValidCredentials",
				"brandLogoUri": "http://dev.virtualearth.net/Branding/logo_powered_by.png",
				"copyright": "Copyright © 2017 Microsoft and its suppliers. All rights reserved. This API cannot be accessed and the content and any results may not be used, reproduced or transmitted in any manner without express written permission from Microsoft Corporation.",
				"entityType": "Address",
				"matchCodes": [
					"Good"
				],
				"name": "53 Rue Price O, Chicoutimi, QC G7J 1G5, Canada",
				"statusCode": 200,
				"statusDescription": "OK",
				"traceId": "8666c47098c147488c8a4ff47295573c|BN20130520|7.7.0.0|",
				"addressLine": "53 Rue Price O",
				"adminDistrict": "QC",
				"adminDistrict2": "Saguenay",
				"countryRegion": "Canada",
				"formattedAddress": "53 Rue Price O, Chicoutimi, QC G7J 1G5, Canada",
				"locality": "Saguenay",
				"neighborhood": "Chicoutimi",
				"postalCode": "G7J 1G5"
			},
			"geometry": {
				"type": "Point",
				"coordinates": [
					-71.07035,
					48.42566
				]
			},
			"bbox": [
				-71.072044,
				48.4245358,
				-71.068656,
				48.4267842
			]
		}
	]
}
