{
	"type": "FeatureCollection",
	"features": [
		{
			"type": "Feature",
			"properties": {
				"confidence": 9,
				"authenticationResultCode": "ValidCredentials",
				"brandLogoUri": "http://dev.virtualearth.net/Branding/logo_powered_by.png",
				"copyright": "Copyright © 2017 Microsoft and its suppliers. All rights reserved. This API cannot be accessed and the content and any results may not be used, reproduced or transmitted in any manner without express written permission from Microsoft Corporation.",
				"entityType": "Address",
				"matchCodes": [
					"Good"
				],
				"name": "530 9 Ave N, Lethbridge, AB T1H 1E4, Canada",
				"statusCode": 200,
				"statusDescription": "OK",
				"traceId": "c6205cac0be94893ae0ff515e3350ad4|BN20171457|7.7.0.0|",
				"addressLine": "530 9 Ave N",
				"adminDistrict": "AB",
				"adminDistrict2": "Alberta",
				"countryRegion": "Canada",
				"formattedAddress": "530 9 Ave N, Lethbridge, AB T1H 1E4, Canada",
				"locality": "Lethbridge",
				"postalCode": "T1H 1E4"
			},
			"geometry": {
				"type": "Point",
				"coordinates": [
					-112.84069,
					49.71191
				]
			},
			"bbox": [
				-112.8424285,
				49.7107858,
				-112.8389515,
				49.7130342
			]
		}
	]
}
