{
	"type": "FeatureCollection",
	"features": [
		{
			"type": "Feature",
			"properties": {
				"confidence": 9,
				"authenticationResultCode": "ValidCredentials",
				"brandLogoUri": "http://dev.virtualearth.net/Branding/logo_powered_by.png",
				"copyright": "Copyright © 2017 Microsoft and its suppliers. All rights reserved. This API cannot be accessed and the content and any results may not be used, reproduced or transmitted in any manner without express written permission from Microsoft Corporation.",
				"entityType": "Address",
				"matchCodes": [
					"Good"
				],
				"name": "532 William St, Victoria, BC V9A 3Y9, Canada",
				"statusCode": 200,
				"statusDescription": "OK",
				"traceId": "0f54ce801c3b4023a0178b4488b043cf|BN20260223|7.7.0.0|",
				"addressLine": "532 William St",
				"adminDistrict": "BC",
				"adminDistrict2": "Capital",
				"countryRegion": "Canada",
				"formattedAddress": "532 William St, Victoria, BC V9A 3Y9, Canada",
				"locality": "Victoria",
				"neighborhood": "Victoria West",
				"postalCode": "V9A 3Y9"
			},
			"geometry": {
				"type": "Point",
				"coordinates": [
					-123.3891154,
					48.4322214
				]
			},
			"bbox": [
				-123.3908097,
				48.4310972,
				-123.3874211,
				48.4333455
			]
		}
	]
}
