{
	"type": "FeatureCollection",
	"features": [
		{
			"type": "Feature",
			"properties": {
				"confidence": 9,
				"authenticationResultCode": "ValidCredentials",
				"brandLogoUri": "http://dev.virtualearth.net/Branding/logo_powered_by.png",
				"copyright": "Copyright © 2017 Microsoft and its suppliers. All rights reserved. This API cannot be accessed and the content and any results may not be used, reproduced or transmitted in any manner without express written permission from Microsoft Corporation.",
				"entityType": "Address",
				"matchCodes": [
					"Good"
				],
				"name": "537 Rue du Charpentier, Bromont, QC J2L 3L7, Canada",
				"statusCode": 200,
				"statusDescription": "OK",
				"traceId": "0647cd7f7c274a51b85a0b5d74368ccf|BN20171457|7.7.0.0|",
				"addressLine": "537 Rue du Charpentier",
				"adminDistrict": "QC",
				"adminDistrict2": "Brome-Missisquoi",
				"countryRegion": "Canada",
				"formattedAddress": "537 Rue du Charpentier, Bromont, QC J2L 3L7, Canada",
				"locality": "Bromont",
				"postalCode": "J2L 3L7"
			},
			"geometry": {
				"type": "Point",
				"coordinates": [
					-72.66436,
					45.32461
				]
			},
			"bbox": [
				-72.6659589,
				45.3234858,
				-72.6627611,
				45.3257342
			]
		}
	]
}
