{
	"type": "FeatureCollection",
	"features": [
		{
			"type": "Feature",
			"properties": {
				"confidence": 9,
				"authenticationResultCode": "ValidCredentials",
				"brandLogoUri": "http://dev.virtualearth.net/Branding/logo_powered_by.png",
				"copyright": "Copyright © 2017 Microsoft and its suppliers. All rights reserved. This API cannot be accessed and the content and any results may not be used, reproduced or transmitted in any manner without express written permission from Microsoft Corporation.",
				"entityType": "Address",
				"matchCodes": [
					"Good"
				],
				"name": "538 Squires St, Fredericton, NB E3B 3V4, Canada",
				"statusCode": 200,
				"statusDescription": "OK",
				"traceId": "cea57caa2d0f44ceb0880378550010d1|BN20131519|7.7.0.0|",
				"addressLine": "538 Squires St",
				"adminDistrict": "NB",
				"adminDistrict2": "York",
				"countryRegion": "Canada",
				"formattedAddress": "538 Squires St, Fredericton, NB E3B 3V4, Canada",
				"locality": "Fredericton",
				"postalCode": "E3B 3V4"
			},
			"geometry": {
				"type": "Point",
				"coordinates": [
					-66.65297,
					45.94778
				]
			},
			"bbox": [
				-66.6545868,
				45.9466558,
				-66.6513532,
				45.9489042
			]
		}
	]
}
