{
	"type": "FeatureCollection",
	"features": [
		{
			"type": "Feature",
			"properties": {
				"confidence": 9,
				"authenticationResultCode": "ValidCredentials",
				"brandLogoUri": "http://dev.virtualearth.net/Branding/logo_powered_by.png",
				"copyright": "Copyright © 2017 Microsoft and its suppliers. All rights reserved. This API cannot be accessed and the content and any results may not be used, reproduced or transmitted in any manner without express written permission from Microsoft Corporation.",
				"entityType": "Address",
				"matchCodes": [
					"Good"
				],
				"name": "540 HWY-16, Burns Lake, BC V0J, Canada",
				"statusCode": 200,
				"statusDescription": "OK",
				"traceId": "c50b0c8898704a4ca49bb2d3ac686253|BN20240423|7.7.0.0|",
				"addressLine": "540 HWY-16",
				"adminDistrict": "BC",
				"adminDistrict2": "Bulkley-Nechako",
				"countryRegion": "Canada",
				"formattedAddress": "540 HWY-16, Burns Lake, BC V0J, Canada",
				"locality": "Burns Lake",
				"postalCode": "V0J 1E0"
			},
			"geometry": {
				"type": "Point",
				"coordinates": [
					-125.7629213,
					54.232047
				]
			},
			"bbox": [
				-125.7648445,
				54.2309229,
				-125.760998,
				54.2331712
			]
		}
	]
}
