{
	"type": "FeatureCollection",
	"features": [
		{
			"type": "Feature",
			"properties": {
				"confidence": 9,
				"authenticationResultCode": "ValidCredentials",
				"brandLogoUri": "http://dev.virtualearth.net/Branding/logo_powered_by.png",
				"copyright": "Copyright © 2017 Microsoft and its suppliers. All rights reserved. This API cannot be accessed and the content and any results may not be used, reproduced or transmitted in any manner without express written permission from Microsoft Corporation.",
				"entityType": "Address",
				"matchCodes": [
					"Good"
				],
				"name": "5421 Long Island Rd, Manotick, ON K4M 1H1, Canada",
				"statusCode": 200,
				"statusDescription": "OK",
				"traceId": "8dd139a88c6144e7878b1d62df2d6353|BN20130431|7.7.0.0|",
				"addressLine": "5421 Long Island Rd",
				"adminDistrict": "ON",
				"adminDistrict2": "Ottawa",
				"countryRegion": "Canada",
				"formattedAddress": "5421 Long Island Rd, Manotick, ON K4M 1H1, Canada",
				"locality": "Ottawa",
				"neighborhood": "Manotick",
				"postalCode": "K4M 1H1"
			},
			"geometry": {
				"type": "Point",
				"coordinates": [
					-75.68655,
					45.2334699
				]
			},
			"bbox": [
				-75.6881463,
				45.2323457,
				-75.6849537,
				45.2345941
			]
		}
	]
}
