{
	"type": "FeatureCollection",
	"features": [
		{
			"type": "Feature",
			"properties": {
				"confidence": 9,
				"authenticationResultCode": "ValidCredentials",
				"brandLogoUri": "http://dev.virtualearth.net/Branding/logo_powered_by.png",
				"copyright": "Copyright © 2017 Microsoft and its suppliers. All rights reserved. This API cannot be accessed and the content and any results may not be used, reproduced or transmitted in any manner without express written permission from Microsoft Corporation.",
				"entityType": "Address",
				"matchCodes": [
					"Good"
				],
				"name": "544 Clarke Rd, London, ON N5V 3K5, Canada",
				"statusCode": 200,
				"statusDescription": "OK",
				"traceId": "cb102ea0d22c43fbb57eec73e3fa0473|BN20210145|7.7.0.0|",
				"addressLine": "544 Clarke Rd",
				"adminDistrict": "ON",
				"adminDistrict2": "Middlesex",
				"countryRegion": "Canada",
				"formattedAddress": "544 Clarke Rd, London, ON N5V 3K5, Canada",
				"locality": "London",
				"neighborhood": "Airport",
				"postalCode": "N5V 3K5"
			},
			"geometry": {
				"type": "Point",
				"coordinates": [
					-81.1774,
					43.0104
				]
			},
			"bbox": [
				-81.1789373,
				43.0092758,
				-81.1758627,
				43.0115242
			]
		}
	]
}
