{
	"type": "FeatureCollection",
	"features": [
		{
			"type": "Feature",
			"properties": {
				"confidence": 9,
				"authenticationResultCode": "ValidCredentials",
				"brandLogoUri": "http://dev.virtualearth.net/Branding/logo_powered_by.png",
				"copyright": "Copyright © 2017 Microsoft and its suppliers. All rights reserved. This API cannot be accessed and the content and any results may not be used, reproduced or transmitted in any manner without express written permission from Microsoft Corporation.",
				"entityType": "Address",
				"matchCodes": [
					"Good"
				],
				"name": "5440 53 St SE, Calgary, AB T2C 4B6, Canada",
				"statusCode": 200,
				"statusDescription": "OK",
				"traceId": "0681f032a1aa45a292f5f86f02865476|BN20300154|7.7.0.0|",
				"addressLine": "5440 53 St SE",
				"adminDistrict": "AB",
				"adminDistrict2": "Alberta",
				"countryRegion": "Canada",
				"formattedAddress": "5440 53 St SE, Calgary, AB T2C 4B6, Canada",
				"locality": "Calgary",
				"postalCode": "T2C 4B6"
			},
			"geometry": {
				"type": "Point",
				"coordinates": [
					-113.9564051,
					51.0044992
				]
			},
			"bbox": [
				-113.9581916,
				51.003375,
				-113.9546186,
				51.0056233
			]
		}
	]
}
