{
	"type": "FeatureCollection",
	"features": [
		{
			"type": "Feature",
			"properties": {
				"confidence": 9,
				"authenticationResultCode": "ValidCredentials",
				"brandLogoUri": "http://dev.virtualearth.net/Branding/logo_powered_by.png",
				"copyright": "Copyright © 2017 Microsoft and its suppliers. All rights reserved. This API cannot be accessed and the content and any results may not be used, reproduced or transmitted in any manner without express written permission from Microsoft Corporation.",
				"entityType": "Address",
				"matchCodes": [
					"Good"
				],
				"name": "5450 Cornwallis St, Halifax, NS B3K 1A9, Canada",
				"statusCode": 200,
				"statusDescription": "OK",
				"traceId": "595d34b83e454af796a6c47582fbae12|BN20130533|7.7.0.0|",
				"addressLine": "5450 Cornwallis St",
				"adminDistrict": "NS",
				"adminDistrict2": "Halifax",
				"countryRegion": "Canada",
				"formattedAddress": "5450 Cornwallis St, Halifax, NS B3K 1A9, Canada",
				"locality": "Halifax",
				"neighborhood": "North End",
				"postalCode": "B3K 1A9"
			},
			"geometry": {
				"type": "Point",
				"coordinates": [
					-63.58316,
					44.65262
				]
			},
			"bbox": [
				-63.5847402,
				44.6514958,
				-63.5815798,
				44.6537442
			]
		}
	]
}
