{
	"type": "FeatureCollection",
	"features": [
		{
			"type": "Feature",
			"properties": {
				"confidence": 9,
				"authenticationResultCode": "ValidCredentials",
				"brandLogoUri": "http://dev.virtualearth.net/Branding/logo_powered_by.png",
				"copyright": "Copyright © 2017 Microsoft and its suppliers. All rights reserved. This API cannot be accessed and the content and any results may not be used, reproduced or transmitted in any manner without express written permission from Microsoft Corporation.",
				"entityType": "Address",
				"matchCodes": [
					"Good"
				],
				"name": "55 Dunlop Rd, Winnipeg, MB R2X, Canada",
				"statusCode": 200,
				"statusDescription": "OK",
				"traceId": "635ce1b21b964ebc91dcb63d4fec0a1e|BN20130521|7.7.0.0|",
				"addressLine": "55 Dunlop Rd",
				"adminDistrict": "MB",
				"adminDistrict2": "Manitoba",
				"countryRegion": "Canada",
				"formattedAddress": "55 Dunlop Rd, Winnipeg, MB R2X, Canada",
				"locality": "Winnipeg",
				"neighborhood": "Inkster Industrial Park",
				"postalCode": "R2X 2V2"
			},
			"geometry": {
				"type": "Point",
				"coordinates": [
					-97.1832699,
					49.94403
				]
			},
			"bbox": [
				-97.1850167,
				49.9429058,
				-97.1815231,
				49.9451542
			]
		}
	]
}
