{
	"type": "FeatureCollection",
	"features": [
		{
			"type": "Feature",
			"properties": {
				"confidence": 9,
				"authenticationResultCode": "ValidCredentials",
				"brandLogoUri": "http://dev.virtualearth.net/Branding/logo_powered_by.png",
				"copyright": "Copyright © 2017 Microsoft and its suppliers. All rights reserved. This API cannot be accessed and the content and any results may not be used, reproduced or transmitted in any manner without express written permission from Microsoft Corporation.",
				"entityType": "Address",
				"matchCodes": [
					"Good"
				],
				"name": "55 John St, Alton, ON L7K 0C4, Canada",
				"statusCode": 200,
				"statusDescription": "OK",
				"traceId": "e0d18cc0132848e6b2a8659c56ce690d|BN20130422|7.7.0.0|",
				"addressLine": "55 John St",
				"adminDistrict": "ON",
				"adminDistrict2": "Peel",
				"countryRegion": "Canada",
				"formattedAddress": "55 John St, Alton, ON L7K 0C4, Canada",
				"locality": "Caledon",
				"neighborhood": "Alton",
				"postalCode": "L7K 0C4"
			},
			"geometry": {
				"type": "Point",
				"coordinates": [
					-80.0229347,
					43.8255161
				]
			},
			"bbox": [
				-80.0244929,
				43.824392,
				-80.0213766,
				43.8266403
			]
		}
	]
}
