{
	"type": "FeatureCollection",
	"features": [
		{
			"type": "Feature",
			"properties": {
				"confidence": 9,
				"authenticationResultCode": "ValidCredentials",
				"brandLogoUri": "http://dev.virtualearth.net/Branding/logo_powered_by.png",
				"copyright": "Copyright © 2017 Microsoft and its suppliers. All rights reserved. This API cannot be accessed and the content and any results may not be used, reproduced or transmitted in any manner without express written permission from Microsoft Corporation.",
				"entityType": "Address",
				"matchCodes": [
					"Good"
				],
				"name": "550 Hall Ave, Renfrew, ON K7V, Canada",
				"statusCode": 200,
				"statusDescription": "OK",
				"traceId": "406b34c5a717459ab43f8cd9459339e9|BN20121764|7.7.0.0|",
				"addressLine": "550 Hall Ave",
				"adminDistrict": "ON",
				"adminDistrict2": "Renfrew",
				"countryRegion": "Canada",
				"formattedAddress": "550 Hall Ave, Renfrew, ON K7V, Canada",
				"locality": "Renfrew",
				"postalCode": "K7V 2S9"
			},
			"geometry": {
				"type": "Point",
				"coordinates": [
					-76.6696677,
					45.4761814
				]
			},
			"bbox": [
				-76.6712709,
				45.4750573,
				-76.6680645,
				45.4773056
			]
		}
	]
}
