{
	"type": "FeatureCollection",
	"features": [
		{
			"type": "Feature",
			"properties": {
				"confidence": 9,
				"authenticationResultCode": "ValidCredentials",
				"brandLogoUri": "http://dev.virtualearth.net/Branding/logo_powered_by.png",
				"copyright": "Copyright © 2017 Microsoft and its suppliers. All rights reserved. This API cannot be accessed and the content and any results may not be used, reproduced or transmitted in any manner without express written permission from Microsoft Corporation.",
				"entityType": "Address",
				"matchCodes": [
					"Good"
				],
				"name": "5500 Parkwood Way, Richmond, BC V6V 2M4, Canada",
				"statusCode": 200,
				"statusDescription": "OK",
				"traceId": "14a22f0e291742b986576ca5fbb4ccf7|BN20130431|7.7.0.0|",
				"addressLine": "5500 Parkwood Way",
				"adminDistrict": "BC",
				"adminDistrict2": "Greater Vancouver",
				"countryRegion": "Canada",
				"formattedAddress": "5500 Parkwood Way, Richmond, BC V6V 2M4, Canada",
				"locality": "Richmond",
				"neighborhood": "East Cambie",
				"postalCode": "V6V 2M4"
			},
			"geometry": {
				"type": "Point",
				"coordinates": [
					-123.07841,
					49.17553
				]
			},
			"bbox": [
				-123.0801296,
				49.1744058,
				-123.0766904,
				49.1766542
			]
		}
	]
}
