{
	"type": "FeatureCollection",
	"features": [
		{
			"type": "Feature",
			"properties": {
				"confidence": 9,
				"authenticationResultCode": "ValidCredentials",
				"brandLogoUri": "http://dev.virtualearth.net/Branding/logo_powered_by.png",
				"copyright": "Copyright © 2017 Microsoft and its suppliers. All rights reserved. This API cannot be accessed and the content and any results may not be used, reproduced or transmitted in any manner without express written permission from Microsoft Corporation.",
				"entityType": "Address",
				"matchCodes": [
					"Good"
				],
				"name": "5500 Alaska Hwy, Peace River, BC V0C, Canada",
				"statusCode": 200,
				"statusDescription": "OK",
				"traceId": "fd25f7ab697148c894753b53df511737|BN20130532|7.7.0.0|",
				"addressLine": "5500 Alaska Hwy",
				"adminDistrict": "BC",
				"adminDistrict2": "Peace River",
				"countryRegion": "Canada",
				"formattedAddress": "5500 Alaska Hwy, Peace River, BC V0C, Canada",
				"locality": "Peace River",
				"postalCode": "V0C 1R0"
			},
			"geometry": {
				"type": "Point",
				"coordinates": [
					-120.4274581,
					55.8755526
				]
			},
			"bbox": [
				-120.429462,
				55.8744285,
				-120.4254543,
				55.8766768
			]
		}
	]
}
