{
	"type": "FeatureCollection",
	"features": [
		{
			"type": "Feature",
			"properties": {
				"confidence": 9,
				"authenticationResultCode": "ValidCredentials",
				"brandLogoUri": "http://dev.virtualearth.net/Branding/logo_powered_by.png",
				"copyright": "Copyright © 2017 Microsoft and its suppliers. All rights reserved. This API cannot be accessed and the content and any results may not be used, reproduced or transmitted in any manner without express written permission from Microsoft Corporation.",
				"entityType": "Address",
				"matchCodes": [
					"Good"
				],
				"name": "5502 Wales St, Vancouver, BC V5R 3M8, Canada",
				"statusCode": 200,
				"statusDescription": "OK",
				"traceId": "63431188e8034c09af914515ae7108f5|BN20130721|7.7.0.0|",
				"addressLine": "5502 Wales St",
				"adminDistrict": "BC",
				"adminDistrict2": "Greater Vancouver",
				"countryRegion": "Canada",
				"formattedAddress": "5502 Wales St, Vancouver, BC V5R 3M8, Canada",
				"locality": "Vancouver",
				"neighborhood": "Renfrew-Collingwood",
				"postalCode": "V5R 3M8"
			},
			"geometry": {
				"type": "Point",
				"coordinates": [
					-123.05132,
					49.2348
				]
			},
			"bbox": [
				-123.0530416,
				49.2336758,
				-123.0495984,
				49.2359242
			]
		}
	]
}
