{
	"type": "FeatureCollection",
	"features": [
		{
			"type": "Feature",
			"properties": {
				"confidence": 9,
				"authenticationResultCode": "ValidCredentials",
				"brandLogoUri": "http://dev.virtualearth.net/Branding/logo_powered_by.png",
				"copyright": "Copyright © 2017 Microsoft and its suppliers. All rights reserved. This API cannot be accessed and the content and any results may not be used, reproduced or transmitted in any manner without express written permission from Microsoft Corporation.",
				"entityType": "Address",
				"matchCodes": [
					"Good"
				],
				"name": "552 Rue Bellevue N, Greenfield Park, QC J4V 1C8, Canada",
				"statusCode": 200,
				"statusDescription": "OK",
				"traceId": "70731a26ac4d4a43b9c20d846a03b045|BN20130423|7.7.0.0|",
				"addressLine": "552 Rue Bellevue N",
				"adminDistrict": "QC",
				"adminDistrict2": "Longueuil",
				"countryRegion": "Canada",
				"formattedAddress": "552 Rue Bellevue N, Greenfield Park, QC J4V 1C8, Canada",
				"locality": "Longueuil",
				"neighborhood": "Greenfield Park",
				"postalCode": "J4V 1C8"
			},
			"geometry": {
				"type": "Point",
				"coordinates": [
					-73.45793,
					45.48678
				]
			},
			"bbox": [
				-73.4595335,
				45.4856558,
				-73.4563265,
				45.4879042
			]
		}
	]
}
