{
	"type": "FeatureCollection",
	"features": [
		{
			"type": "Feature",
			"properties": {
				"confidence": 9,
				"authenticationResultCode": "ValidCredentials",
				"brandLogoUri": "http://dev.virtualearth.net/Branding/logo_powered_by.png",
				"copyright": "Copyright © 2017 Microsoft and its suppliers. All rights reserved. This API cannot be accessed and the content and any results may not be used, reproduced or transmitted in any manner without express written permission from Microsoft Corporation.",
				"entityType": "Address",
				"matchCodes": [
					"Good"
				],
				"name": "553 Basaltic Rd, Concord, ON L4K 4W8, Canada",
				"statusCode": 200,
				"statusDescription": "OK",
				"traceId": "0715e69a9be845f3867e45a76a3fef34|BN20200137|7.7.0.0|",
				"addressLine": "553 Basaltic Rd",
				"adminDistrict": "ON",
				"adminDistrict2": "York",
				"countryRegion": "Canada",
				"formattedAddress": "553 Basaltic Rd, Concord, ON L4K 4W8, Canada",
				"locality": "Vaughan",
				"neighborhood": "Concord",
				"postalCode": "L4K 4W8"
			},
			"geometry": {
				"type": "Point",
				"coordinates": [
					-79.49856,
					43.83401
				]
			},
			"bbox": [
				-79.5001184,
				43.8328858,
				-79.4970016,
				43.8351342
			]
		}
	]
}
