{
	"type": "FeatureCollection",
	"features": [
		{
			"type": "Feature",
			"properties": {
				"confidence": 9,
				"authenticationResultCode": "ValidCredentials",
				"brandLogoUri": "http://dev.virtualearth.net/Branding/logo_powered_by.png",
				"copyright": "Copyright © 2017 Microsoft and its suppliers. All rights reserved. This API cannot be accessed and the content and any results may not be used, reproduced or transmitted in any manner without express written permission from Microsoft Corporation.",
				"entityType": "Address",
				"matchCodes": [
					"Good"
				],
				"name": "5548 Calgary Trl NW, Edmonton, AB T6H 4K1, Canada",
				"statusCode": 200,
				"statusDescription": "OK",
				"traceId": "b82a0e864e2e48018a32d6bef4ecb519|BN20240253|7.7.0.0|",
				"addressLine": "5548 Calgary Trl NW",
				"adminDistrict": "AB",
				"adminDistrict2": "Alberta",
				"countryRegion": "Canada",
				"formattedAddress": "5548 Calgary Trl NW, Edmonton, AB T6H 4K1, Canada",
				"locality": "Edmonton",
				"neighborhood": "Pleasantview",
				"postalCode": "T6H 4K1"
			},
			"geometry": {
				"type": "Point",
				"coordinates": [
					-113.4981,
					53.49298
				]
			},
			"bbox": [
				-113.4999896,
				53.4918558,
				-113.4962104,
				53.4941042
			]
		}
	]
}
