{
	"type": "FeatureCollection",
	"features": [
		{
			"type": "Feature",
			"properties": {
				"confidence": 9,
				"authenticationResultCode": "ValidCredentials",
				"brandLogoUri": "http://dev.virtualearth.net/Branding/logo_powered_by.png",
				"copyright": "Copyright © 2017 Microsoft and its suppliers. All rights reserved. This API cannot be accessed and the content and any results may not be used, reproduced or transmitted in any manner without express written permission from Microsoft Corporation.",
				"entityType": "Address",
				"matchCodes": [
					"Good"
				],
				"name": "557 Massey Rd, Guelph, ON N1K 1B3, Canada",
				"statusCode": 200,
				"statusDescription": "OK",
				"traceId": "f869b70ff60f4d03a296065b6497d55b|BN20130634|7.7.0.0|",
				"addressLine": "557 Massey Rd",
				"adminDistrict": "ON",
				"adminDistrict2": "Wellington",
				"countryRegion": "Canada",
				"formattedAddress": "557 Massey Rd, Guelph, ON N1K 1B3, Canada",
				"locality": "Guelph",
				"neighborhood": "Willow West/Sugarbush",
				"postalCode": "N1K 1B3"
			},
			"geometry": {
				"type": "Point",
				"coordinates": [
					-80.31546,
					43.53169
				]
			},
			"bbox": [
				-80.3170106,
				43.5305658,
				-80.3139094,
				43.5328142
			]
		}
	]
}
