{
	"type": "FeatureCollection",
	"features": [
		{
			"type": "Feature",
			"properties": {
				"confidence": 9,
				"authenticationResultCode": "ValidCredentials",
				"brandLogoUri": "http://dev.virtualearth.net/Branding/logo_powered_by.png",
				"copyright": "Copyright © 2017 Microsoft and its suppliers. All rights reserved. This API cannot be accessed and the content and any results may not be used, reproduced or transmitted in any manner without express written permission from Microsoft Corporation.",
				"entityType": "Address",
				"matchCodes": [
					"Good"
				],
				"name": "557 Rue Tyler, Gatineau, QC J9H 4L2, Canada",
				"statusCode": 200,
				"statusDescription": "OK",
				"traceId": "56f26b2234c242d0b82f1200f53d63d3|BN20130532|7.7.0.0|",
				"addressLine": "557 Rue Tyler",
				"adminDistrict": "QC",
				"adminDistrict2": "Gatineau",
				"countryRegion": "Canada",
				"formattedAddress": "557 Rue Tyler, Gatineau, QC J9H 4L2, Canada",
				"locality": "Gatineau",
				"neighborhood": "Aylmer",
				"postalCode": "J9H 4L2"
			},
			"geometry": {
				"type": "Point",
				"coordinates": [
					-75.84793,
					45.40437
				]
			},
			"bbox": [
				-75.8495311,
				45.4032458,
				-75.8463289,
				45.4054942
			]
		}
	]
}
