{
	"type": "FeatureCollection",
	"features": [
		{
			"type": "Feature",
			"properties": {
				"confidence": 9,
				"authenticationResultCode": "ValidCredentials",
				"brandLogoUri": "http://dev.virtualearth.net/Branding/logo_powered_by.png",
				"copyright": "Copyright © 2017 Microsoft and its suppliers. All rights reserved. This API cannot be accessed and the content and any results may not be used, reproduced or transmitted in any manner without express written permission from Microsoft Corporation.",
				"entityType": "Address",
				"matchCodes": [
					"Good"
				],
				"name": "5580 Rue Bordeaux, Brossard, QC J4Z 1Y2, Canada",
				"statusCode": 200,
				"statusDescription": "OK",
				"traceId": "228a5ae383194d71a17a4821880452f4|BN20130620|7.7.0.0|",
				"addressLine": "5580 Rue Bordeaux",
				"adminDistrict": "QC",
				"adminDistrict2": "Longueuil",
				"countryRegion": "Canada",
				"formattedAddress": "5580 Rue Bordeaux, Brossard, QC J4Z 1Y2, Canada",
				"locality": "Brossard",
				"postalCode": "J4Z 1Y2"
			},
			"geometry": {
				"type": "Point",
				"coordinates": [
					-73.44875,
					45.4721199
				]
			},
			"bbox": [
				-73.4503531,
				45.4709957,
				-73.4471469,
				45.4732441
			]
		}
	]
}
