{
	"type": "FeatureCollection",
	"features": [
		{
			"type": "Feature",
			"properties": {
				"confidence": 9,
				"authenticationResultCode": "ValidCredentials",
				"brandLogoUri": "http://dev.virtualearth.net/Branding/logo_powered_by.png",
				"copyright": "Copyright © 2017 Microsoft and its suppliers. All rights reserved. This API cannot be accessed and the content and any results may not be used, reproduced or transmitted in any manner without express written permission from Microsoft Corporation.",
				"entityType": "Address",
				"matchCodes": [
					"Good"
				],
				"name": "559 Chamberlain St, Peterborough, ON K9J 4L6, Canada",
				"statusCode": 200,
				"statusDescription": "OK",
				"traceId": "767d2e2fa58b49cc9b6991794cbc117a|BN20181720|7.7.0.0|",
				"addressLine": "559 Chamberlain St",
				"adminDistrict": "ON",
				"adminDistrict2": "Peterborough",
				"countryRegion": "Canada",
				"formattedAddress": "559 Chamberlain St, Peterborough, ON K9J 4L6, Canada",
				"locality": "Peterborough",
				"postalCode": "K9J 4L6"
			},
			"geometry": {
				"type": "Point",
				"coordinates": [
					-78.33018,
					44.29224
				]
			},
			"bbox": [
				-78.3317505,
				44.2911158,
				-78.3286095,
				44.2933642
			]
		}
	]
}
