{
	"type": "FeatureCollection",
	"features": [
		{
			"type": "Feature",
			"properties": {
				"confidence": 9,
				"authenticationResultCode": "ValidCredentials",
				"brandLogoUri": "http://dev.virtualearth.net/Branding/logo_powered_by.png",
				"copyright": "Copyright © 2017 Microsoft and its suppliers. All rights reserved. This API cannot be accessed and the content and any results may not be used, reproduced or transmitted in any manner without express written permission from Microsoft Corporation.",
				"entityType": "Address",
				"matchCodes": [
					"Good"
				],
				"name": "56 Willow Ave, Toronto, ON M4E 3K2, Canada",
				"statusCode": 200,
				"statusDescription": "OK",
				"traceId": "c5153e6e3ed54da6a64e04a1e13f56b9|BN20130521|7.7.0.0|",
				"addressLine": "56 Willow Ave",
				"adminDistrict": "ON",
				"adminDistrict2": "Toronto",
				"countryRegion": "Canada",
				"formattedAddress": "56 Willow Ave, Toronto, ON M4E 3K2, Canada",
				"locality": "Toronto",
				"neighborhood": "The Beaches",
				"postalCode": "M4E 3K2"
			},
			"geometry": {
				"type": "Point",
				"coordinates": [
					-79.28614,
					43.6715
				]
			},
			"bbox": [
				-79.2876942,
				43.6703758,
				-79.2845858,
				43.6726242
			]
		}
	]
}
