{
	"type": "FeatureCollection",
	"features": [
		{
			"type": "Feature",
			"properties": {
				"confidence": 9,
				"authenticationResultCode": "ValidCredentials",
				"brandLogoUri": "http://dev.virtualearth.net/Branding/logo_powered_by.png",
				"copyright": "Copyright © 2017 Microsoft and its suppliers. All rights reserved. This API cannot be accessed and the content and any results may not be used, reproduced or transmitted in any manner without express written permission from Microsoft Corporation.",
				"entityType": "Address",
				"matchCodes": [
					"Good"
				],
				"name": "5600 Rocky Point Rd, Metchosin, BC V9C 4G9, Canada",
				"statusCode": 200,
				"statusDescription": "OK",
				"traceId": "9d2e6171c8414080aab1ea6893f59ba1|BN20200137|7.7.0.0|",
				"addressLine": "5600 Rocky Point Rd",
				"adminDistrict": "BC",
				"adminDistrict2": "Capital",
				"countryRegion": "Canada",
				"formattedAddress": "5600 Rocky Point Rd, Metchosin, BC V9C 4G9, Canada",
				"locality": "Metchosin",
				"postalCode": "V9C 4G9"
			},
			"geometry": {
				"type": "Point",
				"coordinates": [
					-123.5825945,
					48.351294
				]
			},
			"bbox": [
				-123.5842861,
				48.3501698,
				-123.5809029,
				48.3524182
			]
		}
	]
}
