{
	"type": "FeatureCollection",
	"features": [
		{
			"type": "Feature",
			"properties": {
				"confidence": 7,
				"authenticationResultCode": "ValidCredentials",
				"brandLogoUri": "http://dev.virtualearth.net/Branding/logo_powered_by.png",
				"copyright": "Copyright © 2017 Microsoft and its suppliers. All rights reserved. This API cannot be accessed and the content and any results may not be used, reproduced or transmitted in any manner without express written permission from Microsoft Corporation.",
				"entityType": "Postcode1",
				"matchCodes": [
					"Ambiguous",
					"UpHierarchy"
				],
				"name": "Antigonish, B2G 2L6, Canada",
				"statusCode": 200,
				"statusDescription": "OK",
				"traceId": "7e714da1dcc7463484a365aadc6cc6e9|BN20130625|7.7.0.0|",
				"adminDistrict": "NS",
				"adminDistrict2": "Antigonish",
				"countryRegion": "Canada",
				"formattedAddress": "Antigonish, B2G 2L6, Canada",
				"locality": "Antigonish",
				"postalCode": "B2G 2L6"
			},
			"geometry": {
				"type": "Point",
				"coordinates": [
					-61.994270324707,
					45.622200012207
				]
			},
			"bbox": [
				-62.0016338291815,
				45.6183372946364,
				-61.9869068202325,
				45.6260627297777
			]
		}
	]
}
