{
	"type": "FeatureCollection",
	"features": [
		{
			"type": "Feature",
			"properties": {
				"confidence": 9,
				"authenticationResultCode": "ValidCredentials",
				"brandLogoUri": "http://dev.virtualearth.net/Branding/logo_powered_by.png",
				"copyright": "Copyright © 2017 Microsoft and its suppliers. All rights reserved. This API cannot be accessed and the content and any results may not be used, reproduced or transmitted in any manner without express written permission from Microsoft Corporation.",
				"entityType": "Address",
				"matchCodes": [
					"Good"
				],
				"name": "563 Barton St, Stoney Creek, ON L8E 5S1, Canada",
				"statusCode": 200,
				"statusDescription": "OK",
				"traceId": "00990fb80fd7486394b96f48a28d2a47|BN20130431|7.7.0.0|",
				"addressLine": "563 Barton St",
				"adminDistrict": "ON",
				"adminDistrict2": "Hamilton",
				"countryRegion": "Canada",
				"formattedAddress": "563 Barton St, Stoney Creek, ON L8E 5S1, Canada",
				"locality": "Hamilton",
				"neighborhood": "Stoney Creek",
				"postalCode": "L8E 5S1"
			},
			"geometry": {
				"type": "Point",
				"coordinates": [
					-79.70572,
					43.22458
				]
			},
			"bbox": [
				-79.7072627,
				43.2234558,
				-79.7041773,
				43.2257042
			]
		}
	]
}
