{
	"type": "FeatureCollection",
	"features": [
		{
			"type": "Feature",
			"properties": {
				"confidence": 9,
				"authenticationResultCode": "ValidCredentials",
				"brandLogoUri": "http://dev.virtualearth.net/Branding/logo_powered_by.png",
				"copyright": "Copyright © 2017 Microsoft and its suppliers. All rights reserved. This API cannot be accessed and the content and any results may not be used, reproduced or transmitted in any manner without express written permission from Microsoft Corporation.",
				"entityType": "Address",
				"matchCodes": [
					"Good"
				],
				"name": "5671 Kennedy Rd, Mississauga, ON L4Z 3E1, Canada",
				"statusCode": 200,
				"statusDescription": "OK",
				"traceId": "0c664905ccc64e3b83af37cc9bab8ca5|BN20260231|7.7.0.0|",
				"addressLine": "5671 Kennedy Rd",
				"adminDistrict": "ON",
				"adminDistrict2": "Peel",
				"countryRegion": "Canada",
				"formattedAddress": "5671 Kennedy Rd, Mississauga, ON L4Z 3E1, Canada",
				"locality": "Mississauga",
				"postalCode": "L4Z 3E1"
			},
			"geometry": {
				"type": "Point",
				"coordinates": [
					-79.65874,
					43.62937
				]
			},
			"bbox": [
				-79.6602931,
				43.6282458,
				-79.6571869,
				43.6304942
			]
		}
	]
}
