{
	"type": "FeatureCollection",
	"features": [
		{
			"type": "Feature",
			"properties": {
				"confidence": 9,
				"authenticationResultCode": "ValidCredentials",
				"brandLogoUri": "http://dev.virtualearth.net/Branding/logo_powered_by.png",
				"copyright": "Copyright © 2017 Microsoft and its suppliers. All rights reserved. This API cannot be accessed and the content and any results may not be used, reproduced or transmitted in any manner without express written permission from Microsoft Corporation.",
				"entityType": "Address",
				"matchCodes": [
					"Good"
				],
				"name": "5684 Beach Ave, Peachland, BC V0H 1X6, Canada",
				"statusCode": 200,
				"statusDescription": "OK",
				"traceId": "b17fcc0cbba148d5b296c4e8344a8083|BN20130522|7.7.0.0|",
				"addressLine": "5684 Beach Ave",
				"adminDistrict": "BC",
				"adminDistrict2": "Central Okanagan",
				"countryRegion": "Canada",
				"formattedAddress": "5684 Beach Ave, Peachland, BC V0H 1X6, Canada",
				"locality": "Peachland",
				"postalCode": "V0H 1X6"
			},
			"geometry": {
				"type": "Point",
				"coordinates": [
					-119.73412,
					49.77703
				]
			},
			"bbox": [
				-119.7358608,
				49.7759058,
				-119.7323792,
				49.7781542
			]
		}
	]
}
