{
	"type": "FeatureCollection",
	"features": [
		{
			"type": "Feature",
			"properties": {
				"confidence": 9,
				"authenticationResultCode": "ValidCredentials",
				"brandLogoUri": "http://dev.virtualearth.net/Branding/logo_powered_by.png",
				"copyright": "Copyright © 2017 Microsoft and its suppliers. All rights reserved. This API cannot be accessed and the content and any results may not be used, reproduced or transmitted in any manner without express written permission from Microsoft Corporation.",
				"entityType": "Address",
				"matchCodes": [
					"Good"
				],
				"name": "57 Cannifton Rd, Belleville, ON K8N 4V1, Canada",
				"statusCode": 200,
				"statusDescription": "OK",
				"traceId": "b58044f0984040aba78e70d47bde10dd|BN20240253|7.7.0.0|",
				"addressLine": "57 Cannifton Rd",
				"adminDistrict": "ON",
				"adminDistrict2": "Hastings",
				"countryRegion": "Canada",
				"formattedAddress": "57 Cannifton Rd, Belleville, ON K8N 4V1, Canada",
				"locality": "Belleville",
				"postalCode": "K8N 4V1"
			},
			"geometry": {
				"type": "Point",
				"coordinates": [
					-77.37962,
					44.17701
				]
			},
			"bbox": [
				-77.3811874,
				44.1758858,
				-77.3780526,
				44.1781342
			]
		}
	]
}
