{
	"type": "FeatureCollection",
	"features": [
		{
			"type": "Feature",
			"properties": {
				"confidence": 9,
				"authenticationResultCode": "ValidCredentials",
				"brandLogoUri": "http://dev.virtualearth.net/Branding/logo_powered_by.png",
				"copyright": "Copyright © 2017 Microsoft and its suppliers. All rights reserved. This API cannot be accessed and the content and any results may not be used, reproduced or transmitted in any manner without express written permission from Microsoft Corporation.",
				"entityType": "Address",
				"matchCodes": [
					"Good"
				],
				"name": "57 Progress Ct, Brampton, ON L6S 5X2, Canada",
				"statusCode": 200,
				"statusDescription": "OK",
				"traceId": "0ed10809fac94f5f9f3831e13193efbc|BN20320521|7.7.0.0|",
				"addressLine": "57 Progress Ct",
				"adminDistrict": "ON",
				"adminDistrict2": "Peel",
				"countryRegion": "Canada",
				"formattedAddress": "57 Progress Ct, Brampton, ON L6S 5X2, Canada",
				"locality": "Brampton",
				"neighborhood": "Castlemore",
				"postalCode": "L6S 5X2"
			},
			"geometry": {
				"type": "Point",
				"coordinates": [
					-79.69467,
					43.75415
				]
			},
			"bbox": [
				-79.6962263,
				43.7530258,
				-79.6931137,
				43.7552742
			]
		}
	]
}
