{
	"type": "FeatureCollection",
	"features": [
		{
			"type": "Feature",
			"properties": {
				"confidence": 9,
				"authenticationResultCode": "ValidCredentials",
				"brandLogoUri": "http://dev.virtualearth.net/Branding/logo_powered_by.png",
				"copyright": "Copyright © 2017 Microsoft and its suppliers. All rights reserved. This API cannot be accessed and the content and any results may not be used, reproduced or transmitted in any manner without express written permission from Microsoft Corporation.",
				"entityType": "Address",
				"matchCodes": [
					"Good"
				],
				"name": "571 Industrial Rd, London, ON N5V 1V2, Canada",
				"statusCode": 200,
				"statusDescription": "OK",
				"traceId": "d4e9009d46f0455b9dcbbaf44f5ff533|CO30323910|7.7.0.0|",
				"addressLine": "571 Industrial Rd",
				"adminDistrict": "ON",
				"adminDistrict2": "Middlesex",
				"countryRegion": "Canada",
				"formattedAddress": "571 Industrial Rd, London, ON N5V 1V2, Canada",
				"locality": "London",
				"neighborhood": "Airport",
				"postalCode": "N5V 1V2"
			},
			"geometry": {
				"type": "Point",
				"coordinates": [
					-81.1625,
					43.0155
				]
			},
			"bbox": [
				-81.1640375,
				43.0143758,
				-81.1609625,
				43.0166242
			]
		}
	]
}
