{
	"type": "FeatureCollection",
	"features": [
		{
			"type": "Feature",
			"properties": {
				"confidence": 9,
				"authenticationResultCode": "ValidCredentials",
				"brandLogoUri": "http://dev.virtualearth.net/Branding/logo_powered_by.png",
				"copyright": "Copyright © 2017 Microsoft and its suppliers. All rights reserved. This API cannot be accessed and the content and any results may not be used, reproduced or transmitted in any manner without express written permission from Microsoft Corporation.",
				"entityType": "Address",
				"matchCodes": [
					"Good"
				],
				"name": "572 Avenue Victoria, Westmount, QC H3Y 2R6, Canada",
				"statusCode": 200,
				"statusDescription": "OK",
				"traceId": "8f817c819821435982d47bb0450b16c2|BN20130632|7.7.0.0|",
				"addressLine": "572 Avenue Victoria",
				"adminDistrict": "QC",
				"adminDistrict2": "Montreal",
				"countryRegion": "Canada",
				"formattedAddress": "572 Avenue Victoria, Westmount, QC H3Y 2R6, Canada",
				"locality": "Westmount",
				"postalCode": "H3Y 2R6"
			},
			"geometry": {
				"type": "Point",
				"coordinates": [
					-73.60955,
					45.48149
				]
			},
			"bbox": [
				-73.6111533,
				45.4803658,
				-73.6079467,
				45.4826142
			]
		}
	]
}
