{
	"type": "FeatureCollection",
	"features": [
		{
			"type": "Feature",
			"properties": {
				"confidence": 9,
				"authenticationResultCode": "ValidCredentials",
				"brandLogoUri": "http://dev.virtualearth.net/Branding/logo_powered_by.png",
				"copyright": "Copyright © 2017 Microsoft and its suppliers. All rights reserved. This API cannot be accessed and the content and any results may not be used, reproduced or transmitted in any manner without express written permission from Microsoft Corporation.",
				"entityType": "Address",
				"matchCodes": [
					"Good"
				],
				"name": "5730 96 St NW, Edmonton, AB T6E 3G1, Canada",
				"statusCode": 200,
				"statusDescription": "OK",
				"traceId": "50a5244244114ee2b6bce0ff0cbda15e|BN20130422|7.7.0.0|",
				"addressLine": "5730 96 St NW",
				"adminDistrict": "AB",
				"adminDistrict2": "Alberta",
				"countryRegion": "Canada",
				"formattedAddress": "5730 96 St NW, Edmonton, AB T6E 3G1, Canada",
				"locality": "Edmonton",
				"neighborhood": "Coronet Industrial",
				"postalCode": "T6E 3G1"
			},
			"geometry": {
				"type": "Point",
				"coordinates": [
					-113.47764,
					53.49364
				]
			},
			"bbox": [
				-113.4795296,
				53.4925158,
				-113.4757504,
				53.4947642
			]
		}
	]
}
