{
	"type": "FeatureCollection",
	"features": [
		{
			"type": "Feature",
			"properties": {
				"confidence": 9,
				"authenticationResultCode": "ValidCredentials",
				"brandLogoUri": "http://dev.virtualearth.net/Branding/logo_powered_by.png",
				"copyright": "Copyright © 2017 Microsoft and its suppliers. All rights reserved. This API cannot be accessed and the content and any results may not be used, reproduced or transmitted in any manner without express written permission from Microsoft Corporation.",
				"entityType": "Address",
				"matchCodes": [
					"Good"
				],
				"name": "5775 McLaughlin Rd, Mississauga, ON L5R 3P7, Canada",
				"statusCode": 200,
				"statusDescription": "OK",
				"traceId": "07e0ff84922d40df80f14271f72281d3|BN20131519|7.7.0.0|",
				"addressLine": "5775 McLaughlin Rd",
				"adminDistrict": "ON",
				"adminDistrict2": "Peel",
				"countryRegion": "Canada",
				"formattedAddress": "5775 McLaughlin Rd, Mississauga, ON L5R 3P7, Canada",
				"locality": "Mississauga",
				"postalCode": "L5R 3P7"
			},
			"geometry": {
				"type": "Point",
				"coordinates": [
					-79.68389,
					43.61276
				]
			},
			"bbox": [
				-79.6854427,
				43.6116358,
				-79.6823373,
				43.6138842
			]
		}
	]
}
