{
	"type": "FeatureCollection",
	"features": [
		{
			"type": "Feature",
			"properties": {
				"confidence": 9,
				"authenticationResultCode": "ValidCredentials",
				"brandLogoUri": "http://dev.virtualearth.net/Branding/logo_powered_by.png",
				"copyright": "Copyright © 2017 Microsoft and its suppliers. All rights reserved. This API cannot be accessed and the content and any results may not be used, reproduced or transmitted in any manner without express written permission from Microsoft Corporation.",
				"entityType": "Address",
				"matchCodes": [
					"Good"
				],
				"name": "578 W Kings Rd, North Vancouver, BC V7N 2M4, Canada",
				"statusCode": 200,
				"statusDescription": "OK",
				"traceId": "47ff3ac10909454382934a5fb4c569d5|BN20240253|7.7.0.0|",
				"addressLine": "578 W Kings Rd",
				"adminDistrict": "BC",
				"adminDistrict2": "Greater Vancouver",
				"countryRegion": "Canada",
				"formattedAddress": "578 W Kings Rd, North Vancouver, BC V7N 2M4, Canada",
				"locality": "North Vancouver District",
				"neighborhood": "Norwood Queens",
				"postalCode": "V7N 2M4"
			},
			"geometry": {
				"type": "Point",
				"coordinates": [
					-123.08452,
					49.33771
				]
			},
			"bbox": [
				-123.0862452,
				49.3365858,
				-123.0827948,
				49.3388342
			]
		}
	]
}
