{
	"type": "FeatureCollection",
	"features": [
		{
			"type": "Feature",
			"properties": {
				"confidence": 9,
				"authenticationResultCode": "ValidCredentials",
				"brandLogoUri": "http://dev.virtualearth.net/Branding/logo_powered_by.png",
				"copyright": "Copyright © 2017 Microsoft and its suppliers. All rights reserved. This API cannot be accessed and the content and any results may not be used, reproduced or transmitted in any manner without express written permission from Microsoft Corporation.",
				"entityType": "Address",
				"matchCodes": [
					"Good"
				],
				"name": "5794 Wellington Road 86, Ariss, ON N0B 1B0, Canada",
				"statusCode": 200,
				"statusDescription": "OK",
				"traceId": "24f997d1ccba4ec68196212086481e31|BN20130532|7.7.0.0|",
				"addressLine": "5794 Wellington Road 86",
				"adminDistrict": "ON",
				"adminDistrict2": "Wellington",
				"countryRegion": "Canada",
				"formattedAddress": "5794 Wellington Road 86, Ariss, ON N0B 1B0, Canada",
				"locality": "Guelph/Eramosa",
				"neighborhood": "Ariss",
				"postalCode": "N0B 1B0"
			},
			"geometry": {
				"type": "Point",
				"coordinates": [
					-80.3810511,
					43.5750637
				]
			},
			"bbox": [
				-80.3826028,
				43.5739396,
				-80.3794995,
				43.5761879
			]
		}
	]
}
