{
	"type": "FeatureCollection",
	"features": [
		{
			"type": "Feature",
			"properties": {
				"confidence": 9,
				"authenticationResultCode": "ValidCredentials",
				"brandLogoUri": "http://dev.virtualearth.net/Branding/logo_powered_by.png",
				"copyright": "Copyright © 2017 Microsoft and its suppliers. All rights reserved. This API cannot be accessed and the content and any results may not be used, reproduced or transmitted in any manner without express written permission from Microsoft Corporation.",
				"entityType": "Address",
				"matchCodes": [
					"Good"
				],
				"name": "58 Rue du Colonial, Gatineau, QC J9H 0A7, Canada",
				"statusCode": 200,
				"statusDescription": "OK",
				"traceId": "8bcfe8db897c4c79957f280cbb6634ef|BN20130631|7.7.0.0|",
				"addressLine": "58 Rue du Colonial",
				"adminDistrict": "QC",
				"adminDistrict2": "Gatineau",
				"countryRegion": "Canada",
				"formattedAddress": "58 Rue du Colonial, Gatineau, QC J9H 0A7, Canada",
				"locality": "Gatineau",
				"neighborhood": "Aylmer",
				"postalCode": "J9H 0A7"
			},
			"geometry": {
				"type": "Point",
				"coordinates": [
					-75.77391,
					45.41027
				]
			},
			"bbox": [
				-75.7755113,
				45.4091458,
				-75.7723087,
				45.4113942
			]
		}
	]
}
