{
	"type": "FeatureCollection",
	"features": [
		{
			"type": "Feature",
			"properties": {
				"confidence": 9,
				"authenticationResultCode": "ValidCredentials",
				"brandLogoUri": "http://dev.virtualearth.net/Branding/logo_powered_by.png",
				"copyright": "Copyright © 2017 Microsoft and its suppliers. All rights reserved. This API cannot be accessed and the content and any results may not be used, reproduced or transmitted in any manner without express written permission from Microsoft Corporation.",
				"entityType": "Address",
				"matchCodes": [
					"Good"
				],
				"name": "580 Horton St E, London, ON N6B 1M7, Canada",
				"statusCode": 200,
				"statusDescription": "OK",
				"traceId": "7b5e0ec6eec24bc8bcec8a84477f4990|BN20130625|7.7.0.0|",
				"addressLine": "580 Horton St E",
				"adminDistrict": "ON",
				"adminDistrict2": "Middlesex",
				"countryRegion": "Canada",
				"formattedAddress": "580 Horton St E, London, ON N6B 1M7, Canada",
				"locality": "London",
				"neighborhood": "Central London",
				"postalCode": "N6B 1M7"
			},
			"geometry": {
				"type": "Point",
				"coordinates": [
					-81.2303856,
					42.9837464
				]
			},
			"bbox": [
				-81.2319223,
				42.9826223,
				-81.2288489,
				42.9848706
			]
		}
	]
}
