{
	"type": "FeatureCollection",
	"features": [
		{
			"type": "Feature",
			"properties": {
				"confidence": 9,
				"authenticationResultCode": "ValidCredentials",
				"brandLogoUri": "http://dev.virtualearth.net/Branding/logo_powered_by.png",
				"copyright": "Copyright © 2017 Microsoft and its suppliers. All rights reserved. This API cannot be accessed and the content and any results may not be used, reproduced or transmitted in any manner without express written permission from Microsoft Corporation.",
				"entityType": "Address",
				"matchCodes": [
					"Good"
				],
				"name": "5821 158 Ave NW, Edmonton, AB T5Y 2R4, Canada",
				"statusCode": 200,
				"statusDescription": "OK",
				"traceId": "4fd9f0f6ea99408ea84941181791fe69|BN20121762|7.7.0.0|",
				"addressLine": "5821 158 Ave NW",
				"adminDistrict": "AB",
				"adminDistrict2": "Alberta",
				"countryRegion": "Canada",
				"formattedAddress": "5821 158 Ave NW, Edmonton, AB T5Y 2R4, Canada",
				"locality": "Edmonton",
				"neighborhood": "Hollick-Kenyon",
				"postalCode": "T5Y 2R4"
			},
			"geometry": {
				"type": "Point",
				"coordinates": [
					-113.42887,
					53.61867
				]
			},
			"bbox": [
				-113.4307652,
				53.6175458,
				-113.4269748,
				53.6197942
			]
		}
	]
}
