{
	"type": "FeatureCollection",
	"features": [
		{
			"type": "Feature",
			"properties": {
				"confidence": 9,
				"authenticationResultCode": "ValidCredentials",
				"brandLogoUri": "http://dev.virtualearth.net/Branding/logo_powered_by.png",
				"copyright": "Copyright © 2017 Microsoft and its suppliers. All rights reserved. This API cannot be accessed and the content and any results may not be used, reproduced or transmitted in any manner without express written permission from Microsoft Corporation.",
				"entityType": "Address",
				"matchCodes": [
					"Good"
				],
				"name": "5860 Chedworth Way, Mississauga, ON L5R 0A2, Canada",
				"statusCode": 200,
				"statusDescription": "OK",
				"traceId": "b04bbdc7b8bc418c8e376770b802c44b|BN20240253|7.7.0.0|",
				"addressLine": "5860 Chedworth Way",
				"adminDistrict": "ON",
				"adminDistrict2": "Peel",
				"countryRegion": "Canada",
				"formattedAddress": "5860 Chedworth Way, Mississauga, ON L5R 0A2, Canada",
				"locality": "Mississauga",
				"postalCode": "L5R 0A2"
			},
			"geometry": {
				"type": "Point",
				"coordinates": [
					-79.68591,
					43.61659
				]
			},
			"bbox": [
				-79.6874628,
				43.6154658,
				-79.6843572,
				43.6177142
			]
		}
	]
}
