{
	"type": "FeatureCollection",
	"features": [
		{
			"type": "Feature",
			"properties": {
				"confidence": 9,
				"authenticationResultCode": "ValidCredentials",
				"brandLogoUri": "http://dev.virtualearth.net/Branding/logo_powered_by.png",
				"copyright": "Copyright © 2017 Microsoft and its suppliers. All rights reserved. This API cannot be accessed and the content and any results may not be used, reproduced or transmitted in any manner without express written permission from Microsoft Corporation.",
				"entityType": "Address",
				"matchCodes": [
					"Good"
				],
				"name": "5865 McLaughlin Rd, Mississauga, ON L5R 1B8, Canada",
				"statusCode": 200,
				"statusDescription": "OK",
				"traceId": "e7c28d28a9564276847d9d7fa1676bc0|BN20121762|7.7.0.0|",
				"addressLine": "5865 McLaughlin Rd",
				"adminDistrict": "ON",
				"adminDistrict2": "Peel",
				"countryRegion": "Canada",
				"formattedAddress": "5865 McLaughlin Rd, Mississauga, ON L5R 1B8, Canada",
				"locality": "Mississauga",
				"postalCode": "L5R 1B8"
			},
			"geometry": {
				"type": "Point",
				"coordinates": [
					-79.68531,
					43.6143
				]
			},
			"bbox": [
				-79.6868627,
				43.6131758,
				-79.6837573,
				43.6154242
			]
		}
	]
}
