{
	"type": "FeatureCollection",
	"features": [
		{
			"type": "Feature",
			"properties": {
				"confidence": 9,
				"authenticationResultCode": "ValidCredentials",
				"brandLogoUri": "http://dev.virtualearth.net/Branding/logo_powered_by.png",
				"copyright": "Copyright © 2017 Microsoft and its suppliers. All rights reserved. This API cannot be accessed and the content and any results may not be used, reproduced or transmitted in any manner without express written permission from Microsoft Corporation.",
				"entityType": "Address",
				"matchCodes": [
					"Good"
				],
				"name": "5894 8th Line, Guelph/Eramosa, ON N0B, Canada",
				"statusCode": 200,
				"statusDescription": "OK",
				"traceId": "3b1c40c2c82f49f69e173d7eb65b729e|BN20200137|7.7.0.0|",
				"addressLine": "5894 8th Line",
				"adminDistrict": "ON",
				"adminDistrict2": "Wellington",
				"countryRegion": "Canada",
				"formattedAddress": "5894 8th Line, Guelph/Eramosa, ON N0B, Canada",
				"locality": "Guelph/Eramosa",
				"postalCode": "N0B 1B0"
			},
			"geometry": {
				"type": "Point",
				"coordinates": [
					-80.39942,
					43.5862
				]
			},
			"bbox": [
				-80.400972,
				43.5850758,
				-80.397868,
				43.5873242
			]
		}
	]
}
