{
	"type": "FeatureCollection",
	"features": [
		{
			"type": "Feature",
			"properties": {
				"confidence": 9,
				"authenticationResultCode": "ValidCredentials",
				"brandLogoUri": "http://dev.virtualearth.net/Branding/logo_powered_by.png",
				"copyright": "Copyright © 2017 Microsoft and its suppliers. All rights reserved. This API cannot be accessed and the content and any results may not be used, reproduced or transmitted in any manner without express written permission from Microsoft Corporation.",
				"entityType": "Address",
				"matchCodes": [
					"Good"
				],
				"name": "59 Tenagadino Mikan, Maniwaki, QC J9E, Canada",
				"statusCode": 200,
				"statusDescription": "OK",
				"traceId": "153e20eda7924b8aa1f087a14476f30e|BN20130521|7.7.0.0|",
				"addressLine": "59 Tenagadino Mikan",
				"adminDistrict": "QC",
				"adminDistrict2": "La Vallée-de-la-Gatineau",
				"countryRegion": "Canada",
				"formattedAddress": "59 Tenagadino Mikan, Maniwaki, QC J9E, Canada",
				"locality": "Maniwaki",
				"postalCode": "J9E 3B1"
			},
			"geometry": {
				"type": "Point",
				"coordinates": [
					-75.9549,
					46.3722123
				]
			},
			"bbox": [
				-75.9565292,
				46.3710882,
				-75.9532707,
				46.3733365
			]
		}
	]
}
