{
	"type": "FeatureCollection",
	"features": [
		{
			"type": "Feature",
			"properties": {
				"confidence": 9,
				"authenticationResultCode": "ValidCredentials",
				"brandLogoUri": "http://dev.virtualearth.net/Branding/logo_powered_by.png",
				"copyright": "Copyright © 2017 Microsoft and its suppliers. All rights reserved. This API cannot be accessed and the content and any results may not be used, reproduced or transmitted in any manner without express written permission from Microsoft Corporation.",
				"entityType": "Address",
				"matchCodes": [
					"Good"
				],
				"name": "591 Reynolds Rd, Lansdowne, ON K0E 1L0, Canada",
				"statusCode": 200,
				"statusDescription": "OK",
				"traceId": "471a8c0048734a6781217c6f373b6a67|BN20130631|7.7.0.0|",
				"addressLine": "591 Reynolds Rd",
				"adminDistrict": "ON",
				"adminDistrict2": "Leeds and Grenville",
				"countryRegion": "Canada",
				"formattedAddress": "591 Reynolds Rd, Lansdowne, ON K0E 1L0, Canada",
				"locality": "Leeds and the Thousand Islands",
				"neighborhood": "Lansdowne",
				"postalCode": "K0E 1L0"
			},
			"geometry": {
				"type": "Point",
				"coordinates": [
					-76.0117705,
					44.3831822
				]
			},
			"bbox": [
				-76.0133434,
				44.3820581,
				-76.0101975,
				44.3843064
			]
		}
	]
}
