{
	"type": "FeatureCollection",
	"features": [
		{
			"type": "Feature",
			"properties": {
				"confidence": 9,
				"authenticationResultCode": "ValidCredentials",
				"brandLogoUri": "http://dev.virtualearth.net/Branding/logo_powered_by.png",
				"copyright": "Copyright © 2017 Microsoft and its suppliers. All rights reserved. This API cannot be accessed and the content and any results may not be used, reproduced or transmitted in any manner without express written permission from Microsoft Corporation.",
				"entityType": "Address",
				"matchCodes": [
					"Good"
				],
				"name": "5919 104 St NW, Edmonton, AB T6H 2K5, Canada",
				"statusCode": 200,
				"statusDescription": "OK",
				"traceId": "c92a786e146c4fafaeb48e0db003b2b4|BN20130621|7.7.0.0|",
				"addressLine": "5919 104 St NW",
				"adminDistrict": "AB",
				"adminDistrict2": "Alberta",
				"countryRegion": "Canada",
				"formattedAddress": "5919 104 St NW, Edmonton, AB T6H 2K5, Canada",
				"locality": "Edmonton",
				"neighborhood": "Calgary Trail North",
				"postalCode": "T6H 2K5"
			},
			"geometry": {
				"type": "Point",
				"coordinates": [
					-113.49719,
					53.4967
				]
			},
			"bbox": [
				-113.4990797,
				53.4955758,
				-113.4953003,
				53.4978242
			]
		}
	]
}
