{
	"type": "FeatureCollection",
	"features": [
		{
			"type": "Feature",
			"properties": {
				"confidence": 9,
				"authenticationResultCode": "ValidCredentials",
				"brandLogoUri": "http://dev.virtualearth.net/Branding/logo_powered_by.png",
				"copyright": "Copyright © 2017 Microsoft and its suppliers. All rights reserved. This API cannot be accessed and the content and any results may not be used, reproduced or transmitted in any manner without express written permission from Microsoft Corporation.",
				"entityType": "Address",
				"matchCodes": [
					"Good"
				],
				"name": "595 Athlone Ave, Woodstock, ON N4V, Canada",
				"statusCode": 200,
				"statusDescription": "OK",
				"traceId": "e23fb3a27904460fa30d902ac667e53b|BN20190653|7.7.0.0|",
				"addressLine": "595 Athlone Ave",
				"adminDistrict": "ON",
				"adminDistrict2": "Oxford",
				"countryRegion": "Canada",
				"formattedAddress": "595 Athlone Ave, Woodstock, ON N4V, Canada",
				"locality": "Woodstock",
				"postalCode": "N4V"
			},
			"geometry": {
				"type": "Point",
				"coordinates": [
					-80.74584,
					43.10644
				]
			},
			"bbox": [
				-80.7473798,
				43.1053158,
				-80.7443002,
				43.1075642
			]
		}
	]
}
