{
	"type": "FeatureCollection",
	"features": [
		{
			"type": "Feature",
			"properties": {
				"confidence": 9,
				"authenticationResultCode": "ValidCredentials",
				"brandLogoUri": "http://dev.virtualearth.net/Branding/logo_powered_by.png",
				"copyright": "Copyright © 2017 Microsoft and its suppliers. All rights reserved. This API cannot be accessed and the content and any results may not be used, reproduced or transmitted in any manner without express written permission from Microsoft Corporation.",
				"entityType": "Address",
				"matchCodes": [
					"Good"
				],
				"name": "5952 Vermillion Pl, Nanaimo, BC V9V 1K2, Canada",
				"statusCode": 200,
				"statusDescription": "OK",
				"traceId": "cc3ca8b9e4a946f5a9db18f7cc3dcdb1|BN20181720|7.7.0.0|",
				"addressLine": "5952 Vermillion Pl",
				"adminDistrict": "BC",
				"adminDistrict2": "Nanaimo",
				"countryRegion": "Canada",
				"formattedAddress": "5952 Vermillion Pl, Nanaimo, BC V9V 1K2, Canada",
				"locality": "Nanaimo",
				"postalCode": "V9V 1K2"
			},
			"geometry": {
				"type": "Point",
				"coordinates": [
					-124.0249951,
					49.2396002
				]
			},
			"bbox": [
				-124.0267169,
				49.2384761,
				-124.0232733,
				49.2407244
			]
		}
	]
}
