{
	"type": "FeatureCollection",
	"features": [
		{
			"type": "Feature",
			"properties": {
				"confidence": 9,
				"authenticationResultCode": "ValidCredentials",
				"brandLogoUri": "http://dev.virtualearth.net/Branding/logo_powered_by.png",
				"copyright": "Copyright © 2017 Microsoft and its suppliers. All rights reserved. This API cannot be accessed and the content and any results may not be used, reproduced or transmitted in any manner without express written permission from Microsoft Corporation.",
				"entityType": "Address",
				"matchCodes": [
					"Good"
				],
				"name": "5958 Fallsview Blvd, Niagara Falls, ON L2G 3V5, Canada",
				"statusCode": 200,
				"statusDescription": "OK",
				"traceId": "a0604d9989f7408f84ff04b5ae506376|BN20130520|7.7.0.0|",
				"addressLine": "5958 Fallsview Blvd",
				"adminDistrict": "ON",
				"adminDistrict2": "Niagara",
				"countryRegion": "Canada",
				"formattedAddress": "5958 Fallsview Blvd, Niagara Falls, ON L2G 3V5, Canada",
				"locality": "Niagara Falls",
				"postalCode": "L2G 3V5"
			},
			"geometry": {
				"type": "Point",
				"coordinates": [
					-79.08282,
					43.08853
				]
			},
			"bbox": [
				-79.0843593,
				43.0874058,
				-79.0812807,
				43.0896542
			]
		}
	]
}
