{
	"type": "FeatureCollection",
	"features": [
		{
			"type": "Feature",
			"properties": {
				"confidence": 9,
				"authenticationResultCode": "ValidCredentials",
				"brandLogoUri": "http://dev.virtualearth.net/Branding/logo_powered_by.png",
				"copyright": "Copyright © 2017 Microsoft and its suppliers. All rights reserved. This API cannot be accessed and the content and any results may not be used, reproduced or transmitted in any manner without express written permission from Microsoft Corporation.",
				"entityType": "Address",
				"matchCodes": [
					"Good"
				],
				"name": "596 Arvin Ave, Stoney Creek, ON L8E 5P1, Canada",
				"statusCode": 200,
				"statusDescription": "OK",
				"traceId": "5f0818028d3a4040bb8860c237bd3992|BN20260223|7.7.0.0|",
				"addressLine": "596 Arvin Ave",
				"adminDistrict": "ON",
				"adminDistrict2": "Hamilton",
				"countryRegion": "Canada",
				"formattedAddress": "596 Arvin Ave, Stoney Creek, ON L8E 5P1, Canada",
				"locality": "Hamilton",
				"neighborhood": "Stoney Creek",
				"postalCode": "L8E 5P1"
			},
			"geometry": {
				"type": "Point",
				"coordinates": [
					-79.70186,
					43.22594
				]
			},
			"bbox": [
				-79.7034028,
				43.2248158,
				-79.7003172,
				43.2270642
			]
		}
	]
}
