{
	"type": "FeatureCollection",
	"features": [
		{
			"type": "Feature",
			"properties": {
				"confidence": 9,
				"authenticationResultCode": "ValidCredentials",
				"brandLogoUri": "http://dev.virtualearth.net/Branding/logo_powered_by.png",
				"copyright": "Copyright © 2017 Microsoft and its suppliers. All rights reserved. This API cannot be accessed and the content and any results may not be used, reproduced or transmitted in any manner without express written permission from Microsoft Corporation.",
				"entityType": "Address",
				"matchCodes": [
					"Good"
				],
				"name": "5979 Baldwin St S, Whitby, ON L1M 2J7, Canada",
				"statusCode": 200,
				"statusDescription": "OK",
				"traceId": "c35b93ae5e3248a9bd824e3d9275e762|BN20130634|7.7.0.0|",
				"addressLine": "5979 Baldwin St S",
				"adminDistrict": "ON",
				"adminDistrict2": "Durham",
				"countryRegion": "Canada",
				"formattedAddress": "5979 Baldwin St S, Whitby, ON L1M 2J7, Canada",
				"locality": "Whitby",
				"postalCode": "L1M 2J7"
			},
			"geometry": {
				"type": "Point",
				"coordinates": [
					-78.9621379,
					43.9530809
				]
			},
			"bbox": [
				-78.9636995,
				43.9519568,
				-78.9605764,
				43.9542051
			]
		}
	]
}
