{
	"type": "FeatureCollection",
	"features": [
		{
			"type": "Feature",
			"properties": {
				"confidence": 9,
				"authenticationResultCode": "ValidCredentials",
				"brandLogoUri": "http://dev.virtualearth.net/Branding/logo_powered_by.png",
				"copyright": "Copyright © 2017 Microsoft and its suppliers. All rights reserved. This API cannot be accessed and the content and any results may not be used, reproduced or transmitted in any manner without express written permission from Microsoft Corporation.",
				"entityType": "Address",
				"matchCodes": [
					"Good"
				],
				"name": "5990 Falbourne St, Mississauga, ON L5R 3S7, Canada",
				"statusCode": 200,
				"statusDescription": "OK",
				"traceId": "9fd479baa8544a42b1d8da137adca944|BN20320521|7.7.0.0|",
				"addressLine": "5990 Falbourne St",
				"adminDistrict": "ON",
				"adminDistrict2": "Peel",
				"countryRegion": "Canada",
				"formattedAddress": "5990 Falbourne St, Mississauga, ON L5R 3S7, Canada",
				"locality": "Mississauga",
				"postalCode": "L5R 3S7"
			},
			"geometry": {
				"type": "Point",
				"coordinates": [
					-79.68591,
					43.6195499
				]
			},
			"bbox": [
				-79.6874628,
				43.6184257,
				-79.6843572,
				43.6206741
			]
		}
	]
}
