{
	"type": "FeatureCollection",
	"features": [
		{
			"type": "Feature",
			"properties": {
				"confidence": 9,
				"authenticationResultCode": "ValidCredentials",
				"brandLogoUri": "http://dev.virtualearth.net/Branding/logo_powered_by.png",
				"copyright": "Copyright © 2017 Microsoft and its suppliers. All rights reserved. This API cannot be accessed and the content and any results may not be used, reproduced or transmitted in any manner without express written permission from Microsoft Corporation.",
				"entityType": "Address",
				"matchCodes": [
					"Good"
				],
				"name": "6 Foxmeadow Ln, Nepean, ON K2G 3W2, Canada",
				"statusCode": 200,
				"statusDescription": "OK",
				"traceId": "22d7d1ecb7fc43c391039be5099dc688|BN20130532|7.7.0.0|",
				"addressLine": "6 Foxmeadow Ln",
				"adminDistrict": "ON",
				"adminDistrict2": "Ottawa",
				"countryRegion": "Canada",
				"formattedAddress": "6 Foxmeadow Ln, Nepean, ON K2G 3W2, Canada",
				"locality": "Ottawa",
				"neighborhood": "Nepean",
				"postalCode": "K2G 3W2"
			},
			"geometry": {
				"type": "Point",
				"coordinates": [
					-75.7477399,
					45.33068
				]
			},
			"bbox": [
				-75.7493389,
				45.3295558,
				-75.7461409,
				45.3318042
			]
		}
	]
}
