{
	"type": "FeatureCollection",
	"features": [
		{
			"type": "Feature",
			"properties": {
				"confidence": 9,
				"authenticationResultCode": "ValidCredentials",
				"brandLogoUri": "http://dev.virtualearth.net/Branding/logo_powered_by.png",
				"copyright": "Copyright © 2017 Microsoft and its suppliers. All rights reserved. This API cannot be accessed and the content and any results may not be used, reproduced or transmitted in any manner without express written permission from Microsoft Corporation.",
				"entityType": "Address",
				"matchCodes": [
					"Good"
				],
				"name": "6 Chemin Old Factory Round Turn, Grand Manan, NB E5G, Canada",
				"statusCode": 200,
				"statusDescription": "OK",
				"traceId": "3461c0bd303e4478917190be6085713a|BN20220145|7.7.0.0|",
				"addressLine": "6 Chemin Old Factory Round Turn",
				"adminDistrict": "NB",
				"adminDistrict2": "Charlotte",
				"countryRegion": "Canada",
				"formattedAddress": "6 Chemin Old Factory Round Turn, Grand Manan, NB E5G, Canada",
				"locality": "Grand Manan",
				"neighborhood": "Seal Cove",
				"postalCode": "E5G 2J4"
			},
			"geometry": {
				"type": "Point",
				"coordinates": [
					-66.8401632,
					44.6505831
				]
			},
			"bbox": [
				-66.8417434,
				44.6494589,
				-66.838583,
				44.6517073
			]
		}
	]
}
