{
	"type": "FeatureCollection",
	"features": [
		{
			"type": "Feature",
			"properties": {
				"confidence": 9,
				"authenticationResultCode": "ValidCredentials",
				"brandLogoUri": "http://dev.virtualearth.net/Branding/logo_powered_by.png",
				"copyright": "Copyright © 2017 Microsoft and its suppliers. All rights reserved. This API cannot be accessed and the content and any results may not be used, reproduced or transmitted in any manner without express written permission from Microsoft Corporation.",
				"entityType": "Address",
				"matchCodes": [
					"Good"
				],
				"name": "6 Ontario St, Sundridge, ON P0A, Canada",
				"statusCode": 200,
				"statusDescription": "OK",
				"traceId": "3f9591e0e5bd49c78a7b405490f14e18|BN20130521|7.7.0.0|",
				"addressLine": "6 Ontario St",
				"adminDistrict": "ON",
				"adminDistrict2": "Parry Sound",
				"countryRegion": "Canada",
				"formattedAddress": "6 Ontario St, Sundridge, ON P0A, Canada",
				"locality": "Sundridge",
				"postalCode": "P0A 1Z0"
			},
			"geometry": {
				"type": "Point",
				"coordinates": [
					-79.3999608,
					45.7663967
				]
			},
			"bbox": [
				-79.4015723,
				45.7652725,
				-79.3983493,
				45.7675208
			]
		}
	]
}
