{
	"type": "FeatureCollection",
	"features": [
		{
			"type": "Feature",
			"properties": {
				"confidence": 9,
				"authenticationResultCode": "ValidCredentials",
				"brandLogoUri": "http://dev.virtualearth.net/Branding/logo_powered_by.png",
				"copyright": "Copyright © 2017 Microsoft and its suppliers. All rights reserved. This API cannot be accessed and the content and any results may not be used, reproduced or transmitted in any manner without express written permission from Microsoft Corporation.",
				"entityType": "Address",
				"matchCodes": [
					"Good"
				],
				"name": "6 Pincarrow Rd, Winnipeg, MB R3Y 1E1, Canada",
				"statusCode": 200,
				"statusDescription": "OK",
				"traceId": "fd4fb1eeee504300ad398c6c6bf06aec|BN20130621|7.7.0.0|",
				"addressLine": "6 Pincarrow Rd",
				"adminDistrict": "MB",
				"adminDistrict2": "Manitoba",
				"countryRegion": "Canada",
				"formattedAddress": "6 Pincarrow Rd, Winnipeg, MB R3Y 1E1, Canada",
				"locality": "Winnipeg",
				"neighborhood": "Whyte Ridge",
				"postalCode": "R3Y 1E1"
			},
			"geometry": {
				"type": "Point",
				"coordinates": [
					-97.20536,
					49.81294
				]
			},
			"bbox": [
				-97.2071021,
				49.8118158,
				-97.2036179,
				49.8140642
			]
		}
	]
}
