{
	"type": "FeatureCollection",
	"features": [
		{
			"type": "Feature",
			"properties": {
				"confidence": 9,
				"authenticationResultCode": "ValidCredentials",
				"brandLogoUri": "http://dev.virtualearth.net/Branding/logo_powered_by.png",
				"copyright": "Copyright © 2017 Microsoft and its suppliers. All rights reserved. This API cannot be accessed and the content and any results may not be used, reproduced or transmitted in any manner without express written permission from Microsoft Corporation.",
				"entityType": "Address",
				"matchCodes": [
					"Good"
				],
				"name": "6 Vansco Rd, Etobicoke, ON M8Z 5J4, Canada",
				"statusCode": 200,
				"statusDescription": "OK",
				"traceId": "a546d37427ae4e86af4bd51c60c64e87|BN20190642|7.7.0.0|",
				"addressLine": "6 Vansco Rd",
				"adminDistrict": "ON",
				"adminDistrict2": "Toronto",
				"countryRegion": "Canada",
				"formattedAddress": "6 Vansco Rd, Etobicoke, ON M8Z 5J4, Canada",
				"locality": "Toronto",
				"neighborhood": "Islington-City Centre West",
				"postalCode": "M8Z 5J4"
			},
			"geometry": {
				"type": "Point",
				"coordinates": [
					-79.5351,
					43.62008
				]
			},
			"bbox": [
				-79.5366528,
				43.6189558,
				-79.5335472,
				43.6212042
			]
		}
	]
}
