{
	"type": "FeatureCollection",
	"features": [
		{
			"type": "Feature",
			"properties": {
				"confidence": 9,
				"authenticationResultCode": "ValidCredentials",
				"brandLogoUri": "http://dev.virtualearth.net/Branding/logo_powered_by.png",
				"copyright": "Copyright © 2017 Microsoft and its suppliers. All rights reserved. This API cannot be accessed and the content and any results may not be used, reproduced or transmitted in any manner without express written permission from Microsoft Corporation.",
				"entityType": "Address",
				"matchCodes": [
					"Good"
				],
				"name": "60 Armstrong Ave, Toronto, ON M6H 1V8, Canada",
				"statusCode": 200,
				"statusDescription": "OK",
				"traceId": "36cbcbe2982f4c4da2ad1de401b8b66f|BN20130533|7.7.0.0|",
				"addressLine": "60 Armstrong Ave",
				"adminDistrict": "ON",
				"adminDistrict2": "Toronto",
				"countryRegion": "Canada",
				"formattedAddress": "60 Armstrong Ave, Toronto, ON M6H 1V8, Canada",
				"locality": "Toronto",
				"neighborhood": "Dovercourt-Wallace Emerson-Junction",
				"postalCode": "M6H 1V8"
			},
			"geometry": {
				"type": "Point",
				"coordinates": [
					-79.43953,
					43.66444
				]
			},
			"bbox": [
				-79.441084,
				43.6633158,
				-79.437976,
				43.6655642
			]
		}
	]
}
