{
	"type": "FeatureCollection",
	"features": [
		{
			"type": "Feature",
			"properties": {
				"confidence": 9,
				"authenticationResultCode": "ValidCredentials",
				"brandLogoUri": "http://dev.virtualearth.net/Branding/logo_powered_by.png",
				"copyright": "Copyright © 2017 Microsoft and its suppliers. All rights reserved. This API cannot be accessed and the content and any results may not be used, reproduced or transmitted in any manner without express written permission from Microsoft Corporation.",
				"entityType": "Address",
				"matchCodes": [
					"Good"
				],
				"name": "60 Courtice Ct, Courtice, ON L1E 2T3, Canada",
				"statusCode": 200,
				"statusDescription": "OK",
				"traceId": "bf358f2c9cfa4368b02d79e1baf6eb36|BN20280152|7.7.0.0|",
				"addressLine": "60 Courtice Ct",
				"adminDistrict": "ON",
				"adminDistrict2": "Durham",
				"countryRegion": "Canada",
				"formattedAddress": "60 Courtice Ct, Courtice, ON L1E 2T3, Canada",
				"locality": "Clarington",
				"neighborhood": "Courtice",
				"postalCode": "L1E 2T3"
			},
			"geometry": {
				"type": "Point",
				"coordinates": [
					-78.75895,
					43.8815
				]
			},
			"bbox": [
				-78.7605096,
				43.8803758,
				-78.7573904,
				43.8826242
			]
		}
	]
}
