{
	"type": "FeatureCollection",
	"features": [
		{
			"type": "Feature",
			"properties": {
				"confidence": 9,
				"authenticationResultCode": "ValidCredentials",
				"brandLogoUri": "http://dev.virtualearth.net/Branding/logo_powered_by.png",
				"copyright": "Copyright © 2017 Microsoft and its suppliers. All rights reserved. This API cannot be accessed and the content and any results may not be used, reproduced or transmitted in any manner without express written permission from Microsoft Corporation.",
				"entityType": "Address",
				"matchCodes": [
					"Good"
				],
				"name": "60 Gloucester Junction Rd, Bathurst Parish, NB E2A 6H2, Canada",
				"statusCode": 200,
				"statusDescription": "OK",
				"traceId": "2a18cd939f6e4aa0a72a7800a7b28489|BN20181720|7.7.0.0|",
				"addressLine": "60 Gloucester Junction Rd",
				"adminDistrict": "NB",
				"adminDistrict2": "Gloucester",
				"countryRegion": "Canada",
				"formattedAddress": "60 Gloucester Junction Rd, Bathurst Parish, NB E2A 6H2, Canada",
				"locality": "Bathurst Parish",
				"neighborhood": "Chamberlain Settlement",
				"postalCode": "E2A 6H2"
			},
			"geometry": {
				"type": "Point",
				"coordinates": [
					-65.6450154,
					47.5720385
				]
			},
			"bbox": [
				-65.6466817,
				47.5709144,
				-65.6433492,
				47.5731627
			]
		}
	]
}
