{
	"type": "FeatureCollection",
	"features": [
		{
			"type": "Feature",
			"properties": {
				"confidence": 9,
				"authenticationResultCode": "ValidCredentials",
				"brandLogoUri": "http://dev.virtualearth.net/Branding/logo_powered_by.png",
				"copyright": "Copyright © 2017 Microsoft and its suppliers. All rights reserved. This API cannot be accessed and the content and any results may not be used, reproduced or transmitted in any manner without express written permission from Microsoft Corporation.",
				"entityType": "Address",
				"matchCodes": [
					"Good"
				],
				"name": "600 Rosmere St, Oshawa, ON L1J 5H7, Canada",
				"statusCode": 200,
				"statusDescription": "OK",
				"traceId": "f03b92571c974e97a7ad1e1f37633480|BN20260223|7.7.0.0|",
				"addressLine": "600 Rosmere St",
				"adminDistrict": "ON",
				"adminDistrict2": "Durham",
				"countryRegion": "Canada",
				"formattedAddress": "600 Rosmere St, Oshawa, ON L1J 5H7, Canada",
				"locality": "Oshawa",
				"neighborhood": "McLaughlin",
				"postalCode": "L1J 5H7"
			},
			"geometry": {
				"type": "Point",
				"coordinates": [
					-78.8868899,
					43.90955
				]
			},
			"bbox": [
				-78.8884503,
				43.9084258,
				-78.8853295,
				43.9106742
			]
		}
	]
}
