{
	"type": "FeatureCollection",
	"features": [
		{
			"type": "Feature",
			"properties": {
				"confidence": 9,
				"authenticationResultCode": "ValidCredentials",
				"brandLogoUri": "http://dev.virtualearth.net/Branding/logo_powered_by.png",
				"copyright": "Copyright © 2017 Microsoft and its suppliers. All rights reserved. This API cannot be accessed and the content and any results may not be used, reproduced or transmitted in any manner without express written permission from Microsoft Corporation.",
				"entityType": "Address",
				"matchCodes": [
					"Good"
				],
				"name": "600 Pleasant St, Halifax, NS B2W, Canada",
				"statusCode": 200,
				"statusDescription": "OK",
				"traceId": "84b1ebc5459c4f7894b00ebeb715e057|BN20290118|7.7.0.0|",
				"addressLine": "600 Pleasant St",
				"adminDistrict": "NS",
				"adminDistrict2": "Halifax",
				"countryRegion": "Canada",
				"formattedAddress": "600 Pleasant St, Halifax, NS B2W, Canada",
				"locality": "Halifax",
				"neighborhood": "Dartmouth",
				"postalCode": "B2W"
			},
			"geometry": {
				"type": "Point",
				"coordinates": [
					-63.5363841,
					44.6423232
				]
			},
			"bbox": [
				-63.537964,
				44.6411991,
				-63.5348041,
				44.6434474
			]
		}
	]
}
