{
	"type": "FeatureCollection",
	"features": [
		{
			"type": "Feature",
			"properties": {
				"confidence": 9,
				"authenticationResultCode": "ValidCredentials",
				"brandLogoUri": "http://dev.virtualearth.net/Branding/logo_powered_by.png",
				"copyright": "Copyright © 2017 Microsoft and its suppliers. All rights reserved. This API cannot be accessed and the content and any results may not be used, reproduced or transmitted in any manner without express written permission from Microsoft Corporation.",
				"entityType": "Address",
				"matchCodes": [
					"Good"
				],
				"name": "600 Rue Harvey O, Alma, QC G8B 1P2, Canada",
				"statusCode": 200,
				"statusDescription": "OK",
				"traceId": "f6b0627606c3463282dfd58ebcd510cb|BN20121762|7.7.0.0|",
				"addressLine": "600 Rue Harvey O",
				"adminDistrict": "QC",
				"adminDistrict2": "Lac-St-Jean-Est",
				"countryRegion": "Canada",
				"formattedAddress": "600 Rue Harvey O, Alma, QC G8B 1P2, Canada",
				"locality": "Alma",
				"postalCode": "G8B 1P2"
			},
			"geometry": {
				"type": "Point",
				"coordinates": [
					-71.65231,
					48.54885
				]
			},
			"bbox": [
				-71.6540082,
				48.5477258,
				-71.6506118,
				48.5499742
			]
		}
	]
}
