{
	"type": "FeatureCollection",
	"features": [
		{
			"type": "Feature",
			"properties": {
				"confidence": 7,
				"authenticationResultCode": "ValidCredentials",
				"brandLogoUri": "http://dev.virtualearth.net/Branding/logo_powered_by.png",
				"copyright": "Copyright © 2017 Microsoft and its suppliers. All rights reserved. This API cannot be accessed and the content and any results may not be used, reproduced or transmitted in any manner without express written permission from Microsoft Corporation.",
				"entityType": "Postcode1",
				"matchCodes": [
					"UpHierarchy"
				],
				"name": "Glaslyn, S0M 0Y0, Canada",
				"statusCode": 200,
				"statusDescription": "OK",
				"traceId": "339834cf3f3a46c3a762482d4e117aa0|BN20290118|7.7.0.0|",
				"adminDistrict": "SK",
				"countryRegion": "Canada",
				"formattedAddress": "Glaslyn, S0M 0Y0, Canada",
				"locality": "Glaslyn",
				"postalCode": "S0M 0Y0"
			},
			"geometry": {
				"type": "Point",
				"coordinates": [
					-108.352416992188,
					53.3599815368652
				]
			},
			"bbox": [
				-108.361046262934,
				53.3561188192946,
				-108.343787721441,
				53.3638442544359
			]
		}
	]
}
