{
	"type": "FeatureCollection",
	"features": [
		{
			"type": "Feature",
			"properties": {
				"confidence": 9,
				"authenticationResultCode": "ValidCredentials",
				"brandLogoUri": "http://dev.virtualearth.net/Branding/logo_powered_by.png",
				"copyright": "Copyright © 2017 Microsoft and its suppliers. All rights reserved. This API cannot be accessed and the content and any results may not be used, reproduced or transmitted in any manner without express written permission from Microsoft Corporation.",
				"entityType": "Address",
				"matchCodes": [
					"UpHierarchy"
				],
				"name": "60330 Range Road 34, Barrhead County No 11, AB T0G, Canada",
				"statusCode": 200,
				"statusDescription": "OK",
				"traceId": "d0e2c06aeb0144edb2aa2049679dbe6d|BN20130422|7.7.0.0|",
				"addressLine": "60330 Range Road 34",
				"adminDistrict": "AB",
				"adminDistrict2": "Alberta",
				"countryRegion": "Canada",
				"formattedAddress": "60330 Range Road 34, Barrhead County No 11, AB T0G, Canada",
				"locality": "Barrhead County No 11",
				"postalCode": "T0G"
			},
			"geometry": {
				"type": "Point",
				"coordinates": [
					-114.4019149,
					54.2053913
				]
			},
			"bbox": [
				-114.4038369,
				54.2042672,
				-114.3999929,
				54.2065155
			]
		}
	]
}
