{
	"type": "FeatureCollection",
	"features": [
		{
			"type": "Feature",
			"properties": {
				"confidence": 9,
				"authenticationResultCode": "ValidCredentials",
				"brandLogoUri": "http://dev.virtualearth.net/Branding/logo_powered_by.png",
				"copyright": "Copyright © 2017 Microsoft and its suppliers. All rights reserved. This API cannot be accessed and the content and any results may not be used, reproduced or transmitted in any manner without express written permission from Microsoft Corporation.",
				"entityType": "Address",
				"matchCodes": [
					"Good"
				],
				"name": "6035 6 St SE, Calgary, AB T2H 1L8, Canada",
				"statusCode": 200,
				"statusDescription": "OK",
				"traceId": "a93337f2f8b14d00b54e02537d259b65|BN20130442|7.7.0.0|",
				"addressLine": "6035 6 St SE",
				"adminDistrict": "AB",
				"adminDistrict2": "Alberta",
				"countryRegion": "Canada",
				"formattedAddress": "6035 6 St SE, Calgary, AB T2H 1L8, Canada",
				"locality": "Calgary",
				"neighborhood": "Alyth-Bonnybrook-Manchester",
				"postalCode": "T2H 1L8"
			},
			"geometry": {
				"type": "Point",
				"coordinates": [
					-114.0504318,
					50.9988151
				]
			},
			"bbox": [
				-114.052218,
				50.997691,
				-114.0486455,
				50.9999393
			]
		}
	]
}
