{
	"type": "FeatureCollection",
	"features": [
		{
			"type": "Feature",
			"properties": {
				"confidence": 9,
				"authenticationResultCode": "ValidCredentials",
				"brandLogoUri": "http://dev.virtualearth.net/Branding/logo_powered_by.png",
				"copyright": "Copyright © 2017 Microsoft and its suppliers. All rights reserved. This API cannot be accessed and the content and any results may not be used, reproduced or transmitted in any manner without express written permission from Microsoft Corporation.",
				"entityType": "Address",
				"matchCodes": [
					"Good"
				],
				"name": "606 Rue de la Noue, Verdun, QC H3E 1S7, Canada",
				"statusCode": 200,
				"statusDescription": "OK",
				"traceId": "a17f0b7b5df34d639f4fd4237a696c0e|BN20131519|7.7.0.0|",
				"addressLine": "606 Rue de la Noue",
				"adminDistrict": "QC",
				"adminDistrict2": "Montreal",
				"countryRegion": "Canada",
				"formattedAddress": "606 Rue de la Noue, Verdun, QC H3E 1S7, Canada",
				"locality": "Montreal",
				"neighborhood": "Verdun",
				"postalCode": "H3E 1S7"
			},
			"geometry": {
				"type": "Point",
				"coordinates": [
					-73.54942,
					45.46212
				]
			},
			"bbox": [
				-73.5510228,
				45.4609958,
				-73.5478172,
				45.4632442
			]
		}
	]
}
