{
	"type": "FeatureCollection",
	"features": [
		{
			"type": "Feature",
			"properties": {
				"confidence": 9,
				"authenticationResultCode": "ValidCredentials",
				"brandLogoUri": "http://dev.virtualearth.net/Branding/logo_powered_by.png",
				"copyright": "Copyright © 2017 Microsoft and its suppliers. All rights reserved. This API cannot be accessed and the content and any results may not be used, reproduced or transmitted in any manner without express written permission from Microsoft Corporation.",
				"entityType": "Address",
				"matchCodes": [
					"Good"
				],
				"name": "606 Campbell St, Tofino, BC V0R, Canada",
				"statusCode": 200,
				"statusDescription": "OK",
				"traceId": "649d88c5e9194602a4b4c80528a53779|BN20130422|7.7.0.0|",
				"addressLine": "606 Campbell St",
				"adminDistrict": "BC",
				"adminDistrict2": "Alberni-Clayoquot",
				"countryRegion": "Canada",
				"formattedAddress": "606 Campbell St, Tofino, BC V0R, Canada",
				"locality": "Tofino",
				"postalCode": "V0R 2Z0"
			},
			"geometry": {
				"type": "Point",
				"coordinates": [
					-125.89734,
					49.15138
				]
			},
			"bbox": [
				-125.8990587,
				49.1502558,
				-125.8956213,
				49.1525042
			]
		}
	]
}
