{
	"type": "FeatureCollection",
	"features": [
		{
			"type": "Feature",
			"properties": {
				"confidence": 9,
				"authenticationResultCode": "ValidCredentials",
				"brandLogoUri": "http://dev.virtualearth.net/Branding/logo_powered_by.png",
				"copyright": "Copyright © 2017 Microsoft and its suppliers. All rights reserved. This API cannot be accessed and the content and any results may not be used, reproduced or transmitted in any manner without express written permission from Microsoft Corporation.",
				"entityType": "Address",
				"matchCodes": [
					"Good"
				],
				"name": "61 Halcomb Rd, Lyttleton, NB E9E 1V5, Canada",
				"statusCode": 200,
				"statusDescription": "OK",
				"traceId": "8392b665b2ff472b91b663fdb0a2e0a2|BN20200239|7.7.0.0|",
				"addressLine": "61 Halcomb Rd",
				"adminDistrict": "NB",
				"adminDistrict2": "Northumberland",
				"countryRegion": "Canada",
				"formattedAddress": "61 Halcomb Rd, Lyttleton, NB E9E 1V5, Canada",
				"locality": "Southesk",
				"neighborhood": "Lyttleton",
				"postalCode": "E9E 1V5"
			},
			"geometry": {
				"type": "Point",
				"coordinates": [
					-65.91295,
					46.93809
				]
			},
			"bbox": [
				-65.9145964,
				46.9369658,
				-65.9113036,
				46.9392142
			]
		}
	]
}
