{
	"type": "FeatureCollection",
	"features": [
		{
			"type": "Feature",
			"properties": {
				"confidence": 9,
				"authenticationResultCode": "ValidCredentials",
				"brandLogoUri": "http://dev.virtualearth.net/Branding/logo_powered_by.png",
				"copyright": "Copyright © 2017 Microsoft and its suppliers. All rights reserved. This API cannot be accessed and the content and any results may not be used, reproduced or transmitted in any manner without express written permission from Microsoft Corporation.",
				"entityType": "Address",
				"matchCodes": [
					"Good"
				],
				"name": "61 Riverview Rd W, Eel Ground, NB E1V 4G2, Canada",
				"statusCode": 200,
				"statusDescription": "OK",
				"traceId": "22015a3e8c4947888612289535b83e4c|BN20121764|7.7.0.0|",
				"addressLine": "61 Riverview Rd W",
				"adminDistrict": "NB",
				"adminDistrict2": "Northumberland",
				"countryRegion": "Canada",
				"formattedAddress": "61 Riverview Rd W, Eel Ground, NB E1V 4G2, Canada",
				"locality": "Northesk",
				"neighborhood": "Eel Ground",
				"postalCode": "E1V 4G2"
			},
			"geometry": {
				"type": "Point",
				"coordinates": [
					-65.6346565,
					46.9629221
				]
			},
			"bbox": [
				-65.6363037,
				46.961798,
				-65.6330093,
				46.9640463
			]
		}
	]
}
