{
	"type": "FeatureCollection",
	"features": [
		{
			"type": "Feature",
			"properties": {
				"confidence": 9,
				"authenticationResultCode": "ValidCredentials",
				"brandLogoUri": "http://dev.virtualearth.net/Branding/logo_powered_by.png",
				"copyright": "Copyright © 2017 Microsoft and its suppliers. All rights reserved. This API cannot be accessed and the content and any results may not be used, reproduced or transmitted in any manner without express written permission from Microsoft Corporation.",
				"entityType": "Address",
				"matchCodes": [
					"Good"
				],
				"name": "610 Lower Slash Rd, Deseronto, ON K0K 1X0, Canada",
				"statusCode": 200,
				"statusDescription": "OK",
				"traceId": "2285abe15d784eafa733a6a877a3762d|BN20260223|7.7.0.0|",
				"addressLine": "610 Lower Slash Rd",
				"adminDistrict": "ON",
				"adminDistrict2": "Hastings",
				"countryRegion": "Canada",
				"formattedAddress": "610 Lower Slash Rd, Deseronto, ON K0K 1X0, Canada",
				"locality": "Tyendinaga",
				"neighborhood": "Deseronto",
				"postalCode": "K0K 1X0"
			},
			"geometry": {
				"type": "Point",
				"coordinates": [
					-77.1092673,
					44.2101992
				]
			},
			"bbox": [
				-77.1108356,
				44.2090751,
				-77.107699,
				44.2113234
			]
		}
	]
}
