{
	"type": "FeatureCollection",
	"features": [
		{
			"type": "Feature",
			"properties": {
				"confidence": 9,
				"authenticationResultCode": "ValidCredentials",
				"brandLogoUri": "http://dev.virtualearth.net/Branding/logo_powered_by.png",
				"copyright": "Copyright © 2017 Microsoft and its suppliers. All rights reserved. This API cannot be accessed and the content and any results may not be used, reproduced or transmitted in any manner without express written permission from Microsoft Corporation.",
				"entityType": "Address",
				"matchCodes": [
					"Good"
				],
				"name": "614 N River Rd, Charlottetown, PE C1E 1K2, Canada",
				"statusCode": 200,
				"statusDescription": "OK",
				"traceId": "953c7dd120f74741842f0f340d01df56|BN20280152|7.7.0.0|",
				"addressLine": "614 N River Rd",
				"adminDistrict": "PE",
				"adminDistrict2": "Queens",
				"countryRegion": "Canada",
				"formattedAddress": "614 N River Rd, Charlottetown, PE C1E 1K2, Canada",
				"locality": "Charlottetown",
				"neighborhood": "Spring Park",
				"postalCode": "C1E 1K2"
			},
			"geometry": {
				"type": "Point",
				"coordinates": [
					-63.15737,
					46.26353
				]
			},
			"bbox": [
				-63.158996,
				46.2624058,
				-63.155744,
				46.2646542
			]
		}
	]
}
