{
	"type": "FeatureCollection",
	"features": [
		{
			"type": "Feature",
			"properties": {
				"confidence": 9,
				"authenticationResultCode": "ValidCredentials",
				"brandLogoUri": "http://dev.virtualearth.net/Branding/logo_powered_by.png",
				"copyright": "Copyright © 2017 Microsoft and its suppliers. All rights reserved. This API cannot be accessed and the content and any results may not be used, reproduced or transmitted in any manner without express written permission from Microsoft Corporation.",
				"entityType": "Address",
				"matchCodes": [
					"Good"
				],
				"name": "6145 Genoa Bay Rd, Duncan, BC V9L 5T7, Canada",
				"statusCode": 200,
				"statusDescription": "OK",
				"traceId": "11e01ddb09f142e792646b0e1c6937d5|BN20190642|7.7.0.0|",
				"addressLine": "6145 Genoa Bay Rd",
				"adminDistrict": "BC",
				"adminDistrict2": "Cowichan Valley",
				"countryRegion": "Canada",
				"formattedAddress": "6145 Genoa Bay Rd, Duncan, BC V9L 5T7, Canada",
				"locality": "North Cowichan",
				"neighborhood": "Duncan",
				"postalCode": "V9L 5T7"
			},
			"geometry": {
				"type": "Point",
				"coordinates": [
					-123.60228,
					48.79526
				]
			},
			"bbox": [
				-123.6039865,
				48.7941358,
				-123.6005735,
				48.7963842
			]
		}
	]
}
