{
	"type": "FeatureCollection",
	"features": [
		{
			"type": "Feature",
			"properties": {
				"confidence": 9,
				"authenticationResultCode": "ValidCredentials",
				"brandLogoUri": "http://dev.virtualearth.net/Branding/logo_powered_by.png",
				"copyright": "Copyright © 2017 Microsoft and its suppliers. All rights reserved. This API cannot be accessed and the content and any results may not be used, reproduced or transmitted in any manner without express written permission from Microsoft Corporation.",
				"entityType": "Address",
				"matchCodes": [
					"Good"
				],
				"name": "615 Davenport Rd, Waterloo, ON N2V 2G2, Canada",
				"statusCode": 200,
				"statusDescription": "OK",
				"traceId": "62547f914e8b4242b07542475b52085a|BN20260223|7.7.0.0|",
				"addressLine": "615 Davenport Rd",
				"adminDistrict": "ON",
				"adminDistrict2": "Waterloo",
				"countryRegion": "Canada",
				"formattedAddress": "615 Davenport Rd, Waterloo, ON N2V 2G2, Canada",
				"locality": "Waterloo",
				"postalCode": "N2V 2G2"
			},
			"geometry": {
				"type": "Point",
				"coordinates": [
					-80.52987,
					43.50357
				]
			},
			"bbox": [
				-80.5314198,
				43.5024458,
				-80.5283202,
				43.5046942
			]
		}
	]
}
