{
	"type": "FeatureCollection",
	"features": [
		{
			"type": "Feature",
			"properties": {
				"confidence": 9,
				"authenticationResultCode": "ValidCredentials",
				"brandLogoUri": "http://dev.virtualearth.net/Branding/logo_powered_by.png",
				"copyright": "Copyright © 2017 Microsoft and its suppliers. All rights reserved. This API cannot be accessed and the content and any results may not be used, reproduced or transmitted in any manner without express written permission from Microsoft Corporation.",
				"entityType": "Address",
				"matchCodes": [
					"Good"
				],
				"name": "616 Welland Ave, St Catharines, ON L2M 5V6, Canada",
				"statusCode": 200,
				"statusDescription": "OK",
				"traceId": "0dc1245c32274d819903d85c1d5b9e73|BN20190642|7.7.0.0|",
				"addressLine": "616 Welland Ave",
				"adminDistrict": "ON",
				"adminDistrict2": "Niagara",
				"countryRegion": "Canada",
				"formattedAddress": "616 Welland Ave, St Catharines, ON L2M 5V6, Canada",
				"locality": "St Catharines",
				"neighborhood": "Queenston",
				"postalCode": "L2M 5V6"
			},
			"geometry": {
				"type": "Point",
				"coordinates": [
					-79.202231,
					43.1792825
				]
			},
			"bbox": [
				-79.2037726,
				43.1781584,
				-79.2006894,
				43.1804067
			]
		}
	]
}
