{
	"type": "FeatureCollection",
	"features": [
		{
			"type": "Feature",
			"properties": {
				"confidence": 9,
				"authenticationResultCode": "ValidCredentials",
				"brandLogoUri": "http://dev.virtualearth.net/Branding/logo_powered_by.png",
				"copyright": "Copyright © 2017 Microsoft and its suppliers. All rights reserved. This API cannot be accessed and the content and any results may not be used, reproduced or transmitted in any manner without express written permission from Microsoft Corporation.",
				"entityType": "Address",
				"matchCodes": [
					"Good"
				],
				"name": "6165 Kennedy Rd, Mississauga, ON L5T 2S8, Canada",
				"statusCode": 200,
				"statusDescription": "OK",
				"traceId": "8b9db61401904f73be18f1a17274582f|BN20130423|7.7.0.0|",
				"addressLine": "6165 Kennedy Rd",
				"adminDistrict": "ON",
				"adminDistrict2": "Peel",
				"countryRegion": "Canada",
				"formattedAddress": "6165 Kennedy Rd, Mississauga, ON L5T 2S8, Canada",
				"locality": "Mississauga",
				"postalCode": "L5T 2S8"
			},
			"geometry": {
				"type": "Point",
				"coordinates": [
					-79.67325,
					43.64023
				]
			},
			"bbox": [
				-79.6748034,
				43.6391058,
				-79.6716966,
				43.6413542
			]
		}
	]
}
