{
	"type": "FeatureCollection",
	"features": [
		{
			"type": "Feature",
			"properties": {
				"confidence": 9,
				"authenticationResultCode": "ValidCredentials",
				"brandLogoUri": "http://dev.virtualearth.net/Branding/logo_powered_by.png",
				"copyright": "Copyright © 2017 Microsoft and its suppliers. All rights reserved. This API cannot be accessed and the content and any results may not be used, reproduced or transmitted in any manner without express written permission from Microsoft Corporation.",
				"entityType": "Address",
				"matchCodes": [
					"Good"
				],
				"name": "6169 River View Line, Chatham-Kent, ON N0P 2L0, Canada",
				"statusCode": 200,
				"statusDescription": "OK",
				"traceId": "6985870b661644c088ab684542529f54|BN20130422|7.7.0.0|",
				"addressLine": "6169 River View Line",
				"adminDistrict": "ON",
				"adminDistrict2": "Chatham-Kent",
				"countryRegion": "Canada",
				"formattedAddress": "6169 River View Line, Chatham-Kent, ON N0P 2L0, Canada",
				"locality": "Chatham-Kent",
				"neighborhood": "Raleigh",
				"postalCode": "N0P 2L0"
			},
			"geometry": {
				"type": "Point",
				"coordinates": [
					-82.31748,
					42.35508
				]
			},
			"bbox": [
				-82.3190012,
				42.3539558,
				-82.3159588,
				42.3562042
			]
		}
	]
}
