{
	"type": "FeatureCollection",
	"features": [
		{
			"type": "Feature",
			"properties": {
				"confidence": 9,
				"authenticationResultCode": "ValidCredentials",
				"brandLogoUri": "http://dev.virtualearth.net/Branding/logo_powered_by.png",
				"copyright": "Copyright © 2017 Microsoft and its suppliers. All rights reserved. This API cannot be accessed and the content and any results may not be used, reproduced or transmitted in any manner without express written permission from Microsoft Corporation.",
				"entityType": "Address",
				"matchCodes": [
					"Good"
				],
				"name": "6182 North St, Halifax, NS B3K 1P5, Canada",
				"statusCode": 200,
				"statusDescription": "OK",
				"traceId": "75ce3821678b4f43b27b94c4fba1d343|BN20210145|7.7.0.0|",
				"addressLine": "6182 North St",
				"adminDistrict": "NS",
				"adminDistrict2": "Halifax",
				"countryRegion": "Canada",
				"formattedAddress": "6182 North St, Halifax, NS B3K 1P5, Canada",
				"locality": "Halifax",
				"neighborhood": "North End",
				"postalCode": "B3K 1P5"
			},
			"geometry": {
				"type": "Point",
				"coordinates": [
					-63.59783,
					44.6523899
				]
			},
			"bbox": [
				-63.5994102,
				44.6512657,
				-63.5962498,
				44.6535141
			]
		}
	]
}
