{
	"type": "FeatureCollection",
	"features": [
		{
			"type": "Feature",
			"properties": {
				"confidence": 9,
				"authenticationResultCode": "ValidCredentials",
				"brandLogoUri": "http://dev.virtualearth.net/Branding/logo_powered_by.png",
				"copyright": "Copyright © 2017 Microsoft and its suppliers. All rights reserved. This API cannot be accessed and the content and any results may not be used, reproduced or transmitted in any manner without express written permission from Microsoft Corporation.",
				"entityType": "Address",
				"matchCodes": [
					"Good"
				],
				"name": "621 46 Ave NE, Calgary, AB T2E 8J6, Canada",
				"statusCode": 200,
				"statusDescription": "OK",
				"traceId": "a04f898d1df7491caa630872b846b12f|BN20130423|7.7.0.0|",
				"addressLine": "621 46 Ave NE",
				"adminDistrict": "AB",
				"adminDistrict2": "Alberta",
				"countryRegion": "Canada",
				"formattedAddress": "621 46 Ave NE, Calgary, AB T2E 8J6, Canada",
				"locality": "Calgary",
				"neighborhood": "Greenview",
				"postalCode": "T2E 8J6"
			},
			"geometry": {
				"type": "Point",
				"coordinates": [
					-114.0506316,
					51.0943751
				]
			},
			"bbox": [
				-114.0524215,
				51.0932509,
				-114.0488416,
				51.0954993
			]
		}
	]
}
