{
	"type": "FeatureCollection",
	"features": [
		{
			"type": "Feature",
			"properties": {
				"confidence": 9,
				"authenticationResultCode": "ValidCredentials",
				"brandLogoUri": "http://dev.virtualearth.net/Branding/logo_powered_by.png",
				"copyright": "Copyright © 2017 Microsoft and its suppliers. All rights reserved. This API cannot be accessed and the content and any results may not be used, reproduced or transmitted in any manner without express written permission from Microsoft Corporation.",
				"entityType": "Address",
				"matchCodes": [
					"Good"
				],
				"name": "6250 Edwards Blvd, Mississauga, ON L5T 2X3, Canada",
				"statusCode": 200,
				"statusDescription": "OK",
				"traceId": "bc5ee2a264a24b528c036e0475973332|BN20130719|7.7.0.0|",
				"addressLine": "6250 Edwards Blvd",
				"adminDistrict": "ON",
				"adminDistrict2": "Peel",
				"countryRegion": "Canada",
				"formattedAddress": "6250 Edwards Blvd, Mississauga, ON L5T 2X3, Canada",
				"locality": "Mississauga",
				"postalCode": "L5T 2X3"
			},
			"geometry": {
				"type": "Point",
				"coordinates": [
					-79.6847474,
					43.6344316
				]
			},
			"bbox": [
				-79.6863006,
				43.6333074,
				-79.6831942,
				43.6355557
			]
		}
	]
}
