{
	"type": "FeatureCollection",
	"features": [
		{
			"type": "Feature",
			"properties": {
				"confidence": 9,
				"authenticationResultCode": "ValidCredentials",
				"brandLogoUri": "http://dev.virtualearth.net/Branding/logo_powered_by.png",
				"copyright": "Copyright © 2017 Microsoft and its suppliers. All rights reserved. This API cannot be accessed and the content and any results may not be used, reproduced or transmitted in any manner without express written permission from Microsoft Corporation.",
				"entityType": "Address",
				"matchCodes": [
					"Good"
				],
				"name": "633 King St, Weyburn, SK S4H 2S5, Canada",
				"statusCode": 200,
				"statusDescription": "OK",
				"traceId": "c5421c36a4284fa293b1aea096d9c251|BN20130532|7.7.0.0|",
				"addressLine": "633 King St",
				"adminDistrict": "SK",
				"adminDistrict2": "Saskatchewan",
				"countryRegion": "Canada",
				"formattedAddress": "633 King St, Weyburn, SK S4H 2S5, Canada",
				"locality": "Weyburn",
				"postalCode": "S4H 2S5"
			},
			"geometry": {
				"type": "Point",
				"coordinates": [
					-103.8583349,
					49.6704931
				]
			},
			"bbox": [
				-103.8600719,
				49.6693689,
				-103.8565979,
				49.6716172
			]
		}
	]
}
