{
	"type": "FeatureCollection",
	"features": [
		{
			"type": "Feature",
			"properties": {
				"confidence": 9,
				"authenticationResultCode": "ValidCredentials",
				"brandLogoUri": "http://dev.virtualearth.net/Branding/logo_powered_by.png",
				"copyright": "Copyright © 2017 Microsoft and its suppliers. All rights reserved. This API cannot be accessed and the content and any results may not be used, reproduced or transmitted in any manner without express written permission from Microsoft Corporation.",
				"entityType": "Address",
				"matchCodes": [
					"Good"
				],
				"name": "6355 Airport Rd, Mississauga, ON L4V 1E4, Canada",
				"statusCode": 200,
				"statusDescription": "OK",
				"traceId": "df567d1ae8e447e78eab3a620ac0c80a|BN20130442|7.7.0.0|",
				"addressLine": "6355 Airport Rd",
				"adminDistrict": "ON",
				"adminDistrict2": "Peel",
				"countryRegion": "Canada",
				"formattedAddress": "6355 Airport Rd, Mississauga, ON L4V 1E4, Canada",
				"locality": "Mississauga",
				"neighborhood": "Malton",
				"postalCode": "L4V 1E4"
			},
			"geometry": {
				"type": "Point",
				"coordinates": [
					-79.62488,
					43.69133
				]
			},
			"bbox": [
				-79.6264347,
				43.6902058,
				-79.6233253,
				43.6924542
			]
		}
	]
}
