{
	"type": "FeatureCollection",
	"features": [
		{
			"type": "Feature",
			"properties": {
				"confidence": 9,
				"authenticationResultCode": "ValidCredentials",
				"brandLogoUri": "http://dev.virtualearth.net/Branding/logo_powered_by.png",
				"copyright": "Copyright © 2017 Microsoft and its suppliers. All rights reserved. This API cannot be accessed and the content and any results may not be used, reproduced or transmitted in any manner without express written permission from Microsoft Corporation.",
				"entityType": "Address",
				"matchCodes": [
					"Good"
				],
				"name": "6365 Northwest Dr, Mississauga, ON L4V 1J8, Canada",
				"statusCode": 200,
				"statusDescription": "OK",
				"traceId": "a57c5dbe61b04366b64aadee82adf9de|BN20320521|7.7.0.0|",
				"addressLine": "6365 Northwest Dr",
				"adminDistrict": "ON",
				"adminDistrict2": "Peel",
				"countryRegion": "Canada",
				"formattedAddress": "6365 Northwest Dr, Mississauga, ON L4V 1J8, Canada",
				"locality": "Mississauga",
				"neighborhood": "Malton",
				"postalCode": "L4V 1J8"
			},
			"geometry": {
				"type": "Point",
				"coordinates": [
					-79.61571,
					43.70103
				]
			},
			"bbox": [
				-79.6172649,
				43.6999058,
				-79.6141551,
				43.7021542
			]
		}
	]
}
