{
	"type": "FeatureCollection",
	"features": [
		{
			"type": "Feature",
			"properties": {
				"confidence": 9,
				"authenticationResultCode": "ValidCredentials",
				"brandLogoUri": "http://dev.virtualearth.net/Branding/logo_powered_by.png",
				"copyright": "Copyright © 2017 Microsoft and its suppliers. All rights reserved. This API cannot be accessed and the content and any results may not be used, reproduced or transmitted in any manner without express written permission from Microsoft Corporation.",
				"entityType": "Address",
				"matchCodes": [
					"Good"
				],
				"name": "637 Lansdowne St W, Peterborough, ON K9J 7C5, Canada",
				"statusCode": 200,
				"statusDescription": "OK",
				"traceId": "1a20039bf5e449cb8b98fb58a0f38c6d|BN20130442|7.7.0.0|",
				"addressLine": "637 Lansdowne St W",
				"adminDistrict": "ON",
				"adminDistrict2": "Peterborough",
				"countryRegion": "Canada",
				"formattedAddress": "637 Lansdowne St W, Peterborough, ON K9J 7C5, Canada",
				"locality": "Peterborough",
				"postalCode": "K9J 7C5"
			},
			"geometry": {
				"type": "Point",
				"coordinates": [
					-78.3317751,
					44.285191
				]
			},
			"bbox": [
				-78.3333454,
				44.2840669,
				-78.3302048,
				44.2863152
			]
		}
	]
}
