{
	"type": "FeatureCollection",
	"features": [
		{
			"type": "Feature",
			"properties": {
				"confidence": 9,
				"authenticationResultCode": "ValidCredentials",
				"brandLogoUri": "http://dev.virtualearth.net/Branding/logo_powered_by.png",
				"copyright": "Copyright © 2017 Microsoft and its suppliers. All rights reserved. This API cannot be accessed and the content and any results may not be used, reproduced or transmitted in any manner without express written permission from Microsoft Corporation.",
				"entityType": "Address",
				"matchCodes": [
					"Good"
				],
				"name": "63720 Rosewood Ave, Hope, BC V0X 1L2, Canada",
				"statusCode": 200,
				"statusDescription": "OK",
				"traceId": "4c04cd912110408eaed91a29c1734f40|BN20280152|7.7.0.0|",
				"addressLine": "63720 Rosewood Ave",
				"adminDistrict": "BC",
				"adminDistrict2": "Fraser Valley",
				"countryRegion": "Canada",
				"formattedAddress": "63720 Rosewood Ave, Hope, BC V0X 1L2, Canada",
				"locality": "Hope",
				"postalCode": "V0X 1L2"
			},
			"geometry": {
				"type": "Point",
				"coordinates": [
					-121.46696,
					49.36204
				]
			},
			"bbox": [
				-121.4686861,
				49.3609158,
				-121.4652339,
				49.3631642
			]
		}
	]
}
