{
	"type": "FeatureCollection",
	"features": [
		{
			"type": "Feature",
			"properties": {
				"confidence": 9,
				"authenticationResultCode": "ValidCredentials",
				"brandLogoUri": "http://dev.virtualearth.net/Branding/logo_powered_by.png",
				"copyright": "Copyright © 2017 Microsoft and its suppliers. All rights reserved. This API cannot be accessed and the content and any results may not be used, reproduced or transmitted in any manner without express written permission from Microsoft Corporation.",
				"entityType": "Address",
				"matchCodes": [
					"Good"
				],
				"name": "6376 Yatton Sdrd, Mapleton, ON N0B, Canada",
				"statusCode": 200,
				"statusDescription": "OK",
				"traceId": "ae5bb05d24c849af971fa156349afff4|BN20181720|7.7.0.0|",
				"addressLine": "6376 Yatton Sdrd",
				"adminDistrict": "ON",
				"adminDistrict2": "Wellington",
				"countryRegion": "Canada",
				"formattedAddress": "6376 Yatton Sdrd, Mapleton, ON N0B, Canada",
				"locality": "Mapleton",
				"postalCode": "N0B 2S0"
			},
			"geometry": {
				"type": "Point",
				"coordinates": [
					-80.6337099,
					43.60168
				]
			},
			"bbox": [
				-80.6352623,
				43.6005558,
				-80.6321575,
				43.6028042
			]
		}
	]
}
