{
	"type": "FeatureCollection",
	"features": [
		{
			"type": "Feature",
			"properties": {
				"confidence": 9,
				"authenticationResultCode": "ValidCredentials",
				"brandLogoUri": "http://dev.virtualearth.net/Branding/logo_powered_by.png",
				"copyright": "Copyright © 2017 Microsoft and its suppliers. All rights reserved. This API cannot be accessed and the content and any results may not be used, reproduced or transmitted in any manner without express written permission from Microsoft Corporation.",
				"entityType": "Address",
				"matchCodes": [
					"Good"
				],
				"name": "64 Fox Run Cres, Richmond Hill, ON L4C 8A9, Canada",
				"statusCode": 200,
				"statusDescription": "OK",
				"traceId": "4704f807983443b48fdbfa29293907a0|BN20260231|7.7.0.0|",
				"addressLine": "64 Fox Run Cres",
				"adminDistrict": "ON",
				"adminDistrict2": "York",
				"countryRegion": "Canada",
				"formattedAddress": "64 Fox Run Cres, Richmond Hill, ON L4C 8A9, Canada",
				"locality": "Richmond Hill",
				"postalCode": "L4C 8A9"
			},
			"geometry": {
				"type": "Point",
				"coordinates": [
					-79.42613,
					43.8705
				]
			},
			"bbox": [
				-79.4276894,
				43.8693758,
				-79.4245706,
				43.8716242
			]
		}
	]
}
