{
	"type": "FeatureCollection",
	"features": [
		{
			"type": "Feature",
			"properties": {
				"confidence": 9,
				"authenticationResultCode": "ValidCredentials",
				"brandLogoUri": "http://dev.virtualearth.net/Branding/logo_powered_by.png",
				"copyright": "Copyright © 2017 Microsoft and its suppliers. All rights reserved. This API cannot be accessed and the content and any results may not be used, reproduced or transmitted in any manner without express written permission from Microsoft Corporation.",
				"entityType": "Address",
				"matchCodes": [
					"Good"
				],
				"name": "6415 75 St NW, Edmonton, AB T6E 0T3, Canada",
				"statusCode": 200,
				"statusDescription": "OK",
				"traceId": "5f8b41c4c37f4790bcbb54dae71bbd79|BN20290118|7.7.0.0|",
				"addressLine": "6415 75 St NW",
				"adminDistrict": "AB",
				"adminDistrict2": "Alberta",
				"countryRegion": "Canada",
				"formattedAddress": "6415 75 St NW, Edmonton, AB T6E 0T3, Canada",
				"locality": "Edmonton",
				"neighborhood": "Davies Industrial East",
				"postalCode": "T6E 0T3"
			},
			"geometry": {
				"type": "Point",
				"coordinates": [
					-113.4424851,
					53.5016387
				]
			},
			"bbox": [
				-113.4443751,
				53.5005145,
				-113.4405951,
				53.5027629
			]
		}
	]
}
