{
	"type": "FeatureCollection",
	"features": [
		{
			"type": "Feature",
			"properties": {
				"confidence": 9,
				"authenticationResultCode": "ValidCredentials",
				"brandLogoUri": "http://dev.virtualearth.net/Branding/logo_powered_by.png",
				"copyright": "Copyright © 2017 Microsoft and its suppliers. All rights reserved. This API cannot be accessed and the content and any results may not be used, reproduced or transmitted in any manner without express written permission from Microsoft Corporation.",
				"entityType": "Address",
				"matchCodes": [
					"Good"
				],
				"name": "645 Dupont St, Toronto, ON M6G 1Z4, Canada",
				"statusCode": 200,
				"statusDescription": "OK",
				"traceId": "b97324576f9942eaa90cc8e0c5afdcbc|BN20171457|7.7.0.0|",
				"addressLine": "645 Dupont St",
				"adminDistrict": "ON",
				"adminDistrict2": "Toronto",
				"countryRegion": "Canada",
				"formattedAddress": "645 Dupont St, Toronto, ON M6G 1Z4, Canada",
				"locality": "Toronto",
				"neighborhood": "Annex",
				"postalCode": "M6G 1Z4"
			},
			"geometry": {
				"type": "Point",
				"coordinates": [
					-79.42091,
					43.67157
				]
			},
			"bbox": [
				-79.4224642,
				43.6704458,
				-79.4193558,
				43.6726942
			]
		}
	]
}
