{
	"type": "FeatureCollection",
	"features": [
		{
			"type": "Feature",
			"properties": {
				"confidence": 9,
				"authenticationResultCode": "ValidCredentials",
				"brandLogoUri": "http://dev.virtualearth.net/Branding/logo_powered_by.png",
				"copyright": "Copyright © 2017 Microsoft and its suppliers. All rights reserved. This API cannot be accessed and the content and any results may not be used, reproduced or transmitted in any manner without express written permission from Microsoft Corporation.",
				"entityType": "Address",
				"matchCodes": [
					"Good"
				],
				"name": "6450 Kestrel Rd, Mississauga, ON L5T 1Z7, Canada",
				"statusCode": 200,
				"statusDescription": "OK",
				"traceId": "c6e110c6e006429ab6ff984f70abff8a|BN20200137|7.7.0.0|",
				"addressLine": "6450 Kestrel Rd",
				"adminDistrict": "ON",
				"adminDistrict2": "Peel",
				"countryRegion": "Canada",
				"formattedAddress": "6450 Kestrel Rd, Mississauga, ON L5T 1Z7, Canada",
				"locality": "Mississauga",
				"postalCode": "L5T 1Z7"
			},
			"geometry": {
				"type": "Point",
				"coordinates": [
					-79.67361,
					43.65236
				]
			},
			"bbox": [
				-79.6751637,
				43.6512358,
				-79.6720563,
				43.6534842
			]
		}
	]
}
