{
	"type": "FeatureCollection",
	"features": [
		{
			"type": "Feature",
			"properties": {
				"confidence": 9,
				"authenticationResultCode": "ValidCredentials",
				"brandLogoUri": "http://dev.virtualearth.net/Branding/logo_powered_by.png",
				"copyright": "Copyright © 2017 Microsoft and its suppliers. All rights reserved. This API cannot be accessed and the content and any results may not be used, reproduced or transmitted in any manner without express written permission from Microsoft Corporation.",
				"entityType": "Address",
				"matchCodes": [
					"Good"
				],
				"name": "6467 Nelson Ave, West Vancouver, BC V7W 2A5, Canada",
				"statusCode": 200,
				"statusDescription": "OK",
				"traceId": "e2916b8e532242e9b50401ae8d4e712f|BN20121763|7.7.0.0|",
				"addressLine": "6467 Nelson Ave",
				"adminDistrict": "BC",
				"adminDistrict2": "Greater Vancouver",
				"countryRegion": "Canada",
				"formattedAddress": "6467 Nelson Ave, West Vancouver, BC V7W 2A5, Canada",
				"locality": "West Vancouver",
				"neighborhood": "Horseshoe Bay",
				"postalCode": "V7W 2A5"
			},
			"geometry": {
				"type": "Point",
				"coordinates": [
					-123.27833,
					49.37239
				]
			},
			"bbox": [
				-123.2800564,
				49.3712658,
				-123.2766036,
				49.3735142
			]
		}
	]
}
