{
	"type": "FeatureCollection",
	"features": [
		{
			"type": "Feature",
			"properties": {
				"confidence": 9,
				"authenticationResultCode": "ValidCredentials",
				"brandLogoUri": "http://dev.virtualearth.net/Branding/logo_powered_by.png",
				"copyright": "Copyright © 2017 Microsoft and its suppliers. All rights reserved. This API cannot be accessed and the content and any results may not be used, reproduced or transmitted in any manner without express written permission from Microsoft Corporation.",
				"entityType": "Address",
				"matchCodes": [
					"Good"
				],
				"name": "65 MacKenzie Dr, Norman Wells, NT X0E, Canada",
				"statusCode": 200,
				"statusDescription": "OK",
				"traceId": "47579a08f7c04532a5b126370535ca6e|BN20160335|7.7.0.0|",
				"addressLine": "65 MacKenzie Dr",
				"adminDistrict": "NT",
				"adminDistrict2": "Northwest Territories",
				"countryRegion": "Canada",
				"formattedAddress": "65 MacKenzie Dr, Norman Wells, NT X0E, Canada",
				"locality": "Norman Wells",
				"postalCode": "X0E 0V0"
			},
			"geometry": {
				"type": "Point",
				"coordinates": [
					-126.8012163,
					65.2763131
				]
			},
			"bbox": [
				-126.8039041,
				65.275189,
				-126.7985285,
				65.2774373
			]
		}
	]
}
