{
	"type": "FeatureCollection",
	"features": [
		{
			"type": "Feature",
			"properties": {
				"confidence": 9,
				"authenticationResultCode": "ValidCredentials",
				"brandLogoUri": "http://dev.virtualearth.net/Branding/logo_powered_by.png",
				"copyright": "Copyright © 2017 Microsoft and its suppliers. All rights reserved. This API cannot be accessed and the content and any results may not be used, reproduced or transmitted in any manner without express written permission from Microsoft Corporation.",
				"entityType": "Address",
				"matchCodes": [
					"Good"
				],
				"name": "65 Spruce St, Tillsonburg, ON N4G 5C4, Canada",
				"statusCode": 200,
				"statusDescription": "OK",
				"traceId": "d8b821a5f0ad419b8840a406a8f2a396|BN20290118|7.7.0.0|",
				"addressLine": "65 Spruce St",
				"adminDistrict": "ON",
				"adminDistrict2": "Oxford",
				"countryRegion": "Canada",
				"formattedAddress": "65 Spruce St, Tillsonburg, ON N4G 5C4, Canada",
				"locality": "Tillsonburg",
				"postalCode": "N4G 5C4"
			},
			"geometry": {
				"type": "Point",
				"coordinates": [
					-80.715,
					42.85112
				]
			},
			"bbox": [
				-80.7165334,
				42.8499958,
				-80.7134666,
				42.8522442
			]
		}
	]
}
