{
	"type": "FeatureCollection",
	"features": [
		{
			"type": "Feature",
			"properties": {
				"confidence": 9,
				"authenticationResultCode": "ValidCredentials",
				"brandLogoUri": "http://dev.virtualearth.net/Branding/logo_powered_by.png",
				"copyright": "Copyright © 2017 Microsoft and its suppliers. All rights reserved. This API cannot be accessed and the content and any results may not be used, reproduced or transmitted in any manner without express written permission from Microsoft Corporation.",
				"entityType": "Address",
				"matchCodes": [
					"Good"
				],
				"name": "65 St Regis Cres N, North York, ON M3J 1Y9, Canada",
				"statusCode": 200,
				"statusDescription": "OK",
				"traceId": "c0a53e0892a44cee99f5ab88b4cc0a32|BN20160335|7.7.0.0|",
				"addressLine": "65 St Regis Cres N",
				"adminDistrict": "ON",
				"adminDistrict2": "Toronto",
				"countryRegion": "Canada",
				"formattedAddress": "65 St Regis Cres N, North York, ON M3J 1Y9, Canada",
				"locality": "Toronto",
				"neighborhood": "York University Heights",
				"postalCode": "M3J 1Y9"
			},
			"geometry": {
				"type": "Point",
				"coordinates": [
					-79.4832799,
					43.75632
				]
			},
			"bbox": [
				-79.4848363,
				43.7551958,
				-79.4817235,
				43.7574442
			]
		}
	]
}
