{
	"type": "FeatureCollection",
	"features": [
		{
			"type": "Feature",
			"properties": {
				"confidence": 9,
				"authenticationResultCode": "ValidCredentials",
				"brandLogoUri": "http://dev.virtualearth.net/Branding/logo_powered_by.png",
				"copyright": "Copyright © 2017 Microsoft and its suppliers. All rights reserved. This API cannot be accessed and the content and any results may not be used, reproduced or transmitted in any manner without express written permission from Microsoft Corporation.",
				"entityType": "Address",
				"matchCodes": [
					"Good"
				],
				"name": "6502 Yonge St, North York, ON M2M 3X4, Canada",
				"statusCode": 200,
				"statusDescription": "OK",
				"traceId": "a42866ff3ccb4608a18f7cf42b177923|BN20130621|7.7.0.0|",
				"addressLine": "6502 Yonge St",
				"adminDistrict": "ON",
				"adminDistrict2": "Toronto",
				"countryRegion": "Canada",
				"formattedAddress": "6502 Yonge St, North York, ON M2M 3X4, Canada",
				"locality": "Toronto",
				"neighborhood": "Newtonbrook West",
				"postalCode": "M2M 3X4"
			},
			"geometry": {
				"type": "Point",
				"coordinates": [
					-79.4198507,
					43.7965122
				]
			},
			"bbox": [
				-79.4214081,
				43.795388,
				-79.4182932,
				43.7976363
			]
		}
	]
}
