{
	"type": "FeatureCollection",
	"features": [
		{
			"type": "Feature",
			"properties": {
				"confidence": 9,
				"authenticationResultCode": "ValidCredentials",
				"brandLogoUri": "http://dev.virtualearth.net/Branding/logo_powered_by.png",
				"copyright": "Copyright © 2017 Microsoft and its suppliers. All rights reserved. This API cannot be accessed and the content and any results may not be used, reproduced or transmitted in any manner without express written permission from Microsoft Corporation.",
				"entityType": "Address",
				"matchCodes": [
					"Good"
				],
				"name": "6509 Airport Rd, Mississauga, ON L4V 1S7, Canada",
				"statusCode": 200,
				"statusDescription": "OK",
				"traceId": "069a26e5ce6844fc914bc711d4ae2bca|BN20130634|7.7.0.0|",
				"addressLine": "6509 Airport Rd",
				"adminDistrict": "ON",
				"adminDistrict2": "Peel",
				"countryRegion": "Canada",
				"formattedAddress": "6509 Airport Rd, Mississauga, ON L4V 1S7, Canada",
				"locality": "Mississauga",
				"neighborhood": "Malton",
				"postalCode": "L4V 1S7"
			},
			"geometry": {
				"type": "Point",
				"coordinates": [
					-79.62908,
					43.69465
				]
			},
			"bbox": [
				-79.6306348,
				43.6935258,
				-79.6275252,
				43.6957742
			]
		}
	]
}
