{
	"type": "FeatureCollection",
	"features": [
		{
			"type": "Feature",
			"properties": {
				"confidence": 9,
				"authenticationResultCode": "ValidCredentials",
				"brandLogoUri": "http://dev.virtualearth.net/Branding/logo_powered_by.png",
				"copyright": "Copyright © 2017 Microsoft and its suppliers. All rights reserved. This API cannot be accessed and the content and any results may not be used, reproduced or transmitted in any manner without express written permission from Microsoft Corporation.",
				"entityType": "Address",
				"matchCodes": [
					"Good"
				],
				"name": "6511 109 St NW, Edmonton, AB T6H 3B5, Canada",
				"statusCode": 200,
				"statusDescription": "OK",
				"traceId": "3806497895e1402db44460ff08a3794c|BN20130520|7.7.0.0|",
				"addressLine": "6511 109 St NW",
				"adminDistrict": "AB",
				"adminDistrict2": "Alberta",
				"countryRegion": "Canada",
				"formattedAddress": "6511 109 St NW, Edmonton, AB T6H 3B5, Canada",
				"locality": "Edmonton",
				"neighborhood": "Allendale",
				"postalCode": "T6H 3B5"
			},
			"geometry": {
				"type": "Point",
				"coordinates": [
					-113.51173,
					53.50271
				]
			},
			"bbox": [
				-113.51362,
				53.5015858,
				-113.50984,
				53.5038342
			]
		}
	]
}
