{
	"type": "FeatureCollection",
	"features": [
		{
			"type": "Feature",
			"properties": {
				"confidence": 9,
				"authenticationResultCode": "ValidCredentials",
				"brandLogoUri": "http://dev.virtualearth.net/Branding/logo_powered_by.png",
				"copyright": "Copyright © 2017 Microsoft and its suppliers. All rights reserved. This API cannot be accessed and the content and any results may not be used, reproduced or transmitted in any manner without express written permission from Microsoft Corporation.",
				"entityType": "Address",
				"matchCodes": [
					"Good"
				],
				"name": "6521 Derry Rd W, Milton, ON L9T 7W1, Canada",
				"statusCode": 200,
				"statusDescription": "OK",
				"traceId": "ef207cc90578466e8214f5d37074bcd6|BN20210145|7.7.0.0|",
				"addressLine": "6521 Derry Rd W",
				"adminDistrict": "ON",
				"adminDistrict2": "Halton",
				"countryRegion": "Canada",
				"formattedAddress": "6521 Derry Rd W, Milton, ON L9T 7W1, Canada",
				"locality": "Milton",
				"postalCode": "L9T 7W1"
			},
			"geometry": {
				"type": "Point",
				"coordinates": [
					-79.8790051,
					43.4907986
				]
			},
			"bbox": [
				-79.8805546,
				43.4896744,
				-79.8774556,
				43.4919227
			]
		}
	]
}
