{
	"type": "FeatureCollection",
	"features": [
		{
			"type": "Feature",
			"properties": {
				"confidence": 9,
				"authenticationResultCode": "ValidCredentials",
				"brandLogoUri": "http://dev.virtualearth.net/Branding/logo_powered_by.png",
				"copyright": "Copyright © 2017 Microsoft and its suppliers. All rights reserved. This API cannot be accessed and the content and any results may not be used, reproduced or transmitted in any manner without express written permission from Microsoft Corporation.",
				"entityType": "Address",
				"matchCodes": [
					"Good"
				],
				"name": "6523 Mississauga Rd, Mississauga, ON L5N 1A6, Canada",
				"statusCode": 200,
				"statusDescription": "OK",
				"traceId": "d365496af6f943ed96523680ceb18105|BN20190642|7.7.0.0|",
				"addressLine": "6523 Mississauga Rd",
				"adminDistrict": "ON",
				"adminDistrict2": "Peel",
				"countryRegion": "Canada",
				"formattedAddress": "6523 Mississauga Rd, Mississauga, ON L5N 1A6, Canada",
				"locality": "Mississauga",
				"neighborhood": "Meadowvale",
				"postalCode": "L5N 1A6"
			},
			"geometry": {
				"type": "Point",
				"coordinates": [
					-79.73669,
					43.59874
				]
			},
			"bbox": [
				-79.7382423,
				43.5976158,
				-79.7351377,
				43.5998642
			]
		}
	]
}
