{
	"type": "FeatureCollection",
	"features": [
		{
			"type": "Feature",
			"properties": {
				"confidence": 9,
				"authenticationResultCode": "ValidCredentials",
				"brandLogoUri": "http://dev.virtualearth.net/Branding/logo_powered_by.png",
				"copyright": "Copyright © 2017 Microsoft and its suppliers. All rights reserved. This API cannot be accessed and the content and any results may not be used, reproduced or transmitted in any manner without express written permission from Microsoft Corporation.",
				"entityType": "Address",
				"matchCodes": [
					"Good"
				],
				"name": "655 Creditstone Rd, Concord, ON L4K 5P9, Canada",
				"statusCode": 200,
				"statusDescription": "OK",
				"traceId": "d11ac1948b544dccaa002429e66bb7ad|BN20250135|7.7.0.0|",
				"addressLine": "655 Creditstone Rd",
				"adminDistrict": "ON",
				"adminDistrict2": "York",
				"countryRegion": "Canada",
				"formattedAddress": "655 Creditstone Rd, Concord, ON L4K 5P9, Canada",
				"locality": "Vaughan",
				"neighborhood": "Concord",
				"postalCode": "L4K 5P9"
			},
			"geometry": {
				"type": "Point",
				"coordinates": [
					-79.51794,
					43.8054
				]
			},
			"bbox": [
				-79.5194977,
				43.8042758,
				-79.5163823,
				43.8065242
			]
		}
	]
}
