{
	"type": "FeatureCollection",
	"features": [
		{
			"type": "Feature",
			"properties": {
				"confidence": 9,
				"authenticationResultCode": "ValidCredentials",
				"brandLogoUri": "http://dev.virtualearth.net/Branding/logo_powered_by.png",
				"copyright": "Copyright © 2017 Microsoft and its suppliers. All rights reserved. This API cannot be accessed and the content and any results may not be used, reproduced or transmitted in any manner without express written permission from Microsoft Corporation.",
				"entityType": "Address",
				"matchCodes": [
					"Good"
				],
				"name": "659 Speedvale Ave W, Guelph, ON N1K 1E6, Canada",
				"statusCode": 200,
				"statusDescription": "OK",
				"traceId": "7a37b3345d1a4534a50bd01fba26191d|BN20200137|7.7.0.0|",
				"addressLine": "659 Speedvale Ave W",
				"adminDistrict": "ON",
				"adminDistrict2": "Wellington",
				"countryRegion": "Canada",
				"formattedAddress": "659 Speedvale Ave W, Guelph, ON N1K 1E6, Canada",
				"locality": "Guelph",
				"neighborhood": "Willow West/Sugarbush",
				"postalCode": "N1K 1E6"
			},
			"geometry": {
				"type": "Point",
				"coordinates": [
					-80.3018836,
					43.5341534
				]
			},
			"bbox": [
				-80.3034342,
				43.5330293,
				-80.3003329,
				43.5352776
			]
		}
	]
}
