{
	"type": "FeatureCollection",
	"features": [
		{
			"type": "Feature",
			"properties": {
				"confidence": 9,
				"authenticationResultCode": "ValidCredentials",
				"brandLogoUri": "http://dev.virtualearth.net/Branding/logo_powered_by.png",
				"copyright": "Copyright © 2017 Microsoft and its suppliers. All rights reserved. This API cannot be accessed and the content and any results may not be used, reproduced or transmitted in any manner without express written permission from Microsoft Corporation.",
				"entityType": "Address",
				"matchCodes": [
					"Good"
				],
				"name": "66 Cowansview Rd, Cambridge, ON N1R 7N3, Canada",
				"statusCode": 200,
				"statusDescription": "OK",
				"traceId": "29d54b9f718242f2822c6de9faaeb42e|BN20220145|7.7.0.0|",
				"addressLine": "66 Cowansview Rd",
				"adminDistrict": "ON",
				"adminDistrict2": "Waterloo",
				"countryRegion": "Canada",
				"formattedAddress": "66 Cowansview Rd, Cambridge, ON N1R 7N3, Canada",
				"locality": "Cambridge",
				"neighborhood": "Greenway-Chaplin",
				"postalCode": "N1R 7N3"
			},
			"geometry": {
				"type": "Point",
				"coordinates": [
					-80.3056,
					43.39408
				]
			},
			"bbox": [
				-80.307147,
				43.3929558,
				-80.304053,
				43.3952042
			]
		}
	]
}
