{
	"type": "FeatureCollection",
	"features": [
		{
			"type": "Feature",
			"properties": {
				"confidence": 9,
				"authenticationResultCode": "ValidCredentials",
				"brandLogoUri": "http://dev.virtualearth.net/Branding/logo_powered_by.png",
				"copyright": "Copyright © 2017 Microsoft and its suppliers. All rights reserved. This API cannot be accessed and the content and any results may not be used, reproduced or transmitted in any manner without express written permission from Microsoft Corporation.",
				"entityType": "Address",
				"matchCodes": [
					"Good"
				],
				"name": "66 Lynn Dr, Dartmouth, NS B2Y 3V9, Canada",
				"statusCode": 200,
				"statusDescription": "OK",
				"traceId": "6c0e06f5920d401dac22a9fa3f95d754|BN20130631|7.7.0.0|",
				"addressLine": "66 Lynn Dr",
				"adminDistrict": "NS",
				"adminDistrict2": "Halifax",
				"countryRegion": "Canada",
				"formattedAddress": "66 Lynn Dr, Dartmouth, NS B2Y 3V9, Canada",
				"locality": "Halifax",
				"neighborhood": "Dartmouth",
				"postalCode": "B2Y 3V9"
			},
			"geometry": {
				"type": "Point",
				"coordinates": [
					-63.5414009,
					44.6644343
				]
			},
			"bbox": [
				-63.5429814,
				44.6633102,
				-63.5398203,
				44.6655585
			]
		}
	]
}
