{
	"type": "FeatureCollection",
	"features": [
		{
			"type": "Feature",
			"properties": {
				"confidence": 9,
				"authenticationResultCode": "ValidCredentials",
				"brandLogoUri": "http://dev.virtualearth.net/Branding/logo_powered_by.png",
				"copyright": "Copyright © 2017 Microsoft and its suppliers. All rights reserved. This API cannot be accessed and the content and any results may not be used, reproduced or transmitted in any manner without express written permission from Microsoft Corporation.",
				"entityType": "Address",
				"matchCodes": [
					"Good"
				],
				"name": "66 Meredith St E, Northeastern Manitoulin and Islands, ON P0P 1H0, Canada",
				"statusCode": 200,
				"statusDescription": "OK",
				"traceId": "e2bd1e476bfb42aca5babcd0d71fb923|BN20300154|7.7.0.0|",
				"addressLine": "66 Meredith St E",
				"adminDistrict": "ON",
				"adminDistrict2": "Manitoulin",
				"countryRegion": "Canada",
				"formattedAddress": "66 Meredith St E, Northeastern Manitoulin and Islands, ON P0P 1H0, Canada",
				"locality": "Northeastern Manitoulin and Islands",
				"neighborhood": "Little Current",
				"postalCode": "P0P 1H0"
			},
			"geometry": {
				"type": "Point",
				"coordinates": [
					-81.9212044,
					45.9780753
				]
			},
			"bbox": [
				-81.9228221,
				45.9769512,
				-81.9195868,
				45.9791995
			]
		}
	]
}
