{
	"type": "FeatureCollection",
	"features": [
		{
			"type": "Feature",
			"properties": {
				"confidence": 9,
				"authenticationResultCode": "ValidCredentials",
				"brandLogoUri": "http://dev.virtualearth.net/Branding/logo_powered_by.png",
				"copyright": "Copyright © 2017 Microsoft and its suppliers. All rights reserved. This API cannot be accessed and the content and any results may not be used, reproduced or transmitted in any manner without express written permission from Microsoft Corporation.",
				"entityType": "Address",
				"matchCodes": [
					"Good"
				],
				"name": "66 Park Ave, Ottawa, ON K2P 1B2, Canada",
				"statusCode": 200,
				"statusDescription": "OK",
				"traceId": "4d422ade4e334b3bb325aa349dd06f78|BN20200239|7.7.0.0|",
				"addressLine": "66 Park Ave",
				"adminDistrict": "ON",
				"adminDistrict2": "Ottawa",
				"countryRegion": "Canada",
				"formattedAddress": "66 Park Ave, Ottawa, ON K2P 1B2, Canada",
				"locality": "Ottawa",
				"neighborhood": "Centretown-Downtown",
				"postalCode": "K2P 1B2"
			},
			"geometry": {
				"type": "Point",
				"coordinates": [
					-75.68546,
					45.4136499
				]
			},
			"bbox": [
				-75.6870614,
				45.4125257,
				-75.6838586,
				45.4147741
			]
		}
	]
}
