{
	"type": "FeatureCollection",
	"features": [
		{
			"type": "Feature",
			"properties": {
				"confidence": 9,
				"authenticationResultCode": "ValidCredentials",
				"brandLogoUri": "http://dev.virtualearth.net/Branding/logo_powered_by.png",
				"copyright": "Copyright © 2017 Microsoft and its suppliers. All rights reserved. This API cannot be accessed and the content and any results may not be used, reproduced or transmitted in any manner without express written permission from Microsoft Corporation.",
				"entityType": "Address",
				"matchCodes": [
					"Good"
				],
				"name": "660 Golspie St, Winnipeg, MB R2K 2V1, Canada",
				"statusCode": 200,
				"statusDescription": "OK",
				"traceId": "b055945a640647b3be592457622ef4f5|BN20130422|7.7.0.0|",
				"addressLine": "660 Golspie St",
				"adminDistrict": "MB",
				"adminDistrict2": "Manitoba",
				"countryRegion": "Canada",
				"formattedAddress": "660 Golspie St, Winnipeg, MB R2K 2V1, Canada",
				"locality": "Winnipeg",
				"neighborhood": "Munroe West",
				"postalCode": "R2K 2V1"
			},
			"geometry": {
				"type": "Point",
				"coordinates": [
					-97.08889,
					49.91974
				]
			},
			"bbox": [
				-97.090636,
				49.9186158,
				-97.087144,
				49.9208642
			]
		}
	]
}
