{
	"type": "FeatureCollection",
	"features": [
		{
			"type": "Feature",
			"properties": {
				"confidence": 9,
				"authenticationResultCode": "ValidCredentials",
				"brandLogoUri": "http://dev.virtualearth.net/Branding/logo_powered_by.png",
				"copyright": "Copyright © 2017 Microsoft and its suppliers. All rights reserved. This API cannot be accessed and the content and any results may not be used, reproduced or transmitted in any manner without express written permission from Microsoft Corporation.",
				"entityType": "Address",
				"matchCodes": [
					"Good"
				],
				"name": "660 Boulevard de Quen, Alma, QC G8B 6H5, Canada",
				"statusCode": 200,
				"statusDescription": "OK",
				"traceId": "2e1bfbc629a545198057bc58f0ca6ace|BN20240423|7.7.0.0|",
				"addressLine": "660 Boulevard de Quen",
				"adminDistrict": "QC",
				"adminDistrict2": "Lac-St-Jean-Est",
				"countryRegion": "Canada",
				"formattedAddress": "660 Boulevard de Quen, Alma, QC G8B 6H5, Canada",
				"locality": "Alma",
				"postalCode": "G8B 6H5"
			},
			"geometry": {
				"type": "Point",
				"coordinates": [
					-71.64433,
					48.56164
				]
			},
			"bbox": [
				-71.6460286,
				48.5605158,
				-71.6426314,
				48.5627642
			]
		}
	]
}
