{
	"type": "FeatureCollection",
	"features": [
		{
			"type": "Feature",
			"properties": {
				"confidence": 7,
				"authenticationResultCode": "ValidCredentials",
				"brandLogoUri": "http://dev.virtualearth.net/Branding/logo_powered_by.png",
				"copyright": "Copyright © 2017 Microsoft and its suppliers. All rights reserved. This API cannot be accessed and the content and any results may not be used, reproduced or transmitted in any manner without express written permission from Microsoft Corporation.",
				"entityType": "PopulatedPlace",
				"matchCodes": [
					"UpHierarchy"
				],
				"name": "Hazelton, British Columbia, Canada",
				"statusCode": 200,
				"statusDescription": "OK",
				"traceId": "62cfcfd05c8848fd8381825280c5bc58|BN20121762|7.7.0.0|",
				"adminDistrict": "BC",
				"adminDistrict2": "Kitimat-Stikine",
				"countryRegion": "Canada",
				"formattedAddress": "Hazelton, British Columbia, Canada",
				"locality": "Hazelton"
			},
			"geometry": {
				"type": "Point",
				"coordinates": [
					-127.643867492676,
					55.2642517089844
				]
			},
			"bbox": [
				-127.653800964355,
				55.2461814880371,
				-127.628372192383,
				55.2724418640137
			]
		},
		{
			"type": "Feature",
			"properties": {
				"confidence": 7,
				"authenticationResultCode": "ValidCredentials",
				"brandLogoUri": "http://dev.virtualearth.net/Branding/logo_powered_by.png",
				"copyright": "Copyright © 2017 Microsoft and its suppliers. All rights reserved. This API cannot be accessed and the content and any results may not be used, reproduced or transmitted in any manner without express written permission from Microsoft Corporation.",
				"entityType": "Postcode1",
				"matchCodes": [
					"UpHierarchy"
				],
				"name": "Kitimat-Stikine, V0J 1Y5, Canada",
				"statusCode": 200,
				"statusDescription": "OK",
				"traceId": "62cfcfd05c8848fd8381825280c5bc58|BN20121762|7.7.0.0|",
				"adminDistrict": "BC",
				"adminDistrict2": "Kitimat-Stikine",
				"countryRegion": "Canada",
				"formattedAddress": "Kitimat-Stikine, V0J 1Y5, Canada",
				"locality": "Kitimat-Stikine",
				"postalCode": "V0J 1Y5"
			},
			"geometry": {
				"type": "Point",
				"coordinates": [
					-127.684425354004,
					55.4732933044434
				]
			},
			"bbox": [
				-127.693511228125,
				55.4694305868727,
				-127.675339479883,
				55.477156022014
			]
		},
		{
			"type": "Feature",
			"properties": {
				"confidence": 1,
				"authenticationResultCode": "ValidCredentials",
				"brandLogoUri": "http://dev.virtualearth.net/Branding/logo_powered_by.png",
				"copyright": "Copyright © 2017 Microsoft and its suppliers. All rights reserved. This API cannot be accessed and the content and any results may not be used, reproduced or transmitted in any manner without express written permission from Microsoft Corporation.",
				"entityType": "Postcode2",
				"matchCodes": [
					"UpHierarchy"
				],
				"name": "668",
				"statusCode": 200,
				"statusDescription": "OK",
				"traceId": "62cfcfd05c8848fd8381825280c5bc58|BN20121762|7.7.0.0|",
				"countryRegion": "United States",
				"formattedAddress": "668",
				"postalCode": "668"
			},
			"geometry": {
				"type": "Point",
				"coordinates": [
					-96.53662109375,
					38.4483032226563
				]
			},
			"bbox": [
				-97.2623519897461,
				37.8300590515137,
				-95.5077819824219,
				39.0665512084961
			]
		}
	]
}
