{
	"type": "FeatureCollection",
	"features": [
		{
			"type": "Feature",
			"properties": {
				"confidence": 9,
				"authenticationResultCode": "ValidCredentials",
				"brandLogoUri": "http://dev.virtualearth.net/Branding/logo_powered_by.png",
				"copyright": "Copyright © 2017 Microsoft and its suppliers. All rights reserved. This API cannot be accessed and the content and any results may not be used, reproduced or transmitted in any manner without express written permission from Microsoft Corporation.",
				"entityType": "Address",
				"matchCodes": [
					"Good"
				],
				"name": "6701 Boulevard Newman, La Salle, QC H8N 3E4, Canada",
				"statusCode": 200,
				"statusDescription": "OK",
				"traceId": "3f63456c21074cef94b3ef76be51755c|BN20130423|7.7.0.0|",
				"addressLine": "6701 Boulevard Newman",
				"adminDistrict": "QC",
				"adminDistrict2": "Montreal",
				"countryRegion": "Canada",
				"formattedAddress": "6701 Boulevard Newman, La Salle, QC H8N 3E4, Canada",
				"locality": "Montreal",
				"neighborhood": "La Salle",
				"postalCode": "H8N 3E4"
			},
			"geometry": {
				"type": "Point",
				"coordinates": [
					-73.60637,
					45.4514799
				]
			},
			"bbox": [
				-73.6079725,
				45.4503557,
				-73.6047675,
				45.4526041
			]
		}
	]
}
