{
	"type": "FeatureCollection",
	"features": [
		{
			"type": "Feature",
			"properties": {
				"confidence": 9,
				"authenticationResultCode": "ValidCredentials",
				"brandLogoUri": "http://dev.virtualearth.net/Branding/logo_powered_by.png",
				"copyright": "Copyright © 2017 Microsoft and its suppliers. All rights reserved. This API cannot be accessed and the content and any results may not be used, reproduced or transmitted in any manner without express written permission from Microsoft Corporation.",
				"entityType": "Address",
				"matchCodes": [
					"Good"
				],
				"name": "679 S Railway St SE, Medicine Hat, AB T1A 2V8, Canada",
				"statusCode": 200,
				"statusDescription": "OK",
				"traceId": "276fb0fdcfd64e109fb0443209593823|BN20130442|7.7.0.0|",
				"addressLine": "679 S Railway St SE",
				"adminDistrict": "AB",
				"adminDistrict2": "Alberta",
				"countryRegion": "Canada",
				"formattedAddress": "679 S Railway St SE, Medicine Hat, AB T1A 2V8, Canada",
				"locality": "Medicine Hat",
				"postalCode": "T1A 2V8"
			},
			"geometry": {
				"type": "Point",
				"coordinates": [
					-110.66666,
					50.03305
				]
			},
			"bbox": [
				-110.6684101,
				50.0319258,
				-110.6649099,
				50.0341742
			]
		}
	]
}
