{
	"type": "FeatureCollection",
	"features": [
		{
			"type": "Feature",
			"properties": {
				"confidence": 9,
				"authenticationResultCode": "ValidCredentials",
				"brandLogoUri": "http://dev.virtualearth.net/Branding/logo_powered_by.png",
				"copyright": "Copyright © 2017 Microsoft and its suppliers. All rights reserved. This API cannot be accessed and the content and any results may not be used, reproduced or transmitted in any manner without express written permission from Microsoft Corporation.",
				"entityType": "Address",
				"matchCodes": [
					"Good"
				],
				"name": "680 Waterloo St, London, ON N6A 0B3, Canada",
				"statusCode": 200,
				"statusDescription": "OK",
				"traceId": "5d9d257ab75e4d73b4e4baf334a776e8|BN20260231|7.7.0.0|",
				"addressLine": "680 Waterloo St",
				"adminDistrict": "ON",
				"adminDistrict2": "Middlesex",
				"countryRegion": "Canada",
				"formattedAddress": "680 Waterloo St, London, ON N6A 0B3, Canada",
				"locality": "London",
				"neighborhood": "Central London",
				"postalCode": "N6A 0B3"
			},
			"geometry": {
				"type": "Point",
				"coordinates": [
					-81.2463,
					42.9943
				]
			},
			"bbox": [
				-81.2478369,
				42.9931758,
				-81.2447631,
				42.9954242
			]
		}
	]
}
