{
	"type": "FeatureCollection",
	"features": [
		{
			"type": "Feature",
			"properties": {
				"confidence": 9,
				"authenticationResultCode": "ValidCredentials",
				"brandLogoUri": "http://dev.virtualearth.net/Branding/logo_powered_by.png",
				"copyright": "Copyright © 2017 Microsoft and its suppliers. All rights reserved. This API cannot be accessed and the content and any results may not be used, reproduced or transmitted in any manner without express written permission from Microsoft Corporation.",
				"entityType": "Address",
				"matchCodes": [
					"Good"
				],
				"name": "6852 Professional Ct, Mississauga, ON L4V 1X6, Canada",
				"statusCode": 200,
				"statusDescription": "OK",
				"traceId": "052981f48ac7445799cbdb8cccdff0cb|BN20240253|7.7.0.0|",
				"addressLine": "6852 Professional Ct",
				"adminDistrict": "ON",
				"adminDistrict2": "Peel",
				"countryRegion": "Canada",
				"formattedAddress": "6852 Professional Ct, Mississauga, ON L4V 1X6, Canada",
				"locality": "Mississauga",
				"neighborhood": "Malton",
				"postalCode": "L4V 1X6"
			},
			"geometry": {
				"type": "Point",
				"coordinates": [
					-79.63169,
					43.70784
				]
			},
			"bbox": [
				-79.6332451,
				43.7067158,
				-79.6301349,
				43.7089642
			]
		}
	]
}
