{
	"type": "FeatureCollection",
	"features": [
		{
			"type": "Feature",
			"properties": {
				"confidence": 9,
				"authenticationResultCode": "ValidCredentials",
				"brandLogoUri": "http://dev.virtualearth.net/Branding/logo_powered_by.png",
				"copyright": "Copyright © 2017 Microsoft and its suppliers. All rights reserved. This API cannot be accessed and the content and any results may not be used, reproduced or transmitted in any manner without express written permission from Microsoft Corporation.",
				"entityType": "Address",
				"matchCodes": [
					"Good"
				],
				"name": "692 McKay St, Kingston, ON K7M 7G2, Canada",
				"statusCode": 200,
				"statusDescription": "OK",
				"traceId": "df3a21885a0e4091a292998d2064dcd8|BN20171457|7.7.0.0|",
				"addressLine": "692 McKay St",
				"adminDistrict": "ON",
				"adminDistrict2": "Frontenac",
				"countryRegion": "Canada",
				"formattedAddress": "692 McKay St, Kingston, ON K7M 7G2, Canada",
				"locality": "Kingston",
				"neighborhood": "Gardiners",
				"postalCode": "K7M 7G2"
			},
			"geometry": {
				"type": "Point",
				"coordinates": [
					-76.576089,
					44.2466032
				]
			},
			"bbox": [
				-76.5776583,
				44.2454791,
				-76.5745197,
				44.2477274
			]
		}
	]
}
