{
	"type": "FeatureCollection",
	"features": [
		{
			"type": "Feature",
			"properties": {
				"confidence": 9,
				"authenticationResultCode": "ValidCredentials",
				"brandLogoUri": "http://dev.virtualearth.net/Branding/logo_powered_by.png",
				"copyright": "Copyright © 2017 Microsoft and its suppliers. All rights reserved. This API cannot be accessed and the content and any results may not be used, reproduced or transmitted in any manner without express written permission from Microsoft Corporation.",
				"entityType": "Address",
				"matchCodes": [
					"Good"
				],
				"name": "6939 Line 26, Staffa, ON N0K 1Y0, Canada",
				"statusCode": 200,
				"statusDescription": "OK",
				"traceId": "fda94b01646d42c28f127c20a873612b|BN20130422|7.7.0.0|",
				"addressLine": "6939 Line 26",
				"adminDistrict": "ON",
				"adminDistrict2": "Perth",
				"countryRegion": "Canada",
				"formattedAddress": "6939 Line 26, Staffa, ON N0K 1Y0, Canada",
				"locality": "West Perth",
				"neighborhood": "Staffa",
				"postalCode": "N0K 1Y0"
			},
			"geometry": {
				"type": "Point",
				"coordinates": [
					-81.31762,
					43.455713
				]
			},
			"bbox": [
				-81.3191686,
				43.4545889,
				-81.3160714,
				43.4568372
			]
		}
	]
}
