{
	"type": "FeatureCollection",
	"features": [
		{
			"type": "Feature",
			"properties": {
				"confidence": 9,
				"authenticationResultCode": "ValidCredentials",
				"brandLogoUri": "http://dev.virtualearth.net/Branding/logo_powered_by.png",
				"copyright": "Copyright © 2017 Microsoft and its suppliers. All rights reserved. This API cannot be accessed and the content and any results may not be used, reproduced or transmitted in any manner without express written permission from Microsoft Corporation.",
				"entityType": "Address",
				"matchCodes": [
					"Good"
				],
				"name": "6939 68 Ave NW, Edmonton, AB T6B 3E3, Canada",
				"statusCode": 200,
				"statusDescription": "OK",
				"traceId": "abfab5fb4e3648b8b2b66b2edefa54bd|BN20130632|7.7.0.0|",
				"addressLine": "6939 68 Ave NW",
				"adminDistrict": "AB",
				"adminDistrict2": "Alberta",
				"countryRegion": "Canada",
				"formattedAddress": "6939 68 Ave NW, Edmonton, AB T6B 3E3, Canada",
				"locality": "Edmonton",
				"neighborhood": "Davies Industrial East",
				"postalCode": "T6B 3E3"
			},
			"geometry": {
				"type": "Point",
				"coordinates": [
					-113.434339,
					53.5048951
				]
			},
			"bbox": [
				-113.4362291,
				53.503771,
				-113.4324488,
				53.5060193
			]
		}
	]
}
