{
	"type": "FeatureCollection",
	"features": [
		{
			"type": "Feature",
			"properties": {
				"confidence": 9,
				"authenticationResultCode": "ValidCredentials",
				"brandLogoUri": "http://dev.virtualearth.net/Branding/logo_powered_by.png",
				"copyright": "Copyright © 2017 Microsoft and its suppliers. All rights reserved. This API cannot be accessed and the content and any results may not be used, reproduced or transmitted in any manner without express written permission from Microsoft Corporation.",
				"entityType": "Address",
				"matchCodes": [
					"Good"
				],
				"name": "6950 Tomken Rd, Mississauga, ON L5T 2S3, Canada",
				"statusCode": 200,
				"statusDescription": "OK",
				"traceId": "cd9dfff1bef049abacaf615b2bf3c170|BN20130621|7.7.0.0|",
				"addressLine": "6950 Tomken Rd",
				"adminDistrict": "ON",
				"adminDistrict2": "Peel",
				"countryRegion": "Canada",
				"formattedAddress": "6950 Tomken Rd, Mississauga, ON L5T 2S3, Canada",
				"locality": "Mississauga",
				"postalCode": "L5T 2S3"
			},
			"geometry": {
				"type": "Point",
				"coordinates": [
					-79.68434,
					43.66428
				]
			},
			"bbox": [
				-79.685894,
				43.6631558,
				-79.682786,
				43.6654042
			]
		}
	]
}
