{
	"type": "FeatureCollection",
	"features": [
		{
			"type": "Feature",
			"properties": {
				"confidence": 9,
				"authenticationResultCode": "ValidCredentials",
				"brandLogoUri": "http://dev.virtualearth.net/Branding/logo_powered_by.png",
				"copyright": "Copyright © 2017 Microsoft and its suppliers. All rights reserved. This API cannot be accessed and the content and any results may not be used, reproduced or transmitted in any manner without express written permission from Microsoft Corporation.",
				"entityType": "Address",
				"matchCodes": [
					"Good"
				],
				"name": "7 Great North Rd, Parry Sound, ON P2A 2X8, Canada",
				"statusCode": 200,
				"statusDescription": "OK",
				"traceId": "ed57e8e6913b460ea8281b605f56d4be|BN20130532|7.7.0.0|",
				"addressLine": "7 Great North Rd",
				"adminDistrict": "ON",
				"adminDistrict2": "Parry Sound",
				"countryRegion": "Canada",
				"formattedAddress": "7 Great North Rd, Parry Sound, ON P2A 2X8, Canada",
				"locality": "Parry Sound",
				"postalCode": "P2A 2X8"
			},
			"geometry": {
				"type": "Point",
				"coordinates": [
					-80.03055,
					45.34298
				]
			},
			"bbox": [
				-80.0321494,
				45.3418558,
				-80.0289506,
				45.3441042
			]
		}
	]
}
