{
	"type": "FeatureCollection",
	"features": [
		{
			"type": "Feature",
			"properties": {
				"confidence": 9,
				"authenticationResultCode": "ValidCredentials",
				"brandLogoUri": "http://dev.virtualearth.net/Branding/logo_powered_by.png",
				"copyright": "Copyright © 2017 Microsoft and its suppliers. All rights reserved. This API cannot be accessed and the content and any results may not be used, reproduced or transmitted in any manner without express written permission from Microsoft Corporation.",
				"entityType": "Address",
				"matchCodes": [
					"Good"
				],
				"name": "7 New Hampshire Ct, Brampton, ON L6S 0B9, Canada",
				"statusCode": 200,
				"statusDescription": "OK",
				"traceId": "44627ba391bf4b858779cd87465afde3|BN20130620|7.7.0.0|",
				"addressLine": "7 New Hampshire Ct",
				"adminDistrict": "ON",
				"adminDistrict2": "Peel",
				"countryRegion": "Canada",
				"formattedAddress": "7 New Hampshire Ct, Brampton, ON L6S 0B9, Canada",
				"locality": "Brampton",
				"neighborhood": "Bramalea",
				"postalCode": "L6S 0B9"
			},
			"geometry": {
				"type": "Point",
				"coordinates": [
					-79.74961,
					43.72157
				]
			},
			"bbox": [
				-79.7511655,
				43.7204458,
				-79.7480545,
				43.7226942
			]
		}
	]
}
