{
	"type": "FeatureCollection",
	"features": [
		{
			"type": "Feature",
			"properties": {
				"confidence": 9,
				"authenticationResultCode": "ValidCredentials",
				"brandLogoUri": "http://dev.virtualearth.net/Branding/logo_powered_by.png",
				"copyright": "Copyright © 2017 Microsoft and its suppliers. All rights reserved. This API cannot be accessed and the content and any results may not be used, reproduced or transmitted in any manner without express written permission from Microsoft Corporation.",
				"entityType": "Address",
				"matchCodes": [
					"Good"
				],
				"name": "7 Tristan Ct, Nepean, ON K2E 8A4, Canada",
				"statusCode": 200,
				"statusDescription": "OK",
				"traceId": "9c640369fed5438c94358a54f9872110|BN20320521|7.7.0.0|",
				"addressLine": "7 Tristan Ct",
				"adminDistrict": "ON",
				"adminDistrict2": "Ottawa",
				"countryRegion": "Canada",
				"formattedAddress": "7 Tristan Ct, Nepean, ON K2E 8A4, Canada",
				"locality": "Ottawa",
				"neighborhood": "Nepean",
				"postalCode": "K2E 8A4"
			},
			"geometry": {
				"type": "Point",
				"coordinates": [
					-75.71299,
					45.33217
				]
			},
			"bbox": [
				-75.7145891,
				45.3310458,
				-75.7113909,
				45.3332942
			]
		}
	]
}
