{
	"type": "FeatureCollection",
	"features": [
		{
			"type": "Feature",
			"properties": {
				"confidence": 9,
				"authenticationResultCode": "ValidCredentials",
				"brandLogoUri": "http://dev.virtualearth.net/Branding/logo_powered_by.png",
				"copyright": "Copyright © 2017 Microsoft and its suppliers. All rights reserved. This API cannot be accessed and the content and any results may not be used, reproduced or transmitted in any manner without express written permission from Microsoft Corporation.",
				"entityType": "Address",
				"matchCodes": [
					"Good"
				],
				"name": "70 Burwell Rd, St Thomas, ON N5P 3R7, Canada",
				"statusCode": 200,
				"statusDescription": "OK",
				"traceId": "299f9452efcd4c3c9730a6e13b7f6402|BN20240253|7.7.0.0|",
				"addressLine": "70 Burwell Rd",
				"adminDistrict": "ON",
				"adminDistrict2": "Elgin",
				"countryRegion": "Canada",
				"formattedAddress": "70 Burwell Rd, St Thomas, ON N5P 3R7, Canada",
				"locality": "St Thomas",
				"postalCode": "N5P 3R7"
			},
			"geometry": {
				"type": "Point",
				"coordinates": [
					-81.1658957,
					42.7845693
				]
			},
			"bbox": [
				-81.1674274,
				42.7834452,
				-81.164364,
				42.7856935
			]
		}
	]
}
