{
	"type": "FeatureCollection",
	"features": [
		{
			"type": "Feature",
			"properties": {
				"confidence": 9,
				"authenticationResultCode": "ValidCredentials",
				"brandLogoUri": "http://dev.virtualearth.net/Branding/logo_powered_by.png",
				"copyright": "Copyright © 2017 Microsoft and its suppliers. All rights reserved. This API cannot be accessed and the content and any results may not be used, reproduced or transmitted in any manner without express written permission from Microsoft Corporation.",
				"entityType": "Address",
				"matchCodes": [
					"Good"
				],
				"name": "70 Wadsworth St, Brantford, ON N3T 3V9, Canada",
				"statusCode": 200,
				"statusDescription": "OK",
				"traceId": "8ccb9b97a14e4195a1e15cdba62c1a32|BN20130719|7.7.0.0|",
				"addressLine": "70 Wadsworth St",
				"adminDistrict": "ON",
				"adminDistrict2": "Brant",
				"countryRegion": "Canada",
				"formattedAddress": "70 Wadsworth St, Brantford, ON N3T 3V9, Canada",
				"locality": "Brantford",
				"postalCode": "N3T 3V9"
			},
			"geometry": {
				"type": "Point",
				"coordinates": [
					-80.26956,
					43.14708
				]
			},
			"bbox": [
				-80.2711008,
				43.1459558,
				-80.2680192,
				43.1482042
			]
		}
	]
}
