{
	"type": "FeatureCollection",
	"features": [
		{
			"type": "Feature",
			"properties": {
				"confidence": 9,
				"authenticationResultCode": "ValidCredentials",
				"brandLogoUri": "http://dev.virtualearth.net/Branding/logo_powered_by.png",
				"copyright": "Copyright © 2017 Microsoft and its suppliers. All rights reserved. This API cannot be accessed and the content and any results may not be used, reproduced or transmitted in any manner without express written permission from Microsoft Corporation.",
				"entityType": "Address",
				"matchCodes": [
					"Good"
				],
				"name": "700 King St W, Toronto, ON M5V 2Y6, Canada",
				"statusCode": 200,
				"statusDescription": "OK",
				"traceId": "c78d94e108754aa88521c5139360403b|BN20200239|7.7.0.0|",
				"addressLine": "700 King St W",
				"adminDistrict": "ON",
				"adminDistrict2": "Toronto",
				"countryRegion": "Canada",
				"formattedAddress": "700 King St W, Toronto, ON M5V 2Y6, Canada",
				"locality": "Toronto",
				"neighborhood": "Niagara",
				"postalCode": "M5V 2Y6"
			},
			"geometry": {
				"type": "Point",
				"coordinates": [
					-79.40322,
					43.64412
				]
			},
			"bbox": [
				-79.4047735,
				43.6429958,
				-79.4016665,
				43.6452442
			]
		}
	]
}
