{
	"type": "FeatureCollection",
	"features": [
		{
			"type": "Feature",
			"properties": {
				"confidence": 9,
				"authenticationResultCode": "ValidCredentials",
				"brandLogoUri": "http://dev.virtualearth.net/Branding/logo_powered_by.png",
				"copyright": "Copyright © 2017 Microsoft and its suppliers. All rights reserved. This API cannot be accessed and the content and any results may not be used, reproduced or transmitted in any manner without express written permission from Microsoft Corporation.",
				"entityType": "Address",
				"matchCodes": [
					"Good"
				],
				"name": "700 9 St SW, Calgary, AB T2P 2B5, Canada",
				"statusCode": 200,
				"statusDescription": "OK",
				"traceId": "b4d8876e9d3f4e87913d2d3eef8d820e|BN20171457|7.7.0.0|",
				"addressLine": "700 9 St SW",
				"adminDistrict": "AB",
				"adminDistrict2": "Alberta",
				"countryRegion": "Canada",
				"formattedAddress": "700 9 St SW, Calgary, AB T2P 2B5, Canada",
				"locality": "Calgary",
				"neighborhood": "Downtown",
				"postalCode": "T2P 2B5"
			},
			"geometry": {
				"type": "Point",
				"coordinates": [
					-114.08313,
					51.04675
				]
			},
			"bbox": [
				-114.0849181,
				51.0456258,
				-114.0813419,
				51.0478742
			]
		}
	]
}
