{
	"type": "FeatureCollection",
	"features": [
		{
			"type": "Feature",
			"properties": {
				"confidence": 9,
				"authenticationResultCode": "ValidCredentials",
				"brandLogoUri": "http://dev.virtualearth.net/Branding/logo_powered_by.png",
				"copyright": "Copyright © 2017 Microsoft and its suppliers. All rights reserved. This API cannot be accessed and the content and any results may not be used, reproduced or transmitted in any manner without express written permission from Microsoft Corporation.",
				"entityType": "Address",
				"matchCodes": [
					"Good"
				],
				"name": "7015 Curragh Ave, Burnaby, BC V5J 4V6, Canada",
				"statusCode": 200,
				"statusDescription": "OK",
				"traceId": "8452cb6f10c8430d8d34b25053f07c98|BN20121763|7.7.0.0|",
				"addressLine": "7015 Curragh Ave",
				"adminDistrict": "BC",
				"adminDistrict2": "Greater Vancouver",
				"countryRegion": "Canada",
				"formattedAddress": "7015 Curragh Ave, Burnaby, BC V5J 4V6, Canada",
				"locality": "Burnaby",
				"neighborhood": "Windsor",
				"postalCode": "V5J 4V6"
			},
			"geometry": {
				"type": "Point",
				"coordinates": [
					-122.97524,
					49.2195899
				]
			},
			"bbox": [
				-122.9769611,
				49.2184657,
				-122.9735189,
				49.2207141
			]
		}
	]
}
