{
	"type": "FeatureCollection",
	"features": [
		{
			"type": "Feature",
			"properties": {
				"confidence": 9,
				"authenticationResultCode": "ValidCredentials",
				"brandLogoUri": "http://dev.virtualearth.net/Branding/logo_powered_by.png",
				"copyright": "Copyright © 2017 Microsoft and its suppliers. All rights reserved. This API cannot be accessed and the content and any results may not be used, reproduced or transmitted in any manner without express written permission from Microsoft Corporation.",
				"entityType": "Address",
				"matchCodes": [
					"Good"
				],
				"name": "704 6th St E, Owen Sound, ON N4K 1G7, Canada",
				"statusCode": 200,
				"statusDescription": "OK",
				"traceId": "dfe38bbcff114d1ab970270c4f35283c|BN20130631|7.7.0.0|",
				"addressLine": "704 6th St E",
				"adminDistrict": "ON",
				"adminDistrict2": "Grey",
				"countryRegion": "Canada",
				"formattedAddress": "704 6th St E, Owen Sound, ON N4K 1G7, Canada",
				"locality": "Owen Sound",
				"postalCode": "N4K 1G7"
			},
			"geometry": {
				"type": "Point",
				"coordinates": [
					-80.93103,
					44.56169
				]
			},
			"bbox": [
				-80.9326078,
				44.5605658,
				-80.9294522,
				44.5628142
			]
		}
	]
}
