{
	"type": "FeatureCollection",
	"features": [
		{
			"type": "Feature",
			"properties": {
				"confidence": 9,
				"authenticationResultCode": "ValidCredentials",
				"brandLogoUri": "http://dev.virtualearth.net/Branding/logo_powered_by.png",
				"copyright": "Copyright © 2017 Microsoft and its suppliers. All rights reserved. This API cannot be accessed and the content and any results may not be used, reproduced or transmitted in any manner without express written permission from Microsoft Corporation.",
				"entityType": "Address",
				"matchCodes": [
					"Good"
				],
				"name": "7045 Auburn Rd, Milton, ON L9E 0T6, Canada",
				"statusCode": 200,
				"statusDescription": "OK",
				"traceId": "831af431efce4083940674c973913801|BN20130530|7.7.0.0|",
				"addressLine": "7045 Auburn Rd",
				"adminDistrict": "ON",
				"adminDistrict2": "Halton",
				"countryRegion": "Canada",
				"formattedAddress": "7045 Auburn Rd, Milton, ON L9E 0T6, Canada",
				"locality": "Milton",
				"postalCode": "L9E 0T6"
			},
			"geometry": {
				"type": "Point",
				"coordinates": [
					-79.8227991,
					43.5681651
				]
			},
			"bbox": [
				-79.8243506,
				43.5670409,
				-79.8212476,
				43.5692892
			]
		}
	]
}
