{
	"type": "FeatureCollection",
	"features": [
		{
			"type": "Feature",
			"properties": {
				"confidence": 9,
				"authenticationResultCode": "ValidCredentials",
				"brandLogoUri": "http://dev.virtualearth.net/Branding/logo_powered_by.png",
				"copyright": "Copyright © 2017 Microsoft and its suppliers. All rights reserved. This API cannot be accessed and the content and any results may not be used, reproduced or transmitted in any manner without express written permission from Microsoft Corporation.",
				"entityType": "Address",
				"matchCodes": [
					"Good"
				],
				"name": "705 Vale Ave, Newmarket, ON L3Y 2L2, Canada",
				"statusCode": 200,
				"statusDescription": "OK",
				"traceId": "902d3bb81e2244b9a27738cb754319ba|BN20190642|7.7.0.0|",
				"addressLine": "705 Vale Ave",
				"adminDistrict": "ON",
				"adminDistrict2": "York",
				"countryRegion": "Canada",
				"formattedAddress": "705 Vale Ave, Newmarket, ON L3Y 2L2, Canada",
				"locality": "Newmarket",
				"postalCode": "L3Y 2L2"
			},
			"geometry": {
				"type": "Point",
				"coordinates": [
					-79.4473508,
					44.057104
				]
			},
			"bbox": [
				-79.448915,
				44.0559798,
				-79.4457865,
				44.0582281
			]
		}
	]
}
