{
	"type": "FeatureCollection",
	"features": [
		{
			"type": "Feature",
			"properties": {
				"confidence": 9,
				"authenticationResultCode": "ValidCredentials",
				"brandLogoUri": "http://dev.virtualearth.net/Branding/logo_powered_by.png",
				"copyright": "Copyright © 2017 Microsoft and its suppliers. All rights reserved. This API cannot be accessed and the content and any results may not be used, reproduced or transmitted in any manner without express written permission from Microsoft Corporation.",
				"entityType": "Address",
				"matchCodes": [
					"Good"
				],
				"name": "7050 Buller Ave, Burnaby, BC V5J 4S4, Canada",
				"statusCode": 200,
				"statusDescription": "OK",
				"traceId": "5a5d1db468044a68a5d6c91160b8cbe5|BN20181720|7.7.0.0|",
				"addressLine": "7050 Buller Ave",
				"adminDistrict": "BC",
				"adminDistrict2": "Greater Vancouver",
				"countryRegion": "Canada",
				"formattedAddress": "7050 Buller Ave, Burnaby, BC V5J 4S4, Canada",
				"locality": "Burnaby",
				"neighborhood": "Windsor",
				"postalCode": "V5J 4S4"
			},
			"geometry": {
				"type": "Point",
				"coordinates": [
					-122.9772815,
					49.2196848
				]
			},
			"bbox": [
				-122.9790026,
				49.2185606,
				-122.9755604,
				49.2208089
			]
		}
	]
}
