{
	"type": "FeatureCollection",
	"features": [
		{
			"type": "Feature",
			"properties": {
				"confidence": 9,
				"authenticationResultCode": "ValidCredentials",
				"brandLogoUri": "http://dev.virtualearth.net/Branding/logo_powered_by.png",
				"copyright": "Copyright © 2017 Microsoft and its suppliers. All rights reserved. This API cannot be accessed and the content and any results may not be used, reproduced or transmitted in any manner without express written permission from Microsoft Corporation.",
				"entityType": "Address",
				"matchCodes": [
					"Good"
				],
				"name": "7067 Wellington Road 124, Guelph, ON N1H 6J3, Canada",
				"statusCode": 200,
				"statusDescription": "OK",
				"traceId": "5cf84f626b574b03b4bc57a745a25a96|BN20130721|7.7.0.0|",
				"addressLine": "7067 Wellington Road 124",
				"adminDistrict": "ON",
				"adminDistrict2": "Wellington",
				"countryRegion": "Canada",
				"formattedAddress": "7067 Wellington Road 124, Guelph, ON N1H 6J3, Canada",
				"locality": "Guelph/Eramosa",
				"neighborhood": "Guelph",
				"postalCode": "N1H 6J3"
			},
			"geometry": {
				"type": "Point",
				"coordinates": [
					-80.2798082,
					43.494085
				]
			},
			"bbox": [
				-80.2813578,
				43.4929609,
				-80.2782586,
				43.4952092
			]
		}
	]
}
