{
	"type": "FeatureCollection",
	"features": [
		{
			"type": "Feature",
			"properties": {
				"confidence": 9,
				"authenticationResultCode": "ValidCredentials",
				"brandLogoUri": "http://dev.virtualearth.net/Branding/logo_powered_by.png",
				"copyright": "Copyright © 2017 Microsoft and its suppliers. All rights reserved. This API cannot be accessed and the content and any results may not be used, reproduced or transmitted in any manner without express written permission from Microsoft Corporation.",
				"entityType": "Address",
				"matchCodes": [
					"Good"
				],
				"name": "709 Kings Rd, Victoria, BC V8T 1W4, Canada",
				"statusCode": 200,
				"statusDescription": "OK",
				"traceId": "9a7febd527d249d9b58f6b30c0801397|BN20121764|7.7.0.0|",
				"addressLine": "709 Kings Rd",
				"adminDistrict": "BC",
				"adminDistrict2": "Capital",
				"countryRegion": "Canada",
				"formattedAddress": "709 Kings Rd, Victoria, BC V8T 1W4, Canada",
				"locality": "Victoria",
				"neighborhood": "Burnside",
				"postalCode": "V8T 1W4"
			},
			"geometry": {
				"type": "Point",
				"coordinates": [
					-123.3652,
					48.43622
				]
			},
			"bbox": [
				-123.3668944,
				48.4350958,
				-123.3635056,
				48.4373442
			]
		}
	]
}
