{
	"type": "FeatureCollection",
	"features": [
		{
			"type": "Feature",
			"properties": {
				"confidence": 9,
				"authenticationResultCode": "ValidCredentials",
				"brandLogoUri": "http://dev.virtualearth.net/Branding/logo_powered_by.png",
				"copyright": "Copyright © 2017 Microsoft and its suppliers. All rights reserved. This API cannot be accessed and the content and any results may not be used, reproduced or transmitted in any manner without express written permission from Microsoft Corporation.",
				"entityType": "Address",
				"matchCodes": [
					"Good"
				],
				"name": "71 Braid St, New Westminster, BC V3L 3P2, Canada",
				"statusCode": 200,
				"statusDescription": "OK",
				"traceId": "1c5ab774cf8d41df8c98bc40ae3103b1|BN20320521|7.7.0.0|",
				"addressLine": "71 Braid St",
				"adminDistrict": "BC",
				"adminDistrict2": "Greater Vancouver",
				"countryRegion": "Canada",
				"formattedAddress": "71 Braid St, New Westminster, BC V3L 3P2, Canada",
				"locality": "New Westminster",
				"neighborhood": "Brunette Creek",
				"postalCode": "V3L 3P2"
			},
			"geometry": {
				"type": "Point",
				"coordinates": [
					-122.8814785,
					49.2310045
				]
			},
			"bbox": [
				-122.8832,
				49.2298804,
				-122.879757,
				49.2321287
			]
		}
	]
}
