{
	"type": "FeatureCollection",
	"features": [
		{
			"type": "Feature",
			"properties": {
				"confidence": 9,
				"authenticationResultCode": "ValidCredentials",
				"brandLogoUri": "http://dev.virtualearth.net/Branding/logo_powered_by.png",
				"copyright": "Copyright © 2017 Microsoft and its suppliers. All rights reserved. This API cannot be accessed and the content and any results may not be used, reproduced or transmitted in any manner without express written permission from Microsoft Corporation.",
				"entityType": "Address",
				"matchCodes": [
					"Good"
				],
				"name": "71 Cheyanne Meadows Way, Rocky View County, AB T3R 1B6, Canada",
				"statusCode": 200,
				"statusDescription": "OK",
				"traceId": "8b68e5d8c0764ea28ad6ed9975586f50|BN20200137|7.7.0.0|",
				"addressLine": "71 Cheyanne Meadows Way",
				"adminDistrict": "AB",
				"adminDistrict2": "Alberta",
				"countryRegion": "Canada",
				"formattedAddress": "71 Cheyanne Meadows Way, Rocky View County, AB T3R 1B6, Canada",
				"locality": "Rocky View County",
				"postalCode": "T3R 1B6"
			},
			"geometry": {
				"type": "Point",
				"coordinates": [
					-114.2706732,
					51.1789433
				]
			},
			"bbox": [
				-114.2724664,
				51.1778191,
				-114.26888,
				51.1800674
			]
		}
	]
}
