{
	"type": "FeatureCollection",
	"features": [
		{
			"type": "Feature",
			"properties": {
				"confidence": 9,
				"authenticationResultCode": "ValidCredentials",
				"brandLogoUri": "http://dev.virtualearth.net/Branding/logo_powered_by.png",
				"copyright": "Copyright © 2017 Microsoft and its suppliers. All rights reserved. This API cannot be accessed and the content and any results may not be used, reproduced or transmitted in any manner without express written permission from Microsoft Corporation.",
				"entityType": "Address",
				"matchCodes": [
					"Good"
				],
				"name": "71 Livingston Rd, Milton, ON L9T 6B8, Canada",
				"statusCode": 200,
				"statusDescription": "OK",
				"traceId": "2a3fe51368b74a828d01712399188dde|BN20260223|7.7.0.0|",
				"addressLine": "71 Livingston Rd",
				"adminDistrict": "ON",
				"adminDistrict2": "Halton",
				"countryRegion": "Canada",
				"formattedAddress": "71 Livingston Rd, Milton, ON L9T 6B8, Canada",
				"locality": "Milton",
				"postalCode": "L9T 6B8"
			},
			"geometry": {
				"type": "Point",
				"coordinates": [
					-79.85867,
					43.53163
				]
			},
			"bbox": [
				-79.8602206,
				43.5305058,
				-79.8571194,
				43.5327542
			]
		}
	]
}
