{
	"type": "FeatureCollection",
	"features": [
		{
			"type": "Feature",
			"properties": {
				"confidence": 9,
				"authenticationResultCode": "ValidCredentials",
				"brandLogoUri": "http://dev.virtualearth.net/Branding/logo_powered_by.png",
				"copyright": "Copyright © 2017 Microsoft and its suppliers. All rights reserved. This API cannot be accessed and the content and any results may not be used, reproduced or transmitted in any manner without express written permission from Microsoft Corporation.",
				"entityType": "Address",
				"matchCodes": [
					"Good"
				],
				"name": "71 Tarawood Clos NE, Calgary, AB T3J 4Y8, Canada",
				"statusCode": 200,
				"statusDescription": "OK",
				"traceId": "b8cd90d3b6fb46d79edab28a04b313e7|BN20130530|7.7.0.0|",
				"addressLine": "71 Tarawood Clos NE",
				"adminDistrict": "AB",
				"adminDistrict2": "Alberta",
				"countryRegion": "Canada",
				"formattedAddress": "71 Tarawood Clos NE, Calgary, AB T3J 4Y8, Canada",
				"locality": "Calgary",
				"neighborhood": "Taradale",
				"postalCode": "T3J 4Y8"
			},
			"geometry": {
				"type": "Point",
				"coordinates": [
					-113.94044,
					51.12298
				]
			},
			"bbox": [
				-113.942231,
				51.1218558,
				-113.938649,
				51.1241042
			]
		}
	]
}
