{
	"type": "FeatureCollection",
	"features": [
		{
			"type": "Feature",
			"properties": {
				"confidence": 9,
				"authenticationResultCode": "ValidCredentials",
				"brandLogoUri": "http://dev.virtualearth.net/Branding/logo_powered_by.png",
				"copyright": "Copyright © 2017 Microsoft and its suppliers. All rights reserved. This API cannot be accessed and the content and any results may not be used, reproduced or transmitted in any manner without express written permission from Microsoft Corporation.",
				"entityType": "Address",
				"matchCodes": [
					"Good"
				],
				"name": "710 Kingston Rd, Toronto, ON M4E 1R7, Canada",
				"statusCode": 200,
				"statusDescription": "OK",
				"traceId": "397417970048435fbae91a3224f55ad4|BN20130631|7.7.0.0|",
				"addressLine": "710 Kingston Rd",
				"adminDistrict": "ON",
				"adminDistrict2": "Toronto",
				"countryRegion": "Canada",
				"formattedAddress": "710 Kingston Rd, Toronto, ON M4E 1R7, Canada",
				"locality": "Toronto",
				"neighborhood": "East End-Danforth",
				"postalCode": "M4E 1R7"
			},
			"geometry": {
				"type": "Point",
				"coordinates": [
					-79.29609,
					43.67954
				]
			},
			"bbox": [
				-79.2976444,
				43.6784158,
				-79.2945356,
				43.6806642
			]
		}
	]
}
