{
	"type": "FeatureCollection",
	"features": [
		{
			"type": "Feature",
			"properties": {
				"confidence": 9,
				"authenticationResultCode": "ValidCredentials",
				"brandLogoUri": "http://dev.virtualearth.net/Branding/logo_powered_by.png",
				"copyright": "Copyright © 2017 Microsoft and its suppliers. All rights reserved. This API cannot be accessed and the content and any results may not be used, reproduced or transmitted in any manner without express written permission from Microsoft Corporation.",
				"entityType": "Address",
				"matchCodes": [
					"Good"
				],
				"name": "7127 Honeyman St, Delta, BC V4G 1E2, Canada",
				"statusCode": 200,
				"statusDescription": "OK",
				"traceId": "8a14d16fe6664ca99d47ca46f06cd731|BN20130532|7.7.0.0|",
				"addressLine": "7127 Honeyman St",
				"adminDistrict": "BC",
				"adminDistrict2": "Greater Vancouver",
				"countryRegion": "Canada",
				"formattedAddress": "7127 Honeyman St, Delta, BC V4G 1E2, Canada",
				"locality": "Delta",
				"postalCode": "V4G 1E2"
			},
			"geometry": {
				"type": "Point",
				"coordinates": [
					-123.01959,
					49.13194
				]
			},
			"bbox": [
				-123.021308,
				49.1308158,
				-123.017872,
				49.1330642
			]
		}
	]
}
