{
	"type": "FeatureCollection",
	"features": [
		{
			"type": "Feature",
			"properties": {
				"confidence": 9,
				"authenticationResultCode": "ValidCredentials",
				"brandLogoUri": "http://dev.virtualearth.net/Branding/logo_powered_by.png",
				"copyright": "Copyright © 2017 Microsoft and its suppliers. All rights reserved. This API cannot be accessed and the content and any results may not be used, reproduced or transmitted in any manner without express written permission from Microsoft Corporation.",
				"entityType": "Address",
				"matchCodes": [
					"Good"
				],
				"name": "7158 Tabbyman Walk, Mississauga, ON L5W 1H4, Canada",
				"statusCode": 200,
				"statusDescription": "OK",
				"traceId": "75534e5751c64112a9f503b3550dd81f|BN20190653|7.7.0.0|",
				"addressLine": "7158 Tabbyman Walk",
				"adminDistrict": "ON",
				"adminDistrict2": "Peel",
				"countryRegion": "Canada",
				"formattedAddress": "7158 Tabbyman Walk, Mississauga, ON L5W 1H4, Canada",
				"locality": "Mississauga",
				"neighborhood": "Meadowvale Village",
				"postalCode": "L5W 1H4"
			},
			"geometry": {
				"type": "Point",
				"coordinates": [
					-79.72751,
					43.63547
				]
			},
			"bbox": [
				-79.7290632,
				43.6343458,
				-79.7259568,
				43.6365942
			]
		}
	]
}
