{
	"type": "FeatureCollection",
	"features": [
		{
			"type": "Feature",
			"properties": {
				"confidence": 9,
				"authenticationResultCode": "ValidCredentials",
				"brandLogoUri": "http://dev.virtualearth.net/Branding/logo_powered_by.png",
				"copyright": "Copyright © 2017 Microsoft and its suppliers. All rights reserved. This API cannot be accessed and the content and any results may not be used, reproduced or transmitted in any manner without express written permission from Microsoft Corporation.",
				"entityType": "Address",
				"matchCodes": [
					"Good"
				],
				"name": "7158 Crowsfoot Rd, Ariss, ON N0B 1B0, Canada",
				"statusCode": 200,
				"statusDescription": "OK",
				"traceId": "88f92dfaf8e14b83bfd918ba42706e5a|BN20300154|7.7.0.0|",
				"addressLine": "7158 Crowsfoot Rd",
				"adminDistrict": "ON",
				"adminDistrict2": "Wellington",
				"countryRegion": "Canada",
				"formattedAddress": "7158 Crowsfoot Rd, Ariss, ON N0B 1B0, Canada",
				"locality": "Guelph/Eramosa",
				"neighborhood": "Ariss",
				"postalCode": "N0B 1B0"
			},
			"geometry": {
				"type": "Point",
				"coordinates": [
					-80.3693,
					43.5694299
				]
			},
			"bbox": [
				-80.3708515,
				43.5683057,
				-80.3677485,
				43.5705541
			]
		}
	]
}
