{
	"type": "FeatureCollection",
	"features": [
		{
			"type": "Feature",
			"properties": {
				"confidence": 9,
				"authenticationResultCode": "ValidCredentials",
				"brandLogoUri": "http://dev.virtualearth.net/Branding/logo_powered_by.png",
				"copyright": "Copyright © 2017 Microsoft and its suppliers. All rights reserved. This API cannot be accessed and the content and any results may not be used, reproduced or transmitted in any manner without express written permission from Microsoft Corporation.",
				"entityType": "Address",
				"matchCodes": [
					"Good"
				],
				"name": "717 Water St, Miramichi, NB E1N 4B9, Canada",
				"statusCode": 200,
				"statusDescription": "OK",
				"traceId": "875e3c2bb97e4bf4a6d0a08f62b90e03|BN20130621|7.7.0.0|",
				"addressLine": "717 Water St",
				"adminDistrict": "NB",
				"adminDistrict2": "Northumberland",
				"countryRegion": "Canada",
				"formattedAddress": "717 Water St, Miramichi, NB E1N 4B9, Canada",
				"locality": "Miramichi",
				"postalCode": "E1N 4B9"
			},
			"geometry": {
				"type": "Point",
				"coordinates": [
					-65.5358936,
					47.0096303
				]
			},
			"bbox": [
				-65.5375422,
				47.0085061,
				-65.534245,
				47.0107544
			]
		}
	]
}
