{
	"type": "FeatureCollection",
	"features": [
		{
			"type": "Feature",
			"properties": {
				"confidence": 9,
				"authenticationResultCode": "ValidCredentials",
				"brandLogoUri": "http://dev.virtualearth.net/Branding/logo_powered_by.png",
				"copyright": "Copyright © 2017 Microsoft and its suppliers. All rights reserved. This API cannot be accessed and the content and any results may not be used, reproduced or transmitted in any manner without express written permission from Microsoft Corporation.",
				"entityType": "Address",
				"matchCodes": [
					"Good"
				],
				"name": "72 Copernicus Blvd, Brantford, ON N3P 1K5, Canada",
				"statusCode": 200,
				"statusDescription": "OK",
				"traceId": "c81b47e5f6304f369b2739fd43676df1|BN20130533|7.7.0.0|",
				"addressLine": "72 Copernicus Blvd",
				"adminDistrict": "ON",
				"adminDistrict2": "Brant",
				"countryRegion": "Canada",
				"formattedAddress": "72 Copernicus Blvd, Brantford, ON N3P 1K5, Canada",
				"locality": "Brantford",
				"postalCode": "N3P 1K5"
			},
			"geometry": {
				"type": "Point",
				"coordinates": [
					-80.24039,
					43.17887
				]
			},
			"bbox": [
				-80.2419316,
				43.1777458,
				-80.2388484,
				43.1799942
			]
		}
	]
}
