{
	"type": "FeatureCollection",
	"features": [
		{
			"type": "Feature",
			"properties": {
				"confidence": 9,
				"authenticationResultCode": "ValidCredentials",
				"brandLogoUri": "http://dev.virtualearth.net/Branding/logo_powered_by.png",
				"copyright": "Copyright © 2017 Microsoft and its suppliers. All rights reserved. This API cannot be accessed and the content and any results may not be used, reproduced or transmitted in any manner without express written permission from Microsoft Corporation.",
				"entityType": "Address",
				"matchCodes": [
					"Good"
				],
				"name": "72 Church St, Huron East, ON N0K, Canada",
				"statusCode": 200,
				"statusDescription": "OK",
				"traceId": "259e11287b33412aad29a06ce4ec2283|BN20200239|7.7.0.0|",
				"addressLine": "72 Church St",
				"adminDistrict": "ON",
				"adminDistrict2": "Huron",
				"countryRegion": "Canada",
				"formattedAddress": "72 Church St, Huron East, ON N0K, Canada",
				"locality": "Huron East",
				"neighborhood": "Seaforth",
				"postalCode": "N0K 1L0"
			},
			"geometry": {
				"type": "Point",
				"coordinates": [
					-81.39291,
					43.55716
				]
			},
			"bbox": [
				-81.3944612,
				43.5560358,
				-81.3913588,
				43.5582842
			]
		}
	]
}
