{
	"type": "FeatureCollection",
	"features": [
		{
			"type": "Feature",
			"properties": {
				"confidence": 9,
				"authenticationResultCode": "ValidCredentials",
				"brandLogoUri": "http://dev.virtualearth.net/Branding/logo_powered_by.png",
				"copyright": "Copyright © 2017 Microsoft and its suppliers. All rights reserved. This API cannot be accessed and the content and any results may not be used, reproduced or transmitted in any manner without express written permission from Microsoft Corporation.",
				"entityType": "Address",
				"matchCodes": [
					"Good"
				],
				"name": "721 Aldford Ave, Delta, BC V3M 5P5, Canada",
				"statusCode": 200,
				"statusDescription": "OK",
				"traceId": "311016387a7540b79e1c858b80dc4a7d|BN20130634|7.7.0.0|",
				"addressLine": "721 Aldford Ave",
				"adminDistrict": "BC",
				"adminDistrict2": "Greater Vancouver",
				"countryRegion": "Canada",
				"formattedAddress": "721 Aldford Ave, Delta, BC V3M 5P5, Canada",
				"locality": "Delta",
				"postalCode": "V3M 5P5"
			},
			"geometry": {
				"type": "Point",
				"coordinates": [
					-122.92938,
					49.17663
				]
			},
			"bbox": [
				-122.9310996,
				49.1755058,
				-122.9276604,
				49.1777542
			]
		}
	]
}
