{
	"type": "FeatureCollection",
	"features": [
		{
			"type": "Feature",
			"properties": {
				"confidence": 9,
				"authenticationResultCode": "ValidCredentials",
				"brandLogoUri": "http://dev.virtualearth.net/Branding/logo_powered_by.png",
				"copyright": "Copyright © 2017 Microsoft and its suppliers. All rights reserved. This API cannot be accessed and the content and any results may not be used, reproduced or transmitted in any manner without express written permission from Microsoft Corporation.",
				"entityType": "Address",
				"matchCodes": [
					"Good"
				],
				"name": "7233 Progress Way, Delta, BC V4G 1E7, Canada",
				"statusCode": 200,
				"statusDescription": "OK",
				"traceId": "028ac7b8542045ba87bd4b22bcec66c9|BN20220145|7.7.0.0|",
				"addressLine": "7233 Progress Way",
				"adminDistrict": "BC",
				"adminDistrict2": "Greater Vancouver",
				"countryRegion": "Canada",
				"formattedAddress": "7233 Progress Way, Delta, BC V4G 1E7, Canada",
				"locality": "Delta",
				"postalCode": "V4G 1E7"
			},
			"geometry": {
				"type": "Point",
				"coordinates": [
					-123.02235,
					49.135
				]
			},
			"bbox": [
				-123.0240682,
				49.1338758,
				-123.0206318,
				49.1361242
			]
		}
	]
}
