{
	"type": "FeatureCollection",
	"features": [
		{
			"type": "Feature",
			"properties": {
				"confidence": 9,
				"authenticationResultCode": "ValidCredentials",
				"brandLogoUri": "http://dev.virtualearth.net/Branding/logo_powered_by.png",
				"copyright": "Copyright © 2017 Microsoft and its suppliers. All rights reserved. This API cannot be accessed and the content and any results may not be used, reproduced or transmitted in any manner without express written permission from Microsoft Corporation.",
				"entityType": "Address",
				"matchCodes": [
					"Good"
				],
				"name": "7250 Victoria Park Ave, Markham, ON L3R 2M5, Canada",
				"statusCode": 200,
				"statusDescription": "OK",
				"traceId": "f0f8a4884eac49cb821a4ce62778a03d|BN20260223|7.7.0.0|",
				"addressLine": "7250 Victoria Park Ave",
				"adminDistrict": "ON",
				"adminDistrict2": "York",
				"countryRegion": "Canada",
				"formattedAddress": "7250 Victoria Park Ave, Markham, ON L3R 2M5, Canada",
				"locality": "Markham",
				"postalCode": "L3R 2M5"
			},
			"geometry": {
				"type": "Point",
				"coordinates": [
					-79.34378,
					43.81896
				]
			},
			"bbox": [
				-79.345338,
				43.8178358,
				-79.342222,
				43.8200842
			]
		}
	]
}
