{
	"type": "FeatureCollection",
	"features": [
		{
			"type": "Feature",
			"properties": {
				"confidence": 9,
				"authenticationResultCode": "ValidCredentials",
				"brandLogoUri": "http://dev.virtualearth.net/Branding/logo_powered_by.png",
				"copyright": "Copyright © 2017 Microsoft and its suppliers. All rights reserved. This API cannot be accessed and the content and any results may not be used, reproduced or transmitted in any manner without express written permission from Microsoft Corporation.",
				"entityType": "Address",
				"matchCodes": [
					"Good"
				],
				"name": "727 Harbour St, Innisfil, ON L0L, Canada",
				"statusCode": 200,
				"statusDescription": "OK",
				"traceId": "9c91a7fbf82c4db0934ed6cff8d631f3|BN20260231|7.7.0.0|",
				"addressLine": "727 Harbour St",
				"adminDistrict": "ON",
				"adminDistrict2": "Simcoe",
				"countryRegion": "Canada",
				"formattedAddress": "727 Harbour St, Innisfil, ON L0L, Canada",
				"locality": "Innisfil",
				"neighborhood": "Bell Ewart",
				"postalCode": "L0L 1W0"
			},
			"geometry": {
				"type": "Point",
				"coordinates": [
					-79.54046,
					44.25634
				]
			},
			"bbox": [
				-79.5420296,
				44.2552158,
				-79.5388904,
				44.2574642
			]
		}
	]
}
