{
	"type": "FeatureCollection",
	"features": [
		{
			"type": "Feature",
			"properties": {
				"confidence": 9,
				"authenticationResultCode": "ValidCredentials",
				"brandLogoUri": "http://dev.virtualearth.net/Branding/logo_powered_by.png",
				"copyright": "Copyright © 2017 Microsoft and its suppliers. All rights reserved. This API cannot be accessed and the content and any results may not be used, reproduced or transmitted in any manner without express written permission from Microsoft Corporation.",
				"entityType": "Address",
				"matchCodes": [
					"Good"
				],
				"name": "7271 Warden Ave, Markham, ON L3R 5X5, Canada",
				"statusCode": 200,
				"statusDescription": "OK",
				"traceId": "42022ea4ddcb4846b18c300948c4fe8a|BN20130631|7.7.0.0|",
				"addressLine": "7271 Warden Ave",
				"adminDistrict": "ON",
				"adminDistrict2": "York",
				"countryRegion": "Canada",
				"formattedAddress": "7271 Warden Ave, Markham, ON L3R 5X5, Canada",
				"locality": "Markham",
				"neighborhood": "North Milliken",
				"postalCode": "L3R 5X5"
			},
			"geometry": {
				"type": "Point",
				"coordinates": [
					-79.3262,
					43.8291899
				]
			},
			"bbox": [
				-79.3277583,
				43.8280657,
				-79.3246417,
				43.8303141
			]
		}
	]
}
