{
	"type": "FeatureCollection",
	"features": [
		{
			"type": "Feature",
			"properties": {
				"confidence": 9,
				"authenticationResultCode": "ValidCredentials",
				"brandLogoUri": "http://dev.virtualearth.net/Branding/logo_powered_by.png",
				"copyright": "Copyright © 2017 Microsoft and its suppliers. All rights reserved. This API cannot be accessed and the content and any results may not be used, reproduced or transmitted in any manner without express written permission from Microsoft Corporation.",
				"entityType": "Address",
				"matchCodes": [
					"Good"
				],
				"name": "72863 Blind Line, Zurich, ON N0M 2T0, Canada",
				"statusCode": 200,
				"statusDescription": "OK",
				"traceId": "bb5ea2f18bc7422ab801fbd3ce23d6d0|BN20130447|7.7.0.0|",
				"addressLine": "72863 Blind Line",
				"adminDistrict": "ON",
				"adminDistrict2": "Huron",
				"countryRegion": "Canada",
				"formattedAddress": "72863 Blind Line, Zurich, ON N0M 2T0, Canada",
				"locality": "Bluewater",
				"neighborhood": "Zurich",
				"postalCode": "N0M 2T0"
			},
			"geometry": {
				"type": "Point",
				"coordinates": [
					-81.61368,
					43.42542
				]
			},
			"bbox": [
				-81.6152278,
				43.4242958,
				-81.6121322,
				43.4265442
			]
		}
	]
}
