{
	"type": "FeatureCollection",
	"features": [
		{
			"type": "Feature",
			"properties": {
				"confidence": 9,
				"authenticationResultCode": "ValidCredentials",
				"brandLogoUri": "http://dev.virtualearth.net/Branding/logo_powered_by.png",
				"copyright": "Copyright © 2017 Microsoft and its suppliers. All rights reserved. This API cannot be accessed and the content and any results may not be used, reproduced or transmitted in any manner without express written permission from Microsoft Corporation.",
				"entityType": "Address",
				"matchCodes": [
					"Good"
				],
				"name": "72999 Bronson Line, Zurich, ON N0M 2T0, Canada",
				"statusCode": 200,
				"statusDescription": "OK",
				"traceId": "b53a78f1ade54ef0aff6e18f40f84c8e|BN20300154|7.7.0.0|",
				"addressLine": "72999 Bronson Line",
				"adminDistrict": "ON",
				"adminDistrict2": "Huron",
				"countryRegion": "Canada",
				"formattedAddress": "72999 Bronson Line, Zurich, ON N0M 2T0, Canada",
				"locality": "Bluewater",
				"neighborhood": "Zurich",
				"postalCode": "N0M 2T0"
			},
			"geometry": {
				"type": "Point",
				"coordinates": [
					-81.65835,
					43.42683
				]
			},
			"bbox": [
				-81.6598979,
				43.4257058,
				-81.6568021,
				43.4279542
			]
		}
	]
}
