{
	"type": "FeatureCollection",
	"features": [
		{
			"type": "Feature",
			"properties": {
				"confidence": 9,
				"authenticationResultCode": "ValidCredentials",
				"brandLogoUri": "http://dev.virtualearth.net/Branding/logo_powered_by.png",
				"copyright": "Copyright © 2017 Microsoft and its suppliers. All rights reserved. This API cannot be accessed and the content and any results may not be used, reproduced or transmitted in any manner without express written permission from Microsoft Corporation.",
				"entityType": "Address",
				"matchCodes": [
					"Good"
				],
				"name": "73 Doncaster Ave, Thornhill, ON L3T 1L6, Canada",
				"statusCode": 200,
				"statusDescription": "OK",
				"traceId": "ca5c43cf900a423fae3ebe4e2c80a89a|BN20160335|7.7.0.0|",
				"addressLine": "73 Doncaster Ave",
				"adminDistrict": "ON",
				"adminDistrict2": "York",
				"countryRegion": "Canada",
				"formattedAddress": "73 Doncaster Ave, Thornhill, ON L3T 1L6, Canada",
				"locality": "Markham",
				"neighborhood": "Thornhill",
				"postalCode": "L3T 1L6"
			},
			"geometry": {
				"type": "Point",
				"coordinates": [
					-79.41552,
					43.80379
				]
			},
			"bbox": [
				-79.4170776,
				43.8026658,
				-79.4139624,
				43.8049142
			]
		}
	]
}
