{
	"type": "FeatureCollection",
	"features": [
		{
			"type": "Feature",
			"properties": {
				"confidence": 9,
				"authenticationResultCode": "ValidCredentials",
				"brandLogoUri": "http://dev.virtualearth.net/Branding/logo_powered_by.png",
				"copyright": "Copyright © 2017 Microsoft and its suppliers. All rights reserved. This API cannot be accessed and the content and any results may not be used, reproduced or transmitted in any manner without express written permission from Microsoft Corporation.",
				"entityType": "Address",
				"matchCodes": [
					"Good"
				],
				"name": "7305 E Danbro Cres, Mississauga, ON L5N 6P8, Canada",
				"statusCode": 200,
				"statusDescription": "OK",
				"traceId": "0f220484f60e4c38a48f4a4b10de750c|BN20290118|7.7.0.0|",
				"addressLine": "7305 E Danbro Cres",
				"adminDistrict": "ON",
				"adminDistrict2": "Peel",
				"countryRegion": "Canada",
				"formattedAddress": "7305 E Danbro Cres, Mississauga, ON L5N 6P8, Canada",
				"locality": "Mississauga",
				"postalCode": "L5N 6P8"
			},
			"geometry": {
				"type": "Point",
				"coordinates": [
					-79.77489,
					43.60606
				]
			},
			"bbox": [
				-79.7764425,
				43.6049358,
				-79.7733375,
				43.6071842
			]
		}
	]
}
