{
	"type": "FeatureCollection",
	"features": [
		{
			"type": "Feature",
			"properties": {
				"confidence": 9,
				"authenticationResultCode": "ValidCredentials",
				"brandLogoUri": "http://dev.virtualearth.net/Branding/logo_powered_by.png",
				"copyright": "Copyright © 2017 Microsoft and its suppliers. All rights reserved. This API cannot be accessed and the content and any results may not be used, reproduced or transmitted in any manner without express written permission from Microsoft Corporation.",
				"entityType": "Address",
				"matchCodes": [
					"Good"
				],
				"name": "731 Baillie Ave, Kelowna, BC V1Y 7E9, Canada",
				"statusCode": 200,
				"statusDescription": "OK",
				"traceId": "a1dcac0bdd28406aabde16d59816acab|BN20210145|7.7.0.0|",
				"addressLine": "731 Baillie Ave",
				"adminDistrict": "BC",
				"adminDistrict2": "Central Okanagan",
				"countryRegion": "Canada",
				"formattedAddress": "731 Baillie Ave, Kelowna, BC V1Y 7E9, Canada",
				"locality": "Kelowna",
				"neighborhood": "North End",
				"postalCode": "V1Y 7E9"
			},
			"geometry": {
				"type": "Point",
				"coordinates": [
					-119.4874,
					49.8960999
				]
			},
			"bbox": [
				-119.4891451,
				49.8949757,
				-119.4856549,
				49.8972241
			]
		}
	]
}
