{
	"type": "FeatureCollection",
	"features": [
		{
			"type": "Feature",
			"properties": {
				"confidence": 9,
				"authenticationResultCode": "ValidCredentials",
				"brandLogoUri": "http://dev.virtualearth.net/Branding/logo_powered_by.png",
				"copyright": "Copyright © 2017 Microsoft and its suppliers. All rights reserved. This API cannot be accessed and the content and any results may not be used, reproduced or transmitted in any manner without express written permission from Microsoft Corporation.",
				"entityType": "Address",
				"matchCodes": [
					"Good"
				],
				"name": "7388 Hume Ave, Delta, BC V4G 1C5, Canada",
				"statusCode": 200,
				"statusDescription": "OK",
				"traceId": "90b627fc894849be94e387120a165bc1|BN20300154|7.7.0.0|",
				"addressLine": "7388 Hume Ave",
				"adminDistrict": "BC",
				"adminDistrict2": "Greater Vancouver",
				"countryRegion": "Canada",
				"formattedAddress": "7388 Hume Ave, Delta, BC V4G 1C5, Canada",
				"locality": "Delta",
				"postalCode": "V4G 1C5"
			},
			"geometry": {
				"type": "Point",
				"coordinates": [
					-123.01996,
					49.13087
				]
			},
			"bbox": [
				-123.021678,
				49.1297458,
				-123.018242,
				49.1319942
			]
		}
	]
}
