{
	"type": "FeatureCollection",
	"features": [
		{
			"type": "Feature",
			"properties": {
				"confidence": 9,
				"authenticationResultCode": "ValidCredentials",
				"brandLogoUri": "http://dev.virtualearth.net/Branding/logo_powered_by.png",
				"copyright": "Copyright © 2017 Microsoft and its suppliers. All rights reserved. This API cannot be accessed and the content and any results may not be used, reproduced or transmitted in any manner without express written permission from Microsoft Corporation.",
				"entityType": "Address",
				"matchCodes": [
					"Good"
				],
				"name": "74 Palace Rd, Napanee, ON K7R 3B2, Canada",
				"statusCode": 200,
				"statusDescription": "OK",
				"traceId": "97f6cc1e791b4a7595b5905c861fd2e0|BN20190653|7.7.0.0|",
				"addressLine": "74 Palace Rd",
				"adminDistrict": "ON",
				"adminDistrict2": "Lennox and Addington",
				"countryRegion": "Canada",
				"formattedAddress": "74 Palace Rd, Napanee, ON K7R 3B2, Canada",
				"locality": "Greater Napanee",
				"neighborhood": "Napanee",
				"postalCode": "K7R 3B2"
			},
			"geometry": {
				"type": "Point",
				"coordinates": [
					-76.945548,
					44.2459694
				]
			},
			"bbox": [
				-76.9471172,
				44.2448452,
				-76.9439787,
				44.2470935
			]
		}
	]
}
