{
	"type": "FeatureCollection",
	"features": [
		{
			"type": "Feature",
			"properties": {
				"confidence": 9,
				"authenticationResultCode": "ValidCredentials",
				"brandLogoUri": "http://dev.virtualearth.net/Branding/logo_powered_by.png",
				"copyright": "Copyright © 2017 Microsoft and its suppliers. All rights reserved. This API cannot be accessed and the content and any results may not be used, reproduced or transmitted in any manner without express written permission from Microsoft Corporation.",
				"entityType": "Address",
				"matchCodes": [
					"Good"
				],
				"name": "74 Wayling Ave, Vanier, ON K1L 6A4, Canada",
				"statusCode": 200,
				"statusDescription": "OK",
				"traceId": "2eb9ba2de0914ada8cea9fb1b18e59d4|BN20130442|7.7.0.0|",
				"addressLine": "74 Wayling Ave",
				"adminDistrict": "ON",
				"adminDistrict2": "Ottawa",
				"countryRegion": "Canada",
				"formattedAddress": "74 Wayling Ave, Vanier, ON K1L 6A4, Canada",
				"locality": "Ottawa",
				"neighborhood": "Vanier",
				"postalCode": "K1L 6A4"
			},
			"geometry": {
				"type": "Point",
				"coordinates": [
					-75.66837,
					45.43474
				]
			},
			"bbox": [
				-75.669972,
				45.4336158,
				-75.666768,
				45.4358642
			]
		}
	]
}
