{
	"type": "FeatureCollection",
	"features": [
		{
			"type": "Feature",
			"properties": {
				"confidence": 9,
				"authenticationResultCode": "ValidCredentials",
				"brandLogoUri": "http://dev.virtualearth.net/Branding/logo_powered_by.png",
				"copyright": "Copyright © 2017 Microsoft and its suppliers. All rights reserved. This API cannot be accessed and the content and any results may not be used, reproduced or transmitted in any manner without express written permission from Microsoft Corporation.",
				"entityType": "Address",
				"matchCodes": [
					"Good"
				],
				"name": "741 Rue Lowe, Lachute, QC J8H 4N9, Canada",
				"statusCode": 200,
				"statusDescription": "OK",
				"traceId": "00db358d8d5d42bdbb7d23bb97cce7f8|BN20130631|7.7.0.0|",
				"addressLine": "741 Rue Lowe",
				"adminDistrict": "QC",
				"adminDistrict2": "Argenteuil",
				"countryRegion": "Canada",
				"formattedAddress": "741 Rue Lowe, Lachute, QC J8H 4N9, Canada",
				"locality": "Lachute",
				"postalCode": "J8H 4N9"
			},
			"geometry": {
				"type": "Point",
				"coordinates": [
					-74.31111,
					45.64209
				]
			},
			"bbox": [
				-74.3127179,
				45.6409658,
				-74.3095021,
				45.6432142
			]
		}
	]
}
