{
	"type": "FeatureCollection",
	"features": [
		{
			"type": "Feature",
			"properties": {
				"confidence": 9,
				"authenticationResultCode": "ValidCredentials",
				"brandLogoUri": "http://dev.virtualearth.net/Branding/logo_powered_by.png",
				"copyright": "Copyright © 2017 Microsoft and its suppliers. All rights reserved. This API cannot be accessed and the content and any results may not be used, reproduced or transmitted in any manner without express written permission from Microsoft Corporation.",
				"entityType": "Address",
				"matchCodes": [
					"Good"
				],
				"name": "7411 Vantage Way, Delta, BC V4G 1C9, Canada",
				"statusCode": 200,
				"statusDescription": "OK",
				"traceId": "cf310242381646439100589cc6e40f42|BN20130532|7.7.0.0|",
				"addressLine": "7411 Vantage Way",
				"adminDistrict": "BC",
				"adminDistrict2": "Greater Vancouver",
				"countryRegion": "Canada",
				"formattedAddress": "7411 Vantage Way, Delta, BC V4G 1C9, Canada",
				"locality": "Delta",
				"postalCode": "V4G 1C9"
			},
			"geometry": {
				"type": "Point",
				"coordinates": [
					-123.0238488,
					49.1358803
				]
			},
			"bbox": [
				-123.025567,
				49.1347562,
				-123.0221306,
				49.1370045
			]
		}
	]
}
