{
	"type": "FeatureCollection",
	"features": [
		{
			"type": "Feature",
			"properties": {
				"confidence": 9,
				"authenticationResultCode": "ValidCredentials",
				"brandLogoUri": "http://dev.virtualearth.net/Branding/logo_powered_by.png",
				"copyright": "Copyright © 2017 Microsoft and its suppliers. All rights reserved. This API cannot be accessed and the content and any results may not be used, reproduced or transmitted in any manner without express written permission from Microsoft Corporation.",
				"entityType": "Address",
				"matchCodes": [
					"Good"
				],
				"name": "742 Avenue Renaud, Dorval, QC H9P 1H5, Canada",
				"statusCode": 200,
				"statusDescription": "OK",
				"traceId": "74cff5387f7e4795a6ec6ba91b968dc0|BN20260231|7.7.0.0|",
				"addressLine": "742 Avenue Renaud",
				"adminDistrict": "QC",
				"adminDistrict2": "Montreal",
				"countryRegion": "Canada",
				"formattedAddress": "742 Avenue Renaud, Dorval, QC H9P 1H5, Canada",
				"locality": "Dorval",
				"postalCode": "H9P 1H5"
			},
			"geometry": {
				"type": "Point",
				"coordinates": [
					-73.71037,
					45.47349
				]
			},
			"bbox": [
				-73.7119731,
				45.4723658,
				-73.7087669,
				45.4746142
			]
		}
	]
}
