{
	"type": "FeatureCollection",
	"features": [
		{
			"type": "Feature",
			"properties": {
				"confidence": 9,
				"authenticationResultCode": "ValidCredentials",
				"brandLogoUri": "http://dev.virtualearth.net/Branding/logo_powered_by.png",
				"copyright": "Copyright © 2017 Microsoft and its suppliers. All rights reserved. This API cannot be accessed and the content and any results may not be used, reproduced or transmitted in any manner without express written permission from Microsoft Corporation.",
				"entityType": "Address",
				"matchCodes": [
					"Good"
				],
				"name": "7425 Avenue Thibault, Brossard, QC J4W 2P2, Canada",
				"statusCode": 200,
				"statusDescription": "OK",
				"traceId": "2d8467f0db5e447ca41e32718951da7f|BN20130422|7.7.0.0|",
				"addressLine": "7425 Avenue Thibault",
				"adminDistrict": "QC",
				"adminDistrict2": "Longueuil",
				"countryRegion": "Canada",
				"formattedAddress": "7425 Avenue Thibault, Brossard, QC J4W 2P2, Canada",
				"locality": "Brossard",
				"postalCode": "J4W 2P2"
			},
			"geometry": {
				"type": "Point",
				"coordinates": [
					-73.47676,
					45.46272
				]
			},
			"bbox": [
				-73.4783628,
				45.4615958,
				-73.4751572,
				45.4638442
			]
		}
	]
}
