{
	"type": "FeatureCollection",
	"features": [
		{
			"type": "Feature",
			"properties": {
				"confidence": 9,
				"authenticationResultCode": "ValidCredentials",
				"brandLogoUri": "http://dev.virtualearth.net/Branding/logo_powered_by.png",
				"copyright": "Copyright © 2017 Microsoft and its suppliers. All rights reserved. This API cannot be accessed and the content and any results may not be used, reproduced or transmitted in any manner without express written permission from Microsoft Corporation.",
				"entityType": "Address",
				"matchCodes": [
					"Good"
				],
				"name": "745 RTE-139, Acton Vale, QC J0H 1A0, Canada",
				"statusCode": 200,
				"statusDescription": "OK",
				"traceId": "e06a0b8f7fcb485c844819263be7771a|BN20130533|7.7.0.0|",
				"addressLine": "745 RTE-139",
				"adminDistrict": "QC",
				"adminDistrict2": "Acton",
				"countryRegion": "Canada",
				"formattedAddress": "745 RTE-139, Acton Vale, QC J0H 1A0, Canada",
				"locality": "Acton Vale",
				"postalCode": "J0H 1A0"
			},
			"geometry": {
				"type": "Point",
				"coordinates": [
					-72.5618259,
					45.6614487
				]
			},
			"bbox": [
				-72.5634344,
				45.6603246,
				-72.5602175,
				45.6625729
			]
		}
	]
}
