{
	"type": "FeatureCollection",
	"features": [
		{
			"type": "Feature",
			"properties": {
				"confidence": 9,
				"authenticationResultCode": "ValidCredentials",
				"brandLogoUri": "http://dev.virtualearth.net/Branding/logo_powered_by.png",
				"copyright": "Copyright © 2017 Microsoft and its suppliers. All rights reserved. This API cannot be accessed and the content and any results may not be used, reproduced or transmitted in any manner without express written permission from Microsoft Corporation.",
				"entityType": "Address",
				"matchCodes": [
					"Good"
				],
				"name": "747 Notre Dame Ave, Sudbury, ON P3A 2T2, Canada",
				"statusCode": 200,
				"statusDescription": "OK",
				"traceId": "69e313567557499baebd363befdcb34a|BN20220145|7.7.0.0|",
				"addressLine": "747 Notre Dame Ave",
				"adminDistrict": "ON",
				"adminDistrict2": "Greater Sudbury",
				"countryRegion": "Canada",
				"formattedAddress": "747 Notre Dame Ave, Sudbury, ON P3A 2T2, Canada",
				"locality": "Greater Sudbury",
				"neighborhood": "Sudbury",
				"postalCode": "P3A 2T2"
			},
			"geometry": {
				"type": "Point",
				"coordinates": [
					-80.9867499,
					46.5097188
				]
			},
			"bbox": [
				-80.9883833,
				46.5085947,
				-80.9851165,
				46.510843
			]
		}
	]
}
