{
	"type": "FeatureCollection",
	"features": [
		{
			"type": "Feature",
			"properties": {
				"confidence": 9,
				"authenticationResultCode": "ValidCredentials",
				"brandLogoUri": "http://dev.virtualearth.net/Branding/logo_powered_by.png",
				"copyright": "Copyright © 2017 Microsoft and its suppliers. All rights reserved. This API cannot be accessed and the content and any results may not be used, reproduced or transmitted in any manner without express written permission from Microsoft Corporation.",
				"entityType": "Address",
				"matchCodes": [
					"Good"
				],
				"name": "75 E Beaver Creek Rd, Richmond Hill, ON L4B 1B8, Canada",
				"statusCode": 200,
				"statusDescription": "OK",
				"traceId": "3090b233e4a64bfb8a7d28114d1d714f|BN20130530|7.7.0.0|",
				"addressLine": "75 E Beaver Creek Rd",
				"adminDistrict": "ON",
				"adminDistrict2": "York",
				"countryRegion": "Canada",
				"formattedAddress": "75 E Beaver Creek Rd, Richmond Hill, ON L4B 1B8, Canada",
				"locality": "Richmond Hill",
				"postalCode": "L4B 1B8"
			},
			"geometry": {
				"type": "Point",
				"coordinates": [
					-79.37972,
					43.85616
				]
			},
			"bbox": [
				-79.381279,
				43.8550358,
				-79.378161,
				43.8572842
			]
		}
	]
}
