{
	"type": "FeatureCollection",
	"features": [
		{
			"type": "Feature",
			"properties": {
				"confidence": 9,
				"authenticationResultCode": "ValidCredentials",
				"brandLogoUri": "http://dev.virtualearth.net/Branding/logo_powered_by.png",
				"copyright": "Copyright © 2017 Microsoft and its suppliers. All rights reserved. This API cannot be accessed and the content and any results may not be used, reproduced or transmitted in any manner without express written permission from Microsoft Corporation.",
				"entityType": "Address",
				"matchCodes": [
					"Good"
				],
				"name": "752098 HWY-59, Norwich, ON N0J 1R0, Canada",
				"statusCode": 200,
				"statusDescription": "OK",
				"traceId": "5ed792e8358e4bf6983c659b65b2dfff|BN20130447|7.7.0.0|",
				"addressLine": "752098 HWY-59",
				"adminDistrict": "ON",
				"adminDistrict2": "Oxford",
				"countryRegion": "Canada",
				"formattedAddress": "752098 HWY-59, Norwich, ON N0J 1R0, Canada",
				"locality": "Norwich",
				"postalCode": "N0J 1R0"
			},
			"geometry": {
				"type": "Point",
				"coordinates": [
					-80.5563528,
					42.8896264
				]
			},
			"bbox": [
				-80.5578871,
				42.8885022,
				-80.5548184,
				42.8907505
			]
		}
	]
}
