{
	"type": "FeatureCollection",
	"features": [
		{
			"type": "Feature",
			"properties": {
				"confidence": 9,
				"authenticationResultCode": "ValidCredentials",
				"brandLogoUri": "http://dev.virtualearth.net/Branding/logo_powered_by.png",
				"copyright": "Copyright © 2017 Microsoft and its suppliers. All rights reserved. This API cannot be accessed and the content and any results may not be used, reproduced or transmitted in any manner without express written permission from Microsoft Corporation.",
				"entityType": "Address",
				"matchCodes": [
					"Good"
				],
				"name": "755 Wallace Rd, North Bay, ON P1A 0E7, Canada",
				"statusCode": 200,
				"statusDescription": "OK",
				"traceId": "6642d2347ac74a2f801be5e3ff183b1a|BN20130625|7.7.0.0|",
				"addressLine": "755 Wallace Rd",
				"adminDistrict": "ON",
				"adminDistrict2": "Nipissing",
				"countryRegion": "Canada",
				"formattedAddress": "755 Wallace Rd, North Bay, ON P1A 0E7, Canada",
				"locality": "North Bay",
				"postalCode": "P1A 0E7"
			},
			"geometry": {
				"type": "Point",
				"coordinates": [
					-79.42458,
					46.31436
				]
			},
			"bbox": [
				-79.4262076,
				46.3132358,
				-79.4229524,
				46.3154842
			]
		}
	]
}
