{
	"type": "FeatureCollection",
	"features": [
		{
			"type": "Feature",
			"properties": {
				"confidence": 9,
				"authenticationResultCode": "ValidCredentials",
				"brandLogoUri": "http://dev.virtualearth.net/Branding/logo_powered_by.png",
				"copyright": "Copyright © 2017 Microsoft and its suppliers. All rights reserved. This API cannot be accessed and the content and any results may not be used, reproduced or transmitted in any manner without express written permission from Microsoft Corporation.",
				"entityType": "Address",
				"matchCodes": [
					"Good"
				],
				"name": "76 King St, Kawartha Lakes, ON K0M, Canada",
				"statusCode": 200,
				"statusDescription": "OK",
				"traceId": "8d9caf65a9694a3d9c492c1f0656c8c6|BN20220145|7.7.0.0|",
				"addressLine": "76 King St",
				"adminDistrict": "ON",
				"adminDistrict2": "Kawartha Lakes",
				"countryRegion": "Canada",
				"formattedAddress": "76 King St, Kawartha Lakes, ON K0M, Canada",
				"locality": "Kawartha Lakes",
				"neighborhood": "Woodville",
				"postalCode": "K0M 2T0"
			},
			"geometry": {
				"type": "Point",
				"coordinates": [
					-78.9884738,
					44.3985933
				]
			},
			"bbox": [
				-78.9900472,
				44.3974692,
				-78.9869005,
				44.3997175
			]
		}
	]
}
