{
	"type": "FeatureCollection",
	"features": [
		{
			"type": "Feature",
			"properties": {
				"confidence": 9,
				"authenticationResultCode": "ValidCredentials",
				"brandLogoUri": "http://dev.virtualearth.net/Branding/logo_powered_by.png",
				"copyright": "Copyright © 2017 Microsoft and its suppliers. All rights reserved. This API cannot be accessed and the content and any results may not be used, reproduced or transmitted in any manner without express written permission from Microsoft Corporation.",
				"entityType": "Address",
				"matchCodes": [
					"Good"
				],
				"name": "76 Waterloo St, Saint John, NB E2L 3P3, Canada",
				"statusCode": 200,
				"statusDescription": "OK",
				"traceId": "bae143e128fb4bf098e64d0e2eaa3dc8|BN20260231|7.7.0.0|",
				"addressLine": "76 Waterloo St",
				"adminDistrict": "NB",
				"adminDistrict2": "Saint John",
				"countryRegion": "Canada",
				"formattedAddress": "76 Waterloo St, Saint John, NB E2L 3P3, Canada",
				"locality": "Saint John",
				"postalCode": "E2L 3P3"
			},
			"geometry": {
				"type": "Point",
				"coordinates": [
					-66.05638,
					45.2771199
				]
			},
			"bbox": [
				-66.0579775,
				45.2759957,
				-66.0547825,
				45.2782441
			]
		}
	]
}
