{
	"type": "FeatureCollection",
	"features": [
		{
			"type": "Feature",
			"properties": {
				"confidence": 9,
				"authenticationResultCode": "ValidCredentials",
				"brandLogoUri": "http://dev.virtualearth.net/Branding/logo_powered_by.png",
				"copyright": "Copyright © 2017 Microsoft and its suppliers. All rights reserved. This API cannot be accessed and the content and any results may not be used, reproduced or transmitted in any manner without express written permission from Microsoft Corporation.",
				"entityType": "Address",
				"matchCodes": [
					"Good"
				],
				"name": "760 Century St, Winnipeg, MB R3H 0M1, Canada",
				"statusCode": 200,
				"statusDescription": "OK",
				"traceId": "6a330b879f664f04932bb2dede4c178c|BN20130423|7.7.0.0|",
				"addressLine": "760 Century St",
				"adminDistrict": "MB",
				"adminDistrict2": "Manitoba",
				"countryRegion": "Canada",
				"formattedAddress": "760 Century St, Winnipeg, MB R3H 0M1, Canada",
				"locality": "Winnipeg",
				"neighborhood": "St James Industrial",
				"postalCode": "R3H 0M1"
			},
			"geometry": {
				"type": "Point",
				"coordinates": [
					-97.20332,
					49.90061
				]
			},
			"bbox": [
				-97.2050653,
				49.8994858,
				-97.2015747,
				49.9017342
			]
		}
	]
}
