{
	"type": "FeatureCollection",
	"features": [
		{
			"type": "Feature",
			"properties": {
				"confidence": 9,
				"authenticationResultCode": "ValidCredentials",
				"brandLogoUri": "http://dev.virtualearth.net/Branding/logo_powered_by.png",
				"copyright": "Copyright © 2017 Microsoft and its suppliers. All rights reserved. This API cannot be accessed and the content and any results may not be used, reproduced or transmitted in any manner without express written permission from Microsoft Corporation.",
				"entityType": "Address",
				"matchCodes": [
					"Good"
				],
				"name": "760 Meadow Wood Rd, Mississauga, ON L5J 2S6, Canada",
				"statusCode": 200,
				"statusDescription": "OK",
				"traceId": "5cb7e67d71f6487498fb511051ec96df|BN20210145|7.7.0.0|",
				"addressLine": "760 Meadow Wood Rd",
				"adminDistrict": "ON",
				"adminDistrict2": "Peel",
				"countryRegion": "Canada",
				"formattedAddress": "760 Meadow Wood Rd, Mississauga, ON L5J 2S6, Canada",
				"locality": "Mississauga",
				"postalCode": "L5J 2S6"
			},
			"geometry": {
				"type": "Point",
				"coordinates": [
					-79.61405,
					43.5151899
				]
			},
			"bbox": [
				-79.6156001,
				43.5140657,
				-79.6124999,
				43.5163141
			]
		}
	]
}
