{
	"type": "FeatureCollection",
	"features": [
		{
			"type": "Feature",
			"properties": {
				"confidence": 9,
				"authenticationResultCode": "ValidCredentials",
				"brandLogoUri": "http://dev.virtualearth.net/Branding/logo_powered_by.png",
				"copyright": "Copyright © 2017 Microsoft and its suppliers. All rights reserved. This API cannot be accessed and the content and any results may not be used, reproduced or transmitted in any manner without express written permission from Microsoft Corporation.",
				"entityType": "Address",
				"matchCodes": [
					"Good"
				],
				"name": "7664 10 St NE, Calgary, AB T2E 8W1, Canada",
				"statusCode": 200,
				"statusDescription": "OK",
				"traceId": "7f33e07bec5443d6a14560c56cce80e7|BN20130620|7.7.0.0|",
				"addressLine": "7664 10 St NE",
				"adminDistrict": "AB",
				"adminDistrict2": "Alberta",
				"countryRegion": "Canada",
				"formattedAddress": "7664 10 St NE, Calgary, AB T2E 8W1, Canada",
				"locality": "Calgary",
				"postalCode": "T2E 8W1"
			},
			"geometry": {
				"type": "Point",
				"coordinates": [
					-114.04101,
					51.12029
				]
			},
			"bbox": [
				-114.0428009,
				51.1191658,
				-114.0392191,
				51.1214142
			]
		}
	]
}
