{
	"type": "FeatureCollection",
	"features": [
		{
			"type": "Feature",
			"properties": {
				"confidence": 9,
				"authenticationResultCode": "ValidCredentials",
				"brandLogoUri": "http://dev.virtualearth.net/Branding/logo_powered_by.png",
				"copyright": "Copyright © 2017 Microsoft and its suppliers. All rights reserved. This API cannot be accessed and the content and any results may not be used, reproduced or transmitted in any manner without express written permission from Microsoft Corporation.",
				"entityType": "Address",
				"matchCodes": [
					"Good"
				],
				"name": "7665 Kennedy Rd, Markham, ON L3R 0L7, Canada",
				"statusCode": 200,
				"statusDescription": "OK",
				"traceId": "4422695699fb489abe11f3f815bca693|BN20250135|7.7.0.0|",
				"addressLine": "7665 Kennedy Rd",
				"adminDistrict": "ON",
				"adminDistrict2": "York",
				"countryRegion": "Canada",
				"formattedAddress": "7665 Kennedy Rd, Markham, ON L3R 0L7, Canada",
				"locality": "Markham",
				"neighborhood": "North Milliken",
				"postalCode": "L3R 0L7"
			},
			"geometry": {
				"type": "Point",
				"coordinates": [
					-79.30382,
					43.84151
				]
			},
			"bbox": [
				-79.3053786,
				43.8403858,
				-79.3022614,
				43.8426342
			]
		}
	]
}
