{
	"type": "FeatureCollection",
	"features": [
		{
			"type": "Feature",
			"properties": {
				"confidence": 9,
				"authenticationResultCode": "ValidCredentials",
				"brandLogoUri": "http://dev.virtualearth.net/Branding/logo_powered_by.png",
				"copyright": "Copyright © 2017 Microsoft and its suppliers. All rights reserved. This API cannot be accessed and the content and any results may not be used, reproduced or transmitted in any manner without express written permission from Microsoft Corporation.",
				"entityType": "Address",
				"matchCodes": [
					"Good"
				],
				"name": "768 Erie St, Stratford, ON N5A, Canada",
				"statusCode": 200,
				"statusDescription": "OK",
				"traceId": "091fe182139a437896cc5710f1c63f84|BN20121763|7.7.0.0|",
				"addressLine": "768 Erie St",
				"adminDistrict": "ON",
				"adminDistrict2": "Perth",
				"countryRegion": "Canada",
				"formattedAddress": "768 Erie St, Stratford, ON N5A, Canada",
				"locality": "Stratford",
				"postalCode": "N5A"
			},
			"geometry": {
				"type": "Point",
				"coordinates": [
					-80.9976364,
					43.3541811
				]
			},
			"bbox": [
				-80.9991824,
				43.3530569,
				-80.9960904,
				43.3553052
			]
		}
	]
}
