{
	"type": "FeatureCollection",
	"features": [
		{
			"type": "Feature",
			"properties": {
				"confidence": 9,
				"authenticationResultCode": "ValidCredentials",
				"brandLogoUri": "http://dev.virtualearth.net/Branding/logo_powered_by.png",
				"copyright": "Copyright © 2017 Microsoft and its suppliers. All rights reserved. This API cannot be accessed and the content and any results may not be used, reproduced or transmitted in any manner without express written permission from Microsoft Corporation.",
				"entityType": "Address",
				"matchCodes": [
					"Good"
				],
				"name": "7685 Martin Grove Rd, Woodbridge, ON L4L 1B5, Canada",
				"statusCode": 200,
				"statusDescription": "OK",
				"traceId": "4e43df61c9a64511a3292113757e9bed|BN20260223|7.7.0.0|",
				"addressLine": "7685 Martin Grove Rd",
				"adminDistrict": "ON",
				"adminDistrict2": "York",
				"countryRegion": "Canada",
				"formattedAddress": "7685 Martin Grove Rd, Woodbridge, ON L4L 1B5, Canada",
				"locality": "Vaughan",
				"neighborhood": "Woodbridge",
				"postalCode": "L4L 1B5"
			},
			"geometry": {
				"type": "Point",
				"coordinates": [
					-79.6081899,
					43.77451
				]
			},
			"bbox": [
				-79.6097468,
				43.7733858,
				-79.606633,
				43.7756342
			]
		}
	]
}
