{
	"type": "FeatureCollection",
	"features": [
		{
			"type": "Feature",
			"properties": {
				"confidence": 9,
				"authenticationResultCode": "ValidCredentials",
				"brandLogoUri": "http://dev.virtualearth.net/Branding/logo_powered_by.png",
				"copyright": "Copyright © 2017 Microsoft and its suppliers. All rights reserved. This API cannot be accessed and the content and any results may not be used, reproduced or transmitted in any manner without express written permission from Microsoft Corporation.",
				"entityType": "Address",
				"matchCodes": [
					"Good"
				],
				"name": "770 Gana Ct, Mississauga, ON L5S 1P1, Canada",
				"statusCode": 200,
				"statusDescription": "OK",
				"traceId": "a19b374095924d6b9c90b9b6d53508d9|BN20200239|7.7.0.0|",
				"addressLine": "770 Gana Ct",
				"adminDistrict": "ON",
				"adminDistrict2": "Peel",
				"countryRegion": "Canada",
				"formattedAddress": "770 Gana Ct, Mississauga, ON L5S 1P1, Canada",
				"locality": "Mississauga",
				"postalCode": "L5S 1P1"
			},
			"geometry": {
				"type": "Point",
				"coordinates": [
					-79.69178,
					43.66698
				]
			},
			"bbox": [
				-79.6933341,
				43.6658558,
				-79.6902259,
				43.6681042
			]
		}
	]
}
