{
	"type": "FeatureCollection",
	"features": [
		{
			"type": "Feature",
			"properties": {
				"confidence": 9,
				"authenticationResultCode": "ValidCredentials",
				"brandLogoUri": "http://dev.virtualearth.net/Branding/logo_powered_by.png",
				"copyright": "Copyright © 2017 Microsoft and its suppliers. All rights reserved. This API cannot be accessed and the content and any results may not be used, reproduced or transmitted in any manner without express written permission from Microsoft Corporation.",
				"entityType": "Address",
				"matchCodes": [
					"Good"
				],
				"name": "773086 HWY-59, Norwich, ON N0J 1P0, Canada",
				"statusCode": 200,
				"statusDescription": "OK",
				"traceId": "f38345433f3740fa9eed7e82c7a6db05|BN20260231|7.7.0.0|",
				"addressLine": "773086 HWY-59",
				"adminDistrict": "ON",
				"adminDistrict2": "Oxford",
				"countryRegion": "Canada",
				"formattedAddress": "773086 HWY-59, Norwich, ON N0J 1P0, Canada",
				"locality": "Norwich",
				"postalCode": "N0J 1P0"
			},
			"geometry": {
				"type": "Point",
				"coordinates": [
					-80.5935971,
					42.9742128
				]
			},
			"bbox": [
				-80.5951336,
				42.9730886,
				-80.5920607,
				42.975337
			]
		}
	]
}
