{
	"type": "FeatureCollection",
	"features": [
		{
			"type": "Feature",
			"properties": {
				"confidence": 9,
				"authenticationResultCode": "ValidCredentials",
				"brandLogoUri": "http://dev.virtualearth.net/Branding/logo_powered_by.png",
				"copyright": "Copyright © 2017 Microsoft and its suppliers. All rights reserved. This API cannot be accessed and the content and any results may not be used, reproduced or transmitted in any manner without express written permission from Microsoft Corporation.",
				"entityType": "Address",
				"matchCodes": [
					"Good"
				],
				"name": "7769 Cedar St, Mission, BC V2V 3M6, Canada",
				"statusCode": 200,
				"statusDescription": "OK",
				"traceId": "daf6190f51084106b26cd82cd33fa7d1|BN20130447|7.7.0.0|",
				"addressLine": "7769 Cedar St",
				"adminDistrict": "BC",
				"adminDistrict2": "Fraser Valley",
				"countryRegion": "Canada",
				"formattedAddress": "7769 Cedar St, Mission, BC V2V 3M6, Canada",
				"locality": "Mission",
				"postalCode": "V2V 3M6"
			},
			"geometry": {
				"type": "Point",
				"coordinates": [
					-122.31673,
					49.14325
				]
			},
			"bbox": [
				-122.3184484,
				49.1421258,
				-122.3150116,
				49.1443742
			]
		}
	]
}
