{
	"type": "FeatureCollection",
	"features": [
		{
			"type": "Feature",
			"properties": {
				"confidence": 9,
				"authenticationResultCode": "ValidCredentials",
				"brandLogoUri": "http://dev.virtualearth.net/Branding/logo_powered_by.png",
				"copyright": "Copyright © 2017 Microsoft and its suppliers. All rights reserved. This API cannot be accessed and the content and any results may not be used, reproduced or transmitted in any manner without express written permission from Microsoft Corporation.",
				"entityType": "Address",
				"matchCodes": [
					"Good"
				],
				"name": "777 McKay Rd, Pickering, ON L1W 3A3, Canada",
				"statusCode": 200,
				"statusDescription": "OK",
				"traceId": "e8a0724b710f4a57bfca13247ce92b76|BN20220145|7.7.0.0|",
				"addressLine": "777 McKay Rd",
				"adminDistrict": "ON",
				"adminDistrict2": "Durham",
				"countryRegion": "Canada",
				"formattedAddress": "777 McKay Rd, Pickering, ON L1W 3A3, Canada",
				"locality": "Pickering",
				"postalCode": "L1W 3A3"
			},
			"geometry": {
				"type": "Point",
				"coordinates": [
					-79.05711,
					43.81979
				]
			},
			"bbox": [
				-79.058668,
				43.8186658,
				-79.055552,
				43.8209142
			]
		}
	]
}
