{
	"type": "FeatureCollection",
	"features": [
		{
			"type": "Feature",
			"properties": {
				"confidence": 9,
				"authenticationResultCode": "ValidCredentials",
				"brandLogoUri": "http://dev.virtualearth.net/Branding/logo_powered_by.png",
				"copyright": "Copyright © 2017 Microsoft and its suppliers. All rights reserved. This API cannot be accessed and the content and any results may not be used, reproduced or transmitted in any manner without express written permission from Microsoft Corporation.",
				"entityType": "Address",
				"matchCodes": [
					"Good"
				],
				"name": "78 5 Field Company Ln, Kingston, ON K7L, Canada",
				"statusCode": 200,
				"statusDescription": "OK",
				"traceId": "621a00af1e934e35b1dd9b869cccee74|BN20210145|7.7.0.0|",
				"addressLine": "78 5 Field Company Ln",
				"adminDistrict": "ON",
				"adminDistrict2": "Frontenac",
				"countryRegion": "Canada",
				"formattedAddress": "78 5 Field Company Ln, Kingston, ON K7L, Canada",
				"locality": "Kingston",
				"neighborhood": "Queens",
				"postalCode": "K7L 3N6"
			},
			"geometry": {
				"type": "Point",
				"coordinates": [
					-76.4935722,
					44.2261126
				]
			},
			"bbox": [
				-76.495141,
				44.2249885,
				-76.4920035,
				44.2272368
			]
		}
	]
}
