{
	"type": "FeatureCollection",
	"features": [
		{
			"type": "Feature",
			"properties": {
				"confidence": 9,
				"authenticationResultCode": "ValidCredentials",
				"brandLogoUri": "http://dev.virtualearth.net/Branding/logo_powered_by.png",
				"copyright": "Copyright © 2017 Microsoft and its suppliers. All rights reserved. This API cannot be accessed and the content and any results may not be used, reproduced or transmitted in any manner without express written permission from Microsoft Corporation.",
				"entityType": "Address",
				"matchCodes": [
					"Good"
				],
				"name": "78 Industrial Ave W, Penticton, BC V2A 6M2, Canada",
				"statusCode": 200,
				"statusDescription": "OK",
				"traceId": "348367f1484e45358475c86c7e699a82|BN20130625|7.7.0.0|",
				"addressLine": "78 Industrial Ave W",
				"adminDistrict": "BC",
				"adminDistrict2": "Okanagan-Similkameen",
				"countryRegion": "Canada",
				"formattedAddress": "78 Industrial Ave W, Penticton, BC V2A 6M2, Canada",
				"locality": "Penticton",
				"postalCode": "V2A 6M2"
			},
			"geometry": {
				"type": "Point",
				"coordinates": [
					-119.58707,
					49.47969
				]
			},
			"bbox": [
				-119.5888002,
				49.4785658,
				-119.5853398,
				49.4808142
			]
		}
	]
}
