{
	"type": "FeatureCollection",
	"features": [
		{
			"type": "Feature",
			"properties": {
				"confidence": 9,
				"authenticationResultCode": "ValidCredentials",
				"brandLogoUri": "http://dev.virtualearth.net/Branding/logo_powered_by.png",
				"copyright": "Copyright © 2017 Microsoft and its suppliers. All rights reserved. This API cannot be accessed and the content and any results may not be used, reproduced or transmitted in any manner without express written permission from Microsoft Corporation.",
				"entityType": "Address",
				"matchCodes": [
					"Good"
				],
				"name": "780 Spruce Ave, Victoria, BC V8T 5A5, Canada",
				"statusCode": 200,
				"statusDescription": "OK",
				"traceId": "4ac7a6bec5014445a268eeb02117c637|BN20200137|7.7.0.0|",
				"addressLine": "780 Spruce Ave",
				"adminDistrict": "BC",
				"adminDistrict2": "Capital",
				"countryRegion": "Canada",
				"formattedAddress": "780 Spruce Ave, Victoria, BC V8T 5A5, Canada",
				"locality": "Victoria",
				"neighborhood": "Burnside",
				"postalCode": "V8T 5A5"
			},
			"geometry": {
				"type": "Point",
				"coordinates": [
					-123.3682706,
					48.4437148
				]
			},
			"bbox": [
				-123.3699652,
				48.4425906,
				-123.3665759,
				48.4448389
			]
		}
	]
}
