{
	"type": "FeatureCollection",
	"features": [
		{
			"type": "Feature",
			"properties": {
				"confidence": 9,
				"authenticationResultCode": "ValidCredentials",
				"brandLogoUri": "http://dev.virtualearth.net/Branding/logo_powered_by.png",
				"copyright": "Copyright © 2017 Microsoft and its suppliers. All rights reserved. This API cannot be accessed and the content and any results may not be used, reproduced or transmitted in any manner without express written permission from Microsoft Corporation.",
				"entityType": "Address",
				"matchCodes": [
					"Good"
				],
				"name": "780 Central Ave, Kings, NS B0P, Canada",
				"statusCode": 200,
				"statusDescription": "OK",
				"traceId": "915e486bfc304bef9715e96adf1c83b6|BN20260223|7.7.0.0|",
				"addressLine": "780 Central Ave",
				"adminDistrict": "NS",
				"adminDistrict2": "Kings",
				"countryRegion": "Canada",
				"formattedAddress": "780 Central Ave, Kings, NS B0P, Canada",
				"locality": "Kings",
				"neighborhood": "Greenwood",
				"postalCode": "B0P 1N0"
			},
			"geometry": {
				"type": "Point",
				"coordinates": [
					-64.93601,
					44.96997
				]
			},
			"bbox": [
				-64.937599,
				44.9688458,
				-64.934421,
				44.9710942
			]
		}
	]
}
