{
	"type": "FeatureCollection",
	"features": [
		{
			"type": "Feature",
			"properties": {
				"confidence": 9,
				"authenticationResultCode": "ValidCredentials",
				"brandLogoUri": "http://dev.virtualearth.net/Branding/logo_powered_by.png",
				"copyright": "Copyright © 2017 Microsoft and its suppliers. All rights reserved. This API cannot be accessed and the content and any results may not be used, reproduced or transmitted in any manner without express written permission from Microsoft Corporation.",
				"entityType": "Address",
				"matchCodes": [
					"Good"
				],
				"name": "79 Industrial Park Rd, Whitewater Region, ON K8A, Canada",
				"statusCode": 200,
				"statusDescription": "OK",
				"traceId": "9bf5ee9263d6444a844557989d515ba6|BN20200239|7.7.0.0|",
				"addressLine": "79 Industrial Park Rd",
				"adminDistrict": "ON",
				"adminDistrict2": "Renfrew",
				"countryRegion": "Canada",
				"formattedAddress": "79 Industrial Park Rd, Whitewater Region, ON K8A, Canada",
				"locality": "Whitewater Region",
				"postalCode": "K8A 6X9"
			},
			"geometry": {
				"type": "Point",
				"coordinates": [
					-77.01729,
					45.76901
				]
			},
			"bbox": [
				-77.0189016,
				45.7678858,
				-77.0156784,
				45.7701342
			]
		}
	]
}
