{
	"type": "FeatureCollection",
	"features": [
		{
			"type": "Feature",
			"properties": {
				"confidence": 9,
				"authenticationResultCode": "ValidCredentials",
				"brandLogoUri": "http://dev.virtualearth.net/Branding/logo_powered_by.png",
				"copyright": "Copyright © 2017 Microsoft and its suppliers. All rights reserved. This API cannot be accessed and the content and any results may not be used, reproduced or transmitted in any manner without express written permission from Microsoft Corporation.",
				"entityType": "Address",
				"matchCodes": [
					"Good"
				],
				"name": "8 Athabaska Rd, Barrie, ON L4N 8C9, Canada",
				"statusCode": 200,
				"statusDescription": "OK",
				"traceId": "e0100751c1354469aacd6509aa6a8a00|BN20300154|7.7.0.0|",
				"addressLine": "8 Athabaska Rd",
				"adminDistrict": "ON",
				"adminDistrict2": "Simcoe",
				"countryRegion": "Canada",
				"formattedAddress": "8 Athabaska Rd, Barrie, ON L4N 8C9, Canada",
				"locality": "Barrie",
				"neighborhood": "Holly",
				"postalCode": "L4N 8C9"
			},
			"geometry": {
				"type": "Point",
				"coordinates": [
					-79.72756,
					44.32196
				]
			},
			"bbox": [
				-79.7291313,
				44.3208358,
				-79.7259887,
				44.3230842
			]
		}
	]
}
