{
	"type": "FeatureCollection",
	"features": [
		{
			"type": "Feature",
			"properties": {
				"confidence": 9,
				"authenticationResultCode": "ValidCredentials",
				"brandLogoUri": "http://dev.virtualearth.net/Branding/logo_powered_by.png",
				"copyright": "Copyright © 2017 Microsoft and its suppliers. All rights reserved. This API cannot be accessed and the content and any results may not be used, reproduced or transmitted in any manner without express written permission from Microsoft Corporation.",
				"entityType": "Address",
				"matchCodes": [
					"Good"
				],
				"name": "8 Rue Boucher, Campbellton, NB E3N 2P1, Canada",
				"statusCode": 200,
				"statusDescription": "OK",
				"traceId": "606a1f7ed57648a6969c0f0590e2a7a9|BN20121763|7.7.0.0|",
				"addressLine": "8 Rue Boucher",
				"adminDistrict": "NB",
				"adminDistrict2": "Restigouche",
				"countryRegion": "Canada",
				"formattedAddress": "8 Rue Boucher, Campbellton, NB E3N 2P1, Canada",
				"locality": "Campbellton",
				"postalCode": "E3N 2P1"
			},
			"geometry": {
				"type": "Point",
				"coordinates": [
					-66.6910599,
					47.99681
				]
			},
			"bbox": [
				-66.6927398,
				47.9956858,
				-66.68938,
				47.9979342
			]
		}
	]
}
