{
	"type": "FeatureCollection",
	"features": [
		{
			"type": "Feature",
			"properties": {
				"confidence": 9,
				"authenticationResultCode": "ValidCredentials",
				"brandLogoUri": "http://dev.virtualearth.net/Branding/logo_powered_by.png",
				"copyright": "Copyright © 2017 Microsoft and its suppliers. All rights reserved. This API cannot be accessed and the content and any results may not be used, reproduced or transmitted in any manner without express written permission from Microsoft Corporation.",
				"entityType": "Address",
				"matchCodes": [
					"Good"
				],
				"name": "8 Green Ln, Thornhill, ON L3T 7P7, Canada",
				"statusCode": 200,
				"statusDescription": "OK",
				"traceId": "534fc0ca689840349498f3bfd6c39a2a|BN20181720|7.7.0.0|",
				"addressLine": "8 Green Ln",
				"adminDistrict": "ON",
				"adminDistrict2": "York",
				"countryRegion": "Canada",
				"formattedAddress": "8 Green Ln, Thornhill, ON L3T 7P7, Canada",
				"locality": "Markham",
				"neighborhood": "Thornhill",
				"postalCode": "L3T 7P7"
			},
			"geometry": {
				"type": "Point",
				"coordinates": [
					-79.40034,
					43.82192
				]
			},
			"bbox": [
				-79.4018981,
				43.8207958,
				-79.3987819,
				43.8230442
			]
		}
	]
}
