{
	"type": "FeatureCollection",
	"features": [
		{
			"type": "Feature",
			"properties": {
				"confidence": 9,
				"authenticationResultCode": "ValidCredentials",
				"brandLogoUri": "http://dev.virtualearth.net/Branding/logo_powered_by.png",
				"copyright": "Copyright © 2017 Microsoft and its suppliers. All rights reserved. This API cannot be accessed and the content and any results may not be used, reproduced or transmitted in any manner without express written permission from Microsoft Corporation.",
				"entityType": "Address",
				"matchCodes": [
					"Good"
				],
				"name": "8 Karl Ct, Thornhill, ON L4J 8H7, Canada",
				"statusCode": 200,
				"statusDescription": "OK",
				"traceId": "0f3dab2cda0841d7bf2780a433bc5bc7|BN20130634|7.7.0.0|",
				"addressLine": "8 Karl Ct",
				"adminDistrict": "ON",
				"adminDistrict2": "York",
				"countryRegion": "Canada",
				"formattedAddress": "8 Karl Ct, Thornhill, ON L4J 8H7, Canada",
				"locality": "Vaughan",
				"neighborhood": "Thornhill",
				"postalCode": "L4J 8H7"
			},
			"geometry": {
				"type": "Point",
				"coordinates": [
					-79.45858,
					43.81204
				]
			},
			"bbox": [
				-79.4601378,
				43.8109158,
				-79.4570222,
				43.8131642
			]
		}
	]
}
