{
	"type": "FeatureCollection",
	"features": [
		{
			"type": "Feature",
			"properties": {
				"confidence": 9,
				"authenticationResultCode": "ValidCredentials",
				"brandLogoUri": "http://dev.virtualearth.net/Branding/logo_powered_by.png",
				"copyright": "Copyright © 2017 Microsoft and its suppliers. All rights reserved. This API cannot be accessed and the content and any results may not be used, reproduced or transmitted in any manner without express written permission from Microsoft Corporation.",
				"entityType": "Address",
				"matchCodes": [
					"Good"
				],
				"name": "8 King St E, Toronto, ON M5C 1B5, Canada",
				"statusCode": 200,
				"statusDescription": "OK",
				"traceId": "6e691414d1354e859c1ec423b30776fe|BN20190653|7.7.0.0|",
				"addressLine": "8 King St E",
				"adminDistrict": "ON",
				"adminDistrict2": "Toronto",
				"countryRegion": "Canada",
				"formattedAddress": "8 King St E, Toronto, ON M5C 1B5, Canada",
				"locality": "Toronto",
				"neighborhood": "Church-Yonge Corridor",
				"postalCode": "M5C 1B5"
			},
			"geometry": {
				"type": "Point",
				"coordinates": [
					-79.37757,
					43.64941
				]
			},
			"bbox": [
				-79.3791236,
				43.6482858,
				-79.3760164,
				43.6505342
			]
		}
	]
}
