{
	"type": "FeatureCollection",
	"features": [
		{
			"type": "Feature",
			"properties": {
				"confidence": 9,
				"authenticationResultCode": "ValidCredentials",
				"brandLogoUri": "http://dev.virtualearth.net/Branding/logo_powered_by.png",
				"copyright": "Copyright © 2017 Microsoft and its suppliers. All rights reserved. This API cannot be accessed and the content and any results may not be used, reproduced or transmitted in any manner without express written permission from Microsoft Corporation.",
				"entityType": "Address",
				"matchCodes": [
					"Good"
				],
				"name": "80 Midpark Rd, London, ON N6N 1B3, Canada",
				"statusCode": 200,
				"statusDescription": "OK",
				"traceId": "1781d3c9181d4043a4159e409ce52232|BN20131519|7.7.0.0|",
				"addressLine": "80 Midpark Rd",
				"adminDistrict": "ON",
				"adminDistrict2": "Middlesex",
				"countryRegion": "Canada",
				"formattedAddress": "80 Midpark Rd, London, ON N6N 1B3, Canada",
				"locality": "London",
				"neighborhood": "Westminster",
				"postalCode": "N6N 1B3"
			},
			"geometry": {
				"type": "Point",
				"coordinates": [
					-81.1863,
					42.9311999
				]
			},
			"bbox": [
				-81.1878354,
				42.9300757,
				-81.1847646,
				42.9323241
			]
		}
	]
}
