{
	"type": "FeatureCollection",
	"features": [
		{
			"type": "Feature",
			"properties": {
				"confidence": 9,
				"authenticationResultCode": "ValidCredentials",
				"brandLogoUri": "http://dev.virtualearth.net/Branding/logo_powered_by.png",
				"copyright": "Copyright © 2017 Microsoft and its suppliers. All rights reserved. This API cannot be accessed and the content and any results may not be used, reproduced or transmitted in any manner without express written permission from Microsoft Corporation.",
				"entityType": "Address",
				"matchCodes": [
					"Good"
				],
				"name": "8065 138 St, Surrey, BC V3W 8M3, Canada",
				"statusCode": 200,
				"statusDescription": "OK",
				"traceId": "3ae4452e089d4c85ae9d05c8ddfa8165|BN20130625|7.7.0.0|",
				"addressLine": "8065 138 St",
				"adminDistrict": "BC",
				"adminDistrict2": "Greater Vancouver",
				"countryRegion": "Canada",
				"formattedAddress": "8065 138 St, Surrey, BC V3W 8M3, Canada",
				"locality": "Surrey",
				"neighborhood": "Newton",
				"postalCode": "V3W 8M3"
			},
			"geometry": {
				"type": "Point",
				"coordinates": [
					-122.83985,
					49.1497699
				]
			},
			"bbox": [
				-122.8415687,
				49.1486457,
				-122.8381313,
				49.1508941
			]
		}
	]
}
