{
	"type": "FeatureCollection",
	"features": [
		{
			"type": "Feature",
			"properties": {
				"confidence": 9,
				"authenticationResultCode": "ValidCredentials",
				"brandLogoUri": "http://dev.virtualearth.net/Branding/logo_powered_by.png",
				"copyright": "Copyright © 2017 Microsoft and its suppliers. All rights reserved. This API cannot be accessed and the content and any results may not be used, reproduced or transmitted in any manner without express written permission from Microsoft Corporation.",
				"entityType": "Address",
				"matchCodes": [
					"Good"
				],
				"name": "810 Phillips St, Portage la Prairie, MB R1N 4A4, Canada",
				"statusCode": 200,
				"statusDescription": "OK",
				"traceId": "bc0b99482c44447fb84ecdf760a79c29|BN20130431|7.7.0.0|",
				"addressLine": "810 Phillips St",
				"adminDistrict": "MB",
				"adminDistrict2": "Manitoba",
				"countryRegion": "Canada",
				"formattedAddress": "810 Phillips St, Portage la Prairie, MB R1N 4A4, Canada",
				"locality": "Portage la Prairie",
				"postalCode": "R1N 4A4"
			},
			"geometry": {
				"type": "Point",
				"coordinates": [
					-98.2721193,
					49.9845318
				]
			},
			"bbox": [
				-98.2738676,
				49.9834076,
				-98.270371,
				49.9856559
			]
		}
	]
}
