{
	"type": "FeatureCollection",
	"features": [
		{
			"type": "Feature",
			"properties": {
				"confidence": 9,
				"authenticationResultCode": "ValidCredentials",
				"brandLogoUri": "http://dev.virtualearth.net/Branding/logo_powered_by.png",
				"copyright": "Copyright © 2017 Microsoft and its suppliers. All rights reserved. This API cannot be accessed and the content and any results may not be used, reproduced or transmitted in any manner without express written permission from Microsoft Corporation.",
				"entityType": "Address",
				"matchCodes": [
					"Good"
				],
				"name": "8105 49 Avenue Clos, Red Deer, AB T4P 2V5, Canada",
				"statusCode": 200,
				"statusDescription": "OK",
				"traceId": "75797e92d0a54b1092c4415631052c88|BN20130620|7.7.0.0|",
				"addressLine": "8105 49 Avenue Clos",
				"adminDistrict": "AB",
				"adminDistrict2": "Alberta",
				"countryRegion": "Canada",
				"formattedAddress": "8105 49 Avenue Clos, Red Deer, AB T4P 2V5, Canada",
				"locality": "Red Deer",
				"postalCode": "T4P 2V5"
			},
			"geometry": {
				"type": "Point",
				"coordinates": [
					-113.81034,
					52.31618
				]
			},
			"bbox": [
				-113.8121789,
				52.3150558,
				-113.8085011,
				52.3173042
			]
		}
	]
}
