{
	"type": "FeatureCollection",
	"features": [
		{
			"type": "Feature",
			"properties": {
				"confidence": 9,
				"authenticationResultCode": "ValidCredentials",
				"brandLogoUri": "http://dev.virtualearth.net/Branding/logo_powered_by.png",
				"copyright": "Copyright © 2017 Microsoft and its suppliers. All rights reserved. This API cannot be accessed and the content and any results may not be used, reproduced or transmitted in any manner without express written permission from Microsoft Corporation.",
				"entityType": "Address",
				"matchCodes": [
					"Good"
				],
				"name": "8117 102 Ave, Peace River, AB T8S 1M6, Canada",
				"statusCode": 200,
				"statusDescription": "OK",
				"traceId": "fdaeef606ffd42af83482aa80052817e|BN20121764|7.7.0.0|",
				"addressLine": "8117 102 Ave",
				"adminDistrict": "AB",
				"adminDistrict2": "Alberta",
				"countryRegion": "Canada",
				"formattedAddress": "8117 102 Ave, Peace River, AB T8S 1M6, Canada",
				"locality": "Peace River",
				"postalCode": "T8S 1M6"
			},
			"geometry": {
				"type": "Point",
				"coordinates": [
					-117.32823,
					56.23204
				]
			},
			"bbox": [
				-117.3302525,
				56.2309158,
				-117.3262075,
				56.2331642
			]
		}
	]
}
