{
	"type": "FeatureCollection",
	"features": [
		{
			"type": "Feature",
			"properties": {
				"confidence": 9,
				"authenticationResultCode": "ValidCredentials",
				"brandLogoUri": "http://dev.virtualearth.net/Branding/logo_powered_by.png",
				"copyright": "Copyright © 2017 Microsoft and its suppliers. All rights reserved. This API cannot be accessed and the content and any results may not be used, reproduced or transmitted in any manner without express written permission from Microsoft Corporation.",
				"entityType": "Address",
				"matchCodes": [
					"Good"
				],
				"name": "811 58th St E, Saskatoon, SK S7K 6X5, Canada",
				"statusCode": 200,
				"statusDescription": "OK",
				"traceId": "f49cf2c3af974734ae33769a27a4c169|BN20280152|7.7.0.0|",
				"addressLine": "811 58th St E",
				"adminDistrict": "SK",
				"adminDistrict2": "Saskatchewan",
				"countryRegion": "Canada",
				"formattedAddress": "811 58th St E, Saskatoon, SK S7K 6X5, Canada",
				"locality": "Saskatoon",
				"neighborhood": "Hudson Bay Industrial",
				"postalCode": "S7K 6X5"
			},
			"geometry": {
				"type": "Point",
				"coordinates": [
					-106.6562299,
					52.18335
				]
			},
			"bbox": [
				-106.6580633,
				52.1822258,
				-106.6543965,
				52.1844742
			]
		}
	]
}
