{
	"type": "FeatureCollection",
	"features": [
		{
			"type": "Feature",
			"properties": {
				"confidence": 9,
				"authenticationResultCode": "ValidCredentials",
				"brandLogoUri": "http://dev.virtualearth.net/Branding/logo_powered_by.png",
				"copyright": "Copyright © 2017 Microsoft and its suppliers. All rights reserved. This API cannot be accessed and the content and any results may not be used, reproduced or transmitted in any manner without express written permission from Microsoft Corporation.",
				"entityType": "Address",
				"matchCodes": [
					"Good"
				],
				"name": "8128 River Way, Delta, BC V4G 1K5, Canada",
				"statusCode": 200,
				"statusDescription": "OK",
				"traceId": "abce180a92074de09a377e0fe162ca4b|BN20130431|7.7.0.0|",
				"addressLine": "8128 River Way",
				"adminDistrict": "BC",
				"adminDistrict2": "Greater Vancouver",
				"countryRegion": "Canada",
				"formattedAddress": "8128 River Way, Delta, BC V4G 1K5, Canada",
				"locality": "Delta",
				"postalCode": "V4G 1K5"
			},
			"geometry": {
				"type": "Point",
				"coordinates": [
					-122.9983243,
					49.1450764
				]
			},
			"bbox": [
				-123.0000428,
				49.1439523,
				-122.9966058,
				49.1462006
			]
		}
	]
}
