{
	"type": "FeatureCollection",
	"features": [
		{
			"type": "Feature",
			"properties": {
				"confidence": 9,
				"authenticationResultCode": "ValidCredentials",
				"brandLogoUri": "http://dev.virtualearth.net/Branding/logo_powered_by.png",
				"copyright": "Copyright © 2017 Microsoft and its suppliers. All rights reserved. This API cannot be accessed and the content and any results may not be used, reproduced or transmitted in any manner without express written permission from Microsoft Corporation.",
				"entityType": "Address",
				"matchCodes": [
					"Good"
				],
				"name": "815 Mackay St, Regina, SK S4N 2S3, Canada",
				"statusCode": 200,
				"statusDescription": "OK",
				"traceId": "e3cbde53b32945cca7f1f33541f02287|BN20130719|7.7.0.0|",
				"addressLine": "815 Mackay St",
				"adminDistrict": "SK",
				"adminDistrict2": "Saskatchewan",
				"countryRegion": "Canada",
				"formattedAddress": "815 Mackay St, Regina, SK S4N 2S3, Canada",
				"locality": "Regina",
				"postalCode": "S4N 2S3"
			},
			"geometry": {
				"type": "Point",
				"coordinates": [
					-104.57957,
					50.46529
				]
			},
			"bbox": [
				-104.581336,
				50.4641658,
				-104.577804,
				50.4664142
			]
		}
	]
}
