{
	"type": "FeatureCollection",
	"features": [
		{
			"type": "Feature",
			"properties": {
				"confidence": 9,
				"authenticationResultCode": "ValidCredentials",
				"brandLogoUri": "http://dev.virtualearth.net/Branding/logo_powered_by.png",
				"copyright": "Copyright © 2017 Microsoft and its suppliers. All rights reserved. This API cannot be accessed and the content and any results may not be used, reproduced or transmitted in any manner without express written permission from Microsoft Corporation.",
				"entityType": "Address",
				"matchCodes": [
					"Good"
				],
				"name": "8187 Yonge St, Thornhill, ON L3T 2C6, Canada",
				"statusCode": 200,
				"statusDescription": "OK",
				"traceId": "ae5d377dee2948b8920d1883d997009f|BN20121762|7.7.0.0|",
				"addressLine": "8187 Yonge St",
				"adminDistrict": "ON",
				"adminDistrict2": "York",
				"countryRegion": "Canada",
				"formattedAddress": "8187 Yonge St, Thornhill, ON L3T 2C6, Canada",
				"locality": "Markham",
				"neighborhood": "Thornhill",
				"postalCode": "L3T 2C6"
			},
			"geometry": {
				"type": "Point",
				"coordinates": [
					-79.42645,
					43.82727
				]
			},
			"bbox": [
				-79.4280082,
				43.8261458,
				-79.4248918,
				43.8283942
			]
		}
	]
}
