{
	"type": "FeatureCollection",
	"features": [
		{
			"type": "Feature",
			"properties": {
				"confidence": 9,
				"authenticationResultCode": "ValidCredentials",
				"brandLogoUri": "http://dev.virtualearth.net/Branding/logo_powered_by.png",
				"copyright": "Copyright © 2017 Microsoft and its suppliers. All rights reserved. This API cannot be accessed and the content and any results may not be used, reproduced or transmitted in any manner without express written permission from Microsoft Corporation.",
				"entityType": "Address",
				"matchCodes": [
					"Good"
				],
				"name": "82 Industry St, York, ON M6M 4L7, Canada",
				"statusCode": 200,
				"statusDescription": "OK",
				"traceId": "8488f1c8872f4849a1deaa5537e39da2|BN20130431|7.7.0.0|",
				"addressLine": "82 Industry St",
				"adminDistrict": "ON",
				"adminDistrict2": "Toronto",
				"countryRegion": "Canada",
				"formattedAddress": "82 Industry St, York, ON M6M 4L7, Canada",
				"locality": "Toronto",
				"neighborhood": "Beechborough-Greenbrook",
				"postalCode": "M6M 4L7"
			},
			"geometry": {
				"type": "Point",
				"coordinates": [
					-79.48891,
					43.69206
				]
			},
			"bbox": [
				-79.4904647,
				43.6909358,
				-79.4873553,
				43.6931842
			]
		}
	]
}
