{
	"type": "FeatureCollection",
	"features": [
		{
			"type": "Feature",
			"properties": {
				"confidence": 9,
				"authenticationResultCode": "ValidCredentials",
				"brandLogoUri": "http://dev.virtualearth.net/Branding/logo_powered_by.png",
				"copyright": "Copyright © 2017 Microsoft and its suppliers. All rights reserved. This API cannot be accessed and the content and any results may not be used, reproduced or transmitted in any manner without express written permission from Microsoft Corporation.",
				"entityType": "Address",
				"matchCodes": [
					"Good"
				],
				"name": "8201 HWY-19, Queens, PE C0A 1C0, Canada",
				"statusCode": 200,
				"statusDescription": "OK",
				"traceId": "7591a29a7e7546038e22dc9c43caf382|BN20130447|7.7.0.0|",
				"addressLine": "8201 HWY-19",
				"adminDistrict": "PE",
				"adminDistrict2": "Queens",
				"countryRegion": "Canada",
				"formattedAddress": "8201 HWY-19, Queens, PE C0A 1C0, Canada",
				"locality": "Queens",
				"postalCode": "C0A 1C0"
			},
			"geometry": {
				"type": "Point",
				"coordinates": [
					-63.3904539,
					46.1788026
				]
			},
			"bbox": [
				-63.3920775,
				46.1776785,
				-63.3888304,
				46.1799268
			]
		}
	]
}
