{
	"type": "FeatureCollection",
	"features": [
		{
			"type": "Feature",
			"properties": {
				"confidence": 9,
				"authenticationResultCode": "ValidCredentials",
				"brandLogoUri": "http://dev.virtualearth.net/Branding/logo_powered_by.png",
				"copyright": "Copyright © 2017 Microsoft and its suppliers. All rights reserved. This API cannot be accessed and the content and any results may not be used, reproduced or transmitted in any manner without express written permission from Microsoft Corporation.",
				"entityType": "Address",
				"matchCodes": [
					"Good"
				],
				"name": "828 Brock St N, Whitby, ON L1N 4J5, Canada",
				"statusCode": 200,
				"statusDescription": "OK",
				"traceId": "67fde9142a1a4d09bdf698e821cd1975|BN20121763|7.7.0.0|",
				"addressLine": "828 Brock St N",
				"adminDistrict": "ON",
				"adminDistrict2": "Durham",
				"countryRegion": "Canada",
				"formattedAddress": "828 Brock St N, Whitby, ON L1N 4J5, Canada",
				"locality": "Whitby",
				"postalCode": "L1N 4J5"
			},
			"geometry": {
				"type": "Point",
				"coordinates": [
					-78.9469168,
					43.8906265
				]
			},
			"bbox": [
				-78.9484766,
				43.8895023,
				-78.9453569,
				43.8917506
			]
		}
	]
}
