{
	"type": "FeatureCollection",
	"features": [
		{
			"type": "Feature",
			"properties": {
				"confidence": 9,
				"authenticationResultCode": "ValidCredentials",
				"brandLogoUri": "http://dev.virtualearth.net/Branding/logo_powered_by.png",
				"copyright": "Copyright © 2017 Microsoft and its suppliers. All rights reserved. This API cannot be accessed and the content and any results may not be used, reproduced or transmitted in any manner without express written permission from Microsoft Corporation.",
				"entityType": "Address",
				"matchCodes": [
					"Good"
				],
				"name": "830 Rue des Actionnaires, Chicoutimi, QC G7J 4N3, Canada",
				"statusCode": 200,
				"statusDescription": "OK",
				"traceId": "a064fd0b31564b78a0f3d4979b45bd5d|BN20280152|7.7.0.0|",
				"addressLine": "830 Rue des Actionnaires",
				"adminDistrict": "QC",
				"adminDistrict2": "Saguenay",
				"countryRegion": "Canada",
				"formattedAddress": "830 Rue des Actionnaires, Chicoutimi, QC G7J 4N3, Canada",
				"locality": "Saguenay",
				"neighborhood": "Chicoutimi",
				"postalCode": "G7J 4N3"
			},
			"geometry": {
				"type": "Point",
				"coordinates": [
					-71.09927,
					48.39914
				]
			},
			"bbox": [
				-71.1009632,
				48.3980158,
				-71.0975768,
				48.4002642
			]
		}
	]
}
