{
	"type": "FeatureCollection",
	"features": [
		{
			"type": "Feature",
			"properties": {
				"confidence": 9,
				"authenticationResultCode": "ValidCredentials",
				"brandLogoUri": "http://dev.virtualearth.net/Branding/logo_powered_by.png",
				"copyright": "Copyright © 2017 Microsoft and its suppliers. All rights reserved. This API cannot be accessed and the content and any results may not be used, reproduced or transmitted in any manner without express written permission from Microsoft Corporation.",
				"entityType": "Address",
				"matchCodes": [
					"Good"
				],
				"name": "832 Crowells St, Oshawa, ON L1K 1X3, Canada",
				"statusCode": 200,
				"statusDescription": "OK",
				"traceId": "ef5ed4c4ffb845d09f15ba53393456b4|BN20240253|7.7.0.0|",
				"addressLine": "832 Crowells St",
				"adminDistrict": "ON",
				"adminDistrict2": "Durham",
				"countryRegion": "Canada",
				"formattedAddress": "832 Crowells St, Oshawa, ON L1K 1X3, Canada",
				"locality": "Oshawa",
				"neighborhood": "Pinecrest",
				"postalCode": "L1K 1X3"
			},
			"geometry": {
				"type": "Point",
				"coordinates": [
					-78.85073,
					43.92573
				]
			},
			"bbox": [
				-78.8522908,
				43.9246058,
				-78.8491692,
				43.9268542
			]
		}
	]
}
