{
	"type": "FeatureCollection",
	"features": [
		{
			"type": "Feature",
			"properties": {
				"confidence": 9,
				"authenticationResultCode": "ValidCredentials",
				"brandLogoUri": "http://dev.virtualearth.net/Branding/logo_powered_by.png",
				"copyright": "Copyright © 2017 Microsoft and its suppliers. All rights reserved. This API cannot be accessed and the content and any results may not be used, reproduced or transmitted in any manner without express written permission from Microsoft Corporation.",
				"entityType": "Address",
				"matchCodes": [
					"Good"
				],
				"name": "8338 Crofton Rd, North Cowichan, BC V0R, Canada",
				"statusCode": 200,
				"statusDescription": "OK",
				"traceId": "069ead3fe534442085deaa15110c37bd|BN20210145|7.7.0.0|",
				"addressLine": "8338 Crofton Rd",
				"adminDistrict": "BC",
				"adminDistrict2": "Cowichan Valley",
				"countryRegion": "Canada",
				"formattedAddress": "8338 Crofton Rd, North Cowichan, BC V0R, Canada",
				"locality": "North Cowichan",
				"neighborhood": "Crofton",
				"postalCode": "V0R 1R0"
			},
			"geometry": {
				"type": "Point",
				"coordinates": [
					-123.6511,
					48.87155
				]
			},
			"bbox": [
				-123.6528091,
				48.8704258,
				-123.6493909,
				48.8726742
			]
		}
	]
}
