{
	"type": "FeatureCollection",
	"features": [
		{
			"type": "Feature",
			"properties": {
				"confidence": 9,
				"authenticationResultCode": "ValidCredentials",
				"brandLogoUri": "http://dev.virtualearth.net/Branding/logo_powered_by.png",
				"copyright": "Copyright © 2017 Microsoft and its suppliers. All rights reserved. This API cannot be accessed and the content and any results may not be used, reproduced or transmitted in any manner without express written permission from Microsoft Corporation.",
				"entityType": "Address",
				"matchCodes": [
					"Good"
				],
				"name": "84 Trojan Cres, Markham, ON L6C 2N4, Canada",
				"statusCode": 200,
				"statusDescription": "OK",
				"traceId": "2e9f91c19d874de49305f5759216b1aa|BN20130631|7.7.0.0|",
				"addressLine": "84 Trojan Cres",
				"adminDistrict": "ON",
				"adminDistrict2": "York",
				"countryRegion": "Canada",
				"formattedAddress": "84 Trojan Cres, Markham, ON L6C 2N4, Canada",
				"locality": "Markham",
				"postalCode": "L6C 2N4"
			},
			"geometry": {
				"type": "Point",
				"coordinates": [
					-79.3097499,
					43.8984499
				]
			},
			"bbox": [
				-79.31131,
				43.8973257,
				-79.3081898,
				43.8995741
			]
		}
	]
}
