{
	"type": "FeatureCollection",
	"features": [
		{
			"type": "Feature",
			"properties": {
				"confidence": 9,
				"authenticationResultCode": "ValidCredentials",
				"brandLogoUri": "http://dev.virtualearth.net/Branding/logo_powered_by.png",
				"copyright": "Copyright © 2017 Microsoft and its suppliers. All rights reserved. This API cannot be accessed and the content and any results may not be used, reproduced or transmitted in any manner without express written permission from Microsoft Corporation.",
				"entityType": "Address",
				"matchCodes": [
					"Good"
				],
				"name": "843 Main St, Sydney Mines, NS B1V 2L9, Canada",
				"statusCode": 200,
				"statusDescription": "OK",
				"traceId": "54af3929bb464604b6398d7048fccd8f|BN20130620|7.7.0.0|",
				"addressLine": "843 Main St",
				"adminDistrict": "NS",
				"adminDistrict2": "Cape Breton",
				"countryRegion": "Canada",
				"formattedAddress": "843 Main St, Sydney Mines, NS B1V 2L9, Canada",
				"locality": "Cape Breton",
				"neighborhood": "Sydney Mines",
				"postalCode": "B1V 2L9"
			},
			"geometry": {
				"type": "Point",
				"coordinates": [
					-60.23342,
					46.24181
				]
			},
			"bbox": [
				-60.2350454,
				46.2406858,
				-60.2317946,
				46.2429342
			]
		}
	]
}
