{
	"type": "FeatureCollection",
	"features": [
		{
			"type": "Feature",
			"properties": {
				"confidence": 9,
				"authenticationResultCode": "ValidCredentials",
				"brandLogoUri": "http://dev.virtualearth.net/Branding/logo_powered_by.png",
				"copyright": "Copyright © 2017 Microsoft and its suppliers. All rights reserved. This API cannot be accessed and the content and any results may not be used, reproduced or transmitted in any manner without express written permission from Microsoft Corporation.",
				"entityType": "Address",
				"matchCodes": [
					"Good"
				],
				"name": "8464 9th Line N, Halton Hills, ON L0P, Canada",
				"statusCode": 200,
				"statusDescription": "OK",
				"traceId": "a7907ce0e8ca4ea5a168511f06cf6907|BN20130423|7.7.0.0|",
				"addressLine": "8464 9th Line N",
				"adminDistrict": "ON",
				"adminDistrict2": "Halton",
				"countryRegion": "Canada",
				"formattedAddress": "8464 9th Line N, Halton Hills, ON L0P, Canada",
				"locality": "Halton Hills",
				"postalCode": "L0P 1K0"
			},
			"geometry": {
				"type": "Point",
				"coordinates": [
					-79.8288817,
					43.5947217
				]
			},
			"bbox": [
				-79.8304339,
				43.5935975,
				-79.8273295,
				43.5958458
			]
		}
	]
}
