{
	"type": "FeatureCollection",
	"features": [
		{
			"type": "Feature",
			"properties": {
				"confidence": 9,
				"authenticationResultCode": "ValidCredentials",
				"brandLogoUri": "http://dev.virtualearth.net/Branding/logo_powered_by.png",
				"copyright": "Copyright © 2017 Microsoft and its suppliers. All rights reserved. This API cannot be accessed and the content and any results may not be used, reproduced or transmitted in any manner without express written permission from Microsoft Corporation.",
				"entityType": "Address",
				"matchCodes": [
					"Good"
				],
				"name": "847 Norsan Ct, Newmarket, ON L3X 1K9, Canada",
				"statusCode": 200,
				"statusDescription": "OK",
				"traceId": "8da93ba257694d4a8c1334bff0ec4880|BN20190642|7.7.0.0|",
				"addressLine": "847 Norsan Ct",
				"adminDistrict": "ON",
				"adminDistrict2": "York",
				"countryRegion": "Canada",
				"formattedAddress": "847 Norsan Ct, Newmarket, ON L3X 1K9, Canada",
				"locality": "Newmarket",
				"postalCode": "L3X 1K9"
			},
			"geometry": {
				"type": "Point",
				"coordinates": [
					-79.43846,
					44.03313
				]
			},
			"bbox": [
				-79.4400236,
				44.0320058,
				-79.4368964,
				44.0342542
			]
		}
	]
}
