{
	"type": "FeatureCollection",
	"features": [
		{
			"type": "Feature",
			"properties": {
				"confidence": 9,
				"authenticationResultCode": "ValidCredentials",
				"brandLogoUri": "http://dev.virtualearth.net/Branding/logo_powered_by.png",
				"copyright": "Copyright © 2017 Microsoft and its suppliers. All rights reserved. This API cannot be accessed and the content and any results may not be used, reproduced or transmitted in any manner without express written permission from Microsoft Corporation.",
				"entityType": "Address",
				"matchCodes": [
					"Good"
				],
				"name": "847 Jane St, York, ON M6N 4C4, Canada",
				"statusCode": 200,
				"statusDescription": "OK",
				"traceId": "83130a7e6ad345aab6cf5ab5cbd37c3e|BN20130719|7.7.0.0|",
				"addressLine": "847 Jane St",
				"adminDistrict": "ON",
				"adminDistrict2": "Toronto",
				"countryRegion": "Canada",
				"formattedAddress": "847 Jane St, York, ON M6N 4C4, Canada",
				"locality": "Toronto",
				"neighborhood": "Rockcliffe-Smythe",
				"postalCode": "M6N 4C4"
			},
			"geometry": {
				"type": "Point",
				"coordinates": [
					-79.4955844,
					43.6764321
				]
			},
			"bbox": [
				-79.4971387,
				43.675308,
				-79.4940301,
				43.6775563
			]
		}
	]
}
