{
	"type": "FeatureCollection",
	"features": [
		{
			"type": "Feature",
			"properties": {
				"confidence": 4,
				"authenticationResultCode": "ValidCredentials",
				"brandLogoUri": "http://dev.virtualearth.net/Branding/logo_powered_by.png",
				"copyright": "Copyright © 2017 Microsoft and its suppliers. All rights reserved. This API cannot be accessed and the content and any results may not be used, reproduced or transmitted in any manner without express written permission from Microsoft Corporation.",
				"entityType": "PopulatedPlace",
				"matchCodes": [
					"Ambiguous",
					"UpHierarchy"
				],
				"name": "Seldom, Newfoundland and Labrador, Canada",
				"statusCode": 200,
				"statusDescription": "OK",
				"traceId": "318accc379144a0ba7c1545154899d12|BN20300154|7.7.0.0|",
				"adminDistrict": "NL",
				"countryRegion": "Canada",
				"formattedAddress": "Seldom, Newfoundland and Labrador, Canada",
				"locality": "Seldom"
			},
			"geometry": {
				"type": "Point",
				"coordinates": [
					-54.1752281188965,
					49.6158790588379
				]
			},
			"bbox": [
				-54.2348109462252,
				49.5869086758453,
				-54.1156452915677,
				49.6448494418304
			]
		},
		{
			"type": "Feature",
			"properties": {
				"confidence": 7,
				"authenticationResultCode": "ValidCredentials",
				"brandLogoUri": "http://dev.virtualearth.net/Branding/logo_powered_by.png",
				"copyright": "Copyright © 2017 Microsoft and its suppliers. All rights reserved. This API cannot be accessed and the content and any results may not be used, reproduced or transmitted in any manner without express written permission from Microsoft Corporation.",
				"entityType": "Postcode1",
				"matchCodes": [
					"Ambiguous",
					"UpHierarchy"
				],
				"name": "Newfoundland and Labrador, A0G 3Z0, Canada",
				"statusCode": 200,
				"statusDescription": "OK",
				"traceId": "318accc379144a0ba7c1545154899d12|BN20300154|7.7.0.0|",
				"adminDistrict": "NL",
				"countryRegion": "Canada",
				"formattedAddress": "Newfoundland and Labrador, A0G 3Z0, Canada",
				"locality": "Newfoundland and Labrador",
				"postalCode": "A0G 3Z0"
			},
			"geometry": {
				"type": "Point",
				"coordinates": [
					-54.4689064025879,
					49.2182693481445
				]
			},
			"bbox": [
				-54.476790743781,
				49.2144066305739,
				-54.4610220613948,
				49.2221320657152
			]
		}
	]
}
