{
	"type": "FeatureCollection",
	"features": [
		{
			"type": "Feature",
			"properties": {
				"confidence": 9,
				"authenticationResultCode": "ValidCredentials",
				"brandLogoUri": "http://dev.virtualearth.net/Branding/logo_powered_by.png",
				"copyright": "Copyright © 2017 Microsoft and its suppliers. All rights reserved. This API cannot be accessed and the content and any results may not be used, reproduced or transmitted in any manner without express written permission from Microsoft Corporation.",
				"entityType": "Address",
				"matchCodes": [
					"Good"
				],
				"name": "85 Mattro St, Saint John, NB E2N 0A3, Canada",
				"statusCode": 200,
				"statusDescription": "OK",
				"traceId": "d694ef80ce1c4754a54b772ba5352655|BN20130625|7.7.0.0|",
				"addressLine": "85 Mattro St",
				"adminDistrict": "NB",
				"adminDistrict2": "Saint John",
				"countryRegion": "Canada",
				"formattedAddress": "85 Mattro St, Saint John, NB E2N 0A3, Canada",
				"locality": "Saint John",
				"postalCode": "E2N 0A3"
			},
			"geometry": {
				"type": "Point",
				"coordinates": [
					-65.9470767,
					45.3286978
				]
			},
			"bbox": [
				-65.9486757,
				45.3275736,
				-65.9454777,
				45.3298219
			]
		}
	]
}
