{
	"type": "FeatureCollection",
	"features": [
		{
			"type": "Feature",
			"properties": {
				"confidence": 9,
				"authenticationResultCode": "ValidCredentials",
				"brandLogoUri": "http://dev.virtualearth.net/Branding/logo_powered_by.png",
				"copyright": "Copyright © 2017 Microsoft and its suppliers. All rights reserved. This API cannot be accessed and the content and any results may not be used, reproduced or transmitted in any manner without express written permission from Microsoft Corporation.",
				"entityType": "Address",
				"matchCodes": [
					"Good"
				],
				"name": "8500 Kinross St, Vancouver, BC V5S 4V9, Canada",
				"statusCode": 200,
				"statusDescription": "OK",
				"traceId": "8ba8b63f64c64a98bbb010cf5d7cbf36|BN20130631|7.7.0.0|",
				"addressLine": "8500 Kinross St",
				"adminDistrict": "BC",
				"adminDistrict2": "Greater Vancouver",
				"countryRegion": "Canada",
				"formattedAddress": "8500 Kinross St, Vancouver, BC V5S 4V9, Canada",
				"locality": "Vancouver",
				"neighborhood": "Champlain Heights",
				"postalCode": "V5S 4V9"
			},
			"geometry": {
				"type": "Point",
				"coordinates": [
					-123.03535,
					49.20633
				]
			},
			"bbox": [
				-123.0370706,
				49.2052058,
				-123.0336294,
				49.2074542
			]
		}
	]
}
