{
	"type": "FeatureCollection",
	"features": [
		{
			"type": "Feature",
			"properties": {
				"confidence": 9,
				"authenticationResultCode": "ValidCredentials",
				"brandLogoUri": "http://dev.virtualearth.net/Branding/logo_powered_by.png",
				"copyright": "Copyright © 2017 Microsoft and its suppliers. All rights reserved. This API cannot be accessed and the content and any results may not be used, reproduced or transmitted in any manner without express written permission from Microsoft Corporation.",
				"entityType": "Address",
				"matchCodes": [
					"Good"
				],
				"name": "8501 Commerce Ct, Burnaby, BC V5A 4N3, Canada",
				"statusCode": 200,
				"statusDescription": "OK",
				"traceId": "4199bdce934b40a382a047299b49d22a|BN20240253|7.7.0.0|",
				"addressLine": "8501 Commerce Ct",
				"adminDistrict": "BC",
				"adminDistrict2": "Greater Vancouver",
				"countryRegion": "Canada",
				"formattedAddress": "8501 Commerce Ct, Burnaby, BC V5A 4N3, Canada",
				"locality": "Burnaby",
				"neighborhood": "Lake City",
				"postalCode": "V5A 4N3"
			},
			"geometry": {
				"type": "Point",
				"coordinates": [
					-122.9168757,
					49.2550621
				]
			},
			"bbox": [
				-122.918598,
				49.2539379,
				-122.9151534,
				49.2561862
			]
		}
	]
}
