{
	"type": "FeatureCollection",
	"features": [
		{
			"type": "Feature",
			"properties": {
				"confidence": 9,
				"authenticationResultCode": "ValidCredentials",
				"brandLogoUri": "http://dev.virtualearth.net/Branding/logo_powered_by.png",
				"copyright": "Copyright © 2017 Microsoft and its suppliers. All rights reserved. This API cannot be accessed and the content and any results may not be used, reproduced or transmitted in any manner without express written permission from Microsoft Corporation.",
				"entityType": "Address",
				"matchCodes": [
					"Good"
				],
				"name": "8513 68 Ave, Grande Prairie, AB T8V, Canada",
				"statusCode": 200,
				"statusDescription": "OK",
				"traceId": "9e60ad7034d84927bff0da8dbc42bc24|BN20130447|7.7.0.0|",
				"addressLine": "8513 68 Ave",
				"adminDistrict": "AB",
				"adminDistrict2": "Alberta",
				"countryRegion": "Canada",
				"formattedAddress": "8513 68 Ave, Grande Prairie, AB T8V, Canada",
				"locality": "Grande Prairie",
				"postalCode": "T8V"
			},
			"geometry": {
				"type": "Point",
				"coordinates": [
					-118.75209,
					55.1415
				]
			},
			"bbox": [
				-118.7540568,
				55.1403758,
				-118.7501232,
				55.1426242
			]
		}
	]
}
