{
	"type": "FeatureCollection",
	"features": [
		{
			"type": "Feature",
			"properties": {
				"confidence": 9,
				"authenticationResultCode": "ValidCredentials",
				"brandLogoUri": "http://dev.virtualearth.net/Branding/logo_powered_by.png",
				"copyright": "Copyright © 2017 Microsoft and its suppliers. All rights reserved. This API cannot be accessed and the content and any results may not be used, reproduced or transmitted in any manner without express written permission from Microsoft Corporation.",
				"entityType": "Address",
				"matchCodes": [
					"Good"
				],
				"name": "8525 109 St, Grande Prairie, AB T8V 8H7, Canada",
				"statusCode": 200,
				"statusDescription": "OK",
				"traceId": "041af875125e4bc6927bc83423528c42|BN20130634|7.7.0.0|",
				"addressLine": "8525 109 St",
				"adminDistrict": "AB",
				"adminDistrict2": "Alberta",
				"countryRegion": "Canada",
				"formattedAddress": "8525 109 St, Grande Prairie, AB T8V 8H7, Canada",
				"locality": "Grande Prairie",
				"neighborhood": "Richmond Industrial Park",
				"postalCode": "T8V 8H7"
			},
			"geometry": {
				"type": "Point",
				"coordinates": [
					-118.82197,
					55.15757
				]
			},
			"bbox": [
				-118.8239376,
				55.1564458,
				-118.8200024,
				55.1586942
			]
		}
	]
}
