{
	"type": "FeatureCollection",
	"features": [
		{
			"type": "Feature",
			"properties": {
				"confidence": 9,
				"authenticationResultCode": "ValidCredentials",
				"brandLogoUri": "http://dev.virtualearth.net/Branding/logo_powered_by.png",
				"copyright": "Copyright © 2017 Microsoft and its suppliers. All rights reserved. This API cannot be accessed and the content and any results may not be used, reproduced or transmitted in any manner without express written permission from Microsoft Corporation.",
				"entityType": "Address",
				"matchCodes": [
					"Good"
				],
				"name": "8536 Baxter Pl, Burnaby, BC V5A 4T8, Canada",
				"statusCode": 200,
				"statusDescription": "OK",
				"traceId": "2172a738bcdd41b495667e3cd21fe252|BN20121764|7.7.0.0|",
				"addressLine": "8536 Baxter Pl",
				"adminDistrict": "BC",
				"adminDistrict2": "Greater Vancouver",
				"countryRegion": "Canada",
				"formattedAddress": "8536 Baxter Pl, Burnaby, BC V5A 4T8, Canada",
				"locality": "Burnaby",
				"neighborhood": "Lake City",
				"postalCode": "V5A 4T8"
			},
			"geometry": {
				"type": "Point",
				"coordinates": [
					-122.9151248,
					49.2588252
				]
			},
			"bbox": [
				-122.9168473,
				49.257701,
				-122.9134023,
				49.2599493
			]
		}
	]
}
