{
	"type": "FeatureCollection",
	"features": [
		{
			"type": "Feature",
			"properties": {
				"confidence": 9,
				"authenticationResultCode": "ValidCredentials",
				"brandLogoUri": "http://dev.virtualearth.net/Branding/logo_powered_by.png",
				"copyright": "Copyright © 2017 Microsoft and its suppliers. All rights reserved. This API cannot be accessed and the content and any results may not be used, reproduced or transmitted in any manner without express written permission from Microsoft Corporation.",
				"entityType": "Address",
				"matchCodes": [
					"Good"
				],
				"name": "854 Place Sardaigne, Brossard, QC J4X 1L7, Canada",
				"statusCode": 200,
				"statusDescription": "OK",
				"traceId": "6f27e2a4c6aa4ff0a73f90e5e39dd440|BN20121762|7.7.0.0|",
				"addressLine": "854 Place Sardaigne",
				"adminDistrict": "QC",
				"adminDistrict2": "Longueuil",
				"countryRegion": "Canada",
				"formattedAddress": "854 Place Sardaigne, Brossard, QC J4X 1L7, Canada",
				"locality": "Brossard",
				"postalCode": "J4X 1L7"
			},
			"geometry": {
				"type": "Point",
				"coordinates": [
					-73.4883399,
					45.45481
				]
			},
			"bbox": [
				-73.4899425,
				45.4536858,
				-73.4867373,
				45.4559342
			]
		}
	]
}
