{
	"type": "FeatureCollection",
	"features": [
		{
			"type": "Feature",
			"properties": {
				"confidence": 9,
				"authenticationResultCode": "ValidCredentials",
				"brandLogoUri": "http://dev.virtualearth.net/Branding/logo_powered_by.png",
				"copyright": "Copyright © 2017 Microsoft and its suppliers. All rights reserved. This API cannot be accessed and the content and any results may not be used, reproduced or transmitted in any manner without express written permission from Microsoft Corporation.",
				"entityType": "Address",
				"matchCodes": [
					"Good"
				],
				"name": "8557 Main St, Vancouver, BC V5X 3M3, Canada",
				"statusCode": 200,
				"statusDescription": "OK",
				"traceId": "6430efd4d74a4977a3207dce967a222c|BN20130431|7.7.0.0|",
				"addressLine": "8557 Main St",
				"adminDistrict": "BC",
				"adminDistrict2": "Greater Vancouver",
				"countryRegion": "Canada",
				"formattedAddress": "8557 Main St, Vancouver, BC V5X 3M3, Canada",
				"locality": "Vancouver",
				"neighborhood": "Sunset",
				"postalCode": "V5X 3M3"
			},
			"geometry": {
				"type": "Point",
				"coordinates": [
					-123.1025954,
					49.2077027
				]
			},
			"bbox": [
				-123.1043161,
				49.2065785,
				-123.1008747,
				49.2088268
			]
		}
	]
}
