{
	"type": "FeatureCollection",
	"features": [
		{
			"type": "Feature",
			"properties": {
				"confidence": 9,
				"authenticationResultCode": "ValidCredentials",
				"brandLogoUri": "http://dev.virtualearth.net/Branding/logo_powered_by.png",
				"copyright": "Copyright © 2017 Microsoft and its suppliers. All rights reserved. This API cannot be accessed and the content and any results may not be used, reproduced or transmitted in any manner without express written permission from Microsoft Corporation.",
				"entityType": "Address",
				"matchCodes": [
					"Good"
				],
				"name": "858 Colborne Rd, Sarnia, ON N7T 6V8, Canada",
				"statusCode": 200,
				"statusDescription": "OK",
				"traceId": "611b13a908b5420b820f7c93a852e45d|BN20200137|7.7.0.0|",
				"addressLine": "858 Colborne Rd",
				"adminDistrict": "ON",
				"adminDistrict2": "Lambton",
				"countryRegion": "Canada",
				"formattedAddress": "858 Colborne Rd, Sarnia, ON N7T 6V8, Canada",
				"locality": "Sarnia",
				"postalCode": "N7T 6V8"
			},
			"geometry": {
				"type": "Point",
				"coordinates": [
					-82.3886268,
					42.9861845
				]
			},
			"bbox": [
				-82.3901635,
				42.9850604,
				-82.38709,
				42.9873087
			]
		}
	]
}
