{
	"type": "FeatureCollection",
	"features": [
		{
			"type": "Feature",
			"properties": {
				"confidence": 9,
				"authenticationResultCode": "ValidCredentials",
				"brandLogoUri": "http://dev.virtualearth.net/Branding/logo_powered_by.png",
				"copyright": "Copyright © 2017 Microsoft and its suppliers. All rights reserved. This API cannot be accessed and the content and any results may not be used, reproduced or transmitted in any manner without express written permission from Microsoft Corporation.",
				"entityType": "Address",
				"matchCodes": [
					"Good"
				],
				"name": "868 Broadview Ave, Toronto, ON M4K 2R1, Canada",
				"statusCode": 200,
				"statusDescription": "OK",
				"traceId": "3ecbada807684e32b39d9d14c45c307f|BN20181720|7.7.0.0|",
				"addressLine": "868 Broadview Ave",
				"adminDistrict": "ON",
				"adminDistrict2": "Toronto",
				"countryRegion": "Canada",
				"formattedAddress": "868 Broadview Ave, Toronto, ON M4K 2R1, Canada",
				"locality": "Toronto",
				"neighborhood": "Playter Estates-Danforth",
				"postalCode": "M4K 2R1"
			},
			"geometry": {
				"type": "Point",
				"coordinates": [
					-79.35836,
					43.6795199
				]
			},
			"bbox": [
				-79.3599144,
				43.6783957,
				-79.3568056,
				43.6806441
			]
		}
	]
}
