{
	"type": "FeatureCollection",
	"features": [
		{
			"type": "Feature",
			"properties": {
				"confidence": 9,
				"authenticationResultCode": "ValidCredentials",
				"brandLogoUri": "http://dev.virtualearth.net/Branding/logo_powered_by.png",
				"copyright": "Copyright © 2017 Microsoft and its suppliers. All rights reserved. This API cannot be accessed and the content and any results may not be used, reproduced or transmitted in any manner without express written permission from Microsoft Corporation.",
				"entityType": "Address",
				"matchCodes": [
					"Good"
				],
				"name": "87 Cement Plant Rd, Colchester, NS B0N, Canada",
				"statusCode": 200,
				"statusDescription": "OK",
				"traceId": "324cbc3d2f7c44babf06b13b9e074723|BN20130631|7.7.0.0|",
				"addressLine": "87 Cement Plant Rd",
				"adminDistrict": "NS",
				"adminDistrict2": "Colchester",
				"countryRegion": "Canada",
				"formattedAddress": "87 Cement Plant Rd, Colchester, NS B0N, Canada",
				"locality": "Colchester",
				"neighborhood": "Colchester",
				"postalCode": "B0N 1C0"
			},
			"geometry": {
				"type": "Point",
				"coordinates": [
					-63.3317,
					45.24162
				]
			},
			"bbox": [
				-63.3332965,
				45.2404958,
				-63.3301035,
				45.2427442
			]
		}
	]
}
