{
	"type": "FeatureCollection",
	"features": [
		{
			"type": "Feature",
			"properties": {
				"confidence": 9,
				"authenticationResultCode": "ValidCredentials",
				"brandLogoUri": "http://dev.virtualearth.net/Branding/logo_powered_by.png",
				"copyright": "Copyright © 2017 Microsoft and its suppliers. All rights reserved. This API cannot be accessed and the content and any results may not be used, reproduced or transmitted in any manner without express written permission from Microsoft Corporation.",
				"entityType": "Address",
				"matchCodes": [
					"Good"
				],
				"name": "87 Dufferin St, Orillia, ON L3V 5S9, Canada",
				"statusCode": 200,
				"statusDescription": "OK",
				"traceId": "fb1b7a1f920f491d8b3c1c7f31d46e64|BN20121762|7.7.0.0|",
				"addressLine": "87 Dufferin St",
				"adminDistrict": "ON",
				"adminDistrict2": "Simcoe",
				"countryRegion": "Canada",
				"formattedAddress": "87 Dufferin St, Orillia, ON L3V 5S9, Canada",
				"locality": "Orillia",
				"postalCode": "L3V 5S9"
			},
			"geometry": {
				"type": "Point",
				"coordinates": [
					-79.4238606,
					44.6030193
				]
			},
			"bbox": [
				-79.4254395,
				44.6018952,
				-79.4222817,
				44.6041435
			]
		}
	]
}
