{
	"type": "FeatureCollection",
	"features": [
		{
			"type": "Feature",
			"properties": {
				"confidence": 9,
				"authenticationResultCode": "ValidCredentials",
				"brandLogoUri": "http://dev.virtualearth.net/Branding/logo_powered_by.png",
				"copyright": "Copyright © 2017 Microsoft and its suppliers. All rights reserved. This API cannot be accessed and the content and any results may not be used, reproduced or transmitted in any manner without express written permission from Microsoft Corporation.",
				"entityType": "Address",
				"matchCodes": [
					"Good"
				],
				"name": "870 Kings Rd, Sydney, NS B1R 2L7, Canada",
				"statusCode": 200,
				"statusDescription": "OK",
				"traceId": "9b50cfadf3324893ad660460fb71dc20|BN20130530|7.7.0.0|",
				"addressLine": "870 Kings Rd",
				"adminDistrict": "NS",
				"adminDistrict2": "Cape Breton",
				"countryRegion": "Canada",
				"formattedAddress": "870 Kings Rd, Sydney, NS B1R 2L7, Canada",
				"locality": "Cape Breton",
				"neighborhood": "Sydney",
				"postalCode": "B1R 2L7"
			},
			"geometry": {
				"type": "Point",
				"coordinates": [
					-60.2132114,
					46.1153789
				]
			},
			"bbox": [
				-60.2148331,
				46.1142547,
				-60.2115898,
				46.116503
			]
		}
	]
}
