{
	"type": "FeatureCollection",
	"features": [
		{
			"type": "Feature",
			"properties": {
				"confidence": 9,
				"authenticationResultCode": "ValidCredentials",
				"brandLogoUri": "http://dev.virtualearth.net/Branding/logo_powered_by.png",
				"copyright": "Copyright © 2017 Microsoft and its suppliers. All rights reserved. This API cannot be accessed and the content and any results may not be used, reproduced or transmitted in any manner without express written permission from Microsoft Corporation.",
				"entityType": "Address",
				"matchCodes": [
					"Good"
				],
				"name": "871 Boulevard Duchesne, Yamachiche, QC G0X 3L0, Canada",
				"statusCode": 200,
				"statusDescription": "OK",
				"traceId": "364a1f47592d440795e53b8ab734092b|BN20131519|7.7.0.0|",
				"addressLine": "871 Boulevard Duchesne",
				"adminDistrict": "QC",
				"adminDistrict2": "Maskinongé",
				"countryRegion": "Canada",
				"formattedAddress": "871 Boulevard Duchesne, Yamachiche, QC G0X 3L0, Canada",
				"locality": "Yamachiche",
				"postalCode": "G0X 3L0"
			},
			"geometry": {
				"type": "Point",
				"coordinates": [
					-72.8328692,
					46.2877561
				]
			},
			"bbox": [
				-72.834496,
				46.286632,
				-72.8312425,
				46.2888803
			]
		}
	]
}
