{
	"type": "FeatureCollection",
	"features": [
		{
			"type": "Feature",
			"properties": {
				"confidence": 9,
				"authenticationResultCode": "ValidCredentials",
				"brandLogoUri": "http://dev.virtualearth.net/Branding/logo_powered_by.png",
				"copyright": "Copyright © 2017 Microsoft and its suppliers. All rights reserved. This API cannot be accessed and the content and any results may not be used, reproduced or transmitted in any manner without express written permission from Microsoft Corporation.",
				"entityType": "Address",
				"matchCodes": [
					"Good"
				],
				"name": "873 Rue Miller, Greenfield Park, QC J4V 1X2, Canada",
				"statusCode": 200,
				"statusDescription": "OK",
				"traceId": "670a16136325453f85cab0f15dc22164|BN20121763|7.7.0.0|",
				"addressLine": "873 Rue Miller",
				"adminDistrict": "QC",
				"adminDistrict2": "Longueuil",
				"countryRegion": "Canada",
				"formattedAddress": "873 Rue Miller, Greenfield Park, QC J4V 1X2, Canada",
				"locality": "Longueuil",
				"neighborhood": "Greenfield Park",
				"postalCode": "J4V 1X2"
			},
			"geometry": {
				"type": "Point",
				"coordinates": [
					-73.47081,
					45.48026
				]
			},
			"bbox": [
				-73.4724133,
				45.4791358,
				-73.4692067,
				45.4813842
			]
		}
	]
}
