{
	"type": "FeatureCollection",
	"features": [
		{
			"type": "Feature",
			"properties": {
				"confidence": 9,
				"authenticationResultCode": "ValidCredentials",
				"brandLogoUri": "http://dev.virtualearth.net/Branding/logo_powered_by.png",
				"copyright": "Copyright © 2017 Microsoft and its suppliers. All rights reserved. This API cannot be accessed and the content and any results may not be used, reproduced or transmitted in any manner without express written permission from Microsoft Corporation.",
				"entityType": "Address",
				"matchCodes": [
					"Good"
				],
				"name": "8735 Rue de Montbrun, Laval, QC H7A 3L2, Canada",
				"statusCode": 200,
				"statusDescription": "OK",
				"traceId": "d258b73b7c2a4a35b2610e0ffeede447|BN20240423|7.7.0.0|",
				"addressLine": "8735 Rue de Montbrun",
				"adminDistrict": "QC",
				"adminDistrict2": "Laval",
				"countryRegion": "Canada",
				"formattedAddress": "8735 Rue de Montbrun, Laval, QC H7A 3L2, Canada",
				"locality": "Laval",
				"neighborhood": "Arèsville",
				"postalCode": "H7A 3L2"
			},
			"geometry": {
				"type": "Point",
				"coordinates": [
					-73.57361,
					45.67352
				]
			},
			"bbox": [
				-73.5752188,
				45.6723958,
				-73.5720012,
				45.6746442
			]
		}
	]
}
