{
	"type": "FeatureCollection",
	"features": [
		{
			"type": "Feature",
			"properties": {
				"confidence": 9,
				"authenticationResultCode": "ValidCredentials",
				"brandLogoUri": "http://dev.virtualearth.net/Branding/logo_powered_by.png",
				"copyright": "Copyright © 2017 Microsoft and its suppliers. All rights reserved. This API cannot be accessed and the content and any results may not be used, reproduced or transmitted in any manner without express written permission from Microsoft Corporation.",
				"entityType": "Address",
				"matchCodes": [
					"Good"
				],
				"name": "8771 Mowbray Rd, Richmond, BC V7A 2B9, Canada",
				"statusCode": 200,
				"statusDescription": "OK",
				"traceId": "bd53f9f1420a423e9dfa2d523450c0a6|BN20250135|7.7.0.0|",
				"addressLine": "8771 Mowbray Rd",
				"adminDistrict": "BC",
				"adminDistrict2": "Greater Vancouver",
				"countryRegion": "Canada",
				"formattedAddress": "8771 Mowbray Rd, Richmond, BC V7A 2B9, Canada",
				"locality": "Richmond",
				"neighborhood": "Broadmoor",
				"postalCode": "V7A 2B9"
			},
			"geometry": {
				"type": "Point",
				"coordinates": [
					-123.12613,
					49.14297
				]
			},
			"bbox": [
				-123.1278484,
				49.1418458,
				-123.1244116,
				49.1440942
			]
		}
	]
}
