{
	"type": "FeatureCollection",
	"features": [
		{
			"type": "Feature",
			"properties": {
				"confidence": 9,
				"authenticationResultCode": "ValidCredentials",
				"brandLogoUri": "http://dev.virtualearth.net/Branding/logo_powered_by.png",
				"copyright": "Copyright © 2017 Microsoft and its suppliers. All rights reserved. This API cannot be accessed and the content and any results may not be used, reproduced or transmitted in any manner without express written permission from Microsoft Corporation.",
				"entityType": "Address",
				"matchCodes": [
					"Good"
				],
				"name": "88 Campbell Dr, Arnprior, ON K7S 3G9, Canada",
				"statusCode": 200,
				"statusDescription": "OK",
				"traceId": "93791aa2c1bd4eee9d2a637456fc84a3|BN20260223|7.7.0.0|",
				"addressLine": "88 Campbell Dr",
				"adminDistrict": "ON",
				"adminDistrict2": "Renfrew",
				"countryRegion": "Canada",
				"formattedAddress": "88 Campbell Dr, Arnprior, ON K7S 3G9, Canada",
				"locality": "McNab/Braeside",
				"neighborhood": "Arnprior",
				"postalCode": "K7S 3G9"
			},
			"geometry": {
				"type": "Point",
				"coordinates": [
					-76.38372,
					45.41842
				]
			},
			"bbox": [
				-76.3853215,
				45.4172958,
				-76.3821185,
				45.4195442
			]
		}
	]
}
