{
	"type": "FeatureCollection",
	"features": [
		{
			"type": "Feature",
			"properties": {
				"confidence": 9,
				"authenticationResultCode": "ValidCredentials",
				"brandLogoUri": "http://dev.virtualearth.net/Branding/logo_powered_by.png",
				"copyright": "Copyright © 2017 Microsoft and its suppliers. All rights reserved. This API cannot be accessed and the content and any results may not be used, reproduced or transmitted in any manner without express written permission from Microsoft Corporation.",
				"entityType": "Address",
				"matchCodes": [
					"Good"
				],
				"name": "88 Riverdale Ave, Ottawa, ON K1S 1R2, Canada",
				"statusCode": 200,
				"statusDescription": "OK",
				"traceId": "18975344735847999b26679f9a07f9a2|BN20130520|7.7.0.0|",
				"addressLine": "88 Riverdale Ave",
				"adminDistrict": "ON",
				"adminDistrict2": "Ottawa",
				"countryRegion": "Canada",
				"formattedAddress": "88 Riverdale Ave, Ottawa, ON K1S 1R2, Canada",
				"locality": "Ottawa",
				"neighborhood": "Golden Triangle-Old Ottawa East",
				"postalCode": "K1S 1R2"
			},
			"geometry": {
				"type": "Point",
				"coordinates": [
					-75.67685,
					45.40096
				]
			},
			"bbox": [
				-75.678451,
				45.3998358,
				-75.675249,
				45.4020842
			]
		}
	]
}
