{
	"type": "FeatureCollection",
	"features": [
		{
			"type": "Feature",
			"properties": {
				"confidence": 9,
				"authenticationResultCode": "ValidCredentials",
				"brandLogoUri": "http://dev.virtualearth.net/Branding/logo_powered_by.png",
				"copyright": "Copyright © 2017 Microsoft and its suppliers. All rights reserved. This API cannot be accessed and the content and any results may not be used, reproduced or transmitted in any manner without express written permission from Microsoft Corporation.",
				"entityType": "Address",
				"matchCodes": [
					"Good"
				],
				"name": "880 Phillips St, Portage la Prairie, MB R1N 4A4, Canada",
				"statusCode": 200,
				"statusDescription": "OK",
				"traceId": "e6d559bb4e9c48d7b6bf86f5175e0137|BN20121762|7.7.0.0|",
				"addressLine": "880 Phillips St",
				"adminDistrict": "MB",
				"adminDistrict2": "Manitoba",
				"countryRegion": "Canada",
				"formattedAddress": "880 Phillips St, Portage la Prairie, MB R1N 4A4, Canada",
				"locality": "Portage la Prairie",
				"postalCode": "R1N 4A4"
			},
			"geometry": {
				"type": "Point",
				"coordinates": [
					-98.272077,
					49.9848348
				]
			},
			"bbox": [
				-98.2738254,
				49.9837107,
				-98.2703287,
				49.985959
			]
		}
	]
}
