{
	"type": "FeatureCollection",
	"features": [
		{
			"type": "Feature",
			"properties": {
				"confidence": 9,
				"authenticationResultCode": "ValidCredentials",
				"brandLogoUri": "http://dev.virtualearth.net/Branding/logo_powered_by.png",
				"copyright": "Copyright © 2017 Microsoft and its suppliers. All rights reserved. This API cannot be accessed and the content and any results may not be used, reproduced or transmitted in any manner without express written permission from Microsoft Corporation.",
				"entityType": "Address",
				"matchCodes": [
					"Good"
				],
				"name": "880 3e Rue, Chibougamau, QC G8P 1P9, Canada",
				"statusCode": 200,
				"statusDescription": "OK",
				"traceId": "d3e80ce3a1ed45729a063efc7e824363|BN20130621|7.7.0.0|",
				"addressLine": "880 3e Rue",
				"adminDistrict": "QC",
				"adminDistrict2": "Baie-James",
				"countryRegion": "Canada",
				"formattedAddress": "880 3e Rue, Chibougamau, QC G8P 1P9, Canada",
				"locality": "Chibougamau",
				"postalCode": "G8P 1P9"
			},
			"geometry": {
				"type": "Point",
				"coordinates": [
					-74.38252,
					49.91306
				]
			},
			"bbox": [
				-74.3842657,
				49.9119358,
				-74.3807743,
				49.9141842
			]
		}
	]
}
