{
	"type": "FeatureCollection",
	"features": [
		{
			"type": "Feature",
			"properties": {
				"confidence": 9,
				"authenticationResultCode": "ValidCredentials",
				"brandLogoUri": "http://dev.virtualearth.net/Branding/logo_powered_by.png",
				"copyright": "Copyright © 2017 Microsoft and its suppliers. All rights reserved. This API cannot be accessed and the content and any results may not be used, reproduced or transmitted in any manner without express written permission from Microsoft Corporation.",
				"entityType": "Address",
				"matchCodes": [
					"Good"
				],
				"name": "8803 58 Ave NW, Edmonton, AB T6E 5X1, Canada",
				"statusCode": 200,
				"statusDescription": "OK",
				"traceId": "019340b1f3bc4cea9a9acc10a6eacdf8|BN20181720|7.7.0.0|",
				"addressLine": "8803 58 Ave NW",
				"adminDistrict": "AB",
				"adminDistrict2": "Alberta",
				"countryRegion": "Canada",
				"formattedAddress": "8803 58 Ave NW, Edmonton, AB T6E 5X1, Canada",
				"locality": "Edmonton",
				"neighborhood": "Davies Industrial West",
				"postalCode": "T6E 5X1"
			},
			"geometry": {
				"type": "Point",
				"coordinates": [
					-113.46402,
					53.49355
				]
			},
			"bbox": [
				-113.4659096,
				53.4924258,
				-113.4621304,
				53.4946742
			]
		}
	]
}
