{
	"type": "FeatureCollection",
	"features": [
		{
			"type": "Feature",
			"properties": {
				"confidence": 9,
				"authenticationResultCode": "ValidCredentials",
				"brandLogoUri": "http://dev.virtualearth.net/Branding/logo_powered_by.png",
				"copyright": "Copyright © 2017 Microsoft and its suppliers. All rights reserved. This API cannot be accessed and the content and any results may not be used, reproduced or transmitted in any manner without express written permission from Microsoft Corporation.",
				"entityType": "Address",
				"matchCodes": [
					"Good"
				],
				"name": "8893 Creditview Rd, Brampton, ON L6Y 2X8, Canada",
				"statusCode": 200,
				"statusDescription": "OK",
				"traceId": "5f3480128a8647599de13772310ada4e|BN20181720|7.7.0.0|",
				"addressLine": "8893 Creditview Rd",
				"adminDistrict": "ON",
				"adminDistrict2": "Peel",
				"countryRegion": "Canada",
				"formattedAddress": "8893 Creditview Rd, Brampton, ON L6Y 2X8, Canada",
				"locality": "Brampton",
				"postalCode": "L6Y 2X8"
			},
			"geometry": {
				"type": "Point",
				"coordinates": [
					-79.78974,
					43.65531
				]
			},
			"bbox": [
				-79.7912938,
				43.6541858,
				-79.7881862,
				43.6564342
			]
		}
	]
}
