{
	"type": "FeatureCollection",
	"features": [
		{
			"type": "Feature",
			"properties": {
				"confidence": 9,
				"authenticationResultCode": "ValidCredentials",
				"brandLogoUri": "http://dev.virtualearth.net/Branding/logo_powered_by.png",
				"copyright": "Copyright © 2017 Microsoft and its suppliers. All rights reserved. This API cannot be accessed and the content and any results may not be used, reproduced or transmitted in any manner without express written permission from Microsoft Corporation.",
				"entityType": "Address",
				"matchCodes": [
					"Good"
				],
				"name": "9 Homestead St, Nepean, ON K2E 7N9, Canada",
				"statusCode": 200,
				"statusDescription": "OK",
				"traceId": "b3fa88fb9073458982b1d61e2129dc1a|BN20130620|7.7.0.0|",
				"addressLine": "9 Homestead St",
				"adminDistrict": "ON",
				"adminDistrict2": "Ottawa",
				"countryRegion": "Canada",
				"formattedAddress": "9 Homestead St, Nepean, ON K2E 7N9, Canada",
				"locality": "Ottawa",
				"neighborhood": "Nepean",
				"postalCode": "K2E 7N9"
			},
			"geometry": {
				"type": "Point",
				"coordinates": [
					-75.71014,
					45.35096
				]
			},
			"bbox": [
				-75.7117396,
				45.3498358,
				-75.7085404,
				45.3520842
			]
		}
	]
}
