{
	"type": "FeatureCollection",
	"features": [
		{
			"type": "Feature",
			"properties": {
				"confidence": 9,
				"authenticationResultCode": "ValidCredentials",
				"brandLogoUri": "http://dev.virtualearth.net/Branding/logo_powered_by.png",
				"copyright": "Copyright © 2017 Microsoft and its suppliers. All rights reserved. This API cannot be accessed and the content and any results may not be used, reproduced or transmitted in any manner without express written permission from Microsoft Corporation.",
				"entityType": "Address",
				"matchCodes": [
					"Good"
				],
				"name": "9 Jim Kimmett Blvd, Napanee, ON K7R 0B3, Canada",
				"statusCode": 200,
				"statusDescription": "OK",
				"traceId": "2085659f97a84dca8363e9889371a083|BN20130631|7.7.0.0|",
				"addressLine": "9 Jim Kimmett Blvd",
				"adminDistrict": "ON",
				"adminDistrict2": "Lennox and Addington",
				"countryRegion": "Canada",
				"formattedAddress": "9 Jim Kimmett Blvd, Napanee, ON K7R 0B3, Canada",
				"locality": "Greater Napanee",
				"neighborhood": "Napanee",
				"postalCode": "K7R 0B3"
			},
			"geometry": {
				"type": "Point",
				"coordinates": [
					-76.9642759,
					44.2610983
				]
			},
			"bbox": [
				-76.9658456,
				44.2599741,
				-76.9627062,
				44.2622224
			]
		}
	]
}
