{
	"type": "FeatureCollection",
	"features": [
		{
			"type": "Feature",
			"properties": {
				"confidence": 9,
				"authenticationResultCode": "ValidCredentials",
				"brandLogoUri": "http://dev.virtualearth.net/Branding/logo_powered_by.png",
				"copyright": "Copyright © 2017 Microsoft and its suppliers. All rights reserved. This API cannot be accessed and the content and any results may not be used, reproduced or transmitted in any manner without express written permission from Microsoft Corporation.",
				"entityType": "Address",
				"matchCodes": [
					"Good"
				],
				"name": "9 Place de Broussey, Lorraine, QC J6Z 4L7, Canada",
				"statusCode": 200,
				"statusDescription": "OK",
				"traceId": "f01a3f83c1ad486881737ebb04f98a40|BN20130442|7.7.0.0|",
				"addressLine": "9 Place de Broussey",
				"adminDistrict": "QC",
				"adminDistrict2": "Thérèse-de-Blainville",
				"countryRegion": "Canada",
				"formattedAddress": "9 Place de Broussey, Lorraine, QC J6Z 4L7, Canada",
				"locality": "Lorraine",
				"postalCode": "J6Z 4L7"
			},
			"geometry": {
				"type": "Point",
				"coordinates": [
					-73.7773799,
					45.67287
				]
			},
			"bbox": [
				-73.7789887,
				45.6717458,
				-73.7757711,
				45.6739942
			]
		}
	]
}
