{
	"type": "FeatureCollection",
	"features": [
		{
			"type": "Feature",
			"properties": {
				"confidence": 9,
				"authenticationResultCode": "ValidCredentials",
				"brandLogoUri": "http://dev.virtualearth.net/Branding/logo_powered_by.png",
				"copyright": "Copyright © 2017 Microsoft and its suppliers. All rights reserved. This API cannot be accessed and the content and any results may not be used, reproduced or transmitted in any manner without express written permission from Microsoft Corporation.",
				"entityType": "Address",
				"matchCodes": [
					"Good"
				],
				"name": "90 E 3rd Ave, Vancouver, BC V5T 1C3, Canada",
				"statusCode": 200,
				"statusDescription": "OK",
				"traceId": "6cf440fa46544260b085abafeda007db|BN20130631|7.7.0.0|",
				"addressLine": "90 E 3rd Ave",
				"adminDistrict": "BC",
				"adminDistrict2": "Greater Vancouver",
				"countryRegion": "Canada",
				"formattedAddress": "90 E 3rd Ave, Vancouver, BC V5T 1C3, Canada",
				"locality": "Vancouver",
				"neighborhood": "Mt Pleasant",
				"postalCode": "V5T 1C3"
			},
			"geometry": {
				"type": "Point",
				"coordinates": [
					-123.10304,
					49.26809
				]
			},
			"bbox": [
				-123.1047628,
				49.2669658,
				-123.1013172,
				49.2692142
			]
		}
	]
}
