{
	"type": "FeatureCollection",
	"features": [
		{
			"type": "Feature",
			"properties": {
				"confidence": 9,
				"authenticationResultCode": "ValidCredentials",
				"brandLogoUri": "http://dev.virtualearth.net/Branding/logo_powered_by.png",
				"copyright": "Copyright © 2017 Microsoft and its suppliers. All rights reserved. This API cannot be accessed and the content and any results may not be used, reproduced or transmitted in any manner without express written permission from Microsoft Corporation.",
				"entityType": "Address",
				"matchCodes": [
					"Good"
				],
				"name": "90 Rue Alstonvale, Hudson, QC J0P 1H0, Canada",
				"statusCode": 200,
				"statusDescription": "OK",
				"traceId": "4e5bdcaf55684ccdb3f16ca01450f9d3|BN20320521|7.7.0.0|",
				"addressLine": "90 Rue Alstonvale",
				"adminDistrict": "QC",
				"adminDistrict2": "Vaudreuil-Soulanges",
				"countryRegion": "Canada",
				"formattedAddress": "90 Rue Alstonvale, Hudson, QC J0P 1H0, Canada",
				"locality": "Hudson",
				"postalCode": "J0P 1H0"
			},
			"geometry": {
				"type": "Point",
				"coordinates": [
					-74.1828857,
					45.46879
				]
			},
			"bbox": [
				-74.1844886,
				45.4676659,
				-74.1812827,
				45.4699142
			]
		}
	]
}
