{
	"type": "FeatureCollection",
	"features": [
		{
			"type": "Feature",
			"properties": {
				"confidence": 9,
				"authenticationResultCode": "ValidCredentials",
				"brandLogoUri": "http://dev.virtualearth.net/Branding/logo_powered_by.png",
				"copyright": "Copyright © 2017 Microsoft and its suppliers. All rights reserved. This API cannot be accessed and the content and any results may not be used, reproduced or transmitted in any manner without express written permission from Microsoft Corporation.",
				"entityType": "Address",
				"matchCodes": [
					"Good"
				],
				"name": "90 Carriage Hill Dr, London, ON N5X 3W9, Canada",
				"statusCode": 200,
				"statusDescription": "OK",
				"traceId": "a3e5e4b082f344d09e45782ba765f501|BN20130533|7.7.0.0|",
				"addressLine": "90 Carriage Hill Dr",
				"adminDistrict": "ON",
				"adminDistrict2": "Middlesex",
				"countryRegion": "Canada",
				"formattedAddress": "90 Carriage Hill Dr, London, ON N5X 3W9, Canada",
				"locality": "London",
				"neighborhood": "Masonville",
				"postalCode": "N5X 3W9"
			},
			"geometry": {
				"type": "Point",
				"coordinates": [
					-81.2711,
					43.0195
				]
			},
			"bbox": [
				-81.2726376,
				43.0183758,
				-81.2695624,
				43.0206242
			]
		}
	]
}
