{
	"type": "FeatureCollection",
	"features": [
		{
			"type": "Feature",
			"properties": {
				"confidence": 9,
				"authenticationResultCode": "ValidCredentials",
				"brandLogoUri": "http://dev.virtualearth.net/Branding/logo_powered_by.png",
				"copyright": "Copyright © 2017 Microsoft and its suppliers. All rights reserved. This API cannot be accessed and the content and any results may not be used, reproduced or transmitted in any manner without express written permission from Microsoft Corporation.",
				"entityType": "Address",
				"matchCodes": [
					"Good"
				],
				"name": "90 Commercial Dr, Calgary, AB T3Z 2A7, Canada",
				"statusCode": 200,
				"statusDescription": "OK",
				"traceId": "f3b0d59f03c64027a450066b68f5173f|BN20130620|7.7.0.0|",
				"addressLine": "90 Commercial Dr",
				"adminDistrict": "AB",
				"adminDistrict2": "Alberta",
				"countryRegion": "Canada",
				"formattedAddress": "90 Commercial Dr, Calgary, AB T3Z 2A7, Canada",
				"locality": "Rocky View County",
				"neighborhood": "Calgary",
				"postalCode": "T3Z 2A7"
			},
			"geometry": {
				"type": "Point",
				"coordinates": [
					-114.3444979,
					51.0844789
				]
			},
			"bbox": [
				-114.3462875,
				51.0833547,
				-114.3427084,
				51.085603
			]
		}
	]
}
