{
	"type": "FeatureCollection",
	"features": [
		{
			"type": "Feature",
			"properties": {
				"confidence": 9,
				"authenticationResultCode": "ValidCredentials",
				"brandLogoUri": "http://dev.virtualearth.net/Branding/logo_powered_by.png",
				"copyright": "Copyright © 2017 Microsoft and its suppliers. All rights reserved. This API cannot be accessed and the content and any results may not be used, reproduced or transmitted in any manner without express written permission from Microsoft Corporation.",
				"entityType": "Address",
				"matchCodes": [
					"Good"
				],
				"name": "90 Marcombe St, Coverdale, NB E1J 1K1, Canada",
				"statusCode": 200,
				"statusDescription": "OK",
				"traceId": "c65d61b7ee7248b1b3a7326a573b562a|BN20290118|7.7.0.0|",
				"addressLine": "90 Marcombe St",
				"adminDistrict": "NB",
				"adminDistrict2": "Albert",
				"countryRegion": "Canada",
				"formattedAddress": "90 Marcombe St, Coverdale, NB E1J 1K1, Canada",
				"locality": "Coverdale",
				"postalCode": "E1J 1K1"
			},
			"geometry": {
				"type": "Point",
				"coordinates": [
					-64.70865,
					46.02528
				]
			},
			"bbox": [
				-64.710269,
				46.0241558,
				-64.707031,
				46.0264042
			]
		}
	]
}
