{
	"type": "FeatureCollection",
	"features": [
		{
			"type": "Feature",
			"properties": {
				"confidence": 9,
				"authenticationResultCode": "ValidCredentials",
				"brandLogoUri": "http://dev.virtualearth.net/Branding/logo_powered_by.png",
				"copyright": "Copyright © 2017 Microsoft and its suppliers. All rights reserved. This API cannot be accessed and the content and any results may not be used, reproduced or transmitted in any manner without express written permission from Microsoft Corporation.",
				"entityType": "Address",
				"matchCodes": [
					"Good"
				],
				"name": "90 Rockwood Way, St Marys, NB E3A 6X4, Canada",
				"statusCode": 200,
				"statusDescription": "OK",
				"traceId": "e036428143b642e5b7f13c4a80e6f302|BN20130719|7.7.0.0|",
				"addressLine": "90 Rockwood Way",
				"adminDistrict": "NB",
				"adminDistrict2": "York",
				"countryRegion": "Canada",
				"formattedAddress": "90 Rockwood Way, St Marys, NB E3A 6X4, Canada",
				"locality": "St Marys",
				"postalCode": "E3A 6X4"
			},
			"geometry": {
				"type": "Point",
				"coordinates": [
					-66.59301,
					45.94694
				]
			},
			"bbox": [
				-66.5946267,
				45.9458158,
				-66.5913933,
				45.9480642
			]
		}
	]
}
