{
	"type": "FeatureCollection",
	"features": [
		{
			"type": "Feature",
			"properties": {
				"confidence": 9,
				"authenticationResultCode": "ValidCredentials",
				"brandLogoUri": "http://dev.virtualearth.net/Branding/logo_powered_by.png",
				"copyright": "Copyright © 2017 Microsoft and its suppliers. All rights reserved. This API cannot be accessed and the content and any results may not be used, reproduced or transmitted in any manner without express written permission from Microsoft Corporation.",
				"entityType": "Address",
				"matchCodes": [
					"Good"
				],
				"name": "902 Lawson Ave, Kelowna, BC V1Y 6T1, Canada",
				"statusCode": 200,
				"statusDescription": "OK",
				"traceId": "92feb0eb0972476b82d152a9fef59944|BN20160335|7.7.0.0|",
				"addressLine": "902 Lawson Ave",
				"adminDistrict": "BC",
				"adminDistrict2": "Central Okanagan",
				"countryRegion": "Canada",
				"formattedAddress": "902 Lawson Ave, Kelowna, BC V1Y 6T1, Canada",
				"locality": "Kelowna",
				"neighborhood": "North End",
				"postalCode": "V1Y 6T1"
			},
			"geometry": {
				"type": "Point",
				"coordinates": [
					-119.48249,
					49.88751
				]
			},
			"bbox": [
				-119.4842348,
				49.8863858,
				-119.4807452,
				49.8886342
			]
		}
	]
}
