{
	"type": "FeatureCollection",
	"features": [
		{
			"type": "Feature",
			"properties": {
				"confidence": 9,
				"authenticationResultCode": "ValidCredentials",
				"brandLogoUri": "http://dev.virtualearth.net/Branding/logo_powered_by.png",
				"copyright": "Copyright © 2017 Microsoft and its suppliers. All rights reserved. This API cannot be accessed and the content and any results may not be used, reproduced or transmitted in any manner without express written permission from Microsoft Corporation.",
				"entityType": "Address",
				"matchCodes": [
					"Good"
				],
				"name": "904 HWY-64, French River, ON P0M 1A0, Canada",
				"statusCode": 200,
				"statusDescription": "OK",
				"traceId": "c90e359931b54eba82eadd7f20c87e22|BN20131519|7.7.0.0|",
				"addressLine": "904 HWY-64",
				"adminDistrict": "ON",
				"adminDistrict2": "Sudbury",
				"countryRegion": "Canada",
				"formattedAddress": "904 HWY-64, French River, ON P0M 1A0, Canada",
				"locality": "French River",
				"postalCode": "P0M 1A0"
			},
			"geometry": {
				"type": "Point",
				"coordinates": [
					-80.6056318,
					46.1042483
				]
			},
			"bbox": [
				-80.6072531,
				46.1031242,
				-80.6040105,
				46.1053725
			]
		}
	]
}
