{
	"type": "FeatureCollection",
	"features": [
		{
			"type": "Feature",
			"properties": {
				"confidence": 7,
				"authenticationResultCode": "ValidCredentials",
				"brandLogoUri": "http://dev.virtualearth.net/Branding/logo_powered_by.png",
				"copyright": "Copyright © 2017 Microsoft and its suppliers. All rights reserved. This API cannot be accessed and the content and any results may not be used, reproduced or transmitted in any manner without express written permission from Microsoft Corporation.",
				"entityType": "Neighborhood",
				"matchCodes": [
					"UpHierarchy"
				],
				"name": "Old Ridge, St Stephen Parish, New Brunswick, Canada",
				"statusCode": 200,
				"statusDescription": "OK",
				"traceId": "457a466fc213482c9d5c273517cb5c20|BN20181720|7.7.0.0|",
				"adminDistrict": "NB",
				"adminDistrict2": "Charlotte",
				"countryRegion": "Canada",
				"formattedAddress": "Old Ridge, St Stephen Parish, New Brunswick, Canada",
				"locality": "St Stephen Parish",
				"neighborhood": "Old Ridge"
			},
			"geometry": {
				"type": "Point",
				"coordinates": [
					-67.2941589355469,
					45.2722702026367
				]
			},
			"bbox": [
				-67.3014769075654,
				45.268407485066,
				-67.2868409635283,
				45.2761329202074
			]
		}
	]
}
