{
	"type": "FeatureCollection",
	"features": [
		{
			"type": "Feature",
			"properties": {
				"confidence": 9,
				"authenticationResultCode": "ValidCredentials",
				"brandLogoUri": "http://dev.virtualearth.net/Branding/logo_powered_by.png",
				"copyright": "Copyright © 2017 Microsoft and its suppliers. All rights reserved. This API cannot be accessed and the content and any results may not be used, reproduced or transmitted in any manner without express written permission from Microsoft Corporation.",
				"entityType": "Address",
				"matchCodes": [
					"Good"
				],
				"name": "90 Hutchings St, Winnipeg, MB R2X 2X1, Canada",
				"statusCode": 200,
				"statusDescription": "OK",
				"traceId": "690d4bbce0354af5a824c9f7af7c40d6|BN20130520|7.7.0.0|",
				"addressLine": "90 Hutchings St",
				"adminDistrict": "MB",
				"adminDistrict2": "Manitoba",
				"countryRegion": "Canada",
				"formattedAddress": "90 Hutchings St, Winnipeg, MB R2X 2X1, Canada",
				"locality": "Winnipeg",
				"neighborhood": "Inkster Industrial Park",
				"postalCode": "R2X 2X1"
			},
			"geometry": {
				"type": "Point",
				"coordinates": [
					-97.18486,
					49.93922
				]
			},
			"bbox": [
				-97.1866067,
				49.9380958,
				-97.1831133,
				49.9403442
			]
		}
	]
}
