{
	"type": "FeatureCollection",
	"features": [
		{
			"type": "Feature",
			"properties": {
				"confidence": 9,
				"authenticationResultCode": "ValidCredentials",
				"brandLogoUri": "http://dev.virtualearth.net/Branding/logo_powered_by.png",
				"copyright": "Copyright © 2017 Microsoft and its suppliers. All rights reserved. This API cannot be accessed and the content and any results may not be used, reproduced or transmitted in any manner without express written permission from Microsoft Corporation.",
				"entityType": "Address",
				"matchCodes": [
					"Good"
				],
				"name": "91 Euston St, Charlottetown, PE C1A 1W3, Canada",
				"statusCode": 200,
				"statusDescription": "OK",
				"traceId": "2b0e4eebb4234e5bb61be815987a4dea|BN20130625|7.7.0.0|",
				"addressLine": "91 Euston St",
				"adminDistrict": "PE",
				"adminDistrict2": "Queens",
				"countryRegion": "Canada",
				"formattedAddress": "91 Euston St, Charlottetown, PE C1A 1W3, Canada",
				"locality": "Charlottetown",
				"neighborhood": "St Avard's",
				"postalCode": "C1A 1W3"
			},
			"geometry": {
				"type": "Point",
				"coordinates": [
					-63.13108,
					46.23705
				]
			},
			"bbox": [
				-63.1327053,
				46.2359258,
				-63.1294547,
				46.2381742
			]
		}
	]
}
