{
	"type": "FeatureCollection",
	"features": [
		{
			"type": "Feature",
			"properties": {
				"confidence": 9,
				"authenticationResultCode": "ValidCredentials",
				"brandLogoUri": "http://dev.virtualearth.net/Branding/logo_powered_by.png",
				"copyright": "Copyright © 2017 Microsoft and its suppliers. All rights reserved. This API cannot be accessed and the content and any results may not be used, reproduced or transmitted in any manner without express written permission from Microsoft Corporation.",
				"entityType": "Address",
				"matchCodes": [
					"Good"
				],
				"name": "9100 Boulevard Ray-Lawson, Anjou, QC H1J 1K8, Canada",
				"statusCode": 200,
				"statusDescription": "OK",
				"traceId": "cf684bf13fbf4974ad86e5c2691370e2|BN20130423|7.7.0.0|",
				"addressLine": "9100 Boulevard Ray-Lawson",
				"adminDistrict": "QC",
				"adminDistrict2": "Montreal",
				"countryRegion": "Canada",
				"formattedAddress": "9100 Boulevard Ray-Lawson, Anjou, QC H1J 1K8, Canada",
				"locality": "Montreal",
				"neighborhood": "Anjou",
				"postalCode": "H1J 1K8"
			},
			"geometry": {
				"type": "Point",
				"coordinates": [
					-73.56434,
					45.61698
				]
			},
			"bbox": [
				-73.5659472,
				45.6158558,
				-73.5627328,
				45.6181042
			]
		}
	]
}
