{
	"type": "FeatureCollection",
	"features": [
		{
			"type": "Feature",
			"properties": {
				"confidence": 9,
				"authenticationResultCode": "ValidCredentials",
				"brandLogoUri": "http://dev.virtualearth.net/Branding/logo_powered_by.png",
				"copyright": "Copyright © 2017 Microsoft and its suppliers. All rights reserved. This API cannot be accessed and the content and any results may not be used, reproduced or transmitted in any manner without express written permission from Microsoft Corporation.",
				"entityType": "Address",
				"matchCodes": [
					"Good"
				],
				"name": "9131 Keele St, Concord, ON L4K 0G7, Canada",
				"statusCode": 200,
				"statusDescription": "OK",
				"traceId": "cf2adeae4dc14f8aa9049c405ddb7d32|BN20200239|7.7.0.0|",
				"addressLine": "9131 Keele St",
				"adminDistrict": "ON",
				"adminDistrict2": "York",
				"countryRegion": "Canada",
				"formattedAddress": "9131 Keele St, Concord, ON L4K 0G7, Canada",
				"locality": "Vaughan",
				"neighborhood": "Concord",
				"postalCode": "L4K 0G7"
			},
			"geometry": {
				"type": "Point",
				"coordinates": [
					-79.50699,
					43.8343599
				]
			},
			"bbox": [
				-79.5085484,
				43.8332357,
				-79.5054316,
				43.8354841
			]
		}
	]
}
