{
	"type": "FeatureCollection",
	"features": [
		{
			"type": "Feature",
			"properties": {
				"confidence": 9,
				"authenticationResultCode": "ValidCredentials",
				"brandLogoUri": "http://dev.virtualearth.net/Branding/logo_powered_by.png",
				"copyright": "Copyright © 2017 Microsoft and its suppliers. All rights reserved. This API cannot be accessed and the content and any results may not be used, reproduced or transmitted in any manner without express written permission from Microsoft Corporation.",
				"entityType": "Address",
				"matchCodes": [
					"Good"
				],
				"name": "919 Palmerston Ave, Toronto, ON M6G 2S4, Canada",
				"statusCode": 200,
				"statusDescription": "OK",
				"traceId": "04cc617ef86b465392a3b77fb2958f0c|BN20130431|7.7.0.0|",
				"addressLine": "919 Palmerston Ave",
				"adminDistrict": "ON",
				"adminDistrict2": "Toronto",
				"countryRegion": "Canada",
				"formattedAddress": "919 Palmerston Ave, Toronto, ON M6G 2S4, Canada",
				"locality": "Toronto",
				"neighborhood": "Annex",
				"postalCode": "M6G 2S4"
			},
			"geometry": {
				"type": "Point",
				"coordinates": [
					-79.41659,
					43.67313
				]
			},
			"bbox": [
				-79.4181442,
				43.6720058,
				-79.4150358,
				43.6742542
			]
		}
	]
}
