{
	"type": "FeatureCollection",
	"features": [
		{
			"type": "Feature",
			"properties": {
				"confidence": 9,
				"authenticationResultCode": "ValidCredentials",
				"brandLogoUri": "http://dev.virtualearth.net/Branding/logo_powered_by.png",
				"copyright": "Copyright © 2017 Microsoft and its suppliers. All rights reserved. This API cannot be accessed and the content and any results may not be used, reproduced or transmitted in any manner without express written permission from Microsoft Corporation.",
				"entityType": "Address",
				"matchCodes": [
					"Good"
				],
				"name": "92 Dana Cres, Thornhill, ON L4J 2R5, Canada",
				"statusCode": 200,
				"statusDescription": "OK",
				"traceId": "8d4b6eb5adc44e98ae62f905cde972fb|BN20130621|7.7.0.0|",
				"addressLine": "92 Dana Cres",
				"adminDistrict": "ON",
				"adminDistrict2": "York",
				"countryRegion": "Canada",
				"formattedAddress": "92 Dana Cres, Thornhill, ON L4J 2R5, Canada",
				"locality": "Vaughan",
				"neighborhood": "Thornhill",
				"postalCode": "L4J 2R5"
			},
			"geometry": {
				"type": "Point",
				"coordinates": [
					-79.44529,
					43.80139
				]
			},
			"bbox": [
				-79.4468476,
				43.8002658,
				-79.4437324,
				43.8025142
			]
		}
	]
}
