{
	"type": "FeatureCollection",
	"features": [
		{
			"type": "Feature",
			"properties": {
				"confidence": 9,
				"authenticationResultCode": "ValidCredentials",
				"brandLogoUri": "http://dev.virtualearth.net/Branding/logo_powered_by.png",
				"copyright": "Copyright © 2017 Microsoft and its suppliers. All rights reserved. This API cannot be accessed and the content and any results may not be used, reproduced or transmitted in any manner without express written permission from Microsoft Corporation.",
				"entityType": "Address",
				"matchCodes": [
					"Good"
				],
				"name": "92190 Alaska Hwy, Whitehorse, YT Y1A 3Y8, Canada",
				"statusCode": 200,
				"statusDescription": "OK",
				"traceId": "66f56089f7614c88ba269b8f0568d390|BN20190642|7.7.0.0|",
				"addressLine": "92190 Alaska Hwy",
				"adminDistrict": "YT",
				"adminDistrict2": "Yukon",
				"countryRegion": "Canada",
				"formattedAddress": "92190 Alaska Hwy, Whitehorse, YT Y1A 3Y8, Canada",
				"locality": "Whitehorse",
				"postalCode": "Y1A 3Y8"
			},
			"geometry": {
				"type": "Point",
				"coordinates": [
					-135.1566324,
					60.7762286
				]
			},
			"bbox": [
				-135.1589349,
				60.7751045,
				-135.1543298,
				60.7773528
			]
		}
	]
}
