{
	"type": "FeatureCollection",
	"features": [
		{
			"type": "Feature",
			"properties": {
				"confidence": 9,
				"authenticationResultCode": "ValidCredentials",
				"brandLogoUri": "http://dev.virtualearth.net/Branding/logo_powered_by.png",
				"copyright": "Copyright © 2017 Microsoft and its suppliers. All rights reserved. This API cannot be accessed and the content and any results may not be used, reproduced or transmitted in any manner without express written permission from Microsoft Corporation.",
				"entityType": "Address",
				"matchCodes": [
					"Good"
				],
				"name": "927 Douglas St, Brandon, MB R7A 7B3, Canada",
				"statusCode": 200,
				"statusDescription": "OK",
				"traceId": "dee056ad45ce47f4bb9f3acb0ea4c517|BN20190642|7.7.0.0|",
				"addressLine": "927 Douglas St",
				"adminDistrict": "MB",
				"adminDistrict2": "Manitoba",
				"countryRegion": "Canada",
				"formattedAddress": "927 Douglas St, Brandon, MB R7A 7B3, Canada",
				"locality": "Brandon",
				"postalCode": "R7A 7B3"
			},
			"geometry": {
				"type": "Point",
				"coordinates": [
					-99.9231889,
					49.835507
				]
			},
			"bbox": [
				-99.9249318,
				49.8343829,
				-99.921446,
				49.8366312
			]
		}
	]
}
