{
	"type": "FeatureCollection",
	"features": [
		{
			"type": "Feature",
			"properties": {
				"confidence": 9,
				"authenticationResultCode": "ValidCredentials",
				"brandLogoUri": "http://dev.virtualearth.net/Branding/logo_powered_by.png",
				"copyright": "Copyright © 2017 Microsoft and its suppliers. All rights reserved. This API cannot be accessed and the content and any results may not be used, reproduced or transmitted in any manner without express written permission from Microsoft Corporation.",
				"entityType": "Address",
				"matchCodes": [
					"Good"
				],
				"name": "93 McKerrell Way SE, Calgary, AB T2Z 1R1, Canada",
				"statusCode": 200,
				"statusDescription": "OK",
				"traceId": "a41f46fd022b4fe798b3e5cb25ca581c|BN20130721|7.7.0.0|",
				"addressLine": "93 McKerrell Way SE",
				"adminDistrict": "AB",
				"adminDistrict2": "Alberta",
				"countryRegion": "Canada",
				"formattedAddress": "93 McKerrell Way SE, Calgary, AB T2Z 1R1, Canada",
				"locality": "Calgary",
				"neighborhood": "McKenzie Lake",
				"postalCode": "T2Z 1R1"
			},
			"geometry": {
				"type": "Point",
				"coordinates": [
					-113.97792,
					50.9058599
				]
			},
			"bbox": [
				-113.9797027,
				50.9047357,
				-113.9761373,
				50.9069841
			]
		}
	]
}
