{
	"type": "FeatureCollection",
	"features": [
		{
			"type": "Feature",
			"properties": {
				"confidence": 9,
				"authenticationResultCode": "ValidCredentials",
				"brandLogoUri": "http://dev.virtualearth.net/Branding/logo_powered_by.png",
				"copyright": "Copyright © 2017 Microsoft and its suppliers. All rights reserved. This API cannot be accessed and the content and any results may not be used, reproduced or transmitted in any manner without express written permission from Microsoft Corporation.",
				"entityType": "Address",
				"matchCodes": [
					"Good"
				],
				"name": "9304 Horton Rd SW, Calgary, AB T2V 2X4, Canada",
				"statusCode": 200,
				"statusDescription": "OK",
				"traceId": "317baf5dc7214df9843df8b7d347a79a|BN20200137|7.7.0.0|",
				"addressLine": "9304 Horton Rd SW",
				"adminDistrict": "AB",
				"adminDistrict2": "Alberta",
				"countryRegion": "Canada",
				"formattedAddress": "9304 Horton Rd SW, Calgary, AB T2V 2X4, Canada",
				"locality": "Calgary",
				"neighborhood": "Haysboro",
				"postalCode": "T2V 2X4"
			},
			"geometry": {
				"type": "Point",
				"coordinates": [
					-114.07565,
					50.97143
				]
			},
			"bbox": [
				-114.0774352,
				50.9703058,
				-114.0738648,
				50.9725542
			]
		}
	]
}
