{
	"type": "FeatureCollection",
	"features": [
		{
			"type": "Feature",
			"properties": {
				"confidence": 9,
				"authenticationResultCode": "ValidCredentials",
				"brandLogoUri": "http://dev.virtualearth.net/Branding/logo_powered_by.png",
				"copyright": "Copyright © 2017 Microsoft and its suppliers. All rights reserved. This API cannot be accessed and the content and any results may not be used, reproduced or transmitted in any manner without express written permission from Microsoft Corporation.",
				"entityType": "Address",
				"matchCodes": [
					"Good"
				],
				"name": "942 Douglas St, Brandon, MB R7A 7B2, Canada",
				"statusCode": 200,
				"statusDescription": "OK",
				"traceId": "03a23c64c8b04601834787b0e8df2919|BN20130631|7.7.0.0|",
				"addressLine": "942 Douglas St",
				"adminDistrict": "MB",
				"adminDistrict2": "Manitoba",
				"countryRegion": "Canada",
				"formattedAddress": "942 Douglas St, Brandon, MB R7A 7B2, Canada",
				"locality": "Brandon",
				"postalCode": "R7A 7B2"
			},
			"geometry": {
				"type": "Point",
				"coordinates": [
					-99.9183,
					49.83226
				]
			},
			"bbox": [
				-99.9200428,
				49.8311358,
				-99.9165572,
				49.8333842
			]
		}
	]
}
