{
	"type": "FeatureCollection",
	"features": [
		{
			"type": "Feature",
			"properties": {
				"confidence": 9,
				"authenticationResultCode": "ValidCredentials",
				"brandLogoUri": "http://dev.virtualearth.net/Branding/logo_powered_by.png",
				"copyright": "Copyright © 2017 Microsoft and its suppliers. All rights reserved. This API cannot be accessed and the content and any results may not be used, reproduced or transmitted in any manner without express written permission from Microsoft Corporation.",
				"entityType": "Address",
				"matchCodes": [
					"Good"
				],
				"name": "945 Eglinton Ave E, East York, ON M4G 4B5, Canada",
				"statusCode": 200,
				"statusDescription": "OK",
				"traceId": "6377aab97eb44bcd887707b5fc70cb8b|BN20130625|7.7.0.0|",
				"addressLine": "945 Eglinton Ave E",
				"adminDistrict": "ON",
				"adminDistrict2": "Toronto",
				"countryRegion": "Canada",
				"formattedAddress": "945 Eglinton Ave E, East York, ON M4G 4B5, Canada",
				"locality": "Toronto",
				"neighborhood": "Thorncliffe Park",
				"postalCode": "M4G 4B5"
			},
			"geometry": {
				"type": "Point",
				"coordinates": [
					-79.35897,
					43.7142399
				]
			},
			"bbox": [
				-79.3605253,
				43.7131157,
				-79.3574147,
				43.7153641
			]
		}
	]
}
