{
	"type": "FeatureCollection",
	"features": [
		{
			"type": "Feature",
			"properties": {
				"confidence": 9,
				"authenticationResultCode": "ValidCredentials",
				"brandLogoUri": "http://dev.virtualearth.net/Branding/logo_powered_by.png",
				"copyright": "Copyright © 2017 Microsoft and its suppliers. All rights reserved. This API cannot be accessed and the content and any results may not be used, reproduced or transmitted in any manner without express written permission from Microsoft Corporation.",
				"entityType": "Address",
				"matchCodes": [
					"Good"
				],
				"name": "947 Burlington St E, Hamilton, ON L8L 4K6, Canada",
				"statusCode": 200,
				"statusDescription": "OK",
				"traceId": "871d35500852432398b29ef47a011eeb|BN20130532|7.7.0.0|",
				"addressLine": "947 Burlington St E",
				"adminDistrict": "ON",
				"adminDistrict2": "Hamilton",
				"countryRegion": "Canada",
				"formattedAddress": "947 Burlington St E, Hamilton, ON L8L 4K6, Canada",
				"locality": "Hamilton",
				"neighborhood": "Industrial Sector C",
				"postalCode": "L8L 4K6"
			},
			"geometry": {
				"type": "Point",
				"coordinates": [
					-79.8227714,
					43.2631453
				]
			},
			"bbox": [
				-79.8243151,
				43.2620212,
				-79.8212277,
				43.2642695
			]
		}
	]
}
