{
	"type": "FeatureCollection",
	"features": [
		{
			"type": "Feature",
			"properties": {
				"confidence": 9,
				"authenticationResultCode": "ValidCredentials",
				"brandLogoUri": "http://dev.virtualearth.net/Branding/logo_powered_by.png",
				"copyright": "Copyright © 2017 Microsoft and its suppliers. All rights reserved. This API cannot be accessed and the content and any results may not be used, reproduced or transmitted in any manner without express written permission from Microsoft Corporation.",
				"entityType": "Address",
				"matchCodes": [
					"Good"
				],
				"name": "949 Wilson Ave, North York, ON M3K 1G2, Canada",
				"statusCode": 200,
				"statusDescription": "OK",
				"traceId": "e71549f39287430eaeb0509bfd547276|BN20130532|7.7.0.0|",
				"addressLine": "949 Wilson Ave",
				"adminDistrict": "ON",
				"adminDistrict2": "Toronto",
				"countryRegion": "Canada",
				"formattedAddress": "949 Wilson Ave, North York, ON M3K 1G2, Canada",
				"locality": "Toronto",
				"neighborhood": "Downsview-Roding-CFB",
				"postalCode": "M3K 1G2"
			},
			"geometry": {
				"type": "Point",
				"coordinates": [
					-79.47489,
					43.72843
				]
			},
			"bbox": [
				-79.4764457,
				43.7273058,
				-79.4733343,
				43.7295542
			]
		}
	]
}
