{
	"type": "FeatureCollection",
	"features": [
		{
			"type": "Feature",
			"properties": {
				"confidence": 9,
				"authenticationResultCode": "ValidCredentials",
				"brandLogoUri": "http://dev.virtualearth.net/Branding/logo_powered_by.png",
				"copyright": "Copyright © 2017 Microsoft and its suppliers. All rights reserved. This API cannot be accessed and the content and any results may not be used, reproduced or transmitted in any manner without express written permission from Microsoft Corporation.",
				"entityType": "Address",
				"matchCodes": [
					"Good"
				],
				"name": "95 5e Avenue, Pincourt, QC J7W 5K8, Canada",
				"statusCode": 200,
				"statusDescription": "OK",
				"traceId": "eec9480eb7d84e2fa35ce57963834167|BN20320521|7.7.0.0|",
				"addressLine": "95 5e Avenue",
				"adminDistrict": "QC",
				"adminDistrict2": "Vaudreuil-Soulanges",
				"countryRegion": "Canada",
				"formattedAddress": "95 5e Avenue, Pincourt, QC J7W 5K8, Canada",
				"locality": "Pincourt",
				"postalCode": "J7W 5K8"
			},
			"geometry": {
				"type": "Point",
				"coordinates": [
					-73.99372,
					45.38196
				]
			},
			"bbox": [
				-73.9953205,
				45.3808358,
				-73.9921195,
				45.3830842
			]
		}
	]
}
