{
	"type": "FeatureCollection",
	"features": [
		{
			"type": "Feature",
			"properties": {
				"confidence": 9,
				"authenticationResultCode": "ValidCredentials",
				"brandLogoUri": "http://dev.virtualearth.net/Branding/logo_powered_by.png",
				"copyright": "Copyright © 2017 Microsoft and its suppliers. All rights reserved. This API cannot be accessed and the content and any results may not be used, reproduced or transmitted in any manner without express written permission from Microsoft Corporation.",
				"entityType": "Address",
				"matchCodes": [
					"Good"
				],
				"name": "95 Grenadier Rd, Toronto, ON M6R 1R1, Canada",
				"statusCode": 200,
				"statusDescription": "OK",
				"traceId": "7efb7cdef24e4b51afa31641d1b5076c|BN20130625|7.7.0.0|",
				"addressLine": "95 Grenadier Rd",
				"adminDistrict": "ON",
				"adminDistrict2": "Toronto",
				"countryRegion": "Canada",
				"formattedAddress": "95 Grenadier Rd, Toronto, ON M6R 1R1, Canada",
				"locality": "Toronto",
				"neighborhood": "Roncesvalles",
				"postalCode": "M6R 1R1"
			},
			"geometry": {
				"type": "Point",
				"coordinates": [
					-79.44824,
					43.64911
				]
			},
			"bbox": [
				-79.4497936,
				43.6479858,
				-79.4466864,
				43.6502342
			]
		}
	]
}
