{
	"type": "FeatureCollection",
	"features": [
		{
			"type": "Feature",
			"properties": {
				"confidence": 9,
				"authenticationResultCode": "ValidCredentials",
				"brandLogoUri": "http://dev.virtualearth.net/Branding/logo_powered_by.png",
				"copyright": "Copyright © 2017 Microsoft and its suppliers. All rights reserved. This API cannot be accessed and the content and any results may not be used, reproduced or transmitted in any manner without express written permission from Microsoft Corporation.",
				"entityType": "Address",
				"matchCodes": [
					"Good"
				],
				"name": "9570 McCowan Rd, Markham, ON L3P 8M1, Canada",
				"statusCode": 200,
				"statusDescription": "OK",
				"traceId": "4d6f6a9fef7a441aabe33c8d760ba61d|BN20290118|7.7.0.0|",
				"addressLine": "9570 McCowan Rd",
				"adminDistrict": "ON",
				"adminDistrict2": "York",
				"countryRegion": "Canada",
				"formattedAddress": "9570 McCowan Rd, Markham, ON L3P 8M1, Canada",
				"locality": "Markham",
				"postalCode": "L3P 8M1"
			},
			"geometry": {
				"type": "Point",
				"coordinates": [
					-79.2915,
					43.89249
				]
			},
			"bbox": [
				-79.2930599,
				43.8913658,
				-79.2899401,
				43.8936142
			]
		}
	]
}
