{
	"type": "FeatureCollection",
	"features": [
		{
			"type": "Feature",
			"properties": {
				"confidence": 9,
				"authenticationResultCode": "ValidCredentials",
				"brandLogoUri": "http://dev.virtualearth.net/Branding/logo_powered_by.png",
				"copyright": "Copyright © 2017 Microsoft and its suppliers. All rights reserved. This API cannot be accessed and the content and any results may not be used, reproduced or transmitted in any manner without express written permission from Microsoft Corporation.",
				"entityType": "Address",
				"matchCodes": [
					"Good"
				],
				"name": "97 Rue de Vaudreuil, Boucherville, QC J4B 1K7, Canada",
				"statusCode": 200,
				"statusDescription": "OK",
				"traceId": "145cf492fdb6461ba10d06dcdb549d55|BN20130423|7.7.0.0|",
				"addressLine": "97 Rue de Vaudreuil",
				"adminDistrict": "QC",
				"adminDistrict2": "Longueuil",
				"countryRegion": "Canada",
				"formattedAddress": "97 Rue de Vaudreuil, Boucherville, QC J4B 1K7, Canada",
				"locality": "Boucherville",
				"postalCode": "J4B 1K7"
			},
			"geometry": {
				"type": "Point",
				"coordinates": [
					-73.46129,
					45.58234
				]
			},
			"bbox": [
				-73.4628962,
				45.5812158,
				-73.4596838,
				45.5834642
			]
		}
	]
}
