{
	"type": "FeatureCollection",
	"features": [
		{
			"type": "Feature",
			"properties": {
				"confidence": 9,
				"authenticationResultCode": "ValidCredentials",
				"brandLogoUri": "http://dev.virtualearth.net/Branding/logo_powered_by.png",
				"copyright": "Copyright © 2017 Microsoft and its suppliers. All rights reserved. This API cannot be accessed and the content and any results may not be used, reproduced or transmitted in any manner without express written permission from Microsoft Corporation.",
				"entityType": "Address",
				"matchCodes": [
					"Good"
				],
				"name": "97 N Renfrew St, Vancouver, BC V5K 3N6, Canada",
				"statusCode": 200,
				"statusDescription": "OK",
				"traceId": "0fa674800e5749c887998dfb8e78c190|BN20130631|7.7.0.0|",
				"addressLine": "97 N Renfrew St",
				"adminDistrict": "BC",
				"adminDistrict2": "Greater Vancouver",
				"countryRegion": "Canada",
				"formattedAddress": "97 N Renfrew St, Vancouver, BC V5K 3N6, Canada",
				"locality": "Vancouver",
				"neighborhood": "Hastings-Sunrise",
				"postalCode": "V5K 3N6"
			},
			"geometry": {
				"type": "Point",
				"coordinates": [
					-123.0441949,
					49.2855603
				]
			},
			"bbox": [
				-123.0459183,
				49.2844361,
				-123.0424715,
				49.2866844
			]
		}
	]
}
