{
	"type": "FeatureCollection",
	"features": [
		{
			"type": "Feature",
			"properties": {
				"confidence": 9,
				"authenticationResultCode": "ValidCredentials",
				"brandLogoUri": "http://dev.virtualearth.net/Branding/logo_powered_by.png",
				"copyright": "Copyright © 2017 Microsoft and its suppliers. All rights reserved. This API cannot be accessed and the content and any results may not be used, reproduced or transmitted in any manner without express written permission from Microsoft Corporation.",
				"entityType": "Address",
				"matchCodes": [
					"Good"
				],
				"name": "9707 Franklin Ave, Fort McMurray, AB T9H 2K1, Canada",
				"statusCode": 200,
				"statusDescription": "OK",
				"traceId": "338b1fba9bd7473d8b0a9652dc642fbe|BN20130620|7.7.0.0|",
				"addressLine": "9707 Franklin Ave",
				"adminDistrict": "AB",
				"adminDistrict2": "Alberta",
				"countryRegion": "Canada",
				"formattedAddress": "9707 Franklin Ave, Fort McMurray, AB T9H 2K1, Canada",
				"locality": "Wood Buffalo",
				"neighborhood": "Fort McMurray",
				"postalCode": "T9H 2K1"
			},
			"geometry": {
				"type": "Point",
				"coordinates": [
					-111.37534,
					56.72486
				]
			},
			"bbox": [
				-111.3773889,
				56.7237358,
				-111.3732911,
				56.7259842
			]
		}
	]
}
