{
	"type": "FeatureCollection",
	"features": [
		{
			"type": "Feature",
			"properties": {
				"confidence": 9,
				"authenticationResultCode": "ValidCredentials",
				"brandLogoUri": "http://dev.virtualearth.net/Branding/logo_powered_by.png",
				"copyright": "Copyright © 2017 Microsoft and its suppliers. All rights reserved. This API cannot be accessed and the content and any results may not be used, reproduced or transmitted in any manner without express written permission from Microsoft Corporation.",
				"entityType": "Address",
				"matchCodes": [
					"Good"
				],
				"name": "9728 199A St, Langley, BC V1M 2X7, Canada",
				"statusCode": 200,
				"statusDescription": "OK",
				"traceId": "6b7e5cadd33543acbd9ce76559517bf9|BN20181720|7.7.0.0|",
				"addressLine": "9728 199A St",
				"adminDistrict": "BC",
				"adminDistrict2": "Greater Vancouver",
				"countryRegion": "Canada",
				"formattedAddress": "9728 199A St, Langley, BC V1M 2X7, Canada",
				"locality": "Langley",
				"postalCode": "V1M 2X7"
			},
			"geometry": {
				"type": "Point",
				"coordinates": [
					-122.6690458,
					49.1798317
				]
			},
			"bbox": [
				-122.6707655,
				49.1787076,
				-122.6673261,
				49.1809559
			]
		}
	]
}
