{
	"type": "FeatureCollection",
	"features": [
		{
			"type": "Feature",
			"properties": {
				"confidence": 9,
				"authenticationResultCode": "ValidCredentials",
				"brandLogoUri": "http://dev.virtualearth.net/Branding/logo_powered_by.png",
				"copyright": "Copyright © 2017 Microsoft and its suppliers. All rights reserved. This API cannot be accessed and the content and any results may not be used, reproduced or transmitted in any manner without express written permission from Microsoft Corporation.",
				"entityType": "Address",
				"matchCodes": [
					"Good"
				],
				"name": "975 Wilson Ave, Kitchener, ON N2C 1J1, Canada",
				"statusCode": 200,
				"statusDescription": "OK",
				"traceId": "aef1223625864d728bc29279f0492416|BN20190642|7.7.0.0|",
				"addressLine": "975 Wilson Ave",
				"adminDistrict": "ON",
				"adminDistrict2": "Waterloo",
				"countryRegion": "Canada",
				"formattedAddress": "975 Wilson Ave, Kitchener, ON N2C 1J1, Canada",
				"locality": "Kitchener",
				"neighborhood": "Trillium Industrial Park",
				"postalCode": "N2C 1J1"
			},
			"geometry": {
				"type": "Point",
				"coordinates": [
					-80.44217,
					43.40989
				]
			},
			"bbox": [
				-80.4437174,
				43.4087658,
				-80.4406226,
				43.4110142
			]
		}
	]
}
