{
	"type": "FeatureCollection",
	"features": [
		{
			"type": "Feature",
			"properties": {
				"confidence": 9,
				"authenticationResultCode": "ValidCredentials",
				"brandLogoUri": "http://dev.virtualearth.net/Branding/logo_powered_by.png",
				"copyright": "Copyright © 2017 Microsoft and its suppliers. All rights reserved. This API cannot be accessed and the content and any results may not be used, reproduced or transmitted in any manner without express written permission from Microsoft Corporation.",
				"entityType": "Address",
				"matchCodes": [
					"Good"
				],
				"name": "977 Hampshire Rd, Victoria, BC V8S 4S3, Canada",
				"statusCode": 200,
				"statusDescription": "OK",
				"traceId": "731be7a22e464625b564ee295d8a6dd1|BN20130625|7.7.0.0|",
				"addressLine": "977 Hampshire Rd",
				"adminDistrict": "BC",
				"adminDistrict2": "Capital",
				"countryRegion": "Canada",
				"formattedAddress": "977 Hampshire Rd, Victoria, BC V8S 4S3, Canada",
				"locality": "Oak Bay",
				"neighborhood": "Victoria",
				"postalCode": "V8S 4S3"
			},
			"geometry": {
				"type": "Point",
				"coordinates": [
					-123.31555,
					48.41997
				]
			},
			"bbox": [
				-123.3172439,
				48.4188458,
				-123.3138561,
				48.4210942
			]
		}
	]
}
