{
	"type": "FeatureCollection",
	"features": [
		{
			"type": "Feature",
			"properties": {
				"confidence": 9,
				"authenticationResultCode": "ValidCredentials",
				"brandLogoUri": "http://dev.virtualearth.net/Branding/logo_powered_by.png",
				"copyright": "Copyright © 2017 Microsoft and its suppliers. All rights reserved. This API cannot be accessed and the content and any results may not be used, reproduced or transmitted in any manner without express written permission from Microsoft Corporation.",
				"entityType": "Address",
				"matchCodes": [
					"Good"
				],
				"name": "9835 101 Ave, Grande Prairie, AB T8V 5V4, Canada",
				"statusCode": 200,
				"statusDescription": "OK",
				"traceId": "b527236343854eb6bcf29b4f08547155|BN20130620|7.7.0.0|",
				"addressLine": "9835 101 Ave",
				"adminDistrict": "AB",
				"adminDistrict2": "Alberta",
				"countryRegion": "Canada",
				"formattedAddress": "9835 101 Ave, Grande Prairie, AB T8V 5V4, Canada",
				"locality": "Grande Prairie",
				"neighborhood": "VLA",
				"postalCode": "T8V 5V4"
			},
			"geometry": {
				"type": "Point",
				"coordinates": [
					-118.79105,
					55.17133
				]
			},
			"bbox": [
				-118.7930183,
				55.1702058,
				-118.7890817,
				55.1724542
			]
		}
	]
}
