{
	"type": "FeatureCollection",
	"features": [
		{
			"type": "Feature",
			"properties": {
				"confidence": 9,
				"authenticationResultCode": "ValidCredentials",
				"brandLogoUri": "http://dev.virtualearth.net/Branding/logo_powered_by.png",
				"copyright": "Copyright © 2017 Microsoft and its suppliers. All rights reserved. This API cannot be accessed and the content and any results may not be used, reproduced or transmitted in any manner without express written permission from Microsoft Corporation.",
				"entityType": "Address",
				"matchCodes": [
					"Good"
				],
				"name": "985 Syscon Rd, Burlington, ON L7L 5S3, Canada",
				"statusCode": 200,
				"statusDescription": "OK",
				"traceId": "13b7afa333434d3abdd06b975b95c8e9|BN20130532|7.7.0.0|",
				"addressLine": "985 Syscon Rd",
				"adminDistrict": "ON",
				"adminDistrict2": "Halton",
				"countryRegion": "Canada",
				"formattedAddress": "985 Syscon Rd, Burlington, ON L7L 5S3, Canada",
				"locality": "Burlington",
				"neighborhood": "Pinedale",
				"postalCode": "L7L 5S3"
			},
			"geometry": {
				"type": "Point",
				"coordinates": [
					-79.75735,
					43.39308
				]
			},
			"bbox": [
				-79.758897,
				43.3919558,
				-79.755803,
				43.3942042
			]
		}
	]
}
