{
	"type": "FeatureCollection",
	"features": [
		{
			"type": "Feature",
			"properties": {
				"confidence": 9,
				"authenticationResultCode": "ValidCredentials",
				"brandLogoUri": "http://dev.virtualearth.net/Branding/logo_powered_by.png",
				"copyright": "Copyright © 2017 Microsoft and its suppliers. All rights reserved. This API cannot be accessed and the content and any results may not be used, reproduced or transmitted in any manner without express written permission from Microsoft Corporation.",
				"entityType": "Address",
				"matchCodes": [
					"Good"
				],
				"name": "99 Tsakis Rd, Port Hardy, BC V0N, Canada",
				"statusCode": 200,
				"statusDescription": "OK",
				"traceId": "9a799f74967e40f1813aeeb44a665f41|BN20260231|7.7.0.0|",
				"addressLine": "99 Tsakis Rd",
				"adminDistrict": "BC",
				"adminDistrict2": "Mt Waddington",
				"countryRegion": "Canada",
				"formattedAddress": "99 Tsakis Rd, Port Hardy, BC V0N, Canada",
				"locality": "Port Hardy",
				"postalCode": "V0N 2P0"
			},
			"geometry": {
				"type": "Point",
				"coordinates": [
					-127.4078396,
					50.6950656
				]
			},
			"bbox": [
				-127.4096142,
				50.6939414,
				-127.4060649,
				50.6961897
			]
		}
	]
}
