{
	"type": "FeatureCollection",
	"features": [
		{
			"type": "Feature",
			"properties": {
				"confidence": 9,
				"authenticationResultCode": "ValidCredentials",
				"brandLogoUri": "http://dev.virtualearth.net/Branding/logo_powered_by.png",
				"copyright": "Copyright © 2017 Microsoft and its suppliers. All rights reserved. This API cannot be accessed and the content and any results may not be used, reproduced or transmitted in any manner without express written permission from Microsoft Corporation.",
				"entityType": "Address",
				"matchCodes": [
					"Good"
				],
				"name": "9913 100 Ave, Grande Prairie, AB T8V 0V1, Canada",
				"statusCode": 200,
				"statusDescription": "OK",
				"traceId": "c223a509cc9a4b10accc63a39c2318d8|BN20130422|7.7.0.0|",
				"addressLine": "9913 100 Ave",
				"adminDistrict": "AB",
				"adminDistrict2": "Alberta",
				"countryRegion": "Canada",
				"formattedAddress": "9913 100 Ave, Grande Prairie, AB T8V 0V1, Canada",
				"locality": "Grande Prairie",
				"neighborhood": "Highland Place",
				"postalCode": "T8V 0V1"
			},
			"geometry": {
				"type": "Point",
				"coordinates": [
					-118.79286,
					55.17043
				]
			},
			"bbox": [
				-118.7948283,
				55.1693058,
				-118.7908917,
				55.1715542
			]
		}
	]
}
