{
	"type": "FeatureCollection",
	"features": [
		{
			"type": "Feature",
			"properties": {
				"confidence": 9,
				"authenticationResultCode": "ValidCredentials",
				"brandLogoUri": "http://dev.virtualearth.net/Branding/logo_powered_by.png",
				"copyright": "Copyright © 2017 Microsoft and its suppliers. All rights reserved. This API cannot be accessed and the content and any results may not be used, reproduced or transmitted in any manner without express written permission from Microsoft Corporation.",
				"entityType": "Address",
				"matchCodes": [
					"Good"
				],
				"name": "992 Dillingham Rd, Pickering, ON L1W 1Z6, Canada",
				"statusCode": 200,
				"statusDescription": "OK",
				"traceId": "4418b33dd8294f96a9fb766fa92f9646|BN20190653|7.7.0.0|",
				"addressLine": "992 Dillingham Rd",
				"adminDistrict": "ON",
				"adminDistrict2": "Durham",
				"countryRegion": "Canada",
				"formattedAddress": "992 Dillingham Rd, Pickering, ON L1W 1Z6, Canada",
				"locality": "Pickering",
				"postalCode": "L1W 1Z6"
			},
			"geometry": {
				"type": "Point",
				"coordinates": [
					-79.06874,
					43.83148
				]
			},
			"bbox": [
				-79.0702983,
				43.8303558,
				-79.0671817,
				43.8326042
			]
		}
	]
}
