{
	"type": "FeatureCollection",
	"features": [
		{
			"type": "Feature",
			"properties": {
				"confidence": 9,
				"authenticationResultCode": "ValidCredentials",
				"brandLogoUri": "http://dev.virtualearth.net/Branding/logo_powered_by.png",
				"copyright": "Copyright © 2017 Microsoft and its suppliers. All rights reserved. This API cannot be accessed and the content and any results may not be used, reproduced or transmitted in any manner without express written permission from Microsoft Corporation.",
				"entityType": "Address",
				"matchCodes": [
					"Good"
				],
				"name": "9990 River Way, Delta, BC V4G 1M9, Canada",
				"statusCode": 200,
				"statusDescription": "OK",
				"traceId": "d125ec3040c447fba41b00078a924848|BN20130625|7.7.0.0|",
				"addressLine": "9990 River Way",
				"adminDistrict": "BC",
				"adminDistrict2": "Greater Vancouver",
				"countryRegion": "Canada",
				"formattedAddress": "9990 River Way, Delta, BC V4G 1M9, Canada",
				"locality": "Delta",
				"postalCode": "V4G 1M9"
			},
			"geometry": {
				"type": "Point",
				"coordinates": [
					-122.9451986,
					49.1490183
				]
			},
			"bbox": [
				-122.9469173,
				49.1478942,
				-122.94348,
				49.1501425
			]
		}
	]
}
