{
	"type": "FeatureCollection",
	"features": [
		{
			"type": "Feature",
			"properties": {
				"confidence": 9,
				"authenticationResultCode": "ValidCredentials",
				"brandLogoUri": "http://dev.virtualearth.net/Branding/logo_powered_by.png",
				"copyright": "Copyright © 2017 Microsoft and its suppliers. All rights reserved. This API cannot be accessed and the content and any results may not be used, reproduced or transmitted in any manner without express written permission from Microsoft Corporation.",
				"entityType": "Address",
				"matchCodes": [
					"Good"
				],
				"name": "900 Greenbank Rd, Nepean, ON K2J 4P6, Canada",
				"statusCode": 200,
				"statusDescription": "OK",
				"traceId": "8a1751349519486093dca7cfff32aa1f|BN20130521|7.7.0.0|",
				"addressLine": "900 Greenbank Rd",
				"adminDistrict": "ON",
				"adminDistrict2": "Ottawa",
				"countryRegion": "Canada",
				"formattedAddress": "900 Greenbank Rd, Nepean, ON K2J 4P6, Canada",
				"locality": "Ottawa",
				"neighborhood": "Nepean",
				"postalCode": "K2J 4P6"
			},
			"geometry": {
				"type": "Point",
				"coordinates": [
					-75.75618,
					45.28492
				]
			},
			"bbox": [
				-75.7577778,
				45.2837958,
				-75.7545822,
				45.2860442
			]
		}
	]
}
