{
	"type": "FeatureCollection",
	"features": [
		{
			"type": "Feature",
			"properties": {
				"confidence": 9,
				"authenticationResultCode": "ValidCredentials",
				"brandLogoUri": "http://dev.virtualearth.net/Branding/logo_powered_by.png",
				"copyright": "Copyright © 2017 Microsoft and its suppliers. All rights reserved. This API cannot be accessed and the content and any results may not be used, reproduced or transmitted in any manner without express written permission from Microsoft Corporation.",
				"entityType": "Address",
				"matchCodes": [
					"Good"
				],
				"name": "19567 Fraser Hwy, Surrey, BC V3S 9A4, Canada",
				"statusCode": 200,
				"statusDescription": "OK",
				"traceId": "9855e7ee32db4703a112c7893154eedc|BN20130520|7.7.0.0|",
				"addressLine": "19567 Fraser Hwy",
				"adminDistrict": "BC",
				"adminDistrict2": "Greater Vancouver",
				"countryRegion": "Canada",
				"formattedAddress": "19567 Fraser Hwy, Surrey, BC V3S 9A4, Canada",
				"locality": "Surrey",
				"neighborhood": "Cloverdale",
				"postalCode": "V3S 9A4"
			},
			"geometry": {
				"type": "Point",
				"coordinates": [
					-122.68077,
					49.11457
				]
			},
			"bbox": [
				-122.6824874,
				49.1134458,
				-122.6790526,
				49.1156942
			]
		}
	]
}
