{
	"type": "FeatureCollection",
	"features": [
		{
			"type": "Feature",
			"properties": {
				"confidence": 7,
				"authenticationResultCode": "ValidCredentials",
				"brandLogoUri": "http://dev.virtualearth.net/Branding/logo_powered_by.png",
				"copyright": "Copyright © 2017 Microsoft and its suppliers. All rights reserved. This API cannot be accessed and the content and any results may not be used, reproduced or transmitted in any manner without express written permission from Microsoft Corporation.",
				"entityType": "Postcode1",
				"matchCodes": [
					"UpHierarchy"
				],
				"name": "Kamsack, S0A 1S0, Canada",
				"statusCode": 200,
				"statusDescription": "OK",
				"traceId": "4e7c5bbb1d02402faa5c80c00f7c7127|BN20131519|7.7.0.0|",
				"adminDistrict": "SK",
				"countryRegion": "Canada",
				"formattedAddress": "Kamsack, S0A 1S0, Canada",
				"locality": "Kamsack",
				"postalCode": "S0A 1S0"
			},
			"geometry": {
				"type": "Point",
				"coordinates": [
					-101.903198242188,
					51.564811706543
				]
			},
			"bbox": [
				-101.911482689793,
				51.5609489889723,
				-101.894913794582,
				51.5686744241136
			]
		}
	]
}
