{
	"type": "FeatureCollection",
	"features": [
		{
			"type": "Feature",
			"properties": {
				"confidence": 9,
				"authenticationResultCode": "ValidCredentials",
				"brandLogoUri": "http://dev.virtualearth.net/Branding/logo_powered_by.png",
				"copyright": "Copyright © 2017 Microsoft and its suppliers. All rights reserved. This API cannot be accessed and the content and any results may not be used, reproduced or transmitted in any manner without express written permission from Microsoft Corporation.",
				"entityType": "RoadBlock",
				"matchCodes": [
					"Good"
				],
				"name": "Wayne Hicks Ln, Saskatoon, SK S7L, Canada",
				"statusCode": 200,
				"statusDescription": "OK",
				"traceId": "1d43247523b64ab48c42820ac4fa4e06|BN20130631|7.7.0.0|",
				"addressLine": "Wayne Hicks Ln",
				"adminDistrict": "SK",
				"adminDistrict2": "Saskatchewan",
				"countryRegion": "Canada",
				"formattedAddress": "Wayne Hicks Ln, Saskatoon, SK S7L, Canada",
				"locality": "Saskatoon",
				"postalCode": "S7L 6S2"
			},
			"geometry": {
				"type": "Point",
				"coordinates": [
					-106.68232,
					52.16849
				]
			},
			"bbox": [
				-106.68691,
				52.1682599,
				-106.68011,
				52.16906
			]
		}
	]
}
