{
	"type": "FeatureCollection",
	"features": [
		{
			"type": "Feature",
			"properties": {
				"confidence": 4,
				"authenticationResultCode": "ValidCredentials",
				"brandLogoUri": "http://dev.virtualearth.net/Branding/logo_powered_by.png",
				"copyright": "Copyright © 2017 Microsoft and its suppliers. All rights reserved. This API cannot be accessed and the content and any results may not be used, reproduced or transmitted in any manner without express written permission from Microsoft Corporation.",
				"entityType": "RoadBlock",
				"matchCodes": [
					"Good"
				],
				"name": "HWY-3, Lower East Pubnico, NS B0W 2A0, Canada",
				"statusCode": 200,
				"statusDescription": "OK",
				"traceId": "3c027e46026b4cbeab3b0d051d18803d|BN20181720|7.7.0.0|",
				"addressLine": "HWY-3",
				"adminDistrict": "NS",
				"adminDistrict2": "Yarmouth",
				"countryRegion": "Canada",
				"formattedAddress": "HWY-3, Lower East Pubnico, NS B0W 2A0, Canada",
				"locality": "Argyle",
				"neighborhood": "Lower East Pubnico",
				"postalCode": "B0W 2A0"
			},
			"geometry": {
				"type": "Point",
				"coordinates": [
					-65.76271,
					43.66113
				]
			},
			"bbox": [
				-65.78093,
				43.59638,
				-65.7603,
				43.70705
			]
		}
	]
}
