{
	"type": "FeatureCollection",
	"features": [
		{
			"type": "Feature",
			"properties": {
				"confidence": 9,
				"authenticationResultCode": "ValidCredentials",
				"brandLogoUri": "http://dev.virtualearth.net/Branding/logo_powered_by.png",
				"copyright": "Copyright © 2017 Microsoft and its suppliers. All rights reserved. This API cannot be accessed and the content and any results may not be used, reproduced or transmitted in any manner without express written permission from Microsoft Corporation.",
				"entityType": "Address",
				"matchCodes": [
					"Good"
				],
				"name": "1350 Regent St, Fredericton, NB E3C 2G6, Canada",
				"statusCode": 200,
				"statusDescription": "OK",
				"traceId": "4f3e7404e8f9431e999f1db8e752baba|BN20260223|7.7.0.0|",
				"addressLine": "1350 Regent St",
				"adminDistrict": "NB",
				"adminDistrict2": "York",
				"countryRegion": "Canada",
				"formattedAddress": "1350 Regent St, Fredericton, NB E3C 2G6, Canada",
				"locality": "Fredericton",
				"postalCode": "E3C 2G6"
			},
			"geometry": {
				"type": "Point",
				"coordinates": [
					-66.66098,
					45.93415
				]
			},
			"bbox": [
				-66.6625964,
				45.9330258,
				-66.6593636,
				45.9352742
			]
		}
	]
}
