{
	"type": "FeatureCollection",
	"features": [
		{
			"type": "Feature",
			"properties": {
				"confidence": 7,
				"authenticationResultCode": "ValidCredentials",
				"brandLogoUri": "http://dev.virtualearth.net/Branding/logo_powered_by.png",
				"copyright": "Copyright © 2017 Microsoft and its suppliers. All rights reserved. This API cannot be accessed and the content and any results may not be used, reproduced or transmitted in any manner without express written permission from Microsoft Corporation.",
				"entityType": "Postcode1",
				"matchCodes": [
					"Ambiguous",
					"UpHierarchy"
				],
				"name": "Earlton, P0J 1E0, Canada",
				"statusCode": 200,
				"statusDescription": "OK",
				"traceId": "417e9df5d47449cb91125a89d25af0ab|BN20181720|7.7.0.0|",
				"adminDistrict": "ON",
				"adminDistrict2": "Timiskaming",
				"countryRegion": "Canada",
				"formattedAddress": "Earlton, P0J 1E0, Canada",
				"locality": "Earlton",
				"postalCode": "P0J 1E0"
			},
			"geometry": {
				"type": "Point",
				"coordinates": [
					-79.824333190918,
					47.7114410400391
				]
			},
			"bbox": [
				-79.8319868954154,
				47.7075783224684,
				-79.8166794864205,
				47.7153037576097
			]
		}
	]
}
