{
	"type": "FeatureCollection",
	"features": [
		{
			"type": "Feature",
			"properties": {
				"confidence": 9,
				"authenticationResultCode": "ValidCredentials",
				"brandLogoUri": "http://dev.virtualearth.net/Branding/logo_powered_by.png",
				"copyright": "Copyright © 2017 Microsoft and its suppliers. All rights reserved. This API cannot be accessed and the content and any results may not be used, reproduced or transmitted in any manner without express written permission from Microsoft Corporation.",
				"entityType": "Address",
				"matchCodes": [
					"Good"
				],
				"name": "155 Glendeer Cir SE, Calgary, AB T2H 2S8, Canada",
				"statusCode": 200,
				"statusDescription": "OK",
				"traceId": "99d69d22b765430890d3afc441b2c22d|BN20130520|7.7.0.0|",
				"addressLine": "155 Glendeer Cir SE",
				"adminDistrict": "AB",
				"adminDistrict2": "Alberta",
				"countryRegion": "Canada",
				"formattedAddress": "155 Glendeer Cir SE, Calgary, AB T2H 2S8, Canada",
				"locality": "Calgary",
				"postalCode": "T2H 2S8"
			},
			"geometry": {
				"type": "Point",
				"coordinates": [
					-114.03349,
					50.9889
				]
			},
			"bbox": [
				-114.0352759,
				50.9877758,
				-114.0317041,
				50.9900242
			]
		}
	]
}
