{
	"type": "FeatureCollection",
	"features": [
		{
			"type": "Feature",
			"properties": {
				"confidence": 7,
				"authenticationResultCode": "ValidCredentials",
				"brandLogoUri": "http://dev.virtualearth.net/Branding/logo_powered_by.png",
				"copyright": "Copyright © 2017 Microsoft and its suppliers. All rights reserved. This API cannot be accessed and the content and any results may not be used, reproduced or transmitted in any manner without express written permission from Microsoft Corporation.",
				"entityType": "Postcode1",
				"matchCodes": [
					"UpHierarchy"
				],
				"name": "Courtice, L1E 1S8, Canada",
				"statusCode": 200,
				"statusDescription": "OK",
				"traceId": "f0498b8852614543ad2af774b0773a9c|BN20130620|7.7.0.0|",
				"adminDistrict": "ON",
				"adminDistrict2": "Durham",
				"countryRegion": "Canada",
				"formattedAddress": "Courtice, L1E 1S8, Canada",
				"locality": "Courtice",
				"postalCode": "L1E 1S8"
			},
			"geometry": {
				"type": "Point",
				"coordinates": [
					-78.7884216308594,
					43.9142456054688
				]
			},
			"bbox": [
				-78.795570587274,
				43.9103828878981,
				-78.7812726744447,
				43.9181083230394
			]
		}
	]
}
