{
	"type": "FeatureCollection",
	"features": [
		{
			"type": "Feature",
			"properties": {
				"confidence": 7,
				"authenticationResultCode": "ValidCredentials",
				"brandLogoUri": "http://dev.virtualearth.net/Branding/logo_powered_by.png",
				"copyright": "Copyright © 2017 Microsoft and its suppliers. All rights reserved. This API cannot be accessed and the content and any results may not be used, reproduced or transmitted in any manner without express written permission from Microsoft Corporation.",
				"entityType": "Postcode1",
				"matchCodes": [
					"UpHierarchy"
				],
				"name": "Abbotsford, V3G 0C6, Canada",
				"statusCode": 200,
				"statusDescription": "OK",
				"traceId": "987e696ce37f4187bd7414a9eac6845f|BN20160335|7.7.0.0|",
				"adminDistrict": "BC",
				"adminDistrict2": "Fraser Valley",
				"countryRegion": "Canada",
				"formattedAddress": "Abbotsford, V3G 0C6, Canada",
				"locality": "Abbotsford",
				"postalCode": "V3G 0C6"
			},
			"geometry": {
				"type": "Point",
				"coordinates": [
					-122.329299926758,
					49.0516204833984
				]
			},
			"bbox": [
				-122.337157809743,
				49.0477577658278,
				-122.321442043773,
				49.0554832009691
			]
		}
	]
}
