{
	"type": "FeatureCollection",
	"features": [
		{
			"type": "Feature",
			"properties": {
				"confidence": 7,
				"authenticationResultCode": "ValidCredentials",
				"brandLogoUri": "http://dev.virtualearth.net/Branding/logo_powered_by.png",
				"copyright": "Copyright © 2017 Microsoft and its suppliers. All rights reserved. This API cannot be accessed and the content and any results may not be used, reproduced or transmitted in any manner without express written permission from Microsoft Corporation.",
				"entityType": "Postcode1",
				"matchCodes": [
					"UpHierarchy"
				],
				"name": "Placentia, A0B 2Y0, Canada",
				"statusCode": 200,
				"statusDescription": "OK",
				"traceId": "cd9e17946a5b4de3a6410f85501af93a|BN20260231|7.7.0.0|",
				"adminDistrict": "NL",
				"countryRegion": "Canada",
				"formattedAddress": "Placentia, A0B 2Y0, Canada",
				"locality": "Placentia",
				"postalCode": "A0B 2Y0"
			},
			"geometry": {
				"type": "Point",
				"coordinates": [
					-53.9518508911133,
					47.2186431884766
				]
			},
			"bbox": [
				-53.9594331876442,
				47.2147804709059,
				-53.9442685945823,
				47.2225059060472
			]
		}
	]
}
