{
	"type": "FeatureCollection",
	"features": [
		{
			"type": "Feature",
			"properties": {
				"confidence": 7,
				"authenticationResultCode": "ValidCredentials",
				"brandLogoUri": "http://dev.virtualearth.net/Branding/logo_powered_by.png",
				"copyright": "Copyright © 2017 Microsoft and its suppliers. All rights reserved. This API cannot be accessed and the content and any results may not be used, reproduced or transmitted in any manner without express written permission from Microsoft Corporation.",
				"entityType": "Postcode1",
				"matchCodes": [
					"Ambiguous",
					"UpHierarchy"
				],
				"name": "Hamilton, L9B 0E4, Canada",
				"statusCode": 200,
				"statusDescription": "OK",
				"traceId": "e8f926457d4f4700aa67e308e4f37b27|BN20210145|7.7.0.0|",
				"adminDistrict": "ON",
				"adminDistrict2": "Hamilton",
				"countryRegion": "Canada",
				"formattedAddress": "Hamilton, L9B 0E4, Canada",
				"locality": "Hamilton",
				"postalCode": "L9B 0E4"
			},
			"geometry": {
				"type": "Point",
				"coordinates": [
					-79.8879928588867,
					43.2619781494141
				]
			},
			"bbox": [
				-79.8950647723722,
				43.2581154318434,
				-79.8809209454012,
				43.2658408669847
			]
		}
	]
}
