{
	"type": "FeatureCollection",
	"features": [
		{
			"type": "Feature",
			"properties": {
				"confidence": 7,
				"authenticationResultCode": "ValidCredentials",
				"brandLogoUri": "http://dev.virtualearth.net/Branding/logo_powered_by.png",
				"copyright": "Copyright © 2017 Microsoft and its suppliers. All rights reserved. This API cannot be accessed and the content and any results may not be used, reproduced or transmitted in any manner without express written permission from Microsoft Corporation.",
				"entityType": "Postcode1",
				"matchCodes": [
					"UpHierarchy"
				],
				"name": "Regina, S4N 7L2, Canada",
				"statusCode": 200,
				"statusDescription": "OK",
				"traceId": "e78c200aaa0f4e048704e9a10457b51b|BN20250135|7.7.0.0|",
				"adminDistrict": "SK",
				"countryRegion": "Canada",
				"formattedAddress": "Regina, S4N 7L2, Canada",
				"locality": "Regina",
				"postalCode": "S4N 7L2"
			},
			"geometry": {
				"type": "Point",
				"coordinates": [
					-104.595169067383,
					50.4482498168945
				]
			},
			"bbox": [
				-104.603256493118,
				50.4443870993239,
				-104.587081641647,
				50.4521125344652
			]
		}
	]
}
