{
	"type": "FeatureCollection",
	"features": [
		{
			"type": "Feature",
			"properties": {
				"confidence": 7,
				"authenticationResultCode": "ValidCredentials",
				"brandLogoUri": "http://dev.virtualearth.net/Branding/logo_powered_by.png",
				"copyright": "Copyright © 2017 Microsoft and its suppliers. All rights reserved. This API cannot be accessed and the content and any results may not be used, reproduced or transmitted in any manner without express written permission from Microsoft Corporation.",
				"entityType": "Postcode1",
				"matchCodes": [
					"UpHierarchy"
				],
				"name": "Fredericton, E3B 5B4, Canada",
				"statusCode": 200,
				"statusDescription": "OK",
				"traceId": "17137719e4ec4af28a9be4a3eaf702f8|BN20130423|7.7.0.0|",
				"adminDistrict": "NB",
				"adminDistrict2": "York",
				"countryRegion": "Canada",
				"formattedAddress": "Fredericton, E3B 5B4, Canada",
				"locality": "Fredericton",
				"postalCode": "E3B 5B4"
			},
			"geometry": {
				"type": "Point",
				"coordinates": [
					-66.6391067504883,
					45.9606285095215
				]
			},
			"bbox": [
				-66.6465150975929,
				45.9567657919508,
				-66.6316984033837,
				45.9644912270922
			]
		}
	]
}
