{
	"type": "FeatureCollection",
	"features": [
		{
			"type": "Feature",
			"properties": {
				"confidence": 7,
				"authenticationResultCode": "ValidCredentials",
				"brandLogoUri": "http://dev.virtualearth.net/Branding/logo_powered_by.png",
				"copyright": "Copyright © 2017 Microsoft and its suppliers. All rights reserved. This API cannot be accessed and the content and any results may not be used, reproduced or transmitted in any manner without express written permission from Microsoft Corporation.",
				"entityType": "Postcode1",
				"matchCodes": [
					"UpHierarchy"
				],
				"name": "Déline, X0E 0G0, Canada",
				"statusCode": 200,
				"statusDescription": "OK",
				"traceId": "da89bc956cd2467baf3ca422e55ddfe4|BN20160335|7.7.0.0|",
				"adminDistrict": "NT",
				"countryRegion": "Canada",
				"formattedAddress": "Déline, X0E 0G0, Canada",
				"locality": "Déline",
				"postalCode": "X0E 0G0"
			},
			"geometry": {
				"type": "Point",
				"coordinates": [
					-123.432220458984,
					65.211669921875
				]
			},
			"bbox": [
				-123.444502694894,
				65.2078072043043,
				-123.419938223075,
				65.2155326394457
			]
		}
	]
}
