{
	"type": "FeatureCollection",
	"features": [
		{
			"type": "Feature",
			"properties": {
				"confidence": 7,
				"authenticationResultCode": "ValidCredentials",
				"brandLogoUri": "http://dev.virtualearth.net/Branding/logo_powered_by.png",
				"copyright": "Copyright © 2017 Microsoft and its suppliers. All rights reserved. This API cannot be accessed and the content and any results may not be used, reproduced or transmitted in any manner without express written permission from Microsoft Corporation.",
				"entityType": "Postcode1",
				"matchCodes": [
					"UpHierarchy"
				],
				"name": "Whitecourt, T7S 1N3, Canada",
				"statusCode": 200,
				"statusDescription": "OK",
				"traceId": "06a6ce5e70c641f78881ee8547dbc7db|BN20130533|7.7.0.0|",
				"adminDistrict": "AB",
				"countryRegion": "Canada",
				"formattedAddress": "Whitecourt, T7S 1N3, Canada",
				"locality": "Whitecourt",
				"postalCode": "T7S 1N3"
			},
			"geometry": {
				"type": "Point",
				"coordinates": [
					-115.660972595215,
					54.1247215270996
				]
			},
			"bbox": [
				-115.669760325215,
				54.1208588095289,
				-115.652184865215,
				54.1285842446703
			]
		}
	]
}
