{
	"type": "FeatureCollection",
	"features": [
		{
			"type": "Feature",
			"properties": {
				"confidence": 5,
				"authenticationResultCode": "ValidCredentials",
				"brandLogoUri": "http://dev.virtualearth.net/Branding/logo_powered_by.png",
				"copyright": "Copyright © 2017 Microsoft and its suppliers. All rights reserved. This API cannot be accessed and the content and any results may not be used, reproduced or transmitted in any manner without express written permission from Microsoft Corporation.",
				"entityType": "Postcode2",
				"matchCodes": [
					"UpHierarchy"
				],
				"name": "Victoria, V8X, Canada",
				"statusCode": 200,
				"statusDescription": "OK",
				"traceId": "0d01111183ad4ec6b6146d80af7e9ac7|BN20130442|7.7.0.0|",
				"adminDistrict": "BC",
				"adminDistrict2": "Capital",
				"countryRegion": "Canada",
				"formattedAddress": "Victoria, V8X, Canada",
				"locality": "Victoria",
				"postalCode": "V8X"
			},
			"geometry": {
				"type": "Point",
				"coordinates": [
					-123.364822387695,
					48.4735298156738
				]
			},
			"bbox": [
				-123.398818969727,
				48.4395294189453,
				-123.33081817627,
				48.5075302124023
			]
		},
		{
			"type": "Feature",
			"properties": {
				"confidence": 7,
				"authenticationResultCode": "ValidCredentials",
				"brandLogoUri": "http://dev.virtualearth.net/Branding/logo_powered_by.png",
				"copyright": "Copyright © 2017 Microsoft and its suppliers. All rights reserved. This API cannot be accessed and the content and any results may not be used, reproduced or transmitted in any manner without express written permission from Microsoft Corporation.",
				"entityType": "Postcode1",
				"matchCodes": [
					"UpHierarchy"
				],
				"name": "Oak Bay, V8X 5E1, Canada",
				"statusCode": 200,
				"statusDescription": "OK",
				"traceId": "0d01111183ad4ec6b6146d80af7e9ac7|BN20130442|7.7.0.0|",
				"adminDistrict": "BC",
				"adminDistrict2": "Capital",
				"countryRegion": "Canada",
				"formattedAddress": "Oak Bay, V8X 5E1, Canada",
				"locality": "Oak Bay",
				"postalCode": "V8X 5E1"
			},
			"geometry": {
				"type": "Point",
				"coordinates": [
					-123.317657470703,
					48.4265289306641
				]
			},
			"bbox": [
				-123.325418252361,
				48.4226662130934,
				-123.309896689045,
				48.4303916482347
			]
		},
		{
			"type": "Feature",
			"properties": {
				"confidence": 2,
				"authenticationResultCode": "ValidCredentials",
				"brandLogoUri": "http://dev.virtualearth.net/Branding/logo_powered_by.png",
				"copyright": "Copyright © 2017 Microsoft and its suppliers. All rights reserved. This API cannot be accessed and the content and any results may not be used, reproduced or transmitted in any manner without express written permission from Microsoft Corporation.",
				"entityType": "PopulatedPlace",
				"matchCodes": [
					"UpHierarchy"
				],
				"name": "Saanich, British Columbia, Canada",
				"statusCode": 200,
				"statusDescription": "OK",
				"traceId": "0d01111183ad4ec6b6146d80af7e9ac7|BN20130442|7.7.0.0|",
				"adminDistrict": "BC",
				"adminDistrict2": "Capital",
				"countryRegion": "Canada",
				"formattedAddress": "Saanich, British Columbia, Canada",
				"locality": "Saanich"
			},
			"geometry": {
				"type": "Point",
				"coordinates": [
					-123.37671661377,
					48.4589500427246
				]
			},
			"bbox": [
				-123.477523803711,
				48.4336395263672,
				-123.264236450195,
				48.5579299926758
			]
		},
		{
			"type": "Feature",
			"properties": {
				"confidence": 6,
				"authenticationResultCode": "ValidCredentials",
				"brandLogoUri": "http://dev.virtualearth.net/Branding/logo_powered_by.png",
				"copyright": "Copyright © 2017 Microsoft and its suppliers. All rights reserved. This API cannot be accessed and the content and any results may not be used, reproduced or transmitted in any manner without express written permission from Microsoft Corporation.",
				"entityType": "Postcode1",
				"matchCodes": [
					"UpHierarchy"
				],
				"name": "Clarkston, GA 30021",
				"statusCode": 200,
				"statusDescription": "OK",
				"traceId": "0d01111183ad4ec6b6146d80af7e9ac7|BN20130442|7.7.0.0|",
				"adminDistrict": "GA",
				"adminDistrict2": "DeKalb",
				"countryRegion": "United States",
				"formattedAddress": "Clarkston, GA 30021",
				"locality": "Clarkston",
				"postalCode": "30021"
			},
			"geometry": {
				"type": "Point",
				"coordinates": [
					-84.2371292114258,
					33.8173789978027
				]
			},
			"bbox": [
				-84.2599258422852,
				33.7856903076172,
				-84.2176132202148,
				33.8279495239258
			]
		}
	]
}
