{
	"type": "FeatureCollection",
	"features": [
		{
			"type": "Feature",
			"properties": {
				"confidence": 7,
				"authenticationResultCode": "ValidCredentials",
				"brandLogoUri": "http://dev.virtualearth.net/Branding/logo_powered_by.png",
				"copyright": "Copyright © 2017 Microsoft and its suppliers. All rights reserved. This API cannot be accessed and the content and any results may not be used, reproduced or transmitted in any manner without express written permission from Microsoft Corporation.",
				"entityType": "Postcode1",
				"matchCodes": [
					"UpHierarchy"
				],
				"name": "Vegreville, T9C 1T4, Canada",
				"statusCode": 200,
				"statusDescription": "OK",
				"traceId": "0657961d5d894b10aa8e03784751b21c|BN20130442|7.7.0.0|",
				"adminDistrict": "AB",
				"countryRegion": "Canada",
				"formattedAddress": "Vegreville, T9C 1T4, Canada",
				"locality": "Vegreville",
				"postalCode": "T9C 1T4"
			},
			"geometry": {
				"type": "Point",
				"coordinates": [
					-112.054153442383,
					53.495288848877
				]
			},
			"bbox": [
				-112.062810220419,
				53.4914261313063,
				-112.045496664347,
				53.4991515664476
			]
		}
	]
}
