{
	"type": "FeatureCollection",
	"features": [
		{
			"type": "Feature",
			"properties": {
				"confidence": 7,
				"authenticationResultCode": "ValidCredentials",
				"brandLogoUri": "http://dev.virtualearth.net/Branding/logo_powered_by.png",
				"copyright": "Copyright © 2017 Microsoft and its suppliers. All rights reserved. This API cannot be accessed and the content and any results may not be used, reproduced or transmitted in any manner without express written permission from Microsoft Corporation.",
				"entityType": "Postcode1",
				"matchCodes": [
					"Ambiguous",
					"UpHierarchy"
				],
				"name": "Sudbury, P3A 4S1, Canada",
				"statusCode": 200,
				"statusDescription": "OK",
				"traceId": "cb3bf273aadd4d88891f3e780c517e18|BN20280152|7.7.0.0|",
				"adminDistrict": "ON",
				"adminDistrict2": "Greater Sudbury",
				"countryRegion": "Canada",
				"formattedAddress": "Sudbury, P3A 4S1, Canada",
				"locality": "Sudbury",
				"postalCode": "P3A 4S1"
			},
			"geometry": {
				"type": "Point",
				"coordinates": [
					-80.9901123046875,
					46.4895896911621
				]
			},
			"bbox": [
				-80.997592372092,
				46.4857269735914,
				-80.982632237283,
				46.4934524087328
			]
		}
	]
}
