{
	"type": "FeatureCollection",
	"features": [
		{
			"type": "Feature",
			"properties": {
				"confidence": 7,
				"authenticationResultCode": "ValidCredentials",
				"brandLogoUri": "http://dev.virtualearth.net/Branding/logo_powered_by.png",
				"copyright": "Copyright © 2017 Microsoft and its suppliers. All rights reserved. This API cannot be accessed and the content and any results may not be used, reproduced or transmitted in any manner without express written permission from Microsoft Corporation.",
				"entityType": "Postcode1",
				"matchCodes": [
					"UpHierarchy"
				],
				"name": "Port Hardy, V0N 2P0, Canada",
				"statusCode": 200,
				"statusDescription": "OK",
				"traceId": "1ed1cabf60ec4955926280f5c42be01e|BN20130532|7.7.0.0|",
				"adminDistrict": "BC",
				"adminDistrict2": "Mt Waddington",
				"countryRegion": "Canada",
				"formattedAddress": "Port Hardy, V0N 2P0, Canada",
				"locality": "Port Hardy",
				"postalCode": "V0N 2P0"
			},
			"geometry": {
				"type": "Point",
				"coordinates": [
					-127.495491027832,
					50.7241897583008
				]
			},
			"bbox": [
				-127.503625981081,
				50.7203270407301,
				-127.487356074583,
				50.7280524758715
			]
		}
	]
}
