{
	"type": "FeatureCollection",
	"features": [
		{
			"type": "Feature",
			"properties": {
				"confidence": 9,
				"authenticationResultCode": "ValidCredentials",
				"brandLogoUri": "http://dev.virtualearth.net/Branding/logo_powered_by.png",
				"copyright": "Copyright © 2017 Microsoft and its suppliers. All rights reserved. This API cannot be accessed and the content and any results may not be used, reproduced or transmitted in any manner without express written permission from Microsoft Corporation.",
				"entityType": "Address",
				"matchCodes": [
					"Good"
				],
				"name": "27 Larry Uteck Blvd, Halifax, NS B3M, Canada",
				"statusCode": 200,
				"statusDescription": "OK",
				"traceId": "5abe2445a39442be85606e953704f619|BN20320521|7.7.0.0|",
				"addressLine": "27 Larry Uteck Blvd",
				"adminDistrict": "NS",
				"adminDistrict2": "Halifax",
				"countryRegion": "Canada",
				"formattedAddress": "27 Larry Uteck Blvd, Halifax, NS B3M, Canada",
				"locality": "Halifax",
				"neighborhood": "Rockingham",
				"postalCode": "B3M 0G3"
			},
			"geometry": {
				"type": "Point",
				"coordinates": [
					-63.6624807,
					44.6994446
				]
			},
			"bbox": [
				-63.6640622,
				44.6983205,
				-63.6608992,
				44.7005688
			]
		}
	]
}
