{
	"type": "FeatureCollection",
	"features": [
		{
			"type": "Feature",
			"properties": {
				"confidence": 7,
				"authenticationResultCode": "ValidCredentials",
				"brandLogoUri": "http://dev.virtualearth.net/Branding/logo_powered_by.png",
				"copyright": "Copyright © 2017 Microsoft and its suppliers. All rights reserved. This API cannot be accessed and the content and any results may not be used, reproduced or transmitted in any manner without express written permission from Microsoft Corporation.",
				"entityType": "Postcode1",
				"matchCodes": [
					"UpHierarchy"
				],
				"name": "Ottawa, K0A 3M0, Canada",
				"statusCode": 200,
				"statusDescription": "OK",
				"traceId": "2d1c27873f0f4531a374d40abde7e205|BN20130634|7.7.0.0|",
				"adminDistrict": "ON",
				"adminDistrict2": "Ottawa",
				"countryRegion": "Canada",
				"formattedAddress": "Ottawa, K0A 3M0, Canada",
				"locality": "Ottawa",
				"postalCode": "K0A 3M0"
			},
			"geometry": {
				"type": "Point",
				"coordinates": [
					-76.10107421875,
					45.4418640136719
				]
			},
			"bbox": [
				-76.1084141533945,
				45.4380012961012,
				-76.0937342841055,
				45.4457267312426
			]
		},
		{
			"type": "Feature",
			"properties": {
				"confidence": 7,
				"authenticationResultCode": "ValidCredentials",
				"brandLogoUri": "http://dev.virtualearth.net/Branding/logo_powered_by.png",
				"copyright": "Copyright © 2017 Microsoft and its suppliers. All rights reserved. This API cannot be accessed and the content and any results may not be used, reproduced or transmitted in any manner without express written permission from Microsoft Corporation.",
				"entityType": "Neighborhood",
				"matchCodes": [
					"Ambiguous",
					"UpHierarchy"
				],
				"name": "Woodlawn, Ottawa, Ontario, Canada",
				"statusCode": 200,
				"statusDescription": "OK",
				"traceId": "2d1c27873f0f4531a374d40abde7e205|BN20130634|7.7.0.0|",
				"adminDistrict": "ON",
				"adminDistrict2": "Ottawa",
				"countryRegion": "Canada",
				"formattedAddress": "Woodlawn, Ottawa, Ontario, Canada",
				"locality": "Ottawa",
				"neighborhood": "Woodlawn"
			},
			"geometry": {
				"type": "Point",
				"coordinates": [
					-76.0752563476563,
					45.4623794555664
				]
			},
			"bbox": [
				-76.0825989523864,
				45.4585167379957,
				-76.0679137429261,
				45.4662421731371
			]
		},
		{
			"type": "Feature",
			"properties": {
				"confidence": 6,
				"authenticationResultCode": "ValidCredentials",
				"brandLogoUri": "http://dev.virtualearth.net/Branding/logo_powered_by.png",
				"copyright": "Copyright © 2017 Microsoft and its suppliers. All rights reserved. This API cannot be accessed and the content and any results may not be used, reproduced or transmitted in any manner without express written permission from Microsoft Corporation.",
				"entityType": "PopulatedPlace",
				"matchCodes": [
					"Ambiguous",
					"UpHierarchy"
				],
				"name": "Woodlawn, Ontario, Canada",
				"statusCode": 200,
				"statusDescription": "OK",
				"traceId": "2d1c27873f0f4531a374d40abde7e205|BN20130634|7.7.0.0|",
				"adminDistrict": "ON",
				"adminDistrict2": "Ottawa",
				"countryRegion": "Canada",
				"formattedAddress": "Woodlawn, Ontario, Canada",
				"locality": "Woodlawn"
			},
			"geometry": {
				"type": "Point",
				"coordinates": [
					-76.0880661010742,
					45.4953765869141
				]
			},
			"bbox": [
				-76.1139831542969,
				45.474609375,
				-76.0661697387695,
				45.5112991333008
			]
		},
		{
			"type": "Feature",
			"properties": {
				"confidence": 1,
				"authenticationResultCode": "ValidCredentials",
				"brandLogoUri": "http://dev.virtualearth.net/Branding/logo_powered_by.png",
				"copyright": "Copyright © 2017 Microsoft and its suppliers. All rights reserved. This API cannot be accessed and the content and any results may not be used, reproduced or transmitted in any manner without express written permission from Microsoft Corporation.",
				"entityType": "AdminDivision1",
				"matchCodes": [
					"UpHierarchy"
				],
				"name": "Roraima, Brazil",
				"statusCode": 200,
				"statusDescription": "OK",
				"traceId": "2d1c27873f0f4531a374d40abde7e205|BN20130634|7.7.0.0|",
				"adminDistrict": "RR",
				"countryRegion": "Brazil",
				"formattedAddress": "Roraima, Brazil"
			},
			"geometry": {
				"type": "Point",
				"coordinates": [
					-60.6574211120605,
					2.82424998283386
				]
			},
			"bbox": [
				-64.8135986328125,
				-1.5964070558548,
				-58.8705787658691,
				5.26487684249878
			]
		}
	]
}
