{
	"type": "FeatureCollection",
	"features": [
		{
			"type": "Feature",
			"properties": {
				"confidence": 7,
				"authenticationResultCode": "ValidCredentials",
				"brandLogoUri": "http://dev.virtualearth.net/Branding/logo_powered_by.png",
				"copyright": "Copyright © 2017 Microsoft and its suppliers. All rights reserved. This API cannot be accessed and the content and any results may not be used, reproduced or transmitted in any manner without express written permission from Microsoft Corporation.",
				"entityType": "PopulatedPlace",
				"matchCodes": [
					"UpHierarchy"
				],
				"name": "Cobden, Ontario, Canada",
				"statusCode": 200,
				"statusDescription": "OK",
				"traceId": "3e42bc8076264797a19bfc773985f76f|BN20121763|7.7.0.0|",
				"adminDistrict": "ON",
				"adminDistrict2": "Renfrew",
				"countryRegion": "Canada",
				"formattedAddress": "Cobden, Ontario, Canada",
				"locality": "Cobden"
			},
			"geometry": {
				"type": "Point",
				"coordinates": [
					-76.879997253418,
					45.6270484924316
				]
			},
			"bbox": [
				-76.8852767944336,
				45.6223907470703,
				-76.875846862793,
				45.6296005249023
			]
		},
		{
			"type": "Feature",
			"properties": {
				"confidence": 7,
				"authenticationResultCode": "ValidCredentials",
				"brandLogoUri": "http://dev.virtualearth.net/Branding/logo_powered_by.png",
				"copyright": "Copyright © 2017 Microsoft and its suppliers. All rights reserved. This API cannot be accessed and the content and any results may not be used, reproduced or transmitted in any manner without express written permission from Microsoft Corporation.",
				"entityType": "Postcode1",
				"matchCodes": [
					"UpHierarchy"
				],
				"name": "Whitewater Region, K0J 1K0, Canada",
				"statusCode": 200,
				"statusDescription": "OK",
				"traceId": "3e42bc8076264797a19bfc773985f76f|BN20121763|7.7.0.0|",
				"adminDistrict": "ON",
				"adminDistrict2": "Renfrew",
				"countryRegion": "Canada",
				"formattedAddress": "Whitewater Region, K0J 1K0, Canada",
				"locality": "Whitewater Region",
				"postalCode": "K0J 1K0"
			},
			"geometry": {
				"type": "Point",
				"coordinates": [
					-76.8424606323242,
					45.600399017334
				]
			},
			"bbox": [
				-76.8498212755005,
				45.5965362997633,
				-76.835099989148,
				45.6042617349047
			]
		}
	]
}
