{
	"type": "FeatureCollection",
	"features": [
		{
			"type": "Feature",
			"properties": {
				"confidence": 7,
				"authenticationResultCode": "ValidCredentials",
				"brandLogoUri": "http://dev.virtualearth.net/Branding/logo_powered_by.png",
				"copyright": "Copyright © 2017 Microsoft and its suppliers. All rights reserved. This API cannot be accessed and the content and any results may not be used, reproduced or transmitted in any manner without express written permission from Microsoft Corporation.",
				"entityType": "Postcode1",
				"matchCodes": [
					"UpHierarchy"
				],
				"name": "Kelowna, V1W 5E2, Canada",
				"statusCode": 200,
				"statusDescription": "OK",
				"traceId": "9bcc09a293214de39effb8d3943f8129|BN20130721|7.7.0.0|",
				"adminDistrict": "BC",
				"adminDistrict2": "Central Okanagan",
				"countryRegion": "Canada",
				"formattedAddress": "Kelowna, V1W 5E2, Canada",
				"locality": "Kelowna",
				"postalCode": "V1W 5E2"
			},
			"geometry": {
				"type": "Point",
				"coordinates": [
					-119.48607635498,
					49.8084182739258
				]
			},
			"bbox": [
				-119.494056389677,
				49.8045555563551,
				-119.478096320284,
				49.8122809914965
			]
		}
	]
}
