{
	"type": "FeatureCollection",
	"features": [
		{
			"type": "Feature",
			"properties": {
				"confidence": 9,
				"authenticationResultCode": "ValidCredentials",
				"brandLogoUri": "http://dev.virtualearth.net/Branding/logo_powered_by.png",
				"copyright": "Copyright © 2017 Microsoft and its suppliers. All rights reserved. This API cannot be accessed and the content and any results may not be used, reproduced or transmitted in any manner without express written permission from Microsoft Corporation.",
				"entityType": "Address",
				"matchCodes": [
					"Good"
				],
				"name": "1 James St N, Hamilton, ON L8R 2K3, Canada",
				"statusCode": 200,
				"statusDescription": "OK",
				"traceId": "c5059cb8c1654a11b13da9445ab48b72|BN20130631|7.7.0.0|",
				"addressLine": "1 James St N",
				"adminDistrict": "ON",
				"adminDistrict2": "Hamilton",
				"countryRegion": "Canada",
				"formattedAddress": "1 James St N, Hamilton, ON L8R 2K3, Canada",
				"locality": "Hamilton",
				"neighborhood": "Central Hamilton",
				"postalCode": "L8R 2K3"
			},
			"geometry": {
				"type": "Point",
				"coordinates": [
					-79.8692023,
					43.256895
				]
			},
			"bbox": [
				-79.8707459,
				43.2557709,
				-79.8676588,
				43.2580192
			]
		}
	]
}
