{
	"type": "FeatureCollection",
	"features": [
		{
			"type": "Feature",
			"properties": {
				"confidence": 9,
				"authenticationResultCode": "ValidCredentials",
				"brandLogoUri": "http://dev.virtualearth.net/Branding/logo_powered_by.png",
				"copyright": "Copyright © 2017 Microsoft and its suppliers. All rights reserved. This API cannot be accessed and the content and any results may not be used, reproduced or transmitted in any manner without express written permission from Microsoft Corporation.",
				"entityType": "Address",
				"matchCodes": [
					"Good"
				],
				"name": "1 Jones St, Baddeck, NS B0E, Canada",
				"statusCode": 200,
				"statusDescription": "OK",
				"traceId": "52eb2f2c8b334a57888e7746f17ca220|BN20200137|7.7.0.0|",
				"addressLine": "1 Jones St",
				"adminDistrict": "NS",
				"adminDistrict2": "Victoria",
				"countryRegion": "Canada",
				"formattedAddress": "1 Jones St, Baddeck, NS B0E, Canada",
				"locality": "Baddeck",
				"postalCode": "B0E 1B0"
			},
			"geometry": {
				"type": "Point",
				"coordinates": [
					-60.7483743,
					46.1006424
				]
			},
			"bbox": [
				-60.7499955,
				46.0995183,
				-60.746753,
				46.1017666
			]
		}
	]
}
