{
	"type": "FeatureCollection",
	"features": [
		{
			"type": "Feature",
			"properties": {
				"confidence": 9,
				"authenticationResultCode": "ValidCredentials",
				"brandLogoUri": "http://dev.virtualearth.net/Branding/logo_powered_by.png",
				"copyright": "Copyright © 2017 Microsoft and its suppliers. All rights reserved. This API cannot be accessed and the content and any results may not be used, reproduced or transmitted in any manner without express written permission from Microsoft Corporation.",
				"entityType": "Address",
				"matchCodes": [
					"Good"
				],
				"name": "1 Market Pl, Stratford, ON N5A 1A4, Canada",
				"statusCode": 200,
				"statusDescription": "OK",
				"traceId": "3f4510ad889c4da698492a99ba362a30|BN20130423|7.7.0.0|",
				"addressLine": "1 Market Pl",
				"adminDistrict": "ON",
				"adminDistrict2": "Perth",
				"countryRegion": "Canada",
				"formattedAddress": "1 Market Pl, Stratford, ON N5A 1A4, Canada",
				"locality": "Stratford",
				"postalCode": "N5A 1A4"
			},
			"geometry": {
				"type": "Point",
				"coordinates": [
					-80.9817576,
					43.3693952
				]
			},
			"bbox": [
				-80.9833041,
				43.3682711,
				-80.9802112,
				43.3705194
			]
		}
	]
}
