{
	"type": "FeatureCollection",
	"features": [
		{
			"type": "Feature",
			"properties": {
				"confidence": 9,
				"authenticationResultCode": "ValidCredentials",
				"brandLogoUri": "http://dev.virtualearth.net/Branding/logo_powered_by.png",
				"copyright": "Copyright © 2017 Microsoft and its suppliers. All rights reserved. This API cannot be accessed and the content and any results may not be used, reproduced or transmitted in any manner without express written permission from Microsoft Corporation.",
				"entityType": "Address",
				"matchCodes": [
					"Good"
				],
				"name": "1 Parkview Dr, Strathroy, ON N7G 4A1, Canada",
				"statusCode": 200,
				"statusDescription": "OK",
				"traceId": "c4cf96d928044096b2dfe136061c3016|BN20190653|7.7.0.0|",
				"addressLine": "1 Parkview Dr",
				"adminDistrict": "ON",
				"adminDistrict2": "Middlesex",
				"countryRegion": "Canada",
				"formattedAddress": "1 Parkview Dr, Strathroy, ON N7G 4A1, Canada",
				"locality": "Strathroy-Caradoc",
				"neighborhood": "Strathroy",
				"postalCode": "N7G 4A1"
			},
			"geometry": {
				"type": "Point",
				"coordinates": [
					-81.6063999,
					42.96354
				]
			},
			"bbox": [
				-81.6079361,
				42.9624158,
				-81.6048637,
				42.9646642
			]
		}
	]
}
