{
	"type": "FeatureCollection",
	"features": [
		{
			"type": "Feature",
			"properties": {
				"confidence": 9,
				"authenticationResultCode": "ValidCredentials",
				"brandLogoUri": "http://dev.virtualearth.net/Branding/logo_powered_by.png",
				"copyright": "Copyright © 2017 Microsoft and its suppliers. All rights reserved. This API cannot be accessed and the content and any results may not be used, reproduced or transmitted in any manner without express written permission from Microsoft Corporation.",
				"entityType": "Address",
				"matchCodes": [
					"Good"
				],
				"name": "1 Retriever Ln, Centre Hastings, ON K0K, Canada",
				"statusCode": 200,
				"statusDescription": "OK",
				"traceId": "b68f0dceca5b45de8ad1fce71260786e|BN20181720|7.7.0.0|",
				"addressLine": "1 Retriever Ln",
				"adminDistrict": "ON",
				"adminDistrict2": "Hastings",
				"countryRegion": "Canada",
				"formattedAddress": "1 Retriever Ln, Centre Hastings, ON K0K, Canada",
				"locality": "Centre Hastings",
				"postalCode": "K0K 2K0"
			},
			"geometry": {
				"type": "Point",
				"coordinates": [
					-77.4218305,
					44.4873321
				]
			},
			"bbox": [
				-77.4234063,
				44.4862079,
				-77.4202548,
				44.4884562
			]
		}
	]
}
