{
	"type": "FeatureCollection",
	"features": [
		{
			"type": "Feature",
			"properties": {
				"confidence": 9,
				"authenticationResultCode": "ValidCredentials",
				"brandLogoUri": "http://dev.virtualearth.net/Branding/logo_powered_by.png",
				"copyright": "Copyright © 2017 Microsoft and its suppliers. All rights reserved. This API cannot be accessed and the content and any results may not be used, reproduced or transmitted in any manner without express written permission from Microsoft Corporation.",
				"entityType": "Address",
				"matchCodes": [
					"Good"
				],
				"name": "1 Shaw St, Toronto, ON M6K 0A1, Canada",
				"statusCode": 200,
				"statusDescription": "OK",
				"traceId": "833351f5edfd4cbdb65adb6fa1053b05|BN20260223|7.7.0.0|",
				"addressLine": "1 Shaw St",
				"adminDistrict": "ON",
				"adminDistrict2": "Toronto",
				"countryRegion": "Canada",
				"formattedAddress": "1 Shaw St, Toronto, ON M6K 0A1, Canada",
				"locality": "Toronto",
				"neighborhood": "Niagara",
				"postalCode": "M6K 0A1"
			},
			"geometry": {
				"type": "Point",
				"coordinates": [
					-79.41428,
					43.64098
				]
			},
			"bbox": [
				-79.4158334,
				43.6398558,
				-79.4127266,
				43.6421042
			]
		}
	]
}
