{
	"type": "FeatureCollection",
	"features": [
		{
			"type": "Feature",
			"properties": {
				"confidence": 9,
				"authenticationResultCode": "ValidCredentials",
				"brandLogoUri": "http://dev.virtualearth.net/Branding/logo_powered_by.png",
				"copyright": "Copyright © 2017 Microsoft and its suppliers. All rights reserved. This API cannot be accessed and the content and any results may not be used, reproduced or transmitted in any manner without express written permission from Microsoft Corporation.",
				"entityType": "Address",
				"matchCodes": [
					"Good"
				],
				"name": "10 Baird Ave, Kitchener, ON N2B 2N4, Canada",
				"statusCode": 200,
				"statusDescription": "OK",
				"traceId": "cbe2e15a0e8f482f939f9bd4f96db9dc|BN20171457|7.7.0.0|",
				"addressLine": "10 Baird Ave",
				"adminDistrict": "ON",
				"adminDistrict2": "Waterloo",
				"countryRegion": "Canada",
				"formattedAddress": "10 Baird Ave, Kitchener, ON N2B 2N4, Canada",
				"locality": "Kitchener",
				"neighborhood": "Heritage Park",
				"postalCode": "N2B 2N4"
			},
			"geometry": {
				"type": "Point",
				"coordinates": [
					-80.44749,
					43.45772
				]
			},
			"bbox": [
				-80.4490387,
				43.4565958,
				-80.4459413,
				43.4588442
			]
		}
	]
}
