{
	"type": "FeatureCollection",
	"features": [
		{
			"type": "Feature",
			"properties": {
				"confidence": 9,
				"authenticationResultCode": "ValidCredentials",
				"brandLogoUri": "http://dev.virtualearth.net/Branding/logo_powered_by.png",
				"copyright": "Copyright © 2017 Microsoft and its suppliers. All rights reserved. This API cannot be accessed and the content and any results may not be used, reproduced or transmitted in any manner without express written permission from Microsoft Corporation.",
				"entityType": "Address",
				"matchCodes": [
					"Good"
				],
				"name": "10 Compass Ct, Scarborough, ON M1S 5R3, Canada",
				"statusCode": 200,
				"statusDescription": "OK",
				"traceId": "04244aaa8f3048008b3c86c21a12aca5|BN20181720|7.7.0.0|",
				"addressLine": "10 Compass Ct",
				"adminDistrict": "ON",
				"adminDistrict2": "Toronto",
				"countryRegion": "Canada",
				"formattedAddress": "10 Compass Ct, Scarborough, ON M1S 5R3, Canada",
				"locality": "Toronto",
				"neighborhood": "Agincourt North",
				"postalCode": "M1S 5R3"
			},
			"geometry": {
				"type": "Point",
				"coordinates": [
					-79.25827,
					43.80285
				]
			},
			"bbox": [
				-79.2598276,
				43.8017258,
				-79.2567124,
				43.8039742
			]
		}
	]
}
