{
	"type": "FeatureCollection",
	"features": [
		{
			"type": "Feature",
			"properties": {
				"confidence": 9,
				"authenticationResultCode": "ValidCredentials",
				"brandLogoUri": "http://dev.virtualearth.net/Branding/logo_powered_by.png",
				"copyright": "Copyright © 2017 Microsoft and its suppliers. All rights reserved. This API cannot be accessed and the content and any results may not be used, reproduced or transmitted in any manner without express written permission from Microsoft Corporation.",
				"entityType": "Address",
				"matchCodes": [
					"Good"
				],
				"name": "10 Cour Capella, Ottawa, ON K2E 7V6, Canada",
				"statusCode": 200,
				"statusDescription": "OK",
				"traceId": "bb6f07366be64b68a5cf5ec428afb987|BN20121762|7.7.0.0|",
				"addressLine": "10 Cour Capella",
				"adminDistrict": "ON",
				"adminDistrict2": "Ottawa",
				"countryRegion": "Canada",
				"formattedAddress": "10 Cour Capella, Ottawa, ON K2E 7V6, Canada",
				"locality": "Ottawa",
				"neighborhood": "Nepean",
				"postalCode": "K2E 7V6"
			},
			"geometry": {
				"type": "Point",
				"coordinates": [
					-75.70814,
					45.33216
				]
			},
			"bbox": [
				-75.7097391,
				45.3310358,
				-75.7065409,
				45.3332842
			]
		}
	]
}
