{
	"type": "FeatureCollection",
	"features": [
		{
			"type": "Feature",
			"properties": {
				"confidence": 9,
				"authenticationResultCode": "ValidCredentials",
				"brandLogoUri": "http://dev.virtualearth.net/Branding/logo_powered_by.png",
				"copyright": "Copyright © 2017 Microsoft and its suppliers. All rights reserved. This API cannot be accessed and the content and any results may not be used, reproduced or transmitted in any manner without express written permission from Microsoft Corporation.",
				"entityType": "Address",
				"matchCodes": [
					"Good"
				],
				"name": "10 Hamilton Rd, Barrie, ON L4N 8Y5, Canada",
				"statusCode": 200,
				"statusDescription": "OK",
				"traceId": "a81ea6f58ddd4b7494248fce1cf52ea2|BN20171457|7.7.0.0|",
				"addressLine": "10 Hamilton Rd",
				"adminDistrict": "ON",
				"adminDistrict2": "Simcoe",
				"countryRegion": "Canada",
				"formattedAddress": "10 Hamilton Rd, Barrie, ON L4N 8Y5, Canada",
				"locality": "Barrie",
				"postalCode": "L4N 8Y5"
			},
			"geometry": {
				"type": "Point",
				"coordinates": [
					-79.67264,
					44.3573499
				]
			},
			"bbox": [
				-79.6742123,
				44.3562257,
				-79.6710677,
				44.3584741
			]
		}
	]
}
