{
	"type": "FeatureCollection",
	"features": [
		{
			"type": "Feature",
			"properties": {
				"confidence": 9,
				"authenticationResultCode": "ValidCredentials",
				"brandLogoUri": "http://dev.virtualearth.net/Branding/logo_powered_by.png",
				"copyright": "Copyright © 2017 Microsoft and its suppliers. All rights reserved. This API cannot be accessed and the content and any results may not be used, reproduced or transmitted in any manner without express written permission from Microsoft Corporation.",
				"entityType": "Address",
				"matchCodes": [
					"Good"
				],
				"name": "10 Queen St, Bridgetown, NS B0S, Canada",
				"statusCode": 200,
				"statusDescription": "OK",
				"traceId": "1d094c64c94e4693a7fdee24d63cad8b|BN20130721|7.7.0.0|",
				"addressLine": "10 Queen St",
				"adminDistrict": "NS",
				"adminDistrict2": "Annapolis",
				"countryRegion": "Canada",
				"formattedAddress": "10 Queen St, Bridgetown, NS B0S, Canada",
				"locality": "Bridgetown",
				"postalCode": "B0S 1C0"
			},
			"geometry": {
				"type": "Point",
				"coordinates": [
					-65.2910314,
					44.8411065
				]
			},
			"bbox": [
				-65.2926168,
				44.8399823,
				-65.289446,
				44.8422306
			]
		}
	]
}
