{
	"type": "FeatureCollection",
	"features": [
		{
			"type": "Feature",
			"properties": {
				"confidence": 9,
				"authenticationResultCode": "ValidCredentials",
				"brandLogoUri": "http://dev.virtualearth.net/Branding/logo_powered_by.png",
				"copyright": "Copyright © 2017 Microsoft and its suppliers. All rights reserved. This API cannot be accessed and the content and any results may not be used, reproduced or transmitted in any manner without express written permission from Microsoft Corporation.",
				"entityType": "Address",
				"matchCodes": [
					"Good"
				],
				"name": "10 Spruce St, Paris, ON N3L 1R6, Canada",
				"statusCode": 200,
				"statusDescription": "OK",
				"traceId": "fe95ab45f2c64524a0cf8dc778f1a788|BN20200239|7.7.0.0|",
				"addressLine": "10 Spruce St",
				"adminDistrict": "ON",
				"adminDistrict2": "Brant",
				"countryRegion": "Canada",
				"formattedAddress": "10 Spruce St, Paris, ON N3L 1R6, Canada",
				"locality": "Brant",
				"neighborhood": "Paris",
				"postalCode": "N3L 1R6"
			},
			"geometry": {
				"type": "Point",
				"coordinates": [
					-80.39339,
					43.203
				]
			},
			"bbox": [
				-80.3949322,
				43.2018758,
				-80.3918478,
				43.2041242
			]
		}
	]
}
