{
	"type": "FeatureCollection",
	"features": [
		{
			"type": "Feature",
			"properties": {
				"confidence": 9,
				"authenticationResultCode": "ValidCredentials",
				"brandLogoUri": "http://dev.virtualearth.net/Branding/logo_powered_by.png",
				"copyright": "Copyright © 2017 Microsoft and its suppliers. All rights reserved. This API cannot be accessed and the content and any results may not be used, reproduced or transmitted in any manner without express written permission from Microsoft Corporation.",
				"entityType": "Address",
				"matchCodes": [
					"Good"
				],
				"name": "10 Thistle St, Dutton, ON N0L 1J0, Canada",
				"statusCode": 200,
				"statusDescription": "OK",
				"traceId": "6a5677628e9d4f6a940b5eaba77157c8|BN20121764|7.7.0.0|",
				"addressLine": "10 Thistle St",
				"adminDistrict": "ON",
				"adminDistrict2": "Elgin",
				"countryRegion": "Canada",
				"formattedAddress": "10 Thistle St, Dutton, ON N0L 1J0, Canada",
				"locality": "Dutton/Dunwich",
				"neighborhood": "Dutton",
				"postalCode": "N0L 1J0"
			},
			"geometry": {
				"type": "Point",
				"coordinates": [
					-81.51211,
					42.66595
				]
			},
			"bbox": [
				-81.5136388,
				42.6648258,
				-81.5105812,
				42.6670742
			]
		}
	]
}
