{
	"type": "FeatureCollection",
	"features": [
		{
			"type": "Feature",
			"properties": {
				"confidence": 9,
				"authenticationResultCode": "ValidCredentials",
				"brandLogoUri": "http://dev.virtualearth.net/Branding/logo_powered_by.png",
				"copyright": "Copyright © 2017 Microsoft and its suppliers. All rights reserved. This API cannot be accessed and the content and any results may not be used, reproduced or transmitted in any manner without express written permission from Microsoft Corporation.",
				"entityType": "Address",
				"matchCodes": [
					"Good"
				],
				"name": "100 Shirley Ave, Kitchener, ON N2B 2E1, Canada",
				"statusCode": 200,
				"statusDescription": "OK",
				"traceId": "4845e57fbd824f4886c43104d6117b27|BN20130532|7.7.0.0|",
				"addressLine": "100 Shirley Ave",
				"adminDistrict": "ON",
				"adminDistrict2": "Waterloo",
				"countryRegion": "Canada",
				"formattedAddress": "100 Shirley Ave, Kitchener, ON N2B 2E1, Canada",
				"locality": "Kitchener",
				"neighborhood": "Victoria North",
				"postalCode": "N2B 2E1"
			},
			"geometry": {
				"type": "Point",
				"coordinates": [
					-80.46163,
					43.46743
				]
			},
			"bbox": [
				-80.4631789,
				43.4663058,
				-80.4600811,
				43.4685542
			]
		}
	]
}
