{
	"type": "FeatureCollection",
	"features": [
		{
			"type": "Feature",
			"properties": {
				"confidence": 9,
				"authenticationResultCode": "ValidCredentials",
				"brandLogoUri": "http://dev.virtualearth.net/Branding/logo_powered_by.png",
				"copyright": "Copyright © 2017 Microsoft and its suppliers. All rights reserved. This API cannot be accessed and the content and any results may not be used, reproduced or transmitted in any manner without express written permission from Microsoft Corporation.",
				"entityType": "Address",
				"matchCodes": [
					"Good"
				],
				"name": "100 McLeod Ave, Saskatoon, SK S7M 5V9, Canada",
				"statusCode": 200,
				"statusDescription": "OK",
				"traceId": "bcf32630582048c591438034de374e5d|BN20131519|7.7.0.0|",
				"addressLine": "100 McLeod Ave",
				"adminDistrict": "SK",
				"adminDistrict2": "Saskatchewan",
				"countryRegion": "Canada",
				"formattedAddress": "100 McLeod Ave, Saskatoon, SK S7M 5V9, Canada",
				"locality": "Saskatoon",
				"neighborhood": "South West Industrial",
				"postalCode": "S7M 5V9"
			},
			"geometry": {
				"type": "Point",
				"coordinates": [
					-106.7126004,
					52.1109767
				]
			},
			"bbox": [
				-106.7144308,
				52.1098526,
				-106.7107699,
				52.1121009
			]
		}
	]
}
