{
	"type": "FeatureCollection",
	"features": [
		{
			"type": "Feature",
			"properties": {
				"confidence": 9,
				"authenticationResultCode": "ValidCredentials",
				"brandLogoUri": "http://dev.virtualearth.net/Branding/logo_powered_by.png",
				"copyright": "Copyright © 2017 Microsoft and its suppliers. All rights reserved. This API cannot be accessed and the content and any results may not be used, reproduced or transmitted in any manner without express written permission from Microsoft Corporation.",
				"entityType": "Address",
				"matchCodes": [
					"Good"
				],
				"name": "999 Canada Pl, Vancouver, BC V6C 3T4, Canada",
				"statusCode": 200,
				"statusDescription": "OK",
				"traceId": "9650964e2f36480f96874c453c2aa93a|BN20240423|7.7.0.0|",
				"addressLine": "999 Canada Pl",
				"adminDistrict": "BC",
				"adminDistrict2": "Greater Vancouver",
				"countryRegion": "Canada",
				"formattedAddress": "999 Canada Pl, Vancouver, BC V6C 3T4, Canada",
				"locality": "Vancouver",
				"neighborhood": "Downtown",
				"postalCode": "V6C 3T4"
			},
			"geometry": {
				"type": "Point",
				"coordinates": [
					-123.1148699,
					49.2881297
				]
			},
			"bbox": [
				-123.1165934,
				49.2870055,
				-123.1131464,
				49.2892538
			]
		}
	]
}
