{
	"type": "FeatureCollection",
	"features": [
		{
			"type": "Feature",
			"properties": {
				"confidence": 9,
				"authenticationResultCode": "ValidCredentials",
				"brandLogoUri": "http://dev.virtualearth.net/Branding/logo_powered_by.png",
				"copyright": "Copyright © 2017 Microsoft and its suppliers. All rights reserved. This API cannot be accessed and the content and any results may not be used, reproduced or transmitted in any manner without express written permission from Microsoft Corporation.",
				"entityType": "Address",
				"matchCodes": [
					"Good"
				],
				"name": "100 Dickins St, Yellowknife, NT X1A, Canada",
				"statusCode": 200,
				"statusDescription": "OK",
				"traceId": "c56e8e9b1ea349f7b6cdddcc44d3d4b0|BN20131519|7.7.0.0|",
				"addressLine": "100 Dickins St",
				"adminDistrict": "NT",
				"adminDistrict2": "Northwest Territories",
				"countryRegion": "Canada",
				"formattedAddress": "100 Dickins St, Yellowknife, NT X1A, Canada",
				"locality": "Yellowknife",
				"postalCode": "X1A 2P4"
			},
			"geometry": {
				"type": "Point",
				"coordinates": [
					-114.4149866,
					62.465539
				]
			},
			"bbox": [
				-114.4174183,
				62.4644148,
				-114.4125548,
				62.4666631
			]
		}
	]
}
