{
	"type": "FeatureCollection",
	"features": [
		{
			"type": "Feature",
			"properties": {
				"confidence": 9,
				"authenticationResultCode": "ValidCredentials",
				"brandLogoUri": "http://dev.virtualearth.net/Branding/logo_powered_by.png",
				"copyright": "Copyright © 2017 Microsoft and its suppliers. All rights reserved. This API cannot be accessed and the content and any results may not be used, reproduced or transmitted in any manner without express written permission from Microsoft Corporation.",
				"entityType": "Address",
				"matchCodes": [
					"Good"
				],
				"name": "100 Anderson Rd SE, Calgary, AB T2J 3V1, Canada",
				"statusCode": 200,
				"statusDescription": "OK",
				"traceId": "e71b1a617963442b88e18367324810e3|BN20121763|7.7.0.0|",
				"addressLine": "100 Anderson Rd SE",
				"adminDistrict": "AB",
				"adminDistrict2": "Alberta",
				"countryRegion": "Canada",
				"formattedAddress": "100 Anderson Rd SE, Calgary, AB T2J 3V1, Canada",
				"locality": "Calgary",
				"neighborhood": "Willow Park",
				"postalCode": "T2J 3V1"
			},
			"geometry": {
				"type": "Point",
				"coordinates": [
					-114.0623102,
					50.9499751
				]
			},
			"bbox": [
				-114.0640946,
				50.9488509,
				-114.0605258,
				50.9510992
			]
		}
	]
}
