{
	"type": "FeatureCollection",
	"features": [
		{
			"type": "Feature",
			"properties": {
				"confidence": 9,
				"authenticationResultCode": "ValidCredentials",
				"brandLogoUri": "http://dev.virtualearth.net/Branding/logo_powered_by.png",
				"copyright": "Copyright © 2017 Microsoft and its suppliers. All rights reserved. This API cannot be accessed and the content and any results may not be used, reproduced or transmitted in any manner without express written permission from Microsoft Corporation.",
				"entityType": "Address",
				"matchCodes": [
					"Good"
				],
				"name": "100 Bluewater Rd, Bedford, NS B4B 1G7, Canada",
				"statusCode": 200,
				"statusDescription": "OK",
				"traceId": "6c7b7981a7e84cb893c11f0c86586f1a|BN20200239|7.7.0.0|",
				"addressLine": "100 Bluewater Rd",
				"adminDistrict": "NS",
				"adminDistrict2": "Halifax",
				"countryRegion": "Canada",
				"formattedAddress": "100 Bluewater Rd, Bedford, NS B4B 1G7, Canada",
				"locality": "Halifax",
				"neighborhood": "Bedford",
				"postalCode": "B4B 1G7"
			},
			"geometry": {
				"type": "Point",
				"coordinates": [
					-63.70914,
					44.7231499
				]
			},
			"bbox": [
				-63.7107222,
				44.7220257,
				-63.7075578,
				44.7242741
			]
		}
	]
}
