{
	"type": "FeatureCollection",
	"features": [
		{
			"type": "Feature",
			"properties": {
				"confidence": 9,
				"authenticationResultCode": "ValidCredentials",
				"brandLogoUri": "http://dev.virtualearth.net/Branding/logo_powered_by.png",
				"copyright": "Copyright © 2017 Microsoft and its suppliers. All rights reserved. This API cannot be accessed and the content and any results may not be used, reproduced or transmitted in any manner without express written permission from Microsoft Corporation.",
				"entityType": "Address",
				"matchCodes": [
					"Good"
				],
				"name": "100 Maplebank Rd, Victoria, BC V9A 4M1, Canada",
				"statusCode": 200,
				"statusDescription": "OK",
				"traceId": "88b3cddbdfca4f448846a1066c19ee75|BN20130533|7.7.0.0|",
				"addressLine": "100 Maplebank Rd",
				"adminDistrict": "BC",
				"adminDistrict2": "Capital",
				"countryRegion": "Canada",
				"formattedAddress": "100 Maplebank Rd, Victoria, BC V9A 4M1, Canada",
				"locality": "Esquimalt",
				"neighborhood": "Victoria",
				"postalCode": "V9A 4M1"
			},
			"geometry": {
				"type": "Point",
				"coordinates": [
					-123.427939,
					48.4415031
				]
			},
			"bbox": [
				-123.4296336,
				48.4403789,
				-123.4262444,
				48.4426272
			]
		}
	]
}
