{
	"type": "FeatureCollection",
	"features": [
		{
			"type": "Feature",
			"properties": {
				"confidence": 9,
				"authenticationResultCode": "ValidCredentials",
				"brandLogoUri": "http://dev.virtualearth.net/Branding/logo_powered_by.png",
				"copyright": "Copyright © 2017 Microsoft and its suppliers. All rights reserved. This API cannot be accessed and the content and any results may not be used, reproduced or transmitted in any manner without express written permission from Microsoft Corporation.",
				"entityType": "Address",
				"matchCodes": [
					"Good"
				],
				"name": "1000 Edgeley Blvd, Concord, ON L4K 4V4, Canada",
				"statusCode": 200,
				"statusDescription": "OK",
				"traceId": "fef24816740f463196e8945edddc1e80|BN20130532|7.7.0.0|",
				"addressLine": "1000 Edgeley Blvd",
				"adminDistrict": "ON",
				"adminDistrict2": "York",
				"countryRegion": "Canada",
				"formattedAddress": "1000 Edgeley Blvd, Concord, ON L4K 4V4, Canada",
				"locality": "Vaughan",
				"neighborhood": "Concord",
				"postalCode": "L4K 4V4"
			},
			"geometry": {
				"type": "Point",
				"coordinates": [
					-79.5399599,
					43.81899
				]
			},
			"bbox": [
				-79.5415179,
				43.8178658,
				-79.5384019,
				43.8201142
			]
		}
	]
}
