{
	"type": "FeatureCollection",
	"features": [
		{
			"type": "Feature",
			"properties": {
				"confidence": 9,
				"authenticationResultCode": "ValidCredentials",
				"brandLogoUri": "http://dev.virtualearth.net/Branding/logo_powered_by.png",
				"copyright": "Copyright © 2017 Microsoft and its suppliers. All rights reserved. This API cannot be accessed and the content and any results may not be used, reproduced or transmitted in any manner without express written permission from Microsoft Corporation.",
				"entityType": "Address",
				"matchCodes": [
					"Good"
				],
				"name": "1000 Kindred Rd, Midland, ON L4R, Canada",
				"statusCode": 200,
				"statusDescription": "OK",
				"traceId": "a66a302788154784896754ab24ba6a60|BN20220145|7.7.0.0|",
				"addressLine": "1000 Kindred Rd",
				"adminDistrict": "ON",
				"adminDistrict2": "Simcoe",
				"countryRegion": "Canada",
				"formattedAddress": "1000 Kindred Rd, Midland, ON L4R, Canada",
				"locality": "Midland",
				"postalCode": "L4R 4K9"
			},
			"geometry": {
				"type": "Point",
				"coordinates": [
					-79.85248,
					44.73639
				]
			},
			"bbox": [
				-79.8540625,
				44.7352658,
				-79.8508975,
				44.7375142
			]
		}
	]
}
