{
	"type": "FeatureCollection",
	"features": [
		{
			"type": "Feature",
			"properties": {
				"confidence": 9,
				"authenticationResultCode": "ValidCredentials",
				"brandLogoUri": "http://dev.virtualearth.net/Branding/logo_powered_by.png",
				"copyright": "Copyright © 2017 Microsoft and its suppliers. All rights reserved. This API cannot be accessed and the content and any results may not be used, reproduced or transmitted in any manner without express written permission from Microsoft Corporation.",
				"entityType": "Address",
				"matchCodes": [
					"Good"
				],
				"name": "1000 Creditstone Rd, Concord, ON L4K 4P8, Canada",
				"statusCode": 200,
				"statusDescription": "OK",
				"traceId": "ebe353f6aa09480b8b214b98a444cf5b|BN20200239|7.7.0.0|",
				"addressLine": "1000 Creditstone Rd",
				"adminDistrict": "ON",
				"adminDistrict2": "York",
				"countryRegion": "Canada",
				"formattedAddress": "1000 Creditstone Rd, Concord, ON L4K 4P8, Canada",
				"locality": "Vaughan",
				"neighborhood": "Concord",
				"postalCode": "L4K 4P8"
			},
			"geometry": {
				"type": "Point",
				"coordinates": [
					-79.5229899,
					43.81553
				]
			},
			"bbox": [
				-79.5245478,
				43.8144058,
				-79.521432,
				43.8166542
			]
		}
	]
}
