{
	"type": "FeatureCollection",
	"features": [
		{
			"type": "Feature",
			"properties": {
				"confidence": 9,
				"authenticationResultCode": "ValidCredentials",
				"brandLogoUri": "http://dev.virtualearth.net/Branding/logo_powered_by.png",
				"copyright": "Copyright © 2017 Microsoft and its suppliers. All rights reserved. This API cannot be accessed and the content and any results may not be used, reproduced or transmitted in any manner without express written permission from Microsoft Corporation.",
				"entityType": "Address",
				"matchCodes": [
					"Good"
				],
				"name": "1000 7 Ave SW, Calgary, AB T2P 5L5, Canada",
				"statusCode": 200,
				"statusDescription": "OK",
				"traceId": "13e82cad80644089a104498efae7b5cc|BN20130530|7.7.0.0|",
				"addressLine": "1000 7 Ave SW",
				"adminDistrict": "AB",
				"adminDistrict2": "Alberta",
				"countryRegion": "Canada",
				"formattedAddress": "1000 7 Ave SW, Calgary, AB T2P 5L5, Canada",
				"locality": "Calgary",
				"neighborhood": "Downtown West End",
				"postalCode": "T2P 5L5"
			},
			"geometry": {
				"type": "Point",
				"coordinates": [
					-114.08407,
					51.0472899
				]
			},
			"bbox": [
				-114.0858581,
				51.0461657,
				-114.0822819,
				51.0484141
			]
		}
	]
}
