{
	"type": "FeatureCollection",
	"features": [
		{
			"type": "Feature",
			"properties": {
				"confidence": 9,
				"authenticationResultCode": "ValidCredentials",
				"brandLogoUri": "http://dev.virtualearth.net/Branding/logo_powered_by.png",
				"copyright": "Copyright © 2017 Microsoft and its suppliers. All rights reserved. This API cannot be accessed and the content and any results may not be used, reproduced or transmitted in any manner without express written permission from Microsoft Corporation.",
				"entityType": "Address",
				"matchCodes": [
					"Good"
				],
				"name": "1003 55 Ave NE, Calgary, AB T2E 6W1, Canada",
				"statusCode": 200,
				"statusDescription": "OK",
				"traceId": "0359d91bd6e94e61927ee431d537c208|BN20240253|7.7.0.0|",
				"addressLine": "1003 55 Ave NE",
				"adminDistrict": "AB",
				"adminDistrict2": "Alberta",
				"countryRegion": "Canada",
				"formattedAddress": "1003 55 Ave NE, Calgary, AB T2E 6W1, Canada",
				"locality": "Calgary",
				"postalCode": "T2E 6W1"
			},
			"geometry": {
				"type": "Point",
				"coordinates": [
					-114.0392709,
					51.1020475
				]
			},
			"bbox": [
				-114.0410611,
				51.1009234,
				-114.0374806,
				51.1031717
			]
		}
	]
}
