{
	"type": "FeatureCollection",
	"features": [
		{
			"type": "Feature",
			"properties": {
				"confidence": 9,
				"authenticationResultCode": "ValidCredentials",
				"brandLogoUri": "http://dev.virtualearth.net/Branding/logo_powered_by.png",
				"copyright": "Copyright © 2017 Microsoft and its suppliers. All rights reserved. This API cannot be accessed and the content and any results may not be used, reproduced or transmitted in any manner without express written permission from Microsoft Corporation.",
				"entityType": "Address",
				"matchCodes": [
					"Good"
				],
				"name": "1006 HWY-124, Norton, NB E5T 1X3, Canada",
				"statusCode": 200,
				"statusDescription": "OK",
				"traceId": "c2658711b8394a7fb3bac54c7efbb51b|BN20300154|7.7.0.0|",
				"addressLine": "1006 HWY-124",
				"adminDistrict": "NB",
				"adminDistrict2": "Kings",
				"countryRegion": "Canada",
				"formattedAddress": "1006 HWY-124, Norton, NB E5T 1X3, Canada",
				"locality": "Norton",
				"postalCode": "E5T 1X3"
			},
			"geometry": {
				"type": "Point",
				"coordinates": [
					-65.7482807,
					45.6600053
				]
			},
			"bbox": [
				-65.7498892,
				45.6588811,
				-65.7466723,
				45.6611294
			]
		}
	]
}
