{
	"type": "FeatureCollection",
	"features": [
		{
			"type": "Feature",
			"properties": {
				"confidence": 9,
				"authenticationResultCode": "ValidCredentials",
				"brandLogoUri": "http://dev.virtualearth.net/Branding/logo_powered_by.png",
				"copyright": "Copyright © 2017 Microsoft and its suppliers. All rights reserved. This API cannot be accessed and the content and any results may not be used, reproduced or transmitted in any manner without express written permission from Microsoft Corporation.",
				"entityType": "Address",
				"matchCodes": [
					"Good"
				],
				"name": "10104 River Rd, Delta, BC V4G, Canada",
				"statusCode": 200,
				"statusDescription": "OK",
				"traceId": "be003b5ce9f44f9ab561a9caa404ae9f|BN20130422|7.7.0.0|",
				"addressLine": "10104 River Rd",
				"adminDistrict": "BC",
				"adminDistrict2": "Greater Vancouver",
				"countryRegion": "Canada",
				"formattedAddress": "10104 River Rd, Delta, BC V4G, Canada",
				"locality": "Delta",
				"postalCode": "V4G"
			},
			"geometry": {
				"type": "Point",
				"coordinates": [
					-122.94231,
					49.15488
				]
			},
			"bbox": [
				-122.9440288,
				49.1537558,
				-122.9405912,
				49.1560042
			]
		}
	]
}
