{
	"type": "FeatureCollection",
	"features": [
		{
			"type": "Feature",
			"properties": {
				"confidence": 9,
				"authenticationResultCode": "ValidCredentials",
				"brandLogoUri": "http://dev.virtualearth.net/Branding/logo_powered_by.png",
				"copyright": "Copyright © 2017 Microsoft and its suppliers. All rights reserved. This API cannot be accessed and the content and any results may not be used, reproduced or transmitted in any manner without express written permission from Microsoft Corporation.",
				"entityType": "Address",
				"matchCodes": [
					"Good"
				],
				"name": "1011 9th Ave W, Kindersley, SK S0L, Canada",
				"statusCode": 200,
				"statusDescription": "OK",
				"traceId": "4431c2bf304447889f316f7286a482df|BN20130442|7.7.0.0|",
				"addressLine": "1011 9th Ave W",
				"adminDistrict": "SK",
				"adminDistrict2": "Saskatchewan",
				"countryRegion": "Canada",
				"formattedAddress": "1011 9th Ave W, Kindersley, SK S0L, Canada",
				"locality": "Kindersley",
				"postalCode": "S0L 1S0"
			},
			"geometry": {
				"type": "Point",
				"coordinates": [
					-109.1743839,
					51.4727051
				]
			},
			"bbox": [
				-109.1761887,
				51.4715809,
				-109.1725792,
				51.4738293
			]
		}
	]
}
