{
	"type": "FeatureCollection",
	"features": [
		{
			"type": "Feature",
			"properties": {
				"confidence": 9,
				"authenticationResultCode": "ValidCredentials",
				"brandLogoUri": "http://dev.virtualearth.net/Branding/logo_powered_by.png",
				"copyright": "Copyright © 2017 Microsoft and its suppliers. All rights reserved. This API cannot be accessed and the content and any results may not be used, reproduced or transmitted in any manner without express written permission from Microsoft Corporation.",
				"entityType": "Address",
				"matchCodes": [
					"Good"
				],
				"name": "10127 120 Ave, Grande Prairie, AB T8V 8H8, Canada",
				"statusCode": 200,
				"statusDescription": "OK",
				"traceId": "9771e78923f94298bacc849799f26b3d|BN20130423|7.7.0.0|",
				"addressLine": "10127 120 Ave",
				"adminDistrict": "AB",
				"adminDistrict2": "Alberta",
				"countryRegion": "Canada",
				"formattedAddress": "10127 120 Ave, Grande Prairie, AB T8V 8H8, Canada",
				"locality": "Grande Prairie",
				"neighborhood": "Northgate",
				"postalCode": "T8V 8H8"
			},
			"geometry": {
				"type": "Point",
				"coordinates": [
					-118.80001,
					55.18765
				]
			},
			"bbox": [
				-118.8019791,
				55.1865258,
				-118.7980409,
				55.1887742
			]
		}
	]
}
