{
	"type": "FeatureCollection",
	"features": [
		{
			"type": "Feature",
			"properties": {
				"confidence": 9,
				"authenticationResultCode": "ValidCredentials",
				"brandLogoUri": "http://dev.virtualearth.net/Branding/logo_powered_by.png",
				"copyright": "Copyright © 2017 Microsoft and its suppliers. All rights reserved. This API cannot be accessed and the content and any results may not be used, reproduced or transmitted in any manner without express written permission from Microsoft Corporation.",
				"entityType": "Address",
				"matchCodes": [
					"Good"
				],
				"name": "10131 117 Ave, Grande Prairie, AB T8V 7Y9, Canada",
				"statusCode": 200,
				"statusDescription": "OK",
				"traceId": "3685971870fa4bac820467f1a2f6aa92|BN20130532|7.7.0.0|",
				"addressLine": "10131 117 Ave",
				"adminDistrict": "AB",
				"adminDistrict2": "Alberta",
				"countryRegion": "Canada",
				"formattedAddress": "10131 117 Ave, Grande Prairie, AB T8V 7Y9, Canada",
				"locality": "Grande Prairie",
				"neighborhood": "Northgate",
				"postalCode": "T8V 7Y9"
			},
			"geometry": {
				"type": "Point",
				"coordinates": [
					-118.80075,
					55.18575
				]
			},
			"bbox": [
				-118.802719,
				55.1846258,
				-118.798781,
				55.1868742
			]
		}
	]
}
