{
	"type": "FeatureCollection",
	"features": [
		{
			"type": "Feature",
			"properties": {
				"confidence": 9,
				"authenticationResultCode": "ValidCredentials",
				"brandLogoUri": "http://dev.virtualearth.net/Branding/logo_powered_by.png",
				"copyright": "Copyright © 2017 Microsoft and its suppliers. All rights reserved. This API cannot be accessed and the content and any results may not be used, reproduced or transmitted in any manner without express written permission from Microsoft Corporation.",
				"entityType": "Address",
				"matchCodes": [
					"Good"
				],
				"name": "10136 King George Blvd, Surrey, BC V3T 2W4, Canada",
				"statusCode": 200,
				"statusDescription": "OK",
				"traceId": "45683602487c4dd68bef5b1876fe39b6|BN20130423|7.7.0.0|",
				"addressLine": "10136 King George Blvd",
				"adminDistrict": "BC",
				"adminDistrict2": "Greater Vancouver",
				"countryRegion": "Canada",
				"formattedAddress": "10136 King George Blvd, Surrey, BC V3T 2W4, Canada",
				"locality": "Surrey",
				"neighborhood": "Whalley",
				"postalCode": "V3T 2W4"
			},
			"geometry": {
				"type": "Point",
				"coordinates": [
					-122.8451951,
					49.18667
				]
			},
			"bbox": [
				-122.8469151,
				49.1855459,
				-122.8434752,
				49.1877942
			]
		}
	]
}
