{
	"type": "FeatureCollection",
	"features": [
		{
			"type": "Feature",
			"properties": {
				"confidence": 9,
				"authenticationResultCode": "ValidCredentials",
				"brandLogoUri": "http://dev.virtualearth.net/Branding/logo_powered_by.png",
				"copyright": "Copyright © 2017 Microsoft and its suppliers. All rights reserved. This API cannot be accessed and the content and any results may not be used, reproduced or transmitted in any manner without express written permission from Microsoft Corporation.",
				"entityType": "Address",
				"matchCodes": [
					"Good"
				],
				"name": "1015 112th Ave, Tisdale, SK S0E, Canada",
				"statusCode": 200,
				"statusDescription": "OK",
				"traceId": "df10b59de8c84c7d8d4fb47f36fbef5b|BN20260231|7.7.0.0|",
				"addressLine": "1015 112th Ave",
				"adminDistrict": "SK",
				"adminDistrict2": "Saskatchewan",
				"countryRegion": "Canada",
				"formattedAddress": "1015 112th Ave, Tisdale, SK S0E, Canada",
				"locality": "Tisdale",
				"postalCode": "S0E 1T0"
			},
			"geometry": {
				"type": "Point",
				"coordinates": [
					-104.043,
					52.85994
				]
			},
			"bbox": [
				-104.0448619,
				52.8588158,
				-104.0411381,
				52.8610642
			]
		}
	]
}
