{
	"type": "FeatureCollection",
	"features": [
		{
			"type": "Feature",
			"properties": {
				"confidence": 9,
				"authenticationResultCode": "ValidCredentials",
				"brandLogoUri": "http://dev.virtualearth.net/Branding/logo_powered_by.png",
				"copyright": "Copyright © 2017 Microsoft and its suppliers. All rights reserved. This API cannot be accessed and the content and any results may not be used, reproduced or transmitted in any manner without express written permission from Microsoft Corporation.",
				"entityType": "Address",
				"matchCodes": [
					"Good"
				],
				"name": "1016 Sabre Ln, Gravenhurst, ON P0C, Canada",
				"statusCode": 200,
				"statusDescription": "OK",
				"traceId": "6853a9dddeb9472caa21048a6918c11d|BN20250135|7.7.0.0|",
				"addressLine": "1016 Sabre Ln",
				"adminDistrict": "ON",
				"adminDistrict2": "Muskoka",
				"countryRegion": "Canada",
				"formattedAddress": "1016 Sabre Ln, Gravenhurst, ON P0C, Canada",
				"locality": "Gravenhurst",
				"postalCode": "P0C"
			},
			"geometry": {
				"type": "Point",
				"coordinates": [
					-79.3113991,
					44.9829353
				]
			},
			"bbox": [
				-79.3129884,
				44.9818111,
				-79.3098098,
				44.9840594
			]
		}
	]
}
