{
	"type": "FeatureCollection",
	"features": [
		{
			"type": "Feature",
			"properties": {
				"confidence": 9,
				"authenticationResultCode": "ValidCredentials",
				"brandLogoUri": "http://dev.virtualearth.net/Branding/logo_powered_by.png",
				"copyright": "Copyright © 2017 Microsoft and its suppliers. All rights reserved. This API cannot be accessed and the content and any results may not be used, reproduced or transmitted in any manner without express written permission from Microsoft Corporation.",
				"entityType": "Address",
				"matchCodes": [
					"Good"
				],
				"name": "1019 Cranbrook St N, Cranbrook, BC V1C 3S4, Canada",
				"statusCode": 200,
				"statusDescription": "OK",
				"traceId": "d91bde4bbefc4ab79c393feaa974c753|BN20280152|7.7.0.0|",
				"addressLine": "1019 Cranbrook St N",
				"adminDistrict": "BC",
				"adminDistrict2": "East Kootenay",
				"countryRegion": "Canada",
				"formattedAddress": "1019 Cranbrook St N, Cranbrook, BC V1C 3S4, Canada",
				"locality": "Cranbrook",
				"postalCode": "V1C 3S4"
			},
			"geometry": {
				"type": "Point",
				"coordinates": [
					-115.75694,
					49.52277
				]
			},
			"bbox": [
				-115.7586717,
				49.5216458,
				-115.7552083,
				49.5238942
			]
		}
	]
}
