{
	"type": "FeatureCollection",
	"features": [
		{
			"type": "Feature",
			"properties": {
				"confidence": 9,
				"authenticationResultCode": "ValidCredentials",
				"brandLogoUri": "http://dev.virtualearth.net/Branding/logo_powered_by.png",
				"copyright": "Copyright © 2017 Microsoft and its suppliers. All rights reserved. This API cannot be accessed and the content and any results may not be used, reproduced or transmitted in any manner without express written permission from Microsoft Corporation.",
				"entityType": "Address",
				"matchCodes": [
					"Good"
				],
				"name": "1019 Venture Way, Gibsons, BC V0N 1V7, Canada",
				"statusCode": 200,
				"statusDescription": "OK",
				"traceId": "b6146875a56443da9c4f95ab0a1df0fc|BN20160335|7.7.0.0|",
				"addressLine": "1019 Venture Way",
				"adminDistrict": "BC",
				"adminDistrict2": "Sunshine Coast",
				"countryRegion": "Canada",
				"formattedAddress": "1019 Venture Way, Gibsons, BC V0N 1V7, Canada",
				"locality": "Gibsons",
				"postalCode": "V0N 1V7"
			},
			"geometry": {
				"type": "Point",
				"coordinates": [
					-123.52608,
					49.40796
				]
			},
			"bbox": [
				-123.5278077,
				49.4068358,
				-123.5243523,
				49.4090842
			]
		}
	]
}
