{
	"type": "FeatureCollection",
	"features": [
		{
			"type": "Feature",
			"properties": {
				"confidence": 9,
				"authenticationResultCode": "ValidCredentials",
				"brandLogoUri": "http://dev.virtualearth.net/Branding/logo_powered_by.png",
				"copyright": "Copyright © 2017 Microsoft and its suppliers. All rights reserved. This API cannot be accessed and the content and any results may not be used, reproduced or transmitted in any manner without express written permission from Microsoft Corporation.",
				"entityType": "Address",
				"matchCodes": [
					"Good"
				],
				"name": "10191 3rd St, Sidney, BC V8L, Canada",
				"statusCode": 200,
				"statusDescription": "OK",
				"traceId": "68646183027f4c788ede1c9f8abd90bc|BN20240423|7.7.0.0|",
				"addressLine": "10191 3rd St",
				"adminDistrict": "BC",
				"adminDistrict2": "Capital",
				"countryRegion": "Canada",
				"formattedAddress": "10191 3rd St, Sidney, BC V8L, Canada",
				"locality": "Sidney",
				"postalCode": "V8L 3B7"
			},
			"geometry": {
				"type": "Point",
				"coordinates": [
					-123.3975851,
					48.6584188
				]
			},
			"bbox": [
				-123.3992869,
				48.6572946,
				-123.3958832,
				48.6595429
			]
		}
	]
}
