{
	"type": "FeatureCollection",
	"features": [
		{
			"type": "Feature",
			"properties": {
				"confidence": 9,
				"authenticationResultCode": "ValidCredentials",
				"brandLogoUri": "http://dev.virtualearth.net/Branding/logo_powered_by.png",
				"copyright": "Copyright © 2017 Microsoft and its suppliers. All rights reserved. This API cannot be accessed and the content and any results may not be used, reproduced or transmitted in any manner without express written permission from Microsoft Corporation.",
				"entityType": "Address",
				"matchCodes": [
					"Good"
				],
				"name": "102 Spruce Haven Rd, Melfort, SK S0E, Canada",
				"statusCode": 200,
				"statusDescription": "OK",
				"traceId": "fb164e5da8134afa86c7ed080e556cc4|BN20181720|7.7.0.0|",
				"addressLine": "102 Spruce Haven Rd",
				"adminDistrict": "SK",
				"adminDistrict2": "Saskatchewan",
				"countryRegion": "Canada",
				"formattedAddress": "102 Spruce Haven Rd, Melfort, SK S0E, Canada",
				"locality": "Melfort",
				"postalCode": "S0E 1A0"
			},
			"geometry": {
				"type": "Point",
				"coordinates": [
					-104.5913699,
					52.8565749
				]
			},
			"bbox": [
				-104.5932316,
				52.8554507,
				-104.5895081,
				52.857699
			]
		}
	]
}
