{
	"type": "FeatureCollection",
	"features": [
		{
			"type": "Feature",
			"properties": {
				"confidence": 9,
				"authenticationResultCode": "ValidCredentials",
				"brandLogoUri": "http://dev.virtualearth.net/Branding/logo_powered_by.png",
				"copyright": "Copyright © 2017 Microsoft and its suppliers. All rights reserved. This API cannot be accessed and the content and any results may not be used, reproduced or transmitted in any manner without express written permission from Microsoft Corporation.",
				"entityType": "Address",
				"matchCodes": [
					"Good"
				],
				"name": "102 Rue Giguère, Scott, QC G0S 3G0, Canada",
				"statusCode": 200,
				"statusDescription": "OK",
				"traceId": "5a647c2db7b54c77a68d4396b9740faa|BN20130719|7.7.0.0|",
				"addressLine": "102 Rue Giguère",
				"adminDistrict": "QC",
				"adminDistrict2": "La Nouvelle-Beauce",
				"countryRegion": "Canada",
				"formattedAddress": "102 Rue Giguère, Scott, QC G0S 3G0, Canada",
				"locality": "Scott",
				"postalCode": "G0S 3G0"
			},
			"geometry": {
				"type": "Point",
				"coordinates": [
					-71.05328,
					46.50986
				]
			},
			"bbox": [
				-71.0549134,
				46.5087358,
				-71.0516466,
				46.5109842
			]
		}
	]
}
