{
	"type": "FeatureCollection",
	"features": [
		{
			"type": "Feature",
			"properties": {
				"confidence": 9,
				"authenticationResultCode": "ValidCredentials",
				"brandLogoUri": "http://dev.virtualearth.net/Branding/logo_powered_by.png",
				"copyright": "Copyright © 2017 Microsoft and its suppliers. All rights reserved. This API cannot be accessed and the content and any results may not be used, reproduced or transmitted in any manner without express written permission from Microsoft Corporation.",
				"entityType": "Address",
				"matchCodes": [
					"Good"
				],
				"name": "10203 184 St NW, Edmonton, AB T5S 2J4, Canada",
				"statusCode": 200,
				"statusDescription": "OK",
				"traceId": "2b9c6aa64f9d4ea9b5b99e2d57f0c562|BN20130423|7.7.0.0|",
				"addressLine": "10203 184 St NW",
				"adminDistrict": "AB",
				"adminDistrict2": "Alberta",
				"countryRegion": "Canada",
				"formattedAddress": "10203 184 St NW, Edmonton, AB T5S 2J4, Canada",
				"locality": "Edmonton",
				"neighborhood": "Morin Industrial",
				"postalCode": "T5S 2J4"
			},
			"geometry": {
				"type": "Point",
				"coordinates": [
					-113.63866,
					53.54402
				]
			},
			"bbox": [
				-113.6405519,
				53.5428958,
				-113.6367681,
				53.5451442
			]
		}
	]
}
