{
	"type": "FeatureCollection",
	"features": [
		{
			"type": "Feature",
			"properties": {
				"confidence": 9,
				"authenticationResultCode": "ValidCredentials",
				"brandLogoUri": "http://dev.virtualearth.net/Branding/logo_powered_by.png",
				"copyright": "Copyright © 2017 Microsoft and its suppliers. All rights reserved. This API cannot be accessed and the content and any results may not be used, reproduced or transmitted in any manner without express written permission from Microsoft Corporation.",
				"entityType": "Address",
				"matchCodes": [
					"Good"
				],
				"name": "1020 Ottawa St N, Kitchener, ON N2A 3Z3, Canada",
				"statusCode": 200,
				"statusDescription": "OK",
				"traceId": "5bc664b52eca4185938f4a3597360ae1|BN20260223|7.7.0.0|",
				"addressLine": "1020 Ottawa St N",
				"adminDistrict": "ON",
				"adminDistrict2": "Waterloo",
				"countryRegion": "Canada",
				"formattedAddress": "1020 Ottawa St N, Kitchener, ON N2A 3Z3, Canada",
				"locality": "Kitchener",
				"neighborhood": "Heritage Park",
				"postalCode": "N2A 3Z3"
			},
			"geometry": {
				"type": "Point",
				"coordinates": [
					-80.44441,
					43.45163
				]
			},
			"bbox": [
				-80.4459585,
				43.4505058,
				-80.4428615,
				43.4527542
			]
		}
	]
}
