{
	"type": "FeatureCollection",
	"features": [
		{
			"type": "Feature",
			"properties": {
				"confidence": 9,
				"authenticationResultCode": "ValidCredentials",
				"brandLogoUri": "http://dev.virtualearth.net/Branding/logo_powered_by.png",
				"copyright": "Copyright © 2017 Microsoft and its suppliers. All rights reserved. This API cannot be accessed and the content and any results may not be used, reproduced or transmitted in any manner without express written permission from Microsoft Corporation.",
				"entityType": "Address",
				"matchCodes": [
					"Good"
				],
				"name": "1020 Laut Ave, Crossfield, AB T0M, Canada",
				"statusCode": 200,
				"statusDescription": "OK",
				"traceId": "fa0c998d778f4c2793da7899eb499597|BN20131519|7.7.0.0|",
				"addressLine": "1020 Laut Ave",
				"adminDistrict": "AB",
				"adminDistrict2": "Alberta",
				"countryRegion": "Canada",
				"formattedAddress": "1020 Laut Ave, Crossfield, AB T0M, Canada",
				"locality": "Crossfield",
				"postalCode": "T0M 0S0"
			},
			"geometry": {
				"type": "Point",
				"coordinates": [
					-114.03271,
					51.4224699
				]
			},
			"bbox": [
				-114.0345128,
				51.4213457,
				-114.0309072,
				51.4235941
			]
		}
	]
}
