{
	"type": "FeatureCollection",
	"features": [
		{
			"type": "Feature",
			"properties": {
				"confidence": 9,
				"authenticationResultCode": "ValidCredentials",
				"brandLogoUri": "http://dev.virtualearth.net/Branding/logo_powered_by.png",
				"copyright": "Copyright © 2017 Microsoft and its suppliers. All rights reserved. This API cannot be accessed and the content and any results may not be used, reproduced or transmitted in any manner without express written permission from Microsoft Corporation.",
				"entityType": "Address",
				"matchCodes": [
					"Good"
				],
				"name": "1028 Westminster Ave, Kamloops, BC V2B 1P2, Canada",
				"statusCode": 200,
				"statusDescription": "OK",
				"traceId": "443fcee10218451c90057dbc65ef0d45|BN20280152|7.7.0.0|",
				"addressLine": "1028 Westminster Ave",
				"adminDistrict": "BC",
				"adminDistrict2": "Thompson-Nicola",
				"countryRegion": "Canada",
				"formattedAddress": "1028 Westminster Ave, Kamloops, BC V2B 1P2, Canada",
				"locality": "Kamloops",
				"neighborhood": "North Shore",
				"postalCode": "V2B 1P2"
			},
			"geometry": {
				"type": "Point",
				"coordinates": [
					-120.36873,
					50.70088
				]
			},
			"bbox": [
				-120.3705049,
				50.6997558,
				-120.3669551,
				50.7020042
			]
		}
	]
}
