{
	"type": "FeatureCollection",
	"features": [
		{
			"type": "Feature",
			"properties": {
				"confidence": 9,
				"authenticationResultCode": "ValidCredentials",
				"brandLogoUri": "http://dev.virtualearth.net/Branding/logo_powered_by.png",
				"copyright": "Copyright © 2017 Microsoft and its suppliers. All rights reserved. This API cannot be accessed and the content and any results may not be used, reproduced or transmitted in any manner without express written permission from Microsoft Corporation.",
				"entityType": "Address",
				"matchCodes": [
					"Good"
				],
				"name": "103 McMurchie Ln, Smithville, ON L0R 2A0, Canada",
				"statusCode": 200,
				"statusDescription": "OK",
				"traceId": "d4d270b3882442bf9d1d6780643a4263|BN20130520|7.7.0.0|",
				"addressLine": "103 McMurchie Ln",
				"adminDistrict": "ON",
				"adminDistrict2": "Niagara",
				"countryRegion": "Canada",
				"formattedAddress": "103 McMurchie Ln, Smithville, ON L0R 2A0, Canada",
				"locality": "West Lincoln",
				"neighborhood": "Smithville",
				"postalCode": "L0R 2A0"
			},
			"geometry": {
				"type": "Point",
				"coordinates": [
					-79.5466835,
					43.0989223
				]
			},
			"bbox": [
				-79.5482231,
				43.0977982,
				-79.545144,
				43.1000465
			]
		}
	]
}
