{
	"type": "FeatureCollection",
	"features": [
		{
			"type": "Feature",
			"properties": {
				"confidence": 8,
				"authenticationResultCode": "ValidCredentials",
				"brandLogoUri": "http://dev.virtualearth.net/Branding/logo_powered_by.png",
				"copyright": "Copyright © 2017 Microsoft and its suppliers. All rights reserved. This API cannot be accessed and the content and any results may not be used, reproduced or transmitted in any manner without express written permission from Microsoft Corporation.",
				"entityType": "RoadBlock",
				"matchCodes": [
					"UpHierarchy"
				],
				"name": "Jack White Rd, Apsley, ON K0L 1A0, Canada",
				"statusCode": 200,
				"statusDescription": "OK",
				"traceId": "1ae2576eeb754aaba030a060cc666f98|BN20121763|7.7.0.0|",
				"addressLine": "Jack White Rd",
				"adminDistrict": "ON",
				"adminDistrict2": "Peterborough",
				"countryRegion": "Canada",
				"formattedAddress": "Jack White Rd, Apsley, ON K0L 1A0, Canada",
				"locality": "North Kawartha",
				"neighborhood": "Apsley",
				"postalCode": "K0L 1A0"
			},
			"geometry": {
				"type": "Point",
				"coordinates": [
					-77.92615,
					44.84002
				]
			},
			"bbox": [
				-77.93152,
				44.83937,
				-77.92487,
				44.84021
			]
		}
	]
}
