{
	"type": "FeatureCollection",
	"features": [
		{
			"type": "Feature",
			"properties": {
				"confidence": 9,
				"authenticationResultCode": "ValidCredentials",
				"brandLogoUri": "http://dev.virtualearth.net/Branding/logo_powered_by.png",
				"copyright": "Copyright © 2017 Microsoft and its suppliers. All rights reserved. This API cannot be accessed and the content and any results may not be used, reproduced or transmitted in any manner without express written permission from Microsoft Corporation.",
				"entityType": "Address",
				"matchCodes": [
					"Good"
				],
				"name": "10314 116 Ave, Grande Prairie, AB T8V 4K5, Canada",
				"statusCode": 200,
				"statusDescription": "OK",
				"traceId": "e10e5086c6a74766b9a0d041ccca208a|BN20200137|7.7.0.0|",
				"addressLine": "10314 116 Ave",
				"adminDistrict": "AB",
				"adminDistrict2": "Alberta",
				"countryRegion": "Canada",
				"formattedAddress": "10314 116 Ave, Grande Prairie, AB T8V 4K5, Canada",
				"locality": "Grande Prairie",
				"neighborhood": "Avondale",
				"postalCode": "T8V 4K5"
			},
			"geometry": {
				"type": "Point",
				"coordinates": [
					-118.80631,
					55.18542
				]
			},
			"bbox": [
				-118.808279,
				55.1842958,
				-118.804341,
				55.1865442
			]
		}
	]
}
