{
	"type": "FeatureCollection",
	"features": [
		{
			"type": "Feature",
			"properties": {
				"confidence": 9,
				"authenticationResultCode": "ValidCredentials",
				"brandLogoUri": "http://dev.virtualearth.net/Branding/logo_powered_by.png",
				"copyright": "Copyright © 2017 Microsoft and its suppliers. All rights reserved. This API cannot be accessed and the content and any results may not be used, reproduced or transmitted in any manner without express written permission from Microsoft Corporation.",
				"entityType": "Address",
				"matchCodes": [
					"Good"
				],
				"name": "10311 84 St NW, Edmonton, AB T6A 3R2, Canada",
				"statusCode": 200,
				"statusDescription": "OK",
				"traceId": "0655474f9a0e42c8bdce62ec4a614a03|BN20130530|7.7.0.0|",
				"addressLine": "10311 84 St NW",
				"adminDistrict": "AB",
				"adminDistrict2": "Alberta",
				"countryRegion": "Canada",
				"formattedAddress": "10311 84 St NW, Edmonton, AB T6A 3R2, Canada",
				"locality": "Edmonton",
				"neighborhood": "Forest Heights",
				"postalCode": "T6A 3R2"
			},
			"geometry": {
				"type": "Point",
				"coordinates": [
					-113.45672,
					53.54525
				]
			},
			"bbox": [
				-113.4586119,
				53.5441258,
				-113.4548281,
				53.5463742
			]
		}
	]
}
