{
	"type": "FeatureCollection",
	"features": [
		{
			"type": "Feature",
			"properties": {
				"confidence": 9,
				"authenticationResultCode": "ValidCredentials",
				"brandLogoUri": "http://dev.virtualearth.net/Branding/logo_powered_by.png",
				"copyright": "Copyright © 2017 Microsoft and its suppliers. All rights reserved. This API cannot be accessed and the content and any results may not be used, reproduced or transmitted in any manner without express written permission from Microsoft Corporation.",
				"entityType": "Address",
				"matchCodes": [
					"Good"
				],
				"name": "10324 82 Ave NW, Edmonton, AB T6E 1Z8, Canada",
				"statusCode": 200,
				"statusDescription": "OK",
				"traceId": "e6f391b480e94be78d20937e7140f14a|BN20320521|7.7.0.0|",
				"addressLine": "10324 82 Ave NW",
				"adminDistrict": "AB",
				"adminDistrict2": "Alberta",
				"countryRegion": "Canada",
				"formattedAddress": "10324 82 Ave NW, Edmonton, AB T6E 1Z8, Canada",
				"locality": "Edmonton",
				"neighborhood": "Strathcona",
				"postalCode": "T6E 1Z8"
			},
			"geometry": {
				"type": "Point",
				"coordinates": [
					-113.4959,
					53.51832
				]
			},
			"bbox": [
				-113.4977907,
				53.5171958,
				-113.4940093,
				53.5194442
			]
		}
	]
}
