{
	"type": "FeatureCollection",
	"features": [
		{
			"type": "Feature",
			"properties": {
				"confidence": 9,
				"authenticationResultCode": "ValidCredentials",
				"brandLogoUri": "http://dev.virtualearth.net/Branding/logo_powered_by.png",
				"copyright": "Copyright © 2017 Microsoft and its suppliers. All rights reserved. This API cannot be accessed and the content and any results may not be used, reproduced or transmitted in any manner without express written permission from Microsoft Corporation.",
				"entityType": "Address",
				"matchCodes": [
					"Good"
				],
				"name": "104 Vancourtland St S, Arnprior, ON K7S 3Y5, Canada",
				"statusCode": 200,
				"statusDescription": "OK",
				"traceId": "b0d7596dacaf4feba035d823bb09b244|BN20190653|7.7.0.0|",
				"addressLine": "104 Vancourtland St S",
				"adminDistrict": "ON",
				"adminDistrict2": "Renfrew",
				"countryRegion": "Canada",
				"formattedAddress": "104 Vancourtland St S, Arnprior, ON K7S 3Y5, Canada",
				"locality": "Arnprior",
				"postalCode": "K7S 3Y5"
			},
			"geometry": {
				"type": "Point",
				"coordinates": [
					-76.36694,
					45.43414
				]
			},
			"bbox": [
				-76.368542,
				45.4330158,
				-76.365338,
				45.4352642
			]
		}
	]
}
