{
	"type": "FeatureCollection",
	"features": [
		{
			"type": "Feature",
			"properties": {
				"confidence": 9,
				"authenticationResultCode": "ValidCredentials",
				"brandLogoUri": "http://dev.virtualearth.net/Branding/logo_powered_by.png",
				"copyright": "Copyright © 2017 Microsoft and its suppliers. All rights reserved. This API cannot be accessed and the content and any results may not be used, reproduced or transmitted in any manner without express written permission from Microsoft Corporation.",
				"entityType": "Address",
				"matchCodes": [
					"Good"
				],
				"name": "104 Farwell Bay, Winnipeg, MB R3T 0S7, Canada",
				"statusCode": 200,
				"statusDescription": "OK",
				"traceId": "c97113579e8b4fd89e56a70b3e3c2a23|BN20190653|7.7.0.0|",
				"addressLine": "104 Farwell Bay",
				"adminDistrict": "MB",
				"adminDistrict2": "Manitoba",
				"countryRegion": "Canada",
				"formattedAddress": "104 Farwell Bay, Winnipeg, MB R3T 0S7, Canada",
				"locality": "Winnipeg",
				"neighborhood": "Maybank",
				"postalCode": "R3T 0S7"
			},
			"geometry": {
				"type": "Point",
				"coordinates": [
					-97.15954,
					49.83567
				]
			},
			"bbox": [
				-97.1612829,
				49.8345458,
				-97.1577971,
				49.8367942
			]
		}
	]
}
