{
	"type": "FeatureCollection",
	"features": [
		{
			"type": "Feature",
			"properties": {
				"confidence": 9,
				"authenticationResultCode": "ValidCredentials",
				"brandLogoUri": "http://dev.virtualearth.net/Branding/logo_powered_by.png",
				"copyright": "Copyright © 2017 Microsoft and its suppliers. All rights reserved. This API cannot be accessed and the content and any results may not be used, reproduced or transmitted in any manner without express written permission from Microsoft Corporation.",
				"entityType": "Address",
				"matchCodes": [
					"Good"
				],
				"name": "1040 McDonald St, Regina, SK S4N 2X8, Canada",
				"statusCode": 200,
				"statusDescription": "OK",
				"traceId": "f76f23817bc94e468533710062a277e7|BN20131519|7.7.0.0|",
				"addressLine": "1040 McDonald St",
				"adminDistrict": "SK",
				"adminDistrict2": "Saskatchewan",
				"countryRegion": "Canada",
				"formattedAddress": "1040 McDonald St, Regina, SK S4N 2X8, Canada",
				"locality": "Regina",
				"neighborhood": "Eastview",
				"postalCode": "S4N 2X8"
			},
			"geometry": {
				"type": "Point",
				"coordinates": [
					-104.5840599,
					50.46217
				]
			},
			"bbox": [
				-104.5858258,
				50.4610458,
				-104.582294,
				50.4632942
			]
		}
	]
}
