{
	"type": "FeatureCollection",
	"features": [
		{
			"type": "Feature",
			"properties": {
				"confidence": 9,
				"authenticationResultCode": "ValidCredentials",
				"brandLogoUri": "http://dev.virtualearth.net/Branding/logo_powered_by.png",
				"copyright": "Copyright © 2017 Microsoft and its suppliers. All rights reserved. This API cannot be accessed and the content and any results may not be used, reproduced or transmitted in any manner without express written permission from Microsoft Corporation.",
				"entityType": "Address",
				"matchCodes": [
					"Good"
				],
				"name": "1045 Matheson Blvd E, Mississauga, ON L4W 3P1, Canada",
				"statusCode": 200,
				"statusDescription": "OK",
				"traceId": "98cda41588e14ffca9718f8fa3ca4b5c|BN20121762|7.7.0.0|",
				"addressLine": "1045 Matheson Blvd E",
				"adminDistrict": "ON",
				"adminDistrict2": "Peel",
				"countryRegion": "Canada",
				"formattedAddress": "1045 Matheson Blvd E, Mississauga, ON L4W 3P1, Canada",
				"locality": "Mississauga",
				"neighborhood": "Dixie",
				"postalCode": "L4W 3P1"
			},
			"geometry": {
				"type": "Point",
				"coordinates": [
					-79.6395299,
					43.6337199
				]
			},
			"bbox": [
				-79.6410831,
				43.6325957,
				-79.6379767,
				43.6348441
			]
		}
	]
}
