{
	"type": "FeatureCollection",
	"features": [
		{
			"type": "Feature",
			"properties": {
				"confidence": 9,
				"authenticationResultCode": "ValidCredentials",
				"brandLogoUri": "http://dev.virtualearth.net/Branding/logo_powered_by.png",
				"copyright": "Copyright © 2017 Microsoft and its suppliers. All rights reserved. This API cannot be accessed and the content and any results may not be used, reproduced or transmitted in any manner without express written permission from Microsoft Corporation.",
				"entityType": "Address",
				"matchCodes": [
					"Good"
				],
				"name": "1048 Rue MacDonald, Acton Vale, QC J0H 1A0, Canada",
				"statusCode": 200,
				"statusDescription": "OK",
				"traceId": "fdf228ea768446e7b11b189981312d0e|BN20171457|7.7.0.0|",
				"addressLine": "1048 Rue MacDonald",
				"adminDistrict": "QC",
				"adminDistrict2": "Acton",
				"countryRegion": "Canada",
				"formattedAddress": "1048 Rue MacDonald, Acton Vale, QC J0H 1A0, Canada",
				"locality": "Acton Vale",
				"postalCode": "J0H 1A0"
			},
			"geometry": {
				"type": "Point",
				"coordinates": [
					-72.5653478,
					45.6485717
				]
			},
			"bbox": [
				-72.5669559,
				45.6474475,
				-72.5637397,
				45.6496958
			]
		}
	]
}
