{
	"type": "FeatureCollection",
	"features": [
		{
			"type": "Feature",
			"properties": {
				"confidence": 9,
				"authenticationResultCode": "ValidCredentials",
				"brandLogoUri": "http://dev.virtualearth.net/Branding/logo_powered_by.png",
				"copyright": "Copyright © 2017 Microsoft and its suppliers. All rights reserved. This API cannot be accessed and the content and any results may not be used, reproduced or transmitted in any manner without express written permission from Microsoft Corporation.",
				"entityType": "Address",
				"matchCodes": [
					"Good"
				],
				"name": "105 Combe Ave, North York, ON M3H 4J8, Canada",
				"statusCode": 200,
				"statusDescription": "OK",
				"traceId": "a6966214c08c45d79479dafb49a4d5c4|BN20190653|7.7.0.0|",
				"addressLine": "105 Combe Ave",
				"adminDistrict": "ON",
				"adminDistrict2": "Toronto",
				"countryRegion": "Canada",
				"formattedAddress": "105 Combe Ave, North York, ON M3H 4J8, Canada",
				"locality": "Toronto",
				"neighborhood": "Bathurst Manor",
				"postalCode": "M3H 4J8"
			},
			"geometry": {
				"type": "Point",
				"coordinates": [
					-79.45406,
					43.7597499
				]
			},
			"bbox": [
				-79.4556165,
				43.7586257,
				-79.4525035,
				43.7608741
			]
		}
	]
}
