{
	"type": "FeatureCollection",
	"features": [
		{
			"type": "Feature",
			"properties": {
				"confidence": 9,
				"authenticationResultCode": "ValidCredentials",
				"brandLogoUri": "http://dev.virtualearth.net/Branding/logo_powered_by.png",
				"copyright": "Copyright © 2017 Microsoft and its suppliers. All rights reserved. This API cannot be accessed and the content and any results may not be used, reproduced or transmitted in any manner without express written permission from Microsoft Corporation.",
				"entityType": "Address",
				"matchCodes": [
					"Good"
				],
				"name": "105 Avenue Renaud, Laurierville, QC G0S, Canada",
				"statusCode": 200,
				"statusDescription": "OK",
				"traceId": "38847c9ed01749f38a99fcd38666cc54|BN20121763|7.7.0.0|",
				"addressLine": "105 Avenue Renaud",
				"adminDistrict": "QC",
				"adminDistrict2": "L'Érable",
				"countryRegion": "Canada",
				"formattedAddress": "105 Avenue Renaud, Laurierville, QC G0S, Canada",
				"locality": "Laurierville",
				"postalCode": "G0S 1P0"
			},
			"geometry": {
				"type": "Point",
				"coordinates": [
					-71.65531,
					46.30106
				]
			},
			"bbox": [
				-71.6569372,
				46.2999358,
				-71.6536828,
				46.3021842
			]
		}
	]
}
