{
	"type": "FeatureCollection",
	"features": [
		{
			"type": "Feature",
			"properties": {
				"confidence": 9,
				"authenticationResultCode": "ValidCredentials",
				"brandLogoUri": "http://dev.virtualearth.net/Branding/logo_powered_by.png",
				"copyright": "Copyright © 2017 Microsoft and its suppliers. All rights reserved. This API cannot be accessed and the content and any results may not be used, reproduced or transmitted in any manner without express written permission from Microsoft Corporation.",
				"entityType": "Address",
				"matchCodes": [
					"Good"
				],
				"name": "105 Father Tobin Rd, Brampton, ON L6R 0W9, Canada",
				"statusCode": 200,
				"statusDescription": "OK",
				"traceId": "bf4268301cf4476c89315777b7b0c164|BN20220145|7.7.0.0|",
				"addressLine": "105 Father Tobin Rd",
				"adminDistrict": "ON",
				"adminDistrict2": "Peel",
				"countryRegion": "Canada",
				"formattedAddress": "105 Father Tobin Rd, Brampton, ON L6R 0W9, Canada",
				"locality": "Brampton",
				"neighborhood": "Springdale",
				"postalCode": "L6R 0W9"
			},
			"geometry": {
				"type": "Point",
				"coordinates": [
					-79.7554847,
					43.7715047
				]
			},
			"bbox": [
				-79.7570414,
				43.7703806,
				-79.7539279,
				43.7726289
			]
		}
	]
}
