{
	"type": "FeatureCollection",
	"features": [
		{
			"type": "Feature",
			"properties": {
				"confidence": 9,
				"authenticationResultCode": "ValidCredentials",
				"brandLogoUri": "http://dev.virtualearth.net/Branding/logo_powered_by.png",
				"copyright": "Copyright © 2017 Microsoft and its suppliers. All rights reserved. This API cannot be accessed and the content and any results may not be used, reproduced or transmitted in any manner without express written permission from Microsoft Corporation.",
				"entityType": "Address",
				"matchCodes": [
					"Good"
				],
				"name": "1050 Delta Ave S, Burnaby, BC V5B 3G1, Canada",
				"statusCode": 200,
				"statusDescription": "OK",
				"traceId": "899f200df4aa42699cc3444276261c4b|BN20130522|7.7.0.0|",
				"addressLine": "1050 Delta Ave S",
				"adminDistrict": "BC",
				"adminDistrict2": "Greater Vancouver",
				"countryRegion": "Canada",
				"formattedAddress": "1050 Delta Ave S, Burnaby, BC V5B 3G1, Canada",
				"locality": "Burnaby",
				"neighborhood": "Brentwood",
				"postalCode": "V5B 3G1"
			},
			"geometry": {
				"type": "Point",
				"coordinates": [
					-122.9918845,
					49.2749334
				]
			},
			"bbox": [
				-122.9936075,
				49.2738092,
				-122.9901614,
				49.2760575
			]
		}
	]
}
