{
	"type": "FeatureCollection",
	"features": [
		{
			"type": "Feature",
			"properties": {
				"confidence": 9,
				"authenticationResultCode": "ValidCredentials",
				"brandLogoUri": "http://dev.virtualearth.net/Branding/logo_powered_by.png",
				"copyright": "Copyright © 2017 Microsoft and its suppliers. All rights reserved. This API cannot be accessed and the content and any results may not be used, reproduced or transmitted in any manner without express written permission from Microsoft Corporation.",
				"entityType": "Address",
				"matchCodes": [
					"Good"
				],
				"name": "10506 98 Ave, Grande Prairie, AB T8V 4K3, Canada",
				"statusCode": 200,
				"statusDescription": "OK",
				"traceId": "94f7ba3ee4ae47bb96fda11116919690|BN20130521|7.7.0.0|",
				"addressLine": "10506 98 Ave",
				"adminDistrict": "AB",
				"adminDistrict2": "Alberta",
				"countryRegion": "Canada",
				"formattedAddress": "10506 98 Ave, Grande Prairie, AB T8V 4K3, Canada",
				"locality": "Grande Prairie",
				"neighborhood": "Westside Park",
				"postalCode": "T8V 4K3"
			},
			"geometry": {
				"type": "Point",
				"coordinates": [
					-118.81238,
					55.16895
				]
			},
			"bbox": [
				-118.8143482,
				55.1678258,
				-118.8104118,
				55.1700742
			]
		}
	]
}
