{
	"type": "FeatureCollection",
	"features": [
		{
			"type": "Feature",
			"properties": {
				"confidence": 9,
				"authenticationResultCode": "ValidCredentials",
				"brandLogoUri": "http://dev.virtualearth.net/Branding/logo_powered_by.png",
				"copyright": "Copyright © 2017 Microsoft and its suppliers. All rights reserved. This API cannot be accessed and the content and any results may not be used, reproduced or transmitted in any manner without express written permission from Microsoft Corporation.",
				"entityType": "Address",
				"matchCodes": [
					"Good"
				],
				"name": "1055 Aviation Ave, Dieppe, NB E1A 9S5, Canada",
				"statusCode": 200,
				"statusDescription": "OK",
				"traceId": "103f4d3048f345ae84f5a69b546913fd|BN20181720|7.7.0.0|",
				"addressLine": "1055 Aviation Ave",
				"adminDistrict": "NB",
				"adminDistrict2": "Westmorland",
				"countryRegion": "Canada",
				"formattedAddress": "1055 Aviation Ave, Dieppe, NB E1A 9S5, Canada",
				"locality": "Dieppe",
				"postalCode": "E1A 9S5"
			},
			"geometry": {
				"type": "Point",
				"coordinates": [
					-64.6826977,
					46.1232676
				]
			},
			"bbox": [
				-64.6843196,
				46.1221434,
				-64.6810758,
				46.1243917
			]
		}
	]
}
