{
	"type": "FeatureCollection",
	"features": [
		{
			"type": "Feature",
			"properties": {
				"confidence": 7,
				"authenticationResultCode": "ValidCredentials",
				"brandLogoUri": "http://dev.virtualearth.net/Branding/logo_powered_by.png",
				"copyright": "Copyright © 2017 Microsoft and its suppliers. All rights reserved. This API cannot be accessed and the content and any results may not be used, reproduced or transmitted in any manner without express written permission from Microsoft Corporation.",
				"entityType": "Postcode1",
				"matchCodes": [
					"UpHierarchy"
				],
				"name": "Salluit, J0M 1S0, Canada",
				"statusCode": 200,
				"statusDescription": "OK",
				"traceId": "e035aeee3bf9439f838df1496e3a7ff3|BN20190653|7.7.0.0|",
				"adminDistrict": "QC",
				"adminDistrict2": "Kativik",
				"countryRegion": "Canada",
				"formattedAddress": "Salluit, J0M 1S0, Canada",
				"locality": "Salluit",
				"postalCode": "J0M 1S0"
			},
			"geometry": {
				"type": "Point",
				"coordinates": [
					-75.6426010131836,
					62.2052001953125
				]
			},
			"bbox": [
				-75.6536444645085,
				62.2013374777418,
				-75.6315575618587,
				62.2090629128832
			]
		}
	]
}
