{
	"type": "FeatureCollection",
	"features": [
		{
			"type": "Feature",
			"properties": {
				"confidence": 9,
				"authenticationResultCode": "ValidCredentials",
				"brandLogoUri": "http://dev.virtualearth.net/Branding/logo_powered_by.png",
				"copyright": "Copyright © 2017 Microsoft and its suppliers. All rights reserved. This API cannot be accessed and the content and any results may not be used, reproduced or transmitted in any manner without express written permission from Microsoft Corporation.",
				"entityType": "Address",
				"matchCodes": [
					"Good"
				],
				"name": "10575 108 St NW, Edmonton, AB T5H 2Z8, Canada",
				"statusCode": 200,
				"statusDescription": "OK",
				"traceId": "64f521a4a3f04b14b558050e21cc4f9c|BN20260231|7.7.0.0|",
				"addressLine": "10575 108 St NW",
				"adminDistrict": "AB",
				"adminDistrict2": "Alberta",
				"countryRegion": "Canada",
				"formattedAddress": "10575 108 St NW, Edmonton, AB T5H 2Z8, Canada",
				"locality": "Edmonton",
				"neighborhood": "Central McDougall",
				"postalCode": "T5H 2Z8"
			},
			"geometry": {
				"type": "Point",
				"coordinates": [
					-113.50604,
					53.54937
				]
			},
			"bbox": [
				-113.5079321,
				53.5482458,
				-113.5041479,
				53.5504942
			]
		}
	]
}
