{
	"type": "FeatureCollection",
	"features": [
		{
			"type": "Feature",
			"properties": {
				"confidence": 9,
				"authenticationResultCode": "ValidCredentials",
				"brandLogoUri": "http://dev.virtualearth.net/Branding/logo_powered_by.png",
				"copyright": "Copyright © 2017 Microsoft and its suppliers. All rights reserved. This API cannot be accessed and the content and any results may not be used, reproduced or transmitted in any manner without express written permission from Microsoft Corporation.",
				"entityType": "Address",
				"matchCodes": [
					"Good"
				],
				"name": "106 Ridgetop Rd, Scarborough, ON M1P 2J9, Canada",
				"statusCode": 200,
				"statusDescription": "OK",
				"traceId": "1a714d90bd4449caa288f1797ace3874|BN20130442|7.7.0.0|",
				"addressLine": "106 Ridgetop Rd",
				"adminDistrict": "ON",
				"adminDistrict2": "Toronto",
				"countryRegion": "Canada",
				"formattedAddress": "106 Ridgetop Rd, Scarborough, ON M1P 2J9, Canada",
				"locality": "Toronto",
				"neighborhood": "Dorset Park",
				"postalCode": "M1P 2J9"
			},
			"geometry": {
				"type": "Point",
				"coordinates": [
					-79.29217,
					43.77087
				]
			},
			"bbox": [
				-79.2937268,
				43.7697458,
				-79.2906132,
				43.7719942
			]
		}
	]
}
