{
	"type": "FeatureCollection",
	"features": [
		{
			"type": "Feature",
			"properties": {
				"confidence": 9,
				"authenticationResultCode": "ValidCredentials",
				"brandLogoUri": "http://dev.virtualearth.net/Branding/logo_powered_by.png",
				"copyright": "Copyright © 2017 Microsoft and its suppliers. All rights reserved. This API cannot be accessed and the content and any results may not be used, reproduced or transmitted in any manner without express written permission from Microsoft Corporation.",
				"entityType": "Address",
				"matchCodes": [
					"Good"
				],
				"name": "1060 Fountain St N, Cambridge, ON N3H, Canada",
				"statusCode": 200,
				"statusDescription": "OK",
				"traceId": "094b0979460b46419142d1909d541019|BN20171457|7.7.0.0|",
				"addressLine": "1060 Fountain St N",
				"adminDistrict": "ON",
				"adminDistrict2": "Waterloo",
				"countryRegion": "Canada",
				"formattedAddress": "1060 Fountain St N, Cambridge, ON N3H, Canada",
				"locality": "Cambridge",
				"postalCode": "N3H"
			},
			"geometry": {
				"type": "Point",
				"coordinates": [
					-80.37664,
					43.4172
				]
			},
			"bbox": [
				-80.3781876,
				43.4160758,
				-80.3750924,
				43.4183242
			]
		}
	]
}
