{
	"type": "FeatureCollection",
	"features": [
		{
			"type": "Feature",
			"properties": {
				"confidence": 9,
				"authenticationResultCode": "ValidCredentials",
				"brandLogoUri": "http://dev.virtualearth.net/Branding/logo_powered_by.png",
				"copyright": "Copyright © 2017 Microsoft and its suppliers. All rights reserved. This API cannot be accessed and the content and any results may not be used, reproduced or transmitted in any manner without express written permission from Microsoft Corporation.",
				"entityType": "Address",
				"matchCodes": [
					"Good"
				],
				"name": "1060 Rue de Cherbourg, Sherbrooke, QC J1K 2N8, Canada",
				"statusCode": 200,
				"statusDescription": "OK",
				"traceId": "46d35b6022d74f7f895a99ee756ea2ae|BN20190653|7.7.0.0|",
				"addressLine": "1060 Rue de Cherbourg",
				"adminDistrict": "QC",
				"adminDistrict2": "Sherbrooke",
				"countryRegion": "Canada",
				"formattedAddress": "1060 Rue de Cherbourg, Sherbrooke, QC J1K 2N8, Canada",
				"locality": "Sherbrooke",
				"postalCode": "J1K 2N8"
			},
			"geometry": {
				"type": "Point",
				"coordinates": [
					-71.92448,
					45.38977
				]
			},
			"bbox": [
				-71.9260807,
				45.3886458,
				-71.9228793,
				45.3908942
			]
		}
	]
}
