{
	"type": "FeatureCollection",
	"features": [
		{
			"type": "Feature",
			"properties": {
				"confidence": 9,
				"authenticationResultCode": "ValidCredentials",
				"brandLogoUri": "http://dev.virtualearth.net/Branding/logo_powered_by.png",
				"copyright": "Copyright © 2017 Microsoft and its suppliers. All rights reserved. This API cannot be accessed and the content and any results may not be used, reproduced or transmitted in any manner without express written permission from Microsoft Corporation.",
				"entityType": "Address",
				"matchCodes": [
					"Good"
				],
				"name": "10646 178 St NW, Edmonton, AB T5S 1H4, Canada",
				"statusCode": 200,
				"statusDescription": "OK",
				"traceId": "51dfff9b25b8469e9b06a96e670a1d61|BN20240253|7.7.0.0|",
				"addressLine": "10646 178 St NW",
				"adminDistrict": "AB",
				"adminDistrict2": "Alberta",
				"countryRegion": "Canada",
				"formattedAddress": "10646 178 St NW, Edmonton, AB T5S 1H4, Canada",
				"locality": "Edmonton",
				"neighborhood": "Wilson Industrial",
				"postalCode": "T5S 1H4"
			},
			"geometry": {
				"type": "Point",
				"coordinates": [
					-113.6282,
					53.5523499
				]
			},
			"bbox": [
				-113.6300922,
				53.5512257,
				-113.6263078,
				53.5534741
			]
		}
	]
}
