{
	"type": "FeatureCollection",
	"features": [
		{
			"type": "Feature",
			"properties": {
				"confidence": 9,
				"authenticationResultCode": "ValidCredentials",
				"brandLogoUri": "http://dev.virtualearth.net/Branding/logo_powered_by.png",
				"copyright": "Copyright © 2017 Microsoft and its suppliers. All rights reserved. This API cannot be accessed and the content and any results may not be used, reproduced or transmitted in any manner without express written permission from Microsoft Corporation.",
				"entityType": "Address",
				"matchCodes": [
					"Good"
				],
				"name": "1065 Barclay St, Vancouver, BC V6E 1G5, Canada",
				"statusCode": 200,
				"statusDescription": "OK",
				"traceId": "6a7d5c106d404cfbbe1d040118342c10|BN20250135|7.7.0.0|",
				"addressLine": "1065 Barclay St",
				"adminDistrict": "BC",
				"adminDistrict2": "Greater Vancouver",
				"countryRegion": "Canada",
				"formattedAddress": "1065 Barclay St, Vancouver, BC V6E 1G5, Canada",
				"locality": "Vancouver",
				"neighborhood": "West End",
				"postalCode": "V6E 1G5"
			},
			"geometry": {
				"type": "Point",
				"coordinates": [
					-123.1263873,
					49.2830082
				]
			},
			"bbox": [
				-123.1281106,
				49.2818841,
				-123.124664,
				49.2841324
			]
		}
	]
}
