{
	"type": "FeatureCollection",
	"features": [
		{
			"type": "Feature",
			"properties": {
				"confidence": 9,
				"authenticationResultCode": "ValidCredentials",
				"brandLogoUri": "http://dev.virtualearth.net/Branding/logo_powered_by.png",
				"copyright": "Copyright © 2017 Microsoft and its suppliers. All rights reserved. This API cannot be accessed and the content and any results may not be used, reproduced or transmitted in any manner without express written permission from Microsoft Corporation.",
				"entityType": "Address",
				"matchCodes": [
					"Good"
				],
				"name": "107 Grenadier Way, Nepean, ON K2J 4L6, Canada",
				"statusCode": 200,
				"statusDescription": "OK",
				"traceId": "e31726a899cb4ecf8371d7fa15acce3b|BN20130631|7.7.0.0|",
				"addressLine": "107 Grenadier Way",
				"adminDistrict": "ON",
				"adminDistrict2": "Ottawa",
				"countryRegion": "Canada",
				"formattedAddress": "107 Grenadier Way, Nepean, ON K2J 4L6, Canada",
				"locality": "Ottawa",
				"neighborhood": "Nepean",
				"postalCode": "K2J 4L6"
			},
			"geometry": {
				"type": "Point",
				"coordinates": [
					-75.72501,
					45.28178
				]
			},
			"bbox": [
				-75.7266077,
				45.2806558,
				-75.7234123,
				45.2829042
			]
		}
	]
}
