{
	"type": "FeatureCollection",
	"features": [
		{
			"type": "Feature",
			"properties": {
				"confidence": 9,
				"authenticationResultCode": "ValidCredentials",
				"brandLogoUri": "http://dev.virtualearth.net/Branding/logo_powered_by.png",
				"copyright": "Copyright © 2017 Microsoft and its suppliers. All rights reserved. This API cannot be accessed and the content and any results may not be used, reproduced or transmitted in any manner without express written permission from Microsoft Corporation.",
				"entityType": "Address",
				"matchCodes": [
					"Good"
				],
				"name": "1070 Main St W, Hamilton, ON L8S 1B4, Canada",
				"statusCode": 200,
				"statusDescription": "OK",
				"traceId": "8373d5bce6f8455bb9c1398d4221f6b1|BN20130533|7.7.0.0|",
				"addressLine": "1070 Main St W",
				"adminDistrict": "ON",
				"adminDistrict2": "Hamilton",
				"countryRegion": "Canada",
				"formattedAddress": "1070 Main St W, Hamilton, ON L8S 1B4, Canada",
				"locality": "Hamilton",
				"neighborhood": "Westdale South",
				"postalCode": "L8S 1B4"
			},
			"geometry": {
				"type": "Point",
				"coordinates": [
					-79.90895,
					43.25853
				]
			},
			"bbox": [
				-79.9104936,
				43.2574058,
				-79.9074064,
				43.2596542
			]
		}
	]
}
