{
	"type": "FeatureCollection",
	"features": [
		{
			"type": "Feature",
			"properties": {
				"confidence": 9,
				"authenticationResultCode": "ValidCredentials",
				"brandLogoUri": "http://dev.virtualearth.net/Branding/logo_powered_by.png",
				"copyright": "Copyright © 2017 Microsoft and its suppliers. All rights reserved. This API cannot be accessed and the content and any results may not be used, reproduced or transmitted in any manner without express written permission from Microsoft Corporation.",
				"entityType": "Address",
				"matchCodes": [
					"Good"
				],
				"name": "10708 181 St NW, Edmonton, AB T5S 1K8, Canada",
				"statusCode": 200,
				"statusDescription": "OK",
				"traceId": "5cb9fe714ff743bb9006c226b1cb1689|BN20130422|7.7.0.0|",
				"addressLine": "10708 181 St NW",
				"adminDistrict": "AB",
				"adminDistrict2": "Alberta",
				"countryRegion": "Canada",
				"formattedAddress": "10708 181 St NW, Edmonton, AB T5S 1K8, Canada",
				"locality": "Edmonton",
				"neighborhood": "Wilson Industrial",
				"postalCode": "T5S 1K8"
			},
			"geometry": {
				"type": "Point",
				"coordinates": [
					-113.63346,
					53.55366
				]
			},
			"bbox": [
				-113.6353523,
				53.5525358,
				-113.6315677,
				53.5547842
			]
		}
	]
}
