{
	"type": "FeatureCollection",
	"features": [
		{
			"type": "Feature",
			"properties": {
				"confidence": 9,
				"authenticationResultCode": "ValidCredentials",
				"brandLogoUri": "http://dev.virtualearth.net/Branding/logo_powered_by.png",
				"copyright": "Copyright © 2017 Microsoft and its suppliers. All rights reserved. This API cannot be accessed and the content and any results may not be used, reproduced or transmitted in any manner without express written permission from Microsoft Corporation.",
				"entityType": "Address",
				"matchCodes": [
					"Good"
				],
				"name": "1070 Rue King O, Sherbrooke, QC J1H 1S2, Canada",
				"statusCode": 200,
				"statusDescription": "OK",
				"traceId": "f389a8ce29a64990a6d93d8eadd5e116|BN20250135|7.7.0.0|",
				"addressLine": "1070 Rue King O",
				"adminDistrict": "QC",
				"adminDistrict2": "Sherbrooke",
				"countryRegion": "Canada",
				"formattedAddress": "1070 Rue King O, Sherbrooke, QC J1H 1S2, Canada",
				"locality": "Sherbrooke",
				"postalCode": "J1H 1S2"
			},
			"geometry": {
				"type": "Point",
				"coordinates": [
					-71.9044843,
					45.3987451
				]
			},
			"bbox": [
				-71.9060852,
				45.3976209,
				-71.9028833,
				45.3998693
			]
		}
	]
}
