{
	"type": "FeatureCollection",
	"features": [
		{
			"type": "Feature",
			"properties": {
				"confidence": 9,
				"authenticationResultCode": "ValidCredentials",
				"brandLogoUri": "http://dev.virtualearth.net/Branding/logo_powered_by.png",
				"copyright": "Copyright © 2017 Microsoft and its suppliers. All rights reserved. This API cannot be accessed and the content and any results may not be used, reproduced or transmitted in any manner without express written permission from Microsoft Corporation.",
				"entityType": "Address",
				"matchCodes": [
					"Good"
				],
				"name": "1076 Lakeshore Rd E, Mississauga, ON L5E 1E4, Canada",
				"statusCode": 200,
				"statusDescription": "OK",
				"traceId": "9dd7e54cff7f46d8a4d789da8c33bc68|BN20300154|7.7.0.0|",
				"addressLine": "1076 Lakeshore Rd E",
				"adminDistrict": "ON",
				"adminDistrict2": "Peel",
				"countryRegion": "Canada",
				"formattedAddress": "1076 Lakeshore Rd E, Mississauga, ON L5E 1E4, Canada",
				"locality": "Mississauga",
				"neighborhood": "Lakeview",
				"postalCode": "L5E 1E4"
			},
			"geometry": {
				"type": "Point",
				"coordinates": [
					-79.5566599,
					43.57758
				]
			},
			"bbox": [
				-79.5582116,
				43.5764558,
				-79.5551082,
				43.5787042
			]
		}
	]
}
