{
	"type": "FeatureCollection",
	"features": [
		{
			"type": "Feature",
			"properties": {
				"confidence": 9,
				"authenticationResultCode": "ValidCredentials",
				"brandLogoUri": "http://dev.virtualearth.net/Branding/logo_powered_by.png",
				"copyright": "Copyright © 2017 Microsoft and its suppliers. All rights reserved. This API cannot be accessed and the content and any results may not be used, reproduced or transmitted in any manner without express written permission from Microsoft Corporation.",
				"entityType": "Address",
				"matchCodes": [
					"Good"
				],
				"name": "1076 Rue Agincourt, Greenfield Park, QC J4V 1A2, Canada",
				"statusCode": 200,
				"statusDescription": "OK",
				"traceId": "e9586069e38d423a819a1c26b1951562|BN20130632|7.7.0.0|",
				"addressLine": "1076 Rue Agincourt",
				"adminDistrict": "QC",
				"adminDistrict2": "Longueuil",
				"countryRegion": "Canada",
				"formattedAddress": "1076 Rue Agincourt, Greenfield Park, QC J4V 1A2, Canada",
				"locality": "Longueuil",
				"neighborhood": "Greenfield Park",
				"postalCode": "J4V 1A2"
			},
			"geometry": {
				"type": "Point",
				"coordinates": [
					-73.45423,
					45.48297
				]
			},
			"bbox": [
				-73.4558334,
				45.4818458,
				-73.4526266,
				45.4840942
			]
		}
	]
}
