{
	"type": "FeatureCollection",
	"features": [
		{
			"type": "Feature",
			"properties": {
				"confidence": 9,
				"authenticationResultCode": "ValidCredentials",
				"brandLogoUri": "http://dev.virtualearth.net/Branding/logo_powered_by.png",
				"copyright": "Copyright © 2017 Microsoft and its suppliers. All rights reserved. This API cannot be accessed and the content and any results may not be used, reproduced or transmitted in any manner without express written permission from Microsoft Corporation.",
				"entityType": "Address",
				"matchCodes": [
					"Good"
				],
				"name": "1077 Oxford St, Springfield, MB R0E, Canada",
				"statusCode": 200,
				"statusDescription": "OK",
				"traceId": "8d4b40c4848b4ef68b04f306dab7cb40|BN20240253|7.7.0.0|",
				"addressLine": "1077 Oxford St",
				"adminDistrict": "MB",
				"adminDistrict2": "Manitoba",
				"countryRegion": "Canada",
				"formattedAddress": "1077 Oxford St, Springfield, MB R0E, Canada",
				"locality": "Springfield",
				"postalCode": "R0E"
			},
			"geometry": {
				"type": "Point",
				"coordinates": [
					-97.0019575,
					49.9286827
				]
			},
			"bbox": [
				-97.0037038,
				49.9275585,
				-97.0002112,
				49.9298068
			]
		}
	]
}
