{
	"type": "FeatureCollection",
	"features": [
		{
			"type": "Feature",
			"properties": {
				"confidence": 9,
				"authenticationResultCode": "ValidCredentials",
				"brandLogoUri": "http://dev.virtualearth.net/Branding/logo_powered_by.png",
				"copyright": "Copyright © 2017 Microsoft and its suppliers. All rights reserved. This API cannot be accessed and the content and any results may not be used, reproduced or transmitted in any manner without express written permission from Microsoft Corporation.",
				"entityType": "Address",
				"matchCodes": [
					"Good"
				],
				"name": "107 Main St N, Dauphin, MB R7N 1C1, Canada",
				"statusCode": 200,
				"statusDescription": "OK",
				"traceId": "a3c5548a967e4237ae30876a71a2bfb7|BN20130532|7.7.0.0|",
				"addressLine": "107 Main St N",
				"adminDistrict": "MB",
				"adminDistrict2": "Manitoba",
				"countryRegion": "Canada",
				"formattedAddress": "107 Main St N, Dauphin, MB R7N 1C1, Canada",
				"locality": "Dauphin",
				"postalCode": "R7N 1C1"
			},
			"geometry": {
				"type": "Point",
				"coordinates": [
					-100.04994,
					51.15007
				]
			},
			"bbox": [
				-100.0517321,
				51.1489458,
				-100.0481479,
				51.1511942
			]
		}
	]
}
