{
	"type": "FeatureCollection",
	"features": [
		{
			"type": "Feature",
			"properties": {
				"confidence": 7,
				"authenticationResultCode": "ValidCredentials",
				"brandLogoUri": "http://dev.virtualearth.net/Branding/logo_powered_by.png",
				"copyright": "Copyright © 2017 Microsoft and its suppliers. All rights reserved. This API cannot be accessed and the content and any results may not be used, reproduced or transmitted in any manner without express written permission from Microsoft Corporation.",
				"entityType": "RoadBlock",
				"matchCodes": [
					"UpHierarchy"
				],
				"name": "Exmouth St, Sarnia, ON N7T 5M3, Canada",
				"statusCode": 200,
				"statusDescription": "OK",
				"traceId": "66ca7ef7ffc749078b84d08f92a28ba9|BN20200137|7.7.0.0|",
				"addressLine": "Exmouth St",
				"adminDistrict": "ON",
				"adminDistrict2": "Lambton",
				"countryRegion": "Canada",
				"formattedAddress": "Exmouth St, Sarnia, ON N7T 5M3, Canada",
				"locality": "Sarnia",
				"postalCode": "N7T 5M3"
			},
			"geometry": {
				"type": "Point",
				"coordinates": [
					-82.40322,
					42.98568
				]
			},
			"bbox": [
				-82.416,
				42.98501,
				-82.37579,
				42.98599
			]
		}
	]
}
