{
	"type": "FeatureCollection",
	"features": [
		{
			"type": "Feature",
			"properties": {
				"confidence": 9,
				"authenticationResultCode": "ValidCredentials",
				"brandLogoUri": "http://dev.virtualearth.net/Branding/logo_powered_by.png",
				"copyright": "Copyright © 2017 Microsoft and its suppliers. All rights reserved. This API cannot be accessed and the content and any results may not be used, reproduced or transmitted in any manner without express written permission from Microsoft Corporation.",
				"entityType": "Address",
				"matchCodes": [
					"Good"
				],
				"name": "108 Whalings Cir, Stittsville, ON K2S 1S4, Canada",
				"statusCode": 200,
				"statusDescription": "OK",
				"traceId": "156b2151a1034711bb63cc8917921805|BN20280152|7.7.0.0|",
				"addressLine": "108 Whalings Cir",
				"adminDistrict": "ON",
				"adminDistrict2": "Ottawa",
				"countryRegion": "Canada",
				"formattedAddress": "108 Whalings Cir, Stittsville, ON K2S 1S4, Canada",
				"locality": "Ottawa",
				"neighborhood": "Stittsville",
				"postalCode": "K2S 1S4"
			},
			"geometry": {
				"type": "Point",
				"coordinates": [
					-75.94282,
					45.26121
				]
			},
			"bbox": [
				-75.9444171,
				45.2600858,
				-75.9412229,
				45.2623342
			]
		}
	]
}
