{
	"type": "FeatureCollection",
	"features": [
		{
			"type": "Feature",
			"properties": {
				"confidence": 9,
				"authenticationResultCode": "ValidCredentials",
				"brandLogoUri": "http://dev.virtualearth.net/Branding/logo_powered_by.png",
				"copyright": "Copyright © 2017 Microsoft and its suppliers. All rights reserved. This API cannot be accessed and the content and any results may not be used, reproduced or transmitted in any manner without express written permission from Microsoft Corporation.",
				"entityType": "Address",
				"matchCodes": [
					"Good"
				],
				"name": "108 Rue Corbeil, Gatineau, QC J8Y 5X5, Canada",
				"statusCode": 200,
				"statusDescription": "OK",
				"traceId": "e60eefaed7aa4beb9f9f037f43fbcfa6|BN20130521|7.7.0.0|",
				"addressLine": "108 Rue Corbeil",
				"adminDistrict": "QC",
				"adminDistrict2": "Gatineau",
				"countryRegion": "Canada",
				"formattedAddress": "108 Rue Corbeil, Gatineau, QC J8Y 5X5, Canada",
				"locality": "Gatineau",
				"neighborhood": "Hull",
				"postalCode": "J8Y 5X5"
			},
			"geometry": {
				"type": "Point",
				"coordinates": [
					-75.75064,
					45.45523
				]
			},
			"bbox": [
				-75.7522426,
				45.4541058,
				-75.7490374,
				45.4563542
			]
		}
	]
}
