{
	"type": "FeatureCollection",
	"features": [
		{
			"type": "Feature",
			"properties": {
				"confidence": 9,
				"authenticationResultCode": "ValidCredentials",
				"brandLogoUri": "http://dev.virtualearth.net/Branding/logo_powered_by.png",
				"copyright": "Copyright © 2017 Microsoft and its suppliers. All rights reserved. This API cannot be accessed and the content and any results may not be used, reproduced or transmitted in any manner without express written permission from Microsoft Corporation.",
				"entityType": "Address",
				"matchCodes": [
					"Good"
				],
				"name": "10901 100 Ave, Grande Prairie, AB T8V 3J9, Canada",
				"statusCode": 200,
				"statusDescription": "OK",
				"traceId": "ee8a7fa22d3241ae97b30376989eb6d4|BN20130632|7.7.0.0|",
				"addressLine": "10901 100 Ave",
				"adminDistrict": "AB",
				"adminDistrict2": "Alberta",
				"countryRegion": "Canada",
				"formattedAddress": "10901 100 Ave, Grande Prairie, AB T8V 3J9, Canada",
				"locality": "Grande Prairie",
				"neighborhood": "Richmond Industrial Park",
				"postalCode": "T8V 3J9"
			},
			"geometry": {
				"type": "Point",
				"coordinates": [
					-118.8212314,
					55.1701551
				]
			},
			"bbox": [
				-118.8231996,
				55.169031,
				-118.8192631,
				55.1712793
			]
		}
	]
}
