{
	"type": "FeatureCollection",
	"features": [
		{
			"type": "Feature",
			"properties": {
				"confidence": 9,
				"authenticationResultCode": "ValidCredentials",
				"brandLogoUri": "http://dev.virtualearth.net/Branding/logo_powered_by.png",
				"copyright": "Copyright © 2017 Microsoft and its suppliers. All rights reserved. This API cannot be accessed and the content and any results may not be used, reproduced or transmitted in any manner without express written permission from Microsoft Corporation.",
				"entityType": "Address",
				"matchCodes": [
					"Good"
				],
				"name": "1093 Dundas St W, Mississauga, ON L5C 1C4, Canada",
				"statusCode": 200,
				"statusDescription": "OK",
				"traceId": "1a84e26ea5ab401daf2b633b9671829d|BN20300154|7.7.0.0|",
				"addressLine": "1093 Dundas St W",
				"adminDistrict": "ON",
				"adminDistrict2": "Peel",
				"countryRegion": "Canada",
				"formattedAddress": "1093 Dundas St W, Mississauga, ON L5C 1C4, Canada",
				"locality": "Mississauga",
				"neighborhood": "Erindale",
				"postalCode": "L5C 1C4"
			},
			"geometry": {
				"type": "Point",
				"coordinates": [
					-79.6433799,
					43.5574
				]
			},
			"bbox": [
				-79.6449311,
				43.5562758,
				-79.6418287,
				43.5585242
			]
		}
	]
}
