{
	"type": "FeatureCollection",
	"features": [
		{
			"type": "Feature",
			"properties": {
				"confidence": 9,
				"authenticationResultCode": "ValidCredentials",
				"brandLogoUri": "http://dev.virtualearth.net/Branding/logo_powered_by.png",
				"copyright": "Copyright © 2017 Microsoft and its suppliers. All rights reserved. This API cannot be accessed and the content and any results may not be used, reproduced or transmitted in any manner without express written permission from Microsoft Corporation.",
				"entityType": "Address",
				"matchCodes": [
					"Good"
				],
				"name": "11 Aviation Ave, Charlottetown, PE C1E 0A1, Canada",
				"statusCode": 200,
				"statusDescription": "OK",
				"traceId": "aad34c3fd28340baba3d4f4e8005a785|BN20300154|7.7.0.0|",
				"addressLine": "11 Aviation Ave",
				"adminDistrict": "PE",
				"adminDistrict2": "Queens",
				"countryRegion": "Canada",
				"formattedAddress": "11 Aviation Ave, Charlottetown, PE C1E 0A1, Canada",
				"locality": "Charlottetown",
				"postalCode": "C1E 0A1"
			},
			"geometry": {
				"type": "Point",
				"coordinates": [
					-63.1332,
					46.28925
				]
			},
			"bbox": [
				-63.1348268,
				46.2881258,
				-63.1315732,
				46.2903742
			]
		}
	]
}
