{
	"type": "FeatureCollection",
	"features": [
		{
			"type": "Feature",
			"properties": {
				"confidence": 9,
				"authenticationResultCode": "ValidCredentials",
				"brandLogoUri": "http://dev.virtualearth.net/Branding/logo_powered_by.png",
				"copyright": "Copyright © 2017 Microsoft and its suppliers. All rights reserved. This API cannot be accessed and the content and any results may not be used, reproduced or transmitted in any manner without express written permission from Microsoft Corporation.",
				"entityType": "Address",
				"matchCodes": [
					"Good"
				],
				"name": "11 Dohme Ave, East York, ON M4B 1Y7, Canada",
				"statusCode": 200,
				"statusDescription": "OK",
				"traceId": "cda1070827624f16b1f0b06360d6b737|BN20130533|7.7.0.0|",
				"addressLine": "11 Dohme Ave",
				"adminDistrict": "ON",
				"adminDistrict2": "Toronto",
				"countryRegion": "Canada",
				"formattedAddress": "11 Dohme Ave, East York, ON M4B 1Y7, Canada",
				"locality": "Toronto",
				"neighborhood": "O'Connor-Parkview",
				"postalCode": "M4B 1Y7"
			},
			"geometry": {
				"type": "Point",
				"coordinates": [
					-79.31186,
					43.71137
				]
			},
			"bbox": [
				-79.3134152,
				43.7102458,
				-79.3103048,
				43.7124942
			]
		}
	]
}
