{
	"type": "FeatureCollection",
	"features": [
		{
			"type": "Feature",
			"properties": {
				"confidence": 9,
				"authenticationResultCode": "ValidCredentials",
				"brandLogoUri": "http://dev.virtualearth.net/Branding/logo_powered_by.png",
				"copyright": "Copyright © 2017 Microsoft and its suppliers. All rights reserved. This API cannot be accessed and the content and any results may not be used, reproduced or transmitted in any manner without express written permission from Microsoft Corporation.",
				"entityType": "Address",
				"matchCodes": [
					"Good"
				],
				"name": "11 Garden Pl, Etobicoke, ON M8W 1M2, Canada",
				"statusCode": 200,
				"statusDescription": "OK",
				"traceId": "8aec354b66ef4cc28bc2d57d0a06ff5c|BN20130719|7.7.0.0|",
				"addressLine": "11 Garden Pl",
				"adminDistrict": "ON",
				"adminDistrict2": "Toronto",
				"countryRegion": "Canada",
				"formattedAddress": "11 Garden Pl, Etobicoke, ON M8W 1M2, Canada",
				"locality": "Toronto",
				"neighborhood": "Long Branch",
				"postalCode": "M8W 1M2"
			},
			"geometry": {
				"type": "Point",
				"coordinates": [
					-79.54077,
					43.58902
				]
			},
			"bbox": [
				-79.542322,
				43.5878958,
				-79.539218,
				43.5901442
			]
		}
	]
}
