{
	"type": "FeatureCollection",
	"features": [
		{
			"type": "Feature",
			"properties": {
				"confidence": 9,
				"authenticationResultCode": "ValidCredentials",
				"brandLogoUri": "http://dev.virtualearth.net/Branding/logo_powered_by.png",
				"copyright": "Copyright © 2017 Microsoft and its suppliers. All rights reserved. This API cannot be accessed and the content and any results may not be used, reproduced or transmitted in any manner without express written permission from Microsoft Corporation.",
				"entityType": "Address",
				"matchCodes": [
					"Good"
				],
				"name": "11 Snaresbrook Cres, Brampton, ON L6P 4G6, Canada",
				"statusCode": 200,
				"statusDescription": "OK",
				"traceId": "ee2204094f9c4873b2b8bfd57aa1d4c9|BN20280152|7.7.0.0|",
				"addressLine": "11 Snaresbrook Cres",
				"adminDistrict": "ON",
				"adminDistrict2": "Peel",
				"countryRegion": "Canada",
				"formattedAddress": "11 Snaresbrook Cres, Brampton, ON L6P 4G6, Canada",
				"locality": "Brampton",
				"neighborhood": "Castlemore",
				"postalCode": "L6P 4G6"
			},
			"geometry": {
				"type": "Point",
				"coordinates": [
					-79.7328361,
					43.7993856
				]
			},
			"bbox": [
				-79.7343936,
				43.7982614,
				-79.7312786,
				43.8005097
			]
		}
	]
}
