{
	"type": "FeatureCollection",
	"features": [
		{
			"type": "Feature",
			"properties": {
				"confidence": 7,
				"authenticationResultCode": "ValidCredentials",
				"brandLogoUri": "http://dev.virtualearth.net/Branding/logo_powered_by.png",
				"copyright": "Copyright © 2017 Microsoft and its suppliers. All rights reserved. This API cannot be accessed and the content and any results may not be used, reproduced or transmitted in any manner without express written permission from Microsoft Corporation.",
				"entityType": "RoadBlock",
				"matchCodes": [
					"UpHierarchy"
				],
				"name": "Boulevard Parkway, Anjou, QC H1J 1R6, Canada",
				"statusCode": 200,
				"statusDescription": "OK",
				"traceId": "357c35ba1dfd4ad1b415b06a28cb0a91|BN20130520|7.7.0.0|",
				"addressLine": "Boulevard Parkway",
				"adminDistrict": "QC",
				"adminDistrict2": "Montreal",
				"countryRegion": "Canada",
				"formattedAddress": "Boulevard Parkway, Anjou, QC H1J 1R6, Canada",
				"locality": "Montreal",
				"neighborhood": "Anjou",
				"postalCode": "H1J 1R6"
			},
			"geometry": {
				"type": "Point",
				"coordinates": [
					-73.57983,
					45.62067
				]
			},
			"bbox": [
				-73.58322,
				45.61218,
				-73.56035,
				45.62205
			]
		}
	]
}
