{
	"type": "FeatureCollection",
	"features": [
		{
			"type": "Feature",
			"properties": {
				"confidence": 9,
				"authenticationResultCode": "ValidCredentials",
				"brandLogoUri": "http://dev.virtualearth.net/Branding/logo_powered_by.png",
				"copyright": "Copyright © 2017 Microsoft and its suppliers. All rights reserved. This API cannot be accessed and the content and any results may not be used, reproduced or transmitted in any manner without express written permission from Microsoft Corporation.",
				"entityType": "Address",
				"matchCodes": [
					"Good"
				],
				"name": "110 Wheeler St, Saskatoon, SK S7K, Canada",
				"statusCode": 200,
				"statusDescription": "OK",
				"traceId": "573e3b2c71a9493ca90e65bdee02800e|BN20171457|7.7.0.0|",
				"addressLine": "110 Wheeler St",
				"adminDistrict": "SK",
				"adminDistrict2": "Saskatchewan",
				"countryRegion": "Canada",
				"formattedAddress": "110 Wheeler St, Saskatoon, SK S7K, Canada",
				"locality": "Saskatoon",
				"neighborhood": "Marquis Industrial",
				"postalCode": "S7K"
			},
			"geometry": {
				"type": "Point",
				"coordinates": [
					-106.6243,
					52.19211
				]
			},
			"bbox": [
				-106.6261338,
				52.1909858,
				-106.6224662,
				52.1932342
			]
		}
	]
}
