{
	"type": "FeatureCollection",
	"features": [
		{
			"type": "Feature",
			"properties": {
				"confidence": 9,
				"authenticationResultCode": "ValidCredentials",
				"brandLogoUri": "http://dev.virtualearth.net/Branding/logo_powered_by.png",
				"copyright": "Copyright © 2017 Microsoft and its suppliers. All rights reserved. This API cannot be accessed and the content and any results may not be used, reproduced or transmitted in any manner without express written permission from Microsoft Corporation.",
				"entityType": "Address",
				"matchCodes": [
					"Good"
				],
				"name": "110 Bessemer Rd, London, ON N6E 1R2, Canada",
				"statusCode": 200,
				"statusDescription": "OK",
				"traceId": "f4fc52400903462b9246fed9228c9a56|BN20171457|7.7.0.0|",
				"addressLine": "110 Bessemer Rd",
				"adminDistrict": "ON",
				"adminDistrict2": "Middlesex",
				"countryRegion": "Canada",
				"formattedAddress": "110 Bessemer Rd, London, ON N6E 1R2, Canada",
				"locality": "London",
				"neighborhood": "Westminster",
				"postalCode": "N6E 1R2"
			},
			"geometry": {
				"type": "Point",
				"coordinates": [
					-81.2127,
					42.9326
				]
			},
			"bbox": [
				-81.2142354,
				42.9314758,
				-81.2111646,
				42.9337242
			]
		}
	]
}
