{
	"type": "FeatureCollection",
	"features": [
		{
			"type": "Feature",
			"properties": {
				"confidence": 9,
				"authenticationResultCode": "ValidCredentials",
				"brandLogoUri": "http://dev.virtualearth.net/Branding/logo_powered_by.png",
				"copyright": "Copyright © 2017 Microsoft and its suppliers. All rights reserved. This API cannot be accessed and the content and any results may not be used, reproduced or transmitted in any manner without express written permission from Microsoft Corporation.",
				"entityType": "Address",
				"matchCodes": [
					"Good"
				],
				"name": "110 Regent Ave W, Winnipeg, MB R2C 1P9, Canada",
				"statusCode": 200,
				"statusDescription": "OK",
				"traceId": "18e12e345ad74f83831b4af148ad31ac|BN20260223|7.7.0.0|",
				"addressLine": "110 Regent Ave W",
				"adminDistrict": "MB",
				"adminDistrict2": "Manitoba",
				"countryRegion": "Canada",
				"formattedAddress": "110 Regent Ave W, Winnipeg, MB R2C 1P9, Canada",
				"locality": "Winnipeg",
				"neighborhood": "Melrose",
				"postalCode": "R2C 1P9"
			},
			"geometry": {
				"type": "Point",
				"coordinates": [
					-97.00346,
					49.89482
				]
			},
			"bbox": [
				-97.0052051,
				49.8936958,
				-97.0017149,
				49.8959442
			]
		}
	]
}
