{
	"type": "FeatureCollection",
	"features": [
		{
			"type": "Feature",
			"properties": {
				"confidence": 9,
				"authenticationResultCode": "ValidCredentials",
				"brandLogoUri": "http://dev.virtualearth.net/Branding/logo_powered_by.png",
				"copyright": "Copyright © 2017 Microsoft and its suppliers. All rights reserved. This API cannot be accessed and the content and any results may not be used, reproduced or transmitted in any manner without express written permission from Microsoft Corporation.",
				"entityType": "Address",
				"matchCodes": [
					"Good"
				],
				"name": "1103 Whitney Rd, Kemptville, ON K0G 1J0, Canada",
				"statusCode": 200,
				"statusDescription": "OK",
				"traceId": "fdaba5e9371b40a1a461cb7ade0f7177|BN20300154|7.7.0.0|",
				"addressLine": "1103 Whitney Rd",
				"adminDistrict": "ON",
				"adminDistrict2": "Leeds and Grenville",
				"countryRegion": "Canada",
				"formattedAddress": "1103 Whitney Rd, Kemptville, ON K0G 1J0, Canada",
				"locality": "North Grenville",
				"neighborhood": "Kemptville",
				"postalCode": "K0G 1J0"
			},
			"geometry": {
				"type": "Point",
				"coordinates": [
					-75.5862346,
					45.0018679
				]
			},
			"bbox": [
				-75.5878245,
				45.0007438,
				-75.5846448,
				45.0029921
			]
		}
	]
}
