{
	"type": "FeatureCollection",
	"features": [
		{
			"type": "Feature",
			"properties": {
				"confidence": 9,
				"authenticationResultCode": "ValidCredentials",
				"brandLogoUri": "http://dev.virtualearth.net/Branding/logo_powered_by.png",
				"copyright": "Copyright © 2017 Microsoft and its suppliers. All rights reserved. This API cannot be accessed and the content and any results may not be used, reproduced or transmitted in any manner without express written permission from Microsoft Corporation.",
				"entityType": "Address",
				"matchCodes": [
					"Good"
				],
				"name": "1107 8A St, Nisku, AB T9E 7R3, Canada",
				"statusCode": 200,
				"statusDescription": "OK",
				"traceId": "8ab0be2ce7da43b7928eb0a19582b7c7|BN20130719|7.7.0.0|",
				"addressLine": "1107 8A St",
				"adminDistrict": "AB",
				"adminDistrict2": "Alberta",
				"countryRegion": "Canada",
				"formattedAddress": "1107 8A St, Nisku, AB T9E 7R3, Canada",
				"locality": "Leduc County",
				"neighborhood": "Nisku",
				"postalCode": "T9E 7R3"
			},
			"geometry": {
				"type": "Point",
				"coordinates": [
					-113.51422,
					53.31148
				]
			},
			"bbox": [
				-113.5161015,
				53.3103558,
				-113.5123385,
				53.3126042
			]
		}
	]
}
