{
	"type": "FeatureCollection",
	"features": [
		{
			"type": "Feature",
			"properties": {
				"confidence": 9,
				"authenticationResultCode": "ValidCredentials",
				"brandLogoUri": "http://dev.virtualearth.net/Branding/logo_powered_by.png",
				"copyright": "Copyright © 2017 Microsoft and its suppliers. All rights reserved. This API cannot be accessed and the content and any results may not be used, reproduced or transmitted in any manner without express written permission from Microsoft Corporation.",
				"entityType": "Address",
				"matchCodes": [
					"Good"
				],
				"name": "1108 Rue Principale E, St-Paul-d'Abbotsford, QC J0E 1A0, Canada",
				"statusCode": 200,
				"statusDescription": "OK",
				"traceId": "f730ae1a6ca248719a419ad8ad9d32bc|BN20240253|7.7.0.0|",
				"addressLine": "1108 Rue Principale E",
				"adminDistrict": "QC",
				"adminDistrict2": "Rouville",
				"countryRegion": "Canada",
				"formattedAddress": "1108 Rue Principale E, St-Paul-d'Abbotsford, QC J0E 1A0, Canada",
				"locality": "St-Paul-d'Abbotsford",
				"postalCode": "J0E 1A0"
			},
			"geometry": {
				"type": "Point",
				"coordinates": [
					-72.8785,
					45.43603
				]
			},
			"bbox": [
				-72.880102,
				45.4349058,
				-72.876898,
				45.4371542
			]
		}
	]
}
