{
	"type": "FeatureCollection",
	"features": [
		{
			"type": "Feature",
			"properties": {
				"confidence": 9,
				"authenticationResultCode": "ValidCredentials",
				"brandLogoUri": "http://dev.virtualearth.net/Branding/logo_powered_by.png",
				"copyright": "Copyright © 2017 Microsoft and its suppliers. All rights reserved. This API cannot be accessed and the content and any results may not be used, reproduced or transmitted in any manner without express written permission from Microsoft Corporation.",
				"entityType": "Address",
				"matchCodes": [
					"Good"
				],
				"name": "111 Bannister Rd, Winnipeg, MB R2R 0P2, Canada",
				"statusCode": 200,
				"statusDescription": "OK",
				"traceId": "b2535514679244788490f3f15b73d7b0|BN20190642|7.7.0.0|",
				"addressLine": "111 Bannister Rd",
				"adminDistrict": "MB",
				"adminDistrict2": "Manitoba",
				"countryRegion": "Canada",
				"formattedAddress": "111 Bannister Rd, Winnipeg, MB R2R 0P2, Canada",
				"locality": "Winnipeg",
				"neighborhood": "Omand's Creek Industrial",
				"postalCode": "R2R 0P2"
			},
			"geometry": {
				"type": "Point",
				"coordinates": [
					-97.2132,
					49.9234
				]
			},
			"bbox": [
				-97.2149461,
				49.9222758,
				-97.2114539,
				49.9245242
			]
		}
	]
}
