{
	"type": "FeatureCollection",
	"features": [
		{
			"type": "Feature",
			"properties": {
				"confidence": 9,
				"authenticationResultCode": "ValidCredentials",
				"brandLogoUri": "http://dev.virtualearth.net/Branding/logo_powered_by.png",
				"copyright": "Copyright © 2017 Microsoft and its suppliers. All rights reserved. This API cannot be accessed and the content and any results may not be used, reproduced or transmitted in any manner without express written permission from Microsoft Corporation.",
				"entityType": "Address",
				"matchCodes": [
					"Good"
				],
				"name": "111 Davisville Ave, Toronto, ON M4S 1G5, Canada",
				"statusCode": 200,
				"statusDescription": "OK",
				"traceId": "de130a86da4247d48980b3b2353939d9|BN20290118|7.7.0.0|",
				"addressLine": "111 Davisville Ave",
				"adminDistrict": "ON",
				"adminDistrict2": "Toronto",
				"countryRegion": "Canada",
				"formattedAddress": "111 Davisville Ave, Toronto, ON M4S 1G5, Canada",
				"locality": "Toronto",
				"neighborhood": "Mt Pleasant West",
				"postalCode": "M4S 1G5"
			},
			"geometry": {
				"type": "Point",
				"coordinates": [
					-79.3921699,
					43.69877
				]
			},
			"bbox": [
				-79.3937248,
				43.6976458,
				-79.390615,
				43.6998942
			]
		}
	]
}
