{
	"type": "FeatureCollection",
	"features": [
		{
			"type": "Feature",
			"properties": {
				"confidence": 9,
				"authenticationResultCode": "ValidCredentials",
				"brandLogoUri": "http://dev.virtualearth.net/Branding/logo_powered_by.png",
				"copyright": "Copyright © 2017 Microsoft and its suppliers. All rights reserved. This API cannot be accessed and the content and any results may not be used, reproduced or transmitted in any manner without express written permission from Microsoft Corporation.",
				"entityType": "Address",
				"matchCodes": [
					"Good"
				],
				"name": "111 Pulford St, Winnipeg, MB R3L 1X8, Canada",
				"statusCode": 200,
				"statusDescription": "OK",
				"traceId": "521db14ca18b4f26a0b904c3c1e88eb0|BN20290118|7.7.0.0|",
				"addressLine": "111 Pulford St",
				"adminDistrict": "MB",
				"adminDistrict2": "Manitoba",
				"countryRegion": "Canada",
				"formattedAddress": "111 Pulford St, Winnipeg, MB R3L 1X8, Canada",
				"locality": "Winnipeg",
				"neighborhood": "River-Osborne",
				"postalCode": "R3L 1X8"
			},
			"geometry": {
				"type": "Point",
				"coordinates": [
					-97.14518,
					49.8788
				]
			},
			"bbox": [
				-97.1469245,
				49.8776758,
				-97.1434355,
				49.8799242
			]
		}
	]
}
