{
	"type": "FeatureCollection",
	"features": [
		{
			"type": "Feature",
			"properties": {
				"confidence": 9,
				"authenticationResultCode": "ValidCredentials",
				"brandLogoUri": "http://dev.virtualearth.net/Branding/logo_powered_by.png",
				"copyright": "Copyright © 2017 Microsoft and its suppliers. All rights reserved. This API cannot be accessed and the content and any results may not be used, reproduced or transmitted in any manner without express written permission from Microsoft Corporation.",
				"entityType": "Address",
				"matchCodes": [
					"Good"
				],
				"name": "111 Malcolm Rd, Guelph, ON N1K 1A8, Canada",
				"statusCode": 200,
				"statusDescription": "OK",
				"traceId": "050e790991374ee7afedf43cfcf6eb47|BN20160335|7.7.0.0|",
				"addressLine": "111 Malcolm Rd",
				"adminDistrict": "ON",
				"adminDistrict2": "Wellington",
				"countryRegion": "Canada",
				"formattedAddress": "111 Malcolm Rd, Guelph, ON N1K 1A8, Canada",
				"locality": "Guelph",
				"neighborhood": "Willow West/Sugarbush",
				"postalCode": "N1K 1A8"
			},
			"geometry": {
				"type": "Point",
				"coordinates": [
					-80.3241,
					43.53602
				]
			},
			"bbox": [
				-80.3256507,
				43.5348958,
				-80.3225493,
				43.5371442
			]
		}
	]
}
