{
	"type": "FeatureCollection",
	"features": [
		{
			"type": "Feature",
			"properties": {
				"confidence": 9,
				"authenticationResultCode": "ValidCredentials",
				"brandLogoUri": "http://dev.virtualearth.net/Branding/logo_powered_by.png",
				"copyright": "Copyright © 2017 Microsoft and its suppliers. All rights reserved. This API cannot be accessed and the content and any results may not be used, reproduced or transmitted in any manner without express written permission from Microsoft Corporation.",
				"entityType": "Address",
				"matchCodes": [
					"Good"
				],
				"name": "11110 Longwoods Rd, Delaware, ON N0L 1E0, Canada",
				"statusCode": 200,
				"statusDescription": "OK",
				"traceId": "d7f392b0f64744ebbd2199a48b1acf02|BN20130620|7.7.0.0|",
				"addressLine": "11110 Longwoods Rd",
				"adminDistrict": "ON",
				"adminDistrict2": "Middlesex",
				"countryRegion": "Canada",
				"formattedAddress": "11110 Longwoods Rd, Delaware, ON N0L 1E0, Canada",
				"locality": "Middlesex Centre",
				"neighborhood": "Delaware",
				"postalCode": "N0L 1E0"
			},
			"geometry": {
				"type": "Point",
				"coordinates": [
					-81.4045123,
					42.908848
				]
			},
			"bbox": [
				-81.4060471,
				42.9077238,
				-81.4029775,
				42.9099721
			]
		}
	]
}
