{
	"type": "FeatureCollection",
	"features": [
		{
			"type": "Feature",
			"properties": {
				"confidence": 9,
				"authenticationResultCode": "ValidCredentials",
				"brandLogoUri": "http://dev.virtualearth.net/Branding/logo_powered_by.png",
				"copyright": "Copyright © 2017 Microsoft and its suppliers. All rights reserved. This API cannot be accessed and the content and any results may not be used, reproduced or transmitted in any manner without express written permission from Microsoft Corporation.",
				"entityType": "Address",
				"matchCodes": [
					"Good"
				],
				"name": "11140 97 Ave, Grande Prairie, AB T8V 3J8, Canada",
				"statusCode": 200,
				"statusDescription": "OK",
				"traceId": "092f1acf87ab41639975127ac491e835|BN20130520|7.7.0.0|",
				"addressLine": "11140 97 Ave",
				"adminDistrict": "AB",
				"adminDistrict2": "Alberta",
				"countryRegion": "Canada",
				"formattedAddress": "11140 97 Ave, Grande Prairie, AB T8V 3J8, Canada",
				"locality": "Grande Prairie",
				"neighborhood": "Richmond Industrial Park",
				"postalCode": "T8V 3J8"
			},
			"geometry": {
				"type": "Point",
				"coordinates": [
					-118.83183,
					55.16824
				]
			},
			"bbox": [
				-118.8337982,
				55.1671158,
				-118.8298618,
				55.1693642
			]
		}
	]
}
