{
	"type": "FeatureCollection",
	"features": [
		{
			"type": "Feature",
			"properties": {
				"confidence": 9,
				"authenticationResultCode": "ValidCredentials",
				"brandLogoUri": "http://dev.virtualearth.net/Branding/logo_powered_by.png",
				"copyright": "Copyright © 2017 Microsoft and its suppliers. All rights reserved. This API cannot be accessed and the content and any results may not be used, reproduced or transmitted in any manner without express written permission from Microsoft Corporation.",
				"entityType": "Address",
				"matchCodes": [
					"Good"
				],
				"name": "11151 Rue Mirabeau, Anjou, QC H1J 2S2, Canada",
				"statusCode": 200,
				"statusDescription": "OK",
				"traceId": "6922ede64e024435923c7a4687f8ecc2|BN20300154|7.7.0.0|",
				"addressLine": "11151 Rue Mirabeau",
				"adminDistrict": "QC",
				"adminDistrict2": "Montreal",
				"countryRegion": "Canada",
				"formattedAddress": "11151 Rue Mirabeau, Anjou, QC H1J 2S2, Canada",
				"locality": "Montreal",
				"neighborhood": "Anjou",
				"postalCode": "H1J 2S2"
			},
			"geometry": {
				"type": "Point",
				"coordinates": [
					-73.58654,
					45.61837
				]
			},
			"bbox": [
				-73.5881472,
				45.6172458,
				-73.5849328,
				45.6194942
			]
		}
	]
}
