{
	"type": "FeatureCollection",
	"features": [
		{
			"type": "Feature",
			"properties": {
				"confidence": 9,
				"authenticationResultCode": "ValidCredentials",
				"brandLogoUri": "http://dev.virtualearth.net/Branding/logo_powered_by.png",
				"copyright": "Copyright © 2017 Microsoft and its suppliers. All rights reserved. This API cannot be accessed and the content and any results may not be used, reproduced or transmitted in any manner without express written permission from Microsoft Corporation.",
				"entityType": "Address",
				"matchCodes": [
					"Good"
				],
				"name": "1119 Fennell Ave E, Hamilton, ON L8T 1S2, Canada",
				"statusCode": 200,
				"statusDescription": "OK",
				"traceId": "3bad9210d12d4d6c8e8fcecb422cb5d9|BN20130533|7.7.0.0|",
				"addressLine": "1119 Fennell Ave E",
				"adminDistrict": "ON",
				"adminDistrict2": "Hamilton",
				"countryRegion": "Canada",
				"formattedAddress": "1119 Fennell Ave E, Hamilton, ON L8T 1S2, Canada",
				"locality": "Hamilton",
				"neighborhood": "Sherwood",
				"postalCode": "L8T 1S2"
			},
			"geometry": {
				"type": "Point",
				"coordinates": [
					-79.82838,
					43.22557
				]
			},
			"bbox": [
				-79.8299228,
				43.2244458,
				-79.8268372,
				43.2266942
			]
		}
	]
}
