{
	"type": "FeatureCollection",
	"features": [
		{
			"type": "Feature",
			"properties": {
				"confidence": 9,
				"authenticationResultCode": "ValidCredentials",
				"brandLogoUri": "http://dev.virtualearth.net/Branding/logo_powered_by.png",
				"copyright": "Copyright © 2017 Microsoft and its suppliers. All rights reserved. This API cannot be accessed and the content and any results may not be used, reproduced or transmitted in any manner without express written permission from Microsoft Corporation.",
				"entityType": "Address",
				"matchCodes": [
					"Good"
				],
				"name": "112 Black Diamond Rd, Belleville, ON K0K, Canada",
				"statusCode": 200,
				"statusDescription": "OK",
				"traceId": "0b3d07275f2b4f968aa29d8a9789bc3b|BN20130631|7.7.0.0|",
				"addressLine": "112 Black Diamond Rd",
				"adminDistrict": "ON",
				"adminDistrict2": "Hastings",
				"countryRegion": "Canada",
				"formattedAddress": "112 Black Diamond Rd, Belleville, ON K0K, Canada",
				"locality": "Belleville",
				"postalCode": "K0K"
			},
			"geometry": {
				"type": "Point",
				"coordinates": [
					-77.38562,
					44.19902
				]
			},
			"bbox": [
				-77.387188,
				44.1978958,
				-77.384052,
				44.2001442
			]
		}
	]
}
