{
	"type": "FeatureCollection",
	"features": [
		{
			"type": "Feature",
			"properties": {
				"confidence": 9,
				"authenticationResultCode": "ValidCredentials",
				"brandLogoUri": "http://dev.virtualearth.net/Branding/logo_powered_by.png",
				"copyright": "Copyright © 2017 Microsoft and its suppliers. All rights reserved. This API cannot be accessed and the content and any results may not be used, reproduced or transmitted in any manner without express written permission from Microsoft Corporation.",
				"entityType": "Address",
				"matchCodes": [
					"Good"
				],
				"name": "112 Tucker Rd SE, Airdrie, AB T4A 1T1, Canada",
				"statusCode": 200,
				"statusDescription": "OK",
				"traceId": "f917d523400d44a0bac72a2ca5c77f1a|BN20131519|7.7.0.0|",
				"addressLine": "112 Tucker Rd SE",
				"adminDistrict": "AB",
				"adminDistrict2": "Alberta",
				"countryRegion": "Canada",
				"formattedAddress": "112 Tucker Rd SE, Airdrie, AB T4A 1T1, Canada",
				"locality": "Airdrie",
				"postalCode": "T4A 1T1"
			},
			"geometry": {
				"type": "Point",
				"coordinates": [
					-113.98663,
					51.2830299
				]
			},
			"bbox": [
				-113.9884273,
				51.2819057,
				-113.9848327,
				51.2841541
			]
		}
	]
}
