{
	"type": "FeatureCollection",
	"features": [
		{
			"type": "Feature",
			"properties": {
				"confidence": 9,
				"authenticationResultCode": "ValidCredentials",
				"brandLogoUri": "http://dev.virtualearth.net/Branding/logo_powered_by.png",
				"copyright": "Copyright © 2017 Microsoft and its suppliers. All rights reserved. This API cannot be accessed and the content and any results may not be used, reproduced or transmitted in any manner without express written permission from Microsoft Corporation.",
				"entityType": "Address",
				"matchCodes": [
					"Good"
				],
				"name": "1120 44 Ave SE, Calgary, AB T2G 4W6, Canada",
				"statusCode": 200,
				"statusDescription": "OK",
				"traceId": "04aaaf47e3fc4d018e1c071f4716096c|BN20240253|7.7.0.0|",
				"addressLine": "1120 44 Ave SE",
				"adminDistrict": "AB",
				"adminDistrict2": "Alberta",
				"countryRegion": "Canada",
				"formattedAddress": "1120 44 Ave SE, Calgary, AB T2G 4W6, Canada",
				"locality": "Calgary",
				"neighborhood": "Alyth-Bonnybrook-Manchester",
				"postalCode": "T2G 4W6"
			},
			"geometry": {
				"type": "Point",
				"coordinates": [
					-114.03997,
					51.01419
				]
			},
			"bbox": [
				-114.0417568,
				51.0130658,
				-114.0381832,
				51.0153142
			]
		}
	]
}
