{
	"type": "FeatureCollection",
	"features": [
		{
			"type": "Feature",
			"properties": {
				"confidence": 9,
				"authenticationResultCode": "ValidCredentials",
				"brandLogoUri": "http://dev.virtualearth.net/Branding/logo_powered_by.png",
				"copyright": "Copyright © 2017 Microsoft and its suppliers. All rights reserved. This API cannot be accessed and the content and any results may not be used, reproduced or transmitted in any manner without express written permission from Microsoft Corporation.",
				"entityType": "Address",
				"matchCodes": [
					"Good"
				],
				"name": "1125 Rue Bergeron, Drummondville, QC J2C 7V5, Canada",
				"statusCode": 200,
				"statusDescription": "OK",
				"traceId": "fa8c8926b5144557b3c8320c7197ea73|BN20130721|7.7.0.0|",
				"addressLine": "1125 Rue Bergeron",
				"adminDistrict": "QC",
				"adminDistrict2": "Drummond",
				"countryRegion": "Canada",
				"formattedAddress": "1125 Rue Bergeron, Drummondville, QC J2C 7V5, Canada",
				"locality": "Drummondville",
				"postalCode": "J2C 7V5"
			},
			"geometry": {
				"type": "Point",
				"coordinates": [
					-72.52873,
					45.87122
				]
			},
			"bbox": [
				-72.5303445,
				45.8700958,
				-72.5271155,
				45.8723442
			]
		}
	]
}
