{
	"type": "FeatureCollection",
	"features": [
		{
			"type": "Feature",
			"properties": {
				"confidence": 9,
				"authenticationResultCode": "ValidCredentials",
				"brandLogoUri": "http://dev.virtualearth.net/Branding/logo_powered_by.png",
				"copyright": "Copyright © 2017 Microsoft and its suppliers. All rights reserved. This API cannot be accessed and the content and any results may not be used, reproduced or transmitted in any manner without express written permission from Microsoft Corporation.",
				"entityType": "Address",
				"matchCodes": [
					"Good"
				],
				"name": "113 Morrison Ave, Toronto, ON M6E 1M3, Canada",
				"statusCode": 200,
				"statusDescription": "OK",
				"traceId": "e6f48ee5a841456eb9d5053cb7044ffa|BN20190653|7.7.0.0|",
				"addressLine": "113 Morrison Ave",
				"adminDistrict": "ON",
				"adminDistrict2": "Toronto",
				"countryRegion": "Canada",
				"formattedAddress": "113 Morrison Ave, Toronto, ON M6E 1M3, Canada",
				"locality": "Toronto",
				"neighborhood": "Corso Italia-Davenport",
				"postalCode": "M6E 1M3"
			},
			"geometry": {
				"type": "Point",
				"coordinates": [
					-79.44962,
					43.6834
				]
			},
			"bbox": [
				-79.4511745,
				43.6822758,
				-79.4480655,
				43.6845242
			]
		}
	]
}
