{
	"type": "FeatureCollection",
	"features": [
		{
			"type": "Feature",
			"properties": {
				"confidence": 9,
				"authenticationResultCode": "ValidCredentials",
				"brandLogoUri": "http://dev.virtualearth.net/Branding/logo_powered_by.png",
				"copyright": "Copyright © 2017 Microsoft and its suppliers. All rights reserved. This API cannot be accessed and the content and any results may not be used, reproduced or transmitted in any manner without express written permission from Microsoft Corporation.",
				"entityType": "Address",
				"matchCodes": [
					"Good"
				],
				"name": "11340 79 Ave NW, Edmonton, AB T6G 0P3, Canada",
				"statusCode": 200,
				"statusDescription": "OK",
				"traceId": "53a2e3d397e74caa94f410b15e04e3e1|BN20181720|7.7.0.0|",
				"addressLine": "11340 79 Ave NW",
				"adminDistrict": "AB",
				"adminDistrict2": "Alberta",
				"countryRegion": "Canada",
				"formattedAddress": "11340 79 Ave NW, Edmonton, AB T6G 0P3, Canada",
				"locality": "Edmonton",
				"neighborhood": "McKernan",
				"postalCode": "T6G 0P3"
			},
			"geometry": {
				"type": "Point",
				"coordinates": [
					-113.52502,
					53.51532
				]
			},
			"bbox": [
				-113.5269106,
				53.5141958,
				-113.5231294,
				53.5164442
			]
		}
	]
}
