{
	"type": "FeatureCollection",
	"features": [
		{
			"type": "Feature",
			"properties": {
				"confidence": 9,
				"authenticationResultCode": "ValidCredentials",
				"brandLogoUri": "http://dev.virtualearth.net/Branding/logo_powered_by.png",
				"copyright": "Copyright © 2017 Microsoft and its suppliers. All rights reserved. This API cannot be accessed and the content and any results may not be used, reproduced or transmitted in any manner without express written permission from Microsoft Corporation.",
				"entityType": "Address",
				"matchCodes": [
					"Good"
				],
				"name": "11371 Twigg Pl, Richmond, BC V6V 3C9, Canada",
				"statusCode": 200,
				"statusDescription": "OK",
				"traceId": "057d416e7e5d41cd97ab16c92293846a|BN20130522|7.7.0.0|",
				"addressLine": "11371 Twigg Pl",
				"adminDistrict": "BC",
				"adminDistrict2": "Greater Vancouver",
				"countryRegion": "Canada",
				"formattedAddress": "11371 Twigg Pl, Richmond, BC V6V 3C9, Canada",
				"locality": "Richmond",
				"neighborhood": "Bridgeport",
				"postalCode": "V6V 3C9"
			},
			"geometry": {
				"type": "Point",
				"coordinates": [
					-123.10187,
					49.2019649
				]
			},
			"bbox": [
				-123.1035905,
				49.2008407,
				-123.1001495,
				49.2030891
			]
		}
	]
}
