{
	"type": "FeatureCollection",
	"features": [
		{
			"type": "Feature",
			"properties": {
				"confidence": 9,
				"authenticationResultCode": "ValidCredentials",
				"brandLogoUri": "http://dev.virtualearth.net/Branding/logo_powered_by.png",
				"copyright": "Copyright © 2017 Microsoft and its suppliers. All rights reserved. This API cannot be accessed and the content and any results may not be used, reproduced or transmitted in any manner without express written permission from Microsoft Corporation.",
				"entityType": "Address",
				"matchCodes": [
					"Good"
				],
				"name": "114 Sinaa St, Iqaluit, NU X0A, Canada",
				"statusCode": 200,
				"statusDescription": "OK",
				"traceId": "8d98918ad4d54a66a52edd178d53bc29|BN20190642|7.7.0.0|",
				"addressLine": "114 Sinaa St",
				"adminDistrict": "NU",
				"adminDistrict2": "Nunavut",
				"countryRegion": "Canada",
				"formattedAddress": "114 Sinaa St, Iqaluit, NU X0A, Canada",
				"locality": "Iqaluit",
				"postalCode": "X0A 0H0"
			},
			"geometry": {
				"type": "Point",
				"coordinates": [
					-68.5098003,
					63.7420255
				]
			},
			"bbox": [
				-68.5123412,
				63.7409013,
				-68.5072593,
				63.7431497
			]
		}
	]
}
