{
	"type": "FeatureCollection",
	"features": [
		{
			"type": "Feature",
			"properties": {
				"confidence": 9,
				"authenticationResultCode": "ValidCredentials",
				"brandLogoUri": "http://dev.virtualearth.net/Branding/logo_powered_by.png",
				"copyright": "Copyright © 2017 Microsoft and its suppliers. All rights reserved. This API cannot be accessed and the content and any results may not be used, reproduced or transmitted in any manner without express written permission from Microsoft Corporation.",
				"entityType": "Address",
				"matchCodes": [
					"Good"
				],
				"name": "11428 77 Ave NW, Edmonton, AB T6G 0L8, Canada",
				"statusCode": 200,
				"statusDescription": "OK",
				"traceId": "6a27d83a87b047a68ae4a5d8bb57ddca|BN20130719|7.7.0.0|",
				"addressLine": "11428 77 Ave NW",
				"adminDistrict": "AB",
				"adminDistrict2": "Alberta",
				"countryRegion": "Canada",
				"formattedAddress": "11428 77 Ave NW, Edmonton, AB T6G 0L8, Canada",
				"locality": "Edmonton",
				"neighborhood": "McKernan",
				"postalCode": "T6G 0L8"
			},
			"geometry": {
				"type": "Point",
				"coordinates": [
					-113.52717,
					53.51342
				]
			},
			"bbox": [
				-113.5290605,
				53.5122958,
				-113.5252795,
				53.5145442
			]
		}
	]
}
