{
	"type": "FeatureCollection",
	"features": [
		{
			"type": "Feature",
			"properties": {
				"confidence": 9,
				"authenticationResultCode": "ValidCredentials",
				"brandLogoUri": "http://dev.virtualearth.net/Branding/logo_powered_by.png",
				"copyright": "Copyright © 2017 Microsoft and its suppliers. All rights reserved. This API cannot be accessed and the content and any results may not be used, reproduced or transmitted in any manner without express written permission from Microsoft Corporation.",
				"entityType": "Address",
				"matchCodes": [
					"Good"
				],
				"name": "11445 104 Ave, Grande Prairie, AB T8V 0N7, Canada",
				"statusCode": 200,
				"statusDescription": "OK",
				"traceId": "de903bad433f486f995af7092f533ac2|BN20130625|7.7.0.0|",
				"addressLine": "11445 104 Ave",
				"adminDistrict": "AB",
				"adminDistrict2": "Alberta",
				"countryRegion": "Canada",
				"formattedAddress": "11445 104 Ave, Grande Prairie, AB T8V 0N7, Canada",
				"locality": "Grande Prairie",
				"neighborhood": "Westgate",
				"postalCode": "T8V 0N7"
			},
			"geometry": {
				"type": "Point",
				"coordinates": [
					-118.8388011,
					55.1733472
				]
			},
			"bbox": [
				-118.8407695,
				55.172223,
				-118.8368327,
				55.1744713
			]
		}
	]
}
