{
	"type": "FeatureCollection",
	"features": [
		{
			"type": "Feature",
			"properties": {
				"confidence": 9,
				"authenticationResultCode": "ValidCredentials",
				"brandLogoUri": "http://dev.virtualearth.net/Branding/logo_powered_by.png",
				"copyright": "Copyright © 2017 Microsoft and its suppliers. All rights reserved. This API cannot be accessed and the content and any results may not be used, reproduced or transmitted in any manner without express written permission from Microsoft Corporation.",
				"entityType": "Address",
				"matchCodes": [
					"Good"
				],
				"name": "114 Railside Rd, North York, ON M3A 1A3, Canada",
				"statusCode": 200,
				"statusDescription": "OK",
				"traceId": "a41c7ac265fb4cc2b27631995e7f10f2|BN20130533|7.7.0.0|",
				"addressLine": "114 Railside Rd",
				"adminDistrict": "ON",
				"adminDistrict2": "Toronto",
				"countryRegion": "Canada",
				"formattedAddress": "114 Railside Rd, North York, ON M3A 1A3, Canada",
				"locality": "Toronto",
				"neighborhood": "Victoria Village",
				"postalCode": "M3A 1A3"
			},
			"geometry": {
				"type": "Point",
				"coordinates": [
					-79.3261,
					43.73598
				]
			},
			"bbox": [
				-79.3276558,
				43.7348558,
				-79.3245442,
				43.7371042
			]
		}
	]
}
