{
	"type": "FeatureCollection",
	"features": [
		{
			"type": "Feature",
			"properties": {
				"confidence": 9,
				"authenticationResultCode": "ValidCredentials",
				"brandLogoUri": "http://dev.virtualearth.net/Branding/logo_powered_by.png",
				"copyright": "Copyright © 2017 Microsoft and its suppliers. All rights reserved. This API cannot be accessed and the content and any results may not be used, reproduced or transmitted in any manner without express written permission from Microsoft Corporation.",
				"entityType": "Address",
				"matchCodes": [
					"Good"
				],
				"name": "115 Sandy Falls Rd, Timmins, ON P4R 0J2, Canada",
				"statusCode": 200,
				"statusDescription": "OK",
				"traceId": "e0c34c0d034b4d7bbea7b7791bae6b78|BN20260223|7.7.0.0|",
				"addressLine": "115 Sandy Falls Rd",
				"adminDistrict": "ON",
				"adminDistrict2": "Cochrane",
				"countryRegion": "Canada",
				"formattedAddress": "115 Sandy Falls Rd, Timmins, ON P4R 0J2, Canada",
				"locality": "Timmins",
				"neighborhood": "Mountjoy",
				"postalCode": "P4R 0J2"
			},
			"geometry": {
				"type": "Point",
				"coordinates": [
					-81.3813709,
					48.489604
				]
			},
			"bbox": [
				-81.383067,
				48.4884798,
				-81.3796747,
				48.4907281
			]
		}
	]
}
