{
	"type": "FeatureCollection",
	"features": [
		{
			"type": "Feature",
			"properties": {
				"confidence": 9,
				"authenticationResultCode": "ValidCredentials",
				"brandLogoUri": "http://dev.virtualearth.net/Branding/logo_powered_by.png",
				"copyright": "Copyright © 2017 Microsoft and its suppliers. All rights reserved. This API cannot be accessed and the content and any results may not be used, reproduced or transmitted in any manner without express written permission from Microsoft Corporation.",
				"entityType": "Address",
				"matchCodes": [
					"Good"
				],
				"name": "115 S Service Rd W, Grimsby, ON L3M, Canada",
				"statusCode": 200,
				"statusDescription": "OK",
				"traceId": "845b1b1d9856418da33864407ed023e1|BN20280152|7.7.0.0|",
				"addressLine": "115 S Service Rd W",
				"adminDistrict": "ON",
				"adminDistrict2": "Niagara",
				"countryRegion": "Canada",
				"formattedAddress": "115 S Service Rd W, Grimsby, ON L3M, Canada",
				"locality": "Grimsby",
				"postalCode": "L3M 4G3"
			},
			"geometry": {
				"type": "Point",
				"coordinates": [
					-79.56483,
					43.19893
				]
			},
			"bbox": [
				-79.5663721,
				43.1978058,
				-79.5632879,
				43.2000542
			]
		}
	]
}
