{
	"type": "FeatureCollection",
	"features": [
		{
			"type": "Feature",
			"properties": {
				"confidence": 8,
				"authenticationResultCode": "ValidCredentials",
				"brandLogoUri": "http://dev.virtualearth.net/Branding/logo_powered_by.png",
				"copyright": "Copyright © 2017 Microsoft and its suppliers. All rights reserved. This API cannot be accessed and the content and any results may not be used, reproduced or transmitted in any manner without express written permission from Microsoft Corporation.",
				"entityType": "RoadBlock",
				"matchCodes": [
					"UpHierarchy"
				],
				"name": "Peacekeepers Way SW, Calgary, AB T3E, Canada",
				"statusCode": 200,
				"statusDescription": "OK",
				"traceId": "0c49e7bf6fe04f4ba344f934d59d27d3|BN20121764|7.7.0.0|",
				"addressLine": "Peacekeepers Way SW",
				"adminDistrict": "AB",
				"adminDistrict2": "Alberta",
				"countryRegion": "Canada",
				"formattedAddress": "Peacekeepers Way SW, Calgary, AB T3E, Canada",
				"locality": "Calgary",
				"neighborhood": "Lincoln Park",
				"postalCode": "T3E 7X4"
			},
			"geometry": {
				"type": "Point",
				"coordinates": [
					-114.12442,
					51.0069
				]
			},
			"bbox": [
				-114.12938,
				51.00303,
				-114.12089,
				51.00691
			]
		}
	]
}
