{
	"type": "FeatureCollection",
	"features": [
		{
			"type": "Feature",
			"properties": {
				"confidence": 9,
				"authenticationResultCode": "ValidCredentials",
				"brandLogoUri": "http://dev.virtualearth.net/Branding/logo_powered_by.png",
				"copyright": "Copyright © 2017 Microsoft and its suppliers. All rights reserved. This API cannot be accessed and the content and any results may not be used, reproduced or transmitted in any manner without express written permission from Microsoft Corporation.",
				"entityType": "Address",
				"matchCodes": [
					"Good"
				],
				"name": "1151 Sarta Rd, Oakville, ON L6L 2P1, Canada",
				"statusCode": 200,
				"statusDescription": "OK",
				"traceId": "d9f45ead678745c888959864501fbf6d|BN20130522|7.7.0.0|",
				"addressLine": "1151 Sarta Rd",
				"adminDistrict": "ON",
				"adminDistrict2": "Halton",
				"countryRegion": "Canada",
				"formattedAddress": "1151 Sarta Rd, Oakville, ON L6L 2P1, Canada",
				"locality": "Oakville",
				"postalCode": "L6L 2P1"
			},
			"geometry": {
				"type": "Point",
				"coordinates": [
					-79.69902,
					43.4236999
				]
			},
			"bbox": [
				-79.7005678,
				43.4225757,
				-79.6974722,
				43.4248241
			]
		}
	]
}
