{
	"type": "FeatureCollection",
	"features": [
		{
			"type": "Feature",
			"properties": {
				"confidence": 9,
				"authenticationResultCode": "ValidCredentials",
				"brandLogoUri": "http://dev.virtualearth.net/Branding/logo_powered_by.png",
				"copyright": "Copyright © 2017 Microsoft and its suppliers. All rights reserved. This API cannot be accessed and the content and any results may not be used, reproduced or transmitted in any manner without express written permission from Microsoft Corporation.",
				"entityType": "Address",
				"matchCodes": [
					"Good"
				],
				"name": "1183 Cecil Ave, Ottawa, ON K1H 7Z6, Canada",
				"statusCode": 200,
				"statusDescription": "OK",
				"traceId": "ea5a1cad74d1466dbbaa0efcc86c8d03|BN20121762|7.7.0.0|",
				"addressLine": "1183 Cecil Ave",
				"adminDistrict": "ON",
				"adminDistrict2": "Ottawa",
				"countryRegion": "Canada",
				"formattedAddress": "1183 Cecil Ave, Ottawa, ON K1H 7Z6, Canada",
				"locality": "Ottawa",
				"neighborhood": "Billings Bridge-Alta Vista",
				"postalCode": "K1H 7Z6"
			},
			"geometry": {
				"type": "Point",
				"coordinates": [
					-75.66956,
					45.37992
				]
			},
			"bbox": [
				-75.6711604,
				45.3787958,
				-75.6679596,
				45.3810442
			]
		}
	]
}
