{
	"type": "FeatureCollection",
	"features": [
		{
			"type": "Feature",
			"properties": {
				"confidence": 9,
				"authenticationResultCode": "ValidCredentials",
				"brandLogoUri": "http://dev.virtualearth.net/Branding/logo_powered_by.png",
				"copyright": "Copyright © 2017 Microsoft and its suppliers. All rights reserved. This API cannot be accessed and the content and any results may not be used, reproduced or transmitted in any manner without express written permission from Microsoft Corporation.",
				"entityType": "Address",
				"matchCodes": [
					"Good"
				],
				"name": "1185 Rolmar Cres, Cobble Hill, BC V0R 1L4, Canada",
				"statusCode": 200,
				"statusDescription": "OK",
				"traceId": "d71b80802dc548cbbc9452623c65c7f4|BN20171457|7.7.0.0|",
				"addressLine": "1185 Rolmar Cres",
				"adminDistrict": "BC",
				"adminDistrict2": "Cowichan Valley",
				"countryRegion": "Canada",
				"formattedAddress": "1185 Rolmar Cres, Cobble Hill, BC V0R 1L4, Canada",
				"locality": "Cowichan Valley",
				"neighborhood": "Cobble Hill",
				"postalCode": "V0R 1L4"
			},
			"geometry": {
				"type": "Point",
				"coordinates": [
					-123.5801366,
					48.6973922
				]
			},
			"bbox": [
				-123.5818398,
				48.696268,
				-123.5784334,
				48.6985163
			]
		}
	]
}
