{
	"type": "FeatureCollection",
	"features": [
		{
			"type": "Feature",
			"properties": {
				"confidence": 9,
				"authenticationResultCode": "ValidCredentials",
				"brandLogoUri": "http://dev.virtualearth.net/Branding/logo_powered_by.png",
				"copyright": "Copyright © 2017 Microsoft and its suppliers. All rights reserved. This API cannot be accessed and the content and any results may not be used, reproduced or transmitted in any manner without express written permission from Microsoft Corporation.",
				"entityType": "Address",
				"matchCodes": [
					"Good"
				],
				"name": "119 Bradford St, Barrie, ON L4N 3B2, Canada",
				"statusCode": 200,
				"statusDescription": "OK",
				"traceId": "7a5fcf2542c8412586e63ffeb5dba792|BN20210145|7.7.0.0|",
				"addressLine": "119 Bradford St",
				"adminDistrict": "ON",
				"adminDistrict2": "Simcoe",
				"countryRegion": "Canada",
				"formattedAddress": "119 Bradford St, Barrie, ON L4N 3B2, Canada",
				"locality": "Barrie",
				"neighborhood": "City Center",
				"postalCode": "L4N 3B2"
			},
			"geometry": {
				"type": "Point",
				"coordinates": [
					-79.69351,
					44.38111
				]
			},
			"bbox": [
				-79.6950829,
				44.3799858,
				-79.6919371,
				44.3822342
			]
		}
	]
}
