{
	"type": "FeatureCollection",
	"features": [
		{
			"type": "Feature",
			"properties": {
				"confidence": 9,
				"authenticationResultCode": "ValidCredentials",
				"brandLogoUri": "http://dev.virtualearth.net/Branding/logo_powered_by.png",
				"copyright": "Copyright © 2017 Microsoft and its suppliers. All rights reserved. This API cannot be accessed and the content and any results may not be used, reproduced or transmitted in any manner without express written permission from Microsoft Corporation.",
				"entityType": "Address",
				"matchCodes": [
					"Good"
				],
				"name": "1191 Grange Rd, Oakville, ON L6H 1P8, Canada",
				"statusCode": 200,
				"statusDescription": "OK",
				"traceId": "c57f91279797417b97fe7029931a4b14|BN20181720|7.7.0.0|",
				"addressLine": "1191 Grange Rd",
				"adminDistrict": "ON",
				"adminDistrict2": "Halton",
				"countryRegion": "Canada",
				"formattedAddress": "1191 Grange Rd, Oakville, ON L6H 1P8, Canada",
				"locality": "Oakville",
				"neighborhood": "Falgarwood",
				"postalCode": "L6H 1P8"
			},
			"geometry": {
				"type": "Point",
				"coordinates": [
					-79.6819,
					43.48025
				]
			},
			"bbox": [
				-79.6834492,
				43.4791258,
				-79.6803508,
				43.4813742
			]
		}
	]
}
