{
	"type": "FeatureCollection",
	"features": [
		{
			"type": "Feature",
			"properties": {
				"confidence": 9,
				"authenticationResultCode": "ValidCredentials",
				"brandLogoUri": "http://dev.virtualearth.net/Branding/logo_powered_by.png",
				"copyright": "Copyright © 2017 Microsoft and its suppliers. All rights reserved. This API cannot be accessed and the content and any results may not be used, reproduced or transmitted in any manner without express written permission from Microsoft Corporation.",
				"entityType": "Address",
				"matchCodes": [
					"Good"
				],
				"name": "11943 224 St, Maple Ridge, BC V2X 6B2, Canada",
				"statusCode": 200,
				"statusDescription": "OK",
				"traceId": "d34b9f90ab41418787dc6a35aa3bed9e|BN20130422|7.7.0.0|",
				"addressLine": "11943 224 St",
				"adminDistrict": "BC",
				"adminDistrict2": "Greater Vancouver",
				"countryRegion": "Canada",
				"formattedAddress": "11943 224 St, Maple Ridge, BC V2X 6B2, Canada",
				"locality": "Maple Ridge",
				"postalCode": "V2X 6B2"
			},
			"geometry": {
				"type": "Point",
				"coordinates": [
					-122.6018749,
					49.2193472
				]
			},
			"bbox": [
				-122.603596,
				49.218223,
				-122.6001538,
				49.2204713
			]
		}
	]
}
