{
	"type": "FeatureCollection",
	"features": [
		{
			"type": "Feature",
			"properties": {
				"confidence": 9,
				"authenticationResultCode": "ValidCredentials",
				"brandLogoUri": "http://dev.virtualearth.net/Branding/logo_powered_by.png",
				"copyright": "Copyright © 2017 Microsoft and its suppliers. All rights reserved. This API cannot be accessed and the content and any results may not be used, reproduced or transmitted in any manner without express written permission from Microsoft Corporation.",
				"entityType": "Address",
				"matchCodes": [
					"Good"
				],
				"name": "12 Hester Ct, Thornhill, ON L3T 3K5, Canada",
				"statusCode": 200,
				"statusDescription": "OK",
				"traceId": "a17d16d561ca4b27abe2f5463bb67d7e|BN20130530|7.7.0.0|",
				"addressLine": "12 Hester Ct",
				"adminDistrict": "ON",
				"adminDistrict2": "York",
				"countryRegion": "Canada",
				"formattedAddress": "12 Hester Ct, Thornhill, ON L3T 3K5, Canada",
				"locality": "Markham",
				"neighborhood": "Thornhill",
				"postalCode": "L3T 3K5"
			},
			"geometry": {
				"type": "Point",
				"coordinates": [
					-79.40684,
					43.83133
				]
			},
			"bbox": [
				-79.4083983,
				43.8302058,
				-79.4052817,
				43.8324542
			]
		}
	]
}
