{
	"type": "FeatureCollection",
	"features": [
		{
			"type": "Feature",
			"properties": {
				"confidence": 9,
				"authenticationResultCode": "ValidCredentials",
				"brandLogoUri": "http://dev.virtualearth.net/Branding/logo_powered_by.png",
				"copyright": "Copyright © 2017 Microsoft and its suppliers. All rights reserved. This API cannot be accessed and the content and any results may not be used, reproduced or transmitted in any manner without express written permission from Microsoft Corporation.",
				"entityType": "Address",
				"matchCodes": [
					"Good"
				],
				"name": "12 Shelley Ln, Barrie, ON L4N 4X9, Canada",
				"statusCode": 200,
				"statusDescription": "OK",
				"traceId": "25c3b2a483d4408c95ce38e496a48928|BN20130719|7.7.0.0|",
				"addressLine": "12 Shelley Ln",
				"adminDistrict": "ON",
				"adminDistrict2": "Simcoe",
				"countryRegion": "Canada",
				"formattedAddress": "12 Shelley Ln, Barrie, ON L4N 4X9, Canada",
				"locality": "Barrie",
				"postalCode": "L4N 4X9"
			},
			"geometry": {
				"type": "Point",
				"coordinates": [
					-79.71656,
					44.39393
				]
			},
			"bbox": [
				-79.7181332,
				44.3928058,
				-79.7149868,
				44.3950542
			]
		}
	]
}
