{
	"type": "FeatureCollection",
	"features": [
		{
			"type": "Feature",
			"properties": {
				"confidence": 9,
				"authenticationResultCode": "ValidCredentials",
				"brandLogoUri": "http://dev.virtualearth.net/Branding/logo_powered_by.png",
				"copyright": "Copyright © 2017 Microsoft and its suppliers. All rights reserved. This API cannot be accessed and the content and any results may not be used, reproduced or transmitted in any manner without express written permission from Microsoft Corporation.",
				"entityType": "Address",
				"matchCodes": [
					"Good"
				],
				"name": "120 Rue des Pme, Sherbrooke, QC J1C 0R2, Canada",
				"statusCode": 200,
				"statusDescription": "OK",
				"traceId": "1c1efef0dab340eda7ee69bb73b34ef6|BN20260223|7.7.0.0|",
				"addressLine": "120 Rue des Pme",
				"adminDistrict": "QC",
				"adminDistrict2": "Sherbrooke",
				"countryRegion": "Canada",
				"formattedAddress": "120 Rue des Pme, Sherbrooke, QC J1C 0R2, Canada",
				"locality": "Sherbrooke",
				"neighborhood": "Bromptonville",
				"postalCode": "J1C 0R2"
			},
			"geometry": {
				"type": "Point",
				"coordinates": [
					-71.9463899,
					45.46692
				]
			},
			"bbox": [
				-71.9479928,
				45.4657958,
				-71.944787,
				45.4680442
			]
		}
	]
}
