{
	"type": "FeatureCollection",
	"features": [
		{
			"type": "Feature",
			"properties": {
				"confidence": 9,
				"authenticationResultCode": "ValidCredentials",
				"brandLogoUri": "http://dev.virtualearth.net/Branding/logo_powered_by.png",
				"copyright": "Copyright © 2017 Microsoft and its suppliers. All rights reserved. This API cannot be accessed and the content and any results may not be used, reproduced or transmitted in any manner without express written permission from Microsoft Corporation.",
				"entityType": "Address",
				"matchCodes": [
					"Good"
				],
				"name": "120 Garden Ave, North Vancouver, BC V7P 3H2, Canada",
				"statusCode": 200,
				"statusDescription": "OK",
				"traceId": "df18a45b878d4725960622518181e9fa|BN20260231|7.7.0.0|",
				"addressLine": "120 Garden Ave",
				"adminDistrict": "BC",
				"adminDistrict2": "Greater Vancouver",
				"countryRegion": "Canada",
				"formattedAddress": "120 Garden Ave, North Vancouver, BC V7P 3H2, Canada",
				"locality": "North Vancouver District",
				"neighborhood": "Norgate",
				"postalCode": "V7P 3H2"
			},
			"geometry": {
				"type": "Point",
				"coordinates": [
					-123.1181851,
					49.3170044
				]
			},
			"bbox": [
				-123.1199096,
				49.3158802,
				-123.1164606,
				49.3181285
			]
		}
	]
}
