{
	"type": "FeatureCollection",
	"features": [
		{
			"type": "Feature",
			"properties": {
				"confidence": 9,
				"authenticationResultCode": "ValidCredentials",
				"brandLogoUri": "http://dev.virtualearth.net/Branding/logo_powered_by.png",
				"copyright": "Copyright © 2017 Microsoft and its suppliers. All rights reserved. This API cannot be accessed and the content and any results may not be used, reproduced or transmitted in any manner without express written permission from Microsoft Corporation.",
				"entityType": "Address",
				"matchCodes": [
					"Good"
				],
				"name": "120 Coastline Dr, Brampton, ON L6Y 0S4, Canada",
				"statusCode": 200,
				"statusDescription": "OK",
				"traceId": "a7332e2c2a36407eaad8332efa02d516|BN20200239|7.7.0.0|",
				"addressLine": "120 Coastline Dr",
				"adminDistrict": "ON",
				"adminDistrict2": "Peel",
				"countryRegion": "Canada",
				"formattedAddress": "120 Coastline Dr, Brampton, ON L6Y 0S4, Canada",
				"locality": "Brampton",
				"postalCode": "L6Y 0S4"
			},
			"geometry": {
				"type": "Point",
				"coordinates": [
					-79.76649,
					43.62626
				]
			},
			"bbox": [
				-79.768043,
				43.6251358,
				-79.764937,
				43.6273842
			]
		}
	]
}
