{
	"type": "FeatureCollection",
	"features": [
		{
			"type": "Feature",
			"properties": {
				"confidence": 9,
				"authenticationResultCode": "ValidCredentials",
				"brandLogoUri": "http://dev.virtualearth.net/Branding/logo_powered_by.png",
				"copyright": "Copyright © 2017 Microsoft and its suppliers. All rights reserved. This API cannot be accessed and the content and any results may not be used, reproduced or transmitted in any manner without express written permission from Microsoft Corporation.",
				"entityType": "Address",
				"matchCodes": [
					"Good"
				],
				"name": "1200 York Mills Rd, North York, ON M3A 1X9, Canada",
				"statusCode": 200,
				"statusDescription": "OK",
				"traceId": "5ef3e884be034cf5bb935649a697db7a|BN20121764|7.7.0.0|",
				"addressLine": "1200 York Mills Rd",
				"adminDistrict": "ON",
				"adminDistrict2": "Toronto",
				"countryRegion": "Canada",
				"formattedAddress": "1200 York Mills Rd, North York, ON M3A 1X9, Canada",
				"locality": "Toronto",
				"neighborhood": "Parkwoods-Donalda",
				"postalCode": "M3A 1X9"
			},
			"geometry": {
				"type": "Point",
				"coordinates": [
					-79.33497,
					43.75965
				]
			},
			"bbox": [
				-79.3365265,
				43.7585258,
				-79.3334135,
				43.7607742
			]
		}
	]
}
