{
	"type": "FeatureCollection",
	"features": [
		{
			"type": "Feature",
			"properties": {
				"confidence": 9,
				"authenticationResultCode": "ValidCredentials",
				"brandLogoUri": "http://dev.virtualearth.net/Branding/logo_powered_by.png",
				"copyright": "Copyright © 2017 Microsoft and its suppliers. All rights reserved. This API cannot be accessed and the content and any results may not be used, reproduced or transmitted in any manner without express written permission from Microsoft Corporation.",
				"entityType": "Address",
				"matchCodes": [
					"Good"
				],
				"name": "1201 Halifax St, Regina, SK S4R 1T7, Canada",
				"statusCode": 200,
				"statusDescription": "OK",
				"traceId": "a0780994cfd34370a06371e751d8b0bb|BN20131519|7.7.0.0|",
				"addressLine": "1201 Halifax St",
				"adminDistrict": "SK",
				"adminDistrict2": "Saskatchewan",
				"countryRegion": "Canada",
				"formattedAddress": "1201 Halifax St, Regina, SK S4R 1T7, Canada",
				"locality": "Regina",
				"postalCode": "S4R 1T7"
			},
			"geometry": {
				"type": "Point",
				"coordinates": [
					-104.60301,
					50.45955
				]
			},
			"bbox": [
				-104.6047758,
				50.4584258,
				-104.6012442,
				50.4606742
			]
		}
	]
}
