{
	"type": "FeatureCollection",
	"features": [
		{
			"type": "Feature",
			"properties": {
				"confidence": 9,
				"authenticationResultCode": "ValidCredentials",
				"brandLogoUri": "http://dev.virtualearth.net/Branding/logo_powered_by.png",
				"copyright": "Copyright © 2017 Microsoft and its suppliers. All rights reserved. This API cannot be accessed and the content and any results may not be used, reproduced or transmitted in any manner without express written permission from Microsoft Corporation.",
				"entityType": "Address",
				"matchCodes": [
					"Good"
				],
				"name": "121 Rang Cyr, St-Cyprien-de-Napierville, QC J0J 1L0, Canada",
				"statusCode": 200,
				"statusDescription": "OK",
				"traceId": "2e82493fe8c548c280f3ccfd0c7be953|BN20121764|7.7.0.0|",
				"addressLine": "121 Rang Cyr",
				"adminDistrict": "QC",
				"adminDistrict2": "Les Jardins-de-Napierville",
				"countryRegion": "Canada",
				"formattedAddress": "121 Rang Cyr, St-Cyprien-de-Napierville, QC J0J 1L0, Canada",
				"locality": "St-Cyprien-de-Napierville",
				"postalCode": "J0J 1L0"
			},
			"geometry": {
				"type": "Point",
				"coordinates": [
					-73.42477,
					45.1935
				]
			},
			"bbox": [
				-73.4263652,
				45.1923758,
				-73.4231748,
				45.1946242
			]
		}
	]
}
