{
	"type": "FeatureCollection",
	"features": [
		{
			"type": "Feature",
			"properties": {
				"confidence": 9,
				"authenticationResultCode": "ValidCredentials",
				"brandLogoUri": "http://dev.virtualearth.net/Branding/logo_powered_by.png",
				"copyright": "Copyright © 2017 Microsoft and its suppliers. All rights reserved. This API cannot be accessed and the content and any results may not be used, reproduced or transmitted in any manner without express written permission from Microsoft Corporation.",
				"entityType": "Address",
				"matchCodes": [
					"Good"
				],
				"name": "121 Rue Industrielle, Lambton, QC G0M 1H0, Canada",
				"statusCode": 200,
				"statusDescription": "OK",
				"traceId": "45a516fc9e384c30a4695421e68f737f|BN20171457|7.7.0.0|",
				"addressLine": "121 Rue Industrielle",
				"adminDistrict": "QC",
				"adminDistrict2": "Le Granit",
				"countryRegion": "Canada",
				"formattedAddress": "121 Rue Industrielle, Lambton, QC G0M 1H0, Canada",
				"locality": "Lambton",
				"postalCode": "G0M 1H0"
			},
			"geometry": {
				"type": "Point",
				"coordinates": [
					-71.07971,
					45.84109
				]
			},
			"bbox": [
				-71.0813237,
				45.8399658,
				-71.0780963,
				45.8422142
			]
		}
	]
}
