{
	"type": "FeatureCollection",
	"features": [
		{
			"type": "Feature",
			"properties": {
				"confidence": 9,
				"authenticationResultCode": "ValidCredentials",
				"brandLogoUri": "http://dev.virtualearth.net/Branding/logo_powered_by.png",
				"copyright": "Copyright © 2017 Microsoft and its suppliers. All rights reserved. This API cannot be accessed and the content and any results may not be used, reproduced or transmitted in any manner without express written permission from Microsoft Corporation.",
				"entityType": "Address",
				"matchCodes": [
					"Good"
				],
				"name": "1210 Sheppard Ave E, North York, ON M2K 1E3, Canada",
				"statusCode": 200,
				"statusDescription": "OK",
				"traceId": "6d7eb5840add4e77ad9495c672110a46|BN20290118|7.7.0.0|",
				"addressLine": "1210 Sheppard Ave E",
				"adminDistrict": "ON",
				"adminDistrict2": "Toronto",
				"countryRegion": "Canada",
				"formattedAddress": "1210 Sheppard Ave E, North York, ON M2K 1E3, Canada",
				"locality": "Toronto",
				"neighborhood": "Bayview Village",
				"postalCode": "M2K 1E3"
			},
			"geometry": {
				"type": "Point",
				"coordinates": [
					-79.3677166,
					43.7715337
				]
			},
			"bbox": [
				-79.3692734,
				43.7704096,
				-79.3661598,
				43.7726579
			]
		}
	]
}
