{
	"type": "FeatureCollection",
	"features": [
		{
			"type": "Feature",
			"properties": {
				"confidence": 9,
				"authenticationResultCode": "ValidCredentials",
				"brandLogoUri": "http://dev.virtualearth.net/Branding/logo_powered_by.png",
				"copyright": "Copyright © 2017 Microsoft and its suppliers. All rights reserved. This API cannot be accessed and the content and any results may not be used, reproduced or transmitted in any manner without express written permission from Microsoft Corporation.",
				"entityType": "Address",
				"matchCodes": [
					"Good"
				],
				"name": "12184 Old Yale Rd, Surrey, BC V3V 3X5, Canada",
				"statusCode": 200,
				"statusDescription": "OK",
				"traceId": "a5293fbc6c434f208953d3adab334831|BN20130530|7.7.0.0|",
				"addressLine": "12184 Old Yale Rd",
				"adminDistrict": "BC",
				"adminDistrict2": "Greater Vancouver",
				"countryRegion": "Canada",
				"formattedAddress": "12184 Old Yale Rd, Surrey, BC V3V 3X5, Canada",
				"locality": "Surrey",
				"neighborhood": "Whalley",
				"postalCode": "V3V 3X5"
			},
			"geometry": {
				"type": "Point",
				"coordinates": [
					-122.88506,
					49.20017
				]
			},
			"bbox": [
				-122.8867804,
				49.1990458,
				-122.8833396,
				49.2012942
			]
		}
	]
}
