{
	"type": "FeatureCollection",
	"features": [
		{
			"type": "Feature",
			"properties": {
				"confidence": 9,
				"authenticationResultCode": "ValidCredentials",
				"brandLogoUri": "http://dev.virtualearth.net/Branding/logo_powered_by.png",
				"copyright": "Copyright © 2017 Microsoft and its suppliers. All rights reserved. This API cannot be accessed and the content and any results may not be used, reproduced or transmitted in any manner without express written permission from Microsoft Corporation.",
				"entityType": "Address",
				"matchCodes": [
					"Good"
				],
				"name": "1227 Rue de la Manic, Chicoutimi, QC G7K 1A1, Canada",
				"statusCode": 200,
				"statusDescription": "OK",
				"traceId": "709fb179d6b6454c898787344bb1b6a8|BN20171457|7.7.0.0|",
				"addressLine": "1227 Rue de la Manic",
				"adminDistrict": "QC",
				"adminDistrict2": "Saguenay",
				"countryRegion": "Canada",
				"formattedAddress": "1227 Rue de la Manic, Chicoutimi, QC G7K 1A1, Canada",
				"locality": "Saguenay",
				"neighborhood": "Chicoutimi",
				"postalCode": "G7K 1A1"
			},
			"geometry": {
				"type": "Point",
				"coordinates": [
					-71.11159,
					48.39815
				]
			},
			"bbox": [
				-71.1132831,
				48.3970258,
				-71.1098969,
				48.3992742
			]
		}
	]
}
