{
	"type": "FeatureCollection",
	"features": [
		{
			"type": "Feature",
			"properties": {
				"confidence": 9,
				"authenticationResultCode": "ValidCredentials",
				"brandLogoUri": "http://dev.virtualearth.net/Branding/logo_powered_by.png",
				"copyright": "Copyright © 2017 Microsoft and its suppliers. All rights reserved. This API cannot be accessed and the content and any results may not be used, reproduced or transmitted in any manner without express written permission from Microsoft Corporation.",
				"entityType": "Address",
				"matchCodes": [
					"Good"
				],
				"name": "123 Cree Rd, Sherwood Park, AB T8A 3X9, Canada",
				"statusCode": 200,
				"statusDescription": "OK",
				"traceId": "321a3ff532f64199b7737568467490ea|BN20160335|7.7.0.0|",
				"addressLine": "123 Cree Rd",
				"adminDistrict": "AB",
				"adminDistrict2": "Alberta",
				"countryRegion": "Canada",
				"formattedAddress": "123 Cree Rd, Sherwood Park, AB T8A 3X9, Canada",
				"locality": "Strathcona County",
				"neighborhood": "Sherwood Park",
				"postalCode": "T8A 3X9"
			},
			"geometry": {
				"type": "Point",
				"coordinates": [
					-113.32823,
					53.53792
				]
			},
			"bbox": [
				-113.3301216,
				53.5367958,
				-113.3263384,
				53.5390442
			]
		}
	]
}
