{
	"type": "FeatureCollection",
	"features": [
		{
			"type": "Feature",
			"properties": {
				"confidence": 7,
				"authenticationResultCode": "ValidCredentials",
				"brandLogoUri": "http://dev.virtualearth.net/Branding/logo_powered_by.png",
				"copyright": "Copyright © 2017 Microsoft and its suppliers. All rights reserved. This API cannot be accessed and the content and any results may not be used, reproduced or transmitted in any manner without express written permission from Microsoft Corporation.",
				"entityType": "Postcode1",
				"matchCodes": [
					"UpHierarchy"
				],
				"name": "Gimli, R0C 1B0, Canada",
				"statusCode": 200,
				"statusDescription": "OK",
				"traceId": "01afcaf4879a46379ea4a29c5253264d|BN20200137|7.7.0.0|",
				"adminDistrict": "MB",
				"countryRegion": "Canada",
				"formattedAddress": "Gimli, R0C 1B0, Canada",
				"locality": "Gimli",
				"postalCode": "R0C 1B0"
			},
			"geometry": {
				"type": "Point",
				"coordinates": [
					-96.9941864013672,
					50.6368598937988
				]
			},
			"bbox": [
				-97.0023062323484,
				50.6329971762282,
				-96.9860665703859,
				50.6407226113695
			]
		}
	]
}
