{
	"type": "FeatureCollection",
	"features": [
		{
			"type": "Feature",
			"properties": {
				"confidence": 9,
				"authenticationResultCode": "ValidCredentials",
				"brandLogoUri": "http://dev.virtualearth.net/Branding/logo_powered_by.png",
				"copyright": "Copyright © 2017 Microsoft and its suppliers. All rights reserved. This API cannot be accessed and the content and any results may not be used, reproduced or transmitted in any manner without express written permission from Microsoft Corporation.",
				"entityType": "Address",
				"matchCodes": [
					"Good"
				],
				"name": "123 Clyde Ave, Mt Pearl, NL A1N 4R9, Canada",
				"statusCode": 200,
				"statusDescription": "OK",
				"traceId": "fb63b71794bf4693adce3851b7df4e8a|BN20320521|7.7.0.0|",
				"addressLine": "123 Clyde Ave",
				"adminDistrict": "NL",
				"adminDistrict2": "Newfoundland and Labrador",
				"countryRegion": "Canada",
				"formattedAddress": "123 Clyde Ave, Mt Pearl, NL A1N 4R9, Canada",
				"locality": "Mt Pearl",
				"postalCode": "A1N 4R9"
			},
			"geometry": {
				"type": "Point",
				"coordinates": [
					-52.8440163,
					47.5168209
				]
			},
			"bbox": [
				-52.8456808,
				47.5156968,
				-52.8423518,
				47.5179451
			]
		}
	]
}
