{
	"type": "FeatureCollection",
	"features": [
		{
			"type": "Feature",
			"properties": {
				"confidence": 9,
				"authenticationResultCode": "ValidCredentials",
				"brandLogoUri": "http://dev.virtualearth.net/Branding/logo_powered_by.png",
				"copyright": "Copyright © 2017 Microsoft and its suppliers. All rights reserved. This API cannot be accessed and the content and any results may not be used, reproduced or transmitted in any manner without express written permission from Microsoft Corporation.",
				"entityType": "Address",
				"matchCodes": [
					"Good"
				],
				"name": "123 Denison St, Markham, ON L3R 1B5, Canada",
				"statusCode": 200,
				"statusDescription": "OK",
				"traceId": "6eb02bdaaa8f479ba2fd59a08d66c239|BN20200137|7.7.0.0|",
				"addressLine": "123 Denison St",
				"adminDistrict": "ON",
				"adminDistrict2": "York",
				"countryRegion": "Canada",
				"formattedAddress": "123 Denison St, Markham, ON L3R 1B5, Canada",
				"locality": "Markham",
				"postalCode": "L3R 1B5"
			},
			"geometry": {
				"type": "Point",
				"coordinates": [
					-79.3544299,
					43.82067
				]
			},
			"bbox": [
				-79.355988,
				43.8195458,
				-79.3528718,
				43.8217942
			]
		}
	]
}
