{
	"type": "FeatureCollection",
	"features": [
		{
			"type": "Feature",
			"properties": {
				"confidence": 9,
				"authenticationResultCode": "ValidCredentials",
				"brandLogoUri": "http://dev.virtualearth.net/Branding/logo_powered_by.png",
				"copyright": "Copyright © 2017 Microsoft and its suppliers. All rights reserved. This API cannot be accessed and the content and any results may not be used, reproduced or transmitted in any manner without express written permission from Microsoft Corporation.",
				"entityType": "Address",
				"matchCodes": [
					"Good"
				],
				"name": "124 Skyway Ave, Etobicoke, ON M9W 4Y9, Canada",
				"statusCode": 200,
				"statusDescription": "OK",
				"traceId": "7c3bcf885afd40bdb0aee6938093facc|BN20130634|7.7.0.0|",
				"addressLine": "124 Skyway Ave",
				"adminDistrict": "ON",
				"adminDistrict2": "Toronto",
				"countryRegion": "Canada",
				"formattedAddress": "124 Skyway Ave, Etobicoke, ON M9W 4Y9, Canada",
				"locality": "Toronto",
				"neighborhood": "West Humber-Clairville",
				"postalCode": "M9W 4Y9"
			},
			"geometry": {
				"type": "Point",
				"coordinates": [
					-79.5826699,
					43.68274
				]
			},
			"bbox": [
				-79.5842244,
				43.6816158,
				-79.5811154,
				43.6838642
			]
		}
	]
}
