{
	"type": "FeatureCollection",
	"features": [
		{
			"type": "Feature",
			"properties": {
				"confidence": 9,
				"authenticationResultCode": "ValidCredentials",
				"brandLogoUri": "http://dev.virtualearth.net/Branding/logo_powered_by.png",
				"copyright": "Copyright © 2017 Microsoft and its suppliers. All rights reserved. This API cannot be accessed and the content and any results may not be used, reproduced or transmitted in any manner without express written permission from Microsoft Corporation.",
				"entityType": "Address",
				"matchCodes": [
					"Good"
				],
				"name": "124 W Petpeswick Rd, Musquodoboit Harbour, NS B0J 2L0, Canada",
				"statusCode": 200,
				"statusDescription": "OK",
				"traceId": "ae5f58c42ded454cb2a4b5f884f7c03e|BN20290118|7.7.0.0|",
				"addressLine": "124 W Petpeswick Rd",
				"adminDistrict": "NS",
				"adminDistrict2": "Halifax",
				"countryRegion": "Canada",
				"formattedAddress": "124 W Petpeswick Rd, Musquodoboit Harbour, NS B0J 2L0, Canada",
				"locality": "Halifax",
				"neighborhood": "Musquodoboit Harbour",
				"postalCode": "B0J 2L0"
			},
			"geometry": {
				"type": "Point",
				"coordinates": [
					-63.15636,
					44.77816
				]
			},
			"bbox": [
				-63.1579437,
				44.7770358,
				-63.1547763,
				44.7792842
			]
		}
	]
}
