{
	"type": "FeatureCollection",
	"features": [
		{
			"type": "Feature",
			"properties": {
				"confidence": 9,
				"authenticationResultCode": "ValidCredentials",
				"brandLogoUri": "http://dev.virtualearth.net/Branding/logo_powered_by.png",
				"copyright": "Copyright © 2017 Microsoft and its suppliers. All rights reserved. This API cannot be accessed and the content and any results may not be used, reproduced or transmitted in any manner without express written permission from Microsoft Corporation.",
				"entityType": "Address",
				"matchCodes": [
					"Good"
				],
				"name": "12400 Vulcan Way, Richmond, BC V6V 1J8, Canada",
				"statusCode": 200,
				"statusDescription": "OK",
				"traceId": "483e93d5632e4267bbcd4d29d28402ec|BN20130631|7.7.0.0|",
				"addressLine": "12400 Vulcan Way",
				"adminDistrict": "BC",
				"adminDistrict2": "Greater Vancouver",
				"countryRegion": "Canada",
				"formattedAddress": "12400 Vulcan Way, Richmond, BC V6V 1J8, Canada",
				"locality": "Richmond",
				"neighborhood": "Bridgeport",
				"postalCode": "V6V 1J8"
			},
			"geometry": {
				"type": "Point",
				"coordinates": [
					-123.0864633,
					49.1937412
				]
			},
			"bbox": [
				-123.0881835,
				49.1926171,
				-123.0847431,
				49.1948654
			]
		}
	]
}
