{
	"type": "FeatureCollection",
	"features": [
		{
			"type": "Feature",
			"properties": {
				"confidence": 9,
				"authenticationResultCode": "ValidCredentials",
				"brandLogoUri": "http://dev.virtualearth.net/Branding/logo_powered_by.png",
				"copyright": "Copyright © 2017 Microsoft and its suppliers. All rights reserved. This API cannot be accessed and the content and any results may not be used, reproduced or transmitted in any manner without express written permission from Microsoft Corporation.",
				"entityType": "Address",
				"matchCodes": [
					"Good"
				],
				"name": "125 Bismark St, Springfield, MB R0E, Canada",
				"statusCode": 200,
				"statusDescription": "OK",
				"traceId": "fe0ca1414fd749e0957545cbbc91f63e|BN20190653|7.7.0.0|",
				"addressLine": "125 Bismark St",
				"adminDistrict": "MB",
				"adminDistrict2": "Manitoba",
				"countryRegion": "Canada",
				"formattedAddress": "125 Bismark St, Springfield, MB R0E, Canada",
				"locality": "Springfield",
				"postalCode": "R0E"
			},
			"geometry": {
				"type": "Point",
				"coordinates": [
					-97.0189089,
					49.929892
				]
			},
			"bbox": [
				-97.0206552,
				49.9287679,
				-97.0171626,
				49.9310162
			]
		}
	]
}
