{
	"type": "FeatureCollection",
	"features": [
		{
			"type": "Feature",
			"properties": {
				"confidence": 9,
				"authenticationResultCode": "ValidCredentials",
				"brandLogoUri": "http://dev.virtualearth.net/Branding/logo_powered_by.png",
				"copyright": "Copyright © 2017 Microsoft and its suppliers. All rights reserved. This API cannot be accessed and the content and any results may not be used, reproduced or transmitted in any manner without express written permission from Microsoft Corporation.",
				"entityType": "Address",
				"matchCodes": [
					"Good"
				],
				"name": "125 Whiting Rd, Fredericton, NB E3B 5Y5, Canada",
				"statusCode": 200,
				"statusDescription": "OK",
				"traceId": "1cad540f52524749b9ca14ee9c4edfbb|BN20220145|7.7.0.0|",
				"addressLine": "125 Whiting Rd",
				"adminDistrict": "NB",
				"adminDistrict2": "York",
				"countryRegion": "Canada",
				"formattedAddress": "125 Whiting Rd, Fredericton, NB E3B 5Y5, Canada",
				"locality": "Fredericton",
				"postalCode": "E3B 5Y5"
			},
			"geometry": {
				"type": "Point",
				"coordinates": [
					-66.61875,
					45.91414
				]
			},
			"bbox": [
				-66.6203658,
				45.9130158,
				-66.6171342,
				45.9152642
			]
		}
	]
}
