{
	"type": "FeatureCollection",
	"features": [
		{
			"type": "Feature",
			"properties": {
				"confidence": 9,
				"authenticationResultCode": "ValidCredentials",
				"brandLogoUri": "http://dev.virtualearth.net/Branding/logo_powered_by.png",
				"copyright": "Copyright © 2017 Microsoft and its suppliers. All rights reserved. This API cannot be accessed and the content and any results may not be used, reproduced or transmitted in any manner without express written permission from Microsoft Corporation.",
				"entityType": "Address",
				"matchCodes": [
					"Good"
				],
				"name": "125 Boulevard Springer, Chapais, QC G0W, Canada",
				"statusCode": 200,
				"statusDescription": "OK",
				"traceId": "0fefcad265c64239a866c1d9bd2e7507|BN20130719|7.7.0.0|",
				"addressLine": "125 Boulevard Springer",
				"adminDistrict": "QC",
				"adminDistrict2": "Baie-James",
				"countryRegion": "Canada",
				"formattedAddress": "125 Boulevard Springer, Chapais, QC G0W, Canada",
				"locality": "Chapais",
				"postalCode": "G0W 1H0"
			},
			"geometry": {
				"type": "Point",
				"coordinates": [
					-74.85632,
					49.78252
				]
			},
			"bbox": [
				-74.858061,
				49.7813958,
				-74.854579,
				49.7836442
			]
		}
	]
}
