{
	"type": "FeatureCollection",
	"features": [
		{
			"type": "Feature",
			"properties": {
				"confidence": 9,
				"authenticationResultCode": "ValidCredentials",
				"brandLogoUri": "http://dev.virtualearth.net/Branding/logo_powered_by.png",
				"copyright": "Copyright © 2017 Microsoft and its suppliers. All rights reserved. This API cannot be accessed and the content and any results may not be used, reproduced or transmitted in any manner without express written permission from Microsoft Corporation.",
				"entityType": "Address",
				"matchCodes": [
					"Good"
				],
				"name": "1250 Stittsville Main St, Stittsville, ON K2S 1S9, Canada",
				"statusCode": 200,
				"statusDescription": "OK",
				"traceId": "6135503dc4aa4405a64c2953b6f43ebf|BN20130522|7.7.0.0|",
				"addressLine": "1250 Stittsville Main St",
				"adminDistrict": "ON",
				"adminDistrict2": "Ottawa",
				"countryRegion": "Canada",
				"formattedAddress": "1250 Stittsville Main St, Stittsville, ON K2S 1S9, Canada",
				"locality": "Ottawa",
				"neighborhood": "Stittsville",
				"postalCode": "K2S 1S9"
			},
			"geometry": {
				"type": "Point",
				"coordinates": [
					-75.93126,
					45.26858
				]
			},
			"bbox": [
				-75.9328573,
				45.2674558,
				-75.9296627,
				45.2697042
			]
		}
	]
}
