{
	"type": "FeatureCollection",
	"features": [
		{
			"type": "Feature",
			"properties": {
				"confidence": 9,
				"authenticationResultCode": "ValidCredentials",
				"brandLogoUri": "http://dev.virtualearth.net/Branding/logo_powered_by.png",
				"copyright": "Copyright © 2017 Microsoft and its suppliers. All rights reserved. This API cannot be accessed and the content and any results may not be used, reproduced or transmitted in any manner without express written permission from Microsoft Corporation.",
				"entityType": "Address",
				"matchCodes": [
					"Good"
				],
				"name": "1255 St Clair Ave W, Toronto, ON M6H, Canada",
				"statusCode": 200,
				"statusDescription": "OK",
				"traceId": "57c3fb30410a438fbad659d79a300798|BN20200137|7.7.0.0|",
				"addressLine": "1255 St Clair Ave W",
				"adminDistrict": "ON",
				"adminDistrict2": "Toronto",
				"countryRegion": "Canada",
				"formattedAddress": "1255 St Clair Ave W, Toronto, ON M6H, Canada",
				"locality": "Toronto",
				"neighborhood": "Corso Italia-Davenport",
				"postalCode": "M6H"
			},
			"geometry": {
				"type": "Point",
				"coordinates": [
					-79.44625,
					43.67701
				]
			},
			"bbox": [
				-79.4478043,
				43.6758858,
				-79.4446957,
				43.6781342
			]
		}
	]
}
