{
	"type": "FeatureCollection",
	"features": [
		{
			"type": "Feature",
			"properties": {
				"confidence": 9,
				"authenticationResultCode": "ValidCredentials",
				"brandLogoUri": "http://dev.virtualearth.net/Branding/logo_powered_by.png",
				"copyright": "Copyright © 2017 Microsoft and its suppliers. All rights reserved. This API cannot be accessed and the content and any results may not be used, reproduced or transmitted in any manner without express written permission from Microsoft Corporation.",
				"entityType": "Address",
				"matchCodes": [
					"Good"
				],
				"name": "1258 Kos Blvd, Mississauga, ON L5J 4L7, Canada",
				"statusCode": 200,
				"statusDescription": "OK",
				"traceId": "d3292fc884144abc9c16d4fc36fdc114|BN20290118|7.7.0.0|",
				"addressLine": "1258 Kos Blvd",
				"adminDistrict": "ON",
				"adminDistrict2": "Peel",
				"countryRegion": "Canada",
				"formattedAddress": "1258 Kos Blvd, Mississauga, ON L5J 4L7, Canada",
				"locality": "Mississauga",
				"neighborhood": "Lorne Park",
				"postalCode": "L5J 4L7"
			},
			"geometry": {
				"type": "Point",
				"coordinates": [
					-79.61617,
					43.52626
				]
			},
			"bbox": [
				-79.6177204,
				43.5251358,
				-79.6146196,
				43.5273842
			]
		}
	]
}
