{
	"type": "FeatureCollection",
	"features": [
		{
			"type": "Feature",
			"properties": {
				"confidence": 9,
				"authenticationResultCode": "ValidCredentials",
				"brandLogoUri": "http://dev.virtualearth.net/Branding/logo_powered_by.png",
				"copyright": "Copyright © 2017 Microsoft and its suppliers. All rights reserved. This API cannot be accessed and the content and any results may not be used, reproduced or transmitted in any manner without express written permission from Microsoft Corporation.",
				"entityType": "Address",
				"matchCodes": [
					"Good"
				],
				"name": "1260 Highfield Cres SE, Calgary, AB T2G 5M3, Canada",
				"statusCode": 200,
				"statusDescription": "OK",
				"traceId": "1876bacb3beb4e1daf86be9b02fe2ef3|BN20250135|7.7.0.0|",
				"addressLine": "1260 Highfield Cres SE",
				"adminDistrict": "AB",
				"adminDistrict2": "Alberta",
				"countryRegion": "Canada",
				"formattedAddress": "1260 Highfield Cres SE, Calgary, AB T2G 5M3, Canada",
				"locality": "Calgary",
				"neighborhood": "Alyth-Bonnybrook-Manchester",
				"postalCode": "T2G 5M3"
			},
			"geometry": {
				"type": "Point",
				"coordinates": [
					-114.03519,
					51.01115
				]
			},
			"bbox": [
				-114.0369767,
				51.0100258,
				-114.0334033,
				51.0122742
			]
		}
	]
}
