{
	"type": "FeatureCollection",
	"features": [
		{
			"type": "Feature",
			"properties": {
				"confidence": 9,
				"authenticationResultCode": "ValidCredentials",
				"brandLogoUri": "http://dev.virtualearth.net/Branding/logo_powered_by.png",
				"copyright": "Copyright © 2017 Microsoft and its suppliers. All rights reserved. This API cannot be accessed and the content and any results may not be used, reproduced or transmitted in any manner without express written permission from Microsoft Corporation.",
				"entityType": "Address",
				"matchCodes": [
					"Good"
				],
				"name": "1260 HWY-95, East Kootenay, BC V0A 1H4, Canada",
				"statusCode": 200,
				"statusDescription": "OK",
				"traceId": "401597c4c0a14135ae53b8b01e8fd374|BN20130721|7.7.0.0|",
				"addressLine": "1260 HWY-95",
				"adminDistrict": "BC",
				"adminDistrict2": "East Kootenay",
				"countryRegion": "Canada",
				"formattedAddress": "1260 HWY-95, East Kootenay, BC V0A 1H4, Canada",
				"locality": "East Kootenay",
				"neighborhood": "Spillimacheen",
				"postalCode": "V0A 1H4"
			},
			"geometry": {
				"type": "Point",
				"coordinates": [
					-116.3570441,
					50.8959187
				]
			},
			"bbox": [
				-116.3588264,
				50.8947946,
				-116.3552618,
				50.8970429
			]
		}
	]
}
