{
	"type": "FeatureCollection",
	"features": [
		{
			"type": "Feature",
			"properties": {
				"confidence": 9,
				"authenticationResultCode": "ValidCredentials",
				"brandLogoUri": "http://dev.virtualearth.net/Branding/logo_powered_by.png",
				"copyright": "Copyright © 2017 Microsoft and its suppliers. All rights reserved. This API cannot be accessed and the content and any results may not be used, reproduced or transmitted in any manner without express written permission from Microsoft Corporation.",
				"entityType": "Address",
				"matchCodes": [
					"Good"
				],
				"name": "1264 Lemonville Rd, Burlington, ON L7P 0T6, Canada",
				"statusCode": 200,
				"statusDescription": "OK",
				"traceId": "4e4cb68cd2744fb1b9a408f68b9b2e07|BN20130442|7.7.0.0|",
				"addressLine": "1264 Lemonville Rd",
				"adminDistrict": "ON",
				"adminDistrict2": "Halton",
				"countryRegion": "Canada",
				"formattedAddress": "1264 Lemonville Rd, Burlington, ON L7P 0T6, Canada",
				"locality": "Burlington",
				"neighborhood": "Aldershot West",
				"postalCode": "L7P 0T6"
			},
			"geometry": {
				"type": "Point",
				"coordinates": [
					-79.8708,
					43.30621
				]
			},
			"bbox": [
				-79.8723448,
				43.3050858,
				-79.8692552,
				43.3073342
			]
		}
	]
}
