{
	"type": "FeatureCollection",
	"features": [
		{
			"type": "Feature",
			"properties": {
				"confidence": 9,
				"authenticationResultCode": "ValidCredentials",
				"brandLogoUri": "http://dev.virtualearth.net/Branding/logo_powered_by.png",
				"copyright": "Copyright © 2017 Microsoft and its suppliers. All rights reserved. This API cannot be accessed and the content and any results may not be used, reproduced or transmitted in any manner without express written permission from Microsoft Corporation.",
				"entityType": "Address",
				"matchCodes": [
					"Good"
				],
				"name": "1269 Carriage Ln, Windsor, ON N9H 2A2, Canada",
				"statusCode": 200,
				"statusDescription": "OK",
				"traceId": "7a30f1163a854b12bebd7f45f649e410|BN20130632|7.7.0.0|",
				"addressLine": "1269 Carriage Ln",
				"adminDistrict": "ON",
				"adminDistrict2": "Essex",
				"countryRegion": "Canada",
				"formattedAddress": "1269 Carriage Ln, Windsor, ON N9H 2A2, Canada",
				"locality": "Lasalle",
				"neighborhood": "Windsor",
				"postalCode": "N9H 2A2"
			},
			"geometry": {
				"type": "Point",
				"coordinates": [
					-83.0060727,
					42.2365445
				]
			},
			"bbox": [
				-83.0075911,
				42.2354204,
				-83.0045544,
				42.2376687
			]
		}
	]
}
