{
	"type": "FeatureCollection",
	"features": [
		{
			"type": "Feature",
			"properties": {
				"confidence": 9,
				"authenticationResultCode": "ValidCredentials",
				"brandLogoUri": "http://dev.virtualearth.net/Branding/logo_powered_by.png",
				"copyright": "Copyright © 2017 Microsoft and its suppliers. All rights reserved. This API cannot be accessed and the content and any results may not be used, reproduced or transmitted in any manner without express written permission from Microsoft Corporation.",
				"entityType": "Address",
				"matchCodes": [
					"Good"
				],
				"name": "127 Delta Park Blvd, Brampton, ON L6T 5M8, Canada",
				"statusCode": 200,
				"statusDescription": "OK",
				"traceId": "f1e57cb8187543a89f45fffa185fab44|BN20200239|7.7.0.0|",
				"addressLine": "127 Delta Park Blvd",
				"adminDistrict": "ON",
				"adminDistrict2": "Peel",
				"countryRegion": "Canada",
				"formattedAddress": "127 Delta Park Blvd, Brampton, ON L6T 5M8, Canada",
				"locality": "Brampton",
				"neighborhood": "Castlemore",
				"postalCode": "L6T 5M8"
			},
			"geometry": {
				"type": "Point",
				"coordinates": [
					-79.68835,
					43.74152
				]
			},
			"bbox": [
				-79.689906,
				43.7403958,
				-79.686794,
				43.7426442
			]
		}
	]
}
