{
	"type": "FeatureCollection",
	"features": [
		{
			"type": "Feature",
			"properties": {
				"confidence": 9,
				"authenticationResultCode": "ValidCredentials",
				"brandLogoUri": "http://dev.virtualearth.net/Branding/logo_powered_by.png",
				"copyright": "Copyright © 2017 Microsoft and its suppliers. All rights reserved. This API cannot be accessed and the content and any results may not be used, reproduced or transmitted in any manner without express written permission from Microsoft Corporation.",
				"entityType": "Address",
				"matchCodes": [
					"Good"
				],
				"name": "127 Verobeach Blvd, North York, ON M9M 1P8, Canada",
				"statusCode": 200,
				"statusDescription": "OK",
				"traceId": "47777d43e56b4839b458021c5b1752d9|BN20220145|7.7.0.0|",
				"addressLine": "127 Verobeach Blvd",
				"adminDistrict": "ON",
				"adminDistrict2": "Toronto",
				"countryRegion": "Canada",
				"formattedAddress": "127 Verobeach Blvd, North York, ON M9M 1P8, Canada",
				"locality": "Toronto",
				"neighborhood": "Humbermede",
				"postalCode": "M9M 1P8"
			},
			"geometry": {
				"type": "Point",
				"coordinates": [
					-79.54446,
					43.73554
				]
			},
			"bbox": [
				-79.5460158,
				43.7344158,
				-79.5429042,
				43.7366642
			]
		}
	]
}
