{
	"type": "FeatureCollection",
	"features": [
		{
			"type": "Feature",
			"properties": {
				"confidence": 9,
				"authenticationResultCode": "ValidCredentials",
				"brandLogoUri": "http://dev.virtualearth.net/Branding/logo_powered_by.png",
				"copyright": "Copyright © 2017 Microsoft and its suppliers. All rights reserved. This API cannot be accessed and the content and any results may not be used, reproduced or transmitted in any manner without express written permission from Microsoft Corporation.",
				"entityType": "Address",
				"matchCodes": [
					"Good"
				],
				"name": "127 Victoria St S, Kitchener, ON N2G 2B4, Canada",
				"statusCode": 200,
				"statusDescription": "OK",
				"traceId": "970e4028cf9c4448b06ae39373fec5d0|BN20200239|7.7.0.0|",
				"addressLine": "127 Victoria St S",
				"adminDistrict": "ON",
				"adminDistrict2": "Waterloo",
				"countryRegion": "Canada",
				"formattedAddress": "127 Victoria St S, Kitchener, ON N2G 2B4, Canada",
				"locality": "Kitchener",
				"neighborhood": "Victoria Park",
				"postalCode": "N2G 2B4"
			},
			"geometry": {
				"type": "Point",
				"coordinates": [
					-80.50071,
					43.4495
				]
			},
			"bbox": [
				-80.5022585,
				43.4483758,
				-80.4991615,
				43.4506242
			]
		}
	]
}
