{
	"type": "FeatureCollection",
	"features": [
		{
			"type": "Feature",
			"properties": {
				"confidence": 9,
				"authenticationResultCode": "ValidCredentials",
				"brandLogoUri": "http://dev.virtualearth.net/Branding/logo_powered_by.png",
				"copyright": "Copyright © 2017 Microsoft and its suppliers. All rights reserved. This API cannot be accessed and the content and any results may not be used, reproduced or transmitted in any manner without express written permission from Microsoft Corporation.",
				"entityType": "Address",
				"matchCodes": [
					"Good"
				],
				"name": "1270 Rue Volta, Boucherville, QC J4B 6G6, Canada",
				"statusCode": 200,
				"statusDescription": "OK",
				"traceId": "e3826d4d5bdf48ae9276dc42fc4971ee|BN20130625|7.7.0.0|",
				"addressLine": "1270 Rue Volta",
				"adminDistrict": "QC",
				"adminDistrict2": "Longueuil",
				"countryRegion": "Canada",
				"formattedAddress": "1270 Rue Volta, Boucherville, QC J4B 6G6, Canada",
				"locality": "Boucherville",
				"postalCode": "J4B 6G6"
			},
			"geometry": {
				"type": "Point",
				"coordinates": [
					-73.4434799,
					45.56439
				]
			},
			"bbox": [
				-73.4450856,
				45.5632658,
				-73.4418742,
				45.5655142
			]
		}
	]
}
