{
	"type": "FeatureCollection",
	"features": [
		{
			"type": "Feature",
			"properties": {
				"confidence": 9,
				"authenticationResultCode": "ValidCredentials",
				"brandLogoUri": "http://dev.virtualearth.net/Branding/logo_powered_by.png",
				"copyright": "Copyright © 2017 Microsoft and its suppliers. All rights reserved. This API cannot be accessed and the content and any results may not be used, reproduced or transmitted in any manner without express written permission from Microsoft Corporation.",
				"entityType": "Address",
				"matchCodes": [
					"Good"
				],
				"name": "1278 W 6th Ave, Vancouver, BC V6H 1A5, Canada",
				"statusCode": 200,
				"statusDescription": "OK",
				"traceId": "8f7cc43ddfab43328f7e9cc3c2cadd84|BN20130520|7.7.0.0|",
				"addressLine": "1278 W 6th Ave",
				"adminDistrict": "BC",
				"adminDistrict2": "Greater Vancouver",
				"countryRegion": "Canada",
				"formattedAddress": "1278 W 6th Ave, Vancouver, BC V6H 1A5, Canada",
				"locality": "Vancouver",
				"neighborhood": "Fairview",
				"postalCode": "V6H 1A5"
			},
			"geometry": {
				"type": "Point",
				"coordinates": [
					-123.1331628,
					49.265997
				]
			},
			"bbox": [
				-123.1348855,
				49.2648729,
				-123.1314401,
				49.2671212
			]
		}
	]
}
