{
	"type": "FeatureCollection",
	"features": [
		{
			"type": "Feature",
			"properties": {
				"confidence": 9,
				"authenticationResultCode": "ValidCredentials",
				"brandLogoUri": "http://dev.virtualearth.net/Branding/logo_powered_by.png",
				"copyright": "Copyright © 2017 Microsoft and its suppliers. All rights reserved. This API cannot be accessed and the content and any results may not be used, reproduced or transmitted in any manner without express written permission from Microsoft Corporation.",
				"entityType": "Address",
				"matchCodes": [
					"Good"
				],
				"name": "1282 Livingstone Ave, Ottawa, ON K1H 7P8, Canada",
				"statusCode": 200,
				"statusDescription": "OK",
				"traceId": "1ca004b1398c433a9c510a394a776c3f|BN20300154|7.7.0.0|",
				"addressLine": "1282 Livingstone Ave",
				"adminDistrict": "ON",
				"adminDistrict2": "Ottawa",
				"countryRegion": "Canada",
				"formattedAddress": "1282 Livingstone Ave, Ottawa, ON K1H 7P8, Canada",
				"locality": "Ottawa",
				"neighborhood": "Billings Bridge-Alta Vista",
				"postalCode": "K1H 7P8"
			},
			"geometry": {
				"type": "Point",
				"coordinates": [
					-75.66764,
					45.3831599
				]
			},
			"bbox": [
				-75.6692405,
				45.3820357,
				-75.6660395,
				45.3842841
			]
		}
	]
}
