{
	"type": "FeatureCollection",
	"features": [
		{
			"type": "Feature",
			"properties": {
				"confidence": 9,
				"authenticationResultCode": "ValidCredentials",
				"brandLogoUri": "http://dev.virtualearth.net/Branding/logo_powered_by.png",
				"copyright": "Copyright © 2017 Microsoft and its suppliers. All rights reserved. This API cannot be accessed and the content and any results may not be used, reproduced or transmitted in any manner without express written permission from Microsoft Corporation.",
				"entityType": "Address",
				"matchCodes": [
					"Good"
				],
				"name": "1287 Gardiners Rd, Kingston, ON K7P 3J6, Canada",
				"statusCode": 200,
				"statusDescription": "OK",
				"traceId": "478344243c2a41e9bab292ac679259aa|BN20130431|7.7.0.0|",
				"addressLine": "1287 Gardiners Rd",
				"adminDistrict": "ON",
				"adminDistrict2": "Frontenac",
				"countryRegion": "Canada",
				"formattedAddress": "1287 Gardiners Rd, Kingston, ON K7P 3J6, Canada",
				"locality": "Kingston",
				"neighborhood": "Cataraqui North",
				"postalCode": "K7P 3J6"
			},
			"geometry": {
				"type": "Point",
				"coordinates": [
					-76.57033,
					44.27263
				]
			},
			"bbox": [
				-76.5719,
				44.2715058,
				-76.56876,
				44.2737542
			]
		}
	]
}
