{
	"type": "FeatureCollection",
	"features": [
		{
			"type": "Feature",
			"properties": {
				"confidence": 9,
				"authenticationResultCode": "ValidCredentials",
				"brandLogoUri": "http://dev.virtualearth.net/Branding/logo_powered_by.png",
				"copyright": "Copyright © 2017 Microsoft and its suppliers. All rights reserved. This API cannot be accessed and the content and any results may not be used, reproduced or transmitted in any manner without express written permission from Microsoft Corporation.",
				"entityType": "Address",
				"matchCodes": [
					"Good"
				],
				"name": "129 Avenue Meadowbrook, Beaconsfield, QC H9W 5B9, Canada",
				"statusCode": 200,
				"statusDescription": "OK",
				"traceId": "a1cedbf824f5459fb42b8eab4e9e4e81|BN20130533|7.7.0.0|",
				"addressLine": "129 Avenue Meadowbrook",
				"adminDistrict": "QC",
				"adminDistrict2": "Montreal",
				"countryRegion": "Canada",
				"formattedAddress": "129 Avenue Meadowbrook, Beaconsfield, QC H9W 5B9, Canada",
				"locality": "Beaconsfield",
				"postalCode": "H9W 5B9"
			},
			"geometry": {
				"type": "Point",
				"coordinates": [
					-73.87236,
					45.42765
				]
			},
			"bbox": [
				-73.8739618,
				45.4265258,
				-73.8707582,
				45.4287742
			]
		}
	]
}
