{
	"type": "FeatureCollection",
	"features": [
		{
			"type": "Feature",
			"properties": {
				"confidence": 9,
				"authenticationResultCode": "ValidCredentials",
				"brandLogoUri": "http://dev.virtualearth.net/Branding/logo_powered_by.png",
				"copyright": "Copyright © 2017 Microsoft and its suppliers. All rights reserved. This API cannot be accessed and the content and any results may not be used, reproduced or transmitted in any manner without express written permission from Microsoft Corporation.",
				"entityType": "Address",
				"matchCodes": [
					"Good"
				],
				"name": "1291 California Ave, Brockville, ON K6V, Canada",
				"statusCode": 200,
				"statusDescription": "OK",
				"traceId": "23647ddaa3004d289407808fe5331a4c|BN20130625|7.7.0.0|",
				"addressLine": "1291 California Ave",
				"adminDistrict": "ON",
				"adminDistrict2": "Leeds and Grenville",
				"countryRegion": "Canada",
				"formattedAddress": "1291 California Ave, Brockville, ON K6V, Canada",
				"locality": "Brockville",
				"postalCode": "K6V 5W3"
			},
			"geometry": {
				"type": "Point",
				"coordinates": [
					-75.69459,
					44.61768
				]
			},
			"bbox": [
				-75.6961693,
				44.6165558,
				-75.6930107,
				44.6188042
			]
		}
	]
}
