{
	"type": "FeatureCollection",
	"features": [
		{
			"type": "Feature",
			"properties": {
				"confidence": 7,
				"authenticationResultCode": "ValidCredentials",
				"brandLogoUri": "http://dev.virtualearth.net/Branding/logo_powered_by.png",
				"copyright": "Copyright © 2017 Microsoft and its suppliers. All rights reserved. This API cannot be accessed and the content and any results may not be used, reproduced or transmitted in any manner without express written permission from Microsoft Corporation.",
				"entityType": "Postcode1",
				"matchCodes": [
					"UpHierarchy"
				],
				"name": "Grande Prairie, T8V 4N1, Canada",
				"statusCode": 200,
				"statusDescription": "OK",
				"traceId": "c15e4b1bd7dc4710be3f0c676a8f1f34|BN20130522|7.7.0.0|",
				"adminDistrict": "AB",
				"countryRegion": "Canada",
				"formattedAddress": "Grande Prairie, T8V 4N1, Canada",
				"locality": "Grande Prairie",
				"postalCode": "T8V 4N1"
			},
			"geometry": {
				"type": "Point",
				"coordinates": [
					-118.815658569336,
					55.1957054138184
				]
			},
			"bbox": [
				-118.824681020622,
				55.1918426962477,
				-118.80663611805,
				55.199568131389
			]
		},
		{
			"type": "Feature",
			"properties": {
				"confidence": 2,
				"authenticationResultCode": "ValidCredentials",
				"brandLogoUri": "http://dev.virtualearth.net/Branding/logo_powered_by.png",
				"copyright": "Copyright © 2017 Microsoft and its suppliers. All rights reserved. This API cannot be accessed and the content and any results may not be used, reproduced or transmitted in any manner without express written permission from Microsoft Corporation.",
				"entityType": "Postcode1",
				"matchCodes": [
					"UpHierarchy"
				],
				"name": "Saranac, NY 12918",
				"statusCode": 200,
				"statusDescription": "OK",
				"traceId": "c15e4b1bd7dc4710be3f0c676a8f1f34|BN20130522|7.7.0.0|",
				"adminDistrict": "NY",
				"adminDistrict2": "Clinton",
				"countryRegion": "United States",
				"formattedAddress": "Saranac, NY 12918",
				"locality": "Saranac",
				"postalCode": "12918"
			},
			"geometry": {
				"type": "Point",
				"coordinates": [
					-73.6280364990234,
					44.6999244689941
				]
			},
			"bbox": [
				-73.7354507446289,
				44.6072311401367,
				-73.605339050293,
				44.7772254943848
			]
		}
	]
}
