{
	"type": "FeatureCollection",
	"features": [
		{
			"type": "Feature",
			"properties": {
				"confidence": 9,
				"authenticationResultCode": "ValidCredentials",
				"brandLogoUri": "http://dev.virtualearth.net/Branding/logo_powered_by.png",
				"copyright": "Copyright © 2017 Microsoft and its suppliers. All rights reserved. This API cannot be accessed and the content and any results may not be used, reproduced or transmitted in any manner without express written permission from Microsoft Corporation.",
				"entityType": "Address",
				"matchCodes": [
					"Good"
				],
				"name": "1295 Ellice Ave, Winnipeg, MB R3G 0N5, Canada",
				"statusCode": 200,
				"statusDescription": "OK",
				"traceId": "ec87f8b4308a41a9ab583d5e5db8fb1e|BN20160335|7.7.0.0|",
				"addressLine": "1295 Ellice Ave",
				"adminDistrict": "MB",
				"adminDistrict2": "Manitoba",
				"countryRegion": "Canada",
				"formattedAddress": "1295 Ellice Ave, Winnipeg, MB R3G 0N5, Canada",
				"locality": "Winnipeg",
				"neighborhood": "Sargent Park",
				"postalCode": "R3G 0N5"
			},
			"geometry": {
				"type": "Point",
				"coordinates": [
					-97.19163,
					49.89456
				]
			},
			"bbox": [
				-97.193375,
				49.8934358,
				-97.189885,
				49.8956842
			]
		}
	]
}
