{
	"type": "FeatureCollection",
	"features": [
		{
			"type": "Feature",
			"properties": {
				"confidence": 9,
				"authenticationResultCode": "ValidCredentials",
				"brandLogoUri": "http://dev.virtualearth.net/Branding/logo_powered_by.png",
				"copyright": "Copyright © 2017 Microsoft and its suppliers. All rights reserved. This API cannot be accessed and the content and any results may not be used, reproduced or transmitted in any manner without express written permission from Microsoft Corporation.",
				"entityType": "Address",
				"matchCodes": [
					"Good"
				],
				"name": "1299 Commerce Way, Woodstock, ON N4V 0A2, Canada",
				"statusCode": 200,
				"statusDescription": "OK",
				"traceId": "e16876f9101b4c7b84cff6c3ef2ec529|BN20190653|7.7.0.0|",
				"addressLine": "1299 Commerce Way",
				"adminDistrict": "ON",
				"adminDistrict2": "Oxford",
				"countryRegion": "Canada",
				"formattedAddress": "1299 Commerce Way, Woodstock, ON N4V 0A2, Canada",
				"locality": "Woodstock",
				"postalCode": "N4V 0A2"
			},
			"geometry": {
				"type": "Point",
				"coordinates": [
					-80.7169897,
					43.1208541
				]
			},
			"bbox": [
				-80.7185298,
				43.11973,
				-80.7154496,
				43.1219783
			]
		}
	]
}
