{
	"type": "FeatureCollection",
	"features": [
		{
			"type": "Feature",
			"properties": {
				"confidence": 9,
				"authenticationResultCode": "ValidCredentials",
				"brandLogoUri": "http://dev.virtualearth.net/Branding/logo_powered_by.png",
				"copyright": "Copyright © 2017 Microsoft and its suppliers. All rights reserved. This API cannot be accessed and the content and any results may not be used, reproduced or transmitted in any manner without express written permission from Microsoft Corporation.",
				"entityType": "Address",
				"matchCodes": [
					"Good"
				],
				"name": "13 Collier St, Barrie, ON L4M 1G5, Canada",
				"statusCode": 200,
				"statusDescription": "OK",
				"traceId": "c0bd7cdb44964e4cbfc70b3146a3a512|BN20130621|7.7.0.0|",
				"addressLine": "13 Collier St",
				"adminDistrict": "ON",
				"adminDistrict2": "Simcoe",
				"countryRegion": "Canada",
				"formattedAddress": "13 Collier St, Barrie, ON L4M 1G5, Canada",
				"locality": "Barrie",
				"neighborhood": "City Center",
				"postalCode": "L4M 1G5"
			},
			"geometry": {
				"type": "Point",
				"coordinates": [
					-79.6897566,
					44.3902462
				]
			},
			"bbox": [
				-79.6913298,
				44.3891221,
				-79.6881835,
				44.3913704
			]
		}
	]
}
