{
	"type": "FeatureCollection",
	"features": [
		{
			"type": "Feature",
			"properties": {
				"confidence": 9,
				"authenticationResultCode": "ValidCredentials",
				"brandLogoUri": "http://dev.virtualearth.net/Branding/logo_powered_by.png",
				"copyright": "Copyright © 2017 Microsoft and its suppliers. All rights reserved. This API cannot be accessed and the content and any results may not be used, reproduced or transmitted in any manner without express written permission from Microsoft Corporation.",
				"entityType": "Address",
				"matchCodes": [
					"Good"
				],
				"name": "13 Strathford Pl, Strathmore, AB T1P 1S4, Canada",
				"statusCode": 200,
				"statusDescription": "OK",
				"traceId": "e00d479dacf74f46a805b0fc463819ea|BN20130533|7.7.0.0|",
				"addressLine": "13 Strathford Pl",
				"adminDistrict": "AB",
				"adminDistrict2": "Alberta",
				"countryRegion": "Canada",
				"formattedAddress": "13 Strathford Pl, Strathmore, AB T1P 1S4, Canada",
				"locality": "Strathmore",
				"postalCode": "T1P 1S4"
			},
			"geometry": {
				"type": "Point",
				"coordinates": [
					-113.38263,
					51.06419
				]
			},
			"bbox": [
				-113.3844188,
				51.0630658,
				-113.3808412,
				51.0653142
			]
		}
	]
}
