{
	"type": "FeatureCollection",
	"features": [
		{
			"type": "Feature",
			"properties": {
				"confidence": 9,
				"authenticationResultCode": "ValidCredentials",
				"brandLogoUri": "http://dev.virtualearth.net/Branding/logo_powered_by.png",
				"copyright": "Copyright © 2017 Microsoft and its suppliers. All rights reserved. This API cannot be accessed and the content and any results may not be used, reproduced or transmitted in any manner without express written permission from Microsoft Corporation.",
				"entityType": "Address",
				"matchCodes": [
					"Good"
				],
				"name": "13171 Mitchell Rd, Richmond, BC V6V 1M7, Canada",
				"statusCode": 200,
				"statusDescription": "OK",
				"traceId": "c37a9e2b24ee4383a75c1ad4ea9d697a|BN20130721|7.7.0.0|",
				"addressLine": "13171 Mitchell Rd",
				"adminDistrict": "BC",
				"adminDistrict2": "Greater Vancouver",
				"countryRegion": "Canada",
				"formattedAddress": "13171 Mitchell Rd, Richmond, BC V6V 1M7, Canada",
				"locality": "Richmond",
				"neighborhood": "Bridgeport",
				"postalCode": "V6V 1M7"
			},
			"geometry": {
				"type": "Point",
				"coordinates": [
					-123.0746868,
					49.205754
				]
			},
			"bbox": [
				-123.0764074,
				49.2046298,
				-123.0729662,
				49.2068781
			]
		}
	]
}
