{
	"type": "FeatureCollection",
	"features": [
		{
			"type": "Feature",
			"properties": {
				"confidence": 9,
				"authenticationResultCode": "ValidCredentials",
				"brandLogoUri": "http://dev.virtualearth.net/Branding/logo_powered_by.png",
				"copyright": "Copyright © 2017 Microsoft and its suppliers. All rights reserved. This API cannot be accessed and the content and any results may not be used, reproduced or transmitted in any manner without express written permission from Microsoft Corporation.",
				"entityType": "Address",
				"matchCodes": [
					"Good"
				],
				"name": "132 Rue 16e, Shippagan, NB E8S 2K2, Canada",
				"statusCode": 200,
				"statusDescription": "OK",
				"traceId": "6fe609b19f63479bb7ab491e3dce1063|BN20130423|7.7.0.0|",
				"addressLine": "132 Rue 16e",
				"adminDistrict": "NB",
				"adminDistrict2": "Gloucester",
				"countryRegion": "Canada",
				"formattedAddress": "132 Rue 16e, Shippagan, NB E8S 2K2, Canada",
				"locality": "Shippagan",
				"postalCode": "E8S 2K2"
			},
			"geometry": {
				"type": "Point",
				"coordinates": [
					-64.7024084,
					47.7415377
				]
			},
			"bbox": [
				-64.7040801,
				47.7404135,
				-64.7007368,
				47.7426618
			]
		}
	]
}
