{
	"type": "FeatureCollection",
	"features": [
		{
			"type": "Feature",
			"properties": {
				"confidence": 9,
				"authenticationResultCode": "ValidCredentials",
				"brandLogoUri": "http://dev.virtualearth.net/Branding/logo_powered_by.png",
				"copyright": "Copyright © 2017 Microsoft and its suppliers. All rights reserved. This API cannot be accessed and the content and any results may not be used, reproduced or transmitted in any manner without express written permission from Microsoft Corporation.",
				"entityType": "Address",
				"matchCodes": [
					"Good"
				],
				"name": "1320 36 St N, Lethbridge, AB T1H 5H8, Canada",
				"statusCode": 200,
				"statusDescription": "OK",
				"traceId": "38076dae844e40579997994cc5211cce|BN20130431|7.7.0.0|",
				"addressLine": "1320 36 St N",
				"adminDistrict": "AB",
				"adminDistrict2": "Alberta",
				"countryRegion": "Canada",
				"formattedAddress": "1320 36 St N, Lethbridge, AB T1H 5H8, Canada",
				"locality": "Lethbridge",
				"postalCode": "T1H 5H8"
			},
			"geometry": {
				"type": "Point",
				"coordinates": [
					-112.78998,
					49.71735
				]
			},
			"bbox": [
				-112.7917187,
				49.7162258,
				-112.7882413,
				49.7184742
			]
		}
	]
}
