{
	"type": "FeatureCollection",
	"features": [
		{
			"type": "Feature",
			"properties": {
				"confidence": 9,
				"authenticationResultCode": "ValidCredentials",
				"brandLogoUri": "http://dev.virtualearth.net/Branding/logo_powered_by.png",
				"copyright": "Copyright © 2017 Microsoft and its suppliers. All rights reserved. This API cannot be accessed and the content and any results may not be used, reproduced or transmitted in any manner without express written permission from Microsoft Corporation.",
				"entityType": "Address",
				"matchCodes": [
					"Good"
				],
				"name": "13212 82 St NW, Edmonton, AB T5E 2T7, Canada",
				"statusCode": 200,
				"statusDescription": "OK",
				"traceId": "382cd9eebdd040c0866428d51b91dcaa|BN20181720|7.7.0.0|",
				"addressLine": "13212 82 St NW",
				"adminDistrict": "AB",
				"adminDistrict2": "Alberta",
				"countryRegion": "Canada",
				"formattedAddress": "13212 82 St NW, Edmonton, AB T5E 2T7, Canada",
				"locality": "Edmonton",
				"neighborhood": "Glengarry",
				"postalCode": "T5E 2T7"
			},
			"geometry": {
				"type": "Point",
				"coordinates": [
					-113.46779,
					53.5926199
				]
			},
			"bbox": [
				-113.469684,
				53.5914957,
				-113.465896,
				53.5937441
			]
		}
	]
}
