{
	"type": "FeatureCollection",
	"features": [
		{
			"type": "Feature",
			"properties": {
				"confidence": 9,
				"authenticationResultCode": "ValidCredentials",
				"brandLogoUri": "http://dev.virtualearth.net/Branding/logo_powered_by.png",
				"copyright": "Copyright © 2017 Microsoft and its suppliers. All rights reserved. This API cannot be accessed and the content and any results may not be used, reproduced or transmitted in any manner without express written permission from Microsoft Corporation.",
				"entityType": "Address",
				"matchCodes": [
					"Good"
				],
				"name": "1321 Rue de la Manic, Chicoutimi, QC G7K 1G7, Canada",
				"statusCode": 200,
				"statusDescription": "OK",
				"traceId": "582043511c5445539a0e900db503d552|BN20130442|7.7.0.0|",
				"addressLine": "1321 Rue de la Manic",
				"adminDistrict": "QC",
				"adminDistrict2": "Saguenay",
				"countryRegion": "Canada",
				"formattedAddress": "1321 Rue de la Manic, Chicoutimi, QC G7K 1G7, Canada",
				"locality": "Saguenay",
				"neighborhood": "Chicoutimi",
				"postalCode": "G7K 1G7"
			},
			"geometry": {
				"type": "Point",
				"coordinates": [
					-71.11395,
					48.39964
				]
			},
			"bbox": [
				-71.1156432,
				48.3985158,
				-71.1122568,
				48.4007642
			]
		}
	]
}
