{
	"type": "FeatureCollection",
	"features": [
		{
			"type": "Feature",
			"properties": {
				"confidence": 9,
				"authenticationResultCode": "ValidCredentials",
				"brandLogoUri": "http://dev.virtualearth.net/Branding/logo_powered_by.png",
				"copyright": "Copyright © 2017 Microsoft and its suppliers. All rights reserved. This API cannot be accessed and the content and any results may not be used, reproduced or transmitted in any manner without express written permission from Microsoft Corporation.",
				"entityType": "Address",
				"matchCodes": [
					"Good"
				],
				"name": "1321 Archibald St, Winnipeg, MB R2J 3A4, Canada",
				"statusCode": 200,
				"statusDescription": "OK",
				"traceId": "237d57f364244e35b750cd4899b15a39|BN20171457|7.7.0.0|",
				"addressLine": "1321 Archibald St",
				"adminDistrict": "MB",
				"adminDistrict2": "Manitoba",
				"countryRegion": "Canada",
				"formattedAddress": "1321 Archibald St, Winnipeg, MB R2J 3A4, Canada",
				"locality": "Winnipeg",
				"neighborhood": "Niakwa Park",
				"postalCode": "R2J 3A4"
			},
			"geometry": {
				"type": "Point",
				"coordinates": [
					-97.0866852,
					49.8578624
				]
			},
			"bbox": [
				-97.0884289,
				49.8567383,
				-97.0849415,
				49.8589866
			]
		}
	]
}
