{
	"type": "FeatureCollection",
	"features": [
		{
			"type": "Feature",
			"properties": {
				"confidence": 7,
				"authenticationResultCode": "ValidCredentials",
				"brandLogoUri": "http://dev.virtualearth.net/Branding/logo_powered_by.png",
				"copyright": "Copyright © 2017 Microsoft and its suppliers. All rights reserved. This API cannot be accessed and the content and any results may not be used, reproduced or transmitted in any manner without express written permission from Microsoft Corporation.",
				"entityType": "Postcode1",
				"matchCodes": [
					"UpHierarchy"
				],
				"name": "Niagara Falls, L2E 6S5, Canada",
				"statusCode": 200,
				"statusDescription": "OK",
				"traceId": "1f32c43e838b49159710e0c9f4382b2d|BN20190642|7.7.0.0|",
				"adminDistrict": "ON",
				"adminDistrict2": "Niagara",
				"countryRegion": "Canada",
				"formattedAddress": "Niagara Falls, L2E 6S5, Canada",
				"locality": "Niagara Falls",
				"postalCode": "L2E 6S5"
			},
			"geometry": {
				"type": "Point",
				"coordinates": [
					-79.1458282470703,
					43.0447807312012
				]
			},
			"bbox": [
				-79.1528750748593,
				43.0409180136305,
				-79.1387814192814,
				43.0486434487718
			]
		}
	]
}
