{
	"type": "FeatureCollection",
	"features": [
		{
			"type": "Feature",
			"properties": {
				"confidence": 9,
				"authenticationResultCode": "ValidCredentials",
				"brandLogoUri": "http://dev.virtualearth.net/Branding/logo_powered_by.png",
				"copyright": "Copyright © 2017 Microsoft and its suppliers. All rights reserved. This API cannot be accessed and the content and any results may not be used, reproduced or transmitted in any manner without express written permission from Microsoft Corporation.",
				"entityType": "Address",
				"matchCodes": [
					"Good"
				],
				"name": "1336 Chemin des Anglais, Terrebonne, QC J6X 4G3, Canada",
				"statusCode": 200,
				"statusDescription": "OK",
				"traceId": "9af9cd28ef314ad481d0b00c2b344e80|BN20171457|7.7.0.0|",
				"addressLine": "1336 Chemin des Anglais",
				"adminDistrict": "QC",
				"adminDistrict2": "Les Moulins",
				"countryRegion": "Canada",
				"formattedAddress": "1336 Chemin des Anglais, Terrebonne, QC J6X 4G3, Canada",
				"locality": "Terrebonne",
				"postalCode": "J6X 4G3"
			},
			"geometry": {
				"type": "Point",
				"coordinates": [
					-73.65769,
					45.72241
				]
			},
			"bbox": [
				-73.6593002,
				45.7212858,
				-73.6560798,
				45.7235342
			]
		}
	]
}
