{
	"type": "FeatureCollection",
	"features": [
		{
			"type": "Feature",
			"properties": {
				"confidence": 9,
				"authenticationResultCode": "ValidCredentials",
				"brandLogoUri": "http://dev.virtualearth.net/Branding/logo_powered_by.png",
				"copyright": "Copyright © 2017 Microsoft and its suppliers. All rights reserved. This API cannot be accessed and the content and any results may not be used, reproduced or transmitted in any manner without express written permission from Microsoft Corporation.",
				"entityType": "Address",
				"matchCodes": [
					"Good"
				],
				"name": "134 Government Rd, Weyburn, SK S4H 0P1, Canada",
				"statusCode": 200,
				"statusDescription": "OK",
				"traceId": "5f19fe9b87b9458fb3250ed46e19dc35|BN20130632|7.7.0.0|",
				"addressLine": "134 Government Rd",
				"adminDistrict": "SK",
				"adminDistrict2": "Saskatchewan",
				"countryRegion": "Canada",
				"formattedAddress": "134 Government Rd, Weyburn, SK S4H 0P1, Canada",
				"locality": "Weyburn",
				"postalCode": "S4H 0P1"
			},
			"geometry": {
				"type": "Point",
				"coordinates": [
					-103.8580551,
					49.663247
				]
			},
			"bbox": [
				-103.8597918,
				49.6621229,
				-103.8563184,
				49.6643712
			]
		}
	]
}
