{
	"type": "FeatureCollection",
	"features": [
		{
			"type": "Feature",
			"properties": {
				"confidence": 9,
				"authenticationResultCode": "ValidCredentials",
				"brandLogoUri": "http://dev.virtualearth.net/Branding/logo_powered_by.png",
				"copyright": "Copyright © 2017 Microsoft and its suppliers. All rights reserved. This API cannot be accessed and the content and any results may not be used, reproduced or transmitted in any manner without express written permission from Microsoft Corporation.",
				"entityType": "Address",
				"matchCodes": [
					"Good"
				],
				"name": "134 Duncan St, Wallaceburg, ON N8A 4E2, Canada",
				"statusCode": 200,
				"statusDescription": "OK",
				"traceId": "d474625ab6484b74ade4750059fffc56|BN20181720|7.7.0.0|",
				"addressLine": "134 Duncan St",
				"adminDistrict": "ON",
				"adminDistrict2": "Chatham-Kent",
				"countryRegion": "Canada",
				"formattedAddress": "134 Duncan St, Wallaceburg, ON N8A 4E2, Canada",
				"locality": "Chatham-Kent",
				"neighborhood": "Wallaceburg",
				"postalCode": "N8A 4E2"
			},
			"geometry": {
				"type": "Point",
				"coordinates": [
					-82.3838153,
					42.5948631
				]
			},
			"bbox": [
				-82.3853423,
				42.5937389,
				-82.3822882,
				42.5959872
			]
		}
	]
}
