{
	"type": "FeatureCollection",
	"features": [
		{
			"type": "Feature",
			"properties": {
				"confidence": 9,
				"authenticationResultCode": "ValidCredentials",
				"brandLogoUri": "http://dev.virtualearth.net/Branding/logo_powered_by.png",
				"copyright": "Copyright © 2017 Microsoft and its suppliers. All rights reserved. This API cannot be accessed and the content and any results may not be used, reproduced or transmitted in any manner without express written permission from Microsoft Corporation.",
				"entityType": "Address",
				"matchCodes": [
					"Good"
				],
				"name": "1345 Driver Ln, London, ON N5V 0B4, Canada",
				"statusCode": 200,
				"statusDescription": "OK",
				"traceId": "6cb54207202e45069125cfb23489b3dc|BN20130520|7.7.0.0|",
				"addressLine": "1345 Driver Ln",
				"adminDistrict": "ON",
				"adminDistrict2": "Middlesex",
				"countryRegion": "Canada",
				"formattedAddress": "1345 Driver Ln, London, ON N5V 0B4, Canada",
				"locality": "London",
				"neighborhood": "Crumlin",
				"postalCode": "N5V 0B4"
			},
			"geometry": {
				"type": "Point",
				"coordinates": [
					-81.1511725,
					43.0127768
				]
			},
			"bbox": [
				-81.1527099,
				43.0116526,
				-81.1496351,
				43.013901
			]
		}
	]
}
