{
	"type": "FeatureCollection",
	"features": [
		{
			"type": "Feature",
			"properties": {
				"confidence": 9,
				"authenticationResultCode": "ValidCredentials",
				"brandLogoUri": "http://dev.virtualearth.net/Branding/logo_powered_by.png",
				"copyright": "Copyright © 2017 Microsoft and its suppliers. All rights reserved. This API cannot be accessed and the content and any results may not be used, reproduced or transmitted in any manner without express written permission from Microsoft Corporation.",
				"entityType": "Address",
				"matchCodes": [
					"Good"
				],
				"name": "135 Riverside Dr, North Vancouver, BC V7H 1T6, Canada",
				"statusCode": 200,
				"statusDescription": "OK",
				"traceId": "ab0ea779e1024a078e1e1731cda282f1|BN20240253|7.7.0.0|",
				"addressLine": "135 Riverside Dr",
				"adminDistrict": "BC",
				"adminDistrict2": "Greater Vancouver",
				"countryRegion": "Canada",
				"formattedAddress": "135 Riverside Dr, North Vancouver, BC V7H 1T6, Canada",
				"locality": "North Vancouver District",
				"neighborhood": "Maplewood",
				"postalCode": "V7H 1T6"
			},
			"geometry": {
				"type": "Point",
				"coordinates": [
					-123.02117,
					49.30436
				]
			},
			"bbox": [
				-123.0228941,
				49.3032358,
				-123.0194459,
				49.3054842
			]
		}
	]
}
