{
	"type": "FeatureCollection",
	"features": [
		{
			"type": "Feature",
			"properties": {
				"confidence": 9,
				"authenticationResultCode": "ValidCredentials",
				"brandLogoUri": "http://dev.virtualearth.net/Branding/logo_powered_by.png",
				"copyright": "Copyright © 2017 Microsoft and its suppliers. All rights reserved. This API cannot be accessed and the content and any results may not be used, reproduced or transmitted in any manner without express written permission from Microsoft Corporation.",
				"entityType": "Address",
				"matchCodes": [
					"Good"
				],
				"name": "13552 97 St NW, Edmonton, AB T5E 4E2, Canada",
				"statusCode": 200,
				"statusDescription": "OK",
				"traceId": "b6b7d5da5a72459bb3fb5774bedb4c9a|BN20220145|7.7.0.0|",
				"addressLine": "13552 97 St NW",
				"adminDistrict": "AB",
				"adminDistrict2": "Alberta",
				"countryRegion": "Canada",
				"formattedAddress": "13552 97 St NW, Edmonton, AB T5E 4E2, Canada",
				"locality": "Edmonton",
				"neighborhood": "Rosslyn",
				"postalCode": "T5E 4E2"
			},
			"geometry": {
				"type": "Point",
				"coordinates": [
					-113.49301,
					53.59786
				]
			},
			"bbox": [
				-113.4949043,
				53.5967358,
				-113.4911157,
				53.5989842
			]
		}
	]
}
