{
	"type": "FeatureCollection",
	"features": [
		{
			"type": "Feature",
			"properties": {
				"confidence": 9,
				"authenticationResultCode": "ValidCredentials",
				"brandLogoUri": "http://dev.virtualearth.net/Branding/logo_powered_by.png",
				"copyright": "Copyright © 2017 Microsoft and its suppliers. All rights reserved. This API cannot be accessed and the content and any results may not be used, reproduced or transmitted in any manner without express written permission from Microsoft Corporation.",
				"entityType": "Address",
				"matchCodes": [
					"Good"
				],
				"name": "1355 Plains Rd E, Burlington, ON L7R 3P7, Canada",
				"statusCode": 200,
				"statusDescription": "OK",
				"traceId": "a2a7bc6872dc462c936769401e1a00b4|BN20200137|7.7.0.0|",
				"addressLine": "1355 Plains Rd E",
				"adminDistrict": "ON",
				"adminDistrict2": "Halton",
				"countryRegion": "Canada",
				"formattedAddress": "1355 Plains Rd E, Burlington, ON L7R 3P7, Canada",
				"locality": "Burlington",
				"neighborhood": "Maple",
				"postalCode": "L7R 3P7"
			},
			"geometry": {
				"type": "Point",
				"coordinates": [
					-79.82019,
					43.3357
				]
			},
			"bbox": [
				-79.8217356,
				43.3345758,
				-79.8186444,
				43.3368242
			]
		}
	]
}
