{
	"type": "FeatureCollection",
	"features": [
		{
			"type": "Feature",
			"properties": {
				"confidence": 9,
				"authenticationResultCode": "ValidCredentials",
				"brandLogoUri": "http://dev.virtualearth.net/Branding/logo_powered_by.png",
				"copyright": "Copyright © 2017 Microsoft and its suppliers. All rights reserved. This API cannot be accessed and the content and any results may not be used, reproduced or transmitted in any manner without express written permission from Microsoft Corporation.",
				"entityType": "Address",
				"matchCodes": [
					"Good"
				],
				"name": "136 Boulevard Taschereau, La Prairie, QC J5R 1S8, Canada",
				"statusCode": 200,
				"statusDescription": "OK",
				"traceId": "e88882e90e224f6e8ed2e7fc3d55be17|BN20130442|7.7.0.0|",
				"addressLine": "136 Boulevard Taschereau",
				"adminDistrict": "QC",
				"adminDistrict2": "Roussillon",
				"countryRegion": "Canada",
				"formattedAddress": "136 Boulevard Taschereau, La Prairie, QC J5R 1S8, Canada",
				"locality": "La Prairie",
				"postalCode": "J5R 1S8"
			},
			"geometry": {
				"type": "Point",
				"coordinates": [
					-73.4877,
					45.41889
				]
			},
			"bbox": [
				-73.4893015,
				45.4177658,
				-73.4860985,
				45.4200142
			]
		}
	]
}
