{
	"type": "FeatureCollection",
	"features": [
		{
			"type": "Feature",
			"properties": {
				"confidence": 9,
				"authenticationResultCode": "ValidCredentials",
				"brandLogoUri": "http://dev.virtualearth.net/Branding/logo_powered_by.png",
				"copyright": "Copyright © 2017 Microsoft and its suppliers. All rights reserved. This API cannot be accessed and the content and any results may not be used, reproduced or transmitted in any manner without express written permission from Microsoft Corporation.",
				"entityType": "Address",
				"matchCodes": [
					"Good"
				],
				"name": "136 Rue Racine E, Chicoutimi, QC G7H 1R7, Canada",
				"statusCode": 200,
				"statusDescription": "OK",
				"traceId": "7adf594e6ca54378bb56638cf5c7ee7e|BN20220145|7.7.0.0|",
				"addressLine": "136 Rue Racine E",
				"adminDistrict": "QC",
				"adminDistrict2": "Saguenay",
				"countryRegion": "Canada",
				"formattedAddress": "136 Rue Racine E, Chicoutimi, QC G7H 1R7, Canada",
				"locality": "Saguenay",
				"neighborhood": "Chicoutimi",
				"postalCode": "G7H 1R7"
			},
			"geometry": {
				"type": "Point",
				"coordinates": [
					-71.06424,
					48.42757
				]
			},
			"bbox": [
				-71.0659341,
				48.4264458,
				-71.0625459,
				48.4286942
			]
		}
	]
}
