{
	"type": "FeatureCollection",
	"features": [
		{
			"type": "Feature",
			"properties": {
				"confidence": 9,
				"authenticationResultCode": "ValidCredentials",
				"brandLogoUri": "http://dev.virtualearth.net/Branding/logo_powered_by.png",
				"copyright": "Copyright © 2017 Microsoft and its suppliers. All rights reserved. This API cannot be accessed and the content and any results may not be used, reproduced or transmitted in any manner without express written permission from Microsoft Corporation.",
				"entityType": "Address",
				"matchCodes": [
					"Good"
				],
				"name": "1360 Inkster Blvd, Winnipeg, MB R2X 3C5, Canada",
				"statusCode": 200,
				"statusDescription": "OK",
				"traceId": "e73dc1968e3f4a29b6c935f051529dfc|BN20130533|7.7.0.0|",
				"addressLine": "1360 Inkster Blvd",
				"adminDistrict": "MB",
				"adminDistrict2": "Manitoba",
				"countryRegion": "Canada",
				"formattedAddress": "1360 Inkster Blvd, Winnipeg, MB R2X 3C5, Canada",
				"locality": "Winnipeg",
				"neighborhood": "Inkster Industrial Park",
				"postalCode": "R2X 3C5"
			},
			"geometry": {
				"type": "Point",
				"coordinates": [
					-97.1706512,
					49.9421645
				]
			},
			"bbox": [
				-97.172398,
				49.9410403,
				-97.1689044,
				49.9432886
			]
		}
	]
}
