{
	"type": "FeatureCollection",
	"features": [
		{
			"type": "Feature",
			"properties": {
				"confidence": 9,
				"authenticationResultCode": "ValidCredentials",
				"brandLogoUri": "http://dev.virtualearth.net/Branding/logo_powered_by.png",
				"copyright": "Copyright © 2017 Microsoft and its suppliers. All rights reserved. This API cannot be accessed and the content and any results may not be used, reproduced or transmitted in any manner without express written permission from Microsoft Corporation.",
				"entityType": "Address",
				"matchCodes": [
					"Good"
				],
				"name": "1361 Una Way, Port Coquitlam, BC V3C 2V1, Canada",
				"statusCode": 200,
				"statusDescription": "OK",
				"traceId": "127ccc5095ac46f1856e4b35fa7155d0|BN20130721|7.7.0.0|",
				"addressLine": "1361 Una Way",
				"adminDistrict": "BC",
				"adminDistrict2": "Greater Vancouver",
				"countryRegion": "Canada",
				"formattedAddress": "1361 Una Way, Port Coquitlam, BC V3C 2V1, Canada",
				"locality": "Port Coquitlam",
				"postalCode": "V3C 2V1"
			},
			"geometry": {
				"type": "Point",
				"coordinates": [
					-122.7784605,
					49.2398746
				]
			},
			"bbox": [
				-122.7801823,
				49.2387504,
				-122.7767387,
				49.2409987
			]
		}
	]
}
