{
	"type": "FeatureCollection",
	"features": [
		{
			"type": "Feature",
			"properties": {
				"confidence": 9,
				"authenticationResultCode": "ValidCredentials",
				"brandLogoUri": "http://dev.virtualearth.net/Branding/logo_powered_by.png",
				"copyright": "Copyright © 2017 Microsoft and its suppliers. All rights reserved. This API cannot be accessed and the content and any results may not be used, reproduced or transmitted in any manner without express written permission from Microsoft Corporation.",
				"entityType": "Address",
				"matchCodes": [
					"Good"
				],
				"name": "1367 Sandhills Rd, New Hamburg, ON N3A 3B1, Canada",
				"statusCode": 200,
				"statusDescription": "OK",
				"traceId": "9cff290cb88b43948372df51b7aea0f3|BN20260231|7.7.0.0|",
				"addressLine": "1367 Sandhills Rd",
				"adminDistrict": "ON",
				"adminDistrict2": "Waterloo",
				"countryRegion": "Canada",
				"formattedAddress": "1367 Sandhills Rd, New Hamburg, ON N3A 3B1, Canada",
				"locality": "Wilmot",
				"neighborhood": "New Hamburg",
				"postalCode": "N3A 3B1"
			},
			"geometry": {
				"type": "Point",
				"coordinates": [
					-80.58677,
					43.35019
				]
			},
			"bbox": [
				-80.5883159,
				43.3490658,
				-80.5852241,
				43.3513142
			]
		}
	]
}
