{
	"type": "FeatureCollection",
	"features": [
		{
			"type": "Feature",
			"properties": {
				"confidence": 9,
				"authenticationResultCode": "ValidCredentials",
				"brandLogoUri": "http://dev.virtualearth.net/Branding/logo_powered_by.png",
				"copyright": "Copyright © 2017 Microsoft and its suppliers. All rights reserved. This API cannot be accessed and the content and any results may not be used, reproduced or transmitted in any manner without express written permission from Microsoft Corporation.",
				"entityType": "Address",
				"matchCodes": [
					"Good"
				],
				"name": "1370 55e Avenue, Lachine, QC H8T 3J8, Canada",
				"statusCode": 200,
				"statusDescription": "OK",
				"traceId": "73e90a636523415284e1801acb7da34a|BN20190653|7.7.0.0|",
				"addressLine": "1370 55e Avenue",
				"adminDistrict": "QC",
				"adminDistrict2": "Montreal",
				"countryRegion": "Canada",
				"formattedAddress": "1370 55e Avenue, Lachine, QC H8T 3J8, Canada",
				"locality": "Montreal",
				"neighborhood": "Lachine",
				"postalCode": "H8T 3J8"
			},
			"geometry": {
				"type": "Point",
				"coordinates": [
					-73.72072,
					45.45161
				]
			},
			"bbox": [
				-73.7223225,
				45.4504858,
				-73.7191175,
				45.4527342
			]
		}
	]
}
