{
	"type": "FeatureCollection",
	"features": [
		{
			"type": "Feature",
			"properties": {
				"confidence": 9,
				"authenticationResultCode": "ValidCredentials",
				"brandLogoUri": "http://dev.virtualearth.net/Branding/logo_powered_by.png",
				"copyright": "Copyright © 2017 Microsoft and its suppliers. All rights reserved. This API cannot be accessed and the content and any results may not be used, reproduced or transmitted in any manner without express written permission from Microsoft Corporation.",
				"entityType": "Address",
				"matchCodes": [
					"Good"
				],
				"name": "1375 Weber St E, Kitchener, ON N2A 3Y7, Canada",
				"statusCode": 200,
				"statusDescription": "OK",
				"traceId": "31e75cc7be164583b2a2143d7d4c8a84|BN20130532|7.7.0.0|",
				"addressLine": "1375 Weber St E",
				"adminDistrict": "ON",
				"adminDistrict2": "Waterloo",
				"countryRegion": "Canada",
				"formattedAddress": "1375 Weber St E, Kitchener, ON N2A 3Y7, Canada",
				"locality": "Kitchener",
				"neighborhood": "Centreville Chicopee",
				"postalCode": "N2A 3Y7"
			},
			"geometry": {
				"type": "Point",
				"coordinates": [
					-80.4414,
					43.43202
				]
			},
			"bbox": [
				-80.442948,
				43.4308958,
				-80.439852,
				43.4331442
			]
		}
	]
}
