{
	"type": "FeatureCollection",
	"features": [
		{
			"type": "Feature",
			"properties": {
				"confidence": 9,
				"authenticationResultCode": "ValidCredentials",
				"brandLogoUri": "http://dev.virtualearth.net/Branding/logo_powered_by.png",
				"copyright": "Copyright © 2017 Microsoft and its suppliers. All rights reserved. This API cannot be accessed and the content and any results may not be used, reproduced or transmitted in any manner without express written permission from Microsoft Corporation.",
				"entityType": "Address",
				"matchCodes": [
					"Good"
				],
				"name": "1377 Christina Ct, Burlington, ON L7P 2V8, Canada",
				"statusCode": 200,
				"statusDescription": "OK",
				"traceId": "2707ae41441d42e696911bceec3b945c|BN20240253|7.7.0.0|",
				"addressLine": "1377 Christina Ct",
				"adminDistrict": "ON",
				"adminDistrict2": "Halton",
				"countryRegion": "Canada",
				"formattedAddress": "1377 Christina Ct, Burlington, ON L7P 2V8, Canada",
				"locality": "Burlington",
				"neighborhood": "Tyandaga",
				"postalCode": "L7P 2V8"
			},
			"geometry": {
				"type": "Point",
				"coordinates": [
					-79.83557,
					43.3480599
				]
			},
			"bbox": [
				-79.8371159,
				43.3469357,
				-79.8340241,
				43.3491841
			]
		}
	]
}
