{
	"type": "FeatureCollection",
	"features": [
		{
			"type": "Feature",
			"properties": {
				"confidence": 9,
				"authenticationResultCode": "ValidCredentials",
				"brandLogoUri": "http://dev.virtualearth.net/Branding/logo_powered_by.png",
				"copyright": "Copyright © 2017 Microsoft and its suppliers. All rights reserved. This API cannot be accessed and the content and any results may not be used, reproduced or transmitted in any manner without express written permission from Microsoft Corporation.",
				"entityType": "Address",
				"matchCodes": [
					"Good"
				],
				"name": "138 West St S, Orillia, ON L3V, Canada",
				"statusCode": 200,
				"statusDescription": "OK",
				"traceId": "2bd9b99f184e4aba8ef6618c1fda1e5e|BN20260231|7.7.0.0|",
				"addressLine": "138 West St S",
				"adminDistrict": "ON",
				"adminDistrict2": "Simcoe",
				"countryRegion": "Canada",
				"formattedAddress": "138 West St S, Orillia, ON L3V, Canada",
				"locality": "Orillia",
				"postalCode": "L3V 3B3"
			},
			"geometry": {
				"type": "Point",
				"coordinates": [
					-79.4169033,
					44.6052213
				]
			},
			"bbox": [
				-79.4184822,
				44.6040972,
				-79.4153243,
				44.6063455
			]
		}
	]
}
