{
	"type": "FeatureCollection",
	"features": [
		{
			"type": "Feature",
			"properties": {
				"confidence": 9,
				"authenticationResultCode": "ValidCredentials",
				"brandLogoUri": "http://dev.virtualearth.net/Branding/logo_powered_by.png",
				"copyright": "Copyright © 2017 Microsoft and its suppliers. All rights reserved. This API cannot be accessed and the content and any results may not be used, reproduced or transmitted in any manner without express written permission from Microsoft Corporation.",
				"entityType": "Address",
				"matchCodes": [
					"Good"
				],
				"name": "13811 Wireless Way, Richmond, BC V6V 3A4, Canada",
				"statusCode": 200,
				"statusDescription": "OK",
				"traceId": "3a4052b9fbf14af3813718222e1a3bd1|BN20130719|7.7.0.0|",
				"addressLine": "13811 Wireless Way",
				"adminDistrict": "BC",
				"adminDistrict2": "Greater Vancouver",
				"countryRegion": "Canada",
				"formattedAddress": "13811 Wireless Way, Richmond, BC V6V 3A4, Canada",
				"locality": "Richmond",
				"neighborhood": "East Cambie",
				"postalCode": "V6V 3A4"
			},
			"geometry": {
				"type": "Point",
				"coordinates": [
					-123.0707444,
					49.1718349
				]
			},
			"bbox": [
				-123.0724638,
				49.1707107,
				-123.0690249,
				49.1729591
			]
		}
	]
}
