{
	"type": "FeatureCollection",
	"features": [
		{
			"type": "Feature",
			"properties": {
				"confidence": 9,
				"authenticationResultCode": "ValidCredentials",
				"brandLogoUri": "http://dev.virtualearth.net/Branding/logo_powered_by.png",
				"copyright": "Copyright © 2017 Microsoft and its suppliers. All rights reserved. This API cannot be accessed and the content and any results may not be used, reproduced or transmitted in any manner without express written permission from Microsoft Corporation.",
				"entityType": "Address",
				"matchCodes": [
					"Good"
				],
				"name": "13904 Hurontario St, Caledon, ON L7C 2B8, Canada",
				"statusCode": 200,
				"statusDescription": "OK",
				"traceId": "2829e7c28fd5489cbbbe103969e20bad|BN20130533|7.7.0.0|",
				"addressLine": "13904 Hurontario St",
				"adminDistrict": "ON",
				"adminDistrict2": "Peel",
				"countryRegion": "Canada",
				"formattedAddress": "13904 Hurontario St, Caledon, ON L7C 2B8, Canada",
				"locality": "Caledon",
				"postalCode": "L7C 2B8"
			},
			"geometry": {
				"type": "Point",
				"coordinates": [
					-79.8765899,
					43.77078
				]
			},
			"bbox": [
				-79.8781467,
				43.7696558,
				-79.8750331,
				43.7719042
			]
		}
	]
}
