{
	"type": "FeatureCollection",
	"features": [
		{
			"type": "Feature",
			"properties": {
				"confidence": 9,
				"authenticationResultCode": "ValidCredentials",
				"brandLogoUri": "http://dev.virtualearth.net/Branding/logo_powered_by.png",
				"copyright": "Copyright © 2017 Microsoft and its suppliers. All rights reserved. This API cannot be accessed and the content and any results may not be used, reproduced or transmitted in any manner without express written permission from Microsoft Corporation.",
				"entityType": "Address",
				"matchCodes": [
					"Good"
				],
				"name": "14 Hull Ave, Winnipeg, MB R2M 0Y8, Canada",
				"statusCode": 200,
				"statusDescription": "OK",
				"traceId": "36b6f80354084206a327e663a03dd90d|BN20300154|7.7.0.0|",
				"addressLine": "14 Hull Ave",
				"adminDistrict": "MB",
				"adminDistrict2": "Manitoba",
				"countryRegion": "Canada",
				"formattedAddress": "14 Hull Ave, Winnipeg, MB R2M 0Y8, Canada",
				"locality": "Winnipeg",
				"neighborhood": "St George",
				"postalCode": "R2M 0Y8"
			},
			"geometry": {
				"type": "Point",
				"coordinates": [
					-97.11102,
					49.84948
				]
			},
			"bbox": [
				-97.1127634,
				49.8483558,
				-97.1092766,
				49.8506042
			]
		}
	]
}
