{
	"type": "FeatureCollection",
	"features": [
		{
			"type": "Feature",
			"properties": {
				"confidence": 9,
				"authenticationResultCode": "ValidCredentials",
				"brandLogoUri": "http://dev.virtualearth.net/Branding/logo_powered_by.png",
				"copyright": "Copyright © 2017 Microsoft and its suppliers. All rights reserved. This API cannot be accessed and the content and any results may not be used, reproduced or transmitted in any manner without express written permission from Microsoft Corporation.",
				"entityType": "Address",
				"matchCodes": [
					"Good"
				],
				"name": "14 Industrial Dr, Sussex, NB E4E 2R8, Canada",
				"statusCode": 200,
				"statusDescription": "OK",
				"traceId": "7fb3af0ddc7a4b12899c38170e73a8cb|BN20130620|7.7.0.0|",
				"addressLine": "14 Industrial Dr",
				"adminDistrict": "NB",
				"adminDistrict2": "Kings",
				"countryRegion": "Canada",
				"formattedAddress": "14 Industrial Dr, Sussex, NB E4E 2R8, Canada",
				"locality": "Sussex",
				"postalCode": "E4E 2R8"
			},
			"geometry": {
				"type": "Point",
				"coordinates": [
					-65.49041,
					45.73017
				]
			},
			"bbox": [
				-65.4920204,
				45.7290458,
				-65.4887996,
				45.7312942
			]
		}
	]
}
