{
	"type": "FeatureCollection",
	"features": [
		{
			"type": "Feature",
			"properties": {
				"confidence": 9,
				"authenticationResultCode": "ValidCredentials",
				"brandLogoUri": "http://dev.virtualearth.net/Branding/logo_powered_by.png",
				"copyright": "Copyright © 2017 Microsoft and its suppliers. All rights reserved. This API cannot be accessed and the content and any results may not be used, reproduced or transmitted in any manner without express written permission from Microsoft Corporation.",
				"entityType": "Address",
				"matchCodes": [
					"Good"
				],
				"name": "14 Queen St, Truro, NS B2N 2A8, Canada",
				"statusCode": 200,
				"statusDescription": "OK",
				"traceId": "363fe14ce72f4be1941b718868749670|BN20280152|7.7.0.0|",
				"addressLine": "14 Queen St",
				"adminDistrict": "NS",
				"adminDistrict2": "Colchester",
				"countryRegion": "Canada",
				"formattedAddress": "14 Queen St, Truro, NS B2N 2A8, Canada",
				"locality": "Truro",
				"postalCode": "B2N 2A8"
			},
			"geometry": {
				"type": "Point",
				"coordinates": [
					-63.2860181,
					45.3667123
				]
			},
			"bbox": [
				-63.2876181,
				45.3655881,
				-63.284418,
				45.3678365
			]
		}
	]
}
