{
	"type": "FeatureCollection",
	"features": [
		{
			"type": "Feature",
			"properties": {
				"confidence": 9,
				"authenticationResultCode": "ValidCredentials",
				"brandLogoUri": "http://dev.virtualearth.net/Branding/logo_powered_by.png",
				"copyright": "Copyright © 2017 Microsoft and its suppliers. All rights reserved. This API cannot be accessed and the content and any results may not be used, reproduced or transmitted in any manner without express written permission from Microsoft Corporation.",
				"entityType": "Address",
				"matchCodes": [
					"Good"
				],
				"name": "14 Woodward Ave, Blind River, ON P0R, Canada",
				"statusCode": 200,
				"statusDescription": "OK",
				"traceId": "001ddfd1b02648ebb363c96ec6b27c77|BN20130533|7.7.0.0|",
				"addressLine": "14 Woodward Ave",
				"adminDistrict": "ON",
				"adminDistrict2": "Algoma",
				"countryRegion": "Canada",
				"formattedAddress": "14 Woodward Ave, Blind River, ON P0R, Canada",
				"locality": "Blind River",
				"postalCode": "P0R 1B0"
			},
			"geometry": {
				"type": "Point",
				"coordinates": [
					-82.9543472,
					46.1858332
				]
			},
			"bbox": [
				-82.9559709,
				46.1847091,
				-82.9527234,
				46.1869574
			]
		}
	]
}
