{
	"type": "FeatureCollection",
	"features": [
		{
			"type": "Feature",
			"properties": {
				"confidence": 9,
				"authenticationResultCode": "ValidCredentials",
				"brandLogoUri": "http://dev.virtualearth.net/Branding/logo_powered_by.png",
				"copyright": "Copyright © 2017 Microsoft and its suppliers. All rights reserved. This API cannot be accessed and the content and any results may not be used, reproduced or transmitted in any manner without express written permission from Microsoft Corporation.",
				"entityType": "Address",
				"matchCodes": [
					"Good"
				],
				"name": "14026 Currie Rd, Dutton/Dunwich, ON N0L 1J0, Canada",
				"statusCode": 200,
				"statusDescription": "OK",
				"traceId": "5e23b3a2f9ee4d3ca06eda695cf0d645|BN20260223|7.7.0.0|",
				"addressLine": "14026 Currie Rd",
				"adminDistrict": "ON",
				"adminDistrict2": "Elgin",
				"countryRegion": "Canada",
				"formattedAddress": "14026 Currie Rd, Dutton/Dunwich, ON N0L 1J0, Canada",
				"locality": "Dutton/Dunwich",
				"postalCode": "N0L 1J0"
			},
			"geometry": {
				"type": "Point",
				"coordinates": [
					-81.56861,
					42.71718
				]
			},
			"bbox": [
				-81.5701401,
				42.7160558,
				-81.5670799,
				42.7183042
			]
		}
	]
}
