{
	"type": "FeatureCollection",
	"features": [
		{
			"type": "Feature",
			"properties": {
				"confidence": 9,
				"authenticationResultCode": "ValidCredentials",
				"brandLogoUri": "http://dev.virtualearth.net/Branding/logo_powered_by.png",
				"copyright": "Copyright © 2017 Microsoft and its suppliers. All rights reserved. This API cannot be accessed and the content and any results may not be used, reproduced or transmitted in any manner without express written permission from Microsoft Corporation.",
				"entityType": "Address",
				"matchCodes": [
					"Good"
				],
				"name": "1404 Scarth St, Regina, SK S4R 2E9, Canada",
				"statusCode": 200,
				"statusDescription": "OK",
				"traceId": "48e773f5918d447991db7710d404fcca|BN20130620|7.7.0.0|",
				"addressLine": "1404 Scarth St",
				"adminDistrict": "SK",
				"adminDistrict2": "Saskatchewan",
				"countryRegion": "Canada",
				"formattedAddress": "1404 Scarth St, Regina, SK S4R 2E9, Canada",
				"locality": "Regina",
				"neighborhood": "North Central",
				"postalCode": "S4R 2E9"
			},
			"geometry": {
				"type": "Point",
				"coordinates": [
					-104.61123,
					50.45658
				]
			},
			"bbox": [
				-104.6129957,
				50.4554558,
				-104.6094643,
				50.4577042
			]
		}
	]
}
