{
	"type": "FeatureCollection",
	"features": [
		{
			"type": "Feature",
			"properties": {
				"confidence": 9,
				"authenticationResultCode": "ValidCredentials",
				"brandLogoUri": "http://dev.virtualearth.net/Branding/logo_powered_by.png",
				"copyright": "Copyright © 2017 Microsoft and its suppliers. All rights reserved. This API cannot be accessed and the content and any results may not be used, reproduced or transmitted in any manner without express written permission from Microsoft Corporation.",
				"entityType": "Address",
				"matchCodes": [
					"Good"
				],
				"name": "14082 HWY-4, Havre Boucher, NS B0H 1P0, Canada",
				"statusCode": 200,
				"statusDescription": "OK",
				"traceId": "c9b27b5259654cf4a7758c49a00f6f57|BN20130521|7.7.0.0|",
				"addressLine": "14082 HWY-4",
				"adminDistrict": "NS",
				"adminDistrict2": "Antigonish",
				"countryRegion": "Canada",
				"formattedAddress": "14082 HWY-4, Havre Boucher, NS B0H 1P0, Canada",
				"locality": "Antigonish County",
				"neighborhood": "Havre Boucher",
				"postalCode": "B0H 1P0"
			},
			"geometry": {
				"type": "Point",
				"coordinates": [
					-61.4520475,
					45.6585831
				]
			},
			"bbox": [
				-61.4536559,
				45.6574589,
				-61.4504391,
				45.6597072
			]
		}
	]
}
