{
	"type": "FeatureCollection",
	"features": [
		{
			"type": "Feature",
			"properties": {
				"confidence": 9,
				"authenticationResultCode": "ValidCredentials",
				"brandLogoUri": "http://dev.virtualearth.net/Branding/logo_powered_by.png",
				"copyright": "Copyright © 2017 Microsoft and its suppliers. All rights reserved. This API cannot be accessed and the content and any results may not be used, reproduced or transmitted in any manner without express written permission from Microsoft Corporation.",
				"entityType": "Address",
				"matchCodes": [
					"Good"
				],
				"name": "141 Kennedy St W, Aurora, ON L4G 2L8, Canada",
				"statusCode": 200,
				"statusDescription": "OK",
				"traceId": "ad9d838a6b054a7db3fb52ba010f1667|BN20240253|7.7.0.0|",
				"addressLine": "141 Kennedy St W",
				"adminDistrict": "ON",
				"adminDistrict2": "York",
				"countryRegion": "Canada",
				"formattedAddress": "141 Kennedy St W, Aurora, ON L4G 2L8, Canada",
				"locality": "Aurora",
				"postalCode": "L4G 2L8"
			},
			"geometry": {
				"type": "Point",
				"coordinates": [
					-79.47505,
					43.99109
				]
			},
			"bbox": [
				-79.4766125,
				43.9899658,
				-79.4734875,
				43.9922142
			]
		}
	]
}
