{
	"type": "FeatureCollection",
	"features": [
		{
			"type": "Feature",
			"properties": {
				"confidence": 9,
				"authenticationResultCode": "ValidCredentials",
				"brandLogoUri": "http://dev.virtualearth.net/Branding/logo_powered_by.png",
				"copyright": "Copyright © 2017 Microsoft and its suppliers. All rights reserved. This API cannot be accessed and the content and any results may not be used, reproduced or transmitted in any manner without express written permission from Microsoft Corporation.",
				"entityType": "Address",
				"matchCodes": [
					"Good"
				],
				"name": "141 Regal Rd, Guelph, ON N1K 1E2, Canada",
				"statusCode": 200,
				"statusDescription": "OK",
				"traceId": "7cffb8f52bd3403db3ac10837926a009|BN20130532|7.7.0.0|",
				"addressLine": "141 Regal Rd",
				"adminDistrict": "ON",
				"adminDistrict2": "Wellington",
				"countryRegion": "Canada",
				"formattedAddress": "141 Regal Rd, Guelph, ON N1K 1E2, Canada",
				"locality": "Guelph",
				"neighborhood": "Willow West/Sugarbush",
				"postalCode": "N1K 1E2"
			},
			"geometry": {
				"type": "Point",
				"coordinates": [
					-80.30428,
					43.55248
				]
			},
			"bbox": [
				-80.3058311,
				43.5513558,
				-80.3027289,
				43.5536042
			]
		}
	]
}
