{
	"type": "FeatureCollection",
	"features": [
		{
			"type": "Feature",
			"properties": {
				"confidence": 9,
				"authenticationResultCode": "ValidCredentials",
				"brandLogoUri": "http://dev.virtualearth.net/Branding/logo_powered_by.png",
				"copyright": "Copyright © 2017 Microsoft and its suppliers. All rights reserved. This API cannot be accessed and the content and any results may not be used, reproduced or transmitted in any manner without express written permission from Microsoft Corporation.",
				"entityType": "Address",
				"matchCodes": [
					"Good"
				],
				"name": "141 Regina St, North Bay, ON P1A 1A1, Canada",
				"statusCode": 200,
				"statusDescription": "OK",
				"traceId": "0ae0e2bf6bbc497a9346d292d3b974a7|BN20130521|7.7.0.0|",
				"addressLine": "141 Regina St",
				"adminDistrict": "ON",
				"adminDistrict2": "Nipissing",
				"countryRegion": "Canada",
				"formattedAddress": "141 Regina St, North Bay, ON P1A 1A1, Canada",
				"locality": "North Bay",
				"neighborhood": "West Ferris",
				"postalCode": "P1A 1A1"
			},
			"geometry": {
				"type": "Point",
				"coordinates": [
					-79.46182,
					46.30335
				]
			},
			"bbox": [
				-79.4634472,
				46.3022258,
				-79.4601928,
				46.3044742
			]
		}
	]
}
