{
	"type": "FeatureCollection",
	"features": [
		{
			"type": "Feature",
			"properties": {
				"confidence": 9,
				"authenticationResultCode": "ValidCredentials",
				"brandLogoUri": "http://dev.virtualearth.net/Branding/logo_powered_by.png",
				"copyright": "Copyright © 2017 Microsoft and its suppliers. All rights reserved. This API cannot be accessed and the content and any results may not be used, reproduced or transmitted in any manner without express written permission from Microsoft Corporation.",
				"entityType": "Address",
				"matchCodes": [
					"Good"
				],
				"name": "1410 39 St N, Lethbridge, AB T1H 5M8, Canada",
				"statusCode": 200,
				"statusDescription": "OK",
				"traceId": "4c635141bd6642ef8ee54db17a2e35b0|BN20190642|7.7.0.0|",
				"addressLine": "1410 39 St N",
				"adminDistrict": "AB",
				"adminDistrict2": "Alberta",
				"countryRegion": "Canada",
				"formattedAddress": "1410 39 St N, Lethbridge, AB T1H 5M8, Canada",
				"locality": "Lethbridge",
				"postalCode": "T1H 5M8"
			},
			"geometry": {
				"type": "Point",
				"coordinates": [
					-112.78539,
					49.71858
				]
			},
			"bbox": [
				-112.7871287,
				49.7174558,
				-112.7836513,
				49.7197042
			]
		}
	]
}
