{
	"type": "FeatureCollection",
	"features": [
		{
			"type": "Feature",
			"properties": {
				"confidence": 9,
				"authenticationResultCode": "ValidCredentials",
				"brandLogoUri": "http://dev.virtualearth.net/Branding/logo_powered_by.png",
				"copyright": "Copyright © 2017 Microsoft and its suppliers. All rights reserved. This API cannot be accessed and the content and any results may not be used, reproduced or transmitted in any manner without express written permission from Microsoft Corporation.",
				"entityType": "Address",
				"matchCodes": [
					"Good"
				],
				"name": "1422 Rue le Ber, Sherbrooke, QC J1G 2Y5, Canada",
				"statusCode": 200,
				"statusDescription": "OK",
				"traceId": "c0a75d7fcdc74ad8a9c2376c20fcd2e3|BN20280152|7.7.0.0|",
				"addressLine": "1422 Rue le Ber",
				"adminDistrict": "QC",
				"adminDistrict2": "Sherbrooke",
				"countryRegion": "Canada",
				"formattedAddress": "1422 Rue le Ber, Sherbrooke, QC J1G 2Y5, Canada",
				"locality": "Sherbrooke",
				"neighborhood": "Fleurimont",
				"postalCode": "J1G 2Y5"
			},
			"geometry": {
				"type": "Point",
				"coordinates": [
					-71.86542,
					45.38641
				]
			},
			"bbox": [
				-71.8670206,
				45.3852858,
				-71.8638194,
				45.3875342
			]
		}
	]
}
