{
	"type": "FeatureCollection",
	"features": [
		{
			"type": "Feature",
			"properties": {
				"confidence": 9,
				"authenticationResultCode": "ValidCredentials",
				"brandLogoUri": "http://dev.virtualearth.net/Branding/logo_powered_by.png",
				"copyright": "Copyright © 2017 Microsoft and its suppliers. All rights reserved. This API cannot be accessed and the content and any results may not be used, reproduced or transmitted in any manner without express written permission from Microsoft Corporation.",
				"entityType": "Address",
				"matchCodes": [
					"Good"
				],
				"name": "1425 Autoroute Transcanadienne, Dorval, QC H9P, Canada",
				"statusCode": 200,
				"statusDescription": "OK",
				"traceId": "cc0b05fc714142d8a7123d013fe6f2e6|BN20260223|7.7.0.0|",
				"addressLine": "1425 Autoroute Transcanadienne",
				"adminDistrict": "QC",
				"adminDistrict2": "Montreal",
				"countryRegion": "Canada",
				"formattedAddress": "1425 Autoroute Transcanadienne, Dorval, QC H9P, Canada",
				"locality": "Dorval",
				"neighborhood": "Dollard-des-Ormeaux",
				"postalCode": "H9P 2W9"
			},
			"geometry": {
				"type": "Point",
				"coordinates": [
					-73.77545,
					45.48914
				]
			},
			"bbox": [
				-73.7770535,
				45.4880158,
				-73.7738465,
				45.4902642
			]
		}
	]
}
