{
	"type": "FeatureCollection",
	"features": [
		{
			"type": "Feature",
			"properties": {
				"confidence": 9,
				"authenticationResultCode": "ValidCredentials",
				"brandLogoUri": "http://dev.virtualearth.net/Branding/logo_powered_by.png",
				"copyright": "Copyright © 2017 Microsoft and its suppliers. All rights reserved. This API cannot be accessed and the content and any results may not be used, reproduced or transmitted in any manner without express written permission from Microsoft Corporation.",
				"entityType": "Address",
				"matchCodes": [
					"Good"
				],
				"name": "143 Holm Cres, Thornhill, ON L3T 5J4, Canada",
				"statusCode": 200,
				"statusDescription": "OK",
				"traceId": "043cd2332f2f4213a288ee670f4738b1|BN20320521|7.7.0.0|",
				"addressLine": "143 Holm Cres",
				"adminDistrict": "ON",
				"adminDistrict2": "York",
				"countryRegion": "Canada",
				"formattedAddress": "143 Holm Cres, Thornhill, ON L3T 5J4, Canada",
				"locality": "Markham",
				"neighborhood": "Thornhill",
				"postalCode": "L3T 5J4"
			},
			"geometry": {
				"type": "Point",
				"coordinates": [
					-79.39106,
					43.82423
				]
			},
			"bbox": [
				-79.3926181,
				43.8231058,
				-79.3895019,
				43.8253542
			]
		}
	]
}
