{
	"type": "FeatureCollection",
	"features": [
		{
			"type": "Feature",
			"properties": {
				"confidence": 9,
				"authenticationResultCode": "ValidCredentials",
				"brandLogoUri": "http://dev.virtualearth.net/Branding/logo_powered_by.png",
				"copyright": "Copyright © 2017 Microsoft and its suppliers. All rights reserved. This API cannot be accessed and the content and any results may not be used, reproduced or transmitted in any manner without express written permission from Microsoft Corporation.",
				"entityType": "Address",
				"matchCodes": [
					"Good"
				],
				"name": "1430 Burrard St, Vancouver, BC V6Z 2A3, Canada",
				"statusCode": 200,
				"statusDescription": "OK",
				"traceId": "9acb9d558e1944aeb2e4b1abf150cc0b|BN20130422|7.7.0.0|",
				"addressLine": "1430 Burrard St",
				"adminDistrict": "BC",
				"adminDistrict2": "Greater Vancouver",
				"countryRegion": "Canada",
				"formattedAddress": "1430 Burrard St, Vancouver, BC V6Z 2A3, Canada",
				"locality": "Vancouver",
				"neighborhood": "Downtown",
				"postalCode": "V6Z 2A3"
			},
			"geometry": {
				"type": "Point",
				"coordinates": [
					-123.13249,
					49.27637
				]
			},
			"bbox": [
				-123.1342131,
				49.2752458,
				-123.1307669,
				49.2774942
			]
		}
	]
}
