{
	"type": "FeatureCollection",
	"features": [
		{
			"type": "Feature",
			"properties": {
				"confidence": 9,
				"authenticationResultCode": "ValidCredentials",
				"brandLogoUri": "http://dev.virtualearth.net/Branding/logo_powered_by.png",
				"copyright": "Copyright © 2017 Microsoft and its suppliers. All rights reserved. This API cannot be accessed and the content and any results may not be used, reproduced or transmitted in any manner without express written permission from Microsoft Corporation.",
				"entityType": "Address",
				"matchCodes": [
					"Good"
				],
				"name": "14339 MacLeod Trl SE, Calgary, AB T2X, Canada",
				"statusCode": 200,
				"statusDescription": "OK",
				"traceId": "af2b205e515440219189ca6d1f25a4df|BN20240253|7.7.0.0|",
				"addressLine": "14339 MacLeod Trl SE",
				"adminDistrict": "AB",
				"adminDistrict2": "Alberta",
				"countryRegion": "Canada",
				"formattedAddress": "14339 MacLeod Trl SE, Calgary, AB T2X, Canada",
				"locality": "Calgary",
				"neighborhood": "Shawnee Slopes",
				"postalCode": "T2X"
			},
			"geometry": {
				"type": "Point",
				"coordinates": [
					-114.07293,
					50.92418
				]
			},
			"bbox": [
				-114.0747134,
				50.9230558,
				-114.0711466,
				50.9253042
			]
		}
	]
}
