{
	"type": "FeatureCollection",
	"features": [
		{
			"type": "Feature",
			"properties": {
				"confidence": 9,
				"authenticationResultCode": "ValidCredentials",
				"brandLogoUri": "http://dev.virtualearth.net/Branding/logo_powered_by.png",
				"copyright": "Copyright © 2017 Microsoft and its suppliers. All rights reserved. This API cannot be accessed and the content and any results may not be used, reproduced or transmitted in any manner without express written permission from Microsoft Corporation.",
				"entityType": "Address",
				"matchCodes": [
					"Good"
				],
				"name": "14355 120 Ave NW, Edmonton, AB T5L 2R8, Canada",
				"statusCode": 200,
				"statusDescription": "OK",
				"traceId": "5abc87b22c084f8a98be23790a34d2f1|BN20240423|7.7.0.0|",
				"addressLine": "14355 120 Ave NW",
				"adminDistrict": "AB",
				"adminDistrict2": "Alberta",
				"countryRegion": "Canada",
				"formattedAddress": "14355 120 Ave NW, Edmonton, AB T5L 2R8, Canada",
				"locality": "Edmonton",
				"neighborhood": "Dominion Industrial",
				"postalCode": "T5L 2R8"
			},
			"geometry": {
				"type": "Point",
				"coordinates": [
					-113.56891,
					53.57147
				]
			},
			"bbox": [
				-113.5708031,
				53.5703458,
				-113.5670169,
				53.5725942
			]
		}
	]
}
