{
	"type": "FeatureCollection",
	"features": [
		{
			"type": "Feature",
			"properties": {
				"confidence": 9,
				"authenticationResultCode": "ValidCredentials",
				"brandLogoUri": "http://dev.virtualearth.net/Branding/logo_powered_by.png",
				"copyright": "Copyright © 2017 Microsoft and its suppliers. All rights reserved. This API cannot be accessed and the content and any results may not be used, reproduced or transmitted in any manner without express written permission from Microsoft Corporation.",
				"entityType": "Address",
				"matchCodes": [
					"Good"
				],
				"name": "1449 Hopkins St, Whitby, ON L1N 2C2, Canada",
				"statusCode": 200,
				"statusDescription": "OK",
				"traceId": "4c2c42983f6e46a39c588214b6ae99a8|BN20181720|7.7.0.0|",
				"addressLine": "1449 Hopkins St",
				"adminDistrict": "ON",
				"adminDistrict2": "Durham",
				"countryRegion": "Canada",
				"formattedAddress": "1449 Hopkins St, Whitby, ON L1N 2C2, Canada",
				"locality": "Whitby",
				"postalCode": "L1N 2C2"
			},
			"geometry": {
				"type": "Point",
				"coordinates": [
					-78.9165352,
					43.871001
				]
			},
			"bbox": [
				-78.9180945,
				43.8698769,
				-78.9149758,
				43.8721252
			]
		}
	]
}
