{
	"type": "FeatureCollection",
	"features": [
		{
			"type": "Feature",
			"properties": {
				"confidence": 9,
				"authenticationResultCode": "ValidCredentials",
				"brandLogoUri": "http://dev.virtualearth.net/Branding/logo_powered_by.png",
				"copyright": "Copyright © 2017 Microsoft and its suppliers. All rights reserved. This API cannot be accessed and the content and any results may not be used, reproduced or transmitted in any manner without express written permission from Microsoft Corporation.",
				"entityType": "Address",
				"matchCodes": [
					"Good"
				],
				"name": "14509 Mt Pleasant Rd, Bolton, ON L7E 3M9, Canada",
				"statusCode": 200,
				"statusDescription": "OK",
				"traceId": "c7ca6864c0cd4047b92b9deb19ac5a91|BN20260223|7.7.0.0|",
				"addressLine": "14509 Mt Pleasant Rd",
				"adminDistrict": "ON",
				"adminDistrict2": "Peel",
				"countryRegion": "Canada",
				"formattedAddress": "14509 Mt Pleasant Rd, Bolton, ON L7E 3M9, Canada",
				"locality": "Caledon",
				"neighborhood": "Bolton",
				"postalCode": "L7E 3M9"
			},
			"geometry": {
				"type": "Point",
				"coordinates": [
					-79.74103,
					43.91919
				]
			},
			"bbox": [
				-79.7425906,
				43.9180658,
				-79.7394694,
				43.9203142
			]
		}
	]
}
