{
	"type": "FeatureCollection",
	"features": [
		{
			"type": "Feature",
			"properties": {
				"confidence": 9,
				"authenticationResultCode": "ValidCredentials",
				"brandLogoUri": "http://dev.virtualearth.net/Branding/logo_powered_by.png",
				"copyright": "Copyright © 2017 Microsoft and its suppliers. All rights reserved. This API cannot be accessed and the content and any results may not be used, reproduced or transmitted in any manner without express written permission from Microsoft Corporation.",
				"entityType": "Address",
				"matchCodes": [
					"Good"
				],
				"name": "1451 Erin St, Winnipeg, MB R3E 2S9, Canada",
				"statusCode": 200,
				"statusDescription": "OK",
				"traceId": "f1b70b78bc27405d994b95f851838771|BN20210145|7.7.0.0|",
				"addressLine": "1451 Erin St",
				"adminDistrict": "MB",
				"adminDistrict2": "Manitoba",
				"countryRegion": "Canada",
				"formattedAddress": "1451 Erin St, Winnipeg, MB R3E 2S9, Canada",
				"locality": "Winnipeg",
				"neighborhood": "Sargent Park",
				"postalCode": "R3E 2S9"
			},
			"geometry": {
				"type": "Point",
				"coordinates": [
					-97.18315,
					49.90293
				]
			},
			"bbox": [
				-97.1848953,
				49.9018058,
				-97.1814047,
				49.9040542
			]
		}
	]
}
