{
	"type": "FeatureCollection",
	"features": [
		{
			"type": "Feature",
			"properties": {
				"confidence": 9,
				"authenticationResultCode": "ValidCredentials",
				"brandLogoUri": "http://dev.virtualearth.net/Branding/logo_powered_by.png",
				"copyright": "Copyright © 2017 Microsoft and its suppliers. All rights reserved. This API cannot be accessed and the content and any results may not be used, reproduced or transmitted in any manner without express written permission from Microsoft Corporation.",
				"entityType": "Address",
				"matchCodes": [
					"Good"
				],
				"name": "1460 Rue Michelin, Laval, QC H7L 4R3, Canada",
				"statusCode": 200,
				"statusDescription": "OK",
				"traceId": "f5d89a8afbfb48a4964b33b0886ba4f1|BN20130620|7.7.0.0|",
				"addressLine": "1460 Rue Michelin",
				"adminDistrict": "QC",
				"adminDistrict2": "Laval",
				"countryRegion": "Canada",
				"formattedAddress": "1460 Rue Michelin, Laval, QC H7L 4R3, Canada",
				"locality": "Laval",
				"postalCode": "H7L 4R3"
			},
			"geometry": {
				"type": "Point",
				"coordinates": [
					-73.74658,
					45.5894199
				]
			},
			"bbox": [
				-73.7481864,
				45.5882957,
				-73.7449736,
				45.5905441
			]
		}
	]
}
