{
	"type": "FeatureCollection",
	"features": [
		{
			"type": "Feature",
			"properties": {
				"confidence": 9,
				"authenticationResultCode": "ValidCredentials",
				"brandLogoUri": "http://dev.virtualearth.net/Branding/logo_powered_by.png",
				"copyright": "Copyright © 2017 Microsoft and its suppliers. All rights reserved. This API cannot be accessed and the content and any results may not be used, reproduced or transmitted in any manner without express written permission from Microsoft Corporation.",
				"entityType": "Address",
				"matchCodes": [
					"Good"
				],
				"name": "1467 Mustang Pl, Port Coquitlam, BC V3C 6L2, Canada",
				"statusCode": 200,
				"statusDescription": "OK",
				"traceId": "701fead9b36a447c9855cc3daa648288|BN20260223|7.7.0.0|",
				"addressLine": "1467 Mustang Pl",
				"adminDistrict": "BC",
				"adminDistrict2": "Greater Vancouver",
				"countryRegion": "Canada",
				"formattedAddress": "1467 Mustang Pl, Port Coquitlam, BC V3C 6L2, Canada",
				"locality": "Port Coquitlam",
				"postalCode": "V3C 6L2"
			},
			"geometry": {
				"type": "Point",
				"coordinates": [
					-122.7495666,
					49.2437794
				]
			},
			"bbox": [
				-122.7512885,
				49.2426552,
				-122.7478447,
				49.2449035
			]
		}
	]
}
