{
	"type": "FeatureCollection",
	"features": [
		{
			"type": "Feature",
			"properties": {
				"confidence": 9,
				"authenticationResultCode": "ValidCredentials",
				"brandLogoUri": "http://dev.virtualearth.net/Branding/logo_powered_by.png",
				"copyright": "Copyright © 2017 Microsoft and its suppliers. All rights reserved. This API cannot be accessed and the content and any results may not be used, reproduced or transmitted in any manner without express written permission from Microsoft Corporation.",
				"entityType": "Address",
				"matchCodes": [
					"Good"
				],
				"name": "1478 Park Rd, Kings, NS B0P, Canada",
				"statusCode": 200,
				"statusDescription": "OK",
				"traceId": "c368b1dde10345a2834ddcb7329dd558|BN20130532|7.7.0.0|",
				"addressLine": "1478 Park Rd",
				"adminDistrict": "NS",
				"adminDistrict2": "Kings",
				"countryRegion": "Canada",
				"formattedAddress": "1478 Park Rd, Kings, NS B0P, Canada",
				"locality": "Kings",
				"neighborhood": "Kingston",
				"postalCode": "B0P 1R0"
			},
			"geometry": {
				"type": "Point",
				"coordinates": [
					-64.9463911,
					44.9876077
				]
			},
			"bbox": [
				-64.9479806,
				44.9864836,
				-64.9448017,
				44.9887319
			]
		}
	]
}
