{
	"type": "FeatureCollection",
	"features": [
		{
			"type": "Feature",
			"properties": {
				"confidence": 9,
				"authenticationResultCode": "ValidCredentials",
				"brandLogoUri": "http://dev.virtualearth.net/Branding/logo_powered_by.png",
				"copyright": "Copyright © 2017 Microsoft and its suppliers. All rights reserved. This API cannot be accessed and the content and any results may not be used, reproduced or transmitted in any manner without express written permission from Microsoft Corporation.",
				"entityType": "Address",
				"matchCodes": [
					"Good"
				],
				"name": "148 Claremont St, Toronto, ON M6J 2M8, Canada",
				"statusCode": 200,
				"statusDescription": "OK",
				"traceId": "3697925da2d8469f9318819c032a608f|BN20181720|7.7.0.0|",
				"addressLine": "148 Claremont St",
				"adminDistrict": "ON",
				"adminDistrict2": "Toronto",
				"countryRegion": "Canada",
				"formattedAddress": "148 Claremont St, Toronto, ON M6J 2M8, Canada",
				"locality": "Toronto",
				"neighborhood": "Trinity-Bellwoods",
				"postalCode": "M6J 2M8"
			},
			"geometry": {
				"type": "Point",
				"coordinates": [
					-79.41138,
					43.65011
				]
			},
			"bbox": [
				-79.4129336,
				43.6489858,
				-79.4098264,
				43.6512342
			]
		}
	]
}
