{
	"type": "FeatureCollection",
	"features": [
		{
			"type": "Feature",
			"properties": {
				"confidence": 9,
				"authenticationResultCode": "ValidCredentials",
				"brandLogoUri": "http://dev.virtualearth.net/Branding/logo_powered_by.png",
				"copyright": "Copyright © 2017 Microsoft and its suppliers. All rights reserved. This API cannot be accessed and the content and any results may not be used, reproduced or transmitted in any manner without express written permission from Microsoft Corporation.",
				"entityType": "Address",
				"matchCodes": [
					"Good"
				],
				"name": "1494 Powell St, Vancouver, BC V5L 5B5, Canada",
				"statusCode": 200,
				"statusDescription": "OK",
				"traceId": "3ed76e3eed2f439482404dcf08f154a0|BN20320521|7.7.0.0|",
				"addressLine": "1494 Powell St",
				"adminDistrict": "BC",
				"adminDistrict2": "Greater Vancouver",
				"countryRegion": "Canada",
				"formattedAddress": "1494 Powell St, Vancouver, BC V5L 5B5, Canada",
				"locality": "Vancouver",
				"neighborhood": "Grandview-Woodland",
				"postalCode": "V5L 5B5"
			},
			"geometry": {
				"type": "Point",
				"coordinates": [
					-123.07483,
					49.2825
				]
			},
			"bbox": [
				-123.0765533,
				49.2813758,
				-123.0731067,
				49.2836242
			]
		}
	]
}
