{
	"type": "FeatureCollection",
	"features": [
		{
			"type": "Feature",
			"properties": {
				"confidence": 9,
				"authenticationResultCode": "ValidCredentials",
				"brandLogoUri": "http://dev.virtualearth.net/Branding/logo_powered_by.png",
				"copyright": "Copyright © 2017 Microsoft and its suppliers. All rights reserved. This API cannot be accessed and the content and any results may not be used, reproduced or transmitted in any manner without express written permission from Microsoft Corporation.",
				"entityType": "Address",
				"matchCodes": [
					"Good"
				],
				"name": "14952 121A Ave NW, Edmonton, AB T5V 1A3, Canada",
				"statusCode": 200,
				"statusDescription": "OK",
				"traceId": "d4dd5e14640646f4a80bd1e2e3f554c2|BN20131519|7.7.0.0|",
				"addressLine": "14952 121A Ave NW",
				"adminDistrict": "AB",
				"adminDistrict2": "Alberta",
				"countryRegion": "Canada",
				"formattedAddress": "14952 121A Ave NW, Edmonton, AB T5V 1A3, Canada",
				"locality": "Edmonton",
				"neighborhood": "Mitchell Industrial",
				"postalCode": "T5V 1A3"
			},
			"geometry": {
				"type": "Point",
				"coordinates": [
					-113.57948,
					53.5740399
				]
			},
			"bbox": [
				-113.5813732,
				53.5729157,
				-113.5775868,
				53.5751641
			]
		}
	]
}
