{
	"type": "FeatureCollection",
	"features": [
		{
			"type": "Feature",
			"properties": {
				"confidence": 9,
				"authenticationResultCode": "ValidCredentials",
				"brandLogoUri": "http://dev.virtualearth.net/Branding/logo_powered_by.png",
				"copyright": "Copyright © 2017 Microsoft and its suppliers. All rights reserved. This API cannot be accessed and the content and any results may not be used, reproduced or transmitted in any manner without express written permission from Microsoft Corporation.",
				"entityType": "Address",
				"matchCodes": [
					"Good"
				],
				"name": "15 Miller Ave, Edmundston, NB E3V 4H4, Canada",
				"statusCode": 200,
				"statusDescription": "OK",
				"traceId": "0534870514b6465ab985d2c3fa093269|BN20130719|7.7.0.0|",
				"addressLine": "15 Miller Ave",
				"adminDistrict": "NB",
				"adminDistrict2": "Madawaska",
				"countryRegion": "Canada",
				"formattedAddress": "15 Miller Ave, Edmundston, NB E3V 4H4, Canada",
				"locality": "Edmundston",
				"postalCode": "E3V 4H4"
			},
			"geometry": {
				"type": "Point",
				"coordinates": [
					-68.32941,
					47.39672
				]
			},
			"bbox": [
				-68.3310707,
				47.3955958,
				-68.3277493,
				47.3978442
			]
		}
	]
}
