{
	"type": "FeatureCollection",
	"features": [
		{
			"type": "Feature",
			"properties": {
				"confidence": 9,
				"authenticationResultCode": "ValidCredentials",
				"brandLogoUri": "http://dev.virtualearth.net/Branding/logo_powered_by.png",
				"copyright": "Copyright © 2017 Microsoft and its suppliers. All rights reserved. This API cannot be accessed and the content and any results may not be used, reproduced or transmitted in any manner without express written permission from Microsoft Corporation.",
				"entityType": "Address",
				"matchCodes": [
					"Good"
				],
				"name": "15 Rivercourt Blvd, East York, ON M4J 3A3, Canada",
				"statusCode": 200,
				"statusDescription": "OK",
				"traceId": "330e1428cfbc4ad584fc41c4bca7d653|BN20130631|7.7.0.0|",
				"addressLine": "15 Rivercourt Blvd",
				"adminDistrict": "ON",
				"adminDistrict2": "Toronto",
				"countryRegion": "Canada",
				"formattedAddress": "15 Rivercourt Blvd, East York, ON M4J 3A3, Canada",
				"locality": "Toronto",
				"neighborhood": "Old East York",
				"postalCode": "M4J 3A3"
			},
			"geometry": {
				"type": "Point",
				"coordinates": [
					-79.34813,
					43.69413
				]
			},
			"bbox": [
				-79.3496848,
				43.6930058,
				-79.3465752,
				43.6952542
			]
		}
	]
}
