{
	"type": "FeatureCollection",
	"features": [
		{
			"type": "Feature",
			"properties": {
				"confidence": 9,
				"authenticationResultCode": "ValidCredentials",
				"brandLogoUri": "http://dev.virtualearth.net/Branding/logo_powered_by.png",
				"copyright": "Copyright © 2017 Microsoft and its suppliers. All rights reserved. This API cannot be accessed and the content and any results may not be used, reproduced or transmitted in any manner without express written permission from Microsoft Corporation.",
				"entityType": "Address",
				"matchCodes": [
					"Good"
				],
				"name": "150 Karl Clark Rd NW, Edmonton, AB T6N 1E2, Canada",
				"statusCode": 200,
				"statusDescription": "OK",
				"traceId": "8e752317d2ef49bbb275dd309bea6d7e|BN20121762|7.7.0.0|",
				"addressLine": "150 Karl Clark Rd NW",
				"adminDistrict": "AB",
				"adminDistrict2": "Alberta",
				"countryRegion": "Canada",
				"formattedAddress": "150 Karl Clark Rd NW, Edmonton, AB T6N 1E2, Canada",
				"locality": "Edmonton",
				"neighborhood": "Edmonton Research and Development",
				"postalCode": "T6N 1E2"
			},
			"geometry": {
				"type": "Point",
				"coordinates": [
					-113.4757,
					53.44986
				]
			},
			"bbox": [
				-113.4775877,
				53.4487358,
				-113.4738123,
				53.4509842
			]
		}
	]
}
