{
	"type": "FeatureCollection",
	"features": [
		{
			"type": "Feature",
			"properties": {
				"confidence": 9,
				"authenticationResultCode": "ValidCredentials",
				"brandLogoUri": "http://dev.virtualearth.net/Branding/logo_powered_by.png",
				"copyright": "Copyright © 2017 Microsoft and its suppliers. All rights reserved. This API cannot be accessed and the content and any results may not be used, reproduced or transmitted in any manner without express written permission from Microsoft Corporation.",
				"entityType": "Address",
				"matchCodes": [
					"Good"
				],
				"name": "1500 Islington Ave, Etobicoke, ON M9A 3L8, Canada",
				"statusCode": 200,
				"statusDescription": "OK",
				"traceId": "41e9232a0ebb43d3b57f0338e8d53f87|BN20130520|7.7.0.0|",
				"addressLine": "1500 Islington Ave",
				"adminDistrict": "ON",
				"adminDistrict2": "Toronto",
				"countryRegion": "Canada",
				"formattedAddress": "1500 Islington Ave, Etobicoke, ON M9A 3L8, Canada",
				"locality": "Toronto",
				"neighborhood": "Princess-Rosethorn",
				"postalCode": "M9A 3L8"
			},
			"geometry": {
				"type": "Point",
				"coordinates": [
					-79.53171,
					43.66294
				]
			},
			"bbox": [
				-79.533264,
				43.6618158,
				-79.530156,
				43.6640642
			]
		}
	]
}
