{
	"type": "FeatureCollection",
	"features": [
		{
			"type": "Feature",
			"properties": {
				"confidence": 9,
				"authenticationResultCode": "ValidCredentials",
				"brandLogoUri": "http://dev.virtualearth.net/Branding/logo_powered_by.png",
				"copyright": "Copyright © 2017 Microsoft and its suppliers. All rights reserved. This API cannot be accessed and the content and any results may not be used, reproduced or transmitted in any manner without express written permission from Microsoft Corporation.",
				"entityType": "Address",
				"matchCodes": [
					"Good"
				],
				"name": "1501 Eagleview Dr, Pickering, ON L1V 5H1, Canada",
				"statusCode": 200,
				"statusDescription": "OK",
				"traceId": "4b61549d434f42469c2d3d813188eaf9|BN20121764|7.7.0.0|",
				"addressLine": "1501 Eagleview Dr",
				"adminDistrict": "ON",
				"adminDistrict2": "Durham",
				"countryRegion": "Canada",
				"formattedAddress": "1501 Eagleview Dr, Pickering, ON L1V 5H1, Canada",
				"locality": "Pickering",
				"postalCode": "L1V 5H1"
			},
			"geometry": {
				"type": "Point",
				"coordinates": [
					-79.1117412,
					43.8380714
				]
			},
			"bbox": [
				-79.1132997,
				43.8369472,
				-79.1101827,
				43.8391955
			]
		}
	]
}
