{
	"type": "FeatureCollection",
	"features": [
		{
			"type": "Feature",
			"properties": {
				"confidence": 9,
				"authenticationResultCode": "ValidCredentials",
				"brandLogoUri": "http://dev.virtualearth.net/Branding/logo_powered_by.png",
				"copyright": "Copyright © 2017 Microsoft and its suppliers. All rights reserved. This API cannot be accessed and the content and any results may not be used, reproduced or transmitted in any manner without express written permission from Microsoft Corporation.",
				"entityType": "Address",
				"matchCodes": [
					"Good"
				],
				"name": "151 Creditview Rd, Woodbridge, ON L4L 9T1, Canada",
				"statusCode": 200,
				"statusDescription": "OK",
				"traceId": "638de7c2bc914266b7b1295041c3f0fd|BN20220145|7.7.0.0|",
				"addressLine": "151 Creditview Rd",
				"adminDistrict": "ON",
				"adminDistrict2": "York",
				"countryRegion": "Canada",
				"formattedAddress": "151 Creditview Rd, Woodbridge, ON L4L 9T1, Canada",
				"locality": "Vaughan",
				"neighborhood": "Woodbridge",
				"postalCode": "L4L 9T1"
			},
			"geometry": {
				"type": "Point",
				"coordinates": [
					-79.54634,
					43.81331
				]
			},
			"bbox": [
				-79.5478979,
				43.8121858,
				-79.5447821,
				43.8144342
			]
		}
	]
}
