{
	"type": "FeatureCollection",
	"features": [
		{
			"type": "Feature",
			"properties": {
				"confidence": 9,
				"authenticationResultCode": "ValidCredentials",
				"brandLogoUri": "http://dev.virtualearth.net/Branding/logo_powered_by.png",
				"copyright": "Copyright © 2017 Microsoft and its suppliers. All rights reserved. This API cannot be accessed and the content and any results may not be used, reproduced or transmitted in any manner without express written permission from Microsoft Corporation.",
				"entityType": "Address",
				"matchCodes": [
					"UpHierarchy"
				],
				"name": "151 Lochside Rd, Richmond, NS B0E 1K0, Canada",
				"statusCode": 200,
				"statusDescription": "OK",
				"traceId": "337086f894e54fd9b6c2f4f03ab298de|BN20200239|7.7.0.0|",
				"addressLine": "151 Lochside Rd",
				"adminDistrict": "NS",
				"adminDistrict2": "Richmond",
				"countryRegion": "Canada",
				"formattedAddress": "151 Lochside Rd, Richmond, NS B0E 1K0, Canada",
				"locality": "Richmond",
				"postalCode": "B0E 1K0"
			},
			"geometry": {
				"type": "Point",
				"coordinates": [
					-61.01213,
					45.54606
				]
			},
			"bbox": [
				-61.0137352,
				45.5449358,
				-61.0105248,
				45.5471842
			]
		}
	]
}
