{
	"type": "FeatureCollection",
	"features": [
		{
			"type": "Feature",
			"properties": {
				"confidence": 9,
				"authenticationResultCode": "ValidCredentials",
				"brandLogoUri": "http://dev.virtualearth.net/Branding/logo_powered_by.png",
				"copyright": "Copyright © 2017 Microsoft and its suppliers. All rights reserved. This API cannot be accessed and the content and any results may not be used, reproduced or transmitted in any manner without express written permission from Microsoft Corporation.",
				"entityType": "Address",
				"matchCodes": [
					"Good"
				],
				"name": "151 Geneva St, St Catharines, ON L2R 4N7, Canada",
				"statusCode": 200,
				"statusDescription": "OK",
				"traceId": "f984c811f7ca4422b7d420097a95739a|BN20290118|7.7.0.0|",
				"addressLine": "151 Geneva St",
				"adminDistrict": "ON",
				"adminDistrict2": "Niagara",
				"countryRegion": "Canada",
				"formattedAddress": "151 Geneva St, St Catharines, ON L2R 4N7, Canada",
				"locality": "St Catharines",
				"neighborhood": "York-Haig",
				"postalCode": "L2R 4N7"
			},
			"geometry": {
				"type": "Point",
				"coordinates": [
					-79.24099,
					43.16892
				]
			},
			"bbox": [
				-79.2425313,
				43.1677958,
				-79.2394487,
				43.1700442
			]
		}
	]
}
