{
	"type": "FeatureCollection",
	"features": [
		{
			"type": "Feature",
			"properties": {
				"confidence": 9,
				"authenticationResultCode": "ValidCredentials",
				"brandLogoUri": "http://dev.virtualearth.net/Branding/logo_powered_by.png",
				"copyright": "Copyright © 2017 Microsoft and its suppliers. All rights reserved. This API cannot be accessed and the content and any results may not be used, reproduced or transmitted in any manner without express written permission from Microsoft Corporation.",
				"entityType": "Address",
				"matchCodes": [
					"Good"
				],
				"name": "151 Arrow Rd, Guelph, ON N1H, Canada",
				"statusCode": 200,
				"statusDescription": "OK",
				"traceId": "442fbe4ce6db4781904754a2d67422f9|BN20130632|7.7.0.0|",
				"addressLine": "151 Arrow Rd",
				"adminDistrict": "ON",
				"adminDistrict2": "Wellington",
				"countryRegion": "Canada",
				"formattedAddress": "151 Arrow Rd, Guelph, ON N1H, Canada",
				"locality": "Guelph",
				"neighborhood": "Willow West/Sugarbush",
				"postalCode": "N1H"
			},
			"geometry": {
				"type": "Point",
				"coordinates": [
					-80.2975058,
					43.5571494
				]
			},
			"bbox": [
				-80.299057,
				43.5560252,
				-80.2959546,
				43.5582736
			]
		}
	]
}
