{
	"type": "FeatureCollection",
	"features": [
		{
			"type": "Feature",
			"properties": {
				"confidence": 9,
				"authenticationResultCode": "ValidCredentials",
				"brandLogoUri": "http://dev.virtualearth.net/Branding/logo_powered_by.png",
				"copyright": "Copyright © 2017 Microsoft and its suppliers. All rights reserved. This API cannot be accessed and the content and any results may not be used, reproduced or transmitted in any manner without express written permission from Microsoft Corporation.",
				"entityType": "Address",
				"matchCodes": [
					"Good"
				],
				"name": "1510 Fairburn St, Sudbury, ON P3A 1N7, Canada",
				"statusCode": 200,
				"statusDescription": "OK",
				"traceId": "cba808039c8a4e5a8e3bca957500bc4b|BN20130631|7.7.0.0|",
				"addressLine": "1510 Fairburn St",
				"adminDistrict": "ON",
				"adminDistrict2": "Greater Sudbury",
				"countryRegion": "Canada",
				"formattedAddress": "1510 Fairburn St, Sudbury, ON P3A 1N7, Canada",
				"locality": "Greater Sudbury",
				"neighborhood": "Sudbury",
				"postalCode": "P3A 1N7"
			},
			"geometry": {
				"type": "Point",
				"coordinates": [
					-80.9412399,
					46.51795
				]
			},
			"bbox": [
				-80.9428735,
				46.5168258,
				-80.9396063,
				46.5190742
			]
		}
	]
}
