{
	"type": "FeatureCollection",
	"features": [
		{
			"type": "Feature",
			"properties": {
				"confidence": 9,
				"authenticationResultCode": "ValidCredentials",
				"brandLogoUri": "http://dev.virtualearth.net/Branding/logo_powered_by.png",
				"copyright": "Copyright © 2017 Microsoft and its suppliers. All rights reserved. This API cannot be accessed and the content and any results may not be used, reproduced or transmitted in any manner without express written permission from Microsoft Corporation.",
				"entityType": "Address",
				"matchCodes": [
					"Good"
				],
				"name": "15311 128 Ave NW, Edmonton, AB T5V 1A5, Canada",
				"statusCode": 200,
				"statusDescription": "OK",
				"traceId": "affa9f46608644b3becd19455708a1e0|BN20130522|7.7.0.0|",
				"addressLine": "15311 128 Ave NW",
				"adminDistrict": "AB",
				"adminDistrict2": "Alberta",
				"countryRegion": "Canada",
				"formattedAddress": "15311 128 Ave NW, Edmonton, AB T5V 1A5, Canada",
				"locality": "Edmonton",
				"neighborhood": "Mistatim Industrial",
				"postalCode": "T5V 1A5"
			},
			"geometry": {
				"type": "Point",
				"coordinates": [
					-113.5853207,
					53.5847651
				]
			},
			"bbox": [
				-113.5872143,
				53.583641,
				-113.583427,
				53.5858893
			]
		}
	]
}
