{
	"type": "FeatureCollection",
	"features": [
		{
			"type": "Feature",
			"properties": {
				"confidence": 7,
				"authenticationResultCode": "ValidCredentials",
				"brandLogoUri": "http://dev.virtualearth.net/Branding/logo_powered_by.png",
				"copyright": "Copyright © 2017 Microsoft and its suppliers. All rights reserved. This API cannot be accessed and the content and any results may not be used, reproduced or transmitted in any manner without express written permission from Microsoft Corporation.",
				"entityType": "Postcode1",
				"matchCodes": [
					"UpHierarchy"
				],
				"name": "Newmarket, L3Y 4W1, Canada",
				"statusCode": 200,
				"statusDescription": "OK",
				"traceId": "e58e364df3d141e9ab5aa6a636131200|BN20130632|7.7.0.0|",
				"adminDistrict": "ON",
				"adminDistrict2": "York",
				"countryRegion": "Canada",
				"formattedAddress": "Newmarket, L3Y 4W1, Canada",
				"locality": "Newmarket",
				"postalCode": "L3Y 4W1"
			},
			"geometry": {
				"type": "Point",
				"coordinates": [
					-79.4180603027344,
					44.0468330383301
				]
			},
			"bbox": [
				-79.4252252396759,
				44.0429703207594,
				-79.4108953657929,
				44.0506957559008
			]
		},
		{
			"type": "Feature",
			"properties": {
				"confidence": 7,
				"authenticationResultCode": "ValidCredentials",
				"brandLogoUri": "http://dev.virtualearth.net/Branding/logo_powered_by.png",
				"copyright": "Copyright © 2017 Microsoft and its suppliers. All rights reserved. This API cannot be accessed and the content and any results may not be used, reproduced or transmitted in any manner without express written permission from Microsoft Corporation.",
				"entityType": "Postcode1",
				"matchCodes": [
					"UpHierarchy"
				],
				"name": "Cumberland Township, PA 15351",
				"statusCode": 200,
				"statusDescription": "OK",
				"traceId": "e58e364df3d141e9ab5aa6a636131200|BN20130632|7.7.0.0|",
				"adminDistrict": "PA",
				"adminDistrict2": "Greene",
				"countryRegion": "United States",
				"formattedAddress": "Cumberland Township, PA 15351",
				"locality": "Cumberland Township",
				"postalCode": "15351"
			},
			"geometry": {
				"type": "Point",
				"coordinates": [
					-79.9226608276367,
					39.8789405822754
				]
			},
			"bbox": [
				-79.9377136230469,
				39.8531608581543,
				-79.9155120849609,
				39.8849983215332
			]
		}
	]
}
