{
	"type": "FeatureCollection",
	"features": [
		{
			"type": "Feature",
			"properties": {
				"confidence": 9,
				"authenticationResultCode": "ValidCredentials",
				"brandLogoUri": "http://dev.virtualearth.net/Branding/logo_powered_by.png",
				"copyright": "Copyright © 2017 Microsoft and its suppliers. All rights reserved. This API cannot be accessed and the content and any results may not be used, reproduced or transmitted in any manner without express written permission from Microsoft Corporation.",
				"entityType": "Address",
				"matchCodes": [
					"Good"
				],
				"name": "155 Ardelt Ave, Kitchener, ON N2C 2E1, Canada",
				"statusCode": 200,
				"statusDescription": "OK",
				"traceId": "17c6e86c2d2a465f982f5ec930b154bc|BN20130621|7.7.0.0|",
				"addressLine": "155 Ardelt Ave",
				"adminDistrict": "ON",
				"adminDistrict2": "Waterloo",
				"countryRegion": "Canada",
				"formattedAddress": "155 Ardelt Ave, Kitchener, ON N2C 2E1, Canada",
				"locality": "Kitchener",
				"neighborhood": "Alpine",
				"postalCode": "N2C 2E1"
			},
			"geometry": {
				"type": "Point",
				"coordinates": [
					-80.47498,
					43.42448
				]
			},
			"bbox": [
				-80.4765278,
				43.4233558,
				-80.4734322,
				43.4256042
			]
		}
	]
}
