{
	"type": "FeatureCollection",
	"features": [
		{
			"type": "Feature",
			"properties": {
				"confidence": 9,
				"authenticationResultCode": "ValidCredentials",
				"brandLogoUri": "http://dev.virtualearth.net/Branding/logo_powered_by.png",
				"copyright": "Copyright © 2017 Microsoft and its suppliers. All rights reserved. This API cannot be accessed and the content and any results may not be used, reproduced or transmitted in any manner without express written permission from Microsoft Corporation.",
				"entityType": "Address",
				"matchCodes": [
					"Good"
				],
				"name": "155 Juniper St, Beaconsfield, QC H9W 2R9, Canada",
				"statusCode": 200,
				"statusDescription": "OK",
				"traceId": "122686a2b45f4a8ea4d3570e0874a749|BN20130719|7.7.0.0|",
				"addressLine": "155 Juniper St",
				"adminDistrict": "QC",
				"adminDistrict2": "Montreal",
				"countryRegion": "Canada",
				"formattedAddress": "155 Juniper St, Beaconsfield, QC H9W 2R9, Canada",
				"locality": "Beaconsfield",
				"postalCode": "H9W 2R9"
			},
			"geometry": {
				"type": "Point",
				"coordinates": [
					-73.8559889,
					45.4349258
				]
			},
			"bbox": [
				-73.8575909,
				45.4338016,
				-73.8543869,
				45.4360499
			]
		}
	]
}
