{
	"type": "FeatureCollection",
	"features": [
		{
			"type": "Feature",
			"properties": {
				"confidence": 9,
				"authenticationResultCode": "ValidCredentials",
				"brandLogoUri": "http://dev.virtualearth.net/Branding/logo_powered_by.png",
				"copyright": "Copyright © 2017 Microsoft and its suppliers. All rights reserved. This API cannot be accessed and the content and any results may not be used, reproduced or transmitted in any manner without express written permission from Microsoft Corporation.",
				"entityType": "Address",
				"matchCodes": [
					"Good"
				],
				"name": "1555 Rue Baxter, La Salle, QC H8N 2S9, Canada",
				"statusCode": 200,
				"statusDescription": "OK",
				"traceId": "3547285b16af41a1b65d5bb30ca8e6f6|BN20210145|7.7.0.0|",
				"addressLine": "1555 Rue Baxter",
				"adminDistrict": "QC",
				"adminDistrict2": "Montreal",
				"countryRegion": "Canada",
				"formattedAddress": "1555 Rue Baxter, La Salle, QC H8N 2S9, Canada",
				"locality": "Montreal",
				"neighborhood": "La Salle",
				"postalCode": "H8N 2S9"
			},
			"geometry": {
				"type": "Point",
				"coordinates": [
					-73.61004,
					45.43904
				]
			},
			"bbox": [
				-73.6116421,
				45.4379158,
				-73.6084379,
				45.4401642
			]
		}
	]
}
