{
	"type": "FeatureCollection",
	"features": [
		{
			"type": "Feature",
			"properties": {
				"confidence": 9,
				"authenticationResultCode": "ValidCredentials",
				"brandLogoUri": "http://dev.virtualearth.net/Branding/logo_powered_by.png",
				"copyright": "Copyright © 2017 Microsoft and its suppliers. All rights reserved. This API cannot be accessed and the content and any results may not be used, reproduced or transmitted in any manner without express written permission from Microsoft Corporation.",
				"entityType": "Address",
				"matchCodes": [
					"Good"
				],
				"name": "15595 24 Ave, Surrey, BC V4A 2J4, Canada",
				"statusCode": 200,
				"statusDescription": "OK",
				"traceId": "370429913ee2473e89720e291e510811|BN20130533|7.7.0.0|",
				"addressLine": "15595 24 Ave",
				"adminDistrict": "BC",
				"adminDistrict2": "Greater Vancouver",
				"countryRegion": "Canada",
				"formattedAddress": "15595 24 Ave, Surrey, BC V4A 2J4, Canada",
				"locality": "Surrey",
				"neighborhood": "South Surrey",
				"postalCode": "V4A 2J4"
			},
			"geometry": {
				"type": "Point",
				"coordinates": [
					-122.79061,
					49.04574
				]
			},
			"bbox": [
				-122.7923251,
				49.0446158,
				-122.7888949,
				49.0468642
			]
		}
	]
}
