{
	"type": "FeatureCollection",
	"features": [
		{
			"type": "Feature",
			"properties": {
				"confidence": 9,
				"authenticationResultCode": "ValidCredentials",
				"brandLogoUri": "http://dev.virtualearth.net/Branding/logo_powered_by.png",
				"copyright": "Copyright © 2017 Microsoft and its suppliers. All rights reserved. This API cannot be accessed and the content and any results may not be used, reproduced or transmitted in any manner without express written permission from Microsoft Corporation.",
				"entityType": "Address",
				"matchCodes": [
					"Good"
				],
				"name": "156 Silver Brook Rd NW, Calgary, AB T3B 3J1, Canada",
				"statusCode": 200,
				"statusDescription": "OK",
				"traceId": "55f4dfb49ba74c5d951d92899190ee14|BN20130634|7.7.0.0|",
				"addressLine": "156 Silver Brook Rd NW",
				"adminDistrict": "AB",
				"adminDistrict2": "Alberta",
				"countryRegion": "Canada",
				"formattedAddress": "156 Silver Brook Rd NW, Calgary, AB T3B 3J1, Canada",
				"locality": "Calgary",
				"neighborhood": "Silver Springs",
				"postalCode": "T3B 3J1"
			},
			"geometry": {
				"type": "Point",
				"coordinates": [
					-114.18753,
					51.10874
				]
			},
			"bbox": [
				-114.1893205,
				51.1076158,
				-114.1857395,
				51.1098642
			]
		}
	]
}
