{
	"type": "FeatureCollection",
	"features": [
		{
			"type": "Feature",
			"properties": {
				"confidence": 9,
				"authenticationResultCode": "ValidCredentials",
				"brandLogoUri": "http://dev.virtualearth.net/Branding/logo_powered_by.png",
				"copyright": "Copyright © 2017 Microsoft and its suppliers. All rights reserved. This API cannot be accessed and the content and any results may not be used, reproduced or transmitted in any manner without express written permission from Microsoft Corporation.",
				"entityType": "Address",
				"matchCodes": [
					"Good"
				],
				"name": "1560 Raven Ave, Ottawa, ON K1Z 7Y9, Canada",
				"statusCode": 200,
				"statusDescription": "OK",
				"traceId": "6487a0d9c7834867b6128067b496e564|BN20121762|7.7.0.0|",
				"addressLine": "1560 Raven Ave",
				"adminDistrict": "ON",
				"adminDistrict2": "Ottawa",
				"countryRegion": "Canada",
				"formattedAddress": "1560 Raven Ave, Ottawa, ON K1Z 7Y9, Canada",
				"locality": "Ottawa",
				"neighborhood": "Carlington",
				"postalCode": "K1Z 7Y9"
			},
			"geometry": {
				"type": "Point",
				"coordinates": [
					-75.74282,
					45.37489
				]
			},
			"bbox": [
				-75.7444203,
				45.3737658,
				-75.7412197,
				45.3760142
			]
		}
	]
}
