{
	"type": "FeatureCollection",
	"features": [
		{
			"type": "Feature",
			"properties": {
				"confidence": 9,
				"authenticationResultCode": "ValidCredentials",
				"brandLogoUri": "http://dev.virtualearth.net/Branding/logo_powered_by.png",
				"copyright": "Copyright © 2017 Microsoft and its suppliers. All rights reserved. This API cannot be accessed and the content and any results may not be used, reproduced or transmitted in any manner without express written permission from Microsoft Corporation.",
				"entityType": "Address",
				"matchCodes": [
					"Good"
				],
				"name": "1561 Rue Sylvain, Beloeil, QC J3G 5T8, Canada",
				"statusCode": 200,
				"statusDescription": "OK",
				"traceId": "e5c75f0c4cfa47b1b2f4848356acb49c|BN20250135|7.7.0.0|",
				"addressLine": "1561 Rue Sylvain",
				"adminDistrict": "QC",
				"adminDistrict2": "La Vallée-du-Richelieu",
				"countryRegion": "Canada",
				"formattedAddress": "1561 Rue Sylvain, Beloeil, QC J3G 5T8, Canada",
				"locality": "Beloeil",
				"postalCode": "J3G 5T8"
			},
			"geometry": {
				"type": "Point",
				"coordinates": [
					-73.19617,
					45.58768
				]
			},
			"bbox": [
				-73.1977764,
				45.5865558,
				-73.1945636,
				45.5888042
			]
		}
	]
}
