{
	"type": "FeatureCollection",
	"features": [
		{
			"type": "Feature",
			"properties": {
				"confidence": 9,
				"authenticationResultCode": "ValidCredentials",
				"brandLogoUri": "http://dev.virtualearth.net/Branding/logo_powered_by.png",
				"copyright": "Copyright © 2017 Microsoft and its suppliers. All rights reserved. This API cannot be accessed and the content and any results may not be used, reproduced or transmitted in any manner without express written permission from Microsoft Corporation.",
				"entityType": "Address",
				"matchCodes": [
					"Good"
				],
				"name": "1569 Bathurst St, Toronto, ON M5P 3H8, Canada",
				"statusCode": 200,
				"statusDescription": "OK",
				"traceId": "daf13e420d804ead8dee62a4f4818bcd|BN20250135|7.7.0.0|",
				"addressLine": "1569 Bathurst St",
				"adminDistrict": "ON",
				"adminDistrict2": "Toronto",
				"countryRegion": "Canada",
				"formattedAddress": "1569 Bathurst St, Toronto, ON M5P 3H8, Canada",
				"locality": "Toronto",
				"neighborhood": "Forest Hill South",
				"postalCode": "M5P 3H8"
			},
			"geometry": {
				"type": "Point",
				"coordinates": [
					-79.41972,
					43.68763
				]
			},
			"bbox": [
				-79.4212746,
				43.6865058,
				-79.4181654,
				43.6887542
			]
		}
	]
}
