{
	"type": "FeatureCollection",
	"features": [
		{
			"type": "Feature",
			"properties": {
				"confidence": 9,
				"authenticationResultCode": "ValidCredentials",
				"brandLogoUri": "http://dev.virtualearth.net/Branding/logo_powered_by.png",
				"copyright": "Copyright © 2017 Microsoft and its suppliers. All rights reserved. This API cannot be accessed and the content and any results may not be used, reproduced or transmitted in any manner without express written permission from Microsoft Corporation.",
				"entityType": "Address",
				"matchCodes": [
					"Good"
				],
				"name": "157 4e Rue, Montmagny, QC G5V 3L6, Canada",
				"statusCode": 200,
				"statusDescription": "OK",
				"traceId": "91a1839401104bee8bfbecdaca79f41d|BN20240253|7.7.0.0|",
				"addressLine": "157 4e Rue",
				"adminDistrict": "QC",
				"adminDistrict2": "Montmagny",
				"countryRegion": "Canada",
				"formattedAddress": "157 4e Rue, Montmagny, QC G5V 3L6, Canada",
				"locality": "Montmagny",
				"postalCode": "G5V 3L6"
			},
			"geometry": {
				"type": "Point",
				"coordinates": [
					-70.57221,
					46.97074
				]
			},
			"bbox": [
				-70.5738574,
				46.9696158,
				-70.5705626,
				46.9718642
			]
		}
	]
}
