{
	"type": "FeatureCollection",
	"features": [
		{
			"type": "Feature",
			"properties": {
				"confidence": 9,
				"authenticationResultCode": "ValidCredentials",
				"brandLogoUri": "http://dev.virtualearth.net/Branding/logo_powered_by.png",
				"copyright": "Copyright © 2017 Microsoft and its suppliers. All rights reserved. This API cannot be accessed and the content and any results may not be used, reproduced or transmitted in any manner without express written permission from Microsoft Corporation.",
				"entityType": "Address",
				"matchCodes": [
					"Good"
				],
				"name": "1570 Glenmore Rd N, Kelowna, BC V1V 2C5, Canada",
				"statusCode": 200,
				"statusDescription": "OK",
				"traceId": "29059586567f4709bf4510c80971c69b|BN20130422|7.7.0.0|",
				"addressLine": "1570 Glenmore Rd N",
				"adminDistrict": "BC",
				"adminDistrict2": "Central Okanagan",
				"countryRegion": "Canada",
				"formattedAddress": "1570 Glenmore Rd N, Kelowna, BC V1V 2C5, Canada",
				"locality": "Kelowna",
				"neighborhood": "McKinley",
				"postalCode": "V1V 2C5"
			},
			"geometry": {
				"type": "Point",
				"coordinates": [
					-119.4265258,
					49.949012
				]
			},
			"bbox": [
				-119.4282728,
				49.9478878,
				-119.4247788,
				49.9501361
			]
		}
	]
}
