{
	"type": "FeatureCollection",
	"features": [
		{
			"type": "Feature",
			"properties": {
				"confidence": 9,
				"authenticationResultCode": "ValidCredentials",
				"brandLogoUri": "http://dev.virtualearth.net/Branding/logo_powered_by.png",
				"copyright": "Copyright © 2017 Microsoft and its suppliers. All rights reserved. This API cannot be accessed and the content and any results may not be used, reproduced or transmitted in any manner without express written permission from Microsoft Corporation.",
				"entityType": "Address",
				"matchCodes": [
					"Good"
				],
				"name": "15753 Central Ave, Inverness, NS B0E, Canada",
				"statusCode": 200,
				"statusDescription": "OK",
				"traceId": "854d3e653e1c4b0f975170db12581b47|BN20130422|7.7.0.0|",
				"addressLine": "15753 Central Ave",
				"adminDistrict": "NS",
				"adminDistrict2": "Inverness",
				"countryRegion": "Canada",
				"formattedAddress": "15753 Central Ave, Inverness, NS B0E, Canada",
				"locality": "Inverness",
				"postalCode": "B0E 1N0"
			},
			"geometry": {
				"type": "Point",
				"coordinates": [
					-61.3079556,
					46.2277288
				]
			},
			"bbox": [
				-61.3095806,
				46.2266047,
				-61.3063306,
				46.228853
			]
		}
	]
}
