{
	"type": "FeatureCollection",
	"features": [
		{
			"type": "Feature",
			"properties": {
				"confidence": 9,
				"authenticationResultCode": "ValidCredentials",
				"brandLogoUri": "http://dev.virtualearth.net/Branding/logo_powered_by.png",
				"copyright": "Copyright © 2017 Microsoft and its suppliers. All rights reserved. This API cannot be accessed and the content and any results may not be used, reproduced or transmitted in any manner without express written permission from Microsoft Corporation.",
				"entityType": "Address",
				"matchCodes": [
					"Good"
				],
				"name": "1580 Star Top Rd, Gloucester, ON K1B 3W6, Canada",
				"statusCode": 200,
				"statusDescription": "OK",
				"traceId": "a25877c1ca35489882350285f07d6a8d|BN20190642|7.7.0.0|",
				"addressLine": "1580 Star Top Rd",
				"adminDistrict": "ON",
				"adminDistrict2": "Ottawa",
				"countryRegion": "Canada",
				"formattedAddress": "1580 Star Top Rd, Gloucester, ON K1B 3W6, Canada",
				"locality": "Ottawa",
				"neighborhood": "Gloucester",
				"postalCode": "K1B 3W6"
			},
			"geometry": {
				"type": "Point",
				"coordinates": [
					-75.61587,
					45.4146
				]
			},
			"bbox": [
				-75.6174714,
				45.4134758,
				-75.6142686,
				45.4157242
			]
		}
	]
}
