{
	"type": "FeatureCollection",
	"features": [
		{
			"type": "Feature",
			"properties": {
				"confidence": 9,
				"authenticationResultCode": "ValidCredentials",
				"brandLogoUri": "http://dev.virtualearth.net/Branding/logo_powered_by.png",
				"copyright": "Copyright © 2017 Microsoft and its suppliers. All rights reserved. This API cannot be accessed and the content and any results may not be used, reproduced or transmitted in any manner without express written permission from Microsoft Corporation.",
				"entityType": "Address",
				"matchCodes": [
					"Good"
				],
				"name": "15801 HWY-3, Hebbville, NS B4V 6X9, Canada",
				"statusCode": 200,
				"statusDescription": "OK",
				"traceId": "48414350754f41af9c7f58fc54b116f9|BN20130632|7.7.0.0|",
				"addressLine": "15801 HWY-3",
				"adminDistrict": "NS",
				"adminDistrict2": "Lunenburg",
				"countryRegion": "Canada",
				"formattedAddress": "15801 HWY-3, Hebbville, NS B4V 6X9, Canada",
				"locality": "Hebbville",
				"postalCode": "B4V 6X9"
			},
			"geometry": {
				"type": "Point",
				"coordinates": [
					-64.5508925,
					44.33453
				]
			},
			"bbox": [
				-64.5524641,
				44.3334059,
				-64.5493208,
				44.3356542
			]
		}
	]
}
