{
	"type": "FeatureCollection",
	"features": [
		{
			"type": "Feature",
			"properties": {
				"confidence": 9,
				"authenticationResultCode": "ValidCredentials",
				"brandLogoUri": "http://dev.virtualearth.net/Branding/logo_powered_by.png",
				"copyright": "Copyright © 2017 Microsoft and its suppliers. All rights reserved. This API cannot be accessed and the content and any results may not be used, reproduced or transmitted in any manner without express written permission from Microsoft Corporation.",
				"entityType": "Address",
				"matchCodes": [
					"Good"
				],
				"name": "1588 Aberdeen St, Hawkesbury, ON K6A 2Y9, Canada",
				"statusCode": 200,
				"statusDescription": "OK",
				"traceId": "36e55f7cc1b045369a1fbdf5b4804302|BN20130621|7.7.0.0|",
				"addressLine": "1588 Aberdeen St",
				"adminDistrict": "ON",
				"adminDistrict2": "Prescott and Russell",
				"countryRegion": "Canada",
				"formattedAddress": "1588 Aberdeen St, Hawkesbury, ON K6A 2Y9, Canada",
				"locality": "Hawkesbury",
				"postalCode": "K6A 2Y9"
			},
			"geometry": {
				"type": "Point",
				"coordinates": [
					-74.5848546,
					45.6025335
				]
			},
			"bbox": [
				-74.5864614,
				45.6014094,
				-74.5832479,
				45.6036577
			]
		}
	]
}
