{
	"type": "FeatureCollection",
	"features": [
		{
			"type": "Feature",
			"properties": {
				"confidence": 9,
				"authenticationResultCode": "ValidCredentials",
				"brandLogoUri": "http://dev.virtualearth.net/Branding/logo_powered_by.png",
				"copyright": "Copyright © 2017 Microsoft and its suppliers. All rights reserved. This API cannot be accessed and the content and any results may not be used, reproduced or transmitted in any manner without express written permission from Microsoft Corporation.",
				"entityType": "Address",
				"matchCodes": [
					"Good"
				],
				"name": "1589 Lovelady Cres, Mississauga, ON L4W 2Y9, Canada",
				"statusCode": 200,
				"statusDescription": "OK",
				"traceId": "61f9f78bd04e4ea49c47527d8c47ffbb|BN20130422|7.7.0.0|",
				"addressLine": "1589 Lovelady Cres",
				"adminDistrict": "ON",
				"adminDistrict2": "Peel",
				"countryRegion": "Canada",
				"formattedAddress": "1589 Lovelady Cres, Mississauga, ON L4W 2Y9, Canada",
				"locality": "Mississauga",
				"neighborhood": "Dixie",
				"postalCode": "L4W 2Y9"
			},
			"geometry": {
				"type": "Point",
				"coordinates": [
					-79.6076,
					43.63259
				]
			},
			"bbox": [
				-79.6091532,
				43.6314658,
				-79.6060468,
				43.6337142
			]
		}
	]
}
