{
	"type": "FeatureCollection",
	"features": [
		{
			"type": "Feature",
			"properties": {
				"confidence": 9,
				"authenticationResultCode": "ValidCredentials",
				"brandLogoUri": "http://dev.virtualearth.net/Branding/logo_powered_by.png",
				"copyright": "Copyright © 2017 Microsoft and its suppliers. All rights reserved. This API cannot be accessed and the content and any results may not be used, reproduced or transmitted in any manner without express written permission from Microsoft Corporation.",
				"entityType": "Address",
				"matchCodes": [
					"Good"
				],
				"name": "16 Patina Park SW, Calgary, AB T3H 3E1, Canada",
				"statusCode": 200,
				"statusDescription": "OK",
				"traceId": "18548da54df246a9b76bb61c3a329440|BN20200239|7.7.0.0|",
				"addressLine": "16 Patina Park SW",
				"adminDistrict": "AB",
				"adminDistrict2": "Alberta",
				"countryRegion": "Canada",
				"formattedAddress": "16 Patina Park SW, Calgary, AB T3H 3E1, Canada",
				"locality": "Calgary",
				"neighborhood": "Patterson",
				"postalCode": "T3H 3E1"
			},
			"geometry": {
				"type": "Point",
				"coordinates": [
					-114.17127,
					51.05704
				]
			},
			"bbox": [
				-114.1730585,
				51.0559158,
				-114.1694815,
				51.0581642
			]
		}
	]
}
