{
	"type": "FeatureCollection",
	"features": [
		{
			"type": "Feature",
			"properties": {
				"confidence": 9,
				"authenticationResultCode": "ValidCredentials",
				"brandLogoUri": "http://dev.virtualearth.net/Branding/logo_powered_by.png",
				"copyright": "Copyright © 2017 Microsoft and its suppliers. All rights reserved. This API cannot be accessed and the content and any results may not be used, reproduced or transmitted in any manner without express written permission from Microsoft Corporation.",
				"entityType": "Address",
				"matchCodes": [
					"Good"
				],
				"name": "16 Robin St, Sherwood Park, AB T8A 0G7, Canada",
				"statusCode": 200,
				"statusDescription": "OK",
				"traceId": "c4bd66a151714205aaab576bb99022db|BN20260223|7.7.0.0|",
				"addressLine": "16 Robin St",
				"adminDistrict": "AB",
				"adminDistrict2": "Alberta",
				"countryRegion": "Canada",
				"formattedAddress": "16 Robin St, Sherwood Park, AB T8A 0G7, Canada",
				"locality": "Strathcona County",
				"neighborhood": "Sherwood Park",
				"postalCode": "T8A 0G7"
			},
			"geometry": {
				"type": "Point",
				"coordinates": [
					-113.28447,
					53.5195099
				]
			},
			"bbox": [
				-113.2863608,
				53.5183857,
				-113.2825792,
				53.5206341
			]
		}
	]
}
