{
	"type": "FeatureCollection",
	"features": [
		{
			"type": "Feature",
			"properties": {
				"confidence": 9,
				"authenticationResultCode": "ValidCredentials",
				"brandLogoUri": "http://dev.virtualearth.net/Branding/logo_powered_by.png",
				"copyright": "Copyright © 2017 Microsoft and its suppliers. All rights reserved. This API cannot be accessed and the content and any results may not be used, reproduced or transmitted in any manner without express written permission from Microsoft Corporation.",
				"entityType": "Address",
				"matchCodes": [
					"Good"
				],
				"name": "160 Starrs Rd, Yarmouth, NS B5A 5J7, Canada",
				"statusCode": 200,
				"statusDescription": "OK",
				"traceId": "776b7c37850a41d0ae084c589d2c61a9|BN20130422|7.7.0.0|",
				"addressLine": "160 Starrs Rd",
				"adminDistrict": "NS",
				"adminDistrict2": "Yarmouth",
				"countryRegion": "Canada",
				"formattedAddress": "160 Starrs Rd, Yarmouth, NS B5A 5J7, Canada",
				"locality": "Yarmouth",
				"postalCode": "B5A 5J7"
			},
			"geometry": {
				"type": "Point",
				"coordinates": [
					-66.09014,
					43.83787
				]
			},
			"bbox": [
				-66.0916985,
				43.8367458,
				-66.0885815,
				43.8389942
			]
		}
	]
}
