{
	"type": "FeatureCollection",
	"features": [
		{
			"type": "Feature",
			"properties": {
				"confidence": 9,
				"authenticationResultCode": "ValidCredentials",
				"brandLogoUri": "http://dev.virtualearth.net/Branding/logo_powered_by.png",
				"copyright": "Copyright © 2017 Microsoft and its suppliers. All rights reserved. This API cannot be accessed and the content and any results may not be used, reproduced or transmitted in any manner without express written permission from Microsoft Corporation.",
				"entityType": "Address",
				"matchCodes": [
					"Good"
				],
				"name": "1600 Rue de Lachenaie, Terrebonne, QC J6W 4J3, Canada",
				"statusCode": 200,
				"statusDescription": "OK",
				"traceId": "b2e4064729f84a07bc5c99c133dc9739|BN20130533|7.7.0.0|",
				"addressLine": "1600 Rue de Lachenaie",
				"adminDistrict": "QC",
				"adminDistrict2": "Les Moulins",
				"countryRegion": "Canada",
				"formattedAddress": "1600 Rue de Lachenaie, Terrebonne, QC J6W 4J3, Canada",
				"locality": "Terrebonne",
				"postalCode": "J6W 4J3"
			},
			"geometry": {
				"type": "Point",
				"coordinates": [
					-73.65354,
					45.70723
				]
			},
			"bbox": [
				-73.6551498,
				45.7061058,
				-73.6519302,
				45.7083542
			]
		}
	]
}
