{
	"type": "FeatureCollection",
	"features": [
		{
			"type": "Feature",
			"properties": {
				"confidence": 9,
				"authenticationResultCode": "ValidCredentials",
				"brandLogoUri": "http://dev.virtualearth.net/Branding/logo_powered_by.png",
				"copyright": "Copyright © 2017 Microsoft and its suppliers. All rights reserved. This API cannot be accessed and the content and any results may not be used, reproduced or transmitted in any manner without express written permission from Microsoft Corporation.",
				"entityType": "Address",
				"matchCodes": [
					"Good"
				],
				"name": "1601 Lower Water St, Halifax, NS B3J 3P6, Canada",
				"statusCode": 200,
				"statusDescription": "OK",
				"traceId": "affef1fc1b18422b85bb835ee214e5dc|BN20130423|7.7.0.0|",
				"addressLine": "1601 Lower Water St",
				"adminDistrict": "NS",
				"adminDistrict2": "Halifax",
				"countryRegion": "Canada",
				"formattedAddress": "1601 Lower Water St, Halifax, NS B3J 3P6, Canada",
				"locality": "Halifax",
				"neighborhood": "Downtown Halifax",
				"postalCode": "B3J 3P6"
			},
			"geometry": {
				"type": "Point",
				"coordinates": [
					-63.5706825,
					44.6458645
				]
			},
			"bbox": [
				-63.5722626,
				44.6447403,
				-63.5691025,
				44.6469886
			]
		}
	]
}
