{
	"type": "FeatureCollection",
	"features": [
		{
			"type": "Feature",
			"properties": {
				"confidence": 9,
				"authenticationResultCode": "ValidCredentials",
				"brandLogoUri": "http://dev.virtualearth.net/Branding/logo_powered_by.png",
				"copyright": "Copyright © 2017 Microsoft and its suppliers. All rights reserved. This API cannot be accessed and the content and any results may not be used, reproduced or transmitted in any manner without express written permission from Microsoft Corporation.",
				"entityType": "Address",
				"matchCodes": [
					"Good"
				],
				"name": "16065 Humber Station Rd, Caledon, ON L7E 3A4, Canada",
				"statusCode": 200,
				"statusDescription": "OK",
				"traceId": "f85a860d723f430cb75292803c3307d4|BN20130423|7.7.0.0|",
				"addressLine": "16065 Humber Station Rd",
				"adminDistrict": "ON",
				"adminDistrict2": "Peel",
				"countryRegion": "Canada",
				"formattedAddress": "16065 Humber Station Rd, Caledon, ON L7E 3A4, Canada",
				"locality": "Caledon",
				"neighborhood": "Palgrave",
				"postalCode": "L7E 3A4"
			},
			"geometry": {
				"type": "Point",
				"coordinates": [
					-79.82566,
					43.90937
				]
			},
			"bbox": [
				-79.8272204,
				43.9082458,
				-79.8240996,
				43.9104942
			]
		}
	]
}
