{
	"type": "FeatureCollection",
	"features": [
		{
			"type": "Feature",
			"properties": {
				"confidence": 9,
				"authenticationResultCode": "ValidCredentials",
				"brandLogoUri": "http://dev.virtualearth.net/Branding/logo_powered_by.png",
				"copyright": "Copyright © 2017 Microsoft and its suppliers. All rights reserved. This API cannot be accessed and the content and any results may not be used, reproduced or transmitted in any manner without express written permission from Microsoft Corporation.",
				"entityType": "Address",
				"matchCodes": [
					"Good"
				],
				"name": "161 Dovetail Dr, Richmond Hill, ON L4E 5A8, Canada",
				"statusCode": 200,
				"statusDescription": "OK",
				"traceId": "3115ffa9cfc74c3abb627ab48ac2c5f8|BN20130521|7.7.0.0|",
				"addressLine": "161 Dovetail Dr",
				"adminDistrict": "ON",
				"adminDistrict2": "York",
				"countryRegion": "Canada",
				"formattedAddress": "161 Dovetail Dr, Richmond Hill, ON L4E 5A8, Canada",
				"locality": "Richmond Hill",
				"postalCode": "L4E 5A8"
			},
			"geometry": {
				"type": "Point",
				"coordinates": [
					-79.4302699,
					43.94101
				]
			},
			"bbox": [
				-79.4318311,
				43.9398858,
				-79.4287087,
				43.9421342
			]
		}
	]
}
