{
	"type": "FeatureCollection",
	"features": [
		{
			"type": "Feature",
			"properties": {
				"confidence": 9,
				"authenticationResultCode": "ValidCredentials",
				"brandLogoUri": "http://dev.virtualearth.net/Branding/logo_powered_by.png",
				"copyright": "Copyright © 2017 Microsoft and its suppliers. All rights reserved. This API cannot be accessed and the content and any results may not be used, reproduced or transmitted in any manner without express written permission from Microsoft Corporation.",
				"entityType": "Address",
				"matchCodes": [
					"Good"
				],
				"name": "161 Bay St, Toronto, ON M5J 2S1, Canada",
				"statusCode": 200,
				"statusDescription": "OK",
				"traceId": "11868f27696a4a75906d1d8eece48f44|BN20130422|7.7.0.0|",
				"addressLine": "161 Bay St",
				"adminDistrict": "ON",
				"adminDistrict2": "Toronto",
				"countryRegion": "Canada",
				"formattedAddress": "161 Bay St, Toronto, ON M5J 2S1, Canada",
				"locality": "Toronto",
				"neighborhood": "Bay Street Corridor",
				"postalCode": "M5J 2S1"
			},
			"geometry": {
				"type": "Point",
				"coordinates": [
					-79.3787399,
					43.64652
				]
			},
			"bbox": [
				-79.3802934,
				43.6453958,
				-79.3771864,
				43.6476442
			]
		}
	]
}
