{
	"type": "FeatureCollection",
	"features": [
		{
			"type": "Feature",
			"properties": {
				"confidence": 9,
				"authenticationResultCode": "ValidCredentials",
				"brandLogoUri": "http://dev.virtualearth.net/Branding/logo_powered_by.png",
				"copyright": "Copyright © 2017 Microsoft and its suppliers. All rights reserved. This API cannot be accessed and the content and any results may not be used, reproduced or transmitted in any manner without express written permission from Microsoft Corporation.",
				"entityType": "Address",
				"matchCodes": [
					"Good"
				],
				"name": "1610 Feldspar Ct, Pickering, ON L1W 3R7, Canada",
				"statusCode": 200,
				"statusDescription": "OK",
				"traceId": "f89d826d46d54947a0999ca6eb8bbb2e|BN20160335|7.7.0.0|",
				"addressLine": "1610 Feldspar Ct",
				"adminDistrict": "ON",
				"adminDistrict2": "Durham",
				"countryRegion": "Canada",
				"formattedAddress": "1610 Feldspar Ct, Pickering, ON L1W 3R7, Canada",
				"locality": "Pickering",
				"postalCode": "L1W 3R7"
			},
			"geometry": {
				"type": "Point",
				"coordinates": [
					-79.06538,
					43.82256
				]
			},
			"bbox": [
				-79.0669381,
				43.8214358,
				-79.0638219,
				43.8236842
			]
		}
	]
}
