{
	"type": "FeatureCollection",
	"features": [
		{
			"type": "Feature",
			"properties": {
				"confidence": 9,
				"authenticationResultCode": "ValidCredentials",
				"brandLogoUri": "http://dev.virtualearth.net/Branding/logo_powered_by.png",
				"copyright": "Copyright © 2017 Microsoft and its suppliers. All rights reserved. This API cannot be accessed and the content and any results may not be used, reproduced or transmitted in any manner without express written permission from Microsoft Corporation.",
				"entityType": "Address",
				"matchCodes": [
					"Good"
				],
				"name": "1615 Towne Centre Blvd NW, Edmonton, AB T6R 0S3, Canada",
				"statusCode": 200,
				"statusDescription": "OK",
				"traceId": "098a422cb13042119b99382d9983e8ca|BN20130532|7.7.0.0|",
				"addressLine": "1615 Towne Centre Blvd NW",
				"adminDistrict": "AB",
				"adminDistrict2": "Alberta",
				"countryRegion": "Canada",
				"formattedAddress": "1615 Towne Centre Blvd NW, Edmonton, AB T6R 0S3, Canada",
				"locality": "Edmonton",
				"neighborhood": "Terwillegar South",
				"postalCode": "T6R 0S3"
			},
			"geometry": {
				"type": "Point",
				"coordinates": [
					-113.5776151,
					53.4434901
				]
			},
			"bbox": [
				-113.5795025,
				53.442366,
				-113.5757277,
				53.4446143
			]
		}
	]
}
