{
	"type": "FeatureCollection",
	"features": [
		{
			"type": "Feature",
			"properties": {
				"confidence": 9,
				"authenticationResultCode": "ValidCredentials",
				"brandLogoUri": "http://dev.virtualearth.net/Branding/logo_powered_by.png",
				"copyright": "Copyright © 2017 Microsoft and its suppliers. All rights reserved. This API cannot be accessed and the content and any results may not be used, reproduced or transmitted in any manner without express written permission from Microsoft Corporation.",
				"entityType": "Address",
				"matchCodes": [
					"Good"
				],
				"name": "16194 CR-43, North Stormont, ON K0C, Canada",
				"statusCode": 200,
				"statusDescription": "OK",
				"traceId": "185b4ef82e1e471da62bcc080ed4190e|BN20130533|7.7.0.0|",
				"addressLine": "16194 CR-43",
				"adminDistrict": "ON",
				"adminDistrict2": "Stormont, Dundas and Glengarry",
				"countryRegion": "Canada",
				"formattedAddress": "16194 CR-43, North Stormont, ON K0C, Canada",
				"locality": "North Stormont",
				"neighborhood": "Avonmore",
				"postalCode": "K0C 1C0"
			},
			"geometry": {
				"type": "Point",
				"coordinates": [
					-74.9790074,
					45.1671403
				]
			},
			"bbox": [
				-74.9806019,
				45.1660162,
				-74.977413,
				45.1682645
			]
		}
	]
}
