{
	"type": "FeatureCollection",
	"features": [
		{
			"type": "Feature",
			"properties": {
				"confidence": 9,
				"authenticationResultCode": "ValidCredentials",
				"brandLogoUri": "http://dev.virtualearth.net/Branding/logo_powered_by.png",
				"copyright": "Copyright © 2017 Microsoft and its suppliers. All rights reserved. This API cannot be accessed and the content and any results may not be used, reproduced or transmitted in any manner without express written permission from Microsoft Corporation.",
				"entityType": "Address",
				"matchCodes": [
					"Good"
				],
				"name": "628 E Kent Ave S, Vancouver, BC V5X, Canada",
				"statusCode": 200,
				"statusDescription": "OK",
				"traceId": "5a3e3841685c436896e6985fa0e85c3f|BN20250135|7.7.0.0|",
				"addressLine": "628 E Kent Ave S",
				"adminDistrict": "BC",
				"adminDistrict2": "Greater Vancouver",
				"countryRegion": "Canada",
				"formattedAddress": "628 E Kent Ave S, Vancouver, BC V5X, Canada",
				"locality": "Vancouver",
				"neighborhood": "Sunset",
				"postalCode": "V5X 0B2"
			},
			"geometry": {
				"type": "Point",
				"coordinates": [
					-123.0930838,
					49.2076837
				]
			},
			"bbox": [
				-123.0948045,
				49.2065595,
				-123.0913631,
				49.2088078
			]
		}
	]
}
