{
	"type": "FeatureCollection",
	"features": [
		{
			"type": "Feature",
			"properties": {
				"confidence": 9,
				"authenticationResultCode": "ValidCredentials",
				"brandLogoUri": "http://dev.virtualearth.net/Branding/logo_powered_by.png",
				"copyright": "Copyright © 2017 Microsoft and its suppliers. All rights reserved. This API cannot be accessed and the content and any results may not be used, reproduced or transmitted in any manner without express written permission from Microsoft Corporation.",
				"entityType": "Address",
				"matchCodes": [
					"Good"
				],
				"name": "1620 W 75th Ave, Vancouver, BC V6P 6G2, Canada",
				"statusCode": 200,
				"statusDescription": "OK",
				"traceId": "a7c2407d51a54f4bb0e5a1672c702f0b|BN20171457|7.7.0.0|",
				"addressLine": "1620 W 75th Ave",
				"adminDistrict": "BC",
				"adminDistrict2": "Greater Vancouver",
				"countryRegion": "Canada",
				"formattedAddress": "1620 W 75th Ave, Vancouver, BC V6P 6G2, Canada",
				"locality": "Vancouver",
				"neighborhood": "Marpole",
				"postalCode": "V6P 6G2"
			},
			"geometry": {
				"type": "Point",
				"coordinates": [
					-123.1449265,
					49.2052331
				]
			},
			"bbox": [
				-123.1466471,
				49.2041089,
				-123.1432059,
				49.2063572
			]
		}
	]
}
