{
	"type": "FeatureCollection",
	"features": [
		{
			"type": "Feature",
			"properties": {
				"confidence": 3,
				"authenticationResultCode": "ValidCredentials",
				"brandLogoUri": "http://dev.virtualearth.net/Branding/logo_powered_by.png",
				"copyright": "Copyright © 2017 Microsoft and its suppliers. All rights reserved. This API cannot be accessed and the content and any results may not be used, reproduced or transmitted in any manner without express written permission from Microsoft Corporation.",
				"entityType": "RoadBlock",
				"matchCodes": [
					"Good"
				],
				"name": "Lake Temagami Access Rd, Temagami, ON P0H, Canada",
				"statusCode": 200,
				"statusDescription": "OK",
				"traceId": "685cfc283c1a473f8234e09c60d09b04|BN20200137|7.7.0.0|",
				"addressLine": "Lake Temagami Access Rd",
				"adminDistrict": "ON",
				"adminDistrict2": "Nipissing",
				"countryRegion": "Canada",
				"formattedAddress": "Lake Temagami Access Rd, Temagami, ON P0H, Canada",
				"locality": "Temagami",
				"postalCode": "P0H 2H0"
			},
			"geometry": {
				"type": "Point",
				"coordinates": [
					-79.91862,
					46.9858199
				]
			},
			"bbox": [
				-80.01845,
				46.96166,
				-79.8185,
				47.01231
			]
		}
	]
}
