{
	"type": "FeatureCollection",
	"features": [
		{
			"type": "Feature",
			"properties": {
				"confidence": 9,
				"authenticationResultCode": "ValidCredentials",
				"brandLogoUri": "http://dev.virtualearth.net/Branding/logo_powered_by.png",
				"copyright": "Copyright © 2017 Microsoft and its suppliers. All rights reserved. This API cannot be accessed and the content and any results may not be used, reproduced or transmitted in any manner without express written permission from Microsoft Corporation.",
				"entityType": "Address",
				"matchCodes": [
					"Good"
				],
				"name": "1626 Rue Galt E, Sherbrooke, QC J1G 3H5, Canada",
				"statusCode": 200,
				"statusDescription": "OK",
				"traceId": "ecd2cc378f4e429cac95e49da961dfd9|BN20171457|7.7.0.0|",
				"addressLine": "1626 Rue Galt E",
				"adminDistrict": "QC",
				"adminDistrict2": "Sherbrooke",
				"countryRegion": "Canada",
				"formattedAddress": "1626 Rue Galt E, Sherbrooke, QC J1G 3H5, Canada",
				"locality": "Sherbrooke",
				"neighborhood": "Fleurimont",
				"postalCode": "J1G 3H5"
			},
			"geometry": {
				"type": "Point",
				"coordinates": [
					-71.85333,
					45.40167
				]
			},
			"bbox": [
				-71.8549311,
				45.4005458,
				-71.8517289,
				45.4027942
			]
		}
	]
}
