{
	"type": "FeatureCollection",
	"features": [
		{
			"type": "Feature",
			"properties": {
				"confidence": 9,
				"authenticationResultCode": "ValidCredentials",
				"brandLogoUri": "http://dev.virtualearth.net/Branding/logo_powered_by.png",
				"copyright": "Copyright © 2017 Microsoft and its suppliers. All rights reserved. This API cannot be accessed and the content and any results may not be used, reproduced or transmitted in any manner without express written permission from Microsoft Corporation.",
				"entityType": "Address",
				"matchCodes": [
					"Good"
				],
				"name": "1629 Rue de Touraine, Laval, QC H7N 5W2, Canada",
				"statusCode": 200,
				"statusDescription": "OK",
				"traceId": "8bdad20d009e4b439d8349ade6ff0107|BN20130620|7.7.0.0|",
				"addressLine": "1629 Rue de Touraine",
				"adminDistrict": "QC",
				"adminDistrict2": "Laval",
				"countryRegion": "Canada",
				"formattedAddress": "1629 Rue de Touraine, Laval, QC H7N 5W2, Canada",
				"locality": "Laval",
				"neighborhood": "Bélanger",
				"postalCode": "H7N 5W2"
			},
			"geometry": {
				"type": "Point",
				"coordinates": [
					-73.70926,
					45.5754
				]
			},
			"bbox": [
				-73.710866,
				45.5742758,
				-73.707654,
				45.5765242
			]
		}
	]
}
