{
	"type": "FeatureCollection",
	"features": [
		{
			"type": "Feature",
			"properties": {
				"confidence": 9,
				"authenticationResultCode": "ValidCredentials",
				"brandLogoUri": "http://dev.virtualearth.net/Branding/logo_powered_by.png",
				"copyright": "Copyright © 2017 Microsoft and its suppliers. All rights reserved. This API cannot be accessed and the content and any results may not be used, reproduced or transmitted in any manner without express written permission from Microsoft Corporation.",
				"entityType": "Address",
				"matchCodes": [
					"Good"
				],
				"name": "163 Stronach Cres, London, ON N5V 3G5, Canada",
				"statusCode": 200,
				"statusDescription": "OK",
				"traceId": "7569fb040d224ece89ec478c4cc6a7b5|BN20320521|7.7.0.0|",
				"addressLine": "163 Stronach Cres",
				"adminDistrict": "ON",
				"adminDistrict2": "Middlesex",
				"countryRegion": "Canada",
				"formattedAddress": "163 Stronach Cres, London, ON N5V 3G5, Canada",
				"locality": "London",
				"neighborhood": "Huron Heights",
				"postalCode": "N5V 3G5"
			},
			"geometry": {
				"type": "Point",
				"coordinates": [
					-81.1875,
					43.0248
				]
			},
			"bbox": [
				-81.1890377,
				43.0236758,
				-81.1859623,
				43.0259242
			]
		}
	]
}
