{
	"type": "FeatureCollection",
	"features": [
		{
			"type": "Feature",
			"properties": {
				"confidence": 9,
				"authenticationResultCode": "ValidCredentials",
				"brandLogoUri": "http://dev.virtualearth.net/Branding/logo_powered_by.png",
				"copyright": "Copyright © 2017 Microsoft and its suppliers. All rights reserved. This API cannot be accessed and the content and any results may not be used, reproduced or transmitted in any manner without express written permission from Microsoft Corporation.",
				"entityType": "Address",
				"matchCodes": [
					"Good"
				],
				"name": "164 Sandalwood Pkwy E, Brampton, ON L6Z 3S4, Canada",
				"statusCode": 200,
				"statusDescription": "OK",
				"traceId": "ebe89a7fe7ee48ccbabdca90970dccb2|BN20190653|7.7.0.0|",
				"addressLine": "164 Sandalwood Pkwy E",
				"adminDistrict": "ON",
				"adminDistrict2": "Peel",
				"countryRegion": "Canada",
				"formattedAddress": "164 Sandalwood Pkwy E, Brampton, ON L6Z 3S4, Canada",
				"locality": "Brampton",
				"neighborhood": "Heart Lake",
				"postalCode": "L6Z 3S4"
			},
			"geometry": {
				"type": "Point",
				"coordinates": [
					-79.79581,
					43.72706
				]
			},
			"bbox": [
				-79.7973656,
				43.7259358,
				-79.7942544,
				43.7281842
			]
		}
	]
}
