{
	"type": "FeatureCollection",
	"features": [
		{
			"type": "Feature",
			"properties": {
				"confidence": 9,
				"authenticationResultCode": "ValidCredentials",
				"brandLogoUri": "http://dev.virtualearth.net/Branding/logo_powered_by.png",
				"copyright": "Copyright © 2017 Microsoft and its suppliers. All rights reserved. This API cannot be accessed and the content and any results may not be used, reproduced or transmitted in any manner without express written permission from Microsoft Corporation.",
				"entityType": "Address",
				"matchCodes": [
					"Good"
				],
				"name": "16404 100 Ave NW, Edmonton, AB T5P 4Y2, Canada",
				"statusCode": 200,
				"statusDescription": "OK",
				"traceId": "5a8cf5fd04f14aa0976c770ff059ed71|BN20200137|7.7.0.0|",
				"addressLine": "16404 100 Ave NW",
				"adminDistrict": "AB",
				"adminDistrict2": "Alberta",
				"countryRegion": "Canada",
				"formattedAddress": "16404 100 Ave NW, Edmonton, AB T5P 4Y2, Canada",
				"locality": "Edmonton",
				"neighborhood": "Glenwood",
				"postalCode": "T5P 4Y2"
			},
			"geometry": {
				"type": "Point",
				"coordinates": [
					-113.60534,
					53.5400599
				]
			},
			"bbox": [
				-113.6072317,
				53.5389357,
				-113.6034483,
				53.5411841
			]
		}
	]
}
