{
	"type": "FeatureCollection",
	"features": [
		{
			"type": "Feature",
			"properties": {
				"confidence": 9,
				"authenticationResultCode": "ValidCredentials",
				"brandLogoUri": "http://dev.virtualearth.net/Branding/logo_powered_by.png",
				"copyright": "Copyright © 2017 Microsoft and its suppliers. All rights reserved. This API cannot be accessed and the content and any results may not be used, reproduced or transmitted in any manner without express written permission from Microsoft Corporation.",
				"entityType": "Address",
				"matchCodes": [
					"Good"
				],
				"name": "165 St Peter St, Lindsay, ON K9V 5A7, Canada",
				"statusCode": 200,
				"statusDescription": "OK",
				"traceId": "ad836e96b9514ad68dce1c488ed8089f|BN20250135|7.7.0.0|",
				"addressLine": "165 St Peter St",
				"adminDistrict": "ON",
				"adminDistrict2": "Kawartha Lakes",
				"countryRegion": "Canada",
				"formattedAddress": "165 St Peter St, Lindsay, ON K9V 5A7, Canada",
				"locality": "Kawartha Lakes",
				"neighborhood": "Lindsay",
				"postalCode": "K9V 5A7"
			},
			"geometry": {
				"type": "Point",
				"coordinates": [
					-78.7328344,
					44.3680825
				]
			},
			"bbox": [
				-78.7344069,
				44.3669583,
				-78.7312618,
				44.3692066
			]
		}
	]
}
