{
	"type": "FeatureCollection",
	"features": [
		{
			"type": "Feature",
			"properties": {
				"confidence": 9,
				"authenticationResultCode": "ValidCredentials",
				"brandLogoUri": "http://dev.virtualearth.net/Branding/logo_powered_by.png",
				"copyright": "Copyright © 2017 Microsoft and its suppliers. All rights reserved. This API cannot be accessed and the content and any results may not be used, reproduced or transmitted in any manner without express written permission from Microsoft Corporation.",
				"entityType": "Address",
				"matchCodes": [
					"Good"
				],
				"name": "1651 King George Blvd, Surrey, BC V4A 4Z7, Canada",
				"statusCode": 200,
				"statusDescription": "OK",
				"traceId": "7f5e029c7db64414a6c8b7080120944a|BN20130422|7.7.0.0|",
				"addressLine": "1651 King George Blvd",
				"adminDistrict": "BC",
				"adminDistrict2": "Greater Vancouver",
				"countryRegion": "Canada",
				"formattedAddress": "1651 King George Blvd, Surrey, BC V4A 4Z7, Canada",
				"locality": "Surrey",
				"neighborhood": "South Surrey",
				"postalCode": "V4A 4Z7"
			},
			"geometry": {
				"type": "Point",
				"coordinates": [
					-122.77694,
					49.03176
				]
			},
			"bbox": [
				-122.7786546,
				49.0306358,
				-122.7752254,
				49.0328842
			]
		}
	]
}
