{
	"type": "FeatureCollection",
	"features": [
		{
			"type": "Feature",
			"properties": {
				"confidence": 9,
				"authenticationResultCode": "ValidCredentials",
				"brandLogoUri": "http://dev.virtualearth.net/Branding/logo_powered_by.png",
				"copyright": "Copyright © 2017 Microsoft and its suppliers. All rights reserved. This API cannot be accessed and the content and any results may not be used, reproduced or transmitted in any manner without express written permission from Microsoft Corporation.",
				"entityType": "Address",
				"matchCodes": [
					"Good"
				],
				"name": "1657 Carling Ave, Ottawa, ON K2A 1C4, Canada",
				"statusCode": 200,
				"statusDescription": "OK",
				"traceId": "b3d081ea9c504882b26b436d11e358b9|BN20130634|7.7.0.0|",
				"addressLine": "1657 Carling Ave",
				"adminDistrict": "ON",
				"adminDistrict2": "Ottawa",
				"countryRegion": "Canada",
				"formattedAddress": "1657 Carling Ave, Ottawa, ON K2A 1C4, Canada",
				"locality": "Ottawa",
				"neighborhood": "Carlingwood-McKellar Pk-Laurentien",
				"postalCode": "K2A 1C4"
			},
			"geometry": {
				"type": "Point",
				"coordinates": [
					-75.74923,
					45.37998
				]
			},
			"bbox": [
				-75.7508304,
				45.3788558,
				-75.7476296,
				45.3811042
			]
		}
	]
}
