{
	"type": "FeatureCollection",
	"features": [
		{
			"type": "Feature",
			"properties": {
				"confidence": 9,
				"authenticationResultCode": "ValidCredentials",
				"brandLogoUri": "http://dev.virtualearth.net/Branding/logo_powered_by.png",
				"copyright": "Copyright © 2017 Microsoft and its suppliers. All rights reserved. This API cannot be accessed and the content and any results may not be used, reproduced or transmitted in any manner without express written permission from Microsoft Corporation.",
				"entityType": "Address",
				"matchCodes": [
					"Good"
				],
				"name": "16680 Mountainview Rd, Caledon East, ON L7C 2V4, Canada",
				"statusCode": 200,
				"statusDescription": "OK",
				"traceId": "4a2103144ab44f8ea27c477a876c6568|BN20121764|7.7.0.0|",
				"addressLine": "16680 Mountainview Rd",
				"adminDistrict": "ON",
				"adminDistrict2": "Peel",
				"countryRegion": "Canada",
				"formattedAddress": "16680 Mountainview Rd, Caledon East, ON L7C 2V4, Canada",
				"locality": "Caledon",
				"neighborhood": "Caledon East",
				"postalCode": "L7C 2V4"
			},
			"geometry": {
				"type": "Point",
				"coordinates": [
					-79.89797,
					43.87324
				]
			},
			"bbox": [
				-79.8995294,
				43.8721158,
				-79.8964106,
				43.8743642
			]
		}
	]
}
