{
	"type": "FeatureCollection",
	"features": [
		{
			"type": "Feature",
			"properties": {
				"confidence": 9,
				"authenticationResultCode": "ValidCredentials",
				"brandLogoUri": "http://dev.virtualearth.net/Branding/logo_powered_by.png",
				"copyright": "Copyright © 2017 Microsoft and its suppliers. All rights reserved. This API cannot be accessed and the content and any results may not be used, reproduced or transmitted in any manner without express written permission from Microsoft Corporation.",
				"entityType": "Address",
				"matchCodes": [
					"Good"
				],
				"name": "1679 Heron Rd, Ottawa, ON K1V 6A2, Canada",
				"statusCode": 200,
				"statusDescription": "OK",
				"traceId": "78bda9f313ba42f5abfbd99bcafa9ac1|BN20121763|7.7.0.0|",
				"addressLine": "1679 Heron Rd",
				"adminDistrict": "ON",
				"adminDistrict2": "Ottawa",
				"countryRegion": "Canada",
				"formattedAddress": "1679 Heron Rd, Ottawa, ON K1V 6A2, Canada",
				"locality": "Ottawa",
				"neighborhood": "Playfair Park-Lynda Park-Guildwood",
				"postalCode": "K1V 6A2"
			},
			"geometry": {
				"type": "Point",
				"coordinates": [
					-75.64394,
					45.38046
				]
			},
			"bbox": [
				-75.6455405,
				45.3793358,
				-75.6423395,
				45.3815842
			]
		}
	]
}
