{
	"type": "FeatureCollection",
	"features": [
		{
			"type": "Feature",
			"properties": {
				"confidence": 9,
				"authenticationResultCode": "ValidCredentials",
				"brandLogoUri": "http://dev.virtualearth.net/Branding/logo_powered_by.png",
				"copyright": "Copyright © 2017 Microsoft and its suppliers. All rights reserved. This API cannot be accessed and the content and any results may not be used, reproduced or transmitted in any manner without express written permission from Microsoft Corporation.",
				"entityType": "Address",
				"matchCodes": [
					"Good"
				],
				"name": "1681 Langstaff Rd, Concord, ON L4K 5T3, Canada",
				"statusCode": 200,
				"statusDescription": "OK",
				"traceId": "940d73d173274ad29a1723bb93e95d18|BN20220145|7.7.0.0|",
				"addressLine": "1681 Langstaff Rd",
				"adminDistrict": "ON",
				"adminDistrict2": "York",
				"countryRegion": "Canada",
				"formattedAddress": "1681 Langstaff Rd, Concord, ON L4K 5T3, Canada",
				"locality": "Vaughan",
				"neighborhood": "Concord",
				"postalCode": "L4K 5T3"
			},
			"geometry": {
				"type": "Point",
				"coordinates": [
					-79.48333,
					43.82238
				]
			},
			"bbox": [
				-79.4848881,
				43.8212558,
				-79.4817719,
				43.8235042
			]
		}
	]
}
