{
	"type": "FeatureCollection",
	"features": [
		{
			"type": "Feature",
			"properties": {
				"confidence": 9,
				"authenticationResultCode": "ValidCredentials",
				"brandLogoUri": "http://dev.virtualearth.net/Branding/logo_powered_by.png",
				"copyright": "Copyright © 2017 Microsoft and its suppliers. All rights reserved. This API cannot be accessed and the content and any results may not be used, reproduced or transmitted in any manner without express written permission from Microsoft Corporation.",
				"entityType": "Address",
				"matchCodes": [
					"Good"
				],
				"name": "16820 107 Ave NW, Edmonton, AB T5P 4C3, Canada",
				"statusCode": 200,
				"statusDescription": "OK",
				"traceId": "47c730ce6af34a2496d3b9b7161a0487|BN20240423|7.7.0.0|",
				"addressLine": "16820 107 Ave NW",
				"adminDistrict": "AB",
				"adminDistrict2": "Alberta",
				"countryRegion": "Canada",
				"formattedAddress": "16820 107 Ave NW, Edmonton, AB T5P 4C3, Canada",
				"locality": "Edmonton",
				"neighborhood": "Youngstown Industrial",
				"postalCode": "T5P 4C3"
			},
			"geometry": {
				"type": "Point",
				"coordinates": [
					-113.60868,
					53.55344
				]
			},
			"bbox": [
				-113.6105723,
				53.5523158,
				-113.6067877,
				53.5545642
			]
		}
	]
}
