{
	"type": "FeatureCollection",
	"features": [
		{
			"type": "Feature",
			"properties": {
				"confidence": 9,
				"authenticationResultCode": "ValidCredentials",
				"brandLogoUri": "http://dev.virtualearth.net/Branding/logo_powered_by.png",
				"copyright": "Copyright © 2017 Microsoft and its suppliers. All rights reserved. This API cannot be accessed and the content and any results may not be used, reproduced or transmitted in any manner without express written permission from Microsoft Corporation.",
				"entityType": "Address",
				"matchCodes": [
					"Good"
				],
				"name": "1685 Rue Fleetwood, Laval, QC H7N 4B2, Canada",
				"statusCode": 200,
				"statusDescription": "OK",
				"traceId": "50b0b7b60eca436ca0a0a84940d23793|BN20210145|7.7.0.0|",
				"addressLine": "1685 Rue Fleetwood",
				"adminDistrict": "QC",
				"adminDistrict2": "Laval",
				"countryRegion": "Canada",
				"formattedAddress": "1685 Rue Fleetwood, Laval, QC H7N 4B2, Canada",
				"locality": "Laval",
				"neighborhood": "Bélanger",
				"postalCode": "H7N 4B2"
			},
			"geometry": {
				"type": "Point",
				"coordinates": [
					-73.71238,
					45.57424
				]
			},
			"bbox": [
				-73.713986,
				45.5731158,
				-73.710774,
				45.5753642
			]
		}
	]
}
