{
	"type": "FeatureCollection",
	"features": [
		{
			"type": "Feature",
			"properties": {
				"confidence": 9,
				"authenticationResultCode": "ValidCredentials",
				"brandLogoUri": "http://dev.virtualearth.net/Branding/logo_powered_by.png",
				"copyright": "Copyright © 2017 Microsoft and its suppliers. All rights reserved. This API cannot be accessed and the content and any results may not be used, reproduced or transmitted in any manner without express written permission from Microsoft Corporation.",
				"entityType": "Address",
				"matchCodes": [
					"Good"
				],
				"name": "1687 Arborwood Dr, Oshawa, ON L1K 0P1, Canada",
				"statusCode": 200,
				"statusDescription": "OK",
				"traceId": "2906a3dedab044258e25481a1bca872e|BN20130522|7.7.0.0|",
				"addressLine": "1687 Arborwood Dr",
				"adminDistrict": "ON",
				"adminDistrict2": "Durham",
				"countryRegion": "Canada",
				"formattedAddress": "1687 Arborwood Dr, Oshawa, ON L1K 0P1, Canada",
				"locality": "Oshawa",
				"neighborhood": "Taunton",
				"postalCode": "L1K 0P1"
			},
			"geometry": {
				"type": "Point",
				"coordinates": [
					-78.8364452,
					43.9499136
				]
			},
			"bbox": [
				-78.8380066,
				43.9487895,
				-78.8348837,
				43.9510378
			]
		}
	]
}
