{
	"type": "FeatureCollection",
	"features": [
		{
			"type": "Feature",
			"properties": {
				"confidence": 9,
				"authenticationResultCode": "ValidCredentials",
				"brandLogoUri": "http://dev.virtualearth.net/Branding/logo_powered_by.png",
				"copyright": "Copyright © 2017 Microsoft and its suppliers. All rights reserved. This API cannot be accessed and the content and any results may not be used, reproduced or transmitted in any manner without express written permission from Microsoft Corporation.",
				"entityType": "Address",
				"matchCodes": [
					"Good"
				],
				"name": "169 Balsam Ave, Toronto, ON M4E 3C2, Canada",
				"statusCode": 200,
				"statusDescription": "OK",
				"traceId": "63b40b991d6643f4883f15c8b160eb44|BN20130632|7.7.0.0|",
				"addressLine": "169 Balsam Ave",
				"adminDistrict": "ON",
				"adminDistrict2": "Toronto",
				"countryRegion": "Canada",
				"formattedAddress": "169 Balsam Ave, Toronto, ON M4E 3C2, Canada",
				"locality": "Toronto",
				"neighborhood": "The Beaches",
				"postalCode": "M4E 3C2"
			},
			"geometry": {
				"type": "Point",
				"coordinates": [
					-79.2902,
					43.67757
				]
			},
			"bbox": [
				-79.2917543,
				43.6764458,
				-79.2886457,
				43.6786942
			]
		}
	]
}
