{
	"type": "FeatureCollection",
	"features": [
		{
			"type": "Feature",
			"properties": {
				"confidence": 9,
				"authenticationResultCode": "ValidCredentials",
				"brandLogoUri": "http://dev.virtualearth.net/Branding/logo_powered_by.png",
				"copyright": "Copyright © 2017 Microsoft and its suppliers. All rights reserved. This API cannot be accessed and the content and any results may not be used, reproduced or transmitted in any manner without express written permission from Microsoft Corporation.",
				"entityType": "Address",
				"matchCodes": [
					"Good"
				],
				"name": "17 Bolan Ct, Hamilton, ON L8V 1S6, Canada",
				"statusCode": 200,
				"statusDescription": "OK",
				"traceId": "70f9a5e20c934c58b757eb8613de9aff|BN20280152|7.7.0.0|",
				"addressLine": "17 Bolan Ct",
				"adminDistrict": "ON",
				"adminDistrict2": "Hamilton",
				"countryRegion": "Canada",
				"formattedAddress": "17 Bolan Ct, Hamilton, ON L8V 1S6, Canada",
				"locality": "Hamilton",
				"neighborhood": "Raleigh",
				"postalCode": "L8V 1S6"
			},
			"geometry": {
				"type": "Point",
				"coordinates": [
					-79.83976,
					43.2295299
				]
			},
			"bbox": [
				-79.8413029,
				43.2284057,
				-79.8382171,
				43.2306541
			]
		}
	]
}
