{
	"type": "FeatureCollection",
	"features": [
		{
			"type": "Feature",
			"properties": {
				"confidence": 9,
				"authenticationResultCode": "ValidCredentials",
				"brandLogoUri": "http://dev.virtualearth.net/Branding/logo_powered_by.png",
				"copyright": "Copyright © 2017 Microsoft and its suppliers. All rights reserved. This API cannot be accessed and the content and any results may not be used, reproduced or transmitted in any manner without express written permission from Microsoft Corporation.",
				"entityType": "Address",
				"matchCodes": [
					"Good"
				],
				"name": "170 HWY-83, Benito, MB R0L, Canada",
				"statusCode": 200,
				"statusDescription": "OK",
				"traceId": "2a6a690f2a8041bcac8bb4255492099b|BN20171457|7.7.0.0|",
				"addressLine": "170 HWY-83",
				"adminDistrict": "MB",
				"adminDistrict2": "Manitoba",
				"countryRegion": "Canada",
				"formattedAddress": "170 HWY-83, Benito, MB R0L, Canada",
				"locality": "Benito",
				"postalCode": "R0L 0C0"
			},
			"geometry": {
				"type": "Point",
				"coordinates": [
					-101.5534351,
					51.9168344
				]
			},
			"bbox": [
				-101.5552576,
				51.9157102,
				-101.5516126,
				51.9179585
			]
		}
	]
}
