{
	"type": "FeatureCollection",
	"features": [
		{
			"type": "Feature",
			"properties": {
				"confidence": 9,
				"authenticationResultCode": "ValidCredentials",
				"brandLogoUri": "http://dev.virtualearth.net/Branding/logo_powered_by.png",
				"copyright": "Copyright © 2017 Microsoft and its suppliers. All rights reserved. This API cannot be accessed and the content and any results may not be used, reproduced or transmitted in any manner without express written permission from Microsoft Corporation.",
				"entityType": "Address",
				"matchCodes": [
					"Good"
				],
				"name": "1700 Midland Ave, Scarborough, ON M1P 3C2, Canada",
				"statusCode": 200,
				"statusDescription": "OK",
				"traceId": "453b5cf643ef4a14b973529fb004c2bf|BN20130423|7.7.0.0|",
				"addressLine": "1700 Midland Ave",
				"adminDistrict": "ON",
				"adminDistrict2": "Toronto",
				"countryRegion": "Canada",
				"formattedAddress": "1700 Midland Ave, Scarborough, ON M1P 3C2, Canada",
				"locality": "Toronto",
				"neighborhood": "Dorset Park",
				"postalCode": "M1P 3C2"
			},
			"geometry": {
				"type": "Point",
				"coordinates": [
					-79.26869,
					43.75977
				]
			},
			"bbox": [
				-79.2702465,
				43.7586458,
				-79.2671335,
				43.7608942
			]
		}
	]
}
