{
	"type": "FeatureCollection",
	"features": [
		{
			"type": "Feature",
			"properties": {
				"confidence": 9,
				"authenticationResultCode": "ValidCredentials",
				"brandLogoUri": "http://dev.virtualearth.net/Branding/logo_powered_by.png",
				"copyright": "Copyright © 2017 Microsoft and its suppliers. All rights reserved. This API cannot be accessed and the content and any results may not be used, reproduced or transmitted in any manner without express written permission from Microsoft Corporation.",
				"entityType": "Address",
				"matchCodes": [
					"Good"
				],
				"name": "1701 Regan Ave, Coquitlam, BC V3J 3C1, Canada",
				"statusCode": 200,
				"statusDescription": "OK",
				"traceId": "f09ba16282fd43209dc0f3c5e67a3060|BN20121762|7.7.0.0|",
				"addressLine": "1701 Regan Ave",
				"adminDistrict": "BC",
				"adminDistrict2": "Greater Vancouver",
				"countryRegion": "Canada",
				"formattedAddress": "1701 Regan Ave, Coquitlam, BC V3J 3C1, Canada",
				"locality": "Coquitlam",
				"neighborhood": "Central Coquitlam",
				"postalCode": "V3J 3C1"
			},
			"geometry": {
				"type": "Point",
				"coordinates": [
					-122.84614,
					49.26191
				]
			},
			"bbox": [
				-122.8478626,
				49.2607858,
				-122.8444174,
				49.2630342
			]
		}
	]
}
