{
	"type": "FeatureCollection",
	"features": [
		{
			"type": "Feature",
			"properties": {
				"confidence": 9,
				"authenticationResultCode": "ValidCredentials",
				"brandLogoUri": "http://dev.virtualearth.net/Branding/logo_powered_by.png",
				"copyright": "Copyright © 2017 Microsoft and its suppliers. All rights reserved. This API cannot be accessed and the content and any results may not be used, reproduced or transmitted in any manner without express written permission from Microsoft Corporation.",
				"entityType": "Address",
				"matchCodes": [
					"Good"
				],
				"name": "1717 Salton Rd, Abbotsford, BC V2S 7P2, Canada",
				"statusCode": 200,
				"statusDescription": "OK",
				"traceId": "763c6625229a431b99ce8f33e52ae819|BN20130621|7.7.0.0|",
				"addressLine": "1717 Salton Rd",
				"adminDistrict": "BC",
				"adminDistrict2": "Fraser Valley",
				"countryRegion": "Canada",
				"formattedAddress": "1717 Salton Rd, Abbotsford, BC V2S 7P2, Canada",
				"locality": "Abbotsford",
				"neighborhood": "Highway 11",
				"postalCode": "V2S 7P2"
			},
			"geometry": {
				"type": "Point",
				"coordinates": [
					-122.2878,
					49.032912
				]
			},
			"bbox": [
				-122.2895146,
				49.0317879,
				-122.2860854,
				49.0340362
			]
		}
	]
}
