{
	"type": "FeatureCollection",
	"features": [
		{
			"type": "Feature",
			"properties": {
				"confidence": 9,
				"authenticationResultCode": "ValidCredentials",
				"brandLogoUri": "http://dev.virtualearth.net/Branding/logo_powered_by.png",
				"copyright": "Copyright © 2017 Microsoft and its suppliers. All rights reserved. This API cannot be accessed and the content and any results may not be used, reproduced or transmitted in any manner without express written permission from Microsoft Corporation.",
				"entityType": "Address",
				"matchCodes": [
					"Good"
				],
				"name": "172 Foster St, Berwick, NS B0P, Canada",
				"statusCode": 200,
				"statusDescription": "OK",
				"traceId": "659322e1e8294756850c108d376728de|BN20130422|7.7.0.0|",
				"addressLine": "172 Foster St",
				"adminDistrict": "NS",
				"adminDistrict2": "Kings",
				"countryRegion": "Canada",
				"formattedAddress": "172 Foster St, Berwick, NS B0P, Canada",
				"locality": "Berwick",
				"postalCode": "B0P 1E0"
			},
			"geometry": {
				"type": "Point",
				"coordinates": [
					-64.7408899,
					45.04757
				]
			},
			"bbox": [
				-64.742481,
				45.0464458,
				-64.7392988,
				45.0486942
			]
		}
	]
}
