{
	"type": "FeatureCollection",
	"features": [
		{
			"type": "Feature",
			"properties": {
				"confidence": 9,
				"authenticationResultCode": "ValidCredentials",
				"brandLogoUri": "http://dev.virtualearth.net/Branding/logo_powered_by.png",
				"copyright": "Copyright © 2017 Microsoft and its suppliers. All rights reserved. This API cannot be accessed and the content and any results may not be used, reproduced or transmitted in any manner without express written permission from Microsoft Corporation.",
				"entityType": "Address",
				"matchCodes": [
					"Good"
				],
				"name": "17339 Cornwall Centre Rd, Cornwall, ON K6K 1K6, Canada",
				"statusCode": 200,
				"statusDescription": "OK",
				"traceId": "65344f2f75004c1d83e1f67a9261123e|BN20260223|7.7.0.0|",
				"addressLine": "17339 Cornwall Centre Rd",
				"adminDistrict": "ON",
				"adminDistrict2": "Stormont, Dundas and Glengarry",
				"countryRegion": "Canada",
				"formattedAddress": "17339 Cornwall Centre Rd, Cornwall, ON K6K 1K6, Canada",
				"locality": "Cornwall",
				"postalCode": "K6K 1K6"
			},
			"geometry": {
				"type": "Point",
				"coordinates": [
					-74.76648,
					45.0621
				]
			},
			"bbox": [
				-74.7680715,
				45.0609758,
				-74.7648885,
				45.0632242
			]
		}
	]
}
