{
	"type": "FeatureCollection",
	"features": [
		{
			"type": "Feature",
			"properties": {
				"confidence": 9,
				"authenticationResultCode": "ValidCredentials",
				"brandLogoUri": "http://dev.virtualearth.net/Branding/logo_powered_by.png",
				"copyright": "Copyright © 2017 Microsoft and its suppliers. All rights reserved. This API cannot be accessed and the content and any results may not be used, reproduced or transmitted in any manner without express written permission from Microsoft Corporation.",
				"entityType": "Address",
				"matchCodes": [
					"Good"
				],
				"name": "1746 Mattawa Ave, Mississauga, ON L4X 1K1, Canada",
				"statusCode": 200,
				"statusDescription": "OK",
				"traceId": "7615cb4677e247c2bd7f79e64feaa948|BN20130533|7.7.0.0|",
				"addressLine": "1746 Mattawa Ave",
				"adminDistrict": "ON",
				"adminDistrict2": "Peel",
				"countryRegion": "Canada",
				"formattedAddress": "1746 Mattawa Ave, Mississauga, ON L4X 1K1, Canada",
				"locality": "Mississauga",
				"postalCode": "L4X 1K1"
			},
			"geometry": {
				"type": "Point",
				"coordinates": [
					-79.57133,
					43.61377
				]
			},
			"bbox": [
				-79.5728827,
				43.6126458,
				-79.5697773,
				43.6148942
			]
		}
	]
}
