{
	"type": "FeatureCollection",
	"features": [
		{
			"type": "Feature",
			"properties": {
				"confidence": 9,
				"authenticationResultCode": "ValidCredentials",
				"brandLogoUri": "http://dev.virtualearth.net/Branding/logo_powered_by.png",
				"copyright": "Copyright © 2017 Microsoft and its suppliers. All rights reserved. This API cannot be accessed and the content and any results may not be used, reproduced or transmitted in any manner without express written permission from Microsoft Corporation.",
				"entityType": "Address",
				"matchCodes": [
					"Good"
				],
				"name": "175 Avenue Guthrie, Dorval, QC H9P 2P5, Canada",
				"statusCode": 200,
				"statusDescription": "OK",
				"traceId": "1df4006590a242a5824888ee887a0c2a|BN20200137|7.7.0.0|",
				"addressLine": "175 Avenue Guthrie",
				"adminDistrict": "QC",
				"adminDistrict2": "Montreal",
				"countryRegion": "Canada",
				"formattedAddress": "175 Avenue Guthrie, Dorval, QC H9P 2P5, Canada",
				"locality": "Dorval",
				"postalCode": "H9P 2P5"
			},
			"geometry": {
				"type": "Point",
				"coordinates": [
					-73.7270589,
					45.4520238
				]
			},
			"bbox": [
				-73.7286613,
				45.4508997,
				-73.7254564,
				45.453148
			]
		}
	]
}
