{
	"type": "FeatureCollection",
	"features": [
		{
			"type": "Feature",
			"properties": {
				"confidence": 9,
				"authenticationResultCode": "ValidCredentials",
				"brandLogoUri": "http://dev.virtualearth.net/Branding/logo_powered_by.png",
				"copyright": "Copyright © 2017 Microsoft and its suppliers. All rights reserved. This API cannot be accessed and the content and any results may not be used, reproduced or transmitted in any manner without express written permission from Microsoft Corporation.",
				"entityType": "Address",
				"matchCodes": [
					"Good"
				],
				"name": "175 Advance Blvd, Brampton, ON L6T 4J1, Canada",
				"statusCode": 200,
				"statusDescription": "OK",
				"traceId": "be6619ad91234b3693d083aab4cea6fa|BN20130431|7.7.0.0|",
				"addressLine": "175 Advance Blvd",
				"adminDistrict": "ON",
				"adminDistrict2": "Peel",
				"countryRegion": "Canada",
				"formattedAddress": "175 Advance Blvd, Brampton, ON L6T 4J1, Canada",
				"locality": "Brampton",
				"neighborhood": "Bramalea",
				"postalCode": "L6T 4J1"
			},
			"geometry": {
				"type": "Point",
				"coordinates": [
					-79.693,
					43.6926599
				]
			},
			"bbox": [
				-79.6945547,
				43.6915357,
				-79.6914453,
				43.6937841
			]
		}
	]
}
