{
	"type": "FeatureCollection",
	"features": [
		{
			"type": "Feature",
			"properties": {
				"confidence": 9,
				"authenticationResultCode": "ValidCredentials",
				"brandLogoUri": "http://dev.virtualearth.net/Branding/logo_powered_by.png",
				"copyright": "Copyright © 2017 Microsoft and its suppliers. All rights reserved. This API cannot be accessed and the content and any results may not be used, reproduced or transmitted in any manner without express written permission from Microsoft Corporation.",
				"entityType": "Address",
				"matchCodes": [
					"Good"
				],
				"name": "175 Lakeshore Rd E, Mississauga, ON L5G 4T9, Canada",
				"statusCode": 200,
				"statusDescription": "OK",
				"traceId": "573317d9bfc6469bb2b0fb2cf947d823|BN20130431|7.7.0.0|",
				"addressLine": "175 Lakeshore Rd E",
				"adminDistrict": "ON",
				"adminDistrict2": "Peel",
				"countryRegion": "Canada",
				"formattedAddress": "175 Lakeshore Rd E, Mississauga, ON L5G 4T9, Canada",
				"locality": "Mississauga",
				"neighborhood": "Port Credit",
				"postalCode": "L5G 4T9"
			},
			"geometry": {
				"type": "Point",
				"coordinates": [
					-79.58034,
					43.55645
				]
			},
			"bbox": [
				-79.5818912,
				43.5553258,
				-79.5787888,
				43.5575742
			]
		}
	]
}
