{
	"type": "FeatureCollection",
	"features": [
		{
			"type": "Feature",
			"properties": {
				"confidence": 9,
				"authenticationResultCode": "ValidCredentials",
				"brandLogoUri": "http://dev.virtualearth.net/Branding/logo_powered_by.png",
				"copyright": "Copyright © 2017 Microsoft and its suppliers. All rights reserved. This API cannot be accessed and the content and any results may not be used, reproduced or transmitted in any manner without express written permission from Microsoft Corporation.",
				"entityType": "Address",
				"matchCodes": [
					"Good"
				],
				"name": "1750 W Reed Rd, Roberts Creek, BC V0N 2W5, Canada",
				"statusCode": 200,
				"statusDescription": "OK",
				"traceId": "0da3d666af1b48c19fff29a80418a6c0|BN20130620|7.7.0.0|",
				"addressLine": "1750 W Reed Rd",
				"adminDistrict": "BC",
				"adminDistrict2": "Sunshine Coast",
				"countryRegion": "Canada",
				"formattedAddress": "1750 W Reed Rd, Roberts Creek, BC V0N 2W5, Canada",
				"locality": "Sunshine Coast",
				"neighborhood": "Roberts Creek",
				"postalCode": "V0N 2W5"
			},
			"geometry": {
				"type": "Point",
				"coordinates": [
					-123.5685008,
					49.4090581
				]
			},
			"bbox": [
				-123.5702285,
				49.4079339,
				-123.566773,
				49.4101822
			]
		}
	]
}
