{
	"type": "FeatureCollection",
	"features": [
		{
			"type": "Feature",
			"properties": {
				"confidence": 9,
				"authenticationResultCode": "ValidCredentials",
				"brandLogoUri": "http://dev.virtualearth.net/Branding/logo_powered_by.png",
				"copyright": "Copyright © 2017 Microsoft and its suppliers. All rights reserved. This API cannot be accessed and the content and any results may not be used, reproduced or transmitted in any manner without express written permission from Microsoft Corporation.",
				"entityType": "Address",
				"matchCodes": [
					"Good"
				],
				"name": "176 N Lake Harbour Rd, Kings, PE C0A, Canada",
				"statusCode": 200,
				"statusDescription": "OK",
				"traceId": "0bc1acd6fcec4cbbacaea2daf706e621|BN20190642|7.7.0.0|",
				"addressLine": "176 N Lake Harbour Rd",
				"adminDistrict": "PE",
				"adminDistrict2": "Kings",
				"countryRegion": "Canada",
				"formattedAddress": "176 N Lake Harbour Rd, Kings, PE C0A, Canada",
				"locality": "Kings",
				"neighborhood": "Souris",
				"postalCode": "C0A 1K0"
			},
			"geometry": {
				"type": "Point",
				"coordinates": [
					-62.0709072,
					46.466565
				]
			},
			"bbox": [
				-62.0725393,
				46.4654409,
				-62.0692751,
				46.4676892
			]
		}
	]
}
