{
	"type": "FeatureCollection",
	"features": [
		{
			"type": "Feature",
			"properties": {
				"confidence": 9,
				"authenticationResultCode": "ValidCredentials",
				"brandLogoUri": "http://dev.virtualearth.net/Branding/logo_powered_by.png",
				"copyright": "Copyright © 2017 Microsoft and its suppliers. All rights reserved. This API cannot be accessed and the content and any results may not be used, reproduced or transmitted in any manner without express written permission from Microsoft Corporation.",
				"entityType": "Address",
				"matchCodes": [
					"Good"
				],
				"name": "17610 Stony Plain Rd NW, Edmonton, AB T5S 1A2, Canada",
				"statusCode": 200,
				"statusDescription": "OK",
				"traceId": "933ec4553c204b1a8b1b9711f2a4bd3c|BN20130719|7.7.0.0|",
				"addressLine": "17610 Stony Plain Rd NW",
				"adminDistrict": "AB",
				"adminDistrict2": "Alberta",
				"countryRegion": "Canada",
				"formattedAddress": "17610 Stony Plain Rd NW, Edmonton, AB T5S 1A2, Canada",
				"locality": "Edmonton",
				"neighborhood": "Stone Industrial",
				"postalCode": "T5S 1A2"
			},
			"geometry": {
				"type": "Point",
				"coordinates": [
					-113.6236618,
					53.5417362
				]
			},
			"bbox": [
				-113.6255535,
				53.5406121,
				-113.62177,
				53.5428604
			]
		}
	]
}
