{
	"type": "FeatureCollection",
	"features": [
		{
			"type": "Feature",
			"properties": {
				"confidence": 9,
				"authenticationResultCode": "ValidCredentials",
				"brandLogoUri": "http://dev.virtualearth.net/Branding/logo_powered_by.png",
				"copyright": "Copyright © 2017 Microsoft and its suppliers. All rights reserved. This API cannot be accessed and the content and any results may not be used, reproduced or transmitted in any manner without express written permission from Microsoft Corporation.",
				"entityType": "Address",
				"matchCodes": [
					"Good"
				],
				"name": "17630 Fraser Dyke Rd, Pitt Meadows, BC V3Y 0A7, Canada",
				"statusCode": 200,
				"statusDescription": "OK",
				"traceId": "5a2525538aa0419184ff8f7773a8a945|BN20121764|7.7.0.0|",
				"addressLine": "17630 Fraser Dyke Rd",
				"adminDistrict": "BC",
				"adminDistrict2": "Greater Vancouver",
				"countryRegion": "Canada",
				"formattedAddress": "17630 Fraser Dyke Rd, Pitt Meadows, BC V3Y 0A7, Canada",
				"locality": "Pitt Meadows",
				"postalCode": "V3Y 0A7"
			},
			"geometry": {
				"type": "Point",
				"coordinates": [
					-122.73304,
					49.21501
				]
			},
			"bbox": [
				-122.7347609,
				49.2138858,
				-122.7313191,
				49.2161342
			]
		}
	]
}
