{
	"type": "FeatureCollection",
	"features": [
		{
			"type": "Feature",
			"properties": {
				"confidence": 9,
				"authenticationResultCode": "ValidCredentials",
				"brandLogoUri": "http://dev.virtualearth.net/Branding/logo_powered_by.png",
				"copyright": "Copyright © 2017 Microsoft and its suppliers. All rights reserved. This API cannot be accessed and the content and any results may not be used, reproduced or transmitted in any manner without express written permission from Microsoft Corporation.",
				"entityType": "Address",
				"matchCodes": [
					"Good"
				],
				"name": "17712 101A Ave, Surrey, BC V4N 5V8, Canada",
				"statusCode": 200,
				"statusDescription": "OK",
				"traceId": "736c60e1e69e4987a8775f1bc8bcc75b|BN20121764|7.7.0.0|",
				"addressLine": "17712 101A Ave",
				"adminDistrict": "BC",
				"adminDistrict2": "Greater Vancouver",
				"countryRegion": "Canada",
				"formattedAddress": "17712 101A Ave, Surrey, BC V4N 5V8, Canada",
				"locality": "Surrey",
				"neighborhood": "Guildford",
				"postalCode": "V4N 5V8"
			},
			"geometry": {
				"type": "Point",
				"coordinates": [
					-122.7318356,
					49.1868832
				]
			},
			"bbox": [
				-122.7335555,
				49.1857591,
				-122.7301156,
				49.1880074
			]
		}
	]
}
