{
	"type": "FeatureCollection",
	"features": [
		{
			"type": "Feature",
			"properties": {
				"confidence": 9,
				"authenticationResultCode": "ValidCredentials",
				"brandLogoUri": "http://dev.virtualearth.net/Branding/logo_powered_by.png",
				"copyright": "Copyright © 2017 Microsoft and its suppliers. All rights reserved. This API cannot be accessed and the content and any results may not be used, reproduced or transmitted in any manner without express written permission from Microsoft Corporation.",
				"entityType": "Address",
				"matchCodes": [
					"Good"
				],
				"name": "17775 Rue des Gouverneurs, Mirabel, QC J7J 0T9, Canada",
				"statusCode": 200,
				"statusDescription": "OK",
				"traceId": "59856a3ed5bb48b29b0bc40b9a0d35cd|BN20220145|7.7.0.0|",
				"addressLine": "17775 Rue des Gouverneurs",
				"adminDistrict": "QC",
				"adminDistrict2": "Mirabel",
				"countryRegion": "Canada",
				"formattedAddress": "17775 Rue des Gouverneurs, Mirabel, QC J7J 0T9, Canada",
				"locality": "Mirabel",
				"postalCode": "J7J 0T9"
			},
			"geometry": {
				"type": "Point",
				"coordinates": [
					-73.9293841,
					45.6781786
				]
			},
			"bbox": [
				-73.930993,
				45.6770545,
				-73.9277751,
				45.6793028
			]
		}
	]
}
