{
	"type": "FeatureCollection",
	"features": [
		{
			"type": "Feature",
			"properties": {
				"confidence": 9,
				"authenticationResultCode": "ValidCredentials",
				"brandLogoUri": "http://dev.virtualearth.net/Branding/logo_powered_by.png",
				"copyright": "Copyright © 2017 Microsoft and its suppliers. All rights reserved. This API cannot be accessed and the content and any results may not be used, reproduced or transmitted in any manner without express written permission from Microsoft Corporation.",
				"entityType": "Address",
				"matchCodes": [
					"Good"
				],
				"name": "17800 Rue Lapointe, Mirabel, QC J7J 0W8, Canada",
				"statusCode": 200,
				"statusDescription": "OK",
				"traceId": "17b51b481c5c432383d6111a56cb48e4|BN20200137|7.7.0.0|",
				"addressLine": "17800 Rue Lapointe",
				"adminDistrict": "QC",
				"adminDistrict2": "Mirabel",
				"countryRegion": "Canada",
				"formattedAddress": "17800 Rue Lapointe, Mirabel, QC J7J 0W8, Canada",
				"locality": "Mirabel",
				"postalCode": "J7J 0W8"
			},
			"geometry": {
				"type": "Point",
				"coordinates": [
					-73.9298249,
					45.6912715
				]
			},
			"bbox": [
				-73.9314342,
				45.6901473,
				-73.9282156,
				45.6923956
			]
		}
	]
}
