{
	"type": "FeatureCollection",
	"features": [
		{
			"type": "Feature",
			"properties": {
				"confidence": 9,
				"authenticationResultCode": "ValidCredentials",
				"brandLogoUri": "http://dev.virtualearth.net/Branding/logo_powered_by.png",
				"copyright": "Copyright © 2017 Microsoft and its suppliers. All rights reserved. This API cannot be accessed and the content and any results may not be used, reproduced or transmitted in any manner without express written permission from Microsoft Corporation.",
				"entityType": "Address",
				"matchCodes": [
					"Good"
				],
				"name": "1797 Logan Ave, Winnipeg, MB R3E 1S9, Canada",
				"statusCode": 200,
				"statusDescription": "OK",
				"traceId": "369639de10e147039b432727b3eb162e|BN20200137|7.7.0.0|",
				"addressLine": "1797 Logan Ave",
				"adminDistrict": "MB",
				"adminDistrict2": "Manitoba",
				"countryRegion": "Canada",
				"formattedAddress": "1797 Logan Ave, Winnipeg, MB R3E 1S9, Canada",
				"locality": "Winnipeg",
				"neighborhood": "Weston",
				"postalCode": "R3E 1S9"
			},
			"geometry": {
				"type": "Point",
				"coordinates": [
					-97.19472,
					49.92172
				]
			},
			"bbox": [
				-97.196466,
				49.9205958,
				-97.192974,
				49.9228442
			]
		}
	]
}
