{
	"type": "FeatureCollection",
	"features": [
		{
			"type": "Feature",
			"properties": {
				"confidence": 9,
				"authenticationResultCode": "ValidCredentials",
				"brandLogoUri": "http://dev.virtualearth.net/Branding/logo_powered_by.png",
				"copyright": "Copyright © 2017 Microsoft and its suppliers. All rights reserved. This API cannot be accessed and the content and any results may not be used, reproduced or transmitted in any manner without express written permission from Microsoft Corporation.",
				"entityType": "Address",
				"matchCodes": [
					"Good"
				],
				"name": "18 Praznik Pl, St Andrews, MB R1A 2Y8, Canada",
				"statusCode": 200,
				"statusDescription": "OK",
				"traceId": "09680d2223f7401d917d708bb82f1c69|BN20171457|7.7.0.0|",
				"addressLine": "18 Praznik Pl",
				"adminDistrict": "MB",
				"adminDistrict2": "Manitoba",
				"countryRegion": "Canada",
				"formattedAddress": "18 Praznik Pl, St Andrews, MB R1A 2Y8, Canada",
				"locality": "St Andrews",
				"neighborhood": "Lockport",
				"postalCode": "R1A 2Y8"
			},
			"geometry": {
				"type": "Point",
				"coordinates": [
					-96.9685905,
					50.0717755
				]
			},
			"bbox": [
				-96.970342,
				50.0706514,
				-96.966839,
				50.0728997
			]
		}
	]
}
