{
	"type": "FeatureCollection",
	"features": [
		{
			"type": "Feature",
			"properties": {
				"confidence": 9,
				"authenticationResultCode": "ValidCredentials",
				"brandLogoUri": "http://dev.virtualearth.net/Branding/logo_powered_by.png",
				"copyright": "Copyright © 2017 Microsoft and its suppliers. All rights reserved. This API cannot be accessed and the content and any results may not be used, reproduced or transmitted in any manner without express written permission from Microsoft Corporation.",
				"entityType": "Address",
				"matchCodes": [
					"Good"
				],
				"name": "18 Underwood Rd, Ingersoll, ON N5C, Canada",
				"statusCode": 200,
				"statusDescription": "OK",
				"traceId": "a64ad94e49874236b74c2a6e8c101724|BN20300154|7.7.0.0|",
				"addressLine": "18 Underwood Rd",
				"adminDistrict": "ON",
				"adminDistrict2": "Oxford",
				"countryRegion": "Canada",
				"formattedAddress": "18 Underwood Rd, Ingersoll, ON N5C, Canada",
				"locality": "Ingersoll",
				"postalCode": "N5C 3V6"
			},
			"geometry": {
				"type": "Point",
				"coordinates": [
					-80.87988,
					43.019
				]
			},
			"bbox": [
				-80.8814176,
				43.0178758,
				-80.8783424,
				43.0201242
			]
		}
	]
}
