{
	"type": "FeatureCollection",
	"features": [
		{
			"type": "Feature",
			"properties": {
				"confidence": 9,
				"authenticationResultCode": "ValidCredentials",
				"brandLogoUri": "http://dev.virtualearth.net/Branding/logo_powered_by.png",
				"copyright": "Copyright © 2017 Microsoft and its suppliers. All rights reserved. This API cannot be accessed and the content and any results may not be used, reproduced or transmitted in any manner without express written permission from Microsoft Corporation.",
				"entityType": "Address",
				"matchCodes": [
					"Good"
				],
				"name": "180 Bartor Rd, North York, ON M9M 2W6, Canada",
				"statusCode": 200,
				"statusDescription": "OK",
				"traceId": "129a8a7fcea74a74969ecabe96e78d4a|BN20200239|7.7.0.0|",
				"addressLine": "180 Bartor Rd",
				"adminDistrict": "ON",
				"adminDistrict2": "Toronto",
				"countryRegion": "Canada",
				"formattedAddress": "180 Bartor Rd, North York, ON M9M 2W6, Canada",
				"locality": "Toronto",
				"neighborhood": "Downsview-Roding-CFB",
				"postalCode": "M9M 2W6"
			},
			"geometry": {
				"type": "Point",
				"coordinates": [
					-79.52576,
					43.72624
				]
			},
			"bbox": [
				-79.5273156,
				43.7251158,
				-79.5242044,
				43.7273642
			]
		}
	]
}
