{
	"type": "FeatureCollection",
	"features": [
		{
			"type": "Feature",
			"properties": {
				"confidence": 9,
				"authenticationResultCode": "ValidCredentials",
				"brandLogoUri": "http://dev.virtualearth.net/Branding/logo_powered_by.png",
				"copyright": "Copyright © 2017 Microsoft and its suppliers. All rights reserved. This API cannot be accessed and the content and any results may not be used, reproduced or transmitted in any manner without express written permission from Microsoft Corporation.",
				"entityType": "Address",
				"matchCodes": [
					"Good"
				],
				"name": "1800 Argyle St, Halifax, NS B3J 3N8, Canada",
				"statusCode": 200,
				"statusDescription": "OK",
				"traceId": "c0991a345d9c435f808de77083b34597|BN20130522|7.7.0.0|",
				"addressLine": "1800 Argyle St",
				"adminDistrict": "NS",
				"adminDistrict2": "Halifax",
				"countryRegion": "Canada",
				"formattedAddress": "1800 Argyle St, Halifax, NS B3J 3N8, Canada",
				"locality": "Halifax",
				"neighborhood": "Downtown Halifax",
				"postalCode": "B3J 3N8"
			},
			"geometry": {
				"type": "Point",
				"coordinates": [
					-63.57594,
					44.64846
				]
			},
			"bbox": [
				-63.5775201,
				44.6473358,
				-63.5743599,
				44.6495842
			]
		}
	]
}
