{
	"type": "FeatureCollection",
	"features": [
		{
			"type": "Feature",
			"properties": {
				"confidence": 9,
				"authenticationResultCode": "ValidCredentials",
				"brandLogoUri": "http://dev.virtualearth.net/Branding/logo_powered_by.png",
				"copyright": "Copyright © 2017 Microsoft and its suppliers. All rights reserved. This API cannot be accessed and the content and any results may not be used, reproduced or transmitted in any manner without express written permission from Microsoft Corporation.",
				"entityType": "Address",
				"matchCodes": [
					"Good"
				],
				"name": "181 King Rd, Richmond Hill, ON L4E 2W1, Canada",
				"statusCode": 200,
				"statusDescription": "OK",
				"traceId": "d2d724c79892408d86b6a3180f09e454|BN20130521|7.7.0.0|",
				"addressLine": "181 King Rd",
				"adminDistrict": "ON",
				"adminDistrict2": "York",
				"countryRegion": "Canada",
				"formattedAddress": "181 King Rd, Richmond Hill, ON L4E 2W1, Canada",
				"locality": "Richmond Hill",
				"neighborhood": "Oak Ridges",
				"postalCode": "L4E 2W1"
			},
			"geometry": {
				"type": "Point",
				"coordinates": [
					-79.46091,
					43.94255
				]
			},
			"bbox": [
				-79.4624712,
				43.9414258,
				-79.4593488,
				43.9436742
			]
		}
	]
}
