{
	"type": "FeatureCollection",
	"features": [
		{
			"type": "Feature",
			"properties": {
				"confidence": 9,
				"authenticationResultCode": "ValidCredentials",
				"brandLogoUri": "http://dev.virtualearth.net/Branding/logo_powered_by.png",
				"copyright": "Copyright © 2017 Microsoft and its suppliers. All rights reserved. This API cannot be accessed and the content and any results may not be used, reproduced or transmitted in any manner without express written permission from Microsoft Corporation.",
				"entityType": "Address",
				"matchCodes": [
					"Good"
				],
				"name": "1810 20 St, Didsbury, AB T0M, Canada",
				"statusCode": 200,
				"statusDescription": "OK",
				"traceId": "d192a28c5ba648b79fae01183a81d45d|BN20130625|7.7.0.0|",
				"addressLine": "1810 20 St",
				"adminDistrict": "AB",
				"adminDistrict2": "Alberta",
				"countryRegion": "Canada",
				"formattedAddress": "1810 20 St, Didsbury, AB T0M, Canada",
				"locality": "Didsbury",
				"postalCode": "T0M 0W0"
			},
			"geometry": {
				"type": "Point",
				"coordinates": [
					-114.13792,
					51.6595
				]
			},
			"bbox": [
				-114.1397322,
				51.6583758,
				-114.1361078,
				51.6606242
			]
		}
	]
}
