{
	"type": "FeatureCollection",
	"features": [
		{
			"type": "Feature",
			"properties": {
				"confidence": 9,
				"authenticationResultCode": "ValidCredentials",
				"brandLogoUri": "http://dev.virtualearth.net/Branding/logo_powered_by.png",
				"copyright": "Copyright © 2017 Microsoft and its suppliers. All rights reserved. This API cannot be accessed and the content and any results may not be used, reproduced or transmitted in any manner without express written permission from Microsoft Corporation.",
				"entityType": "Address",
				"matchCodes": [
					"Good"
				],
				"name": "1810 Birchmount Rd, Scarborough, ON M1P 2H7, Canada",
				"statusCode": 200,
				"statusDescription": "OK",
				"traceId": "db6bd031de4e40448a35f5c905f35f22|BN20190642|7.7.0.0|",
				"addressLine": "1810 Birchmount Rd",
				"adminDistrict": "ON",
				"adminDistrict2": "Toronto",
				"countryRegion": "Canada",
				"formattedAddress": "1810 Birchmount Rd, Scarborough, ON M1P 2H7, Canada",
				"locality": "Toronto",
				"neighborhood": "Wexford-Maryvale",
				"postalCode": "M1P 2H7"
			},
			"geometry": {
				"type": "Point",
				"coordinates": [
					-79.29238,
					43.76614
				]
			},
			"bbox": [
				-79.2939366,
				43.7650158,
				-79.2908234,
				43.7672642
			]
		}
	]
}
