{
	"type": "FeatureCollection",
	"features": [
		{
			"type": "Feature",
			"properties": {
				"confidence": 9,
				"authenticationResultCode": "ValidCredentials",
				"brandLogoUri": "http://dev.virtualearth.net/Branding/logo_powered_by.png",
				"copyright": "Copyright © 2017 Microsoft and its suppliers. All rights reserved. This API cannot be accessed and the content and any results may not be used, reproduced or transmitted in any manner without express written permission from Microsoft Corporation.",
				"entityType": "Address",
				"matchCodes": [
					"Good"
				],
				"name": "1811 100th St, North Battleford, SK S9A 0X1, Canada",
				"statusCode": 200,
				"statusDescription": "OK",
				"traceId": "e4c2dc62d0fa43fd9dae467a49f7441d|BN20250135|7.7.0.0|",
				"addressLine": "1811 100th St",
				"adminDistrict": "SK",
				"adminDistrict2": "Saskatchewan",
				"countryRegion": "Canada",
				"formattedAddress": "1811 100th St, North Battleford, SK S9A 0X1, Canada",
				"locality": "North Battleford",
				"postalCode": "S9A 0X1"
			},
			"geometry": {
				"type": "Point",
				"coordinates": [
					-108.29948,
					52.78418
				]
			},
			"bbox": [
				-108.3013387,
				52.7830558,
				-108.2976213,
				52.7853042
			]
		}
	]
}
