{
	"type": "FeatureCollection",
	"features": [
		{
			"type": "Feature",
			"properties": {
				"confidence": 9,
				"authenticationResultCode": "ValidCredentials",
				"brandLogoUri": "http://dev.virtualearth.net/Branding/logo_powered_by.png",
				"copyright": "Copyright © 2017 Microsoft and its suppliers. All rights reserved. This API cannot be accessed and the content and any results may not be used, reproduced or transmitted in any manner without express written permission from Microsoft Corporation.",
				"entityType": "Address",
				"matchCodes": [
					"Good"
				],
				"name": "1820 Rue Mitis, Chicoutimi, QC G7K 1H5, Canada",
				"statusCode": 200,
				"statusDescription": "OK",
				"traceId": "4bc2be1aa2b243d4b0730678910546b3|BN20200239|7.7.0.0|",
				"addressLine": "1820 Rue Mitis",
				"adminDistrict": "QC",
				"adminDistrict2": "Saguenay",
				"countryRegion": "Canada",
				"formattedAddress": "1820 Rue Mitis, Chicoutimi, QC G7K 1H5, Canada",
				"locality": "Saguenay",
				"neighborhood": "Chicoutimi",
				"postalCode": "G7K 1H5"
			},
			"geometry": {
				"type": "Point",
				"coordinates": [
					-71.12751,
					48.40383
				]
			},
			"bbox": [
				-71.1292033,
				48.4027058,
				-71.1258167,
				48.4049542
			]
		}
	]
}
