{
	"type": "FeatureCollection",
	"features": [
		{
			"type": "Feature",
			"properties": {
				"confidence": 9,
				"authenticationResultCode": "ValidCredentials",
				"brandLogoUri": "http://dev.virtualearth.net/Branding/logo_powered_by.png",
				"copyright": "Copyright © 2017 Microsoft and its suppliers. All rights reserved. This API cannot be accessed and the content and any results may not be used, reproduced or transmitted in any manner without express written permission from Microsoft Corporation.",
				"entityType": "Address",
				"matchCodes": [
					"Good"
				],
				"name": "183 Elizabeth St, Goderich, ON N7A 3T9, Canada",
				"statusCode": 200,
				"statusDescription": "OK",
				"traceId": "1838676ba6b041b49b4ae82535a84704|BN20121762|7.7.0.0|",
				"addressLine": "183 Elizabeth St",
				"adminDistrict": "ON",
				"adminDistrict2": "Huron",
				"countryRegion": "Canada",
				"formattedAddress": "183 Elizabeth St, Goderich, ON N7A 3T9, Canada",
				"locality": "Goderich",
				"postalCode": "N7A 3T9"
			},
			"geometry": {
				"type": "Point",
				"coordinates": [
					-81.71871,
					43.73678
				]
			},
			"bbox": [
				-81.7202659,
				43.7356558,
				-81.7171541,
				43.7379042
			]
		}
	]
}
