{
	"type": "FeatureCollection",
	"features": [
		{
			"type": "Feature",
			"properties": {
				"confidence": 9,
				"authenticationResultCode": "ValidCredentials",
				"brandLogoUri": "http://dev.virtualearth.net/Branding/logo_powered_by.png",
				"copyright": "Copyright © 2017 Microsoft and its suppliers. All rights reserved. This API cannot be accessed and the content and any results may not be used, reproduced or transmitted in any manner without express written permission from Microsoft Corporation.",
				"entityType": "Address",
				"matchCodes": [
					"Good"
				],
				"name": "183 Cocksfield Ave, North York, ON M3H 3T4, Canada",
				"statusCode": 200,
				"statusDescription": "OK",
				"traceId": "4f9f5130cf704dc4a5bc6107d3f8ea04|BN20220145|7.7.0.0|",
				"addressLine": "183 Cocksfield Ave",
				"adminDistrict": "ON",
				"adminDistrict2": "Toronto",
				"countryRegion": "Canada",
				"formattedAddress": "183 Cocksfield Ave, North York, ON M3H 3T4, Canada",
				"locality": "Toronto",
				"neighborhood": "Bathurst Manor",
				"postalCode": "M3H 3T4"
			},
			"geometry": {
				"type": "Point",
				"coordinates": [
					-79.45184,
					43.75385
				]
			},
			"bbox": [
				-79.4533963,
				43.7527258,
				-79.4502837,
				43.7549742
			]
		}
	]
}
