{
	"type": "FeatureCollection",
	"features": [
		{
			"type": "Feature",
			"properties": {
				"confidence": 9,
				"authenticationResultCode": "ValidCredentials",
				"brandLogoUri": "http://dev.virtualearth.net/Branding/logo_powered_by.png",
				"copyright": "Copyright © 2017 Microsoft and its suppliers. All rights reserved. This API cannot be accessed and the content and any results may not be used, reproduced or transmitted in any manner without express written permission from Microsoft Corporation.",
				"entityType": "Address",
				"matchCodes": [
					"Good"
				],
				"name": "184 Riverbrook Way SE, Calgary, AB T2C 3S6, Canada",
				"statusCode": 200,
				"statusDescription": "OK",
				"traceId": "261f6ce5d9e145ff9cb634863e7884e3|BN20130621|7.7.0.0|",
				"addressLine": "184 Riverbrook Way SE",
				"adminDistrict": "AB",
				"adminDistrict2": "Alberta",
				"countryRegion": "Canada",
				"formattedAddress": "184 Riverbrook Way SE, Calgary, AB T2C 3S6, Canada",
				"locality": "Calgary",
				"neighborhood": "Riverbend",
				"postalCode": "T2C 3S6"
			},
			"geometry": {
				"type": "Point",
				"coordinates": [
					-114.02327,
					50.9789699
				]
			},
			"bbox": [
				-114.0250555,
				50.9778457,
				-114.0214845,
				50.9800941
			]
		}
	]
}
