{
	"type": "FeatureCollection",
	"features": [
		{
			"type": "Feature",
			"properties": {
				"confidence": 9,
				"authenticationResultCode": "ValidCredentials",
				"brandLogoUri": "http://dev.virtualearth.net/Branding/logo_powered_by.png",
				"copyright": "Copyright © 2017 Microsoft and its suppliers. All rights reserved. This API cannot be accessed and the content and any results may not be used, reproduced or transmitted in any manner without express written permission from Microsoft Corporation.",
				"entityType": "Address",
				"matchCodes": [
					"Good"
				],
				"name": "184 Cranfield Cir SE, Calgary, AB T3M 1H1, Canada",
				"statusCode": 200,
				"statusDescription": "OK",
				"traceId": "70ba5baaa9a541ce863bf682b6faf8da|BN20190642|7.7.0.0|",
				"addressLine": "184 Cranfield Cir SE",
				"adminDistrict": "AB",
				"adminDistrict2": "Alberta",
				"countryRegion": "Canada",
				"formattedAddress": "184 Cranfield Cir SE, Calgary, AB T3M 1H1, Canada",
				"locality": "Calgary",
				"neighborhood": "Cranston",
				"postalCode": "T3M 1H1"
			},
			"geometry": {
				"type": "Point",
				"coordinates": [
					-113.97808,
					50.88738
				]
			},
			"bbox": [
				-113.979862,
				50.8862558,
				-113.976298,
				50.8885042
			]
		}
	]
}
