{
	"type": "FeatureCollection",
	"features": [
		{
			"type": "Feature",
			"properties": {
				"confidence": 9,
				"authenticationResultCode": "ValidCredentials",
				"brandLogoUri": "http://dev.virtualearth.net/Branding/logo_powered_by.png",
				"copyright": "Copyright © 2017 Microsoft and its suppliers. All rights reserved. This API cannot be accessed and the content and any results may not be used, reproduced or transmitted in any manner without express written permission from Microsoft Corporation.",
				"entityType": "Address",
				"matchCodes": [
					"Good"
				],
				"name": "18439 58 Ave, Surrey, BC V3S 1M3, Canada",
				"statusCode": 200,
				"statusDescription": "OK",
				"traceId": "7a50b37a47bb45d693c9804297434089|BN20320521|7.7.0.0|",
				"addressLine": "18439 58 Ave",
				"adminDistrict": "BC",
				"adminDistrict2": "Greater Vancouver",
				"countryRegion": "Canada",
				"formattedAddress": "18439 58 Ave, Surrey, BC V3S 1M3, Canada",
				"locality": "Surrey",
				"neighborhood": "Cloverdale",
				"postalCode": "V3S 1M3"
			},
			"geometry": {
				"type": "Point",
				"coordinates": [
					-122.71154,
					49.10792
				]
			},
			"bbox": [
				-122.7132572,
				49.1067958,
				-122.7098228,
				49.1090442
			]
		}
	]
}
