{
	"type": "FeatureCollection",
	"features": [
		{
			"type": "Feature",
			"properties": {
				"confidence": 9,
				"authenticationResultCode": "ValidCredentials",
				"brandLogoUri": "http://dev.virtualearth.net/Branding/logo_powered_by.png",
				"copyright": "Copyright © 2017 Microsoft and its suppliers. All rights reserved. This API cannot be accessed and the content and any results may not be used, reproduced or transmitted in any manner without express written permission from Microsoft Corporation.",
				"entityType": "Address",
				"matchCodes": [
					"Good"
				],
				"name": "1848 HWY-11, Gravenhurst, ON P0E 1G0, Canada",
				"statusCode": 200,
				"statusDescription": "OK",
				"traceId": "f849ebb77adb40158d2a066ad19cd249|BN20130530|7.7.0.0|",
				"addressLine": "1848 HWY-11",
				"adminDistrict": "ON",
				"adminDistrict2": "Muskoka",
				"countryRegion": "Canada",
				"formattedAddress": "1848 HWY-11, Gravenhurst, ON P0E 1G0, Canada",
				"locality": "Gravenhurst",
				"neighborhood": "Klueys Bay",
				"postalCode": "P0E 1G0"
			},
			"geometry": {
				"type": "Point",
				"coordinates": [
					-79.3146984,
					44.8524635
				]
			},
			"bbox": [
				-79.3162841,
				44.8513394,
				-79.3131127,
				44.8535877
			]
		}
	]
}
