{
	"type": "FeatureCollection",
	"features": [
		{
			"type": "Feature",
			"properties": {
				"confidence": 9,
				"authenticationResultCode": "ValidCredentials",
				"brandLogoUri": "http://dev.virtualearth.net/Branding/logo_powered_by.png",
				"copyright": "Copyright © 2017 Microsoft and its suppliers. All rights reserved. This API cannot be accessed and the content and any results may not be used, reproduced or transmitted in any manner without express written permission from Microsoft Corporation.",
				"entityType": "Address",
				"matchCodes": [
					"Good"
				],
				"name": "185 Snow Blvd, Concord, ON L4K 4N9, Canada",
				"statusCode": 200,
				"statusDescription": "OK",
				"traceId": "7528793ae5fa44a9a49726ce8a41323e|BN20290118|7.7.0.0|",
				"addressLine": "185 Snow Blvd",
				"adminDistrict": "ON",
				"adminDistrict2": "York",
				"countryRegion": "Canada",
				"formattedAddress": "185 Snow Blvd, Concord, ON L4K 4N9, Canada",
				"locality": "Vaughan",
				"neighborhood": "Concord",
				"postalCode": "L4K 4N9"
			},
			"geometry": {
				"type": "Point",
				"coordinates": [
					-79.52417,
					43.80861
				]
			},
			"bbox": [
				-79.5257277,
				43.8074858,
				-79.5226123,
				43.8097342
			]
		}
	]
}
