{
	"type": "FeatureCollection",
	"features": [
		{
			"type": "Feature",
			"properties": {
				"confidence": 9,
				"authenticationResultCode": "ValidCredentials",
				"brandLogoUri": "http://dev.virtualearth.net/Branding/logo_powered_by.png",
				"copyright": "Copyright © 2017 Microsoft and its suppliers. All rights reserved. This API cannot be accessed and the content and any results may not be used, reproduced or transmitted in any manner without express written permission from Microsoft Corporation.",
				"entityType": "Address",
				"matchCodes": [
					"Good"
				],
				"name": "185 Denison St, Markham, ON L3R 1B5, Canada",
				"statusCode": 200,
				"statusDescription": "OK",
				"traceId": "6168e5884f0d4c0eb31c00c5860dee6f|BN20131519|7.7.0.0|",
				"addressLine": "185 Denison St",
				"adminDistrict": "ON",
				"adminDistrict2": "York",
				"countryRegion": "Canada",
				"formattedAddress": "185 Denison St, Markham, ON L3R 1B5, Canada",
				"locality": "Markham",
				"postalCode": "L3R 1B5"
			},
			"geometry": {
				"type": "Point",
				"coordinates": [
					-79.35308,
					43.82094
				]
			},
			"bbox": [
				-79.3546381,
				43.8198158,
				-79.3515219,
				43.8220642
			]
		}
	]
}
