{
	"type": "FeatureCollection",
	"features": [
		{
			"type": "Feature",
			"properties": {
				"confidence": 9,
				"authenticationResultCode": "ValidCredentials",
				"brandLogoUri": "http://dev.virtualearth.net/Branding/logo_powered_by.png",
				"copyright": "Copyright © 2017 Microsoft and its suppliers. All rights reserved. This API cannot be accessed and the content and any results may not be used, reproduced or transmitted in any manner without express written permission from Microsoft Corporation.",
				"entityType": "Address",
				"matchCodes": [
					"Good"
				],
				"name": "185 King St W, Kitchener, ON N2G 1A7, Canada",
				"statusCode": 200,
				"statusDescription": "OK",
				"traceId": "80b6fd26873b424192589adbed402be5|BN20130530|7.7.0.0|",
				"addressLine": "185 King St W",
				"adminDistrict": "ON",
				"adminDistrict2": "Waterloo",
				"countryRegion": "Canada",
				"formattedAddress": "185 King St W, Kitchener, ON N2G 1A7, Canada",
				"locality": "Kitchener",
				"neighborhood": "City Commercial Core",
				"postalCode": "N2G 1A7"
			},
			"geometry": {
				"type": "Point",
				"coordinates": [
					-80.49255,
					43.45083
				]
			},
			"bbox": [
				-80.4940985,
				43.4497058,
				-80.4910015,
				43.4519542
			]
		}
	]
}
