{
	"type": "FeatureCollection",
	"features": [
		{
			"type": "Feature",
			"properties": {
				"confidence": 9,
				"authenticationResultCode": "ValidCredentials",
				"brandLogoUri": "http://dev.virtualearth.net/Branding/logo_powered_by.png",
				"copyright": "Copyright © 2017 Microsoft and its suppliers. All rights reserved. This API cannot be accessed and the content and any results may not be used, reproduced or transmitted in any manner without express written permission from Microsoft Corporation.",
				"entityType": "Address",
				"matchCodes": [
					"Good"
				],
				"name": "1851 94 St NW, Edmonton, AB T6N 1E6, Canada",
				"statusCode": 200,
				"statusDescription": "OK",
				"traceId": "c2dbe4f78f9642ca9f89743d9d1ec6c6|BN20130631|7.7.0.0|",
				"addressLine": "1851 94 St NW",
				"adminDistrict": "AB",
				"adminDistrict2": "Alberta",
				"countryRegion": "Canada",
				"formattedAddress": "1851 94 St NW, Edmonton, AB T6N 1E6, Canada",
				"locality": "Edmonton",
				"neighborhood": "Edmonton Research and Development",
				"postalCode": "T6N 1E6"
			},
			"geometry": {
				"type": "Point",
				"coordinates": [
					-113.46875,
					53.44958
				]
			},
			"bbox": [
				-113.4706376,
				53.4484558,
				-113.4668624,
				53.4507042
			]
		}
	]
}
