{
	"type": "FeatureCollection",
	"features": [
		{
			"type": "Feature",
			"properties": {
				"confidence": 9,
				"authenticationResultCode": "ValidCredentials",
				"brandLogoUri": "http://dev.virtualearth.net/Branding/logo_powered_by.png",
				"copyright": "Copyright © 2017 Microsoft and its suppliers. All rights reserved. This API cannot be accessed and the content and any results may not be used, reproduced or transmitted in any manner without express written permission from Microsoft Corporation.",
				"entityType": "Address",
				"matchCodes": [
					"Good"
				],
				"name": "1855 Boulevard Industriel, Laval, QC H7S 1P5, Canada",
				"statusCode": 200,
				"statusDescription": "OK",
				"traceId": "32e5ff6653334f998106ab5f4e670836|BN20320521|7.7.0.0|",
				"addressLine": "1855 Boulevard Industriel",
				"adminDistrict": "QC",
				"adminDistrict2": "Laval",
				"countryRegion": "Canada",
				"formattedAddress": "1855 Boulevard Industriel, Laval, QC H7S 1P5, Canada",
				"locality": "Laval",
				"postalCode": "H7S 1P5"
			},
			"geometry": {
				"type": "Point",
				"coordinates": [
					-73.72269,
					45.57355
				]
			},
			"bbox": [
				-73.7242959,
				45.5724258,
				-73.7210841,
				45.5746742
			]
		}
	]
}
