{
	"type": "FeatureCollection",
	"features": [
		{
			"type": "Feature",
			"properties": {
				"confidence": 9,
				"authenticationResultCode": "ValidCredentials",
				"brandLogoUri": "http://dev.virtualearth.net/Branding/logo_powered_by.png",
				"copyright": "Copyright © 2017 Microsoft and its suppliers. All rights reserved. This API cannot be accessed and the content and any results may not be used, reproduced or transmitted in any manner without express written permission from Microsoft Corporation.",
				"entityType": "Address",
				"matchCodes": [
					"Good"
				],
				"name": "1883 Upper Water St, Halifax, NS B3J 1S9, Canada",
				"statusCode": 200,
				"statusDescription": "OK",
				"traceId": "c90244eab93745f2819dd8b71f5b9a24|BN20190642|7.7.0.0|",
				"addressLine": "1883 Upper Water St",
				"adminDistrict": "NS",
				"adminDistrict2": "Halifax",
				"countryRegion": "Canada",
				"formattedAddress": "1883 Upper Water St, Halifax, NS B3J 1S9, Canada",
				"locality": "Halifax",
				"neighborhood": "Downtown Halifax",
				"postalCode": "B3J 1S9"
			},
			"geometry": {
				"type": "Point",
				"coordinates": [
					-63.57343,
					44.65036
				]
			},
			"bbox": [
				-63.5750102,
				44.6492358,
				-63.5718498,
				44.6514842
			]
		}
	]
}
