{
	"type": "FeatureCollection",
	"features": [
		{
			"type": "Feature",
			"properties": {
				"confidence": 9,
				"authenticationResultCode": "ValidCredentials",
				"brandLogoUri": "http://dev.virtualearth.net/Branding/logo_powered_by.png",
				"copyright": "Copyright © 2017 Microsoft and its suppliers. All rights reserved. This API cannot be accessed and the content and any results may not be used, reproduced or transmitted in any manner without express written permission from Microsoft Corporation.",
				"entityType": "Address",
				"matchCodes": [
					"Good"
				],
				"name": "1885 HWY-103, Wakefield, NB E7M 1B1, Canada",
				"statusCode": 200,
				"statusDescription": "OK",
				"traceId": "e93e712db0b24cb1a951f1831087f482|BN20200239|7.7.0.0|",
				"addressLine": "1885 HWY-103",
				"adminDistrict": "NB",
				"adminDistrict2": "Carleton",
				"countryRegion": "Canada",
				"formattedAddress": "1885 HWY-103, Wakefield, NB E7M 1B1, Canada",
				"locality": "Wakefield",
				"postalCode": "E7M 1B1"
			},
			"geometry": {
				"type": "Point",
				"coordinates": [
					-67.5153764,
					46.230481
				]
			},
			"bbox": [
				-67.5170014,
				46.2293568,
				-67.5137513,
				46.2316051
			]
		}
	]
}
