{
	"type": "FeatureCollection",
	"features": [
		{
			"type": "Feature",
			"properties": {
				"confidence": 9,
				"authenticationResultCode": "ValidCredentials",
				"brandLogoUri": "http://dev.virtualearth.net/Branding/logo_powered_by.png",
				"copyright": "Copyright © 2017 Microsoft and its suppliers. All rights reserved. This API cannot be accessed and the content and any results may not be used, reproduced or transmitted in any manner without express written permission from Microsoft Corporation.",
				"entityType": "Address",
				"matchCodes": [
					"Good"
				],
				"name": "1887 Lakehurst Rd, Buckhorn, ON K0L 1J0, Canada",
				"statusCode": 200,
				"statusDescription": "OK",
				"traceId": "476cd7951bfc484182130485bf66ed7a|BN20130632|7.7.0.0|",
				"addressLine": "1887 Lakehurst Rd",
				"adminDistrict": "ON",
				"adminDistrict2": "Peterborough",
				"countryRegion": "Canada",
				"formattedAddress": "1887 Lakehurst Rd, Buckhorn, ON K0L 1J0, Canada",
				"locality": "Trent Lakes",
				"neighborhood": "Buckhorn",
				"postalCode": "K0L 1J0"
			},
			"geometry": {
				"type": "Point",
				"coordinates": [
					-78.3531973,
					44.5541562
				]
			},
			"bbox": [
				-78.3547749,
				44.5530321,
				-78.3516198,
				44.5552804
			]
		}
	]
}
