{
	"type": "FeatureCollection",
	"features": [
		{
			"type": "Feature",
			"properties": {
				"confidence": 9,
				"authenticationResultCode": "ValidCredentials",
				"brandLogoUri": "http://dev.virtualearth.net/Branding/logo_powered_by.png",
				"copyright": "Copyright © 2017 Microsoft and its suppliers. All rights reserved. This API cannot be accessed and the content and any results may not be used, reproduced or transmitted in any manner without express written permission from Microsoft Corporation.",
				"entityType": "Address",
				"matchCodes": [
					"Good"
				],
				"name": "1890 Louise Blvd, London, ON N6G 5H1, Canada",
				"statusCode": 200,
				"statusDescription": "OK",
				"traceId": "9dae8f698c154deeb0e935fb93c9570a|BN20130520|7.7.0.0|",
				"addressLine": "1890 Louise Blvd",
				"adminDistrict": "ON",
				"adminDistrict2": "Middlesex",
				"countryRegion": "Canada",
				"formattedAddress": "1890 Louise Blvd, London, ON N6G 5H1, Canada",
				"locality": "London",
				"neighborhood": "Sunningdale",
				"postalCode": "N6G 5H1"
			},
			"geometry": {
				"type": "Point",
				"coordinates": [
					-81.293,
					43.0284
				]
			},
			"bbox": [
				-81.2945378,
				43.0272758,
				-81.2914622,
				43.0295242
			]
		}
	]
}
