{
	"type": "FeatureCollection",
	"features": [
		{
			"type": "Feature",
			"properties": {
				"confidence": 9,
				"authenticationResultCode": "ValidCredentials",
				"brandLogoUri": "http://dev.virtualearth.net/Branding/logo_powered_by.png",
				"copyright": "Copyright © 2017 Microsoft and its suppliers. All rights reserved. This API cannot be accessed and the content and any results may not be used, reproduced or transmitted in any manner without express written permission from Microsoft Corporation.",
				"entityType": "Address",
				"matchCodes": [
					"Good"
				],
				"name": "1899 Merivale Rd, Nepean, ON K2G 1E7, Canada",
				"statusCode": 200,
				"statusDescription": "OK",
				"traceId": "073e3d5c681045cbb5ee6b4b928fae80|BN20130520|7.7.0.0|",
				"addressLine": "1899 Merivale Rd",
				"adminDistrict": "ON",
				"adminDistrict2": "Ottawa",
				"countryRegion": "Canada",
				"formattedAddress": "1899 Merivale Rd, Nepean, ON K2G 1E7, Canada",
				"locality": "Ottawa",
				"neighborhood": "Nepean",
				"postalCode": "K2G 1E7"
			},
			"geometry": {
				"type": "Point",
				"coordinates": [
					-75.72096,
					45.33088
				]
			},
			"bbox": [
				-75.7225591,
				45.3297558,
				-75.7193609,
				45.3320042
			]
		}
	]
}
