{
	"type": "FeatureCollection",
	"features": [
		{
			"type": "Feature",
			"properties": {
				"confidence": 9,
				"authenticationResultCode": "ValidCredentials",
				"brandLogoUri": "http://dev.virtualearth.net/Branding/logo_powered_by.png",
				"copyright": "Copyright © 2017 Microsoft and its suppliers. All rights reserved. This API cannot be accessed and the content and any results may not be used, reproduced or transmitted in any manner without express written permission from Microsoft Corporation.",
				"entityType": "Address",
				"matchCodes": [
					"Good"
				],
				"name": "19 Lesmill Rd, North York, ON M3B 2T3, Canada",
				"statusCode": 200,
				"statusDescription": "OK",
				"traceId": "9cff5aa7165c43e6881ed0ca18a327d8|BN20121762|7.7.0.0|",
				"addressLine": "19 Lesmill Rd",
				"adminDistrict": "ON",
				"adminDistrict2": "Toronto",
				"countryRegion": "Canada",
				"formattedAddress": "19 Lesmill Rd, North York, ON M3B 2T3, Canada",
				"locality": "Toronto",
				"neighborhood": "St Andrews-Windfields",
				"postalCode": "M3B 2T3"
			},
			"geometry": {
				"type": "Point",
				"coordinates": [
					-79.3521899,
					43.75624
				]
			},
			"bbox": [
				-79.3537463,
				43.7551158,
				-79.3506335,
				43.7573642
			]
		}
	]
}
