{
	"type": "FeatureCollection",
	"features": [
		{
			"type": "Feature",
			"properties": {
				"confidence": 9,
				"authenticationResultCode": "ValidCredentials",
				"brandLogoUri": "http://dev.virtualearth.net/Branding/logo_powered_by.png",
				"copyright": "Copyright © 2017 Microsoft and its suppliers. All rights reserved. This API cannot be accessed and the content and any results may not be used, reproduced or transmitted in any manner without express written permission from Microsoft Corporation.",
				"entityType": "Address",
				"matchCodes": [
					"Good"
				],
				"name": "19 Poplar Pt, Winnipeg, MB R3Y 0E2, Canada",
				"statusCode": 200,
				"statusDescription": "OK",
				"traceId": "de607cf8d90f4de4adbfd384a4315bcc|BN20260231|7.7.0.0|",
				"addressLine": "19 Poplar Pt",
				"adminDistrict": "MB",
				"adminDistrict2": "Manitoba",
				"countryRegion": "Canada",
				"formattedAddress": "19 Poplar Pt, Winnipeg, MB R3Y 0E2, Canada",
				"locality": "Winnipeg",
				"neighborhood": "Waverley West",
				"postalCode": "R3Y 0E2"
			},
			"geometry": {
				"type": "Point",
				"coordinates": [
					-97.17776,
					49.80303
				]
			},
			"bbox": [
				-97.1795017,
				49.8019058,
				-97.1760183,
				49.8041542
			]
		}
	]
}
