{
	"type": "FeatureCollection",
	"features": [
		{
			"type": "Feature",
			"properties": {
				"confidence": 9,
				"authenticationResultCode": "ValidCredentials",
				"brandLogoUri": "http://dev.virtualearth.net/Branding/logo_powered_by.png",
				"copyright": "Copyright © 2017 Microsoft and its suppliers. All rights reserved. This API cannot be accessed and the content and any results may not be used, reproduced or transmitted in any manner without express written permission from Microsoft Corporation.",
				"entityType": "Address",
				"matchCodes": [
					"Good"
				],
				"name": "19087 96 Ave, Surrey, BC V4N 3P2, Canada",
				"statusCode": 200,
				"statusDescription": "OK",
				"traceId": "2b58a26b59384b9f8a9ef6e448e1062e|BN20130625|7.7.0.0|",
				"addressLine": "19087 96 Ave",
				"adminDistrict": "BC",
				"adminDistrict2": "Greater Vancouver",
				"countryRegion": "Canada",
				"formattedAddress": "19087 96 Ave, Surrey, BC V4N 3P2, Canada",
				"locality": "Surrey",
				"neighborhood": "Guildford",
				"postalCode": "V4N 3P2"
			},
			"geometry": {
				"type": "Point",
				"coordinates": [
					-122.69342,
					49.17718
				]
			},
			"bbox": [
				-122.6951396,
				49.1760558,
				-122.6917004,
				49.1783042
			]
		}
	]
}
