{
	"type": "FeatureCollection",
	"features": [
		{
			"type": "Feature",
			"properties": {
				"confidence": 9,
				"authenticationResultCode": "ValidCredentials",
				"brandLogoUri": "http://dev.virtualearth.net/Branding/logo_powered_by.png",
				"copyright": "Copyright © 2017 Microsoft and its suppliers. All rights reserved. This API cannot be accessed and the content and any results may not be used, reproduced or transmitted in any manner without express written permission from Microsoft Corporation.",
				"entityType": "Address",
				"matchCodes": [
					"Good"
				],
				"name": "192 Main St NW, Carman, MB R0G, Canada",
				"statusCode": 200,
				"statusDescription": "OK",
				"traceId": "2e0c88a4ebf349439bdfb04c86b2b0fa|BN20220145|7.7.0.0|",
				"addressLine": "192 Main St NW",
				"adminDistrict": "MB",
				"adminDistrict2": "Manitoba",
				"countryRegion": "Canada",
				"formattedAddress": "192 Main St NW, Carman, MB R0G, Canada",
				"locality": "Carman",
				"postalCode": "R0G 0J0"
			},
			"geometry": {
				"type": "Point",
				"coordinates": [
					-98.0017149,
					49.5168237
				]
			},
			"bbox": [
				-98.0034464,
				49.5156995,
				-97.9999834,
				49.5179478
			]
		}
	]
}
