{
	"type": "FeatureCollection",
	"features": [
		{
			"type": "Feature",
			"properties": {
				"confidence": 9,
				"authenticationResultCode": "ValidCredentials",
				"brandLogoUri": "http://dev.virtualearth.net/Branding/logo_powered_by.png",
				"copyright": "Copyright © 2017 Microsoft and its suppliers. All rights reserved. This API cannot be accessed and the content and any results may not be used, reproduced or transmitted in any manner without express written permission from Microsoft Corporation.",
				"entityType": "Address",
				"matchCodes": [
					"Good"
				],
				"name": "19231 Shaws Creek Rd, Alton, ON L7K 1L4, Canada",
				"statusCode": 200,
				"statusDescription": "OK",
				"traceId": "b69a9803e7e64498937d7349ad27f28c|BN20130422|7.7.0.0|",
				"addressLine": "19231 Shaws Creek Rd",
				"adminDistrict": "ON",
				"adminDistrict2": "Peel",
				"countryRegion": "Canada",
				"formattedAddress": "19231 Shaws Creek Rd, Alton, ON L7K 1L4, Canada",
				"locality": "Caledon",
				"neighborhood": "Alton",
				"postalCode": "L7K 1L4"
			},
			"geometry": {
				"type": "Point",
				"coordinates": [
					-80.07128,
					43.8275999
				]
			},
			"bbox": [
				-80.0728382,
				43.8264757,
				-80.0697218,
				43.8287241
			]
		}
	]
}
