{
	"type": "FeatureCollection",
	"features": [
		{
			"type": "Feature",
			"properties": {
				"confidence": 9,
				"authenticationResultCode": "ValidCredentials",
				"brandLogoUri": "http://dev.virtualearth.net/Branding/logo_powered_by.png",
				"copyright": "Copyright © 2017 Microsoft and its suppliers. All rights reserved. This API cannot be accessed and the content and any results may not be used, reproduced or transmitted in any manner without express written permission from Microsoft Corporation.",
				"entityType": "Address",
				"matchCodes": [
					"Good"
				],
				"name": "1930 Chemin Bellerive, Carignan, QC J3L 4Z4, Canada",
				"statusCode": 200,
				"statusDescription": "OK",
				"traceId": "9f59dde9607546c7ad5f1c3f388ebafb|BN20130721|7.7.0.0|",
				"addressLine": "1930 Chemin Bellerive",
				"adminDistrict": "QC",
				"adminDistrict2": "La Vallée-du-Richelieu",
				"countryRegion": "Canada",
				"formattedAddress": "1930 Chemin Bellerive, Carignan, QC J3L 4Z4, Canada",
				"locality": "Carignan",
				"postalCode": "J3L 4Z4"
			},
			"geometry": {
				"type": "Point",
				"coordinates": [
					-73.28715,
					45.47809
				]
			},
			"bbox": [
				-73.2887532,
				45.4769658,
				-73.2855468,
				45.4792142
			]
		}
	]
}
