{
	"type": "FeatureCollection",
	"features": [
		{
			"type": "Feature",
			"properties": {
				"confidence": 9,
				"authenticationResultCode": "ValidCredentials",
				"brandLogoUri": "http://dev.virtualearth.net/Branding/logo_powered_by.png",
				"copyright": "Copyright © 2017 Microsoft and its suppliers. All rights reserved. This API cannot be accessed and the content and any results may not be used, reproduced or transmitted in any manner without express written permission from Microsoft Corporation.",
				"entityType": "Address",
				"matchCodes": [
					"Good"
				],
				"name": "19350 22 Ave, Surrey, BC V3Z 3S6, Canada",
				"statusCode": 200,
				"statusDescription": "OK",
				"traceId": "1606010576f84fb5b23e3979b1ad8689|BN20130621|7.7.0.0|",
				"addressLine": "19350 22 Ave",
				"adminDistrict": "BC",
				"adminDistrict2": "Greater Vancouver",
				"countryRegion": "Canada",
				"formattedAddress": "19350 22 Ave, Surrey, BC V3Z 3S6, Canada",
				"locality": "Surrey",
				"neighborhood": "South Surrey",
				"postalCode": "V3Z 3S6"
			},
			"geometry": {
				"type": "Point",
				"coordinates": [
					-122.688,
					49.04177
				]
			},
			"bbox": [
				-122.6897149,
				49.0406458,
				-122.6862851,
				49.0428942
			]
		}
	]
}
