{
	"type": "FeatureCollection",
	"features": [
		{
			"type": "Feature",
			"properties": {
				"confidence": 9,
				"authenticationResultCode": "ValidCredentials",
				"brandLogoUri": "http://dev.virtualearth.net/Branding/logo_powered_by.png",
				"copyright": "Copyright © 2017 Microsoft and its suppliers. All rights reserved. This API cannot be accessed and the content and any results may not be used, reproduced or transmitted in any manner without express written permission from Microsoft Corporation.",
				"entityType": "Address",
				"matchCodes": [
					"Good"
				],
				"name": "1938 Queensdale Ave, Gloucester, ON K1T 1K1, Canada",
				"statusCode": 200,
				"statusDescription": "OK",
				"traceId": "bbe5dab8ae094fd89c9015e54831a58d|BN20131519|7.7.0.0|",
				"addressLine": "1938 Queensdale Ave",
				"adminDistrict": "ON",
				"adminDistrict2": "Ottawa",
				"countryRegion": "Canada",
				"formattedAddress": "1938 Queensdale Ave, Gloucester, ON K1T 1K1, Canada",
				"locality": "Ottawa",
				"neighborhood": "Gloucester",
				"postalCode": "K1T 1K1"
			},
			"geometry": {
				"type": "Point",
				"coordinates": [
					-75.6146466,
					45.3517418
				]
			},
			"bbox": [
				-75.6162463,
				45.3506176,
				-75.613047,
				45.3528659
			]
		}
	]
}
