{
	"type": "FeatureCollection",
	"features": [
		{
			"type": "Feature",
			"properties": {
				"confidence": 9,
				"authenticationResultCode": "ValidCredentials",
				"brandLogoUri": "http://dev.virtualearth.net/Branding/logo_powered_by.png",
				"copyright": "Copyright © 2017 Microsoft and its suppliers. All rights reserved. This API cannot be accessed and the content and any results may not be used, reproduced or transmitted in any manner without express written permission from Microsoft Corporation.",
				"entityType": "Address",
				"matchCodes": [
					"Good"
				],
				"name": "19386 McCowan Rd, Mt Albert, ON L0G 1M0, Canada",
				"statusCode": 200,
				"statusDescription": "OK",
				"traceId": "3c6f9169facf4170a096398d2678c672|BN20130620|7.7.0.0|",
				"addressLine": "19386 McCowan Rd",
				"adminDistrict": "ON",
				"adminDistrict2": "York",
				"countryRegion": "Canada",
				"formattedAddress": "19386 McCowan Rd, Mt Albert, ON L0G 1M0, Canada",
				"locality": "East Gwillimbury",
				"neighborhood": "Mt Albert",
				"postalCode": "L0G 1M0"
			},
			"geometry": {
				"type": "Point",
				"coordinates": [
					-79.34639,
					44.13232
				]
			},
			"bbox": [
				-79.3479563,
				44.1311958,
				-79.3448237,
				44.1334442
			]
		}
	]
}
