{
	"type": "FeatureCollection",
	"features": [
		{
			"type": "Feature",
			"properties": {
				"confidence": 9,
				"authenticationResultCode": "ValidCredentials",
				"brandLogoUri": "http://dev.virtualearth.net/Branding/logo_powered_by.png",
				"copyright": "Copyright © 2017 Microsoft and its suppliers. All rights reserved. This API cannot be accessed and the content and any results may not be used, reproduced or transmitted in any manner without express written permission from Microsoft Corporation.",
				"entityType": "Address",
				"matchCodes": [
					"Good"
				],
				"name": "195 Stafford Rd, Nepean, ON K2H, Canada",
				"statusCode": 200,
				"statusDescription": "OK",
				"traceId": "d1d8b55998394b0da9a29897ccc0f601|BN20130431|7.7.0.0|",
				"addressLine": "195 Stafford Rd",
				"adminDistrict": "ON",
				"adminDistrict2": "Ottawa",
				"countryRegion": "Canada",
				"formattedAddress": "195 Stafford Rd, Nepean, ON K2H, Canada",
				"locality": "Ottawa",
				"neighborhood": "Nepean",
				"postalCode": "K2H 9C1"
			},
			"geometry": {
				"type": "Point",
				"coordinates": [
					-75.8209386,
					45.32935
				]
			},
			"bbox": [
				-75.8225376,
				45.3282258,
				-75.8193396,
				45.3304741
			]
		}
	]
}
