{
	"type": "FeatureCollection",
	"features": [
		{
			"type": "Feature",
			"properties": {
				"confidence": 9,
				"authenticationResultCode": "ValidCredentials",
				"brandLogoUri": "http://dev.virtualearth.net/Branding/logo_powered_by.png",
				"copyright": "Copyright © 2017 Microsoft and its suppliers. All rights reserved. This API cannot be accessed and the content and any results may not be used, reproduced or transmitted in any manner without express written permission from Microsoft Corporation.",
				"entityType": "Address",
				"matchCodes": [
					"Good"
				],
				"name": "195 Rue des Soeurs, Chicoutimi, QC G7H 8C4, Canada",
				"statusCode": 200,
				"statusDescription": "OK",
				"traceId": "426785972e0c40548d4514bd26d57eaa|BN20300154|7.7.0.0|",
				"addressLine": "195 Rue des Soeurs",
				"adminDistrict": "QC",
				"adminDistrict2": "Saguenay",
				"countryRegion": "Canada",
				"formattedAddress": "195 Rue des Soeurs, Chicoutimi, QC G7H 8C4, Canada",
				"locality": "Saguenay",
				"neighborhood": "Chicoutimi",
				"postalCode": "G7H 8C4"
			},
			"geometry": {
				"type": "Point",
				"coordinates": [
					-71.06694,
					48.38933
				]
			},
			"bbox": [
				-71.0686328,
				48.3882058,
				-71.0652472,
				48.3904542
			]
		}
	]
}
