{
	"type": "FeatureCollection",
	"features": [
		{
			"type": "Feature",
			"properties": {
				"confidence": 9,
				"authenticationResultCode": "ValidCredentials",
				"brandLogoUri": "http://dev.virtualearth.net/Branding/logo_powered_by.png",
				"copyright": "Copyright © 2017 Microsoft and its suppliers. All rights reserved. This API cannot be accessed and the content and any results may not be used, reproduced or transmitted in any manner without express written permission from Microsoft Corporation.",
				"entityType": "Address",
				"matchCodes": [
					"Good"
				],
				"name": "196 Norwich Townline Rd, Norfolk, ON N0J 1R0, Canada",
				"statusCode": 200,
				"statusDescription": "OK",
				"traceId": "4f764b626ce64f0497831c7defed2df5|BN20260231|7.7.0.0|",
				"addressLine": "196 Norwich Townline Rd",
				"adminDistrict": "ON",
				"adminDistrict2": "Norfolk",
				"countryRegion": "Canada",
				"formattedAddress": "196 Norwich Townline Rd, Norfolk, ON N0J 1R0, Canada",
				"locality": "Norfolk",
				"neighborhood": "Delhi",
				"postalCode": "N0J 1R0"
			},
			"geometry": {
				"type": "Point",
				"coordinates": [
					-80.52445,
					42.881
				]
			},
			"bbox": [
				-80.5259841,
				42.8798758,
				-80.5229159,
				42.8821242
			]
		}
	]
}
