{
	"type": "FeatureCollection",
	"features": [
		{
			"type": "Feature",
			"properties": {
				"confidence": 7,
				"authenticationResultCode": "ValidCredentials",
				"brandLogoUri": "http://dev.virtualearth.net/Branding/logo_powered_by.png",
				"copyright": "Copyright © 2017 Microsoft and its suppliers. All rights reserved. This API cannot be accessed and the content and any results may not be used, reproduced or transmitted in any manner without express written permission from Microsoft Corporation.",
				"entityType": "Postcode1",
				"matchCodes": [
					"UpHierarchy"
				],
				"name": "North Glengarry, K0C 1A0, Canada",
				"statusCode": 200,
				"statusDescription": "OK",
				"traceId": "9a864fe0854946938f2c548ae06e7f42|BN20130632|7.7.0.0|",
				"adminDistrict": "ON",
				"adminDistrict2": "Stormont, Dundas and Glengarry",
				"countryRegion": "Canada",
				"formattedAddress": "North Glengarry, K0C 1A0, Canada",
				"locality": "North Glengarry",
				"postalCode": "K0C 1A0"
			},
			"geometry": {
				"type": "Point",
				"coordinates": [
					-74.620735168457,
					45.3743133544922
				]
			},
			"bbox": [
				-74.6280663317242,
				45.3704506369215,
				-74.6134040051899,
				45.3781760720629
			]
		}
	]
}
