{
	"type": "FeatureCollection",
	"features": [
		{
			"type": "Feature",
			"properties": {
				"confidence": 9,
				"authenticationResultCode": "ValidCredentials",
				"brandLogoUri": "http://dev.virtualearth.net/Branding/logo_powered_by.png",
				"copyright": "Copyright © 2017 Microsoft and its suppliers. All rights reserved. This API cannot be accessed and the content and any results may not be used, reproduced or transmitted in any manner without express written permission from Microsoft Corporation.",
				"entityType": "Address",
				"matchCodes": [
					"Good"
				],
				"name": "197 Grand River St N, Paris, ON N3L 2N2, Canada",
				"statusCode": 200,
				"statusDescription": "OK",
				"traceId": "cd5b0c9ebf4244379424233034d38d51|BN20130632|7.7.0.0|",
				"addressLine": "197 Grand River St N",
				"adminDistrict": "ON",
				"adminDistrict2": "Brant",
				"countryRegion": "Canada",
				"formattedAddress": "197 Grand River St N, Paris, ON N3L 2N2, Canada",
				"locality": "Brant",
				"neighborhood": "Paris",
				"postalCode": "N3L 2N2"
			},
			"geometry": {
				"type": "Point",
				"coordinates": [
					-80.38467,
					43.20001
				]
			},
			"bbox": [
				-80.3862121,
				43.1988858,
				-80.3831279,
				43.2011342
			]
		}
	]
}
