{
	"type": "FeatureCollection",
	"features": [
		{
			"type": "Feature",
			"properties": {
				"confidence": 9,
				"authenticationResultCode": "ValidCredentials",
				"brandLogoUri": "http://dev.virtualearth.net/Branding/logo_powered_by.png",
				"copyright": "Copyright © 2017 Microsoft and its suppliers. All rights reserved. This API cannot be accessed and the content and any results may not be used, reproduced or transmitted in any manner without express written permission from Microsoft Corporation.",
				"entityType": "Address",
				"matchCodes": [
					"Good"
				],
				"name": "1974 Glenmead Rd, Peterborough, ON K9L 1W5, Canada",
				"statusCode": 200,
				"statusDescription": "OK",
				"traceId": "b9e26d8111e241d0bf9b38fef4f0b617|BN20130447|7.7.0.0|",
				"addressLine": "1974 Glenmead Rd",
				"adminDistrict": "ON",
				"adminDistrict2": "Peterborough",
				"countryRegion": "Canada",
				"formattedAddress": "1974 Glenmead Rd, Peterborough, ON K9L 1W5, Canada",
				"locality": "Peterborough",
				"postalCode": "K9L 1W5"
			},
			"geometry": {
				"type": "Point",
				"coordinates": [
					-78.2915,
					44.29795
				]
			},
			"bbox": [
				-78.2930707,
				44.2968258,
				-78.2899293,
				44.2990742
			]
		}
	]
}
