{
	"type": "FeatureCollection",
	"features": [
		{
			"type": "Feature",
			"properties": {
				"confidence": 9,
				"authenticationResultCode": "ValidCredentials",
				"brandLogoUri": "http://dev.virtualearth.net/Branding/logo_powered_by.png",
				"copyright": "Copyright © 2017 Microsoft and its suppliers. All rights reserved. This API cannot be accessed and the content and any results may not be used, reproduced or transmitted in any manner without express written permission from Microsoft Corporation.",
				"entityType": "Address",
				"matchCodes": [
					"Good"
				],
				"name": "1980 Rue le Châtelier, Laval, QC H7L 5B4, Canada",
				"statusCode": 200,
				"statusDescription": "OK",
				"traceId": "d1731333cbda4c14b1ba7a50b8a0d3c6|BN20130520|7.7.0.0|",
				"addressLine": "1980 Rue le Châtelier",
				"adminDistrict": "QC",
				"adminDistrict2": "Laval",
				"countryRegion": "Canada",
				"formattedAddress": "1980 Rue le Châtelier, Laval, QC H7L 5B4, Canada",
				"locality": "Laval",
				"postalCode": "H7L 5B4"
			},
			"geometry": {
				"type": "Point",
				"coordinates": [
					-73.75857,
					45.58719
				]
			},
			"bbox": [
				-73.7601763,
				45.5860658,
				-73.7569637,
				45.5883142
			]
		}
	]
}
