{
	"type": "FeatureCollection",
	"features": [
		{
			"type": "Feature",
			"properties": {
				"confidence": 9,
				"authenticationResultCode": "ValidCredentials",
				"brandLogoUri": "http://dev.virtualearth.net/Branding/logo_powered_by.png",
				"copyright": "Copyright © 2017 Microsoft and its suppliers. All rights reserved. This API cannot be accessed and the content and any results may not be used, reproduced or transmitted in any manner without express written permission from Microsoft Corporation.",
				"entityType": "Address",
				"matchCodes": [
					"Good"
				],
				"name": "199 Wentworth St W, Oshawa, ON L1J 6P4, Canada",
				"statusCode": 200,
				"statusDescription": "OK",
				"traceId": "e7056f84c8394a1386c6ab01b45ed819|BN20290118|7.7.0.0|",
				"addressLine": "199 Wentworth St W",
				"adminDistrict": "ON",
				"adminDistrict2": "Durham",
				"countryRegion": "Canada",
				"formattedAddress": "199 Wentworth St W, Oshawa, ON L1J 6P4, Canada",
				"locality": "Oshawa",
				"neighborhood": "Lakeview",
				"postalCode": "L1J 6P4"
			},
			"geometry": {
				"type": "Point",
				"coordinates": [
					-78.84986,
					43.86976
				]
			},
			"bbox": [
				-78.8514193,
				43.8686358,
				-78.8483007,
				43.8708842
			]
		}
	]
}
