{
	"type": "FeatureCollection",
	"features": [
		{
			"type": "Feature",
			"properties": {
				"confidence": 9,
				"authenticationResultCode": "ValidCredentials",
				"brandLogoUri": "http://dev.virtualearth.net/Branding/logo_powered_by.png",
				"copyright": "Copyright © 2017 Microsoft and its suppliers. All rights reserved. This API cannot be accessed and the content and any results may not be used, reproduced or transmitted in any manner without express written permission from Microsoft Corporation.",
				"entityType": "Address",
				"matchCodes": [
					"Good"
				],
				"name": "199 Forestplain Rd, Oro-Medonte, ON L3V 0R4, Canada",
				"statusCode": 200,
				"statusDescription": "OK",
				"traceId": "770d40ce80a3487db54e7656207d0724|BN20220145|7.7.0.0|",
				"addressLine": "199 Forestplain Rd",
				"adminDistrict": "ON",
				"adminDistrict2": "Simcoe",
				"countryRegion": "Canada",
				"formattedAddress": "199 Forestplain Rd, Oro-Medonte, ON L3V 0R4, Canada",
				"locality": "Oro-Medonte",
				"postalCode": "L3V 0R4"
			},
			"geometry": {
				"type": "Point",
				"coordinates": [
					-79.4396365,
					44.5694447
				]
			},
			"bbox": [
				-79.4412145,
				44.5683206,
				-79.4380586,
				44.5705689
			]
		}
	]
}
