{
	"type": "FeatureCollection",
	"features": [
		{
			"type": "Feature",
			"properties": {
				"confidence": 9,
				"authenticationResultCode": "ValidCredentials",
				"brandLogoUri": "http://dev.virtualearth.net/Branding/logo_powered_by.png",
				"copyright": "Copyright © 2017 Microsoft and its suppliers. All rights reserved. This API cannot be accessed and the content and any results may not be used, reproduced or transmitted in any manner without express written permission from Microsoft Corporation.",
				"entityType": "Address",
				"matchCodes": [
					"Good"
				],
				"name": "1995 Rue Nishk, Le Domaine-du-Roy, QC G0W 2H0, Canada",
				"statusCode": 200,
				"statusDescription": "OK",
				"traceId": "bd04fab842284c64b08579589cf7280c|BN20121763|7.7.0.0|",
				"addressLine": "1995 Rue Nishk",
				"adminDistrict": "QC",
				"adminDistrict2": "Le Domaine-du-Roy",
				"countryRegion": "Canada",
				"formattedAddress": "1995 Rue Nishk, Le Domaine-du-Roy, QC G0W 2H0, Canada",
				"locality": "Le Domaine-du-Roy",
				"neighborhood": "Le Domaine-du-Roy",
				"postalCode": "G0W 2H0"
			},
			"geometry": {
				"type": "Point",
				"coordinates": [
					-72.2612608,
					48.5711052
				]
			},
			"bbox": [
				-72.2629597,
				48.5699811,
				-72.2595618,
				48.5722294
			]
		}
	]
}
