{
	"type": "FeatureCollection",
	"features": [
		{
			"type": "Feature",
			"properties": {
				"confidence": 9,
				"authenticationResultCode": "ValidCredentials",
				"brandLogoUri": "http://dev.virtualearth.net/Branding/logo_powered_by.png",
				"copyright": "Copyright © 2017 Microsoft and its suppliers. All rights reserved. This API cannot be accessed and the content and any results may not be used, reproduced or transmitted in any manner without express written permission from Microsoft Corporation.",
				"entityType": "Address",
				"matchCodes": [
					"Good"
				],
				"name": "2 Fenwood Rd, Halifax, NS B3N 1G8, Canada",
				"statusCode": 200,
				"statusDescription": "OK",
				"traceId": "d6751279a6c64f02826bfde2bb756eff|BN20190653|7.7.0.0|",
				"addressLine": "2 Fenwood Rd",
				"adminDistrict": "NS",
				"adminDistrict2": "Halifax",
				"countryRegion": "Canada",
				"formattedAddress": "2 Fenwood Rd, Halifax, NS B3N 1G8, Canada",
				"locality": "Halifax",
				"neighborhood": "Armdale",
				"postalCode": "B3N 1G8"
			},
			"geometry": {
				"type": "Point",
				"coordinates": [
					-63.63003,
					44.63673
				]
			},
			"bbox": [
				-63.6316098,
				44.6356058,
				-63.6284502,
				44.6378542
			]
		}
	]
}
