{
	"type": "FeatureCollection",
	"features": [
		{
			"type": "Feature",
			"properties": {
				"confidence": 9,
				"authenticationResultCode": "ValidCredentials",
				"brandLogoUri": "http://dev.virtualearth.net/Branding/logo_powered_by.png",
				"copyright": "Copyright © 2017 Microsoft and its suppliers. All rights reserved. This API cannot be accessed and the content and any results may not be used, reproduced or transmitted in any manner without express written permission from Microsoft Corporation.",
				"entityType": "Address",
				"matchCodes": [
					"Good"
				],
				"name": "2 Indell Ln, Brampton, ON L6T 3Y3, Canada",
				"statusCode": 200,
				"statusDescription": "OK",
				"traceId": "58896a44a97f434683496dc905c825d6|BN20130530|7.7.0.0|",
				"addressLine": "2 Indell Ln",
				"adminDistrict": "ON",
				"adminDistrict2": "Peel",
				"countryRegion": "Canada",
				"formattedAddress": "2 Indell Ln, Brampton, ON L6T 3Y3, Canada",
				"locality": "Brampton",
				"neighborhood": "Bramalea",
				"postalCode": "L6T 3Y3"
			},
			"geometry": {
				"type": "Point",
				"coordinates": [
					-79.69148,
					43.73594
				]
			},
			"bbox": [
				-79.6930358,
				43.7348158,
				-79.6899242,
				43.7370642
			]
		}
	]
}
