{
	"type": "FeatureCollection",
	"features": [
		{
			"type": "Feature",
			"properties": {
				"confidence": 9,
				"authenticationResultCode": "ValidCredentials",
				"brandLogoUri": "http://dev.virtualearth.net/Branding/logo_powered_by.png",
				"copyright": "Copyright © 2017 Microsoft and its suppliers. All rights reserved. This API cannot be accessed and the content and any results may not be used, reproduced or transmitted in any manner without express written permission from Microsoft Corporation.",
				"entityType": "Address",
				"matchCodes": [
					"Good"
				],
				"name": "2 Jullin Ct, Hammonds Plains, NS B4B 1M2, Canada",
				"statusCode": 200,
				"statusDescription": "OK",
				"traceId": "4ca6fd933a1e42bbb1842f8e317175f8|BN20131519|7.7.0.0|",
				"addressLine": "2 Jullin Ct",
				"adminDistrict": "NS",
				"adminDistrict2": "Halifax",
				"countryRegion": "Canada",
				"formattedAddress": "2 Jullin Ct, Hammonds Plains, NS B4B 1M2, Canada",
				"locality": "Halifax",
				"neighborhood": "Hammonds Plains",
				"postalCode": "B4B 1M2"
			},
			"geometry": {
				"type": "Point",
				"coordinates": [
					-63.75479,
					44.69706
				]
			},
			"bbox": [
				-63.7563715,
				44.6959358,
				-63.7532085,
				44.6981842
			]
		}
	]
}
