{
	"type": "FeatureCollection",
	"features": [
		{
			"type": "Feature",
			"properties": {
				"confidence": 9,
				"authenticationResultCode": "ValidCredentials",
				"brandLogoUri": "http://dev.virtualearth.net/Branding/logo_powered_by.png",
				"copyright": "Copyright © 2017 Microsoft and its suppliers. All rights reserved. This API cannot be accessed and the content and any results may not be used, reproduced or transmitted in any manner without express written permission from Microsoft Corporation.",
				"entityType": "Address",
				"matchCodes": [
					"Good"
				],
				"name": "2 Murphy St, Hillsdale, ON L0L 1V0, Canada",
				"statusCode": 200,
				"statusDescription": "OK",
				"traceId": "62694fd380bf4e388e7cf986d46d9c96|BN20130431|7.7.0.0|",
				"addressLine": "2 Murphy St",
				"adminDistrict": "ON",
				"adminDistrict2": "Simcoe",
				"countryRegion": "Canada",
				"formattedAddress": "2 Murphy St, Hillsdale, ON L0L 1V0, Canada",
				"locality": "Springwater",
				"neighborhood": "Hillsdale",
				"postalCode": "L0L 1V0"
			},
			"geometry": {
				"type": "Point",
				"coordinates": [
					-79.76594,
					44.5776899
				]
			},
			"bbox": [
				-79.7675182,
				44.5765657,
				-79.7643618,
				44.5788141
			]
		}
	]
}
