{
	"type": "FeatureCollection",
	"features": [
		{
			"type": "Feature",
			"properties": {
				"confidence": 9,
				"authenticationResultCode": "ValidCredentials",
				"brandLogoUri": "http://dev.virtualearth.net/Branding/logo_powered_by.png",
				"copyright": "Copyright © 2017 Microsoft and its suppliers. All rights reserved. This API cannot be accessed and the content and any results may not be used, reproduced or transmitted in any manner without express written permission from Microsoft Corporation.",
				"entityType": "Address",
				"matchCodes": [
					"Good"
				],
				"name": "2 Shale Gate, North York, ON M3J 2Y8, Canada",
				"statusCode": 200,
				"statusDescription": "OK",
				"traceId": "e3cd16f55e7248b6a337dd96e2c0fee8|BN20130533|7.7.0.0|",
				"addressLine": "2 Shale Gate",
				"adminDistrict": "ON",
				"adminDistrict2": "Toronto",
				"countryRegion": "Canada",
				"formattedAddress": "2 Shale Gate, North York, ON M3J 2Y8, Canada",
				"locality": "Toronto",
				"neighborhood": "York University Heights",
				"postalCode": "M3J 2Y8"
			},
			"geometry": {
				"type": "Point",
				"coordinates": [
					-79.48743,
					43.78174
				]
			},
			"bbox": [
				-79.488987,
				43.7806158,
				-79.485873,
				43.7828642
			]
		}
	]
}
