{
	"type": "FeatureCollection",
	"features": [
		{
			"type": "Feature",
			"properties": {
				"confidence": 7,
				"authenticationResultCode": "ValidCredentials",
				"brandLogoUri": "http://dev.virtualearth.net/Branding/logo_powered_by.png",
				"copyright": "Copyright © 2017 Microsoft and its suppliers. All rights reserved. This API cannot be accessed and the content and any results may not be used, reproduced or transmitted in any manner without express written permission from Microsoft Corporation.",
				"entityType": "Neighborhood",
				"matchCodes": [
					"Ambiguous",
					"UpHierarchy"
				],
				"name": "Port au Port East, Port au Port East, Newfoundland and Labrador, Canada",
				"statusCode": 200,
				"statusDescription": "OK",
				"traceId": "e65091112afa4d248d8390a1a349ab30|BN20130719|7.7.0.0|",
				"adminDistrict": "NL",
				"countryRegion": "Canada",
				"formattedAddress": "Port au Port East, Port au Port East, Newfoundland and Labrador, Canada",
				"locality": "Port au Port East",
				"neighborhood": "Port au Port East"
			},
			"geometry": {
				"type": "Point",
				"coordinates": [
					-58.7052001953125,
					48.5555992126465
				]
			},
			"bbox": [
				-58.7129807538775,
				48.5517364950758,
				-58.6974196367475,
				48.5594619302172
			]
		},
		{
			"type": "Feature",
			"properties": {
				"confidence": 7,
				"authenticationResultCode": "ValidCredentials",
				"brandLogoUri": "http://dev.virtualearth.net/Branding/logo_powered_by.png",
				"copyright": "Copyright © 2017 Microsoft and its suppliers. All rights reserved. This API cannot be accessed and the content and any results may not be used, reproduced or transmitted in any manner without express written permission from Microsoft Corporation.",
				"entityType": "Neighborhood",
				"matchCodes": [
					"Ambiguous",
					"UpHierarchy"
				],
				"name": "Port au Port, Port au Port East, Newfoundland and Labrador, Canada",
				"statusCode": 200,
				"statusDescription": "OK",
				"traceId": "e65091112afa4d248d8390a1a349ab30|BN20130719|7.7.0.0|",
				"adminDistrict": "NL",
				"countryRegion": "Canada",
				"formattedAddress": "Port au Port, Port au Port East, Newfoundland and Labrador, Canada",
				"locality": "Port au Port East",
				"neighborhood": "Port au Port"
			},
			"geometry": {
				"type": "Point",
				"coordinates": [
					-58.7100791931152,
					48.5567092895508
				]
			},
			"bbox": [
				-58.7178599223814,
				48.5528465719801,
				-58.7022984638491,
				48.5605720071215
			]
		}
	]
}
