{
	"type": "FeatureCollection",
	"features": [
		{
			"type": "Feature",
			"properties": {
				"confidence": 9,
				"authenticationResultCode": "ValidCredentials",
				"brandLogoUri": "http://dev.virtualearth.net/Branding/logo_powered_by.png",
				"copyright": "Copyright © 2017 Microsoft and its suppliers. All rights reserved. This API cannot be accessed and the content and any results may not be used, reproduced or transmitted in any manner without express written permission from Microsoft Corporation.",
				"entityType": "Address",
				"matchCodes": [
					"Good"
				],
				"name": "20 Mill St, North Dundas, ON K0A, Canada",
				"statusCode": 200,
				"statusDescription": "OK",
				"traceId": "943962dc599b4738a5a41ae624d21bc4|BN20240423|7.7.0.0|",
				"addressLine": "20 Mill St",
				"adminDistrict": "ON",
				"adminDistrict2": "Stormont, Dundas and Glengarry",
				"countryRegion": "Canada",
				"formattedAddress": "20 Mill St, North Dundas, ON K0A, Canada",
				"locality": "North Dundas",
				"neighborhood": "Morewood",
				"postalCode": "K0A 2R0"
			},
			"geometry": {
				"type": "Point",
				"coordinates": [
					-75.28765,
					45.17753
				]
			},
			"bbox": [
				-75.2892447,
				45.1764058,
				-75.2860553,
				45.1786542
			]
		}
	]
}
