{
	"type": "FeatureCollection",
	"features": [
		{
			"type": "Feature",
			"properties": {
				"confidence": 9,
				"authenticationResultCode": "ValidCredentials",
				"brandLogoUri": "http://dev.virtualearth.net/Branding/logo_powered_by.png",
				"copyright": "Copyright © 2017 Microsoft and its suppliers. All rights reserved. This API cannot be accessed and the content and any results may not be used, reproduced or transmitted in any manner without express written permission from Microsoft Corporation.",
				"entityType": "Address",
				"matchCodes": [
					"Good"
				],
				"name": "20 N Shore Rd, Lake Cowichan, BC V0R, Canada",
				"statusCode": 200,
				"statusDescription": "OK",
				"traceId": "945085d846b84ea7a931457a07b7d8fa|BN20130447|7.7.0.0|",
				"addressLine": "20 N Shore Rd",
				"adminDistrict": "BC",
				"adminDistrict2": "Cowichan Valley",
				"countryRegion": "Canada",
				"formattedAddress": "20 N Shore Rd, Lake Cowichan, BC V0R, Canada",
				"locality": "Lake Cowichan",
				"postalCode": "V0R 2G0"
			},
			"geometry": {
				"type": "Point",
				"coordinates": [
					-124.05413,
					48.82755
				]
			},
			"bbox": [
				-124.0558376,
				48.8264258,
				-124.0524224,
				48.8286742
			]
		}
	]
}
