{
	"type": "FeatureCollection",
	"features": [
		{
			"type": "Feature",
			"properties": {
				"confidence": 9,
				"authenticationResultCode": "ValidCredentials",
				"brandLogoUri": "http://dev.virtualearth.net/Branding/logo_powered_by.png",
				"copyright": "Copyright © 2017 Microsoft and its suppliers. All rights reserved. This API cannot be accessed and the content and any results may not be used, reproduced or transmitted in any manner without express written permission from Microsoft Corporation.",
				"entityType": "Address",
				"matchCodes": [
					"Good"
				],
				"name": "20 Old Placentia Rd, Mt Pearl, NL A1N 4P5, Canada",
				"statusCode": 200,
				"statusDescription": "OK",
				"traceId": "94c3984bfd7c40fe8acdb925a1dddc90|BN20130631|7.7.0.0|",
				"addressLine": "20 Old Placentia Rd",
				"adminDistrict": "NL",
				"adminDistrict2": "Newfoundland and Labrador",
				"countryRegion": "Canada",
				"formattedAddress": "20 Old Placentia Rd, Mt Pearl, NL A1N 4P5, Canada",
				"locality": "Mt Pearl",
				"postalCode": "A1N 4P5"
			},
			"geometry": {
				"type": "Point",
				"coordinates": [
					-52.8277266,
					47.512552
				]
			},
			"bbox": [
				-52.829391,
				47.5114279,
				-52.8260623,
				47.5136762
			]
		}
	]
}
