{
	"type": "FeatureCollection",
	"features": [
		{
			"type": "Feature",
			"properties": {
				"confidence": 9,
				"authenticationResultCode": "ValidCredentials",
				"brandLogoUri": "http://dev.virtualearth.net/Branding/logo_powered_by.png",
				"copyright": "Copyright © 2017 Microsoft and its suppliers. All rights reserved. This API cannot be accessed and the content and any results may not be used, reproduced or transmitted in any manner without express written permission from Microsoft Corporation.",
				"entityType": "Address",
				"matchCodes": [
					"Good"
				],
				"name": "200 Steep Rock Cres, Kanata, ON K2M 0C4, Canada",
				"statusCode": 200,
				"statusDescription": "OK",
				"traceId": "07c40cac96a94202b707f7ca22c7b926|BN20130530|7.7.0.0|",
				"addressLine": "200 Steep Rock Cres",
				"adminDistrict": "ON",
				"adminDistrict2": "Ottawa",
				"countryRegion": "Canada",
				"formattedAddress": "200 Steep Rock Cres, Kanata, ON K2M 0C4, Canada",
				"locality": "Ottawa",
				"neighborhood": "Kanata",
				"postalCode": "K2M 0C4"
			},
			"geometry": {
				"type": "Point",
				"coordinates": [
					-75.85344,
					45.29143
				]
			},
			"bbox": [
				-75.8550379,
				45.2903058,
				-75.8518421,
				45.2925542
			]
		}
	]
}
