{
	"type": "FeatureCollection",
	"features": [
		{
			"type": "Feature",
			"properties": {
				"confidence": 9,
				"authenticationResultCode": "ValidCredentials",
				"brandLogoUri": "http://dev.virtualearth.net/Branding/logo_powered_by.png",
				"copyright": "Copyright © 2017 Microsoft and its suppliers. All rights reserved. This API cannot be accessed and the content and any results may not be used, reproduced or transmitted in any manner without express written permission from Microsoft Corporation.",
				"entityType": "Address",
				"matchCodes": [
					"Good"
				],
				"name": "200 Wildcat Rd, North York, ON M3J 2N5, Canada",
				"statusCode": 200,
				"statusDescription": "OK",
				"traceId": "3f0ff2e9b76b437d81d39b19d799002a|BN20210145|7.7.0.0|",
				"addressLine": "200 Wildcat Rd",
				"adminDistrict": "ON",
				"adminDistrict2": "Toronto",
				"countryRegion": "Canada",
				"formattedAddress": "200 Wildcat Rd, North York, ON M3J 2N5, Canada",
				"locality": "Toronto",
				"neighborhood": "York University Heights",
				"postalCode": "M3J 2N5"
			},
			"geometry": {
				"type": "Point",
				"coordinates": [
					-79.4889655,
					43.7782705
				]
			},
			"bbox": [
				-79.4905224,
				43.7771463,
				-79.4874085,
				43.7793946
			]
		}
	]
}
