{
	"type": "FeatureCollection",
	"features": [
		{
			"type": "Feature",
			"properties": {
				"confidence": 9,
				"authenticationResultCode": "ValidCredentials",
				"brandLogoUri": "http://dev.virtualearth.net/Branding/logo_powered_by.png",
				"copyright": "Copyright © 2017 Microsoft and its suppliers. All rights reserved. This API cannot be accessed and the content and any results may not be used, reproduced or transmitted in any manner without express written permission from Microsoft Corporation.",
				"entityType": "Address",
				"matchCodes": [
					"Good"
				],
				"name": "200 Franklin Blvd, Cambridge, ON N1R 8N8, Canada",
				"statusCode": 200,
				"statusDescription": "OK",
				"traceId": "0bea86cd75db4cf1a26a99a5ead194db|BN20130422|7.7.0.0|",
				"addressLine": "200 Franklin Blvd",
				"adminDistrict": "ON",
				"adminDistrict2": "Waterloo",
				"countryRegion": "Canada",
				"formattedAddress": "200 Franklin Blvd, Cambridge, ON N1R 8N8, Canada",
				"locality": "Cambridge",
				"neighborhood": "Southwood",
				"postalCode": "N1R 8N8"
			},
			"geometry": {
				"type": "Point",
				"coordinates": [
					-80.2873973,
					43.3548449
				]
			},
			"bbox": [
				-80.2889434,
				43.3537207,
				-80.2858513,
				43.355969
			]
		}
	]
}
