{
	"type": "FeatureCollection",
	"features": [
		{
			"type": "Feature",
			"properties": {
				"confidence": 9,
				"authenticationResultCode": "ValidCredentials",
				"brandLogoUri": "http://dev.virtualearth.net/Branding/logo_powered_by.png",
				"copyright": "Copyright © 2017 Microsoft and its suppliers. All rights reserved. This API cannot be accessed and the content and any results may not be used, reproduced or transmitted in any manner without express written permission from Microsoft Corporation.",
				"entityType": "Address",
				"matchCodes": [
					"Good"
				],
				"name": "200 Deersaxon Cir SE, Calgary, AB T2J 6R5, Canada",
				"statusCode": 200,
				"statusDescription": "OK",
				"traceId": "2a70718bfcf34bba88f1f58359ef877b|BN20250135|7.7.0.0|",
				"addressLine": "200 Deersaxon Cir SE",
				"adminDistrict": "AB",
				"adminDistrict2": "Alberta",
				"countryRegion": "Canada",
				"formattedAddress": "200 Deersaxon Cir SE, Calgary, AB T2J 6R5, Canada",
				"locality": "Calgary",
				"neighborhood": "Deer Run",
				"postalCode": "T2J 6R5"
			},
			"geometry": {
				"type": "Point",
				"coordinates": [
					-114.01753,
					50.91962
				]
			},
			"bbox": [
				-114.0193132,
				50.9184958,
				-114.0157468,
				50.9207442
			]
		}
	]
}
