{
	"type": "FeatureCollection",
	"features": [
		{
			"type": "Feature",
			"properties": {
				"confidence": 9,
				"authenticationResultCode": "ValidCredentials",
				"brandLogoUri": "http://dev.virtualearth.net/Branding/logo_powered_by.png",
				"copyright": "Copyright © 2017 Microsoft and its suppliers. All rights reserved. This API cannot be accessed and the content and any results may not be used, reproduced or transmitted in any manner without express written permission from Microsoft Corporation.",
				"entityType": "Address",
				"matchCodes": [
					"Good"
				],
				"name": "2003 Rue Tolba, Odanak, QC J0G 1H0, Canada",
				"statusCode": 200,
				"statusDescription": "OK",
				"traceId": "6892244be0264927bb54f564d63d6dca|BN20130431|7.7.0.0|",
				"addressLine": "2003 Rue Tolba",
				"adminDistrict": "QC",
				"adminDistrict2": "Nicolet-Yamaska",
				"countryRegion": "Canada",
				"formattedAddress": "2003 Rue Tolba, Odanak, QC J0G 1H0, Canada",
				"locality": "Pierreville",
				"neighborhood": "Odanak",
				"postalCode": "J0G 1H0"
			},
			"geometry": {
				"type": "Point",
				"coordinates": [
					-72.82226,
					46.07324
				]
			},
			"bbox": [
				-72.8238804,
				46.0721158,
				-72.8206396,
				46.0743642
			]
		}
	]
}
