{
	"type": "FeatureCollection",
	"features": [
		{
			"type": "Feature",
			"properties": {
				"confidence": 9,
				"authenticationResultCode": "ValidCredentials",
				"brandLogoUri": "http://dev.virtualearth.net/Branding/logo_powered_by.png",
				"copyright": "Copyright © 2017 Microsoft and its suppliers. All rights reserved. This API cannot be accessed and the content and any results may not be used, reproduced or transmitted in any manner without express written permission from Microsoft Corporation.",
				"entityType": "Address",
				"matchCodes": [
					"Good"
				],
				"name": "2006 Tomlinson Ct, Kamloops, BC V2E 2M7, Canada",
				"statusCode": 200,
				"statusDescription": "OK",
				"traceId": "2c81f432edb04d23a03e4d3f9399fd9d|BN20130533|7.7.0.0|",
				"addressLine": "2006 Tomlinson Ct",
				"adminDistrict": "BC",
				"adminDistrict2": "Thompson-Nicola",
				"countryRegion": "Canada",
				"formattedAddress": "2006 Tomlinson Ct, Kamloops, BC V2E 2M7, Canada",
				"locality": "Kamloops",
				"neighborhood": "Upper Sahali",
				"postalCode": "V2E 2M7"
			},
			"geometry": {
				"type": "Point",
				"coordinates": [
					-120.34436,
					50.64576
				]
			},
			"bbox": [
				-120.3461328,
				50.6446358,
				-120.3425872,
				50.6468842
			]
		}
	]
}
