{
	"type": "FeatureCollection",
	"features": [
		{
			"type": "Feature",
			"properties": {
				"confidence": 9,
				"authenticationResultCode": "ValidCredentials",
				"brandLogoUri": "http://dev.virtualearth.net/Branding/logo_powered_by.png",
				"copyright": "Copyright © 2017 Microsoft and its suppliers. All rights reserved. This API cannot be accessed and the content and any results may not be used, reproduced or transmitted in any manner without express written permission from Microsoft Corporation.",
				"entityType": "Address",
				"matchCodes": [
					"Good"
				],
				"name": "201 Chrislea Rd, Woodbridge, ON L4L 8N6, Canada",
				"statusCode": 200,
				"statusDescription": "OK",
				"traceId": "523cedfcf5ea4c8c8dd9871c732d8b70|BN20130520|7.7.0.0|",
				"addressLine": "201 Chrislea Rd",
				"adminDistrict": "ON",
				"adminDistrict2": "York",
				"countryRegion": "Canada",
				"formattedAddress": "201 Chrislea Rd, Woodbridge, ON L4L 8N6, Canada",
				"locality": "Vaughan",
				"neighborhood": "Woodbridge",
				"postalCode": "L4L 8N6"
			},
			"geometry": {
				"type": "Point",
				"coordinates": [
					-79.54236,
					43.7959
				]
			},
			"bbox": [
				-79.5439174,
				43.7947758,
				-79.5408026,
				43.7970242
			]
		}
	]
}
