{
	"type": "FeatureCollection",
	"features": [
		{
			"type": "Feature",
			"properties": {
				"confidence": 9,
				"authenticationResultCode": "ValidCredentials",
				"brandLogoUri": "http://dev.virtualearth.net/Branding/logo_powered_by.png",
				"copyright": "Copyright © 2017 Microsoft and its suppliers. All rights reserved. This API cannot be accessed and the content and any results may not be used, reproduced or transmitted in any manner without express written permission from Microsoft Corporation.",
				"entityType": "Address",
				"matchCodes": [
					"Good"
				],
				"name": "201 Portage Ave, Winnipeg, MB R3B 3K6, Canada",
				"statusCode": 200,
				"statusDescription": "OK",
				"traceId": "4e1fefe32bfb4614837c5091cec9403f|BN20130520|7.7.0.0|",
				"addressLine": "201 Portage Ave",
				"adminDistrict": "MB",
				"adminDistrict2": "Manitoba",
				"countryRegion": "Canada",
				"formattedAddress": "201 Portage Ave, Winnipeg, MB R3B 3K6, Canada",
				"locality": "Winnipeg",
				"neighborhood": "Portage & Main",
				"postalCode": "R3B 3K6"
			},
			"geometry": {
				"type": "Point",
				"coordinates": [
					-97.13945,
					49.89562
				]
			},
			"bbox": [
				-97.1411951,
				49.8944958,
				-97.1377049,
				49.8967442
			]
		}
	]
}
