{
	"type": "FeatureCollection",
	"features": [
		{
			"type": "Feature",
			"properties": {
				"confidence": 9,
				"authenticationResultCode": "ValidCredentials",
				"brandLogoUri": "http://dev.virtualearth.net/Branding/logo_powered_by.png",
				"copyright": "Copyright © 2017 Microsoft and its suppliers. All rights reserved. This API cannot be accessed and the content and any results may not be used, reproduced or transmitted in any manner without express written permission from Microsoft Corporation.",
				"entityType": "Address",
				"matchCodes": [
					"Good"
				],
				"name": "201 King St, London, ON N6A 1C9, Canada",
				"statusCode": 200,
				"statusDescription": "OK",
				"traceId": "7d6130c6e50f4e10805844d1a669f4a4|BN20260223|7.7.0.0|",
				"addressLine": "201 King St",
				"adminDistrict": "ON",
				"adminDistrict2": "Middlesex",
				"countryRegion": "Canada",
				"formattedAddress": "201 King St, London, ON N6A 1C9, Canada",
				"locality": "London",
				"neighborhood": "Central London",
				"postalCode": "N6A 1C9"
			},
			"geometry": {
				"type": "Point",
				"coordinates": [
					-81.2475,
					42.9827
				]
			},
			"bbox": [
				-81.2490367,
				42.9815758,
				-81.2459633,
				42.9838242
			]
		}
	]
}
