{
	"type": "FeatureCollection",
	"features": [
		{
			"type": "Feature",
			"properties": {
				"confidence": 9,
				"authenticationResultCode": "ValidCredentials",
				"brandLogoUri": "http://dev.virtualearth.net/Branding/logo_powered_by.png",
				"copyright": "Copyright © 2017 Microsoft and its suppliers. All rights reserved. This API cannot be accessed and the content and any results may not be used, reproduced or transmitted in any manner without express written permission from Microsoft Corporation.",
				"entityType": "Address",
				"matchCodes": [
					"Good"
				],
				"name": "201 Rue Bishop, Portneuf, QC G0A 2Y0, Canada",
				"statusCode": 200,
				"statusDescription": "OK",
				"traceId": "40429f66e9c54bd0bd96063389faccea|BN20220145|7.7.0.0|",
				"addressLine": "201 Rue Bishop",
				"adminDistrict": "QC",
				"adminDistrict2": "Portneuf",
				"countryRegion": "Canada",
				"formattedAddress": "201 Rue Bishop, Portneuf, QC G0A 2Y0, Canada",
				"locality": "Portneuf",
				"postalCode": "G0A 2Y0"
			},
			"geometry": {
				"type": "Point",
				"coordinates": [
					-71.85988,
					46.71798
				]
			},
			"bbox": [
				-71.8615197,
				46.7168558,
				-71.8582403,
				46.7191042
			]
		}
	]
}
