{
	"type": "FeatureCollection",
	"features": [
		{
			"type": "Feature",
			"properties": {
				"confidence": 9,
				"authenticationResultCode": "ValidCredentials",
				"brandLogoUri": "http://dev.virtualearth.net/Branding/logo_powered_by.png",
				"copyright": "Copyright © 2017 Microsoft and its suppliers. All rights reserved. This API cannot be accessed and the content and any results may not be used, reproduced or transmitted in any manner without express written permission from Microsoft Corporation.",
				"entityType": "Address",
				"matchCodes": [
					"Good"
				],
				"name": "201 Rue Pinel, Chicoutimi, QC G7G 3N7, Canada",
				"statusCode": 200,
				"statusDescription": "OK",
				"traceId": "5b65d26a53574298a216ffe5d446afa0|BN20130634|7.7.0.0|",
				"addressLine": "201 Rue Pinel",
				"adminDistrict": "QC",
				"adminDistrict2": "Saguenay",
				"countryRegion": "Canada",
				"formattedAddress": "201 Rue Pinel, Chicoutimi, QC G7G 3N7, Canada",
				"locality": "Saguenay",
				"neighborhood": "Chicoutimi",
				"postalCode": "G7G 3N7"
			},
			"geometry": {
				"type": "Point",
				"coordinates": [
					-71.07761,
					48.45105
				]
			},
			"bbox": [
				-71.0793049,
				48.4499258,
				-71.0759151,
				48.4521742
			]
		}
	]
}
