{
	"type": "FeatureCollection",
	"features": [
		{
			"type": "Feature",
			"properties": {
				"confidence": 9,
				"authenticationResultCode": "ValidCredentials",
				"brandLogoUri": "http://dev.virtualearth.net/Branding/logo_powered_by.png",
				"copyright": "Copyright © 2017 Microsoft and its suppliers. All rights reserved. This API cannot be accessed and the content and any results may not be used, reproduced or transmitted in any manner without express written permission from Microsoft Corporation.",
				"entityType": "Address",
				"matchCodes": [
					"Good"
				],
				"name": "2019 Kenwood St, Sudbury, ON P3B 2A1, Canada",
				"statusCode": 200,
				"statusDescription": "OK",
				"traceId": "68544253a3704409896616378120d70a|BN20200239|7.7.0.0|",
				"addressLine": "2019 Kenwood St",
				"adminDistrict": "ON",
				"adminDistrict2": "Greater Sudbury",
				"countryRegion": "Canada",
				"formattedAddress": "2019 Kenwood St, Sudbury, ON P3B 2A1, Canada",
				"locality": "Greater Sudbury",
				"neighborhood": "Sudbury",
				"postalCode": "P3B 2A1"
			},
			"geometry": {
				"type": "Point",
				"coordinates": [
					-80.9344799,
					46.49584
				]
			},
			"bbox": [
				-80.9361129,
				46.4947158,
				-80.9328469,
				46.4969642
			]
		}
	]
}
