{
	"type": "FeatureCollection",
	"features": [
		{
			"type": "Feature",
			"properties": {
				"confidence": 8,
				"authenticationResultCode": "ValidCredentials",
				"brandLogoUri": "http://dev.virtualearth.net/Branding/logo_powered_by.png",
				"copyright": "Copyright © 2017 Microsoft and its suppliers. All rights reserved. This API cannot be accessed and the content and any results may not be used, reproduced or transmitted in any manner without express written permission from Microsoft Corporation.",
				"entityType": "RoadBlock",
				"matchCodes": [
					"Good"
				],
				"name": "Railway Ave, Goodwater, SK S0C, Canada",
				"statusCode": 200,
				"statusDescription": "OK",
				"traceId": "3a023a2182e84b759844b945c3f2b0d9|BN20130621|7.7.0.0|",
				"addressLine": "Railway Ave",
				"adminDistrict": "SK",
				"adminDistrict2": "Saskatchewan",
				"countryRegion": "Canada",
				"formattedAddress": "Railway Ave, Goodwater, SK S0C, Canada",
				"locality": "Goodwater",
				"postalCode": "S0C 1E0"
			},
			"geometry": {
				"type": "Point",
				"coordinates": [
					-103.70484,
					49.39622
				]
			},
			"bbox": [
				-103.71035,
				49.39615,
				-103.69935,
				49.3964799
			]
		}
	]
}
