{
	"type": "FeatureCollection",
	"features": [
		{
			"type": "Feature",
			"properties": {
				"confidence": 9,
				"authenticationResultCode": "ValidCredentials",
				"brandLogoUri": "http://dev.virtualearth.net/Branding/logo_powered_by.png",
				"copyright": "Copyright © 2017 Microsoft and its suppliers. All rights reserved. This API cannot be accessed and the content and any results may not be used, reproduced or transmitted in any manner without express written permission from Microsoft Corporation.",
				"entityType": "Address",
				"matchCodes": [
					"Good"
				],
				"name": "202 Dufferin Ave, Selkirk, MB R1A 1C1, Canada",
				"statusCode": 200,
				"statusDescription": "OK",
				"traceId": "e9e2c085fbd14d0483713fa2b0bce44c|BN20130634|7.7.0.0|",
				"addressLine": "202 Dufferin Ave",
				"adminDistrict": "MB",
				"adminDistrict2": "Manitoba",
				"countryRegion": "Canada",
				"formattedAddress": "202 Dufferin Ave, Selkirk, MB R1A 1C1, Canada",
				"locality": "Selkirk",
				"postalCode": "R1A 1C1"
			},
			"geometry": {
				"type": "Point",
				"coordinates": [
					-96.8672742,
					50.1458098
				]
			},
			"bbox": [
				-96.8690284,
				50.1446856,
				-96.86552,
				50.1469339
			]
		}
	]
}
