{
	"type": "FeatureCollection",
	"features": [
		{
			"type": "Feature",
			"properties": {
				"confidence": 9,
				"authenticationResultCode": "ValidCredentials",
				"brandLogoUri": "http://dev.virtualearth.net/Branding/logo_powered_by.png",
				"copyright": "Copyright © 2017 Microsoft and its suppliers. All rights reserved. This API cannot be accessed and the content and any results may not be used, reproduced or transmitted in any manner without express written permission from Microsoft Corporation.",
				"entityType": "Address",
				"matchCodes": [
					"Good"
				],
				"name": "2022 Jacamar Ct, Mississauga, ON L5L 3P7, Canada",
				"statusCode": 200,
				"statusDescription": "OK",
				"traceId": "6c8de7ad604e411c8c1743ad0212700e|BN20320521|7.7.0.0|",
				"addressLine": "2022 Jacamar Ct",
				"adminDistrict": "ON",
				"adminDistrict2": "Peel",
				"countryRegion": "Canada",
				"formattedAddress": "2022 Jacamar Ct, Mississauga, ON L5L 3P7, Canada",
				"locality": "Mississauga",
				"neighborhood": "Erin Mills",
				"postalCode": "L5L 3P7"
			},
			"geometry": {
				"type": "Point",
				"coordinates": [
					-79.6735999,
					43.5437
				]
			},
			"bbox": [
				-79.6751508,
				43.5425758,
				-79.672049,
				43.5448242
			]
		}
	]
}
