{
	"type": "FeatureCollection",
	"features": [
		{
			"type": "Feature",
			"properties": {
				"confidence": 9,
				"authenticationResultCode": "ValidCredentials",
				"brandLogoUri": "http://dev.virtualearth.net/Branding/logo_powered_by.png",
				"copyright": "Copyright © 2017 Microsoft and its suppliers. All rights reserved. This API cannot be accessed and the content and any results may not be used, reproduced or transmitted in any manner without express written permission from Microsoft Corporation.",
				"entityType": "Address",
				"matchCodes": [
					"Good"
				],
				"name": "20268 Fraser Hwy, Langley, BC V3A 4E6, Canada",
				"statusCode": 200,
				"statusDescription": "OK",
				"traceId": "90517122a14a41d785c0f3277c57c63b|BN20130634|7.7.0.0|",
				"addressLine": "20268 Fraser Hwy",
				"adminDistrict": "BC",
				"adminDistrict2": "Greater Vancouver",
				"countryRegion": "Canada",
				"formattedAddress": "20268 Fraser Hwy, Langley, BC V3A 4E6, Canada",
				"locality": "Langley",
				"neighborhood": "Nicomeki",
				"postalCode": "V3A 4E6"
			},
			"geometry": {
				"type": "Point",
				"coordinates": [
					-122.6614354,
					49.1056424
				]
			},
			"bbox": [
				-122.6631525,
				49.1045183,
				-122.6597182,
				49.1067666
			]
		}
	]
}
