{
	"type": "FeatureCollection",
	"features": [
		{
			"type": "Feature",
			"properties": {
				"confidence": 9,
				"authenticationResultCode": "ValidCredentials",
				"brandLogoUri": "http://dev.virtualearth.net/Branding/logo_powered_by.png",
				"copyright": "Copyright © 2017 Microsoft and its suppliers. All rights reserved. This API cannot be accessed and the content and any results may not be used, reproduced or transmitted in any manner without express written permission from Microsoft Corporation.",
				"entityType": "Address",
				"matchCodes": [
					"Good"
				],
				"name": "2031 Quincy Ave, Gloucester, ON K1J 6B2, Canada",
				"statusCode": 200,
				"statusDescription": "OK",
				"traceId": "608e9f89e24c4544b739973779059e67|BN20130442|7.7.0.0|",
				"addressLine": "2031 Quincy Ave",
				"adminDistrict": "ON",
				"adminDistrict2": "Ottawa",
				"countryRegion": "Canada",
				"formattedAddress": "2031 Quincy Ave, Gloucester, ON K1J 6B2, Canada",
				"locality": "Ottawa",
				"neighborhood": "Gloucester",
				"postalCode": "K1J 6B2"
			},
			"geometry": {
				"type": "Point",
				"coordinates": [
					-75.60557,
					45.46162
				]
			},
			"bbox": [
				-75.6071728,
				45.4604958,
				-75.6039672,
				45.4627442
			]
		}
	]
}
