{
	"type": "FeatureCollection",
	"features": [
		{
			"type": "Feature",
			"properties": {
				"confidence": 9,
				"authenticationResultCode": "ValidCredentials",
				"brandLogoUri": "http://dev.virtualearth.net/Branding/logo_powered_by.png",
				"copyright": "Copyright © 2017 Microsoft and its suppliers. All rights reserved. This API cannot be accessed and the content and any results may not be used, reproduced or transmitted in any manner without express written permission from Microsoft Corporation.",
				"entityType": "Address",
				"matchCodes": [
					"Good"
				],
				"name": "204 Virginia Ave, Dieppe, NB E1A 1L8, Canada",
				"statusCode": 200,
				"statusDescription": "OK",
				"traceId": "9780378fd9134ef4b1df3f4c535ed1a9|BN20131519|7.7.0.0|",
				"addressLine": "204 Virginia Ave",
				"adminDistrict": "NB",
				"adminDistrict2": "Westmorland",
				"countryRegion": "Canada",
				"formattedAddress": "204 Virginia Ave, Dieppe, NB E1A 1L8, Canada",
				"locality": "Dieppe",
				"postalCode": "E1A 1L8"
			},
			"geometry": {
				"type": "Point",
				"coordinates": [
					-64.74752,
					46.09315
				]
			},
			"bbox": [
				-64.749141,
				46.0920258,
				-64.745899,
				46.0942742
			]
		}
	]
}
