{
	"type": "FeatureCollection",
	"features": [
		{
			"type": "Feature",
			"properties": {
				"confidence": 9,
				"authenticationResultCode": "ValidCredentials",
				"brandLogoUri": "http://dev.virtualearth.net/Branding/logo_powered_by.png",
				"copyright": "Copyright © 2017 Microsoft and its suppliers. All rights reserved. This API cannot be accessed and the content and any results may not be used, reproduced or transmitted in any manner without express written permission from Microsoft Corporation.",
				"entityType": "Address",
				"matchCodes": [
					"Good"
				],
				"name": "2075 16th Ave E, Owen Sound, ON N4K 5N3, Canada",
				"statusCode": 200,
				"statusDescription": "OK",
				"traceId": "b08b5787567048cab7f0695d737f913a|BN20300154|7.7.0.0|",
				"addressLine": "2075 16th Ave E",
				"adminDistrict": "ON",
				"adminDistrict2": "Grey",
				"countryRegion": "Canada",
				"formattedAddress": "2075 16th Ave E, Owen Sound, ON N4K 5N3, Canada",
				"locality": "Owen Sound",
				"postalCode": "N4K 5N3"
			},
			"geometry": {
				"type": "Point",
				"coordinates": [
					-80.918165,
					44.5813593
				]
			},
			"bbox": [
				-80.9197433,
				44.5802351,
				-80.9165867,
				44.5824834
			]
		}
	]
}
