{
	"type": "FeatureCollection",
	"features": [
		{
			"type": "Feature",
			"properties": {
				"confidence": 9,
				"authenticationResultCode": "ValidCredentials",
				"brandLogoUri": "http://dev.virtualearth.net/Branding/logo_powered_by.png",
				"copyright": "Copyright © 2017 Microsoft and its suppliers. All rights reserved. This API cannot be accessed and the content and any results may not be used, reproduced or transmitted in any manner without express written permission from Microsoft Corporation.",
				"entityType": "Address",
				"matchCodes": [
					"Good"
				],
				"name": "208 Railway Ave E, Acadia No 34, AB T0J 0Y4, Canada",
				"statusCode": 200,
				"statusDescription": "OK",
				"traceId": "c1687a45612043c3912aba170b3ed35e|BN20121764|7.7.0.0|",
				"addressLine": "208 Railway Ave E",
				"adminDistrict": "AB",
				"adminDistrict2": "Alberta",
				"countryRegion": "Canada",
				"formattedAddress": "208 Railway Ave E, Acadia No 34, AB T0J 0Y4, Canada",
				"locality": "Acadia No 34",
				"postalCode": "T0J 0Y4"
			},
			"geometry": {
				"type": "Point",
				"coordinates": [
					-110.2034965,
					51.1586141
				]
			},
			"bbox": [
				-110.2052889,
				51.15749,
				-110.2017041,
				51.1597383
			]
		}
	]
}
