{
	"type": "FeatureCollection",
	"features": [
		{
			"type": "Feature",
			"properties": {
				"confidence": 9,
				"authenticationResultCode": "ValidCredentials",
				"brandLogoUri": "http://dev.virtualearth.net/Branding/logo_powered_by.png",
				"copyright": "Copyright © 2017 Microsoft and its suppliers. All rights reserved. This API cannot be accessed and the content and any results may not be used, reproduced or transmitted in any manner without express written permission from Microsoft Corporation.",
				"entityType": "Address",
				"matchCodes": [
					"Good"
				],
				"name": "20841 71B Ave, Langley, BC V2Y 0J1, Canada",
				"statusCode": 200,
				"statusDescription": "OK",
				"traceId": "f383625eb5a84b07a92bcd5c0ede0051|BN20130620|7.7.0.0|",
				"addressLine": "20841 71B Ave",
				"adminDistrict": "BC",
				"adminDistrict2": "Greater Vancouver",
				"countryRegion": "Canada",
				"formattedAddress": "20841 71B Ave, Langley, BC V2Y 0J1, Canada",
				"locality": "Langley",
				"neighborhood": "Langley",
				"postalCode": "V2Y 0J1"
			},
			"geometry": {
				"type": "Point",
				"coordinates": [
					-122.64373,
					49.13263
				]
			},
			"bbox": [
				-122.6454481,
				49.1315058,
				-122.6420119,
				49.1337542
			]
		}
	]
}
