{
	"type": "FeatureCollection",
	"features": [
		{
			"type": "Feature",
			"properties": {
				"confidence": 9,
				"authenticationResultCode": "ValidCredentials",
				"brandLogoUri": "http://dev.virtualearth.net/Branding/logo_powered_by.png",
				"copyright": "Copyright © 2017 Microsoft and its suppliers. All rights reserved. This API cannot be accessed and the content and any results may not be used, reproduced or transmitted in any manner without express written permission from Microsoft Corporation.",
				"entityType": "Address",
				"matchCodes": [
					"Good"
				],
				"name": "20849 Stoney Ave, Maple Ridge, BC V2X 7T2, Canada",
				"statusCode": 200,
				"statusDescription": "OK",
				"traceId": "e2f4b8af4e914605a0f4e62629f6b5c3|BN20260223|7.7.0.0|",
				"addressLine": "20849 Stoney Ave",
				"adminDistrict": "BC",
				"adminDistrict2": "Greater Vancouver",
				"countryRegion": "Canada",
				"formattedAddress": "20849 Stoney Ave, Maple Ridge, BC V2X 7T2, Canada",
				"locality": "Maple Ridge",
				"postalCode": "V2X 7T2"
			},
			"geometry": {
				"type": "Point",
				"coordinates": [
					-122.64304,
					49.21354
				]
			},
			"bbox": [
				-122.6447609,
				49.2124158,
				-122.6413191,
				49.2146642
			]
		}
	]
}
