{
	"type": "FeatureCollection",
	"features": [
		{
			"type": "Feature",
			"properties": {
				"confidence": 9,
				"authenticationResultCode": "ValidCredentials",
				"brandLogoUri": "http://dev.virtualearth.net/Branding/logo_powered_by.png",
				"copyright": "Copyright © 2017 Microsoft and its suppliers. All rights reserved. This API cannot be accessed and the content and any results may not be used, reproduced or transmitted in any manner without express written permission from Microsoft Corporation.",
				"entityType": "Address",
				"matchCodes": [
					"Good"
				],
				"name": "2091 97th St, North Battleford, SK S9A 0L2, Canada",
				"statusCode": 200,
				"statusDescription": "OK",
				"traceId": "b3030cfa5d47417496f1a8cb24bc9833|BN20181720|7.7.0.0|",
				"addressLine": "2091 97th St",
				"adminDistrict": "SK",
				"adminDistrict2": "Saskatchewan",
				"countryRegion": "Canada",
				"formattedAddress": "2091 97th St, North Battleford, SK S9A 0L2, Canada",
				"locality": "North Battleford",
				"postalCode": "S9A 0L2"
			},
			"geometry": {
				"type": "Point",
				"coordinates": [
					-108.30384,
					52.78867
				]
			},
			"bbox": [
				-108.3056989,
				52.7875458,
				-108.3019811,
				52.7897942
			]
		}
	]
}
