{
	"type": "FeatureCollection",
	"features": [
		{
			"type": "Feature",
			"properties": {
				"confidence": 7,
				"authenticationResultCode": "ValidCredentials",
				"brandLogoUri": "http://dev.virtualearth.net/Branding/logo_powered_by.png",
				"copyright": "Copyright © 2017 Microsoft and its suppliers. All rights reserved. This API cannot be accessed and the content and any results may not be used, reproduced or transmitted in any manner without express written permission from Microsoft Corporation.",
				"entityType": "RoadBlock",
				"matchCodes": [
					"UpHierarchy"
				],
				"name": "Rue des Pins, The Nation, ON K0A, Canada",
				"statusCode": 200,
				"statusDescription": "OK",
				"traceId": "dc6206dc0dac446f99cdf08645e3709c|BN20130442|7.7.0.0|",
				"addressLine": "Rue des Pins",
				"adminDistrict": "ON",
				"adminDistrict2": "Prescott and Russell",
				"countryRegion": "Canada",
				"formattedAddress": "Rue des Pins, The Nation, ON K0A, Canada",
				"locality": "The Nation",
				"neighborhood": "Limoges",
				"postalCode": "K0A 2M0"
			},
			"geometry": {
				"type": "Point",
				"coordinates": [
					-75.2467,
					45.33262
				]
			},
			"bbox": [
				-75.2526199,
				45.33106,
				-75.23939,
				45.33442
			]
		}
	]
}
