{
	"type": "FeatureCollection",
	"features": [
		{
			"type": "Feature",
			"properties": {
				"confidence": 9,
				"authenticationResultCode": "ValidCredentials",
				"brandLogoUri": "http://dev.virtualearth.net/Branding/logo_powered_by.png",
				"copyright": "Copyright © 2017 Microsoft and its suppliers. All rights reserved. This API cannot be accessed and the content and any results may not be used, reproduced or transmitted in any manner without express written permission from Microsoft Corporation.",
				"entityType": "Address",
				"matchCodes": [
					"Good"
				],
				"name": "20 Courtland Ave, Concord, ON L4K 5B3, Canada",
				"statusCode": 200,
				"statusDescription": "OK",
				"traceId": "b1f723ffc27d4883b790b09af55cbd3a|BN20181720|7.7.0.0|",
				"addressLine": "20 Courtland Ave",
				"adminDistrict": "ON",
				"adminDistrict2": "York",
				"countryRegion": "Canada",
				"formattedAddress": "20 Courtland Ave, Concord, ON L4K 5B3, Canada",
				"locality": "Vaughan",
				"neighborhood": "Concord",
				"postalCode": "L4K 5B3"
			},
			"geometry": {
				"type": "Point",
				"coordinates": [
					-79.5303799,
					43.81553
				]
			},
			"bbox": [
				-79.5319378,
				43.8144058,
				-79.528822,
				43.8166542
			]
		}
	]
}
