{
	"type": "FeatureCollection",
	"features": [
		{
			"type": "Feature",
			"properties": {
				"confidence": 9,
				"authenticationResultCode": "ValidCredentials",
				"brandLogoUri": "http://dev.virtualearth.net/Branding/logo_powered_by.png",
				"copyright": "Copyright © 2017 Microsoft and its suppliers. All rights reserved. This API cannot be accessed and the content and any results may not be used, reproduced or transmitted in any manner without express written permission from Microsoft Corporation.",
				"entityType": "Address",
				"matchCodes": [
					"Good"
				],
				"name": "21 Beverley St, Mississauga, ON L4T 1E9, Canada",
				"statusCode": 200,
				"statusDescription": "OK",
				"traceId": "9912255e28d94cc0ab5a85f02bafe4f0|BN20130532|7.7.0.0|",
				"addressLine": "21 Beverley St",
				"adminDistrict": "ON",
				"adminDistrict2": "Peel",
				"countryRegion": "Canada",
				"formattedAddress": "21 Beverley St, Mississauga, ON L4T 1E9, Canada",
				"locality": "Mississauga",
				"postalCode": "L4T 1E9"
			},
			"geometry": {
				"type": "Point",
				"coordinates": [
					-79.6491999,
					43.70638
				]
			},
			"bbox": [
				-79.650755,
				43.7052558,
				-79.6476448,
				43.7075042
			]
		}
	]
}
