{
	"type": "FeatureCollection",
	"features": [
		{
			"type": "Feature",
			"properties": {
				"confidence": 9,
				"authenticationResultCode": "ValidCredentials",
				"brandLogoUri": "http://dev.virtualearth.net/Branding/logo_powered_by.png",
				"copyright": "Copyright © 2017 Microsoft and its suppliers. All rights reserved. This API cannot be accessed and the content and any results may not be used, reproduced or transmitted in any manner without express written permission from Microsoft Corporation.",
				"entityType": "Address",
				"matchCodes": [
					"Good"
				],
				"name": "21 Brixham Rd, London, ON N6K 1P5, Canada",
				"statusCode": 200,
				"statusDescription": "OK",
				"traceId": "950897e909f44a5cb3d13dd546f367a9|BN20181720|7.7.0.0|",
				"addressLine": "21 Brixham Rd",
				"adminDistrict": "ON",
				"adminDistrict2": "Middlesex",
				"countryRegion": "Canada",
				"formattedAddress": "21 Brixham Rd, London, ON N6K 1P5, Canada",
				"locality": "London",
				"neighborhood": "Westmount",
				"postalCode": "N6K 1P5"
			},
			"geometry": {
				"type": "Point",
				"coordinates": [
					-81.2920411,
					42.9411911
				]
			},
			"bbox": [
				-81.2935767,
				42.940067,
				-81.2905054,
				42.9423153
			]
		}
	]
}
