{
	"type": "FeatureCollection",
	"features": [
		{
			"type": "Feature",
			"properties": {
				"confidence": 9,
				"authenticationResultCode": "ValidCredentials",
				"brandLogoUri": "http://dev.virtualearth.net/Branding/logo_powered_by.png",
				"copyright": "Copyright © 2017 Microsoft and its suppliers. All rights reserved. This API cannot be accessed and the content and any results may not be used, reproduced or transmitted in any manner without express written permission from Microsoft Corporation.",
				"entityType": "Address",
				"matchCodes": [
					"Good"
				],
				"name": "21 Mountain Ave S, Stoney Creek, ON L8G 2V5, Canada",
				"statusCode": 200,
				"statusDescription": "OK",
				"traceId": "0cf45fc9e39e40458da80ee3c7cf121c|BN20260223|7.7.0.0|",
				"addressLine": "21 Mountain Ave S",
				"adminDistrict": "ON",
				"adminDistrict2": "Hamilton",
				"countryRegion": "Canada",
				"formattedAddress": "21 Mountain Ave S, Stoney Creek, ON L8G 2V5, Canada",
				"locality": "Hamilton",
				"neighborhood": "Stoney Creek",
				"postalCode": "L8G 2V5"
			},
			"geometry": {
				"type": "Point",
				"coordinates": [
					-79.75671,
					43.21538
				]
			},
			"bbox": [
				-79.7582525,
				43.2142558,
				-79.7551675,
				43.2165042
			]
		}
	]
}
