{
	"type": "FeatureCollection",
	"features": [
		{
			"type": "Feature",
			"properties": {
				"confidence": 9,
				"authenticationResultCode": "ValidCredentials",
				"brandLogoUri": "http://dev.virtualearth.net/Branding/logo_powered_by.png",
				"copyright": "Copyright © 2017 Microsoft and its suppliers. All rights reserved. This API cannot be accessed and the content and any results may not be used, reproduced or transmitted in any manner without express written permission from Microsoft Corporation.",
				"entityType": "Address",
				"matchCodes": [
					"Good"
				],
				"name": "21 Maplehurst Ave, Nepean, ON K2H 5A3, Canada",
				"statusCode": 200,
				"statusDescription": "OK",
				"traceId": "bb5a130681924c57a9649b709bc84708|BN20130520|7.7.0.0|",
				"addressLine": "21 Maplehurst Ave",
				"adminDistrict": "ON",
				"adminDistrict2": "Ottawa",
				"countryRegion": "Canada",
				"formattedAddress": "21 Maplehurst Ave, Nepean, ON K2H 5A3, Canada",
				"locality": "Ottawa",
				"neighborhood": "Nepean",
				"postalCode": "K2H 5A3"
			},
			"geometry": {
				"type": "Point",
				"coordinates": [
					-75.80908,
					45.35394
				]
			},
			"bbox": [
				-75.8106797,
				45.3528158,
				-75.8074803,
				45.3550642
			]
		}
	]
}
