{
	"type": "FeatureCollection",
	"features": [
		{
			"type": "Feature",
			"properties": {
				"confidence": 9,
				"authenticationResultCode": "ValidCredentials",
				"brandLogoUri": "http://dev.virtualearth.net/Branding/logo_powered_by.png",
				"copyright": "Copyright © 2017 Microsoft and its suppliers. All rights reserved. This API cannot be accessed and the content and any results may not be used, reproduced or transmitted in any manner without express written permission from Microsoft Corporation.",
				"entityType": "Address",
				"matchCodes": [
					"Good"
				],
				"name": "21 Selby Rd, Brampton, ON L6W 1K5, Canada",
				"statusCode": 200,
				"statusDescription": "OK",
				"traceId": "7cadb89653414b77bec8fe0a558cac9c|BN20290118|7.7.0.0|",
				"addressLine": "21 Selby Rd",
				"adminDistrict": "ON",
				"adminDistrict2": "Peel",
				"countryRegion": "Canada",
				"formattedAddress": "21 Selby Rd, Brampton, ON L6W 1K5, Canada",
				"locality": "Brampton",
				"postalCode": "L6W 1K5"
			},
			"geometry": {
				"type": "Point",
				"coordinates": [
					-79.72768,
					43.68999
				]
			},
			"bbox": [
				-79.7292347,
				43.6888658,
				-79.7261253,
				43.6911142
			]
		}
	]
}
