{
	"type": "FeatureCollection",
	"features": [
		{
			"type": "Feature",
			"properties": {
				"confidence": 9,
				"authenticationResultCode": "ValidCredentials",
				"brandLogoUri": "http://dev.virtualearth.net/Branding/logo_powered_by.png",
				"copyright": "Copyright © 2017 Microsoft and its suppliers. All rights reserved. This API cannot be accessed and the content and any results may not be used, reproduced or transmitted in any manner without express written permission from Microsoft Corporation.",
				"entityType": "Address",
				"matchCodes": [
					"Good"
				],
				"name": "21 25th St, Toronto, ON M8V, Canada",
				"statusCode": 200,
				"statusDescription": "OK",
				"traceId": "b03c81ccc0444d47a7c944472fcaa8f9|BN20121764|7.7.0.0|",
				"addressLine": "21 25th St",
				"adminDistrict": "ON",
				"adminDistrict2": "Toronto",
				"countryRegion": "Canada",
				"formattedAddress": "21 25th St, Toronto, ON M8V, Canada",
				"locality": "Toronto",
				"neighborhood": "Long Branch",
				"postalCode": "M8V 3P4"
			},
			"geometry": {
				"type": "Point",
				"coordinates": [
					-79.5216142,
					43.5923561
				]
			},
			"bbox": [
				-79.5231664,
				43.591232,
				-79.5200621,
				43.5934803
			]
		}
	]
}
