{
	"type": "FeatureCollection",
	"features": [
		{
			"type": "Feature",
			"properties": {
				"confidence": 9,
				"authenticationResultCode": "ValidCredentials",
				"brandLogoUri": "http://dev.virtualearth.net/Branding/logo_powered_by.png",
				"copyright": "Copyright © 2017 Microsoft and its suppliers. All rights reserved. This API cannot be accessed and the content and any results may not be used, reproduced or transmitted in any manner without express written permission from Microsoft Corporation.",
				"entityType": "Address",
				"matchCodes": [
					"Good"
				],
				"name": "2105 Boulevard Industriel, Laval, QC H7S 1P7, Canada",
				"statusCode": 200,
				"statusDescription": "OK",
				"traceId": "861d5231039e4bd692390749699084f2|BN20130532|7.7.0.0|",
				"addressLine": "2105 Boulevard Industriel",
				"adminDistrict": "QC",
				"adminDistrict2": "Laval",
				"countryRegion": "Canada",
				"formattedAddress": "2105 Boulevard Industriel, Laval, QC H7S 1P7, Canada",
				"locality": "Laval",
				"postalCode": "H7S 1P7"
			},
			"geometry": {
				"type": "Point",
				"coordinates": [
					-73.7283999,
					45.57884
				]
			},
			"bbox": [
				-73.730006,
				45.5777158,
				-73.7267938,
				45.5799642
			]
		}
	]
}
