{
	"type": "FeatureCollection",
	"features": [
		{
			"type": "Feature",
			"properties": {
				"confidence": 9,
				"authenticationResultCode": "ValidCredentials",
				"brandLogoUri": "http://dev.virtualearth.net/Branding/logo_powered_by.png",
				"copyright": "Copyright © 2017 Microsoft and its suppliers. All rights reserved. This API cannot be accessed and the content and any results may not be used, reproduced or transmitted in any manner without express written permission from Microsoft Corporation.",
				"entityType": "Address",
				"matchCodes": [
					"Good"
				],
				"name": "2105 Park Royal S, West Vancouver, BC V7T 2W5, Canada",
				"statusCode": 200,
				"statusDescription": "OK",
				"traceId": "faf7f279c5194e1d8c94e7fd00fafe14|BN20121762|7.7.0.0|",
				"addressLine": "2105 Park Royal S",
				"adminDistrict": "BC",
				"adminDistrict2": "Greater Vancouver",
				"countryRegion": "Canada",
				"formattedAddress": "2105 Park Royal S, West Vancouver, BC V7T 2W5, Canada",
				"locality": "West Vancouver",
				"neighborhood": "Capilano Indian Reserve 5",
				"postalCode": "V7T 2W5"
			},
			"geometry": {
				"type": "Point",
				"coordinates": [
					-123.1390324,
					49.3240962
				]
			},
			"bbox": [
				-123.1407571,
				49.322972,
				-123.1373076,
				49.3252203
			]
		}
	]
}
