{
	"type": "FeatureCollection",
	"features": [
		{
			"type": "Feature",
			"properties": {
				"confidence": 9,
				"authenticationResultCode": "ValidCredentials",
				"brandLogoUri": "http://dev.virtualearth.net/Branding/logo_powered_by.png",
				"copyright": "Copyright © 2017 Microsoft and its suppliers. All rights reserved. This API cannot be accessed and the content and any results may not be used, reproduced or transmitted in any manner without express written permission from Microsoft Corporation.",
				"entityType": "Address",
				"matchCodes": [
					"Good"
				],
				"name": "2118 Laurier Cres, Regina, SK S4V, Canada",
				"statusCode": 200,
				"statusDescription": "OK",
				"traceId": "f2eed38e1c6744a49cb2aa27b5ddc91f|BN20130634|7.7.0.0|",
				"addressLine": "2118 Laurier Cres",
				"adminDistrict": "SK",
				"adminDistrict2": "Saskatchewan",
				"countryRegion": "Canada",
				"formattedAddress": "2118 Laurier Cres, Regina, SK S4V, Canada",
				"locality": "Regina",
				"neighborhood": "Arcola East-North Side",
				"postalCode": "S4V 0P6"
			},
			"geometry": {
				"type": "Point",
				"coordinates": [
					-104.5532,
					50.44336
				]
			},
			"bbox": [
				-104.5549652,
				50.4422358,
				-104.5514348,
				50.4444842
			]
		}
	]
}
