{
	"type": "FeatureCollection",
	"features": [
		{
			"type": "Feature",
			"properties": {
				"confidence": 9,
				"authenticationResultCode": "ValidCredentials",
				"brandLogoUri": "http://dev.virtualearth.net/Branding/logo_powered_by.png",
				"copyright": "Copyright © 2017 Microsoft and its suppliers. All rights reserved. This API cannot be accessed and the content and any results may not be used, reproduced or transmitted in any manner without express written permission from Microsoft Corporation.",
				"entityType": "Address",
				"matchCodes": [
					"Good"
				],
				"name": "2125 15th Ave, Regina, SK S4P 0Z8, Canada",
				"statusCode": 200,
				"statusDescription": "OK",
				"traceId": "92207ddf104745349b55922ea4a37992|BN20130532|7.7.0.0|",
				"addressLine": "2125 15th Ave",
				"adminDistrict": "SK",
				"adminDistrict2": "Saskatchewan",
				"countryRegion": "Canada",
				"formattedAddress": "2125 15th Ave, Regina, SK S4P 0Z8, Canada",
				"locality": "Regina",
				"neighborhood": "Transition Area",
				"postalCode": "S4P 0Z8"
			},
			"geometry": {
				"type": "Point",
				"coordinates": [
					-104.6112237,
					50.4422951
				]
			},
			"bbox": [
				-104.6129889,
				50.441171,
				-104.6094586,
				50.4434193
			]
		}
	]
}
