{
	"type": "FeatureCollection",
	"features": [
		{
			"type": "Feature",
			"properties": {
				"confidence": 9,
				"authenticationResultCode": "ValidCredentials",
				"brandLogoUri": "http://dev.virtualearth.net/Branding/logo_powered_by.png",
				"copyright": "Copyright © 2017 Microsoft and its suppliers. All rights reserved. This API cannot be accessed and the content and any results may not be used, reproduced or transmitted in any manner without express written permission from Microsoft Corporation.",
				"entityType": "Address",
				"matchCodes": [
					"Good"
				],
				"name": "213 2nd St, Cobourg, ON K9A, Canada",
				"statusCode": 200,
				"statusDescription": "OK",
				"traceId": "6d9a1c57a0804255af622d7c0d3bc46c|BN20130520|7.7.0.0|",
				"addressLine": "213 2nd St",
				"adminDistrict": "ON",
				"adminDistrict2": "Northumberland",
				"countryRegion": "Canada",
				"formattedAddress": "213 2nd St, Cobourg, ON K9A, Canada",
				"locality": "Cobourg",
				"postalCode": "K9A 3N7"
			},
			"geometry": {
				"type": "Point",
				"coordinates": [
					-78.1675115,
					43.9593699
				]
			},
			"bbox": [
				-78.1690731,
				43.9582458,
				-78.1659498,
				43.9604941
			]
		}
	]
}
