{
	"type": "FeatureCollection",
	"features": [
		{
			"type": "Feature",
			"properties": {
				"confidence": 9,
				"authenticationResultCode": "ValidCredentials",
				"brandLogoUri": "http://dev.virtualearth.net/Branding/logo_powered_by.png",
				"copyright": "Copyright © 2017 Microsoft and its suppliers. All rights reserved. This API cannot be accessed and the content and any results may not be used, reproduced or transmitted in any manner without express written permission from Microsoft Corporation.",
				"entityType": "Address",
				"matchCodes": [
					"Good"
				],
				"name": "21314 Township Road 554, Fort Saskatchewan, AB T8L 4A4, Canada",
				"statusCode": 200,
				"statusDescription": "OK",
				"traceId": "dd99163631c24d34ad1e44f072d4d9c4|BN20210145|7.7.0.0|",
				"addressLine": "21314 Township Road 554",
				"adminDistrict": "AB",
				"adminDistrict2": "Alberta",
				"countryRegion": "Canada",
				"formattedAddress": "21314 Township Road 554, Fort Saskatchewan, AB T8L 4A4, Canada",
				"locality": "Strathcona County",
				"neighborhood": "Fort Saskatchewan",
				"postalCode": "T8L 4A4"
			},
			"geometry": {
				"type": "Point",
				"coordinates": [
					-113.0539472,
					53.7745253
				]
			},
			"bbox": [
				-113.0558494,
				53.7734011,
				-113.0520449,
				53.7756494
			]
		}
	]
}
