{
	"type": "FeatureCollection",
	"features": [
		{
			"type": "Feature",
			"properties": {
				"confidence": 9,
				"authenticationResultCode": "ValidCredentials",
				"brandLogoUri": "http://dev.virtualearth.net/Branding/logo_powered_by.png",
				"copyright": "Copyright © 2017 Microsoft and its suppliers. All rights reserved. This API cannot be accessed and the content and any results may not be used, reproduced or transmitted in any manner without express written permission from Microsoft Corporation.",
				"entityType": "Address",
				"matchCodes": [
					"Good"
				],
				"name": "2144 Winding Way, Burlington, ON L7M 2X9, Canada",
				"statusCode": 200,
				"statusDescription": "OK",
				"traceId": "80f8401f6f3c482f989687a0fa5df7d9|BN20260223|7.7.0.0|",
				"addressLine": "2144 Winding Way",
				"adminDistrict": "ON",
				"adminDistrict2": "Halton",
				"countryRegion": "Canada",
				"formattedAddress": "2144 Winding Way, Burlington, ON L7M 2X9, Canada",
				"locality": "Burlington",
				"neighborhood": "Headon Forest",
				"postalCode": "L7M 2X9"
			},
			"geometry": {
				"type": "Point",
				"coordinates": [
					-79.82668,
					43.37064
				]
			},
			"bbox": [
				-79.8282264,
				43.3695158,
				-79.8251336,
				43.3717642
			]
		}
	]
}
