{
	"type": "FeatureCollection",
	"features": [
		{
			"type": "Feature",
			"properties": {
				"confidence": 9,
				"authenticationResultCode": "ValidCredentials",
				"brandLogoUri": "http://dev.virtualearth.net/Branding/logo_powered_by.png",
				"copyright": "Copyright © 2017 Microsoft and its suppliers. All rights reserved. This API cannot be accessed and the content and any results may not be used, reproduced or transmitted in any manner without express written permission from Microsoft Corporation.",
				"entityType": "Address",
				"matchCodes": [
					"Good"
				],
				"name": "2145 Albert St, Regina, SK S4P 2V1, Canada",
				"statusCode": 200,
				"statusDescription": "OK",
				"traceId": "4279aa5dd9dd4f40a7b2161ddd16f748|BN20130621|7.7.0.0|",
				"addressLine": "2145 Albert St",
				"adminDistrict": "SK",
				"adminDistrict2": "Saskatchewan",
				"countryRegion": "Canada",
				"formattedAddress": "2145 Albert St, Regina, SK S4P 2V1, Canada",
				"locality": "Regina",
				"neighborhood": "Transition Area",
				"postalCode": "S4P 2V1"
			},
			"geometry": {
				"type": "Point",
				"coordinates": [
					-104.61762,
					50.44464
				]
			},
			"bbox": [
				-104.6193852,
				50.4435158,
				-104.6158548,
				50.4457642
			]
		}
	]
}
