{
	"type": "FeatureCollection",
	"features": [
		{
			"type": "Feature",
			"properties": {
				"confidence": 9,
				"authenticationResultCode": "ValidCredentials",
				"brandLogoUri": "http://dev.virtualearth.net/Branding/logo_powered_by.png",
				"copyright": "Copyright © 2017 Microsoft and its suppliers. All rights reserved. This API cannot be accessed and the content and any results may not be used, reproduced or transmitted in any manner without express written permission from Microsoft Corporation.",
				"entityType": "Address",
				"matchCodes": [
					"Good"
				],
				"name": "215 Rivermede Rd, Concord, ON L4K 3M5, Canada",
				"statusCode": 200,
				"statusDescription": "OK",
				"traceId": "15fd01940f3b4340baa2fe5fb97c1f2a|BN20320521|7.7.0.0|",
				"addressLine": "215 Rivermede Rd",
				"adminDistrict": "ON",
				"adminDistrict2": "York",
				"countryRegion": "Canada",
				"formattedAddress": "215 Rivermede Rd, Concord, ON L4K 3M5, Canada",
				"locality": "Vaughan",
				"neighborhood": "Concord",
				"postalCode": "L4K 3M5"
			},
			"geometry": {
				"type": "Point",
				"coordinates": [
					-79.48951,
					43.81046
				]
			},
			"bbox": [
				-79.4910678,
				43.8093358,
				-79.4879522,
				43.8115842
			]
		}
	]
}
