{
	"type": "FeatureCollection",
	"features": [
		{
			"type": "Feature",
			"properties": {
				"confidence": 9,
				"authenticationResultCode": "ValidCredentials",
				"brandLogoUri": "http://dev.virtualearth.net/Branding/logo_powered_by.png",
				"copyright": "Copyright © 2017 Microsoft and its suppliers. All rights reserved. This API cannot be accessed and the content and any results may not be used, reproduced or transmitted in any manner without express written permission from Microsoft Corporation.",
				"entityType": "Address",
				"matchCodes": [
					"Good"
				],
				"name": "217 Lipton St, Winnipeg, MB R3G 2G8, Canada",
				"statusCode": 200,
				"statusDescription": "OK",
				"traceId": "c5701bea1bce4072936092dfdcb6c01d|BN20130522|7.7.0.0|",
				"addressLine": "217 Lipton St",
				"adminDistrict": "MB",
				"adminDistrict2": "Manitoba",
				"countryRegion": "Canada",
				"formattedAddress": "217 Lipton St, Winnipeg, MB R3G 2G8, Canada",
				"locality": "Winnipeg",
				"neighborhood": "Wolseley",
				"postalCode": "R3G 2G8"
			},
			"geometry": {
				"type": "Point",
				"coordinates": [
					-97.1735,
					49.88341
				]
			},
			"bbox": [
				-97.1752446,
				49.8822858,
				-97.1717554,
				49.8845342
			]
		}
	]
}
