{
	"type": "FeatureCollection",
	"features": [
		{
			"type": "Feature",
			"properties": {
				"confidence": 9,
				"authenticationResultCode": "ValidCredentials",
				"brandLogoUri": "http://dev.virtualearth.net/Branding/logo_powered_by.png",
				"copyright": "Copyright © 2017 Microsoft and its suppliers. All rights reserved. This API cannot be accessed and the content and any results may not be used, reproduced or transmitted in any manner without express written permission from Microsoft Corporation.",
				"entityType": "Address",
				"matchCodes": [
					"Good"
				],
				"name": "2177 Wood Islands Rd, Montague, PE C0A 1R0, Canada",
				"statusCode": 200,
				"statusDescription": "OK",
				"traceId": "7c19ecd3dcc641fa8c4a184904ff4c1e|BN20320521|7.7.0.0|",
				"addressLine": "2177 Wood Islands Rd",
				"adminDistrict": "PE",
				"adminDistrict2": "Kings",
				"countryRegion": "Canada",
				"formattedAddress": "2177 Wood Islands Rd, Montague, PE C0A 1R0, Canada",
				"locality": "Kings",
				"neighborhood": "Montague",
				"postalCode": "C0A 1R0"
			},
			"geometry": {
				"type": "Point",
				"coordinates": [
					-62.70182,
					46.07217
				]
			},
			"bbox": [
				-62.7034404,
				46.0710458,
				-62.7001996,
				46.0732942
			]
		}
	]
}
