{
	"type": "FeatureCollection",
	"features": [
		{
			"type": "Feature",
			"properties": {
				"confidence": 9,
				"authenticationResultCode": "ValidCredentials",
				"brandLogoUri": "http://dev.virtualearth.net/Branding/logo_powered_by.png",
				"copyright": "Copyright © 2017 Microsoft and its suppliers. All rights reserved. This API cannot be accessed and the content and any results may not be used, reproduced or transmitted in any manner without express written permission from Microsoft Corporation.",
				"entityType": "Address",
				"matchCodes": [
					"Good"
				],
				"name": "2178 Winchester Ct, Burlington, ON L7P 3K7, Canada",
				"statusCode": 200,
				"statusDescription": "OK",
				"traceId": "1aa899f8196c478faf6a1d509ae2a936|BN20130721|7.7.0.0|",
				"addressLine": "2178 Winchester Ct",
				"adminDistrict": "ON",
				"adminDistrict2": "Halton",
				"countryRegion": "Canada",
				"formattedAddress": "2178 Winchester Ct, Burlington, ON L7P 3K7, Canada",
				"locality": "Burlington",
				"neighborhood": "Tyandaga",
				"postalCode": "L7P 3K7"
			},
			"geometry": {
				"type": "Point",
				"coordinates": [
					-79.84656,
					43.35318
				]
			},
			"bbox": [
				-79.848106,
				43.3520558,
				-79.845014,
				43.3543042
			]
		}
	]
}
