{
	"type": "FeatureCollection",
	"features": [
		{
			"type": "Feature",
			"properties": {
				"confidence": 9,
				"authenticationResultCode": "ValidCredentials",
				"brandLogoUri": "http://dev.virtualearth.net/Branding/logo_powered_by.png",
				"copyright": "Copyright © 2017 Microsoft and its suppliers. All rights reserved. This API cannot be accessed and the content and any results may not be used, reproduced or transmitted in any manner without express written permission from Microsoft Corporation.",
				"entityType": "Address",
				"matchCodes": [
					"Good"
				],
				"name": "219 Herring Cove Rd, Halifax, NS B3P 1L3, Canada",
				"statusCode": 200,
				"statusDescription": "OK",
				"traceId": "add3cb69798441ce8f92ba3119a10592|BN20190642|7.7.0.0|",
				"addressLine": "219 Herring Cove Rd",
				"adminDistrict": "NS",
				"adminDistrict2": "Halifax",
				"countryRegion": "Canada",
				"formattedAddress": "219 Herring Cove Rd, Halifax, NS B3P 1L3, Canada",
				"locality": "Halifax",
				"postalCode": "B3P 1L3"
			},
			"geometry": {
				"type": "Point",
				"coordinates": [
					-63.61805,
					44.62244
				]
			},
			"bbox": [
				-63.6196294,
				44.6213158,
				-63.6164706,
				44.6235642
			]
		}
	]
}
