{
	"type": "FeatureCollection",
	"features": [
		{
			"type": "Feature",
			"properties": {
				"confidence": 7,
				"authenticationResultCode": "ValidCredentials",
				"brandLogoUri": "http://dev.virtualearth.net/Branding/logo_powered_by.png",
				"copyright": "Copyright © 2017 Microsoft and its suppliers. All rights reserved. This API cannot be accessed and the content and any results may not be used, reproduced or transmitted in any manner without express written permission from Microsoft Corporation.",
				"entityType": "Neighborhood",
				"matchCodes": [
					"UpHierarchy"
				],
				"name": "Claremont, Pickering, Ontario, Canada",
				"statusCode": 200,
				"statusDescription": "OK",
				"traceId": "23fbf1a8fb60408c9a0ec74630e0d7d2|BN20240423|7.7.0.0|",
				"adminDistrict": "ON",
				"adminDistrict2": "Durham",
				"countryRegion": "Canada",
				"formattedAddress": "Claremont, Pickering, Ontario, Canada",
				"locality": "Pickering",
				"neighborhood": "Claremont"
			},
			"geometry": {
				"type": "Point",
				"coordinates": [
					-79.1284713745117,
					43.9725189208984
				]
			},
			"bbox": [
				-79.1356273409968,
				43.9686562033278,
				-79.1213154080266,
				43.9763816384691
			]
		},
		{
			"type": "Feature",
			"properties": {
				"confidence": 7,
				"authenticationResultCode": "ValidCredentials",
				"brandLogoUri": "http://dev.virtualearth.net/Branding/logo_powered_by.png",
				"copyright": "Copyright © 2017 Microsoft and its suppliers. All rights reserved. This API cannot be accessed and the content and any results may not be used, reproduced or transmitted in any manner without express written permission from Microsoft Corporation.",
				"entityType": "PopulatedPlace",
				"matchCodes": [
					"UpHierarchy"
				],
				"name": "Claremont, Ontario, Canada",
				"statusCode": 200,
				"statusDescription": "OK",
				"traceId": "23fbf1a8fb60408c9a0ec74630e0d7d2|BN20240423|7.7.0.0|",
				"adminDistrict": "ON",
				"adminDistrict2": "Durham",
				"countryRegion": "Canada",
				"formattedAddress": "Claremont, Ontario, Canada",
				"locality": "Claremont"
			},
			"geometry": {
				"type": "Point",
				"coordinates": [
					-79.1291275024414,
					43.9705085754395
				]
			},
			"bbox": [
				-79.1353988647461,
				43.9644012451172,
				-79.1232681274414,
				43.976749420166
			]
		},
		{
			"type": "Feature",
			"properties": {
				"confidence": 7,
				"authenticationResultCode": "ValidCredentials",
				"brandLogoUri": "http://dev.virtualearth.net/Branding/logo_powered_by.png",
				"copyright": "Copyright © 2017 Microsoft and its suppliers. All rights reserved. This API cannot be accessed and the content and any results may not be used, reproduced or transmitted in any manner without express written permission from Microsoft Corporation.",
				"entityType": "Postcode1",
				"matchCodes": [
					"Ambiguous",
					"UpHierarchy"
				],
				"name": "Sydney, 2195, Australia",
				"statusCode": 200,
				"statusDescription": "OK",
				"traceId": "23fbf1a8fb60408c9a0ec74630e0d7d2|BN20240423|7.7.0.0|",
				"adminDistrict": "NSW",
				"countryRegion": "Australia",
				"formattedAddress": "Sydney, 2195, Australia",
				"locality": "Sydney",
				"postalCode": "2195"
			},
			"geometry": {
				"type": "Point",
				"coordinates": [
					151.072967529297,
					-33.9210243225098
				]
			},
			"bbox": [
				151.059387207031,
				-33.9312171936035,
				151.0869140625,
				-33.9077377319336
			]
		},
		{
			"type": "Feature",
			"properties": {
				"confidence": 5,
				"authenticationResultCode": "ValidCredentials",
				"brandLogoUri": "http://dev.virtualearth.net/Branding/logo_powered_by.png",
				"copyright": "Copyright © 2017 Microsoft and its suppliers. All rights reserved. This API cannot be accessed and the content and any results may not be used, reproduced or transmitted in any manner without express written permission from Microsoft Corporation.",
				"entityType": "Postcode1",
				"matchCodes": [
					"Ambiguous",
					"UpHierarchy"
				],
				"name": "Johannesburg, 2195, South Africa",
				"statusCode": 200,
				"statusDescription": "OK",
				"traceId": "23fbf1a8fb60408c9a0ec74630e0d7d2|BN20240423|7.7.0.0|",
				"adminDistrict": "Gauteng",
				"adminDistrict2": "Johannesburg",
				"countryRegion": "South Africa",
				"formattedAddress": "Johannesburg, 2195, South Africa",
				"locality": "Johannesburg",
				"postalCode": "2195"
			},
			"geometry": {
				"type": "Point",
				"coordinates": [
					27.9770240783691,
					-26.1459121704102
				]
			},
			"bbox": [
				27.9414691925049,
				-26.172815322876,
				28.0167255401611,
				-26.119010925293
			]
		}
	]
}
