{
	"type": "FeatureCollection",
	"features": [
		{
			"type": "Feature",
			"properties": {
				"confidence": 9,
				"authenticationResultCode": "ValidCredentials",
				"brandLogoUri": "http://dev.virtualearth.net/Branding/logo_powered_by.png",
				"copyright": "Copyright © 2017 Microsoft and its suppliers. All rights reserved. This API cannot be accessed and the content and any results may not be used, reproduced or transmitted in any manner without express written permission from Microsoft Corporation.",
				"entityType": "Address",
				"matchCodes": [
					"Good"
				],
				"name": "220 Rosemar Gdns, Richmond Hill, ON L4C 3Z9, Canada",
				"statusCode": 200,
				"statusDescription": "OK",
				"traceId": "9e449e2ebd174adc9edc6bfdc13de171|BN20200137|7.7.0.0|",
				"addressLine": "220 Rosemar Gdns",
				"adminDistrict": "ON",
				"adminDistrict2": "York",
				"countryRegion": "Canada",
				"formattedAddress": "220 Rosemar Gdns, Richmond Hill, ON L4C 3Z9, Canada",
				"locality": "Richmond Hill",
				"postalCode": "L4C 3Z9"
			},
			"geometry": {
				"type": "Point",
				"coordinates": [
					-79.44892,
					43.87525
				]
			},
			"bbox": [
				-79.4504795,
				43.8741258,
				-79.4473605,
				43.8763742
			]
		}
	]
}
