{
	"type": "FeatureCollection",
	"features": [
		{
			"type": "Feature",
			"properties": {
				"confidence": 9,
				"authenticationResultCode": "ValidCredentials",
				"brandLogoUri": "http://dev.virtualearth.net/Branding/logo_powered_by.png",
				"copyright": "Copyright © 2017 Microsoft and its suppliers. All rights reserved. This API cannot be accessed and the content and any results may not be used, reproduced or transmitted in any manner without express written permission from Microsoft Corporation.",
				"entityType": "Address",
				"matchCodes": [
					"Good"
				],
				"name": "2206 Anthony Ave, Ottawa, ON K2B 6V2, Canada",
				"statusCode": 200,
				"statusDescription": "OK",
				"traceId": "92878f6585a94d2caf824a2af13aa803|BN20130533|7.7.0.0|",
				"addressLine": "2206 Anthony Ave",
				"adminDistrict": "ON",
				"adminDistrict2": "Ottawa",
				"countryRegion": "Canada",
				"formattedAddress": "2206 Anthony Ave, Ottawa, ON K2B 6V2, Canada",
				"locality": "Ottawa",
				"neighborhood": "Carlingwood West-Glabar Park",
				"postalCode": "K2B 6V2"
			},
			"geometry": {
				"type": "Point",
				"coordinates": [
					-75.7749599,
					45.37518
				]
			},
			"bbox": [
				-75.7765602,
				45.3740558,
				-75.7733596,
				45.3763042
			]
		}
	]
}
