{
	"type": "FeatureCollection",
	"features": [
		{
			"type": "Feature",
			"properties": {
				"confidence": 9,
				"authenticationResultCode": "ValidCredentials",
				"brandLogoUri": "http://dev.virtualearth.net/Branding/logo_powered_by.png",
				"copyright": "Copyright © 2017 Microsoft and its suppliers. All rights reserved. This API cannot be accessed and the content and any results may not be used, reproduced or transmitted in any manner without express written permission from Microsoft Corporation.",
				"entityType": "Address",
				"matchCodes": [
					"Good"
				],
				"name": "221 Conception Bay Hwy, Conception Bay South, NL A1W 3H1, Canada",
				"statusCode": 200,
				"statusDescription": "OK",
				"traceId": "8bc3740e062647049e91588a8f35bfc7|BN20210145|7.7.0.0|",
				"addressLine": "221 Conception Bay Hwy",
				"adminDistrict": "NL",
				"adminDistrict2": "Newfoundland and Labrador",
				"countryRegion": "Canada",
				"formattedAddress": "221 Conception Bay Hwy, Conception Bay South, NL A1W 3H1, Canada",
				"locality": "Conception Bay South",
				"postalCode": "A1W 3H1"
			},
			"geometry": {
				"type": "Point",
				"coordinates": [
					-52.9649668,
					47.5146874
				]
			},
			"bbox": [
				-52.9666312,
				47.5135632,
				-52.9633023,
				47.5158115
			]
		}
	]
}
