{
	"type": "FeatureCollection",
	"features": [
		{
			"type": "Feature",
			"properties": {
				"confidence": 9,
				"authenticationResultCode": "ValidCredentials",
				"brandLogoUri": "http://dev.virtualearth.net/Branding/logo_powered_by.png",
				"copyright": "Copyright © 2017 Microsoft and its suppliers. All rights reserved. This API cannot be accessed and the content and any results may not be used, reproduced or transmitted in any manner without express written permission from Microsoft Corporation.",
				"entityType": "Address",
				"matchCodes": [
					"Good"
				],
				"name": "221 Magpie St, Gloucester, ON K1T 0N4, Canada",
				"statusCode": 200,
				"statusDescription": "OK",
				"traceId": "789953a057484f729e6f3a6175c20e7f|BN20260231|7.7.0.0|",
				"addressLine": "221 Magpie St",
				"adminDistrict": "ON",
				"adminDistrict2": "Ottawa",
				"countryRegion": "Canada",
				"formattedAddress": "221 Magpie St, Gloucester, ON K1T 0N4, Canada",
				"locality": "Ottawa",
				"neighborhood": "Gloucester",
				"postalCode": "K1T 0N4"
			},
			"geometry": {
				"type": "Point",
				"coordinates": [
					-75.5985045,
					45.3133156
				]
			},
			"bbox": [
				-75.6001031,
				45.3121915,
				-75.5969059,
				45.3144398
			]
		}
	]
}
