{
	"type": "FeatureCollection",
	"features": [
		{
			"type": "Feature",
			"properties": {
				"confidence": 9,
				"authenticationResultCode": "ValidCredentials",
				"brandLogoUri": "http://dev.virtualearth.net/Branding/logo_powered_by.png",
				"copyright": "Copyright © 2017 Microsoft and its suppliers. All rights reserved. This API cannot be accessed and the content and any results may not be used, reproduced or transmitted in any manner without express written permission from Microsoft Corporation.",
				"entityType": "Address",
				"matchCodes": [
					"Good"
				],
				"name": "222 Perehudoff Ct, Saskatoon, SK S7N 4H1, Canada",
				"statusCode": 200,
				"statusDescription": "OK",
				"traceId": "c52722c0d29f42568ed61575a21ccbc4|BN20130721|7.7.0.0|",
				"addressLine": "222 Perehudoff Ct",
				"adminDistrict": "SK",
				"adminDistrict2": "Saskatchewan",
				"countryRegion": "Canada",
				"formattedAddress": "222 Perehudoff Ct, Saskatoon, SK S7N 4H1, Canada",
				"locality": "Saskatoon",
				"neighborhood": "Erindale",
				"postalCode": "S7N 4H1"
			},
			"geometry": {
				"type": "Point",
				"coordinates": [
					-106.5659,
					52.14415
				]
			},
			"bbox": [
				-106.5677318,
				52.1430258,
				-106.5640682,
				52.1452742
			]
		}
	]
}
