{
	"type": "FeatureCollection",
	"features": [
		{
			"type": "Feature",
			"properties": {
				"confidence": 9,
				"authenticationResultCode": "ValidCredentials",
				"brandLogoUri": "http://dev.virtualearth.net/Branding/logo_powered_by.png",
				"copyright": "Copyright © 2017 Microsoft and its suppliers. All rights reserved. This API cannot be accessed and the content and any results may not be used, reproduced or transmitted in any manner without express written permission from Microsoft Corporation.",
				"entityType": "Address",
				"matchCodes": [
					"Good"
				],
				"name": "222 Limestone Cres, North York, ON M3J 2S4, Canada",
				"statusCode": 200,
				"statusDescription": "OK",
				"traceId": "11bdd1c83afc4b2bba09702c446a2b01|BN20200137|7.7.0.0|",
				"addressLine": "222 Limestone Cres",
				"adminDistrict": "ON",
				"adminDistrict2": "Toronto",
				"countryRegion": "Canada",
				"formattedAddress": "222 Limestone Cres, North York, ON M3J 2S4, Canada",
				"locality": "Toronto",
				"neighborhood": "York University Heights",
				"postalCode": "M3J 2S4"
			},
			"geometry": {
				"type": "Point",
				"coordinates": [
					-79.48562,
					43.78093
				]
			},
			"bbox": [
				-79.487177,
				43.7798058,
				-79.484063,
				43.7820542
			]
		}
	]
}
