{
	"type": "FeatureCollection",
	"features": [
		{
			"type": "Feature",
			"properties": {
				"confidence": 9,
				"authenticationResultCode": "ValidCredentials",
				"brandLogoUri": "http://dev.virtualearth.net/Branding/logo_powered_by.png",
				"copyright": "Copyright © 2017 Microsoft and its suppliers. All rights reserved. This API cannot be accessed and the content and any results may not be used, reproduced or transmitted in any manner without express written permission from Microsoft Corporation.",
				"entityType": "Address",
				"matchCodes": [
					"Good"
				],
				"name": "2228 Linea Cres, Lumby, BC V0E, Canada",
				"statusCode": 200,
				"statusDescription": "OK",
				"traceId": "ff1758ac4702415bb9f28f31a73ecb3e|BN20130422|7.7.0.0|",
				"addressLine": "2228 Linea Cres",
				"adminDistrict": "BC",
				"adminDistrict2": "North Okanagan",
				"countryRegion": "Canada",
				"formattedAddress": "2228 Linea Cres, Lumby, BC V0E, Canada",
				"locality": "Lumby",
				"postalCode": "V0E 2G0"
			},
			"geometry": {
				"type": "Point",
				"coordinates": [
					-118.97119,
					50.25107
				]
			},
			"bbox": [
				-118.9729481,
				50.2499458,
				-118.9694319,
				50.2521942
			]
		}
	]
}
