{
	"type": "FeatureCollection",
	"features": [
		{
			"type": "Feature",
			"properties": {
				"confidence": 9,
				"authenticationResultCode": "ValidCredentials",
				"brandLogoUri": "http://dev.virtualearth.net/Branding/logo_powered_by.png",
				"copyright": "Copyright © 2017 Microsoft and its suppliers. All rights reserved. This API cannot be accessed and the content and any results may not be used, reproduced or transmitted in any manner without express written permission from Microsoft Corporation.",
				"entityType": "Address",
				"matchCodes": [
					"Good"
				],
				"name": "223 Corbett Dr, Kawartha Lakes, ON L0A, Canada",
				"statusCode": 200,
				"statusDescription": "OK",
				"traceId": "62da712c254a465ab11f5599eaf5970f|BN20130521|7.7.0.0|",
				"addressLine": "223 Corbett Dr",
				"adminDistrict": "ON",
				"adminDistrict2": "Kawartha Lakes",
				"countryRegion": "Canada",
				"formattedAddress": "223 Corbett Dr, Kawartha Lakes, ON L0A, Canada",
				"locality": "Kawartha Lakes",
				"neighborhood": "Pontypool",
				"postalCode": "L0A 1K0"
			},
			"geometry": {
				"type": "Point",
				"coordinates": [
					-78.63601,
					44.11141
				]
			},
			"bbox": [
				-78.6375757,
				44.1102858,
				-78.6344443,
				44.1125342
			]
		}
	]
}
