{
	"type": "FeatureCollection",
	"features": [
		{
			"type": "Feature",
			"properties": {
				"confidence": 8,
				"authenticationResultCode": "ValidCredentials",
				"brandLogoUri": "http://dev.virtualearth.net/Branding/logo_powered_by.png",
				"copyright": "Copyright © 2017 Microsoft and its suppliers. All rights reserved. This API cannot be accessed and the content and any results may not be used, reproduced or transmitted in any manner without express written permission from Microsoft Corporation.",
				"entityType": "RoadBlock",
				"matchCodes": [
					"UpHierarchy"
				],
				"name": "Blackfoot Trl SE, Calgary, AB T2G 5C5, Canada",
				"statusCode": 200,
				"statusDescription": "OK",
				"traceId": "192c7dc62dfd409ea4c63b3baa6a858d|BN20130719|7.7.0.0|",
				"addressLine": "Blackfoot Trl SE",
				"adminDistrict": "AB",
				"adminDistrict2": "Alberta",
				"countryRegion": "Canada",
				"formattedAddress": "Blackfoot Trl SE, Calgary, AB T2G 5C5, Canada",
				"locality": "Calgary",
				"neighborhood": "Inglewood",
				"postalCode": "T2G 5C5"
			},
			"geometry": {
				"type": "Point",
				"coordinates": [
					-114.0247752,
					51.0346395
				]
			},
			"bbox": [
				-114.02539,
				51.03399,
				-114.01371,
				51.03779
			]
		}
	]
}
