{
	"type": "FeatureCollection",
	"features": [
		{
			"type": "Feature",
			"properties": {
				"confidence": 9,
				"authenticationResultCode": "ValidCredentials",
				"brandLogoUri": "http://dev.virtualearth.net/Branding/logo_powered_by.png",
				"copyright": "Copyright © 2017 Microsoft and its suppliers. All rights reserved. This API cannot be accessed and the content and any results may not be used, reproduced or transmitted in any manner without express written permission from Microsoft Corporation.",
				"entityType": "Address",
				"matchCodes": [
					"Good"
				],
				"name": "224 Edforth Pl NW, Calgary, AB T3A 3V9, Canada",
				"statusCode": 200,
				"statusDescription": "OK",
				"traceId": "c8a344c10f62404584207d56329a6424|BN20121763|7.7.0.0|",
				"addressLine": "224 Edforth Pl NW",
				"adminDistrict": "AB",
				"adminDistrict2": "Alberta",
				"countryRegion": "Canada",
				"formattedAddress": "224 Edforth Pl NW, Calgary, AB T3A 3V9, Canada",
				"locality": "Calgary",
				"neighborhood": "Edgemont",
				"postalCode": "T3A 3V9"
			},
			"geometry": {
				"type": "Point",
				"coordinates": [
					-114.14178,
					51.12694
				]
			},
			"bbox": [
				-114.1435712,
				51.1258158,
				-114.1399888,
				51.1280642
			]
		}
	]
}
