{
	"type": "FeatureCollection",
	"features": [
		{
			"type": "Feature",
			"properties": {
				"confidence": 9,
				"authenticationResultCode": "ValidCredentials",
				"brandLogoUri": "http://dev.virtualearth.net/Branding/logo_powered_by.png",
				"copyright": "Copyright © 2017 Microsoft and its suppliers. All rights reserved. This API cannot be accessed and the content and any results may not be used, reproduced or transmitted in any manner without express written permission from Microsoft Corporation.",
				"entityType": "Address",
				"matchCodes": [
					"Good"
				],
				"name": "2243 W 47th Ave, Vancouver, BC V6M 2M8, Canada",
				"statusCode": 200,
				"statusDescription": "OK",
				"traceId": "498d36db28d54690868c805b4594b32d|BN20290118|7.7.0.0|",
				"addressLine": "2243 W 47th Ave",
				"adminDistrict": "BC",
				"adminDistrict2": "Greater Vancouver",
				"countryRegion": "Canada",
				"formattedAddress": "2243 W 47th Ave, Vancouver, BC V6M 2M8, Canada",
				"locality": "Vancouver",
				"neighborhood": "Kerrisdale",
				"postalCode": "V6M 2M8"
			},
			"geometry": {
				"type": "Point",
				"coordinates": [
					-123.15938,
					49.2293
				]
			},
			"bbox": [
				-123.1611014,
				49.2281758,
				-123.1576586,
				49.2304242
			]
		}
	]
}
