{
	"type": "FeatureCollection",
	"features": [
		{
			"type": "Feature",
			"properties": {
				"confidence": 9,
				"authenticationResultCode": "ValidCredentials",
				"brandLogoUri": "http://dev.virtualearth.net/Branding/logo_powered_by.png",
				"copyright": "Copyright © 2017 Microsoft and its suppliers. All rights reserved. This API cannot be accessed and the content and any results may not be used, reproduced or transmitted in any manner without express written permission from Microsoft Corporation.",
				"entityType": "Address",
				"matchCodes": [
					"Good"
				],
				"name": "22444 Lougheed Hwy, Maple Ridge, BC V2X 2T6, Canada",
				"statusCode": 200,
				"statusDescription": "OK",
				"traceId": "8069ce881cbc4a778da1e839406dffae|BN20130431|7.7.0.0|",
				"addressLine": "22444 Lougheed Hwy",
				"adminDistrict": "BC",
				"adminDistrict2": "Greater Vancouver",
				"countryRegion": "Canada",
				"formattedAddress": "22444 Lougheed Hwy, Maple Ridge, BC V2X 2T6, Canada",
				"locality": "Maple Ridge",
				"postalCode": "V2X 2T6"
			},
			"geometry": {
				"type": "Point",
				"coordinates": [
					-122.60045,
					49.21678
				]
			},
			"bbox": [
				-122.602171,
				49.2156558,
				-122.598729,
				49.2179042
			]
		}
	]
}
