{
	"type": "FeatureCollection",
	"features": [
		{
			"type": "Feature",
			"properties": {
				"confidence": 9,
				"authenticationResultCode": "ValidCredentials",
				"brandLogoUri": "http://dev.virtualearth.net/Branding/logo_powered_by.png",
				"copyright": "Copyright © 2017 Microsoft and its suppliers. All rights reserved. This API cannot be accessed and the content and any results may not be used, reproduced or transmitted in any manner without express written permission from Microsoft Corporation.",
				"entityType": "Address",
				"matchCodes": [
					"Good"
				],
				"name": "2260 Argentia Rd, Mississauga, ON L5N 6H7, Canada",
				"statusCode": 200,
				"statusDescription": "OK",
				"traceId": "0956746ba8b74ee288117ac9d2742956|BN20130423|7.7.0.0|",
				"addressLine": "2260 Argentia Rd",
				"adminDistrict": "ON",
				"adminDistrict2": "Peel",
				"countryRegion": "Canada",
				"formattedAddress": "2260 Argentia Rd, Mississauga, ON L5N 6H7, Canada",
				"locality": "Mississauga",
				"neighborhood": "Meadowvale",
				"postalCode": "L5N 6H7"
			},
			"geometry": {
				"type": "Point",
				"coordinates": [
					-79.7487938,
					43.5985514
				]
			},
			"bbox": [
				-79.7503461,
				43.5974272,
				-79.7472415,
				43.5996755
			]
		}
	]
}
