{
	"type": "FeatureCollection",
	"features": [
		{
			"type": "Feature",
			"properties": {
				"confidence": 9,
				"authenticationResultCode": "ValidCredentials",
				"brandLogoUri": "http://dev.virtualearth.net/Branding/logo_powered_by.png",
				"copyright": "Copyright © 2017 Microsoft and its suppliers. All rights reserved. This API cannot be accessed and the content and any results may not be used, reproduced or transmitted in any manner without express written permission from Microsoft Corporation.",
				"entityType": "Address",
				"matchCodes": [
					"Good"
				],
				"name": "2275 Rue de la Province, Longueuil, QC J4G 1G3, Canada",
				"statusCode": 200,
				"statusDescription": "OK",
				"traceId": "f2b8e60c21fa4b4283eafff7bc6fff29|BN20200239|7.7.0.0|",
				"addressLine": "2275 Rue de la Province",
				"adminDistrict": "QC",
				"adminDistrict2": "Longueuil",
				"countryRegion": "Canada",
				"formattedAddress": "2275 Rue de la Province, Longueuil, QC J4G 1G3, Canada",
				"locality": "Longueuil",
				"postalCode": "J4G 1G3"
			},
			"geometry": {
				"type": "Point",
				"coordinates": [
					-73.46711,
					45.5681
				]
			},
			"bbox": [
				-73.4687158,
				45.5669758,
				-73.4655042,
				45.5692242
			]
		}
	]
}
