{
	"type": "FeatureCollection",
	"features": [
		{
			"type": "Feature",
			"properties": {
				"confidence": 9,
				"authenticationResultCode": "ValidCredentials",
				"brandLogoUri": "http://dev.virtualearth.net/Branding/logo_powered_by.png",
				"copyright": "Copyright © 2017 Microsoft and its suppliers. All rights reserved. This API cannot be accessed and the content and any results may not be used, reproduced or transmitted in any manner without express written permission from Microsoft Corporation.",
				"entityType": "Address",
				"matchCodes": [
					"Good"
				],
				"name": "228 Manitoba Ave, Selkirk, MB R1A 0Y5, Canada",
				"statusCode": 200,
				"statusDescription": "OK",
				"traceId": "9cf082e6e7124551a708c9614c41f809|BN20130621|7.7.0.0|",
				"addressLine": "228 Manitoba Ave",
				"adminDistrict": "MB",
				"adminDistrict2": "Manitoba",
				"countryRegion": "Canada",
				"formattedAddress": "228 Manitoba Ave, Selkirk, MB R1A 0Y5, Canada",
				"locality": "Selkirk",
				"postalCode": "R1A 0Y5"
			},
			"geometry": {
				"type": "Point",
				"coordinates": [
					-96.8703002,
					50.1439891
				]
			},
			"bbox": [
				-96.8720543,
				50.142865,
				-96.868546,
				50.1451133
			]
		}
	]
}
