{
	"type": "FeatureCollection",
	"features": [
		{
			"type": "Feature",
			"properties": {
				"confidence": 9,
				"authenticationResultCode": "ValidCredentials",
				"brandLogoUri": "http://dev.virtualearth.net/Branding/logo_powered_by.png",
				"copyright": "Copyright © 2017 Microsoft and its suppliers. All rights reserved. This API cannot be accessed and the content and any results may not be used, reproduced or transmitted in any manner without express written permission from Microsoft Corporation.",
				"entityType": "Address",
				"matchCodes": [
					"Good"
				],
				"name": "2291 Lasalle Blvd, Sudbury, ON P3A 2A9, Canada",
				"statusCode": 200,
				"statusDescription": "OK",
				"traceId": "7b67679705614d94a2856a05cdd8ccc2|BN20260223|7.7.0.0|",
				"addressLine": "2291 Lasalle Blvd",
				"adminDistrict": "ON",
				"adminDistrict2": "Greater Sudbury",
				"countryRegion": "Canada",
				"formattedAddress": "2291 Lasalle Blvd, Sudbury, ON P3A 2A9, Canada",
				"locality": "Greater Sudbury",
				"neighborhood": "Sudbury",
				"postalCode": "P3A 2A9"
			},
			"geometry": {
				"type": "Point",
				"coordinates": [
					-80.9155,
					46.52141
				]
			},
			"bbox": [
				-80.9171337,
				46.5202858,
				-80.9138663,
				46.5225342
			]
		}
	]
}
