{
	"type": "FeatureCollection",
	"features": [
		{
			"type": "Feature",
			"properties": {
				"confidence": 9,
				"authenticationResultCode": "ValidCredentials",
				"brandLogoUri": "http://dev.virtualearth.net/Branding/logo_powered_by.png",
				"copyright": "Copyright © 2017 Microsoft and its suppliers. All rights reserved. This API cannot be accessed and the content and any results may not be used, reproduced or transmitted in any manner without express written permission from Microsoft Corporation.",
				"entityType": "Address",
				"matchCodes": [
					"Good"
				],
				"name": "23 Burma Rd, Lunenburg, NS B0J, Canada",
				"statusCode": 200,
				"statusDescription": "OK",
				"traceId": "42b1038ed7ea4dc0a34d51623d666d2d|BN20130625|7.7.0.0|",
				"addressLine": "23 Burma Rd",
				"adminDistrict": "NS",
				"adminDistrict2": "Lunenburg",
				"countryRegion": "Canada",
				"formattedAddress": "23 Burma Rd, Lunenburg, NS B0J, Canada",
				"locality": "Lunenburg",
				"postalCode": "B0J 2C0"
			},
			"geometry": {
				"type": "Point",
				"coordinates": [
					-64.30262,
					44.37514
				]
			},
			"bbox": [
				-64.3041927,
				44.3740158,
				-64.3010473,
				44.3762642
			]
		}
	]
}
