{
	"type": "FeatureCollection",
	"features": [
		{
			"type": "Feature",
			"properties": {
				"confidence": 9,
				"authenticationResultCode": "ValidCredentials",
				"brandLogoUri": "http://dev.virtualearth.net/Branding/logo_powered_by.png",
				"copyright": "Copyright © 2017 Microsoft and its suppliers. All rights reserved. This API cannot be accessed and the content and any results may not be used, reproduced or transmitted in any manner without express written permission from Microsoft Corporation.",
				"entityType": "Address",
				"matchCodes": [
					"Good"
				],
				"name": "23 Rue Harold, Kirkland, QC H9J 1R7, Canada",
				"statusCode": 200,
				"statusDescription": "OK",
				"traceId": "be114022ca294451b9f8c90433f8284e|BN20171457|7.7.0.0|",
				"addressLine": "23 Rue Harold",
				"adminDistrict": "QC",
				"adminDistrict2": "Montreal",
				"countryRegion": "Canada",
				"formattedAddress": "23 Rue Harold, Kirkland, QC H9J 1R7, Canada",
				"locality": "Kirkland",
				"postalCode": "H9J 1R7"
			},
			"geometry": {
				"type": "Point",
				"coordinates": [
					-73.85866,
					45.44462
				]
			},
			"bbox": [
				-73.8602623,
				45.4434958,
				-73.8570577,
				45.4457442
			]
		}
	]
}
