{
	"type": "FeatureCollection",
	"features": [
		{
			"type": "Feature",
			"properties": {
				"confidence": 9,
				"authenticationResultCode": "ValidCredentials",
				"brandLogoUri": "http://dev.virtualearth.net/Branding/logo_powered_by.png",
				"copyright": "Copyright © 2017 Microsoft and its suppliers. All rights reserved. This API cannot be accessed and the content and any results may not be used, reproduced or transmitted in any manner without express written permission from Microsoft Corporation.",
				"entityType": "Address",
				"matchCodes": [
					"Good"
				],
				"name": "23 Target Hill Rd, Chester, NS B0J, Canada",
				"statusCode": 200,
				"statusDescription": "OK",
				"traceId": "3a58579434b14b5fb27884f4613df929|BN20181720|7.7.0.0|",
				"addressLine": "23 Target Hill Rd",
				"adminDistrict": "NS",
				"adminDistrict2": "Lunenburg",
				"countryRegion": "Canada",
				"formattedAddress": "23 Target Hill Rd, Chester, NS B0J, Canada",
				"locality": "Chester",
				"postalCode": "B0J 1J0"
			},
			"geometry": {
				"type": "Point",
				"coordinates": [
					-64.23602,
					44.5491699
				]
			},
			"bbox": [
				-64.2375974,
				44.5480457,
				-64.2344426,
				44.5502941
			]
		}
	]
}
