{
	"type": "FeatureCollection",
	"features": [
		{
			"type": "Feature",
			"properties": {
				"confidence": 9,
				"authenticationResultCode": "ValidCredentials",
				"brandLogoUri": "http://dev.virtualearth.net/Branding/logo_powered_by.png",
				"copyright": "Copyright © 2017 Microsoft and its suppliers. All rights reserved. This API cannot be accessed and the content and any results may not be used, reproduced or transmitted in any manner without express written permission from Microsoft Corporation.",
				"entityType": "Address",
				"matchCodes": [
					"Good"
				],
				"name": "230 Rue Principale, Senneterre, QC J0Y 2M0, Canada",
				"statusCode": 200,
				"statusDescription": "OK",
				"traceId": "fe90c9b0975d4d1e958797b7464c37e7|BN20130721|7.7.0.0|",
				"addressLine": "230 Rue Principale",
				"adminDistrict": "QC",
				"adminDistrict2": "La Vallée-de-l'Or",
				"countryRegion": "Canada",
				"formattedAddress": "230 Rue Principale, Senneterre, QC J0Y 2M0, Canada",
				"locality": "Senneterre",
				"postalCode": "J0Y 2M0"
			},
			"geometry": {
				"type": "Point",
				"coordinates": [
					-77.23527,
					48.39158
				]
			},
			"bbox": [
				-77.2369629,
				48.3904558,
				-77.2335771,
				48.3927042
			]
		}
	]
}
