{
	"type": "FeatureCollection",
	"features": [
		{
			"type": "Feature",
			"properties": {
				"confidence": 9,
				"authenticationResultCode": "ValidCredentials",
				"brandLogoUri": "http://dev.virtualearth.net/Branding/logo_powered_by.png",
				"copyright": "Copyright © 2017 Microsoft and its suppliers. All rights reserved. This API cannot be accessed and the content and any results may not be used, reproduced or transmitted in any manner without express written permission from Microsoft Corporation.",
				"entityType": "Address",
				"matchCodes": [
					"Good"
				],
				"name": "2319 23 Ave SW, Calgary, AB T2T 0W3, Canada",
				"statusCode": 200,
				"statusDescription": "OK",
				"traceId": "b9c1d8c417e74a21803b08caa99ccccd|BN20130447|7.7.0.0|",
				"addressLine": "2319 23 Ave SW",
				"adminDistrict": "AB",
				"adminDistrict2": "Alberta",
				"countryRegion": "Canada",
				"formattedAddress": "2319 23 Ave SW, Calgary, AB T2T 0W3, Canada",
				"locality": "Calgary",
				"neighborhood": "Richmond",
				"postalCode": "T2T 0W3"
			},
			"geometry": {
				"type": "Point",
				"coordinates": [
					-114.1148,
					51.03267
				]
			},
			"bbox": [
				-114.1165876,
				51.0315458,
				-114.1130124,
				51.0337942
			]
		}
	]
}
