{
	"type": "FeatureCollection",
	"features": [
		{
			"type": "Feature",
			"properties": {
				"confidence": 9,
				"authenticationResultCode": "ValidCredentials",
				"brandLogoUri": "http://dev.virtualearth.net/Branding/logo_powered_by.png",
				"copyright": "Copyright © 2017 Microsoft and its suppliers. All rights reserved. This API cannot be accessed and the content and any results may not be used, reproduced or transmitted in any manner without express written permission from Microsoft Corporation.",
				"entityType": "Address",
				"matchCodes": [
					"Good"
				],
				"name": "2330 Huron Church Rd, Windsor, ON N9E 3S6, Canada",
				"statusCode": 200,
				"statusDescription": "OK",
				"traceId": "45ebfe224c9f4d09b88bba0cae41ab18|BN20130520|7.7.0.0|",
				"addressLine": "2330 Huron Church Rd",
				"adminDistrict": "ON",
				"adminDistrict2": "Essex",
				"countryRegion": "Canada",
				"formattedAddress": "2330 Huron Church Rd, Windsor, ON N9E 3S6, Canada",
				"locality": "Windsor",
				"neighborhood": "South Cameron",
				"postalCode": "N9E 3S6"
			},
			"geometry": {
				"type": "Point",
				"coordinates": [
					-83.04797,
					42.27317
				]
			},
			"bbox": [
				-83.0494892,
				42.2720458,
				-83.0464508,
				42.2742942
			]
		}
	]
}
