{
	"type": "FeatureCollection",
	"features": [
		{
			"type": "Feature",
			"properties": {
				"confidence": 9,
				"authenticationResultCode": "ValidCredentials",
				"brandLogoUri": "http://dev.virtualearth.net/Branding/logo_powered_by.png",
				"copyright": "Copyright © 2017 Microsoft and its suppliers. All rights reserved. This API cannot be accessed and the content and any results may not be used, reproduced or transmitted in any manner without express written permission from Microsoft Corporation.",
				"entityType": "Address",
				"matchCodes": [
					"Good"
				],
				"name": "2334 RTE-132 E, Rimouski, QC G0L 1B0, Canada",
				"statusCode": 200,
				"statusDescription": "OK",
				"traceId": "18f78f378150412e84eab449d616cfc8|BN20190653|7.7.0.0|",
				"addressLine": "2334 RTE-132 E",
				"adminDistrict": "QC",
				"adminDistrict2": "Rimouski-Neigette",
				"countryRegion": "Canada",
				"formattedAddress": "2334 RTE-132 E, Rimouski, QC G0L 1B0, Canada",
				"locality": "Rimouski",
				"neighborhood": "Le Bic",
				"postalCode": "G0L 1B0"
			},
			"geometry": {
				"type": "Point",
				"coordinates": [
					-68.6679166,
					48.3925524
				]
			},
			"bbox": [
				-68.6696096,
				48.3914282,
				-68.6662237,
				48.3936765
			]
		}
	]
}
