{
	"type": "FeatureCollection",
	"features": [
		{
			"type": "Feature",
			"properties": {
				"confidence": 9,
				"authenticationResultCode": "ValidCredentials",
				"brandLogoUri": "http://dev.virtualearth.net/Branding/logo_powered_by.png",
				"copyright": "Copyright © 2017 Microsoft and its suppliers. All rights reserved. This API cannot be accessed and the content and any results may not be used, reproduced or transmitted in any manner without express written permission from Microsoft Corporation.",
				"entityType": "Address",
				"matchCodes": [
					"Good"
				],
				"name": "2345 Matheson Blvd E, Mississauga, ON L4W 5B3, Canada",
				"statusCode": 200,
				"statusDescription": "OK",
				"traceId": "64b43f3ddfe541ecadbd9f7659acf524|BN20130447|7.7.0.0|",
				"addressLine": "2345 Matheson Blvd E",
				"adminDistrict": "ON",
				"adminDistrict2": "Peel",
				"countryRegion": "Canada",
				"formattedAddress": "2345 Matheson Blvd E, Mississauga, ON L4W 5B3, Canada",
				"locality": "Mississauga",
				"neighborhood": "Dixie",
				"postalCode": "L4W 5B3"
			},
			"geometry": {
				"type": "Point",
				"coordinates": [
					-79.60548,
					43.65533
				]
			},
			"bbox": [
				-79.6070338,
				43.6542058,
				-79.6039262,
				43.6564542
			]
		}
	]
}
