{
	"type": "FeatureCollection",
	"features": [
		{
			"type": "Feature",
			"properties": {
				"confidence": 9,
				"authenticationResultCode": "ValidCredentials",
				"brandLogoUri": "http://dev.virtualearth.net/Branding/logo_powered_by.png",
				"copyright": "Copyright © 2017 Microsoft and its suppliers. All rights reserved. This API cannot be accessed and the content and any results may not be used, reproduced or transmitted in any manner without express written permission from Microsoft Corporation.",
				"entityType": "Address",
				"matchCodes": [
					"Good"
				],
				"name": "235 Adventure Rd, Kelowna, BC V1X 1N5, Canada",
				"statusCode": 200,
				"statusDescription": "OK",
				"traceId": "e9d5460911de4b17aedc197d984d2b01|BN20181720|7.7.0.0|",
				"addressLine": "235 Adventure Rd",
				"adminDistrict": "BC",
				"adminDistrict2": "Central Okanagan",
				"countryRegion": "Canada",
				"formattedAddress": "235 Adventure Rd, Kelowna, BC V1X 1N5, Canada",
				"locality": "Kelowna",
				"neighborhood": "Rutland",
				"postalCode": "V1X 1N5"
			},
			"geometry": {
				"type": "Point",
				"coordinates": [
					-119.38991,
					49.8838
				]
			},
			"bbox": [
				-119.3916547,
				49.8826758,
				-119.3881653,
				49.8849242
			]
		}
	]
}
