{
	"type": "FeatureCollection",
	"features": [
		{
			"type": "Feature",
			"properties": {
				"confidence": 9,
				"authenticationResultCode": "ValidCredentials",
				"brandLogoUri": "http://dev.virtualearth.net/Branding/logo_powered_by.png",
				"copyright": "Copyright © 2017 Microsoft and its suppliers. All rights reserved. This API cannot be accessed and the content and any results may not be used, reproduced or transmitted in any manner without express written permission from Microsoft Corporation.",
				"entityType": "Address",
				"matchCodes": [
					"Good"
				],
				"name": "2355 Rue King O, Sherbrooke, QC J1J 2G6, Canada",
				"statusCode": 200,
				"statusDescription": "OK",
				"traceId": "0c4fa2775cee49eea4117ae18ff4d125|BN20260223|7.7.0.0|",
				"addressLine": "2355 Rue King O",
				"adminDistrict": "QC",
				"adminDistrict2": "Sherbrooke",
				"countryRegion": "Canada",
				"formattedAddress": "2355 Rue King O, Sherbrooke, QC J1J 2G6, Canada",
				"locality": "Sherbrooke",
				"postalCode": "J1J 2G6"
			},
			"geometry": {
				"type": "Point",
				"coordinates": [
					-71.9304496,
					45.3985849
				]
			},
			"bbox": [
				-71.9320506,
				45.3974607,
				-71.9288486,
				45.399709
			]
		}
	]
}
