{
	"type": "FeatureCollection",
	"features": [
		{
			"type": "Feature",
			"properties": {
				"confidence": 9,
				"authenticationResultCode": "ValidCredentials",
				"brandLogoUri": "http://dev.virtualearth.net/Branding/logo_powered_by.png",
				"copyright": "Copyright © 2017 Microsoft and its suppliers. All rights reserved. This API cannot be accessed and the content and any results may not be used, reproduced or transmitted in any manner without express written permission from Microsoft Corporation.",
				"entityType": "Address",
				"matchCodes": [
					"Good"
				],
				"name": "236 Highland Ave, Fort Erie, ON L2A 2X7, Canada",
				"statusCode": 200,
				"statusDescription": "OK",
				"traceId": "e4319b1c0465465ba354ee3d3b2f0644|BN20320521|7.7.0.0|",
				"addressLine": "236 Highland Ave",
				"adminDistrict": "ON",
				"adminDistrict2": "Niagara",
				"countryRegion": "Canada",
				"formattedAddress": "236 Highland Ave, Fort Erie, ON L2A 2X7, Canada",
				"locality": "Fort Erie",
				"postalCode": "L2A 2X7"
			},
			"geometry": {
				"type": "Point",
				"coordinates": [
					-78.92164,
					42.9343999
				]
			},
			"bbox": [
				-78.9231754,
				42.9332757,
				-78.9201046,
				42.9355241
			]
		}
	]
}
