{
	"type": "FeatureCollection",
	"features": [
		{
			"type": "Feature",
			"properties": {
				"confidence": 9,
				"authenticationResultCode": "ValidCredentials",
				"brandLogoUri": "http://dev.virtualearth.net/Branding/logo_powered_by.png",
				"copyright": "Copyright © 2017 Microsoft and its suppliers. All rights reserved. This API cannot be accessed and the content and any results may not be used, reproduced or transmitted in any manner without express written permission from Microsoft Corporation.",
				"entityType": "Address",
				"matchCodes": [
					"Good"
				],
				"name": "237 Carlton St, Toronto, ON M5A 2L2, Canada",
				"statusCode": 200,
				"statusDescription": "OK",
				"traceId": "4268fa9bfd7b43f5a5fdc39fa139b91b|BN20121762|7.7.0.0|",
				"addressLine": "237 Carlton St",
				"adminDistrict": "ON",
				"adminDistrict2": "Toronto",
				"countryRegion": "Canada",
				"formattedAddress": "237 Carlton St, Toronto, ON M5A 2L2, Canada",
				"locality": "Toronto",
				"neighborhood": "Moss Park",
				"postalCode": "M5A 2L2"
			},
			"geometry": {
				"type": "Point",
				"coordinates": [
					-79.36827,
					43.66404
				]
			},
			"bbox": [
				-79.369824,
				43.6629158,
				-79.366716,
				43.6651642
			]
		}
	]
}
