{
	"type": "FeatureCollection",
	"features": [
		{
			"type": "Feature",
			"properties": {
				"confidence": 9,
				"authenticationResultCode": "ValidCredentials",
				"brandLogoUri": "http://dev.virtualearth.net/Branding/logo_powered_by.png",
				"copyright": "Copyright © 2017 Microsoft and its suppliers. All rights reserved. This API cannot be accessed and the content and any results may not be used, reproduced or transmitted in any manner without express written permission from Microsoft Corporation.",
				"entityType": "Address",
				"matchCodes": [
					"Good"
				],
				"name": "237 Jarrett Xing, Milton, ON L9T 7A1, Canada",
				"statusCode": 200,
				"statusDescription": "OK",
				"traceId": "2f6e6e38efb84566ad928b11a336c634|BN20130533|7.7.0.0|",
				"addressLine": "237 Jarrett Xing",
				"adminDistrict": "ON",
				"adminDistrict2": "Halton",
				"countryRegion": "Canada",
				"formattedAddress": "237 Jarrett Xing, Milton, ON L9T 7A1, Canada",
				"locality": "Milton",
				"postalCode": "L9T 7A1"
			},
			"geometry": {
				"type": "Point",
				"coordinates": [
					-79.8842333,
					43.4992871
				]
			},
			"bbox": [
				-79.885783,
				43.4981629,
				-79.8826835,
				43.5004112
			]
		}
	]
}
