{
	"type": "FeatureCollection",
	"features": [
		{
			"type": "Feature",
			"properties": {
				"confidence": 9,
				"authenticationResultCode": "ValidCredentials",
				"brandLogoUri": "http://dev.virtualearth.net/Branding/logo_powered_by.png",
				"copyright": "Copyright © 2017 Microsoft and its suppliers. All rights reserved. This API cannot be accessed and the content and any results may not be used, reproduced or transmitted in any manner without express written permission from Microsoft Corporation.",
				"entityType": "Address",
				"matchCodes": [
					"Good"
				],
				"name": "23712 River Rd, Maple Ridge, BC V2W 1B7, Canada",
				"statusCode": 200,
				"statusDescription": "OK",
				"traceId": "e23b4fb644d0424e8bc9540817fb10a8|BN20130530|7.7.0.0|",
				"addressLine": "23712 River Rd",
				"adminDistrict": "BC",
				"adminDistrict2": "Greater Vancouver",
				"countryRegion": "Canada",
				"formattedAddress": "23712 River Rd, Maple Ridge, BC V2W 1B7, Canada",
				"locality": "Maple Ridge",
				"postalCode": "V2W 1B7"
			},
			"geometry": {
				"type": "Point",
				"coordinates": [
					-122.56477,
					49.1848
				]
			},
			"bbox": [
				-122.5664899,
				49.1836758,
				-122.5630501,
				49.1859242
			]
		}
	]
}
