{
	"type": "FeatureCollection",
	"features": [
		{
			"type": "Feature",
			"properties": {
				"confidence": 9,
				"authenticationResultCode": "ValidCredentials",
				"brandLogoUri": "http://dev.virtualearth.net/Branding/logo_powered_by.png",
				"copyright": "Copyright © 2017 Microsoft and its suppliers. All rights reserved. This API cannot be accessed and the content and any results may not be used, reproduced or transmitted in any manner without express written permission from Microsoft Corporation.",
				"entityType": "Address",
				"matchCodes": [
					"Good"
				],
				"name": "2372 Dobbin Rd, West Kelowna, BC V4T 2H9, Canada",
				"statusCode": 200,
				"statusDescription": "OK",
				"traceId": "be9aa3f3f9324ed582c8bfcf50c3f302|BN20260223|7.7.0.0|",
				"addressLine": "2372 Dobbin Rd",
				"adminDistrict": "BC",
				"adminDistrict2": "Central Okanagan",
				"countryRegion": "Canada",
				"formattedAddress": "2372 Dobbin Rd, West Kelowna, BC V4T 2H9, Canada",
				"locality": "West Kelowna",
				"neighborhood": "Westbank",
				"postalCode": "V4T 2H9"
			},
			"geometry": {
				"type": "Point",
				"coordinates": [
					-119.6245718,
					49.8288381
				]
			},
			"bbox": [
				-119.6263145,
				49.8277139,
				-119.6228291,
				49.8299622
			]
		}
	]
}
