{
	"type": "FeatureCollection",
	"features": [
		{
			"type": "Feature",
			"properties": {
				"confidence": 9,
				"authenticationResultCode": "ValidCredentials",
				"brandLogoUri": "http://dev.virtualearth.net/Branding/logo_powered_by.png",
				"copyright": "Copyright © 2017 Microsoft and its suppliers. All rights reserved. This API cannot be accessed and the content and any results may not be used, reproduced or transmitted in any manner without express written permission from Microsoft Corporation.",
				"entityType": "Address",
				"matchCodes": [
					"Good"
				],
				"name": "23805 114A Ave, Maple Ridge, BC V2W 1V3, Canada",
				"statusCode": 200,
				"statusDescription": "OK",
				"traceId": "4f8d2e272a654a5d916bde3f265964d3|BN20210145|7.7.0.0|",
				"addressLine": "23805 114A Ave",
				"adminDistrict": "BC",
				"adminDistrict2": "Greater Vancouver",
				"countryRegion": "Canada",
				"formattedAddress": "23805 114A Ave, Maple Ridge, BC V2W 1V3, Canada",
				"locality": "Maple Ridge",
				"postalCode": "V2W 1V3"
			},
			"geometry": {
				"type": "Point",
				"coordinates": [
					-122.5610434,
					49.210022
				]
			},
			"bbox": [
				-122.5627641,
				49.2088978,
				-122.5593226,
				49.2111462
			]
		}
	]
}
