{
	"type": "FeatureCollection",
	"features": [
		{
			"type": "Feature",
			"properties": {
				"confidence": 9,
				"authenticationResultCode": "ValidCredentials",
				"brandLogoUri": "http://dev.virtualearth.net/Branding/logo_powered_by.png",
				"copyright": "Copyright © 2017 Microsoft and its suppliers. All rights reserved. This API cannot be accessed and the content and any results may not be used, reproduced or transmitted in any manner without express written permission from Microsoft Corporation.",
				"entityType": "Address",
				"matchCodes": [
					"Good"
				],
				"name": "2386 HWY-134, Shediac Cape, NB E4P 3G8, Canada",
				"statusCode": 200,
				"statusDescription": "OK",
				"traceId": "6a11ac87dd9d45c99b744e9c7e7cc752|BN20240253|7.7.0.0|",
				"addressLine": "2386 HWY-134",
				"adminDistrict": "NB",
				"adminDistrict2": "Westmorland",
				"countryRegion": "Canada",
				"formattedAddress": "2386 HWY-134, Shediac Cape, NB E4P 3G8, Canada",
				"locality": "Shediac Parish",
				"neighborhood": "Shediac Cape",
				"postalCode": "E4P 3G8"
			},
			"geometry": {
				"type": "Point",
				"coordinates": [
					-64.645485,
					46.1724467
				]
			},
			"bbox": [
				-64.6471084,
				46.1713225,
				-64.6438617,
				46.1735708
			]
		}
	]
}
