{
	"type": "FeatureCollection",
	"features": [
		{
			"type": "Feature",
			"properties": {
				"confidence": 9,
				"authenticationResultCode": "ValidCredentials",
				"brandLogoUri": "http://dev.virtualearth.net/Branding/logo_powered_by.png",
				"copyright": "Copyright © 2017 Microsoft and its suppliers. All rights reserved. This API cannot be accessed and the content and any results may not be used, reproduced or transmitted in any manner without express written permission from Microsoft Corporation.",
				"entityType": "Address",
				"matchCodes": [
					"Good"
				],
				"name": "24 Cherry Blossom Rd, Cambridge, ON N3H 4R7, Canada",
				"statusCode": 200,
				"statusDescription": "OK",
				"traceId": "c3e566b8789c4c05a19b0dfa1c6b9fe3|BN20130521|7.7.0.0|",
				"addressLine": "24 Cherry Blossom Rd",
				"adminDistrict": "ON",
				"adminDistrict2": "Waterloo",
				"countryRegion": "Canada",
				"formattedAddress": "24 Cherry Blossom Rd, Cambridge, ON N3H 4R7, Canada",
				"locality": "Cambridge",
				"postalCode": "N3H 4R7"
			},
			"geometry": {
				"type": "Point",
				"coordinates": [
					-80.38015,
					43.41454
				]
			},
			"bbox": [
				-80.3816976,
				43.4134158,
				-80.3786024,
				43.4156642
			]
		}
	]
}
