{
	"type": "FeatureCollection",
	"features": [
		{
			"type": "Feature",
			"properties": {
				"confidence": 9,
				"authenticationResultCode": "ValidCredentials",
				"brandLogoUri": "http://dev.virtualearth.net/Branding/logo_powered_by.png",
				"copyright": "Copyright © 2017 Microsoft and its suppliers. All rights reserved. This API cannot be accessed and the content and any results may not be used, reproduced or transmitted in any manner without express written permission from Microsoft Corporation.",
				"entityType": "Address",
				"matchCodes": [
					"Ambiguous"
				],
				"name": "24 Hillside Ave S, Dundas, ON L9H 4H9, Canada",
				"statusCode": 200,
				"statusDescription": "OK",
				"traceId": "910cbc902ce049f79926b0161cc69d5b|BN20220145|7.7.0.0|",
				"addressLine": "24 Hillside Ave S",
				"adminDistrict": "ON",
				"adminDistrict2": "Hamilton",
				"countryRegion": "Canada",
				"formattedAddress": "24 Hillside Ave S, Dundas, ON L9H 4H9, Canada",
				"locality": "Hamilton",
				"neighborhood": "Dundas",
				"postalCode": "L9H 4H9"
			},
			"geometry": {
				"type": "Point",
				"coordinates": [
					-79.9461,
					43.2588099
				]
			},
			"bbox": [
				-79.9476436,
				43.2576857,
				-79.9445564,
				43.2599341
			]
		},
		{
			"type": "Feature",
			"properties": {
				"confidence": 9,
				"authenticationResultCode": "ValidCredentials",
				"brandLogoUri": "http://dev.virtualearth.net/Branding/logo_powered_by.png",
				"copyright": "Copyright © 2017 Microsoft and its suppliers. All rights reserved. This API cannot be accessed and the content and any results may not be used, reproduced or transmitted in any manner without express written permission from Microsoft Corporation.",
				"entityType": "Address",
				"matchCodes": [
					"Ambiguous"
				],
				"name": "24 Hillside Ave N, Dundas, ON L9H 4H9, Canada",
				"statusCode": 200,
				"statusDescription": "OK",
				"traceId": "910cbc902ce049f79926b0161cc69d5b|BN20220145|7.7.0.0|",
				"addressLine": "24 Hillside Ave N",
				"adminDistrict": "ON",
				"adminDistrict2": "Hamilton",
				"countryRegion": "Canada",
				"formattedAddress": "24 Hillside Ave N, Dundas, ON L9H 4H9, Canada",
				"locality": "Hamilton",
				"neighborhood": "Dundas",
				"postalCode": "L9H 4H9"
			},
			"geometry": {
				"type": "Point",
				"coordinates": [
					-79.9465964,
					43.2613253
				]
			},
			"bbox": [
				-79.9481401,
				43.2602011,
				-79.9450528,
				43.2624494
			]
		}
	]
}
