{
	"type": "FeatureCollection",
	"features": [
		{
			"type": "Feature",
			"properties": {
				"confidence": 9,
				"authenticationResultCode": "ValidCredentials",
				"brandLogoUri": "http://dev.virtualearth.net/Branding/logo_powered_by.png",
				"copyright": "Copyright © 2017 Microsoft and its suppliers. All rights reserved. This API cannot be accessed and the content and any results may not be used, reproduced or transmitted in any manner without express written permission from Microsoft Corporation.",
				"entityType": "Address",
				"matchCodes": [
					"Good"
				],
				"name": "24 Mills Ave, Garnett Settlement, NB E2S 1X3, Canada",
				"statusCode": 200,
				"statusDescription": "OK",
				"traceId": "74a12eb96a83403d8374d894e5479ba4|BN20130422|7.7.0.0|",
				"addressLine": "24 Mills Ave",
				"adminDistrict": "NB",
				"adminDistrict2": "Saint John",
				"countryRegion": "Canada",
				"formattedAddress": "24 Mills Ave, Garnett Settlement, NB E2S 1X3, Canada",
				"locality": "Simonds Saint John",
				"neighborhood": "Garnett Settlement",
				"postalCode": "E2S 1X3"
			},
			"geometry": {
				"type": "Point",
				"coordinates": [
					-65.8457763,
					45.3041273
				]
			},
			"bbox": [
				-65.8473746,
				45.3030032,
				-65.844178,
				45.3052515
			]
		}
	]
}
