{
	"type": "FeatureCollection",
	"features": [
		{
			"type": "Feature",
			"properties": {
				"confidence": 9,
				"authenticationResultCode": "ValidCredentials",
				"brandLogoUri": "http://dev.virtualearth.net/Branding/logo_powered_by.png",
				"copyright": "Copyright © 2017 Microsoft and its suppliers. All rights reserved. This API cannot be accessed and the content and any results may not be used, reproduced or transmitted in any manner without express written permission from Microsoft Corporation.",
				"entityType": "Address",
				"matchCodes": [
					"Good"
				],
				"name": "24 Valencia St, Nepean, ON K2G 6T1, Canada",
				"statusCode": 200,
				"statusDescription": "OK",
				"traceId": "0fb6ad50b06b4569b3b9326e7eaac8f0|BN20240423|7.7.0.0|",
				"addressLine": "24 Valencia St",
				"adminDistrict": "ON",
				"adminDistrict2": "Ottawa",
				"countryRegion": "Canada",
				"formattedAddress": "24 Valencia St, Nepean, ON K2G 6T1, Canada",
				"locality": "Ottawa",
				"neighborhood": "Nepean",
				"postalCode": "K2G 6T1"
			},
			"geometry": {
				"type": "Point",
				"coordinates": [
					-75.71002,
					45.28048
				]
			},
			"bbox": [
				-75.7116176,
				45.2793558,
				-75.7084224,
				45.2816042
			]
		}
	]
}
