{
	"type": "FeatureCollection",
	"features": [
		{
			"type": "Feature",
			"properties": {
				"confidence": 7,
				"authenticationResultCode": "ValidCredentials",
				"brandLogoUri": "http://dev.virtualearth.net/Branding/logo_powered_by.png",
				"copyright": "Copyright © 2017 Microsoft and its suppliers. All rights reserved. This API cannot be accessed and the content and any results may not be used, reproduced or transmitted in any manner without express written permission from Microsoft Corporation.",
				"entityType": "Postcode1",
				"matchCodes": [
					"UpHierarchy"
				],
				"name": "Bragg Creek, T0L 0K0, Canada",
				"statusCode": 200,
				"statusDescription": "OK",
				"traceId": "1188cb2a854d4139a10bebdf8e3b9fab|BN20130521|7.7.0.0|",
				"adminDistrict": "AB",
				"countryRegion": "Canada",
				"formattedAddress": "Bragg Creek, T0L 0K0, Canada",
				"locality": "Bragg Creek",
				"postalCode": "T0L 0K0"
			},
			"geometry": {
				"type": "Point",
				"coordinates": [
					-114.560760498047,
					50.9510383605957
				]
			},
			"bbox": [
				-114.568935086544,
				50.947175643025,
				-114.55258590955,
				50.9549010781664
			]
		}
	]
}
