{
	"type": "FeatureCollection",
	"features": [
		{
			"type": "Feature",
			"properties": {
				"confidence": 9,
				"authenticationResultCode": "ValidCredentials",
				"brandLogoUri": "http://dev.virtualearth.net/Branding/logo_powered_by.png",
				"copyright": "Copyright © 2017 Microsoft and its suppliers. All rights reserved. This API cannot be accessed and the content and any results may not be used, reproduced or transmitted in any manner without express written permission from Microsoft Corporation.",
				"entityType": "Address",
				"matchCodes": [
					"Good"
				],
				"name": "2400 Alert Rd, Gloucester, ON K1V 1S1, Canada",
				"statusCode": 200,
				"statusDescription": "OK",
				"traceId": "296229c5a7194df49c8ac5f86c0ac612|BN20130719|7.7.0.0|",
				"addressLine": "2400 Alert Rd",
				"adminDistrict": "ON",
				"adminDistrict2": "Ottawa",
				"countryRegion": "Canada",
				"formattedAddress": "2400 Alert Rd, Gloucester, ON K1V 1S1, Canada",
				"locality": "Ottawa",
				"neighborhood": "Gloucester",
				"postalCode": "K1V 1S1"
			},
			"geometry": {
				"type": "Point",
				"coordinates": [
					-75.6502587,
					45.3277142
				]
			},
			"bbox": [
				-75.6518577,
				45.32659,
				-75.6486598,
				45.3288383
			]
		}
	]
}
