{
	"type": "FeatureCollection",
	"features": [
		{
			"type": "Feature",
			"properties": {
				"confidence": 9,
				"authenticationResultCode": "ValidCredentials",
				"brandLogoUri": "http://dev.virtualearth.net/Branding/logo_powered_by.png",
				"copyright": "Copyright © 2017 Microsoft and its suppliers. All rights reserved. This API cannot be accessed and the content and any results may not be used, reproduced or transmitted in any manner without express written permission from Microsoft Corporation.",
				"entityType": "Address",
				"matchCodes": [
					"Good"
				],
				"name": "2403 Stanfield Rd, Mississauga, ON L4Y 1R6, Canada",
				"statusCode": 200,
				"statusDescription": "OK",
				"traceId": "b3c3496a473c4e4a9804c858e8c6fff7|BN20130530|7.7.0.0|",
				"addressLine": "2403 Stanfield Rd",
				"adminDistrict": "ON",
				"adminDistrict2": "Peel",
				"countryRegion": "Canada",
				"formattedAddress": "2403 Stanfield Rd, Mississauga, ON L4Y 1R6, Canada",
				"locality": "Mississauga",
				"postalCode": "L4Y 1R6"
			},
			"geometry": {
				"type": "Point",
				"coordinates": [
					-79.58405,
					43.59949
				]
			},
			"bbox": [
				-79.5856023,
				43.5983658,
				-79.5824977,
				43.6006142
			]
		}
	]
}
