{
	"type": "FeatureCollection",
	"features": [
		{
			"type": "Feature",
			"properties": {
				"confidence": 9,
				"authenticationResultCode": "ValidCredentials",
				"brandLogoUri": "http://dev.virtualearth.net/Branding/logo_powered_by.png",
				"copyright": "Copyright © 2017 Microsoft and its suppliers. All rights reserved. This API cannot be accessed and the content and any results may not be used, reproduced or transmitted in any manner without express written permission from Microsoft Corporation.",
				"entityType": "Address",
				"matchCodes": [
					"Good"
				],
				"name": "2411 1st St Louth, St Catharines, ON L2R, Canada",
				"statusCode": 200,
				"statusDescription": "OK",
				"traceId": "db097f15dc6343c9a4d3ec345c8e97a2|BN20220145|7.7.0.0|",
				"addressLine": "2411 1st St Louth",
				"adminDistrict": "ON",
				"adminDistrict2": "Niagara",
				"countryRegion": "Canada",
				"formattedAddress": "2411 1st St Louth, St Catharines, ON L2R, Canada",
				"locality": "St Catharines",
				"neighborhood": "Louth",
				"postalCode": "L2R 6P7"
			},
			"geometry": {
				"type": "Point",
				"coordinates": [
					-79.27604,
					43.1338099
				]
			},
			"bbox": [
				-79.2775804,
				43.1326857,
				-79.2744996,
				43.1349341
			]
		}
	]
}
