{
	"type": "FeatureCollection",
	"features": [
		{
			"type": "Feature",
			"properties": {
				"confidence": 9,
				"authenticationResultCode": "ValidCredentials",
				"brandLogoUri": "http://dev.virtualearth.net/Branding/logo_powered_by.png",
				"copyright": "Copyright © 2017 Microsoft and its suppliers. All rights reserved. This API cannot be accessed and the content and any results may not be used, reproduced or transmitted in any manner without express written permission from Microsoft Corporation.",
				"entityType": "Address",
				"matchCodes": [
					"Good"
				],
				"name": "24294 100B Ave, Maple Ridge, BC V2W 1X3, Canada",
				"statusCode": 200,
				"statusDescription": "OK",
				"traceId": "b66f804c904645ef94e606868ce34952|BN20210145|7.7.0.0|",
				"addressLine": "24294 100B Ave",
				"adminDistrict": "BC",
				"adminDistrict2": "Greater Vancouver",
				"countryRegion": "Canada",
				"formattedAddress": "24294 100B Ave, Maple Ridge, BC V2W 1X3, Canada",
				"locality": "Maple Ridge",
				"postalCode": "V2W 1X3"
			},
			"geometry": {
				"type": "Point",
				"coordinates": [
					-122.5493678,
					49.1849151
				]
			},
			"bbox": [
				-122.5510877,
				49.183791,
				-122.547648,
				49.1860393
			]
		}
	]
}
