{
	"type": "FeatureCollection",
	"features": [
		{
			"type": "Feature",
			"properties": {
				"confidence": 9,
				"authenticationResultCode": "ValidCredentials",
				"brandLogoUri": "http://dev.virtualearth.net/Branding/logo_powered_by.png",
				"copyright": "Copyright © 2017 Microsoft and its suppliers. All rights reserved. This API cannot be accessed and the content and any results may not be used, reproduced or transmitted in any manner without express written permission from Microsoft Corporation.",
				"entityType": "Address",
				"matchCodes": [
					"Good"
				],
				"name": "2440 Cawthra Rd, Mississauga, ON L5A 2X1, Canada",
				"statusCode": 200,
				"statusDescription": "OK",
				"traceId": "7fbd29ce082f48cb927fceceed4a7707|BN20220145|7.7.0.0|",
				"addressLine": "2440 Cawthra Rd",
				"adminDistrict": "ON",
				"adminDistrict2": "Peel",
				"countryRegion": "Canada",
				"formattedAddress": "2440 Cawthra Rd, Mississauga, ON L5A 2X1, Canada",
				"locality": "Mississauga",
				"neighborhood": "Cooksville",
				"postalCode": "L5A 2X1"
			},
			"geometry": {
				"type": "Point",
				"coordinates": [
					-79.59567,
					43.59073
				]
			},
			"bbox": [
				-79.5972221,
				43.5896058,
				-79.5941179,
				43.5918542
			]
		}
	]
}
