{
	"type": "FeatureCollection",
	"features": [
		{
			"type": "Feature",
			"properties": {
				"confidence": 9,
				"authenticationResultCode": "ValidCredentials",
				"brandLogoUri": "http://dev.virtualearth.net/Branding/logo_powered_by.png",
				"copyright": "Copyright © 2017 Microsoft and its suppliers. All rights reserved. This API cannot be accessed and the content and any results may not be used, reproduced or transmitted in any manner without express written permission from Microsoft Corporation.",
				"entityType": "Address",
				"matchCodes": [
					"Good"
				],
				"name": "2448 Pathfinder Dr, Burlington, ON L7L 6X9, Canada",
				"statusCode": 200,
				"statusDescription": "OK",
				"traceId": "ffb5d3f7db7a40b9b1e5d0cbc7f33f43|BN20130447|7.7.0.0|",
				"addressLine": "2448 Pathfinder Dr",
				"adminDistrict": "ON",
				"adminDistrict2": "Halton",
				"countryRegion": "Canada",
				"formattedAddress": "2448 Pathfinder Dr, Burlington, ON L7L 6X9, Canada",
				"locality": "Burlington",
				"neighborhood": "Orchard",
				"postalCode": "L7L 6X9"
			},
			"geometry": {
				"type": "Point",
				"coordinates": [
					-79.7998099,
					43.4097
				]
			},
			"bbox": [
				-79.8013573,
				43.4085758,
				-79.7982625,
				43.4108242
			]
		}
	]
}
