{
	"type": "FeatureCollection",
	"features": [
		{
			"type": "Feature",
			"properties": {
				"confidence": 9,
				"authenticationResultCode": "ValidCredentials",
				"brandLogoUri": "http://dev.virtualearth.net/Branding/logo_powered_by.png",
				"copyright": "Copyright © 2017 Microsoft and its suppliers. All rights reserved. This API cannot be accessed and the content and any results may not be used, reproduced or transmitted in any manner without express written permission from Microsoft Corporation.",
				"entityType": "Address",
				"matchCodes": [
					"Good"
				],
				"name": "2449 Bloor St W, Toronto, ON M6S 1P7, Canada",
				"statusCode": 200,
				"statusDescription": "OK",
				"traceId": "798b230e8a6646f0a41f59c194373dec|BN20300154|7.7.0.0|",
				"addressLine": "2449 Bloor St W",
				"adminDistrict": "ON",
				"adminDistrict2": "Toronto",
				"countryRegion": "Canada",
				"formattedAddress": "2449 Bloor St W, Toronto, ON M6S 1P7, Canada",
				"locality": "Toronto",
				"neighborhood": "High Park-Swansea",
				"postalCode": "M6S 1P7"
			},
			"geometry": {
				"type": "Point",
				"coordinates": [
					-79.4843999,
					43.64914
				]
			},
			"bbox": [
				-79.4859535,
				43.6480158,
				-79.4828463,
				43.6502642
			]
		}
	]
}
