{
	"type": "FeatureCollection",
	"features": [
		{
			"type": "Feature",
			"properties": {
				"confidence": 9,
				"authenticationResultCode": "ValidCredentials",
				"brandLogoUri": "http://dev.virtualearth.net/Branding/logo_powered_by.png",
				"copyright": "Copyright © 2017 Microsoft and its suppliers. All rights reserved. This API cannot be accessed and the content and any results may not be used, reproduced or transmitted in any manner without express written permission from Microsoft Corporation.",
				"entityType": "Address",
				"matchCodes": [
					"Good"
				],
				"name": "246 Central St, Summerside, PE C1N 3M4, Canada",
				"statusCode": 200,
				"statusDescription": "OK",
				"traceId": "122c6cfbaad640a6ae7c7f2681536bcc|BN20130721|7.7.0.0|",
				"addressLine": "246 Central St",
				"adminDistrict": "PE",
				"adminDistrict2": "Prince",
				"countryRegion": "Canada",
				"formattedAddress": "246 Central St, Summerside, PE C1N 3M4, Canada",
				"locality": "Summerside",
				"postalCode": "C1N 3M4"
			},
			"geometry": {
				"type": "Point",
				"coordinates": [
					-63.79032,
					46.40048
				]
			},
			"bbox": [
				-63.7919501,
				46.3993558,
				-63.7886899,
				46.4016042
			]
		}
	]
}
