{
	"type": "FeatureCollection",
	"features": [
		{
			"type": "Feature",
			"properties": {
				"confidence": 9,
				"authenticationResultCode": "ValidCredentials",
				"brandLogoUri": "http://dev.virtualearth.net/Branding/logo_powered_by.png",
				"copyright": "Copyright © 2017 Microsoft and its suppliers. All rights reserved. This API cannot be accessed and the content and any results may not be used, reproduced or transmitted in any manner without express written permission from Microsoft Corporation.",
				"entityType": "Address",
				"matchCodes": [
					"Good"
				],
				"name": "2462 Sir Carodoc Ln, Mississauga, ON L5K 2J6, Canada",
				"statusCode": 200,
				"statusDescription": "OK",
				"traceId": "08935fabc1b8433bb0f57c58729a6938|BN20130422|7.7.0.0|",
				"addressLine": "2462 Sir Carodoc Ln",
				"adminDistrict": "ON",
				"adminDistrict2": "Peel",
				"countryRegion": "Canada",
				"formattedAddress": "2462 Sir Carodoc Ln, Mississauga, ON L5K 2J6, Canada",
				"locality": "Mississauga",
				"neighborhood": "Erin Mills",
				"postalCode": "L5K 2J6"
			},
			"geometry": {
				"type": "Point",
				"coordinates": [
					-79.6547034,
					43.538454
				]
			},
			"bbox": [
				-79.6562541,
				43.5373299,
				-79.6531526,
				43.5395782
			]
		}
	]
}
