{
	"type": "FeatureCollection",
	"features": [
		{
			"type": "Feature",
			"properties": {
				"confidence": 9,
				"authenticationResultCode": "ValidCredentials",
				"brandLogoUri": "http://dev.virtualearth.net/Branding/logo_powered_by.png",
				"copyright": "Copyright © 2017 Microsoft and its suppliers. All rights reserved. This API cannot be accessed and the content and any results may not be used, reproduced or transmitted in any manner without express written permission from Microsoft Corporation.",
				"entityType": "Address",
				"matchCodes": [
					"Good"
				],
				"name": "2479 Parkedale Ave, Brockville, ON K6V 3H2, Canada",
				"statusCode": 200,
				"statusDescription": "OK",
				"traceId": "7bdb5f00b5bb44f4836030b372b9b007|BN20290118|7.7.0.0|",
				"addressLine": "2479 Parkedale Ave",
				"adminDistrict": "ON",
				"adminDistrict2": "Leeds and Grenville",
				"countryRegion": "Canada",
				"formattedAddress": "2479 Parkedale Ave, Brockville, ON K6V 3H2, Canada",
				"locality": "Brockville",
				"postalCode": "K6V 3H2"
			},
			"geometry": {
				"type": "Point",
				"coordinates": [
					-75.7022099,
					44.60233
				]
			},
			"bbox": [
				-75.7037888,
				44.6012058,
				-75.700631,
				44.6034542
			]
		}
	]
}
