{
	"type": "FeatureCollection",
	"features": [
		{
			"type": "Feature",
			"properties": {
				"confidence": 9,
				"authenticationResultCode": "ValidCredentials",
				"brandLogoUri": "http://dev.virtualearth.net/Branding/logo_powered_by.png",
				"copyright": "Copyright © 2017 Microsoft and its suppliers. All rights reserved. This API cannot be accessed and the content and any results may not be used, reproduced or transmitted in any manner without express written permission from Microsoft Corporation.",
				"entityType": "Address",
				"matchCodes": [
					"Good"
				],
				"name": "2482 Glendoik Way, Mill Bay, BC V0R 2P1, Canada",
				"statusCode": 200,
				"statusDescription": "OK",
				"traceId": "3eac9c3723dc418db3ab4ad8ec16b51b|BN20280152|7.7.0.0|",
				"addressLine": "2482 Glendoik Way",
				"adminDistrict": "BC",
				"adminDistrict2": "Cowichan Valley",
				"countryRegion": "Canada",
				"formattedAddress": "2482 Glendoik Way, Mill Bay, BC V0R 2P1, Canada",
				"locality": "Cowichan Valley",
				"neighborhood": "Mill Bay",
				"postalCode": "V0R 2P1"
			},
			"geometry": {
				"type": "Point",
				"coordinates": [
					-123.56143,
					48.642
				]
			},
			"bbox": [
				-123.5631313,
				48.6408758,
				-123.5597287,
				48.6431242
			]
		}
	]
}
