{
	"type": "FeatureCollection",
	"features": [
		{
			"type": "Feature",
			"properties": {
				"confidence": 9,
				"authenticationResultCode": "ValidCredentials",
				"brandLogoUri": "http://dev.virtualearth.net/Branding/logo_powered_by.png",
				"copyright": "Copyright © 2017 Microsoft and its suppliers. All rights reserved. This API cannot be accessed and the content and any results may not be used, reproduced or transmitted in any manner without express written permission from Microsoft Corporation.",
				"entityType": "Address",
				"matchCodes": [
					"Good"
				],
				"name": "2493 Hendershot Rd, Binbrook, ON L0R 1C0, Canada",
				"statusCode": 200,
				"statusDescription": "OK",
				"traceId": "a1a2f0824a7842df98f11858b60928e7|BN20121764|7.7.0.0|",
				"addressLine": "2493 Hendershot Rd",
				"adminDistrict": "ON",
				"adminDistrict2": "Hamilton",
				"countryRegion": "Canada",
				"formattedAddress": "2493 Hendershot Rd, Binbrook, ON L0R 1C0, Canada",
				"locality": "Hamilton",
				"neighborhood": "Binbrook",
				"postalCode": "L0R 1C0"
			},
			"geometry": {
				"type": "Point",
				"coordinates": [
					-79.77707,
					43.12013
				]
			},
			"bbox": [
				-79.7786101,
				43.1190058,
				-79.7755299,
				43.1212542
			]
		}
	]
}
