{
	"type": "FeatureCollection",
	"features": [
		{
			"type": "Feature",
			"properties": {
				"confidence": 9,
				"authenticationResultCode": "ValidCredentials",
				"brandLogoUri": "http://dev.virtualearth.net/Branding/logo_powered_by.png",
				"copyright": "Copyright © 2017 Microsoft and its suppliers. All rights reserved. This API cannot be accessed and the content and any results may not be used, reproduced or transmitted in any manner without express written permission from Microsoft Corporation.",
				"entityType": "Address",
				"matchCodes": [
					"Good"
				],
				"name": "25 Minthorn Blvd, Thornhill, ON L3T 7N5, Canada",
				"statusCode": 200,
				"statusDescription": "OK",
				"traceId": "aa9d8640d36d4d1eb2a1e314d270dd62|BN20200137|7.7.0.0|",
				"addressLine": "25 Minthorn Blvd",
				"adminDistrict": "ON",
				"adminDistrict2": "York",
				"countryRegion": "Canada",
				"formattedAddress": "25 Minthorn Blvd, Thornhill, ON L3T 7N5, Canada",
				"locality": "Markham",
				"neighborhood": "Thornhill",
				"postalCode": "L3T 7N5"
			},
			"geometry": {
				"type": "Point",
				"coordinates": [
					-79.37743,
					43.84236
				]
			},
			"bbox": [
				-79.3789886,
				43.8412358,
				-79.3758714,
				43.8434842
			]
		}
	]
}
