{
	"type": "FeatureCollection",
	"features": [
		{
			"type": "Feature",
			"properties": {
				"confidence": 9,
				"authenticationResultCode": "ValidCredentials",
				"brandLogoUri": "http://dev.virtualearth.net/Branding/logo_powered_by.png",
				"copyright": "Copyright © 2017 Microsoft and its suppliers. All rights reserved. This API cannot be accessed and the content and any results may not be used, reproduced or transmitted in any manner without express written permission from Microsoft Corporation.",
				"entityType": "Address",
				"matchCodes": [
					"Good"
				],
				"name": "25 Trottier Bay, Winnipeg, MB R3T 3R3, Canada",
				"statusCode": 200,
				"statusDescription": "OK",
				"traceId": "46741c353edd418bad0bbdf2f1bd67ff|BN20121763|7.7.0.0|",
				"addressLine": "25 Trottier Bay",
				"adminDistrict": "MB",
				"adminDistrict2": "Manitoba",
				"countryRegion": "Canada",
				"formattedAddress": "25 Trottier Bay, Winnipeg, MB R3T 3R3, Canada",
				"locality": "Winnipeg",
				"neighborhood": "Chevrier",
				"postalCode": "R3T 3R3"
			},
			"geometry": {
				"type": "Point",
				"coordinates": [
					-97.16237,
					49.82737
				]
			},
			"bbox": [
				-97.1641126,
				49.8262458,
				-97.1606274,
				49.8284942
			]
		}
	]
}
