{
	"type": "FeatureCollection",
	"features": [
		{
			"type": "Feature",
			"properties": {
				"confidence": 9,
				"authenticationResultCode": "ValidCredentials",
				"brandLogoUri": "http://dev.virtualearth.net/Branding/logo_powered_by.png",
				"copyright": "Copyright © 2017 Microsoft and its suppliers. All rights reserved. This API cannot be accessed and the content and any results may not be used, reproduced or transmitted in any manner without express written permission from Microsoft Corporation.",
				"entityType": "Address",
				"matchCodes": [
					"Good"
				],
				"name": "250 Panet Rd, Winnipeg, MB R2J 0S3, Canada",
				"statusCode": 200,
				"statusDescription": "OK",
				"traceId": "03c0afc5d7cb4747871d47f9c03f91c2|BN20200137|7.7.0.0|",
				"addressLine": "250 Panet Rd",
				"adminDistrict": "MB",
				"adminDistrict2": "Manitoba",
				"countryRegion": "Canada",
				"formattedAddress": "250 Panet Rd, Winnipeg, MB R2J 0S3, Canada",
				"locality": "Winnipeg",
				"neighborhood": "Mission Industrial",
				"postalCode": "R2J 0S3"
			},
			"geometry": {
				"type": "Point",
				"coordinates": [
					-97.07998,
					49.89082
				]
			},
			"bbox": [
				-97.0817249,
				49.8896958,
				-97.0782351,
				49.8919442
			]
		}
	]
}
