{
	"type": "FeatureCollection",
	"features": [
		{
			"type": "Feature",
			"properties": {
				"confidence": 9,
				"authenticationResultCode": "ValidCredentials",
				"brandLogoUri": "http://dev.virtualearth.net/Branding/logo_powered_by.png",
				"copyright": "Copyright © 2017 Microsoft and its suppliers. All rights reserved. This API cannot be accessed and the content and any results may not be used, reproduced or transmitted in any manner without express written permission from Microsoft Corporation.",
				"entityType": "Address",
				"matchCodes": [
					"Good"
				],
				"name": "250 Martindale Rd, St Catharines, ON L2R 0B2, Canada",
				"statusCode": 200,
				"statusDescription": "OK",
				"traceId": "666fc0d924e14f20b4ea48b5b8924fa9|BN20240423|7.7.0.0|",
				"addressLine": "250 Martindale Rd",
				"adminDistrict": "ON",
				"adminDistrict2": "Niagara",
				"countryRegion": "Canada",
				"formattedAddress": "250 Martindale Rd, St Catharines, ON L2R 0B2, Canada",
				"locality": "St Catharines",
				"neighborhood": "Grapeview",
				"postalCode": "L2R 0B2"
			},
			"geometry": {
				"type": "Point",
				"coordinates": [
					-79.2749528,
					43.1756105
				]
			},
			"bbox": [
				-79.2764943,
				43.1744864,
				-79.2734113,
				43.1767347
			]
		}
	]
}
