{
	"type": "FeatureCollection",
	"features": [
		{
			"type": "Feature",
			"properties": {
				"confidence": 9,
				"authenticationResultCode": "ValidCredentials",
				"brandLogoUri": "http://dev.virtualearth.net/Branding/logo_powered_by.png",
				"copyright": "Copyright © 2017 Microsoft and its suppliers. All rights reserved. This API cannot be accessed and the content and any results may not be used, reproduced or transmitted in any manner without express written permission from Microsoft Corporation.",
				"entityType": "Address",
				"matchCodes": [
					"Good"
				],
				"name": "250 Minerals Rd, Conception Bay South, NL A1W 5A2, Canada",
				"statusCode": 200,
				"statusDescription": "OK",
				"traceId": "26225bbef728494cb3535aeabc74efa0|BN20130530|7.7.0.0|",
				"addressLine": "250 Minerals Rd",
				"adminDistrict": "NL",
				"adminDistrict2": "Newfoundland and Labrador",
				"countryRegion": "Canada",
				"formattedAddress": "250 Minerals Rd, Conception Bay South, NL A1W 5A2, Canada",
				"locality": "Conception Bay South",
				"postalCode": "A1W 5A2"
			},
			"geometry": {
				"type": "Point",
				"coordinates": [
					-52.9602837,
					47.4918298
				]
			},
			"bbox": [
				-52.9619474,
				47.4907057,
				-52.95862,
				47.492954
			]
		}
	]
}
