{
	"type": "FeatureCollection",
	"features": [
		{
			"type": "Feature",
			"properties": {
				"confidence": 9,
				"authenticationResultCode": "ValidCredentials",
				"brandLogoUri": "http://dev.virtualearth.net/Branding/logo_powered_by.png",
				"copyright": "Copyright © 2017 Microsoft and its suppliers. All rights reserved. This API cannot be accessed and the content and any results may not be used, reproduced or transmitted in any manner without express written permission from Microsoft Corporation.",
				"entityType": "Address",
				"matchCodes": [
					"Good"
				],
				"name": "250 Front St W, Toronto, ON M5V 3G5, Canada",
				"statusCode": 200,
				"statusDescription": "OK",
				"traceId": "c198395809004a7c81264497f0b59d71|BN20121763|7.7.0.0|",
				"addressLine": "250 Front St W",
				"adminDistrict": "ON",
				"adminDistrict2": "Toronto",
				"countryRegion": "Canada",
				"formattedAddress": "250 Front St W, Toronto, ON M5V 3G5, Canada",
				"locality": "Toronto",
				"neighborhood": "Waterfront Communities-the Island",
				"postalCode": "M5V 3G5"
			},
			"geometry": {
				"type": "Point",
				"coordinates": [
					-79.38766,
					43.6444199
				]
			},
			"bbox": [
				-79.3892135,
				43.6432957,
				-79.3861065,
				43.6455441
			]
		}
	]
}
