{
	"type": "FeatureCollection",
	"features": [
		{
			"type": "Feature",
			"properties": {
				"confidence": 9,
				"authenticationResultCode": "ValidCredentials",
				"brandLogoUri": "http://dev.virtualearth.net/Branding/logo_powered_by.png",
				"copyright": "Copyright © 2017 Microsoft and its suppliers. All rights reserved. This API cannot be accessed and the content and any results may not be used, reproduced or transmitted in any manner without express written permission from Microsoft Corporation.",
				"entityType": "Address",
				"matchCodes": [
					"Good"
				],
				"name": "2520 Confederation Pkwy, Mississauga, ON L5B 1S2, Canada",
				"statusCode": 200,
				"statusDescription": "OK",
				"traceId": "0ff98cd4b32f4d5c953a35436a61efe9|BN20130522|7.7.0.0|",
				"addressLine": "2520 Confederation Pkwy",
				"adminDistrict": "ON",
				"adminDistrict2": "Peel",
				"countryRegion": "Canada",
				"formattedAddress": "2520 Confederation Pkwy, Mississauga, ON L5B 1S2, Canada",
				"locality": "Mississauga",
				"neighborhood": "Cooksville",
				"postalCode": "L5B 1S2"
			},
			"geometry": {
				"type": "Point",
				"coordinates": [
					-79.61684,
					43.57558
				]
			},
			"bbox": [
				-79.6183917,
				43.5744558,
				-79.6152883,
				43.5767042
			]
		}
	]
}
