{
	"type": "FeatureCollection",
	"features": [
		{
			"type": "Feature",
			"properties": {
				"confidence": 9,
				"authenticationResultCode": "ValidCredentials",
				"brandLogoUri": "http://dev.virtualearth.net/Branding/logo_powered_by.png",
				"copyright": "Copyright © 2017 Microsoft and its suppliers. All rights reserved. This API cannot be accessed and the content and any results may not be used, reproduced or transmitted in any manner without express written permission from Microsoft Corporation.",
				"entityType": "Address",
				"matchCodes": [
					"Good"
				],
				"name": "2525 Inkster Blvd, Winnipeg, MB R2R 2Y4, Canada",
				"statusCode": 200,
				"statusDescription": "OK",
				"traceId": "cb76906ea81c4501b6ac972c6666a896|BN20130634|7.7.0.0|",
				"addressLine": "2525 Inkster Blvd",
				"adminDistrict": "MB",
				"adminDistrict2": "Manitoba",
				"countryRegion": "Canada",
				"formattedAddress": "2525 Inkster Blvd, Winnipeg, MB R2R 2Y4, Canada",
				"locality": "Winnipeg",
				"neighborhood": "North Inkster Industrial",
				"postalCode": "R2R 2Y4"
			},
			"geometry": {
				"type": "Point",
				"coordinates": [
					-97.2216,
					49.94677
				]
			},
			"bbox": [
				-97.2233469,
				49.9456458,
				-97.2198531,
				49.9478942
			]
		}
	]
}
