{
	"type": "FeatureCollection",
	"features": [
		{
			"type": "Feature",
			"properties": {
				"confidence": 9,
				"authenticationResultCode": "ValidCredentials",
				"brandLogoUri": "http://dev.virtualearth.net/Branding/logo_powered_by.png",
				"copyright": "Copyright © 2017 Microsoft and its suppliers. All rights reserved. This API cannot be accessed and the content and any results may not be used, reproduced or transmitted in any manner without express written permission from Microsoft Corporation.",
				"entityType": "Address",
				"matchCodes": [
					"Good"
				],
				"name": "258 Silver Birch Ave, Toronto, ON M4E 3L5, Canada",
				"statusCode": 200,
				"statusDescription": "OK",
				"traceId": "6dc2a60e62f14280ad6b6115eeabda2c|BN20160335|7.7.0.0|",
				"addressLine": "258 Silver Birch Ave",
				"adminDistrict": "ON",
				"adminDistrict2": "Toronto",
				"countryRegion": "Canada",
				"formattedAddress": "258 Silver Birch Ave, Toronto, ON M4E 3L5, Canada",
				"locality": "Toronto",
				"neighborhood": "The Beaches",
				"postalCode": "M4E 3L5"
			},
			"geometry": {
				"type": "Point",
				"coordinates": [
					-79.2878,
					43.6787599
				]
			},
			"bbox": [
				-79.2893544,
				43.6776357,
				-79.2862456,
				43.6798841
			]
		}
	]
}
