{
	"type": "FeatureCollection",
	"features": [
		{
			"type": "Feature",
			"properties": {
				"confidence": 9,
				"authenticationResultCode": "ValidCredentials",
				"brandLogoUri": "http://dev.virtualearth.net/Branding/logo_powered_by.png",
				"copyright": "Copyright © 2017 Microsoft and its suppliers. All rights reserved. This API cannot be accessed and the content and any results may not be used, reproduced or transmitted in any manner without express written permission from Microsoft Corporation.",
				"entityType": "Address",
				"matchCodes": [
					"Good"
				],
				"name": "2595 McCullough Rd, Nanaimo, BC V9S 4M9, Canada",
				"statusCode": 200,
				"statusDescription": "OK",
				"traceId": "d45aeaf414954c29a2b0317f45ddc5f1|BN20160335|7.7.0.0|",
				"addressLine": "2595 McCullough Rd",
				"adminDistrict": "BC",
				"adminDistrict2": "Nanaimo",
				"countryRegion": "Canada",
				"formattedAddress": "2595 McCullough Rd, Nanaimo, BC V9S 4M9, Canada",
				"locality": "Nanaimo",
				"postalCode": "V9S 4M9"
			},
			"geometry": {
				"type": "Point",
				"coordinates": [
					-123.9847387,
					49.1976331
				]
			},
			"bbox": [
				-123.986459,
				49.196509,
				-123.9830183,
				49.1987573
			]
		}
	]
}
