{
	"type": "FeatureCollection",
	"features": [
		{
			"type": "Feature",
			"properties": {
				"confidence": 9,
				"authenticationResultCode": "ValidCredentials",
				"brandLogoUri": "http://dev.virtualearth.net/Branding/logo_powered_by.png",
				"copyright": "Copyright © 2017 Microsoft and its suppliers. All rights reserved. This API cannot be accessed and the content and any results may not be used, reproduced or transmitted in any manner without express written permission from Microsoft Corporation.",
				"entityType": "Address",
				"matchCodes": [
					"Good"
				],
				"name": "26 Dominion St, Alliston, ON L9R 1L5, Canada",
				"statusCode": 200,
				"statusDescription": "OK",
				"traceId": "471e53f78a9341aaba07b618f8be319d|BN20160335|7.7.0.0|",
				"addressLine": "26 Dominion St",
				"adminDistrict": "ON",
				"adminDistrict2": "Simcoe",
				"countryRegion": "Canada",
				"formattedAddress": "26 Dominion St, Alliston, ON L9R 1L5, Canada",
				"locality": "New Tecumseth",
				"neighborhood": "Alliston",
				"postalCode": "L9R 1L5"
			},
			"geometry": {
				"type": "Point",
				"coordinates": [
					-79.8685885,
					44.1546783
				]
			},
			"bbox": [
				-79.8701554,
				44.1535542,
				-79.8670217,
				44.1558025
			]
		}
	]
}
