{
	"type": "FeatureCollection",
	"features": [
		{
			"type": "Feature",
			"properties": {
				"confidence": 9,
				"authenticationResultCode": "ValidCredentials",
				"brandLogoUri": "http://dev.virtualearth.net/Branding/logo_powered_by.png",
				"copyright": "Copyright © 2017 Microsoft and its suppliers. All rights reserved. This API cannot be accessed and the content and any results may not be used, reproduced or transmitted in any manner without express written permission from Microsoft Corporation.",
				"entityType": "Address",
				"matchCodes": [
					"Good"
				],
				"name": "26 Water St, Yarmouth, NS B5A, Canada",
				"statusCode": 200,
				"statusDescription": "OK",
				"traceId": "f3c2a884b9354a059750c7b55aa22f8e|BN20190653|7.7.0.0|",
				"addressLine": "26 Water St",
				"adminDistrict": "NS",
				"adminDistrict2": "Yarmouth",
				"countryRegion": "Canada",
				"formattedAddress": "26 Water St, Yarmouth, NS B5A, Canada",
				"locality": "Yarmouth",
				"postalCode": "B5A 1K8"
			},
			"geometry": {
				"type": "Point",
				"coordinates": [
					-66.12278,
					43.82989
				]
			},
			"bbox": [
				-66.1243383,
				43.8287658,
				-66.1212217,
				43.8310142
			]
		}
	]
}
