{
	"type": "FeatureCollection",
	"features": [
		{
			"type": "Feature",
			"properties": {
				"confidence": 9,
				"authenticationResultCode": "ValidCredentials",
				"brandLogoUri": "http://dev.virtualearth.net/Branding/logo_powered_by.png",
				"copyright": "Copyright © 2017 Microsoft and its suppliers. All rights reserved. This API cannot be accessed and the content and any results may not be used, reproduced or transmitted in any manner without express written permission from Microsoft Corporation.",
				"entityType": "Address",
				"matchCodes": [
					"Good"
				],
				"name": "26 Rue Villeneuve, Chicoutimi, QC G7J 2C4, Canada",
				"statusCode": 200,
				"statusDescription": "OK",
				"traceId": "8d2faaccfbf64315a86aa991ddaa8d66|BN20300154|7.7.0.0|",
				"addressLine": "26 Rue Villeneuve",
				"adminDistrict": "QC",
				"adminDistrict2": "Saguenay",
				"countryRegion": "Canada",
				"formattedAddress": "26 Rue Villeneuve, Chicoutimi, QC G7J 2C4, Canada",
				"locality": "Saguenay",
				"neighborhood": "Chicoutimi",
				"postalCode": "G7J 2C4"
			},
			"geometry": {
				"type": "Point",
				"coordinates": [
					-71.07098,
					48.41372
				]
			},
			"bbox": [
				-71.0726736,
				48.4125958,
				-71.0692864,
				48.4148442
			]
		}
	]
}
