{
	"type": "FeatureCollection",
	"features": [
		{
			"type": "Feature",
			"properties": {
				"confidence": 9,
				"authenticationResultCode": "ValidCredentials",
				"brandLogoUri": "http://dev.virtualearth.net/Branding/logo_powered_by.png",
				"copyright": "Copyright © 2017 Microsoft and its suppliers. All rights reserved. This API cannot be accessed and the content and any results may not be used, reproduced or transmitted in any manner without express written permission from Microsoft Corporation.",
				"entityType": "Address",
				"matchCodes": [
					"Good"
				],
				"name": "2615 1st Ave N, Saskatoon, SK S7K 6E9, Canada",
				"statusCode": 200,
				"statusDescription": "OK",
				"traceId": "dd6d2fa4656f425cbf8a7da72b4424d8|BN20130522|7.7.0.0|",
				"addressLine": "2615 1st Ave N",
				"adminDistrict": "SK",
				"adminDistrict2": "Saskatchewan",
				"countryRegion": "Canada",
				"formattedAddress": "2615 1st Ave N, Saskatoon, SK S7K 6E9, Canada",
				"locality": "Saskatoon",
				"neighborhood": "North Industrial",
				"postalCode": "S7K 6E9"
			},
			"geometry": {
				"type": "Point",
				"coordinates": [
					-106.66167,
					52.1693
				]
			},
			"bbox": [
				-106.6635029,
				52.1681758,
				-106.6598371,
				52.1704242
			]
		}
	]
}
