{
	"type": "FeatureCollection",
	"features": [
		{
			"type": "Feature",
			"properties": {
				"confidence": 9,
				"authenticationResultCode": "ValidCredentials",
				"brandLogoUri": "http://dev.virtualearth.net/Branding/logo_powered_by.png",
				"copyright": "Copyright © 2017 Microsoft and its suppliers. All rights reserved. This API cannot be accessed and the content and any results may not be used, reproduced or transmitted in any manner without express written permission from Microsoft Corporation.",
				"entityType": "Address",
				"matchCodes": [
					"Good"
				],
				"name": "2627 Pembina Hwy, Winnipeg, MB R3T 2H5, Canada",
				"statusCode": 200,
				"statusDescription": "OK",
				"traceId": "f2e87d33583b41fcb370398e8c181288|BN20121764|7.7.0.0|",
				"addressLine": "2627 Pembina Hwy",
				"adminDistrict": "MB",
				"adminDistrict2": "Manitoba",
				"countryRegion": "Canada",
				"formattedAddress": "2627 Pembina Hwy, Winnipeg, MB R3T 2H5, Canada",
				"locality": "Winnipeg",
				"neighborhood": "Fairfield Park",
				"postalCode": "R3T 2H5"
			},
			"geometry": {
				"type": "Point",
				"coordinates": [
					-97.15797,
					49.79699
				]
			},
			"bbox": [
				-97.1597115,
				49.7958658,
				-97.1562285,
				49.7981142
			]
		}
	]
}
