{
	"type": "FeatureCollection",
	"features": [
		{
			"type": "Feature",
			"properties": {
				"confidence": 9,
				"authenticationResultCode": "ValidCredentials",
				"brandLogoUri": "http://dev.virtualearth.net/Branding/logo_powered_by.png",
				"copyright": "Copyright © 2017 Microsoft and its suppliers. All rights reserved. This API cannot be accessed and the content and any results may not be used, reproduced or transmitted in any manner without express written permission from Microsoft Corporation.",
				"entityType": "Address",
				"matchCodes": [
					"Good"
				],
				"name": "263 McKenzie Towne Dr SE, Calgary, AB T2Z 4P8, Canada",
				"statusCode": 200,
				"statusDescription": "OK",
				"traceId": "56be3329a79f458aaf84793547c3052b|BN20130423|7.7.0.0|",
				"addressLine": "263 McKenzie Towne Dr SE",
				"adminDistrict": "AB",
				"adminDistrict2": "Alberta",
				"countryRegion": "Canada",
				"formattedAddress": "263 McKenzie Towne Dr SE, Calgary, AB T2Z 4P8, Canada",
				"locality": "Calgary",
				"neighborhood": "McKenzie Towne",
				"postalCode": "T2Z 4P8"
			},
			"geometry": {
				"type": "Point",
				"coordinates": [
					-113.96488,
					50.90627
				]
			},
			"bbox": [
				-113.9666627,
				50.9051458,
				-113.9630973,
				50.9073942
			]
		}
	]
}
