{
	"type": "FeatureCollection",
	"features": [
		{
			"type": "Feature",
			"properties": {
				"confidence": 9,
				"authenticationResultCode": "ValidCredentials",
				"brandLogoUri": "http://dev.virtualearth.net/Branding/logo_powered_by.png",
				"copyright": "Copyright © 2017 Microsoft and its suppliers. All rights reserved. This API cannot be accessed and the content and any results may not be used, reproduced or transmitted in any manner without express written permission from Microsoft Corporation.",
				"entityType": "Address",
				"matchCodes": [
					"Good"
				],
				"name": "2666 W River Rd, Clyde River, PE C0A, Canada",
				"statusCode": 200,
				"statusDescription": "OK",
				"traceId": "eeaba533b38a497986a12a8a6acb8d3f|BN20130520|7.7.0.0|",
				"addressLine": "2666 W River Rd",
				"adminDistrict": "PE",
				"adminDistrict2": "Queens",
				"countryRegion": "Canada",
				"formattedAddress": "2666 W River Rd, Clyde River, PE C0A, Canada",
				"locality": "Clyde River",
				"postalCode": "C0A 1H3"
			},
			"geometry": {
				"type": "Point",
				"coordinates": [
					-63.28847,
					46.20404
				]
			},
			"bbox": [
				-63.2900943,
				46.2029158,
				-63.2868457,
				46.2051642
			]
		}
	]
}
