{
	"type": "FeatureCollection",
	"features": [
		{
			"type": "Feature",
			"properties": {
				"confidence": 9,
				"authenticationResultCode": "ValidCredentials",
				"brandLogoUri": "http://dev.virtualearth.net/Branding/logo_powered_by.png",
				"copyright": "Copyright © 2017 Microsoft and its suppliers. All rights reserved. This API cannot be accessed and the content and any results may not be used, reproduced or transmitted in any manner without express written permission from Microsoft Corporation.",
				"entityType": "Address",
				"matchCodes": [
					"Good"
				],
				"name": "2676 Wilfert Rd, Colwood, BC V9B 5Z3, Canada",
				"statusCode": 200,
				"statusDescription": "OK",
				"traceId": "f308deb9461a4eff923ae0c685c5bb3d|BN20200239|7.7.0.0|",
				"addressLine": "2676 Wilfert Rd",
				"adminDistrict": "BC",
				"adminDistrict2": "Capital",
				"countryRegion": "Canada",
				"formattedAddress": "2676 Wilfert Rd, Colwood, BC V9B 5Z3, Canada",
				"locality": "Colwood",
				"postalCode": "V9B 5Z3"
			},
			"geometry": {
				"type": "Point",
				"coordinates": [
					-123.47096,
					48.44608
				]
			},
			"bbox": [
				-123.4726547,
				48.4449558,
				-123.4692653,
				48.4472042
			]
		}
	]
}
