{
	"type": "FeatureCollection",
	"features": [
		{
			"type": "Feature",
			"properties": {
				"confidence": 9,
				"authenticationResultCode": "ValidCredentials",
				"brandLogoUri": "http://dev.virtualearth.net/Branding/logo_powered_by.png",
				"copyright": "Copyright © 2017 Microsoft and its suppliers. All rights reserved. This API cannot be accessed and the content and any results may not be used, reproduced or transmitted in any manner without express written permission from Microsoft Corporation.",
				"entityType": "Address",
				"matchCodes": [
					"Good"
				],
				"name": "269 Mississaga St W, Orillia, ON L3V 3B7, Canada",
				"statusCode": 200,
				"statusDescription": "OK",
				"traceId": "9ddbf2a144ce415eb1d0b5bc3bd7d27f|BN20130422|7.7.0.0|",
				"addressLine": "269 Mississaga St W",
				"adminDistrict": "ON",
				"adminDistrict2": "Simcoe",
				"countryRegion": "Canada",
				"formattedAddress": "269 Mississaga St W, Orillia, ON L3V 3B7, Canada",
				"locality": "Orillia",
				"postalCode": "L3V 3B7"
			},
			"geometry": {
				"type": "Point",
				"coordinates": [
					-79.4301691,
					44.6036661
				]
			},
			"bbox": [
				-79.431748,
				44.602542,
				-79.4285902,
				44.6047903
			]
		}
	]
}
