{
	"type": "FeatureCollection",
	"features": [
		{
			"type": "Feature",
			"properties": {
				"confidence": 9,
				"authenticationResultCode": "ValidCredentials",
				"brandLogoUri": "http://dev.virtualearth.net/Branding/logo_powered_by.png",
				"copyright": "Copyright © 2017 Microsoft and its suppliers. All rights reserved. This API cannot be accessed and the content and any results may not be used, reproduced or transmitted in any manner without express written permission from Microsoft Corporation.",
				"entityType": "Address",
				"matchCodes": [
					"Good"
				],
				"name": "2695 Slough St, Mississauga, ON L4T 1G2, Canada",
				"statusCode": 200,
				"statusDescription": "OK",
				"traceId": "8353790339c347b0ad6a83ddecf46fd8|BN20190642|7.7.0.0|",
				"addressLine": "2695 Slough St",
				"adminDistrict": "ON",
				"adminDistrict2": "Peel",
				"countryRegion": "Canada",
				"formattedAddress": "2695 Slough St, Mississauga, ON L4T 1G2, Canada",
				"locality": "Mississauga",
				"postalCode": "L4T 1G2"
			},
			"geometry": {
				"type": "Point",
				"coordinates": [
					-79.66046,
					43.71058
				]
			},
			"bbox": [
				-79.6620152,
				43.7094558,
				-79.6589048,
				43.7117042
			]
		}
	]
}
