{
	"type": "FeatureCollection",
	"features": [
		{
			"type": "Feature",
			"properties": {
				"confidence": 9,
				"authenticationResultCode": "ValidCredentials",
				"brandLogoUri": "http://dev.virtualearth.net/Branding/logo_powered_by.png",
				"copyright": "Copyright © 2017 Microsoft and its suppliers. All rights reserved. This API cannot be accessed and the content and any results may not be used, reproduced or transmitted in any manner without express written permission from Microsoft Corporation.",
				"entityType": "Address",
				"matchCodes": [
					"Good"
				],
				"name": "27 Catharine Ave, Brantford, ON N3T 1X5, Canada",
				"statusCode": 200,
				"statusDescription": "OK",
				"traceId": "9a0501c427d844debe0532563269d9d3|BN20130520|7.7.0.0|",
				"addressLine": "27 Catharine Ave",
				"adminDistrict": "ON",
				"adminDistrict2": "Brant",
				"countryRegion": "Canada",
				"formattedAddress": "27 Catharine Ave, Brantford, ON N3T 1X5, Canada",
				"locality": "Brantford",
				"postalCode": "N3T 1X5"
			},
			"geometry": {
				"type": "Point",
				"coordinates": [
					-80.2801122,
					43.1359018
				]
			},
			"bbox": [
				-80.2816527,
				43.1347776,
				-80.2785717,
				43.1370259
			]
		}
	]
}
