{
	"type": "FeatureCollection",
	"features": [
		{
			"type": "Feature",
			"properties": {
				"confidence": 9,
				"authenticationResultCode": "ValidCredentials",
				"brandLogoUri": "http://dev.virtualearth.net/Branding/logo_powered_by.png",
				"copyright": "Copyright © 2017 Microsoft and its suppliers. All rights reserved. This API cannot be accessed and the content and any results may not be used, reproduced or transmitted in any manner without express written permission from Microsoft Corporation.",
				"entityType": "Address",
				"matchCodes": [
					"Good"
				],
				"name": "27 Lipstan Ave, Nepean, ON K2E 5Z2, Canada",
				"statusCode": 200,
				"statusDescription": "OK",
				"traceId": "39abdeb8630e44bb9d7d77a3c9e87792|BN20280152|7.7.0.0|",
				"addressLine": "27 Lipstan Ave",
				"adminDistrict": "ON",
				"adminDistrict2": "Ottawa",
				"countryRegion": "Canada",
				"formattedAddress": "27 Lipstan Ave, Nepean, ON K2E 5Z2, Canada",
				"locality": "Ottawa",
				"neighborhood": "Nepean",
				"postalCode": "K2E 5Z2"
			},
			"geometry": {
				"type": "Point",
				"coordinates": [
					-75.71972,
					45.36765
				]
			},
			"bbox": [
				-75.7213201,
				45.3665258,
				-75.7181199,
				45.3687742
			]
		}
	]
}
