{
	"type": "FeatureCollection",
	"features": [
		{
			"type": "Feature",
			"properties": {
				"confidence": 9,
				"authenticationResultCode": "ValidCredentials",
				"brandLogoUri": "http://dev.virtualearth.net/Branding/logo_powered_by.png",
				"copyright": "Copyright © 2017 Microsoft and its suppliers. All rights reserved. This API cannot be accessed and the content and any results may not be used, reproduced or transmitted in any manner without express written permission from Microsoft Corporation.",
				"entityType": "Address",
				"matchCodes": [
					"Good"
				],
				"name": "270 Blantyre Ave, Scarborough, ON M1N 2S3, Canada",
				"statusCode": 200,
				"statusDescription": "OK",
				"traceId": "0577c2003f1f4e5386a1ab0f701f753f|BN20240423|7.7.0.0|",
				"addressLine": "270 Blantyre Ave",
				"adminDistrict": "ON",
				"adminDistrict2": "Toronto",
				"countryRegion": "Canada",
				"formattedAddress": "270 Blantyre Ave, Scarborough, ON M1N 2S3, Canada",
				"locality": "Toronto",
				"neighborhood": "Birchcliffe-Cliffside",
				"postalCode": "M1N 2S3"
			},
			"geometry": {
				"type": "Point",
				"coordinates": [
					-79.2827,
					43.68383
				]
			},
			"bbox": [
				-79.2842545,
				43.6827058,
				-79.2811455,
				43.6849542
			]
		}
	]
}
