{
	"type": "FeatureCollection",
	"features": [
		{
			"type": "Feature",
			"properties": {
				"confidence": 9,
				"authenticationResultCode": "ValidCredentials",
				"brandLogoUri": "http://dev.virtualearth.net/Branding/logo_powered_by.png",
				"copyright": "Copyright © 2017 Microsoft and its suppliers. All rights reserved. This API cannot be accessed and the content and any results may not be used, reproduced or transmitted in any manner without express written permission from Microsoft Corporation.",
				"entityType": "Address",
				"matchCodes": [
					"Good"
				],
				"name": "27049 Gloucester Way, Langley, BC V4W 3Y3, Canada",
				"statusCode": 200,
				"statusDescription": "OK",
				"traceId": "8b9ca64b491c4284907a89b935f8d027|BN20130620|7.7.0.0|",
				"addressLine": "27049 Gloucester Way",
				"adminDistrict": "BC",
				"adminDistrict2": "Greater Vancouver",
				"countryRegion": "Canada",
				"formattedAddress": "27049 Gloucester Way, Langley, BC V4W 3Y3, Canada",
				"locality": "Langley",
				"neighborhood": "Langley",
				"postalCode": "V4W 3Y3"
			},
			"geometry": {
				"type": "Point",
				"coordinates": [
					-122.47646,
					49.09808
				]
			},
			"bbox": [
				-122.4781769,
				49.0969558,
				-122.4747431,
				49.0992042
			]
		}
	]
}
