{
	"type": "FeatureCollection",
	"features": [
		{
			"type": "Feature",
			"properties": {
				"confidence": 9,
				"authenticationResultCode": "ValidCredentials",
				"brandLogoUri": "http://dev.virtualearth.net/Branding/logo_powered_by.png",
				"copyright": "Copyright © 2017 Microsoft and its suppliers. All rights reserved. This API cannot be accessed and the content and any results may not be used, reproduced or transmitted in any manner without express written permission from Microsoft Corporation.",
				"entityType": "Address",
				"matchCodes": [
					"Good"
				],
				"name": "2714 Howe St, Ottawa, ON K2B 6W7, Canada",
				"statusCode": 200,
				"statusDescription": "OK",
				"traceId": "21c9158d29c3458a9fe2bceae98d8d93|BN20131519|7.7.0.0|",
				"addressLine": "2714 Howe St",
				"adminDistrict": "ON",
				"adminDistrict2": "Ottawa",
				"countryRegion": "Canada",
				"formattedAddress": "2714 Howe St, Ottawa, ON K2B 6W7, Canada",
				"locality": "Ottawa",
				"neighborhood": "Woodroofe-Lincoln Heights",
				"postalCode": "K2B 6W7"
			},
			"geometry": {
				"type": "Point",
				"coordinates": [
					-75.79575,
					45.36567
				]
			},
			"bbox": [
				-75.79735,
				45.3645458,
				-75.79415,
				45.3667942
			]
		}
	]
}
