{
	"type": "FeatureCollection",
	"features": [
		{
			"type": "Feature",
			"properties": {
				"confidence": 9,
				"authenticationResultCode": "ValidCredentials",
				"brandLogoUri": "http://dev.virtualearth.net/Branding/logo_powered_by.png",
				"copyright": "Copyright © 2017 Microsoft and its suppliers. All rights reserved. This API cannot be accessed and the content and any results may not be used, reproduced or transmitted in any manner without express written permission from Microsoft Corporation.",
				"entityType": "Address",
				"matchCodes": [
					"Good"
				],
				"name": "2725 CR-6, Douro-Dummer, ON K0L, Canada",
				"statusCode": 200,
				"statusDescription": "OK",
				"traceId": "48f643ce16c64dc79d9c4c45c34c6806|BN20260231|7.7.0.0|",
				"addressLine": "2725 CR-6",
				"adminDistrict": "ON",
				"adminDistrict2": "Peterborough",
				"countryRegion": "Canada",
				"formattedAddress": "2725 CR-6, Douro-Dummer, ON K0L, Canada",
				"locality": "Douro-Dummer",
				"neighborhood": "Lakefield",
				"postalCode": "K0L 2H0"
			},
			"geometry": {
				"type": "Point",
				"coordinates": [
					-78.0791485,
					44.5443094
				]
			},
			"bbox": [
				-78.0807258,
				44.5431853,
				-78.0775712,
				44.5454336
			]
		}
	]
}
