{
	"type": "FeatureCollection",
	"features": [
		{
			"type": "Feature",
			"properties": {
				"confidence": 9,
				"authenticationResultCode": "ValidCredentials",
				"brandLogoUri": "http://dev.virtualearth.net/Branding/logo_powered_by.png",
				"copyright": "Copyright © 2017 Microsoft and its suppliers. All rights reserved. This API cannot be accessed and the content and any results may not be used, reproduced or transmitted in any manner without express written permission from Microsoft Corporation.",
				"entityType": "Address",
				"matchCodes": [
					"Good"
				],
				"name": "273 1st Ave E, Prince Rupert, BC V8J 1A7, Canada",
				"statusCode": 200,
				"statusDescription": "OK",
				"traceId": "3ed67a6db8c14189bfae10dba6d2a59c|BN20160335|7.7.0.0|",
				"addressLine": "273 1st Ave E",
				"adminDistrict": "BC",
				"adminDistrict2": "Skeena-Queen Charlotte",
				"countryRegion": "Canada",
				"formattedAddress": "273 1st Ave E, Prince Rupert, BC V8J 1A7, Canada",
				"locality": "Prince Rupert",
				"postalCode": "V8J 1A7"
			},
			"geometry": {
				"type": "Point",
				"coordinates": [
					-130.3185788,
					54.3172068
				]
			},
			"bbox": [
				-130.3205061,
				54.3160826,
				-130.3166516,
				54.3183309
			]
		}
	]
}
