{
	"type": "FeatureCollection",
	"features": [
		{
			"type": "Feature",
			"properties": {
				"confidence": 9,
				"authenticationResultCode": "ValidCredentials",
				"brandLogoUri": "http://dev.virtualearth.net/Branding/logo_powered_by.png",
				"copyright": "Copyright © 2017 Microsoft and its suppliers. All rights reserved. This API cannot be accessed and the content and any results may not be used, reproduced or transmitted in any manner without express written permission from Microsoft Corporation.",
				"entityType": "Address",
				"matchCodes": [
					"Good"
				],
				"name": "273216 Range Road 13, Airdrie, AB T4B, Canada",
				"statusCode": 200,
				"statusDescription": "OK",
				"traceId": "9818646051874b4aaf94cb5155526a85|BN20130533|7.7.0.0|",
				"addressLine": "273216 Range Road 13",
				"adminDistrict": "AB",
				"adminDistrict2": "Alberta",
				"countryRegion": "Canada",
				"formattedAddress": "273216 Range Road 13, Airdrie, AB T4B, Canada",
				"locality": "Airdrie",
				"postalCode": "T4B 2A3"
			},
			"geometry": {
				"type": "Point",
				"coordinates": [
					-114.0718908,
					51.3177602
				]
			},
			"bbox": [
				-114.0736895,
				51.316636,
				-114.0700922,
				51.3188843
			]
		}
	]
}
