{
	"type": "FeatureCollection",
	"features": [
		{
			"type": "Feature",
			"properties": {
				"confidence": 9,
				"authenticationResultCode": "ValidCredentials",
				"brandLogoUri": "http://dev.virtualearth.net/Branding/logo_powered_by.png",
				"copyright": "Copyright © 2017 Microsoft and its suppliers. All rights reserved. This API cannot be accessed and the content and any results may not be used, reproduced or transmitted in any manner without express written permission from Microsoft Corporation.",
				"entityType": "Address",
				"matchCodes": [
					"Good"
				],
				"name": "2753 Place Dollard, Laval, QC H7E 3T8, Canada",
				"statusCode": 200,
				"statusDescription": "OK",
				"traceId": "9c0e251c0a8848fabc12ed9f00583522|BN20121763|7.7.0.0|",
				"addressLine": "2753 Place Dollard",
				"adminDistrict": "QC",
				"adminDistrict2": "Laval",
				"countryRegion": "Canada",
				"formattedAddress": "2753 Place Dollard, Laval, QC H7E 3T8, Canada",
				"locality": "Laval",
				"postalCode": "H7E 3T8"
			},
			"geometry": {
				"type": "Point",
				"coordinates": [
					-73.67505,
					45.59406
				]
			},
			"bbox": [
				-73.6766565,
				45.5929358,
				-73.6734435,
				45.5951842
			]
		}
	]
}
