{
	"type": "FeatureCollection",
	"features": [
		{
			"type": "Feature",
			"properties": {
				"confidence": 7,
				"authenticationResultCode": "ValidCredentials",
				"brandLogoUri": "http://dev.virtualearth.net/Branding/logo_powered_by.png",
				"copyright": "Copyright © 2017 Microsoft and its suppliers. All rights reserved. This API cannot be accessed and the content and any results may not be used, reproduced or transmitted in any manner without express written permission from Microsoft Corporation.",
				"entityType": "Postcode1",
				"matchCodes": [
					"UpHierarchy"
				],
				"name": "Ucluelet, V0R 3A0, Canada",
				"statusCode": 200,
				"statusDescription": "OK",
				"traceId": "8d9caeae5baf4a1da3419b682182a632|BN20250135|7.7.0.0|",
				"adminDistrict": "BC",
				"adminDistrict2": "Alberni-Clayoquot",
				"countryRegion": "Canada",
				"formattedAddress": "Ucluelet, V0R 3A0, Canada",
				"locality": "Ucluelet",
				"postalCode": "V0R 3A0"
			},
			"geometry": {
				"type": "Point",
				"coordinates": [
					-125.542770385742,
					48.9382095336914
				]
			},
			"bbox": [
				-125.550610402041,
				48.9343468161207,
				-125.534930369444,
				48.9420722512621
			]
		}
	]
}
