{
	"type": "FeatureCollection",
	"features": [
		{
			"type": "Feature",
			"properties": {
				"confidence": 9,
				"authenticationResultCode": "ValidCredentials",
				"brandLogoUri": "http://dev.virtualearth.net/Branding/logo_powered_by.png",
				"copyright": "Copyright © 2017 Microsoft and its suppliers. All rights reserved. This API cannot be accessed and the content and any results may not be used, reproduced or transmitted in any manner without express written permission from Microsoft Corporation.",
				"entityType": "Address",
				"matchCodes": [
					"Good"
				],
				"name": "2777 Hopewell Pl NE, Calgary, AB T1Y 7J7, Canada",
				"statusCode": 200,
				"statusDescription": "OK",
				"traceId": "895209e977d54bb481857aa1ad80ea5d|BN20121763|7.7.0.0|",
				"addressLine": "2777 Hopewell Pl NE",
				"adminDistrict": "AB",
				"adminDistrict2": "Alberta",
				"countryRegion": "Canada",
				"formattedAddress": "2777 Hopewell Pl NE, Calgary, AB T1Y 7J7, Canada",
				"locality": "Calgary",
				"neighborhood": "Horizon",
				"postalCode": "T1Y 7J7"
			},
			"geometry": {
				"type": "Point",
				"coordinates": [
					-113.99563,
					51.09188
				]
			},
			"bbox": [
				-113.9974198,
				51.0907558,
				-113.9938402,
				51.0930042
			]
		}
	]
}
