{
	"type": "FeatureCollection",
	"features": [
		{
			"type": "Feature",
			"properties": {
				"confidence": 9,
				"authenticationResultCode": "ValidCredentials",
				"brandLogoUri": "http://dev.virtualearth.net/Branding/logo_powered_by.png",
				"copyright": "Copyright © 2017 Microsoft and its suppliers. All rights reserved. This API cannot be accessed and the content and any results may not be used, reproduced or transmitted in any manner without express written permission from Microsoft Corporation.",
				"entityType": "Address",
				"matchCodes": [
					"Good"
				],
				"name": "2795 Danforth Ave, Toronto, ON M4C 1M2, Canada",
				"statusCode": 200,
				"statusDescription": "OK",
				"traceId": "369414e4a9054af7acae5332e40a2cd2|BN20130423|7.7.0.0|",
				"addressLine": "2795 Danforth Ave",
				"adminDistrict": "ON",
				"adminDistrict2": "Toronto",
				"countryRegion": "Canada",
				"formattedAddress": "2795 Danforth Ave, Toronto, ON M4C 1M2, Canada",
				"locality": "Toronto",
				"neighborhood": "East End-Danforth",
				"postalCode": "M4C 1M2"
			},
			"geometry": {
				"type": "Point",
				"coordinates": [
					-79.29557,
					43.6893
				]
			},
			"bbox": [
				-79.2971246,
				43.6881758,
				-79.2940154,
				43.6904242
			]
		}
	]
}
