{
	"type": "FeatureCollection",
	"features": [
		{
			"type": "Feature",
			"properties": {
				"confidence": 9,
				"authenticationResultCode": "ValidCredentials",
				"brandLogoUri": "http://dev.virtualearth.net/Branding/logo_powered_by.png",
				"copyright": "Copyright © 2017 Microsoft and its suppliers. All rights reserved. This API cannot be accessed and the content and any results may not be used, reproduced or transmitted in any manner without express written permission from Microsoft Corporation.",
				"entityType": "Address",
				"matchCodes": [
					"Good"
				],
				"name": "28 Dunkirk Rd, St Catharines, ON L2R 1A1, Canada",
				"statusCode": 200,
				"statusDescription": "OK",
				"traceId": "979e4c5886fa46369afc87cec8670d56|BN20300154|7.7.0.0|",
				"addressLine": "28 Dunkirk Rd",
				"adminDistrict": "ON",
				"adminDistrict2": "Niagara",
				"countryRegion": "Canada",
				"formattedAddress": "28 Dunkirk Rd, St Catharines, ON L2R 1A1, Canada",
				"locality": "St Catharines",
				"neighborhood": "Queenston",
				"postalCode": "L2R 1A1"
			},
			"geometry": {
				"type": "Point",
				"coordinates": [
					-79.2281,
					43.17177
				]
			},
			"bbox": [
				-79.2296414,
				43.1706458,
				-79.2265586,
				43.1728942
			]
		}
	]
}
