{
	"type": "FeatureCollection",
	"features": [
		{
			"type": "Feature",
			"properties": {
				"confidence": 9,
				"authenticationResultCode": "ValidCredentials",
				"brandLogoUri": "http://dev.virtualearth.net/Branding/logo_powered_by.png",
				"copyright": "Copyright © 2017 Microsoft and its suppliers. All rights reserved. This API cannot be accessed and the content and any results may not be used, reproduced or transmitted in any manner without express written permission from Microsoft Corporation.",
				"entityType": "Address",
				"matchCodes": [
					"Good"
				],
				"name": "280 Rue Bonin, Acton Vale, QC J0H 1A0, Canada",
				"statusCode": 200,
				"statusDescription": "OK",
				"traceId": "5291c825210e49c9a046aa7a09d6f26e|BN20130631|7.7.0.0|",
				"addressLine": "280 Rue Bonin",
				"adminDistrict": "QC",
				"adminDistrict2": "Acton",
				"countryRegion": "Canada",
				"formattedAddress": "280 Rue Bonin, Acton Vale, QC J0H 1A0, Canada",
				"locality": "Acton Vale",
				"postalCode": "J0H 1A0"
			},
			"geometry": {
				"type": "Point",
				"coordinates": [
					-72.57476,
					45.63786
				]
			},
			"bbox": [
				-72.5763678,
				45.6367358,
				-72.5731522,
				45.6389842
			]
		}
	]
}
