{
	"type": "FeatureCollection",
	"features": [
		{
			"type": "Feature",
			"properties": {
				"confidence": 9,
				"authenticationResultCode": "ValidCredentials",
				"brandLogoUri": "http://dev.virtualearth.net/Branding/logo_powered_by.png",
				"copyright": "Copyright © 2017 Microsoft and its suppliers. All rights reserved. This API cannot be accessed and the content and any results may not be used, reproduced or transmitted in any manner without express written permission from Microsoft Corporation.",
				"entityType": "Address",
				"matchCodes": [
					"Good"
				],
				"name": "281 Hillmount Rd, Markham, ON L6C 2S3, Canada",
				"statusCode": 200,
				"statusDescription": "OK",
				"traceId": "fbba6ed9d7924929abfc741298df9242|BN20181720|7.7.0.0|",
				"addressLine": "281 Hillmount Rd",
				"adminDistrict": "ON",
				"adminDistrict2": "York",
				"countryRegion": "Canada",
				"formattedAddress": "281 Hillmount Rd, Markham, ON L6C 2S3, Canada",
				"locality": "Markham",
				"neighborhood": "Cachet",
				"postalCode": "L6C 2S3"
			},
			"geometry": {
				"type": "Point",
				"coordinates": [
					-79.37709,
					43.87844
				]
			},
			"bbox": [
				-79.3786496,
				43.8773158,
				-79.3755304,
				43.8795642
			]
		}
	]
}
