{
	"type": "FeatureCollection",
	"features": [
		{
			"type": "Feature",
			"properties": {
				"confidence": 9,
				"authenticationResultCode": "ValidCredentials",
				"brandLogoUri": "http://dev.virtualearth.net/Branding/logo_powered_by.png",
				"copyright": "Copyright © 2017 Microsoft and its suppliers. All rights reserved. This API cannot be accessed and the content and any results may not be used, reproduced or transmitted in any manner without express written permission from Microsoft Corporation.",
				"entityType": "Address",
				"matchCodes": [
					"Good"
				],
				"name": "285062 Frontier Rd, Rocky View County, AB T1X 0V9, Canada",
				"statusCode": 200,
				"statusDescription": "OK",
				"traceId": "56994958a3b54e60914ddaf920ed9572|BN20121762|7.7.0.0|",
				"addressLine": "285062 Frontier Rd",
				"adminDistrict": "AB",
				"adminDistrict2": "Alberta",
				"countryRegion": "Canada",
				"formattedAddress": "285062 Frontier Rd, Rocky View County, AB T1X 0V9, Canada",
				"locality": "Rocky View County",
				"postalCode": "T1X 0V9"
			},
			"geometry": {
				"type": "Point",
				"coordinates": [
					-113.90202,
					51.01308
				]
			},
			"bbox": [
				-113.9038068,
				51.0119558,
				-113.9002332,
				51.0142042
			]
		}
	]
}
