{
	"type": "FeatureCollection",
	"features": [
		{
			"type": "Feature",
			"properties": {
				"confidence": 9,
				"authenticationResultCode": "ValidCredentials",
				"brandLogoUri": "http://dev.virtualearth.net/Branding/logo_powered_by.png",
				"copyright": "Copyright © 2017 Microsoft and its suppliers. All rights reserved. This API cannot be accessed and the content and any results may not be used, reproduced or transmitted in any manner without express written permission from Microsoft Corporation.",
				"entityType": "Address",
				"matchCodes": [
					"Good"
				],
				"name": "2857 HWY-560, Wilmot, NB E7K 2A3, Canada",
				"statusCode": 200,
				"statusDescription": "OK",
				"traceId": "0740f1a2b1bd485e83afd274ff292b2f|BN20190653|7.7.0.0|",
				"addressLine": "2857 HWY-560",
				"adminDistrict": "NB",
				"adminDistrict2": "Carleton",
				"countryRegion": "Canada",
				"formattedAddress": "2857 HWY-560, Wilmot, NB E7K 2A3, Canada",
				"locality": "Wilmot",
				"neighborhood": "Williamstown Carleton",
				"postalCode": "E7K 2A3"
			},
			"geometry": {
				"type": "Point",
				"coordinates": [
					-67.7070901,
					46.4015899
				]
			},
			"bbox": [
				-67.7087202,
				46.4004657,
				-67.7054599,
				46.402714
			]
		}
	]
}
