{
	"type": "FeatureCollection",
	"features": [
		{
			"type": "Feature",
			"properties": {
				"confidence": 9,
				"authenticationResultCode": "ValidCredentials",
				"brandLogoUri": "http://dev.virtualearth.net/Branding/logo_powered_by.png",
				"copyright": "Copyright © 2017 Microsoft and its suppliers. All rights reserved. This API cannot be accessed and the content and any results may not be used, reproduced or transmitted in any manner without express written permission from Microsoft Corporation.",
				"entityType": "Address",
				"matchCodes": [
					"Good"
				],
				"name": "286 Kent St, Ottawa, ON K2P 2A4, Canada",
				"statusCode": 200,
				"statusDescription": "OK",
				"traceId": "5072375c789948f6a242086b1f2dd402|BN20130522|7.7.0.0|",
				"addressLine": "286 Kent St",
				"adminDistrict": "ON",
				"adminDistrict2": "Ottawa",
				"countryRegion": "Canada",
				"formattedAddress": "286 Kent St, Ottawa, ON K2P 2A4, Canada",
				"locality": "Ottawa",
				"neighborhood": "Centretown-Downtown",
				"postalCode": "K2P 2A4"
			},
			"geometry": {
				"type": "Point",
				"coordinates": [
					-75.69915,
					45.41489
				]
			},
			"bbox": [
				-75.7007514,
				45.4137658,
				-75.6975486,
				45.4160142
			]
		}
	]
}
