{
	"type": "FeatureCollection",
	"features": [
		{
			"type": "Feature",
			"properties": {
				"confidence": 9,
				"authenticationResultCode": "ValidCredentials",
				"brandLogoUri": "http://dev.virtualearth.net/Branding/logo_powered_by.png",
				"copyright": "Copyright © 2017 Microsoft and its suppliers. All rights reserved. This API cannot be accessed and the content and any results may not be used, reproduced or transmitted in any manner without express written permission from Microsoft Corporation.",
				"entityType": "Address",
				"matchCodes": [
					"Good"
				],
				"name": "287 Division St, Kingston, ON K7K 3Z7, Canada",
				"statusCode": 200,
				"statusDescription": "OK",
				"traceId": "9cc514e9fbbf4100a6753cb0415aded1|BN20260223|7.7.0.0|",
				"addressLine": "287 Division St",
				"adminDistrict": "ON",
				"adminDistrict2": "Frontenac",
				"countryRegion": "Canada",
				"formattedAddress": "287 Division St, Kingston, ON K7K 3Z7, Canada",
				"locality": "Kingston",
				"neighborhood": "Inner Harbour",
				"postalCode": "K7K 3Z7"
			},
			"geometry": {
				"type": "Point",
				"coordinates": [
					-76.49377,
					44.23693
				]
			},
			"bbox": [
				-76.495339,
				44.2358058,
				-76.492201,
				44.2380542
			]
		}
	]
}
