{
	"type": "FeatureCollection",
	"features": [
		{
			"type": "Feature",
			"properties": {
				"confidence": 9,
				"authenticationResultCode": "ValidCredentials",
				"brandLogoUri": "http://dev.virtualearth.net/Branding/logo_powered_by.png",
				"copyright": "Copyright © 2017 Microsoft and its suppliers. All rights reserved. This API cannot be accessed and the content and any results may not be used, reproduced or transmitted in any manner without express written permission from Microsoft Corporation.",
				"entityType": "Address",
				"matchCodes": [
					"Good"
				],
				"name": "2870 Sheffield Rd, Ottawa, ON K1B 3V9, Canada",
				"statusCode": 200,
				"statusDescription": "OK",
				"traceId": "cd7f11f28aa3448d99b427470b496482|BN20300154|7.7.0.0|",
				"addressLine": "2870 Sheffield Rd",
				"adminDistrict": "ON",
				"adminDistrict2": "Ottawa",
				"countryRegion": "Canada",
				"formattedAddress": "2870 Sheffield Rd, Ottawa, ON K1B 3V9, Canada",
				"locality": "Ottawa",
				"neighborhood": "Elmvale-Eastway-Riverview",
				"postalCode": "K1B 3V9"
			},
			"geometry": {
				"type": "Point",
				"coordinates": [
					-75.60306,
					45.39715
				]
			},
			"bbox": [
				-75.6046609,
				45.3960258,
				-75.6014591,
				45.3982742
			]
		}
	]
}
