{
	"type": "FeatureCollection",
	"features": [
		{
			"type": "Feature",
			"properties": {
				"confidence": 9,
				"authenticationResultCode": "ValidCredentials",
				"brandLogoUri": "http://dev.virtualearth.net/Branding/logo_powered_by.png",
				"copyright": "Copyright © 2017 Microsoft and its suppliers. All rights reserved. This API cannot be accessed and the content and any results may not be used, reproduced or transmitted in any manner without express written permission from Microsoft Corporation.",
				"entityType": "Address",
				"matchCodes": [
					"Good"
				],
				"name": "2871 HWY-334, Argyle, NS B0W, Canada",
				"statusCode": 200,
				"statusDescription": "OK",
				"traceId": "6f8a77eb230e43e0bd82c66faf301b74|BN20200137|7.7.0.0|",
				"addressLine": "2871 HWY-334",
				"adminDistrict": "NS",
				"adminDistrict2": "Yarmouth",
				"countryRegion": "Canada",
				"formattedAddress": "2871 HWY-334, Argyle, NS B0W, Canada",
				"locality": "Argyle",
				"neighborhood": "Wedgeport",
				"postalCode": "B0W 2B0"
			},
			"geometry": {
				"type": "Point",
				"coordinates": [
					-65.9794492,
					43.7289257
				]
			},
			"bbox": [
				-65.9810049,
				43.7278015,
				-65.9778936,
				43.7300498
			]
		}
	]
}
