{
	"type": "FeatureCollection",
	"features": [
		{
			"type": "Feature",
			"properties": {
				"confidence": 9,
				"authenticationResultCode": "ValidCredentials",
				"brandLogoUri": "http://dev.virtualearth.net/Branding/logo_powered_by.png",
				"copyright": "Copyright © 2017 Microsoft and its suppliers. All rights reserved. This API cannot be accessed and the content and any results may not be used, reproduced or transmitted in any manner without express written permission from Microsoft Corporation.",
				"entityType": "Address",
				"matchCodes": [
					"Good"
				],
				"name": "2882 Gottingen St, Halifax, NS B3K 3E2, Canada",
				"statusCode": 200,
				"statusDescription": "OK",
				"traceId": "356c79957983492abf2716f96e8d33bc|BN20260231|7.7.0.0|",
				"addressLine": "2882 Gottingen St",
				"adminDistrict": "NS",
				"adminDistrict2": "Halifax",
				"countryRegion": "Canada",
				"formattedAddress": "2882 Gottingen St, Halifax, NS B3K 3E2, Canada",
				"locality": "Halifax",
				"neighborhood": "North End",
				"postalCode": "B3K 3E2"
			},
			"geometry": {
				"type": "Point",
				"coordinates": [
					-63.59681,
					44.66097
				]
			},
			"bbox": [
				-63.5983905,
				44.6598458,
				-63.5952295,
				44.6620942
			]
		}
	]
}
