{
	"type": "FeatureCollection",
	"features": [
		{
			"type": "Feature",
			"properties": {
				"confidence": 9,
				"authenticationResultCode": "ValidCredentials",
				"brandLogoUri": "http://dev.virtualearth.net/Branding/logo_powered_by.png",
				"copyright": "Copyright © 2017 Microsoft and its suppliers. All rights reserved. This API cannot be accessed and the content and any results may not be used, reproduced or transmitted in any manner without express written permission from Microsoft Corporation.",
				"entityType": "Address",
				"matchCodes": [
					"Good"
				],
				"name": "28892 Maclure Rd, Abbotsford, BC V4X 1K3, Canada",
				"statusCode": 200,
				"statusDescription": "OK",
				"traceId": "77d5be175560484eb0befd9118c9f886|BN20200239|7.7.0.0|",
				"addressLine": "28892 Maclure Rd",
				"adminDistrict": "BC",
				"adminDistrict2": "Fraser Valley",
				"countryRegion": "Canada",
				"formattedAddress": "28892 Maclure Rd, Abbotsford, BC V4X 1K3, Canada",
				"locality": "Abbotsford",
				"neighborhood": "West Abbotsford",
				"postalCode": "V4X 1K3"
			},
			"geometry": {
				"type": "Point",
				"coordinates": [
					-122.42345,
					49.06024
				]
			},
			"bbox": [
				-122.4251656,
				49.0591158,
				-122.4217344,
				49.0613642
			]
		}
	]
}
