{
	"type": "FeatureCollection",
	"features": [
		{
			"type": "Feature",
			"properties": {
				"confidence": 9,
				"authenticationResultCode": "ValidCredentials",
				"brandLogoUri": "http://dev.virtualearth.net/Branding/logo_powered_by.png",
				"copyright": "Copyright © 2017 Microsoft and its suppliers. All rights reserved. This API cannot be accessed and the content and any results may not be used, reproduced or transmitted in any manner without express written permission from Microsoft Corporation.",
				"entityType": "Address",
				"matchCodes": [
					"Good"
				],
				"name": "2895 HWY-103, Simonds Carleton, NB E7P 2Y6, Canada",
				"statusCode": 200,
				"statusDescription": "OK",
				"traceId": "f62dc31003484a0a8d448f901dfce6cd|BN20190642|7.7.0.0|",
				"addressLine": "2895 HWY-103",
				"adminDistrict": "NB",
				"adminDistrict2": "Carleton",
				"countryRegion": "Canada",
				"formattedAddress": "2895 HWY-103, Simonds Carleton, NB E7P 2Y6, Canada",
				"locality": "Simonds Carleton",
				"postalCode": "E7P 2Y6"
			},
			"geometry": {
				"type": "Point",
				"coordinates": [
					-67.5475447,
					46.3119595
				]
			},
			"bbox": [
				-67.5491722,
				46.3108353,
				-67.5459172,
				46.3130836
			]
		}
	]
}
