{
	"type": "FeatureCollection",
	"features": [
		{
			"type": "Feature",
			"properties": {
				"confidence": 9,
				"authenticationResultCode": "ValidCredentials",
				"brandLogoUri": "http://dev.virtualearth.net/Branding/logo_powered_by.png",
				"copyright": "Copyright © 2017 Microsoft and its suppliers. All rights reserved. This API cannot be accessed and the content and any results may not be used, reproduced or transmitted in any manner without express written permission from Microsoft Corporation.",
				"entityType": "Address",
				"matchCodes": [
					"Good"
				],
				"name": "2896 Drinkwater Rd, Duncan, BC V9L 6C2, Canada",
				"statusCode": 200,
				"statusDescription": "OK",
				"traceId": "842920cc8a4d41208a78e988dd82a673|BN20130431|7.7.0.0|",
				"addressLine": "2896 Drinkwater Rd",
				"adminDistrict": "BC",
				"adminDistrict2": "Cowichan Valley",
				"countryRegion": "Canada",
				"formattedAddress": "2896 Drinkwater Rd, Duncan, BC V9L 6C2, Canada",
				"locality": "North Cowichan",
				"neighborhood": "Duncan",
				"postalCode": "V9L 6C2"
			},
			"geometry": {
				"type": "Point",
				"coordinates": [
					-123.7159551,
					48.8030092
				]
			},
			"bbox": [
				-123.7176619,
				48.801885,
				-123.7142484,
				48.8041333
			]
		}
	]
}
