{
	"type": "FeatureCollection",
	"features": [
		{
			"type": "Feature",
			"properties": {
				"confidence": 9,
				"authenticationResultCode": "ValidCredentials",
				"brandLogoUri": "http://dev.virtualearth.net/Branding/logo_powered_by.png",
				"copyright": "Copyright © 2017 Microsoft and its suppliers. All rights reserved. This API cannot be accessed and the content and any results may not be used, reproduced or transmitted in any manner without express written permission from Microsoft Corporation.",
				"entityType": "Address",
				"matchCodes": [
					"Good"
				],
				"name": "29 Harriet St, Hamilton, ON L8R 2E5, Canada",
				"statusCode": 200,
				"statusDescription": "OK",
				"traceId": "c8e8f8f5e3fc45389e5ab993eda15fc8|BN20130442|7.7.0.0|",
				"addressLine": "29 Harriet St",
				"adminDistrict": "ON",
				"adminDistrict2": "Hamilton",
				"countryRegion": "Canada",
				"formattedAddress": "29 Harriet St, Hamilton, ON L8R 2E5, Canada",
				"locality": "Hamilton",
				"neighborhood": "Central Hamilton",
				"postalCode": "L8R 2E5"
			},
			"geometry": {
				"type": "Point",
				"coordinates": [
					-79.8745,
					43.26393
				]
			},
			"bbox": [
				-79.8760437,
				43.2628058,
				-79.8729563,
				43.2650542
			]
		}
	]
}
