{
	"type": "FeatureCollection",
	"features": [
		{
			"type": "Feature",
			"properties": {
				"confidence": 9,
				"authenticationResultCode": "ValidCredentials",
				"brandLogoUri": "http://dev.virtualearth.net/Branding/logo_powered_by.png",
				"copyright": "Copyright © 2017 Microsoft and its suppliers. All rights reserved. This API cannot be accessed and the content and any results may not be used, reproduced or transmitted in any manner without express written permission from Microsoft Corporation.",
				"entityType": "Address",
				"matchCodes": [
					"Good"
				],
				"name": "29 Rue Langevin, Chambly, QC J3L 2G3, Canada",
				"statusCode": 200,
				"statusDescription": "OK",
				"traceId": "3eda52f6bb9247ac870632d4db1082f1|BN20181720|7.7.0.0|",
				"addressLine": "29 Rue Langevin",
				"adminDistrict": "QC",
				"adminDistrict2": "La Vallée-du-Richelieu",
				"countryRegion": "Canada",
				"formattedAddress": "29 Rue Langevin, Chambly, QC J3L 2G3, Canada",
				"locality": "Chambly",
				"postalCode": "J3L 2G3"
			},
			"geometry": {
				"type": "Point",
				"coordinates": [
					-73.27116,
					45.44511
				]
			},
			"bbox": [
				-73.2727623,
				45.4439858,
				-73.2695577,
				45.4462342
			]
		}
	]
}
