{
	"type": "FeatureCollection",
	"features": [
		{
			"type": "Feature",
			"properties": {
				"confidence": 9,
				"authenticationResultCode": "ValidCredentials",
				"brandLogoUri": "http://dev.virtualearth.net/Branding/logo_powered_by.png",
				"copyright": "Copyright © 2017 Microsoft and its suppliers. All rights reserved. This API cannot be accessed and the content and any results may not be used, reproduced or transmitted in any manner without express written permission from Microsoft Corporation.",
				"entityType": "Address",
				"matchCodes": [
					"Good"
				],
				"name": "29 Whitewood Ave W, Temiskaming Shores, ON P0J, Canada",
				"statusCode": 200,
				"statusDescription": "OK",
				"traceId": "8f1582d9534a49d1be982679b3cff494|BN20130431|7.7.0.0|",
				"addressLine": "29 Whitewood Ave W",
				"adminDistrict": "ON",
				"adminDistrict2": "Timiskaming",
				"countryRegion": "Canada",
				"formattedAddress": "29 Whitewood Ave W, Temiskaming Shores, ON P0J, Canada",
				"locality": "Temiskaming Shores",
				"neighborhood": "New Liskeard",
				"postalCode": "P0J 1P0"
			},
			"geometry": {
				"type": "Point",
				"coordinates": [
					-79.6725531,
					47.5086949
				]
			},
			"bbox": [
				-79.6742174,
				47.5075707,
				-79.6708889,
				47.509819
			]
		}
	]
}
