{
	"type": "FeatureCollection",
	"features": [
		{
			"type": "Feature",
			"properties": {
				"confidence": 9,
				"authenticationResultCode": "ValidCredentials",
				"brandLogoUri": "http://dev.virtualearth.net/Branding/logo_powered_by.png",
				"copyright": "Copyright © 2017 Microsoft and its suppliers. All rights reserved. This API cannot be accessed and the content and any results may not be used, reproduced or transmitted in any manner without express written permission from Microsoft Corporation.",
				"entityType": "Address",
				"matchCodes": [
					"Good"
				],
				"name": "290 Pinebush Rd, Cambridge, ON N1T 1Z6, Canada",
				"statusCode": 200,
				"statusDescription": "OK",
				"traceId": "4d7af7ac80d1463b8f398f27fedd08b1|BN20210145|7.7.0.0|",
				"addressLine": "290 Pinebush Rd",
				"adminDistrict": "ON",
				"adminDistrict2": "Waterloo",
				"countryRegion": "Canada",
				"formattedAddress": "290 Pinebush Rd, Cambridge, ON N1T 1Z6, Canada",
				"locality": "Cambridge",
				"neighborhood": "Fiddlesticks",
				"postalCode": "N1T 1Z6"
			},
			"geometry": {
				"type": "Point",
				"coordinates": [
					-80.30101,
					43.4133
				]
			},
			"bbox": [
				-80.3025575,
				43.4121758,
				-80.2994625,
				43.4144242
			]
		}
	]
}
