{
	"type": "FeatureCollection",
	"features": [
		{
			"type": "Feature",
			"properties": {
				"confidence": 9,
				"authenticationResultCode": "ValidCredentials",
				"brandLogoUri": "http://dev.virtualearth.net/Branding/logo_powered_by.png",
				"copyright": "Copyright © 2017 Microsoft and its suppliers. All rights reserved. This API cannot be accessed and the content and any results may not be used, reproduced or transmitted in any manner without express written permission from Microsoft Corporation.",
				"entityType": "Address",
				"matchCodes": [
					"Good"
				],
				"name": "290 Garry St, Winnipeg, MB R3C 1H3, Canada",
				"statusCode": 200,
				"statusDescription": "OK",
				"traceId": "7169e13a08124faabb944c2dd4973688|BN20130447|7.7.0.0|",
				"addressLine": "290 Garry St",
				"adminDistrict": "MB",
				"adminDistrict2": "Manitoba",
				"countryRegion": "Canada",
				"formattedAddress": "290 Garry St, Winnipeg, MB R3C 1H3, Canada",
				"locality": "Winnipeg",
				"neighborhood": "South Portage",
				"postalCode": "R3C 1H3"
			},
			"geometry": {
				"type": "Point",
				"coordinates": [
					-97.14104,
					49.89371
				]
			},
			"bbox": [
				-97.142785,
				49.8925858,
				-97.139295,
				49.8948342
			]
		}
	]
}
