{
	"type": "FeatureCollection",
	"features": [
		{
			"type": "Feature",
			"properties": {
				"confidence": 9,
				"authenticationResultCode": "ValidCredentials",
				"brandLogoUri": "http://dev.virtualearth.net/Branding/logo_powered_by.png",
				"copyright": "Copyright © 2017 Microsoft and its suppliers. All rights reserved. This API cannot be accessed and the content and any results may not be used, reproduced or transmitted in any manner without express written permission from Microsoft Corporation.",
				"entityType": "Address",
				"matchCodes": [
					"Good"
				],
				"name": "290 Rue des Mouettes, Terrebonne, QC J6Y 1C8, Canada",
				"statusCode": 200,
				"statusDescription": "OK",
				"traceId": "ca0540482a12479cbcc06b357da573ea|BN20130533|7.7.0.0|",
				"addressLine": "290 Rue des Mouettes",
				"adminDistrict": "QC",
				"adminDistrict2": "Les Moulins",
				"countryRegion": "Canada",
				"formattedAddress": "290 Rue des Mouettes, Terrebonne, QC J6Y 1C8, Canada",
				"locality": "Terrebonne",
				"postalCode": "J6Y 1C8"
			},
			"geometry": {
				"type": "Point",
				"coordinates": [
					-73.81242,
					45.71107
				]
			},
			"bbox": [
				-73.8140299,
				45.7099458,
				-73.8108101,
				45.7121942
			]
		}
	]
}
