{
	"type": "FeatureCollection",
	"features": [
		{
			"type": "Feature",
			"properties": {
				"confidence": 8,
				"authenticationResultCode": "ValidCredentials",
				"brandLogoUri": "http://dev.virtualearth.net/Branding/logo_powered_by.png",
				"copyright": "Copyright © 2017 Microsoft and its suppliers. All rights reserved. This API cannot be accessed and the content and any results may not be used, reproduced or transmitted in any manner without express written permission from Microsoft Corporation.",
				"entityType": "RoadBlock",
				"matchCodes": [
					"UpHierarchy"
				],
				"name": "McTavish Rd NE, Calgary, AB T2E 7G5, Canada",
				"statusCode": 200,
				"statusDescription": "OK",
				"traceId": "4854497d7489495589d7148a8fd2eb5b|BN20290118|7.7.0.0|",
				"addressLine": "McTavish Rd NE",
				"adminDistrict": "AB",
				"adminDistrict2": "Alberta",
				"countryRegion": "Canada",
				"formattedAddress": "McTavish Rd NE, Calgary, AB T2E 7G5, Canada",
				"locality": "Calgary",
				"postalCode": "T2E 7G5"
			},
			"geometry": {
				"type": "Point",
				"coordinates": [
					-114.01478,
					51.09735
				]
			},
			"bbox": [
				-114.01526,
				51.09334,
				-114.01302,
				51.0977
			]
		}
	]
}
