{
	"type": "FeatureCollection",
	"features": [
		{
			"type": "Feature",
			"properties": {
				"confidence": 9,
				"authenticationResultCode": "ValidCredentials",
				"brandLogoUri": "http://dev.virtualearth.net/Branding/logo_powered_by.png",
				"copyright": "Copyright © 2017 Microsoft and its suppliers. All rights reserved. This API cannot be accessed and the content and any results may not be used, reproduced or transmitted in any manner without express written permission from Microsoft Corporation.",
				"entityType": "Address",
				"matchCodes": [
					"Good"
				],
				"name": "2904 11 St SE, Calgary, AB T2G 3G8, Canada",
				"statusCode": 200,
				"statusDescription": "OK",
				"traceId": "f32703e578c241288df7cd87d0b07cdf|BN20130719|7.7.0.0|",
				"addressLine": "2904 11 St SE",
				"adminDistrict": "AB",
				"adminDistrict2": "Alberta",
				"countryRegion": "Canada",
				"formattedAddress": "2904 11 St SE, Calgary, AB T2G 3G8, Canada",
				"locality": "Calgary",
				"neighborhood": "Alyth-Bonnybrook-Manchester",
				"postalCode": "T2G 3G8"
			},
			"geometry": {
				"type": "Point",
				"coordinates": [
					-114.036,
					51.02787
				]
			},
			"bbox": [
				-114.0377874,
				51.0267458,
				-114.0342126,
				51.0289942
			]
		}
	]
}
