{
	"type": "FeatureCollection",
	"features": [
		{
			"type": "Feature",
			"properties": {
				"confidence": 9,
				"authenticationResultCode": "ValidCredentials",
				"brandLogoUri": "http://dev.virtualearth.net/Branding/logo_powered_by.png",
				"copyright": "Copyright © 2017 Microsoft and its suppliers. All rights reserved. This API cannot be accessed and the content and any results may not be used, reproduced or transmitted in any manner without express written permission from Microsoft Corporation.",
				"entityType": "Address",
				"matchCodes": [
					"Good"
				],
				"name": "2924 Piper Rd, Prince George, BC V2N 2H8, Canada",
				"statusCode": 200,
				"statusDescription": "OK",
				"traceId": "b8c1539754c64036b0f78fc59bc65aae|BN20121764|7.7.0.0|",
				"addressLine": "2924 Piper Rd",
				"adminDistrict": "BC",
				"adminDistrict2": "Fraser-Fort George",
				"countryRegion": "Canada",
				"formattedAddress": "2924 Piper Rd, Prince George, BC V2N 2H8, Canada",
				"locality": "Prince George",
				"postalCode": "V2N 2H8"
			},
			"geometry": {
				"type": "Point",
				"coordinates": [
					-122.67961,
					53.90618
				]
			},
			"bbox": [
				-122.6815182,
				53.9050558,
				-122.6777018,
				53.9073042
			]
		}
	]
}
