{
	"type": "FeatureCollection",
	"features": [
		{
			"type": "Feature",
			"properties": {
				"confidence": 9,
				"authenticationResultCode": "ValidCredentials",
				"brandLogoUri": "http://dev.virtualearth.net/Branding/logo_powered_by.png",
				"copyright": "Copyright © 2017 Microsoft and its suppliers. All rights reserved. This API cannot be accessed and the content and any results may not be used, reproduced or transmitted in any manner without express written permission from Microsoft Corporation.",
				"entityType": "Address",
				"matchCodes": [
					"Good"
				],
				"name": "293 Mary St, Hamilton, ON L8L 4W3, Canada",
				"statusCode": 200,
				"statusDescription": "OK",
				"traceId": "4db64cd735a04fd69d18da02d873541e|BN20240423|7.7.0.0|",
				"addressLine": "293 Mary St",
				"adminDistrict": "ON",
				"adminDistrict2": "Hamilton",
				"countryRegion": "Canada",
				"formattedAddress": "293 Mary St, Hamilton, ON L8L 4W3, Canada",
				"locality": "Hamilton",
				"neighborhood": "Beasley",
				"postalCode": "L8L 4W3"
			},
			"geometry": {
				"type": "Point",
				"coordinates": [
					-79.86074,
					43.26364
				]
			},
			"bbox": [
				-79.8622837,
				43.2625158,
				-79.8591963,
				43.2647642
			]
		}
	]
}
