{
	"type": "FeatureCollection",
	"features": [
		{
			"type": "Feature",
			"properties": {
				"confidence": 9,
				"authenticationResultCode": "ValidCredentials",
				"brandLogoUri": "http://dev.virtualearth.net/Branding/logo_powered_by.png",
				"copyright": "Copyright © 2017 Microsoft and its suppliers. All rights reserved. This API cannot be accessed and the content and any results may not be used, reproduced or transmitted in any manner without express written permission from Microsoft Corporation.",
				"entityType": "Address",
				"matchCodes": [
					"Good"
				],
				"name": "1445 McGill Rd, Kamloops, BC V2C 6K7, Canada",
				"statusCode": 200,
				"statusDescription": "OK",
				"traceId": "8d31e44a15d44bd4b4ea7ec268ff686b|BN20130632|7.7.0.0|",
				"addressLine": "1445 McGill Rd",
				"adminDistrict": "BC",
				"adminDistrict2": "Thompson-Nicola",
				"countryRegion": "Canada",
				"formattedAddress": "1445 McGill Rd, Kamloops, BC V2C 6K7, Canada",
				"locality": "Kamloops",
				"neighborhood": "Southgate",
				"postalCode": "V2C 6K7"
			},
			"geometry": {
				"type": "Point",
				"coordinates": [
					-120.37678,
					50.67431
				]
			},
			"bbox": [
				-120.3785539,
				50.6731858,
				-120.3750061,
				50.6754342
			]
		}
	]
}
