{
	"type": "FeatureCollection",
	"features": [
		{
			"type": "Feature",
			"properties": {
				"confidence": 9,
				"authenticationResultCode": "ValidCredentials",
				"brandLogoUri": "http://dev.virtualearth.net/Branding/logo_powered_by.png",
				"copyright": "Copyright © 2017 Microsoft and its suppliers. All rights reserved. This API cannot be accessed and the content and any results may not be used, reproduced or transmitted in any manner without express written permission from Microsoft Corporation.",
				"entityType": "Address",
				"matchCodes": [
					"Good"
				],
				"name": "30 Brown Ave, Dartmouth, NS B3B 1X8, Canada",
				"statusCode": 200,
				"statusDescription": "OK",
				"traceId": "a56b3840b5ef414fa1fb65b7d57777b5|BN20130520|7.7.0.0|",
				"addressLine": "30 Brown Ave",
				"adminDistrict": "NS",
				"adminDistrict2": "Halifax",
				"countryRegion": "Canada",
				"formattedAddress": "30 Brown Ave, Dartmouth, NS B3B 1X8, Canada",
				"locality": "Halifax",
				"neighborhood": "Dartmouth",
				"postalCode": "B3B 1X8"
			},
			"geometry": {
				"type": "Point",
				"coordinates": [
					-63.59571,
					44.69625
				]
			},
			"bbox": [
				-63.5972914,
				44.6951258,
				-63.5941286,
				44.6973742
			]
		}
	]
}
