{
	"type": "FeatureCollection",
	"features": [
		{
			"type": "Feature",
			"properties": {
				"confidence": 9,
				"authenticationResultCode": "ValidCredentials",
				"brandLogoUri": "http://dev.virtualearth.net/Branding/logo_powered_by.png",
				"copyright": "Copyright © 2017 Microsoft and its suppliers. All rights reserved. This API cannot be accessed and the content and any results may not be used, reproduced or transmitted in any manner without express written permission from Microsoft Corporation.",
				"entityType": "Address",
				"matchCodes": [
					"Good"
				],
				"name": "30 Elliott Ave, Barrie, ON L4N 4V7, Canada",
				"statusCode": 200,
				"statusDescription": "OK",
				"traceId": "8ec28bdc998b4627aebd96a5dc4dc460|BN20240253|7.7.0.0|",
				"addressLine": "30 Elliott Ave",
				"adminDistrict": "ON",
				"adminDistrict2": "Simcoe",
				"countryRegion": "Canada",
				"formattedAddress": "30 Elliott Ave, Barrie, ON L4N 4V7, Canada",
				"locality": "Barrie",
				"neighborhood": "400 North",
				"postalCode": "L4N 4V7"
			},
			"geometry": {
				"type": "Point",
				"coordinates": [
					-79.71786,
					44.37486
				]
			},
			"bbox": [
				-79.7194327,
				44.3737358,
				-79.7162873,
				44.3759842
			]
		}
	]
}
