{
	"type": "FeatureCollection",
	"features": [
		{
			"type": "Feature",
			"properties": {
				"confidence": 9,
				"authenticationResultCode": "ValidCredentials",
				"brandLogoUri": "http://dev.virtualearth.net/Branding/logo_powered_by.png",
				"copyright": "Copyright © 2017 Microsoft and its suppliers. All rights reserved. This API cannot be accessed and the content and any results may not be used, reproduced or transmitted in any manner without express written permission from Microsoft Corporation.",
				"entityType": "Address",
				"matchCodes": [
					"Good"
				],
				"name": "300 Bayfield St, Barrie, ON L4M 3B9, Canada",
				"statusCode": 200,
				"statusDescription": "OK",
				"traceId": "2465572ba3cb4dbcb49433407af90d73|BN20121762|7.7.0.0|",
				"addressLine": "300 Bayfield St",
				"adminDistrict": "ON",
				"adminDistrict2": "Simcoe",
				"countryRegion": "Canada",
				"formattedAddress": "300 Bayfield St, Barrie, ON L4M 3B9, Canada",
				"locality": "Barrie",
				"neighborhood": "Sunnidale",
				"postalCode": "L4M 3B9"
			},
			"geometry": {
				"type": "Point",
				"coordinates": [
					-79.69974,
					44.39996
				]
			},
			"bbox": [
				-79.7013134,
				44.3988358,
				-79.6981666,
				44.4010842
			]
		}
	]
}
