{
	"type": "FeatureCollection",
	"features": [
		{
			"type": "Feature",
			"properties": {
				"confidence": 9,
				"authenticationResultCode": "ValidCredentials",
				"brandLogoUri": "http://dev.virtualearth.net/Branding/logo_powered_by.png",
				"copyright": "Copyright © 2017 Microsoft and its suppliers. All rights reserved. This API cannot be accessed and the content and any results may not be used, reproduced or transmitted in any manner without express written permission from Microsoft Corporation.",
				"entityType": "Address",
				"matchCodes": [
					"Good"
				],
				"name": "300 Earl Grey Dr, Kanata, ON K2T 1B6, Canada",
				"statusCode": 200,
				"statusDescription": "OK",
				"traceId": "ace85b670a564200a0d414ace071ac52|BN20130442|7.7.0.0|",
				"addressLine": "300 Earl Grey Dr",
				"adminDistrict": "ON",
				"adminDistrict2": "Ottawa",
				"countryRegion": "Canada",
				"formattedAddress": "300 Earl Grey Dr, Kanata, ON K2T 1B6, Canada",
				"locality": "Ottawa",
				"neighborhood": "Kanata",
				"postalCode": "K2T 1B6"
			},
			"geometry": {
				"type": "Point",
				"coordinates": [
					-75.9119824,
					45.3102024
				]
			},
			"bbox": [
				-75.9135808,
				45.3090782,
				-75.9103839,
				45.3113265
			]
		}
	]
}
