{
	"type": "FeatureCollection",
	"features": [
		{
			"type": "Feature",
			"properties": {
				"confidence": 9,
				"authenticationResultCode": "ValidCredentials",
				"brandLogoUri": "http://dev.virtualearth.net/Branding/logo_powered_by.png",
				"copyright": "Copyright © 2017 Microsoft and its suppliers. All rights reserved. This API cannot be accessed and the content and any results may not be used, reproduced or transmitted in any manner without express written permission from Microsoft Corporation.",
				"entityType": "Address",
				"matchCodes": [
					"Good"
				],
				"name": "3013 Boulevard Industriel, Laval, QC H7L 3W9, Canada",
				"statusCode": 200,
				"statusDescription": "OK",
				"traceId": "c9bdbca17e6b44c2b4e20ed0b9a3a552|BN20220145|7.7.0.0|",
				"addressLine": "3013 Boulevard Industriel",
				"adminDistrict": "QC",
				"adminDistrict2": "Laval",
				"countryRegion": "Canada",
				"formattedAddress": "3013 Boulevard Industriel, Laval, QC H7L 3W9, Canada",
				"locality": "Laval",
				"postalCode": "H7L 3W9"
			},
			"geometry": {
				"type": "Point",
				"coordinates": [
					-73.74104,
					45.58964
				]
			},
			"bbox": [
				-73.7426464,
				45.5885158,
				-73.7394336,
				45.5907642
			]
		}
	]
}
