{
	"type": "FeatureCollection",
	"features": [
		{
			"type": "Feature",
			"properties": {
				"confidence": 9,
				"authenticationResultCode": "ValidCredentials",
				"brandLogoUri": "http://dev.virtualearth.net/Branding/logo_powered_by.png",
				"copyright": "Copyright © 2017 Microsoft and its suppliers. All rights reserved. This API cannot be accessed and the content and any results may not be used, reproduced or transmitted in any manner without express written permission from Microsoft Corporation.",
				"entityType": "Address",
				"matchCodes": [
					"Good"
				],
				"name": "3015 Quance St, Regina, SK S4V, Canada",
				"statusCode": 200,
				"statusDescription": "OK",
				"traceId": "7991e41039c64c839a60892683a3edf9|BN20130422|7.7.0.0|",
				"addressLine": "3015 Quance St",
				"adminDistrict": "SK",
				"adminDistrict2": "Saskatchewan",
				"countryRegion": "Canada",
				"formattedAddress": "3015 Quance St, Regina, SK S4V, Canada",
				"locality": "Regina",
				"neighborhood": "Arcola East-North Side",
				"postalCode": "S4V 3B7"
			},
			"geometry": {
				"type": "Point",
				"coordinates": [
					-104.5396899,
					50.44547
				]
			},
			"bbox": [
				-104.5414552,
				50.4443458,
				-104.5379246,
				50.4465942
			]
		}
	]
}
