{
	"type": "FeatureCollection",
	"features": [
		{
			"type": "Feature",
			"properties": {
				"confidence": 9,
				"authenticationResultCode": "ValidCredentials",
				"brandLogoUri": "http://dev.virtualearth.net/Branding/logo_powered_by.png",
				"copyright": "Copyright © 2017 Microsoft and its suppliers. All rights reserved. This API cannot be accessed and the content and any results may not be used, reproduced or transmitted in any manner without express written permission from Microsoft Corporation.",
				"entityType": "Address",
				"matchCodes": [
					"Good"
				],
				"name": "303 Selkirk Ave, Winnipeg, MB R2W 2L8, Canada",
				"statusCode": 200,
				"statusDescription": "OK",
				"traceId": "263e53f67f634d10a5e55751237acca4|BN20130521|7.7.0.0|",
				"addressLine": "303 Selkirk Ave",
				"adminDistrict": "MB",
				"adminDistrict2": "Manitoba",
				"countryRegion": "Canada",
				"formattedAddress": "303 Selkirk Ave, Winnipeg, MB R2W 2L8, Canada",
				"locality": "Winnipeg",
				"neighborhood": "William Whyte",
				"postalCode": "R2W 2L8"
			},
			"geometry": {
				"type": "Point",
				"coordinates": [
					-97.13684,
					49.91329
				]
			},
			"bbox": [
				-97.1385857,
				49.9121658,
				-97.1350943,
				49.9144142
			]
		}
	]
}
