{
	"type": "FeatureCollection",
	"features": [
		{
			"type": "Feature",
			"properties": {
				"confidence": 9,
				"authenticationResultCode": "ValidCredentials",
				"brandLogoUri": "http://dev.virtualearth.net/Branding/logo_powered_by.png",
				"copyright": "Copyright © 2017 Microsoft and its suppliers. All rights reserved. This API cannot be accessed and the content and any results may not be used, reproduced or transmitted in any manner without express written permission from Microsoft Corporation.",
				"entityType": "Address",
				"matchCodes": [
					"Good"
				],
				"name": "303 Etter Rd, Mt Uniacke, NS B0N 1Z0, Canada",
				"statusCode": 200,
				"statusDescription": "OK",
				"traceId": "37a8bd68f8a142b2879d47e3e337addf|BN20290118|7.7.0.0|",
				"addressLine": "303 Etter Rd",
				"adminDistrict": "NS",
				"adminDistrict2": "Hants",
				"countryRegion": "Canada",
				"formattedAddress": "303 Etter Rd, Mt Uniacke, NS B0N 1Z0, Canada",
				"locality": "East Hants",
				"neighborhood": "Mt Uniacke",
				"postalCode": "B0N 1Z0"
			},
			"geometry": {
				"type": "Point",
				"coordinates": [
					-63.80892,
					44.87571
				]
			},
			"bbox": [
				-63.8105064,
				44.8745858,
				-63.8073336,
				44.8768342
			]
		}
	]
}
