{
	"type": "FeatureCollection",
	"features": [
		{
			"type": "Feature",
			"properties": {
				"confidence": 9,
				"authenticationResultCode": "ValidCredentials",
				"brandLogoUri": "http://dev.virtualearth.net/Branding/logo_powered_by.png",
				"copyright": "Copyright © 2017 Microsoft and its suppliers. All rights reserved. This API cannot be accessed and the content and any results may not be used, reproduced or transmitted in any manner without express written permission from Microsoft Corporation.",
				"entityType": "Address",
				"matchCodes": [
					"Good"
				],
				"name": "3030 40th St SE, Salmon Arm, BC V1E 1X7, Canada",
				"statusCode": 200,
				"statusDescription": "OK",
				"traceId": "36be1a659fb542898ffbaea63630dfea|BN20130423|7.7.0.0|",
				"addressLine": "3030 40th St SE",
				"adminDistrict": "BC",
				"adminDistrict2": "Columbia-Shuswap",
				"countryRegion": "Canada",
				"formattedAddress": "3030 40th St SE, Salmon Arm, BC V1E 1X7, Canada",
				"locality": "Salmon Arm",
				"postalCode": "V1E 1X7"
			},
			"geometry": {
				"type": "Point",
				"coordinates": [
					-119.2388851,
					50.6767606
				]
			},
			"bbox": [
				-119.2406591,
				50.6756364,
				-119.2371111,
				50.6778848
			]
		}
	]
}
