{
	"type": "FeatureCollection",
	"features": [
		{
			"type": "Feature",
			"properties": {
				"confidence": 9,
				"authenticationResultCode": "ValidCredentials",
				"brandLogoUri": "http://dev.virtualearth.net/Branding/logo_powered_by.png",
				"copyright": "Copyright © 2017 Microsoft and its suppliers. All rights reserved. This API cannot be accessed and the content and any results may not be used, reproduced or transmitted in any manner without express written permission from Microsoft Corporation.",
				"entityType": "Address",
				"matchCodes": [
					"Good"
				],
				"name": "3030 St Johns St, Port Moody, BC V3H 2C5, Canada",
				"statusCode": 200,
				"statusDescription": "OK",
				"traceId": "99cf837f3cf74687892252892ed7e8a6|BN20190653|7.7.0.0|",
				"addressLine": "3030 St Johns St",
				"adminDistrict": "BC",
				"adminDistrict2": "Greater Vancouver",
				"countryRegion": "Canada",
				"formattedAddress": "3030 St Johns St, Port Moody, BC V3H 2C5, Canada",
				"locality": "Port Moody",
				"postalCode": "V3H 2C5"
			},
			"geometry": {
				"type": "Point",
				"coordinates": [
					-122.8439991,
					49.2767849
				]
			},
			"bbox": [
				-122.8457222,
				49.2756607,
				-122.842276,
				49.2779091
			]
		}
	]
}
