{
	"type": "FeatureCollection",
	"features": [
		{
			"type": "Feature",
			"properties": {
				"confidence": 9,
				"authenticationResultCode": "ValidCredentials",
				"brandLogoUri": "http://dev.virtualearth.net/Branding/logo_powered_by.png",
				"copyright": "Copyright © 2017 Microsoft and its suppliers. All rights reserved. This API cannot be accessed and the content and any results may not be used, reproduced or transmitted in any manner without express written permission from Microsoft Corporation.",
				"entityType": "Address",
				"matchCodes": [
					"Good"
				],
				"name": "306 20th St E, Saskatoon, SK S7K 0A7, Canada",
				"statusCode": 200,
				"statusDescription": "OK",
				"traceId": "6b2b38b2268e461ab51b45478753cab2|BN20280152|7.7.0.0|",
				"addressLine": "306 20th St E",
				"adminDistrict": "SK",
				"adminDistrict2": "Saskatchewan",
				"countryRegion": "Canada",
				"formattedAddress": "306 20th St E, Saskatoon, SK S7K 0A7, Canada",
				"locality": "Saskatoon",
				"neighborhood": "Central Business District",
				"postalCode": "S7K 0A7"
			},
			"geometry": {
				"type": "Point",
				"coordinates": [
					-106.66283,
					52.12558
				]
			},
			"bbox": [
				-106.6646611,
				52.1244558,
				-106.6609989,
				52.1267042
			]
		}
	]
}
