{
	"type": "FeatureCollection",
	"features": [
		{
			"type": "Feature",
			"properties": {
				"confidence": 9,
				"authenticationResultCode": "ValidCredentials",
				"brandLogoUri": "http://dev.virtualearth.net/Branding/logo_powered_by.png",
				"copyright": "Copyright © 2017 Microsoft and its suppliers. All rights reserved. This API cannot be accessed and the content and any results may not be used, reproduced or transmitted in any manner without express written permission from Microsoft Corporation.",
				"entityType": "Address",
				"matchCodes": [
					"Good"
				],
				"name": "3067 Emperor Dr, Orillia, ON L3V 0G4, Canada",
				"statusCode": 200,
				"statusDescription": "OK",
				"traceId": "f0a7202214b647ada4ea42294b9d0c28|BN20121762|7.7.0.0|",
				"addressLine": "3067 Emperor Dr",
				"adminDistrict": "ON",
				"adminDistrict2": "Simcoe",
				"countryRegion": "Canada",
				"formattedAddress": "3067 Emperor Dr, Orillia, ON L3V 0G4, Canada",
				"locality": "Orillia",
				"postalCode": "L3V 0G4"
			},
			"geometry": {
				"type": "Point",
				"coordinates": [
					-79.4576242,
					44.6019721
				]
			},
			"bbox": [
				-79.459203,
				44.6008479,
				-79.4560453,
				44.6030962
			]
		}
	]
}
