{
	"type": "FeatureCollection",
	"features": [
		{
			"type": "Feature",
			"properties": {
				"confidence": 9,
				"authenticationResultCode": "ValidCredentials",
				"brandLogoUri": "http://dev.virtualearth.net/Branding/logo_powered_by.png",
				"copyright": "Copyright © 2017 Microsoft and its suppliers. All rights reserved. This API cannot be accessed and the content and any results may not be used, reproduced or transmitted in any manner without express written permission from Microsoft Corporation.",
				"entityType": "Address",
				"matchCodes": [
					"Good"
				],
				"name": "3074 Sawmill Rd, St Jacobs, ON N0B 2N0, Canada",
				"statusCode": 200,
				"statusDescription": "OK",
				"traceId": "417c4a97a9154c0e8ed750906a4aa7d5|BN20240253|7.7.0.0|",
				"addressLine": "3074 Sawmill Rd",
				"adminDistrict": "ON",
				"adminDistrict2": "Waterloo",
				"countryRegion": "Canada",
				"formattedAddress": "3074 Sawmill Rd, St Jacobs, ON N0B 2N0, Canada",
				"locality": "Woolwich",
				"neighborhood": "St Jacobs",
				"postalCode": "N0B 2N0"
			},
			"geometry": {
				"type": "Point",
				"coordinates": [
					-80.55094,
					43.54564
				]
			},
			"bbox": [
				-80.5524909,
				43.5445158,
				-80.5493891,
				43.5467642
			]
		}
	]
}
