{
	"type": "FeatureCollection",
	"features": [
		{
			"type": "Feature",
			"properties": {
				"confidence": 9,
				"authenticationResultCode": "ValidCredentials",
				"brandLogoUri": "http://dev.virtualearth.net/Branding/logo_powered_by.png",
				"copyright": "Copyright © 2017 Microsoft and its suppliers. All rights reserved. This API cannot be accessed and the content and any results may not be used, reproduced or transmitted in any manner without express written permission from Microsoft Corporation.",
				"entityType": "Address",
				"matchCodes": [
					"Good"
				],
				"name": "308 Whisperwood Ave, London, ON N6K 3Y6, Canada",
				"statusCode": 200,
				"statusDescription": "OK",
				"traceId": "7c2f745c9f494cae9a9c446c89001bd3|BN20130631|7.7.0.0|",
				"addressLine": "308 Whisperwood Ave",
				"adminDistrict": "ON",
				"adminDistrict2": "Middlesex",
				"countryRegion": "Canada",
				"formattedAddress": "308 Whisperwood Ave, London, ON N6K 3Y6, Canada",
				"locality": "London",
				"neighborhood": "Byron",
				"postalCode": "N6K 3Y6"
			},
			"geometry": {
				"type": "Point",
				"coordinates": [
					-81.3258,
					42.9519
				]
			},
			"bbox": [
				-81.3273359,
				42.9507758,
				-81.3242641,
				42.9530242
			]
		}
	]
}
