{
	"type": "FeatureCollection",
	"features": [
		{
			"type": "Feature",
			"properties": {
				"confidence": 9,
				"authenticationResultCode": "ValidCredentials",
				"brandLogoUri": "http://dev.virtualearth.net/Branding/logo_powered_by.png",
				"copyright": "Copyright © 2017 Microsoft and its suppliers. All rights reserved. This API cannot be accessed and the content and any results may not be used, reproduced or transmitted in any manner without express written permission from Microsoft Corporation.",
				"entityType": "Address",
				"matchCodes": [
					"Good"
				],
				"name": "3091 9th Line, Mississauga, ON L5L, Canada",
				"statusCode": 200,
				"statusDescription": "OK",
				"traceId": "dff07fc76eea4ffcbc1948202f751f11|BN20130423|7.7.0.0|",
				"addressLine": "3091 9th Line",
				"adminDistrict": "ON",
				"adminDistrict2": "Peel",
				"countryRegion": "Canada",
				"formattedAddress": "3091 9th Line, Mississauga, ON L5L, Canada",
				"locality": "Mississauga",
				"neighborhood": "Erin Mills",
				"postalCode": "L5L 5Z6"
			},
			"geometry": {
				"type": "Point",
				"coordinates": [
					-79.70173,
					43.51221
				]
			},
			"bbox": [
				-79.7032801,
				43.5110858,
				-79.7001799,
				43.5133342
			]
		}
	]
}
