{
	"type": "FeatureCollection",
	"features": [
		{
			"type": "Feature",
			"properties": {
				"confidence": 9,
				"authenticationResultCode": "ValidCredentials",
				"brandLogoUri": "http://dev.virtualearth.net/Branding/logo_powered_by.png",
				"copyright": "Copyright © 2017 Microsoft and its suppliers. All rights reserved. This API cannot be accessed and the content and any results may not be used, reproduced or transmitted in any manner without express written permission from Microsoft Corporation.",
				"entityType": "Address",
				"matchCodes": [
					"Good"
				],
				"name": "31 Norris Clos, Red Deer, AB T4P 1R2, Canada",
				"statusCode": 200,
				"statusDescription": "OK",
				"traceId": "8e7f576d9b7a4b4bbcf7aadaa2f9631b|BN20260223|7.7.0.0|",
				"addressLine": "31 Norris Clos",
				"adminDistrict": "AB",
				"adminDistrict2": "Alberta",
				"countryRegion": "Canada",
				"formattedAddress": "31 Norris Clos, Red Deer, AB T4P 1R2, Canada",
				"locality": "Red Deer",
				"postalCode": "T4P 1R2"
			},
			"geometry": {
				"type": "Point",
				"coordinates": [
					-113.82248,
					52.29375
				]
			},
			"bbox": [
				-113.824318,
				52.2926258,
				-113.820642,
				52.2948742
			]
		}
	]
}
