{
	"type": "FeatureCollection",
	"features": [
		{
			"type": "Feature",
			"properties": {
				"confidence": 9,
				"authenticationResultCode": "ValidCredentials",
				"brandLogoUri": "http://dev.virtualearth.net/Branding/logo_powered_by.png",
				"copyright": "Copyright © 2017 Microsoft and its suppliers. All rights reserved. This API cannot be accessed and the content and any results may not be used, reproduced or transmitted in any manner without express written permission from Microsoft Corporation.",
				"entityType": "Address",
				"matchCodes": [
					"Good"
				],
				"name": "31 Sterns Ct, Dartmouth, NS B3B 1W7, Canada",
				"statusCode": 200,
				"statusDescription": "OK",
				"traceId": "3b7acf27d85d47d0a37b89cb57410639|BN20240253|7.7.0.0|",
				"addressLine": "31 Sterns Ct",
				"adminDistrict": "NS",
				"adminDistrict2": "Halifax",
				"countryRegion": "Canada",
				"formattedAddress": "31 Sterns Ct, Dartmouth, NS B3B 1W7, Canada",
				"locality": "Halifax",
				"neighborhood": "Dartmouth",
				"postalCode": "B3B 1W7"
			},
			"geometry": {
				"type": "Point",
				"coordinates": [
					-63.59982,
					44.71628
				]
			},
			"bbox": [
				-63.601402,
				44.7151558,
				-63.598238,
				44.7174042
			]
		}
	]
}
