{
	"type": "FeatureCollection",
	"features": [
		{
			"type": "Feature",
			"properties": {
				"confidence": 9,
				"authenticationResultCode": "ValidCredentials",
				"brandLogoUri": "http://dev.virtualearth.net/Branding/logo_powered_by.png",
				"copyright": "Copyright © 2017 Microsoft and its suppliers. All rights reserved. This API cannot be accessed and the content and any results may not be used, reproduced or transmitted in any manner without express written permission from Microsoft Corporation.",
				"entityType": "Address",
				"matchCodes": [
					"Good"
				],
				"name": "31 Tapscott Rd, Scarborough, ON M1B 4Y7, Canada",
				"statusCode": 200,
				"statusDescription": "OK",
				"traceId": "8ef6cfeef55d472d934fa245e3661666|BN20181720|7.7.0.0|",
				"addressLine": "31 Tapscott Rd",
				"adminDistrict": "ON",
				"adminDistrict2": "Toronto",
				"countryRegion": "Canada",
				"formattedAddress": "31 Tapscott Rd, Scarborough, ON M1B 4Y7, Canada",
				"locality": "Toronto",
				"neighborhood": "Malvern",
				"postalCode": "M1B 4Y7"
			},
			"geometry": {
				"type": "Point",
				"coordinates": [
					-79.2211766,
					43.8055878
				]
			},
			"bbox": [
				-79.2227342,
				43.8044636,
				-79.2196189,
				43.8067119
			]
		}
	]
}
