{
	"type": "FeatureCollection",
	"features": [
		{
			"type": "Feature",
			"properties": {
				"confidence": 9,
				"authenticationResultCode": "ValidCredentials",
				"brandLogoUri": "http://dev.virtualearth.net/Branding/logo_powered_by.png",
				"copyright": "Copyright © 2017 Microsoft and its suppliers. All rights reserved. This API cannot be accessed and the content and any results may not be used, reproduced or transmitted in any manner without express written permission from Microsoft Corporation.",
				"entityType": "Address",
				"matchCodes": [
					"Good"
				],
				"name": "3105 Chemin Kingsway, Greater Sudbury, ON P3B 2G5, Canada",
				"statusCode": 200,
				"statusDescription": "OK",
				"traceId": "a44a094cb7464fbf9806e67ac1c12b1b|BN20130520|7.7.0.0|",
				"addressLine": "3105 Chemin Kingsway",
				"adminDistrict": "ON",
				"adminDistrict2": "Greater Sudbury",
				"countryRegion": "Canada",
				"formattedAddress": "3105 Chemin Kingsway, Greater Sudbury, ON P3B 2G5, Canada",
				"locality": "Greater Sudbury",
				"neighborhood": "Sudbury",
				"postalCode": "P3B 2G5"
			},
			"geometry": {
				"type": "Point",
				"coordinates": [
					-80.8990545,
					46.4938344
				]
			},
			"bbox": [
				-80.9006875,
				46.4927103,
				-80.8974216,
				46.4949586
			]
		}
	]
}
