{
	"type": "FeatureCollection",
	"features": [
		{
			"type": "Feature",
			"properties": {
				"confidence": 9,
				"authenticationResultCode": "ValidCredentials",
				"brandLogoUri": "http://dev.virtualearth.net/Branding/logo_powered_by.png",
				"copyright": "Copyright © 2017 Microsoft and its suppliers. All rights reserved. This API cannot be accessed and the content and any results may not be used, reproduced or transmitted in any manner without express written permission from Microsoft Corporation.",
				"entityType": "Address",
				"matchCodes": [
					"Good"
				],
				"name": "311 Hemlock, Port McNeill, BC V0N, Canada",
				"statusCode": 200,
				"statusDescription": "OK",
				"traceId": "40ccea620529494b8deeefb260182410|BN20130520|7.7.0.0|",
				"addressLine": "311 Hemlock",
				"adminDistrict": "BC",
				"adminDistrict2": "Mt Waddington",
				"countryRegion": "Canada",
				"formattedAddress": "311 Hemlock, Port McNeill, BC V0N, Canada",
				"locality": "Port McNeill",
				"postalCode": "V0N 2R0"
			},
			"geometry": {
				"type": "Point",
				"coordinates": [
					-127.08559,
					50.58775
				]
			},
			"bbox": [
				-127.0873606,
				50.5866258,
				-127.0838194,
				50.5888742
			]
		}
	]
}
