{
	"type": "FeatureCollection",
	"features": [
		{
			"type": "Feature",
			"properties": {
				"confidence": 9,
				"authenticationResultCode": "ValidCredentials",
				"brandLogoUri": "http://dev.virtualearth.net/Branding/logo_powered_by.png",
				"copyright": "Copyright © 2017 Microsoft and its suppliers. All rights reserved. This API cannot be accessed and the content and any results may not be used, reproduced or transmitted in any manner without express written permission from Microsoft Corporation.",
				"entityType": "Address",
				"matchCodes": [
					"Good"
				],
				"name": "3111 Shepard Pl SE, Calgary, AB T2C 4P1, Canada",
				"statusCode": 200,
				"statusDescription": "OK",
				"traceId": "111c6815129146f09f116a24fa828c8d|BN20260223|7.7.0.0|",
				"addressLine": "3111 Shepard Pl SE",
				"adminDistrict": "AB",
				"adminDistrict2": "Alberta",
				"countryRegion": "Canada",
				"formattedAddress": "3111 Shepard Pl SE, Calgary, AB T2C 4P1, Canada",
				"locality": "Calgary",
				"postalCode": "T2C 4P1"
			},
			"geometry": {
				"type": "Point",
				"coordinates": [
					-113.99109,
					50.96722
				]
			},
			"bbox": [
				-113.992875,
				50.9660958,
				-113.989305,
				50.9683442
			]
		}
	]
}
