{
	"type": "FeatureCollection",
	"features": [
		{
			"type": "Feature",
			"properties": {
				"confidence": 9,
				"authenticationResultCode": "ValidCredentials",
				"brandLogoUri": "http://dev.virtualearth.net/Branding/logo_powered_by.png",
				"copyright": "Copyright © 2017 Microsoft and its suppliers. All rights reserved. This API cannot be accessed and the content and any results may not be used, reproduced or transmitted in any manner without express written permission from Microsoft Corporation.",
				"entityType": "Address",
				"matchCodes": [
					"Good"
				],
				"name": "312 HWY-305, Dalmeny, SK S0K, Canada",
				"statusCode": 200,
				"statusDescription": "OK",
				"traceId": "c8a294ec555e497198353d2076ddfec9|BN20200137|7.7.0.0|",
				"addressLine": "312 HWY-305",
				"adminDistrict": "SK",
				"adminDistrict2": "Saskatchewan",
				"countryRegion": "Canada",
				"formattedAddress": "312 HWY-305, Dalmeny, SK S0K, Canada",
				"locality": "Dalmeny",
				"postalCode": "S0K 1E0"
			},
			"geometry": {
				"type": "Point",
				"coordinates": [
					-106.7734196,
					52.3390387
				]
			},
			"bbox": [
				-106.7752595,
				52.3379145,
				-106.7715797,
				52.3401628
			]
		}
	]
}
