{
	"type": "FeatureCollection",
	"features": [
		{
			"type": "Feature",
			"properties": {
				"confidence": 9,
				"authenticationResultCode": "ValidCredentials",
				"brandLogoUri": "http://dev.virtualearth.net/Branding/logo_powered_by.png",
				"copyright": "Copyright © 2017 Microsoft and its suppliers. All rights reserved. This API cannot be accessed and the content and any results may not be used, reproduced or transmitted in any manner without express written permission from Microsoft Corporation.",
				"entityType": "Address",
				"matchCodes": [
					"Good"
				],
				"name": "313 Schooner Cv NW, Calgary, AB T3L 1Z3, Canada",
				"statusCode": 200,
				"statusDescription": "OK",
				"traceId": "90fb36ec760f44e1bcf9ab9466b36037|BN20130634|7.7.0.0|",
				"addressLine": "313 Schooner Cv NW",
				"adminDistrict": "AB",
				"adminDistrict2": "Alberta",
				"countryRegion": "Canada",
				"formattedAddress": "313 Schooner Cv NW, Calgary, AB T3L 1Z3, Canada",
				"locality": "Calgary",
				"neighborhood": "Scenic Acres",
				"postalCode": "T3L 1Z3"
			},
			"geometry": {
				"type": "Point",
				"coordinates": [
					-114.22925,
					51.12205
				]
			},
			"bbox": [
				-114.231041,
				51.1209258,
				-114.227459,
				51.1231742
			]
		}
	]
}
