{
	"type": "FeatureCollection",
	"features": [
		{
			"type": "Feature",
			"properties": {
				"confidence": 9,
				"authenticationResultCode": "ValidCredentials",
				"brandLogoUri": "http://dev.virtualearth.net/Branding/logo_powered_by.png",
				"copyright": "Copyright © 2017 Microsoft and its suppliers. All rights reserved. This API cannot be accessed and the content and any results may not be used, reproduced or transmitted in any manner without express written permission from Microsoft Corporation.",
				"entityType": "Address",
				"matchCodes": [
					"Good"
				],
				"name": "3154 265B St, Aldergrove, BC V4W 3E8, Canada",
				"statusCode": 200,
				"statusDescription": "OK",
				"traceId": "f47f88d4fb3f4d5ebdce6b4fb2567e0f|BN20121764|7.7.0.0|",
				"addressLine": "3154 265B St",
				"adminDistrict": "BC",
				"adminDistrict2": "Greater Vancouver",
				"countryRegion": "Canada",
				"formattedAddress": "3154 265B St, Aldergrove, BC V4W 3E8, Canada",
				"locality": "Langley",
				"neighborhood": "Aldergrove",
				"postalCode": "V4W 3E8"
			},
			"geometry": {
				"type": "Point",
				"coordinates": [
					-122.4879151,
					49.0599938
				]
			},
			"bbox": [
				-122.4896307,
				49.0588697,
				-122.4861995,
				49.061118
			]
		}
	]
}
