{
	"type": "FeatureCollection",
	"features": [
		{
			"type": "Feature",
			"properties": {
				"confidence": 9,
				"authenticationResultCode": "ValidCredentials",
				"brandLogoUri": "http://dev.virtualearth.net/Branding/logo_powered_by.png",
				"copyright": "Copyright © 2017 Microsoft and its suppliers. All rights reserved. This API cannot be accessed and the content and any results may not be used, reproduced or transmitted in any manner without express written permission from Microsoft Corporation.",
				"entityType": "Address",
				"matchCodes": [
					"Good"
				],
				"name": "316 HWY-555, Woodstock Parish, NB E7M 4P1, Canada",
				"statusCode": 200,
				"statusDescription": "OK",
				"traceId": "7ed26322bcab4e449981ff8d1d2ad3fa|BN20130532|7.7.0.0|",
				"addressLine": "316 HWY-555",
				"adminDistrict": "NB",
				"adminDistrict2": "Carleton",
				"countryRegion": "Canada",
				"formattedAddress": "316 HWY-555, Woodstock Parish, NB E7M 4P1, Canada",
				"locality": "Woodstock Parish",
				"postalCode": "E7M 4P1"
			},
			"geometry": {
				"type": "Point",
				"coordinates": [
					-67.6314201,
					46.1460642
				]
			},
			"bbox": [
				-67.6330427,
				46.14494,
				-67.6297975,
				46.1471883
			]
		}
	]
}
