{
	"type": "FeatureCollection",
	"features": [
		{
			"type": "Feature",
			"properties": {
				"confidence": 9,
				"authenticationResultCode": "ValidCredentials",
				"brandLogoUri": "http://dev.virtualearth.net/Branding/logo_powered_by.png",
				"copyright": "Copyright © 2017 Microsoft and its suppliers. All rights reserved. This API cannot be accessed and the content and any results may not be used, reproduced or transmitted in any manner without express written permission from Microsoft Corporation.",
				"entityType": "Address",
				"matchCodes": [
					"Good"
				],
				"name": "3175 McCallum Rd, Abbotsford, BC V2S, Canada",
				"statusCode": 200,
				"statusDescription": "OK",
				"traceId": "169176f449e04a0f9c3801312c413b45|BN20200137|7.7.0.0|",
				"addressLine": "3175 McCallum Rd",
				"adminDistrict": "BC",
				"adminDistrict2": "Fraser Valley",
				"countryRegion": "Canada",
				"formattedAddress": "3175 McCallum Rd, Abbotsford, BC V2S, Canada",
				"locality": "Abbotsford",
				"neighborhood": "Lower Ten Oaks",
				"postalCode": "V2S 7W2"
			},
			"geometry": {
				"type": "Point",
				"coordinates": [
					-122.29398,
					49.05978
				]
			},
			"bbox": [
				-122.2956956,
				49.0586558,
				-122.2922644,
				49.0609042
			]
		}
	]
}
