{
	"type": "FeatureCollection",
	"features": [
		{
			"type": "Feature",
			"properties": {
				"confidence": 9,
				"authenticationResultCode": "ValidCredentials",
				"brandLogoUri": "http://dev.virtualearth.net/Branding/logo_powered_by.png",
				"copyright": "Copyright © 2017 Microsoft and its suppliers. All rights reserved. This API cannot be accessed and the content and any results may not be used, reproduced or transmitted in any manner without express written permission from Microsoft Corporation.",
				"entityType": "Address",
				"matchCodes": [
					"Good"
				],
				"name": "319 Winston Blvd, Cambridge, ON N3C 3C4, Canada",
				"statusCode": 200,
				"statusDescription": "OK",
				"traceId": "182ddda0f37545aeb2cb3204e1b7e34f|BN20130721|7.7.0.0|",
				"addressLine": "319 Winston Blvd",
				"adminDistrict": "ON",
				"adminDistrict2": "Waterloo",
				"countryRegion": "Canada",
				"formattedAddress": "319 Winston Blvd, Cambridge, ON N3C 3C4, Canada",
				"locality": "Cambridge",
				"neighborhood": "Hespeler Village",
				"postalCode": "N3C 3C4"
			},
			"geometry": {
				"type": "Point",
				"coordinates": [
					-80.3041,
					43.42162
				]
			},
			"bbox": [
				-80.3056477,
				43.4204958,
				-80.3025523,
				43.4227442
			]
		}
	]
}
