{
	"type": "FeatureCollection",
	"features": [
		{
			"type": "Feature",
			"properties": {
				"confidence": 9,
				"authenticationResultCode": "ValidCredentials",
				"brandLogoUri": "http://dev.virtualearth.net/Branding/logo_powered_by.png",
				"copyright": "Copyright © 2017 Microsoft and its suppliers. All rights reserved. This API cannot be accessed and the content and any results may not be used, reproduced or transmitted in any manner without express written permission from Microsoft Corporation.",
				"entityType": "Address",
				"matchCodes": [
					"Good"
				],
				"name": "3190 Shelbourne St, Victoria, BC V8T 3A8, Canada",
				"statusCode": 200,
				"statusDescription": "OK",
				"traceId": "eb4ca0df053641ddb2f8e3fbf1d9b79b|BN20280152|7.7.0.0|",
				"addressLine": "3190 Shelbourne St",
				"adminDistrict": "BC",
				"adminDistrict2": "Capital",
				"countryRegion": "Canada",
				"formattedAddress": "3190 Shelbourne St, Victoria, BC V8T 3A8, Canada",
				"locality": "Victoria",
				"neighborhood": "Oaklands",
				"postalCode": "V8T 3A8"
			},
			"geometry": {
				"type": "Point",
				"coordinates": [
					-123.33364,
					48.44718
				]
			},
			"bbox": [
				-123.3353348,
				48.4460558,
				-123.3319452,
				48.4483042
			]
		}
	]
}
