{
	"type": "FeatureCollection",
	"features": [
		{
			"type": "Feature",
			"properties": {
				"confidence": 9,
				"authenticationResultCode": "ValidCredentials",
				"brandLogoUri": "http://dev.virtualearth.net/Branding/logo_powered_by.png",
				"copyright": "Copyright © 2017 Microsoft and its suppliers. All rights reserved. This API cannot be accessed and the content and any results may not be used, reproduced or transmitted in any manner without express written permission from Microsoft Corporation.",
				"entityType": "Address",
				"matchCodes": [
					"Good"
				],
				"name": "3195 Production Way, Burnaby, BC V5A 3H2, Canada",
				"statusCode": 200,
				"statusDescription": "OK",
				"traceId": "97fe1c31fad84908b1d5b1164fae3137|BN20260231|7.7.0.0|",
				"addressLine": "3195 Production Way",
				"adminDistrict": "BC",
				"adminDistrict2": "Greater Vancouver",
				"countryRegion": "Canada",
				"formattedAddress": "3195 Production Way, Burnaby, BC V5A 3H2, Canada",
				"locality": "Burnaby",
				"neighborhood": "Lake City",
				"postalCode": "V5A 3H2"
			},
			"geometry": {
				"type": "Point",
				"coordinates": [
					-122.91959,
					49.25489
				]
			},
			"bbox": [
				-122.9213123,
				49.2537658,
				-122.9178677,
				49.2560142
			]
		}
	]
}
