{
	"type": "FeatureCollection",
	"features": [
		{
			"type": "Feature",
			"properties": {
				"confidence": 9,
				"authenticationResultCode": "ValidCredentials",
				"brandLogoUri": "http://dev.virtualearth.net/Branding/logo_powered_by.png",
				"copyright": "Copyright © 2017 Microsoft and its suppliers. All rights reserved. This API cannot be accessed and the content and any results may not be used, reproduced or transmitted in any manner without express written permission from Microsoft Corporation.",
				"entityType": "Address",
				"matchCodes": [
					"Good"
				],
				"name": "32 Goulbourn St, Ottawa, ON K2S, Canada",
				"statusCode": 200,
				"statusDescription": "OK",
				"traceId": "4b5fc8c9277d49b48828796e827c039d|BN20240423|7.7.0.0|",
				"addressLine": "32 Goulbourn St",
				"adminDistrict": "ON",
				"adminDistrict2": "Ottawa",
				"countryRegion": "Canada",
				"formattedAddress": "32 Goulbourn St, Ottawa, ON K2S, Canada",
				"locality": "Ottawa",
				"neighborhood": "Stittsville",
				"postalCode": "K2S 1P4"
			},
			"geometry": {
				"type": "Point",
				"coordinates": [
					-75.91889,
					45.2523
				]
			},
			"bbox": [
				-75.9204868,
				45.2511758,
				-75.9172932,
				45.2534242
			]
		}
	]
}
