{
	"type": "FeatureCollection",
	"features": [
		{
			"type": "Feature",
			"properties": {
				"confidence": 9,
				"authenticationResultCode": "ValidCredentials",
				"brandLogoUri": "http://dev.virtualearth.net/Branding/logo_powered_by.png",
				"copyright": "Copyright © 2017 Microsoft and its suppliers. All rights reserved. This API cannot be accessed and the content and any results may not be used, reproduced or transmitted in any manner without express written permission from Microsoft Corporation.",
				"entityType": "Address",
				"matchCodes": [
					"Good"
				],
				"name": "320 65 Ave SE, Calgary, AB T2H 0R8, Canada",
				"statusCode": 200,
				"statusDescription": "OK",
				"traceId": "6bc9a4e5e36c4d9bbebd4785775bca90|BN20130442|7.7.0.0|",
				"addressLine": "320 65 Ave SE",
				"adminDistrict": "AB",
				"adminDistrict2": "Alberta",
				"countryRegion": "Canada",
				"formattedAddress": "320 65 Ave SE, Calgary, AB T2H 0R8, Canada",
				"locality": "Calgary",
				"neighborhood": "Alyth-Bonnybrook-Manchester",
				"postalCode": "T2H 0R8"
			},
			"geometry": {
				"type": "Point",
				"coordinates": [
					-114.0594439,
					50.9944127
				]
			},
			"bbox": [
				-114.06123,
				50.9932885,
				-114.0576578,
				50.9955369
			]
		}
	]
}
