{
	"type": "FeatureCollection",
	"features": [
		{
			"type": "Feature",
			"properties": {
				"confidence": 9,
				"authenticationResultCode": "ValidCredentials",
				"brandLogoUri": "http://dev.virtualearth.net/Branding/logo_powered_by.png",
				"copyright": "Copyright © 2017 Microsoft and its suppliers. All rights reserved. This API cannot be accessed and the content and any results may not be used, reproduced or transmitted in any manner without express written permission from Microsoft Corporation.",
				"entityType": "Address",
				"matchCodes": [
					"Good"
				],
				"name": "321 Parkhurst Sq, Brampton, ON L6T 5H5, Canada",
				"statusCode": 200,
				"statusDescription": "OK",
				"traceId": "4a5cee167a32437fab921666bf28f4e0|BN20210145|7.7.0.0|",
				"addressLine": "321 Parkhurst Sq",
				"adminDistrict": "ON",
				"adminDistrict2": "Peel",
				"countryRegion": "Canada",
				"formattedAddress": "321 Parkhurst Sq, Brampton, ON L6T 5H5, Canada",
				"locality": "Brampton",
				"neighborhood": "Castlemore",
				"postalCode": "L6T 5H5"
			},
			"geometry": {
				"type": "Point",
				"coordinates": [
					-79.66826,
					43.72546
				]
			},
			"bbox": [
				-79.6698156,
				43.7243358,
				-79.6667044,
				43.7265842
			]
		}
	]
}
