{
	"type": "FeatureCollection",
	"features": [
		{
			"type": "Feature",
			"properties": {
				"confidence": 9,
				"authenticationResultCode": "ValidCredentials",
				"brandLogoUri": "http://dev.virtualearth.net/Branding/logo_powered_by.png",
				"copyright": "Copyright © 2017 Microsoft and its suppliers. All rights reserved. This API cannot be accessed and the content and any results may not be used, reproduced or transmitted in any manner without express written permission from Microsoft Corporation.",
				"entityType": "Address",
				"matchCodes": [
					"Good"
				],
				"name": "322 DR-3, Huntsville, ON P1H 1C4, Canada",
				"statusCode": 200,
				"statusDescription": "OK",
				"traceId": "33d796026a404dbb95bec3fad5cf6a0e|BN20121762|7.7.0.0|",
				"addressLine": "322 DR-3",
				"adminDistrict": "ON",
				"adminDistrict2": "Muskoka",
				"countryRegion": "Canada",
				"formattedAddress": "322 DR-3, Huntsville, ON P1H 1C4, Canada",
				"locality": "Huntsville",
				"postalCode": "P1H 1C4"
			},
			"geometry": {
				"type": "Point",
				"coordinates": [
					-79.2032998,
					45.3378933
				]
			},
			"bbox": [
				-79.2048991,
				45.3367691,
				-79.2017006,
				45.3390174
			]
		}
	]
}
