{
	"type": "FeatureCollection",
	"features": [
		{
			"type": "Feature",
			"properties": {
				"confidence": 9,
				"authenticationResultCode": "ValidCredentials",
				"brandLogoUri": "http://dev.virtualearth.net/Branding/logo_powered_by.png",
				"copyright": "Copyright © 2017 Microsoft and its suppliers. All rights reserved. This API cannot be accessed and the content and any results may not be used, reproduced or transmitted in any manner without express written permission from Microsoft Corporation.",
				"entityType": "Address",
				"matchCodes": [
					"Good"
				],
				"name": "325 Muskoka Rd S, Gravenhurst, ON P1P 1J1, Canada",
				"statusCode": 200,
				"statusDescription": "OK",
				"traceId": "3c3587fc62584874a90f68e65e4b49f7|BN20171457|7.7.0.0|",
				"addressLine": "325 Muskoka Rd S",
				"adminDistrict": "ON",
				"adminDistrict2": "Muskoka",
				"countryRegion": "Canada",
				"formattedAddress": "325 Muskoka Rd S, Gravenhurst, ON P1P 1J1, Canada",
				"locality": "Gravenhurst",
				"postalCode": "P1P 1J1"
			},
			"geometry": {
				"type": "Point",
				"coordinates": [
					-79.3736,
					44.91783
				]
			},
			"bbox": [
				-79.3751875,
				44.9167058,
				-79.3720125,
				44.9189542
			]
		}
	]
}
