{
	"type": "FeatureCollection",
	"features": [
		{
			"type": "Feature",
			"properties": {
				"confidence": 9,
				"authenticationResultCode": "ValidCredentials",
				"brandLogoUri": "http://dev.virtualearth.net/Branding/logo_powered_by.png",
				"copyright": "Copyright © 2017 Microsoft and its suppliers. All rights reserved. This API cannot be accessed and the content and any results may not be used, reproduced or transmitted in any manner without express written permission from Microsoft Corporation.",
				"entityType": "Address",
				"matchCodes": [
					"Good"
				],
				"name": "3258 Wharton Way, Mississauga, ON L4X 2C1, Canada",
				"statusCode": 200,
				"statusDescription": "OK",
				"traceId": "793a6574f6b64a14ac299b1138f29ca9|BN20250135|7.7.0.0|",
				"addressLine": "3258 Wharton Way",
				"adminDistrict": "ON",
				"adminDistrict2": "Peel",
				"countryRegion": "Canada",
				"formattedAddress": "3258 Wharton Way, Mississauga, ON L4X 2C1, Canada",
				"locality": "Mississauga",
				"neighborhood": "Dixie",
				"postalCode": "L4X 2C1"
			},
			"geometry": {
				"type": "Point",
				"coordinates": [
					-79.58111,
					43.6234899
				]
			},
			"bbox": [
				-79.5826629,
				43.6223657,
				-79.5795571,
				43.6246141
			]
		}
	]
}
