{
	"type": "FeatureCollection",
	"features": [
		{
			"type": "Feature",
			"properties": {
				"confidence": 9,
				"authenticationResultCode": "ValidCredentials",
				"brandLogoUri": "http://dev.virtualearth.net/Branding/logo_powered_by.png",
				"copyright": "Copyright © 2017 Microsoft and its suppliers. All rights reserved. This API cannot be accessed and the content and any results may not be used, reproduced or transmitted in any manner without express written permission from Microsoft Corporation.",
				"entityType": "Address",
				"matchCodes": [
					"Good"
				],
				"name": "326 Maple Ave, Tatamagouche, NS B0K 1V0, Canada",
				"statusCode": 200,
				"statusDescription": "OK",
				"traceId": "575edf9f8eee4ed9ba75199367aa49e4|BN20130719|7.7.0.0|",
				"addressLine": "326 Maple Ave",
				"adminDistrict": "NS",
				"adminDistrict2": "Colchester",
				"countryRegion": "Canada",
				"formattedAddress": "326 Maple Ave, Tatamagouche, NS B0K 1V0, Canada",
				"locality": "Colchester",
				"neighborhood": "Tatamagouche",
				"postalCode": "B0K 1V0"
			},
			"geometry": {
				"type": "Point",
				"coordinates": [
					-63.2983169,
					45.7001731
				]
			},
			"bbox": [
				-63.2999264,
				45.6990489,
				-63.2967073,
				45.7012972
			]
		}
	]
}
