{
	"type": "FeatureCollection",
	"features": [
		{
			"type": "Feature",
			"properties": {
				"confidence": 9,
				"authenticationResultCode": "ValidCredentials",
				"brandLogoUri": "http://dev.virtualearth.net/Branding/logo_powered_by.png",
				"copyright": "Copyright © 2017 Microsoft and its suppliers. All rights reserved. This API cannot be accessed and the content and any results may not be used, reproduced or transmitted in any manner without express written permission from Microsoft Corporation.",
				"entityType": "Address",
				"matchCodes": [
					"Good"
				],
				"name": "3267 Lake Shore Blvd W, Etobicoke, ON M8V 1M2, Canada",
				"statusCode": 200,
				"statusDescription": "OK",
				"traceId": "377c911785934d4ebaf654d6471237a3|BN20280152|7.7.0.0|",
				"addressLine": "3267 Lake Shore Blvd W",
				"adminDistrict": "ON",
				"adminDistrict2": "Toronto",
				"countryRegion": "Canada",
				"formattedAddress": "3267 Lake Shore Blvd W, Etobicoke, ON M8V 1M2, Canada",
				"locality": "Toronto",
				"neighborhood": "Long Branch",
				"postalCode": "M8V 1M2"
			},
			"geometry": {
				"type": "Point",
				"coordinates": [
					-79.52288,
					43.59659
				]
			},
			"bbox": [
				-79.5244322,
				43.5954658,
				-79.5213278,
				43.5977142
			]
		}
	]
}
