{
	"type": "FeatureCollection",
	"features": [
		{
			"type": "Feature",
			"properties": {
				"confidence": 9,
				"authenticationResultCode": "ValidCredentials",
				"brandLogoUri": "http://dev.virtualearth.net/Branding/logo_powered_by.png",
				"copyright": "Copyright © 2017 Microsoft and its suppliers. All rights reserved. This API cannot be accessed and the content and any results may not be used, reproduced or transmitted in any manner without express written permission from Microsoft Corporation.",
				"entityType": "Address",
				"matchCodes": [
					"Good"
				],
				"name": "327 Lockhart Mill Rd, Jacksonville, NB E7M 3S5, Canada",
				"statusCode": 200,
				"statusDescription": "OK",
				"traceId": "bb80f622a8464233960de5b7fcdc0d9f|BN20130442|7.7.0.0|",
				"addressLine": "327 Lockhart Mill Rd",
				"adminDistrict": "NB",
				"adminDistrict2": "Carleton",
				"countryRegion": "Canada",
				"formattedAddress": "327 Lockhart Mill Rd, Jacksonville, NB E7M 3S5, Canada",
				"locality": "Wakefield",
				"neighborhood": "Jacksonville",
				"postalCode": "E7M 3S5"
			},
			"geometry": {
				"type": "Point",
				"coordinates": [
					-67.6058492,
					46.1882044
				]
			},
			"bbox": [
				-67.6074731,
				46.1870802,
				-67.6042254,
				46.1893285
			]
		}
	]
}
