{
	"type": "FeatureCollection",
	"features": [
		{
			"type": "Feature",
			"properties": {
				"confidence": 9,
				"authenticationResultCode": "ValidCredentials",
				"brandLogoUri": "http://dev.virtualearth.net/Branding/logo_powered_by.png",
				"copyright": "Copyright © 2017 Microsoft and its suppliers. All rights reserved. This API cannot be accessed and the content and any results may not be used, reproduced or transmitted in any manner without express written permission from Microsoft Corporation.",
				"entityType": "Address",
				"matchCodes": [
					"Good"
				],
				"name": "328 Urquhart Ave, Moncton, NB E1H 2R6, Canada",
				"statusCode": 200,
				"statusDescription": "OK",
				"traceId": "a2b7119129cc401ea33a29ce5dcc13ec|BN20260223|7.7.0.0|",
				"addressLine": "328 Urquhart Ave",
				"adminDistrict": "NB",
				"adminDistrict2": "Westmorland",
				"countryRegion": "Canada",
				"formattedAddress": "328 Urquhart Ave, Moncton, NB E1H 2R6, Canada",
				"locality": "Moncton",
				"postalCode": "E1H 2R6"
			},
			"geometry": {
				"type": "Point",
				"coordinates": [
					-64.74569,
					46.12832
				]
			},
			"bbox": [
				-64.747312,
				46.1271958,
				-64.744068,
				46.1294442
			]
		}
	]
}
