{
	"type": "FeatureCollection",
	"features": [
		{
			"type": "Feature",
			"properties": {
				"confidence": 9,
				"authenticationResultCode": "ValidCredentials",
				"brandLogoUri": "http://dev.virtualearth.net/Branding/logo_powered_by.png",
				"copyright": "Copyright © 2017 Microsoft and its suppliers. All rights reserved. This API cannot be accessed and the content and any results may not be used, reproduced or transmitted in any manner without express written permission from Microsoft Corporation.",
				"entityType": "Address",
				"matchCodes": [
					"Good"
				],
				"name": "32859 Mission Way, Mission, BC V2V 6E4, Canada",
				"statusCode": 200,
				"statusDescription": "OK",
				"traceId": "7f16469401b04e10a26cff7309d4dc89|BN20130521|7.7.0.0|",
				"addressLine": "32859 Mission Way",
				"adminDistrict": "BC",
				"adminDistrict2": "Fraser Valley",
				"countryRegion": "Canada",
				"formattedAddress": "32859 Mission Way, Mission, BC V2V 6E4, Canada",
				"locality": "Mission",
				"postalCode": "V2V 6E4"
			},
			"geometry": {
				"type": "Point",
				"coordinates": [
					-122.31553,
					49.1316
				]
			},
			"bbox": [
				-122.317248,
				49.1304758,
				-122.313812,
				49.1327242
			]
		}
	]
}
