{
	"type": "FeatureCollection",
	"features": [
		{
			"type": "Feature",
			"properties": {
				"confidence": 9,
				"authenticationResultCode": "ValidCredentials",
				"brandLogoUri": "http://dev.virtualearth.net/Branding/logo_powered_by.png",
				"copyright": "Copyright © 2017 Microsoft and its suppliers. All rights reserved. This API cannot be accessed and the content and any results may not be used, reproduced or transmitted in any manner without express written permission from Microsoft Corporation.",
				"entityType": "Address",
				"matchCodes": [
					"Good"
				],
				"name": "3289 HWY-16, Houston, BC V0J 3A1, Canada",
				"statusCode": 200,
				"statusDescription": "OK",
				"traceId": "2c5a91173c2c438da85d788fbeee5fa7|BN20130719|7.7.0.0|",
				"addressLine": "3289 HWY-16",
				"adminDistrict": "BC",
				"adminDistrict2": "Bulkley-Nechako",
				"countryRegion": "Canada",
				"formattedAddress": "3289 HWY-16, Houston, BC V0J 3A1, Canada",
				"locality": "Houston",
				"postalCode": "V0J 3A1"
			},
			"geometry": {
				"type": "Point",
				"coordinates": [
					-126.6505616,
					54.3995465
				]
			},
			"bbox": [
				-126.6524927,
				54.3984224,
				-126.6486305,
				54.4006707
			]
		}
	]
}
