{
	"type": "FeatureCollection",
	"features": [
		{
			"type": "Feature",
			"properties": {
				"confidence": 9,
				"authenticationResultCode": "ValidCredentials",
				"brandLogoUri": "http://dev.virtualearth.net/Branding/logo_powered_by.png",
				"copyright": "Copyright © 2017 Microsoft and its suppliers. All rights reserved. This API cannot be accessed and the content and any results may not be used, reproduced or transmitted in any manner without express written permission from Microsoft Corporation.",
				"entityType": "Address",
				"matchCodes": [
					"Good"
				],
				"name": "32 Bayshore Dr, Nepean, ON K2B 6M8, Canada",
				"statusCode": 200,
				"statusDescription": "OK",
				"traceId": "d5bb1492bb8c4de895f639612bad2baf|BN20260231|7.7.0.0|",
				"addressLine": "32 Bayshore Dr",
				"adminDistrict": "ON",
				"adminDistrict2": "Ottawa",
				"countryRegion": "Canada",
				"formattedAddress": "32 Bayshore Dr, Nepean, ON K2B 6M8, Canada",
				"locality": "Ottawa",
				"neighborhood": "Nepean",
				"postalCode": "K2B 6M8"
			},
			"geometry": {
				"type": "Point",
				"coordinates": [
					-75.8069888,
					45.3519182
				]
			},
			"bbox": [
				-75.8085884,
				45.3507941,
				-75.8053892,
				45.3530424
			]
		}
	]
}
