{
	"type": "FeatureCollection",
	"features": [
		{
			"type": "Feature",
			"properties": {
				"confidence": 9,
				"authenticationResultCode": "ValidCredentials",
				"brandLogoUri": "http://dev.virtualearth.net/Branding/logo_powered_by.png",
				"copyright": "Copyright © 2017 Microsoft and its suppliers. All rights reserved. This API cannot be accessed and the content and any results may not be used, reproduced or transmitted in any manner without express written permission from Microsoft Corporation.",
				"entityType": "Address",
				"matchCodes": [
					"Good"
				],
				"name": "33 Park Ave E, Brantford, ON N3S 7R9, Canada",
				"statusCode": 200,
				"statusDescription": "OK",
				"traceId": "5bf5993e811743aba2301a77cc34ef27|BN20200239|7.7.0.0|",
				"addressLine": "33 Park Ave E",
				"adminDistrict": "ON",
				"adminDistrict2": "Brant",
				"countryRegion": "Canada",
				"formattedAddress": "33 Park Ave E, Brantford, ON N3S 7R9, Canada",
				"locality": "Brantford",
				"postalCode": "N3S 7R9"
			},
			"geometry": {
				"type": "Point",
				"coordinates": [
					-80.24593,
					43.13438
				]
			},
			"bbox": [
				-80.2474705,
				43.1332558,
				-80.2443895,
				43.1355042
			]
		}
	]
}
