{
	"type": "FeatureCollection",
	"features": [
		{
			"type": "Feature",
			"properties": {
				"confidence": 9,
				"authenticationResultCode": "ValidCredentials",
				"brandLogoUri": "http://dev.virtualearth.net/Branding/logo_powered_by.png",
				"copyright": "Copyright © 2017 Microsoft and its suppliers. All rights reserved. This API cannot be accessed and the content and any results may not be used, reproduced or transmitted in any manner without express written permission from Microsoft Corporation.",
				"entityType": "Address",
				"matchCodes": [
					"Good"
				],
				"name": "333 3rd Ave N, Saskatoon, SK S7K 2M2, Canada",
				"statusCode": 200,
				"statusDescription": "OK",
				"traceId": "15058f08c8c7463086ee7e76c4bf114d|BN20121763|7.7.0.0|",
				"addressLine": "333 3rd Ave N",
				"adminDistrict": "SK",
				"adminDistrict2": "Saskatchewan",
				"countryRegion": "Canada",
				"formattedAddress": "333 3rd Ave N, Saskatoon, SK S7K 2M2, Canada",
				"locality": "Saskatoon",
				"neighborhood": "Central Business District",
				"postalCode": "S7K 2M2"
			},
			"geometry": {
				"type": "Point",
				"coordinates": [
					-106.66049,
					52.13297
				]
			},
			"bbox": [
				-106.6623214,
				52.1318458,
				-106.6586586,
				52.1340942
			]
		}
	]
}
