{
	"type": "FeatureCollection",
	"features": [
		{
			"type": "Feature",
			"properties": {
				"confidence": 7,
				"authenticationResultCode": "ValidCredentials",
				"brandLogoUri": "http://dev.virtualearth.net/Branding/logo_powered_by.png",
				"copyright": "Copyright © 2017 Microsoft and its suppliers. All rights reserved. This API cannot be accessed and the content and any results may not be used, reproduced or transmitted in any manner without express written permission from Microsoft Corporation.",
				"entityType": "RoadIntersection",
				"matchCodes": [
					"Good"
				],
				"name": "Ridgeway Dr & Unity Dr, Mississauga, ON L5L 5Z9, Canada",
				"statusCode": 200,
				"statusDescription": "OK",
				"traceId": "41a52b8d2e9243d18c7a4ff5a979503e|BN20121762|7.7.0.0|",
				"addressLine": "Ridgeway Dr & Unity Dr",
				"adminDistrict": "ON",
				"adminDistrict2": "Peel",
				"countryRegion": "Canada",
				"formattedAddress": "Ridgeway Dr & Unity Dr, Mississauga, ON L5L 5Z9, Canada",
				"locality": "Mississauga",
				"neighborhood": "Erin Mills",
				"postalCode": "L5L 5Z9"
			},
			"geometry": {
				"type": "Point",
				"coordinates": [
					-79.7172,
					43.53217
				]
			},
			"bbox": [
				-79.7296046,
				43.5231768,
				-79.7047954,
				43.5411632
			]
		}
	]
}
