{
	"type": "FeatureCollection",
	"features": [
		{
			"type": "Feature",
			"properties": {
				"confidence": 9,
				"authenticationResultCode": "ValidCredentials",
				"brandLogoUri": "http://dev.virtualearth.net/Branding/logo_powered_by.png",
				"copyright": "Copyright © 2017 Microsoft and its suppliers. All rights reserved. This API cannot be accessed and the content and any results may not be used, reproduced or transmitted in any manner without express written permission from Microsoft Corporation.",
				"entityType": "Address",
				"matchCodes": [
					"Good"
				],
				"name": "3371 Skipton Ln, Oakville, ON L6M 0K3, Canada",
				"statusCode": 200,
				"statusDescription": "OK",
				"traceId": "3c3d97c338344ca0b18ae233c938d056|BN20130634|7.7.0.0|",
				"addressLine": "3371 Skipton Ln",
				"adminDistrict": "ON",
				"adminDistrict2": "Halton",
				"countryRegion": "Canada",
				"formattedAddress": "3371 Skipton Ln, Oakville, ON L6M 0K3, Canada",
				"locality": "Oakville",
				"neighborhood": "Bronte Creek",
				"postalCode": "L6M 0K3"
			},
			"geometry": {
				"type": "Point",
				"coordinates": [
					-79.78224,
					43.42503
				]
			},
			"bbox": [
				-79.7837878,
				43.4239058,
				-79.7806922,
				43.4261542
			]
		}
	]
}
