{
	"type": "FeatureCollection",
	"features": [
		{
			"type": "Feature",
			"properties": {
				"confidence": 9,
				"authenticationResultCode": "ValidCredentials",
				"brandLogoUri": "http://dev.virtualearth.net/Branding/logo_powered_by.png",
				"copyright": "Copyright © 2017 Microsoft and its suppliers. All rights reserved. This API cannot be accessed and the content and any results may not be used, reproduced or transmitted in any manner without express written permission from Microsoft Corporation.",
				"entityType": "Address",
				"matchCodes": [
					"Good"
				],
				"name": "3379 Hawthorne Rd, Ottawa, ON K1G 4G2, Canada",
				"statusCode": 200,
				"statusDescription": "OK",
				"traceId": "0689e72f5fe049df9c7e54b5524c12df|BN20130533|7.7.0.0|",
				"addressLine": "3379 Hawthorne Rd",
				"adminDistrict": "ON",
				"adminDistrict2": "Ottawa",
				"countryRegion": "Canada",
				"formattedAddress": "3379 Hawthorne Rd, Ottawa, ON K1G 4G2, Canada",
				"locality": "Ottawa",
				"neighborhood": "Gloucester",
				"postalCode": "K1G 4G2"
			},
			"geometry": {
				"type": "Point",
				"coordinates": [
					-75.5991031,
					45.3776404
				]
			},
			"bbox": [
				-75.6007035,
				45.3765162,
				-75.5975027,
				45.3787645
			]
		}
	]
}
