{
	"type": "FeatureCollection",
	"features": [
		{
			"type": "Feature",
			"properties": {
				"confidence": 9,
				"authenticationResultCode": "ValidCredentials",
				"brandLogoUri": "http://dev.virtualearth.net/Branding/logo_powered_by.png",
				"copyright": "Copyright © 2017 Microsoft and its suppliers. All rights reserved. This API cannot be accessed and the content and any results may not be used, reproduced or transmitted in any manner without express written permission from Microsoft Corporation.",
				"entityType": "Address",
				"matchCodes": [
					"Good"
				],
				"name": "3391 Bloor St W, Etobicoke, ON M8X 1G3, Canada",
				"statusCode": 200,
				"statusDescription": "OK",
				"traceId": "c5128f9956fa49a8a95459bc2f560de4|BN20130530|7.7.0.0|",
				"addressLine": "3391 Bloor St W",
				"adminDistrict": "ON",
				"adminDistrict2": "Toronto",
				"countryRegion": "Canada",
				"formattedAddress": "3391 Bloor St W, Etobicoke, ON M8X 1G3, Canada",
				"locality": "Toronto",
				"neighborhood": "Islington-City Centre West",
				"postalCode": "M8X 1G3"
			},
			"geometry": {
				"type": "Point",
				"coordinates": [
					-79.52361,
					43.64436
				]
			},
			"bbox": [
				-79.5251635,
				43.6432358,
				-79.5220565,
				43.6454842
			]
		}
	]
}
