{
	"type": "FeatureCollection",
	"features": [
		{
			"type": "Feature",
			"properties": {
				"confidence": 9,
				"authenticationResultCode": "ValidCredentials",
				"brandLogoUri": "http://dev.virtualearth.net/Branding/logo_powered_by.png",
				"copyright": "Copyright © 2017 Microsoft and its suppliers. All rights reserved. This API cannot be accessed and the content and any results may not be used, reproduced or transmitted in any manner without express written permission from Microsoft Corporation.",
				"entityType": "Address",
				"matchCodes": [
					"Good"
				],
				"name": "34 The Meadows Ave, Markham, ON L6B 1B5, Canada",
				"statusCode": 200,
				"statusDescription": "OK",
				"traceId": "31c6be052fb24d11a4d5dfd4d037cd9a|BN20130621|7.7.0.0|",
				"addressLine": "34 The Meadows Ave",
				"adminDistrict": "ON",
				"adminDistrict2": "York",
				"countryRegion": "Canada",
				"formattedAddress": "34 The Meadows Ave, Markham, ON L6B 1B5, Canada",
				"locality": "Markham",
				"postalCode": "L6B 1B5"
			},
			"geometry": {
				"type": "Point",
				"coordinates": [
					-79.23493,
					43.8874
				]
			},
			"bbox": [
				-79.2364898,
				43.8862758,
				-79.2333702,
				43.8885242
			]
		}
	]
}
