{
	"type": "FeatureCollection",
	"features": [
		{
			"type": "Feature",
			"properties": {
				"confidence": 9,
				"authenticationResultCode": "ValidCredentials",
				"brandLogoUri": "http://dev.virtualearth.net/Branding/logo_powered_by.png",
				"copyright": "Copyright © 2017 Microsoft and its suppliers. All rights reserved. This API cannot be accessed and the content and any results may not be used, reproduced or transmitted in any manner without express written permission from Microsoft Corporation.",
				"entityType": "Address",
				"matchCodes": [
					"Good"
				],
				"name": "34 Willowshore Way, Carleton Place, ON K7C 0B1, Canada",
				"statusCode": 200,
				"statusDescription": "OK",
				"traceId": "948d2fe458bc4e26b1cb4b7a77ef335e|BN20130631|7.7.0.0|",
				"addressLine": "34 Willowshore Way",
				"adminDistrict": "ON",
				"adminDistrict2": "Lanark",
				"countryRegion": "Canada",
				"formattedAddress": "34 Willowshore Way, Carleton Place, ON K7C 0B1, Canada",
				"locality": "Carleton Place",
				"postalCode": "K7C 0B1"
			},
			"geometry": {
				"type": "Point",
				"coordinates": [
					-76.13472,
					45.14806
				]
			},
			"bbox": [
				-76.1363139,
				45.1469358,
				-76.1331261,
				45.1491842
			]
		}
	]
}
