{
	"type": "FeatureCollection",
	"features": [
		{
			"type": "Feature",
			"properties": {
				"confidence": 9,
				"authenticationResultCode": "ValidCredentials",
				"brandLogoUri": "http://dev.virtualearth.net/Branding/logo_powered_by.png",
				"copyright": "Copyright © 2017 Microsoft and its suppliers. All rights reserved. This API cannot be accessed and the content and any results may not be used, reproduced or transmitted in any manner without express written permission from Microsoft Corporation.",
				"entityType": "Address",
				"matchCodes": [
					"Good"
				],
				"name": "341 Rue Delisle, Chicoutimi, QC G7G 3B4, Canada",
				"statusCode": 200,
				"statusDescription": "OK",
				"traceId": "fe0afbb41ecb4312b9f523f66e89ce4f|BN20130431|7.7.0.0|",
				"addressLine": "341 Rue Delisle",
				"adminDistrict": "QC",
				"adminDistrict2": "Saguenay",
				"countryRegion": "Canada",
				"formattedAddress": "341 Rue Delisle, Chicoutimi, QC G7G 3B4, Canada",
				"locality": "Saguenay",
				"neighborhood": "Chicoutimi",
				"postalCode": "G7G 3B4"
			},
			"geometry": {
				"type": "Point",
				"coordinates": [
					-71.06612,
					48.4446299
				]
			},
			"bbox": [
				-71.0678147,
				48.4435057,
				-71.0644253,
				48.4457541
			]
		}
	]
}
