{
	"type": "FeatureCollection",
	"features": [
		{
			"type": "Feature",
			"properties": {
				"confidence": 9,
				"authenticationResultCode": "ValidCredentials",
				"brandLogoUri": "http://dev.virtualearth.net/Branding/logo_powered_by.png",
				"copyright": "Copyright © 2017 Microsoft and its suppliers. All rights reserved. This API cannot be accessed and the content and any results may not be used, reproduced or transmitted in any manner without express written permission from Microsoft Corporation.",
				"entityType": "Address",
				"matchCodes": [
					"Good"
				],
				"name": "3410 Malcolm Rd, West Kelowna, BC V4T 1H2, Canada",
				"statusCode": 200,
				"statusDescription": "OK",
				"traceId": "151fdff6420f4381a297f3970e959d40|BN20130422|7.7.0.0|",
				"addressLine": "3410 Malcolm Rd",
				"adminDistrict": "BC",
				"adminDistrict2": "Central Okanagan",
				"countryRegion": "Canada",
				"formattedAddress": "3410 Malcolm Rd, West Kelowna, BC V4T 1H2, Canada",
				"locality": "West Kelowna",
				"neighborhood": "Westbank",
				"postalCode": "V4T 1H2"
			},
			"geometry": {
				"type": "Point",
				"coordinates": [
					-119.65486,
					49.83969
				]
			},
			"bbox": [
				-119.6566031,
				49.8385658,
				-119.6531169,
				49.8408142
			]
		}
	]
}
