{
	"type": "FeatureCollection",
	"features": [
		{
			"type": "Feature",
			"properties": {
				"confidence": 9,
				"authenticationResultCode": "ValidCredentials",
				"brandLogoUri": "http://dev.virtualearth.net/Branding/logo_powered_by.png",
				"copyright": "Copyright © 2017 Microsoft and its suppliers. All rights reserved. This API cannot be accessed and the content and any results may not be used, reproduced or transmitted in any manner without express written permission from Microsoft Corporation.",
				"entityType": "Address",
				"matchCodes": [
					"Good"
				],
				"name": "3410 9 St SE, Calgary, AB T2G 3C3, Canada",
				"statusCode": 200,
				"statusDescription": "OK",
				"traceId": "1bb1ffa20a7849448d839b82ae64204c|BN20130522|7.7.0.0|",
				"addressLine": "3410 9 St SE",
				"adminDistrict": "AB",
				"adminDistrict2": "Alberta",
				"countryRegion": "Canada",
				"formattedAddress": "3410 9 St SE, Calgary, AB T2G 3C3, Canada",
				"locality": "Calgary",
				"neighborhood": "Alyth-Bonnybrook-Manchester",
				"postalCode": "T2G 3C3"
			},
			"geometry": {
				"type": "Point",
				"coordinates": [
					-114.0403988,
					51.023275
				]
			},
			"bbox": [
				-114.042186,
				51.0221509,
				-114.0386116,
				51.0243992
			]
		}
	]
}
