{
	"type": "FeatureCollection",
	"features": [
		{
			"type": "Feature",
			"properties": {
				"confidence": 9,
				"authenticationResultCode": "ValidCredentials",
				"brandLogoUri": "http://dev.virtualearth.net/Branding/logo_powered_by.png",
				"copyright": "Copyright © 2017 Microsoft and its suppliers. All rights reserved. This API cannot be accessed and the content and any results may not be used, reproduced or transmitted in any manner without express written permission from Microsoft Corporation.",
				"entityType": "Address",
				"matchCodes": [
					"Good"
				],
				"name": "3420 189 St, Surrey, BC V3Z 1A7, Canada",
				"statusCode": 200,
				"statusDescription": "OK",
				"traceId": "cd738455731f40cfa8e7fd17c888b5fd|BN20260231|7.7.0.0|",
				"addressLine": "3420 189 St",
				"adminDistrict": "BC",
				"adminDistrict2": "Greater Vancouver",
				"countryRegion": "Canada",
				"formattedAddress": "3420 189 St, Surrey, BC V3Z 1A7, Canada",
				"locality": "Surrey",
				"neighborhood": "South Surrey",
				"postalCode": "V3Z 1A7"
			},
			"geometry": {
				"type": "Point",
				"coordinates": [
					-122.7002995,
					49.0632567
				]
			},
			"bbox": [
				-122.7020151,
				49.0621325,
				-122.6985838,
				49.0643808
			]
		}
	]
}
