{
	"type": "FeatureCollection",
	"features": [
		{
			"type": "Feature",
			"properties": {
				"confidence": 9,
				"authenticationResultCode": "ValidCredentials",
				"brandLogoUri": "http://dev.virtualearth.net/Branding/logo_powered_by.png",
				"copyright": "Copyright © 2017 Microsoft and its suppliers. All rights reserved. This API cannot be accessed and the content and any results may not be used, reproduced or transmitted in any manner without express written permission from Microsoft Corporation.",
				"entityType": "Address",
				"matchCodes": [
					"Good"
				],
				"name": "34282 Catchpole Ave, Mission, BC V2V 6P2, Canada",
				"statusCode": 200,
				"statusDescription": "OK",
				"traceId": "000a87a037634f42b11fd48463b2e6f7|BN20130721|7.7.0.0|",
				"addressLine": "34282 Catchpole Ave",
				"adminDistrict": "BC",
				"adminDistrict2": "Fraser Valley",
				"countryRegion": "Canada",
				"formattedAddress": "34282 Catchpole Ave, Mission, BC V2V 6P2, Canada",
				"locality": "Mission",
				"postalCode": "V2V 6P2"
			},
			"geometry": {
				"type": "Point",
				"coordinates": [
					-122.27314,
					49.14457
				]
			},
			"bbox": [
				-122.2748585,
				49.1434458,
				-122.2714215,
				49.1456942
			]
		}
	]
}
