{
	"type": "FeatureCollection",
	"features": [
		{
			"type": "Feature",
			"properties": {
				"confidence": 9,
				"authenticationResultCode": "ValidCredentials",
				"brandLogoUri": "http://dev.virtualearth.net/Branding/logo_powered_by.png",
				"copyright": "Copyright © 2017 Microsoft and its suppliers. All rights reserved. This API cannot be accessed and the content and any results may not be used, reproduced or transmitted in any manner without express written permission from Microsoft Corporation.",
				"entityType": "Address",
				"matchCodes": [
					"Good"
				],
				"name": "3432 Princeton Ave, Coquitlam, BC V3E 0G1, Canada",
				"statusCode": 200,
				"statusDescription": "OK",
				"traceId": "b0e09bf35c0a485a9146c7cb4beddeb5|BN20130721|7.7.0.0|",
				"addressLine": "3432 Princeton Ave",
				"adminDistrict": "BC",
				"adminDistrict2": "Greater Vancouver",
				"countryRegion": "Canada",
				"formattedAddress": "3432 Princeton Ave, Coquitlam, BC V3E 0G1, Canada",
				"locality": "Coquitlam",
				"postalCode": "V3E 0G1"
			},
			"geometry": {
				"type": "Point",
				"coordinates": [
					-122.750634,
					49.2983551
				]
			},
			"bbox": [
				-122.7523579,
				49.2972309,
				-122.7489102,
				49.2994793
			]
		}
	]
}
