{
	"type": "FeatureCollection",
	"features": [
		{
			"type": "Feature",
			"properties": {
				"confidence": 9,
				"authenticationResultCode": "ValidCredentials",
				"brandLogoUri": "http://dev.virtualearth.net/Branding/logo_powered_by.png",
				"copyright": "Copyright © 2017 Microsoft and its suppliers. All rights reserved. This API cannot be accessed and the content and any results may not be used, reproduced or transmitted in any manner without express written permission from Microsoft Corporation.",
				"entityType": "Address",
				"matchCodes": [
					"Good"
				],
				"name": "3433 Pipeline Rd, West St Paul, MB R4A 8A2, Canada",
				"statusCode": 200,
				"statusDescription": "OK",
				"traceId": "7f551a21601b458ba5f60a7dec48f588|BN20220145|7.7.0.0|",
				"addressLine": "3433 Pipeline Rd",
				"adminDistrict": "MB",
				"adminDistrict2": "Manitoba",
				"countryRegion": "Canada",
				"formattedAddress": "3433 Pipeline Rd, West St Paul, MB R4A 8A2, Canada",
				"locality": "West St Paul",
				"postalCode": "R4A 8A2"
			},
			"geometry": {
				"type": "Point",
				"coordinates": [
					-97.1608351,
					50.0179091
				]
			},
			"bbox": [
				-97.1625846,
				50.016785,
				-97.1590856,
				50.0190333
			]
		}
	]
}
