{
	"type": "FeatureCollection",
	"features": [
		{
			"type": "Feature",
			"properties": {
				"confidence": 9,
				"authenticationResultCode": "ValidCredentials",
				"brandLogoUri": "http://dev.virtualearth.net/Branding/logo_powered_by.png",
				"copyright": "Copyright © 2017 Microsoft and its suppliers. All rights reserved. This API cannot be accessed and the content and any results may not be used, reproduced or transmitted in any manner without express written permission from Microsoft Corporation.",
				"entityType": "Address",
				"matchCodes": [
					"Good"
				],
				"name": "345 W 16th Ave, Vancouver, BC V5Y 1Z1, Canada",
				"statusCode": 200,
				"statusDescription": "OK",
				"traceId": "60ba231fa57848a48e23979698808465|BN20121764|7.7.0.0|",
				"addressLine": "345 W 16th Ave",
				"adminDistrict": "BC",
				"adminDistrict2": "Greater Vancouver",
				"countryRegion": "Canada",
				"formattedAddress": "345 W 16th Ave, Vancouver, BC V5Y 1Z1, Canada",
				"locality": "Vancouver",
				"neighborhood": "Mt Pleasant",
				"postalCode": "V5Y 1Z1"
			},
			"geometry": {
				"type": "Point",
				"coordinates": [
					-123.1121834,
					49.2569512
				]
			},
			"bbox": [
				-123.1139058,
				49.2558271,
				-123.110461,
				49.2580754
			]
		}
	]
}
