{
	"type": "FeatureCollection",
	"features": [
		{
			"type": "Feature",
			"properties": {
				"confidence": 9,
				"authenticationResultCode": "ValidCredentials",
				"brandLogoUri": "http://dev.virtualearth.net/Branding/logo_powered_by.png",
				"copyright": "Copyright © 2017 Microsoft and its suppliers. All rights reserved. This API cannot be accessed and the content and any results may not be used, reproduced or transmitted in any manner without express written permission from Microsoft Corporation.",
				"entityType": "Address",
				"matchCodes": [
					"Good"
				],
				"name": "346 Millway Ave, Concord, ON L4K 3W1, Canada",
				"statusCode": 200,
				"statusDescription": "OK",
				"traceId": "c41cb553823e4a25b6884da1ad1d3a8e|BN20130625|7.7.0.0|",
				"addressLine": "346 Millway Ave",
				"adminDistrict": "ON",
				"adminDistrict2": "York",
				"countryRegion": "Canada",
				"formattedAddress": "346 Millway Ave, Concord, ON L4K 3W1, Canada",
				"locality": "Vaughan",
				"neighborhood": "Concord",
				"postalCode": "L4K 3W1"
			},
			"geometry": {
				"type": "Point",
				"coordinates": [
					-79.53,
					43.80251
				]
			},
			"bbox": [
				-79.5315576,
				43.8013858,
				-79.5284424,
				43.8036342
			]
		}
	]
}
