{
	"type": "FeatureCollection",
	"features": [
		{
			"type": "Feature",
			"properties": {
				"confidence": 9,
				"authenticationResultCode": "ValidCredentials",
				"brandLogoUri": "http://dev.virtualearth.net/Branding/logo_powered_by.png",
				"copyright": "Copyright © 2017 Microsoft and its suppliers. All rights reserved. This API cannot be accessed and the content and any results may not be used, reproduced or transmitted in any manner without express written permission from Microsoft Corporation.",
				"entityType": "Address",
				"matchCodes": [
					"Good"
				],
				"name": "3468 Terravita Pl, Vancouver, BC V5K 5H6, Canada",
				"statusCode": 200,
				"statusDescription": "OK",
				"traceId": "1811633e8c944a3c8bf859f69aacb7f8|BN20250135|7.7.0.0|",
				"addressLine": "3468 Terravita Pl",
				"adminDistrict": "BC",
				"adminDistrict2": "Greater Vancouver",
				"countryRegion": "Canada",
				"formattedAddress": "3468 Terravita Pl, Vancouver, BC V5K 5H6, Canada",
				"locality": "Vancouver",
				"neighborhood": "Hastings-Sunrise",
				"postalCode": "V5K 5H6"
			},
			"geometry": {
				"type": "Point",
				"coordinates": [
					-123.0299955,
					49.2764351
				]
			},
			"bbox": [
				-123.0317186,
				49.2753109,
				-123.0282725,
				49.2775593
			]
		}
	]
}
