{
	"type": "FeatureCollection",
	"features": [
		{
			"type": "Feature",
			"properties": {
				"confidence": 9,
				"authenticationResultCode": "ValidCredentials",
				"brandLogoUri": "http://dev.virtualearth.net/Branding/logo_powered_by.png",
				"copyright": "Copyright © 2017 Microsoft and its suppliers. All rights reserved. This API cannot be accessed and the content and any results may not be used, reproduced or transmitted in any manner without express written permission from Microsoft Corporation.",
				"entityType": "Address",
				"matchCodes": [
					"Good"
				],
				"name": "3478 Hideway Pl, Mississauga, ON L5M, Canada",
				"statusCode": 200,
				"statusDescription": "OK",
				"traceId": "e2c4bf88aaea4f03bdb242a62b2d9b02|BN20130632|7.7.0.0|",
				"addressLine": "3478 Hideway Pl",
				"adminDistrict": "ON",
				"adminDistrict2": "Peel",
				"countryRegion": "Canada",
				"formattedAddress": "3478 Hideway Pl, Mississauga, ON L5M, Canada",
				"locality": "Mississauga",
				"neighborhood": "Erin Mills",
				"postalCode": "L5M 0A7"
			},
			"geometry": {
				"type": "Point",
				"coordinates": [
					-79.73524,
					43.54652
				]
			},
			"bbox": [
				-79.7367909,
				43.5453958,
				-79.7336891,
				43.5476442
			]
		}
	]
}
