{
	"type": "FeatureCollection",
	"features": [
		{
			"type": "Feature",
			"properties": {
				"confidence": 9,
				"authenticationResultCode": "ValidCredentials",
				"brandLogoUri": "http://dev.virtualearth.net/Branding/logo_powered_by.png",
				"copyright": "Copyright © 2017 Microsoft and its suppliers. All rights reserved. This API cannot be accessed and the content and any results may not be used, reproduced or transmitted in any manner without express written permission from Microsoft Corporation.",
				"entityType": "Address",
				"matchCodes": [
					"Good"
				],
				"name": "3483 Old HWY-17, Rockland, ON K4K 1W1, Canada",
				"statusCode": 200,
				"statusDescription": "OK",
				"traceId": "f58c8f73b7e842c4bede315ba0048748|BN20200239|7.7.0.0|",
				"addressLine": "3483 Old HWY-17",
				"adminDistrict": "ON",
				"adminDistrict2": "Prescott and Russell",
				"countryRegion": "Canada",
				"formattedAddress": "3483 Old HWY-17, Rockland, ON K4K 1W1, Canada",
				"locality": "Clarence-Rockland",
				"neighborhood": "Rockland",
				"postalCode": "K4K 1W1"
			},
			"geometry": {
				"type": "Point",
				"coordinates": [
					-75.1889502,
					45.5755692
				]
			},
			"bbox": [
				-75.1905562,
				45.574445,
				-75.1873442,
				45.5766933
			]
		}
	]
}
