{
	"type": "FeatureCollection",
	"features": [
		{
			"type": "Feature",
			"properties": {
				"confidence": 9,
				"authenticationResultCode": "ValidCredentials",
				"brandLogoUri": "http://dev.virtualearth.net/Branding/logo_powered_by.png",
				"copyright": "Copyright © 2017 Microsoft and its suppliers. All rights reserved. This API cannot be accessed and the content and any results may not be used, reproduced or transmitted in any manner without express written permission from Microsoft Corporation.",
				"entityType": "Address",
				"matchCodes": [
					"Good"
				],
				"name": "35 Ormskirk Ave, Toronto, ON M6S 1A8, Canada",
				"statusCode": 200,
				"statusDescription": "OK",
				"traceId": "0393aaf4cf6641b6b58b99ab78fcff9c|BN20200137|7.7.0.0|",
				"addressLine": "35 Ormskirk Ave",
				"adminDistrict": "ON",
				"adminDistrict2": "Toronto",
				"countryRegion": "Canada",
				"formattedAddress": "35 Ormskirk Ave, Toronto, ON M6S 1A8, Canada",
				"locality": "Toronto",
				"neighborhood": "High Park-Swansea",
				"postalCode": "M6S 1A8"
			},
			"geometry": {
				"type": "Point",
				"coordinates": [
					-79.47485,
					43.63918
				]
			},
			"bbox": [
				-79.4764033,
				43.6380558,
				-79.4732967,
				43.6403042
			]
		}
	]
}
