{
	"type": "FeatureCollection",
	"features": [
		{
			"type": "Feature",
			"properties": {
				"confidence": 9,
				"authenticationResultCode": "ValidCredentials",
				"brandLogoUri": "http://dev.virtualearth.net/Branding/logo_powered_by.png",
				"copyright": "Copyright © 2017 Microsoft and its suppliers. All rights reserved. This API cannot be accessed and the content and any results may not be used, reproduced or transmitted in any manner without express written permission from Microsoft Corporation.",
				"entityType": "Address",
				"matchCodes": [
					"Good"
				],
				"name": "35 Chemin Victoria O, Scotstown, QC J0B 3B0, Canada",
				"statusCode": 200,
				"statusDescription": "OK",
				"traceId": "0a2553c60103496b963a9169bd4d7f15|BN20131519|7.7.0.0|",
				"addressLine": "35 Chemin Victoria O",
				"adminDistrict": "QC",
				"adminDistrict2": "Le Haut-St-François",
				"countryRegion": "Canada",
				"formattedAddress": "35 Chemin Victoria O, Scotstown, QC J0B 3B0, Canada",
				"locality": "Scotstown",
				"postalCode": "J0B 3B0"
			},
			"geometry": {
				"type": "Point",
				"coordinates": [
					-71.27654,
					45.52499
				]
			},
			"bbox": [
				-71.2781446,
				45.5238658,
				-71.2749354,
				45.5261142
			]
		}
	]
}
