{
	"type": "FeatureCollection",
	"features": [
		{
			"type": "Feature",
			"properties": {
				"confidence": 9,
				"authenticationResultCode": "ValidCredentials",
				"brandLogoUri": "http://dev.virtualearth.net/Branding/logo_powered_by.png",
				"copyright": "Copyright © 2017 Microsoft and its suppliers. All rights reserved. This API cannot be accessed and the content and any results may not be used, reproduced or transmitted in any manner without express written permission from Microsoft Corporation.",
				"entityType": "Address",
				"matchCodes": [
					"Good"
				],
				"name": "350 7 Ave SW, Calgary, AB T2P 3N9, Canada",
				"statusCode": 200,
				"statusDescription": "OK",
				"traceId": "ed761cfae4aa40b98b79c516cc513e58|BN20300154|7.7.0.0|",
				"addressLine": "350 7 Ave SW",
				"adminDistrict": "AB",
				"adminDistrict2": "Alberta",
				"countryRegion": "Canada",
				"formattedAddress": "350 7 Ave SW, Calgary, AB T2P 3N9, Canada",
				"locality": "Calgary",
				"neighborhood": "Downtown",
				"postalCode": "T2P 3N9"
			},
			"geometry": {
				"type": "Point",
				"coordinates": [
					-114.06982,
					51.04684
				]
			},
			"bbox": [
				-114.0716081,
				51.0457158,
				-114.0680319,
				51.0479642
			]
		}
	]
}
