{
	"type": "FeatureCollection",
	"features": [
		{
			"type": "Feature",
			"properties": {
				"confidence": 9,
				"authenticationResultCode": "ValidCredentials",
				"brandLogoUri": "http://dev.virtualearth.net/Branding/logo_powered_by.png",
				"copyright": "Copyright © 2017 Microsoft and its suppliers. All rights reserved. This API cannot be accessed and the content and any results may not be used, reproduced or transmitted in any manner without express written permission from Microsoft Corporation.",
				"entityType": "Address",
				"matchCodes": [
					"Good"
				],
				"name": "354 Old Airport Rd, Yellowknife, NT X1A 3T4, Canada",
				"statusCode": 200,
				"statusDescription": "OK",
				"traceId": "8c6ecbd1ad0049feb626bd5c10721fe6|CO30276243|7.7.0.0|",
				"addressLine": "354 Old Airport Rd",
				"adminDistrict": "NT",
				"adminDistrict2": "Northwest Territories",
				"countryRegion": "Canada",
				"formattedAddress": "354 Old Airport Rd, Yellowknife, NT X1A 3T4, Canada",
				"locality": "Yellowknife",
				"postalCode": "X1A 3T4"
			},
			"geometry": {
				"type": "Point",
				"coordinates": [
					-114.41215,
					62.45914
				]
			},
			"bbox": [
				-114.4145812,
				62.4580158,
				-114.4097188,
				62.4602642
			]
		}
	]
}
