{
	"type": "FeatureCollection",
	"features": [
		{
			"type": "Feature",
			"properties": {
				"confidence": 9,
				"authenticationResultCode": "ValidCredentials",
				"brandLogoUri": "http://dev.virtualearth.net/Branding/logo_powered_by.png",
				"copyright": "Copyright © 2017 Microsoft and its suppliers. All rights reserved. This API cannot be accessed and the content and any results may not be used, reproduced or transmitted in any manner without express written permission from Microsoft Corporation.",
				"entityType": "Address",
				"matchCodes": [
					"Good"
				],
				"name": "3540 Kempt Rd, Halifax, NS B3K 4X8, Canada",
				"statusCode": 200,
				"statusDescription": "OK",
				"traceId": "21a4f50a2e0241a180282bdea8c035dd|BN20130533|7.7.0.0|",
				"addressLine": "3540 Kempt Rd",
				"adminDistrict": "NS",
				"adminDistrict2": "Halifax",
				"countryRegion": "Canada",
				"formattedAddress": "3540 Kempt Rd, Halifax, NS B3K 4X8, Canada",
				"locality": "Halifax",
				"neighborhood": "North End",
				"postalCode": "B3K 4X8"
			},
			"geometry": {
				"type": "Point",
				"coordinates": [
					-63.61567,
					44.66137
				]
			},
			"bbox": [
				-63.6172505,
				44.6602458,
				-63.6140895,
				44.6624942
			]
		}
	]
}
