{
	"type": "FeatureCollection",
	"features": [
		{
			"type": "Feature",
			"properties": {
				"confidence": 9,
				"authenticationResultCode": "ValidCredentials",
				"brandLogoUri": "http://dev.virtualearth.net/Branding/logo_powered_by.png",
				"copyright": "Copyright © 2017 Microsoft and its suppliers. All rights reserved. This API cannot be accessed and the content and any results may not be used, reproduced or transmitted in any manner without express written permission from Microsoft Corporation.",
				"entityType": "Address",
				"matchCodes": [
					"Good"
				],
				"name": "36 John A Trenholm Rd, Upper Cape, NB E4M 2R6, Canada",
				"statusCode": 200,
				"statusDescription": "OK",
				"traceId": "b34522913ea44ac4a12288dafb4718d2|BN20130634|7.7.0.0|",
				"addressLine": "36 John A Trenholm Rd",
				"adminDistrict": "NB",
				"adminDistrict2": "Westmorland",
				"countryRegion": "Canada",
				"formattedAddress": "36 John A Trenholm Rd, Upper Cape, NB E4M 2R6, Canada",
				"locality": "Botsford",
				"neighborhood": "Upper Cape",
				"postalCode": "E4M 2R6"
			},
			"geometry": {
				"type": "Point",
				"coordinates": [
					-64.0447564,
					46.0549442
				]
			},
			"bbox": [
				-64.0463763,
				46.05382,
				-64.0431365,
				46.0560683
			]
		}
	]
}
