{
	"type": "FeatureCollection",
	"features": [
		{
			"type": "Feature",
			"properties": {
				"confidence": 9,
				"authenticationResultCode": "ValidCredentials",
				"brandLogoUri": "http://dev.virtualearth.net/Branding/logo_powered_by.png",
				"copyright": "Copyright © 2017 Microsoft and its suppliers. All rights reserved. This API cannot be accessed and the content and any results may not be used, reproduced or transmitted in any manner without express written permission from Microsoft Corporation.",
				"entityType": "Address",
				"matchCodes": [
					"Good"
				],
				"name": "360 Tom St, Fergus, ON N1M 2A6, Canada",
				"statusCode": 200,
				"statusDescription": "OK",
				"traceId": "d975bce4ccee478ea5ecdd29612798a0|BN20130625|7.7.0.0|",
				"addressLine": "360 Tom St",
				"adminDistrict": "ON",
				"adminDistrict2": "Wellington",
				"countryRegion": "Canada",
				"formattedAddress": "360 Tom St, Fergus, ON N1M 2A6, Canada",
				"locality": "Centre Wellington",
				"neighborhood": "Fergus",
				"postalCode": "N1M 2A6"
			},
			"geometry": {
				"type": "Point",
				"coordinates": [
					-80.3693399,
					43.71525
				]
			},
			"bbox": [
				-80.3708952,
				43.7141258,
				-80.3677846,
				43.7163742
			]
		}
	]
}
