{
	"type": "FeatureCollection",
	"features": [
		{
			"type": "Feature",
			"properties": {
				"confidence": 9,
				"authenticationResultCode": "ValidCredentials",
				"brandLogoUri": "http://dev.virtualearth.net/Branding/logo_powered_by.png",
				"copyright": "Copyright © 2017 Microsoft and its suppliers. All rights reserved. This API cannot be accessed and the content and any results may not be used, reproduced or transmitted in any manner without express written permission from Microsoft Corporation.",
				"entityType": "Address",
				"matchCodes": [
					"Good"
				],
				"name": "3613 63 Ave NE, Calgary, AB T3J 5K1, Canada",
				"statusCode": 200,
				"statusDescription": "OK",
				"traceId": "4650ff3a6d8b498494fa7f03901af77d|BN20130533|7.7.0.0|",
				"addressLine": "3613 63 Ave NE",
				"adminDistrict": "AB",
				"adminDistrict2": "Alberta",
				"countryRegion": "Canada",
				"formattedAddress": "3613 63 Ave NE, Calgary, AB T3J 5K1, Canada",
				"locality": "Calgary",
				"postalCode": "T3J 5K1"
			},
			"geometry": {
				"type": "Point",
				"coordinates": [
					-113.98109,
					51.10936
				]
			},
			"bbox": [
				-113.9828805,
				51.1082358,
				-113.9792995,
				51.1104842
			]
		}
	]
}
