{
	"type": "FeatureCollection",
	"features": [
		{
			"type": "Feature",
			"properties": {
				"confidence": 9,
				"authenticationResultCode": "ValidCredentials",
				"brandLogoUri": "http://dev.virtualearth.net/Branding/logo_powered_by.png",
				"copyright": "Copyright © 2017 Microsoft and its suppliers. All rights reserved. This API cannot be accessed and the content and any results may not be used, reproduced or transmitted in any manner without express written permission from Microsoft Corporation.",
				"entityType": "Address",
				"matchCodes": [
					"Good"
				],
				"name": "3615 Manchester Rd SE, Calgary, AB T2G 3Z7, Canada",
				"statusCode": 200,
				"statusDescription": "OK",
				"traceId": "112ee9f634a64a32a39c9a8c69b3011f|BN20240423|7.7.0.0|",
				"addressLine": "3615 Manchester Rd SE",
				"adminDistrict": "AB",
				"adminDistrict2": "Alberta",
				"countryRegion": "Canada",
				"formattedAddress": "3615 Manchester Rd SE, Calgary, AB T2G 3Z7, Canada",
				"locality": "Calgary",
				"neighborhood": "Alyth-Bonnybrook-Manchester",
				"postalCode": "T2G 3Z7"
			},
			"geometry": {
				"type": "Point",
				"coordinates": [
					-114.05667,
					51.02257
				]
			},
			"bbox": [
				-114.0584572,
				51.0214458,
				-114.0548828,
				51.0236942
			]
		}
	]
}
