{
	"type": "FeatureCollection",
	"features": [
		{
			"type": "Feature",
			"properties": {
				"confidence": 9,
				"authenticationResultCode": "ValidCredentials",
				"brandLogoUri": "http://dev.virtualearth.net/Branding/logo_powered_by.png",
				"copyright": "Copyright © 2017 Microsoft and its suppliers. All rights reserved. This API cannot be accessed and the content and any results may not be used, reproduced or transmitted in any manner without express written permission from Microsoft Corporation.",
				"entityType": "Address",
				"matchCodes": [
					"Good"
				],
				"name": "3636 Research Rd NW, Calgary, AB T2L 1Y1, Canada",
				"statusCode": 200,
				"statusDescription": "OK",
				"traceId": "a7182f9e4a224010af7c93fd5b3a8fcd|BN20280152|7.7.0.0|",
				"addressLine": "3636 Research Rd NW",
				"adminDistrict": "AB",
				"adminDistrict2": "Alberta",
				"countryRegion": "Canada",
				"formattedAddress": "3636 Research Rd NW, Calgary, AB T2L 1Y1, Canada",
				"locality": "Calgary",
				"neighborhood": "Varsity",
				"postalCode": "T2L 1Y1"
			},
			"geometry": {
				"type": "Point",
				"coordinates": [
					-114.13826,
					51.08639
				]
			},
			"bbox": [
				-114.1400496,
				51.0852658,
				-114.1364704,
				51.0875142
			]
		}
	]
}
