{
	"type": "FeatureCollection",
	"features": [
		{
			"type": "Feature",
			"properties": {
				"confidence": 9,
				"authenticationResultCode": "ValidCredentials",
				"brandLogoUri": "http://dev.virtualearth.net/Branding/logo_powered_by.png",
				"copyright": "Copyright © 2017 Microsoft and its suppliers. All rights reserved. This API cannot be accessed and the content and any results may not be used, reproduced or transmitted in any manner without express written permission from Microsoft Corporation.",
				"entityType": "Address",
				"matchCodes": [
					"Good"
				],
				"name": "3638 Manchester Rd SE, Calgary, AB T2G 3Z5, Canada",
				"statusCode": 200,
				"statusDescription": "OK",
				"traceId": "6fa424bcc9ad42519d3542ab44897987|BN20130522|7.7.0.0|",
				"addressLine": "3638 Manchester Rd SE",
				"adminDistrict": "AB",
				"adminDistrict2": "Alberta",
				"countryRegion": "Canada",
				"formattedAddress": "3638 Manchester Rd SE, Calgary, AB T2G 3Z5, Canada",
				"locality": "Calgary",
				"neighborhood": "Alyth-Bonnybrook-Manchester",
				"postalCode": "T2G 3Z5"
			},
			"geometry": {
				"type": "Point",
				"coordinates": [
					-114.05665,
					51.0220399
				]
			},
			"bbox": [
				-114.0584371,
				51.0209157,
				-114.0548629,
				51.0231641
			]
		}
	]
}
