{
	"type": "FeatureCollection",
	"features": [
		{
			"type": "Feature",
			"properties": {
				"confidence": 9,
				"authenticationResultCode": "ValidCredentials",
				"brandLogoUri": "http://dev.virtualearth.net/Branding/logo_powered_by.png",
				"copyright": "Copyright © 2017 Microsoft and its suppliers. All rights reserved. This API cannot be accessed and the content and any results may not be used, reproduced or transmitted in any manner without express written permission from Microsoft Corporation.",
				"entityType": "Address",
				"matchCodes": [
					"Good"
				],
				"name": "364 Davenport Rd, Toronto, ON M5R 1K6, Canada",
				"statusCode": 200,
				"statusDescription": "OK",
				"traceId": "7cd40435b5614bcf9cc53b47ab737f78|BN20300154|7.7.0.0|",
				"addressLine": "364 Davenport Rd",
				"adminDistrict": "ON",
				"adminDistrict2": "Toronto",
				"countryRegion": "Canada",
				"formattedAddress": "364 Davenport Rd, Toronto, ON M5R 1K6, Canada",
				"locality": "Toronto",
				"neighborhood": "Annex",
				"postalCode": "M5R 1K6"
			},
			"geometry": {
				"type": "Point",
				"coordinates": [
					-79.40181,
					43.6757
				]
			},
			"bbox": [
				-79.4033643,
				43.6745758,
				-79.4002557,
				43.6768242
			]
		}
	]
}
