{
	"type": "FeatureCollection",
	"features": [
		{
			"type": "Feature",
			"properties": {
				"confidence": 9,
				"authenticationResultCode": "ValidCredentials",
				"brandLogoUri": "http://dev.virtualearth.net/Branding/logo_powered_by.png",
				"copyright": "Copyright © 2017 Microsoft and its suppliers. All rights reserved. This API cannot be accessed and the content and any results may not be used, reproduced or transmitted in any manner without express written permission from Microsoft Corporation.",
				"entityType": "Address",
				"matchCodes": [
					"Good"
				],
				"name": "3643 Hammstrom Way, Regina, SK S4N, Canada",
				"statusCode": 200,
				"statusDescription": "OK",
				"traceId": "a22f6569ce0a482d9792115ae8db472c|BN20240253|7.7.0.0|",
				"addressLine": "3643 Hammstrom Way",
				"adminDistrict": "SK",
				"adminDistrict2": "Saskatchewan",
				"countryRegion": "Canada",
				"formattedAddress": "3643 Hammstrom Way, Regina, SK S4N, Canada",
				"locality": "Regina",
				"neighborhood": "Glencairn",
				"postalCode": "S4N 7N3"
			},
			"geometry": {
				"type": "Point",
				"coordinates": [
					-104.53017,
					50.45856
				]
			},
			"bbox": [
				-104.5319358,
				50.4574358,
				-104.5284042,
				50.4596842
			]
		}
	]
}
