{
	"type": "FeatureCollection",
	"features": [
		{
			"type": "Feature",
			"properties": {
				"confidence": 9,
				"authenticationResultCode": "ValidCredentials",
				"brandLogoUri": "http://dev.virtualearth.net/Branding/logo_powered_by.png",
				"copyright": "Copyright © 2017 Microsoft and its suppliers. All rights reserved. This API cannot be accessed and the content and any results may not be used, reproduced or transmitted in any manner without express written permission from Microsoft Corporation.",
				"entityType": "Address",
				"matchCodes": [
					"Good"
				],
				"name": "368 Rue des Potentilles, Chicoutimi, QC G7G 0E3, Canada",
				"statusCode": 200,
				"statusDescription": "OK",
				"traceId": "b7dc7c33cbda4998b4aed4df4308aadc|BN20130447|7.7.0.0|",
				"addressLine": "368 Rue des Potentilles",
				"adminDistrict": "QC",
				"adminDistrict2": "Saguenay",
				"countryRegion": "Canada",
				"formattedAddress": "368 Rue des Potentilles, Chicoutimi, QC G7G 0E3, Canada",
				"locality": "Saguenay",
				"neighborhood": "Chicoutimi",
				"postalCode": "G7G 0E3"
			},
			"geometry": {
				"type": "Point",
				"coordinates": [
					-71.10248,
					48.45594
				]
			},
			"bbox": [
				-71.1041751,
				48.4548158,
				-71.1007849,
				48.4570642
			]
		}
	]
}
