{
	"type": "FeatureCollection",
	"features": [
		{
			"type": "Feature",
			"properties": {
				"confidence": 9,
				"authenticationResultCode": "ValidCredentials",
				"brandLogoUri": "http://dev.virtualearth.net/Branding/logo_powered_by.png",
				"copyright": "Copyright © 2017 Microsoft and its suppliers. All rights reserved. This API cannot be accessed and the content and any results may not be used, reproduced or transmitted in any manner without express written permission from Microsoft Corporation.",
				"entityType": "Address",
				"matchCodes": [
					"Good"
				],
				"name": "3684 Alberni Hwy, Qualicum Beach, BC V9K 1X7, Canada",
				"statusCode": 200,
				"statusDescription": "OK",
				"traceId": "63837ab5056649aab2a0e144e642786d|BN20260231|7.7.0.0|",
				"addressLine": "3684 Alberni Hwy",
				"adminDistrict": "BC",
				"adminDistrict2": "Nanaimo",
				"countryRegion": "Canada",
				"formattedAddress": "3684 Alberni Hwy, Qualicum Beach, BC V9K 1X7, Canada",
				"locality": "Nanaimo District",
				"neighborhood": "Qualicum Beach",
				"postalCode": "V9K 1X7"
			},
			"geometry": {
				"type": "Point",
				"coordinates": [
					-124.5204979,
					49.3111693
				]
			},
			"bbox": [
				-124.5222222,
				49.3100452,
				-124.5187736,
				49.3122935
			]
		}
	]
}
