{
	"type": "FeatureCollection",
	"features": [
		{
			"type": "Feature",
			"properties": {
				"confidence": 9,
				"authenticationResultCode": "ValidCredentials",
				"brandLogoUri": "http://dev.virtualearth.net/Branding/logo_powered_by.png",
				"copyright": "Copyright © 2017 Microsoft and its suppliers. All rights reserved. This API cannot be accessed and the content and any results may not be used, reproduced or transmitted in any manner without express written permission from Microsoft Corporation.",
				"entityType": "Address",
				"matchCodes": [
					"Good"
				],
				"name": "3688 12th Ave, Port Alberni, BC V9Y 5A2, Canada",
				"statusCode": 200,
				"statusDescription": "OK",
				"traceId": "f4c8326fb1d34c2d9c60f92c522fe2ce|BN20130447|7.7.0.0|",
				"addressLine": "3688 12th Ave",
				"adminDistrict": "BC",
				"adminDistrict2": "Alberni-Clayoquot",
				"countryRegion": "Canada",
				"formattedAddress": "3688 12th Ave, Port Alberni, BC V9Y 5A2, Canada",
				"locality": "Port Alberni",
				"postalCode": "V9Y 5A2"
			},
			"geometry": {
				"type": "Point",
				"coordinates": [
					-124.7953578,
					49.2432035
				]
			},
			"bbox": [
				-124.7970797,
				49.2420794,
				-124.7936359,
				49.2443277
			]
		}
	]
}
