{
	"type": "FeatureCollection",
	"features": [
		{
			"type": "Feature",
			"properties": {
				"confidence": 9,
				"authenticationResultCode": "ValidCredentials",
				"brandLogoUri": "http://dev.virtualearth.net/Branding/logo_powered_by.png",
				"copyright": "Copyright © 2017 Microsoft and its suppliers. All rights reserved. This API cannot be accessed and the content and any results may not be used, reproduced or transmitted in any manner without express written permission from Microsoft Corporation.",
				"entityType": "Address",
				"matchCodes": [
					"Good"
				],
				"name": "37 Sylvan Way, Winnipeg, MB R2R 2B9, Canada",
				"statusCode": 200,
				"statusDescription": "OK",
				"traceId": "f9336547e1c047c3886c0d11900faf23|BN20240423|7.7.0.0|",
				"addressLine": "37 Sylvan Way",
				"adminDistrict": "MB",
				"adminDistrict2": "Manitoba",
				"countryRegion": "Canada",
				"formattedAddress": "37 Sylvan Way, Winnipeg, MB R2R 2B9, Canada",
				"locality": "Winnipeg",
				"neighborhood": "Omand's Creek Industrial",
				"postalCode": "R2R 2B9"
			},
			"geometry": {
				"type": "Point",
				"coordinates": [
					-97.22571,
					49.92777
				]
			},
			"bbox": [
				-97.2274562,
				49.9266458,
				-97.2239638,
				49.9288942
			]
		}
	]
}
