{
	"type": "FeatureCollection",
	"features": [
		{
			"type": "Feature",
			"properties": {
				"confidence": 9,
				"authenticationResultCode": "ValidCredentials",
				"brandLogoUri": "http://dev.virtualearth.net/Branding/logo_powered_by.png",
				"copyright": "Copyright © 2017 Microsoft and its suppliers. All rights reserved. This API cannot be accessed and the content and any results may not be used, reproduced or transmitted in any manner without express written permission from Microsoft Corporation.",
				"entityType": "Address",
				"matchCodes": [
					"Good"
				],
				"name": "3730 Lansdowne Rd, Prince George, BC V2N 2S5, Canada",
				"statusCode": 200,
				"statusDescription": "OK",
				"traceId": "94ce82b00bb24d72923f364067152850|BN20130447|7.7.0.0|",
				"addressLine": "3730 Lansdowne Rd",
				"adminDistrict": "BC",
				"adminDistrict2": "Fraser-Fort George",
				"countryRegion": "Canada",
				"formattedAddress": "3730 Lansdowne Rd, Prince George, BC V2N 2S5, Canada",
				"locality": "Prince George",
				"postalCode": "V2N 2S5"
			},
			"geometry": {
				"type": "Point",
				"coordinates": [
					-122.76492,
					53.88307
				]
			},
			"bbox": [
				-122.7668272,
				53.8819458,
				-122.7630128,
				53.8841942
			]
		}
	]
}
