{
	"type": "FeatureCollection",
	"features": [
		{
			"type": "Feature",
			"properties": {
				"confidence": 9,
				"authenticationResultCode": "ValidCredentials",
				"brandLogoUri": "http://dev.virtualearth.net/Branding/logo_powered_by.png",
				"copyright": "Copyright © 2017 Microsoft and its suppliers. All rights reserved. This API cannot be accessed and the content and any results may not be used, reproduced or transmitted in any manner without express written permission from Microsoft Corporation.",
				"entityType": "Address",
				"matchCodes": [
					"Good"
				],
				"name": "3785 6th Line Rd, Haldimand, ON N0A 1M0, Canada",
				"statusCode": 200,
				"statusDescription": "OK",
				"traceId": "5fe4afed9fcf48188f73de268669a1d5|BN20171457|7.7.0.0|",
				"addressLine": "3785 6th Line Rd",
				"adminDistrict": "ON",
				"adminDistrict2": "Haldimand",
				"countryRegion": "Canada",
				"formattedAddress": "3785 6th Line Rd, Haldimand, ON N0A 1M0, Canada",
				"locality": "Haldimand",
				"postalCode": "N0A 1M0"
			},
			"geometry": {
				"type": "Point",
				"coordinates": [
					-79.9933347,
					43.064114
				]
			},
			"bbox": [
				-79.9948734,
				43.0629899,
				-79.991796,
				43.0652382
			]
		}
	]
}
