{
	"type": "FeatureCollection",
	"features": [
		{
			"type": "Feature",
			"properties": {
				"confidence": 9,
				"authenticationResultCode": "ValidCredentials",
				"brandLogoUri": "http://dev.virtualearth.net/Branding/logo_powered_by.png",
				"copyright": "Copyright © 2017 Microsoft and its suppliers. All rights reserved. This API cannot be accessed and the content and any results may not be used, reproduced or transmitted in any manner without express written permission from Microsoft Corporation.",
				"entityType": "Address",
				"matchCodes": [
					"Good"
				],
				"name": "379 Harrington Rd, Frankford, ON K0K 2C0, Canada",
				"statusCode": 200,
				"statusDescription": "OK",
				"traceId": "690ae340098f4d4ba32d6e4cda57a7e5|BN20130442|7.7.0.0|",
				"addressLine": "379 Harrington Rd",
				"adminDistrict": "ON",
				"adminDistrict2": "Hastings",
				"countryRegion": "Canada",
				"formattedAddress": "379 Harrington Rd, Frankford, ON K0K 2C0, Canada",
				"locality": "Quinte West",
				"neighborhood": "Frankford",
				"postalCode": "K0K 2C0"
			},
			"geometry": {
				"type": "Point",
				"coordinates": [
					-77.49789,
					44.19943
				]
			},
			"bbox": [
				-77.499458,
				44.1983058,
				-77.496322,
				44.2005542
			]
		}
	]
}
