{
	"type": "FeatureCollection",
	"features": [
		{
			"type": "Feature",
			"properties": {
				"confidence": 9,
				"authenticationResultCode": "ValidCredentials",
				"brandLogoUri": "http://dev.virtualearth.net/Branding/logo_powered_by.png",
				"copyright": "Copyright © 2017 Microsoft and its suppliers. All rights reserved. This API cannot be accessed and the content and any results may not be used, reproduced or transmitted in any manner without express written permission from Microsoft Corporation.",
				"entityType": "Address",
				"matchCodes": [
					"Good"
				],
				"name": "38 Chemin Grimes, Gatineau, QC J9J 1H5, Canada",
				"statusCode": 200,
				"statusDescription": "OK",
				"traceId": "553d59aa7c5344d1b0f6338d577026c3|BN20210145|7.7.0.0|",
				"addressLine": "38 Chemin Grimes",
				"adminDistrict": "QC",
				"adminDistrict2": "Gatineau",
				"countryRegion": "Canada",
				"formattedAddress": "38 Chemin Grimes, Gatineau, QC J9J 1H5, Canada",
				"locality": "Gatineau",
				"neighborhood": "Aylmer",
				"postalCode": "J9J 1H5"
			},
			"geometry": {
				"type": "Point",
				"coordinates": [
					-75.8208499,
					45.40058
				]
			},
			"bbox": [
				-75.8224509,
				45.3994558,
				-75.8192489,
				45.4017042
			]
		}
	]
}
