{
	"type": "FeatureCollection",
	"features": [
		{
			"type": "Feature",
			"properties": {
				"confidence": 9,
				"authenticationResultCode": "ValidCredentials",
				"brandLogoUri": "http://dev.virtualearth.net/Branding/logo_powered_by.png",
				"copyright": "Copyright © 2017 Microsoft and its suppliers. All rights reserved. This API cannot be accessed and the content and any results may not be used, reproduced or transmitted in any manner without express written permission from Microsoft Corporation.",
				"entityType": "Address",
				"matchCodes": [
					"Good"
				],
				"name": "38 Haniak Rd, Rosslyn, ON P7K 0C8, Canada",
				"statusCode": 200,
				"statusDescription": "OK",
				"traceId": "b2850315bb174e0f9db6b35cc815b7c4|BN20130422|7.7.0.0|",
				"addressLine": "38 Haniak Rd",
				"adminDistrict": "ON",
				"adminDistrict2": "Thunder Bay",
				"countryRegion": "Canada",
				"formattedAddress": "38 Haniak Rd, Rosslyn, ON P7K 0C8, Canada",
				"locality": "Oliver Paipoonge",
				"neighborhood": "Rosslyn",
				"postalCode": "P7K 0C8"
			},
			"geometry": {
				"type": "Point",
				"coordinates": [
					-89.4012874,
					48.3788721
				]
			},
			"bbox": [
				-89.4029798,
				48.3777479,
				-89.3995949,
				48.3799962
			]
		}
	]
}
