{
	"type": "FeatureCollection",
	"features": [
		{
			"type": "Feature",
			"properties": {
				"confidence": 9,
				"authenticationResultCode": "ValidCredentials",
				"brandLogoUri": "http://dev.virtualearth.net/Branding/logo_powered_by.png",
				"copyright": "Copyright © 2017 Microsoft and its suppliers. All rights reserved. This API cannot be accessed and the content and any results may not be used, reproduced or transmitted in any manner without express written permission from Microsoft Corporation.",
				"entityType": "Address",
				"matchCodes": [
					"Good"
				],
				"name": "38 Reston Ridge St, Markham, ON L6E 1J5, Canada",
				"statusCode": 200,
				"statusDescription": "OK",
				"traceId": "3bb0f32c47c84cfc89dd0081a93b346d|BN20250135|7.7.0.0|",
				"addressLine": "38 Reston Ridge St",
				"adminDistrict": "ON",
				"adminDistrict2": "York",
				"countryRegion": "Canada",
				"formattedAddress": "38 Reston Ridge St, Markham, ON L6E 1J5, Canada",
				"locality": "Markham",
				"postalCode": "L6E 1J5"
			},
			"geometry": {
				"type": "Point",
				"coordinates": [
					-79.2443,
					43.90095
				]
			},
			"bbox": [
				-79.2458602,
				43.8998258,
				-79.2427398,
				43.9020742
			]
		}
	]
}
