{
	"type": "FeatureCollection",
	"features": [
		{
			"type": "Feature",
			"properties": {
				"confidence": 9,
				"authenticationResultCode": "ValidCredentials",
				"brandLogoUri": "http://dev.virtualearth.net/Branding/logo_powered_by.png",
				"copyright": "Copyright © 2017 Microsoft and its suppliers. All rights reserved. This API cannot be accessed and the content and any results may not be used, reproduced or transmitted in any manner without express written permission from Microsoft Corporation.",
				"entityType": "Address",
				"matchCodes": [
					"Good"
				],
				"name": "3815 7 St SW, Calgary, AB T2T 2Y4, Canada",
				"statusCode": 200,
				"statusDescription": "OK",
				"traceId": "2e29f7681f3a4dce8a8be38f75b2f19b|BN20171457|7.7.0.0|",
				"addressLine": "3815 7 St SW",
				"adminDistrict": "AB",
				"adminDistrict2": "Alberta",
				"countryRegion": "Canada",
				"formattedAddress": "3815 7 St SW, Calgary, AB T2T 2Y4, Canada",
				"locality": "Calgary",
				"neighborhood": "Elbow Park",
				"postalCode": "T2T 2Y4"
			},
			"geometry": {
				"type": "Point",
				"coordinates": [
					-114.08093,
					51.02109
				]
			},
			"bbox": [
				-114.0827171,
				51.0199658,
				-114.0791429,
				51.0222142
			]
		}
	]
}
