{
	"type": "FeatureCollection",
	"features": [
		{
			"type": "Feature",
			"properties": {
				"confidence": 9,
				"authenticationResultCode": "ValidCredentials",
				"brandLogoUri": "http://dev.virtualearth.net/Branding/logo_powered_by.png",
				"copyright": "Copyright © 2017 Microsoft and its suppliers. All rights reserved. This API cannot be accessed and the content and any results may not be used, reproduced or transmitted in any manner without express written permission from Microsoft Corporation.",
				"entityType": "Address",
				"matchCodes": [
					"Good"
				],
				"name": "386 Kwapis Blvd, Newmarket, ON L3X 3H1, Canada",
				"statusCode": 200,
				"statusDescription": "OK",
				"traceId": "f3be8e211fcc425cbbfa7f932876b07c|BN20130719|7.7.0.0|",
				"addressLine": "386 Kwapis Blvd",
				"adminDistrict": "ON",
				"adminDistrict2": "York",
				"countryRegion": "Canada",
				"formattedAddress": "386 Kwapis Blvd, Newmarket, ON L3X 3H1, Canada",
				"locality": "Newmarket",
				"postalCode": "L3X 3H1"
			},
			"geometry": {
				"type": "Point",
				"coordinates": [
					-79.49299,
					44.0614
				]
			},
			"bbox": [
				-79.4945544,
				44.0602758,
				-79.4914256,
				44.0625242
			]
		}
	]
}
