{
	"type": "FeatureCollection",
	"features": [
		{
			"type": "Feature",
			"properties": {
				"confidence": 9,
				"authenticationResultCode": "ValidCredentials",
				"brandLogoUri": "http://dev.virtualearth.net/Branding/logo_powered_by.png",
				"copyright": "Copyright © 2017 Microsoft and its suppliers. All rights reserved. This API cannot be accessed and the content and any results may not be used, reproduced or transmitted in any manner without express written permission from Microsoft Corporation.",
				"entityType": "Address",
				"matchCodes": [
					"Good"
				],
				"name": "3874 Rue Queen, Rawdon, QC J0K 1S0, Canada",
				"statusCode": 200,
				"statusDescription": "OK",
				"traceId": "fe7e778ed5234120ab6d7618063b7f7a|BN20220145|7.7.0.0|",
				"addressLine": "3874 Rue Queen",
				"adminDistrict": "QC",
				"adminDistrict2": "Matawinie",
				"countryRegion": "Canada",
				"formattedAddress": "3874 Rue Queen, Rawdon, QC J0K 1S0, Canada",
				"locality": "Rawdon",
				"postalCode": "J0K 1S0"
			},
			"geometry": {
				"type": "Point",
				"coordinates": [
					-73.71536,
					46.04818
				]
			},
			"bbox": [
				-73.7169797,
				46.0470558,
				-73.7137403,
				46.0493042
			]
		}
	]
}
