{
	"type": "FeatureCollection",
	"features": [
		{
			"type": "Feature",
			"properties": {
				"confidence": 9,
				"authenticationResultCode": "ValidCredentials",
				"brandLogoUri": "http://dev.virtualearth.net/Branding/logo_powered_by.png",
				"copyright": "Copyright © 2017 Microsoft and its suppliers. All rights reserved. This API cannot be accessed and the content and any results may not be used, reproduced or transmitted in any manner without express written permission from Microsoft Corporation.",
				"entityType": "Address",
				"matchCodes": [
					"Good"
				],
				"name": "3875 Rue Isabelle, Brossard, QC J4Y 2R2, Canada",
				"statusCode": 200,
				"statusDescription": "OK",
				"traceId": "5e8bf87b940449dcacc4bb29610f068c|BN20181720|7.7.0.0|",
				"addressLine": "3875 Rue Isabelle",
				"adminDistrict": "QC",
				"adminDistrict2": "Longueuil",
				"countryRegion": "Canada",
				"formattedAddress": "3875 Rue Isabelle, Brossard, QC J4Y 2R2, Canada",
				"locality": "Brossard",
				"neighborhood": "Brosseau",
				"postalCode": "J4Y 2R2"
			},
			"geometry": {
				"type": "Point",
				"coordinates": [
					-73.46786,
					45.42727
				]
			},
			"bbox": [
				-73.4694618,
				45.4261458,
				-73.4662582,
				45.4283942
			]
		}
	]
}
