{
	"type": "FeatureCollection",
	"features": [
		{
			"type": "Feature",
			"properties": {
				"confidence": 9,
				"authenticationResultCode": "ValidCredentials",
				"brandLogoUri": "http://dev.virtualearth.net/Branding/logo_powered_by.png",
				"copyright": "Copyright © 2017 Microsoft and its suppliers. All rights reserved. This API cannot be accessed and the content and any results may not be used, reproduced or transmitted in any manner without express written permission from Microsoft Corporation.",
				"entityType": "Address",
				"matchCodes": [
					"Good"
				],
				"name": "39 Pantego Clos NW, Calgary, AB T3K 0K1, Canada",
				"statusCode": 200,
				"statusDescription": "OK",
				"traceId": "8a158e11d13f45049a26c96983cfe7de|BN20240423|7.7.0.0|",
				"addressLine": "39 Pantego Clos NW",
				"adminDistrict": "AB",
				"adminDistrict2": "Alberta",
				"countryRegion": "Canada",
				"formattedAddress": "39 Pantego Clos NW, Calgary, AB T3K 0K1, Canada",
				"locality": "Calgary",
				"neighborhood": "Panorama Hills",
				"postalCode": "T3K 0K1"
			},
			"geometry": {
				"type": "Point",
				"coordinates": [
					-114.09378,
					51.16372
				]
			},
			"bbox": [
				-114.0955726,
				51.1625958,
				-114.0919874,
				51.1648442
			]
		}
	]
}
