{
	"type": "FeatureCollection",
	"features": [
		{
			"type": "Feature",
			"properties": {
				"confidence": 9,
				"authenticationResultCode": "ValidCredentials",
				"brandLogoUri": "http://dev.virtualearth.net/Branding/logo_powered_by.png",
				"copyright": "Copyright © 2017 Microsoft and its suppliers. All rights reserved. This API cannot be accessed and the content and any results may not be used, reproduced or transmitted in any manner without express written permission from Microsoft Corporation.",
				"entityType": "Address",
				"matchCodes": [
					"Good"
				],
				"name": "390 Alliance Ave, York, ON M6N 2H8, Canada",
				"statusCode": 200,
				"statusDescription": "OK",
				"traceId": "d2efcd566a694f37b60f6ec296b29f9f|BN20290118|7.7.0.0|",
				"addressLine": "390 Alliance Ave",
				"adminDistrict": "ON",
				"adminDistrict2": "Toronto",
				"countryRegion": "Canada",
				"formattedAddress": "390 Alliance Ave, York, ON M6N 2H8, Canada",
				"locality": "Toronto",
				"neighborhood": "Rockcliffe-Smythe",
				"postalCode": "M6N 2H8"
			},
			"geometry": {
				"type": "Point",
				"coordinates": [
					-79.48582,
					43.67826
				]
			},
			"bbox": [
				-79.4873744,
				43.6771358,
				-79.4842656,
				43.6793842
			]
		}
	]
}
