{
	"type": "FeatureCollection",
	"features": [
		{
			"type": "Feature",
			"properties": {
				"confidence": 9,
				"authenticationResultCode": "ValidCredentials",
				"brandLogoUri": "http://dev.virtualearth.net/Branding/logo_powered_by.png",
				"copyright": "Copyright © 2017 Microsoft and its suppliers. All rights reserved. This API cannot be accessed and the content and any results may not be used, reproduced or transmitted in any manner without express written permission from Microsoft Corporation.",
				"entityType": "Address",
				"matchCodes": [
					"Good"
				],
				"name": "390 Murray St, Mulgrave, NS B0E, Canada",
				"statusCode": 200,
				"statusDescription": "OK",
				"traceId": "2daf9102a5b545278596cdf7623375e3|BN20130632|7.7.0.0|",
				"addressLine": "390 Murray St",
				"adminDistrict": "NS",
				"adminDistrict2": "Guysborough",
				"countryRegion": "Canada",
				"formattedAddress": "390 Murray St, Mulgrave, NS B0E, Canada",
				"locality": "Mulgrave",
				"postalCode": "B0E 2G0"
			},
			"geometry": {
				"type": "Point",
				"coordinates": [
					-61.39444,
					45.6086699
				]
			},
			"bbox": [
				-61.396047,
				45.6075457,
				-61.392833,
				45.6097941
			]
		}
	]
}
