{
	"type": "FeatureCollection",
	"features": [
		{
			"type": "Feature",
			"properties": {
				"confidence": 9,
				"authenticationResultCode": "ValidCredentials",
				"brandLogoUri": "http://dev.virtualearth.net/Branding/logo_powered_by.png",
				"copyright": "Copyright © 2017 Microsoft and its suppliers. All rights reserved. This API cannot be accessed and the content and any results may not be used, reproduced or transmitted in any manner without express written permission from Microsoft Corporation.",
				"entityType": "Address",
				"matchCodes": [
					"Good"
				],
				"name": "390 Atwood Ln, Oakville, ON L6H 5G2, Canada",
				"statusCode": 200,
				"statusDescription": "OK",
				"traceId": "f1484bed58b1486781762d7c1139f594|BN20130431|7.7.0.0|",
				"addressLine": "390 Atwood Ln",
				"adminDistrict": "ON",
				"adminDistrict2": "Halton",
				"countryRegion": "Canada",
				"formattedAddress": "390 Atwood Ln, Oakville, ON L6H 5G2, Canada",
				"locality": "Oakville",
				"neighborhood": "River Oaks",
				"postalCode": "L6H 5G2"
			},
			"geometry": {
				"type": "Point",
				"coordinates": [
					-79.7329199,
					43.46418
				]
			},
			"bbox": [
				-79.7344687,
				43.4630558,
				-79.7313711,
				43.4653042
			]
		}
	]
}
