{
	"type": "FeatureCollection",
	"features": [
		{
			"type": "Feature",
			"properties": {
				"confidence": 9,
				"authenticationResultCode": "ValidCredentials",
				"brandLogoUri": "http://dev.virtualearth.net/Branding/logo_powered_by.png",
				"copyright": "Copyright © 2017 Microsoft and its suppliers. All rights reserved. This API cannot be accessed and the content and any results may not be used, reproduced or transmitted in any manner without express written permission from Microsoft Corporation.",
				"entityType": "Address",
				"matchCodes": [
					"Good"
				],
				"name": "3925 Fraser St, Vancouver, BC V5V 4E5, Canada",
				"statusCode": 200,
				"statusDescription": "OK",
				"traceId": "90534c75bff9405e8623699de751ddf8|BN20130631|7.7.0.0|",
				"addressLine": "3925 Fraser St",
				"adminDistrict": "BC",
				"adminDistrict2": "Greater Vancouver",
				"countryRegion": "Canada",
				"formattedAddress": "3925 Fraser St, Vancouver, BC V5V 4E5, Canada",
				"locality": "Vancouver",
				"neighborhood": "Riley Park",
				"postalCode": "V5V 4E5"
			},
			"geometry": {
				"type": "Point",
				"coordinates": [
					-123.0906,
					49.24965
				]
			},
			"bbox": [
				-123.0923221,
				49.2485258,
				-123.0888779,
				49.2507742
			]
		}
	]
}
