{
	"type": "FeatureCollection",
	"features": [
		{
			"type": "Feature",
			"properties": {
				"confidence": 9,
				"authenticationResultCode": "ValidCredentials",
				"brandLogoUri": "http://dev.virtualearth.net/Branding/logo_powered_by.png",
				"copyright": "Copyright © 2017 Microsoft and its suppliers. All rights reserved. This API cannot be accessed and the content and any results may not be used, reproduced or transmitted in any manner without express written permission from Microsoft Corporation.",
				"entityType": "Address",
				"matchCodes": [
					"Good"
				],
				"name": "3939 Duke of York Blvd, Mississauga, ON L5B 4N2, Canada",
				"statusCode": 200,
				"statusDescription": "OK",
				"traceId": "4dcf7c1448334880b0b80df6e0185c72|BN20130423|7.7.0.0|",
				"addressLine": "3939 Duke of York Blvd",
				"adminDistrict": "ON",
				"adminDistrict2": "Peel",
				"countryRegion": "Canada",
				"formattedAddress": "3939 Duke of York Blvd, Mississauga, ON L5B 4N2, Canada",
				"locality": "Mississauga",
				"neighborhood": "Cooksville",
				"postalCode": "L5B 4N2"
			},
			"geometry": {
				"type": "Point",
				"coordinates": [
					-79.64075,
					43.58817
				]
			},
			"bbox": [
				-79.642302,
				43.5870458,
				-79.639198,
				43.5892942
			]
		}
	]
}
