{
	"type": "FeatureCollection",
	"features": [
		{
			"type": "Feature",
			"properties": {
				"confidence": 9,
				"authenticationResultCode": "ValidCredentials",
				"brandLogoUri": "http://dev.virtualearth.net/Branding/logo_powered_by.png",
				"copyright": "Copyright © 2017 Microsoft and its suppliers. All rights reserved. This API cannot be accessed and the content and any results may not be used, reproduced or transmitted in any manner without express written permission from Microsoft Corporation.",
				"entityType": "Address",
				"matchCodes": [
					"Good"
				],
				"name": "395 Ossington Ave, Toronto, ON M6J 3A6, Canada",
				"statusCode": 200,
				"statusDescription": "OK",
				"traceId": "2af970fd179d481286eb8e3580826d51|BN20240423|7.7.0.0|",
				"addressLine": "395 Ossington Ave",
				"adminDistrict": "ON",
				"adminDistrict2": "Toronto",
				"countryRegion": "Canada",
				"formattedAddress": "395 Ossington Ave, Toronto, ON M6J 3A6, Canada",
				"locality": "Toronto",
				"neighborhood": "Trinity-Bellwoods",
				"postalCode": "M6J 3A6"
			},
			"geometry": {
				"type": "Point",
				"coordinates": [
					-79.42193,
					43.65322
				]
			},
			"bbox": [
				-79.4234837,
				43.6520958,
				-79.4203763,
				43.6543442
			]
		}
	]
}
