{
	"type": "FeatureCollection",
	"features": [
		{
			"type": "Feature",
			"properties": {
				"confidence": 9,
				"authenticationResultCode": "ValidCredentials",
				"brandLogoUri": "http://dev.virtualearth.net/Branding/logo_powered_by.png",
				"copyright": "Copyright © 2017 Microsoft and its suppliers. All rights reserved. This API cannot be accessed and the content and any results may not be used, reproduced or transmitted in any manner without express written permission from Microsoft Corporation.",
				"entityType": "Address",
				"matchCodes": [
					"Good"
				],
				"name": "3965 Dumfries St, Vancouver, BC V5N 5R3, Canada",
				"statusCode": 200,
				"statusDescription": "OK",
				"traceId": "c3f820b145074bcfbf8fa121dd95629e|BN20121763|7.7.0.0|",
				"addressLine": "3965 Dumfries St",
				"adminDistrict": "BC",
				"adminDistrict2": "Greater Vancouver",
				"countryRegion": "Canada",
				"formattedAddress": "3965 Dumfries St, Vancouver, BC V5N 5R3, Canada",
				"locality": "Vancouver",
				"neighborhood": "Kensington-Cedar Cottage",
				"postalCode": "V5N 5R3"
			},
			"geometry": {
				"type": "Point",
				"coordinates": [
					-123.0735183,
					49.2497686
				]
			},
			"bbox": [
				-123.0752404,
				49.2486445,
				-123.0717961,
				49.2508928
			]
		}
	]
}
