{
	"type": "FeatureCollection",
	"features": [
		{
			"type": "Feature",
			"properties": {
				"confidence": 9,
				"authenticationResultCode": "ValidCredentials",
				"brandLogoUri": "http://dev.virtualearth.net/Branding/logo_powered_by.png",
				"copyright": "Copyright © 2017 Microsoft and its suppliers. All rights reserved. This API cannot be accessed and the content and any results may not be used, reproduced or transmitted in any manner without express written permission from Microsoft Corporation.",
				"entityType": "Address",
				"matchCodes": [
					"Good"
				],
				"name": "399 Rue Racine E, Chicoutimi, QC G7H 1S8, Canada",
				"statusCode": 200,
				"statusDescription": "OK",
				"traceId": "6f19394225e14bf3978edd92e6cca73e|BN20130632|7.7.0.0|",
				"addressLine": "399 Rue Racine E",
				"adminDistrict": "QC",
				"adminDistrict2": "Saguenay",
				"countryRegion": "Canada",
				"formattedAddress": "399 Rue Racine E, Chicoutimi, QC G7H 1S8, Canada",
				"locality": "Saguenay",
				"neighborhood": "Chicoutimi",
				"postalCode": "G7H 1S8"
			},
			"geometry": {
				"type": "Point",
				"coordinates": [
					-71.0562999,
					48.42824
				]
			},
			"bbox": [
				-71.057994,
				48.4271158,
				-71.0546058,
				48.4293642
			]
		}
	]
}
