{
	"type": "FeatureCollection",
	"features": [
		{
			"type": "Feature",
			"properties": {
				"confidence": 9,
				"authenticationResultCode": "ValidCredentials",
				"brandLogoUri": "http://dev.virtualearth.net/Branding/logo_powered_by.png",
				"copyright": "Copyright © 2017 Microsoft and its suppliers. All rights reserved. This API cannot be accessed and the content and any results may not be used, reproduced or transmitted in any manner without express written permission from Microsoft Corporation.",
				"entityType": "Address",
				"matchCodes": [
					"Good"
				],
				"name": "4 Rue du Fanion, Gatineau, QC J9J 2S6, Canada",
				"statusCode": 200,
				"statusDescription": "OK",
				"traceId": "3069967cd5984555a196ec33122555b2|BN20171457|7.7.0.0|",
				"addressLine": "4 Rue du Fanion",
				"adminDistrict": "QC",
				"adminDistrict2": "Gatineau",
				"countryRegion": "Canada",
				"formattedAddress": "4 Rue du Fanion, Gatineau, QC J9J 2S6, Canada",
				"locality": "Gatineau",
				"neighborhood": "Aylmer",
				"postalCode": "J9J 2S6"
			},
			"geometry": {
				"type": "Point",
				"coordinates": [
					-75.81362,
					45.39958
				]
			},
			"bbox": [
				-75.815221,
				45.3984558,
				-75.812019,
				45.4007042
			]
		}
	]
}
