{
	"type": "FeatureCollection",
	"features": [
		{
			"type": "Feature",
			"properties": {
				"confidence": 9,
				"authenticationResultCode": "ValidCredentials",
				"brandLogoUri": "http://dev.virtualearth.net/Branding/logo_powered_by.png",
				"copyright": "Copyright © 2017 Microsoft and its suppliers. All rights reserved. This API cannot be accessed and the content and any results may not be used, reproduced or transmitted in any manner without express written permission from Microsoft Corporation.",
				"entityType": "Address",
				"matchCodes": [
					"Good"
				],
				"name": "4 Howe St, Hillsburgh, ON N0B 1Z0, Canada",
				"statusCode": 200,
				"statusDescription": "OK",
				"traceId": "7fed5fe2575840e1b4c1fb1b8f524be9|BN20160335|7.7.0.0|",
				"addressLine": "4 Howe St",
				"adminDistrict": "ON",
				"adminDistrict2": "Wellington",
				"countryRegion": "Canada",
				"formattedAddress": "4 Howe St, Hillsburgh, ON N0B 1Z0, Canada",
				"locality": "Erin",
				"neighborhood": "Hillsburgh",
				"postalCode": "N0B 1Z0"
			},
			"geometry": {
				"type": "Point",
				"coordinates": [
					-80.1499,
					43.79555
				]
			},
			"bbox": [
				-80.1514574,
				43.7944258,
				-80.1483426,
				43.7966742
			]
		}
	]
}
