{
	"type": "FeatureCollection",
	"features": [
		{
			"type": "Feature",
			"properties": {
				"confidence": 9,
				"authenticationResultCode": "ValidCredentials",
				"brandLogoUri": "http://dev.virtualearth.net/Branding/logo_powered_by.png",
				"copyright": "Copyright © 2017 Microsoft and its suppliers. All rights reserved. This API cannot be accessed and the content and any results may not be used, reproduced or transmitted in any manner without express written permission from Microsoft Corporation.",
				"entityType": "Address",
				"matchCodes": [
					"Good"
				],
				"name": "4 Jewelville St, Brampton, ON L6X 2Y7, Canada",
				"statusCode": 200,
				"statusDescription": "OK",
				"traceId": "895e2c2e915d478da953ee34f633d0cb|BN20130520|7.7.0.0|",
				"addressLine": "4 Jewelville St",
				"adminDistrict": "ON",
				"adminDistrict2": "Peel",
				"countryRegion": "Canada",
				"formattedAddress": "4 Jewelville St, Brampton, ON L6X 2Y7, Canada",
				"locality": "Brampton",
				"neighborhood": "Mt Pleasant",
				"postalCode": "L6X 2Y7"
			},
			"geometry": {
				"type": "Point",
				"coordinates": [
					-79.8022699,
					43.66308
				]
			},
			"bbox": [
				-79.8038239,
				43.6619558,
				-79.8007159,
				43.6642042
			]
		}
	]
}
