{
	"type": "FeatureCollection",
	"features": [
		{
			"type": "Feature",
			"properties": {
				"confidence": 9,
				"authenticationResultCode": "ValidCredentials",
				"brandLogoUri": "http://dev.virtualearth.net/Branding/logo_powered_by.png",
				"copyright": "Copyright © 2017 Microsoft and its suppliers. All rights reserved. This API cannot be accessed and the content and any results may not be used, reproduced or transmitted in any manner without express written permission from Microsoft Corporation.",
				"entityType": "Address",
				"matchCodes": [
					"Good"
				],
				"name": "400 4 Ave SW, Calgary, AB T2P 0J4, Canada",
				"statusCode": 200,
				"statusDescription": "OK",
				"traceId": "c20015ec199e4ed89f05f0b5b0a18366|BN20300154|7.7.0.0|",
				"addressLine": "400 4 Ave SW",
				"adminDistrict": "AB",
				"adminDistrict2": "Alberta",
				"countryRegion": "Canada",
				"formattedAddress": "400 4 Ave SW, Calgary, AB T2P 0J4, Canada",
				"locality": "Calgary",
				"neighborhood": "Downtown",
				"postalCode": "T2P 0J4"
			},
			"geometry": {
				"type": "Point",
				"coordinates": [
					-114.07093,
					51.04971
				]
			},
			"bbox": [
				-114.0727182,
				51.0485858,
				-114.0691418,
				51.0508342
			]
		}
	]
}
