{
	"type": "FeatureCollection",
	"features": [
		{
			"type": "Feature",
			"properties": {
				"confidence": 9,
				"authenticationResultCode": "ValidCredentials",
				"brandLogoUri": "http://dev.virtualearth.net/Branding/logo_powered_by.png",
				"copyright": "Copyright © 2017 Microsoft and its suppliers. All rights reserved. This API cannot be accessed and the content and any results may not be used, reproduced or transmitted in any manner without express written permission from Microsoft Corporation.",
				"entityType": "Address",
				"matchCodes": [
					"Good"
				],
				"name": "400 Keystone Chas W, Lethbridge, AB T1J 5C4, Canada",
				"statusCode": 200,
				"statusDescription": "OK",
				"traceId": "e90d18f36e6049d68b3fbad87ff92fc9|BN20290118|7.7.0.0|",
				"addressLine": "400 Keystone Chas W",
				"adminDistrict": "AB",
				"adminDistrict2": "Alberta",
				"countryRegion": "Canada",
				"formattedAddress": "400 Keystone Chas W, Lethbridge, AB T1J 5C4, Canada",
				"locality": "Lethbridge",
				"postalCode": "T1J 5C4"
			},
			"geometry": {
				"type": "Point",
				"coordinates": [
					-112.9081904,
					49.6684324
				]
			},
			"bbox": [
				-112.9099273,
				49.6673083,
				-112.9064534,
				49.6695566
			]
		}
	]
}
