{
	"type": "FeatureCollection",
	"features": [
		{
			"type": "Feature",
			"properties": {
				"confidence": 9,
				"authenticationResultCode": "ValidCredentials",
				"brandLogoUri": "http://dev.virtualearth.net/Branding/logo_powered_by.png",
				"copyright": "Copyright © 2017 Microsoft and its suppliers. All rights reserved. This API cannot be accessed and the content and any results may not be used, reproduced or transmitted in any manner without express written permission from Microsoft Corporation.",
				"entityType": "Address",
				"matchCodes": [
					"Good"
				],
				"name": "400 Shuswap Ave, Chase, BC V0E, Canada",
				"statusCode": 200,
				"statusDescription": "OK",
				"traceId": "9afd1e556ff54baa8affff68ad25d3c3|BN20130721|7.7.0.0|",
				"addressLine": "400 Shuswap Ave",
				"adminDistrict": "BC",
				"adminDistrict2": "Thompson-Nicola",
				"countryRegion": "Canada",
				"formattedAddress": "400 Shuswap Ave, Chase, BC V0E, Canada",
				"locality": "Chase",
				"postalCode": "V0E 1M0"
			},
			"geometry": {
				"type": "Point",
				"coordinates": [
					-119.6934,
					50.8168999
				]
			},
			"bbox": [
				-119.6951793,
				50.8157757,
				-119.6916207,
				50.8180241
			]
		}
	]
}
