{
	"type": "FeatureCollection",
	"features": [
		{
			"type": "Feature",
			"properties": {
				"confidence": 9,
				"authenticationResultCode": "ValidCredentials",
				"brandLogoUri": "http://dev.virtualearth.net/Branding/logo_powered_by.png",
				"copyright": "Copyright © 2017 Microsoft and its suppliers. All rights reserved. This API cannot be accessed and the content and any results may not be used, reproduced or transmitted in any manner without express written permission from Microsoft Corporation.",
				"entityType": "Address",
				"matchCodes": [
					"Good"
				],
				"name": "4015 53 St, Athabasca, AB T9S 1A7, Canada",
				"statusCode": 200,
				"statusDescription": "OK",
				"traceId": "a631933a6973480bac7926cee1671d46|BN20130532|7.7.0.0|",
				"addressLine": "4015 53 St",
				"adminDistrict": "AB",
				"adminDistrict2": "Alberta",
				"countryRegion": "Canada",
				"formattedAddress": "4015 53 St, Athabasca, AB T9S 1A7, Canada",
				"locality": "Athabasca",
				"postalCode": "T9S 1A7"
			},
			"geometry": {
				"type": "Point",
				"coordinates": [
					-113.29573,
					54.70849
				]
			},
			"bbox": [
				-113.2976758,
				54.7073658,
				-113.2937842,
				54.7096142
			]
		}
	]
}
