{
	"type": "FeatureCollection",
	"features": [
		{
			"type": "Feature",
			"properties": {
				"confidence": 9,
				"authenticationResultCode": "ValidCredentials",
				"brandLogoUri": "http://dev.virtualearth.net/Branding/logo_powered_by.png",
				"copyright": "Copyright © 2017 Microsoft and its suppliers. All rights reserved. This API cannot be accessed and the content and any results may not be used, reproduced or transmitted in any manner without express written permission from Microsoft Corporation.",
				"entityType": "Address",
				"matchCodes": [
					"Good"
				],
				"name": "4025 Rue Lesage, Sherbrooke, QC J1L 2Z9, Canada",
				"statusCode": 200,
				"statusDescription": "OK",
				"traceId": "6e78d7b997494dc38f705d1b94846df2|BN20130442|7.7.0.0|",
				"addressLine": "4025 Rue Lesage",
				"adminDistrict": "QC",
				"adminDistrict2": "Sherbrooke",
				"countryRegion": "Canada",
				"formattedAddress": "4025 Rue Lesage, Sherbrooke, QC J1L 2Z9, Canada",
				"locality": "Sherbrooke",
				"postalCode": "J1L 2Z9"
			},
			"geometry": {
				"type": "Point",
				"coordinates": [
					-71.96127,
					45.39615
				]
			},
			"bbox": [
				-71.9628709,
				45.3950258,
				-71.9596691,
				45.3972742
			]
		}
	]
}
