{
	"type": "FeatureCollection",
	"features": [
		{
			"type": "Feature",
			"properties": {
				"confidence": 9,
				"authenticationResultCode": "ValidCredentials",
				"brandLogoUri": "http://dev.virtualearth.net/Branding/logo_powered_by.png",
				"copyright": "Copyright © 2017 Microsoft and its suppliers. All rights reserved. This API cannot be accessed and the content and any results may not be used, reproduced or transmitted in any manner without express written permission from Microsoft Corporation.",
				"entityType": "Address",
				"matchCodes": [
					"Good"
				],
				"name": "403 Railway Ave W, Gillam, MB R0B, Canada",
				"statusCode": 200,
				"statusDescription": "OK",
				"traceId": "a1e1e10e2b0f403bb854496dd82748bc|BN20130521|7.7.0.0|",
				"addressLine": "403 Railway Ave W",
				"adminDistrict": "MB",
				"adminDistrict2": "Manitoba",
				"countryRegion": "Canada",
				"formattedAddress": "403 Railway Ave W, Gillam, MB R0B, Canada",
				"locality": "Gillam",
				"postalCode": "R0B 0L0"
			},
			"geometry": {
				"type": "Point",
				"coordinates": [
					-94.70885,
					56.34586
				]
			},
			"bbox": [
				-94.7108785,
				56.3447358,
				-94.7068215,
				56.3469842
			]
		}
	]
}
