{
	"type": "FeatureCollection",
	"features": [
		{
			"type": "Feature",
			"properties": {
				"confidence": 9,
				"authenticationResultCode": "ValidCredentials",
				"brandLogoUri": "http://dev.virtualearth.net/Branding/logo_powered_by.png",
				"copyright": "Copyright © 2017 Microsoft and its suppliers. All rights reserved. This API cannot be accessed and the content and any results may not be used, reproduced or transmitted in any manner without express written permission from Microsoft Corporation.",
				"entityType": "Address",
				"matchCodes": [
					"Good"
				],
				"name": "4044 Express Point Rd, Scotch Creek, BC V0E 1M5, Canada",
				"statusCode": 200,
				"statusDescription": "OK",
				"traceId": "4e46b213e5ea47a78e26363e32eb6488|BN20130522|7.7.0.0|",
				"addressLine": "4044 Express Point Rd",
				"adminDistrict": "BC",
				"adminDistrict2": "Columbia-Shuswap",
				"countryRegion": "Canada",
				"formattedAddress": "4044 Express Point Rd, Scotch Creek, BC V0E 1M5, Canada",
				"locality": "Columbia-Shuswap",
				"neighborhood": "Scotch Creek",
				"postalCode": "V0E 1M5"
			},
			"geometry": {
				"type": "Point",
				"coordinates": [
					-119.44373,
					50.90318
				]
			},
			"bbox": [
				-119.4455126,
				50.9020558,
				-119.4419474,
				50.9043042
			]
		}
	]
}
