{
	"type": "FeatureCollection",
	"features": [
		{
			"type": "Feature",
			"properties": {
				"confidence": 9,
				"authenticationResultCode": "ValidCredentials",
				"brandLogoUri": "http://dev.virtualearth.net/Branding/logo_powered_by.png",
				"copyright": "Copyright © 2017 Microsoft and its suppliers. All rights reserved. This API cannot be accessed and the content and any results may not be used, reproduced or transmitted in any manner without express written permission from Microsoft Corporation.",
				"entityType": "Address",
				"matchCodes": [
					"Good"
				],
				"name": "405 Laird Rd, Guelph, ON N1G 4P7, Canada",
				"statusCode": 200,
				"statusDescription": "OK",
				"traceId": "2ce4d6b01343470abda35d2b9acd6d63|BN20130447|7.7.0.0|",
				"addressLine": "405 Laird Rd",
				"adminDistrict": "ON",
				"adminDistrict2": "Wellington",
				"countryRegion": "Canada",
				"formattedAddress": "405 Laird Rd, Guelph, ON N1G 4P7, Canada",
				"locality": "Guelph",
				"neighborhood": "Clairfields/Hanlon Business Park",
				"postalCode": "N1G 4P7"
			},
			"geometry": {
				"type": "Point",
				"coordinates": [
					-80.2032712,
					43.4937456
				]
			},
			"bbox": [
				-80.2048208,
				43.4926215,
				-80.2017216,
				43.4948698
			]
		}
	]
}
