{
	"type": "FeatureCollection",
	"features": [
		{
			"type": "Feature",
			"properties": {
				"confidence": 9,
				"authenticationResultCode": "ValidCredentials",
				"brandLogoUri": "http://dev.virtualearth.net/Branding/logo_powered_by.png",
				"copyright": "Copyright © 2017 Microsoft and its suppliers. All rights reserved. This API cannot be accessed and the content and any results may not be used, reproduced or transmitted in any manner without express written permission from Microsoft Corporation.",
				"entityType": "Address",
				"matchCodes": [
					"Good"
				],
				"name": "405 Notre Dame Ave, Winnipeg, MB R3B 1R2, Canada",
				"statusCode": 200,
				"statusDescription": "OK",
				"traceId": "b70b16efa5444ade965c37e72f381616|BN20181720|7.7.0.0|",
				"addressLine": "405 Notre Dame Ave",
				"adminDistrict": "MB",
				"adminDistrict2": "Manitoba",
				"countryRegion": "Canada",
				"formattedAddress": "405 Notre Dame Ave, Winnipeg, MB R3B 1R2, Canada",
				"locality": "Winnipeg",
				"neighborhood": "West Alexander",
				"postalCode": "R3B 1R2"
			},
			"geometry": {
				"type": "Point",
				"coordinates": [
					-97.14812,
					49.89814
				]
			},
			"bbox": [
				-97.1498652,
				49.8970158,
				-97.1463748,
				49.8992642
			]
		}
	]
}
