{
	"type": "FeatureCollection",
	"features": [
		{
			"type": "Feature",
			"properties": {
				"confidence": 9,
				"authenticationResultCode": "ValidCredentials",
				"brandLogoUri": "http://dev.virtualearth.net/Branding/logo_powered_by.png",
				"copyright": "Copyright © 2017 Microsoft and its suppliers. All rights reserved. This API cannot be accessed and the content and any results may not be used, reproduced or transmitted in any manner without express written permission from Microsoft Corporation.",
				"entityType": "Address",
				"matchCodes": [
					"Good"
				],
				"name": "405 Aspen Rd, Kimberley, BC V1A 3B6, Canada",
				"statusCode": 200,
				"statusDescription": "OK",
				"traceId": "2625d40dea014458a61bad106ef4d269|BN20300154|7.7.0.0|",
				"addressLine": "405 Aspen Rd",
				"adminDistrict": "BC",
				"adminDistrict2": "East Kootenay",
				"countryRegion": "Canada",
				"formattedAddress": "405 Aspen Rd, Kimberley, BC V1A 3B6, Canada",
				"locality": "Kimberley",
				"postalCode": "V1A 3B6"
			},
			"geometry": {
				"type": "Point",
				"coordinates": [
					-115.99003,
					49.6849
				]
			},
			"bbox": [
				-115.9917675,
				49.6837758,
				-115.9882925,
				49.6860242
			]
		}
	]
}
