{
	"type": "FeatureCollection",
	"features": [
		{
			"type": "Feature",
			"properties": {
				"confidence": 9,
				"authenticationResultCode": "ValidCredentials",
				"brandLogoUri": "http://dev.virtualearth.net/Branding/logo_powered_by.png",
				"copyright": "Copyright © 2017 Microsoft and its suppliers. All rights reserved. This API cannot be accessed and the content and any results may not be used, reproduced or transmitted in any manner without express written permission from Microsoft Corporation.",
				"entityType": "Address",
				"matchCodes": [
					"Good"
				],
				"name": "4053 South River Rd, Antigonish County, NS B2G 2H6, Canada",
				"statusCode": 200,
				"statusDescription": "OK",
				"traceId": "249cdf36b78541e0be0eebce1a0a58ef|BN20130721|7.7.0.0|",
				"addressLine": "4053 South River Rd",
				"adminDistrict": "NS",
				"adminDistrict2": "Antigonish",
				"countryRegion": "Canada",
				"formattedAddress": "4053 South River Rd, Antigonish County, NS B2G 2H6, Canada",
				"locality": "Antigonish County",
				"neighborhood": "South River Road",
				"postalCode": "B2G 2H6"
			},
			"geometry": {
				"type": "Point",
				"coordinates": [
					-61.9655915,
					45.6164148
				]
			},
			"bbox": [
				-61.9671986,
				45.6152906,
				-61.9639843,
				45.6175389
			]
		}
	]
}
