{
	"type": "FeatureCollection",
	"features": [
		{
			"type": "Feature",
			"properties": {
				"confidence": 9,
				"authenticationResultCode": "ValidCredentials",
				"brandLogoUri": "http://dev.virtualearth.net/Branding/logo_powered_by.png",
				"copyright": "Copyright © 2017 Microsoft and its suppliers. All rights reserved. This API cannot be accessed and the content and any results may not be used, reproduced or transmitted in any manner without express written permission from Microsoft Corporation.",
				"entityType": "Address",
				"matchCodes": [
					"Good"
				],
				"name": "4092 Railway Ave, Smithers, BC V0J, Canada",
				"statusCode": 200,
				"statusDescription": "OK",
				"traceId": "9e333781c35540a0b16752298c222085|BN20130620|7.7.0.0|",
				"addressLine": "4092 Railway Ave",
				"adminDistrict": "BC",
				"adminDistrict2": "Bulkley-Nechako",
				"countryRegion": "Canada",
				"formattedAddress": "4092 Railway Ave, Smithers, BC V0J, Canada",
				"locality": "Smithers",
				"postalCode": "V0J 2N0"
			},
			"geometry": {
				"type": "Point",
				"coordinates": [
					-127.18104,
					54.78206
				]
			},
			"bbox": [
				-127.1829893,
				54.7809358,
				-127.1790907,
				54.7831842
			]
		}
	]
}
