{
	"type": "FeatureCollection",
	"features": [
		{
			"type": "Feature",
			"properties": {
				"confidence": 9,
				"authenticationResultCode": "ValidCredentials",
				"brandLogoUri": "http://dev.virtualearth.net/Branding/logo_powered_by.png",
				"copyright": "Copyright © 2017 Microsoft and its suppliers. All rights reserved. This API cannot be accessed and the content and any results may not be used, reproduced or transmitted in any manner without express written permission from Microsoft Corporation.",
				"entityType": "Address",
				"matchCodes": [
					"Good"
				],
				"name": "41 Appian Way, Dartmouth, NS B2X 3G1, Canada",
				"statusCode": 200,
				"statusDescription": "OK",
				"traceId": "1e0b923d67d9479e811672172806ede2|BN20260231|7.7.0.0|",
				"addressLine": "41 Appian Way",
				"adminDistrict": "NS",
				"adminDistrict2": "Halifax",
				"countryRegion": "Canada",
				"formattedAddress": "41 Appian Way, Dartmouth, NS B2X 3G1, Canada",
				"locality": "Halifax",
				"neighborhood": "Dartmouth",
				"postalCode": "B2X 3G1"
			},
			"geometry": {
				"type": "Point",
				"coordinates": [
					-63.54549,
					44.69995
				]
			},
			"bbox": [
				-63.5470715,
				44.6988258,
				-63.5439085,
				44.7010742
			]
		}
	]
}
