{
	"type": "FeatureCollection",
	"features": [
		{
			"type": "Feature",
			"properties": {
				"confidence": 9,
				"authenticationResultCode": "ValidCredentials",
				"brandLogoUri": "http://dev.virtualearth.net/Branding/logo_powered_by.png",
				"copyright": "Copyright © 2017 Microsoft and its suppliers. All rights reserved. This API cannot be accessed and the content and any results may not be used, reproduced or transmitted in any manner without express written permission from Microsoft Corporation.",
				"entityType": "Address",
				"matchCodes": [
					"Good"
				],
				"name": "410 Essa Rd, Barrie, ON L4N 9J7, Canada",
				"statusCode": 200,
				"statusDescription": "OK",
				"traceId": "e911ccc1c0b848c8953e4225175ab478|BN20130422|7.7.0.0|",
				"addressLine": "410 Essa Rd",
				"adminDistrict": "ON",
				"adminDistrict2": "Simcoe",
				"countryRegion": "Canada",
				"formattedAddress": "410 Essa Rd, Barrie, ON L4N 9J7, Canada",
				"locality": "Barrie",
				"neighborhood": "Holly",
				"postalCode": "L4N 9J7"
			},
			"geometry": {
				"type": "Point",
				"coordinates": [
					-79.703673,
					44.3476366
				]
			},
			"bbox": [
				-79.705245,
				44.3465125,
				-79.702101,
				44.3487608
			]
		}
	]
}
