{
	"type": "FeatureCollection",
	"features": [
		{
			"type": "Feature",
			"properties": {
				"confidence": 9,
				"authenticationResultCode": "ValidCredentials",
				"brandLogoUri": "http://dev.virtualearth.net/Branding/logo_powered_by.png",
				"copyright": "Copyright © 2017 Microsoft and its suppliers. All rights reserved. This API cannot be accessed and the content and any results may not be used, reproduced or transmitted in any manner without express written permission from Microsoft Corporation.",
				"entityType": "Address",
				"matchCodes": [
					"Good"
				],
				"name": "4100 72 Ave SE, Calgary, AB T2C 2C1, Canada",
				"statusCode": 200,
				"statusDescription": "OK",
				"traceId": "418dc4ac56a0416fb57c93acb19772ef|BN20260231|7.7.0.0|",
				"addressLine": "4100 72 Ave SE",
				"adminDistrict": "AB",
				"adminDistrict2": "Alberta",
				"countryRegion": "Canada",
				"formattedAddress": "4100 72 Ave SE, Calgary, AB T2C 2C1, Canada",
				"locality": "Calgary",
				"neighborhood": "Foothills",
				"postalCode": "T2C 2C1"
			},
			"geometry": {
				"type": "Point",
				"coordinates": [
					-113.97584,
					50.98975
				]
			},
			"bbox": [
				-113.9776259,
				50.9886258,
				-113.9740541,
				50.9908742
			]
		}
	]
}
