{
	"type": "FeatureCollection",
	"features": [
		{
			"type": "Feature",
			"properties": {
				"confidence": 9,
				"authenticationResultCode": "ValidCredentials",
				"brandLogoUri": "http://dev.virtualearth.net/Branding/logo_powered_by.png",
				"copyright": "Copyright © 2017 Microsoft and its suppliers. All rights reserved. This API cannot be accessed and the content and any results may not be used, reproduced or transmitted in any manner without express written permission from Microsoft Corporation.",
				"entityType": "Address",
				"matchCodes": [
					"Good"
				],
				"name": "4114 Crozier Rd, Spallumcheen, BC V0E 1B6, Canada",
				"statusCode": 200,
				"statusDescription": "OK",
				"traceId": "8b19fe7f54264fa7bd2db5091109a74c|BN20130423|7.7.0.0|",
				"addressLine": "4114 Crozier Rd",
				"adminDistrict": "BC",
				"adminDistrict2": "North Okanagan",
				"countryRegion": "Canada",
				"formattedAddress": "4114 Crozier Rd, Spallumcheen, BC V0E 1B6, Canada",
				"locality": "Spallumcheen",
				"postalCode": "V0E 1B6"
			},
			"geometry": {
				"type": "Point",
				"coordinates": [
					-119.2165698,
					50.4042065
				]
			},
			"bbox": [
				-119.2183336,
				50.4030823,
				-119.2148061,
				50.4053306
			]
		}
	]
}
