{
	"type": "FeatureCollection",
	"features": [
		{
			"type": "Feature",
			"properties": {
				"confidence": 8,
				"authenticationResultCode": "ValidCredentials",
				"brandLogoUri": "http://dev.virtualearth.net/Branding/logo_powered_by.png",
				"copyright": "Copyright © 2017 Microsoft and its suppliers. All rights reserved. This API cannot be accessed and the content and any results may not be used, reproduced or transmitted in any manner without express written permission from Microsoft Corporation.",
				"entityType": "RoadBlock",
				"matchCodes": [
					"UpHierarchy"
				],
				"name": "Liberty Ave, Red Deer County, AB T4E 1B9, Canada",
				"statusCode": 200,
				"statusDescription": "OK",
				"traceId": "29e79bae4acd4973a2d6e503f7f6ddb2|BN20121763|7.7.0.0|",
				"addressLine": "Liberty Ave",
				"adminDistrict": "AB",
				"adminDistrict2": "Alberta",
				"countryRegion": "Canada",
				"formattedAddress": "Liberty Ave, Red Deer County, AB T4E 1B9, Canada",
				"locality": "Red Deer County",
				"postalCode": "T4E 1B9"
			},
			"geometry": {
				"type": "Point",
				"coordinates": [
					-113.82092,
					52.20914
				]
			},
			"bbox": [
				-113.82387,
				52.20591,
				-113.82092,
				52.21382
			]
		}
	]
}
