{
	"type": "FeatureCollection",
	"features": [
		{
			"type": "Feature",
			"properties": {
				"confidence": 7,
				"authenticationResultCode": "ValidCredentials",
				"brandLogoUri": "http://dev.virtualearth.net/Branding/logo_powered_by.png",
				"copyright": "Copyright © 2017 Microsoft and its suppliers. All rights reserved. This API cannot be accessed and the content and any results may not be used, reproduced or transmitted in any manner without express written permission from Microsoft Corporation.",
				"entityType": "Postcode1",
				"matchCodes": [
					"UpHierarchy"
				],
				"name": "Canim Lake, V0K 1J0, Canada",
				"statusCode": 200,
				"statusDescription": "OK",
				"traceId": "bdfa6e1b2d344229abf7696cdd44c35b|BN20260231|7.7.0.0|",
				"adminDistrict": "BC",
				"adminDistrict2": "Cariboo",
				"countryRegion": "Canada",
				"formattedAddress": "Canim Lake, V0K 1J0, Canada",
				"locality": "Canim Lake",
				"postalCode": "V0K 1J0"
			},
			"geometry": {
				"type": "Point",
				"coordinates": [
					-120.910049438477,
					51.7683982849121
				]
			},
			"bbox": [
				-120.918371193554,
				51.7645355673414,
				-120.901727683399,
				51.7722610024828
			]
		}
	]
}
