{
	"type": "FeatureCollection",
	"features": [
		{
			"type": "Feature",
			"properties": {
				"confidence": 9,
				"authenticationResultCode": "ValidCredentials",
				"brandLogoUri": "http://dev.virtualearth.net/Branding/logo_powered_by.png",
				"copyright": "Copyright © 2017 Microsoft and its suppliers. All rights reserved. This API cannot be accessed and the content and any results may not be used, reproduced or transmitted in any manner without express written permission from Microsoft Corporation.",
				"entityType": "Address",
				"matchCodes": [
					"Good"
				],
				"name": "4146 Welsh Rd, Prince George, BC V2K 2W1, Canada",
				"statusCode": 200,
				"statusDescription": "OK",
				"traceId": "91eec31fca844bd2babf0f90e4b0a06e|BN20190642|7.7.0.0|",
				"addressLine": "4146 Welsh Rd",
				"adminDistrict": "BC",
				"adminDistrict2": "Fraser-Fort George",
				"countryRegion": "Canada",
				"formattedAddress": "4146 Welsh Rd, Prince George, BC V2K 2W1, Canada",
				"locality": "Prince George",
				"postalCode": "V2K 2W1"
			},
			"geometry": {
				"type": "Point",
				"coordinates": [
					-122.7966157,
					54.0098181
				]
			},
			"bbox": [
				-122.7985287,
				54.008694,
				-122.7947027,
				54.0109423
			]
		}
	]
}
