{
	"type": "FeatureCollection",
	"features": [
		{
			"type": "Feature",
			"properties": {
				"confidence": 7,
				"authenticationResultCode": "ValidCredentials",
				"brandLogoUri": "http://dev.virtualearth.net/Branding/logo_powered_by.png",
				"copyright": "Copyright © 2017 Microsoft and its suppliers. All rights reserved. This API cannot be accessed and the content and any results may not be used, reproduced or transmitted in any manner without express written permission from Microsoft Corporation.",
				"entityType": "Postcode1",
				"matchCodes": [
					"UpHierarchy"
				],
				"name": "Barriere, V0E 1E0, Canada",
				"statusCode": 200,
				"statusDescription": "OK",
				"traceId": "888de4adccad43c995fc7b3cdf3b9bd2|BN20200137|7.7.0.0|",
				"adminDistrict": "BC",
				"adminDistrict2": "Thompson-Nicola",
				"countryRegion": "Canada",
				"formattedAddress": "Barriere, V0E 1E0, Canada",
				"locality": "Barriere",
				"postalCode": "V0E 1E0"
			},
			"geometry": {
				"type": "Point",
				"coordinates": [
					-120.135589599609,
					51.1800117492676
				]
			},
			"bbox": [
				-120.143804719437,
				51.1761490316969,
				-120.127374479781,
				51.1838744668383
			]
		}
	]
}
