{
	"type": "FeatureCollection",
	"features": [
		{
			"type": "Feature",
			"properties": {
				"confidence": 9,
				"authenticationResultCode": "ValidCredentials",
				"brandLogoUri": "http://dev.virtualearth.net/Branding/logo_powered_by.png",
				"copyright": "Copyright © 2017 Microsoft and its suppliers. All rights reserved. This API cannot be accessed and the content and any results may not be used, reproduced or transmitted in any manner without express written permission from Microsoft Corporation.",
				"entityType": "Address",
				"matchCodes": [
					"Good"
				],
				"name": "416 51 Ave SE, Calgary, AB T2H 0M7, Canada",
				"statusCode": 200,
				"statusDescription": "OK",
				"traceId": "e9d69e1cb7634475a9025b630a552775|BN20130721|7.7.0.0|",
				"addressLine": "416 51 Ave SE",
				"adminDistrict": "AB",
				"adminDistrict2": "Alberta",
				"countryRegion": "Canada",
				"formattedAddress": "416 51 Ave SE, Calgary, AB T2H 0M7, Canada",
				"locality": "Calgary",
				"neighborhood": "Alyth-Bonnybrook-Manchester",
				"postalCode": "T2H 0M7"
			},
			"geometry": {
				"type": "Point",
				"coordinates": [
					-114.0562536,
					51.0075849
				]
			},
			"bbox": [
				-114.0580402,
				51.0064607,
				-114.054467,
				51.0087091
			]
		}
	]
}
