{
	"type": "FeatureCollection",
	"features": [
		{
			"type": "Feature",
			"properties": {
				"confidence": 9,
				"authenticationResultCode": "ValidCredentials",
				"brandLogoUri": "http://dev.virtualearth.net/Branding/logo_powered_by.png",
				"copyright": "Copyright © 2017 Microsoft and its suppliers. All rights reserved. This API cannot be accessed and the content and any results may not be used, reproduced or transmitted in any manner without express written permission from Microsoft Corporation.",
				"entityType": "Address",
				"matchCodes": [
					"Good"
				],
				"name": "419 Notre Dame Ave, Winnipeg, MB R3B 1R3, Canada",
				"statusCode": 200,
				"statusDescription": "OK",
				"traceId": "d3e5f6dcbd12434daa0a6badc43efd24|BN20121763|7.7.0.0|",
				"addressLine": "419 Notre Dame Ave",
				"adminDistrict": "MB",
				"adminDistrict2": "Manitoba",
				"countryRegion": "Canada",
				"formattedAddress": "419 Notre Dame Ave, Winnipeg, MB R3B 1R3, Canada",
				"locality": "Winnipeg",
				"neighborhood": "West Alexander",
				"postalCode": "R3B 1R3"
			},
			"geometry": {
				"type": "Point",
				"coordinates": [
					-97.1490199,
					49.89855
				]
			},
			"bbox": [
				-97.1507651,
				49.8974258,
				-97.1472747,
				49.8996742
			]
		}
	]
}
