{
	"type": "FeatureCollection",
	"features": [
		{
			"type": "Feature",
			"properties": {
				"confidence": 9,
				"authenticationResultCode": "ValidCredentials",
				"brandLogoUri": "http://dev.virtualearth.net/Branding/logo_powered_by.png",
				"copyright": "Copyright © 2017 Microsoft and its suppliers. All rights reserved. This API cannot be accessed and the content and any results may not be used, reproduced or transmitted in any manner without express written permission from Microsoft Corporation.",
				"entityType": "Address",
				"matchCodes": [
					"Good"
				],
				"name": "42 Alice St, Brantford, ON N3R 1Y2, Canada",
				"statusCode": 200,
				"statusDescription": "OK",
				"traceId": "95db48a2a5b54ea792c0bd43e80f9549|BN20130422|7.7.0.0|",
				"addressLine": "42 Alice St",
				"adminDistrict": "ON",
				"adminDistrict2": "Brant",
				"countryRegion": "Canada",
				"formattedAddress": "42 Alice St, Brantford, ON N3R 1Y2, Canada",
				"locality": "Brantford",
				"postalCode": "N3R 1Y2"
			},
			"geometry": {
				"type": "Point",
				"coordinates": [
					-80.2574999,
					43.15116
				]
			},
			"bbox": [
				-80.2590408,
				43.1500358,
				-80.255959,
				43.1522842
			]
		}
	]
}
