{
	"type": "FeatureCollection",
	"features": [
		{
			"type": "Feature",
			"properties": {
				"confidence": 9,
				"authenticationResultCode": "ValidCredentials",
				"brandLogoUri": "http://dev.virtualearth.net/Branding/logo_powered_by.png",
				"copyright": "Copyright © 2017 Microsoft and its suppliers. All rights reserved. This API cannot be accessed and the content and any results may not be used, reproduced or transmitted in any manner without express written permission from Microsoft Corporation.",
				"entityType": "Address",
				"matchCodes": [
					"Good"
				],
				"name": "42 Lakeshore Blvd, Ennismore, ON K0L 1T0, Canada",
				"statusCode": 200,
				"statusDescription": "OK",
				"traceId": "d0b8f940165d4fb2802a2f58aca50cba|BN20130533|7.7.0.0|",
				"addressLine": "42 Lakeshore Blvd",
				"adminDistrict": "ON",
				"adminDistrict2": "Peterborough",
				"countryRegion": "Canada",
				"formattedAddress": "42 Lakeshore Blvd, Ennismore, ON K0L 1T0, Canada",
				"locality": "Selwyn",
				"neighborhood": "Ennismore",
				"postalCode": "K0L 1T0"
			},
			"geometry": {
				"type": "Point",
				"coordinates": [
					-78.4068099,
					44.44667
				]
			},
			"bbox": [
				-78.4083846,
				44.4455458,
				-78.4052352,
				44.4477942
			]
		}
	]
}
