{
	"type": "FeatureCollection",
	"features": [
		{
			"type": "Feature",
			"properties": {
				"confidence": 9,
				"authenticationResultCode": "ValidCredentials",
				"brandLogoUri": "http://dev.virtualearth.net/Branding/logo_powered_by.png",
				"copyright": "Copyright © 2017 Microsoft and its suppliers. All rights reserved. This API cannot be accessed and the content and any results may not be used, reproduced or transmitted in any manner without express written permission from Microsoft Corporation.",
				"entityType": "Address",
				"matchCodes": [
					"Good"
				],
				"name": "420 Academy Rd, Winnipeg, MB R3N 0B9, Canada",
				"statusCode": 200,
				"statusDescription": "OK",
				"traceId": "3c908c2d0a4a428e8ef6671eb573faf1|BN20290118|7.7.0.0|",
				"addressLine": "420 Academy Rd",
				"adminDistrict": "MB",
				"adminDistrict2": "Manitoba",
				"countryRegion": "Canada",
				"formattedAddress": "420 Academy Rd, Winnipeg, MB R3N 0B9, Canada",
				"locality": "Winnipeg",
				"neighborhood": "North River Heights",
				"postalCode": "R3N 0B9"
			},
			"geometry": {
				"type": "Point",
				"coordinates": [
					-97.18472,
					49.87363
				]
			},
			"bbox": [
				-97.1864643,
				49.8725058,
				-97.1829757,
				49.8747542
			]
		}
	]
}
