{
	"type": "FeatureCollection",
	"features": [
		{
			"type": "Feature",
			"properties": {
				"confidence": 9,
				"authenticationResultCode": "ValidCredentials",
				"brandLogoUri": "http://dev.virtualearth.net/Branding/logo_powered_by.png",
				"copyright": "Copyright © 2017 Microsoft and its suppliers. All rights reserved. This API cannot be accessed and the content and any results may not be used, reproduced or transmitted in any manner without express written permission from Microsoft Corporation.",
				"entityType": "Address",
				"matchCodes": [
					"Good"
				],
				"name": "4200 HWY-308, Tusket, NS B0W 3M0, Canada",
				"statusCode": 200,
				"statusDescription": "OK",
				"traceId": "15cf5dbc78d24e9894ada7edf3fa3183|BN20130631|7.7.0.0|",
				"addressLine": "4200 HWY-308",
				"adminDistrict": "NS",
				"adminDistrict2": "Yarmouth",
				"countryRegion": "Canada",
				"formattedAddress": "4200 HWY-308, Tusket, NS B0W 3M0, Canada",
				"locality": "Argyle",
				"neighborhood": "Tusket",
				"postalCode": "B0W 3M0"
			},
			"geometry": {
				"type": "Point",
				"coordinates": [
					-65.9679562,
					43.8690494
				]
			},
			"bbox": [
				-65.9695155,
				43.8679253,
				-65.9663968,
				43.8701736
			]
		}
	]
}
