{
	"type": "FeatureCollection",
	"features": [
		{
			"type": "Feature",
			"properties": {
				"confidence": 9,
				"authenticationResultCode": "ValidCredentials",
				"brandLogoUri": "http://dev.virtualearth.net/Branding/logo_powered_by.png",
				"copyright": "Copyright © 2017 Microsoft and its suppliers. All rights reserved. This API cannot be accessed and the content and any results may not be used, reproduced or transmitted in any manner without express written permission from Microsoft Corporation.",
				"entityType": "Address",
				"matchCodes": [
					"Good"
				],
				"name": "425 21 Ave NW, Calgary, AB T2M 1J6, Canada",
				"statusCode": 200,
				"statusDescription": "OK",
				"traceId": "c94599767b6f41d7ae33e1cf974af0d2|BN20130620|7.7.0.0|",
				"addressLine": "425 21 Ave NW",
				"adminDistrict": "AB",
				"adminDistrict2": "Alberta",
				"countryRegion": "Canada",
				"formattedAddress": "425 21 Ave NW, Calgary, AB T2M 1J6, Canada",
				"locality": "Calgary",
				"neighborhood": "Mt Pleasant",
				"postalCode": "T2M 1J6"
			},
			"geometry": {
				"type": "Point",
				"coordinates": [
					-114.06894,
					51.07121
				]
			},
			"bbox": [
				-114.070729,
				51.0700858,
				-114.067151,
				51.0723342
			]
		}
	]
}
