{
	"type": "FeatureCollection",
	"features": [
		{
			"type": "Feature",
			"properties": {
				"confidence": 9,
				"authenticationResultCode": "ValidCredentials",
				"brandLogoUri": "http://dev.virtualearth.net/Branding/logo_powered_by.png",
				"copyright": "Copyright © 2017 Microsoft and its suppliers. All rights reserved. This API cannot be accessed and the content and any results may not be used, reproduced or transmitted in any manner without express written permission from Microsoft Corporation.",
				"entityType": "Address",
				"matchCodes": [
					"Good"
				],
				"name": "4264 Flitter Ct, Mississauga, ON L5L 2H8, Canada",
				"statusCode": 200,
				"statusDescription": "OK",
				"traceId": "0c4cd57999d1486fb5424db5164c982a|BN20190653|7.7.0.0|",
				"addressLine": "4264 Flitter Ct",
				"adminDistrict": "ON",
				"adminDistrict2": "Peel",
				"countryRegion": "Canada",
				"formattedAddress": "4264 Flitter Ct, Mississauga, ON L5L 2H8, Canada",
				"locality": "Mississauga",
				"neighborhood": "Erin Mills",
				"postalCode": "L5L 2H8"
			},
			"geometry": {
				"type": "Point",
				"coordinates": [
					-79.69998,
					43.54788
				]
			},
			"bbox": [
				-79.701531,
				43.5467558,
				-79.698429,
				43.5490042
			]
		}
	]
}
