{
	"type": "FeatureCollection",
	"features": [
		{
			"type": "Feature",
			"properties": {
				"confidence": 9,
				"authenticationResultCode": "ValidCredentials",
				"brandLogoUri": "http://dev.virtualearth.net/Branding/logo_powered_by.png",
				"copyright": "Copyright © 2017 Microsoft and its suppliers. All rights reserved. This API cannot be accessed and the content and any results may not be used, reproduced or transmitted in any manner without express written permission from Microsoft Corporation.",
				"entityType": "Address",
				"matchCodes": [
					"Good"
				],
				"name": "4281 23 St NE, Calgary, AB T2E 6Y2, Canada",
				"statusCode": 200,
				"statusDescription": "OK",
				"traceId": "4ab2f12bbdc846428132cbe9cbbb55f5|BN20160335|7.7.0.0|",
				"addressLine": "4281 23 St NE",
				"adminDistrict": "AB",
				"adminDistrict2": "Alberta",
				"countryRegion": "Canada",
				"formattedAddress": "4281 23 St NE, Calgary, AB T2E 6Y2, Canada",
				"locality": "Calgary",
				"postalCode": "T2E 6Y2"
			},
			"geometry": {
				"type": "Point",
				"coordinates": [
					-114.00532,
					51.09087
				]
			},
			"bbox": [
				-114.0071098,
				51.0897458,
				-114.0035302,
				51.0919942
			]
		}
	]
}
