{
	"type": "FeatureCollection",
	"features": [
		{
			"type": "Feature",
			"properties": {
				"confidence": 7,
				"authenticationResultCode": "ValidCredentials",
				"brandLogoUri": "http://dev.virtualearth.net/Branding/logo_powered_by.png",
				"copyright": "Copyright © 2017 Microsoft and its suppliers. All rights reserved. This API cannot be accessed and the content and any results may not be used, reproduced or transmitted in any manner without express written permission from Microsoft Corporation.",
				"entityType": "Postcode1",
				"matchCodes": [
					"UpHierarchy"
				],
				"name": "Beresford, E8K 2C2, Canada",
				"statusCode": 200,
				"statusDescription": "OK",
				"traceId": "f4f1ff99fafa4777b787a7e3c431a1d0|BN20130431|7.7.0.0|",
				"adminDistrict": "NB",
				"adminDistrict2": "Gloucester",
				"countryRegion": "Canada",
				"formattedAddress": "Beresford, E8K 2C2, Canada",
				"locality": "Beresford",
				"postalCode": "E8K 2C2"
			},
			"geometry": {
				"type": "Point",
				"coordinates": [
					-65.7220840454102,
					47.70751953125
				]
			},
			"bbox": [
				-65.7297371741185,
				47.7036568136793,
				-65.7144309167018,
				47.7113822488207
			]
		}
	]
}
