{
	"type": "FeatureCollection",
	"features": [
		{
			"type": "Feature",
			"properties": {
				"confidence": 9,
				"authenticationResultCode": "ValidCredentials",
				"brandLogoUri": "http://dev.virtualearth.net/Branding/logo_powered_by.png",
				"copyright": "Copyright © 2017 Microsoft and its suppliers. All rights reserved. This API cannot be accessed and the content and any results may not be used, reproduced or transmitted in any manner without express written permission from Microsoft Corporation.",
				"entityType": "Address",
				"matchCodes": [
					"Good"
				],
				"name": "4305 Spring Creek Rd, Lincoln, ON L0R 2C0, Canada",
				"statusCode": 200,
				"statusDescription": "OK",
				"traceId": "cd7a036f9f4045e6aacffd4ba549ff0e|BN20130522|7.7.0.0|",
				"addressLine": "4305 Spring Creek Rd",
				"adminDistrict": "ON",
				"adminDistrict2": "Niagara",
				"countryRegion": "Canada",
				"formattedAddress": "4305 Spring Creek Rd, Lincoln, ON L0R 2C0, Canada",
				"locality": "Lincoln",
				"postalCode": "L0R 2C0"
			},
			"geometry": {
				"type": "Point",
				"coordinates": [
					-79.4380774,
					43.1052868
				]
			},
			"bbox": [
				-79.4396171,
				43.1041627,
				-79.4365377,
				43.106411
			]
		}
	]
}
