{
	"type": "FeatureCollection",
	"features": [
		{
			"type": "Feature",
			"properties": {
				"confidence": 9,
				"authenticationResultCode": "ValidCredentials",
				"brandLogoUri": "http://dev.virtualearth.net/Branding/logo_powered_by.png",
				"copyright": "Copyright © 2017 Microsoft and its suppliers. All rights reserved. This API cannot be accessed and the content and any results may not be used, reproduced or transmitted in any manner without express written permission from Microsoft Corporation.",
				"entityType": "Address",
				"matchCodes": [
					"Good"
				],
				"name": "431 Brant St, Burlington, ON L7R 2G3, Canada",
				"statusCode": 200,
				"statusDescription": "OK",
				"traceId": "e0d05bfaac17499b867b95b4d91d582b|BN20131519|7.7.0.0|",
				"addressLine": "431 Brant St",
				"adminDistrict": "ON",
				"adminDistrict2": "Halton",
				"countryRegion": "Canada",
				"formattedAddress": "431 Brant St, Burlington, ON L7R 2G3, Canada",
				"locality": "Burlington",
				"neighborhood": "Central",
				"postalCode": "L7R 2G3"
			},
			"geometry": {
				"type": "Point",
				"coordinates": [
					-79.7985999,
					43.32643
				]
			},
			"bbox": [
				-79.8001452,
				43.3253058,
				-79.7970546,
				43.3275542
			]
		}
	]
}
