{
	"type": "FeatureCollection",
	"features": [
		{
			"type": "Feature",
			"properties": {
				"confidence": 9,
				"authenticationResultCode": "ValidCredentials",
				"brandLogoUri": "http://dev.virtualearth.net/Branding/logo_powered_by.png",
				"copyright": "Copyright © 2017 Microsoft and its suppliers. All rights reserved. This API cannot be accessed and the content and any results may not be used, reproduced or transmitted in any manner without express written permission from Microsoft Corporation.",
				"entityType": "Address",
				"matchCodes": [
					"Good"
				],
				"name": "4311 25th Ave, Vernon, BC V1T 1P5, Canada",
				"statusCode": 200,
				"statusDescription": "OK",
				"traceId": "b2aaa271faaf470e97c592ad98ed6d2d|BN20220145|7.7.0.0|",
				"addressLine": "4311 25th Ave",
				"adminDistrict": "BC",
				"adminDistrict2": "North Okanagan",
				"countryRegion": "Canada",
				"formattedAddress": "4311 25th Ave, Vernon, BC V1T 1P5, Canada",
				"locality": "Vernon",
				"postalCode": "V1T 1P5"
			},
			"geometry": {
				"type": "Point",
				"coordinates": [
					-119.2984607,
					50.2587785
				]
			},
			"bbox": [
				-119.300219,
				50.2576543,
				-119.2967023,
				50.2599026
			]
		}
	]
}
