{
	"type": "FeatureCollection",
	"features": [
		{
			"type": "Feature",
			"properties": {
				"confidence": 9,
				"authenticationResultCode": "ValidCredentials",
				"brandLogoUri": "http://dev.virtualearth.net/Branding/logo_powered_by.png",
				"copyright": "Copyright © 2017 Microsoft and its suppliers. All rights reserved. This API cannot be accessed and the content and any results may not be used, reproduced or transmitted in any manner without express written permission from Microsoft Corporation.",
				"entityType": "Address",
				"matchCodes": [
					"Good"
				],
				"name": "433 William St, London, ON N6B 3E1, Canada",
				"statusCode": 200,
				"statusDescription": "OK",
				"traceId": "5724b8408ac64f22a6008526ccedbb90|BN20160335|7.7.0.0|",
				"addressLine": "433 William St",
				"adminDistrict": "ON",
				"adminDistrict2": "Middlesex",
				"countryRegion": "Canada",
				"formattedAddress": "433 William St, London, ON N6B 3E1, Canada",
				"locality": "London",
				"neighborhood": "Central London",
				"postalCode": "N6B 3E1"
			},
			"geometry": {
				"type": "Point",
				"coordinates": [
					-81.2348,
					42.9887
				]
			},
			"bbox": [
				-81.2363368,
				42.9875758,
				-81.2332632,
				42.9898242
			]
		}
	]
}
