{
	"type": "FeatureCollection",
	"features": [
		{
			"type": "Feature",
			"properties": {
				"confidence": 9,
				"authenticationResultCode": "ValidCredentials",
				"brandLogoUri": "http://dev.virtualearth.net/Branding/logo_powered_by.png",
				"copyright": "Copyright © 2017 Microsoft and its suppliers. All rights reserved. This API cannot be accessed and the content and any results may not be used, reproduced or transmitted in any manner without express written permission from Microsoft Corporation.",
				"entityType": "Address",
				"matchCodes": [
					"Good"
				],
				"name": "436 7th St E, The Pas, MB R9A, Canada",
				"statusCode": 200,
				"statusDescription": "OK",
				"traceId": "7b8dd43caf204282af80e565410404f3|BN20121762|7.7.0.0|",
				"addressLine": "436 7th St E",
				"adminDistrict": "MB",
				"adminDistrict2": "Manitoba",
				"countryRegion": "Canada",
				"formattedAddress": "436 7th St E, The Pas, MB R9A, Canada",
				"locality": "The Pas",
				"postalCode": "R9A 1M7"
			},
			"geometry": {
				"type": "Point",
				"coordinates": [
					-101.2376356,
					53.8196759
				]
			},
			"bbox": [
				-101.2395399,
				53.8185518,
				-101.2357313,
				53.8208001
			]
		}
	]
}
