{
	"type": "FeatureCollection",
	"features": [
		{
			"type": "Feature",
			"properties": {
				"confidence": 9,
				"authenticationResultCode": "ValidCredentials",
				"brandLogoUri": "http://dev.virtualearth.net/Branding/logo_powered_by.png",
				"copyright": "Copyright © 2017 Microsoft and its suppliers. All rights reserved. This API cannot be accessed and the content and any results may not be used, reproduced or transmitted in any manner without express written permission from Microsoft Corporation.",
				"entityType": "Address",
				"matchCodes": [
					"Good"
				],
				"name": "437 Cummer Ave, North York, ON M2M 2G3, Canada",
				"statusCode": 200,
				"statusDescription": "OK",
				"traceId": "7bd85d5619024ed4aa3b0d62bedaf713|BN20260231|7.7.0.0|",
				"addressLine": "437 Cummer Ave",
				"adminDistrict": "ON",
				"adminDistrict2": "Toronto",
				"countryRegion": "Canada",
				"formattedAddress": "437 Cummer Ave, North York, ON M2M 2G3, Canada",
				"locality": "Toronto",
				"neighborhood": "Newtonbrook East",
				"postalCode": "M2M 2G3"
			},
			"geometry": {
				"type": "Point",
				"coordinates": [
					-79.3971399,
					43.79122
				]
			},
			"bbox": [
				-79.3986972,
				43.7900958,
				-79.3955826,
				43.7923442
			]
		}
	]
}
