{
	"type": "FeatureCollection",
	"features": [
		{
			"type": "Feature",
			"properties": {
				"confidence": 9,
				"authenticationResultCode": "ValidCredentials",
				"brandLogoUri": "http://dev.virtualearth.net/Branding/logo_powered_by.png",
				"copyright": "Copyright © 2017 Microsoft and its suppliers. All rights reserved. This API cannot be accessed and the content and any results may not be used, reproduced or transmitted in any manner without express written permission from Microsoft Corporation.",
				"entityType": "Address",
				"matchCodes": [
					"Good"
				],
				"name": "439 Wallenberg Cres, Mississauga, ON L5B 3M2, Canada",
				"statusCode": 200,
				"statusDescription": "OK",
				"traceId": "6d91b40111744117a5b2937d4cb4e31f|BN20131519|7.7.0.0|",
				"addressLine": "439 Wallenberg Cres",
				"adminDistrict": "ON",
				"adminDistrict2": "Peel",
				"countryRegion": "Canada",
				"formattedAddress": "439 Wallenberg Cres, Mississauga, ON L5B 3M2, Canada",
				"locality": "Mississauga",
				"neighborhood": "Cooksville",
				"postalCode": "L5B 3M2"
			},
			"geometry": {
				"type": "Point",
				"coordinates": [
					-79.64784,
					43.58417
				]
			},
			"bbox": [
				-79.6493919,
				43.5830458,
				-79.6462881,
				43.5852942
			]
		}
	]
}
