{
	"type": "FeatureCollection",
	"features": [
		{
			"type": "Feature",
			"properties": {
				"confidence": 9,
				"authenticationResultCode": "ValidCredentials",
				"brandLogoUri": "http://dev.virtualearth.net/Branding/logo_powered_by.png",
				"copyright": "Copyright © 2017 Microsoft and its suppliers. All rights reserved. This API cannot be accessed and the content and any results may not be used, reproduced or transmitted in any manner without express written permission from Microsoft Corporation.",
				"entityType": "Address",
				"matchCodes": [
					"Good"
				],
				"name": "44 Balbo Dr, Clarenville, NL A5A 4A7, Canada",
				"statusCode": 200,
				"statusDescription": "OK",
				"traceId": "ae1799004654484fbc835c4ddc749ab6|BN20190653|7.7.0.0|",
				"addressLine": "44 Balbo Dr",
				"adminDistrict": "NL",
				"adminDistrict2": "Newfoundland and Labrador",
				"countryRegion": "Canada",
				"formattedAddress": "44 Balbo Dr, Clarenville, NL A5A 4A7, Canada",
				"locality": "Clarenville",
				"neighborhood": "Shoal Harbour",
				"postalCode": "A5A 4A7"
			},
			"geometry": {
				"type": "Point",
				"coordinates": [
					-53.9705912,
					48.1888521
				]
			},
			"bbox": [
				-53.9722774,
				48.1877279,
				-53.968905,
				48.1899762
			]
		}
	]
}
