{
	"type": "FeatureCollection",
	"features": [
		{
			"type": "Feature",
			"properties": {
				"confidence": 9,
				"authenticationResultCode": "ValidCredentials",
				"brandLogoUri": "http://dev.virtualearth.net/Branding/logo_powered_by.png",
				"copyright": "Copyright © 2017 Microsoft and its suppliers. All rights reserved. This API cannot be accessed and the content and any results may not be used, reproduced or transmitted in any manner without express written permission from Microsoft Corporation.",
				"entityType": "Address",
				"matchCodes": [
					"Good"
				],
				"name": "440 Limerick St, Innisfil, ON L0L 1K0, Canada",
				"statusCode": 200,
				"statusDescription": "OK",
				"traceId": "eca3a6064c544733907c93fcad48bd91|BN20220145|7.7.0.0|",
				"addressLine": "440 Limerick St",
				"adminDistrict": "ON",
				"adminDistrict2": "Simcoe",
				"countryRegion": "Canada",
				"formattedAddress": "440 Limerick St, Innisfil, ON L0L 1K0, Canada",
				"locality": "Innisfil",
				"neighborhood": "Gilford",
				"postalCode": "L0L 1K0"
			},
			"geometry": {
				"type": "Point",
				"coordinates": [
					-79.53291,
					44.24673
				]
			},
			"bbox": [
				-79.5344793,
				44.2456058,
				-79.5313407,
				44.2478542
			]
		}
	]
}
