{
	"type": "FeatureCollection",
	"features": [
		{
			"type": "Feature",
			"properties": {
				"confidence": 9,
				"authenticationResultCode": "ValidCredentials",
				"brandLogoUri": "http://dev.virtualearth.net/Branding/logo_powered_by.png",
				"copyright": "Copyright © 2017 Microsoft and its suppliers. All rights reserved. This API cannot be accessed and the content and any results may not be used, reproduced or transmitted in any manner without express written permission from Microsoft Corporation.",
				"entityType": "Address",
				"matchCodes": [
					"Good"
				],
				"name": "4402 35 Ave, Red Deer, AB T4N 2S2, Canada",
				"statusCode": 200,
				"statusDescription": "OK",
				"traceId": "d661c978e24840f9a6be5e6ebc7766b6|BN20130522|7.7.0.0|",
				"addressLine": "4402 35 Ave",
				"adminDistrict": "AB",
				"adminDistrict2": "Alberta",
				"countryRegion": "Canada",
				"formattedAddress": "4402 35 Ave, Red Deer, AB T4N 2S2, Canada",
				"locality": "Red Deer",
				"postalCode": "T4N 2S2"
			},
			"geometry": {
				"type": "Point",
				"coordinates": [
					-113.77956,
					52.26323
				]
			},
			"bbox": [
				-113.7813967,
				52.2621058,
				-113.7777233,
				52.2643542
			]
		}
	]
}
