{
	"type": "FeatureCollection",
	"features": [
		{
			"type": "Feature",
			"properties": {
				"confidence": 9,
				"authenticationResultCode": "ValidCredentials",
				"brandLogoUri": "http://dev.virtualearth.net/Branding/logo_powered_by.png",
				"copyright": "Copyright © 2017 Microsoft and its suppliers. All rights reserved. This API cannot be accessed and the content and any results may not be used, reproduced or transmitted in any manner without express written permission from Microsoft Corporation.",
				"entityType": "Address",
				"matchCodes": [
					"Good"
				],
				"name": "4415 N Service Rd, Burlington, ON L7L 4X7, Canada",
				"statusCode": 200,
				"statusDescription": "OK",
				"traceId": "d374af02aec54ac88cd07d1acb5dec11|BN20130521|7.7.0.0|",
				"addressLine": "4415 N Service Rd",
				"adminDistrict": "ON",
				"adminDistrict2": "Halton",
				"countryRegion": "Canada",
				"formattedAddress": "4415 N Service Rd, Burlington, ON L7L 4X7, Canada",
				"locality": "Burlington",
				"neighborhood": "Tansley",
				"postalCode": "L7L 4X7"
			},
			"geometry": {
				"type": "Point",
				"coordinates": [
					-79.77696,
					43.37852
				]
			},
			"bbox": [
				-79.7785066,
				43.3773958,
				-79.7754134,
				43.3796442
			]
		}
	]
}
