{
	"type": "FeatureCollection",
	"features": [
		{
			"type": "Feature",
			"properties": {
				"confidence": 9,
				"authenticationResultCode": "ValidCredentials",
				"brandLogoUri": "http://dev.virtualearth.net/Branding/logo_powered_by.png",
				"copyright": "Copyright © 2017 Microsoft and its suppliers. All rights reserved. This API cannot be accessed and the content and any results may not be used, reproduced or transmitted in any manner without express written permission from Microsoft Corporation.",
				"entityType": "Address",
				"matchCodes": [
					"Good"
				],
				"name": "4416 Houlihan Ct, Saanich, BC V8N 6C4, Canada",
				"statusCode": 200,
				"statusDescription": "OK",
				"traceId": "17f6e391a60f4ad2b07636784e03fab1|BN20130521|7.7.0.0|",
				"addressLine": "4416 Houlihan Ct",
				"adminDistrict": "BC",
				"adminDistrict2": "Capital",
				"countryRegion": "Canada",
				"formattedAddress": "4416 Houlihan Ct, Saanich, BC V8N 6C4, Canada",
				"locality": "Saanich",
				"postalCode": "V8N 6C4"
			},
			"geometry": {
				"type": "Point",
				"coordinates": [
					-123.31058,
					48.48412
				]
			},
			"bbox": [
				-123.312276,
				48.4829958,
				-123.308884,
				48.4852442
			]
		}
	]
}
