{
	"type": "FeatureCollection",
	"features": [
		{
			"type": "Feature",
			"properties": {
				"confidence": 9,
				"authenticationResultCode": "ValidCredentials",
				"brandLogoUri": "http://dev.virtualearth.net/Branding/logo_powered_by.png",
				"copyright": "Copyright © 2017 Microsoft and its suppliers. All rights reserved. This API cannot be accessed and the content and any results may not be used, reproduced or transmitted in any manner without express written permission from Microsoft Corporation.",
				"entityType": "Address",
				"matchCodes": [
					"Good"
				],
				"name": "4443 Keith Ave, Terrace, BC V8G 1J7, Canada",
				"statusCode": 200,
				"statusDescription": "OK",
				"traceId": "1d5d661a27764e73a35974383c2aa624|BN20130522|7.7.0.0|",
				"addressLine": "4443 Keith Ave",
				"adminDistrict": "BC",
				"adminDistrict2": "Kitimat-Stikine",
				"countryRegion": "Canada",
				"formattedAddress": "4443 Keith Ave, Terrace, BC V8G 1J7, Canada",
				"locality": "Terrace",
				"postalCode": "V8G 1J7"
			},
			"geometry": {
				"type": "Point",
				"coordinates": [
					-128.5820573,
					54.5129751
				]
			},
			"bbox": [
				-128.5839938,
				54.511851,
				-128.5801208,
				54.5140993
			]
		}
	]
}
