{
	"type": "FeatureCollection",
	"features": [
		{
			"type": "Feature",
			"properties": {
				"confidence": 9,
				"authenticationResultCode": "ValidCredentials",
				"brandLogoUri": "http://dev.virtualearth.net/Branding/logo_powered_by.png",
				"copyright": "Copyright © 2017 Microsoft and its suppliers. All rights reserved. This API cannot be accessed and the content and any results may not be used, reproduced or transmitted in any manner without express written permission from Microsoft Corporation.",
				"entityType": "Address",
				"matchCodes": [
					"Good"
				],
				"name": "445 Banks Rd, Kelowna, BC V1X 6A2, Canada",
				"statusCode": 200,
				"statusDescription": "OK",
				"traceId": "c6abb93640e64d359c8885e69d834957|BN20190653|7.7.0.0|",
				"addressLine": "445 Banks Rd",
				"adminDistrict": "BC",
				"adminDistrict2": "Central Okanagan",
				"countryRegion": "Canada",
				"formattedAddress": "445 Banks Rd, Kelowna, BC V1X 6A2, Canada",
				"locality": "Kelowna",
				"neighborhood": "Central City",
				"postalCode": "V1X 6A2"
			},
			"geometry": {
				"type": "Point",
				"coordinates": [
					-119.4224301,
					49.884608
				]
			},
			"bbox": [
				-119.4241748,
				49.8834839,
				-119.4206854,
				49.8857322
			]
		}
	]
}
