{
	"type": "FeatureCollection",
	"features": [
		{
			"type": "Feature",
			"properties": {
				"confidence": 9,
				"authenticationResultCode": "ValidCredentials",
				"brandLogoUri": "http://dev.virtualearth.net/Branding/logo_powered_by.png",
				"copyright": "Copyright © 2017 Microsoft and its suppliers. All rights reserved. This API cannot be accessed and the content and any results may not be used, reproduced or transmitted in any manner without express written permission from Microsoft Corporation.",
				"entityType": "Address",
				"matchCodes": [
					"Good"
				],
				"name": "445 Wes Graham Way, Waterloo, ON N2L 6R2, Canada",
				"statusCode": 200,
				"statusDescription": "OK",
				"traceId": "42069616902342ffa61e1d98d1738478|BN20220145|7.7.0.0|",
				"addressLine": "445 Wes Graham Way",
				"adminDistrict": "ON",
				"adminDistrict2": "Waterloo",
				"countryRegion": "Canada",
				"formattedAddress": "445 Wes Graham Way, Waterloo, ON N2L 6R2, Canada",
				"locality": "Waterloo",
				"postalCode": "N2L 6R2"
			},
			"geometry": {
				"type": "Point",
				"coordinates": [
					-80.55128,
					43.48032
				]
			},
			"bbox": [
				-80.5528292,
				43.4791958,
				-80.5497308,
				43.4814442
			]
		}
	]
}
