{
	"type": "FeatureCollection",
	"features": [
		{
			"type": "Feature",
			"properties": {
				"confidence": 9,
				"authenticationResultCode": "ValidCredentials",
				"brandLogoUri": "http://dev.virtualearth.net/Branding/logo_powered_by.png",
				"copyright": "Copyright © 2017 Microsoft and its suppliers. All rights reserved. This API cannot be accessed and the content and any results may not be used, reproduced or transmitted in any manner without express written permission from Microsoft Corporation.",
				"entityType": "Address",
				"matchCodes": [
					"Good"
				],
				"name": "446 Albert St, Waterloo, ON N2L 3V3, Canada",
				"statusCode": 200,
				"statusDescription": "OK",
				"traceId": "2641c83a896846dc92382bdf11d95d60|BN20130631|7.7.0.0|",
				"addressLine": "446 Albert St",
				"adminDistrict": "ON",
				"adminDistrict2": "Waterloo",
				"countryRegion": "Canada",
				"formattedAddress": "446 Albert St, Waterloo, ON N2L 3V3, Canada",
				"locality": "Waterloo",
				"postalCode": "N2L 3V3"
			},
			"geometry": {
				"type": "Point",
				"coordinates": [
					-80.5382599,
					43.48426
				]
			},
			"bbox": [
				-80.5398093,
				43.4831358,
				-80.5367105,
				43.4853842
			]
		}
	]
}
