{
	"type": "FeatureCollection",
	"features": [
		{
			"type": "Feature",
			"properties": {
				"confidence": 9,
				"authenticationResultCode": "ValidCredentials",
				"brandLogoUri": "http://dev.virtualearth.net/Branding/logo_powered_by.png",
				"copyright": "Copyright © 2017 Microsoft and its suppliers. All rights reserved. This API cannot be accessed and the content and any results may not be used, reproduced or transmitted in any manner without express written permission from Microsoft Corporation.",
				"entityType": "Address",
				"matchCodes": [
					"Good"
				],
				"name": "45 Timber Rd, Elliot Lake, ON P5A 2T1, Canada",
				"statusCode": 200,
				"statusDescription": "OK",
				"traceId": "91208bb8127d4333a5dcf1b058f6c5eb|BN20250135|7.7.0.0|",
				"addressLine": "45 Timber Rd",
				"adminDistrict": "ON",
				"adminDistrict2": "Algoma",
				"countryRegion": "Canada",
				"formattedAddress": "45 Timber Rd, Elliot Lake, ON P5A 2T1, Canada",
				"locality": "Elliot Lake",
				"postalCode": "P5A 2T1"
			},
			"geometry": {
				"type": "Point",
				"coordinates": [
					-82.6683032,
					46.4025523
				]
			},
			"bbox": [
				-82.6699334,
				46.4014281,
				-82.666673,
				46.4036764
			]
		}
	]
}
