{
	"type": "FeatureCollection",
	"features": [
		{
			"type": "Feature",
			"properties": {
				"confidence": 9,
				"authenticationResultCode": "ValidCredentials",
				"brandLogoUri": "http://dev.virtualearth.net/Branding/logo_powered_by.png",
				"copyright": "Copyright © 2017 Microsoft and its suppliers. All rights reserved. This API cannot be accessed and the content and any results may not be used, reproduced or transmitted in any manner without express written permission from Microsoft Corporation.",
				"entityType": "Address",
				"matchCodes": [
					"Good"
				],
				"name": "450 Talbot St, London, ON N6A 5J6, Canada",
				"statusCode": 200,
				"statusDescription": "OK",
				"traceId": "98c41feb45cd4313ad45d6caf1ec6d27|BN20260231|7.7.0.0|",
				"addressLine": "450 Talbot St",
				"adminDistrict": "ON",
				"adminDistrict2": "Middlesex",
				"countryRegion": "Canada",
				"formattedAddress": "450 Talbot St, London, ON N6A 5J6, Canada",
				"locality": "London",
				"neighborhood": "Central London",
				"postalCode": "N6A 5J6"
			},
			"geometry": {
				"type": "Point",
				"coordinates": [
					-81.2522,
					42.9842
				]
			},
			"bbox": [
				-81.2537367,
				42.9830758,
				-81.2506633,
				42.9853242
			]
		}
	]
}
