{
	"type": "FeatureCollection",
	"features": [
		{
			"type": "Feature",
			"properties": {
				"confidence": 9,
				"authenticationResultCode": "ValidCredentials",
				"brandLogoUri": "http://dev.virtualearth.net/Branding/logo_powered_by.png",
				"copyright": "Copyright © 2017 Microsoft and its suppliers. All rights reserved. This API cannot be accessed and the content and any results may not be used, reproduced or transmitted in any manner without express written permission from Microsoft Corporation.",
				"entityType": "Address",
				"matchCodes": [
					"Good"
				],
				"name": "4505 74 Ave NW, Edmonton, AB T6B 2H5, Canada",
				"statusCode": 200,
				"statusDescription": "OK",
				"traceId": "c686c6fd06f94cd0b38bcb0b995aacbe|BN20130721|7.7.0.0|",
				"addressLine": "4505 74 Ave NW",
				"adminDistrict": "AB",
				"adminDistrict2": "Alberta",
				"countryRegion": "Canada",
				"formattedAddress": "4505 74 Ave NW, Edmonton, AB T6B 2H5, Canada",
				"locality": "Edmonton",
				"neighborhood": "Weir Industrial",
				"postalCode": "T6B 2H5"
			},
			"geometry": {
				"type": "Point",
				"coordinates": [
					-113.41111,
					53.50866
				]
			},
			"bbox": [
				-113.4130003,
				53.5075358,
				-113.4092197,
				53.5097842
			]
		}
	]
}
