{
	"type": "FeatureCollection",
	"features": [
		{
			"type": "Feature",
			"properties": {
				"confidence": 9,
				"authenticationResultCode": "ValidCredentials",
				"brandLogoUri": "http://dev.virtualearth.net/Branding/logo_powered_by.png",
				"copyright": "Copyright © 2017 Microsoft and its suppliers. All rights reserved. This API cannot be accessed and the content and any results may not be used, reproduced or transmitted in any manner without express written permission from Microsoft Corporation.",
				"entityType": "Address",
				"matchCodes": [
					"Good"
				],
				"name": "455 Rue Racine E, Chicoutimi, QC G7H 1T5, Canada",
				"statusCode": 200,
				"statusDescription": "OK",
				"traceId": "f632d09d717246b683abf8e90479256b|BN20240253|7.7.0.0|",
				"addressLine": "455 Rue Racine E",
				"adminDistrict": "QC",
				"adminDistrict2": "Saguenay",
				"countryRegion": "Canada",
				"formattedAddress": "455 Rue Racine E, Chicoutimi, QC G7H 1T5, Canada",
				"locality": "Saguenay",
				"neighborhood": "Chicoutimi",
				"postalCode": "G7H 1T5"
			},
			"geometry": {
				"type": "Point",
				"coordinates": [
					-71.05454,
					48.42878
				]
			},
			"bbox": [
				-71.0562341,
				48.4276558,
				-71.0528459,
				48.4299042
			]
		}
	]
}
