{
	"type": "FeatureCollection",
	"features": [
		{
			"type": "Feature",
			"properties": {
				"confidence": 7,
				"authenticationResultCode": "ValidCredentials",
				"brandLogoUri": "http://dev.virtualearth.net/Branding/logo_powered_by.png",
				"copyright": "Copyright © 2017 Microsoft and its suppliers. All rights reserved. This API cannot be accessed and the content and any results may not be used, reproduced or transmitted in any manner without express written permission from Microsoft Corporation.",
				"entityType": "RoadBlock",
				"matchCodes": [
					"UpHierarchy"
				],
				"name": "Cynthia St, Saskatoon, SK S7L 6A2, Canada",
				"statusCode": 200,
				"statusDescription": "OK",
				"traceId": "bf968b294be14e21b0b8d97b3b97b123|BN20130521|7.7.0.0|",
				"addressLine": "Cynthia St",
				"adminDistrict": "SK",
				"adminDistrict2": "Saskatchewan",
				"countryRegion": "Canada",
				"formattedAddress": "Cynthia St, Saskatoon, SK S7L 6A2, Canada",
				"locality": "Saskatoon",
				"neighborhood": "Airport Business Area",
				"postalCode": "S7L 6A2"
			},
			"geometry": {
				"type": "Point",
				"coordinates": [
					-106.6737,
					52.15962
				]
			},
			"bbox": [
				-106.68717,
				52.1588,
				-106.67079,
				52.1639
			]
		}
	]
}
