{
	"type": "FeatureCollection",
	"features": [
		{
			"type": "Feature",
			"properties": {
				"confidence": 9,
				"authenticationResultCode": "ValidCredentials",
				"brandLogoUri": "http://dev.virtualearth.net/Branding/logo_powered_by.png",
				"copyright": "Copyright © 2017 Microsoft and its suppliers. All rights reserved. This API cannot be accessed and the content and any results may not be used, reproduced or transmitted in any manner without express written permission from Microsoft Corporation.",
				"entityType": "Address",
				"matchCodes": [
					"Good"
				],
				"name": "4575 Tillicum St, Burnaby, BC V5J 5K9, Canada",
				"statusCode": 200,
				"statusDescription": "OK",
				"traceId": "7886706c2bef4a4bb02a3f30ae5515e3|BN20130431|7.7.0.0|",
				"addressLine": "4575 Tillicum St",
				"adminDistrict": "BC",
				"adminDistrict2": "Greater Vancouver",
				"countryRegion": "Canada",
				"formattedAddress": "4575 Tillicum St, Burnaby, BC V5J 5K9, Canada",
				"locality": "Burnaby",
				"neighborhood": "Big Bend",
				"postalCode": "V5J 5K9"
			},
			"geometry": {
				"type": "Point",
				"coordinates": [
					-122.99264,
					49.1883399
				]
			},
			"bbox": [
				-122.99436,
				49.1872157,
				-122.99092,
				49.1894641
			]
		}
	]
}
