{
	"type": "FeatureCollection",
	"features": [
		{
			"type": "Feature",
			"properties": {
				"confidence": 9,
				"authenticationResultCode": "ValidCredentials",
				"brandLogoUri": "http://dev.virtualearth.net/Branding/logo_powered_by.png",
				"copyright": "Copyright © 2017 Microsoft and its suppliers. All rights reserved. This API cannot be accessed and the content and any results may not be used, reproduced or transmitted in any manner without express written permission from Microsoft Corporation.",
				"entityType": "Address",
				"matchCodes": [
					"Good"
				],
				"name": "458 Morden Rd, Oakville, ON L6K 3W4, Canada",
				"statusCode": 200,
				"statusDescription": "OK",
				"traceId": "76a2701405f84acf9285c30070715c5f|BN20240423|7.7.0.0|",
				"addressLine": "458 Morden Rd",
				"adminDistrict": "ON",
				"adminDistrict2": "Halton",
				"countryRegion": "Canada",
				"formattedAddress": "458 Morden Rd, Oakville, ON L6K 3W4, Canada",
				"locality": "Oakville",
				"postalCode": "L6K 3W4"
			},
			"geometry": {
				"type": "Point",
				"coordinates": [
					-79.6946694,
					43.440817
				]
			},
			"bbox": [
				-79.6962176,
				43.4396929,
				-79.6931212,
				43.4419412
			]
		}
	]
}
