{
	"type": "FeatureCollection",
	"features": [
		{
			"type": "Feature",
			"properties": {
				"confidence": 9,
				"authenticationResultCode": "ValidCredentials",
				"brandLogoUri": "http://dev.virtualearth.net/Branding/logo_powered_by.png",
				"copyright": "Copyright © 2017 Microsoft and its suppliers. All rights reserved. This API cannot be accessed and the content and any results may not be used, reproduced or transmitted in any manner without express written permission from Microsoft Corporation.",
				"entityType": "Address",
				"matchCodes": [
					"Good"
				],
				"name": "4581 198 St, Langley, BC V3A 1E7, Canada",
				"statusCode": 200,
				"statusDescription": "OK",
				"traceId": "f66b46ec3ccd423993e6cde9194f9b3d|BN20130625|7.7.0.0|",
				"addressLine": "4581 198 St",
				"adminDistrict": "BC",
				"adminDistrict2": "Greater Vancouver",
				"countryRegion": "Canada",
				"formattedAddress": "4581 198 St, Langley, BC V3A 1E7, Canada",
				"locality": "Langley",
				"neighborhood": "Alice Brown",
				"postalCode": "V3A 1E7"
			},
			"geometry": {
				"type": "Point",
				"coordinates": [
					-122.6749346,
					49.0854679
				]
			},
			"bbox": [
				-122.676651,
				49.0843438,
				-122.6732181,
				49.0865921
			]
		}
	]
}
