{
	"type": "FeatureCollection",
	"features": [
		{
			"type": "Feature",
			"properties": {
				"confidence": 9,
				"authenticationResultCode": "ValidCredentials",
				"brandLogoUri": "http://dev.virtualearth.net/Branding/logo_powered_by.png",
				"copyright": "Copyright © 2017 Microsoft and its suppliers. All rights reserved. This API cannot be accessed and the content and any results may not be used, reproduced or transmitted in any manner without express written permission from Microsoft Corporation.",
				"entityType": "Address",
				"matchCodes": [
					"Good"
				],
				"name": "46 Carlisle St, St Catharines, ON L2R 4H4, Canada",
				"statusCode": 200,
				"statusDescription": "OK",
				"traceId": "93abec6b93ba4d46a35cea09e751552a|BN20200137|7.7.0.0|",
				"addressLine": "46 Carlisle St",
				"adminDistrict": "ON",
				"adminDistrict2": "Niagara",
				"countryRegion": "Canada",
				"formattedAddress": "46 Carlisle St, St Catharines, ON L2R 4H4, Canada",
				"locality": "St Catharines",
				"neighborhood": "Downtown",
				"postalCode": "L2R 4H4"
			},
			"geometry": {
				"type": "Point",
				"coordinates": [
					-79.24169,
					43.15851
				]
			},
			"bbox": [
				-79.2432311,
				43.1573858,
				-79.2401489,
				43.1596342
			]
		}
	]
}
