{
	"type": "FeatureCollection",
	"features": [
		{
			"type": "Feature",
			"properties": {
				"confidence": 9,
				"authenticationResultCode": "ValidCredentials",
				"brandLogoUri": "http://dev.virtualearth.net/Branding/logo_powered_by.png",
				"copyright": "Copyright © 2017 Microsoft and its suppliers. All rights reserved. This API cannot be accessed and the content and any results may not be used, reproduced or transmitted in any manner without express written permission from Microsoft Corporation.",
				"entityType": "Address",
				"matchCodes": [
					"Good"
				],
				"name": "46 Pinegrove Rd, Arnprior, ON K7S 3G8, Canada",
				"statusCode": 200,
				"statusDescription": "OK",
				"traceId": "102cc6c9b36c4e3a9c70c46c22629581|BN20131519|7.7.0.0|",
				"addressLine": "46 Pinegrove Rd",
				"adminDistrict": "ON",
				"adminDistrict2": "Renfrew",
				"countryRegion": "Canada",
				"formattedAddress": "46 Pinegrove Rd, Arnprior, ON K7S 3G8, Canada",
				"locality": "McNab/Braeside",
				"neighborhood": "Arnprior",
				"postalCode": "K7S 3G8"
			},
			"geometry": {
				"type": "Point",
				"coordinates": [
					-76.38893,
					45.43039
				]
			},
			"bbox": [
				-76.3905319,
				45.4292658,
				-76.3873281,
				45.4315142
			]
		}
	]
}
