{
	"type": "FeatureCollection",
	"features": [
		{
			"type": "Feature",
			"properties": {
				"confidence": 9,
				"authenticationResultCode": "ValidCredentials",
				"brandLogoUri": "http://dev.virtualearth.net/Branding/logo_powered_by.png",
				"copyright": "Copyright © 2017 Microsoft and its suppliers. All rights reserved. This API cannot be accessed and the content and any results may not be used, reproduced or transmitted in any manner without express written permission from Microsoft Corporation.",
				"entityType": "Address",
				"matchCodes": [
					"Good"
				],
				"name": "46 Taralake Gdns NE, Calgary, AB T3J 0A8, Canada",
				"statusCode": 200,
				"statusDescription": "OK",
				"traceId": "bf47b45a3d0e49f2947785b1f0dc26d3|BN20190653|7.7.0.0|",
				"addressLine": "46 Taralake Gdns NE",
				"adminDistrict": "AB",
				"adminDistrict2": "Alberta",
				"countryRegion": "Canada",
				"formattedAddress": "46 Taralake Gdns NE, Calgary, AB T3J 0A8, Canada",
				"locality": "Calgary",
				"neighborhood": "Taradale",
				"postalCode": "T3J 0A8"
			},
			"geometry": {
				"type": "Point",
				"coordinates": [
					-113.93267,
					51.11967
				]
			},
			"bbox": [
				-113.9344609,
				51.1185458,
				-113.9308791,
				51.1207942
			]
		}
	]
}
