{
	"type": "FeatureCollection",
	"features": [
		{
			"type": "Feature",
			"properties": {
				"confidence": 9,
				"authenticationResultCode": "ValidCredentials",
				"brandLogoUri": "http://dev.virtualearth.net/Branding/logo_powered_by.png",
				"copyright": "Copyright © 2017 Microsoft and its suppliers. All rights reserved. This API cannot be accessed and the content and any results may not be used, reproduced or transmitted in any manner without express written permission from Microsoft Corporation.",
				"entityType": "Address",
				"matchCodes": [
					"Good"
				],
				"name": "46 Wabana Ct, Sydney, NS B1P 0B9, Canada",
				"statusCode": 200,
				"statusDescription": "OK",
				"traceId": "d6afa0806a884f1e91f5ab18598a5b21|BN20130521|7.7.0.0|",
				"addressLine": "46 Wabana Ct",
				"adminDistrict": "NS",
				"adminDistrict2": "Cape Breton",
				"countryRegion": "Canada",
				"formattedAddress": "46 Wabana Ct, Sydney, NS B1P 0B9, Canada",
				"locality": "Cape Breton",
				"neighborhood": "Sydney",
				"postalCode": "B1P 0B9"
			},
			"geometry": {
				"type": "Point",
				"coordinates": [
					-60.18299,
					46.14802
				]
			},
			"bbox": [
				-60.1846126,
				46.1468958,
				-60.1813674,
				46.1491442
			]
		}
	]
}
