{
	"type": "FeatureCollection",
	"features": [
		{
			"type": "Feature",
			"properties": {
				"confidence": 9,
				"authenticationResultCode": "ValidCredentials",
				"brandLogoUri": "http://dev.virtualearth.net/Branding/logo_powered_by.png",
				"copyright": "Copyright © 2017 Microsoft and its suppliers. All rights reserved. This API cannot be accessed and the content and any results may not be used, reproduced or transmitted in any manner without express written permission from Microsoft Corporation.",
				"entityType": "Address",
				"matchCodes": [
					"Good"
				],
				"name": "46 Rue le Moyne O, Longueuil, QC J4H 1V3, Canada",
				"statusCode": 200,
				"statusDescription": "OK",
				"traceId": "984cc678c45f43b99aa3b58087041db8|BN20130520|7.7.0.0|",
				"addressLine": "46 Rue le Moyne O",
				"adminDistrict": "QC",
				"adminDistrict2": "Longueuil",
				"countryRegion": "Canada",
				"formattedAddress": "46 Rue le Moyne O, Longueuil, QC J4H 1V3, Canada",
				"locality": "Longueuil",
				"neighborhood": "Jacques-Cartier",
				"postalCode": "J4H 1V3"
			},
			"geometry": {
				"type": "Point",
				"coordinates": [
					-73.49987,
					45.53611
				]
			},
			"bbox": [
				-73.5014749,
				45.5349858,
				-73.4982651,
				45.5372342
			]
		}
	]
}
