{
	"type": "FeatureCollection",
	"features": [
		{
			"type": "Feature",
			"properties": {
				"confidence": 9,
				"authenticationResultCode": "ValidCredentials",
				"brandLogoUri": "http://dev.virtualearth.net/Branding/logo_powered_by.png",
				"copyright": "Copyright © 2017 Microsoft and its suppliers. All rights reserved. This API cannot be accessed and the content and any results may not be used, reproduced or transmitted in any manner without express written permission from Microsoft Corporation.",
				"entityType": "Address",
				"matchCodes": [
					"Good"
				],
				"name": "461 N Service Rd W, Oakville, ON L6M 2V5, Canada",
				"statusCode": 200,
				"statusDescription": "OK",
				"traceId": "e684188e27e04658afe63cbb7a4bbd57|BN20290118|7.7.0.0|",
				"addressLine": "461 N Service Rd W",
				"adminDistrict": "ON",
				"adminDistrict2": "Halton",
				"countryRegion": "Canada",
				"formattedAddress": "461 N Service Rd W, Oakville, ON L6M 2V5, Canada",
				"locality": "Oakville",
				"neighborhood": "Glen Abbey",
				"postalCode": "L6M 2V5"
			},
			"geometry": {
				"type": "Point",
				"coordinates": [
					-79.7075,
					43.44082
				]
			},
			"bbox": [
				-79.7090482,
				43.4396958,
				-79.7059518,
				43.4419442
			]
		}
	]
}
