{
	"type": "FeatureCollection",
	"features": [
		{
			"type": "Feature",
			"properties": {
				"confidence": 9,
				"authenticationResultCode": "ValidCredentials",
				"brandLogoUri": "http://dev.virtualearth.net/Branding/logo_powered_by.png",
				"copyright": "Copyright © 2017 Microsoft and its suppliers. All rights reserved. This API cannot be accessed and the content and any results may not be used, reproduced or transmitted in any manner without express written permission from Microsoft Corporation.",
				"entityType": "Address",
				"matchCodes": [
					"Good"
				],
				"name": "4621 Main St, Belledune, NB E8G 2L3, Canada",
				"statusCode": 200,
				"statusDescription": "OK",
				"traceId": "bfd563b925db4f10a3b35491fa436092|BN20130522|7.7.0.0|",
				"addressLine": "4621 Main St",
				"adminDistrict": "NB",
				"adminDistrict2": "Restigouche",
				"countryRegion": "Canada",
				"formattedAddress": "4621 Main St, Belledune, NB E8G 2L3, Canada",
				"locality": "Belledune",
				"postalCode": "E8G 2L3"
			},
			"geometry": {
				"type": "Point",
				"coordinates": [
					-66.04795,
					47.91999
				]
			},
			"bbox": [
				-66.0496274,
				47.9188658,
				-66.0462726,
				47.9211142
			]
		}
	]
}
