{
	"type": "FeatureCollection",
	"features": [
		{
			"type": "Feature",
			"properties": {
				"confidence": 9,
				"authenticationResultCode": "ValidCredentials",
				"brandLogoUri": "http://dev.virtualearth.net/Branding/logo_powered_by.png",
				"copyright": "Copyright © 2017 Microsoft and its suppliers. All rights reserved. This API cannot be accessed and the content and any results may not be used, reproduced or transmitted in any manner without express written permission from Microsoft Corporation.",
				"entityType": "Address",
				"matchCodes": [
					"Good"
				],
				"name": "4623 Park Ave, Terrace, BC V8G 1V5, Canada",
				"statusCode": 200,
				"statusDescription": "OK",
				"traceId": "802773457757431f90c1db43daae46c6|BN20171457|7.7.0.0|",
				"addressLine": "4623 Park Ave",
				"adminDistrict": "BC",
				"adminDistrict2": "Kitimat-Stikine",
				"countryRegion": "Canada",
				"formattedAddress": "4623 Park Ave, Terrace, BC V8G 1V5, Canada",
				"locality": "Terrace",
				"postalCode": "V8G 1V5"
			},
			"geometry": {
				"type": "Point",
				"coordinates": [
					-128.58806,
					54.51812
				]
			},
			"bbox": [
				-128.5899967,
				54.5169958,
				-128.5861233,
				54.5192442
			]
		}
	]
}
