{
	"type": "FeatureCollection",
	"features": [
		{
			"type": "Feature",
			"properties": {
				"confidence": 9,
				"authenticationResultCode": "ValidCredentials",
				"brandLogoUri": "http://dev.virtualearth.net/Branding/logo_powered_by.png",
				"copyright": "Copyright © 2017 Microsoft and its suppliers. All rights reserved. This API cannot be accessed and the content and any results may not be used, reproduced or transmitted in any manner without express written permission from Microsoft Corporation.",
				"entityType": "Address",
				"matchCodes": [
					"Good"
				],
				"name": "4655 Avenue de Lorimier, Montreal, QC H2H 2B4, Canada",
				"statusCode": 200,
				"statusDescription": "OK",
				"traceId": "275a4e19f7434db4b4a54cefb18ab6a0|BN20290118|7.7.0.0|",
				"addressLine": "4655 Avenue de Lorimier",
				"adminDistrict": "QC",
				"adminDistrict2": "Montreal",
				"countryRegion": "Canada",
				"formattedAddress": "4655 Avenue de Lorimier, Montreal, QC H2H 2B4, Canada",
				"locality": "Montreal",
				"neighborhood": "Le Plateau-Mont-Royal",
				"postalCode": "H2H 2B4"
			},
			"geometry": {
				"type": "Point",
				"coordinates": [
					-73.5746,
					45.53647
				]
			},
			"bbox": [
				-73.5762049,
				45.5353458,
				-73.5729951,
				45.5375942
			]
		}
	]
}
