{
	"type": "FeatureCollection",
	"features": [
		{
			"type": "Feature",
			"properties": {
				"confidence": 9,
				"authenticationResultCode": "ValidCredentials",
				"brandLogoUri": "http://dev.virtualearth.net/Branding/logo_powered_by.png",
				"copyright": "Copyright © 2017 Microsoft and its suppliers. All rights reserved. This API cannot be accessed and the content and any results may not be used, reproduced or transmitted in any manner without express written permission from Microsoft Corporation.",
				"entityType": "Address",
				"matchCodes": [
					"Good"
				],
				"name": "467 Exploraton Ave SE, Calgary, AB T3S, Canada",
				"statusCode": 200,
				"statusDescription": "OK",
				"traceId": "9ff2deb1d89e490f962329209ac5f7e7|BN20130530|7.7.0.0|",
				"addressLine": "467 Exploraton Ave SE",
				"adminDistrict": "AB",
				"adminDistrict2": "Alberta",
				"countryRegion": "Canada",
				"formattedAddress": "467 Exploraton Ave SE, Calgary, AB T3S, Canada",
				"locality": "Calgary",
				"postalCode": "T3S 0B4"
			},
			"geometry": {
				"type": "Point",
				"coordinates": [
					-113.89209,
					50.96281
				]
			},
			"bbox": [
				-113.8938749,
				50.9616858,
				-113.8903051,
				50.9639342
			]
		}
	]
}
