{
	"type": "FeatureCollection",
	"features": [
		{
			"type": "Feature",
			"properties": {
				"confidence": 9,
				"authenticationResultCode": "ValidCredentials",
				"brandLogoUri": "http://dev.virtualearth.net/Branding/logo_powered_by.png",
				"copyright": "Copyright © 2017 Microsoft and its suppliers. All rights reserved. This API cannot be accessed and the content and any results may not be used, reproduced or transmitted in any manner without express written permission from Microsoft Corporation.",
				"entityType": "Address",
				"matchCodes": [
					"Good"
				],
				"name": "4670 Marine Ave, Powell River, BC V8A 2L1, Canada",
				"statusCode": 200,
				"statusDescription": "OK",
				"traceId": "ff4314dc9cb34ef7b3a19d3e9908185e|BN20130631|7.7.0.0|",
				"addressLine": "4670 Marine Ave",
				"adminDistrict": "BC",
				"adminDistrict2": "Powell River",
				"countryRegion": "Canada",
				"formattedAddress": "4670 Marine Ave, Powell River, BC V8A 2L1, Canada",
				"locality": "Powell River",
				"postalCode": "V8A 2L1"
			},
			"geometry": {
				"type": "Point",
				"coordinates": [
					-124.5280349,
					49.8424386
				]
			},
			"bbox": [
				-124.5297781,
				49.8413145,
				-124.5262918,
				49.8435628
			]
		}
	]
}
