{
	"type": "FeatureCollection",
	"features": [
		{
			"type": "Feature",
			"properties": {
				"confidence": 9,
				"authenticationResultCode": "ValidCredentials",
				"brandLogoUri": "http://dev.virtualearth.net/Branding/logo_powered_by.png",
				"copyright": "Copyright © 2017 Microsoft and its suppliers. All rights reserved. This API cannot be accessed and the content and any results may not be used, reproduced or transmitted in any manner without express written permission from Microsoft Corporation.",
				"entityType": "Address",
				"matchCodes": [
					"Good"
				],
				"name": "46719 Hudson Rd, Chilliwack, BC V2R 0K6, Canada",
				"statusCode": 200,
				"statusDescription": "OK",
				"traceId": "d57c01d7be844b1d9d1f9b78554ca07b|BN20220145|7.7.0.0|",
				"addressLine": "46719 Hudson Rd",
				"adminDistrict": "BC",
				"adminDistrict2": "Fraser Valley",
				"countryRegion": "Canada",
				"formattedAddress": "46719 Hudson Rd, Chilliwack, BC V2R 0K6, Canada",
				"locality": "Chilliwack",
				"neighborhood": "East Chilliwack-Southside",
				"postalCode": "V2R 0K6"
			},
			"geometry": {
				"type": "Point",
				"coordinates": [
					-121.9274014,
					49.1057742
				]
			},
			"bbox": [
				-121.9291186,
				49.1046501,
				-121.9256843,
				49.1068984
			]
		}
	]
}
