{
	"type": "FeatureCollection",
	"features": [
		{
			"type": "Feature",
			"properties": {
				"confidence": 9,
				"authenticationResultCode": "ValidCredentials",
				"brandLogoUri": "http://dev.virtualearth.net/Branding/logo_powered_by.png",
				"copyright": "Copyright © 2017 Microsoft and its suppliers. All rights reserved. This API cannot be accessed and the content and any results may not be used, reproduced or transmitted in any manner without express written permission from Microsoft Corporation.",
				"entityType": "Address",
				"matchCodes": [
					"Good"
				],
				"name": "47 Eglinton Cres, Winnipeg, MB R3Y 1E6, Canada",
				"statusCode": 200,
				"statusDescription": "OK",
				"traceId": "567b9750a2804d9b9866c35d3428bf93|BN20200137|7.7.0.0|",
				"addressLine": "47 Eglinton Cres",
				"adminDistrict": "MB",
				"adminDistrict2": "Manitoba",
				"countryRegion": "Canada",
				"formattedAddress": "47 Eglinton Cres, Winnipeg, MB R3Y 1E6, Canada",
				"locality": "Winnipeg",
				"neighborhood": "Whyte Ridge",
				"postalCode": "R3Y 1E6"
			},
			"geometry": {
				"type": "Point",
				"coordinates": [
					-97.20774,
					49.81303
				]
			},
			"bbox": [
				-97.2094821,
				49.8119058,
				-97.2059979,
				49.8141542
			]
		}
	]
}
