{
	"type": "FeatureCollection",
	"features": [
		{
			"type": "Feature",
			"properties": {
				"confidence": 9,
				"authenticationResultCode": "ValidCredentials",
				"brandLogoUri": "http://dev.virtualearth.net/Branding/logo_powered_by.png",
				"copyright": "Copyright © 2017 Microsoft and its suppliers. All rights reserved. This API cannot be accessed and the content and any results may not be used, reproduced or transmitted in any manner without express written permission from Microsoft Corporation.",
				"entityType": "Address",
				"matchCodes": [
					"Good"
				],
				"name": "47 Paint St, Port Hawkesbury, NS B9A 3J9, Canada",
				"statusCode": 200,
				"statusDescription": "OK",
				"traceId": "eda88b4779474a7f91a7b497da3f1e3e|BN20290118|7.7.0.0|",
				"addressLine": "47 Paint St",
				"adminDistrict": "NS",
				"adminDistrict2": "Inverness",
				"countryRegion": "Canada",
				"formattedAddress": "47 Paint St, Port Hawkesbury, NS B9A 3J9, Canada",
				"locality": "Port Hawkesbury",
				"postalCode": "B9A 3J9"
			},
			"geometry": {
				"type": "Point",
				"coordinates": [
					-61.3324159,
					45.6173506
				]
			},
			"bbox": [
				-61.3340231,
				45.6162265,
				-61.3308087,
				45.6184748
			]
		}
	]
}
