{
	"type": "FeatureCollection",
	"features": [
		{
			"type": "Feature",
			"properties": {
				"confidence": 9,
				"authenticationResultCode": "ValidCredentials",
				"brandLogoUri": "http://dev.virtualearth.net/Branding/logo_powered_by.png",
				"copyright": "Copyright © 2017 Microsoft and its suppliers. All rights reserved. This API cannot be accessed and the content and any results may not be used, reproduced or transmitted in any manner without express written permission from Microsoft Corporation.",
				"entityType": "Address",
				"matchCodes": [
					"Good"
				],
				"name": "47 Storrie Rd, Campbell River, BC V9H 1H5, Canada",
				"statusCode": 200,
				"statusDescription": "OK",
				"traceId": "5178bca363f1406daace96e42be3ac77|BN20260231|7.7.0.0|",
				"addressLine": "47 Storrie Rd",
				"adminDistrict": "BC",
				"adminDistrict2": "Strathcona",
				"countryRegion": "Canada",
				"formattedAddress": "47 Storrie Rd, Campbell River, BC V9H 1H5, Canada",
				"locality": "Strathcona",
				"neighborhood": "Campbell River",
				"postalCode": "V9H 1H5"
			},
			"geometry": {
				"type": "Point",
				"coordinates": [
					-125.1887446,
					49.9225502
				]
			},
			"bbox": [
				-125.1904907,
				49.921426,
				-125.1869986,
				49.9236743
			]
		}
	]
}
