{
	"type": "FeatureCollection",
	"features": [
		{
			"type": "Feature",
			"properties": {
				"confidence": 9,
				"authenticationResultCode": "ValidCredentials",
				"brandLogoUri": "http://dev.virtualearth.net/Branding/logo_powered_by.png",
				"copyright": "Copyright © 2017 Microsoft and its suppliers. All rights reserved. This API cannot be accessed and the content and any results may not be used, reproduced or transmitted in any manner without express written permission from Microsoft Corporation.",
				"entityType": "Address",
				"matchCodes": [
					"Good"
				],
				"name": "4715 Treetop Hts, Saanich, BC V8Y 1E2, Canada",
				"statusCode": 200,
				"statusDescription": "OK",
				"traceId": "6d20f72c6ae049958b8e24cd920dd8c1|BN20130632|7.7.0.0|",
				"addressLine": "4715 Treetop Hts",
				"adminDistrict": "BC",
				"adminDistrict2": "Capital",
				"countryRegion": "Canada",
				"formattedAddress": "4715 Treetop Hts, Saanich, BC V8Y 1E2, Canada",
				"locality": "Saanich",
				"postalCode": "V8Y 1E2"
			},
			"geometry": {
				"type": "Point",
				"coordinates": [
					-123.35357,
					48.5047
				]
			},
			"bbox": [
				-123.3552667,
				48.5035758,
				-123.3518733,
				48.5058242
			]
		}
	]
}
