{
	"type": "FeatureCollection",
	"features": [
		{
			"type": "Feature",
			"properties": {
				"confidence": 9,
				"authenticationResultCode": "ValidCredentials",
				"brandLogoUri": "http://dev.virtualearth.net/Branding/logo_powered_by.png",
				"copyright": "Copyright © 2017 Microsoft and its suppliers. All rights reserved. This API cannot be accessed and the content and any results may not be used, reproduced or transmitted in any manner without express written permission from Microsoft Corporation.",
				"entityType": "Address",
				"matchCodes": [
					"Good"
				],
				"name": "472 Rue Letendre, Rimouski, QC G5L 4Z9, Canada",
				"statusCode": 200,
				"statusDescription": "OK",
				"traceId": "1728d04a2e864be49d9e8195ea631b23|BN20160335|7.7.0.0|",
				"addressLine": "472 Rue Letendre",
				"adminDistrict": "QC",
				"adminDistrict2": "Rimouski-Neigette",
				"countryRegion": "Canada",
				"formattedAddress": "472 Rue Letendre, Rimouski, QC G5L 4Z9, Canada",
				"locality": "Rimouski",
				"postalCode": "G5L 4Z9"
			},
			"geometry": {
				"type": "Point",
				"coordinates": [
					-68.53888,
					48.43078
				]
			},
			"bbox": [
				-68.5405742,
				48.4296558,
				-68.5371858,
				48.4319042
			]
		}
	]
}
