{
	"type": "FeatureCollection",
	"features": [
		{
			"type": "Feature",
			"properties": {
				"confidence": 9,
				"authenticationResultCode": "ValidCredentials",
				"brandLogoUri": "http://dev.virtualearth.net/Branding/logo_powered_by.png",
				"copyright": "Copyright © 2017 Microsoft and its suppliers. All rights reserved. This API cannot be accessed and the content and any results may not be used, reproduced or transmitted in any manner without express written permission from Microsoft Corporation.",
				"entityType": "Address",
				"matchCodes": [
					"Good"
				],
				"name": "4720 Kingsway, Burnaby, BC V5H 4N2, Canada",
				"statusCode": 200,
				"statusDescription": "OK",
				"traceId": "274f35766f5742c1a85f70cc8422f6e6|BN20130620|7.7.0.0|",
				"addressLine": "4720 Kingsway",
				"adminDistrict": "BC",
				"adminDistrict2": "Greater Vancouver",
				"countryRegion": "Canada",
				"formattedAddress": "4720 Kingsway, Burnaby, BC V5H 4N2, Canada",
				"locality": "Burnaby",
				"neighborhood": "Maywood",
				"postalCode": "V5H 4N2"
			},
			"geometry": {
				"type": "Point",
				"coordinates": [
					-122.998578,
					49.2279839
				]
			},
			"bbox": [
				-123.0002993,
				49.2268598,
				-122.9968566,
				49.2291081
			]
		}
	]
}
