{
	"type": "FeatureCollection",
	"features": [
		{
			"type": "Feature",
			"properties": {
				"confidence": 9,
				"authenticationResultCode": "ValidCredentials",
				"brandLogoUri": "http://dev.virtualearth.net/Branding/logo_powered_by.png",
				"copyright": "Copyright © 2017 Microsoft and its suppliers. All rights reserved. This API cannot be accessed and the content and any results may not be used, reproduced or transmitted in any manner without express written permission from Microsoft Corporation.",
				"entityType": "Address",
				"matchCodes": [
					"Good"
				],
				"name": "4728 78A Street Clos, Red Deer, AB T4P 2J2, Canada",
				"statusCode": 200,
				"statusDescription": "OK",
				"traceId": "6ba9a5c888e54e779886a6e0e65cb525|BN20130447|7.7.0.0|",
				"addressLine": "4728 78A Street Clos",
				"adminDistrict": "AB",
				"adminDistrict2": "Alberta",
				"countryRegion": "Canada",
				"formattedAddress": "4728 78A Street Clos, Red Deer, AB T4P 2J2, Canada",
				"locality": "Red Deer",
				"postalCode": "T4P 2J2"
			},
			"geometry": {
				"type": "Point",
				"coordinates": [
					-113.80382,
					52.3110799
				]
			},
			"bbox": [
				-113.8056587,
				52.3099557,
				-113.8019813,
				52.3122041
			]
		}
	]
}
