{
	"type": "FeatureCollection",
	"features": [
		{
			"type": "Feature",
			"properties": {
				"confidence": 9,
				"authenticationResultCode": "ValidCredentials",
				"brandLogoUri": "http://dev.virtualearth.net/Branding/logo_powered_by.png",
				"copyright": "Copyright © 2017 Microsoft and its suppliers. All rights reserved. This API cannot be accessed and the content and any results may not be used, reproduced or transmitted in any manner without express written permission from Microsoft Corporation.",
				"entityType": "Address",
				"matchCodes": [
					"Good"
				],
				"name": "4741 CR-45, Hamilton Twp, ON K9A, Canada",
				"statusCode": 200,
				"statusDescription": "OK",
				"traceId": "8557798f248147ad8f9ddcd615b5d36b|BN20130530|7.7.0.0|",
				"addressLine": "4741 CR-45",
				"adminDistrict": "ON",
				"adminDistrict2": "Northumberland",
				"countryRegion": "Canada",
				"formattedAddress": "4741 CR-45, Hamilton Twp, ON K9A, Canada",
				"locality": "Hamilton",
				"neighborhood": "Baltimore",
				"postalCode": "K9A"
			},
			"geometry": {
				"type": "Point",
				"coordinates": [
					-78.1487567,
					44.0146856
				]
			},
			"bbox": [
				-78.1503198,
				44.0135615,
				-78.1471935,
				44.0158098
			]
		}
	]
}
