{
	"type": "FeatureCollection",
	"features": [
		{
			"type": "Feature",
			"properties": {
				"confidence": 9,
				"authenticationResultCode": "ValidCredentials",
				"brandLogoUri": "http://dev.virtualearth.net/Branding/logo_powered_by.png",
				"copyright": "Copyright © 2017 Microsoft and its suppliers. All rights reserved. This API cannot be accessed and the content and any results may not be used, reproduced or transmitted in any manner without express written permission from Microsoft Corporation.",
				"entityType": "Address",
				"matchCodes": [
					"Good"
				],
				"name": "475 1st Ave E, Regina, SK S4N 4Z3, Canada",
				"statusCode": 200,
				"statusDescription": "OK",
				"traceId": "c61dc3c43e564cca9c76b8f3a2c951a9|BN20240423|7.7.0.0|",
				"addressLine": "475 1st Ave E",
				"adminDistrict": "SK",
				"adminDistrict2": "Saskatchewan",
				"countryRegion": "Canada",
				"formattedAddress": "475 1st Ave E, Regina, SK S4N 4Z3, Canada",
				"locality": "Regina",
				"postalCode": "S4N 4Z3"
			},
			"geometry": {
				"type": "Point",
				"coordinates": [
					-104.57475,
					50.46732
				]
			},
			"bbox": [
				-104.5765161,
				50.4661958,
				-104.5729839,
				50.4684442
			]
		}
	]
}
