{
	"type": "FeatureCollection",
	"features": [
		{
			"type": "Feature",
			"properties": {
				"confidence": 9,
				"authenticationResultCode": "ValidCredentials",
				"brandLogoUri": "http://dev.virtualearth.net/Branding/logo_powered_by.png",
				"copyright": "Copyright © 2017 Microsoft and its suppliers. All rights reserved. This API cannot be accessed and the content and any results may not be used, reproduced or transmitted in any manner without express written permission from Microsoft Corporation.",
				"entityType": "Address",
				"matchCodes": [
					"Good"
				],
				"name": "48 Evanscove Hts NW, Calgary, AB T3P 0A4, Canada",
				"statusCode": 200,
				"statusDescription": "OK",
				"traceId": "5307a15ca1314fd3a1befae47cfefa20|BN20130632|7.7.0.0|",
				"addressLine": "48 Evanscove Hts NW",
				"adminDistrict": "AB",
				"adminDistrict2": "Alberta",
				"countryRegion": "Canada",
				"formattedAddress": "48 Evanscove Hts NW, Calgary, AB T3P 0A4, Canada",
				"locality": "Calgary",
				"neighborhood": "Evanston",
				"postalCode": "T3P 0A4"
			},
			"geometry": {
				"type": "Point",
				"coordinates": [
					-114.11549,
					51.16696
				]
			},
			"bbox": [
				-114.1172828,
				51.1658358,
				-114.1136972,
				51.1680842
			]
		}
	]
}
