{
	"type": "FeatureCollection",
	"features": [
		{
			"type": "Feature",
			"properties": {
				"confidence": 9,
				"authenticationResultCode": "ValidCredentials",
				"brandLogoUri": "http://dev.virtualearth.net/Branding/logo_powered_by.png",
				"copyright": "Copyright © 2017 Microsoft and its suppliers. All rights reserved. This API cannot be accessed and the content and any results may not be used, reproduced or transmitted in any manner without express written permission from Microsoft Corporation.",
				"entityType": "Address",
				"matchCodes": [
					"Good"
				],
				"name": "48 Westland Cres SW, Calgary, AB T3H 0W1, Canada",
				"statusCode": 200,
				"statusDescription": "OK",
				"traceId": "018f51571ccf419580e9bf3f5f14343f|BN20130634|7.7.0.0|",
				"addressLine": "48 Westland Cres SW",
				"adminDistrict": "AB",
				"adminDistrict2": "Alberta",
				"countryRegion": "Canada",
				"formattedAddress": "48 Westland Cres SW, Calgary, AB T3H 0W1, Canada",
				"locality": "Calgary",
				"neighborhood": "West Springs",
				"postalCode": "T3H 0W1"
			},
			"geometry": {
				"type": "Point",
				"coordinates": [
					-114.2025,
					51.05889
				]
			},
			"bbox": [
				-114.2042886,
				51.0577658,
				-114.2007114,
				51.0600142
			]
		}
	]
}
