{
	"type": "FeatureCollection",
	"features": [
		{
			"type": "Feature",
			"properties": {
				"confidence": 9,
				"authenticationResultCode": "ValidCredentials",
				"brandLogoUri": "http://dev.virtualearth.net/Branding/logo_powered_by.png",
				"copyright": "Copyright © 2017 Microsoft and its suppliers. All rights reserved. This API cannot be accessed and the content and any results may not be used, reproduced or transmitted in any manner without express written permission from Microsoft Corporation.",
				"entityType": "Address",
				"matchCodes": [
					"Good"
				],
				"name": "480 Conestogo Rd W, Waterloo, ON N2L 4E2, Canada",
				"statusCode": 200,
				"statusDescription": "OK",
				"traceId": "9946671f7f354be1a967668bf14c939b|BN20260231|7.7.0.0|",
				"addressLine": "480 Conestogo Rd W",
				"adminDistrict": "ON",
				"adminDistrict2": "Waterloo",
				"countryRegion": "Canada",
				"formattedAddress": "480 Conestogo Rd W, Waterloo, ON N2L 4E2, Canada",
				"locality": "Waterloo",
				"postalCode": "N2L 4E2"
			},
			"geometry": {
				"type": "Point",
				"coordinates": [
					-80.5324399,
					43.49639
				]
			},
			"bbox": [
				-80.5339896,
				43.4952658,
				-80.5308902,
				43.4975142
			]
		}
	]
}
