{
	"type": "FeatureCollection",
	"features": [
		{
			"type": "Feature",
			"properties": {
				"confidence": 9,
				"authenticationResultCode": "ValidCredentials",
				"brandLogoUri": "http://dev.virtualearth.net/Branding/logo_powered_by.png",
				"copyright": "Copyright © 2017 Microsoft and its suppliers. All rights reserved. This API cannot be accessed and the content and any results may not be used, reproduced or transmitted in any manner without express written permission from Microsoft Corporation.",
				"entityType": "Address",
				"matchCodes": [
					"Good"
				],
				"name": "480 Avenue Lafleur, La Salle, QC H8R 3H9, Canada",
				"statusCode": 200,
				"statusDescription": "OK",
				"traceId": "0c141e0d0c9f44ea978073d07ebea021|BN20130447|7.7.0.0|",
				"addressLine": "480 Avenue Lafleur",
				"adminDistrict": "QC",
				"adminDistrict2": "Montreal",
				"countryRegion": "Canada",
				"formattedAddress": "480 Avenue Lafleur, La Salle, QC H8R 3H9, Canada",
				"locality": "Montreal",
				"neighborhood": "La Salle",
				"postalCode": "H8R 3H9"
			},
			"geometry": {
				"type": "Point",
				"coordinates": [
					-73.64589,
					45.43397
				]
			},
			"bbox": [
				-73.647492,
				45.4328458,
				-73.644288,
				45.4350942
			]
		}
	]
}
