{
	"type": "FeatureCollection",
	"features": [
		{
			"type": "Feature",
			"properties": {
				"confidence": 9,
				"authenticationResultCode": "ValidCredentials",
				"brandLogoUri": "http://dev.virtualearth.net/Branding/logo_powered_by.png",
				"copyright": "Copyright © 2017 Microsoft and its suppliers. All rights reserved. This API cannot be accessed and the content and any results may not be used, reproduced or transmitted in any manner without express written permission from Microsoft Corporation.",
				"entityType": "Address",
				"matchCodes": [
					"Good"
				],
				"name": "4802 47 St E, Redwater, AB T0A 3A3, Canada",
				"statusCode": 200,
				"statusDescription": "OK",
				"traceId": "b6ebece881224b6da01a56723d8b7f91|BN20280152|7.7.0.0|",
				"addressLine": "4802 47 St E",
				"adminDistrict": "AB",
				"adminDistrict2": "Alberta",
				"countryRegion": "Canada",
				"formattedAddress": "4802 47 St E, Redwater, AB T0A 3A3, Canada",
				"locality": "Redwater",
				"postalCode": "T0A 3A3"
			},
			"geometry": {
				"type": "Point",
				"coordinates": [
					-113.08934,
					53.9503
				]
			},
			"bbox": [
				-113.0912502,
				53.9491758,
				-113.0874298,
				53.9514242
			]
		}
	]
}
