{
	"type": "FeatureCollection",
	"features": [
		{
			"type": "Feature",
			"properties": {
				"confidence": 9,
				"authenticationResultCode": "ValidCredentials",
				"brandLogoUri": "http://dev.virtualearth.net/Branding/logo_powered_by.png",
				"copyright": "Copyright © 2017 Microsoft and its suppliers. All rights reserved. This API cannot be accessed and the content and any results may not be used, reproduced or transmitted in any manner without express written permission from Microsoft Corporation.",
				"entityType": "Address",
				"matchCodes": [
					"Good"
				],
				"name": "4803 48 St, Camrose, AB T4V 1L4, Canada",
				"statusCode": 200,
				"statusDescription": "OK",
				"traceId": "db18a5583296430588fda7eb00180910|BN20131519|7.7.0.0|",
				"addressLine": "4803 48 St",
				"adminDistrict": "AB",
				"adminDistrict2": "Alberta",
				"countryRegion": "Canada",
				"formattedAddress": "4803 48 St, Camrose, AB T4V 1L4, Canada",
				"locality": "Camrose",
				"postalCode": "T4V 1L4"
			},
			"geometry": {
				"type": "Point",
				"coordinates": [
					-112.8225657,
					53.018398
				]
			},
			"bbox": [
				-112.8244344,
				53.0172738,
				-112.820697,
				53.0195221
			]
		}
	]
}
