{
	"type": "FeatureCollection",
	"features": [
		{
			"type": "Feature",
			"properties": {
				"confidence": 9,
				"authenticationResultCode": "ValidCredentials",
				"brandLogoUri": "http://dev.virtualearth.net/Branding/logo_powered_by.png",
				"copyright": "Copyright © 2017 Microsoft and its suppliers. All rights reserved. This API cannot be accessed and the content and any results may not be used, reproduced or transmitted in any manner without express written permission from Microsoft Corporation.",
				"entityType": "Address",
				"matchCodes": [
					"Good"
				],
				"name": "4845 Rue des Aulnets, Terrebonne, QC J6X 1W5, Canada",
				"statusCode": 200,
				"statusDescription": "OK",
				"traceId": "392ec5a227ce46dc99f669f08c772331|BN20130719|7.7.0.0|",
				"addressLine": "4845 Rue des Aulnets",
				"adminDistrict": "QC",
				"adminDistrict2": "Les Moulins",
				"countryRegion": "Canada",
				"formattedAddress": "4845 Rue des Aulnets, Terrebonne, QC J6X 1W5, Canada",
				"locality": "Terrebonne",
				"postalCode": "J6X 1W5"
			},
			"geometry": {
				"type": "Point",
				"coordinates": [
					-73.65694,
					45.70955
				]
			},
			"bbox": [
				-73.6585499,
				45.7084258,
				-73.6553301,
				45.7106742
			]
		}
	]
}
