{
	"type": "FeatureCollection",
	"features": [
		{
			"type": "Feature",
			"properties": {
				"confidence": 9,
				"authenticationResultCode": "ValidCredentials",
				"brandLogoUri": "http://dev.virtualearth.net/Branding/logo_powered_by.png",
				"copyright": "Copyright © 2017 Microsoft and its suppliers. All rights reserved. This API cannot be accessed and the content and any results may not be used, reproduced or transmitted in any manner without express written permission from Microsoft Corporation.",
				"entityType": "Address",
				"matchCodes": [
					"Good"
				],
				"name": "49 Sheffield St, North York, ON M6M 3E5, Canada",
				"statusCode": 200,
				"statusDescription": "OK",
				"traceId": "513f911e8f7448559c36209e6d09fa9e|BN20130422|7.7.0.0|",
				"addressLine": "49 Sheffield St",
				"adminDistrict": "ON",
				"adminDistrict2": "Toronto",
				"countryRegion": "Canada",
				"formattedAddress": "49 Sheffield St, North York, ON M6M 3E5, Canada",
				"locality": "Toronto",
				"neighborhood": "Brookhaven-Amesbury",
				"postalCode": "M6M 3E5"
			},
			"geometry": {
				"type": "Point",
				"coordinates": [
					-79.46996,
					43.70515
				]
			},
			"bbox": [
				-79.471515,
				43.7040258,
				-79.468405,
				43.7062742
			]
		}
	]
}
