{
	"type": "FeatureCollection",
	"features": [
		{
			"type": "Feature",
			"properties": {
				"confidence": 9,
				"authenticationResultCode": "ValidCredentials",
				"brandLogoUri": "http://dev.virtualearth.net/Branding/logo_powered_by.png",
				"copyright": "Copyright © 2017 Microsoft and its suppliers. All rights reserved. This API cannot be accessed and the content and any results may not be used, reproduced or transmitted in any manner without express written permission from Microsoft Corporation.",
				"entityType": "Address",
				"matchCodes": [
					"Good"
				],
				"name": "490 Adelaide St W, Toronto, ON M5V 1T2, Canada",
				"statusCode": 200,
				"statusDescription": "OK",
				"traceId": "fbb5730da9e14f5abe8301ea96a645b3|BN20210145|7.7.0.0|",
				"addressLine": "490 Adelaide St W",
				"adminDistrict": "ON",
				"adminDistrict2": "Toronto",
				"countryRegion": "Canada",
				"formattedAddress": "490 Adelaide St W, Toronto, ON M5V 1T2, Canada",
				"locality": "Toronto",
				"neighborhood": "Waterfront Communities-the Island",
				"postalCode": "M5V 1T2"
			},
			"geometry": {
				"type": "Point",
				"coordinates": [
					-79.4001,
					43.64618
				]
			},
			"bbox": [
				-79.4016535,
				43.6450558,
				-79.3985465,
				43.6473042
			]
		}
	]
}
