{
	"type": "FeatureCollection",
	"features": [
		{
			"type": "Feature",
			"properties": {
				"confidence": 9,
				"authenticationResultCode": "ValidCredentials",
				"brandLogoUri": "http://dev.virtualearth.net/Branding/logo_powered_by.png",
				"copyright": "Copyright © 2017 Microsoft and its suppliers. All rights reserved. This API cannot be accessed and the content and any results may not be used, reproduced or transmitted in any manner without express written permission from Microsoft Corporation.",
				"entityType": "Address",
				"matchCodes": [
					"Good"
				],
				"name": "4900 54 Ave SE, Calgary, AB T2C 2Y8, Canada",
				"statusCode": 200,
				"statusDescription": "OK",
				"traceId": "9de1593462594f47a33d5d55c8f5bd6e|BN20130620|7.7.0.0|",
				"addressLine": "4900 54 Ave SE",
				"adminDistrict": "AB",
				"adminDistrict2": "Alberta",
				"countryRegion": "Canada",
				"formattedAddress": "4900 54 Ave SE, Calgary, AB T2C 2Y8, Canada",
				"locality": "Calgary",
				"neighborhood": "Foothills",
				"postalCode": "T2C 2Y8"
			},
			"geometry": {
				"type": "Point",
				"coordinates": [
					-113.96294,
					51.00413
				]
			},
			"bbox": [
				-113.9647265,
				51.0030058,
				-113.9611535,
				51.0052542
			]
		}
	]
}
