{
	"type": "FeatureCollection",
	"features": [
		{
			"type": "Feature",
			"properties": {
				"confidence": 9,
				"authenticationResultCode": "ValidCredentials",
				"brandLogoUri": "http://dev.virtualearth.net/Branding/logo_powered_by.png",
				"copyright": "Copyright © 2017 Microsoft and its suppliers. All rights reserved. This API cannot be accessed and the content and any results may not be used, reproduced or transmitted in any manner without express written permission from Microsoft Corporation.",
				"entityType": "Address",
				"matchCodes": [
					"Good"
				],
				"name": "4908 97 St NW, Edmonton, AB T6E 5S1, Canada",
				"statusCode": 200,
				"statusDescription": "OK",
				"traceId": "5d837ff8a10a43369b0667bc758a51e2|BN20171457|7.7.0.0|",
				"addressLine": "4908 97 St NW",
				"adminDistrict": "AB",
				"adminDistrict2": "Alberta",
				"countryRegion": "Canada",
				"formattedAddress": "4908 97 St NW, Edmonton, AB T6E 5S1, Canada",
				"locality": "Edmonton",
				"neighborhood": "Papaschase Industrial",
				"postalCode": "T6E 5S1"
			},
			"geometry": {
				"type": "Point",
				"coordinates": [
					-113.48053,
					53.4867
				]
			},
			"bbox": [
				-113.4824193,
				53.4855758,
				-113.4786407,
				53.4878242
			]
		}
	]
}
