{
	"type": "FeatureCollection",
	"features": [
		{
			"type": "Feature",
			"properties": {
				"confidence": 9,
				"authenticationResultCode": "ValidCredentials",
				"brandLogoUri": "http://dev.virtualearth.net/Branding/logo_powered_by.png",
				"copyright": "Copyright © 2017 Microsoft and its suppliers. All rights reserved. This API cannot be accessed and the content and any results may not be used, reproduced or transmitted in any manner without express written permission from Microsoft Corporation.",
				"entityType": "Address",
				"matchCodes": [
					"Good"
				],
				"name": "4929 Limebank Rd, Gloucester, ON K1X 1E8, Canada",
				"statusCode": 200,
				"statusDescription": "OK",
				"traceId": "78938224a81c4915b7e48a2c8f4a7966|BN20130532|7.7.0.0|",
				"addressLine": "4929 Limebank Rd",
				"adminDistrict": "ON",
				"adminDistrict2": "Ottawa",
				"countryRegion": "Canada",
				"formattedAddress": "4929 Limebank Rd, Gloucester, ON K1X 1E8, Canada",
				"locality": "Ottawa",
				"neighborhood": "Gloucester",
				"postalCode": "K1X 1E8"
			},
			"geometry": {
				"type": "Point",
				"coordinates": [
					-75.65989,
					45.26802
				]
			},
			"bbox": [
				-75.6614873,
				45.2668958,
				-75.6582927,
				45.2691442
			]
		}
	]
}
