{
	"type": "FeatureCollection",
	"features": [
		{
			"type": "Feature",
			"properties": {
				"confidence": 9,
				"authenticationResultCode": "ValidCredentials",
				"brandLogoUri": "http://dev.virtualearth.net/Branding/logo_powered_by.png",
				"copyright": "Copyright © 2017 Microsoft and its suppliers. All rights reserved. This API cannot be accessed and the content and any results may not be used, reproduced or transmitted in any manner without express written permission from Microsoft Corporation.",
				"entityType": "Address",
				"matchCodes": [
					"Good"
				],
				"name": "493 Lynett Cres, Richmond Hill, ON L4C 2V8, Canada",
				"statusCode": 200,
				"statusDescription": "OK",
				"traceId": "c7bfd34288bd4abab2a31c86a7b9868c|BN20220145|7.7.0.0|",
				"addressLine": "493 Lynett Cres",
				"adminDistrict": "ON",
				"adminDistrict2": "York",
				"countryRegion": "Canada",
				"formattedAddress": "493 Lynett Cres, Richmond Hill, ON L4C 2V8, Canada",
				"locality": "Richmond Hill",
				"postalCode": "L4C 2V8"
			},
			"geometry": {
				"type": "Point",
				"coordinates": [
					-79.42098,
					43.88856
				]
			},
			"bbox": [
				-79.4225398,
				43.8874358,
				-79.4194202,
				43.8896842
			]
		}
	]
}
