{
	"type": "FeatureCollection",
	"features": [
		{
			"type": "Feature",
			"properties": {
				"confidence": 9,
				"authenticationResultCode": "ValidCredentials",
				"brandLogoUri": "http://dev.virtualearth.net/Branding/logo_powered_by.png",
				"copyright": "Copyright © 2017 Microsoft and its suppliers. All rights reserved. This API cannot be accessed and the content and any results may not be used, reproduced or transmitted in any manner without express written permission from Microsoft Corporation.",
				"entityType": "Address",
				"matchCodes": [
					"Good"
				],
				"name": "4940 Granville Rd, Granville Ferry, NS B0S 1K0, Canada",
				"statusCode": 200,
				"statusDescription": "OK",
				"traceId": "bb43e29cbae64d029d23c336c565d307|BN20130533|7.7.0.0|",
				"addressLine": "4940 Granville Rd",
				"adminDistrict": "NS",
				"adminDistrict2": "Annapolis",
				"countryRegion": "Canada",
				"formattedAddress": "4940 Granville Rd, Granville Ferry, NS B0S 1K0, Canada",
				"locality": "Annapolis",
				"neighborhood": "Granville Ferry",
				"postalCode": "B0S 1K0"
			},
			"geometry": {
				"type": "Point",
				"coordinates": [
					-65.5474518,
					44.7410239
				]
			},
			"bbox": [
				-65.5490345,
				44.7398997,
				-65.5458692,
				44.742148
			]
		}
	]
}
