{
	"type": "FeatureCollection",
	"features": [
		{
			"type": "Feature",
			"properties": {
				"confidence": 9,
				"authenticationResultCode": "ValidCredentials",
				"brandLogoUri": "http://dev.virtualearth.net/Branding/logo_powered_by.png",
				"copyright": "Copyright © 2017 Microsoft and its suppliers. All rights reserved. This API cannot be accessed and the content and any results may not be used, reproduced or transmitted in any manner without express written permission from Microsoft Corporation.",
				"entityType": "Address",
				"matchCodes": [
					"Good"
				],
				"name": "4950 110 Ave SE, Calgary, AB T2C 3E2, Canada",
				"statusCode": 200,
				"statusDescription": "OK",
				"traceId": "c186b61608714cffaf2d1af4145372be|BN20210145|7.7.0.0|",
				"addressLine": "4950 110 Ave SE",
				"adminDistrict": "AB",
				"adminDistrict2": "Alberta",
				"countryRegion": "Canada",
				"formattedAddress": "4950 110 Ave SE, Calgary, AB T2C 3E2, Canada",
				"locality": "Calgary",
				"postalCode": "T2C 3E2"
			},
			"geometry": {
				"type": "Point",
				"coordinates": [
					-113.96345,
					50.95406
				]
			},
			"bbox": [
				-113.9652345,
				50.9529358,
				-113.9616655,
				50.9551842
			]
		}
	]
}
