{
	"type": "FeatureCollection",
	"features": [
		{
			"type": "Feature",
			"properties": {
				"confidence": 9,
				"authenticationResultCode": "ValidCredentials",
				"brandLogoUri": "http://dev.virtualearth.net/Branding/logo_powered_by.png",
				"copyright": "Copyright © 2017 Microsoft and its suppliers. All rights reserved. This API cannot be accessed and the content and any results may not be used, reproduced or transmitted in any manner without express written permission from Microsoft Corporation.",
				"entityType": "Address",
				"matchCodes": [
					"Good"
				],
				"name": "497 Lorindale St, Waterloo, ON N2K 2X2, Canada",
				"statusCode": 200,
				"statusDescription": "OK",
				"traceId": "2d389027524a4b8ca69ef4cc4556d472|BN20130423|7.7.0.0|",
				"addressLine": "497 Lorindale St",
				"adminDistrict": "ON",
				"adminDistrict2": "Waterloo",
				"countryRegion": "Canada",
				"formattedAddress": "497 Lorindale St, Waterloo, ON N2K 2X2, Canada",
				"locality": "Waterloo",
				"postalCode": "N2K 2X2"
			},
			"geometry": {
				"type": "Point",
				"coordinates": [
					-80.50685,
					43.5024299
				]
			},
			"bbox": [
				-80.5083998,
				43.5013057,
				-80.5053002,
				43.5035541
			]
		}
	]
}
