{
	"type": "FeatureCollection",
	"features": [
		{
			"type": "Feature",
			"properties": {
				"confidence": 9,
				"authenticationResultCode": "ValidCredentials",
				"brandLogoUri": "http://dev.virtualearth.net/Branding/logo_powered_by.png",
				"copyright": "Copyright © 2017 Microsoft and its suppliers. All rights reserved. This API cannot be accessed and the content and any results may not be used, reproduced or transmitted in any manner without express written permission from Microsoft Corporation.",
				"entityType": "Address",
				"matchCodes": [
					"Good"
				],
				"name": "4993 Westminster Ave, Delta, BC V4K 2J1, Canada",
				"statusCode": 200,
				"statusDescription": "OK",
				"traceId": "adc368815485490bb0df20d61637bdf5|BN20130521|7.7.0.0|",
				"addressLine": "4993 Westminster Ave",
				"adminDistrict": "BC",
				"adminDistrict2": "Greater Vancouver",
				"countryRegion": "Canada",
				"formattedAddress": "4993 Westminster Ave, Delta, BC V4K 2J1, Canada",
				"locality": "Delta",
				"neighborhood": "Ladner",
				"postalCode": "V4K 2J1"
			},
			"geometry": {
				"type": "Point",
				"coordinates": [
					-123.08229,
					49.094
				]
			},
			"bbox": [
				-123.0840067,
				49.0928758,
				-123.0805733,
				49.0951242
			]
		}
	]
}
