{
	"type": "FeatureCollection",
	"features": [
		{
			"type": "Feature",
			"properties": {
				"confidence": 9,
				"authenticationResultCode": "ValidCredentials",
				"brandLogoUri": "http://dev.virtualearth.net/Branding/logo_powered_by.png",
				"copyright": "Copyright © 2017 Microsoft and its suppliers. All rights reserved. This API cannot be accessed and the content and any results may not be used, reproduced or transmitted in any manner without express written permission from Microsoft Corporation.",
				"entityType": "Address",
				"matchCodes": [
					"Good"
				],
				"name": "4 Meadowlark Villge, Edmonton, AB T5R, Canada",
				"statusCode": 200,
				"statusDescription": "OK",
				"traceId": "4c7aa45089ac4038b0d0de1ae53e49aa|BN20260231|7.7.0.0|",
				"addressLine": "4 Meadowlark Villge",
				"adminDistrict": "AB",
				"adminDistrict2": "Alberta",
				"countryRegion": "Canada",
				"formattedAddress": "4 Meadowlark Villge, Edmonton, AB T5R, Canada",
				"locality": "Edmonton",
				"neighborhood": "West Meadowlark Park",
				"postalCode": "T5R 5X3"
			},
			"geometry": {
				"type": "Point",
				"coordinates": [
					-113.60733,
					53.52169
				]
			},
			"bbox": [
				-113.6092209,
				53.5205658,
				-113.6054391,
				53.5228142
			]
		}
	]
}
