{
	"type": "FeatureCollection",
	"features": [
		{
			"type": "Feature",
			"properties": {
				"confidence": 7,
				"authenticationResultCode": "ValidCredentials",
				"brandLogoUri": "http://dev.virtualearth.net/Branding/logo_powered_by.png",
				"copyright": "Copyright © 2017 Microsoft and its suppliers. All rights reserved. This API cannot be accessed and the content and any results may not be used, reproduced or transmitted in any manner without express written permission from Microsoft Corporation.",
				"entityType": "Postcode1",
				"matchCodes": [
					"UpHierarchy"
				],
				"name": "Nipissing District, P0H 2A0, Canada",
				"statusCode": 200,
				"statusDescription": "OK",
				"traceId": "9ff948185b944285b03a8eaa695936dd|BN20280152|7.7.0.0|",
				"adminDistrict": "ON",
				"adminDistrict2": "Nipissing",
				"countryRegion": "Canada",
				"formattedAddress": "Nipissing District, P0H 2A0, Canada",
				"locality": "Nipissing District",
				"postalCode": "P0H 2A0"
			},
			"geometry": {
				"type": "Point",
				"coordinates": [
					-79.5763397216797,
					46.491081237793
				]
			},
			"bbox": [
				-79.5838199941864,
				46.4872185202223,
				-79.568859449173,
				46.4949439553636
			]
		},
		{
			"type": "Feature",
			"properties": {
				"confidence": 7,
				"authenticationResultCode": "ValidCredentials",
				"brandLogoUri": "http://dev.virtualearth.net/Branding/logo_powered_by.png",
				"copyright": "Copyright © 2017 Microsoft and its suppliers. All rights reserved. This API cannot be accessed and the content and any results may not be used, reproduced or transmitted in any manner without express written permission from Microsoft Corporation.",
				"entityType": "Neighborhood",
				"matchCodes": [
					"UpHierarchy"
				],
				"name": "Redbridge, Nipissing District, Ontario, Canada",
				"statusCode": 200,
				"statusDescription": "OK",
				"traceId": "9ff948185b944285b03a8eaa695936dd|BN20280152|7.7.0.0|",
				"adminDistrict": "ON",
				"adminDistrict2": "Nipissing",
				"countryRegion": "Canada",
				"formattedAddress": "Redbridge, Nipissing District, Ontario, Canada",
				"locality": "Nipissing District",
				"neighborhood": "Redbridge"
			},
			"geometry": {
				"type": "Point",
				"coordinates": [
					-79.2363662719727,
					46.4003601074219
				]
			},
			"bbox": [
				-79.2438340990661,
				46.3964973898512,
				-79.2288984448792,
				46.4042228249926
			]
		}
	]
}
