{
	"type": "FeatureCollection",
	"features": [
		{
			"type": "Feature",
			"properties": {
				"confidence": 9,
				"authenticationResultCode": "ValidCredentials",
				"brandLogoUri": "http://dev.virtualearth.net/Branding/logo_powered_by.png",
				"copyright": "Copyright © 2017 Microsoft and its suppliers. All rights reserved. This API cannot be accessed and the content and any results may not be used, reproduced or transmitted in any manner without express written permission from Microsoft Corporation.",
				"entityType": "Address",
				"matchCodes": [
					"Good"
				],
				"name": "5 Hastings St N, Bancroft, ON K0L 1C0, Canada",
				"statusCode": 200,
				"statusDescription": "OK",
				"traceId": "afa3f153826e44ada04309b3c5564e21|BN20130431|7.7.0.0|",
				"addressLine": "5 Hastings St N",
				"adminDistrict": "ON",
				"adminDistrict2": "Hastings",
				"countryRegion": "Canada",
				"formattedAddress": "5 Hastings St N, Bancroft, ON K0L 1C0, Canada",
				"locality": "Bancroft",
				"postalCode": "K0L 1C0"
			},
			"geometry": {
				"type": "Point",
				"coordinates": [
					-77.8531535,
					45.0566157
				]
			},
			"bbox": [
				-77.8547449,
				45.0554915,
				-77.8515622,
				45.0577399
			]
		}
	]
}
