{
	"type": "FeatureCollection",
	"features": [
		{
			"type": "Feature",
			"properties": {
				"confidence": 9,
				"authenticationResultCode": "ValidCredentials",
				"brandLogoUri": "http://dev.virtualearth.net/Branding/logo_powered_by.png",
				"copyright": "Copyright © 2017 Microsoft and its suppliers. All rights reserved. This API cannot be accessed and the content and any results may not be used, reproduced or transmitted in any manner without express written permission from Microsoft Corporation.",
				"entityType": "Address",
				"matchCodes": [
					"Good"
				],
				"name": "5 Rees St, Toronto, ON M5V 3J2, Canada",
				"statusCode": 200,
				"statusDescription": "OK",
				"traceId": "1b7e9e90632443c5ae21894fc885335d|BN20260231|7.7.0.0|",
				"addressLine": "5 Rees St",
				"adminDistrict": "ON",
				"adminDistrict2": "Toronto",
				"countryRegion": "Canada",
				"formattedAddress": "5 Rees St, Toronto, ON M5V 3J2, Canada",
				"locality": "Toronto",
				"neighborhood": "Waterfront Communities-the Island",
				"postalCode": "M5V 3J2"
			},
			"geometry": {
				"type": "Point",
				"coordinates": [
					-79.38652,
					43.63926
				]
			},
			"bbox": [
				-79.3880733,
				43.6381358,
				-79.3849667,
				43.6403842
			]
		}
	]
}
