{
	"type": "FeatureCollection",
	"features": [
		{
			"type": "Feature",
			"properties": {
				"confidence": 9,
				"authenticationResultCode": "ValidCredentials",
				"brandLogoUri": "http://dev.virtualearth.net/Branding/logo_powered_by.png",
				"copyright": "Copyright © 2017 Microsoft and its suppliers. All rights reserved. This API cannot be accessed and the content and any results may not be used, reproduced or transmitted in any manner without express written permission from Microsoft Corporation.",
				"entityType": "Address",
				"matchCodes": [
					"Good"
				],
				"name": "5 Shirley Ave, Kitchener, ON N2B 2E6, Canada",
				"statusCode": 200,
				"statusDescription": "OK",
				"traceId": "77a905514fb64f9385a4906018894c46|BN20250135|7.7.0.0|",
				"addressLine": "5 Shirley Ave",
				"adminDistrict": "ON",
				"adminDistrict2": "Waterloo",
				"countryRegion": "Canada",
				"formattedAddress": "5 Shirley Ave, Kitchener, ON N2B 2E6, Canada",
				"locality": "Kitchener",
				"neighborhood": "Victoria North",
				"postalCode": "N2B 2E6"
			},
			"geometry": {
				"type": "Point",
				"coordinates": [
					-80.46623,
					43.46672
				]
			},
			"bbox": [
				-80.4677789,
				43.4655958,
				-80.4646811,
				43.4678442
			]
		}
	]
}
