{
	"type": "FeatureCollection",
	"features": [
		{
			"type": "Feature",
			"properties": {
				"confidence": 9,
				"authenticationResultCode": "ValidCredentials",
				"brandLogoUri": "http://dev.virtualearth.net/Branding/logo_powered_by.png",
				"copyright": "Copyright © 2017 Microsoft and its suppliers. All rights reserved. This API cannot be accessed and the content and any results may not be used, reproduced or transmitted in any manner without express written permission from Microsoft Corporation.",
				"entityType": "Address",
				"matchCodes": [
					"Good"
				],
				"name": "50 Akerley Blvd, Dartmouth, NS B3B 1R8, Canada",
				"statusCode": 200,
				"statusDescription": "OK",
				"traceId": "808808df8b7b48f6b6685d8c3e7c4495|BN20130447|7.7.0.0|",
				"addressLine": "50 Akerley Blvd",
				"adminDistrict": "NS",
				"adminDistrict2": "Halifax",
				"countryRegion": "Canada",
				"formattedAddress": "50 Akerley Blvd, Dartmouth, NS B3B 1R8, Canada",
				"locality": "Halifax",
				"neighborhood": "Dartmouth",
				"postalCode": "B3B 1R8"
			},
			"geometry": {
				"type": "Point",
				"coordinates": [
					-63.60188,
					44.71026
				]
			},
			"bbox": [
				-63.6034618,
				44.7091358,
				-63.6002982,
				44.7113842
			]
		}
	]
}
