{
	"type": "FeatureCollection",
	"features": [
		{
			"type": "Feature",
			"properties": {
				"confidence": 9,
				"authenticationResultCode": "ValidCredentials",
				"brandLogoUri": "http://dev.virtualearth.net/Branding/logo_powered_by.png",
				"copyright": "Copyright © 2017 Microsoft and its suppliers. All rights reserved. This API cannot be accessed and the content and any results may not be used, reproduced or transmitted in any manner without express written permission from Microsoft Corporation.",
				"entityType": "Address",
				"matchCodes": [
					"Good"
				],
				"name": "50 Casmir Ct, Concord, ON L4K 4J5, Canada",
				"statusCode": 200,
				"statusDescription": "OK",
				"traceId": "e364776d3e0a4753990da0ed55985111|BN20190642|7.7.0.0|",
				"addressLine": "50 Casmir Ct",
				"adminDistrict": "ON",
				"adminDistrict2": "York",
				"countryRegion": "Canada",
				"formattedAddress": "50 Casmir Ct, Concord, ON L4K 4J5, Canada",
				"locality": "Vaughan",
				"neighborhood": "Concord",
				"postalCode": "L4K 4J5"
			},
			"geometry": {
				"type": "Point",
				"coordinates": [
					-79.49015,
					43.82698
				]
			},
			"bbox": [
				-79.4917082,
				43.8258558,
				-79.4885918,
				43.8281042
			]
		}
	]
}
