{
	"type": "FeatureCollection",
	"features": [
		{
			"type": "Feature",
			"properties": {
				"confidence": 9,
				"authenticationResultCode": "ValidCredentials",
				"brandLogoUri": "http://dev.virtualearth.net/Branding/logo_powered_by.png",
				"copyright": "Copyright © 2017 Microsoft and its suppliers. All rights reserved. This API cannot be accessed and the content and any results may not be used, reproduced or transmitted in any manner without express written permission from Microsoft Corporation.",
				"entityType": "Address",
				"matchCodes": [
					"Good"
				],
				"name": "50 Farmcrest Ave, Haliburton, ON K0M 1S0, Canada",
				"statusCode": 200,
				"statusDescription": "OK",
				"traceId": "5bdade5ab81b413ba1398b365cde8380|BN20130520|7.7.0.0|",
				"addressLine": "50 Farmcrest Ave",
				"adminDistrict": "ON",
				"adminDistrict2": "Haliburton",
				"countryRegion": "Canada",
				"formattedAddress": "50 Farmcrest Ave, Haliburton, ON K0M 1S0, Canada",
				"locality": "Dysart",
				"neighborhood": "Haliburton",
				"postalCode": "K0M 1S0"
			},
			"geometry": {
				"type": "Point",
				"coordinates": [
					-78.52858,
					45.04969
				]
			},
			"bbox": [
				-78.5301712,
				45.0485658,
				-78.5269888,
				45.0508142
			]
		}
	]
}
