{
	"type": "FeatureCollection",
	"features": [
		{
			"type": "Feature",
			"properties": {
				"confidence": 9,
				"authenticationResultCode": "ValidCredentials",
				"brandLogoUri": "http://dev.virtualearth.net/Branding/logo_powered_by.png",
				"copyright": "Copyright © 2017 Microsoft and its suppliers. All rights reserved. This API cannot be accessed and the content and any results may not be used, reproduced or transmitted in any manner without express written permission from Microsoft Corporation.",
				"entityType": "Address",
				"matchCodes": [
					"Good"
				],
				"name": "50 Maillard St, Cape Breton, NS B1S 3W3, Canada",
				"statusCode": 200,
				"statusDescription": "OK",
				"traceId": "86f2cabfac8a498ba12a3f493750e383|BN20130533|7.7.0.0|",
				"addressLine": "50 Maillard St",
				"adminDistrict": "NS",
				"adminDistrict2": "Cape Breton",
				"countryRegion": "Canada",
				"formattedAddress": "50 Maillard St, Cape Breton, NS B1S 3W3, Canada",
				"locality": "Cape Breton",
				"neighborhood": "Sydney",
				"postalCode": "B1S 3W3"
			},
			"geometry": {
				"type": "Point",
				"coordinates": [
					-60.19249,
					46.12093
				]
			},
			"bbox": [
				-60.1941118,
				46.1198058,
				-60.1908682,
				46.1220542
			]
		}
	]
}
