{
	"type": "FeatureCollection",
	"features": [
		{
			"type": "Feature",
			"properties": {
				"confidence": 7,
				"authenticationResultCode": "ValidCredentials",
				"brandLogoUri": "http://dev.virtualearth.net/Branding/logo_powered_by.png",
				"copyright": "Copyright © 2017 Microsoft and its suppliers. All rights reserved. This API cannot be accessed and the content and any results may not be used, reproduced or transmitted in any manner without express written permission from Microsoft Corporation.",
				"entityType": "RoadIntersection",
				"matchCodes": [
					"Good"
				],
				"name": "Conception Bay Hwy & Newfound Ln, Bay Roberts, NL A0A, Canada",
				"statusCode": 200,
				"statusDescription": "OK",
				"traceId": "abfb6120493442c685ef18f002072aff|BN20130721|7.7.0.0|",
				"addressLine": "Conception Bay Hwy & Newfound Ln",
				"adminDistrict": "NL",
				"adminDistrict2": "Newfoundland and Labrador",
				"countryRegion": "Canada",
				"formattedAddress": "Conception Bay Hwy & Newfound Ln, Bay Roberts, NL A0A, Canada",
				"locality": "Bay Roberts",
				"postalCode": "A0A 1G0"
			},
			"geometry": {
				"type": "Point",
				"coordinates": [
					-53.28906,
					47.56706
				]
			},
			"bbox": [
				-53.3023887,
				47.5580668,
				-53.2757313,
				47.5760532
			]
		}
	]
}
