{
	"type": "FeatureCollection",
	"features": [
		{
			"type": "Feature",
			"properties": {
				"confidence": 9,
				"authenticationResultCode": "ValidCredentials",
				"brandLogoUri": "http://dev.virtualearth.net/Branding/logo_powered_by.png",
				"copyright": "Copyright © 2017 Microsoft and its suppliers. All rights reserved. This API cannot be accessed and the content and any results may not be used, reproduced or transmitted in any manner without express written permission from Microsoft Corporation.",
				"entityType": "Address",
				"matchCodes": [
					"Good"
				],
				"name": "5008 122A St NW, Edmonton, AB T6H 3S7, Canada",
				"statusCode": 200,
				"statusDescription": "OK",
				"traceId": "2095c4a51356403cb82aa1dba8968c1c|BN20130423|7.7.0.0|",
				"addressLine": "5008 122A St NW",
				"adminDistrict": "AB",
				"adminDistrict2": "Alberta",
				"countryRegion": "Canada",
				"formattedAddress": "5008 122A St NW, Edmonton, AB T6H 3S7, Canada",
				"locality": "Edmonton",
				"neighborhood": "Lansdowne",
				"postalCode": "T6H 3S7"
			},
			"geometry": {
				"type": "Point",
				"coordinates": [
					-113.54254,
					53.48781
				]
			},
			"bbox": [
				-113.5444294,
				53.4866858,
				-113.5406506,
				53.4889342
			]
		}
	]
}
