{
	"type": "FeatureCollection",
	"features": [
		{
			"type": "Feature",
			"properties": {
				"confidence": 9,
				"authenticationResultCode": "ValidCredentials",
				"brandLogoUri": "http://dev.virtualearth.net/Branding/logo_powered_by.png",
				"copyright": "Copyright © 2017 Microsoft and its suppliers. All rights reserved. This API cannot be accessed and the content and any results may not be used, reproduced or transmitted in any manner without express written permission from Microsoft Corporation.",
				"entityType": "Address",
				"matchCodes": [
					"Good"
				],
				"name": "500 Slater Rd NW, Cranbrook, BC V1C 4K5, Canada",
				"statusCode": 200,
				"statusDescription": "OK",
				"traceId": "efa45e6cda5249c8b059bea38435f81c|BN20130522|7.7.0.0|",
				"addressLine": "500 Slater Rd NW",
				"adminDistrict": "BC",
				"adminDistrict2": "East Kootenay",
				"countryRegion": "Canada",
				"formattedAddress": "500 Slater Rd NW, Cranbrook, BC V1C 4K5, Canada",
				"locality": "Cranbrook",
				"postalCode": "V1C 4K5"
			},
			"geometry": {
				"type": "Point",
				"coordinates": [
					-115.76535,
					49.5175399
				]
			},
			"bbox": [
				-115.7670816,
				49.5164157,
				-115.7636184,
				49.5186641
			]
		}
	]
}
