{
	"type": "FeatureCollection",
	"features": [
		{
			"type": "Feature",
			"properties": {
				"confidence": 9,
				"authenticationResultCode": "ValidCredentials",
				"brandLogoUri": "http://dev.virtualearth.net/Branding/logo_powered_by.png",
				"copyright": "Copyright © 2017 Microsoft and its suppliers. All rights reserved. This API cannot be accessed and the content and any results may not be used, reproduced or transmitted in any manner without express written permission from Microsoft Corporation.",
				"entityType": "Address",
				"matchCodes": [
					"Good"
				],
				"name": "502 18A St NW, Calgary, AB T2N 2H2, Canada",
				"statusCode": 200,
				"statusDescription": "OK",
				"traceId": "4af69405307f4f2e853471669e1ca757|BN20130442|7.7.0.0|",
				"addressLine": "502 18A St NW",
				"adminDistrict": "AB",
				"adminDistrict2": "Alberta",
				"countryRegion": "Canada",
				"formattedAddress": "502 18A St NW, Calgary, AB T2N 2H2, Canada",
				"locality": "Calgary",
				"neighborhood": "Hillhurst",
				"postalCode": "T2N 2H2"
			},
			"geometry": {
				"type": "Point",
				"coordinates": [
					-114.10411,
					51.05656
				]
			},
			"bbox": [
				-114.1058985,
				51.0554358,
				-114.1023215,
				51.0576842
			]
		}
	]
}
