{
	"type": "FeatureCollection",
	"features": [
		{
			"type": "Feature",
			"properties": {
				"confidence": 9,
				"authenticationResultCode": "ValidCredentials",
				"brandLogoUri": "http://dev.virtualearth.net/Branding/logo_powered_by.png",
				"copyright": "Copyright © 2017 Microsoft and its suppliers. All rights reserved. This API cannot be accessed and the content and any results may not be used, reproduced or transmitted in any manner without express written permission from Microsoft Corporation.",
				"entityType": "Address",
				"matchCodes": [
					"Good"
				],
				"name": "5022 50 Ave, Vermilion, AB T9X 1A2, Canada",
				"statusCode": 200,
				"statusDescription": "OK",
				"traceId": "f669ede0363d461ea77b8e6c59e35d0b|BN20130521|7.7.0.0|",
				"addressLine": "5022 50 Ave",
				"adminDistrict": "AB",
				"adminDistrict2": "Alberta",
				"countryRegion": "Canada",
				"formattedAddress": "5022 50 Ave, Vermilion, AB T9X 1A2, Canada",
				"locality": "Vermilion",
				"postalCode": "T9X 1A2"
			},
			"geometry": {
				"type": "Point",
				"coordinates": [
					-110.85401,
					53.35423
				]
			},
			"bbox": [
				-110.8558934,
				53.3531058,
				-110.8521266,
				53.3553542
			]
		}
	]
}
