{
	"type": "FeatureCollection",
	"features": [
		{
			"type": "Feature",
			"properties": {
				"confidence": 9,
				"authenticationResultCode": "ValidCredentials",
				"brandLogoUri": "http://dev.virtualearth.net/Branding/logo_powered_by.png",
				"copyright": "Copyright © 2017 Microsoft and its suppliers. All rights reserved. This API cannot be accessed and the content and any results may not be used, reproduced or transmitted in any manner without express written permission from Microsoft Corporation.",
				"entityType": "Address",
				"matchCodes": [
					"Good"
				],
				"name": "5030 13 St SE, Calgary, AB T2G 5M9, Canada",
				"statusCode": 200,
				"statusDescription": "OK",
				"traceId": "8ae2f58e3d494ccf8efac5f0b3e26876|BN20130634|7.7.0.0|",
				"addressLine": "5030 13 St SE",
				"adminDistrict": "AB",
				"adminDistrict2": "Alberta",
				"countryRegion": "Canada",
				"formattedAddress": "5030 13 St SE, Calgary, AB T2G 5M9, Canada",
				"locality": "Calgary",
				"neighborhood": "Alyth-Bonnybrook-Manchester",
				"postalCode": "T2G 5M9"
			},
			"geometry": {
				"type": "Point",
				"coordinates": [
					-114.03228,
					51.00812
				]
			},
			"bbox": [
				-114.0340666,
				51.0069958,
				-114.0304934,
				51.0092442
			]
		}
	]
}
