{
	"type": "FeatureCollection",
	"features": [
		{
			"type": "Feature",
			"properties": {
				"confidence": 9,
				"authenticationResultCode": "ValidCredentials",
				"brandLogoUri": "http://dev.virtualearth.net/Branding/logo_powered_by.png",
				"copyright": "Copyright © 2017 Microsoft and its suppliers. All rights reserved. This API cannot be accessed and the content and any results may not be used, reproduced or transmitted in any manner without express written permission from Microsoft Corporation.",
				"entityType": "Address",
				"matchCodes": [
					"Good"
				],
				"name": "505 Main St S, Airdrie, AB T4B, Canada",
				"statusCode": 200,
				"statusDescription": "OK",
				"traceId": "e28048f246a54188adc7bfc433631c75|BN20171457|7.7.0.0|",
				"addressLine": "505 Main St S",
				"adminDistrict": "AB",
				"adminDistrict2": "Alberta",
				"countryRegion": "Canada",
				"formattedAddress": "505 Main St S, Airdrie, AB T4B, Canada",
				"locality": "Airdrie",
				"postalCode": "T4B 3K3"
			},
			"geometry": {
				"type": "Point",
				"coordinates": [
					-114.0136422,
					51.2879282
				]
			},
			"bbox": [
				-114.0154396,
				51.2868041,
				-114.0118447,
				51.2890524
			]
		}
	]
}
