{
	"type": "FeatureCollection",
	"features": [
		{
			"type": "Feature",
			"properties": {
				"confidence": 9,
				"authenticationResultCode": "ValidCredentials",
				"brandLogoUri": "http://dev.virtualearth.net/Branding/logo_powered_by.png",
				"copyright": "Copyright © 2017 Microsoft and its suppliers. All rights reserved. This API cannot be accessed and the content and any results may not be used, reproduced or transmitted in any manner without express written permission from Microsoft Corporation.",
				"entityType": "Address",
				"matchCodes": [
					"Good"
				],
				"name": "5051 N Service Rd, Burlington, ON L7L 5H6, Canada",
				"statusCode": 200,
				"statusDescription": "OK",
				"traceId": "3f608817e75e45f1a0ad2ef8b729d442|BN20130422|7.7.0.0|",
				"addressLine": "5051 N Service Rd",
				"adminDistrict": "ON",
				"adminDistrict2": "Halton",
				"countryRegion": "Canada",
				"formattedAddress": "5051 N Service Rd, Burlington, ON L7L 5H6, Canada",
				"locality": "Burlington",
				"neighborhood": "Corporate",
				"postalCode": "L7L 5H6"
			},
			"geometry": {
				"type": "Point",
				"coordinates": [
					-79.77065,
					43.3843699
				]
			},
			"bbox": [
				-79.7721968,
				43.3832457,
				-79.7691032,
				43.3854941
			]
		}
	]
}
