{
	"type": "FeatureCollection",
	"features": [
		{
			"type": "Feature",
			"properties": {
				"confidence": 9,
				"authenticationResultCode": "ValidCredentials",
				"brandLogoUri": "http://dev.virtualearth.net/Branding/logo_powered_by.png",
				"copyright": "Copyright © 2017 Microsoft and its suppliers. All rights reserved. This API cannot be accessed and the content and any results may not be used, reproduced or transmitted in any manner without express written permission from Microsoft Corporation.",
				"entityType": "Address",
				"matchCodes": [
					"Good"
				],
				"name": "507 14 Ave, Nisku, AB T9E 7M8, Canada",
				"statusCode": 200,
				"statusDescription": "OK",
				"traceId": "e05616b6a3f44fd0b4de5ab87e74ad28|BN20200239|7.7.0.0|",
				"addressLine": "507 14 Ave",
				"adminDistrict": "AB",
				"adminDistrict2": "Alberta",
				"countryRegion": "Canada",
				"formattedAddress": "507 14 Ave, Nisku, AB T9E 7M8, Canada",
				"locality": "Leduc County",
				"neighborhood": "Nisku",
				"postalCode": "T9E 7M8"
			},
			"geometry": {
				"type": "Point",
				"coordinates": [
					-113.52916,
					53.31679
				]
			},
			"bbox": [
				-113.5310418,
				53.3156658,
				-113.5272782,
				53.3179142
			]
		}
	]
}
