{
	"type": "FeatureCollection",
	"features": [
		{
			"type": "Feature",
			"properties": {
				"confidence": 9,
				"authenticationResultCode": "ValidCredentials",
				"brandLogoUri": "http://dev.virtualearth.net/Branding/logo_powered_by.png",
				"copyright": "Copyright © 2017 Microsoft and its suppliers. All rights reserved. This API cannot be accessed and the content and any results may not be used, reproduced or transmitted in any manner without express written permission from Microsoft Corporation.",
				"entityType": "Address",
				"matchCodes": [
					"Good"
				],
				"name": "5085 Rue Rideau, Quebec, QC G2E 5H5, Canada",
				"statusCode": 200,
				"statusDescription": "OK",
				"traceId": "48429b23863c42dcb42c0a26ee0acea4|BN20190653|7.7.0.0|",
				"addressLine": "5085 Rue Rideau",
				"adminDistrict": "QC",
				"adminDistrict2": "Quebec",
				"countryRegion": "Canada",
				"formattedAddress": "5085 Rue Rideau, Quebec, QC G2E 5H5, Canada",
				"locality": "Quebec",
				"neighborhood": "Duberger-les Saules",
				"postalCode": "G2E 5H5"
			},
			"geometry": {
				"type": "Point",
				"coordinates": [
					-71.32547,
					46.79694
				]
			},
			"bbox": [
				-71.3271121,
				46.7958158,
				-71.3238279,
				46.7980642
			]
		}
	]
}
