{
	"type": "FeatureCollection",
	"features": [
		{
			"type": "Feature",
			"properties": {
				"confidence": 9,
				"authenticationResultCode": "ValidCredentials",
				"brandLogoUri": "http://dev.virtualearth.net/Branding/logo_powered_by.png",
				"copyright": "Copyright © 2017 Microsoft and its suppliers. All rights reserved. This API cannot be accessed and the content and any results may not be used, reproduced or transmitted in any manner without express written permission from Microsoft Corporation.",
				"entityType": "Address",
				"matchCodes": [
					"Good"
				],
				"name": "5085 Regent St, Burnaby, BC V5C 4H4, Canada",
				"statusCode": 200,
				"statusDescription": "OK",
				"traceId": "aa4e673306864304aa386d859719cad1|BN20130719|7.7.0.0|",
				"addressLine": "5085 Regent St",
				"adminDistrict": "BC",
				"adminDistrict2": "Greater Vancouver",
				"countryRegion": "Canada",
				"formattedAddress": "5085 Regent St, Burnaby, BC V5C 4H4, Canada",
				"locality": "Burnaby",
				"neighborhood": "Dawson-Delta",
				"postalCode": "V5C 4H4"
			},
			"geometry": {
				"type": "Point",
				"coordinates": [
					-122.9894857,
					49.2585133
				]
			},
			"bbox": [
				-122.9912082,
				49.2573892,
				-122.9877633,
				49.2596375
			]
		}
	]
}
