{
	"type": "FeatureCollection",
	"features": [
		{
			"type": "Feature",
			"properties": {
				"confidence": 9,
				"authenticationResultCode": "ValidCredentials",
				"brandLogoUri": "http://dev.virtualearth.net/Branding/logo_powered_by.png",
				"copyright": "Copyright © 2017 Microsoft and its suppliers. All rights reserved. This API cannot be accessed and the content and any results may not be used, reproduced or transmitted in any manner without express written permission from Microsoft Corporation.",
				"entityType": "Address",
				"matchCodes": [
					"Good"
				],
				"name": "509 Government St, Dryden, ON P8N 2P6, Canada",
				"statusCode": 200,
				"statusDescription": "OK",
				"traceId": "45ecbe2ae41544fca31952b3b22fb0ad|BN20181720|7.7.0.0|",
				"addressLine": "509 Government St",
				"adminDistrict": "ON",
				"adminDistrict2": "Kenora",
				"countryRegion": "Canada",
				"formattedAddress": "509 Government St, Dryden, ON P8N 2P6, Canada",
				"locality": "Dryden",
				"postalCode": "P8N 2P6"
			},
			"geometry": {
				"type": "Point",
				"coordinates": [
					-92.82438,
					49.7863049
				]
			},
			"bbox": [
				-92.8261211,
				49.7851807,
				-92.8226388,
				49.7874291
			]
		}
	]
}
