{
	"type": "FeatureCollection",
	"features": [
		{
			"type": "Feature",
			"properties": {
				"confidence": 9,
				"authenticationResultCode": "ValidCredentials",
				"brandLogoUri": "http://dev.virtualearth.net/Branding/logo_powered_by.png",
				"copyright": "Copyright © 2017 Microsoft and its suppliers. All rights reserved. This API cannot be accessed and the content and any results may not be used, reproduced or transmitted in any manner without express written permission from Microsoft Corporation.",
				"entityType": "Address",
				"matchCodes": [
					"Good"
				],
				"name": "5100 Silver Star Rd, Vernon, BC V1B 3K4, Canada",
				"statusCode": 200,
				"statusDescription": "OK",
				"traceId": "77910c3244be4ff194b94f196617ccf6|BN20220145|7.7.0.0|",
				"addressLine": "5100 Silver Star Rd",
				"adminDistrict": "BC",
				"adminDistrict2": "North Okanagan",
				"countryRegion": "Canada",
				"formattedAddress": "5100 Silver Star Rd, Vernon, BC V1B 3K4, Canada",
				"locality": "Vernon",
				"postalCode": "V1B 3K4"
			},
			"geometry": {
				"type": "Point",
				"coordinates": [
					-119.24587,
					50.2812399
				]
			},
			"bbox": [
				-119.2476292,
				50.2801157,
				-119.2441108,
				50.2823641
			]
		}
	]
}
