{
	"type": "FeatureCollection",
	"features": [
		{
			"type": "Feature",
			"properties": {
				"confidence": 9,
				"authenticationResultCode": "ValidCredentials",
				"brandLogoUri": "http://dev.virtualearth.net/Branding/logo_powered_by.png",
				"copyright": "Copyright © 2017 Microsoft and its suppliers. All rights reserved. This API cannot be accessed and the content and any results may not be used, reproduced or transmitted in any manner without express written permission from Microsoft Corporation.",
				"entityType": "Address",
				"matchCodes": [
					"Good"
				],
				"name": "5109 48th St, Yellowknife, NT X1A 1N5, Canada",
				"statusCode": 200,
				"statusDescription": "OK",
				"traceId": "aa46afa371ce4599b13c1a780338c90c|BN20190653|7.7.0.0|",
				"addressLine": "5109 48th St",
				"adminDistrict": "NT",
				"adminDistrict2": "Northwest Territories",
				"countryRegion": "Canada",
				"formattedAddress": "5109 48th St, Yellowknife, NT X1A 1N5, Canada",
				"locality": "Yellowknife",
				"postalCode": "X1A 1N5"
			},
			"geometry": {
				"type": "Point",
				"coordinates": [
					-114.36542,
					62.45358
				]
			},
			"bbox": [
				-114.3678508,
				62.4524558,
				-114.3629892,
				62.4547042
			]
		}
	]
}
