{
	"type": "FeatureCollection",
	"features": [
		{
			"type": "Feature",
			"properties": {
				"confidence": 7,
				"authenticationResultCode": "ValidCredentials",
				"brandLogoUri": "http://dev.virtualearth.net/Branding/logo_powered_by.png",
				"copyright": "Copyright © 2017 Microsoft and its suppliers. All rights reserved. This API cannot be accessed and the content and any results may not be used, reproduced or transmitted in any manner without express written permission from Microsoft Corporation.",
				"entityType": "Postcode1",
				"matchCodes": [
					"UpHierarchy"
				],
				"name": "Uxbridge, L9P 1N1, Canada",
				"statusCode": 200,
				"statusDescription": "OK",
				"traceId": "c768a0b1c21a4ea28016fb9e817d2b62|BN20220145|7.7.0.0|",
				"adminDistrict": "ON",
				"adminDistrict2": "Durham",
				"countryRegion": "Canada",
				"formattedAddress": "Uxbridge, L9P 1N1, Canada",
				"locality": "Uxbridge",
				"postalCode": "L9P 1N1"
			},
			"geometry": {
				"type": "Point",
				"coordinates": [
					-79.1238632202148,
					44.1061592102051
				]
			},
			"bbox": [
				-79.131035343248,
				44.1022964926344,
				-79.1166910971817,
				44.1100219277758
			]
		}
	]
}
