{
	"type": "FeatureCollection",
	"features": [
		{
			"type": "Feature",
			"properties": {
				"confidence": 9,
				"authenticationResultCode": "ValidCredentials",
				"brandLogoUri": "http://dev.virtualearth.net/Branding/logo_powered_by.png",
				"copyright": "Copyright © 2017 Microsoft and its suppliers. All rights reserved. This API cannot be accessed and the content and any results may not be used, reproduced or transmitted in any manner without express written permission from Microsoft Corporation.",
				"entityType": "Address",
				"matchCodes": [
					"Good"
				],
				"name": "515 Park Rd N, Brantford, ON N3R 7K8, Canada",
				"statusCode": 200,
				"statusDescription": "OK",
				"traceId": "481c393d416145beabec549ef2b247c8|BN20240253|7.7.0.0|",
				"addressLine": "515 Park Rd N",
				"adminDistrict": "ON",
				"adminDistrict2": "Brant",
				"countryRegion": "Canada",
				"formattedAddress": "515 Park Rd N, Brantford, ON N3R 7K8, Canada",
				"locality": "Brantford",
				"postalCode": "N3R 7K8"
			},
			"geometry": {
				"type": "Point",
				"coordinates": [
					-80.2488599,
					43.18216
				]
			},
			"bbox": [
				-80.2504016,
				43.1810358,
				-80.2473182,
				43.1832842
			]
		}
	]
}
