{
	"type": "FeatureCollection",
	"features": [
		{
			"type": "Feature",
			"properties": {
				"confidence": 9,
				"authenticationResultCode": "ValidCredentials",
				"brandLogoUri": "http://dev.virtualearth.net/Branding/logo_powered_by.png",
				"copyright": "Copyright © 2017 Microsoft and its suppliers. All rights reserved. This API cannot be accessed and the content and any results may not be used, reproduced or transmitted in any manner without express written permission from Microsoft Corporation.",
				"entityType": "Address",
				"matchCodes": [
					"Good"
				],
				"name": "516 Old HWY-2, Trenton, ON K8V 5P5, Canada",
				"statusCode": 200,
				"statusDescription": "OK",
				"traceId": "64c710eff1e34694919c1e88a3d896ea|BN20130620|7.7.0.0|",
				"addressLine": "516 Old HWY-2",
				"adminDistrict": "ON",
				"adminDistrict2": "Hastings",
				"countryRegion": "Canada",
				"formattedAddress": "516 Old HWY-2, Trenton, ON K8V 5P5, Canada",
				"locality": "Quinte West",
				"neighborhood": "Trenton",
				"postalCode": "K8V 5P5"
			},
			"geometry": {
				"type": "Point",
				"coordinates": [
					-77.5166372,
					44.1135771
				]
			},
			"bbox": [
				-77.518203,
				44.1124529,
				-77.5150714,
				44.1147012
			]
		}
	]
}
