{
	"type": "FeatureCollection",
	"features": [
		{
			"type": "Feature",
			"properties": {
				"confidence": 9,
				"authenticationResultCode": "ValidCredentials",
				"brandLogoUri": "http://dev.virtualearth.net/Branding/logo_powered_by.png",
				"copyright": "Copyright © 2017 Microsoft and its suppliers. All rights reserved. This API cannot be accessed and the content and any results may not be used, reproduced or transmitted in any manner without express written permission from Microsoft Corporation.",
				"entityType": "Address",
				"matchCodes": [
					"Good"
				],
				"name": "517 Basaltic Rd, Concord, ON L4K 4W8, Canada",
				"statusCode": 200,
				"statusDescription": "OK",
				"traceId": "3710b7692c014bc995f5b382c9639248|BN20290118|7.7.0.0|",
				"addressLine": "517 Basaltic Rd",
				"adminDistrict": "ON",
				"adminDistrict2": "York",
				"countryRegion": "Canada",
				"formattedAddress": "517 Basaltic Rd, Concord, ON L4K 4W8, Canada",
				"locality": "Vaughan",
				"neighborhood": "Concord",
				"postalCode": "L4K 4W8"
			},
			"geometry": {
				"type": "Point",
				"coordinates": [
					-79.49833,
					43.83294
				]
			},
			"bbox": [
				-79.4998884,
				43.8318158,
				-79.4967716,
				43.8340642
			]
		}
	]
}
