{
	"type": "FeatureCollection",
	"features": [
		{
			"type": "Feature",
			"properties": {
				"confidence": 9,
				"authenticationResultCode": "ValidCredentials",
				"brandLogoUri": "http://dev.virtualearth.net/Branding/logo_powered_by.png",
				"copyright": "Copyright © 2017 Microsoft and its suppliers. All rights reserved. This API cannot be accessed and the content and any results may not be used, reproduced or transmitted in any manner without express written permission from Microsoft Corporation.",
				"entityType": "Address",
				"matchCodes": [
					"Good"
				],
				"name": "52 Alsek Rd, Whitehorse, YT Y1A 3K4, Canada",
				"statusCode": 200,
				"statusDescription": "OK",
				"traceId": "ad3fecf1c9eb46dc93e2f51914cb963f|BN20130719|7.7.0.0|",
				"addressLine": "52 Alsek Rd",
				"adminDistrict": "YT",
				"adminDistrict2": "Yukon",
				"countryRegion": "Canada",
				"formattedAddress": "52 Alsek Rd, Whitehorse, YT Y1A 3K4, Canada",
				"locality": "Whitehorse",
				"postalCode": "Y1A 3K4"
			},
			"geometry": {
				"type": "Point",
				"coordinates": [
					-135.0226,
					60.7107
				]
			},
			"bbox": [
				-135.0248978,
				60.7095758,
				-135.0203022,
				60.7118242
			]
		}
	]
}
