{
	"type": "FeatureCollection",
	"features": [
		{
			"type": "Feature",
			"properties": {
				"confidence": 9,
				"authenticationResultCode": "ValidCredentials",
				"brandLogoUri": "http://dev.virtualearth.net/Branding/logo_powered_by.png",
				"copyright": "Copyright © 2017 Microsoft and its suppliers. All rights reserved. This API cannot be accessed and the content and any results may not be used, reproduced or transmitted in any manner without express written permission from Microsoft Corporation.",
				"entityType": "Address",
				"matchCodes": [
					"Good"
				],
				"name": "52 E Lake Ave NE, Airdrie, AB T4A 2G8, Canada",
				"statusCode": 200,
				"statusDescription": "OK",
				"traceId": "4a8f8163b89d467dbff699fa979da144|BN20130422|7.7.0.0|",
				"addressLine": "52 E Lake Ave NE",
				"adminDistrict": "AB",
				"adminDistrict2": "Alberta",
				"countryRegion": "Canada",
				"formattedAddress": "52 E Lake Ave NE, Airdrie, AB T4A 2G8, Canada",
				"locality": "Airdrie",
				"postalCode": "T4A 2G8"
			},
			"geometry": {
				"type": "Point",
				"coordinates": [
					-113.99656,
					51.29601
				]
			},
			"bbox": [
				-113.9983578,
				51.2948858,
				-113.9947622,
				51.2971342
			]
		}
	]
}
