{
	"type": "FeatureCollection",
	"features": [
		{
			"type": "Feature",
			"properties": {
				"confidence": 9,
				"authenticationResultCode": "ValidCredentials",
				"brandLogoUri": "http://dev.virtualearth.net/Branding/logo_powered_by.png",
				"copyright": "Copyright © 2017 Microsoft and its suppliers. All rights reserved. This API cannot be accessed and the content and any results may not be used, reproduced or transmitted in any manner without express written permission from Microsoft Corporation.",
				"entityType": "Address",
				"matchCodes": [
					"Good"
				],
				"name": "520 Clarke Rd, London, ON N5V 2C7, Canada",
				"statusCode": 200,
				"statusDescription": "OK",
				"traceId": "3a4d89171f044912a50a02d7a6baa000|CO30275740|7.7.0.0|",
				"addressLine": "520 Clarke Rd",
				"adminDistrict": "ON",
				"adminDistrict2": "Middlesex",
				"countryRegion": "Canada",
				"formattedAddress": "520 Clarke Rd, London, ON N5V 2C7, Canada",
				"locality": "London",
				"neighborhood": "Airport",
				"postalCode": "N5V 2C7"
			},
			"geometry": {
				"type": "Point",
				"coordinates": [
					-81.1774,
					43.0092
				]
			},
			"bbox": [
				-81.1789373,
				43.0080758,
				-81.1758627,
				43.0103242
			]
		}
	]
}
