{
	"type": "FeatureCollection",
	"features": [
		{
			"type": "Feature",
			"properties": {
				"confidence": 9,
				"authenticationResultCode": "ValidCredentials",
				"brandLogoUri": "http://dev.virtualearth.net/Branding/logo_powered_by.png",
				"copyright": "Copyright © 2017 Microsoft and its suppliers. All rights reserved. This API cannot be accessed and the content and any results may not be used, reproduced or transmitted in any manner without express written permission from Microsoft Corporation.",
				"entityType": "Address",
				"matchCodes": [
					"Good"
				],
				"name": "5212 50 St, Mundare, AB T0B, Canada",
				"statusCode": 200,
				"statusDescription": "OK",
				"traceId": "7447c43894d04f3bb2dbca34001d42ed|BN20240423|7.7.0.0|",
				"addressLine": "5212 50 St",
				"adminDistrict": "AB",
				"adminDistrict2": "Alberta",
				"countryRegion": "Canada",
				"formattedAddress": "5212 50 St, Mundare, AB T0B, Canada",
				"locality": "Mundare",
				"postalCode": "T0B 3H0"
			},
			"geometry": {
				"type": "Point",
				"coordinates": [
					-112.33877,
					53.5944999
				]
			},
			"bbox": [
				-112.3406641,
				53.5933757,
				-112.3368759,
				53.5956241
			]
		}
	]
}
