{
	"type": "FeatureCollection",
	"features": [
		{
			"type": "Feature",
			"properties": {
				"confidence": 9,
				"authenticationResultCode": "ValidCredentials",
				"brandLogoUri": "http://dev.virtualearth.net/Branding/logo_powered_by.png",
				"copyright": "Copyright © 2017 Microsoft and its suppliers. All rights reserved. This API cannot be accessed and the content and any results may not be used, reproduced or transmitted in any manner without express written permission from Microsoft Corporation.",
				"entityType": "Address",
				"matchCodes": [
					"Good"
				],
				"name": "529 Annance Ct, Delta, BC V3M 6Y7, Canada",
				"statusCode": 200,
				"statusDescription": "OK",
				"traceId": "5da2e638ec09452594eba3d23f9602a4|BN20171457|7.7.0.0|",
				"addressLine": "529 Annance Ct",
				"adminDistrict": "BC",
				"adminDistrict2": "Greater Vancouver",
				"countryRegion": "Canada",
				"formattedAddress": "529 Annance Ct, Delta, BC V3M 6Y7, Canada",
				"locality": "Delta",
				"postalCode": "V3M 6Y7"
			},
			"geometry": {
				"type": "Point",
				"coordinates": [
					-122.94068,
					49.16975
				]
			},
			"bbox": [
				-122.9423994,
				49.1686258,
				-122.9389606,
				49.1708742
			]
		}
	]
}
