{
	"type": "FeatureCollection",
	"features": [
		{
			"type": "Feature",
			"properties": {
				"confidence": 9,
				"authenticationResultCode": "ValidCredentials",
				"brandLogoUri": "http://dev.virtualearth.net/Branding/logo_powered_by.png",
				"copyright": "Copyright © 2017 Microsoft and its suppliers. All rights reserved. This API cannot be accessed and the content and any results may not be used, reproduced or transmitted in any manner without express written permission from Microsoft Corporation.",
				"entityType": "Address",
				"matchCodes": [
					"Good"
				],
				"name": "53 MacKenzie Rd, Inuvik, NT X0E, Canada",
				"statusCode": 200,
				"statusDescription": "OK",
				"traceId": "30e81981fed04f359ac730db8cce5eba|BN20130631|7.7.0.0|",
				"addressLine": "53 MacKenzie Rd",
				"adminDistrict": "NT",
				"adminDistrict2": "Northwest Territories",
				"countryRegion": "Canada",
				"formattedAddress": "53 MacKenzie Rd, Inuvik, NT X0E, Canada",
				"locality": "Inuvik",
				"postalCode": "X0E 0T0"
			},
			"geometry": {
				"type": "Point",
				"coordinates": [
					-133.7340701,
					68.360369
				]
			},
			"bbox": [
				-133.7371185,
				68.3592448,
				-133.7310217,
				68.3614931
			]
		}
	]
}
