{
	"type": "FeatureCollection",
	"features": [
		{
			"type": "Feature",
			"properties": {
				"confidence": 9,
				"authenticationResultCode": "ValidCredentials",
				"brandLogoUri": "http://dev.virtualearth.net/Branding/logo_powered_by.png",
				"copyright": "Copyright © 2017 Microsoft and its suppliers. All rights reserved. This API cannot be accessed and the content and any results may not be used, reproduced or transmitted in any manner without express written permission from Microsoft Corporation.",
				"entityType": "Address",
				"matchCodes": [
					"Good"
				],
				"name": "53021 Range Road 270, Spruce Grove, AB T7X 3L4, Canada",
				"statusCode": 200,
				"statusDescription": "OK",
				"traceId": "ad0235472a63489cbcf1b380eca416c4|BN20130530|7.7.0.0|",
				"addressLine": "53021 Range Road 270",
				"adminDistrict": "AB",
				"adminDistrict2": "Alberta",
				"countryRegion": "Canada",
				"formattedAddress": "53021 Range Road 270, Spruce Grove, AB T7X 3L4, Canada",
				"locality": "Parkland County",
				"neighborhood": "Spruce Grove",
				"postalCode": "T7X 3L4"
			},
			"geometry": {
				"type": "Point",
				"coordinates": [
					-113.8427765,
					53.5454758
				]
			},
			"bbox": [
				-113.8446684,
				53.5443516,
				-113.8408845,
				53.5465999
			]
		}
	]
}
