{
	"type": "FeatureCollection",
	"features": [
		{
			"type": "Feature",
			"properties": {
				"confidence": 9,
				"authenticationResultCode": "ValidCredentials",
				"brandLogoUri": "http://dev.virtualearth.net/Branding/logo_powered_by.png",
				"copyright": "Copyright © 2017 Microsoft and its suppliers. All rights reserved. This API cannot be accessed and the content and any results may not be used, reproduced or transmitted in any manner without express written permission from Microsoft Corporation.",
				"entityType": "Address",
				"matchCodes": [
					"Good"
				],
				"name": "5317 10th Line W, Mississauga, ON L5M, Canada",
				"statusCode": 200,
				"statusDescription": "OK",
				"traceId": "09f8c7b608ed4b398dd16fb22cb1d6a5|BN20250135|7.7.0.0|",
				"addressLine": "5317 10th Line W",
				"adminDistrict": "ON",
				"adminDistrict2": "Peel",
				"countryRegion": "Canada",
				"formattedAddress": "5317 10th Line W, Mississauga, ON L5M, Canada",
				"locality": "Mississauga",
				"neighborhood": "Erin Mills",
				"postalCode": "L5M 0V8"
			},
			"geometry": {
				"type": "Point",
				"coordinates": [
					-79.7335623,
					43.553049
				]
			},
			"bbox": [
				-79.7351134,
				43.5519249,
				-79.7320112,
				43.5541732
			]
		}
	]
}
