{
	"type": "FeatureCollection",
	"features": [
		{
			"type": "Feature",
			"properties": {
				"confidence": 9,
				"authenticationResultCode": "ValidCredentials",
				"brandLogoUri": "http://dev.virtualearth.net/Branding/logo_powered_by.png",
				"copyright": "Copyright © 2017 Microsoft and its suppliers. All rights reserved. This API cannot be accessed and the content and any results may not be used, reproduced or transmitted in any manner without express written permission from Microsoft Corporation.",
				"entityType": "Address",
				"matchCodes": [
					"Good"
				],
				"name": "5359 Canotek Rd, Gloucester, ON K1J 9E5, Canada",
				"statusCode": 200,
				"statusDescription": "OK",
				"traceId": "88a726cca7d04f308d8eea9ad5430d04|BN20130422|7.7.0.0|",
				"addressLine": "5359 Canotek Rd",
				"adminDistrict": "ON",
				"adminDistrict2": "Ottawa",
				"countryRegion": "Canada",
				"formattedAddress": "5359 Canotek Rd, Gloucester, ON K1J 9E5, Canada",
				"locality": "Ottawa",
				"neighborhood": "Gloucester",
				"postalCode": "K1J 9E5"
			},
			"geometry": {
				"type": "Point",
				"coordinates": [
					-75.58437,
					45.45519
				]
			},
			"bbox": [
				-75.5859726,
				45.4540658,
				-75.5827674,
				45.4563142
			]
		}
	]
}
