{
	"type": "FeatureCollection",
	"features": [
		{
			"type": "Feature",
			"properties": {
				"confidence": 9,
				"authenticationResultCode": "ValidCredentials",
				"brandLogoUri": "http://dev.virtualearth.net/Branding/logo_powered_by.png",
				"copyright": "Copyright © 2017 Microsoft and its suppliers. All rights reserved. This API cannot be accessed and the content and any results may not be used, reproduced or transmitted in any manner without express written permission from Microsoft Corporation.",
				"entityType": "Address",
				"matchCodes": [
					"Good"
				],
				"name": "5370 S Service Rd, Burlington, ON L7L 5L1, Canada",
				"statusCode": 200,
				"statusDescription": "OK",
				"traceId": "6526387b5cf4461784683685d9d11cce|BN20130520|7.7.0.0|",
				"addressLine": "5370 S Service Rd",
				"adminDistrict": "ON",
				"adminDistrict2": "Halton",
				"countryRegion": "Canada",
				"formattedAddress": "5370 S Service Rd, Burlington, ON L7L 5L1, Canada",
				"locality": "Burlington",
				"neighborhood": "Pinedale",
				"postalCode": "L7L 5L1"
			},
			"geometry": {
				"type": "Point",
				"coordinates": [
					-79.75925,
					43.39061
				]
			},
			"bbox": [
				-79.760797,
				43.3894858,
				-79.757703,
				43.3917342
			]
		}
	]
}
