{
	"type": "FeatureCollection",
	"features": [
		{
			"type": "Feature",
			"properties": {
				"confidence": 9,
				"authenticationResultCode": "ValidCredentials",
				"brandLogoUri": "http://dev.virtualearth.net/Branding/logo_powered_by.png",
				"copyright": "Copyright © 2017 Microsoft and its suppliers. All rights reserved. This API cannot be accessed and the content and any results may not be used, reproduced or transmitted in any manner without express written permission from Microsoft Corporation.",
				"entityType": "Address",
				"matchCodes": [
					"Good"
				],
				"name": "5383 Spumante St, Mississauga, ON L5M 4Z3, Canada",
				"statusCode": 200,
				"statusDescription": "OK",
				"traceId": "12395beaa523451a80ddf87159d174a1|BN20130532|7.7.0.0|",
				"addressLine": "5383 Spumante St",
				"adminDistrict": "ON",
				"adminDistrict2": "Peel",
				"countryRegion": "Canada",
				"formattedAddress": "5383 Spumante St, Mississauga, ON L5M 4Z3, Canada",
				"locality": "Mississauga",
				"neighborhood": "Streetsville",
				"postalCode": "L5M 4Z3"
			},
			"geometry": {
				"type": "Point",
				"coordinates": [
					-79.69756,
					43.5834
				]
			},
			"bbox": [
				-79.6991119,
				43.5822758,
				-79.6960081,
				43.5845242
			]
		}
	]
}
