{
	"type": "FeatureCollection",
	"features": [
		{
			"type": "Feature",
			"properties": {
				"confidence": 9,
				"authenticationResultCode": "ValidCredentials",
				"brandLogoUri": "http://dev.virtualearth.net/Branding/logo_powered_by.png",
				"copyright": "Copyright © 2017 Microsoft and its suppliers. All rights reserved. This API cannot be accessed and the content and any results may not be used, reproduced or transmitted in any manner without express written permission from Microsoft Corporation.",
				"entityType": "Address",
				"matchCodes": [
					"Good"
				],
				"name": "540 Ski Hill Rd, Pakenham, ON K0A 2X0, Canada",
				"statusCode": 200,
				"statusDescription": "OK",
				"traceId": "c54aa403312945618fb064a36c4c0174|BN20200137|7.7.0.0|",
				"addressLine": "540 Ski Hill Rd",
				"adminDistrict": "ON",
				"adminDistrict2": "Lanark",
				"countryRegion": "Canada",
				"formattedAddress": "540 Ski Hill Rd, Pakenham, ON K0A 2X0, Canada",
				"locality": "Mississippi Mills",
				"neighborhood": "Pakenham",
				"postalCode": "K0A 2X0"
			},
			"geometry": {
				"type": "Point",
				"coordinates": [
					-76.3262319,
					45.3235426
				]
			},
			"bbox": [
				-76.3278307,
				45.3224184,
				-76.3246331,
				45.3246667
			]
		}
	]
}
