{
	"type": "FeatureCollection",
	"features": [
		{
			"type": "Feature",
			"properties": {
				"confidence": 9,
				"authenticationResultCode": "ValidCredentials",
				"brandLogoUri": "http://dev.virtualearth.net/Branding/logo_powered_by.png",
				"copyright": "Copyright © 2017 Microsoft and its suppliers. All rights reserved. This API cannot be accessed and the content and any results may not be used, reproduced or transmitted in any manner without express written permission from Microsoft Corporation.",
				"entityType": "Address",
				"matchCodes": [
					"Good"
				],
				"name": "5420 53 Ave SE, Calgary, AB T2C 4R3, Canada",
				"statusCode": 200,
				"statusDescription": "OK",
				"traceId": "a149aae421404b379ca7e1fe09b7ab1c|BN20190642|7.7.0.0|",
				"addressLine": "5420 53 Ave SE",
				"adminDistrict": "AB",
				"adminDistrict2": "Alberta",
				"countryRegion": "Canada",
				"formattedAddress": "5420 53 Ave SE, Calgary, AB T2C 4R3, Canada",
				"locality": "Calgary",
				"postalCode": "T2C 4R3"
			},
			"geometry": {
				"type": "Point",
				"coordinates": [
					-113.95641,
					51.0053399
				]
			},
			"bbox": [
				-113.9581965,
				51.0042157,
				-113.9546235,
				51.0064641
			]
		}
	]
}
