{
	"type": "FeatureCollection",
	"features": [
		{
			"type": "Feature",
			"properties": {
				"confidence": 9,
				"authenticationResultCode": "ValidCredentials",
				"brandLogoUri": "http://dev.virtualearth.net/Branding/logo_powered_by.png",
				"copyright": "Copyright © 2017 Microsoft and its suppliers. All rights reserved. This API cannot be accessed and the content and any results may not be used, reproduced or transmitted in any manner without express written permission from Microsoft Corporation.",
				"entityType": "Address",
				"matchCodes": [
					"Good"
				],
				"name": "5428 Kindos St, Burlington, ON L7L 7M9, Canada",
				"statusCode": 200,
				"statusDescription": "OK",
				"traceId": "bcf9bd86f96b405ebb5e5822c2377593|BN20130634|7.7.0.0|",
				"addressLine": "5428 Kindos St",
				"adminDistrict": "ON",
				"adminDistrict2": "Halton",
				"countryRegion": "Canada",
				"formattedAddress": "5428 Kindos St, Burlington, ON L7L 7M9, Canada",
				"locality": "Burlington",
				"neighborhood": "Orchard",
				"postalCode": "L7L 7M9"
			},
			"geometry": {
				"type": "Point",
				"coordinates": [
					-79.79539,
					43.41026
				]
			},
			"bbox": [
				-79.7969375,
				43.4091358,
				-79.7938425,
				43.4113842
			]
		}
	]
}
