{
	"type": "FeatureCollection",
	"features": [
		{
			"type": "Feature",
			"properties": {
				"confidence": 9,
				"authenticationResultCode": "ValidCredentials",
				"brandLogoUri": "http://dev.virtualearth.net/Branding/logo_powered_by.png",
				"copyright": "Copyright © 2017 Microsoft and its suppliers. All rights reserved. This API cannot be accessed and the content and any results may not be used, reproduced or transmitted in any manner without express written permission from Microsoft Corporation.",
				"entityType": "Address",
				"matchCodes": [
					"Good"
				],
				"name": "547 Avenue Meloche, Dorval, QC H9P 2W2, Canada",
				"statusCode": 200,
				"statusDescription": "OK",
				"traceId": "afa05f40039f44429ae804be71a2deaa|BN20130719|7.7.0.0|",
				"addressLine": "547 Avenue Meloche",
				"adminDistrict": "QC",
				"adminDistrict2": "Montreal",
				"countryRegion": "Canada",
				"formattedAddress": "547 Avenue Meloche, Dorval, QC H9P 2W2, Canada",
				"locality": "Dorval",
				"postalCode": "H9P 2W2"
			},
			"geometry": {
				"type": "Point",
				"coordinates": [
					-73.72538,
					45.45145
				]
			},
			"bbox": [
				-73.7269825,
				45.4503258,
				-73.7237775,
				45.4525742
			]
		}
	]
}
