{
	"type": "FeatureCollection",
	"features": [
		{
			"type": "Feature",
			"properties": {
				"confidence": 9,
				"authenticationResultCode": "ValidCredentials",
				"brandLogoUri": "http://dev.virtualearth.net/Branding/logo_powered_by.png",
				"copyright": "Copyright © 2017 Microsoft and its suppliers. All rights reserved. This API cannot be accessed and the content and any results may not be used, reproduced or transmitted in any manner without express written permission from Microsoft Corporation.",
				"entityType": "Address",
				"matchCodes": [
					"Good"
				],
				"name": "5482 Landsborough Ave, Mississauga, ON L5R 3X1, Canada",
				"statusCode": 200,
				"statusDescription": "OK",
				"traceId": "bad047e83eab445aa5f0037dd9a5d41c|BN20130520|7.7.0.0|",
				"addressLine": "5482 Landsborough Ave",
				"adminDistrict": "ON",
				"adminDistrict2": "Peel",
				"countryRegion": "Canada",
				"formattedAddress": "5482 Landsborough Ave, Mississauga, ON L5R 3X1, Canada",
				"locality": "Mississauga",
				"postalCode": "L5R 3X1"
			},
			"geometry": {
				"type": "Point",
				"coordinates": [
					-79.68325,
					43.60213
				]
			},
			"bbox": [
				-79.6848024,
				43.6010058,
				-79.6816976,
				43.6032542
			]
		}
	]
}
