{
	"type": "FeatureCollection",
	"features": [
		{
			"type": "Feature",
			"properties": {
				"confidence": 9,
				"authenticationResultCode": "ValidCredentials",
				"brandLogoUri": "http://dev.virtualearth.net/Branding/logo_powered_by.png",
				"copyright": "Copyright © 2017 Microsoft and its suppliers. All rights reserved. This API cannot be accessed and the content and any results may not be used, reproduced or transmitted in any manner without express written permission from Microsoft Corporation.",
				"entityType": "Address",
				"matchCodes": [
					"Good"
				],
				"name": "55 10 Ave SE, High River, AB T1V 1E6, Canada",
				"statusCode": 200,
				"statusDescription": "OK",
				"traceId": "bcb3b17b831342d696ce27173b5c86ce|BN20260231|7.7.0.0|",
				"addressLine": "55 10 Ave SE",
				"adminDistrict": "AB",
				"adminDistrict2": "Alberta",
				"countryRegion": "Canada",
				"formattedAddress": "55 10 Ave SE, High River, AB T1V 1E6, Canada",
				"locality": "High River",
				"postalCode": "T1V 1E6"
			},
			"geometry": {
				"type": "Point",
				"coordinates": [
					-113.86936,
					50.57347
				]
			},
			"bbox": [
				-113.8711301,
				50.5723458,
				-113.8675899,
				50.5745942
			]
		}
	]
}
