{
	"type": "FeatureCollection",
	"features": [
		{
			"type": "Feature",
			"properties": {
				"confidence": 9,
				"authenticationResultCode": "ValidCredentials",
				"brandLogoUri": "http://dev.virtualearth.net/Branding/logo_powered_by.png",
				"copyright": "Copyright © 2017 Microsoft and its suppliers. All rights reserved. This API cannot be accessed and the content and any results may not be used, reproduced or transmitted in any manner without express written permission from Microsoft Corporation.",
				"entityType": "Address",
				"matchCodes": [
					"Good"
				],
				"name": "55 Guardsman Rd, Thornhill, ON L3T 6L2, Canada",
				"statusCode": 200,
				"statusDescription": "OK",
				"traceId": "7ff32ae9b315426a88ac76f1ef908afb|BN20290118|7.7.0.0|",
				"addressLine": "55 Guardsman Rd",
				"adminDistrict": "ON",
				"adminDistrict2": "York",
				"countryRegion": "Canada",
				"formattedAddress": "55 Guardsman Rd, Thornhill, ON L3T 6L2, Canada",
				"locality": "Markham",
				"neighborhood": "Thornhill",
				"postalCode": "L3T 6L2"
			},
			"geometry": {
				"type": "Point",
				"coordinates": [
					-79.39619,
					43.82578
				]
			},
			"bbox": [
				-79.3977482,
				43.8246558,
				-79.3946318,
				43.8269042
			]
		}
	]
}
