{
	"type": "FeatureCollection",
	"features": [
		{
			"type": "Feature",
			"properties": {
				"confidence": 9,
				"authenticationResultCode": "ValidCredentials",
				"brandLogoUri": "http://dev.virtualearth.net/Branding/logo_powered_by.png",
				"copyright": "Copyright © 2017 Microsoft and its suppliers. All rights reserved. This API cannot be accessed and the content and any results may not be used, reproduced or transmitted in any manner without express written permission from Microsoft Corporation.",
				"entityType": "Address",
				"matchCodes": [
					"Good"
				],
				"name": "55 Kelfield St, Etobicoke, ON M9W 5A3, Canada",
				"statusCode": 200,
				"statusDescription": "OK",
				"traceId": "a8ce0b8def564e8fab89c0df718d6da4|BN20130423|7.7.0.0|",
				"addressLine": "55 Kelfield St",
				"adminDistrict": "ON",
				"adminDistrict2": "Toronto",
				"countryRegion": "Canada",
				"formattedAddress": "55 Kelfield St, Etobicoke, ON M9W 5A3, Canada",
				"locality": "Toronto",
				"neighborhood": "West Humber-Clairville",
				"postalCode": "M9W 5A3"
			},
			"geometry": {
				"type": "Point",
				"coordinates": [
					-79.57481,
					43.68568
				]
			},
			"bbox": [
				-79.5763645,
				43.6845558,
				-79.5732555,
				43.6868042
			]
		}
	]
}
