{
	"type": "FeatureCollection",
	"features": [
		{
			"type": "Feature",
			"properties": {
				"confidence": 9,
				"authenticationResultCode": "ValidCredentials",
				"brandLogoUri": "http://dev.virtualearth.net/Branding/logo_powered_by.png",
				"copyright": "Copyright © 2017 Microsoft and its suppliers. All rights reserved. This API cannot be accessed and the content and any results may not be used, reproduced or transmitted in any manner without express written permission from Microsoft Corporation.",
				"entityType": "Address",
				"matchCodes": [
					"Good"
				],
				"name": "55 Roadmaster Ln, Brampton, ON L7A 3A7, Canada",
				"statusCode": 200,
				"statusDescription": "OK",
				"traceId": "f6a6062b3c98496681cc0a24407538ef|BN20130422|7.7.0.0|",
				"addressLine": "55 Roadmaster Ln",
				"adminDistrict": "ON",
				"adminDistrict2": "Peel",
				"countryRegion": "Canada",
				"formattedAddress": "55 Roadmaster Ln, Brampton, ON L7A 3A7, Canada",
				"locality": "Brampton",
				"neighborhood": "Heart Lake",
				"postalCode": "L7A 3A7"
			},
			"geometry": {
				"type": "Point",
				"coordinates": [
					-79.83658,
					43.69122
				]
			},
			"bbox": [
				-79.8381347,
				43.6900958,
				-79.8350253,
				43.6923442
			]
		}
	]
}
