{
	"type": "FeatureCollection",
	"features": [
		{
			"type": "Feature",
			"properties": {
				"confidence": 9,
				"authenticationResultCode": "ValidCredentials",
				"brandLogoUri": "http://dev.virtualearth.net/Branding/logo_powered_by.png",
				"copyright": "Copyright © 2017 Microsoft and its suppliers. All rights reserved. This API cannot be accessed and the content and any results may not be used, reproduced or transmitted in any manner without express written permission from Microsoft Corporation.",
				"entityType": "Address",
				"matchCodes": [
					"Good"
				],
				"name": "55 Rymal Rd E, Hamilton, ON L9B 1B9, Canada",
				"statusCode": 200,
				"statusDescription": "OK",
				"traceId": "6e243c2a3dc345ffa2e5eec5f5a69edb|BN20240253|7.7.0.0|",
				"addressLine": "55 Rymal Rd E",
				"adminDistrict": "ON",
				"adminDistrict2": "Hamilton",
				"countryRegion": "Canada",
				"formattedAddress": "55 Rymal Rd E, Hamilton, ON L9B 1B9, Canada",
				"locality": "Hamilton",
				"neighborhood": "Ryckmans",
				"postalCode": "L9B 1B9"
			},
			"geometry": {
				"type": "Point",
				"coordinates": [
					-79.8906467,
					43.2020123
				]
			},
			"bbox": [
				-79.8921889,
				43.2008882,
				-79.8891046,
				43.2031365
			]
		}
	]
}
