{
	"type": "FeatureCollection",
	"features": [
		{
			"type": "Feature",
			"properties": {
				"confidence": 9,
				"authenticationResultCode": "ValidCredentials",
				"brandLogoUri": "http://dev.virtualearth.net/Branding/logo_powered_by.png",
				"copyright": "Copyright © 2017 Microsoft and its suppliers. All rights reserved. This API cannot be accessed and the content and any results may not be used, reproduced or transmitted in any manner without express written permission from Microsoft Corporation.",
				"entityType": "Address",
				"matchCodes": [
					"Good"
				],
				"name": "55 Sinclair Blvd, Brantford, ON N3S 7X6, Canada",
				"statusCode": 200,
				"statusDescription": "OK",
				"traceId": "b3bdc08178224d52917dfd1bc3c772e4|BN20131519|7.7.0.0|",
				"addressLine": "55 Sinclair Blvd",
				"adminDistrict": "ON",
				"adminDistrict2": "Brant",
				"countryRegion": "Canada",
				"formattedAddress": "55 Sinclair Blvd, Brantford, ON N3S 7X6, Canada",
				"locality": "Brantford",
				"postalCode": "N3S 7X6"
			},
			"geometry": {
				"type": "Point",
				"coordinates": [
					-80.2199,
					43.17
				]
			},
			"bbox": [
				-80.2214414,
				43.1688758,
				-80.2183586,
				43.1711242
			]
		}
	]
}
