{
	"type": "FeatureCollection",
	"features": [
		{
			"type": "Feature",
			"properties": {
				"confidence": 9,
				"authenticationResultCode": "ValidCredentials",
				"brandLogoUri": "http://dev.virtualearth.net/Branding/logo_powered_by.png",
				"copyright": "Copyright © 2017 Microsoft and its suppliers. All rights reserved. This API cannot be accessed and the content and any results may not be used, reproduced or transmitted in any manner without express written permission from Microsoft Corporation.",
				"entityType": "Address",
				"matchCodes": [
					"Good"
				],
				"name": "550 Stone St S, Gananoque, ON K7G 2A8, Canada",
				"statusCode": 200,
				"statusDescription": "OK",
				"traceId": "64301b08205546a3adfe9436238f0055|BN20130447|7.7.0.0|",
				"addressLine": "550 Stone St S",
				"adminDistrict": "ON",
				"adminDistrict2": "Leeds and Grenville",
				"countryRegion": "Canada",
				"formattedAddress": "550 Stone St S, Gananoque, ON K7G 2A8, Canada",
				"locality": "Gananoque",
				"postalCode": "K7G 2A8"
			},
			"geometry": {
				"type": "Point",
				"coordinates": [
					-76.1580253,
					44.325749
				]
			},
			"bbox": [
				-76.1595967,
				44.3246248,
				-76.1564538,
				44.3268731
			]
		}
	]
}
