{
	"type": "FeatureCollection",
	"features": [
		{
			"type": "Feature",
			"properties": {
				"confidence": 9,
				"authenticationResultCode": "ValidCredentials",
				"brandLogoUri": "http://dev.virtualearth.net/Branding/logo_powered_by.png",
				"copyright": "Copyright © 2017 Microsoft and its suppliers. All rights reserved. This API cannot be accessed and the content and any results may not be used, reproduced or transmitted in any manner without express written permission from Microsoft Corporation.",
				"entityType": "Address",
				"matchCodes": [
					"Good"
				],
				"name": "5572 275 St, Langley, BC V4W 3X7, Canada",
				"statusCode": 200,
				"statusDescription": "OK",
				"traceId": "88e2b6ca94ac4eb6826354dc2d2eb214|BN20130423|7.7.0.0|",
				"addressLine": "5572 275 St",
				"adminDistrict": "BC",
				"adminDistrict2": "Greater Vancouver",
				"countryRegion": "Canada",
				"formattedAddress": "5572 275 St, Langley, BC V4W 3X7, Canada",
				"locality": "Langley",
				"neighborhood": "Langley",
				"postalCode": "V4W 3X7"
			},
			"geometry": {
				"type": "Point",
				"coordinates": [
					-122.46156,
					49.10269
				]
			},
			"bbox": [
				-122.463277,
				49.1015658,
				-122.459843,
				49.1038142
			]
		}
	]
}
