{
	"type": "FeatureCollection",
	"features": [
		{
			"type": "Feature",
			"properties": {
				"confidence": 9,
				"authenticationResultCode": "ValidCredentials",
				"brandLogoUri": "http://dev.virtualearth.net/Branding/logo_powered_by.png",
				"copyright": "Copyright © 2017 Microsoft and its suppliers. All rights reserved. This API cannot be accessed and the content and any results may not be used, reproduced or transmitted in any manner without express written permission from Microsoft Corporation.",
				"entityType": "Address",
				"matchCodes": [
					"Good"
				],
				"name": "558 Rue Principale, Drummondville, QC J1Z 2C3, Canada",
				"statusCode": 200,
				"statusDescription": "OK",
				"traceId": "d5550bd512db4273a862489d12437159|BN20131519|7.7.0.0|",
				"addressLine": "558 Rue Principale",
				"adminDistrict": "QC",
				"adminDistrict2": "Drummond",
				"countryRegion": "Canada",
				"formattedAddress": "558 Rue Principale, Drummondville, QC J1Z 2C3, Canada",
				"locality": "Drummondville",
				"neighborhood": "St-Joachim-de-Courval",
				"postalCode": "J1Z 2C3"
			},
			"geometry": {
				"type": "Point",
				"coordinates": [
					-72.5525399,
					45.97569
				]
			},
			"bbox": [
				-72.5541575,
				45.9745658,
				-72.5509223,
				45.9768142
			]
		}
	]
}
