{
	"type": "FeatureCollection",
	"features": [
		{
			"type": "Feature",
			"properties": {
				"confidence": 9,
				"authenticationResultCode": "ValidCredentials",
				"brandLogoUri": "http://dev.virtualearth.net/Branding/logo_powered_by.png",
				"copyright": "Copyright © 2017 Microsoft and its suppliers. All rights reserved. This API cannot be accessed and the content and any results may not be used, reproduced or transmitted in any manner without express written permission from Microsoft Corporation.",
				"entityType": "Address",
				"matchCodes": [
					"Good"
				],
				"name": "56 Canova Rd SW, Calgary, AB T2W 2A6, Canada",
				"statusCode": 200,
				"statusDescription": "OK",
				"traceId": "a381dfe6004f4c6eb20bf632f01a996a|BN20240423|7.7.0.0|",
				"addressLine": "56 Canova Rd SW",
				"adminDistrict": "AB",
				"adminDistrict2": "Alberta",
				"countryRegion": "Canada",
				"formattedAddress": "56 Canova Rd SW, Calgary, AB T2W 2A6, Canada",
				"locality": "Calgary",
				"neighborhood": "Canyon Meadows",
				"postalCode": "T2W 2A6"
			},
			"geometry": {
				"type": "Point",
				"coordinates": [
					-114.09256,
					50.94649
				]
			},
			"bbox": [
				-114.0943442,
				50.9453658,
				-114.0907758,
				50.9476142
			]
		}
	]
}
