{
	"type": "FeatureCollection",
	"features": [
		{
			"type": "Feature",
			"properties": {
				"confidence": 9,
				"authenticationResultCode": "ValidCredentials",
				"brandLogoUri": "http://dev.virtualearth.net/Branding/logo_powered_by.png",
				"copyright": "Copyright © 2017 Microsoft and its suppliers. All rights reserved. This API cannot be accessed and the content and any results may not be used, reproduced or transmitted in any manner without express written permission from Microsoft Corporation.",
				"entityType": "Address",
				"matchCodes": [
					"Good"
				],
				"name": "56 Canterbury St, Saint John, NB E2L 2C5, Canada",
				"statusCode": 200,
				"statusDescription": "OK",
				"traceId": "2470aed0b4284df395e9b5d509c73516|BN20130422|7.7.0.0|",
				"addressLine": "56 Canterbury St",
				"adminDistrict": "NB",
				"adminDistrict2": "Saint John",
				"countryRegion": "Canada",
				"formattedAddress": "56 Canterbury St, Saint John, NB E2L 2C5, Canada",
				"locality": "Saint John",
				"postalCode": "E2L 2C5"
			},
			"geometry": {
				"type": "Point",
				"coordinates": [
					-66.06095,
					45.27184
				]
			},
			"bbox": [
				-66.0625474,
				45.2707158,
				-66.0593526,
				45.2729642
			]
		}
	]
}
