{
	"type": "FeatureCollection",
	"features": [
		{
			"type": "Feature",
			"properties": {
				"confidence": 9,
				"authenticationResultCode": "ValidCredentials",
				"brandLogoUri": "http://dev.virtualearth.net/Branding/logo_powered_by.png",
				"copyright": "Copyright © 2017 Microsoft and its suppliers. All rights reserved. This API cannot be accessed and the content and any results may not be used, reproduced or transmitted in any manner without express written permission from Microsoft Corporation.",
				"entityType": "Address",
				"matchCodes": [
					"Good"
				],
				"name": "56 Cour Grand Harbour, Ottawa, ON K2S 1H1, Canada",
				"statusCode": 200,
				"statusDescription": "OK",
				"traceId": "0a66f85fb5314a0bae08e6106037e696|BN20130431|7.7.0.0|",
				"addressLine": "56 Cour Grand Harbour",
				"adminDistrict": "ON",
				"adminDistrict2": "Ottawa",
				"countryRegion": "Canada",
				"formattedAddress": "56 Cour Grand Harbour, Ottawa, ON K2S 1H1, Canada",
				"locality": "Ottawa",
				"neighborhood": "Stittsville",
				"postalCode": "K2S 1H1"
			},
			"geometry": {
				"type": "Point",
				"coordinates": [
					-75.9218152,
					45.2752189
				]
			},
			"bbox": [
				-75.9234126,
				45.2740947,
				-75.9202177,
				45.276343
			]
		}
	]
}
