{
	"type": "FeatureCollection",
	"features": [
		{
			"type": "Feature",
			"properties": {
				"confidence": 9,
				"authenticationResultCode": "ValidCredentials",
				"brandLogoUri": "http://dev.virtualearth.net/Branding/logo_powered_by.png",
				"copyright": "Copyright © 2017 Microsoft and its suppliers. All rights reserved. This API cannot be accessed and the content and any results may not be used, reproduced or transmitted in any manner without express written permission from Microsoft Corporation.",
				"entityType": "Address",
				"matchCodes": [
					"Good"
				],
				"name": "56 Rankin St, Waterloo, ON N2V 1V9, Canada",
				"statusCode": 200,
				"statusDescription": "OK",
				"traceId": "3a1d9ddc81dd4ee6b04f569464c092e6|BN20240253|7.7.0.0|",
				"addressLine": "56 Rankin St",
				"adminDistrict": "ON",
				"adminDistrict2": "Waterloo",
				"countryRegion": "Canada",
				"formattedAddress": "56 Rankin St, Waterloo, ON N2V 1V9, Canada",
				"locality": "Waterloo",
				"postalCode": "N2V 1V9"
			},
			"geometry": {
				"type": "Point",
				"coordinates": [
					-80.53928,
					43.51011
				]
			},
			"bbox": [
				-80.54083,
				43.5089858,
				-80.53773,
				43.5112342
			]
		}
	]
}
