{
	"type": "FeatureCollection",
	"features": [
		{
			"type": "Feature",
			"properties": {
				"confidence": 9,
				"authenticationResultCode": "ValidCredentials",
				"brandLogoUri": "http://dev.virtualearth.net/Branding/logo_powered_by.png",
				"copyright": "Copyright © 2017 Microsoft and its suppliers. All rights reserved. This API cannot be accessed and the content and any results may not be used, reproduced or transmitted in any manner without express written permission from Microsoft Corporation.",
				"entityType": "Address",
				"matchCodes": [
					"Good"
				],
				"name": "5635 McAdam Rd, Mississauga, ON L4Z 1N9, Canada",
				"statusCode": 200,
				"statusDescription": "OK",
				"traceId": "f45c05234dd64e779c3e34c180c025ea|BN20121764|7.7.0.0|",
				"addressLine": "5635 McAdam Rd",
				"adminDistrict": "ON",
				"adminDistrict2": "Peel",
				"countryRegion": "Canada",
				"formattedAddress": "5635 McAdam Rd, Mississauga, ON L4Z 1N9, Canada",
				"locality": "Mississauga",
				"postalCode": "L4Z 1N9"
			},
			"geometry": {
				"type": "Point",
				"coordinates": [
					-79.66355,
					43.62561
				]
			},
			"bbox": [
				-79.665103,
				43.6244858,
				-79.661997,
				43.6267342
			]
		}
	]
}
