{
	"type": "FeatureCollection",
	"features": [
		{
			"type": "Feature",
			"properties": {
				"confidence": 9,
				"authenticationResultCode": "ValidCredentials",
				"brandLogoUri": "http://dev.virtualearth.net/Branding/logo_powered_by.png",
				"copyright": "Copyright © 2017 Microsoft and its suppliers. All rights reserved. This API cannot be accessed and the content and any results may not be used, reproduced or transmitted in any manner without express written permission from Microsoft Corporation.",
				"entityType": "Address",
				"matchCodes": [
					"Good"
				],
				"name": "565 England Ave, Courtenay, BC V9N 2N2, Canada",
				"statusCode": 200,
				"statusDescription": "OK",
				"traceId": "7310635fac754838b5098c61e1f12e96|BN20200137|7.7.0.0|",
				"addressLine": "565 England Ave",
				"adminDistrict": "BC",
				"adminDistrict2": "Comox Valley",
				"countryRegion": "Canada",
				"formattedAddress": "565 England Ave, Courtenay, BC V9N 2N2, Canada",
				"locality": "Courtenay",
				"postalCode": "V9N 2N2"
			},
			"geometry": {
				"type": "Point",
				"coordinates": [
					-124.9997648,
					49.6898273
				]
			},
			"bbox": [
				-125.0015024,
				49.6887032,
				-124.9980271,
				49.6909515
			]
		}
	]
}
