{
	"type": "FeatureCollection",
	"features": [
		{
			"type": "Feature",
			"properties": {
				"confidence": 9,
				"authenticationResultCode": "ValidCredentials",
				"brandLogoUri": "http://dev.virtualearth.net/Branding/logo_powered_by.png",
				"copyright": "Copyright © 2017 Microsoft and its suppliers. All rights reserved. This API cannot be accessed and the content and any results may not be used, reproduced or transmitted in any manner without express written permission from Microsoft Corporation.",
				"entityType": "Address",
				"matchCodes": [
					"Good"
				],
				"name": "567 Main St, Montague, PE C0A, Canada",
				"statusCode": 200,
				"statusDescription": "OK",
				"traceId": "37e4bca59bce40cd8c84964fccf20262|BN20130634|7.7.0.0|",
				"addressLine": "567 Main St",
				"adminDistrict": "PE",
				"adminDistrict2": "Kings",
				"countryRegion": "Canada",
				"formattedAddress": "567 Main St, Montague, PE C0A, Canada",
				"locality": "Montague",
				"postalCode": "C0A 1R0"
			},
			"geometry": {
				"type": "Point",
				"coordinates": [
					-62.64712,
					46.16348
				]
			},
			"bbox": [
				-62.6487431,
				46.1623558,
				-62.6454969,
				46.1646042
			]
		}
	]
}
