{
	"type": "FeatureCollection",
	"features": [
		{
			"type": "Feature",
			"properties": {
				"confidence": 9,
				"authenticationResultCode": "ValidCredentials",
				"brandLogoUri": "http://dev.virtualearth.net/Branding/logo_powered_by.png",
				"copyright": "Copyright © 2017 Microsoft and its suppliers. All rights reserved. This API cannot be accessed and the content and any results may not be used, reproduced or transmitted in any manner without express written permission from Microsoft Corporation.",
				"entityType": "Address",
				"matchCodes": [
					"Good"
				],
				"name": "5680 14th Ave, Markham, ON L3S 3K8, Canada",
				"statusCode": 200,
				"statusDescription": "OK",
				"traceId": "595351800ec74819a789c9c7304ae91c|BN20200137|7.7.0.0|",
				"addressLine": "5680 14th Ave",
				"adminDistrict": "ON",
				"adminDistrict2": "York",
				"countryRegion": "Canada",
				"formattedAddress": "5680 14th Ave, Markham, ON L3S 3K8, Canada",
				"locality": "Markham",
				"postalCode": "L3S 3K8"
			},
			"geometry": {
				"type": "Point",
				"coordinates": [
					-79.2661399,
					43.85292
				]
			},
			"bbox": [
				-79.2676988,
				43.8517958,
				-79.264581,
				43.8540442
			]
		}
	]
}
