{
	"type": "FeatureCollection",
	"features": [
		{
			"type": "Feature",
			"properties": {
				"confidence": 9,
				"authenticationResultCode": "ValidCredentials",
				"brandLogoUri": "http://dev.virtualearth.net/Branding/logo_powered_by.png",
				"copyright": "Copyright © 2017 Microsoft and its suppliers. All rights reserved. This API cannot be accessed and the content and any results may not be used, reproduced or transmitted in any manner without express written permission from Microsoft Corporation.",
				"entityType": "Address",
				"matchCodes": [
					"Good"
				],
				"name": "57 Holland St W, Bradford West Gwillimbury, ON L3Z, Canada",
				"statusCode": 200,
				"statusDescription": "OK",
				"traceId": "9a022fe8b82446f29f73591bb247772d|BN20130442|7.7.0.0|",
				"addressLine": "57 Holland St W",
				"adminDistrict": "ON",
				"adminDistrict2": "Simcoe",
				"countryRegion": "Canada",
				"formattedAddress": "57 Holland St W, Bradford West Gwillimbury, ON L3Z, Canada",
				"locality": "Bradford West Gwillimbury",
				"neighborhood": "Bradford",
				"postalCode": "L3Z 2A7"
			},
			"geometry": {
				"type": "Point",
				"coordinates": [
					-79.56668,
					44.11417
				]
			},
			"bbox": [
				-79.5682458,
				44.1130458,
				-79.5651142,
				44.1152942
			]
		}
	]
}
