{
	"type": "FeatureCollection",
	"features": [
		{
			"type": "Feature",
			"properties": {
				"confidence": 9,
				"authenticationResultCode": "ValidCredentials",
				"brandLogoUri": "http://dev.virtualearth.net/Branding/logo_powered_by.png",
				"copyright": "Copyright © 2017 Microsoft and its suppliers. All rights reserved. This API cannot be accessed and the content and any results may not be used, reproduced or transmitted in any manner without express written permission from Microsoft Corporation.",
				"entityType": "Address",
				"matchCodes": [
					"Good"
				],
				"name": "57 King St, St Stephen, NB E3L 2C4, Canada",
				"statusCode": 200,
				"statusDescription": "OK",
				"traceId": "7065de9b0a804b21a89c1c760840a76a|BN20300154|7.7.0.0|",
				"addressLine": "57 King St",
				"adminDistrict": "NB",
				"adminDistrict2": "Charlotte",
				"countryRegion": "Canada",
				"formattedAddress": "57 King St, St Stephen, NB E3L 2C4, Canada",
				"locality": "St Stephen",
				"postalCode": "E3L 2C4"
			},
			"geometry": {
				"type": "Point",
				"coordinates": [
					-67.27517,
					45.19433
				]
			},
			"bbox": [
				-67.2767652,
				45.1932058,
				-67.2735748,
				45.1954542
			]
		}
	]
}
