{
	"type": "FeatureCollection",
	"features": [
		{
			"type": "Feature",
			"properties": {
				"confidence": 9,
				"authenticationResultCode": "ValidCredentials",
				"brandLogoUri": "http://dev.virtualearth.net/Branding/logo_powered_by.png",
				"copyright": "Copyright © 2017 Microsoft and its suppliers. All rights reserved. This API cannot be accessed and the content and any results may not be used, reproduced or transmitted in any manner without express written permission from Microsoft Corporation.",
				"entityType": "Address",
				"matchCodes": [
					"Good"
				],
				"name": "57 Maricona Way, Kanata, ON K2T 1H2, Canada",
				"statusCode": 200,
				"statusDescription": "OK",
				"traceId": "cf075e6fb2974bbbb21ac264cea4af66|BN20130631|7.7.0.0|",
				"addressLine": "57 Maricona Way",
				"adminDistrict": "ON",
				"adminDistrict2": "Ottawa",
				"countryRegion": "Canada",
				"formattedAddress": "57 Maricona Way, Kanata, ON K2T 1H2, Canada",
				"locality": "Ottawa",
				"neighborhood": "Kanata",
				"postalCode": "K2T 1H2"
			},
			"geometry": {
				"type": "Point",
				"coordinates": [
					-75.9282,
					45.3185
				]
			},
			"bbox": [
				-75.9297987,
				45.3173758,
				-75.9266013,
				45.3196242
			]
		}
	]
}
