{
	"type": "FeatureCollection",
	"features": [
		{
			"type": "Feature",
			"properties": {
				"confidence": 9,
				"authenticationResultCode": "ValidCredentials",
				"brandLogoUri": "http://dev.virtualearth.net/Branding/logo_powered_by.png",
				"copyright": "Copyright © 2017 Microsoft and its suppliers. All rights reserved. This API cannot be accessed and the content and any results may not be used, reproduced or transmitted in any manner without express written permission from Microsoft Corporation.",
				"entityType": "Address",
				"matchCodes": [
					"Good"
				],
				"name": "57 Water St, Summerside, PE C1N 1A4, Canada",
				"statusCode": 200,
				"statusDescription": "OK",
				"traceId": "53c3cd5efa3d486fbec5c819a08cb4f7|BN20300154|7.7.0.0|",
				"addressLine": "57 Water St",
				"adminDistrict": "PE",
				"adminDistrict2": "Prince",
				"countryRegion": "Canada",
				"formattedAddress": "57 Water St, Summerside, PE C1N 1A4, Canada",
				"locality": "Summerside",
				"postalCode": "C1N 1A4"
			},
			"geometry": {
				"type": "Point",
				"coordinates": [
					-63.7781,
					46.39111
				]
			},
			"bbox": [
				-63.7797298,
				46.3899858,
				-63.7764702,
				46.3922342
			]
		}
	]
}
