{
	"type": "FeatureCollection",
	"features": [
		{
			"type": "Feature",
			"properties": {
				"confidence": 9,
				"authenticationResultCode": "ValidCredentials",
				"brandLogoUri": "http://dev.virtualearth.net/Branding/logo_powered_by.png",
				"copyright": "Copyright © 2017 Microsoft and its suppliers. All rights reserved. This API cannot be accessed and the content and any results may not be used, reproduced or transmitted in any manner without express written permission from Microsoft Corporation.",
				"entityType": "Address",
				"matchCodes": [
					"Good"
				],
				"name": "570 Wilkinson Ave, Dartmouth, NS B3B 0J4, Canada",
				"statusCode": 200,
				"statusDescription": "OK",
				"traceId": "c91da5decb2f4049bdc056f97c8fe77d|BN20190653|7.7.0.0|",
				"addressLine": "570 Wilkinson Ave",
				"adminDistrict": "NS",
				"adminDistrict2": "Halifax",
				"countryRegion": "Canada",
				"formattedAddress": "570 Wilkinson Ave, Dartmouth, NS B3B 0J4, Canada",
				"locality": "Halifax",
				"neighborhood": "Dartmouth",
				"postalCode": "B3B 0J4"
			},
			"geometry": {
				"type": "Point",
				"coordinates": [
					-63.5707,
					44.71987
				]
			},
			"bbox": [
				-63.5722821,
				44.7187458,
				-63.5691179,
				44.7209942
			]
		}
	]
}
