{
	"type": "FeatureCollection",
	"features": [
		{
			"type": "Feature",
			"properties": {
				"confidence": 9,
				"authenticationResultCode": "ValidCredentials",
				"brandLogoUri": "http://dev.virtualearth.net/Branding/logo_powered_by.png",
				"copyright": "Copyright © 2017 Microsoft and its suppliers. All rights reserved. This API cannot be accessed and the content and any results may not be used, reproduced or transmitted in any manner without express written permission from Microsoft Corporation.",
				"entityType": "Address",
				"matchCodes": [
					"Good"
				],
				"name": "570 Longworth Ave, Bowmanville, ON L1C 0H4, Canada",
				"statusCode": 200,
				"statusDescription": "OK",
				"traceId": "66e398e7cb4a48b7b073cc34fab0edee|BN20130520|7.7.0.0|",
				"addressLine": "570 Longworth Ave",
				"adminDistrict": "ON",
				"adminDistrict2": "Durham",
				"countryRegion": "Canada",
				"formattedAddress": "570 Longworth Ave, Bowmanville, ON L1C 0H4, Canada",
				"locality": "Clarington",
				"neighborhood": "Bowmanville",
				"postalCode": "L1C 0H4"
			},
			"geometry": {
				"type": "Point",
				"coordinates": [
					-78.69001,
					43.9305
				]
			},
			"bbox": [
				-78.6915709,
				43.9293758,
				-78.6884491,
				43.9316242
			]
		}
	]
}
