{
	"type": "FeatureCollection",
	"features": [
		{
			"type": "Feature",
			"properties": {
				"confidence": 9,
				"authenticationResultCode": "ValidCredentials",
				"brandLogoUri": "http://dev.virtualearth.net/Branding/logo_powered_by.png",
				"copyright": "Copyright © 2017 Microsoft and its suppliers. All rights reserved. This API cannot be accessed and the content and any results may not be used, reproduced or transmitted in any manner without express written permission from Microsoft Corporation.",
				"entityType": "Address",
				"matchCodes": [
					"Good"
				],
				"name": "5711 67 St NW, Edmonton, AB T6B 0B4, Canada",
				"statusCode": 200,
				"statusDescription": "OK",
				"traceId": "d1f035d5d64e4a85a563c4a9abcb9220|BN20130719|7.7.0.0|",
				"addressLine": "5711 67 St NW",
				"adminDistrict": "AB",
				"adminDistrict2": "Alberta",
				"countryRegion": "Canada",
				"formattedAddress": "5711 67 St NW, Edmonton, AB T6B 0B4, Canada",
				"locality": "Edmonton",
				"neighborhood": "Roper Industrial",
				"postalCode": "T6B 0B4"
			},
			"geometry": {
				"type": "Point",
				"coordinates": [
					-113.42799,
					53.49285
				]
			},
			"bbox": [
				-113.4298796,
				53.4917258,
				-113.4261004,
				53.4939742
			]
		}
	]
}
