{
	"type": "FeatureCollection",
	"features": [
		{
			"type": "Feature",
			"properties": {
				"confidence": 9,
				"authenticationResultCode": "ValidCredentials",
				"brandLogoUri": "http://dev.virtualearth.net/Branding/logo_powered_by.png",
				"copyright": "Copyright © 2017 Microsoft and its suppliers. All rights reserved. This API cannot be accessed and the content and any results may not be used, reproduced or transmitted in any manner without express written permission from Microsoft Corporation.",
				"entityType": "Address",
				"matchCodes": [
					"Good"
				],
				"name": "5715 Cowrie St, Sechelt, BC V0N, Canada",
				"statusCode": 200,
				"statusDescription": "OK",
				"traceId": "99d01afd91e94f62a9914d034cefc687|BN20130632|7.7.0.0|",
				"addressLine": "5715 Cowrie St",
				"adminDistrict": "BC",
				"adminDistrict2": "Sunshine Coast",
				"countryRegion": "Canada",
				"formattedAddress": "5715 Cowrie St, Sechelt, BC V0N, Canada",
				"locality": "Sechelt",
				"postalCode": "V0N 3A0"
			},
			"geometry": {
				"type": "Point",
				"coordinates": [
					-123.7586634,
					49.4722551
				]
			},
			"bbox": [
				-123.7603933,
				49.4711309,
				-123.7569334,
				49.4733793
			]
		}
	]
}
