{
	"type": "FeatureCollection",
	"features": [
		{
			"type": "Feature",
			"properties": {
				"confidence": 9,
				"authenticationResultCode": "ValidCredentials",
				"brandLogoUri": "http://dev.virtualearth.net/Branding/logo_powered_by.png",
				"copyright": "Copyright © 2017 Microsoft and its suppliers. All rights reserved. This API cannot be accessed and the content and any results may not be used, reproduced or transmitted in any manner without express written permission from Microsoft Corporation.",
				"entityType": "Address",
				"matchCodes": [
					"Good"
				],
				"name": "5725 Sauer Rd, Niagara Falls, ON L2E, Canada",
				"statusCode": 200,
				"statusDescription": "OK",
				"traceId": "da89b31f39564043823c160becf7c492|BN20280152|7.7.0.0|",
				"addressLine": "5725 Sauer Rd",
				"adminDistrict": "ON",
				"adminDistrict2": "Niagara",
				"countryRegion": "Canada",
				"formattedAddress": "5725 Sauer Rd, Niagara Falls, ON L2E, Canada",
				"locality": "Niagara Falls",
				"postalCode": "L2E 6S6"
			},
			"geometry": {
				"type": "Point",
				"coordinates": [
					-79.0855834,
					42.9897563
				]
			},
			"bbox": [
				-79.0871202,
				42.9886322,
				-79.0840465,
				42.9908805
			]
		}
	]
}
