{
	"type": "FeatureCollection",
	"features": [
		{
			"type": "Feature",
			"properties": {
				"confidence": 9,
				"authenticationResultCode": "ValidCredentials",
				"brandLogoUri": "http://dev.virtualearth.net/Branding/logo_powered_by.png",
				"copyright": "Copyright © 2017 Microsoft and its suppliers. All rights reserved. This API cannot be accessed and the content and any results may not be used, reproduced or transmitted in any manner without express written permission from Microsoft Corporation.",
				"entityType": "Address",
				"matchCodes": [
					"Good"
				],
				"name": "5725 Progress St, Niagara Falls, ON L2G 0C1, Canada",
				"statusCode": 200,
				"statusDescription": "OK",
				"traceId": "a0baa9580d2046838304ee0fb7a98d72|BN20130532|7.7.0.0|",
				"addressLine": "5725 Progress St",
				"adminDistrict": "ON",
				"adminDistrict2": "Niagara",
				"countryRegion": "Canada",
				"formattedAddress": "5725 Progress St, Niagara Falls, ON L2G 0C1, Canada",
				"locality": "Niagara Falls",
				"postalCode": "L2G 0C1"
			},
			"geometry": {
				"type": "Point",
				"coordinates": [
					-79.08758,
					43.05527
				]
			},
			"bbox": [
				-79.0891185,
				43.0541458,
				-79.0860415,
				43.0563942
			]
		}
	]
}
