{
	"type": "FeatureCollection",
	"features": [
		{
			"type": "Feature",
			"properties": {
				"confidence": 9,
				"authenticationResultCode": "ValidCredentials",
				"brandLogoUri": "http://dev.virtualearth.net/Branding/logo_powered_by.png",
				"copyright": "Copyright © 2017 Microsoft and its suppliers. All rights reserved. This API cannot be accessed and the content and any results may not be used, reproduced or transmitted in any manner without express written permission from Microsoft Corporation.",
				"entityType": "Address",
				"matchCodes": [
					"Good"
				],
				"name": "58 Redfern Ave, Barrie, ON L4N 9G3, Canada",
				"statusCode": 200,
				"statusDescription": "OK",
				"traceId": "c7ba68182d1b473e9cca9216b2b763cd|BN20260231|7.7.0.0|",
				"addressLine": "58 Redfern Ave",
				"adminDistrict": "ON",
				"adminDistrict2": "Simcoe",
				"countryRegion": "Canada",
				"formattedAddress": "58 Redfern Ave, Barrie, ON L4N 9G3, Canada",
				"locality": "Barrie",
				"neighborhood": "Holly",
				"postalCode": "L4N 9G3"
			},
			"geometry": {
				"type": "Point",
				"coordinates": [
					-79.7198499,
					44.32607
				]
			},
			"bbox": [
				-79.7214213,
				44.3249458,
				-79.7182785,
				44.3271942
			]
		}
	]
}
