{
	"type": "FeatureCollection",
	"features": [
		{
			"type": "Feature",
			"properties": {
				"confidence": 9,
				"authenticationResultCode": "ValidCredentials",
				"brandLogoUri": "http://dev.virtualearth.net/Branding/logo_powered_by.png",
				"copyright": "Copyright © 2017 Microsoft and its suppliers. All rights reserved. This API cannot be accessed and the content and any results may not be used, reproduced or transmitted in any manner without express written permission from Microsoft Corporation.",
				"entityType": "Address",
				"matchCodes": [
					"Good"
				],
				"name": "58 Weston St, Winnipeg, MB R3E 3H7, Canada",
				"statusCode": 200,
				"statusDescription": "OK",
				"traceId": "420ba8edfba24883affc2c4db32f8704|BN20131519|7.7.0.0|",
				"addressLine": "58 Weston St",
				"adminDistrict": "MB",
				"adminDistrict2": "Manitoba",
				"countryRegion": "Canada",
				"formattedAddress": "58 Weston St, Winnipeg, MB R3E 3H7, Canada",
				"locality": "Winnipeg",
				"neighborhood": "Weston",
				"postalCode": "R3E 3H7"
			},
			"geometry": {
				"type": "Point",
				"coordinates": [
					-97.18451,
					49.91132
				]
			},
			"bbox": [
				-97.1862557,
				49.9101958,
				-97.1827643,
				49.9124442
			]
		}
	]
}
