{
	"type": "FeatureCollection",
	"features": [
		{
			"type": "Feature",
			"properties": {
				"confidence": 9,
				"authenticationResultCode": "ValidCredentials",
				"brandLogoUri": "http://dev.virtualearth.net/Branding/logo_powered_by.png",
				"copyright": "Copyright © 2017 Microsoft and its suppliers. All rights reserved. This API cannot be accessed and the content and any results may not be used, reproduced or transmitted in any manner without express written permission from Microsoft Corporation.",
				"entityType": "Address",
				"matchCodes": [
					"Good"
				],
				"name": "5808 Dalkeith Hl NW, Calgary, AB T3A 1G4, Canada",
				"statusCode": 200,
				"statusDescription": "OK",
				"traceId": "af107c84c0274ffaace6ff81b151728a|BN20200137|7.7.0.0|",
				"addressLine": "5808 Dalkeith Hl NW",
				"adminDistrict": "AB",
				"adminDistrict2": "Alberta",
				"countryRegion": "Canada",
				"formattedAddress": "5808 Dalkeith Hl NW, Calgary, AB T3A 1G4, Canada",
				"locality": "Calgary",
				"neighborhood": "Dalhousie",
				"postalCode": "T3A 1G4"
			},
			"geometry": {
				"type": "Point",
				"coordinates": [
					-114.14592,
					51.10464
				]
			},
			"bbox": [
				-114.1477103,
				51.1035158,
				-114.1441297,
				51.1057642
			]
		}
	]
}
