{
	"type": "FeatureCollection",
	"features": [
		{
			"type": "Feature",
			"properties": {
				"confidence": 9,
				"authenticationResultCode": "ValidCredentials",
				"brandLogoUri": "http://dev.virtualearth.net/Branding/logo_powered_by.png",
				"copyright": "Copyright © 2017 Microsoft and its suppliers. All rights reserved. This API cannot be accessed and the content and any results may not be used, reproduced or transmitted in any manner without express written permission from Microsoft Corporation.",
				"entityType": "Address",
				"matchCodes": [
					"Good"
				],
				"name": "584 Grays Rd, Hamilton, ON L8E 2Z6, Canada",
				"statusCode": 200,
				"statusDescription": "OK",
				"traceId": "43b93f4589b248e49304125b6008fc66|BN20130625|7.7.0.0|",
				"addressLine": "584 Grays Rd",
				"adminDistrict": "ON",
				"adminDistrict2": "Hamilton",
				"countryRegion": "Canada",
				"formattedAddress": "584 Grays Rd, Hamilton, ON L8E 2Z6, Canada",
				"locality": "Hamilton",
				"neighborhood": "Stoney Creek",
				"postalCode": "L8E 2Z6"
			},
			"geometry": {
				"type": "Point",
				"coordinates": [
					-79.73521,
					43.24307
				]
			},
			"bbox": [
				-79.7367532,
				43.2419458,
				-79.7336668,
				43.2441942
			]
		}
	]
}
