{
	"type": "FeatureCollection",
	"features": [
		{
			"type": "Feature",
			"properties": {
				"confidence": 9,
				"authenticationResultCode": "ValidCredentials",
				"brandLogoUri": "http://dev.virtualearth.net/Branding/logo_powered_by.png",
				"copyright": "Copyright © 2017 Microsoft and its suppliers. All rights reserved. This API cannot be accessed and the content and any results may not be used, reproduced or transmitted in any manner without express written permission from Microsoft Corporation.",
				"entityType": "Address",
				"matchCodes": [
					"Good"
				],
				"name": "5860 Rue Sardou, Laval, QC H7H 1R6, Canada",
				"statusCode": 200,
				"statusDescription": "OK",
				"traceId": "eb024a9097464fb9986ab51ac3f3e6a8|BN20260223|7.7.0.0|",
				"addressLine": "5860 Rue Sardou",
				"adminDistrict": "QC",
				"adminDistrict2": "Laval",
				"countryRegion": "Canada",
				"formattedAddress": "5860 Rue Sardou, Laval, QC H7H 1R6, Canada",
				"locality": "Laval",
				"postalCode": "H7H 1R6"
			},
			"geometry": {
				"type": "Point",
				"coordinates": [
					-73.7566499,
					45.63055
				]
			},
			"bbox": [
				-73.7582575,
				45.6294258,
				-73.7550423,
				45.6316742
			]
		}
	]
}
