{
	"type": "FeatureCollection",
	"features": [
		{
			"type": "Feature",
			"properties": {
				"confidence": 9,
				"authenticationResultCode": "ValidCredentials",
				"brandLogoUri": "http://dev.virtualearth.net/Branding/logo_powered_by.png",
				"copyright": "Copyright © 2017 Microsoft and its suppliers. All rights reserved. This API cannot be accessed and the content and any results may not be used, reproduced or transmitted in any manner without express written permission from Microsoft Corporation.",
				"entityType": "Address",
				"matchCodes": [
					"Good"
				],
				"name": "588 Claude St, South Bruce Peninsula, ON N0H, Canada",
				"statusCode": 200,
				"statusDescription": "OK",
				"traceId": "d73bd4e1dac5485aa55e00e749350b1e|BN20130522|7.7.0.0|",
				"addressLine": "588 Claude St",
				"adminDistrict": "ON",
				"adminDistrict2": "Bruce",
				"countryRegion": "Canada",
				"formattedAddress": "588 Claude St, South Bruce Peninsula, ON N0H, Canada",
				"locality": "South Bruce Peninsula",
				"neighborhood": "Wiarton",
				"postalCode": "N0H 2T0"
			},
			"geometry": {
				"type": "Point",
				"coordinates": [
					-81.1397999,
					44.74325
				]
			},
			"bbox": [
				-81.1413826,
				44.7421258,
				-81.1382172,
				44.7443742
			]
		}
	]
}
