{
	"type": "FeatureCollection",
	"features": [
		{
			"type": "Feature",
			"properties": {
				"confidence": 9,
				"authenticationResultCode": "ValidCredentials",
				"brandLogoUri": "http://dev.virtualearth.net/Branding/logo_powered_by.png",
				"copyright": "Copyright © 2017 Microsoft and its suppliers. All rights reserved. This API cannot be accessed and the content and any results may not be used, reproduced or transmitted in any manner without express written permission from Microsoft Corporation.",
				"entityType": "Address",
				"matchCodes": [
					"Good"
				],
				"name": "59 McNaughton Ave, Wallaceburg, ON N8A 1R7, Canada",
				"statusCode": 200,
				"statusDescription": "OK",
				"traceId": "90dc17080ad44a489ddeed517c59cf62|BN20131519|7.7.0.0|",
				"addressLine": "59 McNaughton Ave",
				"adminDistrict": "ON",
				"adminDistrict2": "Chatham-Kent",
				"countryRegion": "Canada",
				"formattedAddress": "59 McNaughton Ave, Wallaceburg, ON N8A 1R7, Canada",
				"locality": "Chatham-Kent",
				"neighborhood": "Wallaceburg",
				"postalCode": "N8A 1R7"
			},
			"geometry": {
				"type": "Point",
				"coordinates": [
					-82.38264,
					42.58599
				]
			},
			"bbox": [
				-82.3841668,
				42.5848658,
				-82.3811132,
				42.5871142
			]
		}
	]
}
