{
	"type": "FeatureCollection",
	"features": [
		{
			"type": "Feature",
			"properties": {
				"confidence": 9,
				"authenticationResultCode": "ValidCredentials",
				"brandLogoUri": "http://dev.virtualearth.net/Branding/logo_powered_by.png",
				"copyright": "Copyright © 2017 Microsoft and its suppliers. All rights reserved. This API cannot be accessed and the content and any results may not be used, reproduced or transmitted in any manner without express written permission from Microsoft Corporation.",
				"entityType": "Address",
				"matchCodes": [
					"Good"
				],
				"name": "5912 50 Ave, Lloydminster, AB T9V 0X6, Canada",
				"statusCode": 200,
				"statusDescription": "OK",
				"traceId": "f1f808dc61294d7e811b1bdae044105b|BN20181720|7.7.0.0|",
				"addressLine": "5912 50 Ave",
				"adminDistrict": "AB",
				"adminDistrict2": "Alberta",
				"countryRegion": "Canada",
				"formattedAddress": "5912 50 Ave, Lloydminster, AB T9V 0X6, Canada",
				"locality": "Lloydminster",
				"postalCode": "T9V 0X6"
			},
			"geometry": {
				"type": "Point",
				"coordinates": [
					-110.0056313,
					53.2960867
				]
			},
			"bbox": [
				-110.0075122,
				53.2949626,
				-110.0037504,
				53.2972109
			]
		}
	]
}
