{
	"type": "FeatureCollection",
	"features": [
		{
			"type": "Feature",
			"properties": {
				"confidence": 7,
				"authenticationResultCode": "ValidCredentials",
				"brandLogoUri": "http://dev.virtualearth.net/Branding/logo_powered_by.png",
				"copyright": "Copyright © 2017 Microsoft and its suppliers. All rights reserved. This API cannot be accessed and the content and any results may not be used, reproduced or transmitted in any manner without express written permission from Microsoft Corporation.",
				"entityType": "RoadBlock",
				"matchCodes": [
					"UpHierarchy"
				],
				"name": "Gunn Rd, Springfield, MB R0E, Canada",
				"statusCode": 200,
				"statusDescription": "OK",
				"traceId": "1aa84a2631774dc48d0c894fcf02de84|BN20210145|7.7.0.0|",
				"addressLine": "Gunn Rd",
				"adminDistrict": "MB",
				"adminDistrict2": "Manitoba",
				"countryRegion": "Canada",
				"formattedAddress": "Gunn Rd, Springfield, MB R0E, Canada",
				"locality": "Springfield",
				"postalCode": "R0E"
			},
			"geometry": {
				"type": "Point",
				"coordinates": [
					-96.98461,
					49.91556
				]
			},
			"bbox": [
				-97.00238,
				49.9155299,
				-96.96686,
				49.91578
			]
		}
	]
}
