{
	"type": "FeatureCollection",
	"features": [
		{
			"type": "Feature",
			"properties": {
				"confidence": 9,
				"authenticationResultCode": "ValidCredentials",
				"brandLogoUri": "http://dev.virtualearth.net/Branding/logo_powered_by.png",
				"copyright": "Copyright © 2017 Microsoft and its suppliers. All rights reserved. This API cannot be accessed and the content and any results may not be used, reproduced or transmitted in any manner without express written permission from Microsoft Corporation.",
				"entityType": "Address",
				"matchCodes": [
					"Good"
				],
				"name": "5947 Talisman Ct, Mississauga, ON L5M 6A1, Canada",
				"statusCode": 200,
				"statusDescription": "OK",
				"traceId": "d66187f8e3f042e98ba4c42892d64146|BN20130422|7.7.0.0|",
				"addressLine": "5947 Talisman Ct",
				"adminDistrict": "ON",
				"adminDistrict2": "Peel",
				"countryRegion": "Canada",
				"formattedAddress": "5947 Talisman Ct, Mississauga, ON L5M 6A1, Canada",
				"locality": "Mississauga",
				"neighborhood": "Streetsville",
				"postalCode": "L5M 6A1"
			},
			"geometry": {
				"type": "Point",
				"coordinates": [
					-79.71469,
					43.59416
				]
			},
			"bbox": [
				-79.7162422,
				43.5930358,
				-79.7131378,
				43.5952842
			]
		}
	]
}
