{
	"type": "FeatureCollection",
	"features": [
		{
			"type": "Feature",
			"properties": {
				"confidence": 9,
				"authenticationResultCode": "ValidCredentials",
				"brandLogoUri": "http://dev.virtualearth.net/Branding/logo_powered_by.png",
				"copyright": "Copyright © 2017 Microsoft and its suppliers. All rights reserved. This API cannot be accessed and the content and any results may not be used, reproduced or transmitted in any manner without express written permission from Microsoft Corporation.",
				"entityType": "Address",
				"matchCodes": [
					"Good"
				],
				"name": "595 Woolwich St, Guelph, ON N1H 3Y5, Canada",
				"statusCode": 200,
				"statusDescription": "OK",
				"traceId": "7aba8cc2cc464cc1a6f08c7a1f837bf1|BN20300154|7.7.0.0|",
				"addressLine": "595 Woolwich St",
				"adminDistrict": "ON",
				"adminDistrict2": "Wellington",
				"countryRegion": "Canada",
				"formattedAddress": "595 Woolwich St, Guelph, ON N1H 3Y5, Canada",
				"locality": "Guelph",
				"neighborhood": "General Hospital/Riverside Park",
				"postalCode": "N1H 3Y5"
			},
			"geometry": {
				"type": "Point",
				"coordinates": [
					-80.26637,
					43.55736
				]
			},
			"bbox": [
				-80.2679212,
				43.5562358,
				-80.2648188,
				43.5584842
			]
		}
	]
}
