{
	"type": "FeatureCollection",
	"features": [
		{
			"type": "Feature",
			"properties": {
				"confidence": 9,
				"authenticationResultCode": "ValidCredentials",
				"brandLogoUri": "http://dev.virtualearth.net/Branding/logo_powered_by.png",
				"copyright": "Copyright © 2017 Microsoft and its suppliers. All rights reserved. This API cannot be accessed and the content and any results may not be used, reproduced or transmitted in any manner without express written permission from Microsoft Corporation.",
				"entityType": "Address",
				"matchCodes": [
					"Good"
				],
				"name": "595666 Blind Line, Mono, ON L0N, Canada",
				"statusCode": 200,
				"statusDescription": "OK",
				"traceId": "8ac3466ada0140e19f9d0b457a4f0a1b|BN20130721|7.7.0.0|",
				"addressLine": "595666 Blind Line",
				"adminDistrict": "ON",
				"adminDistrict2": "Dufferin",
				"countryRegion": "Canada",
				"formattedAddress": "595666 Blind Line, Mono, ON L0N, Canada",
				"locality": "Mono",
				"postalCode": "L0N"
			},
			"geometry": {
				"type": "Point",
				"coordinates": [
					-80.1540941,
					44.0809594
				]
			},
			"bbox": [
				-80.155659,
				44.0798353,
				-80.1525292,
				44.0820836
			]
		}
	]
}
