{
	"type": "FeatureCollection",
	"features": [
		{
			"type": "Feature",
			"properties": {
				"confidence": 9,
				"authenticationResultCode": "ValidCredentials",
				"brandLogoUri": "http://dev.virtualearth.net/Branding/logo_powered_by.png",
				"copyright": "Copyright © 2017 Microsoft and its suppliers. All rights reserved. This API cannot be accessed and the content and any results may not be used, reproduced or transmitted in any manner without express written permission from Microsoft Corporation.",
				"entityType": "Address",
				"matchCodes": [
					"Good"
				],
				"name": "5983 Ladyburn Cres, Mississauga, ON L5M 4V9, Canada",
				"statusCode": 200,
				"statusDescription": "OK",
				"traceId": "14660fd205af463191d26b5afbd0c18d|BN20280152|7.7.0.0|",
				"addressLine": "5983 Ladyburn Cres",
				"adminDistrict": "ON",
				"adminDistrict2": "Peel",
				"countryRegion": "Canada",
				"formattedAddress": "5983 Ladyburn Cres, Mississauga, ON L5M 4V9, Canada",
				"locality": "Mississauga",
				"neighborhood": "Streetsville",
				"postalCode": "L5M 4V9"
			},
			"geometry": {
				"type": "Point",
				"coordinates": [
					-79.71037,
					43.59285
				]
			},
			"bbox": [
				-79.7119221,
				43.5917258,
				-79.7088179,
				43.5939742
			]
		}
	]
}
