{
	"type": "FeatureCollection",
	"features": [
		{
			"type": "Feature",
			"properties": {
				"confidence": 9,
				"authenticationResultCode": "ValidCredentials",
				"brandLogoUri": "http://dev.virtualearth.net/Branding/logo_powered_by.png",
				"copyright": "Copyright © 2017 Microsoft and its suppliers. All rights reserved. This API cannot be accessed and the content and any results may not be used, reproduced or transmitted in any manner without express written permission from Microsoft Corporation.",
				"entityType": "Address",
				"matchCodes": [
					"Good"
				],
				"name": "59 Boulevard Samson, Laval, QC H7X 3E6, Canada",
				"statusCode": 200,
				"statusDescription": "OK",
				"traceId": "1b24139e79bf4ca8afc0d272b1ebaf25|BN20130442|7.7.0.0|",
				"addressLine": "59 Boulevard Samson",
				"adminDistrict": "QC",
				"adminDistrict2": "Laval",
				"countryRegion": "Canada",
				"formattedAddress": "59 Boulevard Samson, Laval, QC H7X 3E6, Canada",
				"locality": "Laval",
				"postalCode": "H7X 3E6"
			},
			"geometry": {
				"type": "Point",
				"coordinates": [
					-73.79213,
					45.52208
				]
			},
			"bbox": [
				-73.7937345,
				45.5209558,
				-73.7905255,
				45.5232042
			]
		}
	]
}
