{
	"type": "FeatureCollection",
	"features": [
		{
			"type": "Feature",
			"properties": {
				"confidence": 9,
				"authenticationResultCode": "ValidCredentials",
				"brandLogoUri": "http://dev.virtualearth.net/Branding/logo_powered_by.png",
				"copyright": "Copyright © 2017 Microsoft and its suppliers. All rights reserved. This API cannot be accessed and the content and any results may not be used, reproduced or transmitted in any manner without express written permission from Microsoft Corporation.",
				"entityType": "Address",
				"matchCodes": [
					"Good"
				],
				"name": "6 Ashwood Ct, Stoney Creek, ON L8E 3E1, Canada",
				"statusCode": 200,
				"statusDescription": "OK",
				"traceId": "d0662b1e8c7f4abbbbb4f2e5b1b0ce42|BN20130719|7.7.0.0|",
				"addressLine": "6 Ashwood Ct",
				"adminDistrict": "ON",
				"adminDistrict2": "Hamilton",
				"countryRegion": "Canada",
				"formattedAddress": "6 Ashwood Ct, Stoney Creek, ON L8E 3E1, Canada",
				"locality": "Hamilton",
				"neighborhood": "Stoney Creek",
				"postalCode": "L8E 3E1"
			},
			"geometry": {
				"type": "Point",
				"coordinates": [
					-79.73342,
					43.22971
				]
			},
			"bbox": [
				-79.7349629,
				43.2285858,
				-79.7318771,
				43.2308342
			]
		}
	]
}
