{
	"type": "FeatureCollection",
	"features": [
		{
			"type": "Feature",
			"properties": {
				"confidence": 9,
				"authenticationResultCode": "ValidCredentials",
				"brandLogoUri": "http://dev.virtualearth.net/Branding/logo_powered_by.png",
				"copyright": "Copyright © 2017 Microsoft and its suppliers. All rights reserved. This API cannot be accessed and the content and any results may not be used, reproduced or transmitted in any manner without express written permission from Microsoft Corporation.",
				"entityType": "Address",
				"matchCodes": [
					"Good"
				],
				"name": "6 Blue Jay Ave, Brampton, ON L6P 0E2, Canada",
				"statusCode": 200,
				"statusDescription": "OK",
				"traceId": "6ef2259324df48c9a3219f7c3ee79d77|BN20190642|7.7.0.0|",
				"addressLine": "6 Blue Jay Ave",
				"adminDistrict": "ON",
				"adminDistrict2": "Peel",
				"countryRegion": "Canada",
				"formattedAddress": "6 Blue Jay Ave, Brampton, ON L6P 0E2, Canada",
				"locality": "Brampton",
				"neighborhood": "Castlemore",
				"postalCode": "L6P 0E2"
			},
			"geometry": {
				"type": "Point",
				"coordinates": [
					-79.72942,
					43.79586
				]
			},
			"bbox": [
				-79.7309774,
				43.7947358,
				-79.7278626,
				43.7969842
			]
		}
	]
}
