{
	"type": "FeatureCollection",
	"features": [
		{
			"type": "Feature",
			"properties": {
				"confidence": 9,
				"authenticationResultCode": "ValidCredentials",
				"brandLogoUri": "http://dev.virtualearth.net/Branding/logo_powered_by.png",
				"copyright": "Copyright © 2017 Microsoft and its suppliers. All rights reserved. This API cannot be accessed and the content and any results may not be used, reproduced or transmitted in any manner without express written permission from Microsoft Corporation.",
				"entityType": "Address",
				"matchCodes": [
					"Good"
				],
				"name": "6 Maginn Mews, North York, ON M3C 0G9, Canada",
				"statusCode": 200,
				"statusDescription": "OK",
				"traceId": "8f6a3ae5a3724669ab345a98dce58d5d|BN20130521|7.7.0.0|",
				"addressLine": "6 Maginn Mews",
				"adminDistrict": "ON",
				"adminDistrict2": "Toronto",
				"countryRegion": "Canada",
				"formattedAddress": "6 Maginn Mews, North York, ON M3C 0G9, Canada",
				"locality": "Toronto",
				"neighborhood": "Banbury-Don Mills",
				"postalCode": "M3C 0G9"
			},
			"geometry": {
				"type": "Point",
				"coordinates": [
					-79.34559,
					43.73485
				]
			},
			"bbox": [
				-79.3471458,
				43.7337258,
				-79.3440342,
				43.7359742
			]
		}
	]
}
