{
	"type": "FeatureCollection",
	"features": [
		{
			"type": "Feature",
			"properties": {
				"confidence": 9,
				"authenticationResultCode": "ValidCredentials",
				"brandLogoUri": "http://dev.virtualearth.net/Branding/logo_powered_by.png",
				"copyright": "Copyright © 2017 Microsoft and its suppliers. All rights reserved. This API cannot be accessed and the content and any results may not be used, reproduced or transmitted in any manner without express written permission from Microsoft Corporation.",
				"entityType": "Address",
				"matchCodes": [
					"Good"
				],
				"name": "6 Rue Pine, Stanstead, QC J0B 3E5, Canada",
				"statusCode": 200,
				"statusDescription": "OK",
				"traceId": "aae7f653478a442081aa729a59f2c3c8|BN20130632|7.7.0.0|",
				"addressLine": "6 Rue Pine",
				"adminDistrict": "QC",
				"adminDistrict2": "Memphrémagog",
				"countryRegion": "Canada",
				"formattedAddress": "6 Rue Pine, Stanstead, QC J0B 3E5, Canada",
				"locality": "Stanstead",
				"postalCode": "J0B 3E5"
			},
			"geometry": {
				"type": "Point",
				"coordinates": [
					-72.1457099,
					45.00879
				]
			},
			"bbox": [
				-72.1472999,
				45.0076658,
				-72.1441199,
				45.0099142
			]
		}
	]
}
