{
	"type": "FeatureCollection",
	"features": [
		{
			"type": "Feature",
			"properties": {
				"confidence": 9,
				"authenticationResultCode": "ValidCredentials",
				"brandLogoUri": "http://dev.virtualearth.net/Branding/logo_powered_by.png",
				"copyright": "Copyright © 2017 Microsoft and its suppliers. All rights reserved. This API cannot be accessed and the content and any results may not be used, reproduced or transmitted in any manner without express written permission from Microsoft Corporation.",
				"entityType": "Address",
				"matchCodes": [
					"Good"
				],
				"name": "60 Nortoba Cres, Kanata, ON K2T 1K6, Canada",
				"statusCode": 200,
				"statusDescription": "OK",
				"traceId": "1593f33485ca4192b7f2db05148e6359|BN20130533|7.7.0.0|",
				"addressLine": "60 Nortoba Cres",
				"adminDistrict": "ON",
				"adminDistrict2": "Ottawa",
				"countryRegion": "Canada",
				"formattedAddress": "60 Nortoba Cres, Kanata, ON K2T 1K6, Canada",
				"locality": "Ottawa",
				"neighborhood": "Kanata",
				"postalCode": "K2T 1K6"
			},
			"geometry": {
				"type": "Point",
				"coordinates": [
					-75.9257,
					45.32011
				]
			},
			"bbox": [
				-75.9272987,
				45.3189858,
				-75.9241013,
				45.3212342
			]
		}
	]
}
