{
	"type": "FeatureCollection",
	"features": [
		{
			"type": "Feature",
			"properties": {
				"confidence": 9,
				"authenticationResultCode": "ValidCredentials",
				"brandLogoUri": "http://dev.virtualearth.net/Branding/logo_powered_by.png",
				"copyright": "Copyright © 2017 Microsoft and its suppliers. All rights reserved. This API cannot be accessed and the content and any results may not be used, reproduced or transmitted in any manner without express written permission from Microsoft Corporation.",
				"entityType": "Address",
				"matchCodes": [
					"Good"
				],
				"name": "60 W 3rd Ave, Vancouver, BC V5Y 1E4, Canada",
				"statusCode": 200,
				"statusDescription": "OK",
				"traceId": "3d5f7f531be146ab903506390f1628ed|BN20240253|7.7.0.0|",
				"addressLine": "60 W 3rd Ave",
				"adminDistrict": "BC",
				"adminDistrict2": "Greater Vancouver",
				"countryRegion": "Canada",
				"formattedAddress": "60 W 3rd Ave, Vancouver, BC V5Y 1E4, Canada",
				"locality": "Vancouver",
				"neighborhood": "Mt Pleasant",
				"postalCode": "V5Y 1E4"
			},
			"geometry": {
				"type": "Point",
				"coordinates": [
					-123.10599,
					49.26805
				]
			},
			"bbox": [
				-123.1077128,
				49.2669258,
				-123.1042672,
				49.2691742
			]
		}
	]
}
