{
	"type": "FeatureCollection",
	"features": [
		{
			"type": "Feature",
			"properties": {
				"confidence": 9,
				"authenticationResultCode": "ValidCredentials",
				"brandLogoUri": "http://dev.virtualearth.net/Branding/logo_powered_by.png",
				"copyright": "Copyright © 2017 Microsoft and its suppliers. All rights reserved. This API cannot be accessed and the content and any results may not be used, reproduced or transmitted in any manner without express written permission from Microsoft Corporation.",
				"entityType": "Address",
				"matchCodes": [
					"Good"
				],
				"name": "600 Garden St, Whitby, ON L1N 7B3, Canada",
				"statusCode": 200,
				"statusDescription": "OK",
				"traceId": "1a1658b5086c4903a3dc57a4cf91a0aa|BN20121762|7.7.0.0|",
				"addressLine": "600 Garden St",
				"adminDistrict": "ON",
				"adminDistrict2": "Durham",
				"countryRegion": "Canada",
				"formattedAddress": "600 Garden St, Whitby, ON L1N 7B3, Canada",
				"locality": "Whitby",
				"postalCode": "L1N 7B3"
			},
			"geometry": {
				"type": "Point",
				"coordinates": [
					-78.93632,
					43.88949
				]
			},
			"bbox": [
				-78.9378799,
				43.8883658,
				-78.9347601,
				43.8906142
			]
		}
	]
}
