{
	"type": "FeatureCollection",
	"features": [
		{
			"type": "Feature",
			"properties": {
				"confidence": 9,
				"authenticationResultCode": "ValidCredentials",
				"brandLogoUri": "http://dev.virtualearth.net/Branding/logo_powered_by.png",
				"copyright": "Copyright © 2017 Microsoft and its suppliers. All rights reserved. This API cannot be accessed and the content and any results may not be used, reproduced or transmitted in any manner without express written permission from Microsoft Corporation.",
				"entityType": "Address",
				"matchCodes": [
					"Good"
				],
				"name": "6001 St Margaret's Bay Rd, Head of St Margarets Bay, NS B3Z 2C5, Canada",
				"statusCode": 200,
				"statusDescription": "OK",
				"traceId": "4bd621b02c094c5eb832de7d762ebe18|BN20130447|7.7.0.0|",
				"addressLine": "6001 St Margaret's Bay Rd",
				"adminDistrict": "NS",
				"adminDistrict2": "Halifax",
				"countryRegion": "Canada",
				"formattedAddress": "6001 St Margaret's Bay Rd, Head of St Margarets Bay, NS B3Z 2C5, Canada",
				"locality": "Halifax",
				"neighborhood": "Head of St Margarets Bay",
				"postalCode": "B3Z 2C5"
			},
			"geometry": {
				"type": "Point",
				"coordinates": [
					-63.90938,
					44.68689
				]
			},
			"bbox": [
				-63.9109612,
				44.6857658,
				-63.9077988,
				44.6880142
			]
		}
	]
}
