{
	"type": "FeatureCollection",
	"features": [
		{
			"type": "Feature",
			"properties": {
				"confidence": 9,
				"authenticationResultCode": "ValidCredentials",
				"brandLogoUri": "http://dev.virtualearth.net/Branding/logo_powered_by.png",
				"copyright": "Copyright © 2017 Microsoft and its suppliers. All rights reserved. This API cannot be accessed and the content and any results may not be used, reproduced or transmitted in any manner without express written permission from Microsoft Corporation.",
				"entityType": "Address",
				"matchCodes": [
					"Good"
				],
				"name": "603 Colborne St, Brantford, ON N3S 7S8, Canada",
				"statusCode": 200,
				"statusDescription": "OK",
				"traceId": "09c913c669a54e708ffff54236f41947|BN20200239|7.7.0.0|",
				"addressLine": "603 Colborne St",
				"adminDistrict": "ON",
				"adminDistrict2": "Brant",
				"countryRegion": "Canada",
				"formattedAddress": "603 Colborne St, Brantford, ON N3S 7S8, Canada",
				"locality": "Brantford",
				"postalCode": "N3S 7S8"
			},
			"geometry": {
				"type": "Point",
				"coordinates": [
					-80.2422717,
					43.1399962
				]
			},
			"bbox": [
				-80.2438123,
				43.138872,
				-80.2407311,
				43.1411203
			]
		}
	]
}
