{
	"type": "FeatureCollection",
	"features": [
		{
			"type": "Feature",
			"properties": {
				"confidence": 9,
				"authenticationResultCode": "ValidCredentials",
				"brandLogoUri": "http://dev.virtualearth.net/Branding/logo_powered_by.png",
				"copyright": "Copyright © 2017 Microsoft and its suppliers. All rights reserved. This API cannot be accessed and the content and any results may not be used, reproduced or transmitted in any manner without express written permission from Microsoft Corporation.",
				"entityType": "Address",
				"matchCodes": [
					"Good"
				],
				"name": "603 50th St E, Saskatoon, SK S7K 5W8, Canada",
				"statusCode": 200,
				"statusDescription": "OK",
				"traceId": "ffc8c72d77df483b9e101d1385a4927d|BN20290118|7.7.0.0|",
				"addressLine": "603 50th St E",
				"adminDistrict": "SK",
				"adminDistrict2": "Saskatchewan",
				"countryRegion": "Canada",
				"formattedAddress": "603 50th St E, Saskatoon, SK S7K 5W8, Canada",
				"locality": "Saskatoon",
				"neighborhood": "North Industrial",
				"postalCode": "S7K 5W8"
			},
			"geometry": {
				"type": "Point",
				"coordinates": [
					-106.66007,
					52.16999
				]
			},
			"bbox": [
				-106.6619029,
				52.1688658,
				-106.6582371,
				52.1711142
			]
		}
	]
}
