{
	"type": "FeatureCollection",
	"features": [
		{
			"type": "Feature",
			"properties": {
				"confidence": 9,
				"authenticationResultCode": "ValidCredentials",
				"brandLogoUri": "http://dev.virtualearth.net/Branding/logo_powered_by.png",
				"copyright": "Copyright © 2017 Microsoft and its suppliers. All rights reserved. This API cannot be accessed and the content and any results may not be used, reproduced or transmitted in any manner without express written permission from Microsoft Corporation.",
				"entityType": "Address",
				"matchCodes": [
					"Good"
				],
				"name": "6099 Vipond Dr, Mississauga, ON L5T 2B2, Canada",
				"statusCode": 200,
				"statusDescription": "OK",
				"traceId": "1b0154c9facc40498eeeb5a6e4313792|BN20320521|7.7.0.0|",
				"addressLine": "6099 Vipond Dr",
				"adminDistrict": "ON",
				"adminDistrict2": "Peel",
				"countryRegion": "Canada",
				"formattedAddress": "6099 Vipond Dr, Mississauga, ON L5T 2B2, Canada",
				"locality": "Mississauga",
				"postalCode": "L5T 2B2"
			},
			"geometry": {
				"type": "Point",
				"coordinates": [
					-79.65188,
					43.65363
				]
			},
			"bbox": [
				-79.6534337,
				43.6525058,
				-79.6503263,
				43.6547542
			]
		}
	]
}
