{
	"type": "FeatureCollection",
	"features": [
		{
			"type": "Feature",
			"properties": {
				"confidence": 9,
				"authenticationResultCode": "ValidCredentials",
				"brandLogoUri": "http://dev.virtualearth.net/Branding/logo_powered_by.png",
				"copyright": "Copyright © 2017 Microsoft and its suppliers. All rights reserved. This API cannot be accessed and the content and any results may not be used, reproduced or transmitted in any manner without express written permission from Microsoft Corporation.",
				"entityType": "Address",
				"matchCodes": [
					"Good"
				],
				"name": "61 Brack Pl, Thornhill, ON L4J 2W3, Canada",
				"statusCode": 200,
				"statusDescription": "OK",
				"traceId": "d9c9eeac8d8f4b3bbf445c751ec59da9|BN20190653|7.7.0.0|",
				"addressLine": "61 Brack Pl",
				"adminDistrict": "ON",
				"adminDistrict2": "York",
				"countryRegion": "Canada",
				"formattedAddress": "61 Brack Pl, Thornhill, ON L4J 2W3, Canada",
				"locality": "Vaughan",
				"neighborhood": "Thornhill",
				"postalCode": "L4J 2W3"
			},
			"geometry": {
				"type": "Point",
				"coordinates": [
					-79.46454,
					43.78991
				]
			},
			"bbox": [
				-79.4660973,
				43.7887858,
				-79.4629827,
				43.7910342
			]
		}
	]
}
