{
	"type": "FeatureCollection",
	"features": [
		{
			"type": "Feature",
			"properties": {
				"confidence": 9,
				"authenticationResultCode": "ValidCredentials",
				"brandLogoUri": "http://dev.virtualearth.net/Branding/logo_powered_by.png",
				"copyright": "Copyright © 2017 Microsoft and its suppliers. All rights reserved. This API cannot be accessed and the content and any results may not be used, reproduced or transmitted in any manner without express written permission from Microsoft Corporation.",
				"entityType": "Address",
				"matchCodes": [
					"Good"
				],
				"name": "61 Shaver St, Brantford, ON N3T 5M1, Canada",
				"statusCode": 200,
				"statusDescription": "OK",
				"traceId": "37e0dae2da16448abf3bea2e2bc71aad|BN20280152|7.7.0.0|",
				"addressLine": "61 Shaver St",
				"adminDistrict": "ON",
				"adminDistrict2": "Brant",
				"countryRegion": "Canada",
				"formattedAddress": "61 Shaver St, Brantford, ON N3T 5M1, Canada",
				"locality": "Brant",
				"neighborhood": "Brantford",
				"postalCode": "N3T 5M1"
			},
			"geometry": {
				"type": "Point",
				"coordinates": [
					-80.1852599,
					43.1442638
				]
			},
			"bbox": [
				-80.1868006,
				43.1431397,
				-80.1837192,
				43.145388
			]
		}
	]
}
