{
	"type": "FeatureCollection",
	"features": [
		{
			"type": "Feature",
			"properties": {
				"confidence": 9,
				"authenticationResultCode": "ValidCredentials",
				"brandLogoUri": "http://dev.virtualearth.net/Branding/logo_powered_by.png",
				"copyright": "Copyright © 2017 Microsoft and its suppliers. All rights reserved. This API cannot be accessed and the content and any results may not be used, reproduced or transmitted in any manner without express written permission from Microsoft Corporation.",
				"entityType": "Address",
				"matchCodes": [
					"Good"
				],
				"name": "6185 Morton Industrial Dr, Lasalle, ON N9J, Canada",
				"statusCode": 200,
				"statusDescription": "OK",
				"traceId": "31fa06a85c2e42d3a1929bd037f9c80d|BN20200239|7.7.0.0|",
				"addressLine": "6185 Morton Industrial Dr",
				"adminDistrict": "ON",
				"adminDistrict2": "Essex",
				"countryRegion": "Canada",
				"formattedAddress": "6185 Morton Industrial Dr, Lasalle, ON N9J, Canada",
				"locality": "Lasalle",
				"neighborhood": "Windsor",
				"postalCode": "N9J 3W2"
			},
			"geometry": {
				"type": "Point",
				"coordinates": [
					-83.0964874,
					42.2485061
				]
			},
			"bbox": [
				-83.098006,
				42.247382,
				-83.0949688,
				42.2496303
			]
		}
	]
}
