{
	"type": "FeatureCollection",
	"features": [
		{
			"type": "Feature",
			"properties": {
				"confidence": 9,
				"authenticationResultCode": "ValidCredentials",
				"brandLogoUri": "http://dev.virtualearth.net/Branding/logo_powered_by.png",
				"copyright": "Copyright © 2017 Microsoft and its suppliers. All rights reserved. This API cannot be accessed and the content and any results may not be used, reproduced or transmitted in any manner without express written permission from Microsoft Corporation.",
				"entityType": "Address",
				"matchCodes": [
					"Good"
				],
				"name": "62 10th St SW, Portage la Prairie, MB R1N 2P8, Canada",
				"statusCode": 200,
				"statusDescription": "OK",
				"traceId": "c68758d605d84b7e8b0b080dc3799114|BN20130625|7.7.0.0|",
				"addressLine": "62 10th St SW",
				"adminDistrict": "MB",
				"adminDistrict2": "Manitoba",
				"countryRegion": "Canada",
				"formattedAddress": "62 10th St SW, Portage la Prairie, MB R1N 2P8, Canada",
				"locality": "Portage la Prairie",
				"postalCode": "R1N 2P8"
			},
			"geometry": {
				"type": "Point",
				"coordinates": [
					-98.3039794,
					49.9722846
				]
			},
			"bbox": [
				-98.3057273,
				49.9711604,
				-98.3022315,
				49.9734088
			]
		}
	]
}
