{
	"type": "FeatureCollection",
	"features": [
		{
			"type": "Feature",
			"properties": {
				"confidence": 9,
				"authenticationResultCode": "ValidCredentials",
				"brandLogoUri": "http://dev.virtualearth.net/Branding/logo_powered_by.png",
				"copyright": "Copyright © 2017 Microsoft and its suppliers. All rights reserved. This API cannot be accessed and the content and any results may not be used, reproduced or transmitted in any manner without express written permission from Microsoft Corporation.",
				"entityType": "Address",
				"matchCodes": [
					"Good"
				],
				"name": "62 Candy Mountain Rd, Mineville, NS B2Z 1K6, Canada",
				"statusCode": 200,
				"statusDescription": "OK",
				"traceId": "6cc8757206d8484f8535770b8d74fe11|BN20130532|7.7.0.0|",
				"addressLine": "62 Candy Mountain Rd",
				"adminDistrict": "NS",
				"adminDistrict2": "Halifax",
				"countryRegion": "Canada",
				"formattedAddress": "62 Candy Mountain Rd, Mineville, NS B2Z 1K6, Canada",
				"locality": "Halifax",
				"neighborhood": "Mineville",
				"postalCode": "B2Z 1K6"
			},
			"geometry": {
				"type": "Point",
				"coordinates": [
					-63.3654663,
					44.6905999
				]
			},
			"bbox": [
				-63.3670475,
				44.6894757,
				-63.363885,
				44.691724
			]
		}
	]
}
