{
	"type": "FeatureCollection",
	"features": [
		{
			"type": "Feature",
			"properties": {
				"confidence": 9,
				"authenticationResultCode": "ValidCredentials",
				"brandLogoUri": "http://dev.virtualearth.net/Branding/logo_powered_by.png",
				"copyright": "Copyright © 2017 Microsoft and its suppliers. All rights reserved. This API cannot be accessed and the content and any results may not be used, reproduced or transmitted in any manner without express written permission from Microsoft Corporation.",
				"entityType": "Address",
				"matchCodes": [
					"Good"
				],
				"name": "62 Glencairn Ave, Ottawa, ON K1S 1M6, Canada",
				"statusCode": 200,
				"statusDescription": "OK",
				"traceId": "ee208f7691c24be4a1b110a1bbe83aac|BN20171457|7.7.0.0|",
				"addressLine": "62 Glencairn Ave",
				"adminDistrict": "ON",
				"adminDistrict2": "Ottawa",
				"countryRegion": "Canada",
				"formattedAddress": "62 Glencairn Ave, Ottawa, ON K1S 1M6, Canada",
				"locality": "Ottawa",
				"neighborhood": "Golden Triangle-Old Ottawa East",
				"postalCode": "K1S 1M6"
			},
			"geometry": {
				"type": "Point",
				"coordinates": [
					-75.67542,
					45.4004
				]
			},
			"bbox": [
				-75.677021,
				45.3992758,
				-75.673819,
				45.4015242
			]
		}
	]
}
