{
	"type": "FeatureCollection",
	"features": [
		{
			"type": "Feature",
			"properties": {
				"confidence": 9,
				"authenticationResultCode": "ValidCredentials",
				"brandLogoUri": "http://dev.virtualearth.net/Branding/logo_powered_by.png",
				"copyright": "Copyright © 2017 Microsoft and its suppliers. All rights reserved. This API cannot be accessed and the content and any results may not be used, reproduced or transmitted in any manner without express written permission from Microsoft Corporation.",
				"entityType": "Address",
				"matchCodes": [
					"Good"
				],
				"name": "620 Wellington Ave, Chilliwack, BC V2R, Canada",
				"statusCode": 200,
				"statusDescription": "OK",
				"traceId": "1194d95205324bfb8e068f5749e482df|BN20130632|7.7.0.0|",
				"addressLine": "620 Wellington Ave",
				"adminDistrict": "BC",
				"adminDistrict2": "Fraser Valley",
				"countryRegion": "Canada",
				"formattedAddress": "620 Wellington Ave, Chilliwack, BC V2R, Canada",
				"locality": "Chilliwack",
				"neighborhood": "Chilliwack Proper Village West",
				"postalCode": "V2R"
			},
			"geometry": {
				"type": "Point",
				"coordinates": [
					-121.9717889,
					49.177139
				]
			},
			"bbox": [
				-121.9735085,
				49.1760149,
				-121.9700692,
				49.1782632
			]
		}
	]
}
