{
	"type": "FeatureCollection",
	"features": [
		{
			"type": "Feature",
			"properties": {
				"confidence": 9,
				"authenticationResultCode": "ValidCredentials",
				"brandLogoUri": "http://dev.virtualearth.net/Branding/logo_powered_by.png",
				"copyright": "Copyright © 2017 Microsoft and its suppliers. All rights reserved. This API cannot be accessed and the content and any results may not be used, reproduced or transmitted in any manner without express written permission from Microsoft Corporation.",
				"entityType": "Address",
				"matchCodes": [
					"Good"
				],
				"name": "621 Route de Tadoussac, Saguenay, QC G7H, Canada",
				"statusCode": 200,
				"statusDescription": "OK",
				"traceId": "0ccfec9266414fc1965ee9b9b92ba944|BN20190653|7.7.0.0|",
				"addressLine": "621 Route de Tadoussac",
				"adminDistrict": "QC",
				"adminDistrict2": "Saguenay",
				"countryRegion": "Canada",
				"formattedAddress": "621 Route de Tadoussac, Saguenay, QC G7H, Canada",
				"locality": "Saguenay",
				"neighborhood": "Tremblay",
				"postalCode": "G7H 5A8"
			},
			"geometry": {
				"type": "Point",
				"coordinates": [
					-71.01828,
					48.45177
				]
			},
			"bbox": [
				-71.0199749,
				48.4506458,
				-71.0165851,
				48.4528942
			]
		}
	]
}
