{
	"type": "FeatureCollection",
	"features": [
		{
			"type": "Feature",
			"properties": {
				"confidence": 9,
				"authenticationResultCode": "ValidCredentials",
				"brandLogoUri": "http://dev.virtualearth.net/Branding/logo_powered_by.png",
				"copyright": "Copyright © 2017 Microsoft and its suppliers. All rights reserved. This API cannot be accessed and the content and any results may not be used, reproduced or transmitted in any manner without express written permission from Microsoft Corporation.",
				"entityType": "Address",
				"matchCodes": [
					"Good"
				],
				"name": "6210 4th Line Rd, Ottawa, ON K0A, Canada",
				"statusCode": 200,
				"statusDescription": "OK",
				"traceId": "c0c2f5098f11489a9c6595a8959abd53|BN20130530|7.7.0.0|",
				"addressLine": "6210 4th Line Rd",
				"adminDistrict": "ON",
				"adminDistrict2": "Ottawa",
				"countryRegion": "Canada",
				"formattedAddress": "6210 4th Line Rd, Ottawa, ON K0A, Canada",
				"locality": "Ottawa",
				"neighborhood": "North Gower",
				"postalCode": "K0A 2T0"
			},
			"geometry": {
				"type": "Point",
				"coordinates": [
					-75.7476499,
					45.14878
				]
			},
			"bbox": [
				-75.7492438,
				45.1476558,
				-75.746056,
				45.1499042
			]
		}
	]
}
