{
	"type": "FeatureCollection",
	"features": [
		{
			"type": "Feature",
			"properties": {
				"confidence": 9,
				"authenticationResultCode": "ValidCredentials",
				"brandLogoUri": "http://dev.virtualearth.net/Branding/logo_powered_by.png",
				"copyright": "Copyright © 2017 Microsoft and its suppliers. All rights reserved. This API cannot be accessed and the content and any results may not be used, reproduced or transmitted in any manner without express written permission from Microsoft Corporation.",
				"entityType": "Address",
				"matchCodes": [
					"Good"
				],
				"name": "6215 Mississauga Rd, Mississauga, ON L5N 1A4, Canada",
				"statusCode": 200,
				"statusDescription": "OK",
				"traceId": "84eba6727d5f47bcbacf60e3d3563cdb|BN20121762|7.7.0.0|",
				"addressLine": "6215 Mississauga Rd",
				"adminDistrict": "ON",
				"adminDistrict2": "Peel",
				"countryRegion": "Canada",
				"formattedAddress": "6215 Mississauga Rd, Mississauga, ON L5N 1A4, Canada",
				"locality": "Mississauga",
				"neighborhood": "Meadowvale",
				"postalCode": "L5N 1A4"
			},
			"geometry": {
				"type": "Point",
				"coordinates": [
					-79.72772,
					43.59256
				]
			},
			"bbox": [
				-79.7292721,
				43.5914358,
				-79.7261679,
				43.5936842
			]
		}
	]
}
