{
	"type": "FeatureCollection",
	"features": [
		{
			"type": "Feature",
			"properties": {
				"confidence": 9,
				"authenticationResultCode": "ValidCredentials",
				"brandLogoUri": "http://dev.virtualearth.net/Branding/logo_powered_by.png",
				"copyright": "Copyright © 2017 Microsoft and its suppliers. All rights reserved. This API cannot be accessed and the content and any results may not be used, reproduced or transmitted in any manner without express written permission from Microsoft Corporation.",
				"entityType": "Address",
				"matchCodes": [
					"Good"
				],
				"name": "6235 Tomken Rd, Mississauga, ON L5T 1K2, Canada",
				"statusCode": 200,
				"statusDescription": "OK",
				"traceId": "97190551c50146848ec4913fb3609b38|BN20260223|7.7.0.0|",
				"addressLine": "6235 Tomken Rd",
				"adminDistrict": "ON",
				"adminDistrict2": "Peel",
				"countryRegion": "Canada",
				"formattedAddress": "6235 Tomken Rd, Mississauga, ON L5T 1K2, Canada",
				"locality": "Mississauga",
				"postalCode": "L5T 1K2"
			},
			"geometry": {
				"type": "Point",
				"coordinates": [
					-79.6665699,
					43.65263
				]
			},
			"bbox": [
				-79.6681236,
				43.6515058,
				-79.6650162,
				43.6537542
			]
		}
	]
}
