{
	"type": "FeatureCollection",
	"features": [
		{
			"type": "Feature",
			"properties": {
				"confidence": 9,
				"authenticationResultCode": "ValidCredentials",
				"brandLogoUri": "http://dev.virtualearth.net/Branding/logo_powered_by.png",
				"copyright": "Copyright © 2017 Microsoft and its suppliers. All rights reserved. This API cannot be accessed and the content and any results may not be used, reproduced or transmitted in any manner without express written permission from Microsoft Corporation.",
				"entityType": "Address",
				"matchCodes": [
					"Good"
				],
				"name": "63 Browning Trl, Barrie, ON L4N 5A5, Canada",
				"statusCode": 200,
				"statusDescription": "OK",
				"traceId": "b3702da285714f5e9bb59bd3414a1ac9|BN20240253|7.7.0.0|",
				"addressLine": "63 Browning Trl",
				"adminDistrict": "ON",
				"adminDistrict2": "Simcoe",
				"countryRegion": "Canada",
				"formattedAddress": "63 Browning Trl, Barrie, ON L4N 5A5, Canada",
				"locality": "Barrie",
				"postalCode": "L4N 5A5"
			},
			"geometry": {
				"type": "Point",
				"coordinates": [
					-79.72238,
					44.38594
				]
			},
			"bbox": [
				-79.723953,
				44.3848158,
				-79.720807,
				44.3870642
			]
		}
	]
}
