{
	"type": "FeatureCollection",
	"features": [
		{
			"type": "Feature",
			"properties": {
				"confidence": 9,
				"authenticationResultCode": "ValidCredentials",
				"brandLogoUri": "http://dev.virtualearth.net/Branding/logo_powered_by.png",
				"copyright": "Copyright © 2017 Microsoft and its suppliers. All rights reserved. This API cannot be accessed and the content and any results may not be used, reproduced or transmitted in any manner without express written permission from Microsoft Corporation.",
				"entityType": "Address",
				"matchCodes": [
					"Good"
				],
				"name": "63 Union St, Elmira, ON N3B 2Y3, Canada",
				"statusCode": 200,
				"statusDescription": "OK",
				"traceId": "352230a354e64acea0f75ed9382b206f|BN20121764|7.7.0.0|",
				"addressLine": "63 Union St",
				"adminDistrict": "ON",
				"adminDistrict2": "Waterloo",
				"countryRegion": "Canada",
				"formattedAddress": "63 Union St, Elmira, ON N3B 2Y3, Canada",
				"locality": "Woolwich",
				"neighborhood": "Elmira",
				"postalCode": "N3B 2Y3"
			},
			"geometry": {
				"type": "Point",
				"coordinates": [
					-80.5540772,
					43.5890502
				]
			},
			"bbox": [
				-80.5556292,
				43.587926,
				-80.5525252,
				43.5901743
			]
		}
	]
}
