{
	"type": "FeatureCollection",
	"features": [
		{
			"type": "Feature",
			"properties": {
				"confidence": 9,
				"authenticationResultCode": "ValidCredentials",
				"brandLogoUri": "http://dev.virtualearth.net/Branding/logo_powered_by.png",
				"copyright": "Copyright © 2017 Microsoft and its suppliers. All rights reserved. This API cannot be accessed and the content and any results may not be used, reproduced or transmitted in any manner without express written permission from Microsoft Corporation.",
				"entityType": "Address",
				"matchCodes": [
					"Good"
				],
				"name": "630 Esquimalt Rd, Victoria, BC V9A 3L4, Canada",
				"statusCode": 200,
				"statusDescription": "OK",
				"traceId": "27d2f437b6c04324b2a7dcdf5e898606|BN20130521|7.7.0.0|",
				"addressLine": "630 Esquimalt Rd",
				"adminDistrict": "BC",
				"adminDistrict2": "Capital",
				"countryRegion": "Canada",
				"formattedAddress": "630 Esquimalt Rd, Victoria, BC V9A 3L4, Canada",
				"locality": "Victoria",
				"neighborhood": "Victoria West",
				"postalCode": "V9A 3L4"
			},
			"geometry": {
				"type": "Point",
				"coordinates": [
					-123.39024,
					48.43157
				]
			},
			"bbox": [
				-123.3919342,
				48.4304458,
				-123.3885458,
				48.4326942
			]
		}
	]
}
