{
	"type": "FeatureCollection",
	"features": [
		{
			"type": "Feature",
			"properties": {
				"confidence": 9,
				"authenticationResultCode": "ValidCredentials",
				"brandLogoUri": "http://dev.virtualearth.net/Branding/logo_powered_by.png",
				"copyright": "Copyright © 2017 Microsoft and its suppliers. All rights reserved. This API cannot be accessed and the content and any results may not be used, reproduced or transmitted in any manner without express written permission from Microsoft Corporation.",
				"entityType": "Address",
				"matchCodes": [
					"Good"
				],
				"name": "630 Rue Desmarais, Richmond, QC J0B 2H0, Canada",
				"statusCode": 200,
				"statusDescription": "OK",
				"traceId": "3a508d6c87e7475e8e01ab7501ce732f|BN20130632|7.7.0.0|",
				"addressLine": "630 Rue Desmarais",
				"adminDistrict": "QC",
				"adminDistrict2": "Le Val-St-François",
				"countryRegion": "Canada",
				"formattedAddress": "630 Rue Desmarais, Richmond, QC J0B 2H0, Canada",
				"locality": "Richmond",
				"postalCode": "J0B 2H0"
			},
			"geometry": {
				"type": "Point",
				"coordinates": [
					-72.12864,
					45.6624
				]
			},
			"bbox": [
				-72.1302485,
				45.6612758,
				-72.1270315,
				45.6635242
			]
		}
	]
}
