{
	"type": "FeatureCollection",
	"features": [
		{
			"type": "Feature",
			"properties": {
				"confidence": 8,
				"authenticationResultCode": "ValidCredentials",
				"brandLogoUri": "http://dev.virtualearth.net/Branding/logo_powered_by.png",
				"copyright": "Copyright © 2017 Microsoft and its suppliers. All rights reserved. This API cannot be accessed and the content and any results may not be used, reproduced or transmitted in any manner without express written permission from Microsoft Corporation.",
				"entityType": "RoadBlock",
				"matchCodes": [
					"UpHierarchy"
				],
				"name": "Laurila Rd, Charlton and Dack, ON P0J, Canada",
				"statusCode": 200,
				"statusDescription": "OK",
				"traceId": "910cfad3214b4232a513a3b6d0d1f84f|BN20250135|7.7.0.0|",
				"addressLine": "Laurila Rd",
				"adminDistrict": "ON",
				"adminDistrict2": "Timiskaming",
				"countryRegion": "Canada",
				"formattedAddress": "Laurila Rd, Charlton and Dack, ON P0J, Canada",
				"locality": "Charlton and Dack",
				"postalCode": "P0J 1B0"
			},
			"geometry": {
				"type": "Point",
				"coordinates": [
					-79.99609,
					47.82407
				]
			},
			"bbox": [
				-79.99619,
				47.82123,
				-79.996,
				47.82691
			]
		}
	]
}
