{
	"type": "FeatureCollection",
	"features": [
		{
			"type": "Feature",
			"properties": {
				"confidence": 9,
				"authenticationResultCode": "ValidCredentials",
				"brandLogoUri": "http://dev.virtualearth.net/Branding/logo_powered_by.png",
				"copyright": "Copyright © 2017 Microsoft and its suppliers. All rights reserved. This API cannot be accessed and the content and any results may not be used, reproduced or transmitted in any manner without express written permission from Microsoft Corporation.",
				"entityType": "Address",
				"matchCodes": [
					"Good"
				],
				"name": "6343 Alderwood Trl, Mississauga, ON L5N 6X1, Canada",
				"statusCode": 200,
				"statusDescription": "OK",
				"traceId": "a41110e923114d53ba6dd340d6624d6f|BN20181720|7.7.0.0|",
				"addressLine": "6343 Alderwood Trl",
				"adminDistrict": "ON",
				"adminDistrict2": "Peel",
				"countryRegion": "Canada",
				"formattedAddress": "6343 Alderwood Trl, Mississauga, ON L5N 6X1, Canada",
				"locality": "Mississauga",
				"neighborhood": "Meadowvale",
				"postalCode": "L5N 6X1"
			},
			"geometry": {
				"type": "Point",
				"coordinates": [
					-79.76775,
					43.56552
				]
			},
			"bbox": [
				-79.7693014,
				43.5643958,
				-79.7661986,
				43.5666442
			]
		}
	]
}
