{
	"type": "FeatureCollection",
	"features": [
		{
			"type": "Feature",
			"properties": {
				"confidence": 9,
				"authenticationResultCode": "ValidCredentials",
				"brandLogoUri": "http://dev.virtualearth.net/Branding/logo_powered_by.png",
				"copyright": "Copyright © 2017 Microsoft and its suppliers. All rights reserved. This API cannot be accessed and the content and any results may not be used, reproduced or transmitted in any manner without express written permission from Microsoft Corporation.",
				"entityType": "Address",
				"matchCodes": [
					"Good"
				],
				"name": "64 Alexander St, Belleville, ON K8N 2H3, Canada",
				"statusCode": 200,
				"statusDescription": "OK",
				"traceId": "668414ed16534b2a8a3715c8a12b5058|BN20190642|7.7.0.0|",
				"addressLine": "64 Alexander St",
				"adminDistrict": "ON",
				"adminDistrict2": "Hastings",
				"countryRegion": "Canada",
				"formattedAddress": "64 Alexander St, Belleville, ON K8N 2H3, Canada",
				"locality": "Belleville",
				"postalCode": "K8N 2H3"
			},
			"geometry": {
				"type": "Point",
				"coordinates": [
					-77.37909,
					44.17145
				]
			},
			"bbox": [
				-77.3806573,
				44.1703258,
				-77.3775227,
				44.1725742
			]
		}
	]
}
