{
	"type": "FeatureCollection",
	"features": [
		{
			"type": "Feature",
			"properties": {
				"confidence": 9,
				"authenticationResultCode": "ValidCredentials",
				"brandLogoUri": "http://dev.virtualearth.net/Branding/logo_powered_by.png",
				"copyright": "Copyright © 2017 Microsoft and its suppliers. All rights reserved. This API cannot be accessed and the content and any results may not be used, reproduced or transmitted in any manner without express written permission from Microsoft Corporation.",
				"entityType": "Address",
				"matchCodes": [
					"Good"
				],
				"name": "64 Signet Dr, North York, ON M9L 2Y4, Canada",
				"statusCode": 200,
				"statusDescription": "OK",
				"traceId": "a471a925031c4839bec6e4e4a8d42ab5|BN20220145|7.7.0.0|",
				"addressLine": "64 Signet Dr",
				"adminDistrict": "ON",
				"adminDistrict2": "Toronto",
				"countryRegion": "Canada",
				"formattedAddress": "64 Signet Dr, North York, ON M9L 2Y4, Canada",
				"locality": "Toronto",
				"neighborhood": "Humber Summit",
				"postalCode": "M9L 2Y4"
			},
			"geometry": {
				"type": "Point",
				"coordinates": [
					-79.53936,
					43.75755
				]
			},
			"bbox": [
				-79.5409164,
				43.7564258,
				-79.5378036,
				43.7586742
			]
		}
	]
}
