{
	"type": "FeatureCollection",
	"features": [
		{
			"type": "Feature",
			"properties": {
				"confidence": 9,
				"authenticationResultCode": "ValidCredentials",
				"brandLogoUri": "http://dev.virtualearth.net/Branding/logo_powered_by.png",
				"copyright": "Copyright © 2017 Microsoft and its suppliers. All rights reserved. This API cannot be accessed and the content and any results may not be used, reproduced or transmitted in any manner without express written permission from Microsoft Corporation.",
				"entityType": "Address",
				"matchCodes": [
					"Good"
				],
				"name": "64 Temperance St, Aurora, ON L4G 2P8, Canada",
				"statusCode": 200,
				"statusDescription": "OK",
				"traceId": "02ac42e7ac9c4db08299764ed84ae9f7|BN20300154|7.7.0.0|",
				"addressLine": "64 Temperance St",
				"adminDistrict": "ON",
				"adminDistrict2": "York",
				"countryRegion": "Canada",
				"formattedAddress": "64 Temperance St, Aurora, ON L4G 2P8, Canada",
				"locality": "Aurora",
				"postalCode": "L4G 2P8"
			},
			"geometry": {
				"type": "Point",
				"coordinates": [
					-79.46854,
					43.99697
				]
			},
			"bbox": [
				-79.4701027,
				43.9958458,
				-79.4669773,
				43.9980942
			]
		}
	]
}
