{
	"type": "FeatureCollection",
	"features": [
		{
			"type": "Feature",
			"properties": {
				"confidence": 9,
				"authenticationResultCode": "ValidCredentials",
				"brandLogoUri": "http://dev.virtualearth.net/Branding/logo_powered_by.png",
				"copyright": "Copyright © 2017 Microsoft and its suppliers. All rights reserved. This API cannot be accessed and the content and any results may not be used, reproduced or transmitted in any manner without express written permission from Microsoft Corporation.",
				"entityType": "Address",
				"matchCodes": [
					"Good"
				],
				"name": "640 Trudale Ct, Oakville, ON L6L 4H1, Canada",
				"statusCode": 200,
				"statusDescription": "OK",
				"traceId": "27cbca6ec64943bdbc06de4c1780956f|BN20130625|7.7.0.0|",
				"addressLine": "640 Trudale Ct",
				"adminDistrict": "ON",
				"adminDistrict2": "Halton",
				"countryRegion": "Canada",
				"formattedAddress": "640 Trudale Ct, Oakville, ON L6L 4H1, Canada",
				"locality": "Oakville",
				"postalCode": "L6L 4H1"
			},
			"geometry": {
				"type": "Point",
				"coordinates": [
					-79.71043,
					43.41842
				]
			},
			"bbox": [
				-79.7119777,
				43.4172958,
				-79.7088823,
				43.4195442
			]
		}
	]
}
