{
	"type": "FeatureCollection",
	"features": [
		{
			"type": "Feature",
			"properties": {
				"confidence": 9,
				"authenticationResultCode": "ValidCredentials",
				"brandLogoUri": "http://dev.virtualearth.net/Branding/logo_powered_by.png",
				"copyright": "Copyright © 2017 Microsoft and its suppliers. All rights reserved. This API cannot be accessed and the content and any results may not be used, reproduced or transmitted in any manner without express written permission from Microsoft Corporation.",
				"entityType": "Address",
				"matchCodes": [
					"Good"
				],
				"name": "649 Derwent Way, Delta, BC V3M 5P7, Canada",
				"statusCode": 200,
				"statusDescription": "OK",
				"traceId": "85cdf75a1565415394e332f3ecdd9037|BN20130522|7.7.0.0|",
				"addressLine": "649 Derwent Way",
				"adminDistrict": "BC",
				"adminDistrict2": "Greater Vancouver",
				"countryRegion": "Canada",
				"formattedAddress": "649 Derwent Way, Delta, BC V3M 5P7, Canada",
				"locality": "Delta",
				"postalCode": "V3M 5P7"
			},
			"geometry": {
				"type": "Point",
				"coordinates": [
					-122.93068,
					49.18006
				]
			},
			"bbox": [
				-122.9323997,
				49.1789358,
				-122.9289603,
				49.1811842
			]
		}
	]
}
