{
	"type": "FeatureCollection",
	"features": [
		{
			"type": "Feature",
			"properties": {
				"confidence": 9,
				"authenticationResultCode": "ValidCredentials",
				"brandLogoUri": "http://dev.virtualearth.net/Branding/logo_powered_by.png",
				"copyright": "Copyright © 2017 Microsoft and its suppliers. All rights reserved. This API cannot be accessed and the content and any results may not be used, reproduced or transmitted in any manner without express written permission from Microsoft Corporation.",
				"entityType": "Address",
				"matchCodes": [
					"Good"
				],
				"name": "65 Neil Ave, Stittsville, ON K2S 1B9, Canada",
				"statusCode": 200,
				"statusDescription": "OK",
				"traceId": "f3b281e598b34826824fb4ec59a1673a|CO30276240|7.7.0.0|",
				"addressLine": "65 Neil Ave",
				"adminDistrict": "ON",
				"adminDistrict2": "Ottawa",
				"countryRegion": "Canada",
				"formattedAddress": "65 Neil Ave, Stittsville, ON K2S 1B9, Canada",
				"locality": "Ottawa",
				"neighborhood": "Stittsville",
				"postalCode": "K2S 1B9"
			},
			"geometry": {
				"type": "Point",
				"coordinates": [
					-75.93587,
					45.26826
				]
			},
			"bbox": [
				-75.9374673,
				45.2671358,
				-75.9342727,
				45.2693842
			]
		}
	]
}
