{
	"type": "FeatureCollection",
	"features": [
		{
			"type": "Feature",
			"properties": {
				"confidence": 9,
				"authenticationResultCode": "ValidCredentials",
				"brandLogoUri": "http://dev.virtualearth.net/Branding/logo_powered_by.png",
				"copyright": "Copyright © 2017 Microsoft and its suppliers. All rights reserved. This API cannot be accessed and the content and any results may not be used, reproduced or transmitted in any manner without express written permission from Microsoft Corporation.",
				"entityType": "Address",
				"matchCodes": [
					"Good"
				],
				"name": "6503 Mississauga Rd, Mississauga, ON L5N 1A6, Canada",
				"statusCode": 200,
				"statusDescription": "OK",
				"traceId": "ab463ca40b40454ab1b42ee7878675f8|BN20280152|7.7.0.0|",
				"addressLine": "6503 Mississauga Rd",
				"adminDistrict": "ON",
				"adminDistrict2": "Peel",
				"countryRegion": "Canada",
				"formattedAddress": "6503 Mississauga Rd, Mississauga, ON L5N 1A6, Canada",
				"locality": "Mississauga",
				"neighborhood": "Meadowvale",
				"postalCode": "L5N 1A6"
			},
			"geometry": {
				"type": "Point",
				"coordinates": [
					-79.7363,
					43.5982399
				]
			},
			"bbox": [
				-79.7378523,
				43.5971157,
				-79.7347477,
				43.5993641
			]
		}
	]
}
