{
	"type": "FeatureCollection",
	"features": [
		{
			"type": "Feature",
			"properties": {
				"confidence": 9,
				"authenticationResultCode": "ValidCredentials",
				"brandLogoUri": "http://dev.virtualearth.net/Branding/logo_powered_by.png",
				"copyright": "Copyright © 2017 Microsoft and its suppliers. All rights reserved. This API cannot be accessed and the content and any results may not be used, reproduced or transmitted in any manner without express written permission from Microsoft Corporation.",
				"entityType": "RoadBlock",
				"matchCodes": [
					"UpHierarchy"
				],
				"name": "104th St, Thunder Bay, ON P7E 6B6, Canada",
				"statusCode": 200,
				"statusDescription": "OK",
				"traceId": "6629e281251b4c438426af5aab798781|BN20130422|7.7.0.0|",
				"addressLine": "104th St",
				"adminDistrict": "ON",
				"adminDistrict2": "Thunder Bay",
				"countryRegion": "Canada",
				"formattedAddress": "104th St, Thunder Bay, ON P7E 6B6, Canada",
				"locality": "Thunder Bay",
				"postalCode": "P7E 6B6"
			},
			"geometry": {
				"type": "Point",
				"coordinates": [
					-89.23766,
					48.37501
				]
			},
			"bbox": [
				-89.24252,
				48.37498,
				-89.2372,
				48.37501
			]
		}
	]
}
