{
	"type": "FeatureCollection",
	"features": [
		{
			"type": "Feature",
			"properties": {
				"confidence": 9,
				"authenticationResultCode": "ValidCredentials",
				"brandLogoUri": "http://dev.virtualearth.net/Branding/logo_powered_by.png",
				"copyright": "Copyright © 2017 Microsoft and its suppliers. All rights reserved. This API cannot be accessed and the content and any results may not be used, reproduced or transmitted in any manner without express written permission from Microsoft Corporation.",
				"entityType": "Address",
				"matchCodes": [
					"Good"
				],
				"name": "6536 HWY-332, Upper Lahave, NS B4V 7B4, Canada",
				"statusCode": 200,
				"statusDescription": "OK",
				"traceId": "cf7f297904e948699013b040bd6a79ab|BN20130522|7.7.0.0|",
				"addressLine": "6536 HWY-332",
				"adminDistrict": "NS",
				"adminDistrict2": "Lunenburg",
				"countryRegion": "Canada",
				"formattedAddress": "6536 HWY-332, Upper Lahave, NS B4V 7B4, Canada",
				"locality": "Lunenburg Municipal District",
				"neighborhood": "Upper Lahave",
				"postalCode": "B4V 7B4"
			},
			"geometry": {
				"type": "Point",
				"coordinates": [
					-64.4405041,
					44.3612478
				]
			},
			"bbox": [
				-64.4420765,
				44.3601236,
				-64.4389318,
				44.3623719
			]
		}
	]
}
