{
	"type": "FeatureCollection",
	"features": [
		{
			"type": "Feature",
			"properties": {
				"confidence": 9,
				"authenticationResultCode": "ValidCredentials",
				"brandLogoUri": "http://dev.virtualearth.net/Branding/logo_powered_by.png",
				"copyright": "Copyright © 2017 Microsoft and its suppliers. All rights reserved. This API cannot be accessed and the content and any results may not be used, reproduced or transmitted in any manner without express written permission from Microsoft Corporation.",
				"entityType": "Address",
				"matchCodes": [
					"Good"
				],
				"name": "6555 Malden Rd, Windsor, ON N9H 1T5, Canada",
				"statusCode": 200,
				"statusDescription": "OK",
				"traceId": "e0a82438990c4371be622a2c91301b9c|BN20130532|7.7.0.0|",
				"addressLine": "6555 Malden Rd",
				"adminDistrict": "ON",
				"adminDistrict2": "Essex",
				"countryRegion": "Canada",
				"formattedAddress": "6555 Malden Rd, Windsor, ON N9H 1T5, Canada",
				"locality": "Lasalle",
				"neighborhood": "Windsor",
				"postalCode": "N9H 1T5"
			},
			"geometry": {
				"type": "Point",
				"coordinates": [
					-83.0617592,
					42.2327054
				]
			},
			"bbox": [
				-83.0632774,
				42.2315812,
				-83.0602409,
				42.2338295
			]
		}
	]
}
