{
	"type": "FeatureCollection",
	"features": [
		{
			"type": "Feature",
			"properties": {
				"confidence": 9,
				"authenticationResultCode": "ValidCredentials",
				"brandLogoUri": "http://dev.virtualearth.net/Branding/logo_powered_by.png",
				"copyright": "Copyright © 2017 Microsoft and its suppliers. All rights reserved. This API cannot be accessed and the content and any results may not be used, reproduced or transmitted in any manner without express written permission from Microsoft Corporation.",
				"entityType": "Address",
				"matchCodes": [
					"Good"
				],
				"name": "657 Yonge St, Toronto, ON M4Y 1Z9, Canada",
				"statusCode": 200,
				"statusDescription": "OK",
				"traceId": "6606f85b86494564ac5bb0cd556ebda9|BN20130631|7.7.0.0|",
				"addressLine": "657 Yonge St",
				"adminDistrict": "ON",
				"adminDistrict2": "Toronto",
				"countryRegion": "Canada",
				"formattedAddress": "657 Yonge St, Toronto, ON M4Y 1Z9, Canada",
				"locality": "Toronto",
				"neighborhood": "Church-Yonge Corridor",
				"postalCode": "M4Y 1Z9"
			},
			"geometry": {
				"type": "Point",
				"coordinates": [
					-79.38553,
					43.66821
				]
			},
			"bbox": [
				-79.3870841,
				43.6670858,
				-79.3839759,
				43.6693342
			]
		}
	]
}
