{
	"type": "FeatureCollection",
	"features": [
		{
			"type": "Feature",
			"properties": {
				"confidence": 9,
				"authenticationResultCode": "ValidCredentials",
				"brandLogoUri": "http://dev.virtualearth.net/Branding/logo_powered_by.png",
				"copyright": "Copyright © 2017 Microsoft and its suppliers. All rights reserved. This API cannot be accessed and the content and any results may not be used, reproduced or transmitted in any manner without express written permission from Microsoft Corporation.",
				"entityType": "Address",
				"matchCodes": [
					"Good"
				],
				"name": "66 Eagle Rock Rd, Westfield Parish, NB E5K 3X7, Canada",
				"statusCode": 200,
				"statusDescription": "OK",
				"traceId": "9d4bfd7bbf914cdb9c00fb64f438eeba|BN20130423|7.7.0.0|",
				"addressLine": "66 Eagle Rock Rd",
				"adminDistrict": "NB",
				"adminDistrict2": "Kings",
				"countryRegion": "Canada",
				"formattedAddress": "66 Eagle Rock Rd, Westfield Parish, NB E5K 3X7, Canada",
				"locality": "Westfield Parish",
				"neighborhood": "Nerepis",
				"postalCode": "E5K 3X7"
			},
			"geometry": {
				"type": "Point",
				"coordinates": [
					-66.3148464,
					45.4101674
				]
			},
			"bbox": [
				-66.3164477,
				45.4090433,
				-66.3132451,
				45.4112916
			]
		}
	]
}
