{
	"type": "FeatureCollection",
	"features": [
		{
			"type": "Feature",
			"properties": {
				"confidence": 9,
				"authenticationResultCode": "ValidCredentials",
				"brandLogoUri": "http://dev.virtualearth.net/Branding/logo_powered_by.png",
				"copyright": "Copyright © 2017 Microsoft and its suppliers. All rights reserved. This API cannot be accessed and the content and any results may not be used, reproduced or transmitted in any manner without express written permission from Microsoft Corporation.",
				"entityType": "Address",
				"matchCodes": [
					"Good"
				],
				"name": "66 Rue Rhainds, Chicoutimi, QC G7G 2H4, Canada",
				"statusCode": 200,
				"statusDescription": "OK",
				"traceId": "aade77e6b1f348a7bfed639428d66143|BN20131519|7.7.0.0|",
				"addressLine": "66 Rue Rhainds",
				"adminDistrict": "QC",
				"adminDistrict2": "Saguenay",
				"countryRegion": "Canada",
				"formattedAddress": "66 Rue Rhainds, Chicoutimi, QC G7G 2H4, Canada",
				"locality": "Saguenay",
				"neighborhood": "Chicoutimi",
				"postalCode": "G7G 2H4"
			},
			"geometry": {
				"type": "Point",
				"coordinates": [
					-71.06484,
					48.43682
				]
			},
			"bbox": [
				-71.0665344,
				48.4356958,
				-71.0631456,
				48.4379442
			]
		}
	]
}
