{
	"type": "FeatureCollection",
	"features": [
		{
			"type": "Feature",
			"properties": {
				"confidence": 9,
				"authenticationResultCode": "ValidCredentials",
				"brandLogoUri": "http://dev.virtualearth.net/Branding/logo_powered_by.png",
				"copyright": "Copyright © 2017 Microsoft and its suppliers. All rights reserved. This API cannot be accessed and the content and any results may not be used, reproduced or transmitted in any manner without express written permission from Microsoft Corporation.",
				"entityType": "Address",
				"matchCodes": [
					"Good"
				],
				"name": "660 Hardwick Rd, Bolton, ON L7E 5R5, Canada",
				"statusCode": 200,
				"statusDescription": "OK",
				"traceId": "b27f19237fc5442fb2eb8ea9998e469c|BN20171457|7.7.0.0|",
				"addressLine": "660 Hardwick Rd",
				"adminDistrict": "ON",
				"adminDistrict2": "Peel",
				"countryRegion": "Canada",
				"formattedAddress": "660 Hardwick Rd, Bolton, ON L7E 5R5, Canada",
				"locality": "Caledon",
				"neighborhood": "Bolton",
				"postalCode": "L7E 5R5"
			},
			"geometry": {
				"type": "Point",
				"coordinates": [
					-79.7218199,
					43.86618
				]
			},
			"bbox": [
				-79.7233791,
				43.8650558,
				-79.7202607,
				43.8673042
			]
		}
	]
}
