{
	"type": "FeatureCollection",
	"features": [
		{
			"type": "Feature",
			"properties": {
				"confidence": 9,
				"authenticationResultCode": "ValidCredentials",
				"brandLogoUri": "http://dev.virtualearth.net/Branding/logo_powered_by.png",
				"copyright": "Copyright © 2017 Microsoft and its suppliers. All rights reserved. This API cannot be accessed and the content and any results may not be used, reproduced or transmitted in any manner without express written permission from Microsoft Corporation.",
				"entityType": "Address",
				"matchCodes": [
					"Good"
				],
				"name": "6605 Fleming St, Vancouver, BC V5P 3H3, Canada",
				"statusCode": 200,
				"statusDescription": "OK",
				"traceId": "e33dcf176523462aafe35e6f97725218|BN20130721|7.7.0.0|",
				"addressLine": "6605 Fleming St",
				"adminDistrict": "BC",
				"adminDistrict2": "Greater Vancouver",
				"countryRegion": "Canada",
				"formattedAddress": "6605 Fleming St, Vancouver, BC V5P 3H3, Canada",
				"locality": "Vancouver",
				"neighborhood": "Victoria-Fraserview",
				"postalCode": "V5P 3H3"
			},
			"geometry": {
				"type": "Point",
				"coordinates": [
					-123.07361,
					49.2242
				]
			},
			"bbox": [
				-123.0753313,
				49.2230758,
				-123.0718887,
				49.2253242
			]
		}
	]
}
