{
	"type": "FeatureCollection",
	"features": [
		{
			"type": "Feature",
			"properties": {
				"confidence": 9,
				"authenticationResultCode": "ValidCredentials",
				"brandLogoUri": "http://dev.virtualearth.net/Branding/logo_powered_by.png",
				"copyright": "Copyright © 2017 Microsoft and its suppliers. All rights reserved. This API cannot be accessed and the content and any results may not be used, reproduced or transmitted in any manner without express written permission from Microsoft Corporation.",
				"entityType": "Address",
				"matchCodes": [
					"Good"
				],
				"name": "662 Boulevard des Laurentides, Laval, QC H7G 2V9, Canada",
				"statusCode": 200,
				"statusDescription": "OK",
				"traceId": "64ad45697e9a43699b28de985b58f294|BN20130522|7.7.0.0|",
				"addressLine": "662 Boulevard des Laurentides",
				"adminDistrict": "QC",
				"adminDistrict2": "Laval",
				"countryRegion": "Canada",
				"formattedAddress": "662 Boulevard des Laurentides, Laval, QC H7G 2V9, Canada",
				"locality": "Laval",
				"postalCode": "H7G 2V9"
			},
			"geometry": {
				"type": "Point",
				"coordinates": [
					-73.6949099,
					45.57212
				]
			},
			"bbox": [
				-73.6965158,
				45.5709958,
				-73.693304,
				45.5732442
			]
		}
	]
}
