{
	"type": "FeatureCollection",
	"features": [
		{
			"type": "Feature",
			"properties": {
				"confidence": 9,
				"authenticationResultCode": "ValidCredentials",
				"brandLogoUri": "http://dev.virtualearth.net/Branding/logo_powered_by.png",
				"copyright": "Copyright © 2017 Microsoft and its suppliers. All rights reserved. This API cannot be accessed and the content and any results may not be used, reproduced or transmitted in any manner without express written permission from Microsoft Corporation.",
				"entityType": "Address",
				"matchCodes": [
					"Good"
				],
				"name": "665 Rue Principale, Joly, QC G0S 1M0, Canada",
				"statusCode": 200,
				"statusDescription": "OK",
				"traceId": "35b64e7c4f9b41d2917f0e549fa1ec13|BN20280152|7.7.0.0|",
				"addressLine": "665 Rue Principale",
				"adminDistrict": "QC",
				"adminDistrict2": "Lotbinière",
				"countryRegion": "Canada",
				"formattedAddress": "665 Rue Principale, Joly, QC G0S 1M0, Canada",
				"locality": "St-Janvier-de-Joly",
				"neighborhood": "Joly",
				"postalCode": "G0S 1M0"
			},
			"geometry": {
				"type": "Point",
				"coordinates": [
					-71.6637694,
					46.4876713
				]
			},
			"bbox": [
				-71.6654021,
				46.4865472,
				-71.6621367,
				46.4887955
			]
		}
	]
}
