{
	"type": "FeatureCollection",
	"features": [
		{
			"type": "Feature",
			"properties": {
				"confidence": 9,
				"authenticationResultCode": "ValidCredentials",
				"brandLogoUri": "http://dev.virtualearth.net/Branding/logo_powered_by.png",
				"copyright": "Copyright © 2017 Microsoft and its suppliers. All rights reserved. This API cannot be accessed and the content and any results may not be used, reproduced or transmitted in any manner without express written permission from Microsoft Corporation.",
				"entityType": "Address",
				"matchCodes": [
					"Good"
				],
				"name": "669 The Queensway, Etobicoke, ON M8Y 1K8, Canada",
				"statusCode": 200,
				"statusDescription": "OK",
				"traceId": "dee810657cd640c09a9e25ad286c5bc6|BN20130442|7.7.0.0|",
				"addressLine": "669 The Queensway",
				"adminDistrict": "ON",
				"adminDistrict2": "Toronto",
				"countryRegion": "Canada",
				"formattedAddress": "669 The Queensway, Etobicoke, ON M8Y 1K8, Canada",
				"locality": "Toronto",
				"neighborhood": "Stonegate-Queensway",
				"postalCode": "M8Y 1K8"
			},
			"geometry": {
				"type": "Point",
				"coordinates": [
					-79.49887,
					43.62698
				]
			},
			"bbox": [
				-79.500423,
				43.6258558,
				-79.497317,
				43.6281042
			]
		}
	]
}
