{
	"type": "FeatureCollection",
	"features": [
		{
			"type": "Feature",
			"properties": {
				"confidence": 9,
				"authenticationResultCode": "ValidCredentials",
				"brandLogoUri": "http://dev.virtualearth.net/Branding/logo_powered_by.png",
				"copyright": "Copyright © 2017 Microsoft and its suppliers. All rights reserved. This API cannot be accessed and the content and any results may not be used, reproduced or transmitted in any manner without express written permission from Microsoft Corporation.",
				"entityType": "Address",
				"matchCodes": [
					"Good"
				],
				"name": "669 Main St, Blacks Harbour, NB E5H 1K1, Canada",
				"statusCode": 200,
				"statusDescription": "OK",
				"traceId": "0bbc2263e5f04217bbdb2ec14d8a23b0|BN20280152|7.7.0.0|",
				"addressLine": "669 Main St",
				"adminDistrict": "NB",
				"adminDistrict2": "Charlotte",
				"countryRegion": "Canada",
				"formattedAddress": "669 Main St, Blacks Harbour, NB E5H 1K1, Canada",
				"locality": "Blacks Harbour",
				"postalCode": "E5H 1K1"
			},
			"geometry": {
				"type": "Point",
				"coordinates": [
					-66.7855662,
					45.0607062
				]
			},
			"bbox": [
				-66.7871577,
				45.0595821,
				-66.7839747,
				45.0618304
			]
		}
	]
}
