{
	"type": "FeatureCollection",
	"features": [
		{
			"type": "Feature",
			"properties": {
				"confidence": 9,
				"authenticationResultCode": "ValidCredentials",
				"brandLogoUri": "http://dev.virtualearth.net/Branding/logo_powered_by.png",
				"copyright": "Copyright © 2017 Microsoft and its suppliers. All rights reserved. This API cannot be accessed and the content and any results may not be used, reproduced or transmitted in any manner without express written permission from Microsoft Corporation.",
				"entityType": "Address",
				"matchCodes": [
					"Good"
				],
				"name": "67 Cadillac Ave, Victoria, BC V8Z 1T5, Canada",
				"statusCode": 200,
				"statusDescription": "OK",
				"traceId": "eced4546cf944e03b02a7457ecaed0cd|BN20130625|7.7.0.0|",
				"addressLine": "67 Cadillac Ave",
				"adminDistrict": "BC",
				"adminDistrict2": "Capital",
				"countryRegion": "Canada",
				"formattedAddress": "67 Cadillac Ave, Victoria, BC V8Z 1T5, Canada",
				"locality": "Saanich",
				"neighborhood": "Victoria",
				"postalCode": "V8Z 1T5"
			},
			"geometry": {
				"type": "Point",
				"coordinates": [
					-123.38059,
					48.4572
				]
			},
			"bbox": [
				-123.3822851,
				48.4560758,
				-123.3788949,
				48.4583242
			]
		}
	]
}
