{
	"type": "FeatureCollection",
	"features": [
		{
			"type": "Feature",
			"properties": {
				"confidence": 9,
				"authenticationResultCode": "ValidCredentials",
				"brandLogoUri": "http://dev.virtualearth.net/Branding/logo_powered_by.png",
				"copyright": "Copyright © 2017 Microsoft and its suppliers. All rights reserved. This API cannot be accessed and the content and any results may not be used, reproduced or transmitted in any manner without express written permission from Microsoft Corporation.",
				"entityType": "Address",
				"matchCodes": [
					"Good"
				],
				"name": "67 Lougheed Rd, Barrie, ON L4N 8G1, Canada",
				"statusCode": 200,
				"statusDescription": "OK",
				"traceId": "47b6d96c507c474ea99074d2d7045f0c|BN20130631|7.7.0.0|",
				"addressLine": "67 Lougheed Rd",
				"adminDistrict": "ON",
				"adminDistrict2": "Simcoe",
				"countryRegion": "Canada",
				"formattedAddress": "67 Lougheed Rd, Barrie, ON L4N 8G1, Canada",
				"locality": "Barrie",
				"neighborhood": "Holly",
				"postalCode": "L4N 8G1"
			},
			"geometry": {
				"type": "Point",
				"coordinates": [
					-79.72862,
					44.31979
				]
			},
			"bbox": [
				-79.7301912,
				44.3186658,
				-79.7270488,
				44.3209142
			]
		}
	]
}
