{
	"type": "FeatureCollection",
	"features": [
		{
			"type": "Feature",
			"properties": {
				"confidence": 9,
				"authenticationResultCode": "ValidCredentials",
				"brandLogoUri": "http://dev.virtualearth.net/Branding/logo_powered_by.png",
				"copyright": "Copyright © 2017 Microsoft and its suppliers. All rights reserved. This API cannot be accessed and the content and any results may not be used, reproduced or transmitted in any manner without express written permission from Microsoft Corporation.",
				"entityType": "Address",
				"matchCodes": [
					"Good"
				],
				"name": "6716 75 St NW, Edmonton, AB T6E 6T9, Canada",
				"statusCode": 200,
				"statusDescription": "OK",
				"traceId": "a19b24e8aeef433f9d2beeab79b7fd6c|BN20260231|7.7.0.0|",
				"addressLine": "6716 75 St NW",
				"adminDistrict": "AB",
				"adminDistrict2": "Alberta",
				"countryRegion": "Canada",
				"formattedAddress": "6716 75 St NW, Edmonton, AB T6E 6T9, Canada",
				"locality": "Edmonton",
				"neighborhood": "Davies Industrial West",
				"postalCode": "T6E 6T9"
			},
			"geometry": {
				"type": "Point",
				"coordinates": [
					-113.44364,
					53.50315
				]
			},
			"bbox": [
				-113.44553,
				53.5020258,
				-113.44175,
				53.5042742
			]
		}
	]
}
