{
	"type": "FeatureCollection",
	"features": [
		{
			"type": "Feature",
			"properties": {
				"confidence": 9,
				"authenticationResultCode": "ValidCredentials",
				"brandLogoUri": "http://dev.virtualearth.net/Branding/logo_powered_by.png",
				"copyright": "Copyright © 2017 Microsoft and its suppliers. All rights reserved. This API cannot be accessed and the content and any results may not be used, reproduced or transmitted in any manner without express written permission from Microsoft Corporation.",
				"entityType": "Address",
				"matchCodes": [
					"Good"
				],
				"name": "675 Irwin St, Chatham, ON N7M 5J5, Canada",
				"statusCode": 200,
				"statusDescription": "OK",
				"traceId": "f5e80484e1994899aca1456325d5fbb6|BN20130632|7.7.0.0|",
				"addressLine": "675 Irwin St",
				"adminDistrict": "ON",
				"adminDistrict2": "Chatham-Kent",
				"countryRegion": "Canada",
				"formattedAddress": "675 Irwin St, Chatham, ON N7M 5J5, Canada",
				"locality": "Chatham-Kent",
				"neighborhood": "Chatham",
				"postalCode": "N7M 5J5"
			},
			"geometry": {
				"type": "Point",
				"coordinates": [
					-82.20968,
					42.38632
				]
			},
			"bbox": [
				-82.211202,
				42.3851958,
				-82.208158,
				42.3874442
			]
		}
	]
}
