{
	"type": "FeatureCollection",
	"features": [
		{
			"type": "Feature",
			"properties": {
				"confidence": 9,
				"authenticationResultCode": "ValidCredentials",
				"brandLogoUri": "http://dev.virtualearth.net/Branding/logo_powered_by.png",
				"copyright": "Copyright © 2017 Microsoft and its suppliers. All rights reserved. This API cannot be accessed and the content and any results may not be used, reproduced or transmitted in any manner without express written permission from Microsoft Corporation.",
				"entityType": "Address",
				"matchCodes": [
					"Good"
				],
				"name": "675 Rue Simonds S, Granby, QC J2J 1C2, Canada",
				"statusCode": 200,
				"statusDescription": "OK",
				"traceId": "d12472c725644a9a98feec39aef901df|BN20121763|7.7.0.0|",
				"addressLine": "675 Rue Simonds S",
				"adminDistrict": "QC",
				"adminDistrict2": "La Haute-Yamaska",
				"countryRegion": "Canada",
				"formattedAddress": "675 Rue Simonds S, Granby, QC J2J 1C2, Canada",
				"locality": "Granby",
				"postalCode": "J2J 1C2"
			},
			"geometry": {
				"type": "Point",
				"coordinates": [
					-72.75712,
					45.38984
				]
			},
			"bbox": [
				-72.7587207,
				45.3887158,
				-72.7555193,
				45.3909642
			]
		}
	]
}
