{
	"type": "FeatureCollection",
	"features": [
		{
			"type": "Feature",
			"properties": {
				"confidence": 9,
				"authenticationResultCode": "ValidCredentials",
				"brandLogoUri": "http://dev.virtualearth.net/Branding/logo_powered_by.png",
				"copyright": "Copyright © 2017 Microsoft and its suppliers. All rights reserved. This API cannot be accessed and the content and any results may not be used, reproduced or transmitted in any manner without express written permission from Microsoft Corporation.",
				"entityType": "Address",
				"matchCodes": [
					"Good"
				],
				"name": "676 Highland Ave, Ottawa, ON K2A 2K4, Canada",
				"statusCode": 200,
				"statusDescription": "OK",
				"traceId": "f50c37462921466d8c09ad2172763c7b|BN20130521|7.7.0.0|",
				"addressLine": "676 Highland Ave",
				"adminDistrict": "ON",
				"adminDistrict2": "Ottawa",
				"countryRegion": "Canada",
				"formattedAddress": "676 Highland Ave, Ottawa, ON K2A 2K4, Canada",
				"locality": "Ottawa",
				"neighborhood": "Carlingwood-McKellar Pk-Laurentien",
				"postalCode": "K2A 2K4"
			},
			"geometry": {
				"type": "Point",
				"coordinates": [
					-75.75569,
					45.3808099
				]
			},
			"bbox": [
				-75.7572905,
				45.3796857,
				-75.7540895,
				45.3819341
			]
		}
	]
}
