{
	"type": "FeatureCollection",
	"features": [
		{
			"type": "Feature",
			"properties": {
				"confidence": 9,
				"authenticationResultCode": "ValidCredentials",
				"brandLogoUri": "http://dev.virtualearth.net/Branding/logo_powered_by.png",
				"copyright": "Copyright © 2017 Microsoft and its suppliers. All rights reserved. This API cannot be accessed and the content and any results may not be used, reproduced or transmitted in any manner without express written permission from Microsoft Corporation.",
				"entityType": "Address",
				"matchCodes": [
					"Good"
				],
				"name": "678 Rue Rocheleau, Drummondville, QC J2C 6Y5, Canada",
				"statusCode": 200,
				"statusDescription": "OK",
				"traceId": "67c31923230144859a18f4ed004b938e|BN20160335|7.7.0.0|",
				"addressLine": "678 Rue Rocheleau",
				"adminDistrict": "QC",
				"adminDistrict2": "Drummond",
				"countryRegion": "Canada",
				"formattedAddress": "678 Rue Rocheleau, Drummondville, QC J2C 6Y5, Canada",
				"locality": "Drummondville",
				"postalCode": "J2C 6Y5"
			},
			"geometry": {
				"type": "Point",
				"coordinates": [
					-72.53444,
					45.87207
				]
			},
			"bbox": [
				-72.5360546,
				45.8709458,
				-72.5328254,
				45.8731942
			]
		}
	]
}
