{
	"type": "FeatureCollection",
	"features": [
		{
			"type": "Feature",
			"properties": {
				"confidence": 9,
				"authenticationResultCode": "ValidCredentials",
				"brandLogoUri": "http://dev.virtualearth.net/Branding/logo_powered_by.png",
				"copyright": "Copyright © 2017 Microsoft and its suppliers. All rights reserved. This API cannot be accessed and the content and any results may not be used, reproduced or transmitted in any manner without express written permission from Microsoft Corporation.",
				"entityType": "Address",
				"matchCodes": [
					"Good"
				],
				"name": "68 Wellington St E, Aurora, ON L4G 1H8, Canada",
				"statusCode": 200,
				"statusDescription": "OK",
				"traceId": "39bebfd675fc4b67982b73f616635087|BN20130422|7.7.0.0|",
				"addressLine": "68 Wellington St E",
				"adminDistrict": "ON",
				"adminDistrict2": "York",
				"countryRegion": "Canada",
				"formattedAddress": "68 Wellington St E, Aurora, ON L4G 1H8, Canada",
				"locality": "Aurora",
				"postalCode": "L4G 1H8"
			},
			"geometry": {
				"type": "Point",
				"coordinates": [
					-79.4638,
					44.00072
				]
			},
			"bbox": [
				-79.4653628,
				43.9995958,
				-79.4622372,
				44.0018442
			]
		}
	]
}
