{
	"type": "FeatureCollection",
	"features": [
		{
			"type": "Feature",
			"properties": {
				"confidence": 9,
				"authenticationResultCode": "ValidCredentials",
				"brandLogoUri": "http://dev.virtualearth.net/Branding/logo_powered_by.png",
				"copyright": "Copyright © 2017 Microsoft and its suppliers. All rights reserved. This API cannot be accessed and the content and any results may not be used, reproduced or transmitted in any manner without express written permission from Microsoft Corporation.",
				"entityType": "Address",
				"matchCodes": [
					"Good"
				],
				"name": "681 Fleet St, Kingston, ON K7M 5A4, Canada",
				"statusCode": 200,
				"statusDescription": "OK",
				"traceId": "69e41b3e7a5a4bdf8aba6c670101d8d9|BN20130634|7.7.0.0|",
				"addressLine": "681 Fleet St",
				"adminDistrict": "ON",
				"adminDistrict2": "Frontenac",
				"countryRegion": "Canada",
				"formattedAddress": "681 Fleet St, Kingston, ON K7M 5A4, Canada",
				"locality": "Kingston",
				"neighborhood": "Bayridge West",
				"postalCode": "K7M 5A4"
			},
			"geometry": {
				"type": "Point",
				"coordinates": [
					-76.595,
					44.24468
				]
			},
			"bbox": [
				-76.5965692,
				44.2435558,
				-76.5934308,
				44.2458042
			]
		}
	]
}
