{
	"type": "FeatureCollection",
	"features": [
		{
			"type": "Feature",
			"properties": {
				"confidence": 9,
				"authenticationResultCode": "ValidCredentials",
				"brandLogoUri": "http://dev.virtualearth.net/Branding/logo_powered_by.png",
				"copyright": "Copyright © 2017 Microsoft and its suppliers. All rights reserved. This API cannot be accessed and the content and any results may not be used, reproduced or transmitted in any manner without express written permission from Microsoft Corporation.",
				"entityType": "Address",
				"matchCodes": [
					"Good"
				],
				"name": "685 Hale St, London, ON N5W 1J1, Canada",
				"statusCode": 200,
				"statusDescription": "OK",
				"traceId": "35409052a86b4e9299d79d6b4fb5a3a9|BN20240423|7.7.0.0|",
				"addressLine": "685 Hale St",
				"adminDistrict": "ON",
				"adminDistrict2": "Middlesex",
				"countryRegion": "Canada",
				"formattedAddress": "685 Hale St, London, ON N5W 1J1, Canada",
				"locality": "London",
				"neighborhood": "East London",
				"postalCode": "N5W 1J1"
			},
			"geometry": {
				"type": "Point",
				"coordinates": [
					-81.199,
					42.9968999
				]
			},
			"bbox": [
				-81.200537,
				42.9957757,
				-81.197463,
				42.9980241
			]
		}
	]
}
