{
	"type": "FeatureCollection",
	"features": [
		{
			"type": "Feature",
			"properties": {
				"confidence": 9,
				"authenticationResultCode": "ValidCredentials",
				"brandLogoUri": "http://dev.virtualearth.net/Branding/logo_powered_by.png",
				"copyright": "Copyright © 2017 Microsoft and its suppliers. All rights reserved. This API cannot be accessed and the content and any results may not be used, reproduced or transmitted in any manner without express written permission from Microsoft Corporation.",
				"entityType": "Address",
				"matchCodes": [
					"Good"
				],
				"name": "6854 Casabello Dr, Chilliwack, BC V2R 2R3, Canada",
				"statusCode": 200,
				"statusDescription": "OK",
				"traceId": "303fe6f784a240838c900f7c58c7bc9a|BN20260231|7.7.0.0|",
				"addressLine": "6854 Casabello Dr",
				"adminDistrict": "BC",
				"adminDistrict2": "Fraser Valley",
				"countryRegion": "Canada",
				"formattedAddress": "6854 Casabello Dr, Chilliwack, BC V2R 2R3, Canada",
				"locality": "Chilliwack",
				"neighborhood": "Sardis",
				"postalCode": "V2R 2R3"
			},
			"geometry": {
				"type": "Point",
				"coordinates": [
					-121.94778,
					49.12684
				]
			},
			"bbox": [
				-121.9494979,
				49.1257158,
				-121.9460621,
				49.1279642
			]
		}
	]
}
