{
	"type": "FeatureCollection",
	"features": [
		{
			"type": "Feature",
			"properties": {
				"confidence": 9,
				"authenticationResultCode": "ValidCredentials",
				"brandLogoUri": "http://dev.virtualearth.net/Branding/logo_powered_by.png",
				"copyright": "Copyright © 2017 Microsoft and its suppliers. All rights reserved. This API cannot be accessed and the content and any results may not be used, reproduced or transmitted in any manner without express written permission from Microsoft Corporation.",
				"entityType": "Address",
				"matchCodes": [
					"Good"
				],
				"name": "69 Chemin du Barrage, Chelsea, QC J9B 1N2, Canada",
				"statusCode": 200,
				"statusDescription": "OK",
				"traceId": "536d1f26418e4f5686d2d8e35b52f9d2|BN20171457|7.7.0.0|",
				"addressLine": "69 Chemin du Barrage",
				"adminDistrict": "QC",
				"adminDistrict2": "Les Collines-de-l'Outaouais",
				"countryRegion": "Canada",
				"formattedAddress": "69 Chemin du Barrage, Chelsea, QC J9B 1N2, Canada",
				"locality": "Chelsea",
				"postalCode": "J9B 1N2"
			},
			"geometry": {
				"type": "Point",
				"coordinates": [
					-75.77124,
					45.50061
				]
			},
			"bbox": [
				-75.7728439,
				45.4994858,
				-75.7696361,
				45.5017342
			]
		}
	]
}
