{
	"type": "FeatureCollection",
	"features": [
		{
			"type": "Feature",
			"properties": {
				"confidence": 9,
				"authenticationResultCode": "ValidCredentials",
				"brandLogoUri": "http://dev.virtualearth.net/Branding/logo_powered_by.png",
				"copyright": "Copyright © 2017 Microsoft and its suppliers. All rights reserved. This API cannot be accessed and the content and any results may not be used, reproduced or transmitted in any manner without express written permission from Microsoft Corporation.",
				"entityType": "Address",
				"matchCodes": [
					"Good"
				],
				"name": "69 Lakeview Blvd, Beaconsfield, QC H9W 4R3, Canada",
				"statusCode": 200,
				"statusDescription": "OK",
				"traceId": "e52ba5900d3744bdab5b3aabf4b19b5c|BN20290118|7.7.0.0|",
				"addressLine": "69 Lakeview Blvd",
				"adminDistrict": "QC",
				"adminDistrict2": "Montreal",
				"countryRegion": "Canada",
				"formattedAddress": "69 Lakeview Blvd, Beaconsfield, QC H9W 4R3, Canada",
				"locality": "Beaconsfield",
				"postalCode": "H9W 4R3"
			},
			"geometry": {
				"type": "Point",
				"coordinates": [
					-73.88983,
					45.42006
				]
			},
			"bbox": [
				-73.8914316,
				45.4189358,
				-73.8882284,
				45.4211842
			]
		}
	]
}
