{
	"type": "FeatureCollection",
	"features": [
		{
			"type": "Feature",
			"properties": {
				"confidence": 9,
				"authenticationResultCode": "ValidCredentials",
				"brandLogoUri": "http://dev.virtualearth.net/Branding/logo_powered_by.png",
				"copyright": "Copyright © 2017 Microsoft and its suppliers. All rights reserved. This API cannot be accessed and the content and any results may not be used, reproduced or transmitted in any manner without express written permission from Microsoft Corporation.",
				"entityType": "Address",
				"matchCodes": [
					"Good"
				],
				"name": "69 Langarth St W, London, ON N6J 1P5, Canada",
				"statusCode": 200,
				"statusDescription": "OK",
				"traceId": "d46caf7aeab34805b594fbca1dd776a6|BN20130533|7.7.0.0|",
				"addressLine": "69 Langarth St W",
				"adminDistrict": "ON",
				"adminDistrict2": "Middlesex",
				"countryRegion": "Canada",
				"formattedAddress": "69 Langarth St W, London, ON N6J 1P5, Canada",
				"locality": "London",
				"neighborhood": "Southcrest",
				"postalCode": "N6J 1P5"
			},
			"geometry": {
				"type": "Point",
				"coordinates": [
					-81.2676,
					42.9643
				]
			},
			"bbox": [
				-81.2691362,
				42.9631758,
				-81.2660638,
				42.9654242
			]
		}
	]
}
