{
	"type": "FeatureCollection",
	"features": [
		{
			"type": "Feature",
			"properties": {
				"confidence": 9,
				"authenticationResultCode": "ValidCredentials",
				"brandLogoUri": "http://dev.virtualearth.net/Branding/logo_powered_by.png",
				"copyright": "Copyright © 2017 Microsoft and its suppliers. All rights reserved. This API cannot be accessed and the content and any results may not be used, reproduced or transmitted in any manner without express written permission from Microsoft Corporation.",
				"entityType": "Address",
				"matchCodes": [
					"Good"
				],
				"name": "69 Ossington Ave, Ottawa, ON K1S 3B5, Canada",
				"statusCode": 200,
				"statusDescription": "OK",
				"traceId": "3671361705014dd591bdc8a9af127cd3|BN20130721|7.7.0.0|",
				"addressLine": "69 Ossington Ave",
				"adminDistrict": "ON",
				"adminDistrict2": "Ottawa",
				"countryRegion": "Canada",
				"formattedAddress": "69 Ossington Ave, Ottawa, ON K1S 3B5, Canada",
				"locality": "Ottawa",
				"neighborhood": "Golden Triangle-Old Ottawa East",
				"postalCode": "K1S 3B5"
			},
			"geometry": {
				"type": "Point",
				"coordinates": [
					-75.68534,
					45.39049
				]
			},
			"bbox": [
				-75.6869407,
				45.3893658,
				-75.6837393,
				45.3916142
			]
		}
	]
}
