{
	"type": "FeatureCollection",
	"features": [
		{
			"type": "Feature",
			"properties": {
				"confidence": 9,
				"authenticationResultCode": "ValidCredentials",
				"brandLogoUri": "http://dev.virtualearth.net/Branding/logo_powered_by.png",
				"copyright": "Copyright © 2017 Microsoft and its suppliers. All rights reserved. This API cannot be accessed and the content and any results may not be used, reproduced or transmitted in any manner without express written permission from Microsoft Corporation.",
				"entityType": "Address",
				"matchCodes": [
					"Good"
				],
				"name": "69 Ramblewood Ln, Thornhill, ON L4J 6R9, Canada",
				"statusCode": 200,
				"statusDescription": "OK",
				"traceId": "89d4dae3e0a742d8a27a646e14fdc220|BN20200239|7.7.0.0|",
				"addressLine": "69 Ramblewood Ln",
				"adminDistrict": "ON",
				"adminDistrict2": "York",
				"countryRegion": "Canada",
				"formattedAddress": "69 Ramblewood Ln, Thornhill, ON L4J 6R9, Canada",
				"locality": "Vaughan",
				"neighborhood": "Thornhill",
				"postalCode": "L4J 6R9"
			},
			"geometry": {
				"type": "Point",
				"coordinates": [
					-79.45477,
					43.79848
				]
			},
			"bbox": [
				-79.4563275,
				43.7973558,
				-79.4532125,
				43.7996042
			]
		}
	]
}
