{
	"type": "FeatureCollection",
	"features": [
		{
			"type": "Feature",
			"properties": {
				"confidence": 9,
				"authenticationResultCode": "ValidCredentials",
				"brandLogoUri": "http://dev.virtualearth.net/Branding/logo_powered_by.png",
				"copyright": "Copyright © 2017 Microsoft and its suppliers. All rights reserved. This API cannot be accessed and the content and any results may not be used, reproduced or transmitted in any manner without express written permission from Microsoft Corporation.",
				"entityType": "Address",
				"matchCodes": [
					"Good"
				],
				"name": "69 RTE-155, Chambord, QC G0W 1G0, Canada",
				"statusCode": 200,
				"statusDescription": "OK",
				"traceId": "c31e930b383b4dd2a00d3d7a6b770164|BN20121762|7.7.0.0|",
				"addressLine": "69 RTE-155",
				"adminDistrict": "QC",
				"adminDistrict2": "Le Domaine-du-Roy",
				"countryRegion": "Canada",
				"formattedAddress": "69 RTE-155, Chambord, QC G0W 1G0, Canada",
				"locality": "Chambord",
				"postalCode": "G0W 1G0"
			},
			"geometry": {
				"type": "Point",
				"coordinates": [
					-72.0810805,
					48.4306015
				]
			},
			"bbox": [
				-72.0827747,
				48.4294773,
				-72.0793863,
				48.4317256
			]
		}
	]
}
