{
	"type": "FeatureCollection",
	"features": [
		{
			"type": "Feature",
			"properties": {
				"confidence": 9,
				"authenticationResultCode": "ValidCredentials",
				"brandLogoUri": "http://dev.virtualearth.net/Branding/logo_powered_by.png",
				"copyright": "Copyright © 2017 Microsoft and its suppliers. All rights reserved. This API cannot be accessed and the content and any results may not be used, reproduced or transmitted in any manner without express written permission from Microsoft Corporation.",
				"entityType": "Address",
				"matchCodes": [
					"Good"
				],
				"name": "690 Gana Ct, Mississauga, ON L5S 1P2, Canada",
				"statusCode": 200,
				"statusDescription": "OK",
				"traceId": "9561ea7aeb0f4dc3b0f0b08293782fb8|BN20130431|7.7.0.0|",
				"addressLine": "690 Gana Ct",
				"adminDistrict": "ON",
				"adminDistrict2": "Peel",
				"countryRegion": "Canada",
				"formattedAddress": "690 Gana Ct, Mississauga, ON L5S 1P2, Canada",
				"locality": "Mississauga",
				"postalCode": "L5S 1P2"
			},
			"geometry": {
				"type": "Point",
				"coordinates": [
					-79.68989,
					43.66875
				]
			},
			"bbox": [
				-79.6914441,
				43.6676258,
				-79.6883359,
				43.6698742
			]
		}
	]
}
