{
	"type": "FeatureCollection",
	"features": [
		{
			"type": "Feature",
			"properties": {
				"confidence": 9,
				"authenticationResultCode": "ValidCredentials",
				"brandLogoUri": "http://dev.virtualearth.net/Branding/logo_powered_by.png",
				"copyright": "Copyright © 2017 Microsoft and its suppliers. All rights reserved. This API cannot be accessed and the content and any results may not be used, reproduced or transmitted in any manner without express written permission from Microsoft Corporation.",
				"entityType": "Address",
				"matchCodes": [
					"Good"
				],
				"name": "6909 Antrim Ave, Burnaby, BC V5J 4M5, Canada",
				"statusCode": 200,
				"statusDescription": "OK",
				"traceId": "e2013ff575ec4629ba73c06e6521d866|BN20181720|7.7.0.0|",
				"addressLine": "6909 Antrim Ave",
				"adminDistrict": "BC",
				"adminDistrict2": "Greater Vancouver",
				"countryRegion": "Canada",
				"formattedAddress": "6909 Antrim Ave, Burnaby, BC V5J 4M5, Canada",
				"locality": "Burnaby",
				"neighborhood": "Windsor",
				"postalCode": "V5J 4M5"
			},
			"geometry": {
				"type": "Point",
				"coordinates": [
					-122.98543,
					49.2207
				]
			},
			"bbox": [
				-122.9871511,
				49.2195758,
				-122.9837089,
				49.2218242
			]
		}
	]
}
