{
	"type": "FeatureCollection",
	"features": [
		{
			"type": "Feature",
			"properties": {
				"confidence": 9,
				"authenticationResultCode": "ValidCredentials",
				"brandLogoUri": "http://dev.virtualearth.net/Branding/logo_powered_by.png",
				"copyright": "Copyright © 2017 Microsoft and its suppliers. All rights reserved. This API cannot be accessed and the content and any results may not be used, reproduced or transmitted in any manner without express written permission from Microsoft Corporation.",
				"entityType": "Address",
				"matchCodes": [
					"Good"
				],
				"name": "69436 Mollard Line, South Huron, ON N0M 2K0, Canada",
				"statusCode": 200,
				"statusDescription": "OK",
				"traceId": "11f23728e9fb4e5e981cb08371bb201f|BN20190642|7.7.0.0|",
				"addressLine": "69436 Mollard Line",
				"adminDistrict": "ON",
				"adminDistrict2": "Huron",
				"countryRegion": "Canada",
				"formattedAddress": "69436 Mollard Line, South Huron, ON N0M 2K0, Canada",
				"locality": "South Huron",
				"postalCode": "N0M 2K0"
			},
			"geometry": {
				"type": "Point",
				"coordinates": [
					-81.74601,
					43.25116
				]
			},
			"bbox": [
				-81.7475534,
				43.2500358,
				-81.7444666,
				43.2522842
			]
		}
	]
}
