{
	"type": "FeatureCollection",
	"features": [
		{
			"type": "Feature",
			"properties": {
				"confidence": 9,
				"authenticationResultCode": "ValidCredentials",
				"brandLogoUri": "http://dev.virtualearth.net/Branding/logo_powered_by.png",
				"copyright": "Copyright © 2017 Microsoft and its suppliers. All rights reserved. This API cannot be accessed and the content and any results may not be used, reproduced or transmitted in any manner without express written permission from Microsoft Corporation.",
				"entityType": "Address",
				"matchCodes": [
					"Good"
				],
				"name": "697 HWY-335, Argyle, NS B0W, Canada",
				"statusCode": 200,
				"statusDescription": "OK",
				"traceId": "91d6b25b449b4bb588e189f073c8678e|BN20220145|7.7.0.0|",
				"addressLine": "697 HWY-335",
				"adminDistrict": "NS",
				"adminDistrict2": "Yarmouth",
				"countryRegion": "Canada",
				"formattedAddress": "697 HWY-335, Argyle, NS B0W, Canada",
				"locality": "Argyle",
				"neighborhood": "West Pubnico",
				"postalCode": "B0W 3S0"
			},
			"geometry": {
				"type": "Point",
				"coordinates": [
					-65.795737,
					43.6740889
				]
			},
			"bbox": [
				-65.7972913,
				43.6729647,
				-65.7941828,
				43.675213
			]
		}
	]
}
