{
	"type": "FeatureCollection",
	"features": [
		{
			"type": "Feature",
			"properties": {
				"confidence": 9,
				"authenticationResultCode": "ValidCredentials",
				"brandLogoUri": "http://dev.virtualearth.net/Branding/logo_powered_by.png",
				"copyright": "Copyright © 2017 Microsoft and its suppliers. All rights reserved. This API cannot be accessed and the content and any results may not be used, reproduced or transmitted in any manner without express written permission from Microsoft Corporation.",
				"entityType": "Address",
				"matchCodes": [
					"Good"
				],
				"name": "699 Champlain St, Dieppe, NB E1A 1P6, Canada",
				"statusCode": 200,
				"statusDescription": "OK",
				"traceId": "dedfe2517d744cf993e1ac3ca3e92966|BN20200239|7.7.0.0|",
				"addressLine": "699 Champlain St",
				"adminDistrict": "NB",
				"adminDistrict2": "Westmorland",
				"countryRegion": "Canada",
				"formattedAddress": "699 Champlain St, Dieppe, NB E1A 1P6, Canada",
				"locality": "Dieppe",
				"postalCode": "E1A 1P6"
			},
			"geometry": {
				"type": "Point",
				"coordinates": [
					-64.72506,
					46.10063
				]
			},
			"bbox": [
				-64.7266812,
				46.0995058,
				-64.7234388,
				46.1017542
			]
		}
	]
}
