{
	"type": "FeatureCollection",
	"features": [
		{
			"type": "Feature",
			"properties": {
				"confidence": 9,
				"authenticationResultCode": "ValidCredentials",
				"brandLogoUri": "http://dev.virtualearth.net/Branding/logo_powered_by.png",
				"copyright": "Copyright © 2017 Microsoft and its suppliers. All rights reserved. This API cannot be accessed and the content and any results may not be used, reproduced or transmitted in any manner without express written permission from Microsoft Corporation.",
				"entityType": "Address",
				"matchCodes": [
					"Good"
				],
				"name": "6999 11 St SE, Calgary, AB T2H 2S1, Canada",
				"statusCode": 200,
				"statusDescription": "OK",
				"traceId": "16938f06dbe54ca48a65eb7d4352c012|BN20290118|7.7.0.0|",
				"addressLine": "6999 11 St SE",
				"adminDistrict": "AB",
				"adminDistrict2": "Alberta",
				"countryRegion": "Canada",
				"formattedAddress": "6999 11 St SE, Calgary, AB T2H 2S1, Canada",
				"locality": "Calgary",
				"postalCode": "T2H 2S1"
			},
			"geometry": {
				"type": "Point",
				"coordinates": [
					-114.04059,
					50.99113
				]
			},
			"bbox": [
				-114.042376,
				50.9900058,
				-114.038804,
				50.9922542
			]
		}
	]
}
