{
	"type": "FeatureCollection",
	"features": [
		{
			"type": "Feature",
			"properties": {
				"confidence": 9,
				"authenticationResultCode": "ValidCredentials",
				"brandLogoUri": "http://dev.virtualearth.net/Branding/logo_powered_by.png",
				"copyright": "Copyright © 2017 Microsoft and its suppliers. All rights reserved. This API cannot be accessed and the content and any results may not be used, reproduced or transmitted in any manner without express written permission from Microsoft Corporation.",
				"entityType": "Address",
				"matchCodes": [
					"Ambiguous"
				],
				"name": "7 Main St, MacDonald RM, MB R0G, Canada",
				"statusCode": 200,
				"statusDescription": "OK",
				"traceId": "35db889fd8b64379b7e499317025e4c0|BN20130634|7.7.0.0|",
				"addressLine": "7 Main St",
				"adminDistrict": "MB",
				"adminDistrict2": "Manitoba",
				"countryRegion": "Canada",
				"formattedAddress": "7 Main St, MacDonald RM, MB R0G, Canada",
				"locality": "MacDonald RM",
				"postalCode": "R0G 1W0"
			},
			"geometry": {
				"type": "Point",
				"coordinates": [
					-97.6182114,
					49.7700332
				]
			},
			"bbox": [
				-97.619952,
				49.768909,
				-97.6164708,
				49.7711573
			]
		},
		{
			"type": "Feature",
			"properties": {
				"confidence": 9,
				"authenticationResultCode": "ValidCredentials",
				"brandLogoUri": "http://dev.virtualearth.net/Branding/logo_powered_by.png",
				"copyright": "Copyright © 2017 Microsoft and its suppliers. All rights reserved. This API cannot be accessed and the content and any results may not be used, reproduced or transmitted in any manner without express written permission from Microsoft Corporation.",
				"entityType": "Address",
				"matchCodes": [
					"Ambiguous"
				],
				"name": "7 Main St, Manitou, MB R0G, Canada",
				"statusCode": 200,
				"statusDescription": "OK",
				"traceId": "35db889fd8b64379b7e499317025e4c0|BN20130634|7.7.0.0|",
				"addressLine": "7 Main St",
				"adminDistrict": "MB",
				"adminDistrict2": "Manitoba",
				"countryRegion": "Canada",
				"formattedAddress": "7 Main St, Manitou, MB R0G, Canada",
				"locality": "Manitou",
				"postalCode": "R0G 1W0"
			},
			"geometry": {
				"type": "Point",
				"coordinates": [
					-98.5441772,
					49.2344224
				]
			},
			"bbox": [
				-98.5458988,
				49.2332982,
				-98.5424555,
				49.2355465
			]
		}
	]
}
