{
	"type": "FeatureCollection",
	"features": [
		{
			"type": "Feature",
			"properties": {
				"confidence": 9,
				"authenticationResultCode": "ValidCredentials",
				"brandLogoUri": "http://dev.virtualearth.net/Branding/logo_powered_by.png",
				"copyright": "Copyright © 2017 Microsoft and its suppliers. All rights reserved. This API cannot be accessed and the content and any results may not be used, reproduced or transmitted in any manner without express written permission from Microsoft Corporation.",
				"entityType": "Address",
				"matchCodes": [
					"Good"
				],
				"name": "7 Presidents Ct, Scarborough, ON M1V 3E7, Canada",
				"statusCode": 200,
				"statusDescription": "OK",
				"traceId": "49101d0dc65340eeacd1d94520ea3bc3|BN20200239|7.7.0.0|",
				"addressLine": "7 Presidents Ct",
				"adminDistrict": "ON",
				"adminDistrict2": "Toronto",
				"countryRegion": "Canada",
				"formattedAddress": "7 Presidents Ct, Scarborough, ON M1V 3E7, Canada",
				"locality": "Toronto",
				"neighborhood": "Milliken",
				"postalCode": "M1V 3E7"
			},
			"geometry": {
				"type": "Point",
				"coordinates": [
					-79.26915,
					43.82124
				]
			},
			"bbox": [
				-79.2707081,
				43.8201158,
				-79.2675919,
				43.8223642
			]
		}
	]
}
