{
	"type": "FeatureCollection",
	"features": [
		{
			"type": "Feature",
			"properties": {
				"confidence": 9,
				"authenticationResultCode": "ValidCredentials",
				"brandLogoUri": "http://dev.virtualearth.net/Branding/logo_powered_by.png",
				"copyright": "Copyright © 2017 Microsoft and its suppliers. All rights reserved. This API cannot be accessed and the content and any results may not be used, reproduced or transmitted in any manner without express written permission from Microsoft Corporation.",
				"entityType": "Address",
				"matchCodes": [
					"Good"
				],
				"name": "7 Tangreen Cir, Thornhill, ON L4J 5E2, Canada",
				"statusCode": 200,
				"statusDescription": "OK",
				"traceId": "cfdfa9cece7e4d1382706255b4201320|BN20130533|7.7.0.0|",
				"addressLine": "7 Tangreen Cir",
				"adminDistrict": "ON",
				"adminDistrict2": "York",
				"countryRegion": "Canada",
				"formattedAddress": "7 Tangreen Cir, Thornhill, ON L4J 5E2, Canada",
				"locality": "Vaughan",
				"neighborhood": "Thornhill",
				"postalCode": "L4J 5E2"
			},
			"geometry": {
				"type": "Point",
				"coordinates": [
					-79.44192,
					43.80646
				]
			},
			"bbox": [
				-79.4434777,
				43.8053358,
				-79.4403623,
				43.8075842
			]
		}
	]
}
