{
	"type": "FeatureCollection",
	"features": [
		{
			"type": "Feature",
			"properties": {
				"confidence": 9,
				"authenticationResultCode": "ValidCredentials",
				"brandLogoUri": "http://dev.virtualearth.net/Branding/logo_powered_by.png",
				"copyright": "Copyright © 2017 Microsoft and its suppliers. All rights reserved. This API cannot be accessed and the content and any results may not be used, reproduced or transmitted in any manner without express written permission from Microsoft Corporation.",
				"entityType": "Address",
				"matchCodes": [
					"Good"
				],
				"name": "70 6A St NE, Calgary, AB T2E 4A3, Canada",
				"statusCode": 200,
				"statusDescription": "OK",
				"traceId": "8e44137d2bcf4d2f94e350f32b8e567d|BN20121764|7.7.0.0|",
				"addressLine": "70 6A St NE",
				"adminDistrict": "AB",
				"adminDistrict2": "Alberta",
				"countryRegion": "Canada",
				"formattedAddress": "70 6A St NE, Calgary, AB T2E 4A3, Canada",
				"locality": "Calgary",
				"neighborhood": "Bridgeland",
				"postalCode": "T2E 4A3"
			},
			"geometry": {
				"type": "Point",
				"coordinates": [
					-114.04683,
					51.05224
				]
			},
			"bbox": [
				-114.0486183,
				51.0511158,
				-114.0450417,
				51.0533642
			]
		}
	]
}
