{
	"type": "FeatureCollection",
	"features": [
		{
			"type": "Feature",
			"properties": {
				"confidence": 9,
				"authenticationResultCode": "ValidCredentials",
				"brandLogoUri": "http://dev.virtualearth.net/Branding/logo_powered_by.png",
				"copyright": "Copyright © 2017 Microsoft and its suppliers. All rights reserved. This API cannot be accessed and the content and any results may not be used, reproduced or transmitted in any manner without express written permission from Microsoft Corporation.",
				"entityType": "Address",
				"matchCodes": [
					"Good"
				],
				"name": "70 Bethridge Rd, Etobicoke, ON M9W 1N1, Canada",
				"statusCode": 200,
				"statusDescription": "OK",
				"traceId": "da261caaa16247428f5ea141cc3f000f|BN20130423|7.7.0.0|",
				"addressLine": "70 Bethridge Rd",
				"adminDistrict": "ON",
				"adminDistrict2": "Toronto",
				"countryRegion": "Canada",
				"formattedAddress": "70 Bethridge Rd, Etobicoke, ON M9W 1N1, Canada",
				"locality": "Toronto",
				"neighborhood": "West Humber-Clairville",
				"postalCode": "M9W 1N1"
			},
			"geometry": {
				"type": "Point",
				"coordinates": [
					-79.57559,
					43.7084199
				]
			},
			"bbox": [
				-79.5771451,
				43.7072957,
				-79.5740349,
				43.7095441
			]
		}
	]
}
