{
	"type": "FeatureCollection",
	"features": [
		{
			"type": "Feature",
			"properties": {
				"confidence": 9,
				"authenticationResultCode": "ValidCredentials",
				"brandLogoUri": "http://dev.virtualearth.net/Branding/logo_powered_by.png",
				"copyright": "Copyright © 2017 Microsoft and its suppliers. All rights reserved. This API cannot be accessed and the content and any results may not be used, reproduced or transmitted in any manner without express written permission from Microsoft Corporation.",
				"entityType": "Address",
				"matchCodes": [
					"Good"
				],
				"name": "70 Crescent St, Sydney, NS B1S 2Z7, Canada",
				"statusCode": 200,
				"statusDescription": "OK",
				"traceId": "55bd73d8d394438183e9b768121c57cd|BN20130422|7.7.0.0|",
				"addressLine": "70 Crescent St",
				"adminDistrict": "NS",
				"adminDistrict2": "Cape Breton",
				"countryRegion": "Canada",
				"formattedAddress": "70 Crescent St, Sydney, NS B1S 2Z7, Canada",
				"locality": "Cape Breton",
				"neighborhood": "Sydney",
				"postalCode": "B1S 2Z7"
			},
			"geometry": {
				"type": "Point",
				"coordinates": [
					-60.19378,
					46.13146
				]
			},
			"bbox": [
				-60.1954021,
				46.1303358,
				-60.1921579,
				46.1325842
			]
		}
	]
}
