{
	"type": "FeatureCollection",
	"features": [
		{
			"type": "Feature",
			"properties": {
				"confidence": 9,
				"authenticationResultCode": "ValidCredentials",
				"brandLogoUri": "http://dev.virtualearth.net/Branding/logo_powered_by.png",
				"copyright": "Copyright © 2017 Microsoft and its suppliers. All rights reserved. This API cannot be accessed and the content and any results may not be used, reproduced or transmitted in any manner without express written permission from Microsoft Corporation.",
				"entityType": "Address",
				"matchCodes": [
					"Good"
				],
				"name": "700 Avenue Meloche, Dorval, QC H9P 2Y4, Canada",
				"statusCode": 200,
				"statusDescription": "OK",
				"traceId": "579297f70d23491d99f9213ad4b58ea6|BN20130422|7.7.0.0|",
				"addressLine": "700 Avenue Meloche",
				"adminDistrict": "QC",
				"adminDistrict2": "Montreal",
				"countryRegion": "Canada",
				"formattedAddress": "700 Avenue Meloche, Dorval, QC H9P 2Y4, Canada",
				"locality": "Dorval",
				"postalCode": "H9P 2Y4"
			},
			"geometry": {
				"type": "Point",
				"coordinates": [
					-73.72847,
					45.45646
				]
			},
			"bbox": [
				-73.7300726,
				45.4553358,
				-73.7268674,
				45.4575842
			]
		}
	]
}
