{
	"type": "FeatureCollection",
	"features": [
		{
			"type": "Feature",
			"properties": {
				"confidence": 9,
				"authenticationResultCode": "ValidCredentials",
				"brandLogoUri": "http://dev.virtualearth.net/Branding/logo_powered_by.png",
				"copyright": "Copyright © 2017 Microsoft and its suppliers. All rights reserved. This API cannot be accessed and the content and any results may not be used, reproduced or transmitted in any manner without express written permission from Microsoft Corporation.",
				"entityType": "Address",
				"matchCodes": [
					"Good"
				],
				"name": "700 Apex Ave, North Vancouver, BC V7H 2R5, Canada",
				"statusCode": 200,
				"statusDescription": "OK",
				"traceId": "812a32c48522409c86d7f0cabe96fa42|BN20240253|7.7.0.0|",
				"addressLine": "700 Apex Ave",
				"adminDistrict": "BC",
				"adminDistrict2": "Greater Vancouver",
				"countryRegion": "Canada",
				"formattedAddress": "700 Apex Ave, North Vancouver, BC V7H 2R5, Canada",
				"locality": "North Vancouver District",
				"neighborhood": "Parkway",
				"postalCode": "V7H 2R5"
			},
			"geometry": {
				"type": "Point",
				"coordinates": [
					-122.9809737,
					49.3125817
				]
			},
			"bbox": [
				-122.982698,
				49.3114575,
				-122.9792494,
				49.3137058
			]
		}
	]
}
