{
	"type": "FeatureCollection",
	"features": [
		{
			"type": "Feature",
			"properties": {
				"confidence": 7,
				"authenticationResultCode": "ValidCredentials",
				"brandLogoUri": "http://dev.virtualearth.net/Branding/logo_powered_by.png",
				"copyright": "Copyright © 2017 Microsoft and its suppliers. All rights reserved. This API cannot be accessed and the content and any results may not be used, reproduced or transmitted in any manner without express written permission from Microsoft Corporation.",
				"entityType": "RoadBlock",
				"matchCodes": [
					"UpHierarchy"
				],
				"name": "Pacific Rim Hwy, Alberni-Clayoquot, BC V9Y, Canada",
				"statusCode": 200,
				"statusDescription": "OK",
				"traceId": "51311157a7fe42e3818b4c76f85aaef9|BN20121762|7.7.0.0|",
				"addressLine": "Pacific Rim Hwy",
				"adminDistrict": "BC",
				"adminDistrict2": "Alberni-Clayoquot",
				"countryRegion": "Canada",
				"formattedAddress": "Pacific Rim Hwy, Alberni-Clayoquot, BC V9Y, Canada",
				"locality": "Alberni-Clayoquot",
				"neighborhood": "Alberni-Clayoquot",
				"postalCode": "V9Y 9G1"
			},
			"geometry": {
				"type": "Point",
				"coordinates": [
					-124.87978,
					49.27545
				]
			},
			"bbox": [
				-124.90416,
				49.26663,
				-124.85341,
				49.2899
			]
		}
	]
}
