{
	"type": "FeatureCollection",
	"features": [
		{
			"type": "Feature",
			"properties": {
				"confidence": 9,
				"authenticationResultCode": "ValidCredentials",
				"brandLogoUri": "http://dev.virtualearth.net/Branding/logo_powered_by.png",
				"copyright": "Copyright © 2017 Microsoft and its suppliers. All rights reserved. This API cannot be accessed and the content and any results may not be used, reproduced or transmitted in any manner without express written permission from Microsoft Corporation.",
				"entityType": "Address",
				"matchCodes": [
					"Good"
				],
				"name": "7002 39 St, Leduc, AB T9E 0W1, Canada",
				"statusCode": 200,
				"statusDescription": "OK",
				"traceId": "87a06db466604273a8deb10cc90825bd|BN20130442|7.7.0.0|",
				"addressLine": "7002 39 St",
				"adminDistrict": "AB",
				"adminDistrict2": "Alberta",
				"countryRegion": "Canada",
				"formattedAddress": "7002 39 St, Leduc, AB T9E 0W1, Canada",
				"locality": "Leduc",
				"postalCode": "T9E 0W1"
			},
			"geometry": {
				"type": "Point",
				"coordinates": [
					-113.5273359,
					53.2878881
				]
			},
			"bbox": [
				-113.5292163,
				53.286764,
				-113.5254554,
				53.2890123
			]
		}
	]
}
