{
	"type": "FeatureCollection",
	"features": [
		{
			"type": "Feature",
			"properties": {
				"confidence": 9,
				"authenticationResultCode": "ValidCredentials",
				"brandLogoUri": "http://dev.virtualearth.net/Branding/logo_powered_by.png",
				"copyright": "Copyright © 2017 Microsoft and its suppliers. All rights reserved. This API cannot be accessed and the content and any results may not be used, reproduced or transmitted in any manner without express written permission from Microsoft Corporation.",
				"entityType": "Address",
				"matchCodes": [
					"Good"
				],
				"name": "701 Main St SW, Falher, AB T0H, Canada",
				"statusCode": 200,
				"statusDescription": "OK",
				"traceId": "291d59b3262a4a7590f1a76c57b27874|BN20260223|7.7.0.0|",
				"addressLine": "701 Main St SW",
				"adminDistrict": "AB",
				"adminDistrict2": "Alberta",
				"countryRegion": "Canada",
				"formattedAddress": "701 Main St SW, Falher, AB T0H, Canada",
				"locality": "Falher",
				"postalCode": "T0H 1M0"
			},
			"geometry": {
				"type": "Point",
				"coordinates": [
					-117.20275,
					55.73006
				]
			},
			"bbox": [
				-117.2047464,
				55.7289358,
				-117.2007536,
				55.7311842
			]
		}
	]
}
