{
	"type": "FeatureCollection",
	"features": [
		{
			"type": "Feature",
			"properties": {
				"confidence": 9,
				"authenticationResultCode": "ValidCredentials",
				"brandLogoUri": "http://dev.virtualearth.net/Branding/logo_powered_by.png",
				"copyright": "Copyright © 2017 Microsoft and its suppliers. All rights reserved. This API cannot be accessed and the content and any results may not be used, reproduced or transmitted in any manner without express written permission from Microsoft Corporation.",
				"entityType": "Address",
				"matchCodes": [
					"Good"
				],
				"name": "702 Merland Rd, Afton Station, NS B0H 1A0, Canada",
				"statusCode": 200,
				"statusDescription": "OK",
				"traceId": "f3c5cb6ef0ea4e5e92b7e31338a0b01b|BN20200239|7.7.0.0|",
				"addressLine": "702 Merland Rd",
				"adminDistrict": "NS",
				"adminDistrict2": "Antigonish",
				"countryRegion": "Canada",
				"formattedAddress": "702 Merland Rd, Afton Station, NS B0H 1A0, Canada",
				"locality": "Antigonish County",
				"neighborhood": "Afton Station",
				"postalCode": "B0H 1A0"
			},
			"geometry": {
				"type": "Point",
				"coordinates": [
					-61.67101,
					45.59747
				]
			},
			"bbox": [
				-61.6726166,
				45.5963458,
				-61.6694034,
				45.5985942
			]
		}
	]
}
