{
	"type": "FeatureCollection",
	"features": [
		{
			"type": "Feature",
			"properties": {
				"confidence": 9,
				"authenticationResultCode": "ValidCredentials",
				"brandLogoUri": "http://dev.virtualearth.net/Branding/logo_powered_by.png",
				"copyright": "Copyright © 2017 Microsoft and its suppliers. All rights reserved. This API cannot be accessed and the content and any results may not be used, reproduced or transmitted in any manner without express written permission from Microsoft Corporation.",
				"entityType": "Address",
				"matchCodes": [
					"Good"
				],
				"name": "703 Chemin de Martindale, Low, QC J0X 2C0, Canada",
				"statusCode": 200,
				"statusDescription": "OK",
				"traceId": "4f2827a884e147cbb68a16133ad60a38|BN20130631|7.7.0.0|",
				"addressLine": "703 Chemin de Martindale",
				"adminDistrict": "QC",
				"adminDistrict2": "La Vallée-de-la-Gatineau",
				"countryRegion": "Canada",
				"formattedAddress": "703 Chemin de Martindale, Low, QC J0X 2C0, Canada",
				"locality": "Low",
				"postalCode": "J0X 2C0"
			},
			"geometry": {
				"type": "Point",
				"coordinates": [
					-75.93772,
					45.89196
				]
			},
			"bbox": [
				-75.9393351,
				45.8908358,
				-75.9361049,
				45.8930842
			]
		}
	]
}
