{
	"type": "FeatureCollection",
	"features": [
		{
			"type": "Feature",
			"properties": {
				"confidence": 9,
				"authenticationResultCode": "ValidCredentials",
				"brandLogoUri": "http://dev.virtualearth.net/Branding/logo_powered_by.png",
				"copyright": "Copyright © 2017 Microsoft and its suppliers. All rights reserved. This API cannot be accessed and the content and any results may not be used, reproduced or transmitted in any manner without express written permission from Microsoft Corporation.",
				"entityType": "Address",
				"matchCodes": [
					"Good"
				],
				"name": "7045 Tomken Rd, Mississauga, ON L5S 1R7, Canada",
				"statusCode": 200,
				"statusDescription": "OK",
				"traceId": "72091dbf655146d285f340127af72e40|BN20250135|7.7.0.0|",
				"addressLine": "7045 Tomken Rd",
				"adminDistrict": "ON",
				"adminDistrict2": "Peel",
				"countryRegion": "Canada",
				"formattedAddress": "7045 Tomken Rd, Mississauga, ON L5S 1R7, Canada",
				"locality": "Mississauga",
				"postalCode": "L5S 1R7"
			},
			"geometry": {
				"type": "Point",
				"coordinates": [
					-79.68545,
					43.6669399
				]
			},
			"bbox": [
				-79.6870041,
				43.6658157,
				-79.6838959,
				43.6680641
			]
		}
	]
}
