{
	"type": "FeatureCollection",
	"features": [
		{
			"type": "Feature",
			"properties": {
				"confidence": 9,
				"authenticationResultCode": "ValidCredentials",
				"brandLogoUri": "http://dev.virtualearth.net/Branding/logo_powered_by.png",
				"copyright": "Copyright © 2017 Microsoft and its suppliers. All rights reserved. This API cannot be accessed and the content and any results may not be used, reproduced or transmitted in any manner without express written permission from Microsoft Corporation.",
				"entityType": "Address",
				"matchCodes": [
					"Good"
				],
				"name": "707 23 Ave SE, Calgary, AB T2G 1N7, Canada",
				"statusCode": 200,
				"statusDescription": "OK",
				"traceId": "ffc5ebe6936744379cfa4a87359d5175|BN20190642|7.7.0.0|",
				"addressLine": "707 23 Ave SE",
				"adminDistrict": "AB",
				"adminDistrict2": "Alberta",
				"countryRegion": "Canada",
				"formattedAddress": "707 23 Ave SE, Calgary, AB T2G 1N7, Canada",
				"locality": "Calgary",
				"neighborhood": "Ramsay",
				"postalCode": "T2G 1N7"
			},
			"geometry": {
				"type": "Point",
				"coordinates": [
					-114.04482,
					51.03269
				]
			},
			"bbox": [
				-114.0466076,
				51.0315658,
				-114.0430324,
				51.0338142
			]
		}
	]
}
