{
	"type": "FeatureCollection",
	"features": [
		{
			"type": "Feature",
			"properties": {
				"confidence": 9,
				"authenticationResultCode": "ValidCredentials",
				"brandLogoUri": "http://dev.virtualearth.net/Branding/logo_powered_by.png",
				"copyright": "Copyright © 2017 Microsoft and its suppliers. All rights reserved. This API cannot be accessed and the content and any results may not be used, reproduced or transmitted in any manner without express written permission from Microsoft Corporation.",
				"entityType": "Address",
				"matchCodes": [
					"Good"
				],
				"name": "709 Hambly Rd, Greater Napanee, ON K7R, Canada",
				"statusCode": 200,
				"statusDescription": "OK",
				"traceId": "deae94d6326a4c499d6918ed2b12e385|BN20130719|7.7.0.0|",
				"addressLine": "709 Hambly Rd",
				"adminDistrict": "ON",
				"adminDistrict2": "Lennox and Addington",
				"countryRegion": "Canada",
				"formattedAddress": "709 Hambly Rd, Greater Napanee, ON K7R, Canada",
				"locality": "Greater Napanee",
				"neighborhood": "Napanee",
				"postalCode": "K7R 3K8"
			},
			"geometry": {
				"type": "Point",
				"coordinates": [
					-76.9408214,
					44.1980272
				]
			},
			"bbox": [
				-76.9423894,
				44.1969031,
				-76.9392534,
				44.1991514
			]
		}
	]
}
