{
	"type": "FeatureCollection",
	"features": [
		{
			"type": "Feature",
			"properties": {
				"confidence": 9,
				"authenticationResultCode": "ValidCredentials",
				"brandLogoUri": "http://dev.virtualearth.net/Branding/logo_powered_by.png",
				"copyright": "Copyright © 2017 Microsoft and its suppliers. All rights reserved. This API cannot be accessed and the content and any results may not be used, reproduced or transmitted in any manner without express written permission from Microsoft Corporation.",
				"entityType": "Address",
				"matchCodes": [
					"Good"
				],
				"name": "709 43rd St E, Saskatoon, SK S7K 0V7, Canada",
				"statusCode": 200,
				"statusDescription": "OK",
				"traceId": "195b5e123f714b5ebe540e68c8735cd4|BN20130520|7.7.0.0|",
				"addressLine": "709 43rd St E",
				"adminDistrict": "SK",
				"adminDistrict2": "Saskatchewan",
				"countryRegion": "Canada",
				"formattedAddress": "709 43rd St E, Saskatoon, SK S7K 0V7, Canada",
				"locality": "Saskatoon",
				"neighborhood": "North Industrial",
				"postalCode": "S7K 0V7"
			},
			"geometry": {
				"type": "Point",
				"coordinates": [
					-106.6564099,
					52.15966
				]
			},
			"bbox": [
				-106.6582424,
				52.1585358,
				-106.6545774,
				52.1607842
			]
		}
	]
}
