{
	"type": "FeatureCollection",
	"features": [
		{
			"type": "Feature",
			"properties": {
				"confidence": 9,
				"authenticationResultCode": "ValidCredentials",
				"brandLogoUri": "http://dev.virtualearth.net/Branding/logo_powered_by.png",
				"copyright": "Copyright © 2017 Microsoft and its suppliers. All rights reserved. This API cannot be accessed and the content and any results may not be used, reproduced or transmitted in any manner without express written permission from Microsoft Corporation.",
				"entityType": "Address",
				"matchCodes": [
					"Good"
				],
				"name": "71 Lynnwood Ave, Chatham, ON N7M 5J4, Canada",
				"statusCode": 200,
				"statusDescription": "OK",
				"traceId": "40483e3e92984d739d9475ef05e0da0c|BN20210145|7.7.0.0|",
				"addressLine": "71 Lynnwood Ave",
				"adminDistrict": "ON",
				"adminDistrict2": "Chatham-Kent",
				"countryRegion": "Canada",
				"formattedAddress": "71 Lynnwood Ave, Chatham, ON N7M 5J4, Canada",
				"locality": "Chatham-Kent",
				"neighborhood": "Chatham",
				"postalCode": "N7M 5J4"
			},
			"geometry": {
				"type": "Point",
				"coordinates": [
					-82.14709,
					42.4161
				]
			},
			"bbox": [
				-82.1486127,
				42.4149758,
				-82.1455673,
				42.4172242
			]
		}
	]
}
