{
	"type": "FeatureCollection",
	"features": [
		{
			"type": "Feature",
			"properties": {
				"confidence": 9,
				"authenticationResultCode": "ValidCredentials",
				"brandLogoUri": "http://dev.virtualearth.net/Branding/logo_powered_by.png",
				"copyright": "Copyright © 2017 Microsoft and its suppliers. All rights reserved. This API cannot be accessed and the content and any results may not be used, reproduced or transmitted in any manner without express written permission from Microsoft Corporation.",
				"entityType": "Address",
				"matchCodes": [
					"Good"
				],
				"name": "710 Burnhamthorpe Rd E, Mississauga, ON L4Y 2X3, Canada",
				"statusCode": 200,
				"statusDescription": "OK",
				"traceId": "1ff0416d7693432391d44ab10a75754f|BN20121764|7.7.0.0|",
				"addressLine": "710 Burnhamthorpe Rd E",
				"adminDistrict": "ON",
				"adminDistrict2": "Peel",
				"countryRegion": "Canada",
				"formattedAddress": "710 Burnhamthorpe Rd E, Mississauga, ON L4Y 2X3, Canada",
				"locality": "Mississauga",
				"neighborhood": "Dixie",
				"postalCode": "L4Y 2X3"
			},
			"geometry": {
				"type": "Point",
				"coordinates": [
					-79.61773,
					43.60806
				]
			},
			"bbox": [
				-79.6192825,
				43.6069358,
				-79.6161775,
				43.6091842
			]
		}
	]
}
