{
	"type": "FeatureCollection",
	"features": [
		{
			"type": "Feature",
			"properties": {
				"confidence": 9,
				"authenticationResultCode": "ValidCredentials",
				"brandLogoUri": "http://dev.virtualearth.net/Branding/logo_powered_by.png",
				"copyright": "Copyright © 2017 Microsoft and its suppliers. All rights reserved. This API cannot be accessed and the content and any results may not be used, reproduced or transmitted in any manner without express written permission from Microsoft Corporation.",
				"entityType": "Address",
				"matchCodes": [
					"Good"
				],
				"name": "710 48th St E, Saskatoon, SK S7K 5B4, Canada",
				"statusCode": 200,
				"statusDescription": "OK",
				"traceId": "765549161f8b4ae7be71c38052331a7d|BN20130447|7.7.0.0|",
				"addressLine": "710 48th St E",
				"adminDistrict": "SK",
				"adminDistrict2": "Saskatchewan",
				"countryRegion": "Canada",
				"formattedAddress": "710 48th St E, Saskatoon, SK S7K 5B4, Canada",
				"locality": "Saskatoon",
				"neighborhood": "North Industrial",
				"postalCode": "S7K 5B4"
			},
			"geometry": {
				"type": "Point",
				"coordinates": [
					-106.65704,
					52.16903
				]
			},
			"bbox": [
				-106.6588729,
				52.1679058,
				-106.6552071,
				52.1701542
			]
		}
	]
}
