{
	"type": "FeatureCollection",
	"features": [
		{
			"type": "Feature",
			"properties": {
				"confidence": 9,
				"authenticationResultCode": "ValidCredentials",
				"brandLogoUri": "http://dev.virtualearth.net/Branding/logo_powered_by.png",
				"copyright": "Copyright © 2017 Microsoft and its suppliers. All rights reserved. This API cannot be accessed and the content and any results may not be used, reproduced or transmitted in any manner without express written permission from Microsoft Corporation.",
				"entityType": "Address",
				"matchCodes": [
					"Good"
				],
				"name": "712 Dundas St W, Belleville, ON K8N 4Z2, Canada",
				"statusCode": 200,
				"statusDescription": "OK",
				"traceId": "4a3d42e6f20a4a02bb18195b29b6012b|BN20181720|7.7.0.0|",
				"addressLine": "712 Dundas St W",
				"adminDistrict": "ON",
				"adminDistrict2": "Hastings",
				"countryRegion": "Canada",
				"formattedAddress": "712 Dundas St W, Belleville, ON K8N 4Z2, Canada",
				"locality": "Belleville",
				"postalCode": "K8N 4Z2"
			},
			"geometry": {
				"type": "Point",
				"coordinates": [
					-77.42592,
					44.14069
				]
			},
			"bbox": [
				-77.4274865,
				44.1395658,
				-77.4243535,
				44.1418142
			]
		}
	]
}
