{
	"type": "FeatureCollection",
	"features": [
		{
			"type": "Feature",
			"properties": {
				"confidence": 9,
				"authenticationResultCode": "ValidCredentials",
				"brandLogoUri": "http://dev.virtualearth.net/Branding/logo_powered_by.png",
				"copyright": "Copyright © 2017 Microsoft and its suppliers. All rights reserved. This API cannot be accessed and the content and any results may not be used, reproduced or transmitted in any manner without express written permission from Microsoft Corporation.",
				"entityType": "Address",
				"matchCodes": [
					"Good"
				],
				"name": "713 Lansdowne Ave, Toronto, ON M6H 3Y9, Canada",
				"statusCode": 200,
				"statusDescription": "OK",
				"traceId": "6c86cbb8754b4f2280b48ae0cec36503|BN20130533|7.7.0.0|",
				"addressLine": "713 Lansdowne Ave",
				"adminDistrict": "ON",
				"adminDistrict2": "Toronto",
				"countryRegion": "Canada",
				"formattedAddress": "713 Lansdowne Ave, Toronto, ON M6H 3Y9, Canada",
				"locality": "Toronto",
				"neighborhood": "Dovercourt-Wallace Emerson-Junction",
				"postalCode": "M6H 3Y9"
			},
			"geometry": {
				"type": "Point",
				"coordinates": [
					-79.44291,
					43.65963
				]
			},
			"bbox": [
				-79.4444639,
				43.6585058,
				-79.4413561,
				43.6607542
			]
		}
	]
}
