{
	"type": "FeatureCollection",
	"features": [
		{
			"type": "Feature",
			"properties": {
				"confidence": 9,
				"authenticationResultCode": "ValidCredentials",
				"brandLogoUri": "http://dev.virtualearth.net/Branding/logo_powered_by.png",
				"copyright": "Copyright © 2017 Microsoft and its suppliers. All rights reserved. This API cannot be accessed and the content and any results may not be used, reproduced or transmitted in any manner without express written permission from Microsoft Corporation.",
				"entityType": "Address",
				"matchCodes": [
					"Good"
				],
				"name": "716 Gordon Baker Rd, North York, ON M2H 3B4, Canada",
				"statusCode": 200,
				"statusDescription": "OK",
				"traceId": "8628a533467745b491d62c5f700fc766|BN20130422|7.7.0.0|",
				"addressLine": "716 Gordon Baker Rd",
				"adminDistrict": "ON",
				"adminDistrict2": "Toronto",
				"countryRegion": "Canada",
				"formattedAddress": "716 Gordon Baker Rd, North York, ON M2H 3B4, Canada",
				"locality": "Toronto",
				"neighborhood": "Hillcrest Village",
				"postalCode": "M2H 3B4"
			},
			"geometry": {
				"type": "Point",
				"coordinates": [
					-79.3428836,
					43.8099001
				]
			},
			"bbox": [
				-79.3444414,
				43.808776,
				-79.3413258,
				43.8110243
			]
		}
	]
}
