{
	"type": "FeatureCollection",
	"features": [
		{
			"type": "Feature",
			"properties": {
				"confidence": 9,
				"authenticationResultCode": "ValidCredentials",
				"brandLogoUri": "http://dev.virtualearth.net/Branding/logo_powered_by.png",
				"copyright": "Copyright © 2017 Microsoft and its suppliers. All rights reserved. This API cannot be accessed and the content and any results may not be used, reproduced or transmitted in any manner without express written permission from Microsoft Corporation.",
				"entityType": "Address",
				"matchCodes": [
					"Good"
				],
				"name": "7168 10th Line, Thornton, ON L0L 2N0, Canada",
				"statusCode": 200,
				"statusDescription": "OK",
				"traceId": "5274dbc8b4dc42ec90ec05e24dea5d41|BN20250135|7.7.0.0|",
				"addressLine": "7168 10th Line",
				"adminDistrict": "ON",
				"adminDistrict2": "Simcoe",
				"countryRegion": "Canada",
				"formattedAddress": "7168 10th Line, Thornton, ON L0L 2N0, Canada",
				"locality": "Essa",
				"neighborhood": "Thornton",
				"postalCode": "L0L 2N0"
			},
			"geometry": {
				"type": "Point",
				"coordinates": [
					-79.7579499,
					44.27723
				]
			},
			"bbox": [
				-79.75952,
				44.2761058,
				-79.7563798,
				44.2783542
			]
		}
	]
}
