{
	"type": "FeatureCollection",
	"features": [
		{
			"type": "Feature",
			"properties": {
				"confidence": 9,
				"authenticationResultCode": "ValidCredentials",
				"brandLogoUri": "http://dev.virtualearth.net/Branding/logo_powered_by.png",
				"copyright": "Copyright © 2017 Microsoft and its suppliers. All rights reserved. This API cannot be accessed and the content and any results may not be used, reproduced or transmitted in any manner without express written permission from Microsoft Corporation.",
				"entityType": "Address",
				"matchCodes": [
					"Good"
				],
				"name": "7168 Honeyman St, Delta, BC V4G 1G1, Canada",
				"statusCode": 200,
				"statusDescription": "OK",
				"traceId": "700c09b984724a578d15dd131474c69c|BN20190642|7.7.0.0|",
				"addressLine": "7168 Honeyman St",
				"adminDistrict": "BC",
				"adminDistrict2": "Greater Vancouver",
				"countryRegion": "Canada",
				"formattedAddress": "7168 Honeyman St, Delta, BC V4G 1G1, Canada",
				"locality": "Delta",
				"postalCode": "V4G 1G1"
			},
			"geometry": {
				"type": "Point",
				"coordinates": [
					-123.0179,
					49.13264
				]
			},
			"bbox": [
				-123.0196181,
				49.1315158,
				-123.0161819,
				49.1337642
			]
		}
	]
}
