{
	"type": "FeatureCollection",
	"features": [
		{
			"type": "Feature",
			"properties": {
				"confidence": 7,
				"authenticationResultCode": "ValidCredentials",
				"brandLogoUri": "http://dev.virtualearth.net/Branding/logo_powered_by.png",
				"copyright": "Copyright © 2017 Microsoft and its suppliers. All rights reserved. This API cannot be accessed and the content and any results may not be used, reproduced or transmitted in any manner without express written permission from Microsoft Corporation.",
				"entityType": "RoadBlock",
				"matchCodes": [
					"UpHierarchy"
				],
				"name": "Range Road 62, Grande Prairie County No 1, AB T0H, Canada",
				"statusCode": 200,
				"statusDescription": "OK",
				"traceId": "1212b05282b14a6584cd7a8491cd5e36|BN20190642|7.7.0.0|",
				"addressLine": "Range Road 62",
				"adminDistrict": "AB",
				"adminDistrict2": "Alberta",
				"countryRegion": "Canada",
				"formattedAddress": "Range Road 62, Grande Prairie County No 1, AB T0H, Canada",
				"locality": "Grande Prairie County No 1",
				"neighborhood": "Clairmont",
				"postalCode": "T0H"
			},
			"geometry": {
				"type": "Point",
				"coordinates": [
					-118.82058,
					55.24442
				]
			},
			"bbox": [
				-118.82061,
				55.22956,
				-118.82058,
				55.25927
			]
		}
	]
}
