{
	"type": "FeatureCollection",
	"features": [
		{
			"type": "Feature",
			"properties": {
				"confidence": 9,
				"authenticationResultCode": "ValidCredentials",
				"brandLogoUri": "http://dev.virtualearth.net/Branding/logo_powered_by.png",
				"copyright": "Copyright © 2017 Microsoft and its suppliers. All rights reserved. This API cannot be accessed and the content and any results may not be used, reproduced or transmitted in any manner without express written permission from Microsoft Corporation.",
				"entityType": "Address",
				"matchCodes": [
					"Good"
				],
				"name": "7217 Girard Rd NW, Edmonton, AB T6B 2C5, Canada",
				"statusCode": 200,
				"statusDescription": "OK",
				"traceId": "548365b7ec904afd83fd68506db0aa95|BN20121764|7.7.0.0|",
				"addressLine": "7217 Girard Rd NW",
				"adminDistrict": "AB",
				"adminDistrict2": "Alberta",
				"countryRegion": "Canada",
				"formattedAddress": "7217 Girard Rd NW, Edmonton, AB T6B 2C5, Canada",
				"locality": "Edmonton",
				"neighborhood": "Girard Industrial",
				"postalCode": "T6B 2C5"
			},
			"geometry": {
				"type": "Point",
				"coordinates": [
					-113.43905,
					53.50817
				]
			},
			"bbox": [
				-113.4409403,
				53.5070458,
				-113.4371597,
				53.5092942
			]
		}
	]
}
