{
	"type": "FeatureCollection",
	"features": [
		{
			"type": "Feature",
			"properties": {
				"confidence": 9,
				"authenticationResultCode": "ValidCredentials",
				"brandLogoUri": "http://dev.virtualearth.net/Branding/logo_powered_by.png",
				"copyright": "Copyright © 2017 Microsoft and its suppliers. All rights reserved. This API cannot be accessed and the content and any results may not be used, reproduced or transmitted in any manner without express written permission from Microsoft Corporation.",
				"entityType": "Address",
				"matchCodes": [
					"Good"
				],
				"name": "7220 Winston St, Burnaby, BC V5A 2G9, Canada",
				"statusCode": 200,
				"statusDescription": "OK",
				"traceId": "744d30c9057d4bb59e503e3efa2ef4ac|BN20130522|7.7.0.0|",
				"addressLine": "7220 Winston St",
				"adminDistrict": "BC",
				"adminDistrict2": "Greater Vancouver",
				"countryRegion": "Canada",
				"formattedAddress": "7220 Winston St, Burnaby, BC V5A 2G9, Canada",
				"locality": "Burnaby",
				"neighborhood": "Government Road",
				"postalCode": "V5A 2G9"
			},
			"geometry": {
				"type": "Point",
				"coordinates": [
					-122.9536072,
					49.2498651
				]
			},
			"bbox": [
				-122.9553293,
				49.2487409,
				-122.951885,
				49.2509893
			]
		}
	]
}
