{
	"type": "FeatureCollection",
	"features": [
		{
			"type": "Feature",
			"properties": {
				"confidence": 9,
				"authenticationResultCode": "ValidCredentials",
				"brandLogoUri": "http://dev.virtualearth.net/Branding/logo_powered_by.png",
				"copyright": "Copyright © 2017 Microsoft and its suppliers. All rights reserved. This API cannot be accessed and the content and any results may not be used, reproduced or transmitted in any manner without express written permission from Microsoft Corporation.",
				"entityType": "Address",
				"matchCodes": [
					"Good"
				],
				"name": "723 49 Ave SW, Calgary, AB T2S 1G7, Canada",
				"statusCode": 200,
				"statusDescription": "OK",
				"traceId": "b801f36268974dd0aebc006abe54efc3|BN20130533|7.7.0.0|",
				"addressLine": "723 49 Ave SW",
				"adminDistrict": "AB",
				"adminDistrict2": "Alberta",
				"countryRegion": "Canada",
				"formattedAddress": "723 49 Ave SW, Calgary, AB T2S 1G7, Canada",
				"locality": "Calgary",
				"neighborhood": "Elboya",
				"postalCode": "T2S 1G7"
			},
			"geometry": {
				"type": "Point",
				"coordinates": [
					-114.08026,
					51.00946
				]
			},
			"bbox": [
				-114.0820467,
				51.0083358,
				-114.0784733,
				51.0105842
			]
		}
	]
}
