{
	"type": "FeatureCollection",
	"features": [
		{
			"type": "Feature",
			"properties": {
				"confidence": 9,
				"authenticationResultCode": "ValidCredentials",
				"brandLogoUri": "http://dev.virtualearth.net/Branding/logo_powered_by.png",
				"copyright": "Copyright © 2017 Microsoft and its suppliers. All rights reserved. This API cannot be accessed and the content and any results may not be used, reproduced or transmitted in any manner without express written permission from Microsoft Corporation.",
				"entityType": "Address",
				"matchCodes": [
					"Good"
				],
				"name": "724 Michigan Ave, Point Edward, ON N7V 1G8, Canada",
				"statusCode": 200,
				"statusDescription": "OK",
				"traceId": "90cf3cf895f248888fe2198426d70199|BN20121762|7.7.0.0|",
				"addressLine": "724 Michigan Ave",
				"adminDistrict": "ON",
				"adminDistrict2": "Lambton",
				"countryRegion": "Canada",
				"formattedAddress": "724 Michigan Ave, Point Edward, ON N7V 1G8, Canada",
				"locality": "Point Edward",
				"postalCode": "N7V 1G8"
			},
			"geometry": {
				"type": "Point",
				"coordinates": [
					-82.40373,
					42.99794
				]
			},
			"bbox": [
				-82.405267,
				42.9968158,
				-82.402193,
				42.9990642
			]
		}
	]
}
