{
	"type": "FeatureCollection",
	"features": [
		{
			"type": "Feature",
			"properties": {
				"confidence": 9,
				"authenticationResultCode": "ValidCredentials",
				"brandLogoUri": "http://dev.virtualearth.net/Branding/logo_powered_by.png",
				"copyright": "Copyright © 2017 Microsoft and its suppliers. All rights reserved. This API cannot be accessed and the content and any results may not be used, reproduced or transmitted in any manner without express written permission from Microsoft Corporation.",
				"entityType": "Address",
				"matchCodes": [
					"Good"
				],
				"name": "727 Lorne St, Sudbury, ON P3C 4R5, Canada",
				"statusCode": 200,
				"statusDescription": "OK",
				"traceId": "94ebf93ba6ed4c178b0e90f2dd603bf0|BN20240253|7.7.0.0|",
				"addressLine": "727 Lorne St",
				"adminDistrict": "ON",
				"adminDistrict2": "Greater Sudbury",
				"countryRegion": "Canada",
				"formattedAddress": "727 Lorne St, Sudbury, ON P3C 4R5, Canada",
				"locality": "Greater Sudbury",
				"neighborhood": "Sudbury",
				"postalCode": "P3C 4R5"
			},
			"geometry": {
				"type": "Point",
				"coordinates": [
					-81.01543,
					46.47891
				]
			},
			"bbox": [
				-81.0170625,
				46.4777858,
				-81.0137975,
				46.4800342
			]
		}
	]
}
