{
	"type": "FeatureCollection",
	"features": [
		{
			"type": "Feature",
			"properties": {
				"confidence": 9,
				"authenticationResultCode": "ValidCredentials",
				"brandLogoUri": "http://dev.virtualearth.net/Branding/logo_powered_by.png",
				"copyright": "Copyright © 2017 Microsoft and its suppliers. All rights reserved. This API cannot be accessed and the content and any results may not be used, reproduced or transmitted in any manner without express written permission from Microsoft Corporation.",
				"entityType": "Address",
				"matchCodes": [
					"Good"
				],
				"name": "730 Birchmount Rd, Scarborough, ON M1K 5H2, Canada",
				"statusCode": 200,
				"statusDescription": "OK",
				"traceId": "a2553d2e6cce40e68f56666f2f0b2842|BN20160335|7.7.0.0|",
				"addressLine": "730 Birchmount Rd",
				"adminDistrict": "ON",
				"adminDistrict2": "Toronto",
				"countryRegion": "Canada",
				"formattedAddress": "730 Birchmount Rd, Scarborough, ON M1K 5H2, Canada",
				"locality": "Toronto",
				"neighborhood": "Clairlea-Birchmount",
				"postalCode": "M1K 5H2"
			},
			"geometry": {
				"type": "Point",
				"coordinates": [
					-79.2764399,
					43.7239999
				]
			},
			"bbox": [
				-79.2779954,
				43.7228757,
				-79.2748844,
				43.7251241
			]
		}
	]
}
