{
	"type": "FeatureCollection",
	"features": [
		{
			"type": "Feature",
			"properties": {
				"confidence": 9,
				"authenticationResultCode": "ValidCredentials",
				"brandLogoUri": "http://dev.virtualearth.net/Branding/logo_powered_by.png",
				"copyright": "Copyright © 2017 Microsoft and its suppliers. All rights reserved. This API cannot be accessed and the content and any results may not be used, reproduced or transmitted in any manner without express written permission from Microsoft Corporation.",
				"entityType": "Address",
				"matchCodes": [
					"Good"
				],
				"name": "731 HWY-2, Elmsdale, NS B2S 1A8, Canada",
				"statusCode": 200,
				"statusDescription": "OK",
				"traceId": "e5620b5b63fc44198f82a950985af4e7|BN20130522|7.7.0.0|",
				"addressLine": "731 HWY-2",
				"adminDistrict": "NS",
				"adminDistrict2": "Hants",
				"countryRegion": "Canada",
				"formattedAddress": "731 HWY-2, Elmsdale, NS B2S 1A8, Canada",
				"locality": "East Hants",
				"neighborhood": "Elmsdale",
				"postalCode": "B2S 1A8"
			},
			"geometry": {
				"type": "Point",
				"coordinates": [
					-63.5071147,
					44.9658618
				]
			},
			"bbox": [
				-63.5087035,
				44.9647377,
				-63.5055259,
				44.966986
			]
		}
	]
}
