{
	"type": "FeatureCollection",
	"features": [
		{
			"type": "Feature",
			"properties": {
				"confidence": 9,
				"authenticationResultCode": "ValidCredentials",
				"brandLogoUri": "http://dev.virtualearth.net/Branding/logo_powered_by.png",
				"copyright": "Copyright © 2017 Microsoft and its suppliers. All rights reserved. This API cannot be accessed and the content and any results may not be used, reproduced or transmitted in any manner without express written permission from Microsoft Corporation.",
				"entityType": "Address",
				"matchCodes": [
					"Good"
				],
				"name": "7310 Woodbine Ave, Markham, ON L3R 1A4, Canada",
				"statusCode": 200,
				"statusDescription": "OK",
				"traceId": "e0e5289dbd0347b5bb21066360a5de18|BN20130533|7.7.0.0|",
				"addressLine": "7310 Woodbine Ave",
				"adminDistrict": "ON",
				"adminDistrict2": "York",
				"countryRegion": "Canada",
				"formattedAddress": "7310 Woodbine Ave, Markham, ON L3R 1A4, Canada",
				"locality": "Markham",
				"postalCode": "L3R 1A4"
			},
			"geometry": {
				"type": "Point",
				"coordinates": [
					-79.35153,
					43.82139
				]
			},
			"bbox": [
				-79.3530881,
				43.8202658,
				-79.3499719,
				43.8225142
			]
		}
	]
}
