{
	"type": "FeatureCollection",
	"features": [
		{
			"type": "Feature",
			"properties": {
				"confidence": 9,
				"authenticationResultCode": "ValidCredentials",
				"brandLogoUri": "http://dev.virtualearth.net/Branding/logo_powered_by.png",
				"copyright": "Copyright © 2017 Microsoft and its suppliers. All rights reserved. This API cannot be accessed and the content and any results may not be used, reproduced or transmitted in any manner without express written permission from Microsoft Corporation.",
				"entityType": "Address",
				"matchCodes": [
					"Good"
				],
				"name": "7373 Rue Cordner, La Salle, QC H8N 2R5, Canada",
				"statusCode": 200,
				"statusDescription": "OK",
				"traceId": "3be6c3f761dd4eb8b2ec02db85d3b6e5|BN20130625|7.7.0.0|",
				"addressLine": "7373 Rue Cordner",
				"adminDistrict": "QC",
				"adminDistrict2": "Montreal",
				"countryRegion": "Canada",
				"formattedAddress": "7373 Rue Cordner, La Salle, QC H8N 2R5, Canada",
				"locality": "Montreal",
				"neighborhood": "La Salle",
				"postalCode": "H8N 2R5"
			},
			"geometry": {
				"type": "Point",
				"coordinates": [
					-73.62694,
					45.44441
				]
			},
			"bbox": [
				-73.6285423,
				45.4432858,
				-73.6253377,
				45.4455342
			]
		}
	]
}
