{
	"type": "FeatureCollection",
	"features": [
		{
			"type": "Feature",
			"properties": {
				"confidence": 9,
				"authenticationResultCode": "ValidCredentials",
				"brandLogoUri": "http://dev.virtualearth.net/Branding/logo_powered_by.png",
				"copyright": "Copyright © 2017 Microsoft and its suppliers. All rights reserved. This API cannot be accessed and the content and any results may not be used, reproduced or transmitted in any manner without express written permission from Microsoft Corporation.",
				"entityType": "Address",
				"matchCodes": [
					"Good"
				],
				"name": "74 Rue MacDonald, Kirkland, QC H9J 3Z7, Canada",
				"statusCode": 200,
				"statusDescription": "OK",
				"traceId": "08a0bfafe6b448f583533770143cd0e3|BN20130520|7.7.0.0|",
				"addressLine": "74 Rue MacDonald",
				"adminDistrict": "QC",
				"adminDistrict2": "Montreal",
				"countryRegion": "Canada",
				"formattedAddress": "74 Rue MacDonald, Kirkland, QC H9J 3Z7, Canada",
				"locality": "Kirkland",
				"postalCode": "H9J 3Z7"
			},
			"geometry": {
				"type": "Point",
				"coordinates": [
					-73.89536,
					45.44121
				]
			},
			"bbox": [
				-73.8969622,
				45.4400858,
				-73.8937578,
				45.4423342
			]
		}
	]
}
