{
	"type": "FeatureCollection",
	"features": [
		{
			"type": "Feature",
			"properties": {
				"confidence": 9,
				"authenticationResultCode": "ValidCredentials",
				"brandLogoUri": "http://dev.virtualearth.net/Branding/logo_powered_by.png",
				"copyright": "Copyright © 2017 Microsoft and its suppliers. All rights reserved. This API cannot be accessed and the content and any results may not be used, reproduced or transmitted in any manner without express written permission from Microsoft Corporation.",
				"entityType": "Address",
				"matchCodes": [
					"Good"
				],
				"name": "74 Songbird Pvt, Nepean, ON K2H 0A2, Canada",
				"statusCode": 200,
				"statusDescription": "OK",
				"traceId": "73d29c4bb0d84b6dbbb90e4450103e53|BN20130631|7.7.0.0|",
				"addressLine": "74 Songbird Pvt",
				"adminDistrict": "ON",
				"adminDistrict2": "Ottawa",
				"countryRegion": "Canada",
				"formattedAddress": "74 Songbird Pvt, Nepean, ON K2H 0A2, Canada",
				"locality": "Ottawa",
				"neighborhood": "Nepean",
				"postalCode": "K2H 0A2"
			},
			"geometry": {
				"type": "Point",
				"coordinates": [
					-75.82763,
					45.31042
				]
			},
			"bbox": [
				-75.8292285,
				45.3092958,
				-75.8260315,
				45.3115442
			]
		}
	]
}
