{
	"type": "FeatureCollection",
	"features": [
		{
			"type": "Feature",
			"properties": {
				"confidence": 9,
				"authenticationResultCode": "ValidCredentials",
				"brandLogoUri": "http://dev.virtualearth.net/Branding/logo_powered_by.png",
				"copyright": "Copyright © 2017 Microsoft and its suppliers. All rights reserved. This API cannot be accessed and the content and any results may not be used, reproduced or transmitted in any manner without express written permission from Microsoft Corporation.",
				"entityType": "Address",
				"matchCodes": [
					"Good"
				],
				"name": "740 Marion Rd, Abbotsford, BC V3G 1S7, Canada",
				"statusCode": 200,
				"statusDescription": "OK",
				"traceId": "1fcdb7468126435aaab74663b21b89e5|BN20160335|7.7.0.0|",
				"addressLine": "740 Marion Rd",
				"adminDistrict": "BC",
				"adminDistrict2": "Fraser Valley",
				"countryRegion": "Canada",
				"formattedAddress": "740 Marion Rd, Abbotsford, BC V3G 1S7, Canada",
				"locality": "Abbotsford",
				"neighborhood": "Sumas Prairie",
				"postalCode": "V3G 1S7"
			},
			"geometry": {
				"type": "Point",
				"coordinates": [
					-122.13858,
					49.01583
				]
			},
			"bbox": [
				-122.140294,
				49.0147058,
				-122.136866,
				49.0169542
			]
		}
	]
}
