{
	"type": "FeatureCollection",
	"features": [
		{
			"type": "Feature",
			"properties": {
				"confidence": 9,
				"authenticationResultCode": "ValidCredentials",
				"brandLogoUri": "http://dev.virtualearth.net/Branding/logo_powered_by.png",
				"copyright": "Copyright © 2017 Microsoft and its suppliers. All rights reserved. This API cannot be accessed and the content and any results may not be used, reproduced or transmitted in any manner without express written permission from Microsoft Corporation.",
				"entityType": "Address",
				"matchCodes": [
					"Good"
				],
				"name": "740 Rue Galt O, Sherbrooke, QC J1H 1Z3, Canada",
				"statusCode": 200,
				"statusDescription": "OK",
				"traceId": "e286afb2f16c41a78e2a2443456b5e47|BN20190653|7.7.0.0|",
				"addressLine": "740 Rue Galt O",
				"adminDistrict": "QC",
				"adminDistrict2": "Sherbrooke",
				"countryRegion": "Canada",
				"formattedAddress": "740 Rue Galt O, Sherbrooke, QC J1H 1Z3, Canada",
				"locality": "Sherbrooke",
				"postalCode": "J1H 1Z3"
			},
			"geometry": {
				"type": "Point",
				"coordinates": [
					-71.8968001,
					45.3940553
				]
			},
			"bbox": [
				-71.8984009,
				45.3929312,
				-71.8951992,
				45.3951795
			]
		}
	]
}
