{
	"type": "FeatureCollection",
	"features": [
		{
			"type": "Feature",
			"properties": {
				"confidence": 9,
				"authenticationResultCode": "ValidCredentials",
				"brandLogoUri": "http://dev.virtualearth.net/Branding/logo_powered_by.png",
				"copyright": "Copyright © 2017 Microsoft and its suppliers. All rights reserved. This API cannot be accessed and the content and any results may not be used, reproduced or transmitted in any manner without express written permission from Microsoft Corporation.",
				"entityType": "Address",
				"matchCodes": [
					"Good"
				],
				"name": "7424 87 St NW, Edmonton, AB T6C 3G3, Canada",
				"statusCode": 200,
				"statusDescription": "OK",
				"traceId": "faacc741f06847cf88a7ae27d1427635|BN20121762|7.7.0.0|",
				"addressLine": "7424 87 St NW",
				"adminDistrict": "AB",
				"adminDistrict2": "Alberta",
				"countryRegion": "Canada",
				"formattedAddress": "7424 87 St NW, Edmonton, AB T6C 3G3, Canada",
				"locality": "Edmonton",
				"neighborhood": "Avonmore",
				"postalCode": "T6C 3G3"
			},
			"geometry": {
				"type": "Point",
				"coordinates": [
					-113.46134,
					53.51084
				]
			},
			"bbox": [
				-113.4632304,
				53.5097158,
				-113.4594496,
				53.5119642
			]
		}
	]
}
