{
	"type": "FeatureCollection",
	"features": [
		{
			"type": "Feature",
			"properties": {
				"confidence": 9,
				"authenticationResultCode": "ValidCredentials",
				"brandLogoUri": "http://dev.virtualearth.net/Branding/logo_powered_by.png",
				"copyright": "Copyright © 2017 Microsoft and its suppliers. All rights reserved. This API cannot be accessed and the content and any results may not be used, reproduced or transmitted in any manner without express written permission from Microsoft Corporation.",
				"entityType": "Address",
				"matchCodes": [
					"Good"
				],
				"name": "7430 Airlie Ct, Burnaby, BC V5A 3R2, Canada",
				"statusCode": 200,
				"statusDescription": "OK",
				"traceId": "914f938fdcb54f8ba25075ac40ddfaea|BN20190642|7.7.0.0|",
				"addressLine": "7430 Airlie Ct",
				"adminDistrict": "BC",
				"adminDistrict2": "Greater Vancouver",
				"countryRegion": "Canada",
				"formattedAddress": "7430 Airlie Ct, Burnaby, BC V5A 3R2, Canada",
				"locality": "Burnaby",
				"neighborhood": "Lochdale",
				"postalCode": "V5A 3R2"
			},
			"geometry": {
				"type": "Point",
				"coordinates": [
					-122.94699,
					49.27419
				]
			},
			"bbox": [
				-122.948713,
				49.2730658,
				-122.945267,
				49.2753142
			]
		}
	]
}
