{
	"type": "FeatureCollection",
	"features": [
		{
			"type": "Feature",
			"properties": {
				"confidence": 9,
				"authenticationResultCode": "ValidCredentials",
				"brandLogoUri": "http://dev.virtualearth.net/Branding/logo_powered_by.png",
				"copyright": "Copyright © 2017 Microsoft and its suppliers. All rights reserved. This API cannot be accessed and the content and any results may not be used, reproduced or transmitted in any manner without express written permission from Microsoft Corporation.",
				"entityType": "Address",
				"matchCodes": [
					"Good"
				],
				"name": "747 Don Mills Rd, North York, ON M3C 1T2, Canada",
				"statusCode": 200,
				"statusDescription": "OK",
				"traceId": "efeda0a7a51d4763ad65c82b81e44e8a|BN20250135|7.7.0.0|",
				"addressLine": "747 Don Mills Rd",
				"adminDistrict": "ON",
				"adminDistrict2": "Toronto",
				"countryRegion": "Canada",
				"formattedAddress": "747 Don Mills Rd, North York, ON M3C 1T2, Canada",
				"locality": "Toronto",
				"neighborhood": "Flemingdon Park",
				"postalCode": "M3C 1T2"
			},
			"geometry": {
				"type": "Point",
				"coordinates": [
					-79.33556,
					43.71355
				]
			},
			"bbox": [
				-79.3371153,
				43.7124258,
				-79.3340047,
				43.7146742
			]
		}
	]
}
