{
	"type": "FeatureCollection",
	"features": [
		{
			"type": "Feature",
			"properties": {
				"confidence": 9,
				"authenticationResultCode": "ValidCredentials",
				"brandLogoUri": "http://dev.virtualearth.net/Branding/logo_powered_by.png",
				"copyright": "Copyright © 2017 Microsoft and its suppliers. All rights reserved. This API cannot be accessed and the content and any results may not be used, reproduced or transmitted in any manner without express written permission from Microsoft Corporation.",
				"entityType": "Address",
				"matchCodes": [
					"Good"
				],
				"name": "748 Guelph Line, Burlington, ON L7R 3N5, Canada",
				"statusCode": 200,
				"statusDescription": "OK",
				"traceId": "b5d8a75749be48c69f5c372c0dbc490a|BN20260231|7.7.0.0|",
				"addressLine": "748 Guelph Line",
				"adminDistrict": "ON",
				"adminDistrict2": "Halton",
				"countryRegion": "Canada",
				"formattedAddress": "748 Guelph Line, Burlington, ON L7R 3N5, Canada",
				"locality": "Burlington",
				"neighborhood": "Central",
				"postalCode": "L7R 3N5"
			},
			"geometry": {
				"type": "Point",
				"coordinates": [
					-79.79572,
					43.34539
				]
			},
			"bbox": [
				-79.7972658,
				43.3442658,
				-79.7941742,
				43.3465142
			]
		}
	]
}
