{
	"type": "FeatureCollection",
	"features": [
		{
			"type": "Feature",
			"properties": {
				"confidence": 9,
				"authenticationResultCode": "ValidCredentials",
				"brandLogoUri": "http://dev.virtualearth.net/Branding/logo_powered_by.png",
				"copyright": "Copyright © 2017 Microsoft and its suppliers. All rights reserved. This API cannot be accessed and the content and any results may not be used, reproduced or transmitted in any manner without express written permission from Microsoft Corporation.",
				"entityType": "Address",
				"matchCodes": [
					"Good"
				],
				"name": "7491 Pacific Cir, Mississauga, ON L5T 2A4, Canada",
				"statusCode": 200,
				"statusDescription": "OK",
				"traceId": "f52e1b29adb14e57b9221e6e8eccd2bf|BN20220145|7.7.0.0|",
				"addressLine": "7491 Pacific Cir",
				"adminDistrict": "ON",
				"adminDistrict2": "Peel",
				"countryRegion": "Canada",
				"formattedAddress": "7491 Pacific Cir, Mississauga, ON L5T 2A4, Canada",
				"locality": "Mississauga",
				"postalCode": "L5T 2A4"
			},
			"geometry": {
				"type": "Point",
				"coordinates": [
					-79.67335,
					43.65639
				]
			},
			"bbox": [
				-79.6749038,
				43.6552658,
				-79.6717962,
				43.6575142
			]
		}
	]
}
