{
	"type": "FeatureCollection",
	"features": [
		{
			"type": "Feature",
			"properties": {
				"confidence": 9,
				"authenticationResultCode": "ValidCredentials",
				"brandLogoUri": "http://dev.virtualearth.net/Branding/logo_powered_by.png",
				"copyright": "Copyright © 2017 Microsoft and its suppliers. All rights reserved. This API cannot be accessed and the content and any results may not be used, reproduced or transmitted in any manner without express written permission from Microsoft Corporation.",
				"entityType": "Address",
				"matchCodes": [
					"Good"
				],
				"name": "7492 May Cmn NW, Edmonton, AB T6R 0G9, Canada",
				"statusCode": 200,
				"statusDescription": "OK",
				"traceId": "78ca4b4eb2d14adabfdc1f99717d6733|BN20200239|7.7.0.0|",
				"addressLine": "7492 May Cmn NW",
				"adminDistrict": "AB",
				"adminDistrict2": "Alberta",
				"countryRegion": "Canada",
				"formattedAddress": "7492 May Cmn NW, Edmonton, AB T6R 0G9, Canada",
				"locality": "Edmonton",
				"neighborhood": "Magrath Heights Area",
				"postalCode": "T6R 0G9"
			},
			"geometry": {
				"type": "Point",
				"coordinates": [
					-113.5521184,
					53.4486163
				]
			},
			"bbox": [
				-113.554006,
				53.4474922,
				-113.5502308,
				53.4497405
			]
		}
	]
}
