{
	"type": "FeatureCollection",
	"features": [
		{
			"type": "Feature",
			"properties": {
				"confidence": 9,
				"authenticationResultCode": "ValidCredentials",
				"brandLogoUri": "http://dev.virtualearth.net/Branding/logo_powered_by.png",
				"copyright": "Copyright © 2017 Microsoft and its suppliers. All rights reserved. This API cannot be accessed and the content and any results may not be used, reproduced or transmitted in any manner without express written permission from Microsoft Corporation.",
				"entityType": "Address",
				"matchCodes": [
					"Good"
				],
				"name": "75 Derry Rd W, Mississauga, ON L5W 1G3, Canada",
				"statusCode": 200,
				"statusDescription": "OK",
				"traceId": "5c364f7fbf6b444caa89529068457df9|BN20130632|7.7.0.0|",
				"addressLine": "75 Derry Rd W",
				"adminDistrict": "ON",
				"adminDistrict2": "Peel",
				"countryRegion": "Canada",
				"formattedAddress": "75 Derry Rd W, Mississauga, ON L5W 1G3, Canada",
				"locality": "Mississauga",
				"neighborhood": "Meadowvale Village",
				"postalCode": "L5W 1G3"
			},
			"geometry": {
				"type": "Point",
				"coordinates": [
					-79.7084608,
					43.6442101
				]
			},
			"bbox": [
				-79.7100143,
				43.6430859,
				-79.7069073,
				43.6453342
			]
		}
	]
}
