{
	"type": "FeatureCollection",
	"features": [
		{
			"type": "Feature",
			"properties": {
				"confidence": 9,
				"authenticationResultCode": "ValidCredentials",
				"brandLogoUri": "http://dev.virtualearth.net/Branding/logo_powered_by.png",
				"copyright": "Copyright © 2017 Microsoft and its suppliers. All rights reserved. This API cannot be accessed and the content and any results may not be used, reproduced or transmitted in any manner without express written permission from Microsoft Corporation.",
				"entityType": "Address",
				"matchCodes": [
					"Good"
				],
				"name": "75 1st St, Orangeville, ON L9W, Canada",
				"statusCode": 200,
				"statusDescription": "OK",
				"traceId": "14bd439529534373bb97e8c216b9172c|BN20121764|7.7.0.0|",
				"addressLine": "75 1st St",
				"adminDistrict": "ON",
				"adminDistrict2": "Dufferin",
				"countryRegion": "Canada",
				"formattedAddress": "75 1st St, Orangeville, ON L9W, Canada",
				"locality": "Orangeville",
				"postalCode": "L9W 5B6"
			},
			"geometry": {
				"type": "Point",
				"coordinates": [
					-80.09882,
					43.92702
				]
			},
			"bbox": [
				-80.1003808,
				43.9258958,
				-80.0972592,
				43.9281442
			]
		}
	]
}
