{
	"type": "FeatureCollection",
	"features": [
		{
			"type": "Feature",
			"properties": {
				"confidence": 9,
				"authenticationResultCode": "ValidCredentials",
				"brandLogoUri": "http://dev.virtualearth.net/Branding/logo_powered_by.png",
				"copyright": "Copyright © 2017 Microsoft and its suppliers. All rights reserved. This API cannot be accessed and the content and any results may not be used, reproduced or transmitted in any manner without express written permission from Microsoft Corporation.",
				"entityType": "Address",
				"matchCodes": [
					"Good"
				],
				"name": "75 Tudhope St, Parry Sound, ON P2A 0C6, Canada",
				"statusCode": 200,
				"statusDescription": "OK",
				"traceId": "e28882550f744816898ac1a85efd1f7f|BN20130431|7.7.0.0|",
				"addressLine": "75 Tudhope St",
				"adminDistrict": "ON",
				"adminDistrict2": "Parry Sound",
				"countryRegion": "Canada",
				"formattedAddress": "75 Tudhope St, Parry Sound, ON P2A 0C6, Canada",
				"locality": "Parry Sound",
				"postalCode": "P2A 0C6"
			},
			"geometry": {
				"type": "Point",
				"coordinates": [
					-80.0270512,
					45.3601802
				]
			},
			"bbox": [
				-80.0286511,
				45.3590561,
				-80.0254513,
				45.3613044
			]
		}
	]
}
