{
	"type": "FeatureCollection",
	"features": [
		{
			"type": "Feature",
			"properties": {
				"confidence": 9,
				"authenticationResultCode": "ValidCredentials",
				"brandLogoUri": "http://dev.virtualearth.net/Branding/logo_powered_by.png",
				"copyright": "Copyright © 2017 Microsoft and its suppliers. All rights reserved. This API cannot be accessed and the content and any results may not be used, reproduced or transmitted in any manner without express written permission from Microsoft Corporation.",
				"entityType": "Address",
				"matchCodes": [
					"Good"
				],
				"name": "750 Hespeler Rd, Cambridge, ON N3H 5L8, Canada",
				"statusCode": 200,
				"statusDescription": "OK",
				"traceId": "470c8bd5a21048ea902f93e3ca57cb57|BN20240253|7.7.0.0|",
				"addressLine": "750 Hespeler Rd",
				"adminDistrict": "ON",
				"adminDistrict2": "Waterloo",
				"countryRegion": "Canada",
				"formattedAddress": "750 Hespeler Rd, Cambridge, ON N3H 5L8, Canada",
				"locality": "Cambridge",
				"postalCode": "N3H 5L8"
			},
			"geometry": {
				"type": "Point",
				"coordinates": [
					-80.3287405,
					43.4096609
				]
			},
			"bbox": [
				-80.3302879,
				43.4085367,
				-80.327193,
				43.410785
			]
		}
	]
}
