{
	"type": "FeatureCollection",
	"features": [
		{
			"type": "Feature",
			"properties": {
				"confidence": 9,
				"authenticationResultCode": "ValidCredentials",
				"brandLogoUri": "http://dev.virtualearth.net/Branding/logo_powered_by.png",
				"copyright": "Copyright © 2017 Microsoft and its suppliers. All rights reserved. This API cannot be accessed and the content and any results may not be used, reproduced or transmitted in any manner without express written permission from Microsoft Corporation.",
				"entityType": "Address",
				"matchCodes": [
					"Good"
				],
				"name": "7509 72A St NW, Edmonton, AB T6B 1Z3, Canada",
				"statusCode": 200,
				"statusDescription": "OK",
				"traceId": "a45fc2dd76b94712b97a1d16fc13b293|BN20130532|7.7.0.0|",
				"addressLine": "7509 72A St NW",
				"adminDistrict": "AB",
				"adminDistrict2": "Alberta",
				"countryRegion": "Canada",
				"formattedAddress": "7509 72A St NW, Edmonton, AB T6B 1Z3, Canada",
				"locality": "Edmonton",
				"neighborhood": "Girard Industrial",
				"postalCode": "T6B 1Z3"
			},
			"geometry": {
				"type": "Point",
				"coordinates": [
					-113.43927,
					53.51119
				]
			},
			"bbox": [
				-113.4411604,
				53.5100658,
				-113.4373796,
				53.5123142
			]
		}
	]
}
