{
	"type": "FeatureCollection",
	"features": [
		{
			"type": "Feature",
			"properties": {
				"confidence": 9,
				"authenticationResultCode": "ValidCredentials",
				"brandLogoUri": "http://dev.virtualearth.net/Branding/logo_powered_by.png",
				"copyright": "Copyright © 2017 Microsoft and its suppliers. All rights reserved. This API cannot be accessed and the content and any results may not be used, reproduced or transmitted in any manner without express written permission from Microsoft Corporation.",
				"entityType": "Address",
				"matchCodes": [
					"Good"
				],
				"name": "756 Great Northern Way, Vancouver, BC V5T 1E4, Canada",
				"statusCode": 200,
				"statusDescription": "OK",
				"traceId": "e76d3d48de9044faa31549c48b411e72|BN20300154|7.7.0.0|",
				"addressLine": "756 Great Northern Way",
				"adminDistrict": "BC",
				"adminDistrict2": "Greater Vancouver",
				"countryRegion": "Canada",
				"formattedAddress": "756 Great Northern Way, Vancouver, BC V5T 1E4, Canada",
				"locality": "Vancouver",
				"neighborhood": "Mt Pleasant",
				"postalCode": "V5T 1E4"
			},
			"geometry": {
				"type": "Point",
				"coordinates": [
					-123.08824,
					49.26609
				]
			},
			"bbox": [
				-123.0899627,
				49.2649658,
				-123.0865173,
				49.2672142
			]
		}
	]
}
