{
	"type": "FeatureCollection",
	"features": [
		{
			"type": "Feature",
			"properties": {
				"confidence": 9,
				"authenticationResultCode": "ValidCredentials",
				"brandLogoUri": "http://dev.virtualearth.net/Branding/logo_powered_by.png",
				"copyright": "Copyright © 2017 Microsoft and its suppliers. All rights reserved. This API cannot be accessed and the content and any results may not be used, reproduced or transmitted in any manner without express written permission from Microsoft Corporation.",
				"entityType": "Address",
				"matchCodes": [
					"Good"
				],
				"name": "76 Davis St E, Norfolk, ON N3Y, Canada",
				"statusCode": 200,
				"statusDescription": "OK",
				"traceId": "c4ae053008db421ba8f169ca1f41f638|BN20250135|7.7.0.0|",
				"addressLine": "76 Davis St E",
				"adminDistrict": "ON",
				"adminDistrict2": "Norfolk",
				"countryRegion": "Canada",
				"formattedAddress": "76 Davis St E, Norfolk, ON N3Y, Canada",
				"locality": "Norfolk",
				"neighborhood": "Simcoe",
				"postalCode": "N3Y 5C3"
			},
			"geometry": {
				"type": "Point",
				"coordinates": [
					-80.3036763,
					42.8528844
				]
			},
			"bbox": [
				-80.3052097,
				42.8517602,
				-80.3021429,
				42.8540085
			]
		}
	]
}
