{
	"type": "FeatureCollection",
	"features": [
		{
			"type": "Feature",
			"properties": {
				"confidence": 9,
				"authenticationResultCode": "ValidCredentials",
				"brandLogoUri": "http://dev.virtualearth.net/Branding/logo_powered_by.png",
				"copyright": "Copyright © 2017 Microsoft and its suppliers. All rights reserved. This API cannot be accessed and the content and any results may not be used, reproduced or transmitted in any manner without express written permission from Microsoft Corporation.",
				"entityType": "Address",
				"matchCodes": [
					"Good"
				],
				"name": "76 Revillion Rd, Moosonee, ON P0L, Canada",
				"statusCode": 200,
				"statusDescription": "OK",
				"traceId": "94e00cdbd5344f3a917c3cfb43cb2b14|BN20130442|7.7.0.0|",
				"addressLine": "76 Revillion Rd",
				"adminDistrict": "ON",
				"adminDistrict2": "Cochrane",
				"countryRegion": "Canada",
				"formattedAddress": "76 Revillion Rd, Moosonee, ON P0L, Canada",
				"locality": "Moosonee",
				"postalCode": "P0L 1Y0"
			},
			"geometry": {
				"type": "Point",
				"coordinates": [
					-80.6325455,
					51.2768607
				]
			},
			"bbox": [
				-80.6343426,
				51.2757365,
				-80.6307485,
				51.2779848
			]
		}
	]
}
