{
	"type": "FeatureCollection",
	"features": [
		{
			"type": "Feature",
			"properties": {
				"confidence": 9,
				"authenticationResultCode": "ValidCredentials",
				"brandLogoUri": "http://dev.virtualearth.net/Branding/logo_powered_by.png",
				"copyright": "Copyright © 2017 Microsoft and its suppliers. All rights reserved. This API cannot be accessed and the content and any results may not be used, reproduced or transmitted in any manner without express written permission from Microsoft Corporation.",
				"entityType": "Address",
				"matchCodes": [
					"Good"
				],
				"name": "7625 104 St NW, Edmonton, AB T6E 4C3, Canada",
				"statusCode": 200,
				"statusDescription": "OK",
				"traceId": "c2442a8f2daa4f1cb5a7178f094219d4|BN20130423|7.7.0.0|",
				"addressLine": "7625 104 St NW",
				"adminDistrict": "AB",
				"adminDistrict2": "Alberta",
				"countryRegion": "Canada",
				"formattedAddress": "7625 104 St NW, Edmonton, AB T6E 4C3, Canada",
				"locality": "Edmonton",
				"neighborhood": "CPR West",
				"postalCode": "T6E 4C3"
			},
			"geometry": {
				"type": "Point",
				"coordinates": [
					-113.49717,
					53.51315
				]
			},
			"bbox": [
				-113.4990605,
				53.5120258,
				-113.4952795,
				53.5142742
			]
		}
	]
}
