{
	"type": "FeatureCollection",
	"features": [
		{
			"type": "Feature",
			"properties": {
				"confidence": 9,
				"authenticationResultCode": "ValidCredentials",
				"brandLogoUri": "http://dev.virtualearth.net/Branding/logo_powered_by.png",
				"copyright": "Copyright © 2017 Microsoft and its suppliers. All rights reserved. This API cannot be accessed and the content and any results may not be used, reproduced or transmitted in any manner without express written permission from Microsoft Corporation.",
				"entityType": "Address",
				"matchCodes": [
					"Good"
				],
				"name": "7680 Schaefer Ave, Richmond, BC V6Y 2W8, Canada",
				"statusCode": 200,
				"statusDescription": "OK",
				"traceId": "c782892618e34f07b30154d113aa39d1|BN20130533|7.7.0.0|",
				"addressLine": "7680 Schaefer Ave",
				"adminDistrict": "BC",
				"adminDistrict2": "Greater Vancouver",
				"countryRegion": "Canada",
				"formattedAddress": "7680 Schaefer Ave, Richmond, BC V6Y 2W8, Canada",
				"locality": "Richmond",
				"neighborhood": "Broadmoor",
				"postalCode": "V6Y 2W8"
			},
			"geometry": {
				"type": "Point",
				"coordinates": [
					-123.14111,
					49.14889
				]
			},
			"bbox": [
				-123.1428286,
				49.1477658,
				-123.1393914,
				49.1500142
			]
		}
	]
}
