{
	"type": "FeatureCollection",
	"features": [
		{
			"type": "Feature",
			"properties": {
				"confidence": 9,
				"authenticationResultCode": "ValidCredentials",
				"brandLogoUri": "http://dev.virtualearth.net/Branding/logo_powered_by.png",
				"copyright": "Copyright © 2017 Microsoft and its suppliers. All rights reserved. This API cannot be accessed and the content and any results may not be used, reproduced or transmitted in any manner without express written permission from Microsoft Corporation.",
				"entityType": "Address",
				"matchCodes": [
					"Good"
				],
				"name": "7695 Blackburn Pkwy, Niagara Falls, ON L2E, Canada",
				"statusCode": 200,
				"statusDescription": "OK",
				"traceId": "75d7b12117d94828bd5925b4219c733b|BN20130522|7.7.0.0|",
				"addressLine": "7695 Blackburn Pkwy",
				"adminDistrict": "ON",
				"adminDistrict2": "Niagara",
				"countryRegion": "Canada",
				"formattedAddress": "7695 Blackburn Pkwy, Niagara Falls, ON L2E, Canada",
				"locality": "Niagara Falls",
				"postalCode": "L2E"
			},
			"geometry": {
				"type": "Point",
				"coordinates": [
					-79.12527,
					43.05438
				]
			},
			"bbox": [
				-79.1268084,
				43.0532558,
				-79.1237316,
				43.0555042
			]
		}
	]
}
