{
	"type": "FeatureCollection",
	"features": [
		{
			"type": "Feature",
			"properties": {
				"confidence": 9,
				"authenticationResultCode": "ValidCredentials",
				"brandLogoUri": "http://dev.virtualearth.net/Branding/logo_powered_by.png",
				"copyright": "Copyright © 2017 Microsoft and its suppliers. All rights reserved. This API cannot be accessed and the content and any results may not be used, reproduced or transmitted in any manner without express written permission from Microsoft Corporation.",
				"entityType": "Address",
				"matchCodes": [
					"Good"
				],
				"name": "77 Frazee Ave, Dartmouth, NS B3B 1Z4, Canada",
				"statusCode": 200,
				"statusDescription": "OK",
				"traceId": "627d1d908f2d42f094b2448f1cf5f649|BN20300154|7.7.0.0|",
				"addressLine": "77 Frazee Ave",
				"adminDistrict": "NS",
				"adminDistrict2": "Halifax",
				"countryRegion": "Canada",
				"formattedAddress": "77 Frazee Ave, Dartmouth, NS B3B 1Z4, Canada",
				"locality": "Halifax",
				"neighborhood": "Dartmouth",
				"postalCode": "B3B 1Z4"
			},
			"geometry": {
				"type": "Point",
				"coordinates": [
					-63.58151,
					44.71484
				]
			},
			"bbox": [
				-63.5830919,
				44.7137158,
				-63.5799281,
				44.7159642
			]
		}
	]
}
