{
	"type": "FeatureCollection",
	"features": [
		{
			"type": "Feature",
			"properties": {
				"confidence": 9,
				"authenticationResultCode": "ValidCredentials",
				"brandLogoUri": "http://dev.virtualearth.net/Branding/logo_powered_by.png",
				"copyright": "Copyright © 2017 Microsoft and its suppliers. All rights reserved. This API cannot be accessed and the content and any results may not be used, reproduced or transmitted in any manner without express written permission from Microsoft Corporation.",
				"entityType": "Address",
				"matchCodes": [
					"Good"
				],
				"name": "770 Boulevard Guimond, Longueuil, QC J4G 1V6, Canada",
				"statusCode": 200,
				"statusDescription": "OK",
				"traceId": "76ff4b9bba934d6bb458d96f00c228cd|BN20121764|7.7.0.0|",
				"addressLine": "770 Boulevard Guimond",
				"adminDistrict": "QC",
				"adminDistrict2": "Longueuil",
				"countryRegion": "Canada",
				"formattedAddress": "770 Boulevard Guimond, Longueuil, QC J4G 1V6, Canada",
				"locality": "Longueuil",
				"postalCode": "J4G 1V6"
			},
			"geometry": {
				"type": "Point",
				"coordinates": [
					-73.46668,
					45.56488
				]
			},
			"bbox": [
				-73.4682857,
				45.5637558,
				-73.4650743,
				45.5660042
			]
		}
	]
}
