{
	"type": "FeatureCollection",
	"features": [
		{
			"type": "Feature",
			"properties": {
				"confidence": 9,
				"authenticationResultCode": "ValidCredentials",
				"brandLogoUri": "http://dev.virtualearth.net/Branding/logo_powered_by.png",
				"copyright": "Copyright © 2017 Microsoft and its suppliers. All rights reserved. This API cannot be accessed and the content and any results may not be used, reproduced or transmitted in any manner without express written permission from Microsoft Corporation.",
				"entityType": "Address",
				"matchCodes": [
					"Good"
				],
				"name": "7760 Rue Grenache, Anjou, QC H1J 1C3, Canada",
				"statusCode": 200,
				"statusDescription": "OK",
				"traceId": "8a9d73e0bba94102a1f46bf9c4954a38|BN20160335|7.7.0.0|",
				"addressLine": "7760 Rue Grenache",
				"adminDistrict": "QC",
				"adminDistrict2": "Montreal",
				"countryRegion": "Canada",
				"formattedAddress": "7760 Rue Grenache, Anjou, QC H1J 1C3, Canada",
				"locality": "Montreal",
				"neighborhood": "Anjou",
				"postalCode": "H1J 1C3"
			},
			"geometry": {
				"type": "Point",
				"coordinates": [
					-73.5730899,
					45.61066
				]
			},
			"bbox": [
				-73.5746969,
				45.6095358,
				-73.5714829,
				45.6117842
			]
		}
	]
}
