{
	"type": "FeatureCollection",
	"features": [
		{
			"type": "Feature",
			"properties": {
				"confidence": 9,
				"authenticationResultCode": "ValidCredentials",
				"brandLogoUri": "http://dev.virtualearth.net/Branding/logo_powered_by.png",
				"copyright": "Copyright © 2017 Microsoft and its suppliers. All rights reserved. This API cannot be accessed and the content and any results may not be used, reproduced or transmitted in any manner without express written permission from Microsoft Corporation.",
				"entityType": "Address",
				"matchCodes": [
					"Good"
				],
				"name": "777 Homer St, Vancouver, BC V6B 2W1, Canada",
				"statusCode": 200,
				"statusDescription": "OK",
				"traceId": "3297facf0f0e45fc87ca9316ebee37eb|BN20181720|7.7.0.0|",
				"addressLine": "777 Homer St",
				"adminDistrict": "BC",
				"adminDistrict2": "Greater Vancouver",
				"countryRegion": "Canada",
				"formattedAddress": "777 Homer St, Vancouver, BC V6B 2W1, Canada",
				"locality": "Vancouver",
				"neighborhood": "Downtown",
				"postalCode": "V6B 2W1"
			},
			"geometry": {
				"type": "Point",
				"coordinates": [
					-123.11641,
					49.28016
				]
			},
			"bbox": [
				-123.1181332,
				49.2790358,
				-123.1146868,
				49.2812842
			]
		}
	]
}
