{
	"type": "FeatureCollection",
	"features": [
		{
			"type": "Feature",
			"properties": {
				"confidence": 9,
				"authenticationResultCode": "ValidCredentials",
				"brandLogoUri": "http://dev.virtualearth.net/Branding/logo_powered_by.png",
				"copyright": "Copyright © 2017 Microsoft and its suppliers. All rights reserved. This API cannot be accessed and the content and any results may not be used, reproduced or transmitted in any manner without express written permission from Microsoft Corporation.",
				"entityType": "Address",
				"matchCodes": [
					"Good"
				],
				"name": "78 Bridge St, Sackville, NB E4L 3N9, Canada",
				"statusCode": 200,
				"statusDescription": "OK",
				"traceId": "93d0165f5f584964be3ed83b28da0ade|BN20130532|7.7.0.0|",
				"addressLine": "78 Bridge St",
				"adminDistrict": "NB",
				"adminDistrict2": "Westmorland",
				"countryRegion": "Canada",
				"formattedAddress": "78 Bridge St, Sackville, NB E4L 3N9, Canada",
				"locality": "Sackville",
				"postalCode": "E4L 3N9"
			},
			"geometry": {
				"type": "Point",
				"coordinates": [
					-64.35973,
					45.89716
				]
			},
			"bbox": [
				-64.3613453,
				45.8960358,
				-64.3581147,
				45.8982842
			]
		}
	]
}
