{
	"type": "FeatureCollection",
	"features": [
		{
			"type": "Feature",
			"properties": {
				"confidence": 9,
				"authenticationResultCode": "ValidCredentials",
				"brandLogoUri": "http://dev.virtualearth.net/Branding/logo_powered_by.png",
				"copyright": "Copyright © 2017 Microsoft and its suppliers. All rights reserved. This API cannot be accessed and the content and any results may not be used, reproduced or transmitted in any manner without express written permission from Microsoft Corporation.",
				"entityType": "Address",
				"matchCodes": [
					"Good"
				],
				"name": "7830 McHugh St, Windsor, ON N8S 2B8, Canada",
				"statusCode": 200,
				"statusDescription": "OK",
				"traceId": "4aa1502c6dfa491d866eb3fbab24bb7e|BN20130447|7.7.0.0|",
				"addressLine": "7830 McHugh St",
				"adminDistrict": "ON",
				"adminDistrict2": "Essex",
				"countryRegion": "Canada",
				"formattedAddress": "7830 McHugh St, Windsor, ON N8S 2B8, Canada",
				"locality": "Windsor",
				"neighborhood": "Riverside",
				"postalCode": "N8S 2B8"
			},
			"geometry": {
				"type": "Point",
				"coordinates": [
					-82.93755,
					42.32065
				]
			},
			"bbox": [
				-82.9390704,
				42.3195258,
				-82.9360296,
				42.3217742
			]
		}
	]
}
