{
	"type": "FeatureCollection",
	"features": [
		{
			"type": "Feature",
			"properties": {
				"confidence": 9,
				"authenticationResultCode": "ValidCredentials",
				"brandLogoUri": "http://dev.virtualearth.net/Branding/logo_powered_by.png",
				"copyright": "Copyright © 2017 Microsoft and its suppliers. All rights reserved. This API cannot be accessed and the content and any results may not be used, reproduced or transmitted in any manner without express written permission from Microsoft Corporation.",
				"entityType": "Address",
				"matchCodes": [
					"Good"
				],
				"name": "788 St Clair St, Chatham, ON N7L 0E8, Canada",
				"statusCode": 200,
				"statusDescription": "OK",
				"traceId": "4c0a712d7cff4ee2ac2db0b15e8c6c30|BN20130532|7.7.0.0|",
				"addressLine": "788 St Clair St",
				"adminDistrict": "ON",
				"adminDistrict2": "Chatham-Kent",
				"countryRegion": "Canada",
				"formattedAddress": "788 St Clair St, Chatham, ON N7L 0E8, Canada",
				"locality": "Chatham-Kent",
				"neighborhood": "Chatham",
				"postalCode": "N7L 0E8"
			},
			"geometry": {
				"type": "Point",
				"coordinates": [
					-82.22302,
					42.43053
				]
			},
			"bbox": [
				-82.224543,
				42.4294058,
				-82.221497,
				42.4316542
			]
		}
	]
}
