{
	"type": "FeatureCollection",
	"features": [
		{
			"type": "Feature",
			"properties": {
				"confidence": 9,
				"authenticationResultCode": "ValidCredentials",
				"brandLogoUri": "http://dev.virtualearth.net/Branding/logo_powered_by.png",
				"copyright": "Copyright © 2017 Microsoft and its suppliers. All rights reserved. This API cannot be accessed and the content and any results may not be used, reproduced or transmitted in any manner without express written permission from Microsoft Corporation.",
				"entityType": "Address",
				"matchCodes": [
					"Good"
				],
				"name": "790 Rue Murdock, Chicoutimi, QC G7H 3Z4, Canada",
				"statusCode": 200,
				"statusDescription": "OK",
				"traceId": "3a2066f7ea584bdeabf98d31bc0d3826|BN20130632|7.7.0.0|",
				"addressLine": "790 Rue Murdock",
				"adminDistrict": "QC",
				"adminDistrict2": "Saguenay",
				"countryRegion": "Canada",
				"formattedAddress": "790 Rue Murdock, Chicoutimi, QC G7H 3Z4, Canada",
				"locality": "Saguenay",
				"neighborhood": "Chicoutimi",
				"postalCode": "G7H 3Z4"
			},
			"geometry": {
				"type": "Point",
				"coordinates": [
					-71.045,
					48.4162899
				]
			},
			"bbox": [
				-71.0466937,
				48.4151657,
				-71.0433063,
				48.4174141
			]
		}
	]
}
