{
	"type": "FeatureCollection",
	"features": [
		{
			"type": "Feature",
			"properties": {
				"confidence": 9,
				"authenticationResultCode": "ValidCredentials",
				"brandLogoUri": "http://dev.virtualearth.net/Branding/logo_powered_by.png",
				"copyright": "Copyright © 2017 Microsoft and its suppliers. All rights reserved. This API cannot be accessed and the content and any results may not be used, reproduced or transmitted in any manner without express written permission from Microsoft Corporation.",
				"entityType": "Address",
				"matchCodes": [
					"Good"
				],
				"name": "7911 128 St, Surrey, BC V3W 4E7, Canada",
				"statusCode": 200,
				"statusDescription": "OK",
				"traceId": "d8288610441f4e639a5756ba2cc9fa76|BN20171457|7.7.0.0|",
				"addressLine": "7911 128 St",
				"adminDistrict": "BC",
				"adminDistrict2": "Greater Vancouver",
				"countryRegion": "Canada",
				"formattedAddress": "7911 128 St, Surrey, BC V3W 4E7, Canada",
				"locality": "Surrey",
				"neighborhood": "Newton",
				"postalCode": "V3W 4E7"
			},
			"geometry": {
				"type": "Point",
				"coordinates": [
					-122.86823,
					49.1466
				]
			},
			"bbox": [
				-122.8699486,
				49.1454758,
				-122.8665114,
				49.1477242
			]
		}
	]
}
