{
	"type": "FeatureCollection",
	"features": [
		{
			"type": "Feature",
			"properties": {
				"confidence": 9,
				"authenticationResultCode": "ValidCredentials",
				"brandLogoUri": "http://dev.virtualearth.net/Branding/logo_powered_by.png",
				"copyright": "Copyright © 2017 Microsoft and its suppliers. All rights reserved. This API cannot be accessed and the content and any results may not be used, reproduced or transmitted in any manner without express written permission from Microsoft Corporation.",
				"entityType": "Address",
				"matchCodes": [
					"Good"
				],
				"name": "7925 Goreway Dr, Brampton, ON L6T 5J7, Canada",
				"statusCode": 200,
				"statusDescription": "OK",
				"traceId": "d957540cb2cf4b969b29de8b4f8becdd|BN20130422|7.7.0.0|",
				"addressLine": "7925 Goreway Dr",
				"adminDistrict": "ON",
				"adminDistrict2": "Peel",
				"countryRegion": "Canada",
				"formattedAddress": "7925 Goreway Dr, Brampton, ON L6T 5J7, Canada",
				"locality": "Brampton",
				"neighborhood": "Malton",
				"postalCode": "L6T 5J7"
			},
			"geometry": {
				"type": "Point",
				"coordinates": [
					-79.6551999,
					43.73246
				]
			},
			"bbox": [
				-79.6567557,
				43.7313358,
				-79.6536441,
				43.7335842
			]
		}
	]
}
