{
	"type": "FeatureCollection",
	"features": [
		{
			"type": "Feature",
			"properties": {
				"confidence": 9,
				"authenticationResultCode": "ValidCredentials",
				"brandLogoUri": "http://dev.virtualearth.net/Branding/logo_powered_by.png",
				"copyright": "Copyright © 2017 Microsoft and its suppliers. All rights reserved. This API cannot be accessed and the content and any results may not be used, reproduced or transmitted in any manner without express written permission from Microsoft Corporation.",
				"entityType": "Address",
				"matchCodes": [
					"Good"
				],
				"name": "796 Fletcher Cir, Kanata, ON K2T 0B6, Canada",
				"statusCode": 200,
				"statusDescription": "OK",
				"traceId": "4589f671ffb04810b8f70dc512412718|BN20130625|7.7.0.0|",
				"addressLine": "796 Fletcher Cir",
				"adminDistrict": "ON",
				"adminDistrict2": "Ottawa",
				"countryRegion": "Canada",
				"formattedAddress": "796 Fletcher Cir, Kanata, ON K2T 0B6, Canada",
				"locality": "Ottawa",
				"neighborhood": "Kanata",
				"postalCode": "K2T 0B6"
			},
			"geometry": {
				"type": "Point",
				"coordinates": [
					-75.9308,
					45.31846
				]
			},
			"bbox": [
				-75.9323987,
				45.3173358,
				-75.9292013,
				45.3195842
			]
		}
	]
}
