{
	"type": "FeatureCollection",
	"features": [
		{
			"type": "Feature",
			"properties": {
				"confidence": 9,
				"authenticationResultCode": "ValidCredentials",
				"brandLogoUri": "http://dev.virtualearth.net/Branding/logo_powered_by.png",
				"copyright": "Copyright © 2017 Microsoft and its suppliers. All rights reserved. This API cannot be accessed and the content and any results may not be used, reproduced or transmitted in any manner without express written permission from Microsoft Corporation.",
				"entityType": "Address",
				"matchCodes": [
					"Good"
				],
				"name": "7965 Heritage Rd, Brampton, ON L6Y 5X5, Canada",
				"statusCode": 200,
				"statusDescription": "OK",
				"traceId": "1bd71cc170dd4c63b8a0025cb27f0df6|BN20130423|7.7.0.0|",
				"addressLine": "7965 Heritage Rd",
				"adminDistrict": "ON",
				"adminDistrict2": "Peel",
				"countryRegion": "Canada",
				"formattedAddress": "7965 Heritage Rd, Brampton, ON L6Y 5X5, Canada",
				"locality": "Brampton",
				"postalCode": "L6Y 5X5"
			},
			"geometry": {
				"type": "Point",
				"coordinates": [
					-79.78369,
					43.6164599
				]
			},
			"bbox": [
				-79.7852428,
				43.6153357,
				-79.7821372,
				43.6175841
			]
		}
	]
}
