{
	"type": "FeatureCollection",
	"features": [
		{
			"type": "Feature",
			"properties": {
				"confidence": 9,
				"authenticationResultCode": "ValidCredentials",
				"brandLogoUri": "http://dev.virtualearth.net/Branding/logo_powered_by.png",
				"copyright": "Copyright © 2017 Microsoft and its suppliers. All rights reserved. This API cannot be accessed and the content and any results may not be used, reproduced or transmitted in any manner without express written permission from Microsoft Corporation.",
				"entityType": "Address",
				"matchCodes": [
					"Good"
				],
				"name": "7979 82 St, Delta, BC V4G 1L7, Canada",
				"statusCode": 200,
				"statusDescription": "OK",
				"traceId": "ed1fba5482b240ad94c83e01eecfb05f|BN20130625|7.7.0.0|",
				"addressLine": "7979 82 St",
				"adminDistrict": "BC",
				"adminDistrict2": "Greater Vancouver",
				"countryRegion": "Canada",
				"formattedAddress": "7979 82 St, Delta, BC V4G 1L7, Canada",
				"locality": "Delta",
				"postalCode": "V4G 1L7"
			},
			"geometry": {
				"type": "Point",
				"coordinates": [
					-122.99817,
					49.14702
				]
			},
			"bbox": [
				-122.9998886,
				49.1458958,
				-122.9964514,
				49.1481442
			]
		}
	]
}
