{
	"type": "FeatureCollection",
	"features": [
		{
			"type": "Feature",
			"properties": {
				"confidence": 9,
				"authenticationResultCode": "ValidCredentials",
				"brandLogoUri": "http://dev.virtualearth.net/Branding/logo_powered_by.png",
				"copyright": "Copyright © 2017 Microsoft and its suppliers. All rights reserved. This API cannot be accessed and the content and any results may not be used, reproduced or transmitted in any manner without express written permission from Microsoft Corporation.",
				"entityType": "Address",
				"matchCodes": [
					"Good"
				],
				"name": "798 Hammonds Plains Rd, Bedford, NS B4B 1B1, Canada",
				"statusCode": 200,
				"statusDescription": "OK",
				"traceId": "ba3bab834b264c63949f563297a55214|BN20130625|7.7.0.0|",
				"addressLine": "798 Hammonds Plains Rd",
				"adminDistrict": "NS",
				"adminDistrict2": "Halifax",
				"countryRegion": "Canada",
				"formattedAddress": "798 Hammonds Plains Rd, Bedford, NS B4B 1B1, Canada",
				"locality": "Halifax",
				"neighborhood": "Bedford",
				"postalCode": "B4B 1B1"
			},
			"geometry": {
				"type": "Point",
				"coordinates": [
					-63.71748,
					44.72519
				]
			},
			"bbox": [
				-63.7190622,
				44.7240658,
				-63.7158978,
				44.7263142
			]
		}
	]
}
