{
	"type": "FeatureCollection",
	"features": [
		{
			"type": "Feature",
			"properties": {
				"confidence": 9,
				"authenticationResultCode": "ValidCredentials",
				"brandLogoUri": "http://dev.virtualearth.net/Branding/logo_powered_by.png",
				"copyright": "Copyright © 2017 Microsoft and its suppliers. All rights reserved. This API cannot be accessed and the content and any results may not be used, reproduced or transmitted in any manner without express written permission from Microsoft Corporation.",
				"entityType": "Address",
				"matchCodes": [
					"Good"
				],
				"name": "798 Hargrove Trl, Peterborough, ON K9L, Canada",
				"statusCode": 200,
				"statusDescription": "OK",
				"traceId": "28b38775618d4728bc3fd8504d4c0d52|BN20130422|7.7.0.0|",
				"addressLine": "798 Hargrove Trl",
				"adminDistrict": "ON",
				"adminDistrict2": "Peterborough",
				"countryRegion": "Canada",
				"formattedAddress": "798 Hargrove Trl, Peterborough, ON K9L, Canada",
				"locality": "Peterborough",
				"postalCode": "K9L 0B6"
			},
			"geometry": {
				"type": "Point",
				"coordinates": [
					-78.2898316,
					44.3034134
				]
			},
			"bbox": [
				-78.2914024,
				44.3022893,
				-78.2882608,
				44.3045376
			]
		}
	]
}
