{
	"type": "FeatureCollection",
	"features": [
		{
			"type": "Feature",
			"properties": {
				"confidence": 9,
				"authenticationResultCode": "ValidCredentials",
				"brandLogoUri": "http://dev.virtualearth.net/Branding/logo_powered_by.png",
				"copyright": "Copyright © 2017 Microsoft and its suppliers. All rights reserved. This API cannot be accessed and the content and any results may not be used, reproduced or transmitted in any manner without express written permission from Microsoft Corporation.",
				"entityType": "Address",
				"matchCodes": [
					"Good"
				],
				"name": "8 Cornwall Rd, Brampton, ON L6W 1M9, Canada",
				"statusCode": 200,
				"statusDescription": "OK",
				"traceId": "7fea1390e0864294aa4099b6e90660e7|BN20320521|7.7.0.0|",
				"addressLine": "8 Cornwall Rd",
				"adminDistrict": "ON",
				"adminDistrict2": "Peel",
				"countryRegion": "Canada",
				"formattedAddress": "8 Cornwall Rd, Brampton, ON L6W 1M9, Canada",
				"locality": "Brampton",
				"neighborhood": "Downtown Brampton",
				"postalCode": "L6W 1M9"
			},
			"geometry": {
				"type": "Point",
				"coordinates": [
					-79.74262,
					43.68792
				]
			},
			"bbox": [
				-79.7441746,
				43.6867958,
				-79.7410654,
				43.6890442
			]
		}
	]
}
