{
	"type": "FeatureCollection",
	"features": [
		{
			"type": "Feature",
			"properties": {
				"confidence": 9,
				"authenticationResultCode": "ValidCredentials",
				"brandLogoUri": "http://dev.virtualearth.net/Branding/logo_powered_by.png",
				"copyright": "Copyright © 2017 Microsoft and its suppliers. All rights reserved. This API cannot be accessed and the content and any results may not be used, reproduced or transmitted in any manner without express written permission from Microsoft Corporation.",
				"entityType": "Address",
				"matchCodes": [
					"Good"
				],
				"name": "80 Ilsley Ave, Dartmouth, NS B3B 1L3, Canada",
				"statusCode": 200,
				"statusDescription": "OK",
				"traceId": "f8006a56a6bc4537b6c69a2588da6090|BN20131519|7.7.0.0|",
				"addressLine": "80 Ilsley Ave",
				"adminDistrict": "NS",
				"adminDistrict2": "Halifax",
				"countryRegion": "Canada",
				"formattedAddress": "80 Ilsley Ave, Dartmouth, NS B3B 1L3, Canada",
				"locality": "Halifax",
				"neighborhood": "Dartmouth",
				"postalCode": "B3B 1L3"
			},
			"geometry": {
				"type": "Point",
				"coordinates": [
					-63.58848,
					44.70035
				]
			},
			"bbox": [
				-63.5900615,
				44.6992258,
				-63.5868985,
				44.7014742
			]
		}
	]
}
