{
	"type": "FeatureCollection",
	"features": [
		{
			"type": "Feature",
			"properties": {
				"confidence": 9,
				"authenticationResultCode": "ValidCredentials",
				"brandLogoUri": "http://dev.virtualearth.net/Branding/logo_powered_by.png",
				"copyright": "Copyright © 2017 Microsoft and its suppliers. All rights reserved. This API cannot be accessed and the content and any results may not be used, reproduced or transmitted in any manner without express written permission from Microsoft Corporation.",
				"entityType": "Address",
				"matchCodes": [
					"Good"
				],
				"name": "80 King St, St Catharines, ON L2R 7G1, Canada",
				"statusCode": 200,
				"statusDescription": "OK",
				"traceId": "e43273ab0d1f497e8288e8b334b8696f|BN20290118|7.7.0.0|",
				"addressLine": "80 King St",
				"adminDistrict": "ON",
				"adminDistrict2": "Niagara",
				"countryRegion": "Canada",
				"formattedAddress": "80 King St, St Catharines, ON L2R 7G1, Canada",
				"locality": "St Catharines",
				"neighborhood": "Downtown",
				"postalCode": "L2R 7G1"
			},
			"geometry": {
				"type": "Point",
				"coordinates": [
					-79.246,
					43.15804
				]
			},
			"bbox": [
				-79.2475411,
				43.1569158,
				-79.2444589,
				43.1591642
			]
		}
	]
}
