{
	"type": "FeatureCollection",
	"features": [
		{
			"type": "Feature",
			"properties": {
				"confidence": 9,
				"authenticationResultCode": "ValidCredentials",
				"brandLogoUri": "http://dev.virtualearth.net/Branding/logo_powered_by.png",
				"copyright": "Copyright © 2017 Microsoft and its suppliers. All rights reserved. This API cannot be accessed and the content and any results may not be used, reproduced or transmitted in any manner without express written permission from Microsoft Corporation.",
				"entityType": "Address",
				"matchCodes": [
					"Good"
				],
				"name": "8017 Chemainus Rd, Chemainus, BC V0R 1K5, Canada",
				"statusCode": 200,
				"statusDescription": "OK",
				"traceId": "5d7cee60f4ee4c3aaf3a7b413c92b9e6|BN20130533|7.7.0.0|",
				"addressLine": "8017 Chemainus Rd",
				"adminDistrict": "BC",
				"adminDistrict2": "Cowichan Valley",
				"countryRegion": "Canada",
				"formattedAddress": "8017 Chemainus Rd, Chemainus, BC V0R 1K5, Canada",
				"locality": "North Cowichan",
				"neighborhood": "Chemainus",
				"postalCode": "V0R 1K5"
			},
			"geometry": {
				"type": "Point",
				"coordinates": [
					-123.6948569,
					48.8762758
				]
			},
			"bbox": [
				-123.6965661,
				48.8751517,
				-123.6931476,
				48.8774
			]
		}
	]
}
