{
	"type": "FeatureCollection",
	"features": [
		{
			"type": "Feature",
			"properties": {
				"confidence": 9,
				"authenticationResultCode": "ValidCredentials",
				"brandLogoUri": "http://dev.virtualearth.net/Branding/logo_powered_by.png",
				"copyright": "Copyright © 2017 Microsoft and its suppliers. All rights reserved. This API cannot be accessed and the content and any results may not be used, reproduced or transmitted in any manner without express written permission from Microsoft Corporation.",
				"entityType": "Address",
				"matchCodes": [
					"Good"
				],
				"name": "8028 Torbram Rd, Brampton, ON L6T 3T2, Canada",
				"statusCode": 200,
				"statusDescription": "OK",
				"traceId": "c33b61b949494edbbafcfcf8ee33066d|BN20130632|7.7.0.0|",
				"addressLine": "8028 Torbram Rd",
				"adminDistrict": "ON",
				"adminDistrict2": "Peel",
				"countryRegion": "Canada",
				"formattedAddress": "8028 Torbram Rd, Brampton, ON L6T 3T2, Canada",
				"locality": "Brampton",
				"neighborhood": "Bramalea",
				"postalCode": "L6T 3T2"
			},
			"geometry": {
				"type": "Point",
				"coordinates": [
					-79.6803716,
					43.7146648
				]
			},
			"bbox": [
				-79.6819269,
				43.7135407,
				-79.6788163,
				43.715789
			]
		}
	]
}
