{
	"type": "FeatureCollection",
	"features": [
		{
			"type": "Feature",
			"properties": {
				"confidence": 9,
				"authenticationResultCode": "ValidCredentials",
				"brandLogoUri": "http://dev.virtualearth.net/Branding/logo_powered_by.png",
				"copyright": "Copyright © 2017 Microsoft and its suppliers. All rights reserved. This API cannot be accessed and the content and any results may not be used, reproduced or transmitted in any manner without express written permission from Microsoft Corporation.",
				"entityType": "Address",
				"matchCodes": [
					"Good"
				],
				"name": "803 Erin St, Winnipeg, MB R3G 2W2, Canada",
				"statusCode": 200,
				"statusDescription": "OK",
				"traceId": "608049f5df4e4882a2136a05cff49fe2|BN20130625|7.7.0.0|",
				"addressLine": "803 Erin St",
				"adminDistrict": "MB",
				"adminDistrict2": "Manitoba",
				"countryRegion": "Canada",
				"formattedAddress": "803 Erin St, Winnipeg, MB R3G 2W2, Canada",
				"locality": "Winnipeg",
				"neighborhood": "Minto",
				"postalCode": "R3G 2W2"
			},
			"geometry": {
				"type": "Point",
				"coordinates": [
					-97.18438,
					49.88961
				]
			},
			"bbox": [
				-97.1861249,
				49.8884858,
				-97.1826351,
				49.8907342
			]
		}
	]
}
