{
	"type": "FeatureCollection",
	"features": [
		{
			"type": "Feature",
			"properties": {
				"confidence": 7,
				"authenticationResultCode": "ValidCredentials",
				"brandLogoUri": "http://dev.virtualearth.net/Branding/logo_powered_by.png",
				"copyright": "Copyright © 2017 Microsoft and its suppliers. All rights reserved. This API cannot be accessed and the content and any results may not be used, reproduced or transmitted in any manner without express written permission from Microsoft Corporation.",
				"entityType": "RoadBlock",
				"matchCodes": [
					"UpHierarchy"
				],
				"name": "Main St, Biggar, SK S0K 0M0, Canada",
				"statusCode": 200,
				"statusDescription": "OK",
				"traceId": "4046a4129bbf4d1090050bb5a18d64f9|BN20130520|7.7.0.0|",
				"addressLine": "Main St",
				"adminDistrict": "SK",
				"adminDistrict2": "Saskatchewan",
				"countryRegion": "Canada",
				"formattedAddress": "Main St, Biggar, SK S0K 0M0, Canada",
				"locality": "Biggar",
				"postalCode": "S0K 0M0"
			},
			"geometry": {
				"type": "Point",
				"coordinates": [
					-107.9863,
					52.05424
				]
			},
			"bbox": [
				-107.9865,
				52.05394,
				-107.98021,
				52.0624899
			]
		}
	]
}
