{
	"type": "FeatureCollection",
	"features": [
		{
			"type": "Feature",
			"properties": {
				"confidence": 9,
				"authenticationResultCode": "ValidCredentials",
				"brandLogoUri": "http://dev.virtualearth.net/Branding/logo_powered_by.png",
				"copyright": "Copyright © 2017 Microsoft and its suppliers. All rights reserved. This API cannot be accessed and the content and any results may not be used, reproduced or transmitted in any manner without express written permission from Microsoft Corporation.",
				"entityType": "Address",
				"matchCodes": [
					"Good"
				],
				"name": "8053 Yonge St, Thornhill, ON L3T 2C5, Canada",
				"statusCode": 200,
				"statusDescription": "OK",
				"traceId": "6484374b50714ebb93f9e0d948c96bb7|BN20190653|7.7.0.0|",
				"addressLine": "8053 Yonge St",
				"adminDistrict": "ON",
				"adminDistrict2": "York",
				"countryRegion": "Canada",
				"formattedAddress": "8053 Yonge St, Thornhill, ON L3T 2C5, Canada",
				"locality": "Markham",
				"neighborhood": "Thornhill",
				"postalCode": "L3T 2C5"
			},
			"geometry": {
				"type": "Point",
				"coordinates": [
					-79.42567,
					43.82195
				]
			},
			"bbox": [
				-79.4272281,
				43.8208258,
				-79.4241119,
				43.8230742
			]
		}
	]
}
