{
	"type": "FeatureCollection",
	"features": [
		{
			"type": "Feature",
			"properties": {
				"confidence": 9,
				"authenticationResultCode": "ValidCredentials",
				"brandLogoUri": "http://dev.virtualearth.net/Branding/logo_powered_by.png",
				"copyright": "Copyright © 2017 Microsoft and its suppliers. All rights reserved. This API cannot be accessed and the content and any results may not be used, reproduced or transmitted in any manner without express written permission from Microsoft Corporation.",
				"entityType": "Address",
				"matchCodes": [
					"Good"
				],
				"name": "806 Primrose Ct, Pickering, ON L1X 2S8, Canada",
				"statusCode": 200,
				"statusDescription": "OK",
				"traceId": "ead531fbe49d4929bf9a1a9818c57ec0|BN20130522|7.7.0.0|",
				"addressLine": "806 Primrose Ct",
				"adminDistrict": "ON",
				"adminDistrict2": "Durham",
				"countryRegion": "Canada",
				"formattedAddress": "806 Primrose Ct, Pickering, ON L1X 2S8, Canada",
				"locality": "Pickering",
				"postalCode": "L1X 2S8"
			},
			"geometry": {
				"type": "Point",
				"coordinates": [
					-79.11739,
					43.84513
				]
			},
			"bbox": [
				-79.1189487,
				43.8440058,
				-79.1158313,
				43.8462542
			]
		}
	]
}
