{
	"type": "FeatureCollection",
	"features": [
		{
			"type": "Feature",
			"properties": {
				"confidence": 9,
				"authenticationResultCode": "ValidCredentials",
				"brandLogoUri": "http://dev.virtualearth.net/Branding/logo_powered_by.png",
				"copyright": "Copyright © 2017 Microsoft and its suppliers. All rights reserved. This API cannot be accessed and the content and any results may not be used, reproduced or transmitted in any manner without express written permission from Microsoft Corporation.",
				"entityType": "Address",
				"matchCodes": [
					"Good"
				],
				"name": "8073 Timber Ln, Whistler, BC V0N 1B8, Canada",
				"statusCode": 200,
				"statusDescription": "OK",
				"traceId": "e75b579ad5824d33909e4df31d3860be|BN20130634|7.7.0.0|",
				"addressLine": "8073 Timber Ln",
				"adminDistrict": "BC",
				"adminDistrict2": "Squamish-Lillooet",
				"countryRegion": "Canada",
				"formattedAddress": "8073 Timber Ln, Whistler, BC V0N 1B8, Canada",
				"locality": "Whistler",
				"postalCode": "V0N 1B8"
			},
			"geometry": {
				"type": "Point",
				"coordinates": [
					-122.96152,
					50.1458299
				]
			},
			"bbox": [
				-122.9632742,
				50.1447057,
				-122.9597658,
				50.1469541
			]
		}
	]
}
