{
	"type": "FeatureCollection",
	"features": [
		{
			"type": "Feature",
			"properties": {
				"confidence": 9,
				"authenticationResultCode": "ValidCredentials",
				"brandLogoUri": "http://dev.virtualearth.net/Branding/logo_powered_by.png",
				"copyright": "Copyright © 2017 Microsoft and its suppliers. All rights reserved. This API cannot be accessed and the content and any results may not be used, reproduced or transmitted in any manner without express written permission from Microsoft Corporation.",
				"entityType": "Address",
				"matchCodes": [
					"Good"
				],
				"name": "81 Doyle St, Bedford, NS B4A 2Y3, Canada",
				"statusCode": 200,
				"statusDescription": "OK",
				"traceId": "46dd7f4582944f4bb31ff001f1ca2852|BN20130423|7.7.0.0|",
				"addressLine": "81 Doyle St",
				"adminDistrict": "NS",
				"adminDistrict2": "Halifax",
				"countryRegion": "Canada",
				"formattedAddress": "81 Doyle St, Bedford, NS B4A 2Y3, Canada",
				"locality": "Halifax",
				"neighborhood": "Bedford",
				"postalCode": "B4A 2Y3"
			},
			"geometry": {
				"type": "Point",
				"coordinates": [
					-63.67822,
					44.71834
				]
			},
			"bbox": [
				-63.679802,
				44.7172158,
				-63.676638,
				44.7194642
			]
		}
	]
}
