{
	"type": "FeatureCollection",
	"features": [
		{
			"type": "Feature",
			"properties": {
				"confidence": 9,
				"authenticationResultCode": "ValidCredentials",
				"brandLogoUri": "http://dev.virtualearth.net/Branding/logo_powered_by.png",
				"copyright": "Copyright © 2017 Microsoft and its suppliers. All rights reserved. This API cannot be accessed and the content and any results may not be used, reproduced or transmitted in any manner without express written permission from Microsoft Corporation.",
				"entityType": "Address",
				"matchCodes": [
					"Good"
				],
				"name": "810 Chemin de Covey Hill, Havelock, QC J0S 2C0, Canada",
				"statusCode": 200,
				"statusDescription": "OK",
				"traceId": "7d61a795be23462296986a863de36bcb|BN20130632|7.7.0.0|",
				"addressLine": "810 Chemin de Covey Hill",
				"adminDistrict": "QC",
				"adminDistrict2": "Le Haut-St-Laurent",
				"countryRegion": "Canada",
				"formattedAddress": "810 Chemin de Covey Hill, Havelock, QC J0S 2C0, Canada",
				"locality": "Havelock",
				"postalCode": "J0S 2C0"
			},
			"geometry": {
				"type": "Point",
				"coordinates": [
					-73.69942,
					45.01922
				]
			},
			"bbox": [
				-73.7010103,
				45.0180958,
				-73.6978297,
				45.0203442
			]
		}
	]
}
