{
	"type": "FeatureCollection",
	"features": [
		{
			"type": "Feature",
			"properties": {
				"confidence": 9,
				"authenticationResultCode": "ValidCredentials",
				"brandLogoUri": "http://dev.virtualearth.net/Branding/logo_powered_by.png",
				"copyright": "Copyright © 2017 Microsoft and its suppliers. All rights reserved. This API cannot be accessed and the content and any results may not be used, reproduced or transmitted in any manner without express written permission from Microsoft Corporation.",
				"entityType": "Address",
				"matchCodes": [
					"Good"
				],
				"name": "8100 Yonge St, Thornhill, ON L4J 6W6, Canada",
				"statusCode": 200,
				"statusDescription": "OK",
				"traceId": "c5c7caaf17eb43f0b75f9f7ffac3cc5f|BN20121763|7.7.0.0|",
				"addressLine": "8100 Yonge St",
				"adminDistrict": "ON",
				"adminDistrict2": "York",
				"countryRegion": "Canada",
				"formattedAddress": "8100 Yonge St, Thornhill, ON L4J 6W6, Canada",
				"locality": "Vaughan",
				"neighborhood": "Thornhill",
				"postalCode": "L4J 6W6"
			},
			"geometry": {
				"type": "Point",
				"coordinates": [
					-79.42723,
					43.82445
				]
			},
			"bbox": [
				-79.4287882,
				43.8233258,
				-79.4256718,
				43.8255742
			]
		}
	]
}
