{
	"type": "FeatureCollection",
	"features": [
		{
			"type": "Feature",
			"properties": {
				"confidence": 9,
				"authenticationResultCode": "ValidCredentials",
				"brandLogoUri": "http://dev.virtualearth.net/Branding/logo_powered_by.png",
				"copyright": "Copyright © 2017 Microsoft and its suppliers. All rights reserved. This API cannot be accessed and the content and any results may not be used, reproduced or transmitted in any manner without express written permission from Microsoft Corporation.",
				"entityType": "Address",
				"matchCodes": [
					"Good"
				],
				"name": "812 Rue des Vignobles, Terrebonne, QC J6W 5V8, Canada",
				"statusCode": 200,
				"statusDescription": "OK",
				"traceId": "8da23f9d284d40c580046b8113f56501|BN20121763|7.7.0.0|",
				"addressLine": "812 Rue des Vignobles",
				"adminDistrict": "QC",
				"adminDistrict2": "Les Moulins",
				"countryRegion": "Canada",
				"formattedAddress": "812 Rue des Vignobles, Terrebonne, QC J6W 5V8, Canada",
				"locality": "Terrebonne",
				"postalCode": "J6W 5V8"
			},
			"geometry": {
				"type": "Point",
				"coordinates": [
					-73.61214,
					45.71062
				]
			},
			"bbox": [
				-73.6137499,
				45.7094958,
				-73.6105301,
				45.7117442
			]
		}
	]
}
