{
	"type": "FeatureCollection",
	"features": [
		{
			"type": "Feature",
			"properties": {
				"confidence": 9,
				"authenticationResultCode": "ValidCredentials",
				"brandLogoUri": "http://dev.virtualearth.net/Branding/logo_powered_by.png",
				"copyright": "Copyright © 2017 Microsoft and its suppliers. All rights reserved. This API cannot be accessed and the content and any results may not be used, reproduced or transmitted in any manner without express written permission from Microsoft Corporation.",
				"entityType": "Address",
				"matchCodes": [
					"Good"
				],
				"name": "8130 Manning Ave, Fort McMurray, AB T9H 1V7, Canada",
				"statusCode": 200,
				"statusDescription": "OK",
				"traceId": "aaf6d229c6bd4dbfa3f94dc41c60de6e|BN20200137|7.7.0.0|",
				"addressLine": "8130 Manning Ave",
				"adminDistrict": "AB",
				"adminDistrict2": "Alberta",
				"countryRegion": "Canada",
				"formattedAddress": "8130 Manning Ave, Fort McMurray, AB T9H 1V7, Canada",
				"locality": "Wood Buffalo",
				"neighborhood": "Fort McMurray",
				"postalCode": "T9H 1V7"
			},
			"geometry": {
				"type": "Point",
				"coordinates": [
					-111.34781,
					56.71614
				]
			},
			"bbox": [
				-111.3498584,
				56.7150158,
				-111.3457616,
				56.7172642
			]
		}
	]
}
