{
	"type": "FeatureCollection",
	"features": [
		{
			"type": "Feature",
			"properties": {
				"confidence": 9,
				"authenticationResultCode": "ValidCredentials",
				"brandLogoUri": "http://dev.virtualearth.net/Branding/logo_powered_by.png",
				"copyright": "Copyright © 2017 Microsoft and its suppliers. All rights reserved. This API cannot be accessed and the content and any results may not be used, reproduced or transmitted in any manner without express written permission from Microsoft Corporation.",
				"entityType": "Address",
				"matchCodes": [
					"Good"
				],
				"name": "8138 13th Ave, Burnaby, BC V3N 2G4, Canada",
				"statusCode": 200,
				"statusDescription": "OK",
				"traceId": "9f08b5ab69714207af1bebffa9362719|BN20130634|7.7.0.0|",
				"addressLine": "8138 13th Ave",
				"adminDistrict": "BC",
				"adminDistrict2": "Greater Vancouver",
				"countryRegion": "Canada",
				"formattedAddress": "8138 13th Ave, Burnaby, BC V3N 2G4, Canada",
				"locality": "Burnaby",
				"neighborhood": "Second Street",
				"postalCode": "V3N 2G4"
			},
			"geometry": {
				"type": "Point",
				"coordinates": [
					-122.92329,
					49.22481
				]
			},
			"bbox": [
				-122.9250113,
				49.2236858,
				-122.9215687,
				49.2259342
			]
		}
	]
}
