{
	"type": "FeatureCollection",
	"features": [
		{
			"type": "Feature",
			"properties": {
				"confidence": 9,
				"authenticationResultCode": "ValidCredentials",
				"brandLogoUri": "http://dev.virtualearth.net/Branding/logo_powered_by.png",
				"copyright": "Copyright © 2017 Microsoft and its suppliers. All rights reserved. This API cannot be accessed and the content and any results may not be used, reproduced or transmitted in any manner without express written permission from Microsoft Corporation.",
				"entityType": "Address",
				"matchCodes": [
					"Good"
				],
				"name": "82 Corstate Ave, Concord, ON L4K 4X2, Canada",
				"statusCode": 200,
				"statusDescription": "OK",
				"traceId": "ab399a45c5374050b6b63d62150b7bad|BN20130631|7.7.0.0|",
				"addressLine": "82 Corstate Ave",
				"adminDistrict": "ON",
				"adminDistrict2": "York",
				"countryRegion": "Canada",
				"formattedAddress": "82 Corstate Ave, Concord, ON L4K 4X2, Canada",
				"locality": "Vaughan",
				"neighborhood": "Concord",
				"postalCode": "L4K 4X2"
			},
			"geometry": {
				"type": "Point",
				"coordinates": [
					-79.53599,
					43.81817
				]
			},
			"bbox": [
				-79.537548,
				43.8170458,
				-79.534432,
				43.8192942
			]
		}
	]
}
