{
	"type": "FeatureCollection",
	"features": [
		{
			"type": "Feature",
			"properties": {
				"confidence": 9,
				"authenticationResultCode": "ValidCredentials",
				"brandLogoUri": "http://dev.virtualearth.net/Branding/logo_powered_by.png",
				"copyright": "Copyright © 2017 Microsoft and its suppliers. All rights reserved. This API cannot be accessed and the content and any results may not be used, reproduced or transmitted in any manner without express written permission from Microsoft Corporation.",
				"entityType": "Address",
				"matchCodes": [
					"Good"
				],
				"name": "820 Guy St, Kelowna, BC V1Y 7R5, Canada",
				"statusCode": 200,
				"statusDescription": "OK",
				"traceId": "c50b6979fb6c4be0b9a0ff632f80896a|BN20130422|7.7.0.0|",
				"addressLine": "820 Guy St",
				"adminDistrict": "BC",
				"adminDistrict2": "Central Okanagan",
				"countryRegion": "Canada",
				"formattedAddress": "820 Guy St, Kelowna, BC V1Y 7R5, Canada",
				"locality": "Kelowna",
				"neighborhood": "North End",
				"postalCode": "V1Y 7R5"
			},
			"geometry": {
				"type": "Point",
				"coordinates": [
					-119.50046,
					49.89942
				]
			},
			"bbox": [
				-119.5022052,
				49.8982958,
				-119.4987148,
				49.9005442
			]
		}
	]
}
