{
	"type": "FeatureCollection",
	"features": [
		{
			"type": "Feature",
			"properties": {
				"confidence": 9,
				"authenticationResultCode": "ValidCredentials",
				"brandLogoUri": "http://dev.virtualearth.net/Branding/logo_powered_by.png",
				"copyright": "Copyright © 2017 Microsoft and its suppliers. All rights reserved. This API cannot be accessed and the content and any results may not be used, reproduced or transmitted in any manner without express written permission from Microsoft Corporation.",
				"entityType": "Address",
				"matchCodes": [
					"Good"
				],
				"name": "83 Caledonia Rd, Moncton, NB E1H 2E6, Canada",
				"statusCode": 200,
				"statusDescription": "OK",
				"traceId": "25023d2216c842e9b008ce2e002ee3c0|BN20130442|7.7.0.0|",
				"addressLine": "83 Caledonia Rd",
				"adminDistrict": "NB",
				"adminDistrict2": "Westmorland",
				"countryRegion": "Canada",
				"formattedAddress": "83 Caledonia Rd, Moncton, NB E1H 2E6, Canada",
				"locality": "Moncton",
				"postalCode": "E1H 2E6"
			},
			"geometry": {
				"type": "Point",
				"coordinates": [
					-64.76628,
					46.12942
				]
			},
			"bbox": [
				-64.7679021,
				46.1282958,
				-64.7646579,
				46.1305442
			]
		}
	]
}
