{
	"type": "FeatureCollection",
	"features": [
		{
			"type": "Feature",
			"properties": {
				"confidence": 9,
				"authenticationResultCode": "ValidCredentials",
				"brandLogoUri": "http://dev.virtualearth.net/Branding/logo_powered_by.png",
				"copyright": "Copyright © 2017 Microsoft and its suppliers. All rights reserved. This API cannot be accessed and the content and any results may not be used, reproduced or transmitted in any manner without express written permission from Microsoft Corporation.",
				"entityType": "Address",
				"matchCodes": [
					"Good"
				],
				"name": "8300 Lawson Rd, Milton, ON L9T 0A4, Canada",
				"statusCode": 200,
				"statusDescription": "OK",
				"traceId": "1a9fe9b217464f0aa522c5b2b8757927|BN20210145|7.7.0.0|",
				"addressLine": "8300 Lawson Rd",
				"adminDistrict": "ON",
				"adminDistrict2": "Halton",
				"countryRegion": "Canada",
				"formattedAddress": "8300 Lawson Rd, Milton, ON L9T 0A4, Canada",
				"locality": "Milton",
				"postalCode": "L9T 0A4"
			},
			"geometry": {
				"type": "Point",
				"coordinates": [
					-79.88333,
					43.5406
				]
			},
			"bbox": [
				-79.8848808,
				43.5394758,
				-79.8817792,
				43.5417242
			]
		}
	]
}
