{
	"type": "FeatureCollection",
	"features": [
		{
			"type": "Feature",
			"properties": {
				"confidence": 9,
				"authenticationResultCode": "ValidCredentials",
				"brandLogoUri": "http://dev.virtualearth.net/Branding/logo_powered_by.png",
				"copyright": "Copyright © 2017 Microsoft and its suppliers. All rights reserved. This API cannot be accessed and the content and any results may not be used, reproduced or transmitted in any manner without express written permission from Microsoft Corporation.",
				"entityType": "Address",
				"matchCodes": [
					"Good"
				],
				"name": "833 The Queensway, Etobicoke, ON M8Z 5Z1, Canada",
				"statusCode": 200,
				"statusDescription": "OK",
				"traceId": "9150a1818c6b4d6d86dbe48f78725804|BN20130431|7.7.0.0|",
				"addressLine": "833 The Queensway",
				"adminDistrict": "ON",
				"adminDistrict2": "Toronto",
				"countryRegion": "Canada",
				"formattedAddress": "833 The Queensway, Etobicoke, ON M8Z 5Z1, Canada",
				"locality": "Toronto",
				"neighborhood": "Stonegate-Queensway",
				"postalCode": "M8Z 5Z1"
			},
			"geometry": {
				"type": "Point",
				"coordinates": [
					-79.50883,
					43.6246
				]
			},
			"bbox": [
				-79.510383,
				43.6234758,
				-79.507277,
				43.6257242
			]
		}
	]
}
