{
	"type": "FeatureCollection",
	"features": [
		{
			"type": "Feature",
			"properties": {
				"confidence": 9,
				"authenticationResultCode": "ValidCredentials",
				"brandLogoUri": "http://dev.virtualearth.net/Branding/logo_powered_by.png",
				"copyright": "Copyright © 2017 Microsoft and its suppliers. All rights reserved. This API cannot be accessed and the content and any results may not be used, reproduced or transmitted in any manner without express written permission from Microsoft Corporation.",
				"entityType": "Address",
				"matchCodes": [
					"Good"
				],
				"name": "84 Lynden Rd, Brantford, ON N3R 5V1, Canada",
				"statusCode": 200,
				"statusDescription": "OK",
				"traceId": "ffefaf7df72446678145e71ec23fa6c9|BN20130631|7.7.0.0|",
				"addressLine": "84 Lynden Rd",
				"adminDistrict": "ON",
				"adminDistrict2": "Brant",
				"countryRegion": "Canada",
				"formattedAddress": "84 Lynden Rd, Brantford, ON N3R 5V1, Canada",
				"locality": "Brantford",
				"postalCode": "N3R 5V1"
			},
			"geometry": {
				"type": "Point",
				"coordinates": [
					-80.2421792,
					43.1732263
				]
			},
			"bbox": [
				-80.2437206,
				43.1721021,
				-80.2406377,
				43.1743505
			]
		}
	]
}
