{
	"type": "FeatureCollection",
	"features": [
		{
			"type": "Feature",
			"properties": {
				"confidence": 9,
				"authenticationResultCode": "ValidCredentials",
				"brandLogoUri": "http://dev.virtualearth.net/Branding/logo_powered_by.png",
				"copyright": "Copyright © 2017 Microsoft and its suppliers. All rights reserved. This API cannot be accessed and the content and any results may not be used, reproduced or transmitted in any manner without express written permission from Microsoft Corporation.",
				"entityType": "Address",
				"matchCodes": [
					"Good"
				],
				"name": "8435 Woodbine Ave, Markham, ON L3R 2P4, Canada",
				"statusCode": 200,
				"statusDescription": "OK",
				"traceId": "63898966d45144b6882ad509581ea931|BN20220145|7.7.0.0|",
				"addressLine": "8435 Woodbine Ave",
				"adminDistrict": "ON",
				"adminDistrict2": "York",
				"countryRegion": "Canada",
				"formattedAddress": "8435 Woodbine Ave, Markham, ON L3R 2P4, Canada",
				"locality": "Markham",
				"neighborhood": "Buttonville",
				"postalCode": "L3R 2P4"
			},
			"geometry": {
				"type": "Point",
				"coordinates": [
					-79.35696,
					43.84861
				]
			},
			"bbox": [
				-79.3585188,
				43.8474858,
				-79.3554012,
				43.8497342
			]
		}
	]
}
