{
	"type": "FeatureCollection",
	"features": [
		{
			"type": "Feature",
			"properties": {
				"confidence": 9,
				"authenticationResultCode": "ValidCredentials",
				"brandLogoUri": "http://dev.virtualearth.net/Branding/logo_powered_by.png",
				"copyright": "Copyright © 2017 Microsoft and its suppliers. All rights reserved. This API cannot be accessed and the content and any results may not be used, reproduced or transmitted in any manner without express written permission from Microsoft Corporation.",
				"entityType": "Address",
				"matchCodes": [
					"Good"
				],
				"name": "845 8th Ave, Dawson, YT Y0B, Canada",
				"statusCode": 200,
				"statusDescription": "OK",
				"traceId": "dcb33a93b3da49ca9e2fab3394857275|BN20250135|7.7.0.0|",
				"addressLine": "845 8th Ave",
				"adminDistrict": "YT",
				"adminDistrict2": "Yukon",
				"countryRegion": "Canada",
				"formattedAddress": "845 8th Ave, Dawson, YT Y0B, Canada",
				"locality": "Dawson",
				"postalCode": "Y0B 1G0"
			},
			"geometry": {
				"type": "Point",
				"coordinates": [
					-139.4283275,
					64.0578645
				]
			},
			"bbox": [
				-139.4308972,
				64.0567404,
				-139.4257578,
				64.0589887
			]
		}
	]
}
