{
	"type": "FeatureCollection",
	"features": [
		{
			"type": "Feature",
			"properties": {
				"confidence": 9,
				"authenticationResultCode": "ValidCredentials",
				"brandLogoUri": "http://dev.virtualearth.net/Branding/logo_powered_by.png",
				"copyright": "Copyright © 2017 Microsoft and its suppliers. All rights reserved. This API cannot be accessed and the content and any results may not be used, reproduced or transmitted in any manner without express written permission from Microsoft Corporation.",
				"entityType": "Address",
				"matchCodes": [
					"Good"
				],
				"name": "848 Eglinton Ave E, East York, ON M4G 2L1, Canada",
				"statusCode": 200,
				"statusDescription": "OK",
				"traceId": "eca57a6b17e8488fb25ac388a5bdcd94|BN20200239|7.7.0.0|",
				"addressLine": "848 Eglinton Ave E",
				"adminDistrict": "ON",
				"adminDistrict2": "Toronto",
				"countryRegion": "Canada",
				"formattedAddress": "848 Eglinton Ave E, East York, ON M4G 2L1, Canada",
				"locality": "Toronto",
				"neighborhood": "Leaside-Bennington",
				"postalCode": "M4G 2L1"
			},
			"geometry": {
				"type": "Point",
				"coordinates": [
					-79.3656,
					43.71361
				]
			},
			"bbox": [
				-79.3671553,
				43.7124858,
				-79.3640447,
				43.7147342
			]
		}
	]
}
