{
	"type": "FeatureCollection",
	"features": [
		{
			"type": "Feature",
			"properties": {
				"confidence": 9,
				"authenticationResultCode": "ValidCredentials",
				"brandLogoUri": "http://dev.virtualearth.net/Branding/logo_powered_by.png",
				"copyright": "Copyright © 2017 Microsoft and its suppliers. All rights reserved. This API cannot be accessed and the content and any results may not be used, reproduced or transmitted in any manner without express written permission from Microsoft Corporation.",
				"entityType": "Address",
				"matchCodes": [
					"Good"
				],
				"name": "848 3e Rue, Chibougamau, QC G8P 1P9, Canada",
				"statusCode": 200,
				"statusDescription": "OK",
				"traceId": "095c3e715f4a414eba8ffe61d27357f3|BN20280152|7.7.0.0|",
				"addressLine": "848 3e Rue",
				"adminDistrict": "QC",
				"adminDistrict2": "Baie-James",
				"countryRegion": "Canada",
				"formattedAddress": "848 3e Rue, Chibougamau, QC G8P 1P9, Canada",
				"locality": "Chibougamau",
				"postalCode": "G8P 1P9"
			},
			"geometry": {
				"type": "Point",
				"coordinates": [
					-74.37908,
					49.91337
				]
			},
			"bbox": [
				-74.3808257,
				49.9122458,
				-74.3773343,
				49.9144942
			]
		}
	]
}
