{
	"type": "FeatureCollection",
	"features": [
		{
			"type": "Feature",
			"properties": {
				"confidence": 9,
				"authenticationResultCode": "ValidCredentials",
				"brandLogoUri": "http://dev.virtualearth.net/Branding/logo_powered_by.png",
				"copyright": "Copyright © 2017 Microsoft and its suppliers. All rights reserved. This API cannot be accessed and the content and any results may not be used, reproduced or transmitted in any manner without express written permission from Microsoft Corporation.",
				"entityType": "Address",
				"matchCodes": [
					"Good"
				],
				"name": "849 Progress Ave, Scarborough, ON M1H 2X4, Canada",
				"statusCode": 200,
				"statusDescription": "OK",
				"traceId": "f296ab3fdbb942b6aab9358f1b8451e5|BN20130530|7.7.0.0|",
				"addressLine": "849 Progress Ave",
				"adminDistrict": "ON",
				"adminDistrict2": "Toronto",
				"countryRegion": "Canada",
				"formattedAddress": "849 Progress Ave, Scarborough, ON M1H 2X4, Canada",
				"locality": "Toronto",
				"neighborhood": "Woburn",
				"postalCode": "M1H 2X4"
			},
			"geometry": {
				"type": "Point",
				"coordinates": [
					-79.2390099,
					43.78022
				]
			},
			"bbox": [
				-79.2405669,
				43.7790958,
				-79.2374529,
				43.7813442
			]
		}
	]
}
