{
	"type": "FeatureCollection",
	"features": [
		{
			"type": "Feature",
			"properties": {
				"confidence": 9,
				"authenticationResultCode": "ValidCredentials",
				"brandLogoUri": "http://dev.virtualearth.net/Branding/logo_powered_by.png",
				"copyright": "Copyright © 2017 Microsoft and its suppliers. All rights reserved. This API cannot be accessed and the content and any results may not be used, reproduced or transmitted in any manner without express written permission from Microsoft Corporation.",
				"entityType": "Address",
				"matchCodes": [
					"Good"
				],
				"name": "85 MacDonald Ave, Dartmouth, NS B3B 1T8, Canada",
				"statusCode": 200,
				"statusDescription": "OK",
				"traceId": "9199ccbe376a487eab2ea318ded38e9f|BN20240423|7.7.0.0|",
				"addressLine": "85 MacDonald Ave",
				"adminDistrict": "NS",
				"adminDistrict2": "Halifax",
				"countryRegion": "Canada",
				"formattedAddress": "85 MacDonald Ave, Dartmouth, NS B3B 1T8, Canada",
				"locality": "Halifax",
				"neighborhood": "Dartmouth",
				"postalCode": "B3B 1T8"
			},
			"geometry": {
				"type": "Point",
				"coordinates": [
					-63.58544,
					44.69491
				]
			},
			"bbox": [
				-63.5870214,
				44.6937858,
				-63.5838586,
				44.6960342
			]
		}
	]
}
