{
	"type": "FeatureCollection",
	"features": [
		{
			"type": "Feature",
			"properties": {
				"confidence": 9,
				"authenticationResultCode": "ValidCredentials",
				"brandLogoUri": "http://dev.virtualearth.net/Branding/logo_powered_by.png",
				"copyright": "Copyright © 2017 Microsoft and its suppliers. All rights reserved. This API cannot be accessed and the content and any results may not be used, reproduced or transmitted in any manner without express written permission from Microsoft Corporation.",
				"entityType": "Address",
				"matchCodes": [
					"Good"
				],
				"name": "85 Rue Victoria, Gatineau, QC J8X 2A3, Canada",
				"statusCode": 200,
				"statusDescription": "OK",
				"traceId": "210c63cbd1734ee897a61231d589902f|BN20130620|7.7.0.0|",
				"addressLine": "85 Rue Victoria",
				"adminDistrict": "QC",
				"adminDistrict2": "Gatineau",
				"countryRegion": "Canada",
				"formattedAddress": "85 Rue Victoria, Gatineau, QC J8X 2A3, Canada",
				"locality": "Gatineau",
				"neighborhood": "Hull",
				"postalCode": "J8X 2A3"
			},
			"geometry": {
				"type": "Point",
				"coordinates": [
					-75.71211,
					45.4287599
				]
			},
			"bbox": [
				-75.7137118,
				45.4276357,
				-75.7105082,
				45.4298841
			]
		}
	]
}
