{
	"type": "FeatureCollection",
	"features": [
		{
			"type": "Feature",
			"properties": {
				"confidence": 9,
				"authenticationResultCode": "ValidCredentials",
				"brandLogoUri": "http://dev.virtualearth.net/Branding/logo_powered_by.png",
				"copyright": "Copyright © 2017 Microsoft and its suppliers. All rights reserved. This API cannot be accessed and the content and any results may not be used, reproduced or transmitted in any manner without express written permission from Microsoft Corporation.",
				"entityType": "Address",
				"matchCodes": [
					"Good"
				],
				"name": "852 Breakwater Rd, Parksville, BC V9P 1Z8, Canada",
				"statusCode": 200,
				"statusDescription": "OK",
				"traceId": "734a97127c2248208b1a5372705940b5|BN20240423|7.7.0.0|",
				"addressLine": "852 Breakwater Rd",
				"adminDistrict": "BC",
				"adminDistrict2": "Nanaimo",
				"countryRegion": "Canada",
				"formattedAddress": "852 Breakwater Rd, Parksville, BC V9P 1Z8, Canada",
				"locality": "Nanaimo District",
				"neighborhood": "Parksville",
				"postalCode": "V9P 1Z8"
			},
			"geometry": {
				"type": "Point",
				"coordinates": [
					-124.354052,
					49.3408678
				]
			},
			"bbox": [
				-124.3557773,
				49.3397437,
				-124.3523267,
				49.341992
			]
		}
	]
}
