{
	"type": "FeatureCollection",
	"features": [
		{
			"type": "Feature",
			"properties": {
				"confidence": 6,
				"authenticationResultCode": "ValidCredentials",
				"brandLogoUri": "http://dev.virtualearth.net/Branding/logo_powered_by.png",
				"copyright": "Copyright © 2017 Microsoft and its suppliers. All rights reserved. This API cannot be accessed and the content and any results may not be used, reproduced or transmitted in any manner without express written permission from Microsoft Corporation.",
				"entityType": "RoadBlock",
				"matchCodes": [
					"UpHierarchy"
				],
				"name": "HWY-93, Midland, ON L4R 4K4, Canada",
				"statusCode": 200,
				"statusDescription": "OK",
				"traceId": "1daf1b5d0cc847f7a80b355c1d2055c5|BN20130522|7.7.0.0|",
				"addressLine": "HWY-93",
				"adminDistrict": "ON",
				"adminDistrict2": "Simcoe",
				"countryRegion": "Canada",
				"formattedAddress": "HWY-93, Midland, ON L4R 4K4, Canada",
				"locality": "Midland",
				"postalCode": "L4R 4K4"
			},
			"geometry": {
				"type": "Point",
				"coordinates": [
					-79.9041347,
					44.7330124
				]
			},
			"bbox": [
				-79.92766,
				44.70719,
				-79.89195,
				44.75918
			]
		}
	]
}
