{
	"type": "FeatureCollection",
	"features": [
		{
			"type": "Feature",
			"properties": {
				"confidence": 9,
				"authenticationResultCode": "ValidCredentials",
				"brandLogoUri": "http://dev.virtualearth.net/Branding/logo_powered_by.png",
				"copyright": "Copyright © 2017 Microsoft and its suppliers. All rights reserved. This API cannot be accessed and the content and any results may not be used, reproduced or transmitted in any manner without express written permission from Microsoft Corporation.",
				"entityType": "Address",
				"matchCodes": [
					"Good"
				],
				"name": "8526 190 St NW, Edmonton, AB T5T 4Z8, Canada",
				"statusCode": 200,
				"statusDescription": "OK",
				"traceId": "b9cbbeae727e4fff9e587758ef662da0|BN20130634|7.7.0.0|",
				"addressLine": "8526 190 St NW",
				"adminDistrict": "AB",
				"adminDistrict2": "Alberta",
				"countryRegion": "Canada",
				"formattedAddress": "8526 190 St NW, Edmonton, AB T5T 4Z8, Canada",
				"locality": "Edmonton",
				"neighborhood": "Aldergrove",
				"postalCode": "T5T 4Z8"
			},
			"geometry": {
				"type": "Point",
				"coordinates": [
					-113.65172,
					53.51927
				]
			},
			"bbox": [
				-113.6536108,
				53.5181458,
				-113.6498292,
				53.5203942
			]
		}
	]
}
