{
	"type": "FeatureCollection",
	"features": [
		{
			"type": "Feature",
			"properties": {
				"confidence": 9,
				"authenticationResultCode": "ValidCredentials",
				"brandLogoUri": "http://dev.virtualearth.net/Branding/logo_powered_by.png",
				"copyright": "Copyright © 2017 Microsoft and its suppliers. All rights reserved. This API cannot be accessed and the content and any results may not be used, reproduced or transmitted in any manner without express written permission from Microsoft Corporation.",
				"entityType": "Address",
				"matchCodes": [
					"Good"
				],
				"name": "855 Homer St, Vancouver, BC V6B 2W2, Canada",
				"statusCode": 200,
				"statusDescription": "OK",
				"traceId": "87da36e7027b4b78843b0b9bdf048957|BN20200137|7.7.0.0|",
				"addressLine": "855 Homer St",
				"adminDistrict": "BC",
				"adminDistrict2": "Greater Vancouver",
				"countryRegion": "Canada",
				"formattedAddress": "855 Homer St, Vancouver, BC V6B 2W2, Canada",
				"locality": "Vancouver",
				"neighborhood": "Downtown",
				"postalCode": "V6B 2W2"
			},
			"geometry": {
				"type": "Point",
				"coordinates": [
					-123.11849,
					49.27892
				]
			},
			"bbox": [
				-123.1202132,
				49.2777958,
				-123.1167668,
				49.2800442
			]
		}
	]
}
