{
	"type": "FeatureCollection",
	"features": [
		{
			"type": "Feature",
			"properties": {
				"confidence": 9,
				"authenticationResultCode": "ValidCredentials",
				"brandLogoUri": "http://dev.virtualearth.net/Branding/logo_powered_by.png",
				"copyright": "Copyright © 2017 Microsoft and its suppliers. All rights reserved. This API cannot be accessed and the content and any results may not be used, reproduced or transmitted in any manner without express written permission from Microsoft Corporation.",
				"entityType": "Address",
				"matchCodes": [
					"Good"
				],
				"name": "8590 Airport Rd, Brampton, ON L6T 5A3, Canada",
				"statusCode": 200,
				"statusDescription": "OK",
				"traceId": "875bf08e9922402386a733e3fc73a990|BN20130533|7.7.0.0|",
				"addressLine": "8590 Airport Rd",
				"adminDistrict": "ON",
				"adminDistrict2": "Peel",
				"countryRegion": "Canada",
				"formattedAddress": "8590 Airport Rd, Brampton, ON L6T 5A3, Canada",
				"locality": "Brampton",
				"neighborhood": "Bramalea",
				"postalCode": "L6T 5A3"
			},
			"geometry": {
				"type": "Point",
				"coordinates": [
					-79.68017,
					43.73058
				]
			},
			"bbox": [
				-79.6817257,
				43.7294558,
				-79.6786143,
				43.7317042
			]
		}
	]
}
