{
	"type": "FeatureCollection",
	"features": [
		{
			"type": "Feature",
			"properties": {
				"confidence": 9,
				"authenticationResultCode": "ValidCredentials",
				"brandLogoUri": "http://dev.virtualearth.net/Branding/logo_powered_by.png",
				"copyright": "Copyright © 2017 Microsoft and its suppliers. All rights reserved. This API cannot be accessed and the content and any results may not be used, reproduced or transmitted in any manner without express written permission from Microsoft Corporation.",
				"entityType": "Address",
				"matchCodes": [
					"Good"
				],
				"name": "859 Courtland Ave E, Kitchener, ON N2C 1K4, Canada",
				"statusCode": 200,
				"statusDescription": "OK",
				"traceId": "71e40a419dc747558bbc45923ebc04dc|BN20240423|7.7.0.0|",
				"addressLine": "859 Courtland Ave E",
				"adminDistrict": "ON",
				"adminDistrict2": "Waterloo",
				"countryRegion": "Canada",
				"formattedAddress": "859 Courtland Ave E, Kitchener, ON N2C 1K4, Canada",
				"locality": "Kitchener",
				"neighborhood": "Vanier",
				"postalCode": "N2C 1K4"
			},
			"geometry": {
				"type": "Point",
				"coordinates": [
					-80.46799,
					43.42759
				]
			},
			"bbox": [
				-80.4695379,
				43.4264658,
				-80.4664421,
				43.4287142
			]
		}
	]
}
