{
	"type": "FeatureCollection",
	"features": [
		{
			"type": "Feature",
			"properties": {
				"confidence": 9,
				"authenticationResultCode": "ValidCredentials",
				"brandLogoUri": "http://dev.virtualearth.net/Branding/logo_powered_by.png",
				"copyright": "Copyright © 2017 Microsoft and its suppliers. All rights reserved. This API cannot be accessed and the content and any results may not be used, reproduced or transmitted in any manner without express written permission from Microsoft Corporation.",
				"entityType": "Address",
				"matchCodes": [
					"Good"
				],
				"name": "86 Auburn Crest Way SE, Calgary, AB T3M 1T8, Canada",
				"statusCode": 200,
				"statusDescription": "OK",
				"traceId": "87c74994004442f1a479bdb0066b1d18|BN20121763|7.7.0.0|",
				"addressLine": "86 Auburn Crest Way SE",
				"adminDistrict": "AB",
				"adminDistrict2": "Alberta",
				"countryRegion": "Canada",
				"formattedAddress": "86 Auburn Crest Way SE, Calgary, AB T3M 1T8, Canada",
				"locality": "Calgary",
				"neighborhood": "Auburn Bay",
				"postalCode": "T3M 1T8"
			},
			"geometry": {
				"type": "Point",
				"coordinates": [
					-113.94646,
					50.89005
				]
			},
			"bbox": [
				-113.9482421,
				50.8889258,
				-113.9446779,
				50.8911742
			]
		}
	]
}
