{
	"type": "FeatureCollection",
	"features": [
		{
			"type": "Feature",
			"properties": {
				"confidence": 9,
				"authenticationResultCode": "ValidCredentials",
				"brandLogoUri": "http://dev.virtualearth.net/Branding/logo_powered_by.png",
				"copyright": "Copyright © 2017 Microsoft and its suppliers. All rights reserved. This API cannot be accessed and the content and any results may not be used, reproduced or transmitted in any manner without express written permission from Microsoft Corporation.",
				"entityType": "Address",
				"matchCodes": [
					"Good"
				],
				"name": "8600 Keele St, Concord, ON L4K 4H8, Canada",
				"statusCode": 200,
				"statusDescription": "OK",
				"traceId": "42218f09360547719fde90946a738e31|BN20240253|7.7.0.0|",
				"addressLine": "8600 Keele St",
				"adminDistrict": "ON",
				"adminDistrict2": "York",
				"countryRegion": "Canada",
				"formattedAddress": "8600 Keele St, Concord, ON L4K 4H8, Canada",
				"locality": "Vaughan",
				"neighborhood": "Concord",
				"postalCode": "L4K 4H8"
			},
			"geometry": {
				"type": "Point",
				"coordinates": [
					-79.50627,
					43.82174
				]
			},
			"bbox": [
				-79.5078281,
				43.8206158,
				-79.5047119,
				43.8228642
			]
		}
	]
}
