{
	"type": "FeatureCollection",
	"features": [
		{
			"type": "Feature",
			"properties": {
				"confidence": 9,
				"authenticationResultCode": "ValidCredentials",
				"brandLogoUri": "http://dev.virtualearth.net/Branding/logo_powered_by.png",
				"copyright": "Copyright © 2017 Microsoft and its suppliers. All rights reserved. This API cannot be accessed and the content and any results may not be used, reproduced or transmitted in any manner without express written permission from Microsoft Corporation.",
				"entityType": "Address",
				"matchCodes": [
					"Good"
				],
				"name": "865 Sawmill Rd, Bloomingdale, ON N0B 1K0, Canada",
				"statusCode": 200,
				"statusDescription": "OK",
				"traceId": "56afc62c3fda4ccaa6a971f5b06d3755|BN20190642|7.7.0.0|",
				"addressLine": "865 Sawmill Rd",
				"adminDistrict": "ON",
				"adminDistrict2": "Waterloo",
				"countryRegion": "Canada",
				"formattedAddress": "865 Sawmill Rd, Bloomingdale, ON N0B 1K0, Canada",
				"locality": "Woolwich",
				"neighborhood": "Bloomingdale",
				"postalCode": "N0B 1K0"
			},
			"geometry": {
				"type": "Point",
				"coordinates": [
					-80.4629498,
					43.5101272
				]
			},
			"bbox": [
				-80.4644999,
				43.5090031,
				-80.4613998,
				43.5112514
			]
		}
	]
}
