{
	"type": "FeatureCollection",
	"features": [
		{
			"type": "Feature",
			"properties": {
				"confidence": 9,
				"authenticationResultCode": "ValidCredentials",
				"brandLogoUri": "http://dev.virtualearth.net/Branding/logo_powered_by.png",
				"copyright": "Copyright © 2017 Microsoft and its suppliers. All rights reserved. This API cannot be accessed and the content and any results may not be used, reproduced or transmitted in any manner without express written permission from Microsoft Corporation.",
				"entityType": "Address",
				"matchCodes": [
					"Good"
				],
				"name": "8681 HWY-1, Clare, NS B0W 2L0, Canada",
				"statusCode": 200,
				"statusDescription": "OK",
				"traceId": "cac05df8fdaa4bfd8fcdfb3356c1681b|BN20220145|7.7.0.0|",
				"addressLine": "8681 HWY-1",
				"adminDistrict": "NS",
				"adminDistrict2": "Digby",
				"countryRegion": "Canada",
				"formattedAddress": "8681 HWY-1, Clare, NS B0W 2L0, Canada",
				"locality": "Clare",
				"neighborhood": "Meteghan Centre",
				"postalCode": "B0W 2L0"
			},
			"geometry": {
				"type": "Point",
				"coordinates": [
					-66.1420752,
					44.2026586
				]
			},
			"bbox": [
				-66.1436434,
				44.2015344,
				-66.1405071,
				44.2037827
			]
		}
	]
}
