{
	"type": "FeatureCollection",
	"features": [
		{
			"type": "Feature",
			"properties": {
				"confidence": 9,
				"authenticationResultCode": "ValidCredentials",
				"brandLogoUri": "http://dev.virtualearth.net/Branding/logo_powered_by.png",
				"copyright": "Copyright © 2017 Microsoft and its suppliers. All rights reserved. This API cannot be accessed and the content and any results may not be used, reproduced or transmitted in any manner without express written permission from Microsoft Corporation.",
				"entityType": "Address",
				"matchCodes": [
					"Good"
				],
				"name": "87 Amelia St, Toronto, ON M4X 1E5, Canada",
				"statusCode": 200,
				"statusDescription": "OK",
				"traceId": "1b1fe663f043430888b7205d54473de1|BN20130620|7.7.0.0|",
				"addressLine": "87 Amelia St",
				"adminDistrict": "ON",
				"adminDistrict2": "Toronto",
				"countryRegion": "Canada",
				"formattedAddress": "87 Amelia St, Toronto, ON M4X 1E5, Canada",
				"locality": "Toronto",
				"neighborhood": "Cabbagetown-South St James Town",
				"postalCode": "M4X 1E5"
			},
			"geometry": {
				"type": "Point",
				"coordinates": [
					-79.36542,
					43.66787
				]
			},
			"bbox": [
				-79.3669741,
				43.6667458,
				-79.3638659,
				43.6689942
			]
		}
	]
}
