{
	"type": "FeatureCollection",
	"features": [
		{
			"type": "Feature",
			"properties": {
				"confidence": 9,
				"authenticationResultCode": "ValidCredentials",
				"brandLogoUri": "http://dev.virtualearth.net/Branding/logo_powered_by.png",
				"copyright": "Copyright © 2017 Microsoft and its suppliers. All rights reserved. This API cannot be accessed and the content and any results may not be used, reproduced or transmitted in any manner without express written permission from Microsoft Corporation.",
				"entityType": "Address",
				"matchCodes": [
					"Good"
				],
				"name": "8702 111A St, Grande Prairie, AB T8V 5L3, Canada",
				"statusCode": 200,
				"statusDescription": "OK",
				"traceId": "4176315ad353428eb71518aa64988a69|BN20240423|7.7.0.0|",
				"addressLine": "8702 111A St",
				"adminDistrict": "AB",
				"adminDistrict2": "Alberta",
				"countryRegion": "Canada",
				"formattedAddress": "8702 111A St, Grande Prairie, AB T8V 5L3, Canada",
				"locality": "Grande Prairie",
				"neighborhood": "Richmond Industrial Park",
				"postalCode": "T8V 5L3"
			},
			"geometry": {
				"type": "Point",
				"coordinates": [
					-118.83248,
					55.15975
				]
			},
			"bbox": [
				-118.8344477,
				55.1586258,
				-118.8305123,
				55.1608742
			]
		}
	]
}
