{
	"type": "FeatureCollection",
	"features": [
		{
			"type": "Feature",
			"properties": {
				"confidence": 9,
				"authenticationResultCode": "ValidCredentials",
				"brandLogoUri": "http://dev.virtualearth.net/Branding/logo_powered_by.png",
				"copyright": "Copyright © 2017 Microsoft and its suppliers. All rights reserved. This API cannot be accessed and the content and any results may not be used, reproduced or transmitted in any manner without express written permission from Microsoft Corporation.",
				"entityType": "Address",
				"matchCodes": [
					"Good"
				],
				"name": "8707 CR-45, Alnwick/Haldimand, ON K0K, Canada",
				"statusCode": 200,
				"statusDescription": "OK",
				"traceId": "b003b01ce41243fd87e4b85a790311b6|BN20280152|7.7.0.0|",
				"addressLine": "8707 CR-45",
				"adminDistrict": "ON",
				"adminDistrict2": "Northumberland",
				"countryRegion": "Canada",
				"formattedAddress": "8707 CR-45, Alnwick/Haldimand, ON K0K, Canada",
				"locality": "Alnwick/Haldimand",
				"neighborhood": "Roseneath",
				"postalCode": "K0K 2X0"
			},
			"geometry": {
				"type": "Point",
				"coordinates": [
					-78.071081,
					44.1767201
				]
			},
			"bbox": [
				-78.0726484,
				44.175596,
				-78.0695135,
				44.1778443
			]
		}
	]
}
