{
	"type": "FeatureCollection",
	"features": [
		{
			"type": "Feature",
			"properties": {
				"confidence": 9,
				"authenticationResultCode": "ValidCredentials",
				"brandLogoUri": "http://dev.virtualearth.net/Branding/logo_powered_by.png",
				"copyright": "Copyright © 2017 Microsoft and its suppliers. All rights reserved. This API cannot be accessed and the content and any results may not be used, reproduced or transmitted in any manner without express written permission from Microsoft Corporation.",
				"entityType": "Address",
				"matchCodes": [
					"Good"
				],
				"name": "871 Whitmore Ave E, Dauphin, MB R7N, Canada",
				"statusCode": 200,
				"statusDescription": "OK",
				"traceId": "c807eaac9aa0433ea67d1cf61d843d14|BN20130719|7.7.0.0|",
				"addressLine": "871 Whitmore Ave E",
				"adminDistrict": "MB",
				"adminDistrict2": "Manitoba",
				"countryRegion": "Canada",
				"formattedAddress": "871 Whitmore Ave E, Dauphin, MB R7N, Canada",
				"locality": "Dauphin",
				"postalCode": "R7N 3B3"
			},
			"geometry": {
				"type": "Point",
				"coordinates": [
					-100.018068,
					51.1398451
				]
			},
			"bbox": [
				-100.0198597,
				51.138721,
				-100.0162763,
				51.1409693
			]
		}
	]
}
