{
	"type": "FeatureCollection",
	"features": [
		{
			"type": "Feature",
			"properties": {
				"confidence": 9,
				"authenticationResultCode": "ValidCredentials",
				"brandLogoUri": "http://dev.virtualearth.net/Branding/logo_powered_by.png",
				"copyright": "Copyright © 2017 Microsoft and its suppliers. All rights reserved. This API cannot be accessed and the content and any results may not be used, reproduced or transmitted in any manner without express written permission from Microsoft Corporation.",
				"entityType": "Address",
				"matchCodes": [
					"Good"
				],
				"name": "8812 44 St SE, Calgary, AB T2C 2P6, Canada",
				"statusCode": 200,
				"statusDescription": "OK",
				"traceId": "54cee00bb5d04560955f1f1a4fcd8918|BN20240423|7.7.0.0|",
				"addressLine": "8812 44 St SE",
				"adminDistrict": "AB",
				"adminDistrict2": "Alberta",
				"countryRegion": "Canada",
				"formattedAddress": "8812 44 St SE, Calgary, AB T2C 2P6, Canada",
				"locality": "Calgary",
				"postalCode": "T2C 2P6"
			},
			"geometry": {
				"type": "Point",
				"coordinates": [
					-113.96969,
					50.9746499
				]
			},
			"bbox": [
				-113.9714753,
				50.9735257,
				-113.9679047,
				50.9757741
			]
		}
	]
}
