{
	"type": "FeatureCollection",
	"features": [
		{
			"type": "Feature",
			"properties": {
				"confidence": 9,
				"authenticationResultCode": "ValidCredentials",
				"brandLogoUri": "http://dev.virtualearth.net/Branding/logo_powered_by.png",
				"copyright": "Copyright © 2017 Microsoft and its suppliers. All rights reserved. This API cannot be accessed and the content and any results may not be used, reproduced or transmitted in any manner without express written permission from Microsoft Corporation.",
				"entityType": "Address",
				"matchCodes": [
					"Good"
				],
				"name": "8819 HWY-105, Baddeck, NS B0E 1B0, Canada",
				"statusCode": 200,
				"statusDescription": "OK",
				"traceId": "e881aea716614811ad60e38d6ce03168|BN20130422|7.7.0.0|",
				"addressLine": "8819 HWY-105",
				"adminDistrict": "NS",
				"adminDistrict2": "Victoria",
				"countryRegion": "Canada",
				"formattedAddress": "8819 HWY-105, Baddeck, NS B0E 1B0, Canada",
				"locality": "Victoria",
				"neighborhood": "Baddeck",
				"postalCode": "B0E 1B0"
			},
			"geometry": {
				"type": "Point",
				"coordinates": [
					-60.8144205,
					46.0811685
				]
			},
			"bbox": [
				-60.8160412,
				46.0800444,
				-60.8127999,
				46.0822927
			]
		}
	]
}
