{
	"type": "FeatureCollection",
	"features": [
		{
			"type": "Feature",
			"properties": {
				"confidence": 9,
				"authenticationResultCode": "ValidCredentials",
				"brandLogoUri": "http://dev.virtualearth.net/Branding/logo_powered_by.png",
				"copyright": "Copyright © 2017 Microsoft and its suppliers. All rights reserved. This API cannot be accessed and the content and any results may not be used, reproduced or transmitted in any manner without express written permission from Microsoft Corporation.",
				"entityType": "Address",
				"matchCodes": [
					"Good"
				],
				"name": "887 Chemin Parent, Duclos, QC J0X 1S0, Canada",
				"statusCode": 200,
				"statusDescription": "OK",
				"traceId": "95f403125aef461a82557cd198ae8edd|BN20300154|7.7.0.0|",
				"addressLine": "887 Chemin Parent",
				"adminDistrict": "QC",
				"adminDistrict2": "Les Collines-de-l'Outaouais",
				"countryRegion": "Canada",
				"formattedAddress": "887 Chemin Parent, Duclos, QC J0X 1S0, Canada",
				"locality": "La Pêche",
				"neighborhood": "Duclos",
				"postalCode": "J0X 1S0"
			},
			"geometry": {
				"type": "Point",
				"coordinates": [
					-76.11015,
					45.68939
				]
			},
			"bbox": [
				-76.1117593,
				45.6882658,
				-76.1085407,
				45.6905142
			]
		}
	]
}
