{
	"type": "FeatureCollection",
	"features": [
		{
			"type": "Feature",
			"properties": {
				"confidence": 9,
				"authenticationResultCode": "ValidCredentials",
				"brandLogoUri": "http://dev.virtualearth.net/Branding/logo_powered_by.png",
				"copyright": "Copyright © 2017 Microsoft and its suppliers. All rights reserved. This API cannot be accessed and the content and any results may not be used, reproduced or transmitted in any manner without express written permission from Microsoft Corporation.",
				"entityType": "Address",
				"matchCodes": [
					"Good"
				],
				"name": "895 John St N, Gravenhurst, ON P1P 1C3, Canada",
				"statusCode": 200,
				"statusDescription": "OK",
				"traceId": "cea2c5eafd1f4c139b4bbc1144797972|BN20121762|7.7.0.0|",
				"addressLine": "895 John St N",
				"adminDistrict": "ON",
				"adminDistrict2": "Muskoka",
				"countryRegion": "Canada",
				"formattedAddress": "895 John St N, Gravenhurst, ON P1P 1C3, Canada",
				"locality": "Gravenhurst",
				"postalCode": "P1P 1C3"
			},
			"geometry": {
				"type": "Point",
				"coordinates": [
					-79.3789,
					44.92641
				]
			},
			"bbox": [
				-79.3804878,
				44.9252858,
				-79.3773122,
				44.9275342
			]
		}
	]
}
