{
	"type": "FeatureCollection",
	"features": [
		{
			"type": "Feature",
			"properties": {
				"confidence": 9,
				"authenticationResultCode": "ValidCredentials",
				"brandLogoUri": "http://dev.virtualearth.net/Branding/logo_powered_by.png",
				"copyright": "Copyright © 2017 Microsoft and its suppliers. All rights reserved. This API cannot be accessed and the content and any results may not be used, reproduced or transmitted in any manner without express written permission from Microsoft Corporation.",
				"entityType": "Address",
				"matchCodes": [
					"Good"
				],
				"name": "8955 Fraserwood Ct, Burnaby, BC V5J 5H7, Canada",
				"statusCode": 200,
				"statusDescription": "OK",
				"traceId": "6d601ce493c2449fb8216644fb1234af|BN20171457|7.7.0.0|",
				"addressLine": "8955 Fraserwood Ct",
				"adminDistrict": "BC",
				"adminDistrict2": "Greater Vancouver",
				"countryRegion": "Canada",
				"formattedAddress": "8955 Fraserwood Ct, Burnaby, BC V5J 5H7, Canada",
				"locality": "Burnaby",
				"neighborhood": "Big Bend",
				"postalCode": "V5J 5H7"
			},
			"geometry": {
				"type": "Point",
				"coordinates": [
					-123.0183349,
					49.2007715
				]
			},
			"bbox": [
				-123.0200553,
				49.1996473,
				-123.0166145,
				49.2018956
			]
		}
	]
}
