{
	"type": "FeatureCollection",
	"features": [
		{
			"type": "Feature",
			"properties": {
				"confidence": 9,
				"authenticationResultCode": "ValidCredentials",
				"brandLogoUri": "http://dev.virtualearth.net/Branding/logo_powered_by.png",
				"copyright": "Copyright © 2017 Microsoft and its suppliers. All rights reserved. This API cannot be accessed and the content and any results may not be used, reproduced or transmitted in any manner without express written permission from Microsoft Corporation.",
				"entityType": "Address",
				"matchCodes": [
					"Good"
				],
				"name": "899 Rue du Patrimoine, Cacouna, QC G0L 1G0, Canada",
				"statusCode": 200,
				"statusDescription": "OK",
				"traceId": "4c204c8a66674bb2adfe8c1df356e725|BN20130520|7.7.0.0|",
				"addressLine": "899 Rue du Patrimoine",
				"adminDistrict": "QC",
				"adminDistrict2": "Riviere-du-Loup",
				"countryRegion": "Canada",
				"formattedAddress": "899 Rue du Patrimoine, Cacouna, QC G0L 1G0, Canada",
				"locality": "Cacouna",
				"postalCode": "G0L 1G0"
			},
			"geometry": {
				"type": "Point",
				"coordinates": [
					-69.50002,
					47.92075
				]
			},
			"bbox": [
				-69.5016974,
				47.9196258,
				-69.4983426,
				47.9218742
			]
		}
	]
}
