{
	"type": "FeatureCollection",
	"features": [
		{
			"type": "Feature",
			"properties": {
				"confidence": 9,
				"authenticationResultCode": "ValidCredentials",
				"brandLogoUri": "http://dev.virtualearth.net/Branding/logo_powered_by.png",
				"copyright": "Copyright © 2017 Microsoft and its suppliers. All rights reserved. This API cannot be accessed and the content and any results may not be used, reproduced or transmitted in any manner without express written permission from Microsoft Corporation.",
				"entityType": "Address",
				"matchCodes": [
					"Good"
				],
				"name": "9 Carousel Cres, Richmond Hill, ON L4E 3X7, Canada",
				"statusCode": 200,
				"statusDescription": "OK",
				"traceId": "2a2f159960934d13af7ed28b50030c97|BN20130442|7.7.0.0|",
				"addressLine": "9 Carousel Cres",
				"adminDistrict": "ON",
				"adminDistrict2": "York",
				"countryRegion": "Canada",
				"formattedAddress": "9 Carousel Cres, Richmond Hill, ON L4E 3X7, Canada",
				"locality": "Richmond Hill",
				"postalCode": "L4E 3X7"
			},
			"geometry": {
				"type": "Point",
				"coordinates": [
					-79.45239,
					43.94045
				]
			},
			"bbox": [
				-79.4539512,
				43.9393258,
				-79.4508288,
				43.9415742
			]
		}
	]
}
