{
	"type": "FeatureCollection",
	"features": [
		{
			"type": "Feature",
			"properties": {
				"confidence": 9,
				"authenticationResultCode": "ValidCredentials",
				"brandLogoUri": "http://dev.virtualearth.net/Branding/logo_powered_by.png",
				"copyright": "Copyright © 2017 Microsoft and its suppliers. All rights reserved. This API cannot be accessed and the content and any results may not be used, reproduced or transmitted in any manner without express written permission from Microsoft Corporation.",
				"entityType": "Address",
				"matchCodes": [
					"Good"
				],
				"name": "9 Dairydale Rd, Studholm, NB E4G 2E2, Canada",
				"statusCode": 200,
				"statusDescription": "OK",
				"traceId": "e62d0a24a0f0411faed072c019cc1a3d|BN20240253|7.7.0.0|",
				"addressLine": "9 Dairydale Rd",
				"adminDistrict": "NB",
				"adminDistrict2": "Kings",
				"countryRegion": "Canada",
				"formattedAddress": "9 Dairydale Rd, Studholm, NB E4G 2E2, Canada",
				"locality": "Studholm",
				"postalCode": "E4G 2E2"
			},
			"geometry": {
				"type": "Point",
				"coordinates": [
					-65.5263888,
					45.7373622
				]
			},
			"bbox": [
				-65.5279994,
				45.736238,
				-65.5247781,
				45.7384863
			]
		}
	]
}
