{
	"type": "FeatureCollection",
	"features": [
		{
			"type": "Feature",
			"properties": {
				"confidence": 9,
				"authenticationResultCode": "ValidCredentials",
				"brandLogoUri": "http://dev.virtualearth.net/Branding/logo_powered_by.png",
				"copyright": "Copyright © 2017 Microsoft and its suppliers. All rights reserved. This API cannot be accessed and the content and any results may not be used, reproduced or transmitted in any manner without express written permission from Microsoft Corporation.",
				"entityType": "Address",
				"matchCodes": [
					"Good"
				],
				"name": "9 John St, Moncton, NB E1C 2G7, Canada",
				"statusCode": 200,
				"statusDescription": "OK",
				"traceId": "15c10a20fdaa43fba5806ac160f48cc5|BN20130431|7.7.0.0|",
				"addressLine": "9 John St",
				"adminDistrict": "NB",
				"adminDistrict2": "Westmorland",
				"countryRegion": "Canada",
				"formattedAddress": "9 John St, Moncton, NB E1C 2G7, Canada",
				"locality": "Moncton",
				"postalCode": "E1C 2G7"
			},
			"geometry": {
				"type": "Point",
				"coordinates": [
					-64.78624,
					46.09473
				]
			},
			"bbox": [
				-64.7878611,
				46.0936058,
				-64.7846189,
				46.0958542
			]
		}
	]
}
