{
	"type": "FeatureCollection",
	"features": [
		{
			"type": "Feature",
			"properties": {
				"confidence": 9,
				"authenticationResultCode": "ValidCredentials",
				"brandLogoUri": "http://dev.virtualearth.net/Branding/logo_powered_by.png",
				"copyright": "Copyright © 2017 Microsoft and its suppliers. All rights reserved. This API cannot be accessed and the content and any results may not be used, reproduced or transmitted in any manner without express written permission from Microsoft Corporation.",
				"entityType": "Address",
				"matchCodes": [
					"Good"
				],
				"name": "90 Patti McCulloch Way, Newmarket, ON L3X 3G2, Canada",
				"statusCode": 200,
				"statusDescription": "OK",
				"traceId": "6559722a18344de891c3c5c7bcd8ea48|BN20200239|7.7.0.0|",
				"addressLine": "90 Patti McCulloch Way",
				"adminDistrict": "ON",
				"adminDistrict2": "York",
				"countryRegion": "Canada",
				"formattedAddress": "90 Patti McCulloch Way, Newmarket, ON L3X 3G2, Canada",
				"locality": "Newmarket",
				"postalCode": "L3X 3G2"
			},
			"geometry": {
				"type": "Point",
				"coordinates": [
					-79.50118,
					44.05561
				]
			},
			"bbox": [
				-79.5027442,
				44.0544858,
				-79.4996158,
				44.0567342
			]
		}
	]
}
