{
	"type": "FeatureCollection",
	"features": [
		{
			"type": "Feature",
			"properties": {
				"confidence": 9,
				"authenticationResultCode": "ValidCredentials",
				"brandLogoUri": "http://dev.virtualearth.net/Branding/logo_powered_by.png",
				"copyright": "Copyright © 2017 Microsoft and its suppliers. All rights reserved. This API cannot be accessed and the content and any results may not be used, reproduced or transmitted in any manner without express written permission from Microsoft Corporation.",
				"entityType": "Address",
				"matchCodes": [
					"Good"
				],
				"name": "900 Major Bennett Dr, Peterborough, ON K9J 6X6, Canada",
				"statusCode": 200,
				"statusDescription": "OK",
				"traceId": "11febbebc92a4885896a90535cdb703f|BN20121762|7.7.0.0|",
				"addressLine": "900 Major Bennett Dr",
				"adminDistrict": "ON",
				"adminDistrict2": "Peterborough",
				"countryRegion": "Canada",
				"formattedAddress": "900 Major Bennett Dr, Peterborough, ON K9J 6X6, Canada",
				"locality": "Peterborough",
				"postalCode": "K9J 6X6"
			},
			"geometry": {
				"type": "Point",
				"coordinates": [
					-78.35543,
					44.25922
				]
			},
			"bbox": [
				-78.3569996,
				44.2580958,
				-78.3538604,
				44.2603442
			]
		}
	]
}
