{
	"type": "FeatureCollection",
	"features": [
		{
			"type": "Feature",
			"properties": {
				"confidence": 9,
				"authenticationResultCode": "ValidCredentials",
				"brandLogoUri": "http://dev.virtualearth.net/Branding/logo_powered_by.png",
				"copyright": "Copyright © 2017 Microsoft and its suppliers. All rights reserved. This API cannot be accessed and the content and any results may not be used, reproduced or transmitted in any manner without express written permission from Microsoft Corporation.",
				"entityType": "Address",
				"matchCodes": [
					"Good"
				],
				"name": "9000 Boulevard Industriel, Chambly, QC J3L 4X3, Canada",
				"statusCode": 200,
				"statusDescription": "OK",
				"traceId": "9f70742d6b0a47b1805b85543158f54a|BN20130521|7.7.0.0|",
				"addressLine": "9000 Boulevard Industriel",
				"adminDistrict": "QC",
				"adminDistrict2": "La Vallée-du-Richelieu",
				"countryRegion": "Canada",
				"formattedAddress": "9000 Boulevard Industriel, Chambly, QC J3L 4X3, Canada",
				"locality": "Chambly",
				"postalCode": "J3L 4X3"
			},
			"geometry": {
				"type": "Point",
				"coordinates": [
					-73.28313,
					45.41183
				]
			},
			"bbox": [
				-73.2847313,
				45.4107058,
				-73.2815287,
				45.4129542
			]
		}
	]
}
