{
	"type": "FeatureCollection",
	"features": [
		{
			"type": "Feature",
			"properties": {
				"confidence": 7,
				"authenticationResultCode": "ValidCredentials",
				"brandLogoUri": "http://dev.virtualearth.net/Branding/logo_powered_by.png",
				"copyright": "Copyright © 2017 Microsoft and its suppliers. All rights reserved. This API cannot be accessed and the content and any results may not be used, reproduced or transmitted in any manner without express written permission from Microsoft Corporation.",
				"entityType": "Postcode1",
				"matchCodes": [
					"UpHierarchy"
				],
				"name": "Melfort, S0E 1A0, Canada",
				"statusCode": 200,
				"statusDescription": "OK",
				"traceId": "bbdaa2f890434bbcb9bc894639a4178f|BN20130719|7.7.0.0|",
				"adminDistrict": "SK",
				"countryRegion": "Canada",
				"formattedAddress": "Melfort, S0E 1A0, Canada",
				"locality": "Melfort",
				"postalCode": "S0E 1A0"
			},
			"geometry": {
				"type": "Point",
				"coordinates": [
					-104.618728637695,
					52.8615417480469
				]
			},
			"bbox": [
				-104.627258475587,
				52.8576790304762,
				-104.610198799804,
				52.8654044656176
			]
		}
	]
}
