{
	"type": "FeatureCollection",
	"features": [
		{
			"type": "Feature",
			"properties": {
				"confidence": 9,
				"authenticationResultCode": "ValidCredentials",
				"brandLogoUri": "http://dev.virtualearth.net/Branding/logo_powered_by.png",
				"copyright": "Copyright © 2017 Microsoft and its suppliers. All rights reserved. This API cannot be accessed and the content and any results may not be used, reproduced or transmitted in any manner without express written permission from Microsoft Corporation.",
				"entityType": "Address",
				"matchCodes": [
					"Good"
				],
				"name": "901 Rue Dollard, Gatineau, QC J8L 3T4, Canada",
				"statusCode": 200,
				"statusDescription": "OK",
				"traceId": "1af4d2d9c5054670a462bd0748b40f63|BN20130521|7.7.0.0|",
				"addressLine": "901 Rue Dollard",
				"adminDistrict": "QC",
				"adminDistrict2": "Gatineau",
				"countryRegion": "Canada",
				"formattedAddress": "901 Rue Dollard, Gatineau, QC J8L 3T4, Canada",
				"locality": "Gatineau",
				"neighborhood": "Quartier de Masson-Angers",
				"postalCode": "J8L 3T4"
			},
			"geometry": {
				"type": "Point",
				"coordinates": [
					-75.40791,
					45.57855
				]
			},
			"bbox": [
				-75.4095161,
				45.5774258,
				-75.4063039,
				45.5796742
			]
		}
	]
}
