{
	"type": "FeatureCollection",
	"features": [
		{
			"type": "Feature",
			"properties": {
				"confidence": 9,
				"authenticationResultCode": "ValidCredentials",
				"brandLogoUri": "http://dev.virtualearth.net/Branding/logo_powered_by.png",
				"copyright": "Copyright © 2017 Microsoft and its suppliers. All rights reserved. This API cannot be accessed and the content and any results may not be used, reproduced or transmitted in any manner without express written permission from Microsoft Corporation.",
				"entityType": "Address",
				"matchCodes": [
					"Good"
				],
				"name": "9044 18 St NW, Strathcona County, AB T8A, Canada",
				"statusCode": 200,
				"statusDescription": "OK",
				"traceId": "9a1534e6b47640de9cd088818c34dd33|BN20121764|7.7.0.0|",
				"addressLine": "9044 18 St NW",
				"adminDistrict": "AB",
				"adminDistrict2": "Alberta",
				"countryRegion": "Canada",
				"formattedAddress": "9044 18 St NW, Strathcona County, AB T8A, Canada",
				"locality": "Strathcona County",
				"neighborhood": "Sherwood Park",
				"postalCode": "T8A"
			},
			"geometry": {
				"type": "Point",
				"coordinates": [
					-113.37115,
					53.52386
				]
			},
			"bbox": [
				-113.373041,
				53.5227358,
				-113.369259,
				53.5249842
			]
		}
	]
}
