{
	"type": "FeatureCollection",
	"features": [
		{
			"type": "Feature",
			"properties": {
				"confidence": 9,
				"authenticationResultCode": "ValidCredentials",
				"brandLogoUri": "http://dev.virtualearth.net/Branding/logo_powered_by.png",
				"copyright": "Copyright © 2017 Microsoft and its suppliers. All rights reserved. This API cannot be accessed and the content and any results may not be used, reproduced or transmitted in any manner without express written permission from Microsoft Corporation.",
				"entityType": "Address",
				"matchCodes": [
					"Good"
				],
				"name": "909 17 Ave SW, Calgary, AB T2T 0A4, Canada",
				"statusCode": 200,
				"statusDescription": "OK",
				"traceId": "8b61f0143b2e4e7c827ce3ea3b4515df|BN20250135|7.7.0.0|",
				"addressLine": "909 17 Ave SW",
				"adminDistrict": "AB",
				"adminDistrict2": "Alberta",
				"countryRegion": "Canada",
				"formattedAddress": "909 17 Ave SW, Calgary, AB T2T 0A4, Canada",
				"locality": "Calgary",
				"neighborhood": "Mont Royal",
				"postalCode": "T2T 0A4"
			},
			"geometry": {
				"type": "Point",
				"coordinates": [
					-114.08267,
					51.03756
				]
			},
			"bbox": [
				-114.0844577,
				51.0364358,
				-114.0808823,
				51.0386842
			]
		}
	]
}
