{
	"type": "FeatureCollection",
	"features": [
		{
			"type": "Feature",
			"properties": {
				"confidence": 9,
				"authenticationResultCode": "ValidCredentials",
				"brandLogoUri": "http://dev.virtualearth.net/Branding/logo_powered_by.png",
				"copyright": "Copyright © 2017 Microsoft and its suppliers. All rights reserved. This API cannot be accessed and the content and any results may not be used, reproduced or transmitted in any manner without express written permission from Microsoft Corporation.",
				"entityType": "Address",
				"matchCodes": [
					"Good"
				],
				"name": "91 Conair Pkwy, Woodbridge, ON L4H 0S4, Canada",
				"statusCode": 200,
				"statusDescription": "OK",
				"traceId": "d67fbf87718940bd8b0917987317f2a3|BN20130625|7.7.0.0|",
				"addressLine": "91 Conair Pkwy",
				"adminDistrict": "ON",
				"adminDistrict2": "York",
				"countryRegion": "Canada",
				"formattedAddress": "91 Conair Pkwy, Woodbridge, ON L4H 0S4, Canada",
				"locality": "Vaughan",
				"neighborhood": "Woodbridge",
				"postalCode": "L4H 0S4"
			},
			"geometry": {
				"type": "Point",
				"coordinates": [
					-79.64312,
					43.77713
				]
			},
			"bbox": [
				-79.6446769,
				43.7760058,
				-79.6415631,
				43.7782542
			]
		}
	]
}
