{
	"type": "FeatureCollection",
	"features": [
		{
			"type": "Feature",
			"properties": {
				"confidence": 9,
				"authenticationResultCode": "ValidCredentials",
				"brandLogoUri": "http://dev.virtualearth.net/Branding/logo_powered_by.png",
				"copyright": "Copyright © 2017 Microsoft and its suppliers. All rights reserved. This API cannot be accessed and the content and any results may not be used, reproduced or transmitted in any manner without express written permission from Microsoft Corporation.",
				"entityType": "Address",
				"matchCodes": [
					"Good"
				],
				"name": "91 Fulton St, Winnipeg, MB R2N 4C1, Canada",
				"statusCode": 200,
				"statusDescription": "OK",
				"traceId": "2c464b14b91b482ca4c5c3914114d9f1|BN20320521|7.7.0.0|",
				"addressLine": "91 Fulton St",
				"adminDistrict": "MB",
				"adminDistrict2": "Manitoba",
				"countryRegion": "Canada",
				"formattedAddress": "91 Fulton St, Winnipeg, MB R2N 4C1, Canada",
				"locality": "Winnipeg",
				"neighborhood": "Dakota Crossing",
				"postalCode": "R2N 4C1"
			},
			"geometry": {
				"type": "Point",
				"coordinates": [
					-97.07972,
					49.81395
				]
			},
			"bbox": [
				-97.0814621,
				49.8128258,
				-97.0779779,
				49.8150742
			]
		}
	]
}
