{
	"type": "FeatureCollection",
	"features": [
		{
			"type": "Feature",
			"properties": {
				"confidence": 9,
				"authenticationResultCode": "ValidCredentials",
				"brandLogoUri": "http://dev.virtualearth.net/Branding/logo_powered_by.png",
				"copyright": "Copyright © 2017 Microsoft and its suppliers. All rights reserved. This API cannot be accessed and the content and any results may not be used, reproduced or transmitted in any manner without express written permission from Microsoft Corporation.",
				"entityType": "Address",
				"matchCodes": [
					"Good"
				],
				"name": "91 Lincoln St, Tillsonburg, ON N4G 2P9, Canada",
				"statusCode": 200,
				"statusDescription": "OK",
				"traceId": "5850149798a6414f8e7ddac3f68661c7|BN20280152|7.7.0.0|",
				"addressLine": "91 Lincoln St",
				"adminDistrict": "ON",
				"adminDistrict2": "Oxford",
				"countryRegion": "Canada",
				"formattedAddress": "91 Lincoln St, Tillsonburg, ON N4G 2P9, Canada",
				"locality": "Tillsonburg",
				"postalCode": "N4G 2P9"
			},
			"geometry": {
				"type": "Point",
				"coordinates": [
					-80.71627,
					42.85418
				]
			},
			"bbox": [
				-80.7178034,
				42.8530558,
				-80.7147366,
				42.8553042
			]
		}
	]
}
