{
	"type": "FeatureCollection",
	"features": [
		{
			"type": "Feature",
			"properties": {
				"confidence": 9,
				"authenticationResultCode": "ValidCredentials",
				"brandLogoUri": "http://dev.virtualearth.net/Branding/logo_powered_by.png",
				"copyright": "Copyright © 2017 Microsoft and its suppliers. All rights reserved. This API cannot be accessed and the content and any results may not be used, reproduced or transmitted in any manner without express written permission from Microsoft Corporation.",
				"entityType": "Address",
				"matchCodes": [
					"Good"
				],
				"name": "914 Dupont St, Toronto, ON M6H 1Z2, Canada",
				"statusCode": 200,
				"statusDescription": "OK",
				"traceId": "d446b13965f34de2afe5229697160797|BN20130625|7.7.0.0|",
				"addressLine": "914 Dupont St",
				"adminDistrict": "ON",
				"adminDistrict2": "Toronto",
				"countryRegion": "Canada",
				"formattedAddress": "914 Dupont St, Toronto, ON M6H 1Z2, Canada",
				"locality": "Toronto",
				"neighborhood": "Dovercourt-Wallace Emerson-Junction",
				"postalCode": "M6H 1Z2"
			},
			"geometry": {
				"type": "Point",
				"coordinates": [
					-79.43019,
					43.67033
				]
			},
			"bbox": [
				-79.4317441,
				43.6692058,
				-79.4286359,
				43.6714542
			]
		}
	]
}
