{
	"type": "FeatureCollection",
	"features": [
		{
			"type": "Feature",
			"properties": {
				"confidence": 9,
				"authenticationResultCode": "ValidCredentials",
				"brandLogoUri": "http://dev.virtualearth.net/Branding/logo_powered_by.png",
				"copyright": "Copyright © 2017 Microsoft and its suppliers. All rights reserved. This API cannot be accessed and the content and any results may not be used, reproduced or transmitted in any manner without express written permission from Microsoft Corporation.",
				"entityType": "Address",
				"matchCodes": [
					"Good"
				],
				"name": "92 Colesbrook Rd, Richmond Hill, ON L4S 2G5, Canada",
				"statusCode": 200,
				"statusDescription": "OK",
				"traceId": "78639e04673c4439b1fcf44e3ff5024a|BN20300154|7.7.0.0|",
				"addressLine": "92 Colesbrook Rd",
				"adminDistrict": "ON",
				"adminDistrict2": "York",
				"countryRegion": "Canada",
				"formattedAddress": "92 Colesbrook Rd, Richmond Hill, ON L4S 2G5, Canada",
				"locality": "Richmond Hill",
				"postalCode": "L4S 2G5"
			},
			"geometry": {
				"type": "Point",
				"coordinates": [
					-79.46292,
					43.90076
				]
			},
			"bbox": [
				-79.4644801,
				43.8996358,
				-79.4613599,
				43.9018842
			]
		}
	]
}
