{
	"type": "FeatureCollection",
	"features": [
		{
			"type": "Feature",
			"properties": {
				"confidence": 9,
				"authenticationResultCode": "ValidCredentials",
				"brandLogoUri": "http://dev.virtualearth.net/Branding/logo_powered_by.png",
				"copyright": "Copyright © 2017 Microsoft and its suppliers. All rights reserved. This API cannot be accessed and the content and any results may not be used, reproduced or transmitted in any manner without express written permission from Microsoft Corporation.",
				"entityType": "Address",
				"matchCodes": [
					"Good"
				],
				"name": "92 Lakeshore Rd E, Mississauga, ON L5G 4S2, Canada",
				"statusCode": 200,
				"statusDescription": "OK",
				"traceId": "87ce7bb20f704337b552b411895833e0|BN20130530|7.7.0.0|",
				"addressLine": "92 Lakeshore Rd E",
				"adminDistrict": "ON",
				"adminDistrict2": "Peel",
				"countryRegion": "Canada",
				"formattedAddress": "92 Lakeshore Rd E, Mississauga, ON L5G 4S2, Canada",
				"locality": "Mississauga",
				"neighborhood": "Port Credit",
				"postalCode": "L5G 4S2"
			},
			"geometry": {
				"type": "Point",
				"coordinates": [
					-79.58432,
					43.55339
				]
			},
			"bbox": [
				-79.5858711,
				43.5522658,
				-79.5827689,
				43.5545142
			]
		}
	]
}
