{
	"type": "FeatureCollection",
	"features": [
		{
			"type": "Feature",
			"properties": {
				"confidence": 9,
				"authenticationResultCode": "ValidCredentials",
				"brandLogoUri": "http://dev.virtualearth.net/Branding/logo_powered_by.png",
				"copyright": "Copyright © 2017 Microsoft and its suppliers. All rights reserved. This API cannot be accessed and the content and any results may not be used, reproduced or transmitted in any manner without express written permission from Microsoft Corporation.",
				"entityType": "Address",
				"matchCodes": [
					"Good"
				],
				"name": "9215 118 St, Delta, BC V4C 6J3, Canada",
				"statusCode": 200,
				"statusDescription": "OK",
				"traceId": "2b16e93b4e98465aa4fb236466ccb667|BN20160335|7.7.0.0|",
				"addressLine": "9215 118 St",
				"adminDistrict": "BC",
				"adminDistrict2": "Greater Vancouver",
				"countryRegion": "Canada",
				"formattedAddress": "9215 118 St, Delta, BC V4C 6J3, Canada",
				"locality": "Delta",
				"postalCode": "V4C 6J3"
			},
			"geometry": {
				"type": "Point",
				"coordinates": [
					-122.8958714,
					49.170868
				]
			},
			"bbox": [
				-122.8975908,
				49.1697439,
				-122.894152,
				49.1719922
			]
		}
	]
}
