{
	"type": "FeatureCollection",
	"features": [
		{
			"type": "Feature",
			"properties": {
				"confidence": 9,
				"authenticationResultCode": "ValidCredentials",
				"brandLogoUri": "http://dev.virtualearth.net/Branding/logo_powered_by.png",
				"copyright": "Copyright © 2017 Microsoft and its suppliers. All rights reserved. This API cannot be accessed and the content and any results may not be used, reproduced or transmitted in any manner without express written permission from Microsoft Corporation.",
				"entityType": "Address",
				"matchCodes": [
					"Good"
				],
				"name": "9230 Islington Ave, Woodbridge, ON L4L 1A6, Canada",
				"statusCode": 200,
				"statusDescription": "OK",
				"traceId": "aa3bc27507084f5886c877bcebb3260f|BN20130621|7.7.0.0|",
				"addressLine": "9230 Islington Ave",
				"adminDistrict": "ON",
				"adminDistrict2": "York",
				"countryRegion": "Canada",
				"formattedAddress": "9230 Islington Ave, Woodbridge, ON L4L 1A6, Canada",
				"locality": "Vaughan",
				"neighborhood": "Woodbridge",
				"postalCode": "L4L 1A6"
			},
			"geometry": {
				"type": "Point",
				"coordinates": [
					-79.60002,
					43.81581
				]
			},
			"bbox": [
				-79.6015779,
				43.8146858,
				-79.5984621,
				43.8169342
			]
		}
	]
}
