{
	"type": "FeatureCollection",
	"features": [
		{
			"type": "Feature",
			"properties": {
				"confidence": 9,
				"authenticationResultCode": "ValidCredentials",
				"brandLogoUri": "http://dev.virtualearth.net/Branding/logo_powered_by.png",
				"copyright": "Copyright © 2017 Microsoft and its suppliers. All rights reserved. This API cannot be accessed and the content and any results may not be used, reproduced or transmitted in any manner without express written permission from Microsoft Corporation.",
				"entityType": "Address",
				"matchCodes": [
					"Good"
				],
				"name": "93 Else St, St Catharines, ON L2N 2C4, Canada",
				"statusCode": 200,
				"statusDescription": "OK",
				"traceId": "2805fbd79993433891e284a90fcf0a22|BN20130520|7.7.0.0|",
				"addressLine": "93 Else St",
				"adminDistrict": "ON",
				"adminDistrict2": "Niagara",
				"countryRegion": "Canada",
				"formattedAddress": "93 Else St, St Catharines, ON L2N 2C4, Canada",
				"locality": "St Catharines",
				"neighborhood": "Grantham",
				"postalCode": "L2N 2C4"
			},
			"geometry": {
				"type": "Point",
				"coordinates": [
					-79.23954,
					43.19341
				]
			},
			"bbox": [
				-79.2410819,
				43.1922858,
				-79.2379981,
				43.1945342
			]
		}
	]
}
