{
	"type": "FeatureCollection",
	"features": [
		{
			"type": "Feature",
			"properties": {
				"confidence": 9,
				"authenticationResultCode": "ValidCredentials",
				"brandLogoUri": "http://dev.virtualearth.net/Branding/logo_powered_by.png",
				"copyright": "Copyright © 2017 Microsoft and its suppliers. All rights reserved. This API cannot be accessed and the content and any results may not be used, reproduced or transmitted in any manner without express written permission from Microsoft Corporation.",
				"entityType": "Address",
				"matchCodes": [
					"Good"
				],
				"name": "9309 179 Ave NW, Edmonton, AB T5Z 2H7, Canada",
				"statusCode": 200,
				"statusDescription": "OK",
				"traceId": "e2b0c5fc91e34dc183d0be57205812f9|BN20130530|7.7.0.0|",
				"addressLine": "9309 179 Ave NW",
				"adminDistrict": "AB",
				"adminDistrict2": "Alberta",
				"countryRegion": "Canada",
				"formattedAddress": "9309 179 Ave NW, Edmonton, AB T5Z 2H7, Canada",
				"locality": "Edmonton",
				"neighborhood": "Lago Lindo",
				"postalCode": "T5Z 2H7"
			},
			"geometry": {
				"type": "Point",
				"coordinates": [
					-113.48553,
					53.64162
				]
			},
			"bbox": [
				-113.4874262,
				53.6404958,
				-113.4836338,
				53.6427442
			]
		}
	]
}
