{
	"type": "FeatureCollection",
	"features": [
		{
			"type": "Feature",
			"properties": {
				"confidence": 9,
				"authenticationResultCode": "ValidCredentials",
				"brandLogoUri": "http://dev.virtualearth.net/Branding/logo_powered_by.png",
				"copyright": "Copyright © 2017 Microsoft and its suppliers. All rights reserved. This API cannot be accessed and the content and any results may not be used, reproduced or transmitted in any manner without express written permission from Microsoft Corporation.",
				"entityType": "Address",
				"matchCodes": [
					"Good"
				],
				"name": "931 Leathorne St, London, ON N5Z 3M7, Canada",
				"statusCode": 200,
				"statusDescription": "OK",
				"traceId": "b9057234b6524fc7b4d07802f4e128e7|CO30275838|7.7.0.0|",
				"addressLine": "931 Leathorne St",
				"adminDistrict": "ON",
				"adminDistrict2": "Middlesex",
				"countryRegion": "Canada",
				"formattedAddress": "931 Leathorne St, London, ON N5Z 3M7, Canada",
				"locality": "London",
				"neighborhood": "Glen Cairn",
				"postalCode": "N5Z 3M7"
			},
			"geometry": {
				"type": "Point",
				"coordinates": [
					-81.2153,
					42.9617999
				]
			},
			"bbox": [
				-81.2168361,
				42.9606757,
				-81.2137639,
				42.9629241
			]
		}
	]
}
