{
	"type": "FeatureCollection",
	"features": [
		{
			"type": "Feature",
			"properties": {
				"confidence": 9,
				"authenticationResultCode": "ValidCredentials",
				"brandLogoUri": "http://dev.virtualearth.net/Branding/logo_powered_by.png",
				"copyright": "Copyright © 2017 Microsoft and its suppliers. All rights reserved. This API cannot be accessed and the content and any results may not be used, reproduced or transmitted in any manner without express written permission from Microsoft Corporation.",
				"entityType": "Address",
				"matchCodes": [
					"Good"
				],
				"name": "9329 62 Ave NW, Edmonton, AB T6E 0E1, Canada",
				"statusCode": 200,
				"statusDescription": "OK",
				"traceId": "e01bf193582f419b94200563bfa33076|BN20300154|7.7.0.0|",
				"addressLine": "9329 62 Ave NW",
				"adminDistrict": "AB",
				"adminDistrict2": "Alberta",
				"countryRegion": "Canada",
				"formattedAddress": "9329 62 Ave NW, Edmonton, AB T6E 0E1, Canada",
				"locality": "Edmonton",
				"neighborhood": "Rosedale Industrial",
				"postalCode": "T6E 0E1"
			},
			"geometry": {
				"type": "Point",
				"coordinates": [
					-113.47168,
					53.49768
				]
			},
			"bbox": [
				-113.4735698,
				53.4965558,
				-113.4697902,
				53.4988042
			]
		}
	]
}
