{
	"type": "FeatureCollection",
	"features": [
		{
			"type": "Feature",
			"properties": {
				"confidence": 9,
				"authenticationResultCode": "ValidCredentials",
				"brandLogoUri": "http://dev.virtualearth.net/Branding/logo_powered_by.png",
				"copyright": "Copyright © 2017 Microsoft and its suppliers. All rights reserved. This API cannot be accessed and the content and any results may not be used, reproduced or transmitted in any manner without express written permission from Microsoft Corporation.",
				"entityType": "Address",
				"matchCodes": [
					"Good"
				],
				"name": "9356 Army Camp Rd, Lambton Shores, ON N0N 1J3, Canada",
				"statusCode": 200,
				"statusDescription": "OK",
				"traceId": "25e4d498033b421381223b74aee5bd95|BN20130719|7.7.0.0|",
				"addressLine": "9356 Army Camp Rd",
				"adminDistrict": "ON",
				"adminDistrict2": "Lambton",
				"countryRegion": "Canada",
				"formattedAddress": "9356 Army Camp Rd, Lambton Shores, ON N0N 1J3, Canada",
				"locality": "Lambton Shores",
				"postalCode": "N0N 1J3"
			},
			"geometry": {
				"type": "Point",
				"coordinates": [
					-81.94071,
					43.19059
				]
			},
			"bbox": [
				-81.9422519,
				43.1894658,
				-81.9391681,
				43.1917142
			]
		}
	]
}
