{
	"type": "FeatureCollection",
	"features": [
		{
			"type": "Feature",
			"properties": {
				"confidence": 9,
				"authenticationResultCode": "ValidCredentials",
				"brandLogoUri": "http://dev.virtualearth.net/Branding/logo_powered_by.png",
				"copyright": "Copyright © 2017 Microsoft and its suppliers. All rights reserved. This API cannot be accessed and the content and any results may not be used, reproduced or transmitted in any manner without express written permission from Microsoft Corporation.",
				"entityType": "Address",
				"matchCodes": [
					"Good"
				],
				"name": "936081 Airport Rd, Mulmur, ON L9V 0L3, Canada",
				"statusCode": 200,
				"statusDescription": "OK",
				"traceId": "40f416349ca2438aa13b5b6ed082acdf|BN20220145|7.7.0.0|",
				"addressLine": "936081 Airport Rd",
				"adminDistrict": "ON",
				"adminDistrict2": "Dufferin",
				"countryRegion": "Canada",
				"formattedAddress": "936081 Airport Rd, Mulmur, ON L9V 0L3, Canada",
				"locality": "Mulmur",
				"postalCode": "L9V 0L3"
			},
			"geometry": {
				"type": "Point",
				"coordinates": [
					-80.0267748,
					44.1226134
				]
			},
			"bbox": [
				-80.0283408,
				44.1214893,
				-80.0252088,
				44.1237376
			]
		}
	]
}
