{
	"type": "FeatureCollection",
	"features": [
		{
			"type": "Feature",
			"properties": {
				"confidence": 9,
				"authenticationResultCode": "ValidCredentials",
				"brandLogoUri": "http://dev.virtualearth.net/Branding/logo_powered_by.png",
				"copyright": "Copyright © 2017 Microsoft and its suppliers. All rights reserved. This API cannot be accessed and the content and any results may not be used, reproduced or transmitted in any manner without express written permission from Microsoft Corporation.",
				"entityType": "Address",
				"matchCodes": [
					"Good"
				],
				"name": "937 E Main St, Welland, ON L3B 3Z1, Canada",
				"statusCode": 200,
				"statusDescription": "OK",
				"traceId": "2166df6676454e5c9aaedfe5e7f53e2e|BN20260231|7.7.0.0|",
				"addressLine": "937 E Main St",
				"adminDistrict": "ON",
				"adminDistrict2": "Niagara",
				"countryRegion": "Canada",
				"formattedAddress": "937 E Main St, Welland, ON L3B 3Z1, Canada",
				"locality": "Welland",
				"postalCode": "L3B 3Z1"
			},
			"geometry": {
				"type": "Point",
				"coordinates": [
					-79.22903,
					42.99321
				]
			},
			"bbox": [
				-79.2305669,
				42.9920858,
				-79.2274931,
				42.9943342
			]
		}
	]
}
