{
	"type": "FeatureCollection",
	"features": [
		{
			"type": "Feature",
			"properties": {
				"confidence": 9,
				"authenticationResultCode": "ValidCredentials",
				"brandLogoUri": "http://dev.virtualearth.net/Branding/logo_powered_by.png",
				"copyright": "Copyright © 2017 Microsoft and its suppliers. All rights reserved. This API cannot be accessed and the content and any results may not be used, reproduced or transmitted in any manner without express written permission from Microsoft Corporation.",
				"entityType": "Address",
				"matchCodes": [
					"Good"
				],
				"name": "9384 Smiley Rd, Chemainus, BC V0R 1K4, Canada",
				"statusCode": 200,
				"statusDescription": "OK",
				"traceId": "052a87c6760f4c5fbf6ed620d8d6f5a8|BN20130431|7.7.0.0|",
				"addressLine": "9384 Smiley Rd",
				"adminDistrict": "BC",
				"adminDistrict2": "Cowichan Valley",
				"countryRegion": "Canada",
				"formattedAddress": "9384 Smiley Rd, Chemainus, BC V0R 1K4, Canada",
				"locality": "North Cowichan",
				"neighborhood": "Chemainus",
				"postalCode": "V0R 1K4"
			},
			"geometry": {
				"type": "Point",
				"coordinates": [
					-123.73367,
					48.90827
				]
			},
			"bbox": [
				-123.7353803,
				48.9071458,
				-123.7319597,
				48.9093942
			]
		}
	]
}
