{
	"type": "FeatureCollection",
	"features": [
		{
			"type": "Feature",
			"properties": {
				"confidence": 9,
				"authenticationResultCode": "ValidCredentials",
				"brandLogoUri": "http://dev.virtualearth.net/Branding/logo_powered_by.png",
				"copyright": "Copyright © 2017 Microsoft and its suppliers. All rights reserved. This API cannot be accessed and the content and any results may not be used, reproduced or transmitted in any manner without express written permission from Microsoft Corporation.",
				"entityType": "Address",
				"matchCodes": [
					"Good"
				],
				"name": "939 The Queensway, Etobicoke, ON M8Z 1P3, Canada",
				"statusCode": 200,
				"statusDescription": "OK",
				"traceId": "5e81fb23a44e4970ac8864a2700f64b6|BN20130625|7.7.0.0|",
				"addressLine": "939 The Queensway",
				"adminDistrict": "ON",
				"adminDistrict2": "Toronto",
				"countryRegion": "Canada",
				"formattedAddress": "939 The Queensway, Etobicoke, ON M8Z 1P3, Canada",
				"locality": "Toronto",
				"neighborhood": "Stonegate-Queensway",
				"postalCode": "M8Z 1P3"
			},
			"geometry": {
				"type": "Point",
				"coordinates": [
					-79.5125599,
					43.62386
				]
			},
			"bbox": [
				-79.5141128,
				43.6227358,
				-79.511007,
				43.6249842
			]
		}
	]
}
