{
	"type": "FeatureCollection",
	"features": [
		{
			"type": "Feature",
			"properties": {
				"confidence": 9,
				"authenticationResultCode": "ValidCredentials",
				"brandLogoUri": "http://dev.virtualearth.net/Branding/logo_powered_by.png",
				"copyright": "Copyright © 2017 Microsoft and its suppliers. All rights reserved. This API cannot be accessed and the content and any results may not be used, reproduced or transmitted in any manner without express written permission from Microsoft Corporation.",
				"entityType": "Address",
				"matchCodes": [
					"Good"
				],
				"name": "940 Warden Ave, Scarborough, ON M1L 4C9, Canada",
				"statusCode": 200,
				"statusDescription": "OK",
				"traceId": "642803548e25445b93868145ecb37fa6|BN20200137|7.7.0.0|",
				"addressLine": "940 Warden Ave",
				"adminDistrict": "ON",
				"adminDistrict2": "Toronto",
				"countryRegion": "Canada",
				"formattedAddress": "940 Warden Ave, Scarborough, ON M1L 4C9, Canada",
				"locality": "Toronto",
				"neighborhood": "Wexford-Maryvale",
				"postalCode": "M1L 4C9"
			},
			"geometry": {
				"type": "Point",
				"coordinates": [
					-79.29009,
					43.73203
				]
			},
			"bbox": [
				-79.2916457,
				43.7309058,
				-79.2885343,
				43.7331542
			]
		}
	]
}
