{
	"type": "FeatureCollection",
	"features": [
		{
			"type": "Feature",
			"properties": {
				"confidence": 9,
				"authenticationResultCode": "ValidCredentials",
				"brandLogoUri": "http://dev.virtualearth.net/Branding/logo_powered_by.png",
				"copyright": "Copyright © 2017 Microsoft and its suppliers. All rights reserved. This API cannot be accessed and the content and any results may not be used, reproduced or transmitted in any manner without express written permission from Microsoft Corporation.",
				"entityType": "Address",
				"matchCodes": [
					"Good"
				],
				"name": "943 Marine Dr, North Vancouver, BC V7P 1S1, Canada",
				"statusCode": 200,
				"statusDescription": "OK",
				"traceId": "d88e26e23b3945288caad4573329e3d3|BN20290118|7.7.0.0|",
				"addressLine": "943 Marine Dr",
				"adminDistrict": "BC",
				"adminDistrict2": "Greater Vancouver",
				"countryRegion": "Canada",
				"formattedAddress": "943 Marine Dr, North Vancouver, BC V7P 1S1, Canada",
				"locality": "North Vancouver",
				"postalCode": "V7P 1S1"
			},
			"geometry": {
				"type": "Point",
				"coordinates": [
					-123.0996205,
					49.3227992
				]
			},
			"bbox": [
				-123.1013452,
				49.321675,
				-123.0978958,
				49.3239234
			]
		}
	]
}
