{
	"type": "FeatureCollection",
	"features": [
		{
			"type": "Feature",
			"properties": {
				"confidence": 9,
				"authenticationResultCode": "ValidCredentials",
				"brandLogoUri": "http://dev.virtualearth.net/Branding/logo_powered_by.png",
				"copyright": "Copyright © 2017 Microsoft and its suppliers. All rights reserved. This API cannot be accessed and the content and any results may not be used, reproduced or transmitted in any manner without express written permission from Microsoft Corporation.",
				"entityType": "Address",
				"matchCodes": [
					"Good"
				],
				"name": "945 McMaster Way, Kamloops, BC V2C 6K2, Canada",
				"statusCode": 200,
				"statusDescription": "OK",
				"traceId": "0090eadab0b44c38935d69613f7e7b8e|BN20130533|7.7.0.0|",
				"addressLine": "945 McMaster Way",
				"adminDistrict": "BC",
				"adminDistrict2": "Thompson-Nicola",
				"countryRegion": "Canada",
				"formattedAddress": "945 McMaster Way, Kamloops, BC V2C 6K2, Canada",
				"locality": "Kamloops",
				"neighborhood": "Southgate",
				"postalCode": "V2C 6K2"
			},
			"geometry": {
				"type": "Point",
				"coordinates": [
					-120.37584,
					50.67093
				]
			},
			"bbox": [
				-120.3776137,
				50.6698058,
				-120.3740663,
				50.6720542
			]
		}
	]
}
