{
	"type": "FeatureCollection",
	"features": [
		{
			"type": "Feature",
			"properties": {
				"confidence": 9,
				"authenticationResultCode": "ValidCredentials",
				"brandLogoUri": "http://dev.virtualearth.net/Branding/logo_powered_by.png",
				"copyright": "Copyright © 2017 Microsoft and its suppliers. All rights reserved. This API cannot be accessed and the content and any results may not be used, reproduced or transmitted in any manner without express written permission from Microsoft Corporation.",
				"entityType": "Address",
				"matchCodes": [
					"Good"
				],
				"name": "9522 97 St, Grande Prairie, AB T8V 0R8, Canada",
				"statusCode": 200,
				"statusDescription": "OK",
				"traceId": "9f15a80911b549609345e6e5c04ac56d|BN20190653|7.7.0.0|",
				"addressLine": "9522 97 St",
				"adminDistrict": "AB",
				"adminDistrict2": "Alberta",
				"countryRegion": "Canada",
				"formattedAddress": "9522 97 St, Grande Prairie, AB T8V 0R8, Canada",
				"locality": "Grande Prairie",
				"neighborhood": "Railway Industrial",
				"postalCode": "T8V 0R8"
			},
			"geometry": {
				"type": "Point",
				"coordinates": [
					-118.7855188,
					55.1685173
				]
			},
			"bbox": [
				-118.7874869,
				55.1673931,
				-118.7835506,
				55.1696414
			]
		}
	]
}
