{
	"type": "FeatureCollection",
	"features": [
		{
			"type": "Feature",
			"properties": {
				"confidence": 9,
				"authenticationResultCode": "ValidCredentials",
				"brandLogoUri": "http://dev.virtualearth.net/Branding/logo_powered_by.png",
				"copyright": "Copyright © 2017 Microsoft and its suppliers. All rights reserved. This API cannot be accessed and the content and any results may not be used, reproduced or transmitted in any manner without express written permission from Microsoft Corporation.",
				"entityType": "Address",
				"matchCodes": [
					"Good"
				],
				"name": "955 Expo Blvd, Vancouver, BC V6Z 3G8, Canada",
				"statusCode": 200,
				"statusDescription": "OK",
				"traceId": "233434349acf472389afa8fa369603cb|BN20240253|7.7.0.0|",
				"addressLine": "955 Expo Blvd",
				"adminDistrict": "BC",
				"adminDistrict2": "Greater Vancouver",
				"countryRegion": "Canada",
				"formattedAddress": "955 Expo Blvd, Vancouver, BC V6Z 3G8, Canada",
				"locality": "Vancouver",
				"neighborhood": "Downtown",
				"postalCode": "V6Z 3G8"
			},
			"geometry": {
				"type": "Point",
				"coordinates": [
					-123.1154768,
					49.2753892
				]
			},
			"bbox": [
				-123.1171999,
				49.2742651,
				-123.1137538,
				49.2765134
			]
		}
	]
}
