{
	"type": "FeatureCollection",
	"features": [
		{
			"type": "Feature",
			"properties": {
				"confidence": 9,
				"authenticationResultCode": "ValidCredentials",
				"brandLogoUri": "http://dev.virtualearth.net/Branding/logo_powered_by.png",
				"copyright": "Copyright © 2017 Microsoft and its suppliers. All rights reserved. This API cannot be accessed and the content and any results may not be used, reproduced or transmitted in any manner without express written permission from Microsoft Corporation.",
				"entityType": "Address",
				"matchCodes": [
					"Good"
				],
				"name": "959 Portage Ave, Winnipeg, MB R3G 0R2, Canada",
				"statusCode": 200,
				"statusDescription": "OK",
				"traceId": "40f35594ae0f4e43a64298085cce97bf|BN20130431|7.7.0.0|",
				"addressLine": "959 Portage Ave",
				"adminDistrict": "MB",
				"adminDistrict2": "Manitoba",
				"countryRegion": "Canada",
				"formattedAddress": "959 Portage Ave, Winnipeg, MB R3G 0R2, Canada",
				"locality": "Winnipeg",
				"neighborhood": "St Matthews",
				"postalCode": "R3G 0R2"
			},
			"geometry": {
				"type": "Point",
				"coordinates": [
					-97.17414,
					49.88506
				]
			},
			"bbox": [
				-97.1758847,
				49.8839358,
				-97.1723953,
				49.8861842
			]
		}
	]
}
