{
	"type": "FeatureCollection",
	"features": [
		{
			"type": "Feature",
			"properties": {
				"confidence": 9,
				"authenticationResultCode": "ValidCredentials",
				"brandLogoUri": "http://dev.virtualearth.net/Branding/logo_powered_by.png",
				"copyright": "Copyright © 2017 Microsoft and its suppliers. All rights reserved. This API cannot be accessed and the content and any results may not be used, reproduced or transmitted in any manner without express written permission from Microsoft Corporation.",
				"entityType": "Address",
				"matchCodes": [
					"Good"
				],
				"name": "962 Rue Paradis, Roberval, QC G8H 2K1, Canada",
				"statusCode": 200,
				"statusDescription": "OK",
				"traceId": "76d9e151c0354249b2c9227f975be689|BN20250135|7.7.0.0|",
				"addressLine": "962 Rue Paradis",
				"adminDistrict": "QC",
				"adminDistrict2": "Le Domaine-du-Roy",
				"countryRegion": "Canada",
				"formattedAddress": "962 Rue Paradis, Roberval, QC G8H 2K1, Canada",
				"locality": "Roberval",
				"postalCode": "G8H 2K1"
			},
			"geometry": {
				"type": "Point",
				"coordinates": [
					-72.22153,
					48.52131
				]
			},
			"bbox": [
				-72.2232272,
				48.5201858,
				-72.2198328,
				48.5224342
			]
		}
	]
}
