{
	"type": "FeatureCollection",
	"features": [
		{
			"type": "Feature",
			"properties": {
				"confidence": 9,
				"authenticationResultCode": "ValidCredentials",
				"brandLogoUri": "http://dev.virtualearth.net/Branding/logo_powered_by.png",
				"copyright": "Copyright © 2017 Microsoft and its suppliers. All rights reserved. This API cannot be accessed and the content and any results may not be used, reproduced or transmitted in any manner without express written permission from Microsoft Corporation.",
				"entityType": "Address",
				"matchCodes": [
					"Good"
				],
				"name": "9624 112 St, Grande Prairie, AB T8V 4E7, Canada",
				"statusCode": 200,
				"statusDescription": "OK",
				"traceId": "75daefcfe9f2497f9aa10242080cc475|BN20121764|7.7.0.0|",
				"addressLine": "9624 112 St",
				"adminDistrict": "AB",
				"adminDistrict2": "Alberta",
				"countryRegion": "Canada",
				"formattedAddress": "9624 112 St, Grande Prairie, AB T8V 4E7, Canada",
				"locality": "Grande Prairie",
				"neighborhood": "Richmond Industrial Park",
				"postalCode": "T8V 4E7"
			},
			"geometry": {
				"type": "Point",
				"coordinates": [
					-118.83355,
					55.1668
				]
			},
			"bbox": [
				-118.8355181,
				55.1656758,
				-118.8315819,
				55.1679242
			]
		}
	]
}
