{
	"type": "FeatureCollection",
	"features": [
		{
			"type": "Feature",
			"properties": {
				"confidence": 9,
				"authenticationResultCode": "ValidCredentials",
				"brandLogoUri": "http://dev.virtualearth.net/Branding/logo_powered_by.png",
				"copyright": "Copyright © 2017 Microsoft and its suppliers. All rights reserved. This API cannot be accessed and the content and any results may not be used, reproduced or transmitted in any manner without express written permission from Microsoft Corporation.",
				"entityType": "Address",
				"matchCodes": [
					"Good"
				],
				"name": "9626 69 Ave, Clairmont, AB T0H 0W0, Canada",
				"statusCode": 200,
				"statusDescription": "OK",
				"traceId": "2486f1a15191494da456d19c153997b0|BN20130423|7.7.0.0|",
				"addressLine": "9626 69 Ave",
				"adminDistrict": "AB",
				"adminDistrict2": "Alberta",
				"countryRegion": "Canada",
				"formattedAddress": "9626 69 Ave, Clairmont, AB T0H 0W0, Canada",
				"locality": "Grande Prairie County No 1",
				"neighborhood": "Clairmont",
				"postalCode": "T0H 0W0"
			},
			"geometry": {
				"type": "Point",
				"coordinates": [
					-118.7844193,
					55.2297052
				]
			},
			"bbox": [
				-118.7863905,
				55.228581,
				-118.7824481,
				55.2308294
			]
		}
	]
}
