{
	"type": "FeatureCollection",
	"features": [
		{
			"type": "Feature",
			"properties": {
				"confidence": 9,
				"authenticationResultCode": "ValidCredentials",
				"brandLogoUri": "http://dev.virtualearth.net/Branding/logo_powered_by.png",
				"copyright": "Copyright © 2017 Microsoft and its suppliers. All rights reserved. This API cannot be accessed and the content and any results may not be used, reproduced or transmitted in any manner without express written permission from Microsoft Corporation.",
				"entityType": "Address",
				"matchCodes": [
					"Good"
				],
				"name": "963 Gibsons Way, Gibsons, BC V0N 1V8, Canada",
				"statusCode": 200,
				"statusDescription": "OK",
				"traceId": "2dcf4c9997c14ca7a946a128f27c4fb2|BN20250135|7.7.0.0|",
				"addressLine": "963 Gibsons Way",
				"adminDistrict": "BC",
				"adminDistrict2": "Sunshine Coast",
				"countryRegion": "Canada",
				"formattedAddress": "963 Gibsons Way, Gibsons, BC V0N 1V8, Canada",
				"locality": "Gibsons",
				"postalCode": "V0N 1V8"
			},
			"geometry": {
				"type": "Point",
				"coordinates": [
					-123.5222472,
					49.4065545
				]
			},
			"bbox": [
				-123.5239749,
				49.4054303,
				-123.5205196,
				49.4076786
			]
		}
	]
}
