{
	"type": "FeatureCollection",
	"features": [
		{
			"type": "Feature",
			"properties": {
				"confidence": 9,
				"authenticationResultCode": "ValidCredentials",
				"brandLogoUri": "http://dev.virtualearth.net/Branding/logo_powered_by.png",
				"copyright": "Copyright © 2017 Microsoft and its suppliers. All rights reserved. This API cannot be accessed and the content and any results may not be used, reproduced or transmitted in any manner without express written permission from Microsoft Corporation.",
				"entityType": "Address",
				"matchCodes": [
					"Good"
				],
				"name": "965 Strathcona Ave, Thunder Bay, ON P7A 0A2, Canada",
				"statusCode": 200,
				"statusDescription": "OK",
				"traceId": "6ff7b3761e56406782bdc77a6d96da98|BN20130422|7.7.0.0|",
				"addressLine": "965 Strathcona Ave",
				"adminDistrict": "ON",
				"adminDistrict2": "Thunder Bay",
				"countryRegion": "Canada",
				"formattedAddress": "965 Strathcona Ave, Thunder Bay, ON P7A 0A2, Canada",
				"locality": "Thunder Bay",
				"postalCode": "P7A 0A2"
			},
			"geometry": {
				"type": "Point",
				"coordinates": [
					-89.1577345,
					48.4769694
				]
			},
			"bbox": [
				-89.1594302,
				48.4758452,
				-89.1560387,
				48.4780935
			]
		}
	]
}
