{
	"type": "FeatureCollection",
	"features": [
		{
			"type": "Feature",
			"properties": {
				"confidence": 9,
				"authenticationResultCode": "ValidCredentials",
				"brandLogoUri": "http://dev.virtualearth.net/Branding/logo_powered_by.png",
				"copyright": "Copyright © 2017 Microsoft and its suppliers. All rights reserved. This API cannot be accessed and the content and any results may not be used, reproduced or transmitted in any manner without express written permission from Microsoft Corporation.",
				"entityType": "Address",
				"matchCodes": [
					"Good"
				],
				"name": "97 Toronto St, Barrie, ON L4N 1V1, Canada",
				"statusCode": 200,
				"statusDescription": "OK",
				"traceId": "47bf379673dd417b971c0e7b01a30fd9|BN20130423|7.7.0.0|",
				"addressLine": "97 Toronto St",
				"adminDistrict": "ON",
				"adminDistrict2": "Simcoe",
				"countryRegion": "Canada",
				"formattedAddress": "97 Toronto St, Barrie, ON L4N 1V1, Canada",
				"locality": "Barrie",
				"neighborhood": "Queen's Park",
				"postalCode": "L4N 1V1"
			},
			"geometry": {
				"type": "Point",
				"coordinates": [
					-79.69498,
					44.3899199
				]
			},
			"bbox": [
				-79.6965531,
				44.3887957,
				-79.6934069,
				44.3910441
			]
		}
	]
}
