{
	"type": "FeatureCollection",
	"features": [
		{
			"type": "Feature",
			"properties": {
				"confidence": 9,
				"authenticationResultCode": "ValidCredentials",
				"brandLogoUri": "http://dev.virtualearth.net/Branding/logo_powered_by.png",
				"copyright": "Copyright © 2017 Microsoft and its suppliers. All rights reserved. This API cannot be accessed and the content and any results may not be used, reproduced or transmitted in any manner without express written permission from Microsoft Corporation.",
				"entityType": "Address",
				"matchCodes": [
					"Good"
				],
				"name": "971 Rue Moisan, Chibougamau, QC G8P 1M9, Canada",
				"statusCode": 200,
				"statusDescription": "OK",
				"traceId": "5371d18eeffa4cfb8956415f511c3a28|BN20130522|7.7.0.0|",
				"addressLine": "971 Rue Moisan",
				"adminDistrict": "QC",
				"adminDistrict2": "Baie-James",
				"countryRegion": "Canada",
				"formattedAddress": "971 Rue Moisan, Chibougamau, QC G8P 1M9, Canada",
				"locality": "Chibougamau",
				"postalCode": "G8P 1M9"
			},
			"geometry": {
				"type": "Point",
				"coordinates": [
					-74.385,
					49.91666
				]
			},
			"bbox": [
				-74.3867458,
				49.9155358,
				-74.3832542,
				49.9177842
			]
		}
	]
}
