{
	"type": "FeatureCollection",
	"features": [
		{
			"type": "Feature",
			"properties": {
				"confidence": 9,
				"authenticationResultCode": "ValidCredentials",
				"brandLogoUri": "http://dev.virtualearth.net/Branding/logo_powered_by.png",
				"copyright": "Copyright © 2017 Microsoft and its suppliers. All rights reserved. This API cannot be accessed and the content and any results may not be used, reproduced or transmitted in any manner without express written permission from Microsoft Corporation.",
				"entityType": "Address",
				"matchCodes": [
					"Good"
				],
				"name": "9735 Grierson Hl NW, Edmonton, AB T5H, Canada",
				"statusCode": 200,
				"statusDescription": "OK",
				"traceId": "f9f5f783f89844d49f99f22e3c83d18c|BN20121763|7.7.0.0|",
				"addressLine": "9735 Grierson Hl NW",
				"adminDistrict": "AB",
				"adminDistrict2": "Alberta",
				"countryRegion": "Canada",
				"formattedAddress": "9735 Grierson Hl NW, Edmonton, AB T5H, Canada",
				"locality": "Edmonton",
				"neighborhood": "Riverdale",
				"postalCode": "T5H"
			},
			"geometry": {
				"type": "Point",
				"coordinates": [
					-113.48466,
					53.5413564
				]
			},
			"bbox": [
				-113.4865517,
				53.5402323,
				-113.4827682,
				53.5424806
			]
		}
	]
}
