{
	"type": "FeatureCollection",
	"features": [
		{
			"type": "Feature",
			"properties": {
				"confidence": 9,
				"authenticationResultCode": "ValidCredentials",
				"brandLogoUri": "http://dev.virtualearth.net/Branding/logo_powered_by.png",
				"copyright": "Copyright © 2017 Microsoft and its suppliers. All rights reserved. This API cannot be accessed and the content and any results may not be used, reproduced or transmitted in any manner without express written permission from Microsoft Corporation.",
				"entityType": "Address",
				"matchCodes": [
					"Good"
				],
				"name": "975 Rue du Pacifique, Lachine, QC H8S 2R1, Canada",
				"statusCode": 200,
				"statusDescription": "OK",
				"traceId": "93441ab1fbe04a9fbff501737e166d7a|BN20130431|7.7.0.0|",
				"addressLine": "975 Rue du Pacifique",
				"adminDistrict": "QC",
				"adminDistrict2": "Montreal",
				"countryRegion": "Canada",
				"formattedAddress": "975 Rue du Pacifique, Lachine, QC H8S 2R1, Canada",
				"locality": "Montreal",
				"neighborhood": "Lachine",
				"postalCode": "H8S 2R1"
			},
			"geometry": {
				"type": "Point",
				"coordinates": [
					-73.6554,
					45.44153
				]
			},
			"bbox": [
				-73.6570022,
				45.4404058,
				-73.6537978,
				45.4426542
			]
		}
	]
}
