{
	"type": "FeatureCollection",
	"features": [
		{
			"type": "Feature",
			"properties": {
				"confidence": 9,
				"authenticationResultCode": "ValidCredentials",
				"brandLogoUri": "http://dev.virtualearth.net/Branding/logo_powered_by.png",
				"copyright": "Copyright © 2017 Microsoft and its suppliers. All rights reserved. This API cannot be accessed and the content and any results may not be used, reproduced or transmitted in any manner without express written permission from Microsoft Corporation.",
				"entityType": "Address",
				"matchCodes": [
					"Good"
				],
				"name": "980 Old Glass Rd, Wallaceburg, ON N8A 3T2, Canada",
				"statusCode": 200,
				"statusDescription": "OK",
				"traceId": "a911498a33df468e87ce51ddcd58cfee|BN20181720|7.7.0.0|",
				"addressLine": "980 Old Glass Rd",
				"adminDistrict": "ON",
				"adminDistrict2": "Chatham-Kent",
				"countryRegion": "Canada",
				"formattedAddress": "980 Old Glass Rd, Wallaceburg, ON N8A 3T2, Canada",
				"locality": "Chatham-Kent",
				"neighborhood": "Wallaceburg",
				"postalCode": "N8A 3T2"
			},
			"geometry": {
				"type": "Point",
				"coordinates": [
					-82.39706,
					42.5819199
				]
			},
			"bbox": [
				-82.3985867,
				42.5807957,
				-82.3955333,
				42.5830441
			]
		}
	]
}
