{
	"type": "FeatureCollection",
	"features": [
		{
			"type": "Feature",
			"properties": {
				"confidence": 9,
				"authenticationResultCode": "ValidCredentials",
				"brandLogoUri": "http://dev.virtualearth.net/Branding/logo_powered_by.png",
				"copyright": "Copyright © 2017 Microsoft and its suppliers. All rights reserved. This API cannot be accessed and the content and any results may not be used, reproduced or transmitted in any manner without express written permission from Microsoft Corporation.",
				"entityType": "Address",
				"matchCodes": [
					"Good"
				],
				"name": "9810 60 Ave NW, Edmonton, AB T6E 0C5, Canada",
				"statusCode": 200,
				"statusDescription": "OK",
				"traceId": "bb6557b69dec4785b1de65f8a8bc5505|BN20121762|7.7.0.0|",
				"addressLine": "9810 60 Ave NW",
				"adminDistrict": "AB",
				"adminDistrict2": "Alberta",
				"countryRegion": "Canada",
				"formattedAddress": "9810 60 Ave NW, Edmonton, AB T6E 0C5, Canada",
				"locality": "Edmonton",
				"neighborhood": "Coronet Industrial",
				"postalCode": "T6E 0C5"
			},
			"geometry": {
				"type": "Point",
				"coordinates": [
					-113.48381,
					53.49639
				]
			},
			"bbox": [
				-113.4856997,
				53.4952658,
				-113.4819203,
				53.4975142
			]
		}
	]
}
