{
	"type": "FeatureCollection",
	"features": [
		{
			"type": "Feature",
			"properties": {
				"confidence": 9,
				"authenticationResultCode": "ValidCredentials",
				"brandLogoUri": "http://dev.virtualearth.net/Branding/logo_powered_by.png",
				"copyright": "Copyright © 2017 Microsoft and its suppliers. All rights reserved. This API cannot be accessed and the content and any results may not be used, reproduced or transmitted in any manner without express written permission from Microsoft Corporation.",
				"entityType": "Address",
				"matchCodes": [
					"Good"
				],
				"name": "9848 33 Ave NW, Edmonton, AB T6N 1C6, Canada",
				"statusCode": 200,
				"statusDescription": "OK",
				"traceId": "ca76f1991cb844798175b822e96f3559|BN20130719|7.7.0.0|",
				"addressLine": "9848 33 Ave NW",
				"adminDistrict": "AB",
				"adminDistrict2": "Alberta",
				"countryRegion": "Canada",
				"formattedAddress": "9848 33 Ave NW, Edmonton, AB T6N 1C6, Canada",
				"locality": "Edmonton",
				"neighborhood": "Parsons Industrial",
				"postalCode": "T6N 1C6"
			},
			"geometry": {
				"type": "Point",
				"coordinates": [
					-113.48365,
					53.46614
				]
			},
			"bbox": [
				-113.4855384,
				53.4650158,
				-113.4817616,
				53.4672642
			]
		}
	]
}
