{
	"type": "FeatureCollection",
	"features": [
		{
			"type": "Feature",
			"properties": {
				"confidence": 9,
				"authenticationResultCode": "ValidCredentials",
				"brandLogoUri": "http://dev.virtualearth.net/Branding/logo_powered_by.png",
				"copyright": "Copyright © 2017 Microsoft and its suppliers. All rights reserved. This API cannot be accessed and the content and any results may not be used, reproduced or transmitted in any manner without express written permission from Microsoft Corporation.",
				"entityType": "Address",
				"matchCodes": [
					"Good"
				],
				"name": "9876 63 Ave NW, Edmonton, AB T6E 0G6, Canada",
				"statusCode": 200,
				"statusDescription": "OK",
				"traceId": "9a6d4a9b91bb4dd9895c78fd527173e6|BN20250135|7.7.0.0|",
				"addressLine": "9876 63 Ave NW",
				"adminDistrict": "AB",
				"adminDistrict2": "Alberta",
				"countryRegion": "Canada",
				"formattedAddress": "9876 63 Ave NW, Edmonton, AB T6E 0G6, Canada",
				"locality": "Edmonton",
				"neighborhood": "Hazeldean",
				"postalCode": "T6E 0G6"
			},
			"geometry": {
				"type": "Point",
				"coordinates": [
					-113.48531,
					53.50011
				]
			},
			"bbox": [
				-113.4871999,
				53.4989858,
				-113.4834201,
				53.5012342
			]
		}
	]
}
