{
	"type": "FeatureCollection",
	"features": [
		{
			"type": "Feature",
			"properties": {
				"confidence": 9,
				"authenticationResultCode": "ValidCredentials",
				"brandLogoUri": "http://dev.virtualearth.net/Branding/logo_powered_by.png",
				"copyright": "Copyright © 2017 Microsoft and its suppliers. All rights reserved. This API cannot be accessed and the content and any results may not be used, reproduced or transmitted in any manner without express written permission from Microsoft Corporation.",
				"entityType": "Address",
				"matchCodes": [
					"Good"
				],
				"name": "9889 54 St SE, Calgary, AB T2C 5J4, Canada",
				"statusCode": 200,
				"statusDescription": "OK",
				"traceId": "92fcc4a5f9484c4aa2e128fba3717c8c|BN20171457|7.7.0.0|",
				"addressLine": "9889 54 St SE",
				"adminDistrict": "AB",
				"adminDistrict2": "Alberta",
				"countryRegion": "Canada",
				"formattedAddress": "9889 54 St SE, Calgary, AB T2C 5J4, Canada",
				"locality": "Calgary",
				"postalCode": "T2C 5J4"
			},
			"geometry": {
				"type": "Point",
				"coordinates": [
					-113.95556,
					50.96556
				]
			},
			"bbox": [
				-113.957345,
				50.9644358,
				-113.953775,
				50.9666842
			]
		}
	]
}
