{
	"type": "FeatureCollection",
	"features": [
		{
			"type": "Feature",
			"properties": {
				"confidence": 9,
				"authenticationResultCode": "ValidCredentials",
				"brandLogoUri": "http://dev.virtualearth.net/Branding/logo_powered_by.png",
				"copyright": "Copyright © 2017 Microsoft and its suppliers. All rights reserved. This API cannot be accessed and the content and any results may not be used, reproduced or transmitted in any manner without express written permission from Microsoft Corporation.",
				"entityType": "Address",
				"matchCodes": [
					"Good"
				],
				"name": "99 Murray Park Rd, Winnipeg, MB R3J 3M6, Canada",
				"statusCode": 200,
				"statusDescription": "OK",
				"traceId": "3fa703b544df43a5b944fe99c9dc348c|BN20171457|7.7.0.0|",
				"addressLine": "99 Murray Park Rd",
				"adminDistrict": "MB",
				"adminDistrict2": "Manitoba",
				"countryRegion": "Canada",
				"formattedAddress": "99 Murray Park Rd, Winnipeg, MB R3J 3M6, Canada",
				"locality": "Winnipeg",
				"neighborhood": "Murray Industrial Park",
				"postalCode": "R3J 3M6"
			},
			"geometry": {
				"type": "Point",
				"coordinates": [
					-97.2690499,
					49.89604
				]
			},
			"bbox": [
				-97.270795,
				49.8949158,
				-97.2673048,
				49.8971642
			]
		}
	]
}
