{
	"type": "FeatureCollection",
	"features": [
		{
			"type": "Feature",
			"properties": {
				"confidence": 9,
				"authenticationResultCode": "ValidCredentials",
				"brandLogoUri": "http://dev.virtualearth.net/Branding/logo_powered_by.png",
				"copyright": "Copyright © 2017 Microsoft and its suppliers. All rights reserved. This API cannot be accessed and the content and any results may not be used, reproduced or transmitted in any manner without express written permission from Microsoft Corporation.",
				"entityType": "Address",
				"matchCodes": [
					"Good"
				],
				"name": "99 Yoho Dr, Kanata, ON K2M 2V3, Canada",
				"statusCode": 200,
				"statusDescription": "OK",
				"traceId": "4b373d06922a4d8ab7289f410080ff8f|BN20320521|7.7.0.0|",
				"addressLine": "99 Yoho Dr",
				"adminDistrict": "ON",
				"adminDistrict2": "Ottawa",
				"countryRegion": "Canada",
				"formattedAddress": "99 Yoho Dr, Kanata, ON K2M 2V3, Canada",
				"locality": "Ottawa",
				"neighborhood": "Kanata",
				"postalCode": "K2M 2V3"
			},
			"geometry": {
				"type": "Point",
				"coordinates": [
					-75.85597,
					45.29748
				]
			},
			"bbox": [
				-75.8575681,
				45.2963558,
				-75.8543719,
				45.2986042
			]
		}
	]
}
