{
	"type": "FeatureCollection",
	"features": [
		{
			"type": "Feature",
			"properties": {
				"confidence": 9,
				"authenticationResultCode": "ValidCredentials",
				"brandLogoUri": "http://dev.virtualearth.net/Branding/logo_powered_by.png",
				"copyright": "Copyright © 2017 Microsoft and its suppliers. All rights reserved. This API cannot be accessed and the content and any results may not be used, reproduced or transmitted in any manner without express written permission from Microsoft Corporation.",
				"entityType": "Address",
				"matchCodes": [
					"Good"
				],
				"name": "991 Debra Ave, Ottawa, ON K2C 0J6, Canada",
				"statusCode": 200,
				"statusDescription": "OK",
				"traceId": "034629932aba487d895a2624d0772bc7|BN20220145|7.7.0.0|",
				"addressLine": "991 Debra Ave",
				"adminDistrict": "ON",
				"adminDistrict2": "Ottawa",
				"countryRegion": "Canada",
				"formattedAddress": "991 Debra Ave, Ottawa, ON K2C 0J6, Canada",
				"locality": "Ottawa",
				"neighborhood": "Carleton Heights-Rideauview",
				"postalCode": "K2C 0J6"
			},
			"geometry": {
				"type": "Point",
				"coordinates": [
					-75.70737,
					45.36636
				]
			},
			"bbox": [
				-75.7089701,
				45.3652358,
				-75.7057699,
				45.3674842
			]
		}
	]
}
