{
	"type": "FeatureCollection",
	"features": [
		{
			"type": "Feature",
			"properties": {
				"confidence": 9,
				"authenticationResultCode": "ValidCredentials",
				"brandLogoUri": "http://dev.virtualearth.net/Branding/logo_powered_by.png",
				"copyright": "Copyright © 2017 Microsoft and its suppliers. All rights reserved. This API cannot be accessed and the content and any results may not be used, reproduced or transmitted in any manner without express written permission from Microsoft Corporation.",
				"entityType": "Address",
				"matchCodes": [
					"Good"
				],
				"name": "5279 Still Creek Ave, Burnaby, BC V5C 5V1, Canada",
				"statusCode": 200,
				"statusDescription": "OK",
				"traceId": "52359a384a564321aa342195865fdb99|BN20130625|7.7.0.0|",
				"addressLine": "5279 Still Creek Ave",
				"adminDistrict": "BC",
				"adminDistrict2": "Greater Vancouver",
				"countryRegion": "Canada",
				"formattedAddress": "5279 Still Creek Ave, Burnaby, BC V5C 5V1, Canada",
				"locality": "Burnaby",
				"neighborhood": "Dawson-Delta",
				"postalCode": "V5C 5V1"
			},
			"geometry": {
				"type": "Point",
				"coordinates": [
					-122.9886,
					49.26143
				]
			},
			"bbox": [
				-122.9903226,
				49.2603058,
				-122.9868774,
				49.2625542
			]
		}
	]
}
