{
	"type": "FeatureCollection",
	"features": [
		{
			"type": "Feature",
			"properties": {
				"confidence": 7,
				"authenticationResultCode": "ValidCredentials",
				"brandLogoUri": "http://dev.virtualearth.net/Branding/logo_powered_by.png",
				"copyright": "Copyright © 2017 Microsoft and its suppliers. All rights reserved. This API cannot be accessed and the content and any results may not be used, reproduced or transmitted in any manner without express written permission from Microsoft Corporation.",
				"entityType": "Postcode1",
				"matchCodes": [
					"UpHierarchy"
				],
				"name": "Lac La Biche, T0A 2C0, Canada",
				"statusCode": 200,
				"statusDescription": "OK",
				"traceId": "418414fcc96744bb93ad07ca27b71f13|BN20130422|7.7.0.0|",
				"adminDistrict": "AB",
				"countryRegion": "Canada",
				"formattedAddress": "Lac La Biche, T0A 2C0, Canada",
				"locality": "Lac La Biche",
				"postalCode": "T0A 2C0"
			},
			"geometry": {
				"type": "Point",
				"coordinates": [
					-111.974449157715,
					54.7710990905762
				]
			},
			"bbox": [
				-111.983376692196,
				54.7672363730055,
				-111.965521623233,
				54.7749618081468
			]
		},
		{
			"type": "Feature",
			"properties": {
				"confidence": 4,
				"authenticationResultCode": "ValidCredentials",
				"brandLogoUri": "http://dev.virtualearth.net/Branding/logo_powered_by.png",
				"copyright": "Copyright © 2017 Microsoft and its suppliers. All rights reserved. This API cannot be accessed and the content and any results may not be used, reproduced or transmitted in any manner without express written permission from Microsoft Corporation.",
				"entityType": "PopulatedPlace",
				"matchCodes": [
					"UpHierarchy"
				],
				"name": "Beaver Lake Cree Nation, Canada",
				"statusCode": 200,
				"statusDescription": "OK",
				"traceId": "418414fcc96744bb93ad07ca27b71f13|BN20130422|7.7.0.0|",
				"countryRegion": "Canada",
				"formattedAddress": "Beaver Lake Cree Nation, Canada",
				"locality": "Beaver Lake Cree Nation"
			},
			"geometry": {
				"type": "Point",
				"coordinates": [
					-111.871391296387,
					54.6686096191406
				]
			},
			"bbox": [
				-111.938137525998,
				54.6396392361481,
				-111.804645066776,
				54.6975800021332
			]
		}
	]
}
