{
	"type": "FeatureCollection",
	"features": [
		{
			"type": "Feature",
			"properties": {
				"confidence": 7,
				"authenticationResultCode": "ValidCredentials",
				"brandLogoUri": "http://dev.virtualearth.net/Branding/logo_powered_by.png",
				"copyright": "Copyright © 2017 Microsoft and its suppliers. All rights reserved. This API cannot be accessed and the content and any results may not be used, reproduced or transmitted in any manner without express written permission from Microsoft Corporation.",
				"entityType": "Postcode1",
				"matchCodes": [
					"UpHierarchy"
				],
				"name": "Whitchurch-Stouffville, L4A 0N2, Canada",
				"statusCode": 200,
				"statusDescription": "OK",
				"traceId": "b2908f13cca945f38514e72fe8a584a0|BN20130431|7.7.0.0|",
				"adminDistrict": "ON",
				"adminDistrict2": "York",
				"countryRegion": "Canada",
				"formattedAddress": "Whitchurch-Stouffville, L4A 0N2, Canada",
				"locality": "Whitchurch-Stouffville",
				"postalCode": "L4A 0N2"
			},
			"geometry": {
				"type": "Point",
				"coordinates": [
					-79.2745208740234,
					43.9647979736328
				]
			},
			"bbox": [
				-79.2816759104909,
				43.9609352560621,
				-79.267365837556,
				43.9686606912035
			]
		}
	]
}
