{
	"type": "FeatureCollection",
	"features": [
		{
			"type": "Feature",
			"properties": {
				"confidence": 7,
				"authenticationResultCode": "ValidCredentials",
				"brandLogoUri": "http://dev.virtualearth.net/Branding/logo_powered_by.png",
				"copyright": "Copyright © 2017 Microsoft and its suppliers. All rights reserved. This API cannot be accessed and the content and any results may not be used, reproduced or transmitted in any manner without express written permission from Microsoft Corporation.",
				"entityType": "Postcode1",
				"matchCodes": [
					"UpHierarchy"
				],
				"name": "Bonnyville, T9N 2H7, Canada",
				"statusCode": 200,
				"statusDescription": "OK",
				"traceId": "99cdcb42d02f48449a5ba08bf98ac9c0|BN20190653|7.7.0.0|",
				"adminDistrict": "AB",
				"countryRegion": "Canada",
				"formattedAddress": "Bonnyville, T9N 2H7, Canada",
				"locality": "Bonnyville",
				"postalCode": "T9N 2H7"
			},
			"geometry": {
				"type": "Point",
				"coordinates": [
					-110.753318786621,
					54.2679481506348
				]
			},
			"bbox": [
				-110.762137019544,
				54.2640854330641,
				-110.744500553698,
				54.2718108682054
			]
		}
	]
}
