{
	"type": "FeatureCollection",
	"features": [
		{
			"type": "Feature",
			"properties": {
				"confidence": 9,
				"authenticationResultCode": "ValidCredentials",
				"brandLogoUri": "http://dev.virtualearth.net/Branding/logo_powered_by.png",
				"copyright": "Copyright © 2017 Microsoft and its suppliers. All rights reserved. This API cannot be accessed and the content and any results may not be used, reproduced or transmitted in any manner without express written permission from Microsoft Corporation.",
				"entityType": "Address",
				"matchCodes": [
					"Good"
				],
				"name": "6045 Creditview Rd, Mississauga, ON L5N, Canada",
				"statusCode": 200,
				"statusDescription": "OK",
				"traceId": "815eb516f6b94fd0802494bc820afac4|BN20181720|7.7.0.0|",
				"addressLine": "6045 Creditview Rd",
				"adminDistrict": "ON",
				"adminDistrict2": "Peel",
				"countryRegion": "Canada",
				"formattedAddress": "6045 Creditview Rd, Mississauga, ON L5N, Canada",
				"locality": "Mississauga",
				"neighborhood": "Meadowvale",
				"postalCode": "L5N"
			},
			"geometry": {
				"type": "Point",
				"coordinates": [
					-79.71251,
					43.59865
				]
			},
			"bbox": [
				-79.7140623,
				43.5975258,
				-79.7109577,
				43.5997742
			]
		}
	]
}
