{
	"type": "FeatureCollection",
	"features": [
		{
			"type": "Feature",
			"properties": {
				"confidence": 7,
				"authenticationResultCode": "ValidCredentials",
				"brandLogoUri": "http://dev.virtualearth.net/Branding/logo_powered_by.png",
				"copyright": "Copyright © 2017 Microsoft and its suppliers. All rights reserved. This API cannot be accessed and the content and any results may not be used, reproduced or transmitted in any manner without express written permission from Microsoft Corporation.",
				"entityType": "Postcode1",
				"matchCodes": [
					"UpHierarchy"
				],
				"name": "Prince Albert, S6V 8A4, Canada",
				"statusCode": 200,
				"statusDescription": "OK",
				"traceId": "fe87831680544085884108cc0d7ce09a|BN20280152|7.7.0.0|",
				"adminDistrict": "SK",
				"countryRegion": "Canada",
				"formattedAddress": "Prince Albert, S6V 8A4, Canada",
				"locality": "Prince Albert",
				"postalCode": "S6V 8A4"
			},
			"geometry": {
				"type": "Point",
				"coordinates": [
					-105.745819091797,
					53.1994514465332
				]
			},
			"bbox": [
				-105.75441601543,
				53.1955887289625,
				-105.737222168164,
				53.2033141641039
			]
		}
	]
}
