{
	"type": "FeatureCollection",
	"features": [
		{
			"type": "Feature",
			"properties": {
				"confidence": 9,
				"authenticationResultCode": "ValidCredentials",
				"brandLogoUri": "http://dev.virtualearth.net/Branding/logo_powered_by.png",
				"copyright": "Copyright © 2017 Microsoft and its suppliers. All rights reserved. This API cannot be accessed and the content and any results may not be used, reproduced or transmitted in any manner without express written permission from Microsoft Corporation.",
				"entityType": "Address",
				"matchCodes": [
					"Good"
				],
				"name": "1568 Merivale Rd, Nepean, ON K2G 3J9, Canada",
				"statusCode": 200,
				"statusDescription": "OK",
				"traceId": "c68a69b68bba40cd97ccdb441e8642fe|BN20130634|7.7.0.0|",
				"addressLine": "1568 Merivale Rd",
				"adminDistrict": "ON",
				"adminDistrict2": "Ottawa",
				"countryRegion": "Canada",
				"formattedAddress": "1568 Merivale Rd, Nepean, ON K2G 3J9, Canada",
				"locality": "Ottawa",
				"neighborhood": "Nepean",
				"postalCode": "K2G 3J9"
			},
			"geometry": {
				"type": "Point",
				"coordinates": [
					-75.7343578,
					45.3518741
				]
			},
			"bbox": [
				-75.7359574,
				45.3507499,
				-75.7327581,
				45.3529982
			]
		}
	]
}
