{
	"type": "FeatureCollection",
	"features": [
		{
			"type": "Feature",
			"properties": {
				"confidence": 9,
				"authenticationResultCode": "ValidCredentials",
				"brandLogoUri": "http://dev.virtualearth.net/Branding/logo_powered_by.png",
				"copyright": "Copyright © 2017 Microsoft and its suppliers. All rights reserved. This API cannot be accessed and the content and any results may not be used, reproduced or transmitted in any manner without express written permission from Microsoft Corporation.",
				"entityType": "Address",
				"matchCodes": [
					"Good"
				],
				"name": "327 Guelph St, Georgetown, ON L7G 4B3, Canada",
				"statusCode": 200,
				"statusDescription": "OK",
				"traceId": "b5a66d61685e40b78fd924355bfdf0f7|BN20130532|7.7.0.0|",
				"addressLine": "327 Guelph St",
				"adminDistrict": "ON",
				"adminDistrict2": "Halton",
				"countryRegion": "Canada",
				"formattedAddress": "327 Guelph St, Georgetown, ON L7G 4B3, Canada",
				"locality": "Halton Hills",
				"neighborhood": "Georgetown",
				"postalCode": "L7G 4B3"
			},
			"geometry": {
				"type": "Point",
				"coordinates": [
					-79.8859324,
					43.6494748
				]
			},
			"bbox": [
				-79.887486,
				43.6483506,
				-79.8843788,
				43.6505989
			]
		}
	]
}
