{
	"type": "FeatureCollection",
	"features": [
		{
			"type": "Feature",
			"properties": {
				"confidence": 7,
				"authenticationResultCode": "ValidCredentials",
				"brandLogoUri": "http://dev.virtualearth.net/Branding/logo_powered_by.png",
				"copyright": "Copyright © 2017 Microsoft and its suppliers. All rights reserved. This API cannot be accessed and the content and any results may not be used, reproduced or transmitted in any manner without express written permission from Microsoft Corporation.",
				"entityType": "Postcode1",
				"matchCodes": [
					"UpHierarchy"
				],
				"name": "Saskatoon, S7K 3J7, Canada",
				"statusCode": 200,
				"statusDescription": "OK",
				"traceId": "93d1fa3c4d8d47b498f52b47f0ed55d6|BN20290118|7.7.0.0|",
				"adminDistrict": "SK",
				"countryRegion": "Canada",
				"formattedAddress": "Saskatoon, S7K 3J7, Canada",
				"locality": "Saskatoon",
				"postalCode": "S7K 3J7"
			},
			"geometry": {
				"type": "Point",
				"coordinates": [
					-106.65926361084,
					52.1304893493652
				]
			},
			"bbox": [
				-106.667652820005,
				52.1266266317946,
				-106.650874401675,
				52.1343520669359
			]
		},
		{
			"type": "Feature",
			"properties": {
				"confidence": 4,
				"authenticationResultCode": "ValidCredentials",
				"brandLogoUri": "http://dev.virtualearth.net/Branding/logo_powered_by.png",
				"copyright": "Copyright © 2017 Microsoft and its suppliers. All rights reserved. This API cannot be accessed and the content and any results may not be used, reproduced or transmitted in any manner without express written permission from Microsoft Corporation.",
				"entityType": "PopulatedPlace",
				"matchCodes": [
					"UpHierarchy"
				],
				"name": "North Saskatoon, Saskatchewan, Canada",
				"statusCode": 200,
				"statusDescription": "OK",
				"traceId": "93d1fa3c4d8d47b498f52b47f0ed55d6|BN20290118|7.7.0.0|",
				"adminDistrict": "SK",
				"countryRegion": "Canada",
				"formattedAddress": "North Saskatoon, Saskatchewan, Canada",
				"locality": "North Saskatoon"
			},
			"geometry": {
				"type": "Point",
				"coordinates": [
					-106.647216796875,
					52.1802291870117
				]
			},
			"bbox": [
				-106.710170683304,
				52.1512588040192,
				-106.584262910446,
				52.2091995700043
			]
		}
	]
}
