{
	"type": "FeatureCollection",
	"features": [
		{
			"type": "Feature",
			"properties": {
				"confidence": 9,
				"authenticationResultCode": "ValidCredentials",
				"brandLogoUri": "http://dev.virtualearth.net/Branding/logo_powered_by.png",
				"copyright": "Copyright © 2017 Microsoft and its suppliers. All rights reserved. This API cannot be accessed and the content and any results may not be used, reproduced or transmitted in any manner without express written permission from Microsoft Corporation.",
				"entityType": "Address",
				"matchCodes": [
					"Good"
				],
				"name": "1405 Rue de Guise, La Prairie, QC J5R 5W6, Canada",
				"statusCode": 200,
				"statusDescription": "OK",
				"traceId": "a042e884d20c44b5aee412a4a791c6d1|BN20130632|7.7.0.0|",
				"addressLine": "1405 Rue de Guise",
				"adminDistrict": "QC",
				"adminDistrict2": "Roussillon",
				"countryRegion": "Canada",
				"formattedAddress": "1405 Rue de Guise, La Prairie, QC J5R 5W6, Canada",
				"locality": "La Prairie",
				"postalCode": "J5R 5W6"
			},
			"geometry": {
				"type": "Point",
				"coordinates": [
					-73.4952839,
					45.3973378
				]
			},
			"bbox": [
				-73.4968849,
				45.3962137,
				-73.493683,
				45.398462
			]
		}
	]
}
