{
	"type": "FeatureCollection",
	"features": [
		{
			"type": "Feature",
			"properties": {
				"confidence": 7,
				"authenticationResultCode": "ValidCredentials",
				"brandLogoUri": "http://dev.virtualearth.net/Branding/logo_powered_by.png",
				"copyright": "Copyright © 2017 Microsoft and its suppliers. All rights reserved. This API cannot be accessed and the content and any results may not be used, reproduced or transmitted in any manner without express written permission from Microsoft Corporation.",
				"entityType": "Postcode1",
				"matchCodes": [
					"UpHierarchy"
				],
				"name": "Banff, T1L 1B2, Canada",
				"statusCode": 200,
				"statusDescription": "OK",
				"traceId": "e0ddad5a152c4d06ab5828b3545131f6|BN20300154|7.7.0.0|",
				"adminDistrict": "AB",
				"countryRegion": "Canada",
				"formattedAddress": "Banff, T1L 1B2, Canada",
				"locality": "Banff",
				"postalCode": "T1L 1B2"
			},
			"geometry": {
				"type": "Point",
				"coordinates": [
					-115.572738647461,
					51.17578125
				]
			},
			"bbox": [
				-115.580953013599,
				51.1719185324293,
				-115.564524281323,
				51.1796439675707
			]
		}
	]
}
