{
	"type": "FeatureCollection",
	"features": [
		{
			"type": "Feature",
			"properties": {
				"confidence": 7,
				"authenticationResultCode": "ValidCredentials",
				"brandLogoUri": "http://dev.virtualearth.net/Branding/logo_powered_by.png",
				"copyright": "Copyright © 2017 Microsoft and its suppliers. All rights reserved. This API cannot be accessed and the content and any results may not be used, reproduced or transmitted in any manner without express written permission from Microsoft Corporation.",
				"entityType": "Postcode1",
				"matchCodes": [
					"UpHierarchy"
				],
				"name": "Imperial, S0G 2J0, Canada",
				"statusCode": 200,
				"statusDescription": "OK",
				"traceId": "dba0c3b1e31c4f3c9bb0ff81a532c66a|BN20130423|7.7.0.0|",
				"adminDistrict": "SK",
				"countryRegion": "Canada",
				"formattedAddress": "Imperial, S0G 2J0, Canada",
				"locality": "Imperial",
				"postalCode": "S0G 2J0"
			},
			"geometry": {
				"type": "Point",
				"coordinates": [
					-105.434516906738,
					51.3443298339844
				]
			},
			"bbox": [
				-105.442761443124,
				51.3404671164137,
				-105.426272370353,
				51.3481925515551
			]
		}
	]
}
