{
	"type": "FeatureCollection",
	"features": [
		{
			"type": "Feature",
			"properties": {
				"confidence": 9,
				"authenticationResultCode": "ValidCredentials",
				"brandLogoUri": "http://dev.virtualearth.net/Branding/logo_powered_by.png",
				"copyright": "Copyright © 2017 Microsoft and its suppliers. All rights reserved. This API cannot be accessed and the content and any results may not be used, reproduced or transmitted in any manner without express written permission from Microsoft Corporation.",
				"entityType": "Address",
				"matchCodes": [
					"Good"
				],
				"name": "133 Paudash St, Otonabee-South Monaghan, ON K9J 0E6, Canada",
				"statusCode": 200,
				"statusDescription": "OK",
				"traceId": "6fe4d1d549624b269bc67fab1dbdab0a|BN20200239|7.7.0.0|",
				"addressLine": "133 Paudash St",
				"adminDistrict": "ON",
				"adminDistrict2": "Peterborough",
				"countryRegion": "Canada",
				"formattedAddress": "133 Paudash St, Otonabee-South Monaghan, ON K9J 0E6, Canada",
				"locality": "Otonabee-South Monaghan",
				"neighborhood": "Keene",
				"postalCode": "K9J 0E6"
			},
			"geometry": {
				"type": "Point",
				"coordinates": [
					-78.2125312,
					44.1728916
				]
			},
			"bbox": [
				-78.2140985,
				44.1717675,
				-78.2109639,
				44.1740158
			]
		}
	]
}
