{
	"type": "FeatureCollection",
	"features": [
		{
			"type": "Feature",
			"properties": {
				"confidence": 7,
				"authenticationResultCode": "ValidCredentials",
				"brandLogoUri": "http://dev.virtualearth.net/Branding/logo_powered_by.png",
				"copyright": "Copyright © 2017 Microsoft and its suppliers. All rights reserved. This API cannot be accessed and the content and any results may not be used, reproduced or transmitted in any manner without express written permission from Microsoft Corporation.",
				"entityType": "Postcode1",
				"matchCodes": [
					"UpHierarchy"
				],
				"name": "Saskatoon, S7K 3J8, Canada",
				"statusCode": 200,
				"statusDescription": "OK",
				"traceId": "5b4cae5203cf4876ac7d5700f92539de|BN20130631|7.7.0.0|",
				"adminDistrict": "SK",
				"countryRegion": "Canada",
				"formattedAddress": "Saskatoon, S7K 3J8, Canada",
				"locality": "Saskatoon",
				"postalCode": "S7K 3J8"
			},
			"geometry": {
				"type": "Point",
				"coordinates": [
					-106.65926361084,
					52.1304893493652
				]
			},
			"bbox": [
				-106.667652820005,
				52.1266266317946,
				-106.650874401675,
				52.1343520669359
			]
		}
	]
}
