{
	"type": "FeatureCollection",
	"features": [
		{
			"type": "Feature",
			"properties": {
				"confidence": 9,
				"authenticationResultCode": "ValidCredentials",
				"brandLogoUri": "http://dev.virtualearth.net/Branding/logo_powered_by.png",
				"copyright": "Copyright © 2017 Microsoft and its suppliers. All rights reserved. This API cannot be accessed and the content and any results may not be used, reproduced or transmitted in any manner without express written permission from Microsoft Corporation.",
				"entityType": "Address",
				"matchCodes": [
					"Good"
				],
				"name": "4819 45 St, Rocky Mountain House, AB T4T, Canada",
				"statusCode": 200,
				"statusDescription": "OK",
				"traceId": "3279804d2727458d806a03936252015c|BN20300154|7.7.0.0|",
				"addressLine": "4819 45 St",
				"adminDistrict": "AB",
				"adminDistrict2": "Alberta",
				"countryRegion": "Canada",
				"formattedAddress": "4819 45 St, Rocky Mountain House, AB T4T, Canada",
				"locality": "Rocky Mountain House",
				"postalCode": "T4T 1A9"
			},
			"geometry": {
				"type": "Point",
				"coordinates": [
					-114.91067,
					52.37228
				]
			},
			"bbox": [
				-114.9125113,
				52.3711558,
				-114.9088287,
				52.3734042
			]
		}
	]
}
