{
	"type": "FeatureCollection",
	"features": [
		{
			"type": "Feature",
			"properties": {
				"confidence": 8,
				"authenticationResultCode": "ValidCredentials",
				"brandLogoUri": "http://dev.virtualearth.net/Branding/logo_powered_by.png",
				"copyright": "Copyright © 2017 Microsoft and its suppliers. All rights reserved. This API cannot be accessed and the content and any results may not be used, reproduced or transmitted in any manner without express written permission from Microsoft Corporation.",
				"entityType": "RoadBlock",
				"matchCodes": [
					"UpHierarchy"
				],
				"name": "Golling St, Lemberg, SK S0A, Canada",
				"statusCode": 200,
				"statusDescription": "OK",
				"traceId": "df23c5dc7b944f70a354332745179711|BN20130532|7.7.0.0|",
				"addressLine": "Golling St",
				"adminDistrict": "SK",
				"adminDistrict2": "Saskatchewan",
				"countryRegion": "Canada",
				"formattedAddress": "Golling St, Lemberg, SK S0A, Canada",
				"locality": "Lemberg",
				"postalCode": "S0A 2B0"
			},
			"geometry": {
				"type": "Point",
				"coordinates": [
					-103.20878,
					50.7271
				]
			},
			"bbox": [
				-103.2088,
				50.72436,
				-103.20876,
				50.72984
			]
		}
	]
}
