{
	"type": "FeatureCollection",
	"features": [
		{
			"type": "Feature",
			"properties": {
				"confidence": 7,
				"authenticationResultCode": "ValidCredentials",
				"brandLogoUri": "http://dev.virtualearth.net/Branding/logo_powered_by.png",
				"copyright": "Copyright © 2017 Microsoft and its suppliers. All rights reserved. This API cannot be accessed and the content and any results may not be used, reproduced or transmitted in any manner without express written permission from Microsoft Corporation.",
				"entityType": "Neighborhood",
				"matchCodes": [
					"Ambiguous",
					"UpHierarchy"
				],
				"name": "Peguis, Manitoba, Manitoba, Canada",
				"statusCode": 200,
				"statusDescription": "OK",
				"traceId": "07f302484dad468dbeeff83e18de3df8|BN20200239|7.7.0.0|",
				"adminDistrict": "MB",
				"countryRegion": "Canada",
				"formattedAddress": "Peguis, Manitoba, Manitoba, Canada",
				"locality": "Manitoba",
				"neighborhood": "Peguis"
			},
			"geometry": {
				"type": "Point",
				"coordinates": [
					-97.5597229003906,
					51.3197708129883
				]
			},
			"bbox": [
				-97.567963022476,
				51.3159080954176,
				-97.5514827783053,
				51.323633530559
			]
		},
		{
			"type": "Feature",
			"properties": {
				"confidence": 4,
				"authenticationResultCode": "ValidCredentials",
				"brandLogoUri": "http://dev.virtualearth.net/Branding/logo_powered_by.png",
				"copyright": "Copyright © 2017 Microsoft and its suppliers. All rights reserved. This API cannot be accessed and the content and any results may not be used, reproduced or transmitted in any manner without express written permission from Microsoft Corporation.",
				"entityType": "PopulatedPlace",
				"matchCodes": [
					"UpHierarchy"
				],
				"name": "Lot 16, Prince Edward Island, Canada",
				"statusCode": 200,
				"statusDescription": "OK",
				"traceId": "07f302484dad468dbeeff83e18de3df8|BN20200239|7.7.0.0|",
				"adminDistrict": "PE",
				"adminDistrict2": "Prince",
				"countryRegion": "Canada",
				"formattedAddress": "Lot 16, Prince Edward Island, Canada",
				"locality": "Lot 16"
			},
			"geometry": {
				"type": "Point",
				"coordinates": [
					-63.9329986572266,
					46.4669990539551
				]
			},
			"bbox": [
				-63.9890500436414,
				46.4380286709625,
				-63.8769472708117,
				46.4959694369476
			]
		}
	]
}
