{
	"type": "FeatureCollection",
	"features": [
		{
			"type": "Feature",
			"properties": {
				"confidence": 10,
				"authenticationResultCode": "ValidCredentials",
				"brandLogoUri": "http://dev.virtualearth.net/Branding/logo_powered_by.png",
				"copyright": "Copyright © 2017 Microsoft and its suppliers. All rights reserved. This API cannot be accessed and the content and any results may not be used, reproduced or transmitted in any manner without express written permission from Microsoft Corporation.",
				"entityType": "RoadBlock",
				"matchCodes": [
					"Good"
				],
				"name": "Black Rd, Manitouwadge, ON P0T, Canada",
				"statusCode": 200,
				"statusDescription": "OK",
				"traceId": "e9a2da59174440378726f29539eb454c|BN20130533|7.7.0.0|",
				"addressLine": "Black Rd",
				"adminDistrict": "ON",
				"adminDistrict2": "Thunder Bay",
				"countryRegion": "Canada",
				"formattedAddress": "Black Rd, Manitouwadge, ON P0T, Canada",
				"locality": "Manitouwadge",
				"postalCode": "P0T 2C0"
			},
			"geometry": {
				"type": "Point",
				"coordinates": [
					-85.81771,
					49.12149
				]
			},
			"bbox": [
				-85.8187,
				49.12082,
				-85.8169099,
				49.12207
			]
		}
	]
}
