{
	"type": "FeatureCollection",
	"features": [
		{
			"type": "Feature",
			"properties": {
				"confidence": 9,
				"authenticationResultCode": "ValidCredentials",
				"brandLogoUri": "http://dev.virtualearth.net/Branding/logo_powered_by.png",
				"copyright": "Copyright © 2017 Microsoft and its suppliers. All rights reserved. This API cannot be accessed and the content and any results may not be used, reproduced or transmitted in any manner without express written permission from Microsoft Corporation.",
				"entityType": "Address",
				"matchCodes": [
					"Good"
				],
				"name": "308 E 5th Ave, Vancouver, BC V5T 1H4, Canada",
				"statusCode": 200,
				"statusDescription": "OK",
				"traceId": "603dab4614304c99b18b12e6e2637f2c|BN20130422|7.7.0.0|",
				"addressLine": "308 E 5th Ave",
				"adminDistrict": "BC",
				"adminDistrict2": "Greater Vancouver",
				"countryRegion": "Canada",
				"formattedAddress": "308 E 5th Ave, Vancouver, BC V5T 1H4, Canada",
				"locality": "Vancouver",
				"neighborhood": "Mt Pleasant",
				"postalCode": "V5T 1H4"
			},
			"geometry": {
				"type": "Point",
				"coordinates": [
					-123.09843,
					49.2661
				]
			},
			"bbox": [
				-123.1001527,
				49.2649758,
				-123.0967073,
				49.2672242
			]
		}
	]
}
