{
	"type": "FeatureCollection",
	"features": [
		{
			"type": "Feature",
			"properties": {
				"confidence": 7,
				"authenticationResultCode": "ValidCredentials",
				"brandLogoUri": "http://dev.virtualearth.net/Branding/logo_powered_by.png",
				"copyright": "Copyright © 2017 Microsoft and its suppliers. All rights reserved. This API cannot be accessed and the content and any results may not be used, reproduced or transmitted in any manner without express written permission from Microsoft Corporation.",
				"entityType": "Postcode1",
				"matchCodes": [
					"UpHierarchy"
				],
				"name": "Edmonton, T5Z 3P3, Canada",
				"statusCode": 200,
				"statusDescription": "OK",
				"traceId": "0dfb210143a5421d966ba14efdd171d0|BN20200137|7.7.0.0|",
				"adminDistrict": "AB",
				"countryRegion": "Canada",
				"formattedAddress": "Edmonton, T5Z 3P3, Canada",
				"locality": "Edmonton",
				"postalCode": "T5Z 3P3"
			},
			"geometry": {
				"type": "Point",
				"coordinates": [
					-113.490371704102,
					53.5462417602539
				]
			},
			"bbox": [
				-113.499038898666,
				53.5423790426832,
				-113.481704509537,
				53.5501044778246
			]
		}
	]
}
