{
	"type": "FeatureCollection",
	"features": [
		{
			"type": "Feature",
			"properties": {
				"confidence": 7,
				"authenticationResultCode": "ValidCredentials",
				"brandLogoUri": "http://dev.virtualearth.net/Branding/logo_powered_by.png",
				"copyright": "Copyright © 2017 Microsoft and its suppliers. All rights reserved. This API cannot be accessed and the content and any results may not be used, reproduced or transmitted in any manner without express written permission from Microsoft Corporation.",
				"entityType": "Postcode1",
				"matchCodes": [
					"UpHierarchy"
				],
				"name": "Brooks, T1R 1C5, Canada",
				"statusCode": 200,
				"statusDescription": "OK",
				"traceId": "ea5dfc10db04462999daad734063f564|BN20130632|7.7.0.0|",
				"adminDistrict": "AB",
				"countryRegion": "Canada",
				"formattedAddress": "Brooks, T1R 1C5, Canada",
				"locality": "Brooks",
				"postalCode": "T1R 1C5"
			},
			"geometry": {
				"type": "Point",
				"coordinates": [
					-111.898483276367,
					50.5658493041992
				]
			},
			"bbox": [
				-111.906590866213,
				50.5619865866285,
				-111.890375686521,
				50.5697120217699
			]
		}
	]
}
