{
	"type": "FeatureCollection",
	"features": [
		{
			"type": "Feature",
			"properties": {
				"confidence": 7,
				"authenticationResultCode": "ValidCredentials",
				"brandLogoUri": "http://dev.virtualearth.net/Branding/logo_powered_by.png",
				"copyright": "Copyright © 2017 Microsoft and its suppliers. All rights reserved. This API cannot be accessed and the content and any results may not be used, reproduced or transmitted in any manner without express written permission from Microsoft Corporation.",
				"entityType": "Postcode1",
				"matchCodes": [
					"Ambiguous",
					"UpHierarchy"
				],
				"name": "Halifax, B3H 4R2, Canada",
				"statusCode": 200,
				"statusDescription": "OK",
				"traceId": "8194ea2079db475b856e25ea81e70030|BN20131519|7.7.0.0|",
				"adminDistrict": "NS",
				"adminDistrict2": "Halifax",
				"countryRegion": "Canada",
				"formattedAddress": "Halifax, B3H 4R2, Canada",
				"locality": "Halifax",
				"postalCode": "B3H 4R2"
			},
			"geometry": {
				"type": "Point",
				"coordinates": [
					-63.5765991210938,
					44.6454696655273
				]
			},
			"bbox": [
				-63.5838375954512,
				44.6416069479567,
				-63.5693606467363,
				44.649332383098
			]
		}
	]
}
