{
	"type": "FeatureCollection",
	"features": [
		{
			"type": "Feature",
			"properties": {
				"confidence": 7,
				"authenticationResultCode": "ValidCredentials",
				"brandLogoUri": "http://dev.virtualearth.net/Branding/logo_powered_by.png",
				"copyright": "Copyright © 2017 Microsoft and its suppliers. All rights reserved. This API cannot be accessed and the content and any results may not be used, reproduced or transmitted in any manner without express written permission from Microsoft Corporation.",
				"entityType": "Postcode1",
				"matchCodes": [
					"UpHierarchy"
				],
				"name": "Embrun, K0A 1W0, Canada",
				"statusCode": 200,
				"statusDescription": "OK",
				"traceId": "8678a5bf2b14422c8b5f6273ea724b9e|BN20121763|7.7.0.0|",
				"adminDistrict": "ON",
				"adminDistrict2": "Prescott and Russell",
				"countryRegion": "Canada",
				"formattedAddress": "Embrun, K0A 1W0, Canada",
				"locality": "Embrun",
				"postalCode": "K0A 1W0"
			},
			"geometry": {
				"type": "Point",
				"coordinates": [
					-75.2758255004883,
					45.2768669128418
				]
			},
			"bbox": [
				-75.2831440652093,
				45.2730041952711,
				-75.2685069357673,
				45.2807296304125
			]
		}
	]
}
