{
	"type": "FeatureCollection",
	"features": [
		{
			"type": "Feature",
			"properties": {
				"confidence": 7,
				"authenticationResultCode": "ValidCredentials",
				"brandLogoUri": "http://dev.virtualearth.net/Branding/logo_powered_by.png",
				"copyright": "Copyright © 2017 Microsoft and its suppliers. All rights reserved. This API cannot be accessed and the content and any results may not be used, reproduced or transmitted in any manner without express written permission from Microsoft Corporation.",
				"entityType": "Postcode1",
				"matchCodes": [
					"UpHierarchy"
				],
				"name": "Whitby, L1M 1B5, Canada",
				"statusCode": 200,
				"statusDescription": "OK",
				"traceId": "c36f5e5da4454056bdf985c47d1cd4df|BN20260231|7.7.0.0|",
				"adminDistrict": "ON",
				"adminDistrict2": "Durham",
				"countryRegion": "Canada",
				"formattedAddress": "Whitby, L1M 1B5, Canada",
				"locality": "Whitby",
				"postalCode": "L1M 1B5"
			},
			"geometry": {
				"type": "Point",
				"coordinates": [
					-78.9425277709961,
					43.8992500305176
				]
			},
			"bbox": [
				-78.9496749269137,
				43.8953873129469,
				-78.9353806150785,
				43.9031127480883
			]
		}
	]
}
