{
	"type": "FeatureCollection",
	"features": [
		{
			"type": "Feature",
			"properties": {
				"confidence": 7,
				"authenticationResultCode": "ValidCredentials",
				"brandLogoUri": "http://dev.virtualearth.net/Branding/logo_powered_by.png",
				"copyright": "Copyright © 2017 Microsoft and its suppliers. All rights reserved. This API cannot be accessed and the content and any results may not be used, reproduced or transmitted in any manner without express written permission from Microsoft Corporation.",
				"entityType": "Postcode1",
				"matchCodes": [
					"UpHierarchy"
				],
				"name": "Sidney, V8L 4C1, Canada",
				"statusCode": 200,
				"statusDescription": "OK",
				"traceId": "7583559ab390410cb6bb97c82a7142b7|BN20130422|7.7.0.0|",
				"adminDistrict": "BC",
				"adminDistrict2": "Capital",
				"countryRegion": "Canada",
				"formattedAddress": "Sidney, V8L 4C1, Canada",
				"locality": "Sidney",
				"postalCode": "V8L 4C1"
			},
			"geometry": {
				"type": "Point",
				"coordinates": [
					-123.398422241211,
					48.6502113342285
				]
			},
			"bbox": [
				-123.406217386123,
				48.6463486166578,
				-123.390627096298,
				48.6540740517992
			]
		}
	]
}
