{
	"type": "FeatureCollection",
	"features": [
		{
			"type": "Feature",
			"properties": {
				"confidence": 7,
				"authenticationResultCode": "ValidCredentials",
				"brandLogoUri": "http://dev.virtualearth.net/Branding/logo_powered_by.png",
				"copyright": "Copyright © 2017 Microsoft and its suppliers. All rights reserved. This API cannot be accessed and the content and any results may not be used, reproduced or transmitted in any manner without express written permission from Microsoft Corporation.",
				"entityType": "Postcode1",
				"matchCodes": [
					"UpHierarchy"
				],
				"name": "Rothesay, E2E 5T6, Canada",
				"statusCode": 200,
				"statusDescription": "OK",
				"traceId": "641109d2394c4ca6b09815d1594ad102|BN20130422|7.7.0.0|",
				"adminDistrict": "NB",
				"adminDistrict2": "Kings",
				"countryRegion": "Canada",
				"formattedAddress": "Rothesay, E2E 5T6, Canada",
				"locality": "Rothesay",
				"postalCode": "E2E 5T6"
			},
			"geometry": {
				"type": "Point",
				"coordinates": [
					-66.001106262207,
					45.3876609802246
				]
			},
			"bbox": [
				-66.0084391561782,
				45.3837982626539,
				-65.9937733682358,
				45.3915236977953
			]
		}
	]
}
