{
	"type": "FeatureCollection",
	"features": [
		{
			"type": "Feature",
			"properties": {
				"confidence": 7,
				"authenticationResultCode": "ValidCredentials",
				"brandLogoUri": "http://dev.virtualearth.net/Branding/logo_powered_by.png",
				"copyright": "Copyright © 2017 Microsoft and its suppliers. All rights reserved. This API cannot be accessed and the content and any results may not be used, reproduced or transmitted in any manner without express written permission from Microsoft Corporation.",
				"entityType": "Postcode1",
				"matchCodes": [
					"UpHierarchy"
				],
				"name": "Alma, G8B 5V8, Canada",
				"statusCode": 200,
				"statusDescription": "OK",
				"traceId": "f44856b94ae7412aa68f03ba801f2aab|BN20130422|7.7.0.0|",
				"adminDistrict": "QC",
				"adminDistrict2": "Lac-St-Jean-Est",
				"countryRegion": "Canada",
				"formattedAddress": "Alma, G8B 5V8, Canada",
				"locality": "Alma",
				"postalCode": "G8B 5V8"
			},
			"geometry": {
				"type": "Point",
				"coordinates": [
					-71.6526565551758,
					48.5497283935547
				]
			},
			"bbox": [
				-71.6604362111339,
				48.545865675984,
				-71.6448768992177,
				48.5535911111254
			]
		}
	]
}
