{
	"type": "FeatureCollection",
	"features": [
		{
			"type": "Feature",
			"properties": {
				"confidence": 7,
				"authenticationResultCode": "ValidCredentials",
				"brandLogoUri": "http://dev.virtualearth.net/Branding/logo_powered_by.png",
				"copyright": "Copyright © 2017 Microsoft and its suppliers. All rights reserved. This API cannot be accessed and the content and any results may not be used, reproduced or transmitted in any manner without express written permission from Microsoft Corporation.",
				"entityType": "Postcode1",
				"matchCodes": [
					"UpHierarchy"
				],
				"name": "Dundas, L9H 6Y6, Canada",
				"statusCode": 200,
				"statusDescription": "OK",
				"traceId": "70d8705dcc66490ba83341d87be19cdf|BN20240253|7.7.0.0|",
				"adminDistrict": "ON",
				"adminDistrict2": "Hamilton",
				"countryRegion": "Canada",
				"formattedAddress": "Dundas, L9H 6Y6, Canada",
				"locality": "Dundas",
				"postalCode": "L9H 6Y6"
			},
			"geometry": {
				"type": "Point",
				"coordinates": [
					-79.9524307250977,
					43.2639503479004
				]
			},
			"bbox": [
				-79.959502867651,
				43.2600876303297,
				-79.9453585825443,
				43.2678130654711
			]
		},
		{
			"type": "Feature",
			"properties": {
				"confidence": 7,
				"authenticationResultCode": "ValidCredentials",
				"brandLogoUri": "http://dev.virtualearth.net/Branding/logo_powered_by.png",
				"copyright": "Copyright © 2017 Microsoft and its suppliers. All rights reserved. This API cannot be accessed and the content and any results may not be used, reproduced or transmitted in any manner without express written permission from Microsoft Corporation.",
				"entityType": "PopulatedPlace",
				"matchCodes": [
					"UpHierarchy"
				],
				"name": "Dundas, Ontario, Canada",
				"statusCode": 200,
				"statusDescription": "OK",
				"traceId": "70d8705dcc66490ba83341d87be19cdf|BN20240253|7.7.0.0|",
				"adminDistrict": "ON",
				"adminDistrict2": "Hamilton",
				"countryRegion": "Canada",
				"formattedAddress": "Dundas, Ontario, Canada",
				"locality": "Dundas"
			},
			"geometry": {
				"type": "Point",
				"coordinates": [
					-79.9957809448242,
					43.2771911621094
				]
			},
			"bbox": [
				-80.0058135986328,
				43.2645683288574,
				-79.9794006347656,
				43.2919883728027
			]
		},
		{
			"type": "Feature",
			"properties": {
				"confidence": 1,
				"authenticationResultCode": "ValidCredentials",
				"brandLogoUri": "http://dev.virtualearth.net/Branding/logo_powered_by.png",
				"copyright": "Copyright © 2017 Microsoft and its suppliers. All rights reserved. This API cannot be accessed and the content and any results may not be used, reproduced or transmitted in any manner without express written permission from Microsoft Corporation.",
				"entityType": "Postcode1",
				"matchCodes": [
					"UpHierarchy"
				],
				"name": "Dallion Ford, MO 65590",
				"statusCode": 200,
				"statusDescription": "OK",
				"traceId": "70d8705dcc66490ba83341d87be19cdf|BN20240253|7.7.0.0|",
				"adminDistrict": "MO",
				"adminDistrict2": "Dallas",
				"countryRegion": "United States",
				"formattedAddress": "Dallion Ford, MO 65590",
				"locality": "Dallion Ford",
				"postalCode": "65590"
			},
			"geometry": {
				"type": "Point",
				"coordinates": [
					-92.9118804931641,
					37.6115837097168
				]
			},
			"bbox": [
				-93.0467376708984,
				37.5129089355469,
				-92.8480682373047,
				37.6985397338867
			]
		}
	]
}
