{
	"type": "FeatureCollection",
	"features": [
		{
			"type": "Feature",
			"properties": {
				"confidence": 1,
				"authenticationResultCode": "ValidCredentials",
				"brandLogoUri": "http://dev.virtualearth.net/Branding/logo_powered_by.png",
				"copyright": "Copyright © 2017 Microsoft and its suppliers. All rights reserved. This API cannot be accessed and the content and any results may not be used, reproduced or transmitted in any manner without express written permission from Microsoft Corporation.",
				"entityType": "Postcode2",
				"matchCodes": [
					"UpHierarchy"
				],
				"name": "Bolton, L7E, Canada",
				"statusCode": 200,
				"statusDescription": "OK",
				"traceId": "24ab450aa0a7454580227b3d54e39a23|BN20130423|7.7.0.0|",
				"adminDistrict": "ON",
				"countryRegion": "Canada",
				"formattedAddress": "Bolton, L7E, Canada",
				"locality": "Bolton",
				"postalCode": "L7E"
			},
			"geometry": {
				"type": "Point",
				"coordinates": [
					-79.7810363769531,
					43.8999710083008
				]
			},
			"bbox": [
				-79.9252319335938,
				43.810188293457,
				-79.6948623657227,
				43.9897499084473
			]
		},
		{
			"type": "Feature",
			"properties": {
				"confidence": 7,
				"authenticationResultCode": "ValidCredentials",
				"brandLogoUri": "http://dev.virtualearth.net/Branding/logo_powered_by.png",
				"copyright": "Copyright © 2017 Microsoft and its suppliers. All rights reserved. This API cannot be accessed and the content and any results may not be used, reproduced or transmitted in any manner without express written permission from Microsoft Corporation.",
				"entityType": "Postcode1",
				"matchCodes": [
					"UpHierarchy"
				],
				"name": "Caledon East, L7E 1H6, Canada",
				"statusCode": 200,
				"statusDescription": "OK",
				"traceId": "24ab450aa0a7454580227b3d54e39a23|BN20130423|7.7.0.0|",
				"adminDistrict": "ON",
				"adminDistrict2": "Peel",
				"countryRegion": "Canada",
				"formattedAddress": "Caledon East, L7E 1H6, Canada",
				"locality": "Caledon East",
				"postalCode": "L7E 1H6"
			},
			"geometry": {
				"type": "Point",
				"coordinates": [
					-79.8581085205078,
					43.8760414123535
				]
			},
			"bbox": [
				-79.865252892552,
				43.8721786947828,
				-79.8509641484636,
				43.8799041299242
			]
		},
		{
			"type": "Feature",
			"properties": {
				"confidence": 3,
				"authenticationResultCode": "ValidCredentials",
				"brandLogoUri": "http://dev.virtualearth.net/Branding/logo_powered_by.png",
				"copyright": "Copyright © 2017 Microsoft and its suppliers. All rights reserved. This API cannot be accessed and the content and any results may not be used, reproduced or transmitted in any manner without express written permission from Microsoft Corporation.",
				"entityType": "Postcode1",
				"matchCodes": [
					"UpHierarchy"
				],
				"name": "The Colony, TX 75056",
				"statusCode": 200,
				"statusDescription": "OK",
				"traceId": "24ab450aa0a7454580227b3d54e39a23|BN20130423|7.7.0.0|",
				"adminDistrict": "TX",
				"adminDistrict2": "Denton",
				"countryRegion": "United States",
				"formattedAddress": "The Colony, TX 75056",
				"locality": "The Colony",
				"postalCode": "75056"
			},
			"geometry": {
				"type": "Point",
				"coordinates": [
					-96.8486480712891,
					33.0572395324707
				]
			},
			"bbox": [
				-96.9715270996094,
				33.0244598388672,
				-96.8428268432617,
				33.1201591491699
			]
		}
	]
}
