{
	"type": "FeatureCollection",
	"features": [
		{
			"type": "Feature",
			"properties": {
				"confidence": 7,
				"authenticationResultCode": "ValidCredentials",
				"brandLogoUri": "http://dev.virtualearth.net/Branding/logo_powered_by.png",
				"copyright": "Copyright © 2017 Microsoft and its suppliers. All rights reserved. This API cannot be accessed and the content and any results may not be used, reproduced or transmitted in any manner without express written permission from Microsoft Corporation.",
				"entityType": "Postcode1",
				"matchCodes": [
					"UpHierarchy"
				],
				"name": "Powassan, P0H 1Z0, Canada",
				"statusCode": 200,
				"statusDescription": "OK",
				"traceId": "c89e587355ba4bb8a6d4a2600701ca90|BN20130620|7.7.0.0|",
				"adminDistrict": "ON",
				"adminDistrict2": "Parry Sound",
				"countryRegion": "Canada",
				"formattedAddress": "Powassan, P0H 1Z0, Canada",
				"locality": "Powassan",
				"postalCode": "P0H 1Z0"
			},
			"geometry": {
				"type": "Point",
				"coordinates": [
					-79.2515716552734,
					46.0378227233887
				]
			},
			"bbox": [
				-79.2589903437699,
				46.033960005818,
				-79.244152966777,
				46.0416854409593
			]
		}
	]
}
