{
	"type": "FeatureCollection",
	"features": [
		{
			"type": "Feature",
			"properties": {
				"confidence": 7,
				"authenticationResultCode": "ValidCredentials",
				"brandLogoUri": "http://dev.virtualearth.net/Branding/logo_powered_by.png",
				"copyright": "Copyright © 2017 Microsoft and its suppliers. All rights reserved. This API cannot be accessed and the content and any results may not be used, reproduced or transmitted in any manner without express written permission from Microsoft Corporation.",
				"entityType": "Postcode1",
				"matchCodes": [
					"UpHierarchy"
				],
				"name": "Nelson, V1L 5P9, Canada",
				"statusCode": 200,
				"statusDescription": "OK",
				"traceId": "db5f2d40522b455d8ff9b7bd5e573a65|BN20130532|7.7.0.0|",
				"adminDistrict": "BC",
				"adminDistrict2": "Central Kootenay",
				"countryRegion": "Canada",
				"formattedAddress": "Nelson, V1L 5P9, Canada",
				"locality": "Nelson",
				"postalCode": "V1L 5P9"
			},
			"geometry": {
				"type": "Point",
				"coordinates": [
					-117.288818359375,
					49.4975509643555
				]
			},
			"bbox": [
				-117.296747593966,
				49.4936882467848,
				-117.280889124784,
				49.5014136819261
			]
		}
	]
}
