{
	"type": "FeatureCollection",
	"features": [
		{
			"type": "Feature",
			"properties": {
				"confidence": 7,
				"authenticationResultCode": "ValidCredentials",
				"brandLogoUri": "http://dev.virtualearth.net/Branding/logo_powered_by.png",
				"copyright": "Copyright © 2017 Microsoft and its suppliers. All rights reserved. This API cannot be accessed and the content and any results may not be used, reproduced or transmitted in any manner without express written permission from Microsoft Corporation.",
				"entityType": "Neighborhood",
				"matchCodes": [
					"Ambiguous",
					"UpHierarchy"
				],
				"name": "Marsh Lake, Yukon, Yukon Territory, Canada",
				"statusCode": 200,
				"statusDescription": "OK",
				"traceId": "e6b5689c7e62491b9d1e66616b0c2fb5|BN20131519|7.7.0.0|",
				"adminDistrict": "YT",
				"adminDistrict2": "Yukon",
				"countryRegion": "Canada",
				"formattedAddress": "Marsh Lake, Yukon, Yukon Territory, Canada",
				"locality": "Yukon",
				"neighborhood": "Marsh Lake"
			},
			"geometry": {
				"type": "Point",
				"coordinates": [
					-134.328598022461,
					60.5151100158691
				]
			},
			"bbox": [
				-134.339060718029,
				60.5112472982985,
				-134.318135326892,
				60.5189727334398
			]
		},
		{
			"type": "Feature",
			"properties": {
				"confidence": 7,
				"authenticationResultCode": "ValidCredentials",
				"brandLogoUri": "http://dev.virtualearth.net/Branding/logo_powered_by.png",
				"copyright": "Copyright © 2017 Microsoft and its suppliers. All rights reserved. This API cannot be accessed and the content and any results may not be used, reproduced or transmitted in any manner without express written permission from Microsoft Corporation.",
				"entityType": "Postcode1",
				"matchCodes": [
					"UpHierarchy"
				],
				"name": "Yukon, Y0B 1Y2, Canada",
				"statusCode": 200,
				"statusDescription": "OK",
				"traceId": "e6b5689c7e62491b9d1e66616b0c2fb5|BN20131519|7.7.0.0|",
				"adminDistrict": "YT",
				"adminDistrict2": "Yukon",
				"countryRegion": "Canada",
				"formattedAddress": "Yukon, Y0B 1Y2, Canada",
				"locality": "Yukon",
				"postalCode": "Y0B 1Y2"
			},
			"geometry": {
				"type": "Point",
				"coordinates": [
					-134.328598022461,
					60.5151100158691
				]
			},
			"bbox": [
				-134.339060718029,
				60.5112472982985,
				-134.318135326892,
				60.5189727334398
			]
		}
	]
}
