{
	"type": "FeatureCollection",
	"features": [
		{
			"type": "Feature",
			"properties": {
				"confidence": 7,
				"authenticationResultCode": "ValidCredentials",
				"brandLogoUri": "http://dev.virtualearth.net/Branding/logo_powered_by.png",
				"copyright": "Copyright © 2017 Microsoft and its suppliers. All rights reserved. This API cannot be accessed and the content and any results may not be used, reproduced or transmitted in any manner without express written permission from Microsoft Corporation.",
				"entityType": "Postcode1",
				"matchCodes": [
					"UpHierarchy"
				],
				"name": "Bedford, B4A 3Z2, Canada",
				"statusCode": 200,
				"statusDescription": "OK",
				"traceId": "be5f4268feba45a68383ef59bbf9b338|BN20131519|7.7.0.0|",
				"adminDistrict": "NS",
				"adminDistrict2": "Halifax",
				"countryRegion": "Canada",
				"formattedAddress": "Bedford, B4A 3Z2, Canada",
				"locality": "Bedford",
				"postalCode": "B4A 3Z2"
			},
			"geometry": {
				"type": "Point",
				"coordinates": [
					-63.6772918701172,
					44.7137184143066
				]
			},
			"bbox": [
				-63.6845388746714,
				44.709855696736,
				-63.670044865563,
				44.7175811318773
			]
		},
		{
			"type": "Feature",
			"properties": {
				"confidence": 1,
				"authenticationResultCode": "ValidCredentials",
				"brandLogoUri": "http://dev.virtualearth.net/Branding/logo_powered_by.png",
				"copyright": "Copyright © 2017 Microsoft and its suppliers. All rights reserved. This API cannot be accessed and the content and any results may not be used, reproduced or transmitted in any manner without express written permission from Microsoft Corporation.",
				"entityType": "Postcode1",
				"matchCodes": [
					"UpHierarchy"
				],
				"name": "Chelsea, MI 48118",
				"statusCode": 200,
				"statusDescription": "OK",
				"traceId": "be5f4268feba45a68383ef59bbf9b338|BN20131519|7.7.0.0|",
				"adminDistrict": "MI",
				"adminDistrict2": "Washtenaw",
				"countryRegion": "United States",
				"formattedAddress": "Chelsea, MI 48118",
				"locality": "Chelsea",
				"postalCode": "48118"
			},
			"geometry": {
				"type": "Point",
				"coordinates": [
					-84.0215911865234,
					42.3127479553223
				]
			},
			"bbox": [
				-84.1315765380859,
				42.2244491577148,
				-83.8960113525391,
				42.4110717773438
			]
		},
		{
			"type": "Feature",
			"properties": {
				"confidence": 4,
				"authenticationResultCode": "ValidCredentials",
				"brandLogoUri": "http://dev.virtualearth.net/Branding/logo_powered_by.png",
				"copyright": "Copyright © 2017 Microsoft and its suppliers. All rights reserved. This API cannot be accessed and the content and any results may not be used, reproduced or transmitted in any manner without express written permission from Microsoft Corporation.",
				"entityType": "Postcode2",
				"matchCodes": [
					"UpHierarchy"
				],
				"name": "Bedford, B4A, Canada",
				"statusCode": 200,
				"statusDescription": "OK",
				"traceId": "be5f4268feba45a68383ef59bbf9b338|BN20131519|7.7.0.0|",
				"adminDistrict": "NS",
				"adminDistrict2": "Halifax",
				"countryRegion": "Canada",
				"formattedAddress": "Bedford, B4A, Canada",
				"locality": "Bedford",
				"postalCode": "B4A"
			},
			"geometry": {
				"type": "Point",
				"coordinates": [
					-63.6743278503418,
					44.727294921875
				]
			},
			"bbox": [
				-63.7180595397949,
				44.6932945251465,
				-63.6299705505371,
				44.7767295837402
			]
		},
		{
			"type": "Feature",
			"properties": {
				"confidence": 4,
				"authenticationResultCode": "ValidCredentials",
				"brandLogoUri": "http://dev.virtualearth.net/Branding/logo_powered_by.png",
				"copyright": "Copyright © 2017 Microsoft and its suppliers. All rights reserved. This API cannot be accessed and the content and any results may not be used, reproduced or transmitted in any manner without express written permission from Microsoft Corporation.",
				"entityType": "PopulatedPlace",
				"matchCodes": [
					"UpHierarchy"
				],
				"name": "Mill Cove, Nova Scotia, Canada",
				"statusCode": 200,
				"statusDescription": "OK",
				"traceId": "be5f4268feba45a68383ef59bbf9b338|BN20131519|7.7.0.0|",
				"adminDistrict": "NS",
				"adminDistrict2": "Lunenburg",
				"countryRegion": "Canada",
				"formattedAddress": "Mill Cove, Nova Scotia, Canada",
				"locality": "Mill Cove"
			},
			"geometry": {
				"type": "Point",
				"coordinates": [
					-64.0573196411133,
					44.5812683105469
				]
			},
			"bbox": [
				-64.1115248314821,
				44.5522979275543,
				-64.0031144507444,
				44.6102386935394
			]
		}
	]
}
