{
	"type": "FeatureCollection",
	"features": [
		{
			"type": "Feature",
			"properties": {
				"confidence": 9,
				"authenticationResultCode": "ValidCredentials",
				"brandLogoUri": "http://dev.virtualearth.net/Branding/logo_powered_by.png",
				"copyright": "Copyright © 2017 Microsoft and its suppliers. All rights reserved. This API cannot be accessed and the content and any results may not be used, reproduced or transmitted in any manner without express written permission from Microsoft Corporation.",
				"entityType": "Address",
				"matchCodes": [
					"Good"
				],
				"name": "555 Barrydowne Rd, Sudbury, ON P3A 3T4, Canada",
				"statusCode": 200,
				"statusDescription": "OK",
				"traceId": "6ca9d5dbdcd940d3980b900ce763f434|BN20280152|7.7.0.0|",
				"addressLine": "555 Barrydowne Rd",
				"adminDistrict": "ON",
				"adminDistrict2": "Greater Sudbury",
				"countryRegion": "Canada",
				"formattedAddress": "555 Barrydowne Rd, Sudbury, ON P3A 3T4, Canada",
				"locality": "Greater Sudbury",
				"neighborhood": "Sudbury",
				"postalCode": "P3A 3T4"
			},
			"geometry": {
				"type": "Point",
				"coordinates": [
					-80.9449099,
					46.50805
				]
			},
			"bbox": [
				-80.9465432,
				46.5069258,
				-80.9432766,
				46.5091742
			]
		}
	]
}
