{
	"type": "FeatureCollection",
	"features": [
		{
			"type": "Feature",
			"properties": {
				"confidence": 5,
				"authenticationResultCode": "ValidCredentials",
				"brandLogoUri": "http://dev.virtualearth.net/Branding/logo_powered_by.png",
				"copyright": "Copyright © 2017 Microsoft and its suppliers. All rights reserved. This API cannot be accessed and the content and any results may not be used, reproduced or transmitted in any manner without express written permission from Microsoft Corporation.",
				"entityType": "PopulatedPlace",
				"matchCodes": [
					"UpHierarchy"
				],
				"name": "Oak Bay, British Columbia, Canada",
				"statusCode": 200,
				"statusDescription": "OK",
				"traceId": "aba3b2e5cfa144448a008a9a3ff9c2cd|BN20171457|7.7.0.0|",
				"adminDistrict": "BC",
				"adminDistrict2": "Capital",
				"countryRegion": "Canada",
				"formattedAddress": "Oak Bay, British Columbia, Canada",
				"locality": "Oak Bay"
			},
			"geometry": {
				"type": "Point",
				"coordinates": [
					-123.317657470703,
					48.4265289306641
				]
			},
			"bbox": [
				-123.327743530273,
				48.4054794311523,
				-123.276657104492,
				48.4659385681152
			]
		}
	]
}
