{
	"type": "FeatureCollection",
	"features": [
		{
			"type": "Feature",
			"properties": {
				"confidence": 9,
				"authenticationResultCode": "ValidCredentials",
				"brandLogoUri": "http://dev.virtualearth.net/Branding/logo_powered_by.png",
				"copyright": "Copyright © 2017 Microsoft and its suppliers. All rights reserved. This API cannot be accessed and the content and any results may not be used, reproduced or transmitted in any manner without express written permission from Microsoft Corporation.",
				"entityType": "Address",
				"matchCodes": [
					"Good"
				],
				"name": "15 Lambeth Ave, London, ON N6C 2L3, Canada",
				"statusCode": 200,
				"statusDescription": "OK",
				"traceId": "2efcdec35ad04f81b50a4ae8ec2a8090|BN20130621|7.7.0.0|",
				"addressLine": "15 Lambeth Ave",
				"adminDistrict": "ON",
				"adminDistrict2": "Middlesex",
				"countryRegion": "Canada",
				"formattedAddress": "15 Lambeth Ave, London, ON N6C 2L3, Canada",
				"locality": "London",
				"neighborhood": "Highland",
				"postalCode": "N6C 2L3"
			},
			"geometry": {
				"type": "Point",
				"coordinates": [
					-81.2602,
					42.9608
				]
			},
			"bbox": [
				-81.2617361,
				42.9596758,
				-81.2586639,
				42.9619242
			]
		}
	]
}
