{
	"type": "FeatureCollection",
	"features": [
		{
			"type": "Feature",
			"properties": {
				"confidence": 7,
				"authenticationResultCode": "ValidCredentials",
				"brandLogoUri": "http://dev.virtualearth.net/Branding/logo_powered_by.png",
				"copyright": "Copyright © 2017 Microsoft and its suppliers. All rights reserved. This API cannot be accessed and the content and any results may not be used, reproduced or transmitted in any manner without express written permission from Microsoft Corporation.",
				"entityType": "Postcode1",
				"matchCodes": [
					"UpHierarchy"
				],
				"name": "Niagara-on-the-Lake, L0S 1J0, Canada",
				"statusCode": 200,
				"statusDescription": "OK",
				"traceId": "1acf3ebba2914c04990addeb3326e769|BN20130621|7.7.0.0|",
				"adminDistrict": "ON",
				"adminDistrict2": "Niagara",
				"countryRegion": "Canada",
				"formattedAddress": "Niagara-on-the-Lake, L0S 1J0, Canada",
				"locality": "Niagara-on-the-Lake",
				"postalCode": "L0S 1J0"
			},
			"geometry": {
				"type": "Point",
				"coordinates": [
					-79.0843811035156,
					43.2457275390625
				]
			},
			"bbox": [
				-79.091451130401,
				43.2418648214918,
				-79.0773110766302,
				43.2495902566332
			]
		}
	]
}
