{
	"type": "FeatureCollection",
	"features": [
		{
			"type": "Feature",
			"properties": {
				"confidence": 7,
				"authenticationResultCode": "ValidCredentials",
				"brandLogoUri": "http://dev.virtualearth.net/Branding/logo_powered_by.png",
				"copyright": "Copyright © 2017 Microsoft and its suppliers. All rights reserved. This API cannot be accessed and the content and any results may not be used, reproduced or transmitted in any manner without express written permission from Microsoft Corporation.",
				"entityType": "Postcode1",
				"matchCodes": [
					"UpHierarchy"
				],
				"name": "Lytton, V0K 1Z0, Canada",
				"statusCode": 200,
				"statusDescription": "OK",
				"traceId": "c2d3e2c9d27240e68e1095d9f0ca4793|BN20200137|7.7.0.0|",
				"adminDistrict": "BC",
				"adminDistrict2": "Thompson-Nicola",
				"countryRegion": "Canada",
				"formattedAddress": "Lytton, V0K 1Z0, Canada",
				"locality": "Lytton",
				"postalCode": "V0K 1Z0"
			},
			"geometry": {
				"type": "Point",
				"coordinates": [
					-121.577621459961,
					50.232738494873
				]
			},
			"bbox": [
				-121.585672280037,
				50.2288757773024,
				-121.569570639885,
				50.2366012124437
			]
		}
	]
}
