{
	"type": "FeatureCollection",
	"features": [
		{
			"type": "Feature",
			"properties": {
				"confidence": 7,
				"authenticationResultCode": "ValidCredentials",
				"brandLogoUri": "http://dev.virtualearth.net/Branding/logo_powered_by.png",
				"copyright": "Copyright © 2017 Microsoft and its suppliers. All rights reserved. This API cannot be accessed and the content and any results may not be used, reproduced or transmitted in any manner without express written permission from Microsoft Corporation.",
				"entityType": "Postcode1",
				"matchCodes": [
					"UpHierarchy"
				],
				"name": "Brockville, K6V 5V6, Canada",
				"statusCode": 200,
				"statusDescription": "OK",
				"traceId": "5e4c4712b42d4a83bdd13892ec7051e3|BN20130422|7.7.0.0|",
				"adminDistrict": "ON",
				"adminDistrict2": "Leeds and Grenville",
				"countryRegion": "Canada",
				"formattedAddress": "Brockville, K6V 5V6, Canada",
				"locality": "Brockville",
				"postalCode": "K6V 5V6"
			},
			"geometry": {
				"type": "Point",
				"coordinates": [
					-75.6830062866211,
					44.5903816223145
				]
			},
			"bbox": [
				-75.6902378978052,
				44.5865189047438,
				-75.675774675437,
				44.5942443398851
			]
		}
	]
}
