{
	"type": "FeatureCollection",
	"features": [
		{
			"type": "Feature",
			"properties": {
				"confidence": 7,
				"authenticationResultCode": "ValidCredentials",
				"brandLogoUri": "http://dev.virtualearth.net/Branding/logo_powered_by.png",
				"copyright": "Copyright © 2017 Microsoft and its suppliers. All rights reserved. This API cannot be accessed and the content and any results may not be used, reproduced or transmitted in any manner without express written permission from Microsoft Corporation.",
				"entityType": "Neighborhood",
				"matchCodes": [
					"UpHierarchy"
				],
				"name": "Crooked Creek, Greenview No 16, Alberta, Canada",
				"statusCode": 200,
				"statusDescription": "OK",
				"traceId": "de70661f879c4feea046b73f7a691c11|BN20130533|7.7.0.0|",
				"adminDistrict": "AB",
				"countryRegion": "Canada",
				"formattedAddress": "Crooked Creek, Greenview No 16, Alberta, Canada",
				"locality": "Greenview No 16",
				"neighborhood": "Crooked Creek"
			},
			"geometry": {
				"type": "Point",
				"coordinates": [
					-117.846626281738,
					55.1616897583008
				]
			},
			"bbox": [
				-117.855641036539,
				55.1578270407301,
				-117.837611526937,
				55.1655524758715
			]
		}
	]
}
