{
	"type": "FeatureCollection",
	"features": [
		{
			"type": "Feature",
			"properties": {
				"confidence": 7,
				"authenticationResultCode": "ValidCredentials",
				"brandLogoUri": "http://dev.virtualearth.net/Branding/logo_powered_by.png",
				"copyright": "Copyright © 2017 Microsoft and its suppliers. All rights reserved. This API cannot be accessed and the content and any results may not be used, reproduced or transmitted in any manner without express written permission from Microsoft Corporation.",
				"entityType": "Postcode1",
				"matchCodes": [
					"UpHierarchy"
				],
				"name": "North Gower, K0A 2T0, Canada",
				"statusCode": 200,
				"statusDescription": "OK",
				"traceId": "e2b3630806ba4669bd874a37cabd86f8|BN20190642|7.7.0.0|",
				"adminDistrict": "ON",
				"adminDistrict2": "Ottawa",
				"countryRegion": "Canada",
				"formattedAddress": "North Gower, K0A 2T0, Canada",
				"locality": "North Gower",
				"postalCode": "K0A 2T0"
			},
			"geometry": {
				"type": "Point",
				"coordinates": [
					-75.7167739868164,
					45.1425628662109
				]
			},
			"bbox": [
				-75.7240752931225,
				45.1387001486403,
				-75.7094726805103,
				45.1464255837816
			]
		}
	]
}
