{
	"type": "FeatureCollection",
	"features": [
		{
			"type": "Feature",
			"properties": {
				"confidence": 9,
				"authenticationResultCode": "ValidCredentials",
				"brandLogoUri": "http://dev.virtualearth.net/Branding/logo_powered_by.png",
				"copyright": "Copyright © 2017 Microsoft and its suppliers. All rights reserved. This API cannot be accessed and the content and any results may not be used, reproduced or transmitted in any manner without express written permission from Microsoft Corporation.",
				"entityType": "Address",
				"matchCodes": [
					"Good"
				],
				"name": "2910 S Sheridan Way, Oakville, ON L6J 7T4, Canada",
				"statusCode": 200,
				"statusDescription": "OK",
				"traceId": "cec1b59ab552466c8cc1683dbe0cdc67|BN20171457|7.7.0.0|",
				"addressLine": "2910 S Sheridan Way",
				"adminDistrict": "ON",
				"adminDistrict2": "Halton",
				"countryRegion": "Canada",
				"formattedAddress": "2910 S Sheridan Way, Oakville, ON L6J 7T4, Canada",
				"locality": "Oakville",
				"postalCode": "L6J 7T4"
			},
			"geometry": {
				"type": "Point",
				"coordinates": [
					-79.66511,
					43.50681
				]
			},
			"bbox": [
				-79.6666599,
				43.5056858,
				-79.6635601,
				43.5079342
			]
		}
	]
}
