{
	"type": "FeatureCollection",
	"features": [
		{
			"type": "Feature",
			"properties": {
				"confidence": 7,
				"authenticationResultCode": "ValidCredentials",
				"brandLogoUri": "http://dev.virtualearth.net/Branding/logo_powered_by.png",
				"copyright": "Copyright © 2017 Microsoft and its suppliers. All rights reserved. This API cannot be accessed and the content and any results may not be used, reproduced or transmitted in any manner without express written permission from Microsoft Corporation.",
				"entityType": "PopulatedPlace",
				"matchCodes": [
					"UpHierarchy"
				],
				"name": "Deseronto, Ontario, Canada",
				"statusCode": 200,
				"statusDescription": "OK",
				"traceId": "5666738e0dff4afab05e8220cea7e2e1|BN20130632|7.7.0.0|",
				"adminDistrict": "ON",
				"adminDistrict2": "Hastings",
				"countryRegion": "Canada",
				"formattedAddress": "Deseronto, Ontario, Canada",
				"locality": "Deseronto"
			},
			"geometry": {
				"type": "Point",
				"coordinates": [
					-77.0492935180664,
					44.194580078125
				]
			},
			"bbox": [
				-77.0662689208984,
				44.1801795959473,
				-77.0361862182617,
				44.2084007263184
			]
		},
		{
			"type": "Feature",
			"properties": {
				"confidence": 7,
				"authenticationResultCode": "ValidCredentials",
				"brandLogoUri": "http://dev.virtualearth.net/Branding/logo_powered_by.png",
				"copyright": "Copyright © 2017 Microsoft and its suppliers. All rights reserved. This API cannot be accessed and the content and any results may not be used, reproduced or transmitted in any manner without express written permission from Microsoft Corporation.",
				"entityType": "Postcode1",
				"matchCodes": [
					"UpHierarchy"
				],
				"name": "Tyendinaga, K0K 1X0, Canada",
				"statusCode": 200,
				"statusDescription": "OK",
				"traceId": "5666738e0dff4afab05e8220cea7e2e1|BN20130632|7.7.0.0|",
				"adminDistrict": "ON",
				"adminDistrict2": "Hastings",
				"countryRegion": "Canada",
				"formattedAddress": "Tyendinaga, K0K 1X0, Canada",
				"locality": "Tyendinaga",
				"postalCode": "K0K 1X0"
			},
			"geometry": {
				"type": "Point",
				"coordinates": [
					-77.0620346069336,
					44.1962242126465
				]
			},
			"bbox": [
				-77.0692176817422,
				44.1923614950758,
				-77.0548515321249,
				44.2000869302172
			]
		},
		{
			"type": "Feature",
			"properties": {
				"confidence": 3,
				"authenticationResultCode": "ValidCredentials",
				"brandLogoUri": "http://dev.virtualearth.net/Branding/logo_powered_by.png",
				"copyright": "Copyright © 2017 Microsoft and its suppliers. All rights reserved. This API cannot be accessed and the content and any results may not be used, reproduced or transmitted in any manner without express written permission from Microsoft Corporation.",
				"entityType": "IndigenousPeoplesReserve",
				"matchCodes": [
					"UpHierarchy"
				],
				"name": "Tyendinaga Mohawk Territory, Ontario, Canada",
				"statusCode": 200,
				"statusDescription": "OK",
				"traceId": "5666738e0dff4afab05e8220cea7e2e1|BN20130632|7.7.0.0|",
				"adminDistrict": "ON",
				"adminDistrict2": "Hastings",
				"countryRegion": "Canada",
				"formattedAddress": "Tyendinaga Mohawk Territory, Ontario, Canada"
			},
			"geometry": {
				"type": "Point",
				"coordinates": [
					-77.1481170654297,
					44.1911239624023
				]
			},
			"bbox": [
				-77.2591171264648,
				44.1548881530762,
				-77.0542526245117,
				44.2254104614258
			]
		}
	]
}
