{
	"type": "FeatureCollection",
	"features": [
		{
			"type": "Feature",
			"properties": {
				"confidence": 8,
				"authenticationResultCode": "ValidCredentials",
				"brandLogoUri": "http://dev.virtualearth.net/Branding/logo_powered_by.png",
				"copyright": "Copyright © 2017 Microsoft and its suppliers. All rights reserved. This API cannot be accessed and the content and any results may not be used, reproduced or transmitted in any manner without express written permission from Microsoft Corporation.",
				"entityType": "RoadBlock",
				"matchCodes": [
					"UpHierarchy"
				],
				"name": "Agar Dr, Richmond, BC V7B 1A3, Canada",
				"statusCode": 200,
				"statusDescription": "OK",
				"traceId": "40cd7a04a331473299cd81f6d6b05321|BN20240253|7.7.0.0|",
				"addressLine": "Agar Dr",
				"adminDistrict": "BC",
				"adminDistrict2": "Greater Vancouver",
				"countryRegion": "Canada",
				"formattedAddress": "Agar Dr, Richmond, BC V7B 1A3, Canada",
				"locality": "Richmond",
				"neighborhood": "Sea Island",
				"postalCode": "V7B 1A3"
			},
			"geometry": {
				"type": "Point",
				"coordinates": [
					-123.17578,
					49.18334
				]
			},
			"bbox": [
				-123.17588,
				49.17889,
				-123.17364,
				49.18334
			]
		}
	]
}
